{
  "type": "Feature",
  "properties": {
    "gn:admin1_code":"35.0",
    "gn:admin2_code":"464.0",
    "gn:asciiname":"Wani",
    "gn:country_code":"IN",
    "gn:dem":450,
    "gn:feature_class":"P",
    "gn:feature_code":"PPL",
    "gn:name":"W\u0101ni",
    "gn:population":0,
    "gn:timezone":"Asia/Kolkata",
    "iso:country":"IN",
    "name:ceb_x_preferred":[
        "Wani"
    ],
    "name:deu_x_preferred":[
        "Wani"
    ],
    "name:kat_x_preferred":[
        "\u10d5\u10d0\u10dc\u10d8"
    ],
    "name:pol_x_preferred":[
        "Wani"
    ],
    "name:swe_x_preferred":[
        "Wani"
    ],
    "name:xmf_x_preferred":[
        "\u10d5\u10d0\u10dc\u10d8"
    ],
    "wof:name":"Wani",
    "wof:placetype":"locality"
},
  "geometry": {"coordinates":[74.84705,22.93181],"type":"Point"}
}