{
  "type": "Feature",
  "properties": {
    "iso:country":"IN",
    "ks:ks_name":"Keketapa",
    "ks:ks_pop":119,
    "ks:ks_type":"VILLAGE",
    "name:eng_x_preferred":[
        "Keketapa"
    ],
    "wof:name":"Keketapa",
    "wof:placetype":"locality",
    "wof:population":119
},
  "geometry": {"coordinates":[84.526931,20.153524],"type":"Point"}
}