{
  "type": "Feature",
  "properties": {
    "gn:admin1_code":"35.0",
    "gn:admin2_code":"447.0",
    "gn:asciiname":"Kanarhana",
    "gn:country_code":"IN",
    "gn:dem":741,
    "gn:feature_class":"P",
    "gn:feature_code":"PPL",
    "gn:name":"K\u0101n\u0101rh\u0101na",
    "gn:population":0,
    "gn:timezone":"Asia/Kolkata",
    "iso:country":"IN",
    "wof:name":"Kanarhana",
    "wof:placetype":"locality"
},
  "geometry": {"coordinates":[78.22103,21.98881],"type":"Point"}
}