{
  "type": "Feature",
  "properties": {
    "gn:admin1_code":"36",
    "gn:admin2_code":"147.0",
    "gn:asciiname":"Dayaganj",
    "gn:country_code":"IN",
    "gn:dem":163,
    "gn:feature_class":"P",
    "gn:feature_code":"PPL",
    "gn:name":"Day\u0101ganj",
    "gn:population":0,
    "gn:timezone":"Asia/Kolkata",
    "iso:country":"IN",
    "wof:name":"Dayaganj",
    "wof:placetype":"locality"
},
  "geometry": {"coordinates":[78.69112,27.05335],"type":"Point"}
}