{
  "type": "Feature",
  "properties": {
    "iso:country":"IN",
    "ks:ks_name":"Shiv Dayal Purwa",
    "ks:ks_pop":157,
    "ks:ks_type":"HABITATION",
    "name:eng_x_preferred":[
        "Shiv Dayal Purwa"
    ],
    "wof:name":"Shiv Dayal Purwa",
    "wof:placetype":"locality",
    "wof:population":157
},
  "geometry": {"coordinates":[81.402126,27.945061],"type":"Point"}
}