{
  "type": "Feature",
  "properties": {
    "iso:country":"IN",
    "ks:ks_name":"Dharmasaranbindha",
    "ks:ks_pop":577,
    "ks:ks_type":"VILLAGE",
    "ks:ks_uagg_main":0,
    "name:eng_x_preferred":[
        "Dharmasaranbindha"
    ],
    "wof:name":"Dharmasaranbindha",
    "wof:placetype":"neighbourhood",
    "wof:population":577
},
  "geometry": {"coordinates":[86.640157,21.052029],"type":"Point"}
}