{
  "type": "Feature",
  "properties": {
    "iso:country":"IN",
    "ks:ks_alt_nam":"RAJPUT TOLA",
    "ks:ks_name":"Rajput Tola",
    "ks:ks_pop":315,
    "ks:ks_type":"HABITATION",
    "ks:ks_uagg_main":0,
    "name:eng_x_preferred":[
        "Rajput Tola"
    ],
    "wof:name":"Rajput Tola",
    "wof:placetype":"neighbourhood",
    "wof:population":315
},
  "geometry": {"coordinates":[86.76911,26.188898],"type":"Point"}
}