{
  "type": "Feature",
  "properties": {
    "gn:admin1_code":"24.0",
    "gn:admin2_code":"119.0",
    "gn:asciiname":"Kayar",
    "gn:country_code":"IN",
    "gn:dem":480,
    "gn:feature_class":"P",
    "gn:feature_code":"PPL",
    "gn:name":"K\u0101yar",
    "gn:population":0,
    "gn:timezone":"Asia/Kolkata",
    "iso:country":"IN",
    "ks:ks_alt_nam":"K\u0101yar",
    "ks:ks_name":"Kayar",
    "ks:ks_pop":2822,
    "ks:ks_type":"VILLAGE",
    "name:eng_x_preferred":[
        "Kayar"
    ],
    "name:eng_x_variant":[
        "K\u0101yar"
    ],
    "wof:name":"Kayar",
    "wof:placetype":"locality",
    "wof:population":2822
},
  "geometry": {"coordinates":[74.689122,26.532968],"type":"Point"}
}