{
  "type": "Feature",
  "properties": {
    "gn:admin1_code":"02",
    "gn:admin2_code":"550.0",
    "gn:asciiname":"Tammenapatam",
    "gn:country_code":"IN",
    "gn:dem":6,
    "gn:feature_class":"P",
    "gn:feature_code":"PPL",
    "gn:name":"Tammenapatam",
    "gn:population":0,
    "gn:timezone":"Asia/Kolkata",
    "iso:country":"IN",
    "name:und_x_variant":[
        "Tammenapatnam"
    ],
    "wof:name":"Tammenapatam",
    "wof:placetype":"locality"
},
  "geometry": {"coordinates":[80.1023,14.23272],"type":"Point"}
}