{
  "type": "Feature",
  "properties": {
    "iso:country":"IN",
    "ks:ks_name":"Kabbinagola3",
    "ks:ks_pop":42,
    "ks:ks_type":"HABITATION",
    "name:eng_x_preferred":[
        "Kabbinagola3"
    ],
    "wof:name":"Kabbinagola3",
    "wof:placetype":"locality",
    "wof:population":42
},
  "geometry": {"coordinates":[74.739712,14.978171],"type":"Point"}
}