{
  "type": "Feature",
  "properties": {
    "gn:admin1_code":"36",
    "gn:admin2_code":"179.0",
    "gn:asciiname":"Purwa Dasaundhi",
    "gn:country_code":"IN",
    "gn:dem":101,
    "gn:feature_class":"P",
    "gn:feature_code":"PPL",
    "gn:name":"Purwa Dasaundhi",
    "gn:population":0,
    "gn:timezone":"Asia/Kolkata",
    "iso:country":"IN",
    "wof:name":"Purwa Dasaundhi",
    "wof:placetype":"locality"
},
  "geometry": {"coordinates":[82.06891999999998,26.16054],"type":"Point"}
}