{
  "type": "Feature",
  "properties": {
    "iso:country":"IN",
    "ks:ks_name":"Nadi Falia",
    "ks:ks_pop":1004,
    "ks:ks_type":"HABITATION",
    "name:eng_x_preferred":[
        "Nadi Falia"
    ],
    "wof:name":"Nadi Falia",
    "wof:placetype":"locality",
    "wof:population":1004
},
  "geometry": {"coordinates":[73.8565,22.746694],"type":"Point"}
}