{
  "type": "Feature",
  "properties": {
    "gn:admin1_code":"36",
    "gn:admin2_code":"174.0",
    "gn:asciiname":"Kura Muridan",
    "gn:country_code":"IN",
    "gn:dem":108,
    "gn:feature_class":"P",
    "gn:feature_code":"PPL",
    "gn:name":"Kura Mur\u012bdan",
    "gn:population":0,
    "gn:timezone":"Asia/Kolkata",
    "iso:country":"IN",
    "wof:name":"Kura Muridan",
    "wof:placetype":"locality"
},
  "geometry": {"coordinates":[81.29661,25.65113],"type":"Point"}
}