{
  "type": "Feature",
  "properties": {
    "iso:country":"IN",
    "ks:ks_name":"Gadayun",
    "ks:ks_pop":190,
    "ks:ks_type":"VILLAGE",
    "name:eng_x_preferred":[
        "Gadayun"
    ],
    "wof:name":"Gadayun",
    "wof:placetype":"locality",
    "wof:population":190
},
  "geometry": {"coordinates":[78.890944,29.6895],"type":"Point"}
}