{
  "type": "Feature",
  "properties": {
    "iso:country":"IN",
    "ks:ks_alt_nam":"PATOLEPATIL  WASTI",
    "ks:ks_name":"Patolepatil Wasti",
    "ks:ks_pop":80,
    "ks:ks_type":"HABITATION",
    "name:eng_x_preferred":[
        "Patolepatil Wasti"
    ],
    "name:eng_x_variant":[
        "PATOLEPATIL  WASTI"
    ],
    "wof:name":"Patolepatil Wasti",
    "wof:placetype":"locality",
    "wof:population":80
},
  "geometry": {"coordinates":[74.787711,17.093408],"type":"Point"}
}