{
  "type": "Feature",
  "properties": {
    "iso:country":"IN",
    "ks:ks_name":"Watda",
    "ks:ks_pop":1045,
    "ks:ks_type":"HABITATION",
    "name:eng_x_preferred":[
        "Watda"
    ],
    "wof:name":"Watda",
    "wof:placetype":"locality",
    "wof:population":1045
},
  "geometry": {"coordinates":[77.122444,26.425942],"type":"Point"}
}