{
  "type": "Feature",
  "properties": {
    "gn:admin1_code":"36",
    "gn:admin2_code":"172.0",
    "gn:asciiname":"Shahipur",
    "gn:country_code":"IN",
    "gn:dem":114,
    "gn:feature_class":"P",
    "gn:feature_code":"PPL",
    "gn:name":"Sh\u0101h\u012bpur",
    "gn:population":0,
    "gn:timezone":"Asia/Kolkata",
    "iso:country":"IN",
    "name:und_x_variant":[
        "Sh\u0101h\u012bpur",
        "S\u0101habpur"
    ],
    "wof:name":"Shahipur",
    "wof:placetype":"locality"
},
  "geometry": {"coordinates":[81.05863000000002,25.67978],"type":"Point"}
}