{
  "type": "Feature",
  "properties": {
    "gn:admin1_code":"35",
    "gn:admin2_code":"443.0",
    "gn:asciiname":"Dabra",
    "gn:country_code":"IN",
    "gn:dem":410,
    "gn:feature_class":"P",
    "gn:feature_code":"PPL",
    "gn:name":"D\u0101bra",
    "gn:population":0,
    "gn:timezone":"Asia/Kolkata",
    "iso:country":"IN",
    "ks:ks_alt_nam":"D\u0101bra",
    "ks:ks_name":"Dabra",
    "ks:ks_type":"VILLAGE",
    "name:eng_x_preferred":[
        "Dabra"
    ],
    "name:eng_x_variant":[
        "D\u0101bra"
    ],
    "wof:name":"Dabra",
    "wof:placetype":"locality"
},
  "geometry": {"coordinates":[78.00359400000001,23.862494],"type":"Point"}
}