{
  "type": "Feature",
  "properties": {
    "gn:admin1_code":"25.0",
    "gn:admin2_code":"619.0",
    "gn:asciiname":"Mela Korukkai",
    "gn:country_code":"IN",
    "gn:dem":4,
    "gn:feature_class":"P",
    "gn:feature_code":"PPL",
    "gn:name":"Mela Korukkai",
    "gn:population":0,
    "gn:timezone":"Asia/Kolkata",
    "iso:country":"IN",
    "wof:name":"Mela Korukkai",
    "wof:placetype":"locality"
},
  "geometry": {"coordinates":[79.69141,10.54423],"type":"Point"}
}