{
  "type": "Feature",
  "properties": {
    "gn:admin1_code":"25.0",
    "gn:admin2_code":"619.0",
    "gn:asciiname":"Mela Korukkai",
    "gn:country_code":"IN",
    "gn:dem":4,
    "gn:feature_class":"P",
    "gn:feature_code":"PPL",
    "gn:name":"Mela Korukkai",
    "gn:population":0,
    "gn:timezone":"Asia/Kolkata",
    "iso:country":"IN",
    "ks:ks_name":"Meelakorukkai",
    "ks:ks_pop":1020,
    "ks:ks_type":"HABITATION",
    "name:eng_x_preferred":[
        "Meelakorukkai"
    ],
    "name:eng_x_variant":[
        "Mela Korukkai"
    ],
    "wof:name":"Meelakorukkai",
    "wof:placetype":"locality",
    "wof:population":1020
},
  "geometry": {"coordinates":[79.699789,10.53935],"type":"Point"}
}