{
  "type": "Feature",
  "properties": {
    "iso:country":"IN",
    "ks:ks_name":"13 BLD-A",
    "ks:ks_pop":191,
    "ks:ks_type":"VILLAGE",
    "name:eng_x_preferred":[
        "13 BLD-A"
    ],
    "wof:name":"13 BLD-A",
    "wof:placetype":"locality",
    "wof:population":191
},
  "geometry": {"coordinates":[73.39705600000001,29.273954],"type":"Point"}
}