{
  "type": "Feature",
  "properties": {
    "gn:admin1_code":"36.0",
    "gn:admin2_code":"172.0",
    "gn:asciiname":"Rajapur",
    "gn:country_code":"IN",
    "gn:dem":115,
    "gn:feature_class":"P",
    "gn:feature_code":"PPL",
    "gn:name":"R\u0101j\u0101pur",
    "gn:population":0,
    "gn:timezone":"Asia/Kolkata",
    "iso:country":"IN",
    "name:ceb_x_preferred":[
        "Rajapur"
    ],
    "name:fra_x_preferred":[
        "Rajapur"
    ],
    "name:ita_x_preferred":[
        "Rajapur"
    ],
    "name:pol_x_preferred":[
        "Rajapur"
    ],
    "name:swe_x_preferred":[
        "Rajapur"
    ],
    "wof:name":"Rajapur",
    "wof:placetype":"neighbourhood"
},
  "geometry": {"coordinates":[81.13369,25.88442],"type":"Point"}
}