{
  "type": "Feature",
  "properties": {
    "gn:admin1_code":"16",
    "gn:admin2_code":"503.0",
    "gn:asciiname":"Virul",
    "gn:country_code":"IN",
    "gn:dem":317,
    "gn:feature_class":"P",
    "gn:feature_code":"PPL",
    "gn:name":"V\u012br\u016bl",
    "gn:population":0,
    "gn:timezone":"Asia/Kolkata",
    "iso:country":"IN",
    "name:und_x_variant":[
        "Virul-Ronghe",
        "Virul",
        "V\u012br\u016bl"
    ],
    "wof:name":"Virul",
    "wof:placetype":"neighbourhood"
},
  "geometry": {"coordinates":[78.07922000000001,20.84144],"type":"Point"}
}