{
  "type": "Feature",
  "properties": {
    "iso:country":"IN",
    "ks:ks_name":"Jadlgadde",
    "ks:ks_pop":60,
    "ks:ks_type":"HABITATION",
    "name:eng_x_preferred":[
        "Jadlgadde"
    ],
    "wof:name":"Jadlgadde",
    "wof:placetype":"locality",
    "wof:population":60
},
  "geometry": {"coordinates":[74.211834,14.76218],"type":"Point"}
}