{
  "type": "Feature",
  "properties": {
    "iso:country":"IN",
    "ks:ks_alt_nam":"Shubba khera",
    "ks:ks_name":"Shubba Khera",
    "ks:ks_pop":291,
    "ks:ks_type":"HABITATION",
    "ks:ks_uagg_main":0,
    "name:eng_x_preferred":[
        "Shubba Khera"
    ],
    "wof:name":"Shubba Khera",
    "wof:placetype":"neighbourhood",
    "wof:population":291
},
  "geometry": {"coordinates":[80.58358200000001,26.764909],"type":"Point"}
}