{
  "type": "Feature",
  "properties": {
    "gn:admin1_code":"35.0",
    "gn:admin2_code":"441.0",
    "gn:asciiname":"Nanvanya",
    "gn:country_code":"IN",
    "gn:dem":322,
    "gn:feature_class":"P",
    "gn:feature_code":"PPL",
    "gn:name":"Nanv\u0101nya",
    "gn:population":0,
    "gn:timezone":"Asia/Kolkata",
    "iso:country":"IN",
    "ks:ks_name":"Nanvanya",
    "ks:ks_pop":816,
    "ks:ks_type":"HABITATION",
    "name:eng_x_preferred":[
        "Nanvanya"
    ],
    "wof:name":"Nanvanya",
    "wof:placetype":"locality",
    "wof:population":816
},
  "geometry": {"coordinates":[74.72530999999999,21.736641],"type":"Point"}
}