{
  "type": "Feature",
  "properties": {
    "iso:country":"IN",
    "ks:ks_name":"Kaziranga National Park",
    "ks:ks_pop":161,
    "ks:ks_type":"VILLAGE",
    "name:eng_x_preferred":[
        "Kaziranga National Park"
    ],
    "wof:name":"Kaziranga National Park",
    "wof:placetype":"locality",
    "wof:population":161
},
  "geometry": {"coordinates":[93.433913,26.679992],"type":"Point"}
}