{
  "type": "Feature",
  "properties": {
    "iso:country":"IN",
    "ks:ks_name":"Benia Baid",
    "ks:ks_pop":415,
    "ks:ks_type":"VILLAGE",
    "ks:ks_uagg_main":0,
    "name:eng_x_preferred":[
        "Benia Baid"
    ],
    "wof:name":"Benia Baid",
    "wof:placetype":"neighbourhood",
    "wof:population":415
},
  "geometry": {"coordinates":[86.88618200000001,22.928219],"type":"Point"}
}