{
  "type": "Feature",
  "properties": {
    "gn:admin1_code":"2.0",
    "gn:admin2_code":"548.0",
    "gn:asciiname":"Kunchavaram",
    "gn:country_code":"IN",
    "gn:dem":17,
    "gn:feature_class":"P",
    "gn:feature_code":"PPL",
    "gn:name":"Kunchavaram",
    "gn:population":0,
    "gn:timezone":"Asia/Kolkata",
    "iso:country":"IN",
    "wof:name":"Kunchavaram",
    "wof:placetype":"locality"
},
  "geometry": {"coordinates":[80.67453,16.30067],"type":"Point"}
}