{
  "type": "Feature",
  "properties": {
    "iso:country":"IN",
    "ks:ks_alt_nam":"Kadamanguri colony",
    "ks:ks_name":"Kadamanguri Colony",
    "ks:ks_pop":820,
    "ks:ks_type":"HABITATION",
    "name:eng_x_preferred":[
        "Kadamanguri Colony"
    ],
    "wof:name":"Kadamanguri Colony",
    "wof:placetype":"locality",
    "wof:population":820
},
  "geometry": {"coordinates":[76.744783,9.394561],"type":"Point"}
}