{
  "type": "Feature",
  "properties": {
    "iso:country":"IN",
    "ks:ks_name":"Ubbanguda",
    "ks:ks_pop":101,
    "ks:ks_type":"HABITATION",
    "name:eng_x_preferred":[
        "Ubbanguda"
    ],
    "wof:name":"Ubbanguda",
    "wof:placetype":"locality",
    "wof:population":101
},
  "geometry": {"coordinates":[82.41179,18.378106],"type":"Point"}
}