{
  "type": "Feature",
  "properties": {
    "gn:admin1_code":"35",
    "gn:admin2_code":"422.0",
    "gn:asciiname":"Khairaunaghat",
    "gn:country_code":"IN",
    "gn:dem":185,
    "gn:feature_class":"P",
    "gn:feature_code":"PPL",
    "gn:name":"Khairaun\u0101gh\u0101t",
    "gn:population":0,
    "gn:timezone":"Asia/Kolkata",
    "iso:country":"IN",
    "wof:name":"Khairaunaghat",
    "wof:placetype":"neighbourhood"
},
  "geometry": {"coordinates":[78.51202000000001,25.96176],"type":"Point"}
}