{
  "type": "Feature",
  "properties": {
    "gn:country":"IN",
    "gn:fcode":"PPL",
    "gn:pop":24767,
    "iso:country":"IN",
    "name:ara_x_preferred":[
        "\u062e\u064a\u062f\u0627"
    ],
    "name:bpy_x_preferred":[
        "\u0996\u09c7\u09a1\u09be"
    ],
    "name:cat_x_preferred":[
        "Kheda"
    ],
    "name:ceb_x_preferred":[
        "Kheda"
    ],
    "name:eng_x_preferred":[
        "Kheda"
    ],
    "name:fra_x_preferred":[
        "Kheda"
    ],
    "name:guj_x_preferred":[
        "\u0a96\u0ac7\u0aa1\u0abe"
    ],
    "name:hin_x_preferred":[
        "\u0916\u0947\u0921\u093c\u093e"
    ],
    "name:ita_x_preferred":[
        "Kheda"
    ],
    "name:jpn_x_preferred":[
        "\u30b1\u30fc\u30c0\u30fc\u770c"
    ],
    "name:mar_x_preferred":[
        "\u0916\u0947\u0921\u093e"
    ],
    "name:mlg_x_preferred":[
        "Kheda"
    ],
    "name:msa_x_preferred":[
        "Kheda"
    ],
    "name:new_x_preferred":[
        "\u0916\u0947\u0926\u093e"
    ],
    "name:nld_x_preferred":[
        "Kheda"
    ],
    "name:pam_x_preferred":[
        "Kheda"
    ],
    "name:pan_x_preferred":[
        "\u0a16\u0a47\u0a5c\u0a3e"
    ],
    "name:rus_x_preferred":[
        "\u0425\u0435\u0434\u0430"
    ],
    "name:rus_x_variant":[
        "\u041a\u0445\u0435\u0434\u0430"
    ],
    "name:spa_x_preferred":[
        "Kheda"
    ],
    "name:swe_x_preferred":[
        "Kheda"
    ],
    "name:tam_x_preferred":[
        "\u0b95\u0bc7\u0b9f\u0bbe"
    ],
    "name:ukr_x_preferred":[
        "\u041a\u0445\u0435\u0434\u0430"
    ],
    "name:unk_x_variant":[
        "Kaira"
    ],
    "name:urd_x_preferred":[
        "\u06a9\u06be\u06cc\u0691\u0627"
    ],
    "name:vie_x_preferred":[
        "Kheda"
    ],
    "name:war_x_preferred":[
        "Kheda"
    ],
    "name:xmf_x_preferred":[
        "\u10ee\u10d4\u10d3\u10d0"
    ],
    "name:zho_x_preferred":[
        "\u51ef\u8fbe"
    ],
    "qs:name":"Kheda",
    "qs:name_adm0":"India",
    "qs:name_adm1":"Gujarat",
    "qs:photos":4,
    "qs:photos_1k":1,
    "qs:photos_9k":1,
    "qs:photos_9r":1,
    "qs:photos_all":4,
    "qs:photos_sr":1,
    "qs:placetype":"Town",
    "qs:pop_sr":"7",
    "wd:elevation":21.0,
    "wd:wordcount":562,
    "wof:name":"Kheda",
    "wof:placetype":"locality",
    "wof:population":24767
},
  "geometry": {"coordinates":[72.68532999999999,22.75218],"type":"Point"}
}