{
  "type": "Feature",
  "properties": {
    "iso:country":"IN",
    "ks:ks_name":"Boma Punji Dona Punji",
    "ks:ks_pop":435,
    "ks:ks_type":"HABITATION",
    "name:eng_x_preferred":[
        "Boma Punji Dona Punji"
    ],
    "wof:name":"Boma Punji Dona Punji",
    "wof:placetype":"locality",
    "wof:population":435
},
  "geometry": {"coordinates":[93.152686,24.877403],"type":"Point"}
}