{
  "type": "Feature",
  "properties": {
    "iso:country":"IN",
    "ks:ks_name":"Avaravalasi",
    "ks:ks_pop":120,
    "ks:ks_type":"HABITATION",
    "name:eng_x_preferred":[
        "Avaravalasi"
    ],
    "wof:name":"Avaravalasi",
    "wof:placetype":"locality",
    "wof:population":120
},
  "geometry": {"coordinates":[79.023894,12.673377],"type":"Point"}
}