{
  "type": "Feature",
  "properties": {
    "gn:admin1_code":"35.0",
    "gn:admin2_code":"466.0",
    "gn:asciiname":"Khutiya",
    "gn:country_code":"IN",
    "gn:dem":255,
    "gn:feature_class":"P",
    "gn:feature_code":"PPL",
    "gn:name":"Kh\u016btiya",
    "gn:population":0,
    "gn:timezone":"Asia/Kolkata",
    "iso:country":"IN",
    "ks:ks_alt_nam":"Kh\u016btiya",
    "ks:ks_name":"Khutiya",
    "ks:ks_type":"VILLAGE",
    "name:eng_x_preferred":[
        "Khutiya"
    ],
    "name:eng_x_variant":[
        "Kh\u016btiya"
    ],
    "wof:name":"Khutiya",
    "wof:placetype":"locality"
},
  "geometry": {"coordinates":[76.67168100000001,22.049662],"type":"Point"}
}