{
  "type": "Feature",
  "properties": {
    "iso:country":"IN",
    "ks:ks_name":"Tarauna Basgaw",
    "ks:ks_pop":1341,
    "ks:ks_type":"VILLAGE",
    "name:eng_x_preferred":[
        "Tarauna Basgaw"
    ],
    "wof:name":"Tarauna Basgaw",
    "wof:placetype":"locality",
    "wof:population":1341
},
  "geometry": {"coordinates":[83.09111,26.31788],"type":"Point"}
}