{
  "type": "Feature",
  "properties": {
    "gn:admin1_code":"34.0",
    "gn:admin2_code":"214.0",
    "gn:asciiname":"Raghunathpur",
    "gn:country_code":"IN",
    "gn:dem":45,
    "gn:feature_class":"P",
    "gn:feature_code":"PPL",
    "gn:name":"Raghun\u0101thpur",
    "gn:population":0,
    "gn:timezone":"Asia/Kolkata",
    "iso:country":"IN",
    "wof:name":"Raghunathpur",
    "wof:placetype":"locality"
},
  "geometry": {"coordinates":[86.82363000000002,25.6695],"type":"Point"}
}