{
  "type": "Feature",
  "properties": {
    "iso:country":"IN",
    "ks:ks_name":"Chuanput",
    "ks:ks_pop":74,
    "ks:ks_type":"HABITATION",
    "name:eng_x_preferred":[
        "Chuanput"
    ],
    "wof:name":"Chuanput",
    "wof:placetype":"locality",
    "wof:population":74
},
  "geometry": {"coordinates":[82.72080800000001,18.344642],"type":"Point"}
}