{
  "type": "Feature",
  "properties": {
    "iso:country":"IN",
    "ks:ks_name":"Kondabinnidi",
    "ks:ks_pop":68,
    "ks:ks_type":"HABITATION",
    "name:eng_x_preferred":[
        "Kondabinnidi"
    ],
    "wof:name":"Kondabinnidi",
    "wof:placetype":"locality",
    "wof:population":68
},
  "geometry": {"coordinates":[83.583377,19.0461],"type":"Point"}
}