{
  "type": "Feature",
  "properties": {
    "iso:country":"IN",
    "ks:ks_name":"Tol Dungari",
    "ks:ks_pop":620,
    "ks:ks_type":"VILLAGE",
    "name:eng_x_preferred":[
        "Tol Dungari"
    ],
    "wof:name":"Tol Dungari",
    "wof:placetype":"locality",
    "wof:population":620
},
  "geometry": {"coordinates":[73.227998,23.951503],"type":"Point"}
}