{
  "type": "Feature",
  "properties": {
    "iso:country":"IN",
    "ks:ks_name":"Gubbalavaripalem",
    "ks:ks_pop":371,
    "ks:ks_type":"HABITATION",
    "name:eng_x_preferred":[
        "Gubbalavaripalem"
    ],
    "wof:name":"Gubbalavaripalem",
    "wof:placetype":"locality",
    "wof:population":371
},
  "geometry": {"coordinates":[81.90198700000001,16.685193],"type":"Point"}
}