{
  "type": "Feature",
  "properties": {
    "gn:admin1_code":"19.0",
    "gn:admin2_code":"582.0",
    "gn:asciiname":"Digava Biramangla",
    "gn:country_code":"IN",
    "gn:dem":736,
    "gn:feature_class":"P",
    "gn:feature_code":"PPL",
    "gn:name":"Digava Biramangla",
    "gn:population":0,
    "gn:timezone":"Asia/Kolkata",
    "iso:country":"IN",
    "wof:name":"Digava Biramangla",
    "wof:placetype":"locality"
},
  "geometry": {"coordinates":[77.55693000000002,13.55918],"type":"Point"}
}