{
  "type": "Feature",
  "properties": {
    "gn:admin1_code":"2.0",
    "gn:admin2_code":"553.0",
    "gn:asciiname":"Nyamaddala",
    "gn:country_code":"IN",
    "gn:dem":454,
    "gn:feature_class":"P",
    "gn:feature_code":"PPL",
    "gn:name":"Ny\u0101maddala",
    "gn:population":0,
    "gn:timezone":"Asia/Kolkata",
    "iso:country":"IN",
    "wof:name":"Nyamaddala",
    "wof:placetype":"locality"
},
  "geometry": {"coordinates":[77.58593,14.26148],"type":"Point"}
}