{
  "type": "Feature",
  "properties": {
    "iso:country":"IN",
    "ks:ks_name":"Schoolpara",
    "ks:ks_pop":912,
    "ks:ks_type":"HABITATION",
    "name:eng_x_preferred":[
        "Schoolpara"
    ],
    "wof:name":"Schoolpara",
    "wof:placetype":"locality",
    "wof:population":912
},
  "geometry": {"coordinates":[91.248442,26.059565],"type":"Point"}
}