{
  "type": "Feature",
  "properties": {
    "gn:admin1_code":"36",
    "gn:admin2_code":"199.0",
    "gn:asciiname":"Khamharia",
    "gn:country_code":"IN",
    "gn:dem":292,
    "gn:feature_class":"P",
    "gn:feature_code":"PPL",
    "gn:name":"Khamharia",
    "gn:population":0,
    "gn:timezone":"Asia/Kolkata",
    "iso:country":"IN",
    "name:ceb_x_preferred":[
        "Khamharia"
    ],
    "name:swe_x_preferred":[
        "Khamharia"
    ],
    "wof:name":"Khamharia",
    "wof:placetype":"locality"
},
  "geometry": {"coordinates":[83.05419999999999,24.82182],"type":"Point"}
}