{
  "type": "Feature",
  "properties": {
    "iso:country":"IN",
    "ks:ks_alt_nam":"DHAMANKAR WASTI",
    "ks:ks_name":"Dhamankar Wasti",
    "ks:ks_pop":75,
    "ks:ks_type":"HABITATION",
    "name:eng_x_preferred":[
        "Dhamankar Wasti"
    ],
    "wof:name":"Dhamankar Wasti",
    "wof:placetype":"locality",
    "wof:population":75
},
  "geometry": {"coordinates":[73.918618,17.111038],"type":"Point"}
}