{
  "type": "Feature",
  "properties": {
    "gn:admin1_code":"36",
    "gn:admin2_code":"188.0",
    "gn:asciiname":"Chhajanian",
    "gn:country_code":"IN",
    "gn:dem":85,
    "gn:feature_class":"P",
    "gn:feature_code":"PPL",
    "gn:name":"Chhajani\u0101n",
    "gn:population":0,
    "gn:timezone":"Asia/Kolkata",
    "iso:country":"IN",
    "ks:ks_name":"Chhajania",
    "ks:ks_pop":92,
    "ks:ks_type":"HABITATION",
    "name:eng_x_preferred":[
        "Chhajania"
    ],
    "name:eng_x_variant":[
        "Chhajanian"
    ],
    "wof:name":"Chhajania",
    "wof:placetype":"locality",
    "wof:population":92
},
  "geometry": {"coordinates":[83.142866,26.717518],"type":"Point"}
}