{
  "type": "Feature",
  "properties": {
    "iso:country":"IN",
    "ks:ks_name":"Masitiya",
    "ks:ks_pop":3180,
    "ks:ks_type":"VILLAGE",
    "name:eng_x_preferred":[
        "Masitiya"
    ],
    "wof:name":"Masitiya",
    "wof:placetype":"neighbourhood",
    "wof:population":3180
},
  "geometry": {"coordinates":[70.016356,22.40405],"type":"Point"}
}