{
  "type": "Feature",
  "properties": {
    "iso:country":"IN",
    "ks:ks_name":"Kharodi",
    "ks:ks_pop":73,
    "ks:ks_type":"VILLAGE",
    "name:eng_x_preferred":[
        "Kharodi"
    ],
    "wof:name":"Kharodi",
    "wof:placetype":"locality",
    "wof:population":73
},
  "geometry": {"coordinates":[71.57622499999999,25.236347],"type":"Point"}
}