{
  "type": "Feature",
  "properties": {
    "iso:country":"IN",
    "ks:ks_name":"Unhari Kheda Ryt",
    "ks:ks_pop":238,
    "ks:ks_type":"HABITATION",
    "name:eng_x_preferred":[
        "Unhari Kheda Ryt"
    ],
    "wof:name":"Unhari Kheda Ryt",
    "wof:placetype":"locality",
    "wof:population":238
},
  "geometry": {"coordinates":[79.30538300000001,23.429304],"type":"Point"}
}