{
  "type": "Feature",
  "properties": {
    "gn:admin1_code":"34.0",
    "gn:admin2_code":"209.0",
    "gn:asciiname":"Majlispur",
    "gn:country_code":"IN",
    "gn:dem":57,
    "gn:feature_class":"P",
    "gn:feature_code":"PPL",
    "gn:name":"Majlispur",
    "gn:population":0,
    "gn:timezone":"Asia/Kolkata",
    "iso:country":"IN",
    "ks:ks_name":"Majlispur",
    "ks:ks_pop":2804,
    "ks:ks_type":"VILLAGE",
    "name:eng_x_preferred":[
        "Majlispur"
    ],
    "wof:name":"Majlispur",
    "wof:placetype":"locality",
    "wof:population":2804
},
  "geometry": {"coordinates":[87.606527,26.236518],"type":"Point"}
}