{
  "type": "Feature",
  "properties": {
    "gn:admin1_code":"19.0",
    "gn:admin2_code":"571.0",
    "gn:asciiname":"Gidaganhalli",
    "gn:country_code":"IN",
    "gn:dem":918,
    "gn:feature_class":"P",
    "gn:feature_code":"PPL",
    "gn:name":"Gidaganhalli",
    "gn:population":0,
    "gn:timezone":"Asia/Kolkata",
    "iso:country":"IN",
    "wof:name":"Gidaganhalli",
    "wof:placetype":"locality"
},
  "geometry": {"coordinates":[77.29901,13.31762],"type":"Point"}
}