{
  "type": "Feature",
  "properties": {
    "gn:admin1_code":"25.0",
    "gn:admin2_code":"619.0",
    "gn:asciiname":"Parappanamodu",
    "gn:country_code":"IN",
    "gn:dem":22,
    "gn:feature_class":"P",
    "gn:feature_code":"PPL",
    "gn:name":"Parappan\u0101modu",
    "gn:population":0,
    "gn:timezone":"Asia/Kolkata",
    "iso:country":"IN",
    "ks:ks_alt_nam":"Parappan\u0101modu",
    "ks:ks_name":"Parappanamodu",
    "ks:ks_type":"VILLAGE",
    "name:eng_x_preferred":[
        "Parappanamodu"
    ],
    "name:eng_x_variant":[
        "Parappan\u0101modu"
    ],
    "wof:name":"Parappanamodu",
    "wof:placetype":"locality"
},
  "geometry": {"coordinates":[79.400976,10.762088],"type":"Point"}
}