{
  "type": "Feature",
  "properties": {
    "iso:country":"IN",
    "ks:ks_name":"Patkhauli",
    "ks:ks_pop":156,
    "ks:ks_type":"HABITATION",
    "name:eng_x_preferred":[
        "Patkhauli"
    ],
    "wof:name":"Patkhauli",
    "wof:placetype":"locality",
    "wof:population":156
},
  "geometry": {"coordinates":[82.468616,26.525197],"type":"Point"}
}