{
  "type": "Feature",
  "properties": {
    "iso:country":"IN",
    "ks:ks_name":"Ram Pura",
    "ks:ks_pop":163,
    "ks:ks_type":"HABITATION",
    "ks:ks_uagg_main":0,
    "name:eng_x_preferred":[
        "Ram Pura"
    ],
    "wof:name":"Ram Pura",
    "wof:placetype":"neighbourhood",
    "wof:population":163
},
  "geometry": {"coordinates":[79.792147,27.035593],"type":"Point"}
}