{
  "type": "Feature",
  "properties": {
    "iso:country":"IN",
    "ks:ks_name":"Semhalpara",
    "ks:ks_pop":247,
    "ks:ks_type":"HABITATION",
    "name:eng_x_preferred":[
        "Semhalpara"
    ],
    "wof:name":"Semhalpara",
    "wof:placetype":"locality",
    "wof:population":247
},
  "geometry": {"coordinates":[82.388482,19.941924],"type":"Point"}
}