{
  "type": "Feature",
  "properties": {
    "iso:country":"IN",
    "ks:ks_name":"Chattam",
    "ks:ks_pop":821,
    "ks:ks_type":"HABITATION",
    "name:eng_x_preferred":[
        "Chattam"
    ],
    "wof:name":"Chattam",
    "wof:placetype":"locality",
    "wof:population":821
},
  "geometry": {"coordinates":[84.52481299999999,22.079103],"type":"Point"}
}