{
  "type": "Feature",
  "properties": {
    "gn:admin1_code":"36.0",
    "gn:admin2_code":"152.0",
    "gn:asciiname":"Sari Nagla",
    "gn:country_code":"IN",
    "gn:dem":160,
    "gn:feature_class":"P",
    "gn:feature_code":"PPL",
    "gn:name":"S\u0101ri N\u0101gla",
    "gn:population":0,
    "gn:timezone":"Asia/Kolkata",
    "iso:country":"IN",
    "ks:ks_alt_nam":"S\u0101ri N\u0101gla",
    "ks:ks_name":"Sari Nagla",
    "ks:ks_type":"VILLAGE",
    "name:eng_x_preferred":[
        "Sari Nagla"
    ],
    "name:eng_x_variant":[
        "S\u0101ri N\u0101gla"
    ],
    "wof:name":"Sari Nagla",
    "wof:placetype":"locality"
},
  "geometry": {"coordinates":[79.73289800000001,28.071322],"type":"Point"}
}