{
  "type": "Feature",
  "properties": {
    "iso:country":"IN",
    "ks:ks_alt_nam":"R\u0101j\u0101dumar",
    "ks:ks_name":"Rajadumar",
    "ks:ks_type":"VILLAGE",
    "name:eng_x_preferred":[
        "Rajadumar"
    ],
    "name:eng_x_variant":[
        "R\u0101j\u0101dumar"
    ],
    "wof:name":"Rajadumar",
    "wof:placetype":"locality"
},
  "geometry": {"coordinates":[86.152604,24.612315],"type":"Point"}
}