{
  "type": "Feature",
  "properties": {
    "gn:admin1_code":"36",
    "gn:admin2_code":"175.0",
    "gn:asciiname":"Satanpur",
    "gn:country_code":"IN",
    "gn:dem":97,
    "gn:feature_class":"P",
    "gn:feature_code":"PPL",
    "gn:name":"S\u0101tanpur",
    "gn:population":0,
    "gn:timezone":"Asia/Kolkata",
    "iso:country":"IN",
    "ks:ks_alt_nam":"S\u0101tanpur",
    "ks:ks_name":"Satanpur",
    "ks:ks_pop":862,
    "ks:ks_type":"VILLAGE",
    "ks:ks_uagg_main":0,
    "name:eng_x_preferred":[
        "Satanpur"
    ],
    "name:eng_x_variant":[
        "S\u0101tanpur"
    ],
    "wof:name":"Satanpur",
    "wof:placetype":"neighbourhood",
    "wof:population":862
},
  "geometry": {"coordinates":[82.00326099999999,25.645091],"type":"Point"}
}