{
  "type": "Feature",
  "properties": {
    "iso:country":"IN",
    "ks:ks_name":"Nemutangakur",
    "ks:ks_pop":540,
    "ks:ks_type":"VILLAGE",
    "name:eng_x_preferred":[
        "Nemutangakur"
    ],
    "wof:name":"Nemutangakur",
    "wof:placetype":"locality",
    "wof:population":540
},
  "geometry": {"coordinates":[94.70858200000001,27.209352],"type":"Point"}
}