{
  "type": "Feature",
  "properties": {
    "iso:country":"IN",
    "ks:ks_name":"Jasvali",
    "ks:ks_pop":1544,
    "ks:ks_type":"VILLAGE",
    "ks:ks_uagg_main":0,
    "name:eng_x_preferred":[
        "Jasvali"
    ],
    "wof:name":"Jasvali",
    "wof:placetype":"neighbourhood",
    "wof:population":1544
},
  "geometry": {"coordinates":[73.04637200000001,18.067637],"type":"Point"}
}