{
  "type": "Feature",
  "properties": {
    "iso:country":"IN",
    "ks:ks_alt_nam":"Morapp\u016br Reserved Forest",
    "ks:ks_name":"Morappur Reserved Forest",
    "ks:ks_type":"VILLAGE",
    "name:eng_x_preferred":[
        "Morappur Reserved Forest"
    ],
    "name:eng_x_variant":[
        "Morapp\u016br Reserved Forest"
    ],
    "wof:name":"Morappur Reserved Forest",
    "wof:placetype":"locality"
},
  "geometry": {"coordinates":[78.454911,12.145543],"type":"Point"}
}