{
  "type": "Feature",
  "properties": {
    "iso:country":"IN",
    "ks:ks_name":"Kaljuri",
    "ks:ks_pop":991,
    "ks:ks_type":"VILLAGE",
    "ks:ks_uagg_main":0,
    "name:eng_x_preferred":[
        "Kaljuri"
    ],
    "wof:name":"Kaljuri",
    "wof:placetype":"neighbourhood",
    "wof:population":991
},
  "geometry": {"coordinates":[91.832469,26.575856],"type":"Point"}
}