{
  "type": "Feature",
  "properties": {
    "iso:country":"IN",
    "ks:ks_name":"Bhelwatoli",
    "ks:ks_pop":78,
    "ks:ks_type":"HABITATION",
    "name:eng_x_preferred":[
        "Bhelwatoli"
    ],
    "wof:name":"Bhelwatoli",
    "wof:placetype":"locality",
    "wof:population":78
},
  "geometry": {"coordinates":[84.05332,22.548458],"type":"Point"}
}