{
  "type": "Feature",
  "properties": {
    "iso:country":"IN",
    "ks:ks_name":"Bhandai",
    "ks:ks_pop":42,
    "ks:ks_type":"VILLAGE",
    "name:eng_x_preferred":[
        "Bhandai"
    ],
    "wof:name":"Bhandai",
    "wof:placetype":"locality",
    "wof:population":42
},
  "geometry": {"coordinates":[78.89263,30.20779],"type":"Point"}
}