{
  "type": "Feature",
  "properties": {
    "iso:country":"IN",
    "ks:ks_name":"Lakhipathar",
    "ks:ks_pop":426,
    "ks:ks_type":"HABITATION",
    "ks:ks_uagg_main":0,
    "name:eng_x_preferred":[
        "Lakhipathar"
    ],
    "wof:name":"Lakhipathar",
    "wof:placetype":"neighbourhood",
    "wof:population":426
},
  "geometry": {"coordinates":[93.466301,26.60495],"type":"Point"}
}