{
  "type": "Feature",
  "properties": {
    "gn:admin1_code":"16.0",
    "gn:admin2_code":"506.0",
    "gn:asciiname":"Sindhi",
    "gn:country_code":"IN",
    "gn:dem":233,
    "gn:feature_class":"P",
    "gn:feature_code":"PPL",
    "gn:name":"Sindhi",
    "gn:population":0,
    "gn:timezone":"Asia/Kolkata",
    "iso:country":"IN",
    "wof:name":"Sindhi",
    "wof:placetype":"locality"
},
  "geometry": {"coordinates":[79.68777,20.74233],"type":"Point"}
}