{
  "type": "Feature",
  "properties": {
    "gn:admin1_code":"16.0",
    "gn:admin2_code":"506.0",
    "gn:asciiname":"Sindhi",
    "gn:country_code":"IN",
    "gn:dem":233,
    "gn:feature_class":"P",
    "gn:feature_code":"PPL",
    "gn:name":"Sindhi",
    "gn:population":0,
    "gn:timezone":"Asia/Kolkata",
    "iso:country":"IN",
    "name:fas_x_preferred":[
        "\u0633\u0646\u062f\u06cc"
    ],
    "name:guj_x_preferred":[
        "\u0ab8\u0abf\u0a82\u0aa7\u0ac0"
    ],
    "name:hin_x_preferred":[
        "\u0938\u093f\u0902\u0927\u0940"
    ],
    "name:mar_x_preferred":[
        "\u0938\u093f\u0902\u0927\u0940"
    ],
    "name:nld_x_preferred":[
        "Sindhi"
    ],
    "name:nor_x_preferred":[
        "Sindhi"
    ],
    "name:rus_x_preferred":[
        "\u0421\u0438\u043d\u0434\u0445\u0438"
    ],
    "name:snd_x_preferred":[
        "\u0633\u0646\u068c\u064a"
    ],
    "wof:name":"Sindhi",
    "wof:placetype":"locality"
},
  "geometry": {"coordinates":[79.68777,20.74233],"type":"Point"}
}