{
  "type": "Feature",
  "properties": {
    "gn:admin1_code":"11.0",
    "gn:admin2_code":"26.0",
    "gn:asciiname":"Shagogi",
    "gn:country_code":"IN",
    "gn:dem":1729,
    "gn:feature_class":"P",
    "gn:feature_code":"PPL",
    "gn:name":"Shagogi",
    "gn:population":0,
    "gn:timezone":"Asia/Kolkata",
    "iso:country":"IN",
    "wof:name":"Shagogi",
    "wof:placetype":"locality"
},
  "geometry": {"coordinates":[77.44965999999999,31.39021],"type":"Point"}
}