{
  "type": "Feature",
  "properties": {
    "gn:admin1_code":"39.0",
    "gn:admin2_code":"64.0",
    "gn:asciiname":"Malta",
    "gn:country_code":"IN",
    "gn:dem":1569,
    "gn:feature_class":"P",
    "gn:feature_code":"PPL",
    "gn:name":"Malta",
    "gn:population":0,
    "gn:timezone":"Asia/Kolkata",
    "iso:country":"IN",
    "wof:name":"Malta",
    "wof:placetype":"locality"
},
  "geometry": {"coordinates":[79.71234,29.56853],"type":"Point"}
}