{
  "type": "Feature",
  "properties": {
    "gn:admin1_code":"37",
    "gn:admin2_code":"403.0",
    "gn:asciiname":"Randidih",
    "gn:country_code":"IN",
    "gn:dem":200,
    "gn:feature_class":"P",
    "gn:feature_code":"PPL",
    "gn:name":"R\u0101ndidih",
    "gn:population":0,
    "gn:timezone":"Asia/Kolkata",
    "iso:country":"IN",
    "wof:name":"Randidih",
    "wof:placetype":"locality"
},
  "geometry": {"coordinates":[83.39409999999999,21.6751],"type":"Point"}
}