{
  "type": "Feature",
  "properties": {
    "gn:admin1_code":"2",
    "gn:admin2_code":"546.0",
    "gn:asciiname":"Ramachandrapuram",
    "gn:country_code":"IN",
    "gn:dem":44,
    "gn:feature_class":"P",
    "gn:feature_code":"PPL",
    "gn:name":"R\u0101machandrapuram",
    "gn:population":0,
    "gn:timezone":"Asia/Kolkata",
    "iso:country":"IN",
    "name:ita_x_preferred":[
        "Ramachandrapuram"
    ],
    "name:vie_x_preferred":[
        "Ramachandrapuram"
    ],
    "wof:name":"Ramachandrapuram",
    "wof:placetype":"locality"
},
  "geometry": {"coordinates":[81.36856999999998,16.88564],"type":"Point"}
}