{
  "type": "Feature",
  "properties": {
    "iso:country":"IN",
    "ks:ks_name":"Pittalagudem",
    "ks:ks_pop":112,
    "ks:ks_type":"HABITATION",
    "name:eng_x_preferred":[
        "Pittalagudem"
    ],
    "wof:name":"Pittalagudem",
    "wof:placetype":"locality",
    "wof:population":112
},
  "geometry": {"coordinates":[78.95476499999999,17.747802],"type":"Point"}
}