{
  "type": "Feature",
  "properties": {
    "gn:admin1_code":"37",
    "gn:admin2_code":"412.0",
    "gn:asciiname":"Rajpur",
    "gn:country_code":"IN",
    "gn:dem":304,
    "gn:feature_class":"P",
    "gn:feature_code":"PPL",
    "gn:name":"R\u0101jpur",
    "gn:population":0,
    "gn:timezone":"Asia/Kolkata",
    "iso:country":"IN",
    "name:cat_x_preferred":[
        "Rajpur"
    ],
    "name:ceb_x_preferred":[
        "Rajpur"
    ],
    "name:pol_x_preferred":[
        "Rajpur"
    ],
    "name:spa_x_preferred":[
        "Rajpur"
    ],
    "name:swe_x_preferred":[
        "Rajpur"
    ],
    "wof:name":"Rajpur",
    "wof:placetype":"locality"
},
  "geometry": {"coordinates":[81.77687,20.73464],"type":"Point"}
}