{
  "type": "Feature",
  "properties": {
    "iso:country":"IN",
    "ks:ks_name":"Talawari",
    "ks:ks_pop":84,
    "ks:ks_type":"HABITATION",
    "name:eng_x_preferred":[
        "Talawari"
    ],
    "wof:name":"Talawari",
    "wof:placetype":"locality",
    "wof:population":84
},
  "geometry": {"coordinates":[82.090659,18.343749],"type":"Point"}
}