{
  "type": "Feature",
  "properties": {
    "gn:admin1_code":"38.0",
    "gn:admin2_code":"347.0",
    "gn:asciiname":"Gidhaur",
    "gn:country_code":"IN",
    "gn:dem":463,
    "gn:feature_class":"P",
    "gn:feature_code":"PPL",
    "gn:name":"Gidhaur",
    "gn:population":0,
    "gn:timezone":"Asia/Kolkata",
    "iso:country":"IN",
    "name:cat_x_preferred":[
        "Gidhaur"
    ],
    "wof:name":"Gidhaur",
    "wof:placetype":"locality"
},
  "geometry": {"coordinates":[85.02544,24.17705],"type":"Point"}
}