{
  "type": "Feature",
  "properties": {
    "iso:country":"IN",
    "ks:ks_name":"Janabar",
    "ks:ks_pop":594,
    "ks:ks_type":"VILLAGE",
    "name:eng_x_preferred":[
        "Janabar"
    ],
    "wof:name":"Janabar",
    "wof:placetype":"locality",
    "wof:population":594
},
  "geometry": {"coordinates":[87.706964,22.411534],"type":"Point"}
}