{
  "type": "Feature",
  "properties": {
    "gn:admin1_code":"19.0",
    "gn:admin2_code":"574.0",
    "gn:asciiname":"Kondavagilu",
    "gn:country_code":"IN",
    "gn:dem":784,
    "gn:feature_class":"P",
    "gn:feature_code":"PPL",
    "gn:name":"Kondavagilu",
    "gn:population":0,
    "gn:timezone":"Asia/Kolkata",
    "iso:country":"IN",
    "wof:name":"Kondavagilu",
    "wof:placetype":"locality"
},
  "geometry": {"coordinates":[76.23613,13.39984],"type":"Point"}
}