{
  "type": "Feature",
  "properties": {
    "gn:admin1_code":"19.0",
    "gn:admin2_code":"584.0",
    "gn:asciiname":"Channasandra",
    "gn:country_code":"IN",
    "gn:dem":642,
    "gn:feature_class":"P",
    "gn:feature_code":"PPL",
    "gn:name":"Channasandra",
    "gn:population":0,
    "gn:timezone":"Asia/Kolkata",
    "iso:country":"IN",
    "name:vie_x_preferred":[
        "Channasandra"
    ],
    "wof:name":"Channasandra",
    "wof:placetype":"locality"
},
  "geometry": {"coordinates":[77.4973,12.41627],"type":"Point"}
}