{
  "type": "Feature",
  "properties": {
    "gn:admin1_code":"16",
    "gn:admin2_code":"500.0",
    "gn:asciiname":"Belura",
    "gn:country_code":"IN",
    "gn:dem":306,
    "gn:feature_class":"P",
    "gn:feature_code":"PPL",
    "gn:name":"Belura",
    "gn:population":0,
    "gn:timezone":"Asia/Kolkata",
    "iso:country":"IN",
    "ks:ks_name":"Belura",
    "ks:ks_pop":293,
    "ks:ks_type":"HABITATION",
    "name:eng_x_preferred":[
        "Belura"
    ],
    "name:vie_x_preferred":[
        "Belura"
    ],
    "wof:name":"Belura",
    "wof:placetype":"locality",
    "wof:population":293
},
  "geometry": {"coordinates":[76.46514000000001,20.708445],"type":"Point"}
}