{
  "type": "Feature",
  "properties": {
    "iso:country":"IN",
    "ks:ks_name":"Sangagua",
    "ks:ks_pop":547,
    "ks:ks_type":"VILLAGE",
    "name:eng_x_preferred":[
        "Sangagua"
    ],
    "wof:name":"Sangagua",
    "wof:placetype":"locality",
    "wof:population":547
},
  "geometry": {"coordinates":[84.937753,21.763916],"type":"Point"}
}