{
  "type": "Feature",
  "properties": {
    "iso:country":"IN",
    "ks:ks_name":"Mushari East",
    "ks:ks_pop":630,
    "ks:ks_type":"HABITATION",
    "name:eng_x_preferred":[
        "Mushari East"
    ],
    "wof:name":"Mushari East",
    "wof:placetype":"locality",
    "wof:population":630
},
  "geometry": {"coordinates":[87.309392,25.802092],"type":"Point"}
}