{
  "type": "Feature",
  "properties": {
    "iso:country":"IN",
    "name:ast_x_preferred":[
        "Mandav"
    ],
    "name:ben_x_preferred":[
        "\u09ae\u09be\u09a8\u09cd\u09a1\u09ac"
    ],
    "name:bpy_x_preferred":[
        "\u09ae\u09be\u09a8\u09cd\u09a1\u09ac"
    ],
    "name:eng_x_preferred":[
        "Mandav"
    ],
    "name:fra_x_preferred":[
        "Mandav"
    ],
    "name:hin_x_preferred":[
        "\u092e\u093e\u0902\u0921\u0935"
    ],
    "name:ita_x_preferred":[
        "Mandav"
    ],
    "name:mlg_x_preferred":[
        "Mandav"
    ],
    "name:msa_x_preferred":[
        "Mandav"
    ],
    "name:nan_x_preferred":[
        "Mandav"
    ],
    "name:new_x_preferred":[
        "\u092e\u0928\u094d\u0926\u092d"
    ],
    "name:nld_x_preferred":[
        "Mandav"
    ],
    "name:por_x_preferred":[
        "Mandav"
    ],
    "name:vie_x_preferred":[
        "Mandav"
    ],
    "name:zho_x_preferred":[
        "\u9a6c\u6069\u8fbe\u6c83"
    ],
    "qs:name":"Mandav",
    "qs:name_adm0":"India",
    "qs:name_adm1":"Madhya Pradesh",
    "qs:photos":617,
    "qs:photos_1k":125,
    "qs:photos_9k":3,
    "qs:photos_9r":5,
    "qs:photos_all":617,
    "qs:photos_sr":8,
    "qs:placetype":"Town",
    "qs:pop_sr":"0",
    "wd:wordcount":804,
    "wof:name":"Mandav",
    "wof:placetype":"locality"
},
  "geometry": {"coordinates":[75.413932,22.33625],"type":"Point"}
}