{
  "type": "Feature",
  "properties": {
    "iso:country":"IN",
    "ks:ks_name":"Cluster Para",
    "ks:ks_pop":78,
    "ks:ks_type":"HABITATION",
    "name:eng_x_preferred":[
        "Cluster Para"
    ],
    "wof:name":"Cluster Para",
    "wof:placetype":"locality",
    "wof:population":78
},
  "geometry": {"coordinates":[91.732412,23.415871],"type":"Point"}
}