{
  "type": "Feature",
  "properties": {
    "iso:country":"IN",
    "ks:ks_name":"Odon Ka Guda",
    "ks:ks_pop":221,
    "ks:ks_type":"HABITATION",
    "name:eng_x_preferred":[
        "Odon Ka Guda"
    ],
    "wof:name":"Odon Ka Guda",
    "wof:placetype":"locality",
    "wof:population":221
},
  "geometry": {"coordinates":[73.528808,24.858553],"type":"Point"}
}