{
  "type": "Feature",
  "properties": {
    "gn:admin1_code":"39.0",
    "gn:admin2_code":"061",
    "gn:asciiname":"Khala",
    "gn:country_code":"IN",
    "gn:dem":940,
    "gn:feature_class":"P",
    "gn:feature_code":"PPL",
    "gn:name":"Kh\u0101la",
    "gn:population":0,
    "gn:timezone":"Asia/Kolkata",
    "iso:country":"IN",
    "ks:ks_alt_nam":"Kh\u0101la",
    "ks:ks_name":"Khala",
    "ks:ks_type":"VILLAGE",
    "name:eng_x_preferred":[
        "Khala"
    ],
    "name:eng_x_variant":[
        "Kh\u0101la"
    ],
    "wof:name":"Khala",
    "wof:placetype":"locality"
},
  "geometry": {"coordinates":[78.524508,29.800075],"type":"Point"}
}