{
  "type": "Feature",
  "properties": {
    "iso:country":"IN",
    "ks:ks_alt_nam":"Upper tola",
    "ks:ks_name":"Upper Tola",
    "ks:ks_pop":495,
    "ks:ks_type":"HABITATION",
    "name:eng_x_preferred":[
        "Upper Tola"
    ],
    "wof:name":"Upper Tola",
    "wof:placetype":"locality",
    "wof:population":495
},
  "geometry": {"coordinates":[86.621207,24.878352],"type":"Point"}
}