{
  "type": "Feature",
  "properties": {
    "iso:country":"IN",
    "ks:ks_name":"Kutia Ka Purwa",
    "ks:ks_pop":324,
    "ks:ks_type":"HABITATION",
    "name:eng_x_preferred":[
        "Kutia Ka Purwa"
    ],
    "wof:name":"Kutia Ka Purwa",
    "wof:placetype":"locality",
    "wof:population":324
},
  "geometry": {"coordinates":[81.629105,25.374609],"type":"Point"}
}