{
  "type": "Feature",
  "properties": {
    "gn:admin1_code":"35",
    "gn:admin2_code":"464.0",
    "gn:asciiname":"Jharni",
    "gn:country_code":"IN",
    "gn:dem":245,
    "gn:feature_class":"P",
    "gn:feature_code":"PPL",
    "gn:name":"Jharni",
    "gn:population":0,
    "gn:timezone":"Asia/Kolkata",
    "iso:country":"IN",
    "ks:ks_name":"Jharni",
    "ks:ks_pop":1822,
    "ks:ks_type":"VILLAGE",
    "name:eng_x_preferred":[
        "Jharni"
    ],
    "wof:name":"Jharni",
    "wof:placetype":"locality",
    "wof:population":1822
},
  "geometry": {"coordinates":[74.3357,23.053834],"type":"Point"}
}