{
  "type": "Feature",
  "properties": {
    "gn:admin1_code":"37",
    "gn:admin2_code":"407.0",
    "gn:asciiname":"Kothar",
    "gn:country_code":"IN",
    "gn:dem":329,
    "gn:feature_class":"P",
    "gn:feature_code":"PPL",
    "gn:name":"Koth\u0101r",
    "gn:population":0,
    "gn:timezone":"Asia/Kolkata",
    "iso:country":"IN",
    "name:snd_x_preferred":[
        "\u0622\u0628 \u06aa\u0648\u062b\u0631"
    ],
    "wof:name":"Kothar",
    "wof:placetype":"locality"
},
  "geometry": {"coordinates":[81.30481999999998,22.00605],"type":"Point"}
}