{
  "type": "Feature",
  "properties": {
    "iso:country":"IN",
    "ks:ks_name":"Veerisettypalle",
    "ks:ks_pop":137,
    "ks:ks_type":"HABITATION",
    "name:eng_x_preferred":[
        "Veerisettypalle"
    ],
    "wof:name":"Veerisettypalle",
    "wof:placetype":"locality",
    "wof:population":137
},
  "geometry": {"coordinates":[79.14630699999999,13.495813],"type":"Point"}
}