{
  "type": "Feature",
  "properties": {
    "iso:country":"IN",
    "ks:ks_alt_nam":"pedapolam",
    "ks:ks_name":"Pedapolam",
    "ks:ks_pop":57,
    "ks:ks_type":"HABITATION",
    "name:eng_x_preferred":[
        "Pedapolam"
    ],
    "wof:name":"Pedapolam",
    "wof:placetype":"locality",
    "wof:population":57
},
  "geometry": {"coordinates":[82.60324,17.924592],"type":"Point"}
}