{
  "type": "Feature",
  "properties": {
    "iso:country":"IN",
    "ks:ks_name":"Bhalukamri",
    "ks:ks_pop":445,
    "ks:ks_type":"VILLAGE",
    "name:eng_x_preferred":[
        "Bhalukamri"
    ],
    "wof:name":"Bhalukamri",
    "wof:placetype":"locality",
    "wof:population":445
},
  "geometry": {"coordinates":[91.644794,26.679483],"type":"Point"}
}