{
  "type": "Feature",
  "properties": {
    "iso:country":"IN",
    "ks:ks_name":"Pakimurigaon Part 1",
    "ks:ks_pop":296,
    "ks:ks_type":"HABITATION",
    "ks:ks_uagg_main":0,
    "name:eng_x_preferred":[
        "Pakimurigaon Part 1"
    ],
    "wof:name":"Pakimurigaon Part 1",
    "wof:placetype":"neighbourhood",
    "wof:population":296
},
  "geometry": {"coordinates":[91.985737,26.625756],"type":"Point"}
}