{
  "type": "Feature",
  "properties": {
    "gn:admin1_code":"39.0",
    "gn:admin2_code":"60.0",
    "gn:asciiname":"Jawagi",
    "gn:country_code":"IN",
    "gn:dem":1946,
    "gn:feature_class":"P",
    "gn:feature_code":"PPL",
    "gn:name":"Jaw\u0101gi",
    "gn:population":0,
    "gn:timezone":"Asia/Kolkata",
    "iso:country":"IN",
    "wof:name":"Jawagi",
    "wof:placetype":"locality"
},
  "geometry": {"coordinates":[77.99758,30.71255],"type":"Point"}
}