{
  "type": "Feature",
  "properties": {
    "iso:country":"IN",
    "ks:ks_name":"Somanpalli",
    "ks:ks_pop":74,
    "ks:ks_type":"HABITATION",
    "name:eng_x_preferred":[
        "Somanpalli"
    ],
    "wof:name":"Somanpalli",
    "wof:placetype":"locality",
    "wof:population":74
},
  "geometry": {"coordinates":[80.76952199999999,19.090202],"type":"Point"}
}