{
  "type": "Feature",
  "properties": {
    "iso:country":"IN",
    "ks:ks_name":"Rajpura",
    "ks:ks_pop":717,
    "ks:ks_type":"VILLAGE",
    "name:eng_x_preferred":[
        "Rajpura"
    ],
    "wof:name":"Rajpura",
    "wof:placetype":"locality",
    "wof:population":717
},
  "geometry": {"coordinates":[87.50322799999999,22.44397],"type":"Point"}
}