{
  "type": "Feature",
  "properties": {
    "gn:admin1_code":"19",
    "gn:admin2_code":"578.0",
    "gn:asciiname":"Maddur",
    "gn:country_code":"IN",
    "gn:dem":895,
    "gn:feature_class":"P",
    "gn:feature_code":"PPL",
    "gn:name":"Madd\u016br",
    "gn:population":0,
    "gn:timezone":"Asia/Kolkata",
    "iso:country":"IN",
    "name:und_x_variant":[
        "Madd\u016br"
    ],
    "wof:name":"Maddur",
    "wof:placetype":"locality"
},
  "geometry": {"coordinates":[76.55897,11.77915],"type":"Point"}
}