{
  "type": "Feature",
  "properties": {
    "gn:admin1_code":"19",
    "gn:admin2_code":"578.0",
    "gn:asciiname":"Maddur",
    "gn:country_code":"IN",
    "gn:dem":895,
    "gn:feature_class":"P",
    "gn:feature_code":"PPL",
    "gn:name":"Madd\u016br",
    "gn:population":0,
    "gn:timezone":"Asia/Kolkata",
    "iso:country":"IN",
    "name:ben_x_preferred":[
        "\u09ae\u09be\u09a6\u09cd\u09a6\u09c1\u09b0"
    ],
    "name:bpy_x_preferred":[
        "\u09ae\u09be\u09a6\u09cd\u09a6\u09c1\u09b0"
    ],
    "name:ceb_x_preferred":[
        "Madd\u016br"
    ],
    "name:ita_x_preferred":[
        "Maddur"
    ],
    "name:kan_x_preferred":[
        "\u0cae\u0ca6\u0ccd\u0ca6\u0cc2\u0cb0\u0cc1"
    ],
    "name:msa_x_preferred":[
        "Maddur"
    ],
    "name:new_x_preferred":[
        "\u092e\u0926\u094d\u0926\u0941\u0930"
    ],
    "name:nld_x_preferred":[
        "Maddur"
    ],
    "name:ori_x_preferred":[
        "\u0b2e\u0b3e\u0b26\u0b4d\u0b26\u0b41\u0b30\u0b4d"
    ],
    "name:por_x_preferred":[
        "Maddur"
    ],
    "name:spa_x_preferred":[
        "Maddur"
    ],
    "name:swe_x_preferred":[
        "Madd\u016br"
    ],
    "name:tcy_x_preferred":[
        "\u0cae\u0ca6\u0ccd\u0ca6\u0cc2\u0cb0\u0cc1"
    ],
    "name:und_x_variant":[
        "Madd\u016br"
    ],
    "name:urd_x_preferred":[
        "\u0645\u06cc\u0688\u0648\u0631"
    ],
    "name:vie_x_preferred":[
        "Maddur"
    ],
    "name:zho_x_preferred":[
        "\u9a6c\u5fb7\u675c\u5c14"
    ],
    "wof:name":"Maddur",
    "wof:placetype":"locality"
},
  "geometry": {"coordinates":[76.55897,11.77915],"type":"Point"}
}