{
  "type": "Feature",
  "properties": {
    "iso:country":"IN",
    "ks:ks_name":"Kantashala",
    "ks:ks_pop":115,
    "ks:ks_type":"VILLAGE",
    "name:eng_x_preferred":[
        "Kantashala"
    ],
    "wof:name":"Kantashala",
    "wof:placetype":"locality",
    "wof:population":115
},
  "geometry": {"coordinates":[87.064414,22.456316],"type":"Point"}
}