{
  "type": "Feature",
  "properties": {
    "iso:country":"IN",
    "ks:ks_name":"Ailae Khurd",
    "ks:ks_pop":8,
    "ks:ks_type":"VILLAGE",
    "ks:ks_uagg_main":0,
    "name:eng_x_preferred":[
        "Ailae Khurd"
    ],
    "wof:name":"Ailae Khurd",
    "wof:placetype":"neighbourhood",
    "wof:population":8
},
  "geometry": {"coordinates":[83.38939000000001,25.071073],"type":"Point"}
}