{
  "type": "Feature",
  "properties": {
    "iso:country":"IN",
    "ks:ks_name":"Jallurumett",
    "ks:ks_pop":147,
    "ks:ks_type":"HABITATION",
    "name:eng_x_preferred":[
        "Jallurumett"
    ],
    "wof:name":"Jallurumett",
    "wof:placetype":"locality",
    "wof:population":147
},
  "geometry": {"coordinates":[82.49269,17.801716],"type":"Point"}
}