{
  "type": "Feature",
  "properties": {
    "gn:admin1_code":"28.0",
    "gn:admin2_code":"335.0",
    "gn:asciiname":"Belgram",
    "gn:country_code":"IN",
    "gn:dem":25,
    "gn:feature_class":"P",
    "gn:feature_code":"PPL",
    "gn:name":"Belgram",
    "gn:population":0,
    "gn:timezone":"Asia/Kolkata",
    "iso:country":"IN",
    "wof:name":"Belgram",
    "wof:placetype":"locality"
},
  "geometry": {"coordinates":[87.99594,23.46034],"type":"Point"}
}