{
  "type": "Feature",
  "properties": {
    "iso:country":"IN",
    "ks:ks_alt_nam":"Cikkagadda camp",
    "ks:ks_name":"Cikkagadda Camp",
    "ks:ks_pop":149,
    "ks:ks_type":"HABITATION",
    "name:eng_x_preferred":[
        "Cikkagadda Camp"
    ],
    "wof:name":"Cikkagadda Camp",
    "wof:placetype":"locality",
    "wof:population":149
},
  "geometry": {"coordinates":[76.95652699999999,15.724804],"type":"Point"}
}