{
  "type": "Feature",
  "properties": {
    "iso:country":"IN",
    "ks:ks_name":"Banka Jura",
    "ks:ks_pop":64,
    "ks:ks_type":"VILLAGE",
    "name:eng_x_preferred":[
        "Banka Jura"
    ],
    "wof:name":"Banka Jura",
    "wof:placetype":"locality",
    "wof:population":64
},
  "geometry": {"coordinates":[87.001319,23.409455],"type":"Point"}
}