{
  "type": "Feature",
  "properties": {
    "iso:country":"IN",
    "ks:ks_name":"Rautwadi",
    "ks:ks_pop":31,
    "ks:ks_type":"HABITATION",
    "name:eng_x_preferred":[
        "Rautwadi"
    ],
    "wof:name":"Rautwadi",
    "wof:placetype":"locality",
    "wof:population":31
},
  "geometry": {"coordinates":[73.511494,16.590544],"type":"Point"}
}