{
  "type": "Feature",
  "properties": {
    "iso:country":"IN",
    "ks:ks_name":"Main Faliya",
    "ks:ks_pop":302,
    "ks:ks_type":"HABITATION",
    "name:eng_x_preferred":[
        "Main Faliya"
    ],
    "wof:name":"Main Faliya",
    "wof:placetype":"locality",
    "wof:population":302
},
  "geometry": {"coordinates":[73.892667,23.272722],"type":"Point"}
}