{
  "type": "Feature",
  "properties": {
    "iso:country":"IN",
    "ks:ks_alt_nam":"MASJID TOLA",
    "ks:ks_name":"Masjid Tola",
    "ks:ks_pop":870,
    "ks:ks_type":"HABITATION",
    "name:eng_x_preferred":[
        "Masjid Tola"
    ],
    "wof:name":"Masjid Tola",
    "wof:placetype":"locality",
    "wof:population":870
},
  "geometry": {"coordinates":[85.46643400000001,23.598699],"type":"Point"}
}