{
  "type": "Feature",
  "properties": {
    "gn:admin1_code":"11",
    "gn:admin2_code":"24.0",
    "gn:asciiname":"Khungnun",
    "gn:country_code":"IN",
    "gn:dem":955,
    "gn:feature_class":"P",
    "gn:feature_code":"PPL",
    "gn:name":"Kh\u016bngn\u016bn",
    "gn:population":0,
    "gn:timezone":"Asia/Kolkata",
    "iso:country":"IN",
    "wof:name":"Khungnun",
    "wof:placetype":"locality"
},
  "geometry": {"coordinates":[76.55435,32.03377],"type":"Point"}
}