{
  "type": "Feature",
  "properties": {
    "gn:admin1_code":"24.0",
    "gn:admin2_code":"123",
    "gn:asciiname":"Gurach",
    "gn:country_code":"IN",
    "gn:dem":715,
    "gn:feature_class":"P",
    "gn:feature_code":"PPL",
    "gn:name":"G\u016brach",
    "gn:population":0,
    "gn:timezone":"Asia/Kolkata",
    "iso:country":"IN",
    "name:und_x_variant":[
        "G\u016brach",
        "Gur\u0101ch"
    ],
    "wof:name":"Gurach",
    "wof:placetype":"locality"
},
  "geometry": {"coordinates":[73.66825,24.79847],"type":"Point"}
}