{
  "type": "Feature",
  "properties": {
    "iso:country":"IN",
    "ks:ks_name":"Manjha Kanhwaria",
    "ks:ks_pop":1117,
    "ks:ks_type":"VILLAGE",
    "ks:ks_uagg_main":0,
    "name:eng_x_preferred":[
        "Manjha Kanhwaria"
    ],
    "wof:name":"Manjha Kanhwaria",
    "wof:placetype":"neighbourhood",
    "wof:population":1117
},
  "geometry": {"coordinates":[84.252504,26.412208],"type":"Point"}
}