{
  "type": "Feature",
  "properties": {
    "iso:country":"IN",
    "ks:ks_name":"Beniya Tola",
    "ks:ks_pop":219,
    "ks:ks_type":"HABITATION",
    "ks:ks_uagg_main":0,
    "name:eng_x_preferred":[
        "Beniya Tola"
    ],
    "wof:name":"Beniya Tola",
    "wof:placetype":"neighbourhood",
    "wof:population":219
},
  "geometry": {"coordinates":[84.268114,26.735303],"type":"Point"}
}