{
  "type": "Feature",
  "properties": {
    "iso:country":"IN",
    "ks:ks_name":"Pedamadi",
    "ks:ks_pop":109,
    "ks:ks_type":"HABITATION",
    "name:eng_x_preferred":[
        "Pedamadi"
    ],
    "wof:name":"Pedamadi",
    "wof:placetype":"locality",
    "wof:population":109
},
  "geometry": {"coordinates":[84.29662399999999,18.746965],"type":"Point"}
}