{
  "type": "Feature",
  "properties": {
    "gn:admin1_code":"36",
    "gn:admin2_code":"167.0",
    "gn:asciiname":"Deogarh",
    "gn:country_code":"IN",
    "gn:dem":326,
    "gn:feature_class":"P",
    "gn:feature_code":"PPL",
    "gn:name":"Deogarh",
    "gn:population":0,
    "gn:timezone":"Asia/Kolkata",
    "iso:country":"IN",
    "name:ceb_x_preferred":[
        "Deogarh"
    ],
    "name:deu_x_preferred":[
        "Deogarh"
    ],
    "name:swe_x_preferred":[
        "Deogarh"
    ],
    "wof:name":"Deogarh",
    "wof:placetype":"locality"
},
  "geometry": {"coordinates":[78.62182,24.91051],"type":"Point"}
}