{
  "type": "Feature",
  "properties": {
    "gn:country":"IN",
    "gn:fcode":"PPL",
    "gn:population":19592,
    "iso:country":"IN",
    "name:und_x_variant":[
        "Ch\u0101ndor"
    ],
    "qs:name":"Chandvad",
    "qs:name_adm0":"India",
    "qs:name_adm1":"Maharashtra",
    "qs:photos_9r":0,
    "qs:photos_sr":0,
    "qs:placetype":"Town",
    "qs:pop_sr":"6",
    "wof:name":"Chandvad",
    "wof:placetype":"locality",
    "wof:population":19592
},
  "geometry": {"coordinates":[74.24439,20.33045],"type":"Point"}
}