{
  "type": "Feature",
  "properties": {
    "iso:country":"IN",
    "ks:ks_alt_nam":"Sarpa singra",
    "ks:ks_name":"Sarpa Singra",
    "ks:ks_pop":1225,
    "ks:ks_type":"HABITATION",
    "name:eng_x_preferred":[
        "Sarpa Singra"
    ],
    "wof:name":"Sarpa Singra",
    "wof:placetype":"locality",
    "wof:population":1225
},
  "geometry": {"coordinates":[89.640495,26.250157],"type":"Point"}
}