{
  "type": "Feature",
  "properties": {
    "gn:admin1_code":"34.0",
    "gn:admin2_code":"217.0",
    "gn:asciiname":"Bishunpur",
    "gn:country_code":"IN",
    "gn:dem":73,
    "gn:feature_class":"P",
    "gn:feature_code":"PPL",
    "gn:name":"Bishunpur",
    "gn:population":0,
    "gn:timezone":"Asia/Kolkata",
    "iso:country":"IN",
    "wof:name":"Bishunpur",
    "wof:placetype":"locality"
},
  "geometry": {"coordinates":[84.53649,26.3652],"type":"Point"}
}