{
  "type": "Feature",
  "properties": {
    "iso:country":"IN",
    "ks:ks_name":"Bhukero Ki Dhani",
    "ks:ks_pop":1211,
    "ks:ks_type":"HABITATION",
    "name:eng_x_preferred":[
        "Bhukero Ki Dhani"
    ],
    "wof:name":"Bhukero Ki Dhani",
    "wof:placetype":"locality",
    "wof:population":1211
},
  "geometry": {"coordinates":[72.79519500000001,26.651583],"type":"Point"}
}