{
  "type": "Feature",
  "properties": {
    "iso:country":"IN",
    "ks:ks_alt_nam":"Ankalamma ST Colony",
    "ks:ks_name":"Ankalamma St Colony",
    "ks:ks_pop":142,
    "ks:ks_type":"HABITATION",
    "name:eng_x_preferred":[
        "Ankalamma St Colony"
    ],
    "wof:name":"Ankalamma St Colony",
    "wof:placetype":"locality",
    "wof:population":142
},
  "geometry": {"coordinates":[79.36815199999999,14.058358],"type":"Point"}
}