{
  "type": "Feature",
  "properties": {
    "iso:country":"IN",
    "ks:ks_name":"Botegaon",
    "ks:ks_pop":38,
    "ks:ks_type":"VILLAGE",
    "name:eng_x_preferred":[
        "Botegaon"
    ],
    "wof:name":"Botegaon",
    "wof:placetype":"locality",
    "wof:population":38
},
  "geometry": {"coordinates":[79.907375,20.307919],"type":"Point"}
}