{
  "type": "Feature",
  "properties": {
    "iso:country":"IN",
    "ks:ks_name":"Banjarewala Mafi",
    "ks:ks_pop":2198,
    "ks:ks_type":"VILLAGE",
    "ks:ks_uagg_main":0,
    "name:eng_x_preferred":[
        "Banjarewala Mafi"
    ],
    "wof:name":"Banjarewala Mafi",
    "wof:placetype":"locality",
    "wof:population":2198
},
  "geometry": {"coordinates":[78.022919,30.275486],"type":"Point"}
}