{
  "type": "Feature",
  "properties": {
    "gn:admin1_code":"36.0",
    "gn:admin2_code":"172.0",
    "gn:asciiname":"Yohan",
    "gn:country_code":"IN",
    "gn:dem":121,
    "gn:feature_class":"P",
    "gn:feature_code":"PPL",
    "gn:name":"Yohan",
    "gn:population":0,
    "gn:timezone":"Asia/Kolkata",
    "iso:country":"IN",
    "name:nor_x_preferred":[
        "Yohan"
    ],
    "wof:name":"Yohan",
    "wof:placetype":"locality"
},
  "geometry": {"coordinates":[81.07987,25.9626],"type":"Point"}
}