{
  "type": "Feature",
  "properties": {
    "iso:country":"IN",
    "ks:ks_name":"Bharawal",
    "ks:ks_pop":308,
    "ks:ks_type":"HABITATION",
    "ks:ks_uagg_main":0,
    "name:eng_x_preferred":[
        "Bharawal"
    ],
    "wof:name":"Bharawal",
    "wof:placetype":"neighbourhood",
    "wof:population":308
},
  "geometry": {"coordinates":[82.774609,25.509945],"type":"Point"}
}