{
  "type": "Feature",
  "properties": {
    "gn:admin1_code":"10",
    "gn:admin2_code":"76.0",
    "gn:asciiname":"Rai",
    "gn:country_code":"IN",
    "gn:dem":219,
    "gn:feature_class":"P",
    "gn:feature_code":"PPL",
    "gn:name":"Rai",
    "gn:population":0,
    "gn:timezone":"Asia/Kolkata",
    "iso:country":"IN",
    "ks:ks_name":"Rai",
    "ks:ks_pop":2459,
    "ks:ks_type":"VILLAGE",
    "ks:ks_uagg_main":0,
    "name:ara_x_preferred":[
        "\u0631\u0627\u064a"
    ],
    "name:ben_x_preferred":[
        "\u09b0\u09be\u0987"
    ],
    "name:ceb_x_preferred":[
        "Rai"
    ],
    "name:ces_x_preferred":[
        "Rai"
    ],
    "name:eng_x_preferred":[
        "Rai"
    ],
    "name:fin_x_preferred":[
        "Rai"
    ],
    "name:fra_x_preferred":[
        "Rai"
    ],
    "name:hun_x_preferred":[
        "Rai"
    ],
    "name:ita_x_preferred":[
        "RAI"
    ],
    "name:nld_x_preferred":[
        "Rai"
    ],
    "name:nor_x_preferred":[
        "Rai"
    ],
    "name:pol_x_preferred":[
        "Rai"
    ],
    "name:por_x_preferred":[
        "RAI"
    ],
    "name:ron_x_preferred":[
        "Rai"
    ],
    "name:slk_x_preferred":[
        "Rai"
    ],
    "name:spa_x_preferred":[
        "Rai"
    ],
    "name:srp_x_preferred":[
        "Rai"
    ],
    "name:swe_x_preferred":[
        "Rai"
    ],
    "name:und_x_variant":[
        "R\u0101i"
    ],
    "wof:name":"Rai",
    "wof:placetype":"neighbourhood",
    "wof:population":2459
},
  "geometry": {"coordinates":[77.095923,28.941763],"type":"Point"}
}