{
  "type": "Feature",
  "properties": {
    "iso:country":"IN",
    "ks:ks_name":"Shivajot",
    "ks:ks_pop":445,
    "ks:ks_type":"HABITATION",
    "name:eng_x_preferred":[
        "Shivajot"
    ],
    "wof:name":"Shivajot",
    "wof:placetype":"locality",
    "wof:population":445
},
  "geometry": {"coordinates":[81.957285,27.520372],"type":"Point"}
}