{
  "type": "Feature",
  "properties": {
    "gn:admin1_code":"36",
    "gn:admin2_code":"142.0",
    "gn:asciiname":"Ashrafpur Abdullapur",
    "gn:country_code":"IN",
    "gn:dem":195,
    "gn:feature_class":"P",
    "gn:feature_code":"PPL",
    "gn:name":"Ashrafp\u016br Abdullap\u016br",
    "gn:population":0,
    "gn:timezone":"Asia/Kolkata",
    "iso:country":"IN",
    "wof:name":"Ashrafpur Abdullapur",
    "wof:placetype":"locality"
},
  "geometry": {"coordinates":[78.05065999999999,28.3238],"type":"Point"}
}