{
  "type": "Feature",
  "properties": {
    "iso:country":"IN",
    "ks:ks_name":"Dalkhera",
    "ks:ks_pop":584,
    "ks:ks_type":"HABITATION",
    "name:eng_x_preferred":[
        "Dalkhera"
    ],
    "wof:name":"Dalkhera",
    "wof:placetype":"locality",
    "wof:population":584
},
  "geometry": {"coordinates":[80.253784,27.708817],"type":"Point"}
}