{
  "type": "Feature",
  "properties": {
    "iso:country":"IN",
    "ks:ks_name":"Shekhoopur Mafi",
    "ks:ks_pop":55,
    "ks:ks_type":"VILLAGE",
    "ks:ks_uagg_main":0,
    "name:eng_x_preferred":[
        "Shekhoopur Mafi"
    ],
    "wof:name":"Shekhoopur Mafi",
    "wof:placetype":"neighbourhood",
    "wof:population":55
},
  "geometry": {"coordinates":[77.632293,29.758727],"type":"Point"}
}