{
  "type": "Feature",
  "properties": {
    "iso:country":"IN",
    "ks:ks_name":"Tapkocha",
    "ks:ks_pop":257,
    "ks:ks_type":"VILLAGE",
    "name:eng_x_preferred":[
        "Tapkocha"
    ],
    "wof:name":"Tapkocha",
    "wof:placetype":"locality",
    "wof:population":257
},
  "geometry": {"coordinates":[85.719673,22.683255],"type":"Point"}
}