{
  "type": "Feature",
  "properties": {
    "iso:country":"IN",
    "ks:ks_name":"Gantemane",
    "ks:ks_pop":90,
    "ks:ks_type":"HABITATION",
    "name:eng_x_preferred":[
        "Gantemane"
    ],
    "wof:name":"Gantemane",
    "wof:placetype":"locality",
    "wof:population":90
},
  "geometry": {"coordinates":[74.370942,14.587539],"type":"Point"}
}