{
  "type": "Feature",
  "properties": {
    "iso:country":"IN",
    "ks:ks_name":"Chandraili",
    "ks:ks_pop":759,
    "ks:ks_type":"VILLAGE",
    "name:eng_x_preferred":[
        "Chandraili"
    ],
    "wof:name":"Chandraili",
    "wof:placetype":"locality",
    "wof:population":759
},
  "geometry": {"coordinates":[83.28206400000001,23.472269],"type":"Point"}
}