{
  "type": "Feature",
  "properties": {
    "iso:country":"IN",
    "ks:ks_name":"Bhemtia",
    "ks:ks_pop":2932,
    "ks:ks_type":"VILLAGE",
    "ks:ks_uagg_main":0,
    "name:eng_x_preferred":[
        "Bhemtia"
    ],
    "wof:name":"Bhemtia",
    "wof:placetype":"locality",
    "wof:population":2932
},
  "geometry": {"coordinates":[88.977391,26.578155],"type":"Point"}
}