{
  "type": "Feature",
  "properties": {
    "gn:admin1_code":"11",
    "gn:admin2_code":"23.0",
    "gn:asciiname":"Chinjhoti",
    "gn:country_code":"IN",
    "gn:dem":1934,
    "gn:feature_class":"P",
    "gn:feature_code":"PPL",
    "gn:name":"Chinjhot\u012b",
    "gn:population":0,
    "gn:timezone":"Asia/Kolkata",
    "iso:country":"IN",
    "wof:name":"Chinjhoti",
    "wof:placetype":"locality"
},
  "geometry": {"coordinates":[76.06703,32.50506],"type":"Point"}
}