{
  "type": "Feature",
  "properties": {
    "iso:country":"IN",
    "ks:ks_alt_nam":"Kawaibil gaon",
    "ks:ks_name":"Kawaibil Gaon",
    "ks:ks_pop":94,
    "ks:ks_type":"HABITATION",
    "ks:ks_uagg_main":0,
    "name:eng_x_preferred":[
        "Kawaibil Gaon"
    ],
    "wof:name":"Kawaibil Gaon",
    "wof:placetype":"neighbourhood",
    "wof:population":94
},
  "geometry": {"coordinates":[93.17263800000001,26.286489],"type":"Point"}
}