{
  "type": "Feature",
  "properties": {
    "iso:country":"IN",
    "ks:ks_name":"Kundala Falia",
    "ks:ks_pop":501,
    "ks:ks_type":"HABITATION",
    "name:eng_x_preferred":[
        "Kundala Falia"
    ],
    "wof:name":"Kundala Falia",
    "wof:placetype":"locality",
    "wof:population":501
},
  "geometry": {"coordinates":[73.742667,23.3285],"type":"Point"}
}