{
  "type": "Feature",
  "properties": {
    "gn:admin1_code":"38.0",
    "gn:asciiname":"Baniawatanrtoli",
    "gn:country_code":"IN",
    "gn:dem":194,
    "gn:feature_class":"P",
    "gn:feature_code":"PPL",
    "gn:name":"Baniawat\u0101nrtoli",
    "gn:population":0,
    "gn:timezone":"Asia/Kolkata",
    "iso:country":"IN",
    "wof:name":"Baniawatanrtoli",
    "wof:placetype":"locality"
},
  "geometry": {"coordinates":[85.17039,24.43486],"type":"Point"}
}