{
  "type": "Feature",
  "properties": {
    "iso:country":"IN",
    "ks:ks_alt_nam":"Chamar tol",
    "ks:ks_name":"Chamar Tol",
    "ks:ks_pop":287,
    "ks:ks_type":"HABITATION",
    "ks:ks_uagg_main":0,
    "name:eng_x_preferred":[
        "Chamar Tol"
    ],
    "wof:name":"Chamar Tol",
    "wof:placetype":"neighbourhood",
    "wof:population":287
},
  "geometry": {"coordinates":[86.22432000000001,26.05855],"type":"Point"}
}