{
  "type": "Feature",
  "properties": {
    "iso:country":"IN",
    "ks:ks_name":"Ganeshwadi",
    "ks:ks_pop":83,
    "ks:ks_type":"HABITATION",
    "name:eng_x_preferred":[
        "Ganeshwadi"
    ],
    "wof:name":"Ganeshwadi",
    "wof:placetype":"locality",
    "wof:population":83
},
  "geometry": {"coordinates":[73.244956,17.714903],"type":"Point"}
}