{
  "type": "Feature",
  "properties": {
    "iso:country":"IN",
    "ks:ks_name":"Talav Faliya",
    "ks:ks_pop":1924,
    "ks:ks_type":"HABITATION",
    "name:eng_x_preferred":[
        "Talav Faliya"
    ],
    "wof:name":"Talav Faliya",
    "wof:placetype":"locality",
    "wof:population":1924
},
  "geometry": {"coordinates":[74.23316699999999,23.154417],"type":"Point"}
}