{
  "type": "Feature",
  "properties": {
    "gn:admin1_code":"35",
    "gn:admin2_code":"419.0",
    "gn:asciiname":"Gandhar ka Pura",
    "gn:country_code":"IN",
    "gn:dem":155,
    "gn:feature_class":"P",
    "gn:feature_code":"PPL",
    "gn:name":"Gandh\u0101r ka Pura",
    "gn:population":0,
    "gn:timezone":"Asia/Kolkata",
    "iso:country":"IN",
    "wof:name":"Gandhar ka Pura",
    "wof:placetype":"locality"
},
  "geometry": {"coordinates":[78.46548,26.71626],"type":"Point"}
}