{
  "type": "Feature",
  "properties": {
    "iso:country":"IN",
    "ks:ks_name":"Jogaldinni",
    "ks:ks_type":"VILLAGE",
    "name:eng_x_preferred":[
        "Jogaldinni"
    ],
    "wof:name":"Jogaldinni",
    "wof:placetype":"locality"
},
  "geometry": {"coordinates":[76.61256299999999,15.876437],"type":"Point"}
}