{
  "type": "Feature",
  "properties": {
    "iso:country":"IN",
    "ks:ks_alt_nam":"Kheluapara Pt VII",
    "ks:ks_name":"Kheluapara Pt Vii",
    "ks:ks_pop":1162,
    "ks:ks_type":"HABITATION",
    "name:eng_x_preferred":[
        "Kheluapara Pt Vii"
    ],
    "wof:name":"Kheluapara Pt Vii",
    "wof:placetype":"locality",
    "wof:population":1162
},
  "geometry": {"coordinates":[90.50517000000001,26.266801],"type":"Point"}
}