{
  "type": "Feature",
  "properties": {
    "gn:admin1_code":"16",
    "gn:admin2_code":"507.0",
    "gn:asciiname":"Tirkhuri",
    "gn:country_code":"IN",
    "gn:dem":283,
    "gn:feature_class":"P",
    "gn:feature_code":"PPL",
    "gn:name":"Tirkhuri",
    "gn:population":0,
    "gn:timezone":"Asia/Kolkata",
    "iso:country":"IN",
    "wof:name":"Tirkhuri",
    "wof:placetype":"locality"
},
  "geometry": {"coordinates":[80.2891,20.71466],"type":"Point"}
}