{
  "type": "Feature",
  "properties": {
    "iso:country":"IN",
    "ks:ks_name":"Jamunadeipur",
    "ks:ks_pop":399,
    "ks:ks_type":"VILLAGE",
    "name:eng_x_preferred":[
        "Jamunadeipur"
    ],
    "wof:name":"Jamunadeipur",
    "wof:placetype":"locality",
    "wof:population":399
},
  "geometry": {"coordinates":[86.761574,21.640463],"type":"Point"}
}