{
  "type": "Feature",
  "properties": {
    "iso:country":"IN",
    "ks:ks_name":"Engurai",
    "ks:ks_pop":195,
    "ks:ks_type":"HABITATION",
    "name:eng_x_preferred":[
        "Engurai"
    ],
    "wof:name":"Engurai",
    "wof:placetype":"locality",
    "wof:population":195
},
  "geometry": {"coordinates":[82.003297,18.039745],"type":"Point"}
}