{
  "type": "Feature",
  "properties": {
    "iso:country":"IN",
    "ks:ks_name":"Suthana",
    "ks:ks_pop":751,
    "ks:ks_type":"VILLAGE",
    "ks:ks_uagg_main":0,
    "name:eng_x_preferred":[
        "Suthana"
    ],
    "wof:name":"Suthana",
    "wof:placetype":"neighbourhood",
    "wof:population":751
},
  "geometry": {"coordinates":[76.59336,28.103658],"type":"Point"}
}