{
  "type": "Feature",
  "properties": {
    "gn:admin1_code":"35",
    "gn:admin2_code":"425.0",
    "gn:asciiname":"Silap",
    "gn:country_code":"IN",
    "gn:dem":139,
    "gn:feature_class":"P",
    "gn:feature_code":"PPL",
    "gn:name":"S\u012blap",
    "gn:population":0,
    "gn:timezone":"Asia/Kolkata",
    "iso:country":"IN",
    "name:eng_x_preferred":[
        "S\u012blap"
    ],
    "wof:name":"Silap",
    "wof:placetype":"neighbourhood"
},
  "geometry": {"coordinates":[80.24267999999999,25.30397],"type":"Point"}
}