{
  "type": "Feature",
  "properties": {
    "iso:country":"IN",
    "ks:ks_name":"Talukdar Suba2",
    "ks:ks_pop":550,
    "ks:ks_type":"HABITATION",
    "name:eng_x_preferred":[
        "Talukdar Suba2"
    ],
    "wof:name":"Talukdar Suba2",
    "wof:placetype":"locality",
    "wof:population":550
},
  "geometry": {"coordinates":[91.717069,26.377757],"type":"Point"}
}