{
  "type": "Feature",
  "properties": {
    "iso:country":"IN",
    "ks:ks_name":"Kharatwadi",
    "ks:ks_pop":500,
    "ks:ks_type":"HABITATION",
    "name:eng_x_preferred":[
        "Kharatwadi"
    ],
    "wof:name":"Kharatwadi",
    "wof:placetype":"locality",
    "wof:population":500
},
  "geometry": {"coordinates":[74.829481,17.518025],"type":"Point"}
}