{
  "type": "Feature",
  "properties": {
    "iso:country":"IN",
    "ks:ks_name":"Jakknagadde",
    "ks:ks_pop":101,
    "ks:ks_type":"HABITATION",
    "name:eng_x_preferred":[
        "Jakknagadde"
    ],
    "wof:name":"Jakknagadde",
    "wof:placetype":"locality",
    "wof:population":101
},
  "geometry": {"coordinates":[75.078135,13.864114],"type":"Point"}
}