{
  "type": "Feature",
  "properties": {
    "iso:country":"IN",
    "ks:ks_name":"Tentlikhunti",
    "ks:ks_pop":118,
    "ks:ks_type":"VILLAGE",
    "name:eng_x_preferred":[
        "Tentlikhunti"
    ],
    "wof:name":"Tentlikhunti",
    "wof:placetype":"locality",
    "wof:population":118
},
  "geometry": {"coordinates":[82.755295,20.493662],"type":"Point"}
}