{
  "type": "Feature",
  "properties": {
    "iso:country":"IN",
    "ks:ks_name":"Krishnapuram",
    "ks:ks_pop":44,
    "ks:ks_type":"HABITATION",
    "ks:ks_uagg_main":0,
    "name:eng_x_preferred":[
        "Krishnapuram"
    ],
    "wof:name":"Krishnapuram",
    "wof:placetype":"neighbourhood",
    "wof:population":44
},
  "geometry": {"coordinates":[77.79171700000001,10.183545],"type":"Point"}
}