{
  "type": "Feature",
  "properties": {
    "iso:country":"IN",
    "ks:ks_name":"Ringoli",
    "ks:ks_pop":14,
    "ks:ks_type":"HABITATION",
    "name:eng_x_preferred":[
        "Ringoli"
    ],
    "wof:name":"Ringoli",
    "wof:placetype":"locality",
    "wof:population":14
},
  "geometry": {"coordinates":[78.711044,30.235898],"type":"Point"}
}