{
  "type": "Feature",
  "properties": {
    "iso:country":"IN",
    "ks:ks_alt_nam":"makakenda",
    "ks:ks_name":"Makakenda",
    "ks:ks_pop":423,
    "ks:ks_type":"HABITATION",
    "name:eng_x_preferred":[
        "Makakenda"
    ],
    "wof:name":"Makakenda",
    "wof:placetype":"locality",
    "wof:population":423
},
  "geometry": {"coordinates":[87.00797,24.254297],"type":"Point"}
}