{
  "type": "Feature",
  "properties": {
    "iso:country":"IN",
    "ks:ks_name":"Kaspada",
    "ks:ks_pop":496,
    "ks:ks_type":"HABITATION",
    "name:eng_x_preferred":[
        "Kaspada"
    ],
    "wof:name":"Kaspada",
    "wof:placetype":"locality",
    "wof:population":496
},
  "geometry": {"coordinates":[72.84835099999999,19.692323],"type":"Point"}
}