{
  "type": "Feature",
  "properties": {
    "iso:country":"IN",
    "ks:ks_name":"4 KM",
    "ks:ks_pop":140,
    "ks:ks_type":"VILLAGE",
    "name:eng_x_preferred":[
        "4 KM"
    ],
    "wof:name":"4 KM",
    "wof:placetype":"locality",
    "wof:population":140
},
  "geometry": {"coordinates":[73.206677,28.976136],"type":"Point"}
}