{
  "type": "Feature",
  "properties": {
    "iso:country":"IN",
    "ks:ks_name":"Akchek Trisghoria",
    "ks:ks_pop":1029,
    "ks:ks_type":"HABITATION",
    "ks:ks_uagg_main":0,
    "name:eng_x_preferred":[
        "Akchek Trisghoria"
    ],
    "wof:name":"Akchek Trisghoria",
    "wof:placetype":"neighbourhood",
    "wof:population":1029
},
  "geometry": {"coordinates":[92.979056,26.066308],"type":"Point"}
}