{
  "type": "Feature",
  "properties": {
    "gn:admin1_code":"36",
    "gn:admin2_code":"177.0",
    "gn:asciiname":"Sahapur",
    "gn:country_code":"IN",
    "gn:dem":114,
    "gn:feature_class":"P",
    "gn:feature_code":"PPL",
    "gn:name":"S\u0101h\u0101pur",
    "gn:population":0,
    "gn:timezone":"Asia/Kolkata",
    "iso:country":"IN",
    "ks:ks_name":"Shahapur",
    "ks:ks_pop":1172,
    "ks:ks_type":"VILLAGE",
    "ks:ks_uagg_main":0,
    "name:ben_x_preferred":[
        "\u09b8\u09be\u09b9\u09be\u09aa\u09c1\u09b0"
    ],
    "name:bpy_x_preferred":[
        "\u09b8\u09be\u09b9\u09be\u09aa\u09c1\u09b0"
    ],
    "name:ceb_x_preferred":[
        "S\u0101h\u0101pur"
    ],
    "name:eng_x_preferred":[
        "Shahapur"
    ],
    "name:hif_x_preferred":[
        "Sahapur"
    ],
    "name:ita_x_preferred":[
        "Sahapur"
    ],
    "name:msa_x_preferred":[
        "Sahapur"
    ],
    "name:nld_x_preferred":[
        "Sahapur"
    ],
    "name:por_x_preferred":[
        "Sahapur"
    ],
    "name:swe_x_preferred":[
        "S\u0101h\u0101pur"
    ],
    "name:urd_x_preferred":[
        "\u0633\u06c1\u067e\u0631"
    ],
    "name:vie_x_preferred":[
        "Sahapur"
    ],
    "name:zho_x_preferred":[
        "\u8428\u54c8\u666e\u5c14"
    ],
    "wof:name":"Shahapur",
    "wof:placetype":"neighbourhood",
    "wof:population":1172
},
  "geometry": {"coordinates":[81.74397,26.847908],"type":"Point"}
}