{
  "type": "Feature",
  "properties": {
    "iso:country":"IN",
    "ks:ks_name":"Khohra",
    "ks:ks_pop":380,
    "ks:ks_type":"VILLAGE",
    "name:eng_x_preferred":[
        "Khohra"
    ],
    "wof:name":"Khohra",
    "wof:placetype":"locality",
    "wof:population":380
},
  "geometry": {"coordinates":[76.52383,27.106658],"type":"Point"}
}