{
  "type": "Feature",
  "properties": {
    "gn:admin1_code":"13.0",
    "gn:admin2_code":"599.0",
    "gn:asciiname":"Valljkkod",
    "gn:country_code":"IN",
    "gn:dem":32,
    "gn:feature_class":"P",
    "gn:feature_code":"PPL",
    "gn:name":"Valljkkod",
    "gn:population":0,
    "gn:timezone":"Asia/Kolkata",
    "iso:country":"IN",
    "wof:name":"Valljkkod",
    "wof:placetype":"neighbourhood"
},
  "geometry": {"coordinates":[76.7774,9.21845],"type":"Point"}
}