{
  "type": "Feature",
  "properties": {
    "gn:admin1_code":"11",
    "gn:admin2_code":"27.0",
    "gn:asciiname":"Hara Bagh",
    "gn:country_code":"IN",
    "gn:dem":1383,
    "gn:feature_class":"P",
    "gn:feature_code":"PPL",
    "gn:name":"Hara B\u0101gh",
    "gn:population":0,
    "gn:timezone":"Asia/Kolkata",
    "iso:country":"IN",
    "wof:name":"Hara Bagh",
    "wof:placetype":"locality"
},
  "geometry": {"coordinates":[76.81891999999998,31.98511],"type":"Point"}
}