{
  "type": "Feature",
  "properties": {
    "iso:country":"IN",
    "ks:ks_name":"Honagodu",
    "ks:ks_pop":178,
    "ks:ks_type":"HABITATION",
    "name:eng_x_preferred":[
        "Honagodu"
    ],
    "wof:name":"Honagodu",
    "wof:placetype":"locality",
    "wof:population":178
},
  "geometry": {"coordinates":[75.159836,13.838496],"type":"Point"}
}