{
  "type": "Feature",
  "properties": {
    "iso:country":"IN",
    "ks:ks_alt_nam":"Jah\u0101n\u0101b\u0101d",
    "ks:ks_name":"Jahanabad",
    "ks:ks_pop":195,
    "ks:ks_type":"VILLAGE",
    "ks:ks_uagg_main":0,
    "name:eng_x_preferred":[
        "Jahanabad"
    ],
    "name:eng_x_variant":[
        "Jah\u0101n\u0101b\u0101d"
    ],
    "wof:name":"Jahanabad",
    "wof:placetype":"neighbourhood",
    "wof:population":195
},
  "geometry": {"coordinates":[86.456992,24.02931],"type":"Point"}
}