{
  "type": "Feature",
  "properties": {
    "iso:country":"IN",
    "ks:ks_alt_nam":"BADAILPARA",
    "ks:ks_name":"Badailpara",
    "ks:ks_pop":590,
    "ks:ks_type":"HABITATION",
    "name:eng_x_preferred":[
        "Badailpara"
    ],
    "wof:name":"Badailpara",
    "wof:placetype":"locality",
    "wof:population":590
},
  "geometry": {"coordinates":[83.727144,22.48829],"type":"Point"}
}