{
  "type": "Feature",
  "properties": {
    "gn:admin1_code":"19.0",
    "gn:admin2_code":"570.0",
    "gn:asciiname":"Makvalli",
    "gn:country_code":"IN",
    "gn:dem":667,
    "gn:feature_class":"P",
    "gn:feature_code":"PPL",
    "gn:name":"Makvalli",
    "gn:population":0,
    "gn:timezone":"Asia/Kolkata",
    "iso:country":"IN",
    "ks:ks_name":"Makkivalli",
    "ks:ks_pop":59,
    "ks:ks_type":"HABITATION",
    "name:eng_x_preferred":[
        "Makkivalli"
    ],
    "name:eng_x_variant":[
        "Makvalli"
    ],
    "wof:name":"Makkivalli",
    "wof:placetype":"locality",
    "wof:population":59
},
  "geometry": {"coordinates":[75.22393599999999,13.473705],"type":"Point"}
}