{
  "type": "Feature",
  "properties": {
    "iso:country":"IN",
    "ks:ks_name":"Navi Bedi",
    "ks:ks_pop":732,
    "ks:ks_type":"VILLAGE",
    "name:eng_x_preferred":[
        "Navi Bedi"
    ],
    "wof:name":"Navi Bedi",
    "wof:placetype":"locality",
    "wof:population":732
},
  "geometry": {"coordinates":[73.882761,22.577025],"type":"Point"}
}