{
  "type": "Feature",
  "properties": {
    "gn:admin1_code":"19.0",
    "gn:admin2_code":"571.0",
    "gn:asciiname":"Upparahalli",
    "gn:country_code":"IN",
    "gn:dem":654,
    "gn:feature_class":"P",
    "gn:feature_code":"PPL",
    "gn:name":"Upp\u0101rahalli",
    "gn:population":0,
    "gn:timezone":"Asia/Kolkata",
    "iso:country":"IN",
    "wof:name":"Upparahalli",
    "wof:placetype":"locality"
},
  "geometry": {"coordinates":[77.43214999999999,13.71821],"type":"Point"}
}