{
  "type": "Feature",
  "properties": {
    "iso:country":"IN",
    "ks:ks_alt_nam":"MILAK DAAMGANJ",
    "ks:ks_name":"Milak Daamganj",
    "ks:ks_pop":413,
    "ks:ks_type":"HABITATION",
    "ks:ks_uagg_main":0,
    "name:eng_x_preferred":[
        "Milak Daamganj"
    ],
    "wof:name":"Milak Daamganj",
    "wof:placetype":"neighbourhood",
    "wof:population":413
},
  "geometry": {"coordinates":[78.949563,28.91717],"type":"Point"}
}