{
  "type": "Feature",
  "properties": {
    "gn:admin1_code":"16",
    "gn:admin2_code":"507.0",
    "gn:asciiname":"Sarra",
    "gn:country_code":"IN",
    "gn:dem":294,
    "gn:feature_class":"P",
    "gn:feature_code":"PPL",
    "gn:name":"Sarr\u0101",
    "gn:population":0,
    "gn:timezone":"Asia/Kolkata",
    "iso:country":"IN",
    "name:bre_x_preferred":[
        "Sarra"
    ],
    "name:deu_x_preferred":[
        "Sarra"
    ],
    "name:ita_x_preferred":[
        "Sarra"
    ],
    "name:rus_x_preferred":[
        "\u0421\u0430\u0440\u0440\u0430"
    ],
    "wof:name":"Sarra",
    "wof:placetype":"locality"
},
  "geometry": {"coordinates":[79.91969,21.30321],"type":"Point"}
}