{
  "type": "Feature",
  "properties": {
    "gn:admin1_code":"34.0",
    "gn:admin2_code":"239.0",
    "gn:asciiname":"Khudauri",
    "gn:country_code":"IN",
    "gn:dem":79,
    "gn:feature_class":"P",
    "gn:feature_code":"PPL",
    "gn:name":"Khudauri",
    "gn:population":0,
    "gn:timezone":"Asia/Kolkata",
    "iso:country":"IN",
    "ks:ks_name":"Khudaur",
    "ks:ks_pop":2095,
    "ks:ks_type":"VILLAGE",
    "name:eng_x_preferred":[
        "Khudaur"
    ],
    "name:eng_x_variant":[
        "Khudauri"
    ],
    "wof:name":"Khudaur",
    "wof:placetype":"locality",
    "wof:population":2095
},
  "geometry": {"coordinates":[85.131272,25.08404],"type":"Point"}
}