{
  "type": "Feature",
  "properties": {
    "gn:admin1_code":"36",
    "gn:admin2_code":"180.0",
    "gn:asciiname":"Pahara Pakkar",
    "gn:country_code":"IN",
    "gn:dem":124,
    "gn:feature_class":"P",
    "gn:feature_code":"PPL",
    "gn:name":"Pah\u0101ra Pakkar",
    "gn:population":0,
    "gn:timezone":"Asia/Kolkata",
    "iso:country":"IN",
    "wof:name":"Pahara Pakkar",
    "wof:placetype":"locality"
},
  "geometry": {"coordinates":[81.63334,27.59463],"type":"Point"}
}