{
  "type": "Feature",
  "properties": {
    "gn:admin1_code":"40",
    "gn:admin2_code":"535.0",
    "gn:asciiname":"Macherla",
    "gn:country_code":"IN",
    "gn:dem":530,
    "gn:feature_class":"P",
    "gn:feature_code":"PPL",
    "gn:name":"Macherla",
    "gn:population":0,
    "gn:timezone":"Asia/Kolkata",
    "iso:country":"IN",
    "name:bpy_x_preferred":[
        "\u09ae\u09be\u099a\u09c7\u09b0\u09b2\u09be"
    ],
    "name:ceb_x_preferred":[
        "M\u0101cherla"
    ],
    "name:hif_x_preferred":[
        "Macherla"
    ],
    "name:ita_x_preferred":[
        "Macherla"
    ],
    "name:msa_x_preferred":[
        "Macherla"
    ],
    "name:new_x_preferred":[
        "\u092e\u091a\u0947\u0930\u094d\u0932\u093e"
    ],
    "name:ori_x_preferred":[
        "\u0b2e\u0b3e\u0b15\u0b47\u0b30\u0b4d\u0b32\u0b3e"
    ],
    "name:pam_x_preferred":[
        "Macherla"
    ],
    "name:por_x_preferred":[
        "Macherla"
    ],
    "name:spa_x_preferred":[
        "Macherla"
    ],
    "name:swe_x_preferred":[
        "M\u0101cherla"
    ],
    "name:tel_x_preferred":[
        "\u0c2e\u0c3e\u0c1a\u0c30\u0c4d\u0c32"
    ],
    "name:tgl_x_preferred":[
        "Macherla"
    ],
    "name:urd_x_preferred":[
        "\u0645\u0627\u0686\u06cc\u0631\u0644\u0627"
    ],
    "name:vie_x_preferred":[
        "Macherla"
    ],
    "name:zho_x_preferred":[
        "\u9a6c\u5207\u5c14\u62c9"
    ],
    "wof:name":"Macherla",
    "wof:placetype":"locality"
},
  "geometry": {"coordinates":[78.22062,17.6911],"type":"Point"}
}