{
  "type": "Feature",
  "properties": {
    "iso:country":"IN",
    "ks:ks_alt_nam":"K\u0101il\u0101mba",
    "ks:ks_name":"Kailamba",
    "ks:ks_pop":110,
    "ks:ks_type":"VILLAGE",
    "name:eng_x_preferred":[
        "Kailamba"
    ],
    "name:eng_x_variant":[
        "K\u0101il\u0101mba"
    ],
    "wof:name":"Kailamba",
    "wof:placetype":"locality",
    "wof:population":110
},
  "geometry": {"coordinates":[84.117002,20.262922],"type":"Point"}
}