{
  "type": "Feature",
  "properties": {
    "iso:country":"IN",
    "ks:ks_name":"Badanga",
    "ks:ks_pop":111,
    "ks:ks_type":"HABITATION",
    "name:eng_x_preferred":[
        "Badanga"
    ],
    "wof:name":"Badanga",
    "wof:placetype":"locality",
    "wof:population":111
},
  "geometry": {"coordinates":[82.719195,18.352394],"type":"Point"}
}