{
  "type": "Feature",
  "properties": {
    "gn:admin1_code":"2.0",
    "gn:admin2_code":"547.0",
    "gn:asciiname":"Malepalle",
    "gn:country_code":"IN",
    "gn:dem":10,
    "gn:feature_class":"P",
    "gn:feature_code":"PPL",
    "gn:name":"Malepalle",
    "gn:population":0,
    "gn:timezone":"Asia/Kolkata",
    "iso:country":"IN",
    "wof:name":"Malepalle",
    "wof:placetype":"locality"
},
  "geometry": {"coordinates":[80.94159000000001,16.46382],"type":"Point"}
}