{
  "type": "Feature",
  "properties": {
    "iso:country":"IN",
    "ks:ks_name":"Amkot",
    "ks:ks_pop":18,
    "ks:ks_type":"VILLAGE",
    "ks:ks_uagg_main":0,
    "name:eng_x_preferred":[
        "Amkot"
    ],
    "wof:name":"Amkot",
    "wof:placetype":"neighbourhood",
    "wof:population":18
},
  "geometry": {"coordinates":[78.75481600000001,30.175976],"type":"Point"}
}