{
  "type": "Feature",
  "properties": {
    "iso:country":"IN",
    "ks:ks_name":"Marjadpur",
    "ks:ks_pop":944,
    "ks:ks_type":"VILLAGE",
    "ks:ks_uagg_main":0,
    "name:eng_x_preferred":[
        "Marjadpur"
    ],
    "wof:name":"Marjadpur",
    "wof:placetype":"neighbourhood",
    "wof:population":944
},
  "geometry": {"coordinates":[84.168806,27.232226],"type":"Point"}
}