{
  "type": "Feature",
  "properties": {
    "gn:admin1_code":"36",
    "gn:admin2_code":"163.0",
    "gn:asciiname":"Bhalar",
    "gn:country_code":"IN",
    "gn:dem":131,
    "gn:feature_class":"P",
    "gn:feature_code":"PPL",
    "gn:name":"Bhal\u0101r",
    "gn:population":0,
    "gn:timezone":"Asia/Kolkata",
    "iso:country":"IN",
    "wof:name":"Bhalar",
    "wof:placetype":"neighbourhood"
},
  "geometry": {"coordinates":[79.79116,26.13374],"type":"Point"}
}