{
  "type": "Feature",
  "properties": {
    "iso:country":"IN",
    "ks:ks_name":"Yerragadda",
    "ks:ks_pop":520,
    "ks:ks_type":"HABITATION",
    "ks:ks_uagg_main":0,
    "name:eng_x_preferred":[
        "Yerragadda"
    ],
    "wof:name":"Yerragadda",
    "wof:placetype":"neighbourhood",
    "wof:population":520
},
  "geometry": {"coordinates":[80.65134,17.489342],"type":"Point"}
}