{
  "type": "Feature",
  "properties": {
    "iso:country":"IN",
    "ks:ks_name":"Valavanary",
    "ks:ks_pop":356,
    "ks:ks_type":"HABITATION",
    "name:eng_x_preferred":[
        "Valavanary"
    ],
    "wof:name":"Valavanary",
    "wof:placetype":"locality",
    "wof:population":356
},
  "geometry": {"coordinates":[76.522176,9.397355],"type":"Point"}
}