{
  "type": "Feature",
  "properties": {
    "iso:country":"IN",
    "ks:ks_name":"Ukher",
    "ks:ks_pop":0,
    "ks:ks_type":"VILLAGE",
    "name:eng_x_preferred":[
        "Ukher"
    ],
    "wof:name":"Ukher",
    "wof:placetype":"locality",
    "wof:population":0
},
  "geometry": {"coordinates":[68.84537899999999,23.746583],"type":"Point"}
}