{
  "type": "Feature",
  "properties": {
    "gn:admin1_code":"39",
    "gn:admin2_code":"61.0",
    "gn:asciiname":"Than",
    "gn:country_code":"IN",
    "gn:dem":1551,
    "gn:feature_class":"P",
    "gn:feature_code":"PPL",
    "gn:name":"Th\u0101n",
    "gn:population":0,
    "gn:timezone":"Asia/Kolkata",
    "iso:country":"IN",
    "wof:name":"Than",
    "wof:placetype":"locality"
},
  "geometry": {"coordinates":[78.86983000000002,30.15599000000001],"type":"Point"}
}