{
  "type": "Feature",
  "properties": {
    "gn:admin1_code":"12.0",
    "gn:asciiname":"Rah na Parat",
    "gn:country_code":"IN",
    "gn:dem":884,
    "gn:feature_class":"P",
    "gn:feature_code":"PPL",
    "gn:name":"R\u0101h na Par\u0101t",
    "gn:population":0,
    "gn:timezone":"Asia/Kolkata",
    "iso:country":"IN",
    "name:und_x_variant":[
        "R\u0101h na Par\u0101t",
        "R\u0101li na Par\u0101t"
    ],
    "wof:name":"Rah na Parat",
    "wof:placetype":"locality"
},
  "geometry": {"coordinates":[74.08322,33.18519000000001],"type":"Point"}
}