{
  "type": "Feature",
  "properties": {
    "iso:country":"IN",
    "ks:ks_name":"Panditghat",
    "ks:ks_pop":357,
    "ks:ks_type":"HABITATION",
    "ks:ks_uagg_main":0,
    "name:eng_x_preferred":[
        "Panditghat"
    ],
    "wof:name":"Panditghat",
    "wof:placetype":"neighbourhood",
    "wof:population":357
},
  "geometry": {"coordinates":[92.97516299999999,26.134385],"type":"Point"}
}