{
  "type": "Feature",
  "properties": {
    "iso:country":"IN",
    "ks:ks_alt_nam":"poovathamkandi mukku",
    "ks:ks_name":"Poovathamkandi Mukku",
    "ks:ks_pop":639,
    "ks:ks_type":"HABITATION",
    "name:eng_x_preferred":[
        "Poovathamkandi Mukku"
    ],
    "wof:name":"Poovathamkandi Mukku",
    "wof:placetype":"locality",
    "wof:population":639
},
  "geometry": {"coordinates":[75.753231,11.589767],"type":"Point"}
}