{
  "type": "Feature",
  "properties": {
    "iso:country":"IN",
    "ks:ks_alt_nam":"BAGH  BADHIK",
    "ks:ks_name":"Bagh Badhik",
    "ks:ks_pop":450,
    "ks:ks_type":"HABITATION",
    "name:eng_x_preferred":[
        "Bagh Badhik"
    ],
    "name:eng_x_variant":[
        "BAGH  BADHIK"
    ],
    "wof:name":"Bagh Badhik",
    "wof:placetype":"locality",
    "wof:population":450
},
  "geometry": {"coordinates":[78.17828799999999,27.424221],"type":"Point"}
}