{
  "type": "Feature",
  "properties": {
    "gn:admin1_code":"19.0",
    "gn:admin2_code":"581.0",
    "gn:asciiname":"Alambadi",
    "gn:country_code":"IN",
    "gn:dem":817,
    "gn:feature_class":"P",
    "gn:feature_code":"PPL",
    "gn:name":"Alamb\u0101di",
    "gn:population":0,
    "gn:timezone":"Asia/Kolkata",
    "iso:country":"IN",
    "name:fra_x_preferred":[
        "Alambadi"
    ],
    "name:tam_x_preferred":[
        "\u0b86\u0bb2\u0bae\u0bcd\u0baa\u0bbe\u0b9f\u0bbf \u0bae\u0bbe\u0b9f\u0bc1"
    ],
    "name:vie_x_preferred":[
        "Alambadi"
    ],
    "wof:name":"Alambadi",
    "wof:placetype":"locality"
},
  "geometry": {"coordinates":[78.14105000000001,12.92207],"type":"Point"}
}