{
  "type": "Feature",
  "properties": {
    "gn:admin1_code":"35",
    "gn:admin2_code":"462.0",
    "gn:asciiname":"Sarra",
    "gn:country_code":"IN",
    "gn:dem":270,
    "gn:feature_class":"P",
    "gn:feature_code":"PPL",
    "gn:name":"Sarra",
    "gn:population":0,
    "gn:timezone":"Asia/Kolkata",
    "iso:country":"IN",
    "ks:ks_name":"Sarra",
    "ks:ks_type":"VILLAGE",
    "name:ara_x_preferred":[
        "\u0633\u0627\u0631\u0629"
    ],
    "name:aze_x_preferred":[
        "Sara"
    ],
    "name:bel_x_preferred":[
        "\u0421\u0430\u0440\u0430"
    ],
    "name:bre_x_preferred":[
        "Sarra"
    ],
    "name:bul_x_preferred":[
        "\u0421\u0430\u0440\u0430"
    ],
    "name:ceb_x_preferred":[
        "Sara"
    ],
    "name:deu_x_preferred":[
        "Sarra"
    ],
    "name:eng_x_preferred":[
        "Sarra"
    ],
    "name:eng_x_variant":[
        "Sara"
    ],
    "name:eus_x_preferred":[
        "Sara"
    ],
    "name:fin_x_preferred":[
        "Sara"
    ],
    "name:fra_x_preferred":[
        "Sara"
    ],
    "name:ind_x_preferred":[
        "Sara"
    ],
    "name:ita_x_preferred":[
        "Sarra"
    ],
    "name:jpn_x_preferred":[
        "\u30b5\u30e9"
    ],
    "name:kor_x_preferred":[
        "\uc0ac\ub77c"
    ],
    "name:kur_x_preferred":[
        "Sara"
    ],
    "name:lit_x_preferred":[
        "Sara"
    ],
    "name:nld_x_preferred":[
        "Sara"
    ],
    "name:pol_x_preferred":[
        "Sara"
    ],
    "name:por_x_preferred":[
        "Sara"
    ],
    "name:que_x_preferred":[
        "Sara"
    ],
    "name:rus_x_preferred":[
        "\u0421\u0430\u0440\u0440\u0430"
    ],
    "name:spa_x_preferred":[
        "Sara"
    ],
    "name:swe_x_preferred":[
        "Sara"
    ],
    "name:tgl_x_preferred":[
        "Sara"
    ],
    "name:tur_x_preferred":[
        "Sara"
    ],
    "name:ukr_x_preferred":[
        "\u0421\u0430\u0440\u0430"
    ],
    "name:war_x_preferred":[
        "Sara"
    ],
    "wof:name":"Sarra",
    "wof:placetype":"locality"
},
  "geometry": {"coordinates":[81.70560999999999,24.42116],"type":"Point"}
}