{
  "type": "Feature",
  "properties": {
    "iso:country":"IN",
    "ks:ks_name":"Pitkuhi Khurd",
    "ks:ks_pop":113,
    "ks:ks_type":"HABITATION",
    "name:eng_x_preferred":[
        "Pitkuhi Khurd"
    ],
    "wof:name":"Pitkuhi Khurd",
    "wof:placetype":"locality",
    "wof:population":113
},
  "geometry": {"coordinates":[80.224312,23.26073],"type":"Point"}
}