{
  "type": "Feature",
  "properties": {
    "gn:admin1_code":"19.0",
    "gn:admin2_code":"569.0",
    "gn:asciiname":"Kesrani",
    "gn:country_code":"IN",
    "gn:dem":381,
    "gn:feature_class":"P",
    "gn:feature_code":"PPL",
    "gn:name":"Kesrani",
    "gn:population":0,
    "gn:timezone":"Asia/Kolkata",
    "iso:country":"IN",
    "wof:name":"Kesrani",
    "wof:placetype":"locality"
},
  "geometry": {"coordinates":[75.06300999999998,13.40968],"type":"Point"}
}