{
  "type": "Feature",
  "properties": {
    "iso:country":"IN",
    "ks:ks_alt_nam":"SonalurColony",
    "ks:ks_name":"Sonalurcolony",
    "ks:ks_pop":360,
    "ks:ks_type":"HABITATION",
    "ks:ks_uagg_main":0,
    "name:eng_x_preferred":[
        "Sonalurcolony"
    ],
    "wof:name":"Sonalurcolony",
    "wof:placetype":"neighbourhood",
    "wof:population":360
},
  "geometry": {"coordinates":[80.185632,12.839563],"type":"Point"}
}