{
  "type": "Feature",
  "properties": {
    "gn:admin1_code":"36.0",
    "gn:admin2_code":"175.0",
    "gn:asciiname":"Deori Beni",
    "gn:country_code":"IN",
    "gn:dem":108,
    "gn:feature_class":"P",
    "gn:feature_code":"PPL",
    "gn:name":"Deori Beni",
    "gn:population":0,
    "gn:timezone":"Asia/Kolkata",
    "iso:country":"IN",
    "wof:name":"Deori Beni",
    "wof:placetype":"locality"
},
  "geometry": {"coordinates":[81.64889000000002,25.0989],"type":"Point"}
}