{
  "type": "Feature",
  "properties": {
    "iso:country":"IN",
    "ks:ks_name":"Manewasti",
    "ks:ks_pop":95,
    "ks:ks_type":"HABITATION",
    "name:eng_x_preferred":[
        "Manewasti"
    ],
    "wof:name":"Manewasti",
    "wof:placetype":"locality",
    "wof:population":95
},
  "geometry": {"coordinates":[74.988,18.057],"type":"Point"}
}