{
  "type": "Feature",
  "properties": {
    "iso:country":"IN",
    "ks:ks_name":"Badai Ka Pura",
    "ks:ks_pop":118,
    "ks:ks_type":"HABITATION",
    "ks:ks_uagg_main":0,
    "name:eng_x_preferred":[
        "Badai Ka Pura"
    ],
    "wof:name":"Badai Ka Pura",
    "wof:placetype":"neighbourhood",
    "wof:population":118
},
  "geometry": {"coordinates":[82.42868,26.638761],"type":"Point"}
}