{
  "type": "Feature",
  "properties": {
    "iso:country":"IN",
    "ks:ks_alt_nam":"Karekal palya",
    "ks:ks_name":"Karekal Palya",
    "ks:ks_pop":106,
    "ks:ks_type":"HABITATION",
    "name:eng_x_preferred":[
        "Karekal Palya"
    ],
    "wof:name":"Karekal Palya",
    "wof:placetype":"locality",
    "wof:population":106
},
  "geometry": {"coordinates":[77.37064700000001,12.971729],"type":"Point"}
}