{
  "type": "Feature",
  "properties": {
    "iso:country":"IN",
    "ks:ks_name":"Bachappu",
    "ks:ks_pop":189,
    "ks:ks_type":"HABITATION",
    "name:eng_x_preferred":[
        "Bachappu"
    ],
    "wof:name":"Bachappu",
    "wof:placetype":"locality",
    "wof:population":189
},
  "geometry": {"coordinates":[75.010533,13.439694],"type":"Point"}
}