{
  "type": "Feature",
  "properties": {
    "iso:country":"IN",
    "ks:ks_alt_nam":"BAIRAB SARDAR PARA",
    "ks:ks_name":"Bairab Sardar Para",
    "ks:ks_pop":203,
    "ks:ks_type":"HABITATION",
    "name:eng_x_preferred":[
        "Bairab Sardar Para"
    ],
    "wof:name":"Bairab Sardar Para",
    "wof:placetype":"locality",
    "wof:population":203
},
  "geometry": {"coordinates":[91.492487,23.856685],"type":"Point"}
}