{
  "type": "Feature",
  "properties": {
    "iso:country":"IN",
    "ks:ks_name":"Ongnar Khaspara",
    "ks:ks_pop":645,
    "ks:ks_type":"HABITATION",
    "name:eng_x_preferred":[
        "Ongnar Khaspara"
    ],
    "wof:name":"Ongnar Khaspara",
    "wof:placetype":"locality",
    "wof:population":645
},
  "geometry": {"coordinates":[81.390585,19.651354],"type":"Point"}
}