{
  "type": "Feature",
  "properties": {
    "iso:country":"IN",
    "ks:ks_name":"Pattipoi",
    "ks:ks_pop":166,
    "ks:ks_type":"VILLAGE",
    "name:eng_x_preferred":[
        "Pattipoi"
    ],
    "wof:name":"Pattipoi",
    "wof:placetype":"locality",
    "wof:population":166
},
  "geometry": {"coordinates":[86.990838,24.302904],"type":"Point"}
}