{
  "type": "Feature",
  "properties": {
    "gn:admin1_code":"25.0",
    "gn:admin2_code":"610.0",
    "gn:asciiname":"Ettikkuttaipalaiyam",
    "gn:country_code":"IN",
    "gn:dem":202,
    "gn:feature_class":"P",
    "gn:feature_code":"PPL",
    "gn:name":"Ettikkuttaip\u0101laiyam",
    "gn:population":0,
    "gn:timezone":"Asia/Kolkata",
    "iso:country":"IN",
    "wof:name":"Ettikkuttaipalaiyam",
    "wof:placetype":"locality"
},
  "geometry": {"coordinates":[77.59174,11.51737],"type":"Point"}
}