{
  "type": "Feature",
  "properties": {
    "gn:admin1_code":"36.0",
    "gn:admin2_code":"171.0",
    "gn:asciiname":"Tarhwa",
    "gn:country_code":"IN",
    "gn:dem":184,
    "gn:feature_class":"P",
    "gn:feature_code":"PPL",
    "gn:name":"Tarhwa",
    "gn:population":0,
    "gn:timezone":"Asia/Kolkata",
    "iso:country":"IN",
    "wof:name":"Tarhwa",
    "wof:placetype":"locality"
},
  "geometry": {"coordinates":[81.19202,25.03685],"type":"Point"}
}