{
  "type": "Feature",
  "properties": {
    "iso:country":"IN",
    "ks:ks_name":"Tribal Colony",
    "ks:ks_pop":156,
    "ks:ks_type":"HABITATION",
    "name:eng_x_preferred":[
        "Tribal Colony"
    ],
    "wof:name":"Tribal Colony",
    "wof:placetype":"locality",
    "wof:population":156
},
  "geometry": {"coordinates":[75.003198,13.539009],"type":"Point"}
}