{
  "type": "Feature",
  "properties": {
    "gn:admin1_code":"34.0",
    "gn:admin2_code":"233",
    "gn:asciiname":"Basahi",
    "gn:country_code":"IN",
    "gn:dem":85,
    "gn:feature_class":"P",
    "gn:feature_code":"PPL",
    "gn:name":"Basahi",
    "gn:population":0,
    "gn:timezone":"Asia/Kolkata",
    "iso:country":"IN",
    "name:und_x_variant":[
        "Basah"
    ],
    "wof:name":"Basahi",
    "wof:placetype":"locality"
},
  "geometry": {"coordinates":[83.79575,25.12188],"type":"Point"}
}