{
  "type": "Feature",
  "properties": {
    "iso:country":"IN",
    "ks:ks_name":"Mohni Ryt.",
    "ks:ks_pop":0,
    "ks:ks_type":"VILLAGE",
    "name:eng_x_preferred":[
        "Mohni Ryt."
    ],
    "wof:name":"Mohni Ryt.",
    "wof:placetype":"locality",
    "wof:population":0
},
  "geometry": {"coordinates":[80.629825,23.077553],"type":"Point"}
}