{
  "type": "Feature",
  "properties": {
    "iso:country":"IN",
    "ks:ks_name":"Dum Dumwa",
    "ks:ks_pop":400,
    "ks:ks_type":"HABITATION",
    "ks:ks_uagg_main":0,
    "name:eng_x_preferred":[
        "Dum Dumwa"
    ],
    "wof:name":"Dum Dumwa",
    "wof:placetype":"neighbourhood",
    "wof:population":400
},
  "geometry": {"coordinates":[84.343,26.813],"type":"Point"}
}