{
  "type": "Feature",
  "properties": {
    "gn:admin1_code":"35",
    "gn:admin2_code":"436.0",
    "gn:asciiname":"Aroliya",
    "gn:country_code":"IN",
    "gn:dem":416,
    "gn:feature_class":"P",
    "gn:feature_code":"PPL",
    "gn:name":"Aroliya",
    "gn:population":0,
    "gn:timezone":"Asia/Kolkata",
    "iso:country":"IN",
    "ks:ks_name":"Aroliya",
    "ks:ks_pop":1010,
    "ks:ks_type":"VILLAGE",
    "name:eng_x_preferred":[
        "Aroliya"
    ],
    "wof:name":"Aroliya",
    "wof:placetype":"locality",
    "wof:population":1010
},
  "geometry": {"coordinates":[76.233687,23.605846],"type":"Point"}
}