{
  "type": "Feature",
  "properties": {
    "gn:admin1_code":"28",
    "gn:asciiname":"Nimtita",
    "gn:country_code":"IN",
    "gn:dem":17,
    "gn:feature_class":"P",
    "gn:feature_code":"PPL",
    "gn:name":"Nimtita",
    "gn:population":0,
    "gn:timezone":"Asia/Kolkata",
    "iso:country":"IN",
    "ks:ks_name":"Nimtita",
    "ks:ks_pop":706,
    "ks:ks_type":"VILLAGE",
    "ks:ks_uagg_main":0,
    "name:eng_x_preferred":[
        "Nimtita"
    ],
    "wof:name":"Nimtita",
    "wof:placetype":"neighbourhood",
    "wof:population":706
},
  "geometry": {"coordinates":[88.018248,24.638267],"type":"Point"}
}