{
  "type": "Feature",
  "properties": {
    "iso:country":"IN",
    "ks:ks_alt_nam":"JUNIDORLI",
    "ks:ks_name":"Junidorli",
    "ks:ks_pop":527,
    "ks:ks_type":"HABITATION",
    "name:eng_x_preferred":[
        "Junidorli"
    ],
    "wof:name":"Junidorli",
    "wof:placetype":"locality",
    "wof:population":527
},
  "geometry": {"coordinates":[74.681167,17.101043],"type":"Point"}
}