{
  "type": "Feature",
  "properties": {
    "iso:country":"IN",
    "ks:ks_alt_nam":"KANCHA KHAOYA",
    "ks:ks_name":"Kancha Khaoya",
    "ks:ks_pop":636,
    "ks:ks_type":"HABITATION",
    "name:eng_x_preferred":[
        "Kancha Khaoya"
    ],
    "wof:name":"Kancha Khaoya",
    "wof:placetype":"locality",
    "wof:population":636
},
  "geometry": {"coordinates":[88.674864,26.291995],"type":"Point"}
}