{
  "type": "Feature",
  "properties": {
    "iso:country":"IN",
    "ks:ks_name":"Ghasipur",
    "ks:ks_pop":204,
    "ks:ks_type":"HABITATION",
    "name:eng_x_preferred":[
        "Ghasipur"
    ],
    "wof:name":"Ghasipur",
    "wof:placetype":"locality",
    "wof:population":204
},
  "geometry": {"coordinates":[87.47280499999999,24.321726],"type":"Point"}
}