{
  "type": "Feature",
  "properties": {
    "iso:country":"IN",
    "ks:ks_name":"Elayidemthuruth",
    "ks:ks_pop":989,
    "ks:ks_type":"HABITATION",
    "name:eng_x_preferred":[
        "Elayidemthuruth"
    ],
    "wof:name":"Elayidemthuruth",
    "wof:placetype":"locality",
    "wof:population":989
},
  "geometry": {"coordinates":[76.372641,9.398853],"type":"Point"}
}