{
  "type": "Feature",
  "properties": {
    "gn:admin1_code":"38.0",
    "gn:admin2_code":"352.0",
    "gn:asciiname":"Adro",
    "gn:country_code":"IN",
    "gn:dem":53,
    "gn:feature_class":"P",
    "gn:feature_code":"PPL",
    "gn:name":"Adro",
    "gn:population":0,
    "gn:timezone":"Asia/Kolkata",
    "iso:country":"IN",
    "name:azb_x_preferred":[
        "\u0622\u062f\u0631\u0648"
    ],
    "name:bar_x_preferred":[
        "Adro"
    ],
    "name:bul_x_preferred":[
        "\u0410\u0434\u0440\u043e"
    ],
    "name:cat_x_preferred":[
        "Adro"
    ],
    "name:ceb_x_preferred":[
        "Adro"
    ],
    "name:deu_x_preferred":[
        "Adro"
    ],
    "name:epo_x_preferred":[
        "Adro"
    ],
    "name:eus_x_preferred":[
        "Adro"
    ],
    "name:fas_x_preferred":[
        "\u0622\u062f\u0631\u0648"
    ],
    "name:fra_x_preferred":[
        "Adro"
    ],
    "name:hun_x_preferred":[
        "Adro"
    ],
    "name:hye_x_preferred":[
        "\u0531\u0564\u0580\u0578"
    ],
    "name:ina_x_preferred":[
        "Adro"
    ],
    "name:ind_x_preferred":[
        "Adro"
    ],
    "name:ita_x_preferred":[
        "Adro"
    ],
    "name:jpn_x_preferred":[
        "\u30a2\u30c9\u30ed"
    ],
    "name:kaz_x_preferred":[
        "\u0410\u0434\u0440\u043e"
    ],
    "name:lat_x_preferred":[
        "Adrum"
    ],
    "name:lmo_x_preferred":[
        "\u00c0der"
    ],
    "name:msa_x_preferred":[
        "Adro"
    ],
    "name:nap_x_preferred":[
        "Adro"
    ],
    "name:nld_x_preferred":[
        "Adro"
    ],
    "name:pms_x_preferred":[
        "Adro"
    ],
    "name:pol_x_preferred":[
        "Adro"
    ],
    "name:por_x_preferred":[
        "Adro"
    ],
    "name:ron_x_preferred":[
        "Adro"
    ],
    "name:rus_x_preferred":[
        "\u0410\u0434\u0440\u043e"
    ],
    "name:scn_x_preferred":[
        "Adro"
    ],
    "name:spa_x_preferred":[
        "Adro"
    ],
    "name:srp_x_preferred":[
        "\u0410\u0434\u0440\u043e"
    ],
    "name:tgl_x_preferred":[
        "Adro"
    ],
    "name:ukr_x_preferred":[
        "\u0410\u0434\u0440\u043e"
    ],
    "name:uzb_x_preferred":[
        "Adro"
    ],
    "name:vie_x_preferred":[
        "Adro"
    ],
    "name:vol_x_preferred":[
        "Adro"
    ],
    "name:war_x_preferred":[
        "Adro"
    ],
    "name:zho_x_preferred":[
        "\u963f\u5fb7\u7f57"
    ],
    "wof:name":"Adro",
    "wof:placetype":"locality"
},
  "geometry": {"coordinates":[87.6679,25.21244],"type":"Point"}
}