{
  "type": "Feature",
  "properties": {
    "iso:country":"IN",
    "ks:ks_name":"Tajpur",
    "ks:ks_pop":1988,
    "ks:ks_type":"VILLAGE",
    "ks:ks_uagg_main":0,
    "name:eng_x_preferred":[
        "Tajpur"
    ],
    "wof:name":"Tajpur",
    "wof:placetype":"neighbourhood",
    "wof:population":1988
},
  "geometry": {"coordinates":[75.539669,31.263977],"type":"Point"}
}