{
  "type": "Feature",
  "properties": {
    "iso:country":"IN",
    "ks:ks_name":"Sampyadi Mule",
    "ks:ks_pop":286,
    "ks:ks_type":"HABITATION",
    "name:eng_x_preferred":[
        "Sampyadi Mule"
    ],
    "wof:name":"Sampyadi Mule",
    "wof:placetype":"locality",
    "wof:population":286
},
  "geometry": {"coordinates":[75.236724,12.732058],"type":"Point"}
}