{
  "type": "Feature",
  "properties": {
    "iso:country":"IN",
    "ks:ks_name":"Hol T. Haveli",
    "ks:ks_pop":885,
    "ks:ks_type":"VILLAGE",
    "ks:ks_uagg_main":0,
    "name:eng_x_preferred":[
        "Hol T. Haveli"
    ],
    "wof:name":"Hol T. Haveli",
    "wof:placetype":"locality",
    "wof:population":885
},
  "geometry": {"coordinates":[74.26336999999999,21.382124],"type":"Point"}
}