{
  "type": "Feature",
  "properties": {
    "iso:country":"IN",
    "ks:ks_name":"Pidaran Street",
    "ks:ks_pop":450,
    "ks:ks_type":"HABITATION",
    "name:eng_x_preferred":[
        "Pidaran Street"
    ],
    "wof:name":"Pidaran Street",
    "wof:placetype":"locality",
    "wof:population":450
},
  "geometry": {"coordinates":[79.53591299999999,10.604756],"type":"Point"}
}