{
  "type": "Feature",
  "properties": {
    "iso:country":"IN",
    "ks:ks_name":"Malisubular",
    "ks:ks_pop":312,
    "ks:ks_type":"VILLAGE",
    "name:eng_x_preferred":[
        "Malisubular"
    ],
    "wof:name":"Malisubular",
    "wof:placetype":"locality",
    "wof:population":312
},
  "geometry": {"coordinates":[82.669352,18.415314],"type":"Point"}
}