{
  "type": "Feature",
  "properties": {
    "iso:country":"IN",
    "ks:ks_name":"Yawat Station",
    "ks:ks_pop":2851,
    "ks:ks_type":"HABITATION",
    "name:eng_x_preferred":[
        "Yawat Station"
    ],
    "wof:name":"Yawat Station",
    "wof:placetype":"locality",
    "wof:population":2851
},
  "geometry": {"coordinates":[74.25761,18.48999],"type":"Point"}
}