{
  "type": "Feature",
  "properties": {
    "iso:country":"IN",
    "ks:ks_name":"Gundurapasi",
    "ks:ks_pop":175,
    "ks:ks_type":"VILLAGE",
    "ks:ks_uagg_main":0,
    "name:eng_x_preferred":[
        "Gundurapasi"
    ],
    "wof:name":"Gundurapasi",
    "wof:placetype":"neighbourhood",
    "wof:population":175
},
  "geometry": {"coordinates":[85.519739,20.660255],"type":"Point"}
}