{
  "type": "Feature",
  "properties": {
    "iso:country":"IN",
    "ks:ks_name":"Pitambar Chak",
    "ks:ks_pop":1155,
    "ks:ks_type":"VILLAGE",
    "name:eng_x_preferred":[
        "Pitambar Chak"
    ],
    "wof:name":"Pitambar Chak",
    "wof:placetype":"locality",
    "wof:population":1155
},
  "geometry": {"coordinates":[87.53842899999999,22.532285],"type":"Point"}
}