{
  "type": "Feature",
  "properties": {
    "iso:country":"IN",
    "ks:ks_name":"Biraguda",
    "ks:ks_pop":207,
    "ks:ks_type":"HABITATION",
    "name:eng_x_preferred":[
        "Biraguda"
    ],
    "wof:name":"Biraguda",
    "wof:placetype":"locality",
    "wof:population":207
},
  "geometry": {"coordinates":[83.87209,20.216256],"type":"Point"}
}