{
  "type": "Feature",
  "properties": {
    "gn:admin1_code":"35",
    "gn:admin2_code":"438.0",
    "gn:asciiname":"Kunjrod",
    "gn:country_code":"IN",
    "gn:dem":544,
    "gn:feature_class":"P",
    "gn:feature_code":"PPL",
    "gn:name":"Kunjrod",
    "gn:population":0,
    "gn:timezone":"Asia/Kolkata",
    "iso:country":"IN",
    "wof:name":"Kunjrod",
    "wof:placetype":"locality"
},
  "geometry": {"coordinates":[75.5305,22.50768],"type":"Point"}
}