{
  "type": "Feature",
  "properties": {
    "iso:country":"IN",
    "ks:ks_name":"Sidung Cherra",
    "ks:ks_pop":423,
    "ks:ks_type":"HABITATION",
    "name:eng_x_preferred":[
        "Sidung Cherra"
    ],
    "wof:name":"Sidung Cherra",
    "wof:placetype":"locality",
    "wof:population":423
},
  "geometry": {"coordinates":[91.877797,23.982178],"type":"Point"}
}