{
  "type": "Feature",
  "properties": {
    "iso:country":"IN",
    "ks:ks_name":"Barajaipur",
    "ks:ks_pop":438,
    "ks:ks_type":"VILLAGE",
    "name:eng_x_preferred":[
        "Barajaipur"
    ],
    "wof:name":"Barajaipur",
    "wof:placetype":"locality",
    "wof:population":438
},
  "geometry": {"coordinates":[85.899293,22.5252],"type":"Point"}
}