{
  "type": "Feature",
  "properties": {
    "iso:country":"IN",
    "ks:ks_name":"Kombe Yerlapady",
    "ks:ks_pop":60,
    "ks:ks_type":"HABITATION",
    "name:eng_x_preferred":[
        "Kombe Yerlapady"
    ],
    "wof:name":"Kombe Yerlapady",
    "wof:placetype":"locality",
    "wof:population":60
},
  "geometry": {"coordinates":[74.951313,13.377717],"type":"Point"}
}