{
  "type": "Feature",
  "properties": {
    "gn:admin1_code":"36",
    "gn:admin2_code":"167.0",
    "gn:asciiname":"Karmuhra",
    "gn:country_code":"IN",
    "gn:dem":354,
    "gn:feature_class":"P",
    "gn:feature_code":"PPL",
    "gn:name":"Karmuhra",
    "gn:population":0,
    "gn:timezone":"Asia/Kolkata",
    "iso:country":"IN",
    "ks:ks_name":"Karmuharo",
    "ks:ks_pop":1346,
    "ks:ks_type":"VILLAGE",
    "name:eng_x_preferred":[
        "Karmuharo"
    ],
    "name:eng_x_variant":[
        "Karmuhra"
    ],
    "wof:name":"Karmuharo",
    "wof:placetype":"locality",
    "wof:population":1346
},
  "geometry": {"coordinates":[78.233141,24.815459],"type":"Point"}
}