{
  "type": "Feature",
  "properties": {
    "gn:admin1_code":"35.0",
    "gn:admin2_code":"464.0",
    "gn:asciiname":"Bhora",
    "gn:country_code":"IN",
    "gn:dem":333,
    "gn:feature_class":"P",
    "gn:feature_code":"PPL",
    "gn:name":"Bhora",
    "gn:population":0,
    "gn:timezone":"Asia/Kolkata",
    "iso:country":"IN",
    "name:ara_x_preferred":[
        "\u0628\u062d\u0648\u0631\u0649"
    ],
    "name:fas_x_preferred":[
        "\u0628\u062d\u0648\u0631\u06cc"
    ],
    "name:pol_x_preferred":[
        "Bahura"
    ],
    "name:vie_x_preferred":[
        "Bhora"
    ],
    "wof:name":"Bhora",
    "wof:placetype":"locality"
},
  "geometry": {"coordinates":[74.53546,22.75631],"type":"Point"}
}