{
  "type": "Feature",
  "properties": {
    "gn:admin1_code":"36",
    "gn:admin2_code":"191.0",
    "gn:asciiname":"Hasnadih",
    "gn:country_code":"IN",
    "gn:dem":88,
    "gn:feature_class":"P",
    "gn:feature_code":"PPL",
    "gn:name":"Hasn\u0101d\u012bh",
    "gn:population":0,
    "gn:timezone":"Asia/Kolkata",
    "iso:country":"IN",
    "ks:ks_alt_nam":"Hasn\u0101d\u012bh",
    "ks:ks_name":"Hasnadih",
    "ks:ks_type":"VILLAGE",
    "name:eng_x_preferred":[
        "Hasnadih"
    ],
    "name:eng_x_variant":[
        "Hasn\u0101d\u012bh"
    ],
    "wof:name":"Hasnadih",
    "wof:placetype":"locality"
},
  "geometry": {"coordinates":[82.935677,26.207451],"type":"Point"}
}