{
  "type": "Feature",
  "properties": {
    "iso:country":"IN",
    "ks:ks_alt_nam":"Thekkenattu kavala",
    "ks:ks_name":"Thekkenattu Kavala",
    "ks:ks_pop":220,
    "ks:ks_type":"HABITATION",
    "name:eng_x_preferred":[
        "Thekkenattu Kavala"
    ],
    "wof:name":"Thekkenattu Kavala",
    "wof:placetype":"locality",
    "wof:population":220
},
  "geometry": {"coordinates":[76.205074,11.839471],"type":"Point"}
}