{
  "type": "Feature",
  "properties": {
    "iso:country":"IN",
    "ks:ks_name":"Panniyod",
    "ks:ks_pop":5250,
    "ks:ks_type":"HABITATION",
    "name:eng_x_preferred":[
        "Panniyod"
    ],
    "wof:name":"Panniyod",
    "wof:placetype":"locality",
    "wof:population":5250
},
  "geometry": {"coordinates":[77.111293,8.546199],"type":"Point"}
}