{
  "type": "Feature",
  "properties": {
    "gn:admin1_code":"11",
    "gn:admin2_code":"27.0",
    "gn:asciiname":"Jhamerha",
    "gn:country_code":"IN",
    "gn:dem":1742,
    "gn:feature_class":"P",
    "gn:feature_code":"PPL",
    "gn:name":"Jhamerha",
    "gn:population":0,
    "gn:timezone":"Asia/Kolkata",
    "iso:country":"IN",
    "wof:name":"Jhamerha",
    "wof:placetype":"locality"
},
  "geometry": {"coordinates":[76.86350999999998,32.0013],"type":"Point"}
}