{
  "type": "Feature",
  "properties": {
    "iso:country":"IN",
    "ks:ks_name":"Paniksha",
    "ks:ks_pop":606,
    "ks:ks_type":"HABITATION",
    "name:eng_x_preferred":[
        "Paniksha"
    ],
    "wof:name":"Paniksha",
    "wof:placetype":"locality",
    "wof:population":606
},
  "geometry": {"coordinates":[83.462204,25.731582],"type":"Point"}
}