{
  "type": "Feature",
  "properties": {
    "iso:country":"IN",
    "ks:ks_name":"Aduru",
    "ks:ks_pop":11,
    "ks:ks_type":"HABITATION",
    "name:eng_x_preferred":[
        "Aduru"
    ],
    "wof:name":"Aduru",
    "wof:placetype":"locality",
    "wof:population":11
},
  "geometry": {"coordinates":[74.981948,13.86898],"type":"Point"}
}