{
  "type": "Feature",
  "properties": {
    "iso:country":"IN",
    "ks:ks_alt_nam":"Ch\u0101npi",
    "ks:ks_name":"Chanpi",
    "ks:ks_pop":178,
    "ks:ks_type":"VILLAGE",
    "name:eng_x_preferred":[
        "Chanpi"
    ],
    "name:eng_x_variant":[
        "Ch\u0101npi"
    ],
    "wof:name":"Chanpi",
    "wof:placetype":"locality",
    "wof:population":178
},
  "geometry": {"coordinates":[84.96058600000001,23.077355],"type":"Point"}
}