{
  "type": "Feature",
  "properties": {
    "gn:admin1_code":"2.0",
    "gn:admin2_code":"543.0",
    "gn:asciiname":"Korivalasa",
    "gn:country_code":"IN",
    "gn:dem":89,
    "gn:feature_class":"P",
    "gn:feature_code":"PPL",
    "gn:name":"Korivalasa",
    "gn:population":0,
    "gn:timezone":"Asia/Kolkata",
    "iso:country":"IN",
    "wof:name":"Korivalasa",
    "wof:placetype":"locality"
},
  "geometry": {"coordinates":[83.54385000000001,18.72977],"type":"Point"}
}