{
  "type": "Feature",
  "properties": {
    "iso:country":"IN",
    "ks:ks_name":"T Olapalayam",
    "ks:ks_pop":150,
    "ks:ks_type":"HABITATION",
    "name:eng_x_preferred":[
        "T Olapalayam"
    ],
    "wof:name":"T Olapalayam",
    "wof:placetype":"locality",
    "wof:population":150
},
  "geometry": {"coordinates":[77.560845,11.307318],"type":"Point"}
}