{
  "type": "Feature",
  "properties": {
    "gn:admin1_code":"34.0",
    "gn:admin2_code":"220.0",
    "gn:asciiname":"Bhakurahar Sital",
    "gn:country_code":"IN",
    "gn:dem":56,
    "gn:feature_class":"P",
    "gn:feature_code":"PPL",
    "gn:name":"Bhakur\u0101har Sital",
    "gn:population":0,
    "gn:timezone":"Asia/Kolkata",
    "iso:country":"IN",
    "ks:ks_name":"Bhakurahar Sital",
    "ks:ks_pop":3719,
    "ks:ks_type":"VILLAGE",
    "name:eng_x_preferred":[
        "Bhakurahar Sital"
    ],
    "wof:name":"Bhakurahar Sital",
    "wof:placetype":"locality",
    "wof:population":3719
},
  "geometry": {"coordinates":[85.242217,25.810544],"type":"Point"}
}