{
  "type": "Feature",
  "properties": {
    "iso:country":"IN",
    "ks:ks_name":"Ududa",
    "ks:ks_pop":175,
    "ks:ks_type":"VILLAGE",
    "name:eng_x_preferred":[
        "Ududa"
    ],
    "wof:name":"Ududa",
    "wof:placetype":"locality",
    "wof:population":175
},
  "geometry": {"coordinates":[84.78383700000001,20.256205],"type":"Point"}
}