{
  "type": "Feature",
  "properties": {
    "gn:admin1_code":"11.0",
    "gn:admin2_code":"32.0",
    "gn:asciiname":"Semala",
    "gn:country_code":"IN",
    "gn:dem":1171,
    "gn:feature_class":"P",
    "gn:feature_code":"PPL",
    "gn:name":"Semala",
    "gn:population":0,
    "gn:timezone":"Asia/Kolkata",
    "iso:country":"IN",
    "wof:name":"Semala",
    "wof:placetype":"locality"
},
  "geometry": {"coordinates":[77.59054999999999,30.59495],"type":"Point"}
}