{
  "type": "Feature",
  "properties": {
    "gn:admin1_code":"36.0",
    "gn:admin2_code":"184.0",
    "gn:asciiname":"Gulhaura",
    "gn:country_code":"IN",
    "gn:dem":94,
    "gn:feature_class":"P",
    "gn:feature_code":"PPL",
    "gn:name":"Gulhaura",
    "gn:population":0,
    "gn:timezone":"Asia/Kolkata",
    "iso:country":"IN",
    "ks:ks_name":"Golhaura",
    "ks:ks_pop":206,
    "ks:ks_type":"VILLAGE",
    "name:eng_x_preferred":[
        "Golhaura"
    ],
    "name:eng_x_variant":[
        "Gulhaura"
    ],
    "wof:name":"Golhaura",
    "wof:placetype":"locality",
    "wof:population":206
},
  "geometry": {"coordinates":[82.827375,27.233325],"type":"Point"}
}