{
  "type": "Feature",
  "properties": {
    "iso:country":"IN",
    "ks:ks_alt_nam":"Allaudin wasti",
    "ks:ks_name":"Allaudin Wasti",
    "ks:ks_pop":80,
    "ks:ks_type":"HABITATION",
    "name:eng_x_preferred":[
        "Allaudin Wasti"
    ],
    "wof:name":"Allaudin Wasti",
    "wof:placetype":"locality",
    "wof:population":80
},
  "geometry": {"coordinates":[75.531243,17.271641],"type":"Point"}
}