{
  "type": "Feature",
  "properties": {
    "iso:country":"IN",
    "ks:ks_name":"Vinchupada",
    "ks:ks_pop":147,
    "ks:ks_type":"HABITATION",
    "name:eng_x_preferred":[
        "Vinchupada"
    ],
    "wof:name":"Vinchupada",
    "wof:placetype":"locality",
    "wof:population":147
},
  "geometry": {"coordinates":[73.40514,19.562007],"type":"Point"}
}