{
  "type": "Feature",
  "properties": {
    "iso:country":"IN",
    "ks:ks_name":"Bar Basudebpur",
    "ks:ks_pop":5751,
    "ks:ks_type":"VILLAGE",
    "name:eng_x_preferred":[
        "Bar Basudebpur"
    ],
    "wof:name":"Bar Basudebpur",
    "wof:placetype":"locality",
    "wof:population":5751
},
  "geometry": {"coordinates":[88.05667,22.117356],"type":"Point"}
}