{
  "type": "Feature",
  "properties": {
    "gn:admin1_code":"24.0",
    "gn:admin2_code":"114.0",
    "gn:asciiname":"Khara",
    "gn:country_code":"IN",
    "gn:dem":63,
    "gn:feature_class":"P",
    "gn:feature_code":"PPL",
    "gn:name":"Khara",
    "gn:population":0,
    "gn:timezone":"Asia/Kolkata",
    "iso:country":"IN",
    "name:ceb_x_preferred":[
        "Khara"
    ],
    "name:deu_x_preferred":[
        "Khara"
    ],
    "name:new_x_preferred":[
        "\u0916\u0930\u093e"
    ],
    "name:swe_x_preferred":[
        "Khara"
    ],
    "wof:name":"Khara",
    "wof:placetype":"locality"
},
  "geometry": {"coordinates":[69.71354000000001,26.66389],"type":"Point"}
}