{
  "type": "Feature",
  "properties": {
    "gn:admin1_code":"19.0",
    "gn:admin2_code":"566.0",
    "gn:asciiname":"Ramajogihalli",
    "gn:country_code":"IN",
    "gn:dem":608,
    "gn:feature_class":"P",
    "gn:feature_code":"PPL",
    "gn:name":"R\u0101majogihalli",
    "gn:population":0,
    "gn:timezone":"Asia/Kolkata",
    "iso:country":"IN",
    "wof:name":"Ramajogihalli",
    "wof:placetype":"locality"
},
  "geometry": {"coordinates":[76.62600999999999,14.16701],"type":"Point"}
}