{
  "type": "Feature",
  "properties": {
    "gn:admin1_code":"36",
    "gn:admin2_code":"188.0",
    "gn:asciiname":"Jagdispur",
    "gn:country_code":"IN",
    "gn:dem":77,
    "gn:feature_class":"P",
    "gn:feature_code":"PPL",
    "gn:name":"Jagd\u012bspur",
    "gn:population":0,
    "gn:timezone":"Asia/Kolkata",
    "iso:country":"IN",
    "ks:ks_name":"Jagdishpur",
    "ks:ks_pop":161,
    "ks:ks_type":"VILLAGE",
    "ks:ks_uagg_main":0,
    "name:ceb_x_preferred":[
        "Jagd\u012bspur"
    ],
    "name:eng_x_preferred":[
        "Jagdishpur"
    ],
    "name:jpn_x_preferred":[
        "\u30b8\u30e3\u30b0\u30c7\u30a3\u30fc\u30b7\u30e5\u30d7\u30eb"
    ],
    "name:msa_x_preferred":[
        "Jagdishpur"
    ],
    "name:ori_x_preferred":[
        "\u0b1c\u0b17\u0b26\u0b40\u0b36\u0b2a\u0b41\u0b30"
    ],
    "name:spa_x_preferred":[
        "Jagdispur"
    ],
    "name:swe_x_preferred":[
        "Jagd\u012bspur"
    ],
    "name:urd_x_preferred":[
        "\u062c\u06af\u062f\u06cc\u0633 \u067e\u0648\u0631"
    ],
    "wof:name":"Jagdishpur",
    "wof:placetype":"neighbourhood",
    "wof:population":161
},
  "geometry": {"coordinates":[83.47174200000001,26.352034],"type":"Point"}
}