{
  "type": "Feature",
  "properties": {
    "gn:admin1_code":"36",
    "gn:admin2_code":"195.0",
    "gn:asciiname":"Khara",
    "gn:country_code":"IN",
    "gn:dem":76,
    "gn:feature_class":"P",
    "gn:feature_code":"PPL",
    "gn:name":"Kh\u0101ra",
    "gn:population":0,
    "gn:timezone":"Asia/Kolkata",
    "iso:country":"IN",
    "name:ceb_x_preferred":[
        "Khara"
    ],
    "name:deu_x_preferred":[
        "Khara"
    ],
    "name:new_x_preferred":[
        "\u0916\u0930\u093e"
    ],
    "name:swe_x_preferred":[
        "Khara"
    ],
    "wof:name":"Khara",
    "wof:placetype":"locality"
},
  "geometry": {"coordinates":[83.78305999999998,25.72007],"type":"Point"}
}