{
  "type": "Feature",
  "properties": {
    "iso:country":"IN",
    "ks:ks_name":"Upla Amda",
    "ks:ks_pop":1267,
    "ks:ks_type":"VILLAGE",
    "name:eng_x_preferred":[
        "Upla Amda"
    ],
    "wof:name":"Upla Amda",
    "wof:placetype":"locality",
    "wof:population":1267
},
  "geometry": {"coordinates":[73.33183099999999,24.215058],"type":"Point"}
}