{
  "type": "Feature",
  "properties": {
    "iso:country":"IN",
    "ks:ks_name":"Gondhalwadi",
    "ks:ks_pop":85,
    "ks:ks_type":"HABITATION",
    "name:eng_x_preferred":[
        "Gondhalwadi"
    ],
    "wof:name":"Gondhalwadi",
    "wof:placetype":"locality",
    "wof:population":85
},
  "geometry": {"coordinates":[73.61197799999999,16.000859],"type":"Point"}
}