{
  "type": "Feature",
  "properties": {
    "iso:country":"IN",
    "ks:ks_name":"Afalkhola",
    "ks:ks_pop":77,
    "ks:ks_type":"VILLAGE",
    "name:eng_x_preferred":[
        "Afalkhola"
    ],
    "wof:name":"Afalkhola",
    "wof:placetype":"locality",
    "wof:population":77
},
  "geometry": {"coordinates":[79.24000100000001,29.791944],"type":"Point"}
}