{
  "type": "Feature",
  "properties": {
    "gn:admin1_code":"19.0",
    "gn:admin2_code":"575.0",
    "gn:asciiname":"Arkana",
    "gn:country_code":"IN",
    "gn:dem":74,
    "gn:feature_class":"P",
    "gn:feature_code":"PPL",
    "gn:name":"Arkana",
    "gn:population":0,
    "gn:timezone":"Asia/Kolkata",
    "iso:country":"IN",
    "ks:ks_name":"Arkana",
    "ks:ks_pop":254,
    "ks:ks_type":"HABITATION",
    "name:deu_x_preferred":[
        "Arkana"
    ],
    "name:eng_x_preferred":[
        "Arkana"
    ],
    "wof:name":"Arkana",
    "wof:placetype":"locality",
    "wof:population":254
},
  "geometry": {"coordinates":[74.952884,12.816475],"type":"Point"}
}