{
  "type": "Feature",
  "properties": {
    "gn:admin1_code":"19.0",
    "gn:admin2_code":"575.0",
    "gn:asciiname":"Arkana",
    "gn:country_code":"IN",
    "gn:dem":74,
    "gn:feature_class":"P",
    "gn:feature_code":"PPL",
    "gn:name":"Arkana",
    "gn:population":0,
    "gn:timezone":"Asia/Kolkata",
    "iso:country":"IN",
    "name:deu_x_preferred":[
        "Arkana"
    ],
    "wof:name":"Arkana",
    "wof:placetype":"locality"
},
  "geometry": {"coordinates":[74.95144999999999,12.8151],"type":"Point"}
}