{
  "type": "Feature",
  "properties": {
    "iso:country":"IN",
    "ks:ks_name":"Srirampur",
    "ks:ks_pop":148,
    "ks:ks_type":"VILLAGE",
    "name:eng_x_preferred":[
        "Srirampur"
    ],
    "wof:name":"Srirampur",
    "wof:placetype":"locality",
    "wof:population":148
},
  "geometry": {"coordinates":[86.112223,23.118728],"type":"Point"}
}