{
  "type": "Feature",
  "properties": {
    "gn:admin1_code":"34.0",
    "gn:admin2_code":"236.0",
    "gn:asciiname":"Kewal",
    "gn:country_code":"IN",
    "gn:dem":189,
    "gn:feature_class":"P",
    "gn:feature_code":"PPL",
    "gn:name":"Kew\u0101l",
    "gn:population":0,
    "gn:timezone":"Asia/Kolkata",
    "iso:country":"IN",
    "name:fas_x_preferred":[
        "\u06a9\u0648\u0627\u0626\u06cc"
    ],
    "name:urd_x_preferred":[
        "\u06a9\u0648\u0627\u0626\u06cc"
    ],
    "wof:name":"Kewal",
    "wof:placetype":"locality"
},
  "geometry": {"coordinates":[85.29579,24.57259],"type":"Point"}
}