{
  "type": "Feature",
  "properties": {
    "iso:country":"IN",
    "ks:ks_alt_nam":"T\u0101keria",
    "ks:ks_name":"Takeria",
    "ks:ks_pop":21,
    "ks:ks_type":"VILLAGE",
    "name:eng_x_preferred":[
        "Takeria"
    ],
    "name:eng_x_variant":[
        "T\u0101keria"
    ],
    "wof:name":"Takeria",
    "wof:placetype":"locality",
    "wof:population":21
},
  "geometry": {"coordinates":[85.09273899999999,20.301022],"type":"Point"}
}