{
  "type": "Feature",
  "properties": {
    "gn:admin1_code":"11.0",
    "gn:admin2_code":"33.0",
    "gn:asciiname":"Manan",
    "gn:country_code":"IN",
    "gn:dem":1198,
    "gn:feature_class":"P",
    "gn:feature_code":"PPL",
    "gn:name":"M\u0101nan",
    "gn:population":0,
    "gn:timezone":"Asia/Kolkata",
    "iso:country":"IN",
    "wof:name":"Manan",
    "wof:placetype":"locality"
},
  "geometry": {"coordinates":[77.41194,31.34144],"type":"Point"}
}