{
  "type": "Feature",
  "properties": {
    "iso:country":"IN",
    "ks:ks_name":"Mathadi",
    "ks:ks_pop":154,
    "ks:ks_type":"VILLAGE",
    "name:eng_x_preferred":[
        "Mathadi"
    ],
    "wof:name":"Mathadi",
    "wof:placetype":"locality",
    "wof:population":154
},
  "geometry": {"coordinates":[79.69255200000001,21.113412],"type":"Point"}
}