{
  "type": "Feature",
  "properties": {
    "iso:country":"IN",
    "ks:ks_name":"Ghanera",
    "ks:ks_pop":869,
    "ks:ks_type":"VILLAGE",
    "name:eng_x_preferred":[
        "Ghanera"
    ],
    "wof:name":"Ghanera",
    "wof:placetype":"locality",
    "wof:population":869
},
  "geometry": {"coordinates":[74.41348499999999,23.929785],"type":"Point"}
}