{
  "type": "Feature",
  "properties": {
    "iso:country":"IN",
    "ks:ks_name":"Namchelekha I",
    "ks:ks_pop":396,
    "ks:ks_type":"HABITATION",
    "name:eng_x_preferred":[
        "Namchelekha I"
    ],
    "wof:name":"Namchelekha I",
    "wof:placetype":"locality",
    "wof:population":396
},
  "geometry": {"coordinates":[88.600185,27.165996],"type":"Point"}
}