{
  "type": "Feature",
  "properties": {
    "gn:admin1_code":"36.0",
    "gn:admin2_code":"181.0",
    "gn:asciiname":"Seondha",
    "gn:country_code":"IN",
    "gn:dem":122,
    "gn:feature_class":"P",
    "gn:feature_code":"PPL",
    "gn:name":"Seondha",
    "gn:population":0,
    "gn:timezone":"Asia/Kolkata",
    "iso:country":"IN",
    "name:ben_x_preferred":[
        "\u09b8\u09c7\u0993\u09a8\u09cd\u09a6\u09be"
    ],
    "name:bpy_x_preferred":[
        "\u09b8\u09c7\u0993\u09a8\u09cd\u09a6\u09be"
    ],
    "name:ceb_x_preferred":[
        "Seondha"
    ],
    "name:hin_x_preferred":[
        "\u0938\u0947\u0935\u0922\u093c\u093e"
    ],
    "name:ita_x_preferred":[
        "Seondha"
    ],
    "name:msa_x_preferred":[
        "Seondha"
    ],
    "name:nld_x_preferred":[
        "Seondha"
    ],
    "name:por_x_preferred":[
        "Seondha"
    ],
    "name:spa_x_preferred":[
        "Seondha"
    ],
    "name:swe_x_preferred":[
        "Seondha"
    ],
    "name:vie_x_preferred":[
        "Seondha"
    ],
    "name:zho_x_preferred":[
        "\u585e\u5965\u6069\u8fbe"
    ],
    "wof:name":"Seondha",
    "wof:placetype":"locality"
},
  "geometry": {"coordinates":[81.78255,27.49763],"type":"Point"}
}