{
  "type": "Feature",
  "properties": {
    "iso:country":"IN",
    "ks:ks_name":"Wabalewasti",
    "ks:ks_pop":172,
    "ks:ks_type":"HABITATION",
    "name:eng_x_preferred":[
        "Wabalewasti"
    ],
    "wof:name":"Wabalewasti",
    "wof:placetype":"locality",
    "wof:population":172
},
  "geometry": {"coordinates":[74.44447700000001,19.423639],"type":"Point"}
}