{
  "type": "Feature",
  "properties": {
    "gn:admin1_code":"36",
    "gn:admin2_code":"187.0",
    "gn:asciiname":"Ismailpur",
    "gn:country_code":"IN",
    "gn:dem":92,
    "gn:feature_class":"P",
    "gn:feature_code":"PPL",
    "gn:name":"Ism\u0101ilpur",
    "gn:population":0,
    "gn:timezone":"Asia/Kolkata",
    "iso:country":"IN",
    "wof:name":"Ismailpur",
    "wof:placetype":"locality"
},
  "geometry": {"coordinates":[83.54531999999998,27.11913],"type":"Point"}
}