{
  "type": "Feature",
  "properties": {
    "iso:country":"IN",
    "ks:ks_name":"Uperguda",
    "ks:ks_pop":250,
    "ks:ks_type":"HABITATION",
    "name:eng_x_preferred":[
        "Uperguda"
    ],
    "wof:name":"Uperguda",
    "wof:placetype":"locality",
    "wof:population":250
},
  "geometry": {"coordinates":[82.488933,19.012806],"type":"Point"}
}