{
  "type": "Feature",
  "properties": {
    "iso:country":"IN",
    "ks:ks_name":"14 APD-B",
    "ks:ks_pop":725,
    "ks:ks_type":"VILLAGE",
    "ks:ks_uagg_main":0,
    "name:eng_x_preferred":[
        "14 APD-B"
    ],
    "wof:name":"14 APD-B",
    "wof:placetype":"neighbourhood",
    "wof:population":725
},
  "geometry": {"coordinates":[73.31214300000001,29.296905],"type":"Point"}
}