{
  "type": "Feature",
  "properties": {
    "gn:admin1_code":"09",
    "gn:admin2_code":"477.0",
    "gn:asciiname":"Unurala",
    "gn:country_code":"IN",
    "gn:dem":128,
    "gn:feature_class":"P",
    "gn:feature_code":"PPL",
    "gn:name":"Unur\u0101la",
    "gn:population":0,
    "gn:timezone":"Asia/Kolkata",
    "iso:country":"IN",
    "name:und_x_variant":[
        "Umr\u0101la",
        "Unur\u0101la"
    ],
    "wof:name":"Unurala",
    "wof:placetype":"locality"
},
  "geometry": {"coordinates":[70.30790999999999,22.03402],"type":"Point"}
}