{
  "type": "Feature",
  "properties": {
    "gn:admin1_code":"34.0",
    "gn:admin2_code":"211.0",
    "gn:asciiname":"Kathal",
    "gn:country_code":"IN",
    "gn:dem":43,
    "gn:feature_class":"P",
    "gn:feature_code":"PPL",
    "gn:name":"Kath\u0101l",
    "gn:population":0,
    "gn:timezone":"Asia/Kolkata",
    "iso:country":"IN",
    "wof:name":"Kathal",
    "wof:placetype":"neighbourhood"
},
  "geometry": {"coordinates":[87.73219,25.76933],"type":"Point"}
}