{
  "type": "Feature",
  "properties": {
    "gn:admin1_code":"11",
    "gn:admin2_code":"24.0",
    "gn:asciiname":"Manei",
    "gn:country_code":"IN",
    "gn:dem":579,
    "gn:feature_class":"P",
    "gn:feature_code":"PPL",
    "gn:name":"Manei",
    "gn:population":0,
    "gn:timezone":"Asia/Kolkata",
    "iso:country":"IN",
    "wof:name":"Manei",
    "wof:placetype":"locality"
},
  "geometry": {"coordinates":[76.13736,32.1207],"type":"Point"}
}