{
  "type": "Feature",
  "properties": {
    "gn:admin1_code":"21",
    "gn:admin2_code":"370.0",
    "gn:asciiname":"Khaliapali",
    "gn:country_code":"IN",
    "gn:dem":187,
    "gn:feature_class":"P",
    "gn:feature_code":"PPL",
    "gn:name":"Khaliap\u0101li",
    "gn:population":0,
    "gn:timezone":"Asia/Kolkata",
    "iso:country":"IN",
    "name:ben_x_preferred":[
        "\u0996\u09be\u09b2\u09bf\u09aa\u09be\u09b2\u09bf"
    ],
    "name:bpy_x_preferred":[
        "\u0996\u09be\u09b2\u09bf\u09aa\u09be\u09b2\u09bf"
    ],
    "name:ita_x_preferred":[
        "Khaliapali"
    ],
    "name:msa_x_preferred":[
        "Khaliapali"
    ],
    "name:nld_x_preferred":[
        "Khaliapali"
    ],
    "name:ori_x_preferred":[
        "\u0b16\u0b33\u0b3f\u0b06\u0b2a\u0b3e\u0b33\u0b3f"
    ],
    "name:por_x_preferred":[
        "Khaliapali"
    ],
    "name:vie_x_preferred":[
        "Khaliapali"
    ],
    "name:zho_x_preferred":[
        "\u5361\u5229\u4e9a\u5e15\u5229"
    ],
    "wof:name":"Khaliapali",
    "wof:placetype":"locality"
},
  "geometry": {"coordinates":[83.61641,21.36397],"type":"Point"}
}