{
  "type": "Feature",
  "properties": {
    "gn:admin1_code":"16.0",
    "gn:admin2_code":"504.0",
    "gn:asciiname":"Chistur",
    "gn:country_code":"IN",
    "gn:dem":309,
    "gn:feature_class":"P",
    "gn:feature_code":"PPL",
    "gn:name":"Chist\u016br",
    "gn:population":0,
    "gn:timezone":"Asia/Kolkata",
    "iso:country":"IN",
    "wof:name":"Chistur",
    "wof:placetype":"locality"
},
  "geometry": {"coordinates":[78.17596999999998,21.10158],"type":"Point"}
}