{
  "type": "Feature",
  "properties": {
    "iso:country":"IN",
    "ks:ks_name":"Akapur Chak",
    "ks:ks_pop":516,
    "ks:ks_type":"VILLAGE",
    "name:eng_x_preferred":[
        "Akapur Chak"
    ],
    "wof:name":"Akapur Chak",
    "wof:placetype":"locality",
    "wof:population":516
},
  "geometry": {"coordinates":[80.008763,20.388116],"type":"Point"}
}