{
  "type": "Feature",
  "properties": {
    "gn:admin1_code":"24.0",
    "gn:admin2_code":"130.0",
    "gn:asciiname":"Nawagaun",
    "gn:country_code":"IN",
    "gn:dem":506,
    "gn:feature_class":"P",
    "gn:feature_code":"PPL",
    "gn:name":"Nawag\u0101un",
    "gn:population":0,
    "gn:timezone":"Asia/Kolkata",
    "iso:country":"IN",
    "wof:name":"Nawagaun",
    "wof:placetype":"locality"
},
  "geometry": {"coordinates":[73.42584000000002,24.3886],"type":"Point"}
}