{
  "type": "Feature",
  "properties": {
    "iso:country":"IN",
    "ks:ks_name":"Talichiwadi",
    "ks:ks_pop":82,
    "ks:ks_type":"HABITATION",
    "name:eng_x_preferred":[
        "Talichiwadi"
    ],
    "wof:name":"Talichiwadi",
    "wof:placetype":"locality",
    "wof:population":82
},
  "geometry": {"coordinates":[73.535956,17.097492],"type":"Point"}
}