{
  "type": "Feature",
  "properties": {
    "iso:country":"IN",
    "ks:ks_alt_nam":"khurd hai",
    "ks:ks_name":"Khurd Hai",
    "ks:ks_pop":240,
    "ks:ks_type":"HABITATION",
    "name:eng_x_preferred":[
        "Khurd Hai"
    ],
    "wof:name":"Khurd Hai",
    "wof:placetype":"locality",
    "wof:population":240
},
  "geometry": {"coordinates":[80.713438,26.2799],"type":"Point"}
}