{
  "type": "Feature",
  "properties": {
    "iso:country":"IN",
    "ks:ks_name":"Chaspara",
    "ks:ks_pop":5630,
    "ks:ks_type":"URBAN",
    "ks:ks_uagg_main":0,
    "name:eng_x_preferred":[
        "Chaspara"
    ],
    "wof:name":"Chaspara",
    "wof:placetype":"neighbourhood",
    "wof:population":5630
},
  "geometry": {"coordinates":[88.082559,24.910893],"type":"Point"}
}