{
  "type": "Feature",
  "properties": {
    "gn:admin1_code":"10.0",
    "gn:admin2_code":"71.0",
    "gn:asciiname":"Pansra",
    "gn:country_code":"IN",
    "gn:dem":272,
    "gn:feature_class":"P",
    "gn:feature_code":"PPL",
    "gn:name":"P\u0101nsra",
    "gn:population":0,
    "gn:timezone":"Asia/Kolkata",
    "iso:country":"IN",
    "ks:ks_alt_nam":"P\u0101nsra",
    "ks:ks_name":"Pansra",
    "ks:ks_pop":2748,
    "ks:ks_type":"VILLAGE",
    "ks:ks_uagg_main":0,
    "name:eng_x_preferred":[
        "Pansra"
    ],
    "name:eng_x_variant":[
        "P\u0101nsra"
    ],
    "wof:name":"Pansra",
    "wof:placetype":"neighbourhood",
    "wof:population":2748
},
  "geometry": {"coordinates":[77.305904,30.106005],"type":"Point"}
}