{
  "type": "Feature",
  "properties": {
    "iso:country":"IN",
    "ks:ks_name":"Njndala",
    "ks:ks_pop":819,
    "ks:ks_type":"HABITATION",
    "name:eng_x_preferred":[
        "Njndala"
    ],
    "wof:name":"Njndala",
    "wof:placetype":"locality",
    "wof:population":819
},
  "geometry": {"coordinates":[76.9212,10.044673],"type":"Point"}
}