{
  "type": "Feature",
  "properties": {
    "iso:country":"IN",
    "ks:ks_name":"Kalvavandlapalli",
    "ks:ks_pop":90,
    "ks:ks_type":"HABITATION",
    "name:eng_x_preferred":[
        "Kalvavandlapalli"
    ],
    "wof:name":"Kalvavandlapalli",
    "wof:placetype":"locality",
    "wof:population":90
},
  "geometry": {"coordinates":[78.62893699999999,14.065236],"type":"Point"}
}