{
  "type": "Feature",
  "properties": {
    "iso:country":"IN",
    "ks:ks_alt_nam":"GURVPD KA PURA",
    "ks:ks_name":"Gurvpd Ka Pura",
    "ks:ks_pop":203,
    "ks:ks_type":"HABITATION",
    "name:eng_x_preferred":[
        "Gurvpd Ka Pura"
    ],
    "wof:name":"Gurvpd Ka Pura",
    "wof:placetype":"locality",
    "wof:population":203
},
  "geometry": {"coordinates":[82.002072,24.996803],"type":"Point"}
}