{
  "type": "Feature",
  "properties": {
    "iso:country":"IN",
    "ks:ks_alt_nam":"GUDHALE WASTI",
    "ks:ks_name":"Gudhale Wasti",
    "ks:ks_pop":129,
    "ks:ks_type":"HABITATION",
    "name:eng_x_preferred":[
        "Gudhale Wasti"
    ],
    "wof:name":"Gudhale Wasti",
    "wof:placetype":"locality",
    "wof:population":129
},
  "geometry": {"coordinates":[75.433959,17.092643],"type":"Point"}
}