{
  "type": "Feature",
  "properties": {
    "gn:admin1_code":"35.0",
    "gn:admin2_code":"455.0",
    "gn:asciiname":"Dighawani",
    "gn:country_code":"IN",
    "gn:dem":738,
    "gn:feature_class":"P",
    "gn:feature_code":"PPL",
    "gn:name":"Digh\u0101w\u0101ni",
    "gn:population":0,
    "gn:timezone":"Asia/Kolkata",
    "iso:country":"IN",
    "name:und_x_variant":[
        "Digh\u0101w\u0101ni"
    ],
    "wof:name":"Dighawani",
    "wof:placetype":"locality"
},
  "geometry": {"coordinates":[78.81348,22.20606],"type":"Point"}
}