{
  "type": "Feature",
  "properties": {
    "iso:country":"IN",
    "ks:ks_name":"Bhatkarwadi",
    "ks:ks_pop":593,
    "ks:ks_type":"HABITATION",
    "name:eng_x_preferred":[
        "Bhatkarwadi"
    ],
    "wof:name":"Bhatkarwadi",
    "wof:placetype":"locality",
    "wof:population":593
},
  "geometry": {"coordinates":[73.490886,15.98698],"type":"Point"}
}