{
  "type": "Feature",
  "properties": {
    "gn:admin1_code":"21.0",
    "gn:admin2_code":"398.0",
    "gn:asciiname":"Galiputtu",
    "gn:country_code":"IN",
    "gn:dem":915,
    "gn:feature_class":"P",
    "gn:feature_code":"PPL",
    "gn:name":"Galiputtu",
    "gn:population":0,
    "gn:timezone":"Asia/Kolkata",
    "iso:country":"IN",
    "wof:name":"Galiputtu",
    "wof:placetype":"locality"
},
  "geometry": {"coordinates":[82.77627,18.591],"type":"Point"}
}