{
  "type": "Feature",
  "properties": {
    "gn:admin1_code":"19.0",
    "gn:admin2_code":"574.0",
    "gn:asciiname":"Muttugada Honnenahalli",
    "gn:country_code":"IN",
    "gn:dem":884,
    "gn:feature_class":"P",
    "gn:feature_code":"PPL",
    "gn:name":"Muttugada Honnenahalli",
    "gn:population":0,
    "gn:timezone":"Asia/Kolkata",
    "iso:country":"IN",
    "wof:name":"Muttugada Honnenahalli",
    "wof:placetype":"neighbourhood"
},
  "geometry": {"coordinates":[76.49784,12.9524],"type":"Point"}
}