{
  "type": "Feature",
  "properties": {
    "iso:country":"IN",
    "ks:ks_name":"Honnali",
    "ks:ks_pop":291,
    "ks:ks_type":"HABITATION",
    "name:eng_x_preferred":[
        "Honnali"
    ],
    "wof:name":"Honnali",
    "wof:placetype":"locality",
    "wof:population":291
},
  "geometry": {"coordinates":[74.436345,14.675988],"type":"Point"}
}