{
  "type": "Feature",
  "properties": {
    "gn:admin1_code":"36",
    "gn:admin2_code":"202.0",
    "gn:asciiname":"Arjunpur Qadim",
    "gn:country_code":"IN",
    "gn:dem":173,
    "gn:feature_class":"P",
    "gn:feature_code":"PPL",
    "gn:name":"Arjunpur Qad\u012bm",
    "gn:population":0,
    "gn:timezone":"Asia/Kolkata",
    "iso:country":"IN",
    "wof:name":"Arjunpur Qadim",
    "wof:placetype":"locality"
},
  "geometry": {"coordinates":[78.80088000000001,27.67741],"type":"Point"}
}