{
  "type": "Feature",
  "properties": {
    "iso:country":"IN",
    "ks:ks_name":"Nagaraopally",
    "ks:ks_pop":78,
    "ks:ks_type":"HABITATION",
    "name:eng_x_preferred":[
        "Nagaraopally"
    ],
    "wof:name":"Nagaraopally",
    "wof:placetype":"locality",
    "wof:population":78
},
  "geometry": {"coordinates":[78.57879200000001,16.764999],"type":"Point"}
}