{
  "type": "Feature",
  "properties": {
    "iso:country":"IN",
    "ks:ks_name":"Pachahi Machhaita",
    "ks:ks_pop":540,
    "ks:ks_type":"VILLAGE",
    "name:eng_x_preferred":[
        "Pachahi Machhaita"
    ],
    "wof:name":"Pachahi Machhaita",
    "wof:placetype":"locality",
    "wof:population":540
},
  "geometry": {"coordinates":[86.288189,26.145869],"type":"Point"}
}