{
  "type": "Feature",
  "properties": {
    "gn:admin1_code":"35.0",
    "gn:admin2_code":"424.0",
    "gn:asciiname":"Changuwan",
    "gn:country_code":"IN",
    "gn:dem":256,
    "gn:feature_class":"P",
    "gn:feature_code":"PPL",
    "gn:name":"Changuw\u0101n",
    "gn:population":0,
    "gn:timezone":"Asia/Kolkata",
    "iso:country":"IN",
    "wof:name":"Changuwan",
    "wof:placetype":"locality"
},
  "geometry": {"coordinates":[79.29895,24.83212],"type":"Point"}
}