{
  "type": "Feature",
  "properties": {
    "gn:admin1_code":"25.0",
    "gn:admin2_code":"607.0",
    "gn:asciiname":"Karanasettitangal",
    "gn:country_code":"IN",
    "gn:dem":121,
    "gn:feature_class":"P",
    "gn:feature_code":"PPL",
    "gn:name":"Karanasettitangal",
    "gn:population":0,
    "gn:timezone":"Asia/Kolkata",
    "iso:country":"IN",
    "wof:name":"Karanasettitangal",
    "wof:placetype":"neighbourhood"
},
  "geometry": {"coordinates":[79.07048,12.00336],"type":"Point"}
}