{
  "type": "Feature",
  "properties": {
    "iso:country":"IN",
    "ks:ks_name":"Mangudih",
    "ks:ks_pop":50,
    "ks:ks_type":"HABITATION",
    "name:eng_x_preferred":[
        "Mangudih"
    ],
    "wof:name":"Mangudih",
    "wof:placetype":"locality",
    "wof:population":50
},
  "geometry": {"coordinates":[85.415313,22.964018],"type":"Point"}
}