{
  "type": "Feature",
  "properties": {
    "iso:country":"IN",
    "ks:ks_name":"Kadsari Lingana",
    "ks:ks_pop":147,
    "ks:ks_type":"VILLAGE",
    "name:eng_x_preferred":[
        "Kadsari Lingana"
    ],
    "wof:name":"Kadsari Lingana",
    "wof:placetype":"locality",
    "wof:population":147
},
  "geometry": {"coordinates":[73.495803,18.253881],"type":"Point"}
}