{
  "type": "Feature",
  "properties": {
    "gn:admin1_code":"37.0",
    "gn:admin2_code":"414.0",
    "gn:asciiname":"Lakharas",
    "gn:country_code":"IN",
    "gn:dem":615,
    "gn:feature_class":"P",
    "gn:feature_code":"PPL",
    "gn:name":"Lakh\u0101r\u0101s",
    "gn:population":0,
    "gn:timezone":"Asia/Kolkata",
    "iso:country":"IN",
    "ks:ks_alt_nam":"Lakh\u0101r\u0101s",
    "ks:ks_name":"Lakharas",
    "ks:ks_pop":576,
    "ks:ks_type":"VILLAGE",
    "name:eng_x_preferred":[
        "Lakharas"
    ],
    "name:eng_x_variant":[
        "Lakh\u0101r\u0101s"
    ],
    "wof:name":"Lakharas",
    "wof:placetype":"locality",
    "wof:population":576
},
  "geometry": {"coordinates":[81.64478200000001,18.815636],"type":"Point"}
}