{
  "type": "Feature",
  "properties": {
    "gn:admin1_code":"29.0",
    "gn:admin2_code":"242.0",
    "gn:asciiname":"Kaluk",
    "gn:country_code":"IN",
    "gn:dem":1598,
    "gn:feature_class":"P",
    "gn:feature_code":"PPL",
    "gn:name":"Kaluk",
    "gn:population":0,
    "gn:timezone":"Asia/Kolkata",
    "iso:country":"IN",
    "wof:name":"Kaluk",
    "wof:placetype":"locality"
},
  "geometry": {"coordinates":[88.25381999999998,27.2313],"type":"Point"}
}