{
  "type": "Feature",
  "properties": {
    "gn:admin1_code":"33.0",
    "gn:admin2_code":"585",
    "gn:asciiname":"Advolpale",
    "gn:country_code":"IN",
    "gn:dem":19,
    "gn:feature_class":"P",
    "gn:feature_code":"PPL",
    "gn:name":"Advolpale",
    "gn:population":0,
    "gn:timezone":"Asia/Kolkata",
    "iso:country":"IN",
    "wof:name":"Advolpale",
    "wof:placetype":"locality"
},
  "geometry": {"coordinates":[73.9023,15.63869],"type":"Point"}
}