{
  "type": "Feature",
  "properties": {
    "iso:country":"IN",
    "ks:ks_name":"Mal Kh",
    "ks:ks_pop":683,
    "ks:ks_type":"HABITATION",
    "name:eng_x_preferred":[
        "Mal Kh"
    ],
    "wof:name":"Mal Kh",
    "wof:placetype":"locality",
    "wof:population":683
},
  "geometry": {"coordinates":[74.154804,21.653303],"type":"Point"}
}