{
  "type": "Feature",
  "properties": {
    "gn:country":"IN",
    "gn:fcode":"PPL",
    "gn:pop":13498,
    "iso:country":"IN",
    "name:bpy_x_preferred":[
        "\u09b8\u09be\u09b8\u09a8\u09bf"
    ],
    "name:eng_x_preferred":[
        "Sasni"
    ],
    "name:fra_x_preferred":[
        "Sasni"
    ],
    "name:ita_x_preferred":[
        "Sasni"
    ],
    "name:mlg_x_preferred":[
        "Sasni"
    ],
    "name:msa_x_preferred":[
        "Sasni"
    ],
    "name:nan_x_preferred":[
        "Sasni"
    ],
    "name:nld_x_preferred":[
        "Sasni"
    ],
    "name:pol_x_preferred":[
        "Sasni"
    ],
    "name:por_x_preferred":[
        "Sasni"
    ],
    "name:swe_x_preferred":[
        "S\u0101sni"
    ],
    "name:unk_x_variant":[
        "S\u0101sni"
    ],
    "name:urd_x_preferred":[
        "\u0633\u0627\u0633\u0646\u06cc"
    ],
    "name:vie_x_preferred":[
        "Sasni"
    ],
    "name:zho_x_preferred":[
        "\u8428\u65af\u5c3c"
    ],
    "qs:name":"Sasni",
    "qs:name_adm0":"India",
    "qs:name_adm1":"Uttar Pradesh",
    "qs:photos_9k":1,
    "qs:photos_9r":1,
    "qs:photos_all":2,
    "qs:photos_sr":0,
    "qs:placetype":"Town",
    "qs:pop_sr":"6",
    "wd:wordcount":275,
    "wof:name":"Sasni",
    "wof:placetype":"locality",
    "wof:population":13498
},
  "geometry": {"coordinates":[78.08228,27.7038],"type":"Point"}
}