{
  "type": "Feature",
  "properties": {
    "iso:country":"IN",
    "ks:ks_name":"Hetalia",
    "ks:ks_pop":577,
    "ks:ks_type":"HABITATION",
    "name:eng_x_preferred":[
        "Hetalia"
    ],
    "wof:name":"Hetalia",
    "wof:placetype":"locality",
    "wof:population":577
},
  "geometry": {"coordinates":[91.392456,23.311272],"type":"Point"}
}