{
  "type": "Feature",
  "properties": {
    "iso:country":"IN",
    "ks:ks_name":"Depakulaguda",
    "ks:ks_pop":65,
    "ks:ks_type":"HABITATION",
    "name:eng_x_preferred":[
        "Depakulaguda"
    ],
    "wof:name":"Depakulaguda",
    "wof:placetype":"locality",
    "wof:population":65
},
  "geometry": {"coordinates":[83.86640300000001,18.721816],"type":"Point"}
}