{
  "type": "Feature",
  "properties": {
    "iso:country":"IN",
    "ks:ks_name":"Pramodaprasad",
    "ks:ks_pop":14,
    "ks:ks_type":"HABITATION",
    "name:eng_x_preferred":[
        "Pramodaprasad"
    ],
    "wof:name":"Pramodaprasad",
    "wof:placetype":"locality",
    "wof:population":14
},
  "geometry": {"coordinates":[85.099385,20.950751],"type":"Point"}
}