{
  "type": "Feature",
  "properties": {
    "iso:country":"IN",
    "ks:ks_name":"Kokodi",
    "ks:ks_pop":216,
    "ks:ks_type":"VILLAGE",
    "name:eng_x_preferred":[
        "Kokodi"
    ],
    "wof:name":"Kokodi",
    "wof:placetype":"locality",
    "wof:population":216
},
  "geometry": {"coordinates":[81.547337,19.664501],"type":"Point"}
}