{
  "type": "Feature",
  "properties": {
    "iso:country":"IN",
    "ks:ks_name":"Mukundapur",
    "ks:ks_pop":814,
    "ks:ks_type":"VILLAGE",
    "name:eng_x_preferred":[
        "Mukundapur"
    ],
    "wof:name":"Mukundapur",
    "wof:placetype":"locality",
    "wof:population":814
},
  "geometry": {"coordinates":[91.720618,26.567927],"type":"Point"}
}