{
  "type": "Feature",
  "properties": {
    "iso:country":"IN",
    "ks:ks_name":"Akri",
    "ks:ks_pop":18,
    "ks:ks_type":"HABITATION",
    "name:eng_x_preferred":[
        "Akri"
    ],
    "wof:name":"Akri",
    "wof:placetype":"locality",
    "wof:population":18
},
  "geometry": {"coordinates":[82.949141,27.370079],"type":"Point"}
}