{
  "type": "Feature",
  "properties": {
    "gn:admin1_code":"12.0",
    "gn:admin2_code":"7.0",
    "gn:asciiname":"Lilh",
    "gn:country_code":"IN",
    "gn:dem":1847,
    "gn:feature_class":"P",
    "gn:feature_code":"PPL",
    "gn:name":"Lilh",
    "gn:population":0,
    "gn:timezone":"Asia/Kolkata",
    "iso:country":"IN",
    "wof:name":"Lilh",
    "wof:placetype":"locality"
},
  "geometry": {"coordinates":[75.62564,32.67825999999999],"type":"Point"}
}