{
  "type": "Feature",
  "properties": {
    "iso:country":"IN",
    "ks:ks_alt_nam":"kelagina sirkuli",
    "ks:ks_name":"Kelagina Sirkuli",
    "ks:ks_pop":106,
    "ks:ks_type":"HABITATION",
    "name:eng_x_preferred":[
        "Kelagina Sirkuli"
    ],
    "wof:name":"Kelagina Sirkuli",
    "wof:placetype":"locality",
    "wof:population":106
},
  "geometry": {"coordinates":[74.762136,14.519749],"type":"Point"}
}