{
  "type": "Feature",
  "properties": {
    "gn:admin1_code":"40",
    "gn:admin2_code":"534.0",
    "gn:asciiname":"Yelgonda",
    "gn:country_code":"IN",
    "gn:dem":196,
    "gn:feature_class":"P",
    "gn:feature_code":"PPL",
    "gn:name":"Yelgonda",
    "gn:population":0,
    "gn:timezone":"Asia/Kolkata",
    "iso:country":"IN",
    "wof:name":"Yelgonda",
    "wof:placetype":"locality"
},
  "geometry": {"coordinates":[79.05762,18.89573],"type":"Point"}
}