{
  "type": "Feature",
  "properties": {
    "iso:country":"IN",
    "ks:ks_name":"Jonkaha",
    "ks:ks_type":"VILLAGE",
    "name:eng_x_preferred":[
        "Jonkaha"
    ],
    "wof:name":"Jonkaha",
    "wof:placetype":"locality"
},
  "geometry": {"coordinates":[81.97138099999999,27.474824],"type":"Point"}
}