{
  "type": "Feature",
  "properties": {
    "gn:admin1_code":"11",
    "gn:admin2_code":"24.0",
    "gn:asciiname":"Pukhrun",
    "gn:country_code":"IN",
    "gn:dem":507,
    "gn:feature_class":"P",
    "gn:feature_code":"PPL",
    "gn:name":"Pukhr\u016bn",
    "gn:population":0,
    "gn:timezone":"Asia/Kolkata",
    "iso:country":"IN",
    "wof:name":"Pukhrun",
    "wof:placetype":"locality"
},
  "geometry": {"coordinates":[76.20716999999998,31.93831],"type":"Point"}
}