{
  "type": "Feature",
  "properties": {
    "gn:admin1_code":"36.0",
    "gn:admin2_code":"132.0",
    "gn:asciiname":"Mukarrampur Lalwala",
    "gn:country_code":"IN",
    "gn:dem":275,
    "gn:feature_class":"P",
    "gn:feature_code":"PPL",
    "gn:name":"Mukarrampur L\u0101lw\u0101la",
    "gn:population":0,
    "gn:timezone":"Asia/Kolkata",
    "iso:country":"IN",
    "wof:name":"Mukarrampur Lalwala",
    "wof:placetype":"locality"
},
  "geometry": {"coordinates":[77.44025000000001,30.12711],"type":"Point"}
}