{
  "type": "Feature",
  "properties": {
    "gn:admin1_code":"21.0",
    "gn:admin2_code":"377.0",
    "gn:asciiname":"Khalabadia",
    "gn:country_code":"IN",
    "gn:dem":6,
    "gn:feature_class":"P",
    "gn:feature_code":"PPL",
    "gn:name":"Khalabadia",
    "gn:population":0,
    "gn:timezone":"Asia/Kolkata",
    "iso:country":"IN",
    "ks:ks_name":"Khalabadia",
    "ks:ks_pop":1186,
    "ks:ks_type":"VILLAGE",
    "ks:ks_uagg_main":0,
    "name:eng_x_preferred":[
        "Khalabadia"
    ],
    "wof:name":"Khalabadia",
    "wof:placetype":"neighbourhood",
    "wof:population":1186
},
  "geometry": {"coordinates":[87.33925600000001,21.658707],"type":"Point"}
}