{
  "type": "Feature",
  "properties": {
    "iso:country":"IN",
    "ks:ks_name":"Nimdaspur",
    "ks:ks_pop":347,
    "ks:ks_type":"VILLAGE",
    "ks:ks_uagg_main":0,
    "name:eng_x_preferred":[
        "Nimdaspur"
    ],
    "wof:name":"Nimdaspur",
    "wof:placetype":"neighbourhood",
    "wof:population":347
},
  "geometry": {"coordinates":[87.47319400000001,23.939177],"type":"Point"}
}