{
  "type": "Feature",
  "properties": {
    "iso:country":"IN",
    "ks:ks_name":"9 MKS",
    "ks:ks_pop":99,
    "ks:ks_type":"VILLAGE",
    "name:eng_x_preferred":[
        "9 MKS"
    ],
    "wof:name":"9 MKS",
    "wof:placetype":"locality",
    "wof:population":99
},
  "geometry": {"coordinates":[74.47194399999999,29.674006],"type":"Point"}
}