{
  "type": "Feature",
  "properties": {
    "gn:admin1_code":"35.0",
    "gn:admin2_code":"464.0",
    "gn:asciiname":"Masuria",
    "gn:country_code":"IN",
    "gn:dem":325,
    "gn:feature_class":"P",
    "gn:feature_code":"PPL",
    "gn:name":"Masuria",
    "gn:population":0,
    "gn:timezone":"Asia/Kolkata",
    "iso:country":"IN",
    "name:afr_x_preferred":[
        "Masuri\u00eb"
    ],
    "name:bul_x_preferred":[
        "\u041c\u0430\u0437\u0443\u0440\u0438\u044f"
    ],
    "name:cat_x_preferred":[
        "Mas\u00faria"
    ],
    "name:ces_x_preferred":[
        "Mazury"
    ],
    "name:cym_x_preferred":[
        "Maswria"
    ],
    "name:dan_x_preferred":[
        "Masurien"
    ],
    "name:deu_x_preferred":[
        "Masuren"
    ],
    "name:dsb_x_preferred":[
        "Mazurska"
    ],
    "name:eus_x_preferred":[
        "Masuria"
    ],
    "name:fra_x_preferred":[
        "Mazurie"
    ],
    "name:glg_x_preferred":[
        "Masuria"
    ],
    "name:hrv_x_preferred":[
        "Mazurija"
    ],
    "name:ind_x_preferred":[
        "Mazuria"
    ],
    "name:ita_x_preferred":[
        "Masuria"
    ],
    "name:kat_x_preferred":[
        "\u10db\u10d0\u10d6\u10e3\u10e0\u10d8\u10d0"
    ],
    "name:lat_x_preferred":[
        "Masuria"
    ],
    "name:lav_x_preferred":[
        "Maz\u016brija"
    ],
    "name:msa_x_preferred":[
        "Mazuria"
    ],
    "name:nld_x_preferred":[
        "Mazuri\u00eb"
    ],
    "name:nor_x_preferred":[
        "Masuria"
    ],
    "name:pol_x_preferred":[
        "Mazury"
    ],
    "name:por_x_preferred":[
        "Mas\u00faria"
    ],
    "name:ron_x_preferred":[
        "Mazuria"
    ],
    "name:rus_x_preferred":[
        "\u041c\u0430\u0437\u0443\u0440\u0438\u044f"
    ],
    "name:spa_x_preferred":[
        "Masuria"
    ],
    "name:srp_x_preferred":[
        "\u041c\u0430\u0437\u0443\u0440\u0438\u0458\u0430"
    ],
    "name:swe_x_preferred":[
        "Masurien"
    ],
    "name:ukr_x_preferred":[
        "\u041c\u0430\u0437\u0443\u0440\u0438"
    ],
    "name:zho_x_preferred":[
        "\u99ac\u7956\u91cc\u4e9e"
    ],
    "wof:name":"Masuria",
    "wof:placetype":"locality"
},
  "geometry": {"coordinates":[74.54224000000001,22.81202],"type":"Point"}
}