{
  "type": "Feature",
  "properties": {
    "gn:admin1_code":"34.0",
    "gn:admin2_code":"220.0",
    "gn:asciiname":"Suratpur",
    "gn:country_code":"IN",
    "gn:dem":55,
    "gn:feature_class":"P",
    "gn:feature_code":"PPL",
    "gn:name":"Suratpur",
    "gn:population":0,
    "gn:timezone":"Asia/Kolkata",
    "iso:country":"IN",
    "ks:ks_name":"Suratpur",
    "ks:ks_pop":674,
    "ks:ks_type":"VILLAGE",
    "name:eng_x_preferred":[
        "Suratpur"
    ],
    "wof:name":"Suratpur",
    "wof:placetype":"locality",
    "wof:population":674
},
  "geometry": {"coordinates":[85.4109,25.792847],"type":"Point"}
}