{
  "type": "Feature",
  "properties": {
    "gn:admin1_code":"19.0",
    "gn:admin2_code":"582.0",
    "gn:asciiname":"Gurappanahalli",
    "gn:country_code":"IN",
    "gn:dem":697,
    "gn:feature_class":"P",
    "gn:feature_code":"PPL",
    "gn:name":"Gurappanahalli",
    "gn:population":0,
    "gn:timezone":"Asia/Kolkata",
    "iso:country":"IN",
    "wof:name":"Gurappanahalli",
    "wof:placetype":"locality"
},
  "geometry": {"coordinates":[77.41676,13.57858],"type":"Point"}
}