{
  "type": "Feature",
  "properties": {
    "iso:country":"IN",
    "ks:ks_name":"Paschim Tola",
    "ks:ks_pop":608,
    "ks:ks_type":"HABITATION",
    "ks:ks_uagg_main":0,
    "name:eng_x_preferred":[
        "Paschim Tola"
    ],
    "wof:name":"Paschim Tola",
    "wof:placetype":"neighbourhood",
    "wof:population":608
},
  "geometry": {"coordinates":[83.677436,26.958194],"type":"Point"}
}