{
  "type": "Feature",
  "properties": {
    "gn:admin1_code":"35.0",
    "gn:admin2_code":"433",
    "gn:asciiname":"Garot",
    "gn:country_code":"IN",
    "gn:dem":431,
    "gn:feature_class":"P",
    "gn:feature_code":"PPL",
    "gn:name":"Garot",
    "gn:population":0,
    "gn:timezone":"Asia/Kolkata",
    "iso:country":"IN",
    "name:und_x_variant":[
        "Garoth",
        "Garot"
    ],
    "wof:name":"Garot",
    "wof:placetype":"locality"
},
  "geometry": {"coordinates":[75.65204,24.32342],"type":"Point"}
}