{
  "type": "Feature",
  "properties": {
    "gn:admin1_code":"11.0",
    "gn:admin2_code":"34.0",
    "gn:asciiname":"Jani",
    "gn:country_code":"IN",
    "gn:dem":1983,
    "gn:feature_class":"P",
    "gn:feature_code":"PPL",
    "gn:name":"J\u0101ni",
    "gn:population":0,
    "gn:timezone":"Asia/Kolkata",
    "iso:country":"IN",
    "name:ceb_x_preferred":[
        "Jani"
    ],
    "name:deu_x_preferred":[
        "Jani"
    ],
    "name:fas_x_preferred":[
        "\u062c\u0627\u0646\u06cc"
    ],
    "name:fra_x_preferred":[
        "Jani"
    ],
    "name:rus_x_preferred":[
        "\u0414\u0436\u0430\u043d\u0438"
    ],
    "wof:name":"Jani",
    "wof:placetype":"locality"
},
  "geometry": {"coordinates":[78.06804,31.51851],"type":"Point"}
}