{
  "type": "Feature",
  "properties": {
    "gn:admin1_code":"2.0",
    "gn:admin2_code":"544.0",
    "gn:asciiname":"Barapalle",
    "gn:country_code":"IN",
    "gn:dem":897,
    "gn:feature_class":"P",
    "gn:feature_code":"PPL",
    "gn:name":"Barapalle",
    "gn:population":0,
    "gn:timezone":"Asia/Kolkata",
    "iso:country":"IN",
    "ks:ks_name":"Barapalle",
    "ks:ks_pop":377,
    "ks:ks_type":"VILLAGE",
    "name:eng_x_preferred":[
        "Barapalle"
    ],
    "wof:name":"Barapalle",
    "wof:placetype":"locality",
    "wof:population":377
},
  "geometry": {"coordinates":[82.705276,18.14108],"type":"Point"}
}