{
  "type": "Feature",
  "properties": {
    "iso:country":"IN",
    "ks:ks_name":"Chak Chharera",
    "ks:ks_type":"VILLAGE",
    "name:eng_x_preferred":[
        "Chak Chharera"
    ],
    "wof:name":"Chak Chharera",
    "wof:placetype":"locality"
},
  "geometry": {"coordinates":[76.427307,26.706249],"type":"Point"}
}