{
  "type": "Feature",
  "properties": {
    "iso:country":"IN",
    "ks:ks_name":"Paharpur",
    "ks:ks_pop":421,
    "ks:ks_type":"HABITATION",
    "ks:ks_uagg_main":0,
    "name:eng_x_preferred":[
        "Paharpur"
    ],
    "wof:name":"Paharpur",
    "wof:placetype":"neighbourhood",
    "wof:population":421
},
  "geometry": {"coordinates":[87.79353500000001,23.159745],"type":"Point"}
}