{
  "type": "Feature",
  "properties": {
    "iso:country":"IN",
    "ks:ks_name":"Adhiarpara",
    "ks:ks_pop":669,
    "ks:ks_type":"HABITATION",
    "ks:ks_uagg_main":0,
    "name:eng_x_preferred":[
        "Adhiarpara"
    ],
    "wof:name":"Adhiarpara",
    "wof:placetype":"neighbourhood",
    "wof:population":669
},
  "geometry": {"coordinates":[91.46889899999999,26.274054],"type":"Point"}
}