{
  "type": "Feature",
  "properties": {
    "iso:country":"IN",
    "ks:ks_name":"Tirukkanji",
    "ks:ks_type":"VILLAGE",
    "ks:ks_uagg_main":0,
    "name:eng_x_preferred":[
        "Tirukkanji"
    ],
    "wof:name":"Tirukkanji",
    "wof:placetype":"neighbourhood"
},
  "geometry": {"coordinates":[79.767884,11.888643],"type":"Point"}
}