{
  "type": "Feature",
  "properties": {
    "iso:country":"IN",
    "ks:ks_name":"Kanainatshal",
    "ks:ks_pop":712,
    "ks:ks_type":"VILLAGE",
    "ks:ks_uagg_main":0,
    "name:eng_x_preferred":[
        "Kanainatshal"
    ],
    "wof:name":"Kanainatshal",
    "wof:placetype":"neighbourhood",
    "wof:population":712
},
  "geometry": {"coordinates":[87.87413599999999,23.218807],"type":"Point"}
}