{
  "type": "Feature",
  "properties": {
    "gn:admin1_code":"11",
    "gn:admin2_code":"23.0",
    "gn:asciiname":"Kalail",
    "gn:country_code":"IN",
    "gn:dem":1850,
    "gn:feature_class":"P",
    "gn:feature_code":"PPL",
    "gn:name":"Kalail",
    "gn:population":0,
    "gn:timezone":"Asia/Kolkata",
    "iso:country":"IN",
    "wof:name":"Kalail",
    "wof:placetype":"locality"
},
  "geometry": {"coordinates":[76.47823000000002,32.46129000000001],"type":"Point"}
}