{
  "type": "Feature",
  "properties": {
    "iso:country":"IN",
    "ks:ks_name":"Malatathhedi Road",
    "ks:ks_pop":828,
    "ks:ks_type":"HABITATION",
    "name:eng_x_preferred":[
        "Malatathhedi Road"
    ],
    "wof:name":"Malatathhedi Road",
    "wof:placetype":"locality",
    "wof:population":828
},
  "geometry": {"coordinates":[76.032369,11.135267],"type":"Point"}
}