{
  "type": "Feature",
  "properties": {
    "gn:admin1_code":"37",
    "gn:admin2_code":"417.0",
    "gn:asciiname":"Kannayagudem",
    "gn:country_code":"IN",
    "gn:dem":344,
    "gn:feature_class":"P",
    "gn:feature_code":"PPL",
    "gn:name":"Kannayagudem",
    "gn:population":0,
    "gn:timezone":"Asia/Kolkata",
    "iso:country":"IN",
    "wof:name":"Kannayagudem",
    "wof:placetype":"locality"
},
  "geometry": {"coordinates":[80.85290999999999,18.76688],"type":"Point"}
}