{
  "type": "Feature",
  "properties": {
    "gn:admin1_code":"40.0",
    "gn:admin2_code":"541.0",
    "gn:asciiname":"Kapavaram",
    "gn:country_code":"IN",
    "gn:dem":49,
    "gn:feature_class":"P",
    "gn:feature_code":"PPL",
    "gn:name":"K\u0101pavaram",
    "gn:population":0,
    "gn:timezone":"Asia/Kolkata",
    "iso:country":"IN",
    "ks:ks_alt_nam":"K\u0101pavaram",
    "ks:ks_name":"Kapavaram",
    "ks:ks_type":"VILLAGE",
    "name:eng_x_preferred":[
        "Kapavaram"
    ],
    "name:eng_x_variant":[
        "K\u0101pavaram"
    ],
    "wof:name":"Kapavaram",
    "wof:placetype":"locality"
},
  "geometry": {"coordinates":[81.041409,17.605463],"type":"Point"}
}