{
  "type": "Feature",
  "properties": {
    "gn:admin1_code":"23",
    "gn:admin2_code":"36.0",
    "gn:asciiname":"Pindori",
    "gn:country_code":"IN",
    "gn:dem":242,
    "gn:feature_class":"P",
    "gn:feature_code":"PPL",
    "gn:name":"Pindori",
    "gn:population":0,
    "gn:timezone":"Asia/Kolkata",
    "iso:country":"IN",
    "wof:name":"Pindori",
    "wof:placetype":"locality"
},
  "geometry": {"coordinates":[75.83405,31.24936],"type":"Point"}
}