{
  "type": "Feature",
  "properties": {
    "iso:country":"IN",
    "ks:ks_name":"Balipasi",
    "ks:ks_pop":189,
    "ks:ks_type":"VILLAGE",
    "ks:ks_uagg_main":0,
    "name:eng_x_preferred":[
        "Balipasi"
    ],
    "wof:name":"Balipasi",
    "wof:placetype":"neighbourhood",
    "wof:population":189
},
  "geometry": {"coordinates":[85.94978,20.888483],"type":"Point"}
}