{
  "type": "Feature",
  "properties": {
    "gn:admin1_code":"11",
    "gn:admin2_code":"28.0",
    "gn:asciiname":"Ambgahra",
    "gn:country_code":"IN",
    "gn:dem":790,
    "gn:feature_class":"P",
    "gn:feature_code":"PPL",
    "gn:name":"Ambg\u0101hra",
    "gn:population":0,
    "gn:timezone":"Asia/Kolkata",
    "iso:country":"IN",
    "wof:name":"Ambgahra",
    "wof:placetype":"locality"
},
  "geometry": {"coordinates":[76.46513,31.77065],"type":"Point"}
}