{
  "type": "Feature",
  "properties": {
    "gn:admin1_code":"19",
    "gn:admin2_code":"558.0",
    "gn:asciiname":"Kadhal",
    "gn:country_code":"IN",
    "gn:dem":598,
    "gn:feature_class":"P",
    "gn:feature_code":"PPL",
    "gn:name":"Kadh\u0101l",
    "gn:population":0,
    "gn:timezone":"Asia/Kolkata",
    "iso:country":"IN",
    "wof:name":"Kadhal",
    "wof:placetype":"locality"
},
  "geometry": {"coordinates":[77.26867,18.02619],"type":"Point"}
}