{
  "type": "Feature",
  "properties": {
    "gn:admin1_code":"36",
    "gn:admin2_code":"163.0",
    "gn:asciiname":"Rahimpur Bisdhan",
    "gn:country_code":"IN",
    "gn:dem":142,
    "gn:feature_class":"P",
    "gn:feature_code":"PPL",
    "gn:name":"Rah\u012bmpur Bisdhan",
    "gn:population":0,
    "gn:timezone":"Asia/Kolkata",
    "iso:country":"IN",
    "wof:name":"Rahimpur Bisdhan",
    "wof:placetype":"locality"
},
  "geometry": {"coordinates":[79.90576999999998,26.82513],"type":"Point"}
}