{
  "type": "Feature",
  "properties": {
    "gn:admin1_code":"24.0",
    "gn:admin2_code":"127.0",
    "gn:asciiname":"Dhaba",
    "gn:country_code":"IN",
    "gn:dem":263,
    "gn:feature_class":"P",
    "gn:feature_code":"PPL",
    "gn:name":"Dh\u0101ba",
    "gn:population":0,
    "gn:timezone":"Asia/Kolkata",
    "iso:country":"IN",
    "name:afr_x_preferred":[
        "Dhaba"
    ],
    "name:fas_x_preferred":[
        "\u062f\u0628\u0647"
    ],
    "name:guj_x_preferred":[
        "\u0aa2\u0abe\u0aac\u0abe"
    ],
    "name:hin_x_preferred":[
        "\u0922\u093e\u092c\u093e"
    ],
    "name:spa_x_preferred":[
        "Dhaba"
    ],
    "wof:name":"Dhaba",
    "wof:placetype":"locality"
},
  "geometry": {"coordinates":[76.13091,25.15511],"type":"Point"}
}