{
  "type": "Feature",
  "properties": {
    "iso:country":"IN",
    "ks:ks_name":"Aribhanga Gaon",
    "ks:ks_pop":439,
    "ks:ks_type":"VILLAGE",
    "name:eng_x_preferred":[
        "Aribhanga Gaon"
    ],
    "wof:name":"Aribhanga Gaon",
    "wof:placetype":"locality",
    "wof:population":439
},
  "geometry": {"coordinates":[93.44953,26.831882],"type":"Point"}
}