{
  "type": "Feature",
  "properties": {
    "iso:country":"IN",
    "ks:ks_name":"Joyrampur",
    "ks:ks_pop":976,
    "ks:ks_type":"VILLAGE",
    "ks:ks_uagg_main":0,
    "name:eng_x_preferred":[
        "Joyrampur"
    ],
    "wof:name":"Joyrampur",
    "wof:placetype":"neighbourhood",
    "wof:population":976
},
  "geometry": {"coordinates":[87.293539,21.99478],"type":"Point"}
}