{
  "type": "Feature",
  "properties": {
    "iso:country":"IN",
    "ks:ks_name":"Boldih",
    "ks:ks_pop":27,
    "ks:ks_type":"VILLAGE",
    "name:eng_x_preferred":[
        "Boldih"
    ],
    "wof:name":"Boldih",
    "wof:placetype":"locality",
    "wof:population":27
},
  "geometry": {"coordinates":[87.49502699999999,24.663743],"type":"Point"}
}