{
  "type": "Feature",
  "properties": {
    "iso:country":"IN",
    "ks:ks_name":"Kathal Guri",
    "ks:ks_pop":534,
    "ks:ks_type":"HABITATION",
    "name:eng_x_preferred":[
        "Kathal Guri"
    ],
    "wof:name":"Kathal Guri",
    "wof:placetype":"locality",
    "wof:population":534
},
  "geometry": {"coordinates":[94.669326,27.385644],"type":"Point"}
}