{
  "type": "Feature",
  "properties": {
    "iso:country":"IN",
    "ks:ks_name":"Nettimvaripalli",
    "ks:ks_pop":34,
    "ks:ks_type":"HABITATION",
    "name:eng_x_preferred":[
        "Nettimvaripalli"
    ],
    "wof:name":"Nettimvaripalli",
    "wof:placetype":"locality",
    "wof:population":34
},
  "geometry": {"coordinates":[79.201402,14.099924],"type":"Point"}
}