{
  "type": "Feature",
  "properties": {
    "iso:country":"IN",
    "ks:ks_name":"Pathrudwadi",
    "ks:ks_pop":230,
    "ks:ks_type":"HABITATION",
    "name:eng_x_preferred":[
        "Pathrudwadi"
    ],
    "wof:name":"Pathrudwadi",
    "wof:placetype":"locality",
    "wof:population":230
},
  "geometry": {"coordinates":[76.18938900000001,18.247894],"type":"Point"}
}