{
  "type": "Feature",
  "properties": {
    "iso:country":"IN",
    "ks:ks_name":"Anandanagar",
    "ks:ks_pop":9969,
    "ks:ks_type":"URBAN",
    "ks:ks_uagg_main":0,
    "name:eng_x_preferred":[
        "Anandanagar"
    ],
    "wof:name":"Anandanagar",
    "wof:placetype":"locality",
    "wof:population":9969
},
  "geometry": {"coordinates":[91.32884,23.79865],"type":"Point"}
}