{
  "type": "Feature",
  "properties": {
    "iso:country":"IN",
    "ks:ks_name":"Pachhmi Tola",
    "ks:ks_pop":1349,
    "ks:ks_type":"HABITATION",
    "name:eng_x_preferred":[
        "Pachhmi Tola"
    ],
    "wof:name":"Pachhmi Tola",
    "wof:placetype":"locality",
    "wof:population":1349
},
  "geometry": {"coordinates":[85.6913,25.98325],"type":"Point"}
}