{
  "type": "Feature",
  "properties": {
    "iso:country":"IN",
    "ks:ks_name":"Dher Ki Madhiayan",
    "ks:ks_pop":660,
    "ks:ks_type":"HABITATION",
    "name:eng_x_preferred":[
        "Dher Ki Madhiayan"
    ],
    "wof:name":"Dher Ki Madhiayan",
    "wof:placetype":"locality",
    "wof:population":660
},
  "geometry": {"coordinates":[77.795726,28.531035],"type":"Point"}
}