{
  "type": "Feature",
  "properties": {
    "gn:admin1_code":"24.0",
    "gn:admin2_code":"107",
    "gn:asciiname":"Dhawan",
    "gn:country_code":"IN",
    "gn:dem":259,
    "gn:feature_class":"P",
    "gn:feature_code":"PPL",
    "gn:name":"Dhaw\u0101n",
    "gn:population":0,
    "gn:timezone":"Asia/Kolkata",
    "iso:country":"IN",
    "name:und_x_variant":[
        "Dhaw\u0101n",
        "Dhwain"
    ],
    "wof:name":"Dhawan",
    "wof:placetype":"locality"
},
  "geometry": {"coordinates":[76.75027,26.79885],"type":"Point"}
}