{
  "type": "Feature",
  "properties": {
    "iso:country":"IN",
    "ks:ks_name":"Trimalpur",
    "ks:ks_pop":91,
    "ks:ks_type":"VILLAGE",
    "ks:ks_uagg_main":0,
    "name:eng_x_preferred":[
        "Trimalpur"
    ],
    "wof:name":"Trimalpur",
    "wof:placetype":"neighbourhood",
    "wof:population":91
},
  "geometry": {"coordinates":[77.788803,21.199703],"type":"Point"}
}