{
  "type": "Feature",
  "properties": {
    "gn:admin1_code":"19.0",
    "gn:admin2_code":"570.0",
    "gn:asciiname":"Chittedlu",
    "gn:country_code":"IN",
    "gn:dem":643,
    "gn:feature_class":"P",
    "gn:feature_code":"PPL",
    "gn:name":"Chittedlu",
    "gn:population":0,
    "gn:timezone":"Asia/Kolkata",
    "iso:country":"IN",
    "ks:ks_name":"Chittehadlu",
    "ks:ks_pop":91,
    "ks:ks_type":"HABITATION",
    "name:eng_x_preferred":[
        "Chittehadlu"
    ],
    "name:eng_x_variant":[
        "Chittedlu"
    ],
    "wof:name":"Chittehadlu",
    "wof:placetype":"locality",
    "wof:population":91
},
  "geometry": {"coordinates":[75.250135,13.544906],"type":"Point"}
}