{
  "type": "Feature",
  "properties": {
    "gn:admin1_code":"37",
    "gn:admin2_code":"405.0",
    "gn:asciiname":"Churia",
    "gn:country_code":"IN",
    "gn:dem":250,
    "gn:feature_class":"P",
    "gn:feature_code":"PPL",
    "gn:name":"Churia",
    "gn:population":0,
    "gn:timezone":"Asia/Kolkata",
    "iso:country":"IN",
    "name:ceb_x_preferred":[
        "Churia"
    ],
    "name:swe_x_preferred":[
        "Churia"
    ],
    "name:war_x_preferred":[
        "Churia"
    ],
    "wof:name":"Churia",
    "wof:placetype":"locality"
},
  "geometry": {"coordinates":[82.77678,21.96298],"type":"Point"}
}