{
  "type": "Feature",
  "properties": {
    "iso:country":"IN",
    "ks:ks_name":"Mahulpanga",
    "ks:ks_pop":526,
    "ks:ks_type":"VILLAGE",
    "name:eng_x_preferred":[
        "Mahulpanga"
    ],
    "wof:name":"Mahulpanga",
    "wof:placetype":"locality",
    "wof:population":526
},
  "geometry": {"coordinates":[85.77085099999999,21.206152],"type":"Point"}
}