{
  "type": "Feature",
  "properties": {
    "iso:country":"IN",
    "ks:ks_name":"Tal Suhela",
    "ks:ks_pop":0,
    "ks:ks_type":"VILLAGE",
    "name:eng_x_preferred":[
        "Tal Suhela"
    ],
    "wof:name":"Tal Suhela",
    "wof:placetype":"locality",
    "wof:population":0
},
  "geometry": {"coordinates":[79.27149199999999,27.199517],"type":"Point"}
}