{
  "type": "Feature",
  "properties": {
    "gn:country":"IN",
    "gn:fcode":"PPL",
    "gn:pop":21828,
    "iso:country":"IN",
    "name:rus_x_preferred":[
        "\u0421\u0438\u043b\u0430\u043e"
    ],
    "name:unk_x_variant":[
        "Vikramasila"
    ],
    "qs:name":"Silao",
    "qs:name_adm0":"India",
    "qs:name_adm1":"Bihar",
    "qs:photos":91,
    "qs:photos_1k":18,
    "qs:photos_9k":1,
    "qs:photos_9r":3,
    "qs:photos_all":91,
    "qs:photos_sr":3,
    "qs:placetype":"Town",
    "qs:pop_sr":"7",
    "wd:elevation":1780.0,
    "wd:wordcount":1053,
    "wof:name":"Silao",
    "wof:placetype":"locality",
    "wof:population":21828
},
  "geometry": {"coordinates":[85.42782,25.08317],"type":"Point"}
}