{
  "type": "Feature",
  "properties": {
    "iso:country":"IN",
    "ks:ks_name":"Kahansewasti",
    "ks:ks_pop":150,
    "ks:ks_type":"HABITATION",
    "name:eng_x_preferred":[
        "Kahansewasti"
    ],
    "wof:name":"Kahansewasti",
    "wof:placetype":"locality",
    "wof:population":150
},
  "geometry": {"coordinates":[75.23466500000001,17.917603],"type":"Point"}
}