{
  "type": "Feature",
  "properties": {
    "gn:admin1_code":"35.0",
    "gn:admin2_code":"444.0",
    "gn:asciiname":"Arjunkhedi",
    "gn:country_code":"IN",
    "gn:dem":436,
    "gn:feature_class":"P",
    "gn:feature_code":"PPL",
    "gn:name":"Arjunkhedi",
    "gn:population":0,
    "gn:timezone":"Asia/Kolkata",
    "iso:country":"IN",
    "wof:name":"Arjunkhedi",
    "wof:placetype":"locality"
},
  "geometry": {"coordinates":[77.59359000000001,23.7275],"type":"Point"}
}