{
  "type": "Feature",
  "properties": {
    "iso:country":"IN",
    "ks:ks_name":"Ambogam",
    "ks:ks_pop":31,
    "ks:ks_type":"HABITATION",
    "name:eng_x_preferred":[
        "Ambogam"
    ],
    "wof:name":"Ambogam",
    "wof:placetype":"locality",
    "wof:population":31
},
  "geometry": {"coordinates":[84.421122,18.834448],"type":"Point"}
}