{
  "type": "Feature",
  "properties": {
    "gn:admin1_code":"36",
    "gn:admin2_code":"152.0",
    "gn:asciiname":"Mukandpur",
    "gn:country_code":"IN",
    "gn:dem":153,
    "gn:feature_class":"P",
    "gn:feature_code":"PPL",
    "gn:name":"Mukandpur",
    "gn:population":0,
    "gn:timezone":"Asia/Kolkata",
    "iso:country":"IN",
    "name:pan_x_preferred":[
        "\u0a2e\u0a41\u0a15\u0a70\u0a26\u0a2a\u0a41\u0a30"
    ],
    "wof:name":"Mukandpur",
    "wof:placetype":"locality"
},
  "geometry": {"coordinates":[79.75445999999999,27.90294],"type":"Point"}
}