{
  "type": "Feature",
  "properties": {
    "iso:country":"IN",
    "ks:ks_name":"Laljuri Bazar",
    "ks:ks_pop":110,
    "ks:ks_type":"HABITATION",
    "name:eng_x_preferred":[
        "Laljuri Bazar"
    ],
    "wof:name":"Laljuri Bazar",
    "wof:placetype":"locality",
    "wof:population":110
},
  "geometry": {"coordinates":[92.198044,24.111965],"type":"Point"}
}