{
  "type": "Feature",
  "properties": {
    "iso:country":"IN",
    "ks:ks_alt_nam":"7 SRW",
    "ks:ks_name":"7 Srw",
    "ks:ks_pop":23,
    "ks:ks_type":"HABITATION",
    "name:eng_x_preferred":[
        "7 Srw"
    ],
    "wof:name":"7 Srw",
    "wof:placetype":"locality",
    "wof:population":23
},
  "geometry": {"coordinates":[74.527624,29.559985],"type":"Point"}
}