{
  "type": "Feature",
  "properties": {
    "iso:country":"IN",
    "ks:ks_name":"Baluapura",
    "ks:ks_pop":790,
    "ks:ks_type":"HABITATION",
    "name:eng_x_preferred":[
        "Baluapura"
    ],
    "wof:name":"Baluapura",
    "wof:placetype":"locality",
    "wof:population":790
},
  "geometry": {"coordinates":[76.773197,26.241993],"type":"Point"}
}