{
  "type": "Feature",
  "properties": {
    "iso:country":"IN",
    "ks:ks_name":"S Vellimala",
    "ks:ks_pop":335,
    "ks:ks_type":"HABITATION",
    "name:eng_x_preferred":[
        "S Vellimala"
    ],
    "wof:name":"S Vellimala",
    "wof:placetype":"locality",
    "wof:population":335
},
  "geometry": {"coordinates":[77.158872,9.710293],"type":"Point"}
}