{
  "type": "Feature",
  "properties": {
    "iso:country":"IN",
    "ks:ks_name":"Chiurgudapara",
    "ks:ks_pop":30,
    "ks:ks_type":"HABITATION",
    "name:eng_x_preferred":[
        "Chiurgudapara"
    ],
    "wof:name":"Chiurgudapara",
    "wof:placetype":"locality",
    "wof:population":30
},
  "geometry": {"coordinates":[81.895905,19.14073],"type":"Point"}
}