{
  "type": "Feature",
  "properties": {
    "iso:country":"IN",
    "ks:ks_name":"Indira Nagari",
    "ks:ks_pop":343,
    "ks:ks_type":"HABITATION",
    "name:eng_x_preferred":[
        "Indira Nagari"
    ],
    "wof:name":"Indira Nagari",
    "wof:placetype":"locality",
    "wof:population":343
},
  "geometry": {"coordinates":[74.235694,22.743722],"type":"Point"}
}