{
  "type": "Feature",
  "properties": {
    "gn:admin1_code":"2.0",
    "gn:admin2_code":"549.0",
    "gn:asciiname":"Sivaramapuram",
    "gn:country_code":"IN",
    "gn:dem":54,
    "gn:feature_class":"P",
    "gn:feature_code":"PPL",
    "gn:name":"Sivar\u0101mapuram",
    "gn:population":0,
    "gn:timezone":"Asia/Kolkata",
    "iso:country":"IN",
    "name:tel_x_preferred":[
        "\u0c36\u0c3f\u0c35\u0c30\u0c3e\u0c2e\u0c2a\u0c41\u0c30\u0c02"
    ],
    "name:urd_x_preferred":[
        "\u0633\u0648\u0627\u0631\u0627\u0645\u0627\u067e\u0648\u0631\u0645"
    ],
    "wof:name":"Sivaramapuram",
    "wof:placetype":"locality"
},
  "geometry": {"coordinates":[79.89277,15.70007],"type":"Point"}
}