{
  "type": "Feature",
  "properties": {
    "iso:country":"IN",
    "ks:ks_name":"Hojaigaon",
    "ks:ks_pop":518,
    "ks:ks_type":"VILLAGE",
    "ks:ks_uagg_main":0,
    "name:eng_x_preferred":[
        "Hojaigaon"
    ],
    "wof:name":"Hojaigaon",
    "wof:placetype":"neighbourhood",
    "wof:population":518
},
  "geometry": {"coordinates":[92.582247,26.637255],"type":"Point"}
}