{
  "type": "Feature",
  "properties": {
    "iso:country":"IN",
    "ks:ks_name":"Khodiyarnagar",
    "ks:ks_pop":211,
    "ks:ks_type":"HABITATION",
    "name:eng_x_preferred":[
        "Khodiyarnagar"
    ],
    "wof:name":"Khodiyarnagar",
    "wof:placetype":"locality",
    "wof:population":211
},
  "geometry": {"coordinates":[71.586293,24.159074],"type":"Point"}
}