{
  "type": "Feature",
  "properties": {
    "iso:country":"IN",
    "ks:ks_name":"Gopalapuram",
    "ks:ks_pop":132,
    "ks:ks_type":"VILLAGE",
    "ks:ks_uagg_main":0,
    "name:eng_x_preferred":[
        "Gopalapuram"
    ],
    "wof:name":"Gopalapuram",
    "wof:placetype":"neighbourhood",
    "wof:population":132
},
  "geometry": {"coordinates":[79.31693300000001,10.51466],"type":"Point"}
}