{
  "type": "Feature",
  "properties": {
    "gn:admin1_code":"25.0",
    "gn:admin2_code":"607.0",
    "gn:asciiname":"Vadataram",
    "gn:country_code":"IN",
    "gn:dem":66,
    "gn:feature_class":"P",
    "gn:feature_code":"PPL",
    "gn:name":"Vadataram",
    "gn:population":0,
    "gn:timezone":"Asia/Kolkata",
    "iso:country":"IN",
    "ks:ks_name":"Vadataram",
    "ks:ks_pop":481,
    "ks:ks_type":"VILLAGE",
    "ks:ks_uagg_main":0,
    "name:eng_x_preferred":[
        "Vadataram"
    ],
    "wof:name":"Vadataram",
    "wof:placetype":"neighbourhood",
    "wof:population":481
},
  "geometry": {"coordinates":[79.475365,12.185699],"type":"Point"}
}