{
  "type": "Feature",
  "properties": {
    "gn:admin1_code":"36.0",
    "gn:admin2_code":"184.0",
    "gn:asciiname":"Uski",
    "gn:country_code":"IN",
    "gn:dem":91,
    "gn:feature_class":"P",
    "gn:feature_code":"PPL",
    "gn:name":"Uski",
    "gn:population":0,
    "gn:timezone":"Asia/Kolkata",
    "iso:country":"IN",
    "ks:ks_name":"Uski",
    "ks:ks_pop":452,
    "ks:ks_type":"VILLAGE",
    "name:eng_x_preferred":[
        "Uski"
    ],
    "wof:name":"Uski",
    "wof:placetype":"locality",
    "wof:population":452
},
  "geometry": {"coordinates":[82.94883,27.124823],"type":"Point"}
}