{
  "type": "Feature",
  "properties": {
    "gn:admin1_code":"36.0",
    "gn:admin2_code":"184.0",
    "gn:asciiname":"Uski",
    "gn:country_code":"IN",
    "gn:dem":91,
    "gn:feature_class":"P",
    "gn:feature_code":"PPL",
    "gn:name":"Uski",
    "gn:population":0,
    "gn:timezone":"Asia/Kolkata",
    "iso:country":"IN",
    "wof:name":"Uski",
    "wof:placetype":"locality"
},
  "geometry": {"coordinates":[82.95073000000002,27.11894],"type":"Point"}
}