{
  "type": "Feature",
  "properties": {
    "iso:country":"IN",
    "ks:ks_name":"Deurpur",
    "ks:ks_pop":881,
    "ks:ks_type":"VILLAGE",
    "ks:ks_uagg_main":0,
    "name:eng_x_preferred":[
        "Deurpur"
    ],
    "wof:name":"Deurpur",
    "wof:placetype":"neighbourhood",
    "wof:population":881
},
  "geometry": {"coordinates":[83.037502,26.249796],"type":"Point"}
}