{
  "type": "Feature",
  "properties": {
    "gn:admin1_code":"36",
    "gn:admin2_code":"157.0",
    "gn:asciiname":"Baburia",
    "gn:country_code":"IN",
    "gn:dem":129,
    "gn:feature_class":"P",
    "gn:feature_code":"PPL",
    "gn:name":"Baburi\u0101",
    "gn:population":0,
    "gn:timezone":"Asia/Kolkata",
    "iso:country":"IN",
    "name:ceb_x_preferred":[
        "Baburia"
    ],
    "name:swe_x_preferred":[
        "Baburia"
    ],
    "name:vie_x_preferred":[
        "Baburia"
    ],
    "name:war_x_preferred":[
        "Baburia"
    ],
    "wof:name":"Baburia",
    "wof:placetype":"neighbourhood"
},
  "geometry": {"coordinates":[80.70264,27.03537],"type":"Point"}
}