{
  "type": "Feature",
  "properties": {
    "gn:admin1_code":"34.0",
    "gn:admin2_code":"230.0",
    "gn:asciiname":"Lakha Chak",
    "gn:country_code":"IN",
    "gn:dem":48,
    "gn:feature_class":"P",
    "gn:feature_code":"PPL",
    "gn:name":"Lakha Chak",
    "gn:population":0,
    "gn:timezone":"Asia/Kolkata",
    "iso:country":"IN",
    "wof:name":"Lakha Chak",
    "wof:placetype":"locality"
},
  "geometry": {"coordinates":[85.68221,25.36856],"type":"Point"}
}