{
  "type": "Feature",
  "properties": {
    "iso:country":"IN",
    "ks:ks_name":"Pinachanda",
    "ks:ks_pop":209,
    "ks:ks_type":"VILLAGE",
    "name:eng_x_preferred":[
        "Pinachanda"
    ],
    "wof:name":"Pinachanda",
    "wof:placetype":"locality",
    "wof:population":209
},
  "geometry": {"coordinates":[81.007553,18.178164],"type":"Point"}
}