{
  "type": "Feature",
  "properties": {
    "iso:country":"IN",
    "ks:ks_name":"Purohitpur",
    "ks:ks_pop":566,
    "ks:ks_type":"VILLAGE",
    "ks:ks_uagg_main":0,
    "name:eng_x_preferred":[
        "Purohitpur"
    ],
    "wof:name":"Purohitpur",
    "wof:placetype":"neighbourhood",
    "wof:population":566
},
  "geometry": {"coordinates":[85.818641,19.991713],"type":"Point"}
}