{
  "type": "Feature",
  "properties": {
    "iso:country":"IN",
    "name:ara_x_preferred":[
        "\u0633\u0646\u062c\u0627\u0631 \u0628\u0648\u0631\u0627\u0645"
    ],
    "name:ben_bn_x_preferred":[
        "\u09b8\u09bf\u0999\u09cd\u0997\u09be\u09b0\u09aa\u09c1\u09b0\u09ae"
    ],
    "name:ben_in_x_preferred":[
        "\u09b8\u09bf\u0999\u09cd\u0997\u09be\u09b0\u09aa\u09c1\u09b0\u09ae"
    ],
    "name:eng_x_preferred":[
        "Singarpuram"
    ],
    "name:guj_x_preferred":[
        "\u0ab8\u0abf\u0a82\u0a97\u0abe\u0aaa\u0ac1\u0ab0\u0aae"
    ],
    "name:hin_x_preferred":[
        "\u0938\u093f\u0902\u0917\u093e\u0930\u092a\u0941\u0930\u092e"
    ],
    "name:kan_x_preferred":[
        "\u0cb8\u0cbf\u0c82\u0c97\u0cbe\u0cb0\u0caa\u0cc1\u0cb0\u0c82"
    ],
    "name:mal_x_preferred":[
        "\u0d38\u0d3f\u0d02\u0d17\u0d7c\u0d2a\u0d41\u0d30\u0d02"
    ],
    "name:mar_x_preferred":[
        "\u0938\u093f\u0902\u0917\u093e\u0930\u092a\u0941\u0930\u092e"
    ],
    "name:pan_x_preferred":[
        "\u0a38\u0a3f\u0a70\u0a17\u0a30\u0a2a\u0a41\u0a30\u0a2e"
    ],
    "name:tam_x_preferred":[
        "\u0b9a\u0bbf\u0b99\u0bcd\u0b95\u0bb0\u0bcd\u0baa\u0bc1\u0bb0\u0bae\u0bcd"
    ],
    "name:tel_x_preferred":[
        "\u0c38\u0c3f\u0c02\u0c17\u0c3e\u0c30\u0c4d"
    ],
    "name:urd_x_preferred":[
        "\u0633\u0646\u06af\u0631 \u067e\u0648\u0631\u0645"
    ],
    "qs:gn_adm0_cc":"IN",
    "qs:gn_local":1264521,
    "qs:gn_nam_loc":"Madurai, Madurai, Tamil Nadu, IN",
    "qs:gn_namadm1":"25",
    "qs:local_max":1568,
    "qs:local_sum":2851,
    "qs:localhoods":8,
    "qs:name":"Singarpuram",
    "qs:name_adm0":"India",
    "qs:name_adm1":"Tamil Nadu",
    "qs:name_adm2":"Madurai",
    "qs:name_local":"Madurai",
    "qs:photo_max":22,
    "qs:photo_sum":38,
    "qs:placetype":"Suburb",
    "qs:quad_count":4,
    "qs:woe_adm0":23424848,
    "qs:woe_adm1":2345758,
    "qs:woe_adm2":12586687,
    "qs:woe_lau":0,
    "qs:woe_local":2295425,
    "qs:woe_ver":"7.10.0",
    "wof:lang":[
        "eng"
    ],
    "wof:name":"Singarpuram",
    "wof:placetype":"neighbourhood"
},
  "geometry": {"coordinates":[78.10942799999999,9.918734],"type":"Point"}
}