{
  "type": "Feature",
  "properties": {
    "gn:admin1_code":"39.0",
    "gn:admin2_code":"64.0",
    "gn:asciiname":"Talli Chanoli",
    "gn:country_code":"IN",
    "gn:dem":1343,
    "gn:feature_class":"P",
    "gn:feature_code":"PPL",
    "gn:name":"Talli Chanoli",
    "gn:population":0,
    "gn:timezone":"Asia/Kolkata",
    "iso:country":"IN",
    "wof:name":"Talli Chanoli",
    "wof:placetype":"locality"
},
  "geometry": {"coordinates":[79.14884000000001,29.8535],"type":"Point"}
}