{
  "type": "Feature",
  "properties": {
    "gn:admin1_code":"35",
    "gn:admin2_code":"455.0",
    "gn:asciiname":"Khoraimau",
    "gn:country_code":"IN",
    "gn:dem":950,
    "gn:feature_class":"P",
    "gn:feature_code":"PPL",
    "gn:name":"Khoraimau",
    "gn:population":0,
    "gn:timezone":"Asia/Kolkata",
    "iso:country":"IN",
    "wof:name":"Khoraimau",
    "wof:placetype":"locality"
},
  "geometry": {"coordinates":[78.37494000000002,22.22981],"type":"Point"}
}