{
  "type": "Feature",
  "properties": {
    "iso:country":"IN",
    "ks:ks_alt_nam":"Pucca line",
    "ks:ks_name":"Pucca Line",
    "ks:ks_pop":604,
    "ks:ks_type":"HABITATION",
    "ks:ks_uagg_main":0,
    "name:eng_x_preferred":[
        "Pucca Line"
    ],
    "wof:name":"Pucca Line",
    "wof:placetype":"neighbourhood",
    "wof:population":604
},
  "geometry": {"coordinates":[94.368565,26.671005],"type":"Point"}
}