{
  "type": "Feature",
  "properties": {
    "gn:admin1_code":"36",
    "gn:admin2_code":"144.0",
    "gn:asciiname":"Purdilnagar",
    "gn:country_code":"IN",
    "gn:dem":181,
    "gn:feature_class":"P",
    "gn:feature_code":"PPL",
    "gn:name":"Purdilnagar",
    "gn:population":0,
    "gn:timezone":"Asia/Kolkata",
    "iso:country":"IN",
    "name:bpy_x_preferred":[
        "\u09aa\u09c1\u09b0\u09a6\u09bf\u09b2\u09a8\u0997\u09b0"
    ],
    "name:fas_x_preferred":[
        "\u067e\u0631\u062f\u0644\u200c\u0646\u06af\u0631"
    ],
    "name:ita_x_preferred":[
        "Purdilnagar"
    ],
    "name:msa_x_preferred":[
        "Purdilnagar"
    ],
    "name:nld_x_preferred":[
        "Purdilnagar"
    ],
    "name:pol_x_preferred":[
        "Purdilnagar"
    ],
    "name:por_x_preferred":[
        "Purdilnagar"
    ],
    "name:urd_x_preferred":[
        "\u067e\u0631\u062f\u06cc\u0644 \u0646\u06af\u0631"
    ],
    "name:vie_x_preferred":[
        "Purdilnagar"
    ],
    "name:zho_x_preferred":[
        "\u666e\u5c14\u8fea\u5c14\u7eb3\u52a0\u5c14"
    ],
    "wof:name":"Purdilnagar",
    "wof:placetype":"locality"
},
  "geometry": {"coordinates":[78.36960999999999,27.65764],"type":"Point"}
}