{
  "type": "Feature",
  "properties": {
    "iso:country":"IN",
    "ks:ks_alt_nam":"Adenkila palke",
    "ks:ks_name":"Adenkila Palke",
    "ks:ks_pop":503,
    "ks:ks_type":"HABITATION",
    "name:eng_x_preferred":[
        "Adenkila Palke"
    ],
    "wof:name":"Adenkila Palke",
    "wof:placetype":"locality",
    "wof:population":503
},
  "geometry": {"coordinates":[75.273112,12.870757],"type":"Point"}
}