{
  "type": "Feature",
  "properties": {
    "iso:country":"IN",
    "ks:ks_name":"Diyara Bhagar",
    "ks:ks_pop":1005,
    "ks:ks_type":"VILLAGE",
    "name:eng_x_preferred":[
        "Diyara Bhagar"
    ],
    "wof:name":"Diyara Bhagar",
    "wof:placetype":"locality",
    "wof:population":1005
},
  "geometry": {"coordinates":[84.34093799999999,25.934343],"type":"Point"}
}