{
  "type": "Feature",
  "properties": {
    "iso:country":"IN",
    "ks:ks_name":"N.bich",
    "ks:ks_pop":700,
    "ks:ks_type":"HABITATION",
    "ks:ks_uagg_main":0,
    "name:eng_x_preferred":[
        "N.bich"
    ],
    "wof:name":"N.bich",
    "wof:placetype":"neighbourhood",
    "wof:population":700
},
  "geometry": {"coordinates":[78.323221,27.316127],"type":"Point"}
}