{
  "type": "Feature",
  "properties": {
    "gn:admin1_code":"36",
    "gn:admin2_code":"191.0",
    "gn:asciiname":"Thatha",
    "gn:country_code":"IN",
    "gn:dem":82,
    "gn:feature_class":"P",
    "gn:feature_code":"PPL",
    "gn:name":"Th\u0101tha",
    "gn:population":0,
    "gn:timezone":"Asia/Kolkata",
    "iso:country":"IN",
    "name:und_x_variant":[
        "Th\u0101tha",
        "Dayam"
    ],
    "wof:name":"Thatha",
    "wof:placetype":"locality"
},
  "geometry": {"coordinates":[83.26231999999997,25.78296],"type":"Point"}
}