{
  "type": "Feature",
  "properties": {
    "iso:country":"IN",
    "ks:ks_name":"Loyongkel",
    "ks:ks_pop":692,
    "ks:ks_type":"VILLAGE",
    "ks:ks_uagg_main":0,
    "name:eng_x_preferred":[
        "Loyongkel"
    ],
    "wof:name":"Loyongkel",
    "wof:placetype":"neighbourhood",
    "wof:population":692
},
  "geometry": {"coordinates":[85.12208099999999,23.117511],"type":"Point"}
}