{
  "type": "Feature",
  "properties": {
    "iso:country":"IN",
    "ks:ks_name":"Isakagaruvu",
    "ks:ks_pop":65,
    "ks:ks_type":"HABITATION",
    "name:eng_x_preferred":[
        "Isakagaruvu"
    ],
    "wof:name":"Isakagaruvu",
    "wof:placetype":"locality",
    "wof:population":65
},
  "geometry": {"coordinates":[82.73289,17.995067],"type":"Point"}
}