{
  "type": "Feature",
  "properties": {
    "iso:country":"IN",
    "ks:ks_name":"7 SJM-B",
    "ks:ks_pop":129,
    "ks:ks_type":"VILLAGE",
    "name:eng_x_preferred":[
        "7 SJM-B"
    ],
    "wof:name":"7 SJM-B",
    "wof:placetype":"locality",
    "wof:population":129
},
  "geometry": {"coordinates":[73.30278199999999,29.333209],"type":"Point"}
}