{
  "type": "Feature",
  "properties": {
    "gn:admin1_code":"39",
    "gn:admin2_code":"61.0",
    "gn:asciiname":"Dobri",
    "gn:country_code":"IN",
    "gn:dem":912,
    "gn:feature_class":"P",
    "gn:feature_code":"PPL",
    "gn:name":"Dobri",
    "gn:population":0,
    "gn:timezone":"Asia/Kolkata",
    "iso:country":"IN",
    "wof:name":"Dobri",
    "wof:placetype":"locality"
},
  "geometry": {"coordinates":[78.49366999999999,29.99576],"type":"Point"}
}