{
  "type": "Feature",
  "properties": {
    "gn:admin1_code":"19.0",
    "gn:admin2_code":"584.0",
    "gn:asciiname":"Chikmaskallu",
    "gn:country_code":"IN",
    "gn:dem":872,
    "gn:feature_class":"P",
    "gn:feature_code":"PPL",
    "gn:name":"Chikmaskallu",
    "gn:population":0,
    "gn:timezone":"Asia/Kolkata",
    "iso:country":"IN",
    "wof:name":"Chikmaskallu",
    "wof:placetype":"neighbourhood"
},
  "geometry": {"coordinates":[77.17747,13.17865],"type":"Point"}
}