{
  "type": "Feature",
  "properties": {
    "gn:admin1_code":"24",
    "gn:admin2_code":"104.0",
    "gn:asciiname":"Badhin",
    "gn:country_code":"IN",
    "gn:dem":314,
    "gn:feature_class":"P",
    "gn:feature_code":"PPL",
    "gn:name":"Badhin",
    "gn:population":0,
    "gn:timezone":"Asia/Kolkata",
    "iso:country":"IN",
    "wof:name":"Badhin",
    "wof:placetype":"locality"
},
  "geometry": {"coordinates":[76.37368000000002,27.84516],"type":"Point"}
}