{
  "type": "Feature",
  "properties": {
    "gn:admin1_code":"35",
    "gn:admin2_code":"423.0",
    "gn:asciiname":"Lakhari",
    "gn:country_code":"IN",
    "gn:dem":414,
    "gn:feature_class":"P",
    "gn:feature_code":"PPL",
    "gn:name":"Lakh\u0101ri",
    "gn:population":0,
    "gn:timezone":"Asia/Kolkata",
    "iso:country":"IN",
    "ks:ks_alt_nam":"Lakh\u0101ri",
    "ks:ks_name":"Lakhari",
    "ks:ks_pop":360,
    "ks:ks_type":"VILLAGE",
    "name:eng_x_preferred":[
        "Lakhari"
    ],
    "name:eng_x_variant":[
        "Lakh\u0101ri"
    ],
    "wof:name":"Lakhari",
    "wof:placetype":"locality",
    "wof:population":360
},
  "geometry": {"coordinates":[78.021962,24.860049],"type":"Point"}
}