{
  "type": "Feature",
  "properties": {
    "iso:country":"IN",
    "ks:ks_name":"Daragedda",
    "ks:ks_pop":14,
    "ks:ks_type":"HABITATION",
    "name:eng_x_preferred":[
        "Daragedda"
    ],
    "wof:name":"Daragedda",
    "wof:placetype":"locality",
    "wof:population":14
},
  "geometry": {"coordinates":[82.820127,18.036813],"type":"Point"}
}