{
  "type": "Feature",
  "properties": {
    "gn:admin1_code":"11",
    "gn:admin2_code":"23.0",
    "gn:asciiname":"Langhauta",
    "gn:country_code":"IN",
    "gn:dem":2250,
    "gn:feature_class":"P",
    "gn:feature_code":"PPL",
    "gn:name":"Langhauta",
    "gn:population":0,
    "gn:timezone":"Asia/Kolkata",
    "iso:country":"IN",
    "wof:name":"Langhauta",
    "wof:placetype":"locality"
},
  "geometry": {"coordinates":[76.40291999999999,32.42871],"type":"Point"}
}