{
  "type": "Feature",
  "properties": {
    "iso:country":"IN",
    "ks:ks_name":"Moolassery",
    "ks:ks_pop":1349,
    "ks:ks_type":"HABITATION",
    "name:eng_x_preferred":[
        "Moolassery"
    ],
    "wof:name":"Moolassery",
    "wof:placetype":"locality",
    "wof:population":1349
},
  "geometry": {"coordinates":[76.44519699999999,9.342893],"type":"Point"}
}