{
  "type": "Feature",
  "properties": {
    "gn:admin1_code":"16.0",
    "gn:admin2_code":"516.0",
    "gn:asciiname":"Jamdari",
    "gn:country_code":"IN",
    "gn:dem":425,
    "gn:feature_class":"P",
    "gn:feature_code":"PPL",
    "gn:name":"J\u0101mdari",
    "gn:population":0,
    "gn:timezone":"Asia/Kolkata",
    "iso:country":"IN",
    "wof:name":"Jamdari",
    "wof:placetype":"locality"
},
  "geometry": {"coordinates":[74.70010000000001,20.40013],"type":"Point"}
}