{
  "type": "Feature",
  "properties": {
    "gn:admin1_code":"21.0",
    "gn:admin2_code":"371.0",
    "gn:asciiname":"Sanyasipali",
    "gn:country_code":"IN",
    "gn:dem":221,
    "gn:feature_class":"P",
    "gn:feature_code":"PPL",
    "gn:name":"Sanyasipali",
    "gn:population":0,
    "gn:timezone":"Asia/Kolkata",
    "iso:country":"IN",
    "wof:name":"Sanyasipali",
    "wof:placetype":"locality"
},
  "geometry": {"coordinates":[84.18835,21.79958],"type":"Point"}
}