{
  "type": "Feature",
  "properties": {
    "iso:country":"IN",
    "ks:ks_name":"Sullipakoni",
    "ks:ks_pop":93,
    "ks:ks_type":"HABITATION",
    "name:eng_x_preferred":[
        "Sullipakoni"
    ],
    "wof:name":"Sullipakoni",
    "wof:placetype":"locality",
    "wof:population":93
},
  "geometry": {"coordinates":[82.925749,18.190694],"type":"Point"}
}