{
  "type": "Feature",
  "properties": {
    "gn:admin1_code":"10.0",
    "gn:admin2_code":"069",
    "gn:asciiname":"Narawala",
    "gn:country_code":"IN",
    "gn:dem":477,
    "gn:feature_class":"P",
    "gn:feature_code":"PPL",
    "gn:name":"Nar\u0101w\u0101la",
    "gn:population":0,
    "gn:timezone":"Asia/Kolkata",
    "iso:country":"IN",
    "wof:name":"Narawala",
    "wof:placetype":"locality"
},
  "geometry": {"coordinates":[76.98893000000002,30.73924],"type":"Point"}
}