{
  "type": "Feature",
  "properties": {
    "gn:admin1_code":"12",
    "gn:admin2_code":"18.0",
    "gn:asciiname":"Metwan",
    "gn:country_code":"IN",
    "gn:dem":2574,
    "gn:feature_class":"P",
    "gn:feature_code":"PPL",
    "gn:name":"M\u0113twan",
    "gn:population":0,
    "gn:timezone":"Asia/Kolkata",
    "iso:country":"IN",
    "name:und_x_variant":[
        "M\u0113twan",
        "Metwan"
    ],
    "wof:name":"Metwan",
    "wof:placetype":"locality"
},
  "geometry": {"coordinates":[75.85214999999999,33.69729],"type":"Point"}
}