{
  "type": "Feature",
  "properties": {
    "iso:country":"IN",
    "ks:ks_name":"Reharwa",
    "ks:ks_pop":480,
    "ks:ks_type":"HABITATION",
    "name:eng_x_preferred":[
        "Reharwa"
    ],
    "wof:name":"Reharwa",
    "wof:placetype":"locality",
    "wof:population":480
},
  "geometry": {"coordinates":[82.492823,27.274562],"type":"Point"}
}