{
  "type": "Feature",
  "properties": {
    "iso:country":"IN",
    "ks:ks_name":"Bhadatoli",
    "ks:ks_pop":295,
    "ks:ks_type":"HABITATION",
    "name:eng_x_preferred":[
        "Bhadatoli"
    ],
    "wof:name":"Bhadatoli",
    "wof:placetype":"locality",
    "wof:population":295
},
  "geometry": {"coordinates":[84.92524400000001,22.933796],"type":"Point"}
}