{
  "type": "Feature",
  "properties": {
    "iso:country":"IN",
    "ks:ks_alt_nam":"Parshika gudem",
    "ks:ks_name":"Parshika Gudem",
    "ks:ks_pop":90,
    "ks:ks_type":"HABITATION",
    "name:eng_x_preferred":[
        "Parshika Gudem"
    ],
    "wof:name":"Parshika Gudem",
    "wof:placetype":"locality",
    "wof:population":90
},
  "geometry": {"coordinates":[80.517689,18.355522],"type":"Point"}
}