{
  "type": "Feature",
  "properties": {
    "gn:admin1_code":"36.0",
    "gn:admin2_code":"153.0",
    "gn:asciiname":"Garatpur",
    "gn:country_code":"IN",
    "gn:dem":160,
    "gn:feature_class":"P",
    "gn:feature_code":"PPL",
    "gn:name":"G\u0101ratpur",
    "gn:population":0,
    "gn:timezone":"Asia/Kolkata",
    "iso:country":"IN",
    "wof:name":"Garatpur",
    "wof:placetype":"neighbourhood"
},
  "geometry": {"coordinates":[80.19664,27.94111],"type":"Point"}
}