{
  "type": "Feature",
  "properties": {
    "iso:country":"IN",
    "ks:ks_name":"Puthur",
    "ks:ks_pop":780,
    "ks:ks_type":"HABITATION",
    "ks:ks_uagg_main":0,
    "name:eng_x_preferred":[
        "Puthur"
    ],
    "wof:name":"Puthur",
    "wof:placetype":"neighbourhood",
    "wof:population":780
},
  "geometry": {"coordinates":[77.583939,8.279519],"type":"Point"}
}