{
  "type": "Feature",
  "properties": {
    "gn:admin1_code":"33",
    "gn:admin2_code":"586.0",
    "gn:asciiname":"Sangod",
    "gn:country_code":"IN",
    "gn:dem":143,
    "gn:feature_class":"P",
    "gn:feature_code":"PPL",
    "gn:name":"Sangod",
    "gn:population":0,
    "gn:timezone":"Asia/Kolkata",
    "iso:country":"IN",
    "name:ben_x_preferred":[
        "\u09b8\u09be\u09a8\u0997\u09cb\u09a6"
    ],
    "name:bpy_x_preferred":[
        "\u09b8\u09be\u09a8\u0997\u09cb\u09a6"
    ],
    "name:ceb_x_preferred":[
        "Sangod"
    ],
    "name:ita_x_preferred":[
        "Sangod"
    ],
    "name:msa_x_preferred":[
        "Sangod"
    ],
    "name:por_x_preferred":[
        "Sangod"
    ],
    "name:swe_x_preferred":[
        "Sangod"
    ],
    "name:vie_x_preferred":[
        "Sangod"
    ],
    "name:zho_x_preferred":[
        "\u6851\u683c\u5965\u5fb7"
    ],
    "wof:name":"Sangod",
    "wof:placetype":"locality"
},
  "geometry": {"coordinates":[74.16667,15.38333],"type":"Point"}
}