{
  "type": "Feature",
  "properties": {
    "gn:admin1_code":"16",
    "gn:admin2_code":"502.0",
    "gn:asciiname":"Mahuli",
    "gn:country_code":"IN",
    "gn:dem":381,
    "gn:feature_class":"P",
    "gn:feature_code":"PPL",
    "gn:name":"M\u0101huli",
    "gn:population":0,
    "gn:timezone":"Asia/Kolkata",
    "iso:country":"IN",
    "name:guj_x_preferred":[
        "\u0aae\u0abe\u0ab9\u0ac1\u0ab2\u0ac0\u0a97\u0aa1"
    ],
    "name:mar_x_preferred":[
        "\u092e\u093e\u0939\u0941\u0932\u0940\u0917\u0921"
    ],
    "wof:name":"Mahuli",
    "wof:placetype":"locality"
},
  "geometry": {"coordinates":[77.59059000000001,20.16593],"type":"Point"}
}