{
  "type": "Feature",
  "properties": {
    "gn:admin1_code":"39",
    "gn:admin2_code":"61.0",
    "gn:asciiname":"Katal",
    "gn:country_code":"IN",
    "gn:dem":887,
    "gn:feature_class":"P",
    "gn:feature_code":"PPL",
    "gn:name":"K\u0101tal",
    "gn:population":0,
    "gn:timezone":"Asia/Kolkata",
    "iso:country":"IN",
    "name:ara_x_preferred":[
        "\u0643\u0627\u062a\u0627\u0644"
    ],
    "name:bel_x_preferred":[
        "\u041a\u0430\u0442\u0430\u043b"
    ],
    "name:bos_x_preferred":[
        "Katal"
    ],
    "name:bul_x_preferred":[
        "\u041a\u0430\u0442\u0430\u043b"
    ],
    "name:cat_x_preferred":[
        "Katal"
    ],
    "name:ces_x_preferred":[
        "Katal"
    ],
    "name:dan_x_preferred":[
        "Katal"
    ],
    "name:deu_x_preferred":[
        "Katal"
    ],
    "name:ell_x_preferred":[
        "\u039a\u03b1\u03c4\u03ac\u03bb"
    ],
    "name:epo_x_preferred":[
        "Katalo"
    ],
    "name:est_x_preferred":[
        "Katal"
    ],
    "name:eus_x_preferred":[
        "Katal"
    ],
    "name:fas_x_preferred":[
        "\u06a9\u0627\u062a\u0627\u0644"
    ],
    "name:fin_x_preferred":[
        "Katal"
    ],
    "name:fra_x_preferred":[
        "Katal"
    ],
    "name:hrv_x_preferred":[
        "Katal"
    ],
    "name:hye_x_preferred":[
        "\u053f\u0561\u057f\u0561\u056c"
    ],
    "name:ita_x_preferred":[
        "Katal"
    ],
    "name:jpn_x_preferred":[
        "\u30ab\u30bf\u30fc\u30eb"
    ],
    "name:lav_x_preferred":[
        "Katals"
    ],
    "name:lit_x_preferred":[
        "Katalas"
    ],
    "name:mkd_x_preferred":[
        "\u041a\u0430\u0442\u0430\u043b"
    ],
    "name:mon_x_preferred":[
        "\u041a\u0430\u0442\u0430\u043b"
    ],
    "name:nld_x_preferred":[
        "Katal"
    ],
    "name:nno_x_preferred":[
        "Katal"
    ],
    "name:nor_x_preferred":[
        "Katal"
    ],
    "name:pol_x_preferred":[
        "Katal"
    ],
    "name:por_x_preferred":[
        "Katal"
    ],
    "name:ron_x_preferred":[
        "Katal"
    ],
    "name:rus_x_preferred":[
        "\u041a\u0430\u0442\u0430\u043b"
    ],
    "name:scn_x_preferred":[
        "Katal"
    ],
    "name:slk_x_preferred":[
        "Katal"
    ],
    "name:slv_x_preferred":[
        "Katal"
    ],
    "name:spa_x_preferred":[
        "Katal"
    ],
    "name:srp_x_preferred":[
        "\u041a\u0430\u0442\u0430\u043b"
    ],
    "name:swe_x_preferred":[
        "Katal"
    ],
    "name:tha_x_preferred":[
        "\u0e04\u0e32\u0e17\u0e31\u0e25"
    ],
    "name:ukr_x_preferred":[
        "\u041a\u0430\u0442\u0430\u043b"
    ],
    "name:vie_x_preferred":[
        "Katal"
    ],
    "wof:name":"Katal",
    "wof:placetype":"locality"
},
  "geometry": {"coordinates":[78.37017,29.92385],"type":"Point"}
}