{
  "type": "Feature",
  "properties": {
    "iso:country":"IN",
    "ks:ks_name":"6 DOL-B",
    "ks:ks_pop":177,
    "ks:ks_type":"VILLAGE",
    "name:eng_x_preferred":[
        "6 DOL-B"
    ],
    "wof:name":"6 DOL-B",
    "wof:placetype":"locality",
    "wof:population":177
},
  "geometry": {"coordinates":[72.821381,28.847692],"type":"Point"}
}