{
  "type": "Feature",
  "properties": {
    "gn:admin1_code":"2",
    "gn:admin2_code":"547.0",
    "gn:asciiname":"Bhujabalapatnam",
    "gn:country_code":"IN",
    "gn:dem":5,
    "gn:feature_class":"P",
    "gn:feature_code":"PPL",
    "gn:name":"Bhujabalapatnam",
    "gn:population":0,
    "gn:timezone":"Asia/Kolkata",
    "iso:country":"IN",
    "name:hin_x_preferred":[
        "\u092d\u0941\u091c\u092c\u0932\u092a\u091f\u094d\u0928\u0902"
    ],
    "name:new_x_preferred":[
        "\u092d\u0941\u091c\u092c\u0932\u092a\u091f\u094d\u0928\u0902"
    ],
    "name:tat_x_preferred":[
        "\u0411\u04bb\u0443\u0434\u0436\u0430\u0431\u0430\u043b\u0430\u043f\u0430\u0442\u043d\u0430\u043c"
    ],
    "name:tel_x_preferred":[
        "\u0c2d\u0c41\u0c1c\u0c2c\u0c32\u0c2a\u0c1f\u0c4d\u0c28\u0c02"
    ],
    "name:urd_x_preferred":[
        "\u0628\u06be\u062c\u0628\u0644\u0627\u067e\u0679\u0646\u0645"
    ],
    "wof:name":"Bhujabalapatnam",
    "wof:placetype":"locality"
},
  "geometry": {"coordinates":[81.27163,16.57718],"type":"Point"}
}