{
  "type": "Feature",
  "properties": {
    "iso:country":"IN",
    "ks:ks_alt_nam":"S R Kandriga YC",
    "ks:ks_name":"S R Kandriga Yc",
    "ks:ks_pop":189,
    "ks:ks_type":"HABITATION",
    "name:eng_x_preferred":[
        "S R Kandriga Yc"
    ],
    "wof:name":"S R Kandriga Yc",
    "wof:placetype":"locality",
    "wof:population":189
},
  "geometry": {"coordinates":[79.77587,13.344377],"type":"Point"}
}