{
  "type": "Feature",
  "properties": {
    "gn:admin1_code":"35",
    "gn:admin2_code":"421.0",
    "gn:asciiname":"Barka",
    "gn:country_code":"IN",
    "gn:dem":175,
    "gn:feature_class":"P",
    "gn:feature_code":"PPL",
    "gn:name":"Barka",
    "gn:population":0,
    "gn:timezone":"Asia/Kolkata",
    "iso:country":"IN",
    "name:bos_x_preferred":[
        "Barka"
    ],
    "name:bul_x_preferred":[
        "\u0411\u0430\u0440\u043a\u0430"
    ],
    "name:ceb_x_preferred":[
        "Barka"
    ],
    "name:ces_x_preferred":[
        "Barka"
    ],
    "name:deu_x_preferred":[
        "Barka"
    ],
    "name:fra_x_preferred":[
        "Barka"
    ],
    "name:hun_x_preferred":[
        "Barka"
    ],
    "name:ita_x_preferred":[
        "Barka"
    ],
    "name:lav_x_preferred":[
        "Barka"
    ],
    "name:nld_x_preferred":[
        "Barka"
    ],
    "name:pol_x_preferred":[
        "Barka"
    ],
    "name:rus_x_preferred":[
        "\u0411\u0430\u0440\u043a\u0430"
    ],
    "name:slv_x_preferred":[
        "Barka"
    ],
    "name:srp_x_preferred":[
        "\u0411\u0430\u0440\u043a\u0430"
    ],
    "name:swe_x_preferred":[
        "Barka"
    ],
    "name:ukr_x_preferred":[
        "\u0411\u0430\u0440\u043a\u0430"
    ],
    "wof:name":"Barka",
    "wof:placetype":"locality"
},
  "geometry": {"coordinates":[78.73213,25.8937],"type":"Point"}
}