{
  "type": "Feature",
  "properties": {
    "iso:country":"IN",
    "ks:ks_name":"Harparwa Alias Biratpurwa",
    "ks:ks_pop":19,
    "ks:ks_type":"VILLAGE",
    "name:eng_x_preferred":[
        "Harparwa Alias Biratpurwa"
    ],
    "wof:name":"Harparwa Alias Biratpurwa",
    "wof:placetype":"locality",
    "wof:population":19
},
  "geometry": {"coordinates":[84.16728000000001,23.910619],"type":"Point"}
}