{
  "type": "Feature",
  "properties": {
    "iso:country":"IN",
    "ks:ks_name":"Navanagar",
    "ks:ks_pop":165,
    "ks:ks_type":"HABITATION",
    "name:eng_x_preferred":[
        "Navanagar"
    ],
    "wof:name":"Navanagar",
    "wof:placetype":"locality",
    "wof:population":165
},
  "geometry": {"coordinates":[73.559167,17.173333],"type":"Point"}
}