{
  "type": "Feature",
  "properties": {
    "iso:country":"IN",
    "ks:ks_name":"Anuary",
    "ks:ks_pop":590,
    "ks:ks_type":"VILLAGE",
    "ks:ks_uagg_main":0,
    "name:eng_x_preferred":[
        "Anuary"
    ],
    "wof:name":"Anuary",
    "wof:placetype":"neighbourhood",
    "wof:population":590
},
  "geometry": {"coordinates":[85.439623,20.351541],"type":"Point"}
}