{
  "type": "Feature",
  "properties": {
    "iso:country":"IN",
    "ks:ks_name":"Kajomra",
    "ks:ks_pop":133,
    "ks:ks_type":"HABITATION",
    "name:eng_x_preferred":[
        "Kajomra"
    ],
    "wof:name":"Kajomra",
    "wof:placetype":"locality",
    "wof:population":133
},
  "geometry": {"coordinates":[85.521075,22.672682],"type":"Point"}
}