{
  "type": "Feature",
  "properties": {
    "iso:country":"IN",
    "ks:ks_name":"Lukuia",
    "ks:ks_pop":133,
    "ks:ks_type":"VILLAGE",
    "name:eng_x_preferred":[
        "Lukuia"
    ],
    "wof:name":"Lukuia",
    "wof:placetype":"locality",
    "wof:population":133
},
  "geometry": {"coordinates":[86.109629,24.205867],"type":"Point"}
}