{
  "type": "Feature",
  "properties": {
    "iso:country":"IN",
    "ks:ks_name":"Seoron Ki Dhnai",
    "ks:ks_pop":547,
    "ks:ks_type":"VILLAGE",
    "name:eng_x_preferred":[
        "Seoron Ki Dhnai"
    ],
    "wof:name":"Seoron Ki Dhnai",
    "wof:placetype":"locality",
    "wof:population":547
},
  "geometry": {"coordinates":[71.88405299999999,25.709514],"type":"Point"}
}