{
  "type": "Feature",
  "properties": {
    "gn:admin1_code":"16",
    "gn:admin2_code":"509.0",
    "gn:asciiname":"Charur",
    "gn:country_code":"IN",
    "gn:dem":209,
    "gn:feature_class":"P",
    "gn:feature_code":"PPL",
    "gn:name":"Char\u016br",
    "gn:population":0,
    "gn:timezone":"Asia/Kolkata",
    "iso:country":"IN",
    "name:und_x_variant":[
        "Char\u016br",
        "Khati"
    ],
    "wof:name":"Charur",
    "wof:placetype":"locality"
},
  "geometry": {"coordinates":[78.95203000000002,20.27401],"type":"Point"}
}