{
  "type": "Feature",
  "properties": {
    "iso:country":"IN",
    "ks:ks_name":"Bondiguda",
    "ks:ks_pop":139,
    "ks:ks_type":"HABITATION",
    "name:eng_x_preferred":[
        "Bondiguda"
    ],
    "wof:name":"Bondiguda",
    "wof:placetype":"locality",
    "wof:population":139
},
  "geometry": {"coordinates":[83.890484,18.642589],"type":"Point"}
}