{
  "type": "Feature",
  "properties": {
    "gn:admin1_code":"35.0",
    "gn:admin2_code":"454.0",
    "gn:asciiname":"Bharbheli",
    "gn:country_code":"IN",
    "gn:dem":516,
    "gn:feature_class":"P",
    "gn:feature_code":"PPL",
    "gn:name":"Bharbhel\u012b",
    "gn:population":0,
    "gn:timezone":"Asia/Kolkata",
    "iso:country":"IN",
    "ks:ks_name":"Bharveli",
    "ks:ks_pop":579,
    "ks:ks_type":"HABITATION",
    "name:eng_x_preferred":[
        "Bharveli"
    ],
    "name:eng_x_variant":[
        "Bharbheli"
    ],
    "wof:name":"Bharveli",
    "wof:placetype":"locality",
    "wof:population":579
},
  "geometry": {"coordinates":[80.35697399999999,22.305523],"type":"Point"}
}