{
  "type": "Feature",
  "properties": {
    "iso:country":"IN",
    "ks:ks_name":"Ampalakunnu Jn",
    "ks:ks_pop":745,
    "ks:ks_type":"HABITATION",
    "name:eng_x_preferred":[
        "Ampalakunnu Jn"
    ],
    "wof:name":"Ampalakunnu Jn",
    "wof:placetype":"locality",
    "wof:population":745
},
  "geometry": {"coordinates":[76.30703699999999,11.146386],"type":"Point"}
}