{
  "type": "Feature",
  "properties": {
    "gn:admin1_code":"16",
    "gn:admin2_code":"512.0",
    "gn:asciiname":"Dagad Pipri",
    "gn:country_code":"IN",
    "gn:dem":373,
    "gn:feature_class":"P",
    "gn:feature_code":"PPL",
    "gn:name":"Dagad Pipri",
    "gn:population":0,
    "gn:timezone":"Asia/Kolkata",
    "iso:country":"IN",
    "name:eng_x_preferred":[
        "Dagad Pipri"
    ],
    "wof:name":"Dagad Pipri",
    "wof:placetype":"locality"
},
  "geometry": {"coordinates":[77.19469000000002,19.2501],"type":"Point"}
}