{
  "type": "Feature",
  "properties": {
    "iso:country":"IN",
    "ks:ks_name":"Kerpani G",
    "ks:ks_pop":3175,
    "ks:ks_type":"HABITATION",
    "name:eng_x_preferred":[
        "Kerpani G"
    ],
    "wof:name":"Kerpani G",
    "wof:placetype":"locality",
    "wof:population":3175
},
  "geometry": {"coordinates":[79.12906700000001,22.813087],"type":"Point"}
}