{
  "type": "Feature",
  "properties": {
    "iso:country":"IN",
    "ks:ks_name":"Uddanur",
    "ks:ks_pop":141,
    "ks:ks_type":"HABITATION",
    "name:eng_x_preferred":[
        "Uddanur"
    ],
    "wof:name":"Uddanur",
    "wof:placetype":"locality",
    "wof:population":141
},
  "geometry": {"coordinates":[75.269471,14.111766],"type":"Point"}
}