{
  "type": "Feature",
  "properties": {
    "iso:country":"IN",
    "ks:ks_name":"Dalbali",
    "ks:ks_pop":195,
    "ks:ks_type":"VILLAGE",
    "name:eng_x_preferred":[
        "Dalbali"
    ],
    "wof:name":"Dalbali",
    "wof:placetype":"locality",
    "wof:population":195
},
  "geometry": {"coordinates":[84.218245,20.063209],"type":"Point"}
}