{
  "type": "Feature",
  "properties": {
    "iso:country":"IN",
    "ks:ks_name":"Kuntapadavu",
    "ks:ks_pop":427,
    "ks:ks_type":"HABITATION",
    "name:eng_x_preferred":[
        "Kuntapadavu"
    ],
    "wof:name":"Kuntapadavu",
    "wof:placetype":"locality",
    "wof:population":427
},
  "geometry": {"coordinates":[74.951499,12.784581],"type":"Point"}
}