{
  "type": "Feature",
  "properties": {
    "iso:country":"IN",
    "ks:ks_name":"Arisol",
    "ks:ks_pop":490,
    "ks:ks_type":"VILLAGE",
    "name:eng_x_preferred":[
        "Arisol"
    ],
    "wof:name":"Arisol",
    "wof:placetype":"locality",
    "wof:population":490
},
  "geometry": {"coordinates":[85.693932,20.241156],"type":"Point"}
}