{
  "type": "Feature",
  "properties": {
    "gn:admin1_code":"12.0",
    "gn:admin2_code":"12.0",
    "gn:asciiname":"Hajbal",
    "gn:country_code":"IN",
    "gn:dem":1589,
    "gn:feature_class":"P",
    "gn:feature_code":"PPL",
    "gn:name":"H\u0101jbal",
    "gn:population":0,
    "gn:timezone":"Asia/Kolkata",
    "iso:country":"IN",
    "wof:name":"Hajbal",
    "wof:placetype":"locality"
},
  "geometry": {"coordinates":[74.9603,33.96378],"type":"Point"}
}