{
  "type": "Feature",
  "properties": {
    "iso:country":"IN",
    "ks:ks_name":"Nalwadi",
    "ks:ks_pop":8052,
    "ks:ks_type":"VILLAGE",
    "ks:ks_uagg_main":0,
    "name:eng_x_preferred":[
        "Nalwadi"
    ],
    "wof:name":"Nalwadi",
    "wof:placetype":"neighbourhood",
    "wof:population":8052
},
  "geometry": {"coordinates":[78.620722,20.757097],"type":"Point"}
}