{
  "type": "Feature",
  "properties": {
    "gn:admin1_code":"19.0",
    "gn:admin2_code":"577.0",
    "gn:asciiname":"Sigalli Koppal",
    "gn:country_code":"IN",
    "gn:dem":835,
    "gn:feature_class":"P",
    "gn:feature_code":"PPL",
    "gn:name":"Sigalli Koppal",
    "gn:population":0,
    "gn:timezone":"Asia/Kolkata",
    "iso:country":"IN",
    "wof:name":"Sigalli Koppal",
    "wof:placetype":"locality"
},
  "geometry": {"coordinates":[76.51222,12.32755],"type":"Point"}
}