{
  "type": "Feature",
  "properties": {
    "iso:country":"IN",
    "ks:ks_name":"Kaithwalia",
    "ks:ks_pop":1498,
    "ks:ks_type":"VILLAGE",
    "ks:ks_uagg_main":0,
    "name:eng_x_preferred":[
        "Kaithwalia"
    ],
    "wof:name":"Kaithwalia",
    "wof:placetype":"locality",
    "wof:population":1498
},
  "geometry": {"coordinates":[83.600702,25.594342],"type":"Point"}
}