{
  "type": "Feature",
  "properties": {
    "iso:country":"IN",
    "ks:ks_name":"Pavarwasti",
    "ks:ks_pop":200,
    "ks:ks_type":"HABITATION",
    "name:eng_x_preferred":[
        "Pavarwasti"
    ],
    "wof:name":"Pavarwasti",
    "wof:placetype":"locality",
    "wof:population":200
},
  "geometry": {"coordinates":[74.906167,17.876849],"type":"Point"}
}