{
  "type": "Feature",
  "properties": {
    "gn:admin1_code":"36",
    "gn:admin2_code":"186.0",
    "gn:asciiname":"Maila",
    "gn:country_code":"IN",
    "gn:dem":83,
    "gn:feature_class":"P",
    "gn:feature_code":"PPL",
    "gn:name":"Maila",
    "gn:population":0,
    "gn:timezone":"Asia/Kolkata",
    "iso:country":"IN",
    "name:ceb_x_preferred":[
        "Maila"
    ],
    "name:msa_x_preferred":[
        "Maila"
    ],
    "name:nep_x_preferred":[
        "\u092e\u0948\u0932\u093e"
    ],
    "name:new_x_preferred":[
        "\u092e\u093e\u0908\u0932\u093e"
    ],
    "name:pol_x_preferred":[
        "Maila"
    ],
    "wof:name":"Maila",
    "wof:placetype":"neighbourhood"
},
  "geometry": {"coordinates":[83.11138,26.89869],"type":"Point"}
}