{
  "type": "Feature",
  "properties": {
    "iso:country":"IN",
    "ks:ks_name":"Bandhpali",
    "ks:ks_pop":611,
    "ks:ks_type":"VILLAGE",
    "name:eng_x_preferred":[
        "Bandhpali"
    ],
    "wof:name":"Bandhpali",
    "wof:placetype":"locality",
    "wof:population":611
},
  "geometry": {"coordinates":[83.838278,22.004086],"type":"Point"}
}