{
  "type": "Feature",
  "properties": {
    "gn:admin1_code":"36.0",
    "gn:admin2_code":"179.0",
    "gn:asciiname":"Bhojpur",
    "gn:country_code":"IN",
    "gn:dem":104,
    "gn:feature_class":"P",
    "gn:feature_code":"PPL",
    "gn:name":"Bhojpur",
    "gn:population":0,
    "gn:timezone":"Asia/Kolkata",
    "iso:country":"IN",
    "name:ara_x_preferred":[
        "\u0628\u0648\u062c \u0628\u0648\u0631"
    ],
    "name:ceb_x_preferred":[
        "Bhojpur"
    ],
    "name:deu_x_preferred":[
        "Bhojpur"
    ],
    "name:fra_x_preferred":[
        "Bhojpur"
    ],
    "name:hin_x_preferred":[
        "\u092d\u094b\u091c\u092a\u0941\u0930"
    ],
    "name:nld_x_preferred":[
        "Bhojpur"
    ],
    "name:swe_x_preferred":[
        "Bhojpur"
    ],
    "name:vie_x_preferred":[
        "Bhojpur"
    ],
    "wof:name":"Bhojpur",
    "wof:placetype":"locality"
},
  "geometry": {"coordinates":[81.86353000000003,26.32126],"type":"Point"}
}