{
  "type": "Feature",
  "properties": {
    "iso:country":"IN",
    "ks:ks_name":"Meharban",
    "ks:ks_pop":2663,
    "ks:ks_type":"VILLAGE",
    "ks:ks_uagg_main":0,
    "name:eng_x_preferred":[
        "Meharban"
    ],
    "wof:name":"Meharban",
    "wof:placetype":"locality",
    "wof:population":2663
},
  "geometry": {"coordinates":[75.900052,30.952419],"type":"Point"}
}