{
  "type": "Feature",
  "properties": {
    "iso:country":"IN",
    "ks:ks_name":"Kaira Kocha",
    "ks:ks_pop":53,
    "ks:ks_type":"HABITATION",
    "name:eng_x_preferred":[
        "Kaira Kocha"
    ],
    "wof:name":"Kaira Kocha",
    "wof:placetype":"locality",
    "wof:population":53
},
  "geometry": {"coordinates":[85.711324,23.391435],"type":"Point"}
}