{
  "type": "Feature",
  "properties": {
    "gn:admin1_code":"11.0",
    "gn:admin2_code":"33.0",
    "gn:asciiname":"Ghorgar",
    "gn:country_code":"IN",
    "gn:dem":1716,
    "gn:feature_class":"P",
    "gn:feature_code":"PPL",
    "gn:name":"Ghorgar",
    "gn:population":0,
    "gn:timezone":"Asia/Kolkata",
    "iso:country":"IN",
    "wof:name":"Ghorgar",
    "wof:placetype":"locality"
},
  "geometry": {"coordinates":[77.28016,31.15545],"type":"Point"}
}