{
  "type": "Feature",
  "properties": {
    "iso:country":"IN",
    "ks:ks_name":"Sundipur",
    "ks:ks_pop":522,
    "ks:ks_type":"VILLAGE",
    "ks:ks_uagg_main":0,
    "name:eng_x_preferred":[
        "Sundipur"
    ],
    "wof:name":"Sundipur",
    "wof:placetype":"neighbourhood",
    "wof:population":522
},
  "geometry": {"coordinates":[87.77728500000001,24.184036],"type":"Point"}
}