{
  "type": "Feature",
  "properties": {
    "iso:country":"IN",
    "ks:ks_name":"Malrajakuppam",
    "ks:ks_pop":20,
    "ks:ks_type":"VILLAGE",
    "ks:ks_uagg_main":0,
    "name:eng_x_preferred":[
        "Malrajakuppam"
    ],
    "wof:name":"Malrajakuppam",
    "wof:placetype":"neighbourhood",
    "wof:population":20
},
  "geometry": {"coordinates":[80.090853,12.43721],"type":"Point"}
}