{
  "type": "Feature",
  "properties": {
    "iso:country":"IN",
    "ks:ks_name":"Nahardara Puranibasti Schoolpara",
    "ks:ks_pop":25,
    "ks:ks_type":"HABITATION",
    "name:eng_x_preferred":[
        "Nahardara Puranibasti Schoolpara"
    ],
    "wof:name":"Nahardara Puranibasti Schoolpara",
    "wof:placetype":"locality",
    "wof:population":25
},
  "geometry": {"coordinates":[81.571185,20.552823],"type":"Point"}
}