{
  "type": "Feature",
  "properties": {
    "iso:country":"IN",
    "ks:ks_name":"Cheyari",
    "ks:ks_pop":1394,
    "ks:ks_type":"VILLAGE",
    "name:eng_x_preferred":[
        "Cheyari"
    ],
    "wof:name":"Cheyari",
    "wof:placetype":"locality",
    "wof:population":1394
},
  "geometry": {"coordinates":[88.35069,22.418645],"type":"Point"}
}