{
  "type": "Feature",
  "properties": {
    "gn:admin1_code":"21",
    "gn:admin2_code":"399.0",
    "gn:asciiname":"Kammaruputtu",
    "gn:country_code":"IN",
    "gn:dem":274,
    "gn:feature_class":"P",
    "gn:feature_code":"PPL",
    "gn:name":"Kamm\u0101ruputtu",
    "gn:population":0,
    "gn:timezone":"Asia/Kolkata",
    "iso:country":"IN",
    "wof:name":"Kammaruputtu",
    "wof:placetype":"neighbourhood"
},
  "geometry": {"coordinates":[82.23902,18.4862],"type":"Point"}
}