{
  "type": "Feature",
  "properties": {
    "gn:country":"IN",
    "gn:fcode":"PPL",
    "gn:pop":29749,
    "iso:country":"IN",
    "name:ben_x_preferred":[
        "\u0997\u099c\u09c7\u09a8\u09cd\u09a6\u09cd\u09b0\u0997\u09a1\u09bc"
    ],
    "name:bpy_x_preferred":[
        "\u0997\u099c\u09c7\u09a8\u09cd\u09a6\u09cd\u09b0\u0997\u09a1\u09bc"
    ],
    "name:cat_x_preferred":[
        "Gajendragad"
    ],
    "name:chi_x_preferred":[
        "\u52a0\u6770\u6069\u5fb7\u62c9\u52a0\u5c14"
    ],
    "name:dut_x_preferred":[
        "Gajendragarh"
    ],
    "name:eng_x_preferred":[
        "Gajendragarh"
    ],
    "name:fre_x_preferred":[
        "Gajendragarh"
    ],
    "name:hin_x_preferred":[
        "\u0917\u091c\u0947\u0902\u0926\u094d\u0930\u0917\u0922\u093c"
    ],
    "name:ita_x_preferred":[
        "Gajendragarh"
    ],
    "name:jpn_x_preferred":[
        "\u30ac\u30b8\u30a7\u30fc\u30f3\u30c9\u30e9\u30ac\u30eb"
    ],
    "name:may_x_preferred":[
        "Gajendragarh"
    ],
    "name:mlg_x_preferred":[
        "Gajendragarh"
    ],
    "name:nan_x_preferred":[
        "Gajendragarh"
    ],
    "name:new_x_preferred":[
        "\u0917\u091c\u0947\u0928\u094d\u0926\u094d\u0930\u0917\u0922"
    ],
    "name:por_x_preferred":[
        "Gajendragarh"
    ],
    "name:san_x_preferred":[
        "\u0917\u091c\u0947\u0928\u094d\u0926\u094d\u0930\u0917\u0921"
    ],
    "name:spa_x_preferred":[
        "Gajendragarh"
    ],
    "name:swe_x_preferred":[
        "Gajendragarh"
    ],
    "name:unk_x_variant":[
        "Gajendragad"
    ],
    "name:vie_x_preferred":[
        "Gajendragarh"
    ],
    "qs:name":"Gajendragarh",
    "qs:name_adm0":"India",
    "qs:name_adm1":"Karnataka",
    "qs:photos_9r":0,
    "qs:photos_sr":0,
    "qs:placetype":"Town",
    "qs:pop_sr":"7",
    "wd:wordcount":1553,
    "wof:name":"Gajendragarh",
    "wof:placetype":"locality",
    "wof:population":29749
},
  "geometry": {"coordinates":[75.96975999999999,15.73628],"type":"Point"}
}