{
  "type": "Feature",
  "properties": {
    "gn:admin1_code":"36",
    "gn:admin2_code":"169.0",
    "gn:asciiname":"Bhandra",
    "gn:country_code":"IN",
    "gn:dem":234,
    "gn:feature_class":"P",
    "gn:feature_code":"PPL",
    "gn:name":"Bhandra",
    "gn:population":0,
    "gn:timezone":"Asia/Kolkata",
    "iso:country":"IN",
    "wof:name":"Bhandra",
    "wof:placetype":"locality"
},
  "geometry": {"coordinates":[79.85306,25.16261],"type":"Point"}
}