{
  "type": "Feature",
  "properties": {
    "iso:country":"IN",
    "ks:ks_name":"Kohra",
    "ks:ks_pop":223,
    "ks:ks_type":"VILLAGE",
    "name:eng_x_preferred":[
        "Kohra"
    ],
    "wof:name":"Kohra",
    "wof:placetype":"locality",
    "wof:population":223
},
  "geometry": {"coordinates":[70.92205800000001,26.188458],"type":"Point"}
}