{
  "type": "Feature",
  "properties": {
    "iso:country":"IN",
    "ks:ks_name":"Kakibangarupalem",
    "ks:ks_pop":676,
    "ks:ks_type":"HABITATION",
    "name:eng_x_preferred":[
        "Kakibangarupalem"
    ],
    "wof:name":"Kakibangarupalem",
    "wof:placetype":"locality",
    "wof:population":676
},
  "geometry": {"coordinates":[79.92012699999999,15.257413],"type":"Point"}
}