{
  "type": "Feature",
  "properties": {
    "iso:country":"IN",
    "ks:ks_alt_nam":"BAGIYA PURWA",
    "ks:ks_name":"Bagiya Purwa",
    "ks:ks_pop":165,
    "ks:ks_type":"HABITATION",
    "ks:ks_uagg_main":0,
    "name:eng_x_preferred":[
        "Bagiya Purwa"
    ],
    "wof:name":"Bagiya Purwa",
    "wof:placetype":"neighbourhood",
    "wof:population":165
},
  "geometry": {"coordinates":[81.229702,28.057163],"type":"Point"}
}