{
  "type": "Feature",
  "properties": {
    "iso:country":"IN",
    "ks:ks_name":"Kurpania",
    "ks:ks_pop":7436,
    "ks:ks_type":"VILLAGE",
    "ks:ks_uagg_main":0,
    "name:eng_x_preferred":[
        "Kurpania"
    ],
    "wof:name":"Kurpania",
    "wof:placetype":"neighbourhood",
    "wof:population":7436
},
  "geometry": {"coordinates":[85.93212,23.79117],"type":"Point"}
}