{
  "type": "Feature",
  "properties": {
    "gn:admin1_code":"16",
    "gn:admin2_code":"505.0",
    "gn:asciiname":"Lapka",
    "gn:country_code":"IN",
    "gn:dem":268,
    "gn:feature_class":"P",
    "gn:feature_code":"PPL",
    "gn:name":"L\u0101pka",
    "gn:population":0,
    "gn:timezone":"Asia/Kolkata",
    "iso:country":"IN",
    "name:rus_x_preferred":[
        "\u041b\u0430\u043f\u043a\u0430"
    ],
    "name:ukr_x_preferred":[
        "\u041b\u0430\u043f\u043a\u0430"
    ],
    "wof:name":"Lapka",
    "wof:placetype":"locality"
},
  "geometry": {"coordinates":[79.41405999999998,21.15639],"type":"Point"}
}