{
  "type": "Feature",
  "properties": {
    "iso:country":"IN",
    "ks:ks_name":"Mangalur",
    "ks:ks_pop":502,
    "ks:ks_type":"HABITATION",
    "name:eng_x_preferred":[
        "Mangalur"
    ],
    "wof:name":"Mangalur",
    "wof:placetype":"locality",
    "wof:population":502
},
  "geometry": {"coordinates":[75.569033,16.497487],"type":"Point"}
}