{
  "type": "Feature",
  "properties": {
    "iso:country":"IN",
    "ks:ks_name":"Patrapali",
    "ks:ks_pop":312,
    "ks:ks_type":"VILLAGE",
    "name:eng_x_preferred":[
        "Patrapali"
    ],
    "wof:name":"Patrapali",
    "wof:placetype":"locality",
    "wof:population":312
},
  "geometry": {"coordinates":[84.232961,21.462161],"type":"Point"}
}