{
  "type": "Feature",
  "properties": {
    "gn:admin1_code":"25",
    "gn:admin2_code":"602.0",
    "gn:asciiname":"Ponpadi",
    "gn:country_code":"IN",
    "gn:dem":99,
    "gn:feature_class":"P",
    "gn:feature_code":"PPL",
    "gn:name":"Ponpadi",
    "gn:population":0,
    "gn:timezone":"Asia/Kolkata",
    "iso:country":"IN",
    "wof:name":"Ponpadi",
    "wof:placetype":"locality"
},
  "geometry": {"coordinates":[79.59857,13.23028],"type":"Point"}
}