{
  "type": "Feature",
  "properties": {
    "iso:country":"IN",
    "ks:ks_name":"Goligram",
    "ks:ks_pop":1236,
    "ks:ks_type":"HABITATION",
    "name:eng_x_preferred":[
        "Goligram"
    ],
    "wof:name":"Goligram",
    "wof:placetype":"locality",
    "wof:population":1236
},
  "geometry": {"coordinates":[87.620176,23.54849],"type":"Point"}
}