{
  "type": "Feature",
  "properties": {
    "gn:admin1_code":"19.0",
    "gn:admin2_code":"559",
    "gn:asciiname":"Balganur",
    "gn:country_code":"IN",
    "gn:dem":410,
    "gn:feature_class":"P",
    "gn:feature_code":"PPL",
    "gn:name":"Balgan\u016br",
    "gn:population":0,
    "gn:timezone":"Asia/Kolkata",
    "iso:country":"IN",
    "wof:name":"Balganur",
    "wof:placetype":"locality"
},
  "geometry": {"coordinates":[76.75164000000002,15.95613],"type":"Point"}
}