{
  "type": "Feature",
  "properties": {
    "iso:country":"IN",
    "ks:ks_name":"Tentulipadar",
    "ks:ks_pop":0,
    "ks:ks_type":"VILLAGE",
    "name:eng_x_preferred":[
        "Tentulipadar"
    ],
    "wof:name":"Tentulipadar",
    "wof:placetype":"locality",
    "wof:population":0
},
  "geometry": {"coordinates":[82.888488,19.278224],"type":"Point"}
}