{
  "type": "Feature",
  "properties": {
    "iso:country":"IN",
    "ks:ks_name":"Thazathvadaku",
    "ks:ks_pop":286,
    "ks:ks_type":"HABITATION",
    "name:eng_x_preferred":[
        "Thazathvadaku"
    ],
    "wof:name":"Thazathvadaku",
    "wof:placetype":"locality",
    "wof:population":286
},
  "geometry": {"coordinates":[76.778049,9.110413],"type":"Point"}
}