{
  "type": "Feature",
  "properties": {
    "iso:country":"IN",
    "ks:ks_name":"Idaripath",
    "ks:ks_pop":164,
    "ks:ks_type":"VILLAGE",
    "name:eng_x_preferred":[
        "Idaripath"
    ],
    "wof:name":"Idaripath",
    "wof:placetype":"locality",
    "wof:population":164
},
  "geometry": {"coordinates":[83.87284099999999,23.453695],"type":"Point"}
}