{
  "type": "Feature",
  "properties": {
    "gn:admin1_code":"38",
    "gn:admin2_code":"358.0",
    "gn:asciiname":"Kunrwa Kalan",
    "gn:country_code":"IN",
    "gn:dem":200,
    "gn:feature_class":"P",
    "gn:feature_code":"PPL",
    "gn:name":"Kunrwa Kal\u0101n",
    "gn:population":0,
    "gn:timezone":"Asia/Kolkata",
    "iso:country":"IN",
    "ks:ks_alt_nam":"Kunrwa Kal\u0101n",
    "ks:ks_name":"Kunrwa Kalan",
    "ks:ks_type":"VILLAGE",
    "ks:ks_uagg_main":0,
    "name:eng_x_preferred":[
        "Kunrwa Kalan"
    ],
    "name:eng_x_variant":[
        "Kunrwa Kal\u0101n"
    ],
    "wof:name":"Kunrwa Kalan",
    "wof:placetype":"neighbourhood"
},
  "geometry": {"coordinates":[83.94931200000001,24.323284],"type":"Point"}
}