{
  "type": "Feature",
  "properties": {
    "gn:country":"IN",
    "gn:fcode":"PPL",
    "gn:population":73835,
    "iso:country":"IN",
    "qs:name":"Rabkavi",
    "qs:name_adm0":"India",
    "qs:name_adm1":"Karnataka",
    "qs:photos_9r":0,
    "qs:photos_sr":0,
    "qs:placetype":"Town",
    "qs:pop_sr":"8",
    "wof:name":"Rabkavi",
    "wof:placetype":"locality",
    "wof:population":73835
},
  "geometry": {"coordinates":[75.11060000000001,16.47567],"type":"Point"}
}