{
  "type": "Feature",
  "properties": {
    "iso:country":"IN",
    "ks:ks_alt_nam":"GUTTAKINDA INDLU",
    "ks:ks_name":"Guttakinda Indlu",
    "ks:ks_pop":34,
    "ks:ks_type":"HABITATION",
    "name:eng_x_preferred":[
        "Guttakinda Indlu"
    ],
    "wof:name":"Guttakinda Indlu",
    "wof:placetype":"locality",
    "wof:population":34
},
  "geometry": {"coordinates":[79.209942,13.241587],"type":"Point"}
}