{
  "type": "Feature",
  "properties": {
    "iso:country":"IN",
    "ks:ks_name":"Janathakeri",
    "ks:ks_pop":590,
    "ks:ks_type":"HABITATION",
    "name:eng_x_preferred":[
        "Janathakeri"
    ],
    "wof:name":"Janathakeri",
    "wof:placetype":"locality",
    "wof:population":590
},
  "geometry": {"coordinates":[74.919051,14.258601],"type":"Point"}
}