{
  "type": "Feature",
  "properties": {
    "iso:country":"IN",
    "ks:ks_alt_nam":"SARDAR PARA 2",
    "ks:ks_name":"Sardar Para 2",
    "ks:ks_pop":870,
    "ks:ks_type":"HABITATION",
    "name:eng_x_preferred":[
        "Sardar Para 2"
    ],
    "wof:name":"Sardar Para 2",
    "wof:placetype":"locality",
    "wof:population":870
},
  "geometry": {"coordinates":[88.74486899999999,26.379399],"type":"Point"}
}