{
  "type": "Feature",
  "properties": {
    "iso:country":"IN",
    "ks:ks_name":"Mahuwa Khera",
    "ks:ks_pop":0,
    "ks:ks_type":"VILLAGE",
    "name:eng_x_preferred":[
        "Mahuwa Khera"
    ],
    "wof:name":"Mahuwa Khera",
    "wof:placetype":"locality",
    "wof:population":0
},
  "geometry": {"coordinates":[78.77799,24.814177],"type":"Point"}
}