{
  "type": "Feature",
  "properties": {
    "iso:country":"IN",
    "ks:ks_name":"Siyalkund",
    "ks:ks_pop":91,
    "ks:ks_type":"VILLAGE",
    "name:eng_x_preferred":[
        "Siyalkund"
    ],
    "wof:name":"Siyalkund",
    "wof:placetype":"locality",
    "wof:population":91
},
  "geometry": {"coordinates":[74.739014,24.794617],"type":"Point"}
}