{
  "type": "Feature",
  "properties": {
    "gn:admin1_code":"36",
    "gn:admin2_code":"192.0",
    "gn:asciiname":"Surajpur Khas",
    "gn:country_code":"IN",
    "gn:dem":76,
    "gn:feature_class":"P",
    "gn:feature_code":"PPL",
    "gn:name":"Surajpur Kh\u0101s",
    "gn:population":0,
    "gn:timezone":"Asia/Kolkata",
    "iso:country":"IN",
    "name:und_x_variant":[
        "Surajpur Kh\u0101s",
        "Surajpur Khas"
    ],
    "wof:name":"Surajpur Khas",
    "wof:placetype":"locality"
},
  "geometry": {"coordinates":[83.60914,26.22649],"type":"Point"}
}