{
  "type": "Feature",
  "properties": {
    "gn:admin1_code":"21.0",
    "gn:admin2_code":"370.0",
    "gn:asciiname":"Khapanpali",
    "gn:country_code":"IN",
    "gn:dem":230,
    "gn:feature_class":"P",
    "gn:feature_code":"PPL",
    "gn:name":"Khapanpali",
    "gn:population":0,
    "gn:timezone":"Asia/Kolkata",
    "iso:country":"IN",
    "wof:name":"Khapanpali",
    "wof:placetype":"locality"
},
  "geometry": {"coordinates":[83.27516999999997,21.24834],"type":"Point"}
}