{
  "type": "Feature",
  "properties": {
    "iso:country":"IN",
    "ks:ks_alt_nam":"SAJAPARA",
    "ks:ks_name":"Sajapara",
    "ks:ks_pop":185,
    "ks:ks_type":"HABITATION",
    "name:eng_x_preferred":[
        "Sajapara"
    ],
    "wof:name":"Sajapara",
    "wof:placetype":"locality",
    "wof:population":185
},
  "geometry": {"coordinates":[81.392477,22.34604],"type":"Point"}
}