{
  "type": "Feature",
  "properties": {
    "gn:admin1_code":"11",
    "gn:admin2_code":"24.0",
    "gn:asciiname":"Choki Kalan",
    "gn:country_code":"IN",
    "gn:dem":577,
    "gn:feature_class":"P",
    "gn:feature_code":"PPL",
    "gn:name":"Choki Kal\u0101n",
    "gn:population":0,
    "gn:timezone":"Asia/Kolkata",
    "iso:country":"IN",
    "wof:name":"Choki Kalan",
    "wof:placetype":"locality"
},
  "geometry": {"coordinates":[76.23262,31.97579],"type":"Point"}
}