{
  "type": "Feature",
  "properties": {
    "iso:country":"IN",
    "ks:ks_name":"Karihonnaiahnapalya",
    "ks:ks_pop":46,
    "ks:ks_type":"HABITATION",
    "name:eng_x_preferred":[
        "Karihonnaiahnapalya"
    ],
    "wof:name":"Karihonnaiahnapalya",
    "wof:placetype":"locality",
    "wof:population":46
},
  "geometry": {"coordinates":[77.063891,13.0881],"type":"Point"}
}