{
  "type": "Feature",
  "properties": {
    "iso:country":"IN",
    "ks:ks_name":"Parikheta",
    "ks:ks_pop":0,
    "ks:ks_type":"VILLAGE",
    "name:eng_x_preferred":[
        "Parikheta"
    ],
    "wof:name":"Parikheta",
    "wof:placetype":"locality",
    "wof:population":0
},
  "geometry": {"coordinates":[85.497609,20.228657],"type":"Point"}
}