{
  "type": "Feature",
  "properties": {
    "gn:admin1_code":"2.0",
    "gn:admin2_code":"544.0",
    "gn:asciiname":"Surtipili",
    "gn:country_code":"IN",
    "gn:dem":757,
    "gn:feature_class":"P",
    "gn:feature_code":"PPL",
    "gn:name":"Surtipili",
    "gn:population":0,
    "gn:timezone":"Asia/Kolkata",
    "iso:country":"IN",
    "ks:ks_name":"Surtipalli",
    "ks:ks_pop":52,
    "ks:ks_type":"HABITATION",
    "name:eng_x_preferred":[
        "Surtipalli"
    ],
    "name:eng_x_variant":[
        "Surtipili"
    ],
    "wof:name":"Surtipalli",
    "wof:placetype":"locality",
    "wof:population":52
},
  "geometry": {"coordinates":[82.38688999999999,18.102963],"type":"Point"}
}