{
  "type": "Feature",
  "properties": {
    "iso:country":"IN",
    "ks:ks_alt_nam":"Bettadak\u016brli State Forest",
    "ks:ks_name":"Bettadakurli State Forest",
    "ks:ks_pop":21,
    "ks:ks_type":"VILLAGE",
    "name:eng_x_preferred":[
        "Bettadakurli State Forest"
    ],
    "name:eng_x_variant":[
        "Bettadak\u016brli State Forest"
    ],
    "wof:name":"Bettadakurli State Forest",
    "wof:placetype":"locality",
    "wof:population":21
},
  "geometry": {"coordinates":[75.137372,14.501745],"type":"Point"}
}