{
  "type": "Feature",
  "properties": {
    "gn:admin1_code":"19.0",
    "gn:admin2_code":"581.0",
    "gn:asciiname":"Boyinayinipalli",
    "gn:country_code":"IN",
    "gn:dem":824,
    "gn:feature_class":"P",
    "gn:feature_code":"PPL",
    "gn:name":"Boyin\u0101yinipalli",
    "gn:population":0,
    "gn:timezone":"Asia/Kolkata",
    "iso:country":"IN",
    "wof:name":"Boyinayinipalli",
    "wof:placetype":"neighbourhood"
},
  "geometry": {"coordinates":[78.35227,13.56497],"type":"Point"}
}