{
  "type": "Feature",
  "properties": {
    "gn:admin1_code":"34",
    "gn:admin2_code":"233.0",
    "gn:asciiname":"Kotamdag",
    "gn:country_code":"IN",
    "gn:dem":493,
    "gn:feature_class":"P",
    "gn:feature_code":"PPL",
    "gn:name":"Kotamd\u0101g",
    "gn:population":0,
    "gn:timezone":"Asia/Kolkata",
    "iso:country":"IN",
    "ks:ks_alt_nam":"Kotamd\u0101g",
    "ks:ks_name":"Kotamdag",
    "ks:ks_pop":172,
    "ks:ks_type":"VILLAGE",
    "name:eng_x_preferred":[
        "Kotamdag"
    ],
    "name:eng_x_variant":[
        "Kotamd\u0101g"
    ],
    "wof:name":"Kotamdag",
    "wof:placetype":"locality",
    "wof:population":172
},
  "geometry": {"coordinates":[83.64038499999999,24.641397],"type":"Point"}
}