{
  "type": "Feature",
  "properties": {
    "gn:admin1_code":"12.0",
    "gn:admin2_code":"019",
    "gn:asciiname":"Dudu",
    "gn:country_code":"IN",
    "gn:dem":1959,
    "gn:feature_class":"P",
    "gn:feature_code":"PPL",
    "gn:name":"Dudu",
    "gn:population":0,
    "gn:timezone":"Asia/Kolkata",
    "iso:country":"IN",
    "wof:name":"Dudu",
    "wof:placetype":"locality"
},
  "geometry": {"coordinates":[75.5147,32.8781],"type":"Point"}
}