{
  "type": "Feature",
  "properties": {
    "gn:admin1_code":"12.0",
    "gn:admin2_code":"019",
    "gn:asciiname":"Dudu",
    "gn:country_code":"IN",
    "gn:dem":1959,
    "gn:feature_class":"P",
    "gn:feature_code":"PPL",
    "gn:name":"Dudu",
    "gn:population":0,
    "gn:timezone":"Asia/Kolkata",
    "iso:country":"IN",
    "name:ceb_x_preferred":[
        "Dudu"
    ],
    "name:deu_x_preferred":[
        "Dudu"
    ],
    "name:fra_x_preferred":[
        "Dudu"
    ],
    "name:hun_x_preferred":[
        "Dudu"
    ],
    "name:ita_x_preferred":[
        "Dudu"
    ],
    "name:jpn_x_preferred":[
        "\u30c9\u30a5\u30c9\u30a5"
    ],
    "name:msa_x_preferred":[
        "Dudu"
    ],
    "name:nld_x_preferred":[
        "Dudu"
    ],
    "name:por_x_preferred":[
        "Dudu"
    ],
    "name:ron_x_preferred":[
        "Dudu"
    ],
    "name:rus_x_preferred":[
        "Dudu"
    ],
    "name:spa_x_preferred":[
        "Dudu"
    ],
    "name:srp_x_preferred":[
        "\u0414\u0443\u0434\u0443"
    ],
    "name:ukr_x_preferred":[
        "Dudu"
    ],
    "wof:name":"Dudu",
    "wof:placetype":"locality"
},
  "geometry": {"coordinates":[75.5147,32.8781],"type":"Point"}
}