{
  "type": "Feature",
  "properties": {
    "iso:country":"IN",
    "ks:ks_name":"Dudukhanga",
    "ks:ks_pop":27,
    "ks:ks_type":"VILLAGE",
    "name:eng_x_preferred":[
        "Dudukhanga"
    ],
    "wof:name":"Dudukhanga",
    "wof:placetype":"locality",
    "wof:population":27
},
  "geometry": {"coordinates":[84.08974600000001,20.176906],"type":"Point"}
}