{
  "type": "Feature",
  "properties": {
    "iso:country":"IN",
    "ks:ks_name":"Gandkeda",
    "ks:ks_pop":107,
    "ks:ks_type":"VILLAGE",
    "name:eng_x_preferred":[
        "Gandkeda"
    ],
    "wof:name":"Gandkeda",
    "wof:placetype":"locality",
    "wof:population":107
},
  "geometry": {"coordinates":[85.199449,22.803807],"type":"Point"}
}