{
  "type": "Feature",
  "properties": {
    "iso:country":"IN",
    "ks:ks_alt_nam":"chinchwadi",
    "ks:ks_name":"Chinchwadi",
    "ks:ks_pop":178,
    "ks:ks_type":"HABITATION",
    "name:eng_x_preferred":[
        "Chinchwadi"
    ],
    "wof:name":"Chinchwadi",
    "wof:placetype":"locality",
    "wof:population":178
},
  "geometry": {"coordinates":[73.536389,17.348333],"type":"Point"}
}