{
  "type": "Feature",
  "properties": {
    "iso:country":"IN",
    "ks:ks_name":"Karmale",
    "ks:ks_pop":315,
    "ks:ks_type":"VILLAGE",
    "name:eng_x_preferred":[
        "Karmale"
    ],
    "wof:name":"Karmale",
    "wof:placetype":"locality",
    "wof:population":315
},
  "geometry": {"coordinates":[73.14321200000001,19.464449],"type":"Point"}
}