{
  "type": "Feature",
  "properties": {
    "gn:admin1_code":"35",
    "gn:admin2_code":"455.0",
    "gn:asciiname":"Dunda",
    "gn:country_code":"IN",
    "gn:dem":562,
    "gn:feature_class":"P",
    "gn:feature_code":"PPL",
    "gn:name":"Dunda",
    "gn:population":0,
    "gn:timezone":"Asia/Kolkata",
    "iso:country":"IN",
    "ks:ks_name":"Dunda",
    "ks:ks_pop":206,
    "ks:ks_type":"HABITATION",
    "name:eng_x_preferred":[
        "Dunda"
    ],
    "wof:name":"Dunda",
    "wof:placetype":"locality",
    "wof:population":206
},
  "geometry": {"coordinates":[79.221317,22.756215],"type":"Point"}
}