{
  "type": "Feature",
  "properties": {
    "iso:country":"IN",
    "ks:ks_name":"Y Malapalle1",
    "ks:ks_pop":66,
    "ks:ks_type":"HABITATION",
    "name:eng_x_preferred":[
        "Y Malapalle1"
    ],
    "wof:name":"Y Malapalle1",
    "wof:placetype":"locality",
    "wof:population":66
},
  "geometry": {"coordinates":[78.884187,13.931466],"type":"Point"}
}