{
  "type": "Feature",
  "properties": {
    "gn:admin1_code":"25.0",
    "gn:admin2_code":"610.0",
    "gn:asciiname":"Kuppakkavundanvalasu",
    "gn:country_code":"IN",
    "gn:dem":204,
    "gn:feature_class":"P",
    "gn:feature_code":"PPL",
    "gn:name":"Kuppakkavundanvalasu",
    "gn:population":0,
    "gn:timezone":"Asia/Kolkata",
    "iso:country":"IN",
    "wof:name":"Kuppakkavundanvalasu",
    "wof:placetype":"locality"
},
  "geometry": {"coordinates":[77.74332,11.21979],"type":"Point"}
}