{
  "type": "Feature",
  "properties": {
    "iso:country":"IN",
    "ks:ks_name":"Chaitanpur",
    "ks:ks_pop":890,
    "ks:ks_type":"VILLAGE",
    "name:eng_x_preferred":[
        "Chaitanpur"
    ],
    "wof:name":"Chaitanpur",
    "wof:placetype":"locality",
    "wof:population":890
},
  "geometry": {"coordinates":[87.418018,23.336141],"type":"Point"}
}