{
  "type": "Feature",
  "properties": {
    "iso:country":"IN",
    "ks:ks_name":"Vaijnath",
    "ks:ks_pop":383,
    "ks:ks_type":"VILLAGE",
    "name:eng_x_preferred":[
        "Vaijnath"
    ],
    "wof:name":"Vaijnath",
    "wof:placetype":"locality",
    "wof:population":383
},
  "geometry": {"coordinates":[73.214202,18.452264],"type":"Point"}
}