{
  "type": "Feature",
  "properties": {
    "iso:country":"IN",
    "ks:ks_alt_nam":"Naw\u0101dih",
    "ks:ks_name":"Nawadih",
    "ks:ks_pop":27,
    "ks:ks_type":"VILLAGE",
    "name:eng_x_preferred":[
        "Nawadih"
    ],
    "name:eng_x_variant":[
        "Naw\u0101dih"
    ],
    "wof:name":"Nawadih",
    "wof:placetype":"locality",
    "wof:population":27
},
  "geometry": {"coordinates":[85.891762,23.990306],"type":"Point"}
}