{
  "type": "Feature",
  "properties": {
    "gn:admin1_code":"35",
    "gn:admin2_code":"446.0",
    "gn:asciiname":"Ponri",
    "gn:country_code":"IN",
    "gn:dem":560,
    "gn:feature_class":"P",
    "gn:feature_code":"PPL",
    "gn:name":"Ponri",
    "gn:population":0,
    "gn:timezone":"Asia/Kolkata",
    "iso:country":"IN",
    "ks:ks_name":"Pondi",
    "ks:ks_pop":478,
    "ks:ks_type":"HABITATION",
    "name:eng_x_preferred":[
        "Pondi"
    ],
    "name:eng_x_variant":[
        "Ponri"
    ],
    "wof:name":"Pondi",
    "wof:placetype":"locality",
    "wof:population":478
},
  "geometry": {"coordinates":[78.173891,23.20255],"type":"Point"}
}