{
  "type": "Feature",
  "properties": {
    "gn:admin1_code":"34.0",
    "gn:admin2_code":"236.0",
    "gn:asciiname":"Jogini",
    "gn:country_code":"IN",
    "gn:dem":157,
    "gn:feature_class":"P",
    "gn:feature_code":"PPL",
    "gn:name":"Jogini",
    "gn:population":0,
    "gn:timezone":"Asia/Kolkata",
    "iso:country":"IN",
    "ks:ks_name":"Jogini",
    "ks:ks_pop":272,
    "ks:ks_type":"VILLAGE",
    "ks:ks_uagg_main":0,
    "name:eng_x_preferred":[
        "Jogini"
    ],
    "wof:name":"Jogini",
    "wof:placetype":"neighbourhood",
    "wof:population":272
},
  "geometry": {"coordinates":[85.12514299999999,24.582546],"type":"Point"}
}