{
  "type": "Feature",
  "properties": {
    "iso:country":"IN",
    "ks:ks_name":"Amhat",
    "ks:ks_pop":810,
    "ks:ks_type":"VILLAGE",
    "ks:ks_uagg_main":0,
    "name:eng_x_preferred":[
        "Amhat"
    ],
    "wof:name":"Amhat",
    "wof:placetype":"neighbourhood",
    "wof:population":810
},
  "geometry": {"coordinates":[83.993726,27.272544],"type":"Point"}
}