{
  "type": "Feature",
  "properties": {
    "gn:admin1_code":"2.0",
    "gn:admin2_code":"553.0",
    "gn:asciiname":"Brahmadevamarri",
    "gn:country_code":"IN",
    "gn:dem":321,
    "gn:feature_class":"P",
    "gn:feature_code":"PPL",
    "gn:name":"Br\u0101hmadevamarri",
    "gn:population":0,
    "gn:timezone":"Asia/Kolkata",
    "iso:country":"IN",
    "wof:name":"Brahmadevamarri",
    "wof:placetype":"neighbourhood"
},
  "geometry": {"coordinates":[77.95099999999999,14.45381],"type":"Point"}
}