{
  "type": "Feature",
  "properties": {
    "gn:admin1_code":"24",
    "gn:admin2_code":"113.0",
    "gn:asciiname":"Malar",
    "gn:country_code":"IN",
    "gn:dem":209,
    "gn:feature_class":"P",
    "gn:feature_code":"PPL",
    "gn:name":"Mal\u0101r",
    "gn:population":0,
    "gn:timezone":"Asia/Kolkata",
    "iso:country":"IN",
    "name:und_x_variant":[
        "Mal\u0101r",
        "Malh\u0101r"
    ],
    "wof:name":"Malar",
    "wof:placetype":"locality"
},
  "geometry": {"coordinates":[72.38268000000002,27.20303],"type":"Point"}
}