{
  "type": "Feature",
  "properties": {
    "iso:country":"IN",
    "ks:ks_name":"Oraontoli",
    "ks:ks_pop":96,
    "ks:ks_type":"HABITATION",
    "name:eng_x_preferred":[
        "Oraontoli"
    ],
    "wof:name":"Oraontoli",
    "wof:placetype":"locality",
    "wof:population":96
},
  "geometry": {"coordinates":[85.168333,22.36785],"type":"Point"}
}