{
  "type": "Feature",
  "properties": {
    "gn:admin1_code":"37",
    "gn:admin2_code":"406.0",
    "gn:asciiname":"Barela Kalan",
    "gn:country_code":"IN",
    "gn:dem":274,
    "gn:feature_class":"P",
    "gn:feature_code":"PPL",
    "gn:name":"Barela Kal\u0101n",
    "gn:population":0,
    "gn:timezone":"Asia/Kolkata",
    "iso:country":"IN",
    "ks:ks_alt_nam":"Barela Kal\u0101n",
    "ks:ks_name":"Barela Kalan",
    "ks:ks_pop":4520,
    "ks:ks_type":"VILLAGE",
    "ks:ks_uagg_main":0,
    "name:eng_x_preferred":[
        "Barela Kalan"
    ],
    "name:eng_x_variant":[
        "Barela Kal\u0101n"
    ],
    "wof:name":"Barela Kalan",
    "wof:placetype":"neighbourhood",
    "wof:population":4520
},
  "geometry": {"coordinates":[81.864745,22.129488],"type":"Point"}
}