{
  "type": "Feature",
  "properties": {
    "iso:country":"IN",
    "ks:ks_name":"Mererchar",
    "ks:ks_pop":692,
    "ks:ks_type":"VILLAGE",
    "ks:ks_uagg_main":0,
    "name:eng_x_preferred":[
        "Mererchar"
    ],
    "wof:name":"Mererchar",
    "wof:placetype":"neighbourhood",
    "wof:population":692
},
  "geometry": {"coordinates":[90.7197,26.280436],"type":"Point"}
}