{
  "type": "Feature",
  "properties": {
    "gn:admin1_code":"11",
    "gn:admin2_code":"29.0",
    "gn:asciiname":"Chauk",
    "gn:country_code":"IN",
    "gn:dem":550,
    "gn:feature_class":"P",
    "gn:feature_code":"PPL",
    "gn:name":"Chauk",
    "gn:population":0,
    "gn:timezone":"Asia/Kolkata",
    "iso:country":"IN",
    "wof:name":"Chauk",
    "wof:placetype":"locality"
},
  "geometry": {"coordinates":[75.99836999999999,31.77977000000001],"type":"Point"}
}