{
  "type": "Feature",
  "properties": {
    "iso:country":"IN",
    "ks:ks_alt_nam":"Surutaiyan kottai",
    "ks:ks_name":"Surutaiyan Kottai",
    "ks:ks_pop":177,
    "ks:ks_type":"HABITATION",
    "ks:ks_uagg_main":0,
    "name:eng_x_preferred":[
        "Surutaiyan Kottai"
    ],
    "wof:name":"Surutaiyan Kottai",
    "wof:placetype":"neighbourhood",
    "wof:population":177
},
  "geometry": {"coordinates":[78.272057,12.335704],"type":"Point"}
}