{
  "type": "Feature",
  "properties": {
    "gn:admin1_code":"23",
    "gn:admin2_code":"52.0",
    "gn:asciiname":"Dharak Khurd",
    "gn:country_code":"IN",
    "gn:dem":289,
    "gn:feature_class":"P",
    "gn:feature_code":"PPL",
    "gn:name":"Dhar\u0101k Khurd",
    "gn:population":0,
    "gn:timezone":"Asia/Kolkata",
    "iso:country":"IN",
    "ks:ks_name":"Dharak Khurd",
    "ks:ks_pop":373,
    "ks:ks_type":"VILLAGE",
    "ks:ks_uagg_main":0,
    "name:eng_x_preferred":[
        "Dharak Khurd"
    ],
    "wof:name":"Dharak Khurd",
    "wof:placetype":"neighbourhood",
    "wof:population":373
},
  "geometry": {"coordinates":[76.575593,30.686588],"type":"Point"}
}