{
  "type": "Feature",
  "properties": {
    "gn:admin1_code":"23.0",
    "gn:admin2_code":"43.0",
    "gn:asciiname":"Akbarwala",
    "gn:country_code":"IN",
    "gn:dem":209,
    "gn:feature_class":"P",
    "gn:feature_code":"PPL",
    "gn:name":"Akbarw\u0101la",
    "gn:population":0,
    "gn:timezone":"Asia/Kolkata",
    "iso:country":"IN",
    "name:und_x_variant":[
        "Akbarw\u0101la",
        "Ghussuw\u0101la"
    ],
    "wof:name":"Akbarwala",
    "wof:placetype":"locality"
},
  "geometry": {"coordinates":[75.09635,31.10688],"type":"Point"}
}