{
  "type": "Feature",
  "properties": {
    "iso:country":"IN",
    "ks:ks_name":"Tarsadi",
    "ks:ks_pop":18748,
    "ks:ks_type":"URBAN",
    "ks:ks_uagg_main":1,
    "name:eng_x_preferred":[
        "Tarsadi"
    ],
    "wof:name":"Tarsadi",
    "wof:placetype":"neighbourhood",
    "wof:population":18748
},
  "geometry": {"coordinates":[72.953198,21.471471],"type":"Point"}
}