{
  "type": "Feature",
  "properties": {
    "iso:country":"IN",
    "ks:ks_name":"Teliwadi",
    "ks:ks_pop":164,
    "ks:ks_type":"HABITATION",
    "name:eng_x_preferred":[
        "Teliwadi"
    ],
    "wof:name":"Teliwadi",
    "wof:placetype":"locality",
    "wof:population":164
},
  "geometry": {"coordinates":[73.53444399999999,17.258056],"type":"Point"}
}