{
  "type": "Feature",
  "properties": {
    "iso:country":"IN",
    "ks:ks_name":"Amarapura",
    "ks:ks_pop":189,
    "ks:ks_type":"HABITATION",
    "name:eng_x_preferred":[
        "Amarapura"
    ],
    "wof:name":"Amarapura",
    "wof:placetype":"locality",
    "wof:population":189
},
  "geometry": {"coordinates":[74.871439,23.456948],"type":"Point"}
}