{
  "type": "Feature",
  "properties": {
    "iso:country":"IN",
    "ks:ks_name":"Kothodi",
    "ks:ks_pop":166,
    "ks:ks_type":"VILLAGE",
    "name:eng_x_preferred":[
        "Kothodi"
    ],
    "wof:name":"Kothodi",
    "wof:placetype":"locality",
    "wof:population":166
},
  "geometry": {"coordinates":[81.397603,20.050479],"type":"Point"}
}