{
  "type": "Feature",
  "properties": {
    "iso:country":"IN",
    "ks:ks_name":"Huralihaklu",
    "ks:ks_pop":121,
    "ks:ks_type":"HABITATION",
    "name:eng_x_preferred":[
        "Huralihaklu"
    ],
    "wof:name":"Huralihaklu",
    "wof:placetype":"locality",
    "wof:population":121
},
  "geometry": {"coordinates":[75.310357,13.42336],"type":"Point"}
}