{
  "type": "Feature",
  "properties": {
    "iso:country":"IN",
    "ks:ks_name":"Khajuriguda",
    "ks:ks_pop":69,
    "ks:ks_type":"HABITATION",
    "name:eng_x_preferred":[
        "Khajuriguda"
    ],
    "wof:name":"Khajuriguda",
    "wof:placetype":"locality",
    "wof:population":69
},
  "geometry": {"coordinates":[82.84247999999999,18.489344],"type":"Point"}
}