{
  "type": "Feature",
  "properties": {
    "iso:country":"IN",
    "ks:ks_name":"Thirupathi Vattam",
    "ks:ks_pop":101,
    "ks:ks_type":"HABITATION",
    "name:eng_x_preferred":[
        "Thirupathi Vattam"
    ],
    "wof:name":"Thirupathi Vattam",
    "wof:placetype":"locality",
    "wof:population":101
},
  "geometry": {"coordinates":[78.537119,12.642484],"type":"Point"}
}