{
  "type": "Feature",
  "properties": {
    "iso:country":"IN",
    "ks:ks_name":"Patilwadi",
    "ks:ks_pop":95,
    "ks:ks_type":"HABITATION",
    "name:eng_x_preferred":[
        "Patilwadi"
    ],
    "wof:name":"Patilwadi",
    "wof:placetype":"locality",
    "wof:population":95
},
  "geometry": {"coordinates":[73.66249999999999,17.176111],"type":"Point"}
}