{
  "type": "Feature",
  "properties": {
    "iso:country":"IN",
    "ks:ks_name":"Palayakariyampalayam",
    "ks:ks_pop":250,
    "ks:ks_type":"HABITATION",
    "name:eng_x_preferred":[
        "Palayakariyampalayam"
    ],
    "wof:name":"Palayakariyampalayam",
    "wof:placetype":"locality",
    "wof:population":250
},
  "geometry": {"coordinates":[77.987664,11.4103],"type":"Point"}
}