{
  "type": "Feature",
  "properties": {
    "gn:admin1_code":"11.0",
    "gn:admin2_code":"033",
    "gn:asciiname":"Madrayah",
    "gn:country_code":"IN",
    "gn:dem":985,
    "gn:feature_class":"P",
    "gn:feature_code":"PPL",
    "gn:name":"Madray\u0101h",
    "gn:population":0,
    "gn:timezone":"Asia/Kolkata",
    "iso:country":"IN",
    "wof:name":"Madrayah",
    "wof:placetype":"locality"
},
  "geometry": {"coordinates":[77.015,31.21306],"type":"Point"}
}