{
  "type": "Feature",
  "properties": {
    "iso:country":"IN",
    "ks:ks_name":"Kalale",
    "ks:ks_pop":10,
    "ks:ks_type":"HABITATION",
    "name:eng_x_preferred":[
        "Kalale"
    ],
    "wof:name":"Kalale",
    "wof:placetype":"locality",
    "wof:population":10
},
  "geometry": {"coordinates":[74.747857,14.43689],"type":"Point"}
}