{
  "type": "Feature",
  "properties": {
    "gn:admin1_code":"36.0",
    "gn:admin2_code":"138",
    "gn:asciiname":"Bhatipura Manakpur",
    "gn:country_code":"IN",
    "gn:dem":223,
    "gn:feature_class":"P",
    "gn:feature_code":"PPL",
    "gn:name":"Bhatipura M\u0101nakpur",
    "gn:population":0,
    "gn:timezone":"Asia/Kolkata",
    "iso:country":"IN",
    "name:und_x_variant":[
        "Bhatipura M\u0101nakpur",
        "Bhatipura Manakpur"
    ],
    "wof:name":"Bhatipura Manakpur",
    "wof:placetype":"neighbourhood"
},
  "geometry": {"coordinates":[77.85142999999999,28.91165],"type":"Point"}
}