{
  "type": "Feature",
  "properties": {
    "gn:admin1_code":"34.0",
    "gn:admin2_code":"237.0",
    "gn:asciiname":"Takiya",
    "gn:country_code":"IN",
    "gn:dem":130,
    "gn:feature_class":"P",
    "gn:feature_code":"PPL",
    "gn:name":"Takiya",
    "gn:population":0,
    "gn:timezone":"Asia/Kolkata",
    "iso:country":"IN",
    "ks:ks_name":"Takiya",
    "ks:ks_type":"VILLAGE",
    "name:eng_x_preferred":[
        "Takiya"
    ],
    "wof:name":"Takiya",
    "wof:placetype":"locality"
},
  "geometry": {"coordinates":[85.427181,24.681826],"type":"Point"}
}