{
  "type": "Feature",
  "properties": {
    "iso:country":"IN",
    "ks:ks_alt_nam":"chandalmundar",
    "ks:ks_name":"Chandalmundar",
    "ks:ks_pop":390,
    "ks:ks_type":"HABITATION",
    "name:eng_x_preferred":[
        "Chandalmundar"
    ],
    "wof:name":"Chandalmundar",
    "wof:placetype":"locality",
    "wof:population":390
},
  "geometry": {"coordinates":[82.72551,18.714971],"type":"Point"}
}