{
  "type": "Feature",
  "properties": {
    "iso:country":"IN",
    "ks:ks_name":"Belvariya Tola",
    "ks:ks_pop":128,
    "ks:ks_type":"HABITATION",
    "ks:ks_uagg_main":0,
    "name:eng_x_preferred":[
        "Belvariya Tola"
    ],
    "wof:name":"Belvariya Tola",
    "wof:placetype":"neighbourhood",
    "wof:population":128
},
  "geometry": {"coordinates":[83.934765,27.154947],"type":"Point"}
}