{
  "type": "Feature",
  "properties": {
    "iso:country":"IN",
    "ks:ks_name":"Dugela Talab",
    "ks:ks_pop":221,
    "ks:ks_type":"HABITATION",
    "name:eng_x_preferred":[
        "Dugela Talab"
    ],
    "wof:name":"Dugela Talab",
    "wof:placetype":"locality",
    "wof:population":221
},
  "geometry": {"coordinates":[73.745189,23.705633],"type":"Point"}
}