{
  "type": "Feature",
  "properties": {
    "iso:country":"IN",
    "ks:ks_name":"Khanpur",
    "ks:ks_pop":894,
    "ks:ks_type":"VILLAGE",
    "ks:ks_uagg_main":0,
    "name:eng_x_preferred":[
        "Khanpur"
    ],
    "wof:name":"Khanpur",
    "wof:placetype":"neighbourhood",
    "wof:population":894
},
  "geometry": {"coordinates":[88.140896,22.147149],"type":"Point"}
}