{
  "type": "Feature",
  "properties": {
    "iso:country":"IN",
    "ks:ks_name":"Holemadlu",
    "ks:ks_pop":37,
    "ks:ks_type":"HABITATION",
    "name:eng_x_preferred":[
        "Holemadlu"
    ],
    "wof:name":"Holemadlu",
    "wof:placetype":"locality",
    "wof:population":37
},
  "geometry": {"coordinates":[75.20885699999999,13.646709],"type":"Point"}
}