{
  "type": "Feature",
  "properties": {
    "iso:country":"IN",
    "ks:ks_name":"Ramannapakalu",
    "ks:ks_pop":231,
    "ks:ks_type":"HABITATION",
    "name:eng_x_preferred":[
        "Ramannapakalu"
    ],
    "wof:name":"Ramannapakalu",
    "wof:placetype":"locality",
    "wof:population":231
},
  "geometry": {"coordinates":[82.510848,17.798725],"type":"Point"}
}