{
  "type": "Feature",
  "properties": {
    "iso:country":"IN",
    "ks:ks_name":"Akawani",
    "ks:ks_pop":345,
    "ks:ks_type":"HABITATION",
    "name:eng_x_preferred":[
        "Akawani"
    ],
    "wof:name":"Akawani",
    "wof:placetype":"locality",
    "wof:population":345
},
  "geometry": {"coordinates":[74.129722,21.86888],"type":"Point"}
}