{
  "type": "Feature",
  "properties": {
    "iso:country":"IN",
    "ks:ks_name":"Ambatanr",
    "ks:ks_pop":472,
    "ks:ks_type":"VILLAGE",
    "name:eng_x_preferred":[
        "Ambatanr"
    ],
    "wof:name":"Ambatanr",
    "wof:placetype":"locality",
    "wof:population":472
},
  "geometry": {"coordinates":[86.679687,24.451116],"type":"Point"}
}