{
  "type": "Feature",
  "properties": {
    "gn:admin1_code":"34.0",
    "gn:admin2_code":"229.0",
    "gn:asciiname":"Sakraura",
    "gn:country_code":"IN",
    "gn:dem":56,
    "gn:feature_class":"P",
    "gn:feature_code":"PPL",
    "gn:name":"Sakraura",
    "gn:population":0,
    "gn:timezone":"Asia/Kolkata",
    "iso:country":"IN",
    "ks:ks_name":"Sakraura",
    "ks:ks_pop":895,
    "ks:ks_type":"HABITATION",
    "name:eng_x_preferred":[
        "Sakraura"
    ],
    "wof:name":"Sakraura",
    "wof:placetype":"locality",
    "wof:population":895
},
  "geometry": {"coordinates":[85.326509,25.356874],"type":"Point"}
}