{
  "type": "Feature",
  "properties": {
    "iso:country":"IN",
    "ks:ks_name":"Tekalamila",
    "ks:ks_pop":355,
    "ks:ks_type":"VILLAGE",
    "name:eng_x_preferred":[
        "Tekalamila"
    ],
    "wof:name":"Tekalamila",
    "wof:placetype":"locality",
    "wof:population":355
},
  "geometry": {"coordinates":[83.778794,20.007756],"type":"Point"}
}