{
  "type": "Feature",
  "properties": {
    "iso:country":"IN",
    "ks:ks_name":"Kabirpura",
    "ks:ks_pop":377,
    "ks:ks_type":"HABITATION",
    "name:eng_x_preferred":[
        "Kabirpura"
    ],
    "wof:name":"Kabirpura",
    "wof:placetype":"locality",
    "wof:population":377
},
  "geometry": {"coordinates":[71.641671,27.557632],"type":"Point"}
}