{
  "type": "Feature",
  "properties": {
    "gn:admin1_code":"35",
    "gn:admin2_code":"429.0",
    "gn:asciiname":"Amlia",
    "gn:country_code":"IN",
    "gn:dem":333,
    "gn:feature_class":"P",
    "gn:feature_code":"PPL",
    "gn:name":"Amlia",
    "gn:population":0,
    "gn:timezone":"Asia/Kolkata",
    "iso:country":"IN",
    "name:cat_x_preferred":[
        "Amlia"
    ],
    "name:ceb_x_preferred":[
        "Amlia Island"
    ],
    "name:deu_x_preferred":[
        "Amlia Island"
    ],
    "name:fra_x_preferred":[
        "Amlia"
    ],
    "name:ita_x_preferred":[
        "Amlia"
    ],
    "name:jpn_x_preferred":[
        "\u30a2\u30e0\u30ea\u30a2\u5cf6"
    ],
    "name:rus_x_preferred":[
        "\u0410\u043c\u043b\u044f"
    ],
    "name:srp_x_preferred":[
        "\u0410\u043c\u043b\u0438\u0458\u0430"
    ],
    "name:ukr_x_preferred":[
        "\u0410\u043c\u043b\u044f"
    ],
    "name:zho_x_preferred":[
        "\u963f\u7c73\u5229\u4e9e\u5cf6"
    ],
    "wof:name":"Amlia",
    "wof:placetype":"locality"
},
  "geometry": {"coordinates":[80.5654,24.61699],"type":"Point"}
}