{
  "type": "Feature",
  "properties": {
    "gn:admin1_code":"37",
    "gn:admin2_code":"408.0",
    "gn:asciiname":"Jamri",
    "gn:country_code":"IN",
    "gn:dem":361,
    "gn:feature_class":"P",
    "gn:feature_code":"PPL",
    "gn:name":"J\u0101mri",
    "gn:population":0,
    "gn:timezone":"Asia/Kolkata",
    "iso:country":"IN",
    "ks:ks_name":"Jamdi",
    "ks:ks_pop":659,
    "ks:ks_type":"VILLAGE",
    "name:eng_x_preferred":[
        "Jamdi"
    ],
    "name:eng_x_variant":[
        "Jamri"
    ],
    "wof:name":"Jamdi",
    "wof:placetype":"locality",
    "wof:population":659
},
  "geometry": {"coordinates":[80.625612,20.351434],"type":"Point"}
}