{
  "type": "Feature",
  "properties": {
    "iso:country":"IN",
    "ks:ks_name":"Bhagwangarh",
    "ks:ks_pop":153,
    "ks:ks_type":"HABITATION",
    "name:eng_x_preferred":[
        "Bhagwangarh"
    ],
    "wof:name":"Bhagwangarh",
    "wof:placetype":"locality",
    "wof:population":153
},
  "geometry": {"coordinates":[82.722016,23.428297],"type":"Point"}
}