{
  "type": "Feature",
  "properties": {
    "gn:admin1_code":"16.0",
    "gn:admin2_code":"507.0",
    "gn:asciiname":"Pandharpur",
    "gn:country_code":"IN",
    "gn:dem":329,
    "gn:feature_class":"P",
    "gn:feature_code":"PPL",
    "gn:name":"Pandharpur",
    "gn:population":0,
    "gn:timezone":"Asia/Kolkata",
    "iso:country":"IN",
    "wof:name":"Pandharpur",
    "wof:placetype":"locality"
},
  "geometry": {"coordinates":[80.39451,21.19798],"type":"Point"}
}