{
  "type": "Feature",
  "properties": {
    "gn:admin1_code":"16.0",
    "gn:admin2_code":"507.0",
    "gn:asciiname":"Pandharpur",
    "gn:country_code":"IN",
    "gn:dem":329,
    "gn:feature_class":"P",
    "gn:feature_code":"PPL",
    "gn:name":"Pandharpur",
    "gn:population":0,
    "gn:timezone":"Asia/Kolkata",
    "iso:country":"IN",
    "name:ben_x_preferred":[
        "\u09aa\u09a3\u09cd\u09a2\u09b0\u09aa\u09c1\u09b0"
    ],
    "name:bpy_x_preferred":[
        "\u09aa\u09be\u09a7\u09b0\u09aa\u09c1\u09b0"
    ],
    "name:cat_x_preferred":[
        "Pandharpur"
    ],
    "name:ceb_x_preferred":[
        "Pandharpur"
    ],
    "name:hif_x_preferred":[
        "Pandharpur"
    ],
    "name:hin_x_preferred":[
        "\u092a\u0902\u0922\u0930\u092a\u0941\u0930"
    ],
    "name:ita_x_preferred":[
        "Pandharpur"
    ],
    "name:kan_x_preferred":[
        "\u0caa\u0c82\u0ca2\u0cb0\u0caa\u0cc1\u0cb0"
    ],
    "name:mal_x_preferred":[
        "\u0d2a\u0d23\u0d4d\u0d21\u0d7c\u0d2a\u0d42\u0d7c"
    ],
    "name:mar_x_preferred":[
        "\u092a\u0902\u0922\u0930\u092a\u0942\u0930"
    ],
    "name:msa_x_preferred":[
        "Pandharpur"
    ],
    "name:nld_x_preferred":[
        "Pandharpur"
    ],
    "name:ori_x_preferred":[
        "\u0b2a\u0b3e\u0b23\u0b4d\u0b22\u0b3e\u0b30\u0b2a\u0b41\u0b30"
    ],
    "name:pam_x_preferred":[
        "Pandharpur"
    ],
    "name:rus_x_preferred":[
        "\u041f\u0430\u043d\u0434\u0445\u0430\u0440\u043f\u0443\u0440"
    ],
    "name:swe_x_preferred":[
        "Pandharpur"
    ],
    "name:tam_x_preferred":[
        "\u0baa\u0ba3\u0bcd\u0b9f\u0bb0\u0bbf\u0baa\u0bc1\u0bb0\u0bae\u0bcd"
    ],
    "name:tel_x_preferred":[
        "\u0c2a\u0c02\u0c21\u0c30\u0c40\u0c2a\u0c41\u0c30\u0c2e\u0c41"
    ],
    "name:urd_x_preferred":[
        "\u067e\u0646\u0688\u06be\u0631\u067e\u0648\u0631"
    ],
    "name:vie_x_preferred":[
        "Pandharpur"
    ],
    "name:zho_x_preferred":[
        "\u6f58\u8fbe\u5c14\u666e\u5c14"
    ],
    "wof:name":"Pandharpur",
    "wof:placetype":"locality"
},
  "geometry": {"coordinates":[80.39451,21.19798],"type":"Point"}
}