{
  "type": "Feature",
  "properties": {
    "iso:country":"IN",
    "ks:ks_name":"Khalihai Pathar",
    "ks:ks_pop":230,
    "ks:ks_type":"VILLAGE",
    "name:eng_x_preferred":[
        "Khalihai Pathar"
    ],
    "wof:name":"Khalihai Pathar",
    "wof:placetype":"locality",
    "wof:population":230
},
  "geometry": {"coordinates":[93.66268700000001,26.883549],"type":"Point"}
}