{
  "type": "Feature",
  "properties": {
    "gn:admin1_code":"11.0",
    "gn:admin2_code":"31.0",
    "gn:asciiname":"Kin",
    "gn:country_code":"IN",
    "gn:dem":1166,
    "gn:feature_class":"P",
    "gn:feature_code":"PPL",
    "gn:name":"Kin",
    "gn:population":0,
    "gn:timezone":"Asia/Kolkata",
    "iso:country":"IN",
    "wof:name":"Kin",
    "wof:placetype":"locality"
},
  "geometry": {"coordinates":[77.13602,30.975],"type":"Point"}
}