{
  "type": "Feature",
  "properties": {
    "gn:admin1_code":"11.0",
    "gn:admin2_code":"31.0",
    "gn:asciiname":"Kin",
    "gn:country_code":"IN",
    "gn:dem":1166,
    "gn:feature_class":"P",
    "gn:feature_code":"PPL",
    "gn:name":"Kin",
    "gn:population":0,
    "gn:timezone":"Asia/Kolkata",
    "iso:country":"IN",
    "name:ara_x_preferred":[
        "\u0639\u0634\u064a\u0631\u0629"
    ],
    "name:ceb_x_preferred":[
        "Kin"
    ],
    "name:fin_x_preferred":[
        "Kin"
    ],
    "name:mya_x_preferred":[
        "\u1000\u1004\u103a\u1038\u101b\u103d\u102c\u104a \u101b\u1014\u103a\u1000\u102f\u1014\u103a"
    ],
    "name:nld_x_preferred":[
        "Kin"
    ],
    "name:pol_x_preferred":[
        "Kin"
    ],
    "name:por_x_preferred":[
        "Kin"
    ],
    "name:rus_x_preferred":[
        "\u041a\u0438\u043d"
    ],
    "name:spa_x_preferred":[
        "Kin"
    ],
    "name:swe_x_preferred":[
        "Kin"
    ],
    "name:zho_x_preferred":[
        "Kin"
    ],
    "wof:name":"Kin",
    "wof:placetype":"locality"
},
  "geometry": {"coordinates":[77.13602,30.975],"type":"Point"}
}