{
  "type": "Feature",
  "properties": {
    "gn:admin1_code":"24",
    "gn:admin2_code":"130.0",
    "gn:asciiname":"Kundela",
    "gn:country_code":"IN",
    "gn:dem":464,
    "gn:feature_class":"P",
    "gn:feature_code":"PPL",
    "gn:name":"Kundela",
    "gn:population":0,
    "gn:timezone":"Asia/Kolkata",
    "iso:country":"IN",
    "ks:ks_name":"Kandela",
    "ks:ks_pop":567,
    "ks:ks_type":"VILLAGE",
    "name:eng_x_preferred":[
        "Kandela"
    ],
    "name:eng_x_variant":[
        "Kundela"
    ],
    "wof:name":"Kandela",
    "wof:placetype":"locality",
    "wof:population":567
},
  "geometry": {"coordinates":[74.2697,24.258942],"type":"Point"}
}