{
  "type": "Feature",
  "properties": {
    "gn:admin1_code":"24",
    "gn:admin2_code":"130.0",
    "gn:asciiname":"Kundela",
    "gn:country_code":"IN",
    "gn:dem":464,
    "gn:feature_class":"P",
    "gn:feature_code":"PPL",
    "gn:name":"Kundela",
    "gn:population":0,
    "gn:timezone":"Asia/Kolkata",
    "iso:country":"IN",
    "wof:name":"Kundela",
    "wof:placetype":"locality"
},
  "geometry": {"coordinates":[74.26938,24.26232000000001],"type":"Point"}
}