{
  "type": "Feature",
  "properties": {
    "iso:country":"IN",
    "ks:ks_name":"Malimala",
    "ks:ks_pop":510,
    "ks:ks_type":"HABITATION",
    "name:eng_x_preferred":[
        "Malimala"
    ],
    "wof:name":"Malimala",
    "wof:placetype":"locality",
    "wof:population":510
},
  "geometry": {"coordinates":[75.29018000000001,17.521641],"type":"Point"}
}