{
  "type": "Feature",
  "properties": {
    "gn:admin1_code":"34.0",
    "gn:admin2_code":"218.0",
    "gn:asciiname":"Teghra",
    "gn:country_code":"IN",
    "gn:dem":68,
    "gn:feature_class":"P",
    "gn:feature_code":"PPL",
    "gn:name":"Teghra",
    "gn:population":0,
    "gn:timezone":"Asia/Kolkata",
    "iso:country":"IN",
    "ks:ks_name":"Teghra",
    "ks:ks_pop":2117,
    "ks:ks_type":"VILLAGE",
    "ks:ks_uagg_main":0,
    "name:eng_x_preferred":[
        "Teghra"
    ],
    "wof:name":"Teghra",
    "wof:placetype":"neighbourhood",
    "wof:population":2117
},
  "geometry": {"coordinates":[84.51657899999999,26.1414],"type":"Point"}
}