{
  "type": "Feature",
  "properties": {
    "gn:country":"IN",
    "iso:country":"IN",
    "name:ara_x_preferred":[
        "\u062a\u064a\u0641\u0627\u064a \u0641\u0627\u062f\u0648"
    ],
    "name:ben_bn_x_preferred":[
        "\u09a4\u09bf\u09ad\u09be\u0987\u09ad\u09be\u09a1\u09cd\u09a1\u09cb"
    ],
    "name:ben_in_x_preferred":[
        "\u09a4\u09bf\u09ad\u09be\u0987\u09ad\u09be\u09a1\u09cd\u09a1\u09cb"
    ],
    "name:guj_x_preferred":[
        "\u0aa4\u0abf\u0ab5\u0ac8\u0ab5\u0abe\u0aa6\u0acd\u0aa6\u0acb"
    ],
    "name:hin_x_preferred":[
        "\u0924\u093f\u0935\u0908\u0935\u093e\u0926\u094d\u0926\u094b"
    ],
    "name:kan_x_preferred":[
        "\u0ca4\u0cbf\u0cb5\u0cc8\u0cb5\u0ca6\u0ccd\u0ca6\u0cca"
    ],
    "name:mal_x_preferred":[
        "\u0d24\u0d3f\u0d35\u0d48\u0d35\u0d26\u0d4d\u0d26\u0d4b"
    ],
    "name:mar_x_preferred":[
        "\u0924\u093f\u0935\u093e\u0908 \u0935\u0921\u094b"
    ],
    "name:pan_x_preferred":[
        "\u0a1f\u0a3f\u0a35\u0a3e\u0a07\u0a35\u0a3e\u0a21\u0a4b"
    ],
    "name:tam_x_preferred":[
        "\u0b9f\u0bbf\u0bb5\u0bbe\u0baf\u0bcd\u0bb5\u0b9f\u0bcd\u0b9f\u0bca"
    ],
    "name:tel_x_preferred":[
        "\u0c1f\u0c3f\u0c35\u0c48\u0c35\u0c21\u0c4d\u0c21\u0c4b"
    ],
    "name:urd_x_preferred":[
        "\u062a\u0648\u06cc\u0648\u0627\u0626\u06cc\u0648\u0627\u0688\u0648"
    ],
    "qs:name":"Tivaivaddo",
    "qs:name_adm0":"India",
    "qs:name_adm1":"Goa",
    "qs:photos":115,
    "qs:photos_1k":23,
    "qs:photos_9k":1,
    "qs:photos_9r":3,
    "qs:photos_all":115,
    "qs:photos_sr":3,
    "qs:placetype":"Suburb",
    "qs:pop_sr":"0",
    "wof:name":"Tivaivaddo",
    "wof:placetype":"neighbourhood"
},
  "geometry": {"coordinates":[73.757057,15.535729],"type":"Point"}
}