{
  "type": "Feature",
  "properties": {
    "gn:country":"IN",
    "iso:country":"IN",
    "qs:name":"Tivaivaddo",
    "qs:name_adm0":"India",
    "qs:name_adm1":"Goa",
    "qs:photos":115,
    "qs:photos_1k":23,
    "qs:photos_9k":1,
    "qs:photos_9r":3,
    "qs:photos_all":115,
    "qs:photos_sr":3,
    "qs:placetype":"Suburb",
    "qs:pop_sr":"0",
    "wof:name":"Tivaivaddo",
    "wof:placetype":"neighbourhood"
},
  "geometry": {"coordinates":[73.757057,15.535729],"type":"Point"}
}