{
  "type": "Feature",
  "properties": {
    "gn:admin1_code":"11",
    "gn:admin2_code":"33.0",
    "gn:asciiname":"Bagheli",
    "gn:country_code":"IN",
    "gn:dem":1569,
    "gn:feature_class":"P",
    "gn:feature_code":"PPL",
    "gn:name":"Bagheli",
    "gn:population":0,
    "gn:timezone":"Asia/Kolkata",
    "iso:country":"IN",
    "wof:name":"Bagheli",
    "wof:placetype":"locality"
},
  "geometry": {"coordinates":[77.10562,31.0953],"type":"Point"}
}