{
  "type": "Feature",
  "properties": {
    "gn:admin1_code":"19.0",
    "gn:admin2_code":"574.0",
    "gn:asciiname":"Padavalalu",
    "gn:country_code":"IN",
    "gn:dem":947,
    "gn:feature_class":"P",
    "gn:feature_code":"PPL",
    "gn:name":"Padavalalu",
    "gn:population":0,
    "gn:timezone":"Asia/Kolkata",
    "iso:country":"IN",
    "wof:name":"Padavalalu",
    "wof:placetype":"locality"
},
  "geometry": {"coordinates":[75.94166,13.07671],"type":"Point"}
}