{
  "type": "Feature",
  "properties": {
    "gn:admin1_code":"38.0",
    "gn:admin2_code":"351.0",
    "gn:asciiname":"Bhandaridih Mal",
    "gn:country_code":"IN",
    "gn:dem":68,
    "gn:feature_class":"P",
    "gn:feature_code":"PPL",
    "gn:name":"Bh\u0101nd\u0101r\u012bdih M\u0101l",
    "gn:population":0,
    "gn:timezone":"Asia/Kolkata",
    "iso:country":"IN",
    "wof:name":"Bhandaridih Mal",
    "wof:placetype":"locality"
},
  "geometry": {"coordinates":[87.26413000000002,25.00319],"type":"Point"}
}