{
  "type": "Feature",
  "properties": {
    "gn:country":"IN",
    "gn:fcode":"PPL",
    "gn:population":0,
    "iso:country":"IN",
    "name:ara_x_preferred":[
        "\u0644\u0627\u0634\u0643\u0627\u0631"
    ],
    "name:ben_bn_x_preferred":[
        "\u09b2\u09b8\u09cd\u0995\u09b0"
    ],
    "name:ben_in_x_preferred":[
        "\u09b2\u09b8\u09cd\u0995\u09b0"
    ],
    "name:guj_x_preferred":[
        "\u0ab2\u0abe\u0ab6\u0a95\u0ab0"
    ],
    "name:hin_x_preferred":[
        "\u0932\u0936\u094d\u0915\u0930"
    ],
    "name:kan_x_preferred":[
        "\u0cb2\u0cb7\u0ccd\u0c95\u0cb0\u0ccd"
    ],
    "name:mal_x_preferred":[
        "\u0d32\u0d37\u0d4d"
    ],
    "name:mar_x_preferred":[
        "\u0932\u0937\u094d\u0915\u0930"
    ],
    "name:pan_x_preferred":[
        "\u0a32\u0a36\u0a15\u0a30"
    ],
    "name:tam_x_preferred":[
        "\u0bb2\u0bb7\u0bcd\u0b95\u0bb0\u0bcd"
    ],
    "name:tel_x_preferred":[
        "\u0c32\u0c15\u0c4d\u0c37\u0c30\u0c4d"
    ],
    "name:urd_x_preferred":[
        "\u0644\u0634\u06a9\u0631"
    ],
    "qs:name":"Lashkar",
    "qs:name_adm0":"India",
    "qs:name_adm1":"Madhya Pradesh",
    "qs:photos":16,
    "qs:photos_1k":3,
    "qs:photos_9k":1,
    "qs:photos_9r":1,
    "qs:photos_all":16,
    "qs:photos_sr":1,
    "qs:placetype":"Suburb",
    "qs:pop_sr":"7",
    "wd:wordcount":128,
    "wof:name":"Lashkar",
    "wof:placetype":"neighbourhood",
    "wof:population":0
},
  "geometry": {"coordinates":[78.15326,26.19966],"type":"Point"}
}