{
  "type": "Feature",
  "properties": {
    "iso:country":"IN",
    "ks:ks_name":"Bhagatolaa",
    "ks:ks_pop":871,
    "ks:ks_type":"HABITATION",
    "name:eng_x_preferred":[
        "Bhagatolaa"
    ],
    "wof:name":"Bhagatolaa",
    "wof:placetype":"locality",
    "wof:population":871
},
  "geometry": {"coordinates":[84.757229,22.096488],"type":"Point"}
}