{
  "type": "Feature",
  "properties": {
    "iso:country":"IN",
    "ks:ks_name":"Alagdiha",
    "ks:ks_pop":124,
    "ks:ks_type":"HABITATION",
    "name:eng_x_preferred":[
        "Alagdiha"
    ],
    "wof:name":"Alagdiha",
    "wof:placetype":"locality",
    "wof:population":124
},
  "geometry": {"coordinates":[85.315375,24.432491],"type":"Point"}
}