{
  "type": "Feature",
  "properties": {
    "iso:country":"IN",
    "ks:ks_name":"Brahmano Ki Dhani",
    "ks:ks_pop":573,
    "ks:ks_type":"HABITATION",
    "name:eng_x_preferred":[
        "Brahmano Ki Dhani"
    ],
    "wof:name":"Brahmano Ki Dhani",
    "wof:placetype":"locality",
    "wof:population":573
},
  "geometry": {"coordinates":[71.328925,25.856108],"type":"Point"}
}