{
  "type": "Feature",
  "properties": {
    "gn:admin1_code":"12.0",
    "gn:admin2_code":"9.0",
    "gn:asciiname":"Takia Rasul Shah",
    "gn:country_code":"IN",
    "gn:dem":1624,
    "gn:feature_class":"P",
    "gn:feature_code":"PPL",
    "gn:name":"Takia Ras\u016bl Shah",
    "gn:population":0,
    "gn:timezone":"Asia/Kolkata",
    "iso:country":"IN",
    "name:eng_x_preferred":[
        "Takia Ras\u016bl Shah"
    ],
    "wof:name":"Takia Rasul Shah",
    "wof:placetype":"locality"
},
  "geometry": {"coordinates":[74.66683,34.40838],"type":"Point"}
}