{
  "type": "Feature",
  "properties": {
    "gn:admin1_code":"36.0",
    "gn:admin2_code":"158.0",
    "gn:asciiname":"Amalia",
    "gn:country_code":"IN",
    "gn:dem":116,
    "gn:feature_class":"P",
    "gn:feature_code":"PPL",
    "gn:name":"Amalia",
    "gn:population":0,
    "gn:timezone":"Asia/Kolkata",
    "iso:country":"IN",
    "name:bre_x_preferred":[
        "Amalia"
    ],
    "name:fra_x_preferred":[
        "Amalia"
    ],
    "name:ita_x_preferred":[
        "Amalia"
    ],
    "name:jpn_x_preferred":[
        "\u30a2\u30de\u30ea\u30a2"
    ],
    "name:kor_x_preferred":[
        "\uc544\ub9d0\ub9ac\uc544"
    ],
    "name:nld_x_preferred":[
        "Amalia"
    ],
    "name:por_x_preferred":[
        "Am\u00e1lia"
    ],
    "name:ron_x_preferred":[
        "Amalia"
    ],
    "name:rus_x_preferred":[
        "\u0410\u043c\u0430\u043b\u0438\u044f"
    ],
    "name:spa_x_preferred":[
        "Amalia"
    ],
    "wof:name":"Amalia",
    "wof:placetype":"locality"
},
  "geometry": {"coordinates":[81.35908000000001,26.48944],"type":"Point"}
}