{
  "type": "Feature",
  "properties": {
    "iso:country":"IN",
    "ks:ks_name":"Lower Sirubari",
    "ks:ks_pop":613,
    "ks:ks_type":"HABITATION",
    "name:eng_x_preferred":[
        "Lower Sirubari"
    ],
    "wof:name":"Lower Sirubari",
    "wof:placetype":"locality",
    "wof:population":613
},
  "geometry": {"coordinates":[88.291505,26.858097],"type":"Point"}
}