{
  "type": "Feature",
  "properties": {
    "iso:country":"IN",
    "ks:ks_name":"Thalkarwadi",
    "ks:ks_pop":194,
    "ks:ks_type":"HABITATION",
    "name:eng_x_preferred":[
        "Thalkarwadi"
    ],
    "wof:name":"Thalkarwadi",
    "wof:placetype":"locality",
    "wof:population":194
},
  "geometry": {"coordinates":[73.57397,16.153792],"type":"Point"}
}