{
  "type": "Feature",
  "properties": {
    "gn:admin1_code":"11",
    "gn:admin2_code":"24.0",
    "gn:asciiname":"Muktehr",
    "gn:country_code":"IN",
    "gn:dem":791,
    "gn:feature_class":"P",
    "gn:feature_code":"PPL",
    "gn:name":"Muktehr",
    "gn:population":0,
    "gn:timezone":"Asia/Kolkata",
    "iso:country":"IN",
    "wof:name":"Muktehr",
    "wof:placetype":"locality"
},
  "geometry": {"coordinates":[76.36553000000001,31.93257],"type":"Point"}
}