{
  "type": "Feature",
  "properties": {
    "iso:country":"IN",
    "ks:ks_name":"Gher Tipera",
    "ks:ks_pop":507,
    "ks:ks_type":"HABITATION",
    "name:eng_x_preferred":[
        "Gher Tipera"
    ],
    "wof:name":"Gher Tipera",
    "wof:placetype":"locality",
    "wof:population":507
},
  "geometry": {"coordinates":[78.36347000000001,28.288858],"type":"Point"}
}