{
  "type": "Feature",
  "properties": {
    "iso:country":"IN",
    "ks:ks_name":"Singardih",
    "ks:ks_pop":681,
    "ks:ks_type":"VILLAGE",
    "ks:ks_uagg_main":0,
    "name:eng_x_preferred":[
        "Singardih"
    ],
    "wof:name":"Singardih",
    "wof:placetype":"neighbourhood",
    "wof:population":681
},
  "geometry": {"coordinates":[86.749127,24.498241],"type":"Point"}
}