{
  "type": "Feature",
  "properties": {
    "iso:country":"IN",
    "ks:ks_name":"Dakshinpara",
    "ks:ks_pop":310,
    "ks:ks_type":"HABITATION",
    "ks:ks_uagg_main":0,
    "name:eng_x_preferred":[
        "Dakshinpara"
    ],
    "wof:name":"Dakshinpara",
    "wof:placetype":"neighbourhood",
    "wof:population":310
},
  "geometry": {"coordinates":[91.16618800000001,23.642628],"type":"Point"}
}