{
  "type": "Feature",
  "properties": {
    "iso:country":"IN",
    "ks:ks_name":"Hegdemane",
    "ks:ks_pop":67,
    "ks:ks_type":"HABITATION",
    "name:eng_x_preferred":[
        "Hegdemane"
    ],
    "wof:name":"Hegdemane",
    "wof:placetype":"locality",
    "wof:population":67
},
  "geometry": {"coordinates":[74.658422,14.949222],"type":"Point"}
}