{
  "type": "Feature",
  "properties": {
    "iso:country":"IN",
    "ks:ks_alt_nam":"Bhunjay moti",
    "ks:ks_name":"Bhunjay Moti",
    "ks:ks_pop":57,
    "ks:ks_type":"HABITATION",
    "name:eng_x_preferred":[
        "Bhunjay Moti"
    ],
    "wof:name":"Bhunjay Moti",
    "wof:placetype":"locality",
    "wof:population":57
},
  "geometry": {"coordinates":[69.0064,23.467458],"type":"Point"}
}