{
  "type": "Feature",
  "properties": {
    "iso:country":"IN",
    "ks:ks_alt_nam":"TEPRI",
    "ks:ks_name":"Tepri",
    "ks:ks_pop":215,
    "ks:ks_type":"HABITATION",
    "name:eng_x_preferred":[
        "Tepri"
    ],
    "wof:name":"Tepri",
    "wof:placetype":"locality",
    "wof:population":215
},
  "geometry": {"coordinates":[81.663917,27.363153],"type":"Point"}
}