{
  "type": "Feature",
  "properties": {
    "gn:admin1_code":"38.0",
    "gn:admin2_code":"348.0",
    "gn:asciiname":"Kurmidih",
    "gn:country_code":"IN",
    "gn:dem":369,
    "gn:feature_class":"P",
    "gn:feature_code":"PPL",
    "gn:name":"Kurmidih",
    "gn:population":0,
    "gn:timezone":"Asia/Kolkata",
    "iso:country":"IN",
    "wof:name":"Kurmidih",
    "wof:placetype":"locality"
},
  "geometry": {"coordinates":[85.53425,24.37008],"type":"Point"}
}