{
  "type": "Feature",
  "properties": {
    "iso:country":"IN",
    "ks:ks_name":"Ghuidand",
    "ks:ks_pop":321,
    "ks:ks_type":"HABITATION",
    "name:eng_x_preferred":[
        "Ghuidand"
    ],
    "wof:name":"Ghuidand",
    "wof:placetype":"locality",
    "wof:population":321
},
  "geometry": {"coordinates":[83.93495299999999,22.615258],"type":"Point"}
}