{
  "type": "Feature",
  "properties": {
    "iso:country":"IN",
    "ks:ks_name":"Patrapalli Thanda",
    "ks:ks_pop":431,
    "ks:ks_type":"HABITATION",
    "name:eng_x_preferred":[
        "Patrapalli Thanda"
    ],
    "wof:name":"Patrapalli Thanda",
    "wof:placetype":"locality",
    "wof:population":431
},
  "geometry": {"coordinates":[78.520419,13.427647],"type":"Point"}
}