{
  "type": "Feature",
  "properties": {
    "gn:admin1_code":"34.0",
    "gn:admin2_code":"234.0",
    "gn:asciiname":"Kusdihra",
    "gn:country_code":"IN",
    "gn:dem":117,
    "gn:feature_class":"P",
    "gn:feature_code":"PPL",
    "gn:name":"Kusdihra",
    "gn:population":0,
    "gn:timezone":"Asia/Kolkata",
    "iso:country":"IN",
    "wof:name":"Kusdihra",
    "wof:placetype":"locality"
},
  "geometry": {"coordinates":[84.10205999999999,24.87223],"type":"Point"}
}