{
  "type": "Feature",
  "properties": {
    "gn:admin1_code":"25.0",
    "gn:admin2_code":"630.0",
    "gn:asciiname":"Dasampatti",
    "gn:country_code":"IN",
    "gn:dem":418,
    "gn:feature_class":"P",
    "gn:feature_code":"PPL",
    "gn:name":"D\u0101sampatti",
    "gn:population":0,
    "gn:timezone":"Asia/Kolkata",
    "iso:country":"IN",
    "name:tam_x_preferred":[
        "\u0ba4\u0bbe\u0b9a\u0bae\u0bcd\u0baa\u0b9f\u0bcd\u0b9f\u0bbf"
    ],
    "wof:name":"Dasampatti",
    "wof:placetype":"locality"
},
  "geometry": {"coordinates":[78.41054,12.11951],"type":"Point"}
}