{
  "type": "Feature",
  "properties": {
    "gn:admin1_code":"2.0",
    "gn:admin2_code":"548.0",
    "gn:asciiname":"Kubadupuram",
    "gn:country_code":"IN",
    "gn:dem":103,
    "gn:feature_class":"P",
    "gn:feature_code":"PPL",
    "gn:name":"Kub\u0101dupuram",
    "gn:population":0,
    "gn:timezone":"Asia/Kolkata",
    "iso:country":"IN",
    "name:und_x_variant":[
        "Kub\u0101dupuram",
        "Annap\u0101lem"
    ],
    "wof:name":"Kubadupuram",
    "wof:placetype":"locality"
},
  "geometry": {"coordinates":[79.95511999999999,16.46572],"type":"Point"}
}