{
  "type": "Feature",
  "properties": {
    "iso:country":"IN",
    "ks:ks_name":"Madauria",
    "ks:ks_pop":122,
    "ks:ks_type":"VILLAGE",
    "name:eng_x_preferred":[
        "Madauria"
    ],
    "wof:name":"Madauria",
    "wof:placetype":"locality",
    "wof:population":122
},
  "geometry": {"coordinates":[84.032794,24.969846],"type":"Point"}
}