{
  "type": "Feature",
  "properties": {
    "gn:country":"IN",
    "gn:fcode":"PPL",
    "gn:population":110983,
    "iso:country":"IN",
    "name:ara_x_preferred":[
        "\u0628\u0627\u0631\u0633\u064a"
    ],
    "name:ben_x_preferred":[
        "\u09ac\u09be\u09b0\u09cd\u09b6\u09bf"
    ],
    "name:bho_x_preferred":[
        "\u092c\u093e\u0930\u094d\u0936\u0940"
    ],
    "name:bpy_x_preferred":[
        "\u09ac\u09be\u09b0\u09cd\u09b6\u09bf"
    ],
    "name:deu_x_preferred":[
        "Barshi"
    ],
    "name:eng_x_preferred":[
        "Barshi"
    ],
    "name:fra_x_preferred":[
        "Barshi"
    ],
    "name:guj_x_preferred":[
        "\u0aac\u0ab0\u0acd\u0ab6\u0ac0"
    ],
    "name:ita_x_preferred":[
        "Barshi"
    ],
    "name:jpn_x_preferred":[
        "\u30d0\u30fc\u30b7"
    ],
    "name:kan_x_preferred":[
        "\u0cac\u0cbe\u0cb0\u0ccd\u0cb6\u0cbf"
    ],
    "name:kor_x_preferred":[
        "\ubc14\ub974\uc2dc"
    ],
    "name:mar_x_preferred":[
        "\u092c\u093e\u0930\u094d\u0936\u0940"
    ],
    "name:mlg_x_preferred":[
        "Barshi"
    ],
    "name:msa_x_preferred":[
        "Barshi"
    ],
    "name:nan_x_preferred":[
        "Barshi"
    ],
    "name:new_x_preferred":[
        "\u092c\u0930\u094d\u0936\u093f"
    ],
    "name:nld_x_preferred":[
        "Barshi"
    ],
    "name:por_x_preferred":[
        "Barshi"
    ],
    "name:rus_x_preferred":[
        "\u0411\u0430\u0440\u0448\u0438"
    ],
    "name:spa_x_preferred":[
        "Barshi"
    ],
    "name:swe_x_preferred":[
        "Barshi"
    ],
    "name:tam_x_preferred":[
        "\u0baa\u0bbe\u0bb0\u0bcd\u0bb7\u0bbf"
    ],
    "name:tel_x_preferred":[
        "\u0c2c\u0c3e\u0c30\u0c4d\u0c37\u0c3f"
    ],
    "name:urd_x_preferred":[
        "\u0628\u0627\u0631\u0634\u06cc"
    ],
    "name:vie_x_preferred":[
        "Barshi"
    ],
    "name:zho_x_preferred":[
        "\u5df4\u5c14\u65af\u5e0c"
    ],
    "qs:name":"B\u0101rsi",
    "qs:photos_9r":0,
    "qs:photos_sr":0,
    "qs:pop_sr":"9",
    "wof:name":"B\u0101rsi",
    "wof:placetype":"locality",
    "wof:population":110983
},
  "geometry": {"coordinates":[75.69275,18.23454],"type":"Point"}
}