{
  "type": "Feature",
  "properties": {
    "iso:country":"IN",
    "ks:ks_name":"Raitanbag",
    "ks:ks_pop":1513,
    "ks:ks_type":"VILLAGE",
    "ks:ks_uagg_main":0,
    "name:eng_x_preferred":[
        "Raitanbag"
    ],
    "wof:name":"Raitanbag",
    "wof:placetype":"neighbourhood",
    "wof:population":1513
},
  "geometry": {"coordinates":[88.26491799999999,24.178542],"type":"Point"}
}