{
  "type": "Feature",
  "properties": {
    "iso:country":"IN",
    "ks:ks_name":"Wadhupada",
    "ks:ks_pop":112,
    "ks:ks_type":"HABITATION",
    "name:eng_x_preferred":[
        "Wadhupada"
    ],
    "wof:name":"Wadhupada",
    "wof:placetype":"locality",
    "wof:population":112
},
  "geometry": {"coordinates":[73.205505,19.844382],"type":"Point"}
}