{
  "type": "Feature",
  "properties": {
    "iso:country":"IN",
    "ks:ks_name":"Hastinapur",
    "ks:ks_pop":230,
    "ks:ks_type":"HABITATION",
    "name:eng_x_preferred":[
        "Hastinapur"
    ],
    "wof:name":"Hastinapur",
    "wof:placetype":"locality",
    "wof:population":230
},
  "geometry": {"coordinates":[91.389078,26.730739],"type":"Point"}
}