{
  "type": "Feature",
  "properties": {
    "gn:admin1_code":"37",
    "gn:admin2_code":"401.0",
    "gn:asciiname":"Dhulangi",
    "gn:country_code":"IN",
    "gn:dem":365,
    "gn:feature_class":"P",
    "gn:feature_code":"PPL",
    "gn:name":"Dh\u016blangi",
    "gn:population":0,
    "gn:timezone":"Asia/Kolkata",
    "iso:country":"IN",
    "ks:ks_alt_nam":"Dh\u016blangi",
    "ks:ks_name":"Dhulangi",
    "ks:ks_pop":1004,
    "ks:ks_type":"VILLAGE",
    "name:eng_x_preferred":[
        "Dhulangi"
    ],
    "name:eng_x_variant":[
        "Dh\u016blangi"
    ],
    "wof:name":"Dhulangi",
    "wof:placetype":"locality",
    "wof:population":1004
},
  "geometry": {"coordinates":[83.44935700000001,24.002315],"type":"Point"}
}