{
  "type": "Feature",
  "properties": {
    "gn:admin1_code":"36.0",
    "gn:admin2_code":"169.0",
    "gn:asciiname":"Mahobkanth",
    "gn:country_code":"IN",
    "gn:dem":191,
    "gn:feature_class":"P",
    "gn:feature_code":"PPL",
    "gn:name":"Mahobkanth",
    "gn:population":0,
    "gn:timezone":"Asia/Kolkata",
    "iso:country":"IN",
    "wof:name":"Mahobkanth",
    "wof:placetype":"locality"
},
  "geometry": {"coordinates":[79.40079,25.33674],"type":"Point"}
}