{
  "type": "Feature",
  "properties": {
    "iso:country":"IN",
    "ks:ks_name":"Banshiyar",
    "ks:ks_pop":0,
    "ks:ks_type":"VILLAGE",
    "name:eng_x_preferred":[
        "Banshiyar"
    ],
    "wof:name":"Banshiyar",
    "wof:placetype":"locality",
    "wof:population":0
},
  "geometry": {"coordinates":[87.313175,22.132732],"type":"Point"}
}