{
  "type": "Feature",
  "properties": {
    "iso:country":"IN",
    "ks:ks_name":"Chaitanyapur",
    "ks:ks_pop":886,
    "ks:ks_type":"VILLAGE",
    "ks:ks_uagg_main":0,
    "name:eng_x_preferred":[
        "Chaitanyapur"
    ],
    "wof:name":"Chaitanyapur",
    "wof:placetype":"neighbourhood",
    "wof:population":886
},
  "geometry": {"coordinates":[88.384044,22.170696],"type":"Point"}
}