{
  "type": "Feature",
  "properties": {
    "iso:country":"IN",
    "ks:ks_name":"Manjhipara",
    "ks:ks_pop":188,
    "ks:ks_type":"HABITATION",
    "name:eng_x_preferred":[
        "Manjhipara"
    ],
    "wof:name":"Manjhipara",
    "wof:placetype":"locality",
    "wof:population":188
},
  "geometry": {"coordinates":[81.392724,19.420834],"type":"Point"}
}