{
  "type": "Feature",
  "properties": {
    "iso:country":"IN",
    "ks:ks_name":"Dodage",
    "ks:ks_pop":63,
    "ks:ks_type":"HABITATION",
    "name:eng_x_preferred":[
        "Dodage"
    ],
    "wof:name":"Dodage",
    "wof:placetype":"locality",
    "wof:population":63
},
  "geometry": {"coordinates":[81.046611,19.326827],"type":"Point"}
}