{
  "type": "Feature",
  "properties": {
    "gn:admin1_code":"19.0",
    "gn:admin2_code":"572",
    "gn:asciiname":"Garvi Bhavi Palya Hosur Road",
    "gn:country_code":"IN",
    "gn:dem":890,
    "gn:feature_class":"P",
    "gn:feature_code":"PPL",
    "gn:name":"Garvi Bhavi Palya Hosur Road",
    "gn:population":0,
    "gn:timezone":"Asia/Kolkata",
    "iso:country":"IN",
    "wof:name":"Garvi Bhavi Palya Hosur Road",
    "wof:placetype":"locality"
},
  "geometry": {"coordinates":[77.63729000000002,12.89598],"type":"Point"}
}