{
  "type": "Feature",
  "properties": {
    "iso:country":"IN",
    "ks:ks_name":"Gawara",
    "ks:ks_pop":460,
    "ks:ks_type":"VILLAGE",
    "name:eng_x_preferred":[
        "Gawara"
    ],
    "wof:name":"Gawara",
    "wof:placetype":"locality",
    "wof:population":460
},
  "geometry": {"coordinates":[78.37870700000001,30.67253],"type":"Point"}
}