{
  "type": "Feature",
  "properties": {
    "iso:country":"IN",
    "ks:ks_name":"Sugalithanda",
    "ks:ks_pop":75,
    "ks:ks_type":"HABITATION",
    "name:eng_x_preferred":[
        "Sugalithanda"
    ],
    "wof:name":"Sugalithanda",
    "wof:placetype":"locality",
    "wof:population":75
},
  "geometry": {"coordinates":[78.60627100000001,15.178782],"type":"Point"}
}