{
  "type": "Feature",
  "properties": {
    "gn:admin1_code":"23.0",
    "gn:admin2_code":"44.0",
    "gn:asciiname":"Samagh",
    "gn:country_code":"IN",
    "gn:dem":204,
    "gn:feature_class":"P",
    "gn:feature_code":"PPL",
    "gn:name":"Sam\u0101gh",
    "gn:population":0,
    "gn:timezone":"Asia/Kolkata",
    "iso:country":"IN",
    "wof:name":"Samagh",
    "wof:placetype":"locality"
},
  "geometry": {"coordinates":[74.74389000000002,30.49092000000001],"type":"Point"}
}