{
  "type": "Feature",
  "properties": {
    "gn:admin1_code":"3.0",
    "gn:admin2_code":"316.0",
    "gn:asciiname":"Algpur",
    "gn:country_code":"IN",
    "gn:dem":27,
    "gn:feature_class":"P",
    "gn:feature_code":"PPL",
    "gn:name":"Algpur",
    "gn:population":0,
    "gn:timezone":"Asia/Kolkata",
    "iso:country":"IN",
    "wof:name":"Algpur",
    "wof:placetype":"neighbourhood"
},
  "geometry": {"coordinates":[92.68720999999999,24.86681],"type":"Point"}
}