{
  "type": "Feature",
  "properties": {
    "iso:country":"IN",
    "ks:ks_name":"Balkhad",
    "ks:ks_pop":485,
    "ks:ks_type":"VILLAGE",
    "name:eng_x_preferred":[
        "Balkhad"
    ],
    "wof:name":"Balkhad",
    "wof:placetype":"locality",
    "wof:population":485
},
  "geometry": {"coordinates":[74.842358,22.032048],"type":"Point"}
}