{
  "type": "Feature",
  "properties": {
    "iso:country":"IN",
    "ks:ks_name":"Harijan Tola",
    "ks:ks_pop":459,
    "ks:ks_type":"HABITATION",
    "ks:ks_uagg_main":0,
    "name:eng_x_preferred":[
        "Harijan Tola"
    ],
    "wof:name":"Harijan Tola",
    "wof:placetype":"neighbourhood",
    "wof:population":459
},
  "geometry": {"coordinates":[84.79589799999999,26.564613],"type":"Point"}
}