{
  "type": "Feature",
  "properties": {
    "gn:admin1_code":"12.0",
    "gn:asciiname":"Barthi",
    "gn:country_code":"IN",
    "gn:dem":2436,
    "gn:feature_class":"P",
    "gn:feature_code":"PPL",
    "gn:name":"Barthi",
    "gn:population":0,
    "gn:timezone":"Asia/Kolkata",
    "iso:country":"IN",
    "wof:name":"Barthi",
    "wof:placetype":"locality"
},
  "geometry": {"coordinates":[73.98411,34.65263],"type":"Point"}
}