{
  "type": "Feature",
  "properties": {
    "gn:admin1_code":"39.0",
    "gn:admin2_code":"68.0",
    "gn:asciiname":"Pherupur",
    "gn:country_code":"IN",
    "gn:dem":263,
    "gn:feature_class":"P",
    "gn:feature_code":"PPL",
    "gn:name":"Pher\u016bpur",
    "gn:population":0,
    "gn:timezone":"Asia/Kolkata",
    "iso:country":"IN",
    "name:und_x_variant":[
        "Pher\u016bpur",
        "R\u0101mkhera"
    ],
    "wof:name":"Pherupur",
    "wof:placetype":"locality"
},
  "geometry": {"coordinates":[78.11716,29.85448],"type":"Point"}
}