{
  "type": "Feature",
  "properties": {
    "iso:country":"IN",
    "ks:ks_name":"Tepra",
    "ks:ks_pop":185,
    "ks:ks_type":"HABITATION",
    "name:eng_x_preferred":[
        "Tepra"
    ],
    "wof:name":"Tepra",
    "wof:placetype":"locality",
    "wof:population":185
},
  "geometry": {"coordinates":[81.784192,27.208038],"type":"Point"}
}