{
  "type": "Feature",
  "properties": {
    "gn:admin1_code":"39",
    "gn:admin2_code":"61.0",
    "gn:asciiname":"Shilongaon",
    "gn:country_code":"IN",
    "gn:dem":1340,
    "gn:feature_class":"P",
    "gn:feature_code":"PPL",
    "gn:name":"Sh\u012blongaon",
    "gn:population":0,
    "gn:timezone":"Asia/Kolkata",
    "iso:country":"IN",
    "name:und_x_variant":[
        "Sh\u012blongaon",
        "Pithrora"
    ],
    "wof:name":"Shilongaon",
    "wof:placetype":"locality"
},
  "geometry": {"coordinates":[78.9101,29.91284000000001],"type":"Point"}
}