{
  "type": "Feature",
  "properties": {
    "gn:admin1_code":"36",
    "gn:admin2_code":"172.0",
    "gn:asciiname":"Barnapur",
    "gn:country_code":"IN",
    "gn:dem":115,
    "gn:feature_class":"P",
    "gn:feature_code":"PPL",
    "gn:name":"Barn\u0101pur",
    "gn:population":0,
    "gn:timezone":"Asia/Kolkata",
    "iso:country":"IN",
    "ks:ks_name":"Barna Pur",
    "ks:ks_pop":150,
    "ks:ks_type":"VILLAGE",
    "name:eng_x_preferred":[
        "Barna Pur"
    ],
    "name:eng_x_variant":[
        "Barnapur"
    ],
    "wof:name":"Barna Pur",
    "wof:placetype":"locality",
    "wof:population":150
},
  "geometry": {"coordinates":[80.93958000000001,26.036536],"type":"Point"}
}