{
  "type": "Feature",
  "properties": {
    "iso:country":"IN",
    "ks:ks_name":"Bachat Ki Madaia",
    "ks:ks_pop":100,
    "ks:ks_type":"HABITATION",
    "name:eng_x_preferred":[
        "Bachat Ki Madaia"
    ],
    "wof:name":"Bachat Ki Madaia",
    "wof:placetype":"locality",
    "wof:population":100
},
  "geometry": {"coordinates":[79.63806599999999,27.327133],"type":"Point"}
}