{
  "type": "Feature",
  "properties": {
    "iso:country":"IN",
    "ks:ks_name":"Kalagin Keri",
    "ks:ks_pop":66,
    "ks:ks_type":"HABITATION",
    "name:eng_x_preferred":[
        "Kalagin Keri"
    ],
    "wof:name":"Kalagin Keri",
    "wof:placetype":"locality",
    "wof:population":66
},
  "geometry": {"coordinates":[74.47114999999999,14.405619],"type":"Point"}
}