{
  "type": "Feature",
  "properties": {
    "iso:country":"IN",
    "ks:ks_name":"Ghaghra",
    "ks:ks_pop":639,
    "ks:ks_type":"VILLAGE",
    "name:eng_x_preferred":[
        "Ghaghra"
    ],
    "wof:name":"Ghaghra",
    "wof:placetype":"locality",
    "wof:population":639
},
  "geometry": {"coordinates":[86.819197,24.5212],"type":"Point"}
}