{
  "type": "Feature",
  "properties": {
    "iso:country":"IN",
    "ks:ks_alt_nam":"Rajbhar basti",
    "ks:ks_name":"Rajbhar Basti",
    "ks:ks_pop":124,
    "ks:ks_type":"HABITATION",
    "name:eng_x_preferred":[
        "Rajbhar Basti"
    ],
    "wof:name":"Rajbhar Basti",
    "wof:placetype":"locality",
    "wof:population":124
},
  "geometry": {"coordinates":[82.900919,25.406441],"type":"Point"}
}