{
  "type": "Feature",
  "properties": {
    "gn:admin1_code":"34.0",
    "gn:admin2_code":"220.0",
    "gn:asciiname":"Qutubpur Bangri",
    "gn:country_code":"IN",
    "gn:dem":60,
    "gn:feature_class":"P",
    "gn:feature_code":"PPL",
    "gn:name":"Qutubpur Bangri",
    "gn:population":0,
    "gn:timezone":"Asia/Kolkata",
    "iso:country":"IN",
    "ks:ks_name":"Kutubpur Bangri",
    "ks:ks_pop":1524,
    "ks:ks_type":"VILLAGE",
    "name:eng_x_preferred":[
        "Kutubpur Bangri"
    ],
    "name:eng_x_variant":[
        "Qutubpur Bangri"
    ],
    "wof:name":"Kutubpur Bangri",
    "wof:placetype":"locality",
    "wof:population":1524
},
  "geometry": {"coordinates":[85.094211,25.962156],"type":"Point"}
}