{
  "type": "Feature",
  "properties": {
    "iso:country":"IN",
    "ks:ks_name":"Dhobikuwa",
    "ks:ks_pop":1310,
    "ks:ks_type":"VILLAGE",
    "name:eng_x_preferred":[
        "Dhobikuwa"
    ],
    "wof:name":"Dhobikuwa",
    "wof:placetype":"locality",
    "wof:population":1310
},
  "geometry": {"coordinates":[72.99775200000001,22.222258],"type":"Point"}
}