{
  "type": "Feature",
  "properties": {
    "iso:country":"IN",
    "ks:ks_name":"Eguvaravivalasa",
    "ks:ks_pop":135,
    "ks:ks_type":"HABITATION",
    "name:eng_x_preferred":[
        "Eguvaravivalasa"
    ],
    "wof:name":"Eguvaravivalasa",
    "wof:placetype":"locality",
    "wof:population":135
},
  "geometry": {"coordinates":[83.206952,18.429506],"type":"Point"}
}