{
  "type": "Feature",
  "properties": {
    "gn:admin1_code":"36.0",
    "gn:admin2_code":"138.0",
    "gn:asciiname":"Kuri",
    "gn:country_code":"IN",
    "gn:dem":217,
    "gn:feature_class":"P",
    "gn:feature_code":"PPL",
    "gn:name":"Kuri",
    "gn:population":0,
    "gn:timezone":"Asia/Kolkata",
    "iso:country":"IN",
    "name:ceb_x_preferred":[
        "Kuri"
    ],
    "name:ces_x_preferred":[
        "Kuri"
    ],
    "name:deu_x_preferred":[
        "Kuri"
    ],
    "name:fra_x_preferred":[
        "Kuri"
    ],
    "name:spa_x_preferred":[
        "Kuri"
    ],
    "name:swe_x_preferred":[
        "Kuri"
    ],
    "wof:name":"Kuri",
    "wof:placetype":"locality"
},
  "geometry": {"coordinates":[77.76674,28.80069],"type":"Point"}
}