{
  "type": "Feature",
  "properties": {
    "gn:admin1_code":"36",
    "gn:admin2_code":"155.0",
    "gn:asciiname":"Jaliamau",
    "gn:country_code":"IN",
    "gn:dem":136,
    "gn:feature_class":"P",
    "gn:feature_code":"PPL",
    "gn:name":"Jali\u0101mau",
    "gn:population":0,
    "gn:timezone":"Asia/Kolkata",
    "iso:country":"IN",
    "wof:name":"Jaliamau",
    "wof:placetype":"locality"
},
  "geometry": {"coordinates":[80.55580999999999,27.16725],"type":"Point"}
}