{
  "type": "Feature",
  "properties": {
    "iso:country":"IN",
    "ks:ks_name":"Tukaramaradoddi",
    "ks:ks_pop":144,
    "ks:ks_type":"HABITATION",
    "name:eng_x_preferred":[
        "Tukaramaradoddi"
    ],
    "wof:name":"Tukaramaradoddi",
    "wof:placetype":"locality",
    "wof:population":144
},
  "geometry": {"coordinates":[77.51911699999999,12.6011],"type":"Point"}
}