{
  "type": "Feature",
  "properties": {
    "gn:admin1_code":"11",
    "gn:admin2_code":"23.0",
    "gn:asciiname":"Palel",
    "gn:country_code":"IN",
    "gn:dem":1292,
    "gn:feature_class":"P",
    "gn:feature_code":"PPL",
    "gn:name":"Palel",
    "gn:population":0,
    "gn:timezone":"Asia/Kolkata",
    "iso:country":"IN",
    "name:por_x_preferred":[
        "Palel"
    ],
    "wof:name":"Palel",
    "wof:placetype":"locality"
},
  "geometry": {"coordinates":[76.06995999999999,32.65482],"type":"Point"}
}