{
  "type": "Feature",
  "properties": {
    "gn:admin1_code":"38.0",
    "gn:admin2_code":"358.0",
    "gn:asciiname":"Panchrukhia",
    "gn:country_code":"IN",
    "gn:dem":288,
    "gn:feature_class":"P",
    "gn:feature_code":"PPL",
    "gn:name":"Panchrukh\u012b\u0101",
    "gn:population":0,
    "gn:timezone":"Asia/Kolkata",
    "iso:country":"IN",
    "ks:ks_name":"Pachrukhiya",
    "ks:ks_pop":161,
    "ks:ks_type":"VILLAGE",
    "name:eng_x_preferred":[
        "Pachrukhiya"
    ],
    "name:eng_x_variant":[
        "Panchrukhia"
    ],
    "wof:name":"Pachrukhiya",
    "wof:placetype":"locality",
    "wof:population":161
},
  "geometry": {"coordinates":[84.368402,24.130854],"type":"Point"}
}