{
  "type": "Feature",
  "properties": {
    "iso:country":"IN",
    "ks:ks_name":"Gangedda",
    "ks:ks_pop":292,
    "ks:ks_type":"VILLAGE",
    "name:eng_x_preferred":[
        "Gangedda"
    ],
    "wof:name":"Gangedda",
    "wof:placetype":"locality",
    "wof:population":292
},
  "geometry": {"coordinates":[88.06702,23.928759],"type":"Point"}
}