{
  "type": "Feature",
  "properties": {
    "iso:country":"IN",
    "ks:ks_name":"Vellakkari Thadam Rd End",
    "ks:ks_pop":405,
    "ks:ks_type":"HABITATION",
    "name:eng_x_preferred":[
        "Vellakkari Thadam Rd End"
    ],
    "wof:name":"Vellakkari Thadam Rd End",
    "wof:placetype":"locality",
    "wof:population":405
},
  "geometry": {"coordinates":[76.36873300000001,10.511713],"type":"Point"}
}