{
  "type": "Feature",
  "properties": {
    "iso:country":"IN",
    "ks:ks_name":"Patakhedi",
    "ks:ks_pop":949,
    "ks:ks_type":"VILLAGE",
    "name:eng_x_preferred":[
        "Patakhedi"
    ],
    "wof:name":"Patakhedi",
    "wof:placetype":"locality",
    "wof:population":949
},
  "geometry": {"coordinates":[75.124979,23.525908],"type":"Point"}
}