{
  "type": "Feature",
  "properties": {
    "iso:country":"IN",
    "ks:ks_alt_nam":"Pazhaya vattavazhi",
    "ks:ks_name":"Pazhaya Vattavazhi",
    "ks:ks_pop":960,
    "ks:ks_type":"HABITATION",
    "name:eng_x_preferred":[
        "Pazhaya Vattavazhi"
    ],
    "wof:name":"Pazhaya Vattavazhi",
    "wof:placetype":"locality",
    "wof:population":960
},
  "geometry": {"coordinates":[76.148363,10.53116],"type":"Point"}
}