{
  "type": "Feature",
  "properties": {
    "iso:country":"IN",
    "ks:ks_name":"Chokkanathapuram",
    "ks:ks_pop":273,
    "ks:ks_type":"HABITATION",
    "name:eng_x_preferred":[
        "Chokkanathapuram"
    ],
    "wof:name":"Chokkanathapuram",
    "wof:placetype":"locality",
    "wof:population":273
},
  "geometry": {"coordinates":[78.745565,9.877418],"type":"Point"}
}