{
  "type": "Feature",
  "properties": {
    "gn:admin1_code":"24",
    "gn:admin2_code":"105.0",
    "gn:asciiname":"Nagla Kishorsingh",
    "gn:country_code":"IN",
    "gn:dem":191,
    "gn:feature_class":"P",
    "gn:feature_code":"PPL",
    "gn:name":"Nagla Kishorsingh",
    "gn:population":0,
    "gn:timezone":"Asia/Kolkata",
    "iso:country":"IN",
    "wof:name":"Nagla Kishorsingh",
    "wof:placetype":"locality"
},
  "geometry": {"coordinates":[77.24297,27.58729000000001],"type":"Point"}
}