{
  "type": "Feature",
  "properties": {
    "gn:admin1_code":"24",
    "gn:admin2_code":"105.0",
    "gn:asciiname":"Nagla Kishorsingh",
    "gn:country_code":"IN",
    "gn:dem":191,
    "gn:feature_class":"P",
    "gn:feature_code":"PPL",
    "gn:name":"Nagla Kishorsingh",
    "gn:population":0,
    "gn:timezone":"Asia/Kolkata",
    "iso:country":"IN",
    "ks:ks_name":"Nagla Kishorsingh",
    "ks:ks_pop":155,
    "ks:ks_type":"VILLAGE",
    "name:eng_x_preferred":[
        "Nagla Kishorsingh"
    ],
    "wof:name":"Nagla Kishorsingh",
    "wof:placetype":"locality",
    "wof:population":155
},
  "geometry": {"coordinates":[77.242947,27.587352],"type":"Point"}
}