{
  "type": "Feature",
  "properties": {
    "iso:country":"IN",
    "ks:ks_name":"Mulanthara Pady",
    "ks:ks_pop":633,
    "ks:ks_type":"HABITATION",
    "name:eng_x_preferred":[
        "Mulanthara Pady"
    ],
    "wof:name":"Mulanthara Pady",
    "wof:placetype":"locality",
    "wof:population":633
},
  "geometry": {"coordinates":[77.01923600000001,9.123297],"type":"Point"}
}