{
  "type": "Feature",
  "properties": {
    "iso:country":"IN",
    "ks:ks_name":"9 SSW",
    "ks:ks_pop":647,
    "ks:ks_type":"VILLAGE",
    "name:eng_x_preferred":[
        "9 SSW"
    ],
    "wof:name":"9 SSW",
    "wof:placetype":"locality",
    "wof:population":647
},
  "geometry": {"coordinates":[74.37082700000001,29.509392],"type":"Point"}
}