{
  "type": "Feature",
  "properties": {
    "iso:country":"IN",
    "ks:ks_name":"Guttameeda Thanda",
    "ks:ks_pop":77,
    "ks:ks_type":"HABITATION",
    "ks:ks_uagg_main":0,
    "name:eng_x_preferred":[
        "Guttameeda Thanda"
    ],
    "wof:name":"Guttameeda Thanda",
    "wof:placetype":"neighbourhood",
    "wof:population":77
},
  "geometry": {"coordinates":[79.00658799999999,13.89177],"type":"Point"}
}