{
  "type": "Feature",
  "properties": {
    "gn:admin1_code":"37.0",
    "gn:admin2_code":"417.0",
    "gn:asciiname":"Indripal",
    "gn:country_code":"IN",
    "gn:dem":433,
    "gn:feature_class":"P",
    "gn:feature_code":"PPL",
    "gn:name":"Indrip\u0101l",
    "gn:population":0,
    "gn:timezone":"Asia/Kolkata",
    "iso:country":"IN",
    "ks:ks_alt_nam":"Indrip\u0101l",
    "ks:ks_name":"Indripal",
    "ks:ks_type":"VILLAGE",
    "name:eng_x_preferred":[
        "Indripal"
    ],
    "name:eng_x_variant":[
        "Indrip\u0101l"
    ],
    "wof:name":"Indripal",
    "wof:placetype":"locality"
},
  "geometry": {"coordinates":[81.179716,18.778844],"type":"Point"}
}