{
  "type": "Feature",
  "properties": {
    "iso:country":"IN",
    "ks:ks_name":"Kurunja",
    "ks:ks_pop":250,
    "ks:ks_type":"HABITATION",
    "name:eng_x_preferred":[
        "Kurunja"
    ],
    "wof:name":"Kurunja",
    "wof:placetype":"locality",
    "wof:population":250
},
  "geometry": {"coordinates":[75.248891,12.683206],"type":"Point"}
}