{
  "type": "Feature",
  "properties": {
    "iso:country":"IN",
    "ks:ks_name":"Bhatvar Vas",
    "ks:ks_pop":1228,
    "ks:ks_type":"VILLAGE",
    "ks:ks_uagg_main":0,
    "name:eng_x_preferred":[
        "Bhatvar Vas"
    ],
    "wof:name":"Bhatvar Vas",
    "wof:placetype":"neighbourhood",
    "wof:population":1228
},
  "geometry": {"coordinates":[71.44106499999999,24.280521],"type":"Point"}
}