{
  "type": "Feature",
  "properties": {
    "gn:admin1_code":"37.0",
    "gn:admin2_code":"407.0",
    "gn:asciiname":"Titri",
    "gn:country_code":"IN",
    "gn:dem":628,
    "gn:feature_class":"P",
    "gn:feature_code":"PPL",
    "gn:name":"Titr\u012b",
    "gn:population":0,
    "gn:timezone":"Asia/Kolkata",
    "iso:country":"IN",
    "ks:ks_name":"Titari",
    "ks:ks_pop":552,
    "ks:ks_type":"HABITATION",
    "name:eng_x_preferred":[
        "Titari"
    ],
    "name:eng_x_variant":[
        "Titri"
    ],
    "wof:name":"Titari",
    "wof:placetype":"locality",
    "wof:population":552
},
  "geometry": {"coordinates":[80.902985,22.021771],"type":"Point"}
}