{
  "type": "Feature",
  "properties": {
    "gn:admin1_code":"36",
    "gn:admin2_code":"167.0",
    "gn:asciiname":"Barwai",
    "gn:country_code":"IN",
    "gn:dem":319,
    "gn:feature_class":"P",
    "gn:feature_code":"PPL",
    "gn:name":"Barw\u0101i",
    "gn:population":0,
    "gn:timezone":"Asia/Kolkata",
    "iso:country":"IN",
    "ks:ks_name":"Barwari",
    "ks:ks_pop":216,
    "ks:ks_type":"HABITATION",
    "name:eng_x_preferred":[
        "Barwari"
    ],
    "name:eng_x_variant":[
        "Barwai"
    ],
    "wof:name":"Barwari",
    "wof:placetype":"locality",
    "wof:population":216
},
  "geometry": {"coordinates":[78.400677,25.028994],"type":"Point"}
}