{
  "type": "Feature",
  "properties": {
    "gn:admin1_code":"21.0",
    "gn:admin2_code":"398.0",
    "gn:asciiname":"Kakra-ambo",
    "gn:country_code":"IN",
    "gn:dem":933,
    "gn:feature_class":"P",
    "gn:feature_code":"PPL",
    "gn:name":"Kakra-\u0101mbo",
    "gn:population":0,
    "gn:timezone":"Asia/Kolkata",
    "iso:country":"IN",
    "wof:name":"Kakra-ambo",
    "wof:placetype":"locality"
},
  "geometry": {"coordinates":[82.89974000000002,18.65169],"type":"Point"}
}