{
  "type": "Feature",
  "properties": {
    "gn:admin1_code":"39",
    "gn:admin2_code":"61.0",
    "gn:asciiname":"Musasu",
    "gn:country_code":"IN",
    "gn:dem":1469,
    "gn:feature_class":"P",
    "gn:feature_code":"PPL",
    "gn:name":"Mus\u0101su",
    "gn:population":0,
    "gn:timezone":"Asia/Kolkata",
    "iso:country":"IN",
    "ks:ks_alt_nam":"Mus\u0101su",
    "ks:ks_name":"Musasu",
    "ks:ks_type":"VILLAGE",
    "name:eng_x_preferred":[
        "Musasu"
    ],
    "name:eng_x_variant":[
        "Mus\u0101su"
    ],
    "wof:name":"Musasu",
    "wof:placetype":"locality"
},
  "geometry": {"coordinates":[78.846874,30.00255],"type":"Point"}
}