{
  "type": "Feature",
  "properties": {
    "gn:admin1_code":"25.0",
    "gn:admin2_code":"630.0",
    "gn:asciiname":"Mallikuttai",
    "gn:country_code":"IN",
    "gn:dem":452,
    "gn:feature_class":"P",
    "gn:feature_code":"PPL",
    "gn:name":"Mallikuttai",
    "gn:population":0,
    "gn:timezone":"Asia/Kolkata",
    "iso:country":"IN",
    "ks:ks_name":"Mallikuttai",
    "ks:ks_pop":973,
    "ks:ks_type":"VILLAGE",
    "name:eng_x_preferred":[
        "Mallikuttai"
    ],
    "wof:name":"Mallikuttai",
    "wof:placetype":"locality",
    "wof:population":973
},
  "geometry": {"coordinates":[78.166073,12.191766],"type":"Point"}
}