{
  "type": "Feature",
  "properties": {
    "iso:country":"IN",
    "ks:ks_name":"Golagodu",
    "ks:ks_pop":26,
    "ks:ks_type":"HABITATION",
    "name:eng_x_preferred":[
        "Golagodu"
    ],
    "wof:name":"Golagodu",
    "wof:placetype":"locality",
    "wof:population":26
},
  "geometry": {"coordinates":[74.836904,14.009752],"type":"Point"}
}