{
  "type": "Feature",
  "properties": {
    "gn:admin1_code":"38.0",
    "gn:admin2_code":"348.0",
    "gn:asciiname":"Ambatari",
    "gn:country_code":"IN",
    "gn:dem":197,
    "gn:feature_class":"P",
    "gn:feature_code":"PPL",
    "gn:name":"Amb\u0101tari",
    "gn:population":0,
    "gn:timezone":"Asia/Kolkata",
    "iso:country":"IN",
    "ks:ks_alt_nam":"Amb\u0101tari",
    "ks:ks_name":"Ambatari",
    "ks:ks_pop":360,
    "ks:ks_type":"VILLAGE",
    "name:eng_x_preferred":[
        "Ambatari"
    ],
    "name:eng_x_variant":[
        "Amb\u0101tari"
    ],
    "wof:name":"Ambatari",
    "wof:placetype":"locality",
    "wof:population":360
},
  "geometry": {"coordinates":[85.28784899999999,24.517483],"type":"Point"}
}