{
  "type": "Feature",
  "properties": {
    "gn:admin1_code":"34",
    "gn:admin2_code":"232.0",
    "gn:asciiname":"Panrepatti",
    "gn:country_code":"IN",
    "gn:dem":67,
    "gn:feature_class":"P",
    "gn:feature_code":"PPL",
    "gn:name":"P\u0101nrepatti",
    "gn:population":0,
    "gn:timezone":"Asia/Kolkata",
    "iso:country":"IN",
    "ks:ks_alt_nam":"P\u0101nrepatti",
    "ks:ks_name":"Panrepatti",
    "ks:ks_pop":7596,
    "ks:ks_type":"VILLAGE",
    "ks:ks_uagg_main":0,
    "name:eng_x_preferred":[
        "Panrepatti"
    ],
    "name:eng_x_variant":[
        "P\u0101nrepatti"
    ],
    "wof:name":"Panrepatti",
    "wof:placetype":"locality",
    "wof:population":7596
},
  "geometry": {"coordinates":[83.977541,25.553662],"type":"Point"}
}