{
  "type": "Feature",
  "properties": {
    "gn:admin1_code":"35",
    "gn:admin2_code":"448.0",
    "gn:asciiname":"Surjana",
    "gn:country_code":"IN",
    "gn:dem":276,
    "gn:feature_class":"P",
    "gn:feature_code":"PPL",
    "gn:name":"Surjana",
    "gn:population":0,
    "gn:timezone":"Asia/Kolkata",
    "iso:country":"IN",
    "wof:name":"Surjana",
    "wof:placetype":"locality"
},
  "geometry": {"coordinates":[77.06336999999998,22.50062],"type":"Point"}
}