{
  "type": "Feature",
  "properties": {
    "iso:country":"IN",
    "ks:ks_name":"Kandi",
    "ks:ks_pop":194,
    "ks:ks_type":"VILLAGE",
    "name:eng_x_preferred":[
        "Kandi"
    ],
    "wof:name":"Kandi",
    "wof:placetype":"locality",
    "wof:population":194
},
  "geometry": {"coordinates":[78.26280800000001,30.618987],"type":"Point"}
}