{
  "type": "Feature",
  "properties": {
    "iso:country":"IN",
    "ks:ks_name":"Utangan Reserved Forest",
    "ks:ks_type":"VILLAGE",
    "name:eng_x_preferred":[
        "Utangan Reserved Forest"
    ],
    "wof:name":"Utangan Reserved Forest",
    "wof:placetype":"locality"
},
  "geometry": {"coordinates":[78.40612400000001,26.842375],"type":"Point"}
}