{
  "type": "Feature",
  "properties": {
    "iso:country":"IN",
    "ks:ks_name":"Janakideipur",
    "ks:ks_pop":346,
    "ks:ks_type":"VILLAGE",
    "ks:ks_uagg_main":0,
    "name:eng_x_preferred":[
        "Janakideipur"
    ],
    "wof:name":"Janakideipur",
    "wof:placetype":"neighbourhood",
    "wof:population":346
},
  "geometry": {"coordinates":[86.630754,22.262089],"type":"Point"}
}