{
  "type": "Feature",
  "properties": {
    "iso:country":"IN",
    "ks:ks_name":"Kelakali",
    "ks:ks_pop":936,
    "ks:ks_type":"HABITATION",
    "name:eng_x_preferred":[
        "Kelakali"
    ],
    "wof:name":"Kelakali",
    "wof:placetype":"locality",
    "wof:population":936
},
  "geometry": {"coordinates":[74.689458,13.698999],"type":"Point"}
}