{
  "type": "Feature",
  "properties": {
    "iso:country":"IN",
    "ks:ks_alt_nam":"CHAUHAN BASTI",
    "ks:ks_name":"Chauhan Basti",
    "ks:ks_pop":80,
    "ks:ks_type":"HABITATION",
    "name:eng_x_preferred":[
        "Chauhan Basti"
    ],
    "wof:name":"Chauhan Basti",
    "wof:placetype":"locality",
    "wof:population":80
},
  "geometry": {"coordinates":[82.211197,26.053225],"type":"Point"}
}