{
  "type": "Feature",
  "properties": {
    "gn:admin1_code":"36.0",
    "gn:admin2_code":"174.0",
    "gn:asciiname":"Chandrabhanpur",
    "gn:country_code":"IN",
    "gn:dem":99,
    "gn:feature_class":"P",
    "gn:feature_code":"PPL",
    "gn:name":"Chandrabh\u0101npur",
    "gn:population":0,
    "gn:timezone":"Asia/Kolkata",
    "iso:country":"IN",
    "ks:ks_alt_nam":"Chandrabh\u0101npur",
    "ks:ks_name":"Chandrabhanpur",
    "ks:ks_type":"VILLAGE",
    "name:eng_x_preferred":[
        "Chandrabhanpur"
    ],
    "name:eng_x_variant":[
        "Chandrabh\u0101npur"
    ],
    "wof:name":"Chandrabhanpur",
    "wof:placetype":"locality"
},
  "geometry": {"coordinates":[81.748357,25.428029],"type":"Point"}
}