{
  "type": "Feature",
  "properties": {
    "gn:admin1_code":"36",
    "gn:admin2_code":"188.0",
    "gn:asciiname":"Miranpur",
    "gn:country_code":"IN",
    "gn:dem":87,
    "gn:feature_class":"P",
    "gn:feature_code":"PPL",
    "gn:name":"Mir\u0101npur",
    "gn:population":0,
    "gn:timezone":"Asia/Kolkata",
    "iso:country":"IN",
    "ks:ks_name":"Mirapur",
    "ks:ks_pop":659,
    "ks:ks_type":"VILLAGE",
    "ks:ks_uagg_main":0,
    "name:eng_x_preferred":[
        "Mirapur"
    ],
    "wof:name":"Mirapur",
    "wof:placetype":"neighbourhood",
    "wof:population":659
},
  "geometry": {"coordinates":[83.47609799999999,26.889584],"type":"Point"}
}