{
  "type": "Feature",
  "properties": {
    "iso:country":"IN",
    "ks:ks_name":"Guhia",
    "ks:ks_pop":228,
    "ks:ks_type":"HABITATION",
    "name:eng_x_preferred":[
        "Guhia"
    ],
    "wof:name":"Guhia",
    "wof:placetype":"locality",
    "wof:population":228
},
  "geometry": {"coordinates":[86.30397600000001,24.588239],"type":"Point"}
}