{
  "type": "Feature",
  "properties": {
    "iso:country":"IN",
    "ks:ks_name":"Chintamanpur",
    "ks:ks_pop":2268,
    "ks:ks_type":"VILLAGE",
    "name:eng_x_preferred":[
        "Chintamanpur"
    ],
    "wof:name":"Chintamanpur",
    "wof:placetype":"locality",
    "wof:population":2268
},
  "geometry": {"coordinates":[85.01455,26.034153],"type":"Point"}
}