{
  "type": "Feature",
  "properties": {
    "iso:country":"IN",
    "ks:ks_name":"Golaghat",
    "ks:ks_pop":0,
    "ks:ks_type":"VILLAGE",
    "name:eng_x_preferred":[
        "Golaghat"
    ],
    "wof:name":"Golaghat",
    "wof:placetype":"locality",
    "wof:population":0
},
  "geometry": {"coordinates":[83.573986,25.554555],"type":"Point"}
}