{
  "type": "Feature",
  "properties": {
    "iso:country":"IN",
    "ks:ks_alt_nam":"MLA Road jun",
    "ks:ks_name":"Mla Road Jun",
    "ks:ks_pop":580,
    "ks:ks_type":"HABITATION",
    "ks:ks_uagg_main":0,
    "name:eng_x_preferred":[
        "Mla Road Jun"
    ],
    "wof:name":"Mla Road Jun",
    "wof:placetype":"locality",
    "wof:population":580
},
  "geometry": {"coordinates":[76.194914,10.562913],"type":"Point"}
}