{
  "type": "Feature",
  "properties": {
    "gn:admin1_code":"2",
    "gn:admin2_code":"545.0",
    "gn:asciiname":"Dumpavalasa",
    "gn:country_code":"IN",
    "gn:dem":614,
    "gn:feature_class":"P",
    "gn:feature_code":"PPL",
    "gn:name":"Dumpavalasa",
    "gn:population":0,
    "gn:timezone":"Asia/Kolkata",
    "iso:country":"IN",
    "ks:ks_name":"Dumpavalasa",
    "ks:ks_pop":446,
    "ks:ks_type":"HABITATION",
    "name:eng_x_preferred":[
        "Dumpavalasa"
    ],
    "wof:name":"Dumpavalasa",
    "wof:placetype":"locality",
    "wof:population":446
},
  "geometry": {"coordinates":[81.882485,17.787122],"type":"Point"}
}