{
  "type": "Feature",
  "properties": {
    "gn:admin1_code":"19.0",
    "gn:admin2_code":"574.0",
    "gn:asciiname":"Irakaravalli",
    "gn:country_code":"IN",
    "gn:dem":1029,
    "gn:feature_class":"P",
    "gn:feature_code":"PPL",
    "gn:name":"Irakaravalli",
    "gn:population":0,
    "gn:timezone":"Asia/Kolkata",
    "iso:country":"IN",
    "wof:name":"Irakaravalli",
    "wof:placetype":"locality"
},
  "geometry": {"coordinates":[75.85445,13.02528],"type":"Point"}
}