{
  "type": "Feature",
  "properties": {
    "iso:country":"IN",
    "ks:ks_alt_nam":"kusumpathbarudhana",
    "ks:ks_name":"Kusumpathbarudhana",
    "ks:ks_pop":155,
    "ks:ks_type":"HABITATION",
    "name:eng_x_preferred":[
        "Kusumpathbarudhana"
    ],
    "wof:name":"Kusumpathbarudhana",
    "wof:placetype":"locality",
    "wof:population":155
},
  "geometry": {"coordinates":[78.326913,22.202695],"type":"Point"}
}