{
  "type": "Feature",
  "properties": {
    "iso:country":"IN",
    "ks:ks_name":"Mhatemura",
    "ks:ks_pop":305,
    "ks:ks_type":"HABITATION",
    "name:eng_x_preferred":[
        "Mhatemura"
    ],
    "wof:name":"Mhatemura",
    "wof:placetype":"locality",
    "wof:population":305
},
  "geometry": {"coordinates":[73.79240900000001,17.796086],"type":"Point"}
}