{
  "type": "Feature",
  "properties": {
    "iso:country":"IN",
    "ks:ks_name":"Kondapalligunnalu",
    "ks:ks_pop":101,
    "ks:ks_type":"HABITATION",
    "name:eng_x_preferred":[
        "Kondapalligunnalu"
    ],
    "wof:name":"Kondapalligunnalu",
    "wof:placetype":"locality",
    "wof:population":101
},
  "geometry": {"coordinates":[82.380835,17.988098],"type":"Point"}
}