{
  "type": "Feature",
  "properties": {
    "iso:country":"IN",
    "ks:ks_name":"Gerenchi",
    "ks:ks_pop":303,
    "ks:ks_type":"HABITATION",
    "name:eng_x_preferred":[
        "Gerenchi"
    ],
    "wof:name":"Gerenchi",
    "wof:placetype":"locality",
    "wof:population":303
},
  "geometry": {"coordinates":[92.097618,26.826504],"type":"Point"}
}