{
  "type": "Feature",
  "properties": {
    "gn:admin1_code":"10",
    "gn:admin2_code":"86.0",
    "gn:asciiname":"Motisingh ki Dhani",
    "gn:country_code":"IN",
    "gn:dem":224,
    "gn:feature_class":"P",
    "gn:feature_code":"PPL",
    "gn:name":"Motisingh ki Dh\u0101ni",
    "gn:population":0,
    "gn:timezone":"Asia/Kolkata",
    "iso:country":"IN",
    "wof:name":"Motisingh ki Dhani",
    "wof:placetype":"locality"
},
  "geometry": {"coordinates":[76.74929,28.4061],"type":"Point"}
}