{
  "type": "Feature",
  "properties": {
    "iso:country":"IN",
    "ks:ks_alt_nam":"CHANDRA KANTA PARA",
    "ks:ks_name":"Chandra Kanta Para",
    "ks:ks_pop":54,
    "ks:ks_type":"HABITATION",
    "name:eng_x_preferred":[
        "Chandra Kanta Para"
    ],
    "wof:name":"Chandra Kanta Para",
    "wof:placetype":"locality",
    "wof:population":54
},
  "geometry": {"coordinates":[91.70370699999999,23.843345],"type":"Point"}
}