{
  "type": "Feature",
  "properties": {
    "gn:admin1_code":"23.0",
    "gn:admin2_code":"49.0",
    "gn:asciiname":"Fatehwal",
    "gn:country_code":"IN",
    "gn:dem":235,
    "gn:feature_class":"P",
    "gn:feature_code":"PPL",
    "gn:name":"Fatehw\u0101l",
    "gn:population":0,
    "gn:timezone":"Asia/Kolkata",
    "iso:country":"IN",
    "name:und_x_variant":[
        "Naranjanpur Fattuwal",
        "Niranjanpur Fattuwal",
        "Naranjanpur",
        "Fattuwal",
        "Fatehw\u0101l"
    ],
    "wof:name":"Fatehwal",
    "wof:placetype":"locality"
},
  "geometry": {"coordinates":[75.20761,31.54555],"type":"Point"}
}