{
  "type": "Feature",
  "properties": {
    "gn:admin1_code":"24",
    "gn:admin2_code":"110.0",
    "gn:asciiname":"Shahpura",
    "gn:country_code":"IN",
    "gn:dem":438,
    "gn:feature_class":"P",
    "gn:feature_code":"PPL",
    "gn:name":"Sh\u0101hpura",
    "gn:population":33273,
    "gn:timezone":"Asia/Kolkata",
    "iso:country":"IN",
    "name:cat_x_preferred":[
        "Shahpura"
    ],
    "name:deu_x_preferred":[
        "Shahpura"
    ],
    "name:ita_x_preferred":[
        "Shahpura"
    ],
    "name:msa_x_preferred":[
        "Shahpura"
    ],
    "name:ori_x_preferred":[
        "\u0b36\u0b3e\u0b39\u0b3e\u0b2a\u0b41\u0b30\u0b3e"
    ],
    "name:vie_x_preferred":[
        "Shahpura"
    ],
    "wof:name":"Shahpura",
    "wof:placetype":"locality",
    "wof:population":33273
},
  "geometry": {"coordinates":[75.95956,27.3912],"type":"Point"}
}