{
  "type": "Feature",
  "properties": {
    "iso:country":"IN",
    "ks:ks_name":"Jhar Singheshwar",
    "ks:ks_pop":243,
    "ks:ks_type":"VILLAGE",
    "name:eng_x_preferred":[
        "Jhar Singheshwar"
    ],
    "wof:name":"Jhar Singheshwar",
    "wof:placetype":"locality",
    "wof:population":243
},
  "geometry": {"coordinates":[88.91883199999999,26.288756],"type":"Point"}
}