{
  "type": "Feature",
  "properties": {
    "iso:country":"IN",
    "ks:ks_name":"Singda",
    "ks:ks_pop":452,
    "ks:ks_type":"VILLAGE",
    "name:eng_x_preferred":[
        "Singda"
    ],
    "wof:name":"Singda",
    "wof:placetype":"locality",
    "wof:population":452
},
  "geometry": {"coordinates":[87.582928,22.041993],"type":"Point"}
}