{
  "type": "Feature",
  "properties": {
    "iso:country":"IN",
    "ks:ks_name":"Tarigi",
    "ks:ks_pop":329,
    "ks:ks_type":"VILLAGE",
    "name:eng_x_preferred":[
        "Tarigi"
    ],
    "wof:name":"Tarigi",
    "wof:placetype":"locality",
    "wof:population":329
},
  "geometry": {"coordinates":[84.03345400000001,19.027164],"type":"Point"}
}