{
  "type": "Feature",
  "properties": {
    "iso:country":"IN",
    "ks:ks_alt_nam":"4th mile",
    "ks:ks_name":"4th Mile",
    "ks:ks_pop":566,
    "ks:ks_type":"HABITATION",
    "name:eng_x_preferred":[
        "4th Mile"
    ],
    "wof:name":"4th Mile",
    "wof:placetype":"locality",
    "wof:population":566
},
  "geometry": {"coordinates":[76.976268,9.688885],"type":"Point"}
}