{
  "type": "Feature",
  "properties": {
    "gn:admin1_code":"36",
    "gn:admin2_code":"200.0",
    "gn:asciiname":"Dumhan",
    "gn:country_code":"IN",
    "gn:dem":250,
    "gn:feature_class":"P",
    "gn:feature_code":"PPL",
    "gn:name":"Dumh\u0101n",
    "gn:population":0,
    "gn:timezone":"Asia/Kolkata",
    "iso:country":"IN",
    "ks:ks_alt_nam":"Dumh\u0101n",
    "ks:ks_name":"Dumhan",
    "ks:ks_pop":2398,
    "ks:ks_type":"VILLAGE",
    "name:eng_x_preferred":[
        "Dumhan"
    ],
    "name:eng_x_variant":[
        "Dumh\u0101n"
    ],
    "wof:name":"Dumhan",
    "wof:placetype":"locality",
    "wof:population":2398
},
  "geometry": {"coordinates":[83.181226,24.202448],"type":"Point"}
}