{
  "type": "Feature",
  "properties": {
    "iso:country":"IN",
    "ks:ks_name":"Surhela",
    "ks:ks_pop":265,
    "ks:ks_type":"VILLAGE",
    "name:eng_x_preferred":[
        "Surhela"
    ],
    "wof:name":"Surhela",
    "wof:placetype":"locality",
    "wof:population":265
},
  "geometry": {"coordinates":[77.829103,26.138748],"type":"Point"}
}