{
  "type": "Feature",
  "properties": {
    "gn:admin1_code":"12.0",
    "gn:admin2_code":"18.0",
    "gn:asciiname":"Dargushtaen",
    "gn:country_code":"IN",
    "gn:dem":2945,
    "gn:feature_class":"P",
    "gn:feature_code":"PPL",
    "gn:name":"Dargusht\u00e4n",
    "gn:population":0,
    "gn:timezone":"Asia/Kolkata",
    "iso:country":"IN",
    "wof:name":"Dargushtaen",
    "wof:placetype":"locality"
},
  "geometry": {"coordinates":[75.80403000000003,33.39136],"type":"Point"}
}