{
  "type": "Feature",
  "properties": {
    "iso:country":"IN",
    "ks:ks_name":"Srinivasaiah Colony",
    "ks:ks_pop":54,
    "ks:ks_type":"HABITATION",
    "name:eng_x_preferred":[
        "Srinivasaiah Colony"
    ],
    "wof:name":"Srinivasaiah Colony",
    "wof:placetype":"locality",
    "wof:population":54
},
  "geometry": {"coordinates":[78.81780500000001,13.626532],"type":"Point"}
}