{
  "type": "Feature",
  "properties": {
    "iso:country":"IN",
    "ks:ks_name":"Hatiakhowa",
    "ks:ks_pop":430,
    "ks:ks_type":"VILLAGE",
    "ks:ks_uagg_main":0,
    "name:eng_x_preferred":[
        "Hatiakhowa"
    ],
    "wof:name":"Hatiakhowa",
    "wof:placetype":"neighbourhood",
    "wof:population":430
},
  "geometry": {"coordinates":[92.902856,26.550323],"type":"Point"}
}