{
  "type": "Feature",
  "properties": {
    "iso:country":"IN",
    "ks:ks_alt_nam":"Gamit falia",
    "ks:ks_name":"Gamit Falia",
    "ks:ks_pop":173,
    "ks:ks_type":"HABITATION",
    "name:eng_x_preferred":[
        "Gamit Falia"
    ],
    "wof:name":"Gamit Falia",
    "wof:placetype":"locality",
    "wof:population":173
},
  "geometry": {"coordinates":[73.40297200000001,21.010778],"type":"Point"}
}