{
  "type": "Feature",
  "properties": {
    "gn:admin1_code":"39.0",
    "gn:admin2_code":"63.0",
    "gn:asciiname":"Anarpatta",
    "gn:country_code":"IN",
    "gn:dem":1631,
    "gn:feature_class":"P",
    "gn:feature_code":"PPL",
    "gn:name":"Anarpatta",
    "gn:population":0,
    "gn:timezone":"Asia/Kolkata",
    "iso:country":"IN",
    "wof:name":"Anarpatta",
    "wof:placetype":"locality"
},
  "geometry": {"coordinates":[79.68526999999997,29.98211],"type":"Point"}
}