{
  "type": "Feature",
  "properties": {
    "iso:country":"IN",
    "ks:ks_name":"Uttar Durllabhpur",
    "ks:ks_pop":294,
    "ks:ks_type":"VILLAGE",
    "name:eng_x_preferred":[
        "Uttar Durllabhpur"
    ],
    "wof:name":"Uttar Durllabhpur",
    "wof:placetype":"locality",
    "wof:population":294
},
  "geometry": {"coordinates":[88.529399,22.901569],"type":"Point"}
}