{
  "type": "Feature",
  "properties": {
    "gn:admin1_code":"11.0",
    "gn:admin2_code":"31.0",
    "gn:asciiname":"Gan ki Ser",
    "gn:country_code":"IN",
    "gn:dem":1096,
    "gn:feature_class":"P",
    "gn:feature_code":"PPL",
    "gn:name":"Gan ki Ser",
    "gn:population":0,
    "gn:timezone":"Asia/Kolkata",
    "iso:country":"IN",
    "wof:name":"Gan ki Ser",
    "wof:placetype":"locality"
},
  "geometry": {"coordinates":[77.15127,30.92844],"type":"Point"}
}