{
  "type": "Feature",
  "properties": {
    "gn:admin1_code":"10",
    "gn:admin2_code":"77.0",
    "gn:asciiname":"Ramrae",
    "gn:country_code":"IN",
    "gn:dem":231,
    "gn:feature_class":"P",
    "gn:feature_code":"PPL",
    "gn:name":"R\u0101mr\u0101e",
    "gn:population":0,
    "gn:timezone":"Asia/Kolkata",
    "iso:country":"IN",
    "wof:name":"Ramrae",
    "wof:placetype":"locality"
},
  "geometry": {"coordinates":[76.23425999999998,29.28043],"type":"Point"}
}