{
  "type": "Feature",
  "properties": {
    "gn:admin1_code":"35.0",
    "gn:admin2_code":"420",
    "gn:asciiname":"Phup Kalan",
    "gn:country_code":"IN",
    "gn:dem":146,
    "gn:feature_class":"P",
    "gn:feature_code":"PPL",
    "gn:name":"Ph\u016bp Kal\u0101n",
    "gn:population":0,
    "gn:timezone":"Asia/Kolkata",
    "iso:country":"IN",
    "wof:name":"Phup Kalan",
    "wof:placetype":"locality"
},
  "geometry": {"coordinates":[78.87359000000002,26.64454000000001],"type":"Point"}
}