{
  "type": "Feature",
  "properties": {
    "gn:country":"IN",
    "gn:fcode":"PPL",
    "gn:population":14463,
    "iso:country":"IN",
    "ks:ks_name":"Valavanur",
    "ks:ks_pop":14083,
    "ks:ks_type":"URBAN",
    "ks:ks_uagg_main":0,
    "name:bpy_x_preferred":[
        "\u09ac\u09be\u09b2\u09be\u09ac\u09be\u09a8\u09c1\u09b0"
    ],
    "name:bul_x_preferred":[
        "\u0412\u0430\u043b\u0430\u0432\u0430\u043d\u0443\u0440"
    ],
    "name:ceb_x_preferred":[
        "Valavanur"
    ],
    "name:eng_x_preferred":[
        "Valavanur"
    ],
    "name:fra_x_preferred":[
        "Valavanur"
    ],
    "name:hin_x_preferred":[
        "\u0935\u0932\u0935\u0928\u0942\u0930"
    ],
    "name:ita_x_preferred":[
        "Valavanur"
    ],
    "name:msa_x_preferred":[
        "Valavanur"
    ],
    "name:nan_x_preferred":[
        "Valavanur"
    ],
    "name:nld_x_preferred":[
        "Valavanur"
    ],
    "name:por_x_preferred":[
        "Valavanur"
    ],
    "name:rus_x_preferred":[
        "\u0412\u0430\u043b\u0430\u0432\u0430\u043d\u0443\u0440"
    ],
    "name:swe_x_preferred":[
        "Valavanur"
    ],
    "name:tam_x_preferred":[
        "\u0bb5\u0bb3\u0bb5\u0ba9\u0bc2\u0bb0\u0bcd"
    ],
    "name:und_x_variant":[
        "Valavan\u016br"
    ],
    "name:vie_x_preferred":[
        "Valavanur"
    ],
    "name:zho_x_preferred":[
        "\u74e6\u62c9\u74e6\u52aa\u5c14"
    ],
    "qs:name":"Dalavanur",
    "qs:name_adm0":"India",
    "qs:name_adm1":"Tamil Nadu",
    "qs:photos_9r":0,
    "qs:photos_sr":0,
    "qs:placetype":"Town",
    "qs:pop_sr":"6",
    "wof:name":"Valavanur",
    "wof:placetype":"locality",
    "wof:population":14083
},
  "geometry": {"coordinates":[79.579786,11.917995],"type":"Point"}
}