{
  "type": "Feature",
  "properties": {
    "iso:country":"IN",
    "ks:ks_name":"Teghra",
    "ks:ks_pop":1177,
    "ks:ks_type":"VILLAGE",
    "name:eng_x_preferred":[
        "Teghra"
    ],
    "wof:name":"Teghra",
    "wof:placetype":"locality",
    "wof:population":1177
},
  "geometry": {"coordinates":[86.45969700000001,25.865973],"type":"Point"}
}