{
  "type": "Feature",
  "properties": {
    "gn:admin1_code":"35",
    "gn:admin2_code":"455.0",
    "gn:asciiname":"Shardamai",
    "gn:country_code":"IN",
    "gn:dem":746,
    "gn:feature_class":"P",
    "gn:feature_code":"PPL",
    "gn:name":"Sh\u0101rd\u0101m\u0101i",
    "gn:population":0,
    "gn:timezone":"Asia/Kolkata",
    "iso:country":"IN",
    "wof:name":"Shardamai",
    "wof:placetype":"locality"
},
  "geometry": {"coordinates":[79.22299,22.28324],"type":"Point"}
}