{
  "type": "Feature",
  "properties": {
    "iso:country":"IN",
    "ks:ks_name":"Maghuachapari",
    "ks:ks_pop":385,
    "ks:ks_type":"VILLAGE",
    "name:eng_x_preferred":[
        "Maghuachapari"
    ],
    "wof:name":"Maghuachapari",
    "wof:placetype":"locality",
    "wof:population":385
},
  "geometry": {"coordinates":[94.15686700000001,27.15122],"type":"Point"}
}