{
  "type": "Feature",
  "properties": {
    "gn:admin1_code":"2.0",
    "gn:admin2_code":"554.0",
    "gn:asciiname":"Mamadigunta",
    "gn:country_code":"IN",
    "gn:dem":85,
    "gn:feature_class":"P",
    "gn:feature_code":"PPL",
    "gn:name":"M\u0101madigunta",
    "gn:population":0,
    "gn:timezone":"Asia/Kolkata",
    "iso:country":"IN",
    "ks:ks_name":"Mamidigunta",
    "ks:ks_pop":349,
    "ks:ks_type":"HABITATION",
    "name:eng_x_preferred":[
        "Mamidigunta"
    ],
    "name:eng_x_variant":[
        "Mamadigunta"
    ],
    "wof:name":"Mamidigunta",
    "wof:placetype":"locality",
    "wof:population":349
},
  "geometry": {"coordinates":[79.558498,13.897924],"type":"Point"}
}