{
  "type": "Feature",
  "properties": {
    "iso:country":"IN",
    "ks:ks_name":"Hermadu",
    "ks:ks_pop":53,
    "ks:ks_type":"HABITATION",
    "name:eng_x_preferred":[
        "Hermadu"
    ],
    "wof:name":"Hermadu",
    "wof:placetype":"locality",
    "wof:population":53
},
  "geometry": {"coordinates":[76.005833,12.021944],"type":"Point"}
}