{
  "type": "Feature",
  "properties": {
    "gn:admin1_code":"16.0",
    "gn:admin2_code":"526.0",
    "gn:asciiname":"Shirval",
    "gn:country_code":"IN",
    "gn:dem":469,
    "gn:feature_class":"P",
    "gn:feature_code":"PPL",
    "gn:name":"Shirval",
    "gn:population":0,
    "gn:timezone":"Asia/Kolkata",
    "iso:country":"IN",
    "name:und_x_variant":[
        "Shir\u0101val"
    ],
    "wof:name":"Shirval",
    "wof:placetype":"locality"
},
  "geometry": {"coordinates":[76.29141,17.5905],"type":"Point"}
}