{
  "type": "Feature",
  "properties": {
    "gn:admin1_code":"11.0",
    "gn:admin2_code":"27.0",
    "gn:asciiname":"Thawanu",
    "gn:country_code":"IN",
    "gn:dem":1960,
    "gn:feature_class":"P",
    "gn:feature_code":"PPL",
    "gn:name":"Thaw\u0101nu",
    "gn:population":0,
    "gn:timezone":"Asia/Kolkata",
    "iso:country":"IN",
    "wof:name":"Thawanu",
    "wof:placetype":"locality"
},
  "geometry": {"coordinates":[77.14755,31.65867],"type":"Point"}
}