{
  "type": "Feature",
  "properties": {
    "iso:country":"IN",
    "ks:ks_name":"Khorta",
    "ks:ks_pop":224,
    "ks:ks_type":"VILLAGE",
    "ks:ks_uagg_main":0,
    "name:eng_x_preferred":[
        "Khorta"
    ],
    "wof:name":"Khorta",
    "wof:placetype":"neighbourhood",
    "wof:population":224
},
  "geometry": {"coordinates":[86.222515,20.189801],"type":"Point"}
}