{
  "type": "Feature",
  "properties": {
    "iso:country":"IN",
    "ks:ks_alt_nam":"MUSALMANO KA PADA",
    "ks:ks_name":"Musalmano Ka Pada",
    "ks:ks_pop":678,
    "ks:ks_type":"HABITATION",
    "name:eng_x_preferred":[
        "Musalmano Ka Pada"
    ],
    "wof:name":"Musalmano Ka Pada",
    "wof:placetype":"locality",
    "wof:population":678
},
  "geometry": {"coordinates":[70.768113,25.531232],"type":"Point"}
}