{
  "type": "Feature",
  "properties": {
    "iso:country":"IN",
    "ks:ks_name":"Nawa Gaon",
    "ks:ks_pop":528,
    "ks:ks_type":"HABITATION",
    "name:eng_x_preferred":[
        "Nawa Gaon"
    ],
    "wof:name":"Nawa Gaon",
    "wof:placetype":"locality",
    "wof:population":528
},
  "geometry": {"coordinates":[73.955067,23.422892],"type":"Point"}
}