{
  "type": "Feature",
  "properties": {
    "gn:country":"IN",
    "gn:fcode":"PPL",
    "gn:population":0,
    "iso:country":"IN",
    "name:ara_x_preferred":[
        "\u0641\u0627\u062a\u062d \u0628\u0648\u0631\u064a"
    ],
    "name:ben_bn_x_preferred":[
        "\u09ab\u09a4\u09c7\u09aa\u09c1\u09b0\u09c0"
    ],
    "name:ben_in_x_preferred":[
        "\u09ab\u09a4\u09c7\u09aa\u09c1\u09b0\u09c0"
    ],
    "name:guj_x_preferred":[
        "\u0aab\u0aa4\u0ac7\u0ab9\u0aaa\u0ac1\u0ab0\u0ac0"
    ],
    "name:hin_x_preferred":[
        "\u092b\u0924\u0947\u0939\u092a\u0941\u0930\u0940"
    ],
    "name:kan_x_preferred":[
        "\u0cab\u0ca4\u0cc7\u0cb9\u0ccd"
    ],
    "name:mal_x_preferred":[
        "\u0d2b\u0d24\u0d4d\u0d24\u0d47\u0d2a\u0d41\u0d30\u0d3f"
    ],
    "name:mar_x_preferred":[
        "\u092b\u0924\u0947\u0939\u092a\u0941\u0930\u0940"
    ],
    "name:pan_x_preferred":[
        "\u0a2b\u0a24\u0a47\u0a39\u0a2a\u0a41\u0a30\u0a40"
    ],
    "name:tam_x_preferred":[
        "\u0b83\u0baa\u0ba4\u0bc7\u0baa\u0bc1\u0bb0\u0bbf"
    ],
    "name:tel_x_preferred":[
        "\u0c2b\u0c24\u0c47\u0c2a\u0c42\u0c30\u0c3f"
    ],
    "name:urd_x_preferred":[
        "\u0641\u062a\u062d \u067e\u0648\u0631\u06cc"
    ],
    "qs:name":"Fatehpuri",
    "qs:name_adm0":"India",
    "qs:name_adm1":"Delhi",
    "qs:photos":366,
    "qs:photos_1k":74,
    "qs:photos_9k":2,
    "qs:photos_9r":5,
    "qs:photos_all":366,
    "qs:photos_sr":6,
    "qs:placetype":"Suburb",
    "qs:pop_sr":"0",
    "wof:name":"Fatehpuri",
    "wof:placetype":"neighbourhood",
    "wof:population":0
},
  "geometry": {"coordinates":[76.97906,28.92482],"type":"Point"}
}