{
  "type": "Feature",
  "properties": {
    "iso:country":"IN",
    "ks:ks_name":"Veviko",
    "ks:ks_pop":234,
    "ks:ks_type":"HABITATION",
    "ks:ks_uagg_main":0,
    "name:eng_x_preferred":[
        "Veviko"
    ],
    "wof:name":"Veviko",
    "wof:placetype":"neighbourhood",
    "wof:population":234
},
  "geometry": {"coordinates":[93.90266099999999,25.944472],"type":"Point"}
}