{
  "type": "Feature",
  "properties": {
    "iso:country":"IN",
    "ks:ks_name":"Dariapara",
    "ks:ks_pop":1153,
    "ks:ks_type":"VILLAGE",
    "ks:ks_uagg_main":0,
    "name:eng_x_preferred":[
        "Dariapara"
    ],
    "wof:name":"Dariapara",
    "wof:placetype":"neighbourhood",
    "wof:population":1153
},
  "geometry": {"coordinates":[91.972002,26.396207],"type":"Point"}
}