{
  "type": "Feature",
  "properties": {
    "iso:country":"IN",
    "ks:ks_name":"Rangaguda",
    "ks:ks_pop":481,
    "ks:ks_type":"VILLAGE",
    "name:eng_x_preferred":[
        "Rangaguda"
    ],
    "wof:name":"Rangaguda",
    "wof:placetype":"locality",
    "wof:population":481
},
  "geometry": {"coordinates":[84.236659,19.475805],"type":"Point"}
}