{
  "type": "Feature",
  "properties": {
    "iso:country":"IN",
    "ks:ks_alt_nam":"SURYAVAVNSHI MALA",
    "ks:ks_name":"Suryavavnshi Mala",
    "ks:ks_pop":120,
    "ks:ks_type":"HABITATION",
    "name:eng_x_preferred":[
        "Suryavavnshi Mala"
    ],
    "wof:name":"Suryavavnshi Mala",
    "wof:placetype":"locality",
    "wof:population":120
},
  "geometry": {"coordinates":[74.756855,17.203622],"type":"Point"}
}