{
  "type": "Feature",
  "properties": {
    "iso:country":"IN",
    "ks:ks_alt_nam":"Shri vel ka pura",
    "ks:ks_name":"Shri Vel Ka Pura",
    "ks:ks_pop":68,
    "ks:ks_type":"HABITATION",
    "name:eng_x_preferred":[
        "Shri Vel Ka Pura"
    ],
    "wof:name":"Shri Vel Ka Pura",
    "wof:placetype":"locality",
    "wof:population":68
},
  "geometry": {"coordinates":[81.878107,26.193451],"type":"Point"}
}