{
  "type": "Feature",
  "properties": {
    "iso:country":"IN",
    "ks:ks_name":"Attihaklu",
    "ks:ks_pop":7,
    "ks:ks_type":"HABITATION",
    "name:eng_x_preferred":[
        "Attihaklu"
    ],
    "wof:name":"Attihaklu",
    "wof:placetype":"locality",
    "wof:population":7
},
  "geometry": {"coordinates":[75.340862,13.791809],"type":"Point"}
}