{
  "type": "Feature",
  "properties": {
    "iso:country":"IN",
    "ks:ks_name":"Dongaripada",
    "ks:ks_pop":127,
    "ks:ks_type":"HABITATION",
    "name:eng_x_preferred":[
        "Dongaripada"
    ],
    "wof:name":"Dongaripada",
    "wof:placetype":"locality",
    "wof:population":127
},
  "geometry": {"coordinates":[72.918538,19.904402],"type":"Point"}
}