{
  "type": "Feature",
  "properties": {
    "iso:country":"IN",
    "ks:ks_name":"Jeerivanivalasa",
    "ks:ks_pop":20,
    "ks:ks_type":"HABITATION",
    "name:eng_x_preferred":[
        "Jeerivanivalasa"
    ],
    "wof:name":"Jeerivanivalasa",
    "wof:placetype":"locality",
    "wof:population":20
},
  "geometry": {"coordinates":[83.173445,18.32837],"type":"Point"}
}