{
  "type": "Feature",
  "properties": {
    "gn:admin1_code":"24.0",
    "gn:admin2_code":"114.0",
    "gn:asciiname":"Hadda",
    "gn:country_code":"IN",
    "gn:dem":162,
    "gn:feature_class":"P",
    "gn:feature_code":"PPL",
    "gn:name":"Hadda",
    "gn:population":0,
    "gn:timezone":"Asia/Kolkata",
    "iso:country":"IN",
    "wof:name":"Hadda",
    "wof:placetype":"locality"
},
  "geometry": {"coordinates":[71.03228,27.09936],"type":"Point"}
}