{
  "type": "Feature",
  "properties": {
    "gn:admin1_code":"37",
    "gn:admin2_code":"406.0",
    "gn:asciiname":"Banjarpara",
    "gn:country_code":"IN",
    "gn:dem":292,
    "gn:feature_class":"P",
    "gn:feature_code":"PPL",
    "gn:name":"Banjarp\u0101ra",
    "gn:population":0,
    "gn:timezone":"Asia/Kolkata",
    "iso:country":"IN",
    "wof:name":"Banjarpara",
    "wof:placetype":"neighbourhood"
},
  "geometry": {"coordinates":[82.19844999999999,22.28317],"type":"Point"}
}