{
  "type": "Feature",
  "properties": {
    "iso:country":"IN",
    "ks:ks_name":"Parwalia",
    "ks:ks_pop":395,
    "ks:ks_type":"VILLAGE",
    "ks:ks_uagg_main":0,
    "name:eng_x_preferred":[
        "Parwalia"
    ],
    "wof:name":"Parwalia",
    "wof:placetype":"neighbourhood",
    "wof:population":395
},
  "geometry": {"coordinates":[84.317289,26.470277],"type":"Point"}
}