{
  "type": "Feature",
  "properties": {
    "iso:country":"IN",
    "ks:ks_alt_nam":"R\u0101mgarh Reserved Forest",
    "ks:ks_alt_nam_2":"Ramgarh Reserved Forest",
    "ks:ks_name":"Ramgarh",
    "ks:ks_type":"VILLAGE",
    "name:eng_x_preferred":[
        "Ramgarh"
    ],
    "name:eng_x_variant":[
        "R\u0101mgarh Reserved Forest",
        "Ramgarh Reserved Forest"
    ],
    "wof:name":"Ramgarh",
    "wof:placetype":"locality"
},
  "geometry": {"coordinates":[83.46084500000001,26.731416],"type":"Point"}
}