{
  "type": "Feature",
  "properties": {
    "iso:country":"IN",
    "ks:ks_name":"Taharpur II",
    "ks:ks_pop":1699,
    "ks:ks_type":"VILLAGE",
    "ks:ks_uagg_main":0,
    "name:eng_x_preferred":[
        "Taharpur II"
    ],
    "wof:name":"Taharpur II",
    "wof:placetype":"neighbourhood",
    "wof:population":1699
},
  "geometry": {"coordinates":[78.73046600000001,28.739685],"type":"Point"}
}