{
  "type": "Feature",
  "properties": {
    "gn:admin1_code":"11",
    "gn:admin2_code":"27.0",
    "gn:asciiname":"Rhapna",
    "gn:country_code":"IN",
    "gn:dem":1861,
    "gn:feature_class":"P",
    "gn:feature_code":"PPL",
    "gn:name":"Rhapna",
    "gn:population":0,
    "gn:timezone":"Asia/Kolkata",
    "iso:country":"IN",
    "wof:name":"Rhapna",
    "wof:placetype":"locality"
},
  "geometry": {"coordinates":[76.99824,31.3621],"type":"Point"}
}