{
  "type": "Feature",
  "properties": {
    "iso:country":"IN",
    "ks:ks_name":"Bala Tola",
    "ks:ks_pop":353,
    "ks:ks_type":"VILLAGE",
    "name:eng_x_preferred":[
        "Bala Tola"
    ],
    "wof:name":"Bala Tola",
    "wof:placetype":"locality",
    "wof:population":353
},
  "geometry": {"coordinates":[85.223434,26.317342],"type":"Point"}
}