{
  "type": "Feature",
  "properties": {
    "iso:country":"IN",
    "ks:ks_name":"Kisantoli",
    "ks:ks_pop":125,
    "ks:ks_type":"HABITATION",
    "name:eng_x_preferred":[
        "Kisantoli"
    ],
    "wof:name":"Kisantoli",
    "wof:placetype":"locality",
    "wof:population":125
},
  "geometry": {"coordinates":[84.781485,22.522537],"type":"Point"}
}