{
  "type": "Feature",
  "properties": {
    "gn:admin1_code":"11",
    "gn:admin2_code":"23.0",
    "gn:asciiname":"Kundi Adwar",
    "gn:country_code":"IN",
    "gn:dem":2612,
    "gn:feature_class":"P",
    "gn:feature_code":"PPL",
    "gn:name":"K\u016bndi Adw\u0101r",
    "gn:population":0,
    "gn:timezone":"Asia/Kolkata",
    "iso:country":"IN",
    "wof:name":"Kundi Adwar",
    "wof:placetype":"locality"
},
  "geometry": {"coordinates":[76.00662,32.794],"type":"Point"}
}