{
  "type": "Feature",
  "properties": {
    "iso:country":"IN",
    "ks:ks_name":"Kheenwsar",
    "ks:ks_pop":281,
    "ks:ks_type":"HABITATION",
    "name:eng_x_preferred":[
        "Kheenwsar"
    ],
    "wof:name":"Kheenwsar",
    "wof:placetype":"locality",
    "wof:population":281
},
  "geometry": {"coordinates":[71.922465,26.614239],"type":"Point"}
}