{
  "type": "Feature",
  "properties": {
    "iso:country":"IN",
    "ks:ks_name":"Bansidag",
    "ks:ks_pop":87,
    "ks:ks_type":"HABITATION",
    "name:eng_x_preferred":[
        "Bansidag"
    ],
    "wof:name":"Bansidag",
    "wof:placetype":"locality",
    "wof:population":87
},
  "geometry": {"coordinates":[85.45690399999999,23.20884],"type":"Point"}
}