{
  "type": "Feature",
  "properties": {
    "gn:admin1_code":"37",
    "gn:admin2_code":"408.0",
    "gn:asciiname":"Tumrikasa",
    "gn:country_code":"IN",
    "gn:dem":363,
    "gn:feature_class":"P",
    "gn:feature_code":"PPL",
    "gn:name":"Tumr\u012bkasa",
    "gn:population":0,
    "gn:timezone":"Asia/Kolkata",
    "iso:country":"IN",
    "ks:ks_name":"Tumdikasa",
    "ks:ks_pop":774,
    "ks:ks_type":"VILLAGE",
    "name:eng_x_preferred":[
        "Tumdikasa"
    ],
    "name:eng_x_variant":[
        "Tumrikasa"
    ],
    "wof:name":"Tumdikasa",
    "wof:placetype":"locality",
    "wof:population":774
},
  "geometry": {"coordinates":[80.758031,20.376342],"type":"Point"}
}