{
  "type": "Feature",
  "properties": {
    "iso:country":"IN",
    "ks:ks_name":"Jadumani",
    "ks:ks_pop":1015,
    "ks:ks_type":"VILLAGE",
    "name:eng_x_preferred":[
        "Jadumani"
    ],
    "wof:name":"Jadumani",
    "wof:placetype":"locality",
    "wof:population":1015
},
  "geometry": {"coordinates":[90.164362,26.391959],"type":"Point"}
}