{
  "type": "Feature",
  "properties": {
    "iso:country":"IN",
    "ks:ks_name":"Rampur Dan",
    "ks:ks_pop":1743,
    "ks:ks_type":"VILLAGE",
    "name:eng_x_preferred":[
        "Rampur Dan"
    ],
    "wof:name":"Rampur Dan",
    "wof:placetype":"locality",
    "wof:population":1743
},
  "geometry": {"coordinates":[82.20670800000001,25.753459],"type":"Point"}
}