{
  "type": "Feature",
  "properties": {
    "iso:country":"IN",
    "qs:name":"Luhri",
    "qs:name_adm0":"India",
    "qs:name_adm1":"Himachal Pradesh",
    "qs:photos":9,
    "qs:photos_1k":2,
    "qs:photos_9k":1,
    "qs:photos_9r":1,
    "qs:photos_all":9,
    "qs:photos_sr":1,
    "qs:placetype":"Town",
    "qs:pop_sr":"0",
    "wd:wordcount":56,
    "wof:name":"Luhri",
    "wof:placetype":"locality"
},
  "geometry": {"coordinates":[77.42886300000001,31.340008],"type":"Point"}
}