{
  "type": "Feature",
  "properties": {
    "iso:country":"IN",
    "ks:ks_alt_nam":"10 GGM",
    "ks:ks_name":"10 Ggm",
    "ks:ks_pop":33,
    "ks:ks_type":"HABITATION",
    "name:eng_x_preferred":[
        "10 Ggm"
    ],
    "wof:name":"10 Ggm",
    "wof:placetype":"locality",
    "wof:population":33
},
  "geometry": {"coordinates":[74.958536,29.115531],"type":"Point"}
}