{
  "type": "Feature",
  "properties": {
    "iso:country":"IN",
    "ks:ks_name":"Gavalwadi",
    "ks:ks_pop":350,
    "ks:ks_type":"HABITATION",
    "name:eng_x_preferred":[
        "Gavalwadi"
    ],
    "wof:name":"Gavalwadi",
    "wof:placetype":"locality",
    "wof:population":350
},
  "geometry": {"coordinates":[73.67694400000001,17.001944],"type":"Point"}
}