{
  "type": "Feature",
  "properties": {
    "iso:country":"IN",
    "ks:ks_name":"Patademala",
    "ks:ks_pop":521,
    "ks:ks_type":"HABITATION",
    "name:eng_x_preferred":[
        "Patademala"
    ],
    "wof:name":"Patademala",
    "wof:placetype":"locality",
    "wof:population":521
},
  "geometry": {"coordinates":[74.115295,19.066965],"type":"Point"}
}