{
  "type": "Feature",
  "properties": {
    "iso:country":"IN",
    "ks:ks_name":"Bojjiguda",
    "ks:ks_pop":118,
    "ks:ks_type":"HABITATION",
    "name:eng_x_preferred":[
        "Bojjiguda"
    ],
    "wof:name":"Bojjiguda",
    "wof:placetype":"locality",
    "wof:population":118
},
  "geometry": {"coordinates":[79.137827,19.218498],"type":"Point"}
}