{
  "type": "Feature",
  "properties": {
    "gn:admin1_code":"36.0",
    "gn:admin2_code":"190.0",
    "gn:asciiname":"Harku",
    "gn:country_code":"IN",
    "gn:dem":75,
    "gn:feature_class":"P",
    "gn:feature_code":"PPL",
    "gn:name":"Harku",
    "gn:population":0,
    "gn:timezone":"Asia/Kolkata",
    "iso:country":"IN",
    "name:ceb_x_preferred":[
        "Harku"
    ],
    "name:ces_x_preferred":[
        "Harku"
    ],
    "name:est_x_preferred":[
        "Harku"
    ],
    "name:fas_x_preferred":[
        "\u0647\u0627\u0631\u06a9\u0648"
    ],
    "name:fra_x_preferred":[
        "Harku"
    ],
    "name:hye_x_preferred":[
        "\u0540\u0561\u057c\u056f\u0578\u0582"
    ],
    "name:lit_x_preferred":[
        "Harku"
    ],
    "name:pol_x_preferred":[
        "Harku"
    ],
    "name:sco_x_preferred":[
        "Harku"
    ],
    "name:spa_x_preferred":[
        "Harku"
    ],
    "name:swe_x_preferred":[
        "Harku"
    ],
    "name:vol_x_preferred":[
        "Harku"
    ],
    "wof:name":"Harku",
    "wof:placetype":"locality"
},
  "geometry": {"coordinates":[84.03549,26.38093],"type":"Point"}
}