{
  "type": "Feature",
  "properties": {
    "iso:country":"IN",
    "ks:ks_name":"Pimpala Bhatya",
    "ks:ks_pop":1158,
    "ks:ks_type":"VILLAGE",
    "name:eng_x_preferred":[
        "Pimpala Bhatya"
    ],
    "wof:name":"Pimpala Bhatya",
    "wof:placetype":"locality",
    "wof:population":1158
},
  "geometry": {"coordinates":[77.168029,19.179446],"type":"Point"}
}