{
  "type": "Feature",
  "properties": {
    "iso:country":"IN",
    "ks:ks_name":"Keeranahola",
    "ks:ks_pop":180,
    "ks:ks_type":"HABITATION",
    "name:eng_x_preferred":[
        "Keeranahola"
    ],
    "wof:name":"Keeranahola",
    "wof:placetype":"locality",
    "wof:population":180
},
  "geometry": {"coordinates":[77.60703700000001,12.041419],"type":"Point"}
}