{
  "type": "Feature",
  "properties": {
    "iso:country":"IN",
    "ks:ks_name":"Badko",
    "ks:ks_pop":447,
    "ks:ks_type":"VILLAGE",
    "name:eng_x_preferred":[
        "Badko"
    ],
    "wof:name":"Badko",
    "wof:placetype":"locality",
    "wof:population":447
},
  "geometry": {"coordinates":[81.49391300000001,19.514888],"type":"Point"}
}