{
  "type": "Feature",
  "properties": {
    "iso:country":"IN",
    "ks:ks_name":"Nemuadih",
    "ks:ks_pop":758,
    "ks:ks_type":"VILLAGE",
    "ks:ks_uagg_main":0,
    "name:eng_x_preferred":[
        "Nemuadih"
    ],
    "wof:name":"Nemuadih",
    "wof:placetype":"neighbourhood",
    "wof:population":758
},
  "geometry": {"coordinates":[86.510704,24.278749],"type":"Point"}
}