{
  "type": "Feature",
  "properties": {
    "iso:country":"IN",
    "ks:ks_name":"Palliyara",
    "ks:ks_pop":677,
    "ks:ks_type":"HABITATION",
    "name:eng_x_preferred":[
        "Palliyara"
    ],
    "wof:name":"Palliyara",
    "wof:placetype":"locality",
    "wof:population":677
},
  "geometry": {"coordinates":[75.72147099999999,11.729224],"type":"Point"}
}