{
  "type": "Feature",
  "properties": {
    "iso:country":"IN",
    "ks:ks_name":"Teliatura",
    "ks:ks_pop":1691,
    "ks:ks_type":"VILLAGE",
    "ks:ks_uagg_main":0,
    "name:eng_x_preferred":[
        "Teliatura"
    ],
    "wof:name":"Teliatura",
    "wof:placetype":"neighbourhood",
    "wof:population":1691
},
  "geometry": {"coordinates":[86.06215899999999,23.983241],"type":"Point"}
}