{
  "type": "Feature",
  "properties": {
    "iso:country":"IN",
    "ks:ks_alt_nam":"RENUKAWASTI",
    "ks:ks_name":"Renukawasti",
    "ks:ks_pop":40,
    "ks:ks_type":"HABITATION",
    "name:eng_x_preferred":[
        "Renukawasti"
    ],
    "wof:name":"Renukawasti",
    "wof:placetype":"locality",
    "wof:population":40
},
  "geometry": {"coordinates":[74.616422,18.820015],"type":"Point"}
}