{
  "type": "Feature",
  "properties": {
    "iso:country":"IN",
    "ks:ks_alt_nam":"PIPRA 114",
    "ks:ks_name":"Pipra 114",
    "ks:ks_pop":552,
    "ks:ks_type":"HABITATION",
    "name:eng_x_preferred":[
        "Pipra 114"
    ],
    "wof:name":"Pipra 114",
    "wof:placetype":"locality",
    "wof:population":552
},
  "geometry": {"coordinates":[84.083648,24.256414],"type":"Point"}
}