{
  "type": "Feature",
  "properties": {
    "iso:country":"IN",
    "ks:ks_name":"Majhigaon",
    "ks:ks_pop":212,
    "ks:ks_type":"VILLAGE",
    "name:eng_x_preferred":[
        "Majhigaon"
    ],
    "wof:name":"Majhigaon",
    "wof:placetype":"locality",
    "wof:population":212
},
  "geometry": {"coordinates":[90.48329,26.394625],"type":"Point"}
}