{
  "type": "Feature",
  "properties": {
    "iso:country":"IN",
    "ks:ks_name":"Mafiya",
    "ks:ks_pop":84,
    "ks:ks_type":"HABITATION",
    "name:eng_x_preferred":[
        "Mafiya"
    ],
    "wof:name":"Mafiya",
    "wof:placetype":"locality",
    "wof:population":84
},
  "geometry": {"coordinates":[82.24932200000001,26.677432],"type":"Point"}
}