{
  "type": "Feature",
  "properties": {
    "gn:admin1_code":"23",
    "gn:admin2_code":"40.0",
    "gn:asciiname":"Baraunga Baland",
    "gn:country_code":"IN",
    "gn:dem":266,
    "gn:feature_class":"P",
    "gn:feature_code":"PPL",
    "gn:name":"Baraunga Baland",
    "gn:population":0,
    "gn:timezone":"Asia/Kolkata",
    "iso:country":"IN",
    "ks:ks_name":"Baraunga Buland",
    "ks:ks_pop":644,
    "ks:ks_type":"VILLAGE",
    "ks:ks_uagg_main":0,
    "name:eng_x_preferred":[
        "Baraunga Buland"
    ],
    "wof:name":"Baraunga Buland",
    "wof:placetype":"neighbourhood",
    "wof:population":644
},
  "geometry": {"coordinates":[76.268725,30.627765],"type":"Point"}
}