{
  "type": "Feature",
  "properties": {
    "gn:admin1_code":"16.0",
    "gn:admin2_code":"515.0",
    "gn:asciiname":"Malpur",
    "gn:country_code":"IN",
    "gn:dem":611,
    "gn:feature_class":"P",
    "gn:feature_code":"PPL",
    "gn:name":"M\u0101lpur",
    "gn:population":0,
    "gn:timezone":"Asia/Kolkata",
    "iso:country":"IN",
    "wof:name":"Malpur",
    "wof:placetype":"locality"
},
  "geometry": {"coordinates":[75.15483,20.23187],"type":"Point"}
}