{
  "type": "Feature",
  "properties": {
    "iso:country":"IN",
    "ks:ks_name":"Morni",
    "ks:ks_pop":78,
    "ks:ks_type":"VILLAGE",
    "name:eng_x_preferred":[
        "Morni"
    ],
    "wof:name":"Morni",
    "wof:placetype":"locality",
    "wof:population":78
},
  "geometry": {"coordinates":[73.643404,17.728066],"type":"Point"}
}