{
  "type": "Feature",
  "properties": {
    "gn:admin1_code":"34",
    "gn:admin2_code":"234.0",
    "gn:asciiname":"Salthua",
    "gn:country_code":"IN",
    "gn:dem":98,
    "gn:feature_class":"P",
    "gn:feature_code":"PPL",
    "gn:name":"Salthua",
    "gn:population":0,
    "gn:timezone":"Asia/Kolkata",
    "iso:country":"IN",
    "ks:ks_name":"Salthura",
    "ks:ks_pop":120,
    "ks:ks_type":"HABITATION",
    "name:eng_x_preferred":[
        "Salthura"
    ],
    "name:eng_x_variant":[
        "Salthua"
    ],
    "wof:name":"Salthura",
    "wof:placetype":"locality",
    "wof:population":120
},
  "geometry": {"coordinates":[83.83999900000001,24.942397],"type":"Point"}
}