{
  "type": "Feature",
  "properties": {
    "iso:country":"IN",
    "ks:ks_name":"Zami Machavaram",
    "ks:ks_type":"VILLAGE",
    "name:eng_x_preferred":[
        "Zami Machavaram"
    ],
    "wof:name":"Zami Machavaram",
    "wof:placetype":"locality"
},
  "geometry": {"coordinates":[80.46337200000001,16.631484],"type":"Point"}
}