{
  "type": "Feature",
  "properties": {
    "gn:admin1_code":"2.0",
    "gn:admin2_code":"551.0",
    "gn:asciiname":"Kammapalli",
    "gn:country_code":"IN",
    "gn:dem":195,
    "gn:feature_class":"P",
    "gn:feature_code":"PPL",
    "gn:name":"Kammapalli",
    "gn:population":0,
    "gn:timezone":"Asia/Kolkata",
    "iso:country":"IN",
    "name:tel_x_preferred":[
        "\u0c15\u0c2e\u0c4d\u0c2e\u0c2a\u0c32\u0c4d\u0c32\u0c3f"
    ],
    "wof:name":"Kammapalli",
    "wof:placetype":"locality"
},
  "geometry": {"coordinates":[79.2248,14.06011],"type":"Point"}
}