{
  "type": "Feature",
  "properties": {
    "iso:country":"IN",
    "ks:ks_name":"Nadupatti",
    "ks:ks_pop":270,
    "ks:ks_type":"HABITATION",
    "name:eng_x_preferred":[
        "Nadupatti"
    ],
    "wof:name":"Nadupatti",
    "wof:placetype":"locality",
    "wof:population":270
},
  "geometry": {"coordinates":[78.859995,10.575101],"type":"Point"}
}