{
  "type": "Feature",
  "properties": {
    "gn:admin1_code":"36",
    "gn:admin2_code":"200.0",
    "gn:asciiname":"Kanhaura",
    "gn:country_code":"IN",
    "gn:dem":301,
    "gn:feature_class":"P",
    "gn:feature_code":"PPL",
    "gn:name":"Kanhaura",
    "gn:population":0,
    "gn:timezone":"Asia/Kolkata",
    "iso:country":"IN",
    "ks:ks_name":"Kanhara",
    "ks:ks_pop":314,
    "ks:ks_type":"VILLAGE",
    "name:eng_x_preferred":[
        "Kanhara"
    ],
    "name:eng_x_variant":[
        "Kanhaura"
    ],
    "wof:name":"Kanhara",
    "wof:placetype":"locality",
    "wof:population":314
},
  "geometry": {"coordinates":[83.009896,24.751618],"type":"Point"}
}