{
  "type": "Feature",
  "properties": {
    "iso:country":"IN",
    "ks:ks_name":"Bandhan",
    "ks:ks_pop":65,
    "ks:ks_type":"VILLAGE",
    "name:eng_x_preferred":[
        "Bandhan"
    ],
    "wof:name":"Bandhan",
    "wof:placetype":"locality",
    "wof:population":65
},
  "geometry": {"coordinates":[78.39720699999999,30.192933],"type":"Point"}
}