{
  "type": "Feature",
  "properties": {
    "iso:country":"IN",
    "ks:ks_name":"Shankarpura",
    "ks:ks_pop":313,
    "ks:ks_type":"HABITATION",
    "name:eng_x_preferred":[
        "Shankarpura"
    ],
    "wof:name":"Shankarpura",
    "wof:placetype":"locality",
    "wof:population":313
},
  "geometry": {"coordinates":[72.758111,22.541417],"type":"Point"}
}