{
  "type": "Feature",
  "properties": {
    "iso:country":"IN",
    "ks:ks_name":"Bajitpur",
    "ks:ks_pop":1003,
    "ks:ks_type":"VILLAGE",
    "ks:ks_uagg_main":0,
    "name:eng_x_preferred":[
        "Bajitpur"
    ],
    "wof:name":"Bajitpur",
    "wof:placetype":"neighbourhood",
    "wof:population":1003
},
  "geometry": {"coordinates":[88.649123,22.666878],"type":"Point"}
}