{
  "type": "Feature",
  "properties": {
    "gn:admin1_code":"12.0",
    "gn:asciiname":"Kaiyan",
    "gn:country_code":"IN",
    "gn:dem":2470,
    "gn:feature_class":"P",
    "gn:feature_code":"PPL",
    "gn:name":"Kaiy\u0101n",
    "gn:population":0,
    "gn:timezone":"Asia/Karachi",
    "iso:country":"IN",
    "wof:name":"Kaiyan",
    "wof:placetype":"locality"
},
  "geometry": {"coordinates":[73.95390999999999,34.30191],"type":"Point"}
}