{
  "type": "Feature",
  "properties": {
    "iso:country":"IN",
    "ks:ks_alt_nam":"chamaran purwa",
    "ks:ks_name":"Chamaran Purwa",
    "ks:ks_pop":26,
    "ks:ks_type":"HABITATION",
    "name:eng_x_preferred":[
        "Chamaran Purwa"
    ],
    "wof:name":"Chamaran Purwa",
    "wof:placetype":"locality",
    "wof:population":26
},
  "geometry": {"coordinates":[81.63945699999999,27.256923],"type":"Point"}
}