{
  "type": "Feature",
  "properties": {
    "gn:admin1_code":"2.0",
    "gn:admin2_code":"554.0",
    "gn:asciiname":"Uddandamaharajupuram",
    "gn:country_code":"IN",
    "gn:dem":202,
    "gn:feature_class":"P",
    "gn:feature_code":"PPL",
    "gn:name":"Uddandamah\u0101r\u0101jupuram",
    "gn:population":0,
    "gn:timezone":"Asia/Kolkata",
    "iso:country":"IN",
    "wof:name":"Uddandamaharajupuram",
    "wof:placetype":"locality"
},
  "geometry": {"coordinates":[79.34775,13.29994],"type":"Point"}
}