{
  "type": "Feature",
  "properties": {
    "iso:country":"IN",
    "ks:ks_name":"Batakuchi",
    "ks:ks_pop":550,
    "ks:ks_type":"VILLAGE",
    "name:eng_x_preferred":[
        "Batakuchi"
    ],
    "wof:name":"Batakuchi",
    "wof:placetype":"locality",
    "wof:population":550
},
  "geometry": {"coordinates":[91.966724,26.69714],"type":"Point"}
}