{
  "type": "Feature",
  "properties": {
    "iso:country":"IN",
    "ks:ks_name":"Ramanabandha",
    "ks:ks_pop":47,
    "ks:ks_type":"HABITATION",
    "name:eng_x_preferred":[
        "Ramanabandha"
    ],
    "wof:name":"Ramanabandha",
    "wof:placetype":"locality",
    "wof:population":47
},
  "geometry": {"coordinates":[82.57634899999999,18.024589],"type":"Point"}
}