{
  "type": "Feature",
  "properties": {
    "gn:admin1_code":"39.0",
    "gn:admin2_code":"63.0",
    "gn:asciiname":"Okhalisirod",
    "gn:country_code":"IN",
    "gn:dem":1321,
    "gn:feature_class":"P",
    "gn:feature_code":"PPL",
    "gn:name":"Okhalisirod",
    "gn:population":0,
    "gn:timezone":"Asia/Kolkata",
    "iso:country":"IN",
    "wof:name":"Okhalisirod",
    "wof:placetype":"locality"
},
  "geometry": {"coordinates":[79.75301999999998,29.74199],"type":"Point"}
}