{
  "type": "Feature",
  "properties": {
    "iso:country":"IN",
    "ks:ks_name":"Chikarpada Falia",
    "ks:ks_pop":661,
    "ks:ks_type":"HABITATION",
    "name:eng_x_preferred":[
        "Chikarpada Falia"
    ],
    "wof:name":"Chikarpada Falia",
    "wof:placetype":"locality",
    "wof:population":661
},
  "geometry": {"coordinates":[73.357472,20.826528],"type":"Point"}
}