{
  "type": "Feature",
  "properties": {
    "gn:admin1_code":"36",
    "gn:admin2_code":"199.0",
    "gn:asciiname":"Saria",
    "gn:country_code":"IN",
    "gn:dem":98,
    "gn:feature_class":"P",
    "gn:feature_code":"PPL",
    "gn:name":"Saria",
    "gn:population":0,
    "gn:timezone":"Asia/Kolkata",
    "iso:country":"IN",
    "name:ceb_x_preferred":[
        "Saria"
    ],
    "name:deu_x_preferred":[
        "Saria"
    ],
    "name:fra_x_preferred":[
        "Saria"
    ],
    "name:jpn_x_preferred":[
        "\u30b5\u30ea\u30a2"
    ],
    "name:pol_x_preferred":[
        "Saria"
    ],
    "name:swe_x_preferred":[
        "Saria"
    ],
    "name:vie_x_preferred":[
        "Saria"
    ],
    "wof:name":"Saria",
    "wof:placetype":"locality"
},
  "geometry": {"coordinates":[82.99091,25.0278],"type":"Point"}
}