{
  "type": "Feature",
  "properties": {
    "gn:admin1_code":"23.0",
    "gn:admin2_code":"38.0",
    "gn:asciiname":"Chak Kalan",
    "gn:country_code":"IN",
    "gn:dem":257,
    "gn:feature_class":"P",
    "gn:feature_code":"PPL",
    "gn:name":"Chak Kal\u0101n",
    "gn:population":0,
    "gn:timezone":"Asia/Kolkata",
    "iso:country":"IN",
    "wof:name":"Chak Kalan",
    "wof:placetype":"locality"
},
  "geometry": {"coordinates":[75.62151999999998,32.06407],"type":"Point"}
}