{
  "type": "Feature",
  "properties": {
    "iso:country":"IN",
    "ks:ks_name":"P Indra Nagar",
    "ks:ks_pop":341,
    "ks:ks_type":"HABITATION",
    "name:eng_x_preferred":[
        "P Indra Nagar"
    ],
    "wof:name":"P Indra Nagar",
    "wof:placetype":"locality",
    "wof:population":341
},
  "geometry": {"coordinates":[78.815085,11.560287],"type":"Point"}
}