{
  "type": "Feature",
  "properties": {
    "gn:admin1_code":"12.0",
    "gn:admin2_code":"003",
    "gn:asciiname":"Dumkhar",
    "gn:country_code":"IN",
    "gn:dem":2954,
    "gn:feature_class":"P",
    "gn:feature_code":"PPL",
    "gn:name":"Dumkhar",
    "gn:population":0,
    "gn:timezone":"Asia/Kolkata",
    "iso:country":"IN",
    "name:und_x_variant":[
        "Dumkbar",
        "Dumkhar"
    ],
    "wof:name":"Dumkhar",
    "wof:placetype":"locality"
},
  "geometry": {"coordinates":[76.762,34.38692],"type":"Point"}
}