{
  "type": "Feature",
  "properties": {
    "iso:country":"IN",
    "ks:ks_name":"Bangarh",
    "ks:ks_pop":788,
    "ks:ks_type":"HABITATION",
    "name:eng_x_preferred":[
        "Bangarh"
    ],
    "wof:name":"Bangarh",
    "wof:placetype":"locality",
    "wof:population":788
},
  "geometry": {"coordinates":[75.161846,26.952415],"type":"Point"}
}