{
  "type": "Feature",
  "properties": {
    "iso:country":"IN",
    "ks:ks_name":"Singhpur",
    "ks:ks_pop":343,
    "ks:ks_type":"VILLAGE",
    "name:eng_x_preferred":[
        "Singhpur"
    ],
    "wof:name":"Singhpur",
    "wof:placetype":"locality",
    "wof:population":343
},
  "geometry": {"coordinates":[84.43726100000001,24.437239],"type":"Point"}
}