{
  "type": "Feature",
  "properties": {
    "iso:country":"IN",
    "ks:ks_name":"Deori Amhai",
    "ks:ks_pop":310,
    "ks:ks_type":"HABITATION",
    "name:eng_x_preferred":[
        "Deori Amhai"
    ],
    "wof:name":"Deori Amhai",
    "wof:placetype":"locality",
    "wof:population":310
},
  "geometry": {"coordinates":[80.927779,23.330644],"type":"Point"}
}