{
  "type": "Feature",
  "properties": {
    "iso:country":"IN",
    "ks:ks_name":"Gaughatiya",
    "ks:ks_pop":200,
    "ks:ks_type":"HABITATION",
    "name:eng_x_preferred":[
        "Gaughatiya"
    ],
    "wof:name":"Gaughatiya",
    "wof:placetype":"locality",
    "wof:population":200
},
  "geometry": {"coordinates":[79.85266799999999,25.804217],"type":"Point"}
}