{
  "type": "Feature",
  "properties": {
    "iso:country":"IN",
    "ks:ks_name":"Patajoshipursasan",
    "ks:ks_pop":238,
    "ks:ks_type":"VILLAGE",
    "name:eng_x_preferred":[
        "Patajoshipursasan"
    ],
    "wof:name":"Patajoshipursasan",
    "wof:placetype":"locality",
    "wof:population":238
},
  "geometry": {"coordinates":[85.25982,19.829926],"type":"Point"}
}