{
  "type": "Feature",
  "properties": {
    "iso:country":"IN",
    "ks:ks_name":"Poonthotapalam",
    "ks:ks_pop":642,
    "ks:ks_type":"HABITATION",
    "name:eng_x_preferred":[
        "Poonthotapalam"
    ],
    "wof:name":"Poonthotapalam",
    "wof:placetype":"locality",
    "wof:population":642
},
  "geometry": {"coordinates":[77.742075,12.2186],"type":"Point"}
}