{
  "type": "Feature",
  "properties": {
    "iso:country":"IN",
    "ks:ks_name":"Dhokra",
    "ks:ks_pop":1003,
    "ks:ks_type":"HABITATION",
    "ks:ks_uagg_main":0,
    "name:eng_x_preferred":[
        "Dhokra"
    ],
    "wof:name":"Dhokra",
    "wof:placetype":"neighbourhood",
    "wof:population":1003
},
  "geometry": {"coordinates":[88.860242,22.803233],"type":"Point"}
}