{
  "type": "Feature",
  "properties": {
    "iso:country":"IN",
    "ks:ks_name":"Doddekoppalu",
    "ks:ks_pop":243,
    "ks:ks_type":"HABITATION",
    "name:eng_x_preferred":[
        "Doddekoppalu"
    ],
    "wof:name":"Doddekoppalu",
    "wof:placetype":"locality",
    "wof:population":243
},
  "geometry": {"coordinates":[76.33956499999999,12.183885],"type":"Point"}
}