{
  "type": "Feature",
  "properties": {
    "gn:admin1_code":"16",
    "gn:admin2_code":"503.0",
    "gn:asciiname":"Tatra",
    "gn:country_code":"IN",
    "gn:dem":356,
    "gn:feature_class":"P",
    "gn:feature_code":"PPL",
    "gn:name":"Tatra",
    "gn:population":0,
    "gn:timezone":"Asia/Kolkata",
    "iso:country":"IN",
    "name:deu_x_preferred":[
        "Tatra"
    ],
    "name:epo_x_preferred":[
        "Tatro"
    ],
    "name:fin_x_preferred":[
        "Tatra"
    ],
    "name:fra_x_preferred":[
        "Tatra"
    ],
    "name:heb_x_preferred":[
        "\u05d8\u05d8\u05e8\u05d4"
    ],
    "name:hun_x_preferred":[
        "T\u00e1tra"
    ],
    "name:ita_x_preferred":[
        "Tatra"
    ],
    "name:jpn_x_preferred":[
        "\u30bf\u30c8\u30e9"
    ],
    "name:kor_x_preferred":[
        "\ud0c0\ud2b8\ub77c"
    ],
    "name:nld_x_preferred":[
        "Tatra"
    ],
    "name:nor_x_preferred":[
        "Tatra"
    ],
    "name:pol_x_preferred":[
        "Tatra"
    ],
    "name:por_x_preferred":[
        "Tatra"
    ],
    "name:rus_x_preferred":[
        "\u0422\u0430\u0442\u0440\u044b"
    ],
    "name:slk_x_preferred":[
        "Tatra"
    ],
    "wof:name":"Tatra",
    "wof:placetype":"locality"
},
  "geometry": {"coordinates":[76.95248000000002,21.4529],"type":"Point"}
}