{
  "type": "Feature",
  "properties": {
    "iso:country":"IN",
    "ks:ks_name":"Madhya Para",
    "ks:ks_pop":696,
    "ks:ks_type":"HABITATION",
    "name:eng_x_preferred":[
        "Madhya Para"
    ],
    "wof:name":"Madhya Para",
    "wof:placetype":"locality",
    "wof:population":696
},
  "geometry": {"coordinates":[91.671424,23.656921],"type":"Point"}
}