{
  "type": "Feature",
  "properties": {
    "iso:country":"IN",
    "ks:ks_name":"Mugdi",
    "ks:ks_pop":811,
    "ks:ks_type":"VILLAGE",
    "name:eng_x_preferred":[
        "Mugdi"
    ],
    "wof:name":"Mugdi",
    "wof:placetype":"locality",
    "wof:population":811
},
  "geometry": {"coordinates":[87.526869,24.815467],"type":"Point"}
}