{
  "type": "Feature",
  "properties": {
    "iso:country":"IN",
    "ks:ks_name":"Damita",
    "ks:ks_pop":194,
    "ks:ks_type":"VILLAGE",
    "name:eng_x_preferred":[
        "Damita"
    ],
    "wof:name":"Damita",
    "wof:placetype":"locality",
    "wof:population":194
},
  "geometry": {"coordinates":[85.07933800000001,21.547762],"type":"Point"}
}