{
  "type": "Feature",
  "properties": {
    "iso:country":"IN",
    "ks:ks_name":"Budakumba",
    "ks:ks_pop":350,
    "ks:ks_type":"HABITATION",
    "name:eng_x_preferred":[
        "Budakumba"
    ],
    "wof:name":"Budakumba",
    "wof:placetype":"locality",
    "wof:population":350
},
  "geometry": {"coordinates":[83.803805,19.982488],"type":"Point"}
}