{
  "type": "Feature",
  "properties": {
    "iso:country":"IN",
    "ks:ks_name":"Kuruvikuppam",
    "ks:ks_pop":157,
    "ks:ks_type":"HABITATION",
    "name:eng_x_preferred":[
        "Kuruvikuppam"
    ],
    "wof:name":"Kuruvikuppam",
    "wof:placetype":"locality",
    "wof:population":157
},
  "geometry": {"coordinates":[79.46195299999999,13.2734],"type":"Point"}
}