{
  "type": "Feature",
  "properties": {
    "iso:country":"IN",
    "ks:ks_name":"Mura",
    "ks:ks_pop":200,
    "ks:ks_type":"HABITATION",
    "name:eng_x_preferred":[
        "Mura"
    ],
    "wof:name":"Mura",
    "wof:placetype":"locality",
    "wof:population":200
},
  "geometry": {"coordinates":[75.29416399999999,12.863744],"type":"Point"}
}