{
  "type": "Feature",
  "properties": {
    "iso:country":"IN",
    "ks:ks_name":"Chandu",
    "ks:ks_pop":1937,
    "ks:ks_type":"HABITATION",
    "name:eng_x_preferred":[
        "Chandu"
    ],
    "wof:name":"Chandu",
    "wof:placetype":"neighbourhood",
    "wof:population":1937
},
  "geometry": {"coordinates":[76.922499,28.471205],"type":"Point"}
}