{
  "type": "Feature",
  "properties": {
    "gn:admin1_code":"19.0",
    "gn:admin2_code":"568.0",
    "gn:asciiname":"Yalavata",
    "gn:country_code":"IN",
    "gn:dem":581,
    "gn:feature_class":"P",
    "gn:feature_code":"PPL",
    "gn:name":"Yalav\u0101ta",
    "gn:population":0,
    "gn:timezone":"Asia/Kolkata",
    "iso:country":"IN",
    "ks:ks_name":"Yalavata",
    "ks:ks_pop":415,
    "ks:ks_type":"HABITATION",
    "name:eng_x_preferred":[
        "Yalavata"
    ],
    "wof:name":"Yalavata",
    "wof:placetype":"locality",
    "wof:population":415
},
  "geometry": {"coordinates":[75.138373,14.441668],"type":"Point"}
}