{
  "type": "Feature",
  "properties": {
    "iso:country":"IN",
    "ks:ks_alt_nam":"T\u0101l Kundwa",
    "ks:ks_name":"Tal Kundwa",
    "ks:ks_type":"VILLAGE",
    "name:eng_x_preferred":[
        "Tal Kundwa"
    ],
    "name:eng_x_variant":[
        "T\u0101l Kundwa"
    ],
    "wof:name":"Tal Kundwa",
    "wof:placetype":"locality"
},
  "geometry": {"coordinates":[82.60431800000001,25.324131],"type":"Point"}
}