{
  "type": "Feature",
  "properties": {
    "gn:admin1_code":"11",
    "gn:admin2_code":"27.0",
    "gn:asciiname":"Rota",
    "gn:country_code":"IN",
    "gn:dem":817,
    "gn:feature_class":"P",
    "gn:feature_code":"PPL",
    "gn:name":"Rota",
    "gn:population":0,
    "gn:timezone":"Asia/Kolkata",
    "iso:country":"IN",
    "name:bre_x_preferred":[
        "Rota"
    ],
    "name:cat_x_preferred":[
        "Rota"
    ],
    "name:ceb_x_preferred":[
        "Rota"
    ],
    "name:ces_x_preferred":[
        "Rota"
    ],
    "name:chv_x_preferred":[
        "\u0420\u043e\u0442\u0430"
    ],
    "name:deu_x_preferred":[
        "Rota"
    ],
    "name:fas_x_preferred":[
        "\u0631\u0648\u062a\u0627"
    ],
    "name:fin_x_preferred":[
        "Rota"
    ],
    "name:fra_x_preferred":[
        "Rota"
    ],
    "name:glg_x_preferred":[
        "Rota"
    ],
    "name:ita_x_preferred":[
        "Rota"
    ],
    "name:lat_x_preferred":[
        "Rota"
    ],
    "name:lav_x_preferred":[
        "Rota"
    ],
    "name:mlg_x_preferred":[
        "Rota"
    ],
    "name:nld_x_preferred":[
        "Rota"
    ],
    "name:pol_x_preferred":[
        "Rota"
    ],
    "name:por_x_preferred":[
        "Rota"
    ],
    "name:rus_x_preferred":[
        "\u0420\u043e\u0442\u0430"
    ],
    "name:slk_x_preferred":[
        "Rota"
    ],
    "name:spa_x_preferred":[
        "Rota"
    ],
    "name:swe_x_preferred":[
        "Rota"
    ],
    "name:ukr_x_preferred":[
        "\u0420\u043e\u0442\u0430"
    ],
    "wof:name":"Rota",
    "wof:placetype":"locality"
},
  "geometry": {"coordinates":[76.80341999999997,31.90584],"type":"Point"}
}