{
  "type": "Feature",
  "properties": {
    "gn:admin1_code":"11",
    "gn:admin2_code":"23.0",
    "gn:asciiname":"Lun",
    "gn:country_code":"IN",
    "gn:dem":657,
    "gn:feature_class":"P",
    "gn:feature_code":"PPL",
    "gn:name":"L\u016bn",
    "gn:population":0,
    "gn:timezone":"Asia/Kolkata",
    "iso:country":"IN",
    "name:bre_x_preferred":[
        "Lun"
    ],
    "name:ceb_x_preferred":[
        "Lun"
    ],
    "name:deu_x_preferred":[
        "Lun"
    ],
    "name:hun_x_preferred":[
        "Lun"
    ],
    "name:rus_x_preferred":[
        "\u041b\u0443\u043d\u044c"
    ],
    "wof:name":"Lun",
    "wof:placetype":"locality"
},
  "geometry": {"coordinates":[76.38769000000001,32.45288],"type":"Point"}
}