{
  "type": "Feature",
  "properties": {
    "iso:country":"IN",
    "ks:ks_alt_nam":"RAM SOORAT PURWA",
    "ks:ks_name":"Ram Soorat Purwa",
    "ks:ks_pop":56,
    "ks:ks_type":"HABITATION",
    "name:eng_x_preferred":[
        "Ram Soorat Purwa"
    ],
    "wof:name":"Ram Soorat Purwa",
    "wof:placetype":"locality",
    "wof:population":56
},
  "geometry": {"coordinates":[81.641497,27.33605],"type":"Point"}
}