{
  "type": "Feature",
  "properties": {
    "gn:admin1_code":"36",
    "gn:admin2_code":"160.0",
    "gn:asciiname":"Akilpur",
    "gn:country_code":"IN",
    "gn:dem":144,
    "gn:feature_class":"P",
    "gn:feature_code":"PPL",
    "gn:name":"Akilpur",
    "gn:population":0,
    "gn:timezone":"Asia/Kolkata",
    "iso:country":"IN",
    "ks:ks_name":"Akilpur",
    "ks:ks_pop":806,
    "ks:ks_type":"VILLAGE",
    "ks:ks_uagg_main":0,
    "name:eng_x_preferred":[
        "Akilpur"
    ],
    "wof:name":"Akilpur",
    "wof:placetype":"neighbourhood",
    "wof:population":806
},
  "geometry": {"coordinates":[79.96388399999999,26.964764],"type":"Point"}
}