{
  "type": "Feature",
  "properties": {
    "gn:admin1_code":"36",
    "gn:admin2_code":"172.0",
    "gn:asciiname":"Madaripur Kalan",
    "gn:country_code":"IN",
    "gn:dem":116,
    "gn:feature_class":"P",
    "gn:feature_code":"PPL",
    "gn:name":"Mad\u0101r\u012bpur Kal\u0101n",
    "gn:population":0,
    "gn:timezone":"Asia/Kolkata",
    "iso:country":"IN",
    "ks:ks_name":"Madaripur Kalan",
    "ks:ks_pop":1102,
    "ks:ks_type":"VILLAGE",
    "name:eng_x_preferred":[
        "Madaripur Kalan"
    ],
    "wof:name":"Madaripur Kalan",
    "wof:placetype":"locality",
    "wof:population":1102
},
  "geometry": {"coordinates":[80.856071,25.896653],"type":"Point"}
}