{
  "type": "Feature",
  "properties": {
    "iso:country":"IN",
    "ks:ks_name":"Vijaywadi",
    "ks:ks_pop":88,
    "ks:ks_type":"HABITATION",
    "name:eng_x_preferred":[
        "Vijaywadi"
    ],
    "wof:name":"Vijaywadi",
    "wof:placetype":"locality",
    "wof:population":88
},
  "geometry": {"coordinates":[73.81621199999999,16.268802],"type":"Point"}
}