{
  "type": "Feature",
  "properties": {
    "gn:admin1_code":"34.0",
    "gn:admin2_code":"236.0",
    "gn:asciiname":"Bagdaha",
    "gn:country_code":"IN",
    "gn:dem":118,
    "gn:feature_class":"P",
    "gn:feature_code":"PPL",
    "gn:name":"Bagdaha",
    "gn:population":0,
    "gn:timezone":"Asia/Kolkata",
    "iso:country":"IN",
    "ks:ks_name":"Bagdaha",
    "ks:ks_pop":1276,
    "ks:ks_type":"VILLAGE",
    "ks:ks_uagg_main":0,
    "name:eng_x_preferred":[
        "Bagdaha"
    ],
    "wof:name":"Bagdaha",
    "wof:placetype":"neighbourhood",
    "wof:population":1276
},
  "geometry": {"coordinates":[84.946023,24.727957],"type":"Point"}
}