{
  "type": "Feature",
  "properties": {
    "gn:admin1_code":"39",
    "gn:admin2_code":"58.0",
    "gn:asciiname":"Tulanga",
    "gn:country_code":"IN",
    "gn:dem":1482,
    "gn:feature_class":"P",
    "gn:feature_code":"PPL",
    "gn:name":"Tulanga",
    "gn:population":0,
    "gn:timezone":"Asia/Kolkata",
    "iso:country":"IN",
    "wof:name":"Tulanga",
    "wof:placetype":"locality"
},
  "geometry": {"coordinates":[79.13646999999997,30.50537000000001],"type":"Point"}
}