{
  "type": "Feature",
  "properties": {
    "iso:country":"IN",
    "ks:ks_name":"Barashyamnagar",
    "ks:ks_pop":205,
    "ks:ks_type":"HABITATION",
    "name:eng_x_preferred":[
        "Barashyamnagar"
    ],
    "wof:name":"Barashyamnagar",
    "wof:placetype":"locality",
    "wof:population":205
},
  "geometry": {"coordinates":[86.988716,22.546865],"type":"Point"}
}