{
  "type": "Feature",
  "properties": {
    "gn:admin1_code":"11",
    "gn:admin2_code":"24.0",
    "gn:asciiname":"Bari",
    "gn:country_code":"IN",
    "gn:dem":726,
    "gn:feature_class":"P",
    "gn:feature_code":"PPL",
    "gn:name":"B\u0101ri",
    "gn:population":0,
    "gn:timezone":"Asia/Kolkata",
    "iso:country":"IN",
    "wof:name":"Bari",
    "wof:placetype":"locality"
},
  "geometry": {"coordinates":[76.3263,32.01042],"type":"Point"}
}