{
  "type": "Feature",
  "properties": {
    "iso:country":"IN",
    "ks:ks_name":"Mundajhola",
    "ks:ks_pop":263,
    "ks:ks_type":"VILLAGE",
    "name:eng_x_preferred":[
        "Mundajhola"
    ],
    "wof:name":"Mundajhola",
    "wof:placetype":"locality",
    "wof:population":263
},
  "geometry": {"coordinates":[82.983653,19.056121],"type":"Point"}
}