{
  "type": "Feature",
  "properties": {
    "iso:country":"IN",
    "ks:ks_alt_nam":"Kadm\u0101",
    "ks:ks_name":"Kadma",
    "ks:ks_pop":1144,
    "ks:ks_type":"VILLAGE",
    "name:eng_x_preferred":[
        "Kadma"
    ],
    "name:eng_x_variant":[
        "Kadm\u0101"
    ],
    "wof:name":"Kadma",
    "wof:placetype":"neighbourhood",
    "wof:population":1144
},
  "geometry": {"coordinates":[85.30558000000001,23.441236],"type":"Point"}
}