{
  "type": "Feature",
  "properties": {
    "gn:admin1_code":"39",
    "gn:admin2_code":"60.0",
    "gn:asciiname":"Khaldhar",
    "gn:country_code":"IN",
    "gn:dem":896,
    "gn:feature_class":"P",
    "gn:feature_code":"PPL",
    "gn:name":"Khaldh\u0101r",
    "gn:population":0,
    "gn:timezone":"Asia/Kolkata",
    "iso:country":"IN",
    "ks:ks_name":"Khaldhar",
    "ks:ks_pop":83,
    "ks:ks_type":"VILLAGE",
    "name:eng_x_preferred":[
        "Khaldhar"
    ],
    "wof:name":"Khaldhar",
    "wof:placetype":"locality",
    "wof:population":83
},
  "geometry": {"coordinates":[78.243467,30.209829],"type":"Point"}
}