{
  "type": "Feature",
  "properties": {
    "iso:country":"IN",
    "ks:ks_name":"Sorekaipura",
    "ks:ks_pop":24,
    "ks:ks_type":"VILLAGE",
    "name:eng_x_preferred":[
        "Sorekaipura"
    ],
    "wof:name":"Sorekaipura",
    "wof:placetype":"locality",
    "wof:population":24
},
  "geometry": {"coordinates":[76.418684,12.956182],"type":"Point"}
}