{
  "type": "Feature",
  "properties": {
    "iso:country":"IN",
    "ks:ks_name":"Bhitarkormari",
    "ks:ks_pop":892,
    "ks:ks_type":"VILLAGE",
    "name:eng_x_preferred":[
        "Bhitarkormari"
    ],
    "wof:name":"Bhitarkormari",
    "wof:placetype":"locality",
    "wof:population":892
},
  "geometry": {"coordinates":[82.53448899999999,19.718255],"type":"Point"}
}