{
  "type": "Feature",
  "properties": {
    "gn:admin1_code":"36",
    "gn:admin2_code":"199.0",
    "gn:asciiname":"Rehia",
    "gn:country_code":"IN",
    "gn:dem":88,
    "gn:feature_class":"P",
    "gn:feature_code":"PPL",
    "gn:name":"Rehia",
    "gn:population":0,
    "gn:timezone":"Asia/Kolkata",
    "iso:country":"IN",
    "name:cat_x_preferred":[
        "Rehia"
    ],
    "name:nld_x_preferred":[
        "Rehia"
    ],
    "name:por_x_preferred":[
        "Rehia"
    ],
    "name:spa_x_preferred":[
        "Rehia"
    ],
    "name:vie_x_preferred":[
        "Rehia"
    ],
    "wof:name":"Rehia",
    "wof:placetype":"locality"
},
  "geometry": {"coordinates":[82.95820999999999,25.10534],"type":"Point"}
}