{
  "type": "Feature",
  "properties": {
    "iso:country":"IN",
    "ks:ks_name":"Adivasi Colony",
    "ks:ks_pop":401,
    "ks:ks_type":"HABITATION",
    "name:eng_x_preferred":[
        "Adivasi Colony"
    ],
    "wof:name":"Adivasi Colony",
    "wof:placetype":"locality",
    "wof:population":401
},
  "geometry": {"coordinates":[82.32251100000001,19.732426],"type":"Point"}
}