{
  "type": "Feature",
  "properties": {
    "iso:country":"IN",
    "ks:ks_name":"Uduvememooli",
    "ks:ks_pop":35,
    "ks:ks_type":"HABITATION",
    "name:eng_x_preferred":[
        "Uduvememooli"
    ],
    "wof:name":"Uduvememooli",
    "wof:placetype":"locality",
    "wof:population":35
},
  "geometry": {"coordinates":[75.623499,13.111838],"type":"Point"}
}