{
  "type": "Feature",
  "properties": {
    "iso:country":"IN",
    "ks:ks_name":"Dungapar",
    "ks:ks_pop":1156,
    "ks:ks_type":"HABITATION",
    "name:eng_x_preferred":[
        "Dungapar"
    ],
    "wof:name":"Dungapar",
    "wof:placetype":"locality",
    "wof:population":1156
},
  "geometry": {"coordinates":[92.20144500000001,26.361815],"type":"Point"}
}