{
  "type": "Feature",
  "properties": {
    "gn:admin1_code":"36.0",
    "gn:admin2_code":"134.0",
    "gn:asciiname":"Alampur",
    "gn:country_code":"IN",
    "gn:dem":245,
    "gn:feature_class":"P",
    "gn:feature_code":"PPL",
    "gn:name":"\u0100lampur",
    "gn:population":0,
    "gn:timezone":"Asia/Kolkata",
    "iso:country":"IN",
    "ks:ks_name":"Alampur",
    "ks:ks_type":"VILLAGE",
    "name:ceb_x_preferred":[
        "Alampur"
    ],
    "name:eng_x_preferred":[
        "Alampur"
    ],
    "name:hin_x_preferred":[
        "\u0906\u0932\u092e\u092a\u0941\u0930"
    ],
    "name:swe_x_preferred":[
        "Alampur"
    ],
    "wof:name":"Alampur",
    "wof:placetype":"locality"
},
  "geometry": {"coordinates":[78.19401999999999,29.441622],"type":"Point"}
}