{
  "type": "Feature",
  "properties": {
    "iso:country":"IN",
    "ks:ks_alt_nam":"thattavanipalem",
    "ks:ks_name":"Thattavanipalem",
    "ks:ks_pop":139,
    "ks:ks_type":"HABITATION",
    "name:eng_x_preferred":[
        "Thattavanipalem"
    ],
    "wof:name":"Thattavanipalem",
    "wof:placetype":"locality",
    "wof:population":139
},
  "geometry": {"coordinates":[82.998496,17.564902],"type":"Point"}
}