{
  "type": "Feature",
  "properties": {
    "gn:admin1_code":"35",
    "gn:admin2_code":"421.0",
    "gn:asciiname":"Simiriya Tanka",
    "gn:country_code":"IN",
    "gn:dem":278,
    "gn:feature_class":"P",
    "gn:feature_code":"PPL",
    "gn:name":"Simiriya T\u0101nka",
    "gn:population":0,
    "gn:timezone":"Asia/Kolkata",
    "iso:country":"IN",
    "wof:name":"Simiriya Tanka",
    "wof:placetype":"locality"
},
  "geometry": {"coordinates":[77.98246999999998,26.02147],"type":"Point"}
}