{
  "type": "Feature",
  "properties": {
    "gn:admin1_code":"11.0",
    "gn:admin2_code":"33.0",
    "gn:asciiname":"Yalionke",
    "gn:country_code":"IN",
    "gn:dem":2709,
    "gn:feature_class":"P",
    "gn:feature_code":"PPL",
    "gn:name":"Yalionke",
    "gn:population":0,
    "gn:timezone":"Asia/Kolkata",
    "iso:country":"IN",
    "wof:name":"Yalionke",
    "wof:placetype":"locality"
},
  "geometry": {"coordinates":[78.09275,31.26593],"type":"Point"}
}