{
  "type": "Feature",
  "properties": {
    "gn:admin1_code":"38.0",
    "gn:admin2_code":"362",
    "gn:asciiname":"Hariharpur",
    "gn:country_code":"IN",
    "gn:dem":265,
    "gn:feature_class":"P",
    "gn:feature_code":"PPL",
    "gn:name":"Hariharpur",
    "gn:population":0,
    "gn:timezone":"Asia/Kolkata",
    "iso:country":"IN",
    "name:fra_x_preferred":[
        "Hariharpur"
    ],
    "name:new_x_preferred":[
        "\u0939\u0930\u093f\u0939\u0930\u092a\u0941\u0930 \u0917\u093e\u0935\u093f\u0938"
    ],
    "name:pol_x_preferred":[
        "Hariharpur"
    ],
    "name:und_x_variant":[
        "Hariharpur-Dumka",
        "Hariharpur"
    ],
    "wof:name":"Hariharpur",
    "wof:placetype":"locality"
},
  "geometry": {"coordinates":[86.91707,24.42329],"type":"Point"}
}