{
  "type": "Feature",
  "properties": {
    "iso:country":"IN",
    "ks:ks_name":"Shivaramapura Yelagondanahalli",
    "ks:ks_pop":225,
    "ks:ks_type":"HABITATION",
    "name:eng_x_preferred":[
        "Shivaramapura Yelagondanahalli"
    ],
    "wof:name":"Shivaramapura Yelagondanahalli",
    "wof:placetype":"locality",
    "wof:population":225
},
  "geometry": {"coordinates":[76.06950399999999,13.076928],"type":"Point"}
}