{
  "type": "Feature",
  "properties": {
    "iso:country":"IN",
    "name:eng_x_preferred":[
        "Dayal Nagar"
    ],
    "qs:gn_adm0_cc":"IN",
    "qs:gn_local":1253102,
    "qs:gn_nam_loc":"Visakhapatnam, Visakhapatnam, Andhra Pradesh, IN",
    "qs:gn_namadm1":"02",
    "qs:local_max":739,
    "qs:local_sum":1004,
    "qs:localhoods":4,
    "qs:name":"Dayal Nagar",
    "qs:name_adm0":"India",
    "qs:name_adm1":"Andhra Pradesh",
    "qs:name_adm2":"Visakhapatnam",
    "qs:name_local":"Visakhapatnam",
    "qs:photo_max":47,
    "qs:photo_sum":152,
    "qs:placetype":"Suburb",
    "qs:quad_count":12,
    "qs:woe_adm0":23424848,
    "qs:woe_adm1":2345740,
    "qs:woe_adm2":12586346,
    "qs:woe_lau":0,
    "qs:woe_local":2295418,
    "qs:woe_ver":"7.10.0",
    "wd:elevation":19.0,
    "wd:wordcount":389,
    "wof:lang":[
        "eng"
    ],
    "wof:name":"Dayal Nagar",
    "wof:placetype":"neighbourhood"
},
  "geometry": {"coordinates":[83.35211099999999,17.754399],"type":"Point"}
}