{
  "type": "Feature",
  "properties": {
    "iso:country":"IN",
    "ks:ks_alt_nam":"hansrampurwa",
    "ks:ks_name":"Hansrampurwa",
    "ks:ks_pop":320,
    "ks:ks_type":"HABITATION",
    "name:eng_x_preferred":[
        "Hansrampurwa"
    ],
    "wof:name":"Hansrampurwa",
    "wof:placetype":"locality",
    "wof:population":320
},
  "geometry": {"coordinates":[81.885133,27.366317],"type":"Point"}
}