{
  "type": "Feature",
  "properties": {
    "gn:admin1_code":"2",
    "gn:admin2_code":"544.0",
    "gn:asciiname":"Santaripadu",
    "gn:country_code":"IN",
    "gn:dem":951,
    "gn:feature_class":"P",
    "gn:feature_code":"PPL",
    "gn:name":"Santarip\u0101du",
    "gn:population":0,
    "gn:timezone":"Asia/Kolkata",
    "iso:country":"IN",
    "wof:name":"Santaripadu",
    "wof:placetype":"locality"
},
  "geometry": {"coordinates":[82.91996,18.19742],"type":"Point"}
}