{
  "type": "Feature",
  "properties": {
    "gn:admin1_code":"21.0",
    "gn:admin2_code":"399.0",
    "gn:asciiname":"Potakallu",
    "gn:country_code":"IN",
    "gn:dem":158,
    "gn:feature_class":"P",
    "gn:feature_code":"PPL",
    "gn:name":"Potakallu",
    "gn:population":0,
    "gn:timezone":"Asia/Kolkata",
    "iso:country":"IN",
    "wof:name":"Potakallu",
    "wof:placetype":"locality"
},
  "geometry": {"coordinates":[81.79006,18.11397],"type":"Point"}
}