{
  "type": "Feature",
  "properties": {
    "gn:admin1_code":"36.0",
    "gn:admin2_code":"148",
    "gn:asciiname":"Chatrupur",
    "gn:country_code":"IN",
    "gn:dem":154,
    "gn:feature_class":"P",
    "gn:feature_code":"PPL",
    "gn:name":"Chatrupur",
    "gn:population":0,
    "gn:timezone":"Asia/Kolkata",
    "iso:country":"IN",
    "name:und_x_variant":[
        "Chatur\u012bpur"
    ],
    "wof:name":"Chatrupur",
    "wof:placetype":"locality"
},
  "geometry": {"coordinates":[79.21143000000002,26.99046],"type":"Point"}
}