{
  "type": "Feature",
  "properties": {
    "iso:country":"IN",
    "ks:ks_name":"Tasada",
    "ks:ks_pop":263,
    "ks:ks_type":"VILLAGE",
    "name:eng_x_preferred":[
        "Tasada"
    ],
    "wof:name":"Tasada",
    "wof:placetype":"locality",
    "wof:population":263
},
  "geometry": {"coordinates":[85.15285900000001,21.621365],"type":"Point"}
}