{
  "type": "Feature",
  "properties": {
    "iso:country":"IN",
    "ks:ks_name":"Miyati",
    "ks:ks_pop":1774,
    "ks:ks_type":"VILLAGE",
    "name:eng_x_preferred":[
        "Miyati"
    ],
    "wof:name":"Miyati",
    "wof:placetype":"locality",
    "wof:population":1774
},
  "geometry": {"coordinates":[74.57334,23.063425],"type":"Point"}
}