{
  "type": "Feature",
  "properties": {
    "iso:country":"IN",
    "ks:ks_name":"No.3 Balijuri",
    "ks:ks_pop":493,
    "ks:ks_type":"VILLAGE",
    "name:eng_x_preferred":[
        "No.3 Balijuri"
    ],
    "wof:name":"No.3 Balijuri",
    "wof:placetype":"locality",
    "wof:population":493
},
  "geometry": {"coordinates":[92.97517999999999,26.869626],"type":"Point"}
}