{
  "type": "Feature",
  "properties": {
    "gn:admin1_code":"37",
    "gn:admin2_code":"411.0",
    "gn:asciiname":"Sagarpali",
    "gn:country_code":"IN",
    "gn:dem":252,
    "gn:feature_class":"P",
    "gn:feature_code":"PPL",
    "gn:name":"S\u0101garp\u0101li",
    "gn:population":0,
    "gn:timezone":"Asia/Kolkata",
    "iso:country":"IN",
    "ks:ks_alt_nam":"S\u0101garp\u0101li",
    "ks:ks_name":"Sagarpali",
    "ks:ks_type":"VILLAGE",
    "name:eng_x_preferred":[
        "Sagarpali"
    ],
    "name:eng_x_variant":[
        "S\u0101garp\u0101li"
    ],
    "wof:name":"Sagarpali",
    "wof:placetype":"locality"
},
  "geometry": {"coordinates":[83.16596199999999,21.304369],"type":"Point"}
}