{
  "type": "Feature",
  "properties": {
    "iso:country":"IN",
    "ks:ks_name":"Hill Block",
    "ks:ks_pop":19,
    "ks:ks_type":"HABITATION",
    "name:eng_x_preferred":[
        "Hill Block"
    ],
    "wof:name":"Hill Block",
    "wof:placetype":"locality",
    "wof:population":19
},
  "geometry": {"coordinates":[86.078626,22.048151],"type":"Point"}
}