{
  "type": "Feature",
  "properties": {
    "iso:country":"IN",
    "ks:ks_name":"Mahal",
    "ks:ks_pop":4272,
    "ks:ks_type":"VILLAGE",
    "ks:ks_uagg_main":0,
    "name:eng_x_preferred":[
        "Mahal"
    ],
    "wof:name":"Mahal",
    "wof:placetype":"neighbourhood",
    "wof:population":4272
},
  "geometry": {"coordinates":[87.275262,23.711962],"type":"Point"}
}