{
  "type": "Feature",
  "properties": {
    "iso:country":"IN",
    "ks:ks_name":"Embili",
    "ks:ks_pop":193,
    "ks:ks_type":"HABITATION",
    "name:eng_x_preferred":[
        "Embili"
    ],
    "wof:name":"Embili",
    "wof:placetype":"locality",
    "wof:population":193
},
  "geometry": {"coordinates":[76.475408,14.598631],"type":"Point"}
}