{
  "type": "Feature",
  "properties": {
    "gn:admin1_code":"36",
    "gn:admin2_code":"200.0",
    "gn:asciiname":"Harra",
    "gn:country_code":"IN",
    "gn:dem":170,
    "gn:feature_class":"P",
    "gn:feature_code":"PPL",
    "gn:name":"Harra",
    "gn:population":0,
    "gn:timezone":"Asia/Kolkata",
    "iso:country":"IN",
    "ks:ks_name":"Harra",
    "ks:ks_pop":1006,
    "ks:ks_type":"VILLAGE",
    "name:bak_x_preferred":[
        "\u0425\u0430\u0440\u0440\u0430"
    ],
    "name:ceb_x_preferred":[
        "Harra"
    ],
    "name:deu_x_preferred":[
        "Harra"
    ],
    "name:eng_x_preferred":[
        "Harra"
    ],
    "name:epo_x_preferred":[
        "Harra"
    ],
    "name:eus_x_preferred":[
        "Harra"
    ],
    "name:fas_x_preferred":[
        "\u0647\u0627\u0631\u0627"
    ],
    "name:fra_x_preferred":[
        "Harra"
    ],
    "name:hun_x_preferred":[
        "Harra"
    ],
    "name:ita_x_preferred":[
        "Harra"
    ],
    "name:kaz_x_preferred":[
        "\u0425\u0430\u0440\u0440\u0430"
    ],
    "name:kir_x_preferred":[
        "\u0425\u0430\u0440\u0440\u0430"
    ],
    "name:mkd_x_preferred":[
        "\u0425\u0430\u0440\u0430"
    ],
    "name:msa_x_preferred":[
        "Harra"
    ],
    "name:nld_x_preferred":[
        "Harra"
    ],
    "name:pol_x_preferred":[
        "Harra"
    ],
    "name:por_x_preferred":[
        "Harra"
    ],
    "name:ron_x_preferred":[
        "Harra"
    ],
    "name:rus_x_preferred":[
        "\u0425\u0430\u0440\u0440\u0430"
    ],
    "name:spa_x_preferred":[
        "Harra"
    ],
    "name:srp_x_preferred":[
        "\u0425\u0430\u0440\u0430"
    ],
    "name:ukr_x_preferred":[
        "\u0413\u0430\u0440\u0440\u0430"
    ],
    "name:uzb_x_preferred":[
        "Harra"
    ],
    "name:vie_x_preferred":[
        "Harra"
    ],
    "name:vol_x_preferred":[
        "Harra"
    ],
    "name:war_x_preferred":[
        "Harra"
    ],
    "name:zho_x_preferred":[
        "\u54c8\u62c9"
    ],
    "wof:name":"Harra",
    "wof:placetype":"locality",
    "wof:population":1006
},
  "geometry": {"coordinates":[83.223883,24.449727],"type":"Point"}
}