{
  "type": "Feature",
  "properties": {
    "gn:admin1_code":"2",
    "gn:admin2_code":"544.0",
    "gn:asciiname":"Mittalapadu",
    "gn:country_code":"IN",
    "gn:dem":448,
    "gn:feature_class":"P",
    "gn:feature_code":"PPL",
    "gn:name":"Mittalap\u0101du",
    "gn:population":0,
    "gn:timezone":"Asia/Kolkata",
    "iso:country":"IN",
    "wof:name":"Mittalapadu",
    "wof:placetype":"locality"
},
  "geometry": {"coordinates":[82.68998000000001,17.96633],"type":"Point"}
}