{
  "type": "Feature",
  "properties": {
    "iso:country":"IN",
    "ks:ks_alt_nam":"KAMLATILLA",
    "ks:ks_name":"Kamlatilla",
    "ks:ks_pop":1206,
    "ks:ks_type":"HABITATION",
    "name:eng_x_preferred":[
        "Kamlatilla"
    ],
    "wof:name":"Kamlatilla",
    "wof:placetype":"locality",
    "wof:population":1206
},
  "geometry": {"coordinates":[92.46692400000001,24.553494],"type":"Point"}
}