{
  "type": "Feature",
  "properties": {
    "iso:country":"IN",
    "ks:ks_name":"Chhotaki Belahari",
    "ks:ks_pop":538,
    "ks:ks_type":"HABITATION",
    "name:eng_x_preferred":[
        "Chhotaki Belahari"
    ],
    "wof:name":"Chhotaki Belahari",
    "wof:placetype":"locality",
    "wof:population":538
},
  "geometry": {"coordinates":[83.16718299999999,27.412587],"type":"Point"}
}