{
  "type": "Feature",
  "properties": {
    "gn:admin1_code":"36",
    "gn:admin2_code":"134.0",
    "gn:asciiname":"Birampur",
    "gn:country_code":"IN",
    "gn:dem":229,
    "gn:feature_class":"P",
    "gn:feature_code":"PPL",
    "gn:name":"Bir\u0101mpur",
    "gn:population":0,
    "gn:timezone":"Asia/Kolkata",
    "iso:country":"IN",
    "ks:ks_alt_nam":"Bir\u0101mpur",
    "ks:ks_name":"Birampur",
    "ks:ks_type":"VILLAGE",
    "name:eng_x_preferred":[
        "Birampur"
    ],
    "name:eng_x_variant":[
        "Bir\u0101mpur"
    ],
    "wof:name":"Birampur",
    "wof:placetype":"locality"
},
  "geometry": {"coordinates":[78.573669,29.213263],"type":"Point"}
}