{
  "type": "Feature",
  "properties": {
    "iso:country":"IN",
    "ks:ks_name":"A Belaguli",
    "ks:ks_pop":931,
    "ks:ks_type":"HABITATION",
    "name:eng_x_preferred":[
        "A Belaguli"
    ],
    "wof:name":"A Belaguli",
    "wof:placetype":"locality",
    "wof:population":931
},
  "geometry": {"coordinates":[76.48091599999999,13.05548],"type":"Point"}
}