{
  "type": "Feature",
  "properties": {
    "gn:admin1_code":"23",
    "gn:admin2_code":"39.0",
    "gn:asciiname":"Mahli",
    "gn:country_code":"IN",
    "gn:dem":247,
    "gn:feature_class":"P",
    "gn:feature_code":"PPL",
    "gn:name":"Mahli",
    "gn:population":0,
    "gn:timezone":"Asia/Kolkata",
    "iso:country":"IN",
    "name:ceb_x_preferred":[
        "Mahli"
    ],
    "name:swe_x_preferred":[
        "Mahli"
    ],
    "wof:name":"Mahli",
    "wof:placetype":"locality"
},
  "geometry": {"coordinates":[75.81353,31.21167],"type":"Point"}
}