{
  "type": "Feature",
  "properties": {
    "iso:country":"IN",
    "ks:ks_name":"Thathacheruvu",
    "ks:ks_pop":230,
    "ks:ks_type":"HABITATION",
    "name:eng_x_preferred":[
        "Thathacheruvu"
    ],
    "wof:name":"Thathacheruvu",
    "wof:placetype":"locality",
    "wof:population":230
},
  "geometry": {"coordinates":[82.110131,16.5369],"type":"Point"}
}