{
  "type": "Feature",
  "properties": {
    "iso:country":"IN",
    "ks:ks_alt_nam":"dhamalwadi",
    "ks:ks_name":"Dhamalwadi",
    "ks:ks_pop":42,
    "ks:ks_type":"HABITATION",
    "name:eng_x_preferred":[
        "Dhamalwadi"
    ],
    "wof:name":"Dhamalwadi",
    "wof:placetype":"locality",
    "wof:population":42
},
  "geometry": {"coordinates":[74.05583300000001,15.691889],"type":"Point"}
}