{
  "type": "Feature",
  "properties": {
    "iso:country":"IN",
    "ks:ks_name":"Jaipattan Purwa",
    "ks:ks_pop":78,
    "ks:ks_type":"HABITATION",
    "ks:ks_uagg_main":0,
    "name:eng_x_preferred":[
        "Jaipattan Purwa"
    ],
    "wof:name":"Jaipattan Purwa",
    "wof:placetype":"neighbourhood",
    "wof:population":78
},
  "geometry": {"coordinates":[81.623893,27.866089],"type":"Point"}
}