{
  "type": "Feature",
  "properties": {
    "gn:admin1_code":"35",
    "gn:admin2_code":"422.0",
    "gn:asciiname":"Siyari",
    "gn:country_code":"IN",
    "gn:dem":221,
    "gn:feature_class":"P",
    "gn:feature_code":"PPL",
    "gn:name":"Siy\u0101ri",
    "gn:population":0,
    "gn:timezone":"Asia/Kolkata",
    "iso:country":"IN",
    "ks:ks_name":"Syari",
    "ks:ks_pop":442,
    "ks:ks_type":"VILLAGE",
    "name:eng_x_preferred":[
        "Syari"
    ],
    "name:eng_x_variant":[
        "Siyari"
    ],
    "wof:name":"Syari",
    "wof:placetype":"locality",
    "wof:population":442
},
  "geometry": {"coordinates":[78.537712,25.678168],"type":"Point"}
}