{
  "type": "Feature",
  "properties": {
    "iso:country":"IN",
    "ks:ks_alt_nam":"SOLGE WADI",
    "ks:ks_name":"Solge Wadi",
    "ks:ks_pop":78,
    "ks:ks_type":"HABITATION",
    "name:eng_x_preferred":[
        "Solge Wadi"
    ],
    "wof:name":"Solge Wadi",
    "wof:placetype":"locality",
    "wof:population":78
},
  "geometry": {"coordinates":[75.183177,17.241197],"type":"Point"}
}