{
  "type": "Feature",
  "properties": {
    "iso:country":"IN",
    "ks:ks_name":"Chhota Hundru",
    "ks:ks_pop":61,
    "ks:ks_type":"HABITATION",
    "name:eng_x_preferred":[
        "Chhota Hundru"
    ],
    "wof:name":"Chhota Hundru",
    "wof:placetype":"locality",
    "wof:population":61
},
  "geometry": {"coordinates":[85.70351700000001,23.427534],"type":"Point"}
}