{
  "type": "Feature",
  "properties": {
    "iso:country":"IN",
    "ks:ks_name":"Ghilaguri Pt V",
    "ks:ks_pop":927,
    "ks:ks_type":"HABITATION",
    "name:eng_x_preferred":[
        "Ghilaguri Pt V"
    ],
    "wof:name":"Ghilaguri Pt V",
    "wof:placetype":"locality",
    "wof:population":927
},
  "geometry": {"coordinates":[90.579104,26.329075],"type":"Point"}
}