{
  "type": "Feature",
  "properties": {
    "iso:country":"IN",
    "ks:ks_name":"Chimtahi Urf Murlidum",
    "ks:ks_pop":0,
    "ks:ks_type":"VILLAGE",
    "name:eng_x_preferred":[
        "Chimtahi Urf Murlidum"
    ],
    "wof:name":"Chimtahi Urf Murlidum",
    "wof:placetype":"locality",
    "wof:population":0
},
  "geometry": {"coordinates":[87.34282399999999,24.383992],"type":"Point"}
}