{
  "type": "Feature",
  "properties": {
    "gn:admin1_code":"36.0",
    "gn:admin2_code":"151.0",
    "gn:asciiname":"Pakaria Taluka Deoria",
    "gn:country_code":"IN",
    "gn:dem":176,
    "gn:feature_class":"P",
    "gn:feature_code":"PPL",
    "gn:name":"Pakaria T\u0101luka Deoria",
    "gn:population":0,
    "gn:timezone":"Asia/Kolkata",
    "iso:country":"IN",
    "wof:name":"Pakaria Taluka Deoria",
    "wof:placetype":"locality"
},
  "geometry": {"coordinates":[79.92591999999998,28.37694],"type":"Point"}
}