{
  "type": "Feature",
  "properties": {
    "iso:country":"IN",
    "ks:ks_name":"Padaw",
    "ks:ks_pop":444,
    "ks:ks_type":"HABITATION",
    "name:eng_x_preferred":[
        "Padaw"
    ],
    "wof:name":"Padaw",
    "wof:placetype":"locality",
    "wof:population":444
},
  "geometry": {"coordinates":[79.098433,27.479589],"type":"Point"}
}