{
  "type": "Feature",
  "properties": {
    "iso:country":"IN",
    "ks:ks_name":"Khauti",
    "ks:ks_pop":9,
    "ks:ks_type":"HABITATION",
    "name:eng_x_preferred":[
        "Khauti"
    ],
    "wof:name":"Khauti",
    "wof:placetype":"locality",
    "wof:population":9
},
  "geometry": {"coordinates":[82.82180099999999,27.34624],"type":"Point"}
}