{
  "type": "Feature",
  "properties": {
    "gn:admin1_code":"11.0",
    "gn:admin2_code":"33.0",
    "gn:asciiname":"Shiran",
    "gn:country_code":"IN",
    "gn:dem":2143,
    "gn:feature_class":"P",
    "gn:feature_code":"PPL",
    "gn:name":"Shir\u0101n",
    "gn:population":0,
    "gn:timezone":"Asia/Kolkata",
    "iso:country":"IN",
    "wof:name":"Shiran",
    "wof:placetype":"locality"
},
  "geometry": {"coordinates":[77.74008000000001,31.53602],"type":"Point"}
}