{
  "type": "Feature",
  "properties": {
    "gn:admin1_code":"38",
    "gn:admin2_code":"346.0",
    "gn:asciiname":"Gareriyadihtola",
    "gn:country_code":"IN",
    "gn:dem":189,
    "gn:feature_class":"P",
    "gn:feature_code":"PPL",
    "gn:name":"Gareriy\u0101d\u012bhtola",
    "gn:population":0,
    "gn:timezone":"Asia/Kolkata",
    "iso:country":"IN",
    "wof:name":"Gareriyadihtola",
    "wof:placetype":"neighbourhood"
},
  "geometry": {"coordinates":[83.79181,24.2899],"type":"Point"}
}