{
  "type": "Feature",
  "properties": {
    "iso:country":"IN",
    "ks:ks_name":"Bhikanpur Dih",
    "ks:ks_pop":1275,
    "ks:ks_type":"VILLAGE",
    "name:eng_x_preferred":[
        "Bhikanpur Dih"
    ],
    "wof:name":"Bhikanpur Dih",
    "wof:placetype":"locality",
    "wof:population":1275
},
  "geometry": {"coordinates":[85.382152,26.093901],"type":"Point"}
}