{
  "type": "Feature",
  "properties": {
    "iso:country":"IN",
    "ks:ks_name":"Madarguri",
    "ks:ks_pop":255,
    "ks:ks_type":"VILLAGE",
    "name:eng_x_preferred":[
        "Madarguri"
    ],
    "wof:name":"Madarguri",
    "wof:placetype":"locality",
    "wof:population":255
},
  "geometry": {"coordinates":[92.379805,26.466188],"type":"Point"}
}