{
  "type": "Feature",
  "properties": {
    "gn:admin1_code":"37",
    "gn:admin2_code":"408.0",
    "gn:asciiname":"Ramatola",
    "gn:country_code":"IN",
    "gn:dem":351,
    "gn:feature_class":"P",
    "gn:feature_code":"PPL",
    "gn:name":"R\u0101m\u0101tol\u0101",
    "gn:population":0,
    "gn:timezone":"Asia/Kolkata",
    "iso:country":"IN",
    "ks:ks_name":"Ramatola",
    "ks:ks_pop":1611,
    "ks:ks_type":"HABITATION",
    "name:eng_x_preferred":[
        "Ramatola"
    ],
    "wof:name":"Ramatola",
    "wof:placetype":"locality",
    "wof:population":1611
},
  "geometry": {"coordinates":[80.709839,21.127535],"type":"Point"}
}