{
  "type": "Feature",
  "properties": {
    "iso:country":"IN",
    "ks:ks_name":"Juwee Palli",
    "ks:ks_pop":57,
    "ks:ks_type":"VILLAGE",
    "name:eng_x_preferred":[
        "Juwee Palli"
    ],
    "wof:name":"Juwee Palli",
    "wof:placetype":"locality",
    "wof:population":57
},
  "geometry": {"coordinates":[79.067387,29.925465],"type":"Point"}
}