{
  "type": "Feature",
  "properties": {
    "iso:country":"IN",
    "ks:ks_alt_nam":"REVALI",
    "ks:ks_name":"Revali",
    "ks:ks_pop":786,
    "ks:ks_type":"HABITATION",
    "name:eng_x_preferred":[
        "Revali"
    ],
    "wof:name":"Revali",
    "wof:placetype":"locality",
    "wof:population":786
},
  "geometry": {"coordinates":[81.678877,27.577635],"type":"Point"}
}