{
  "type": "Feature",
  "properties": {
    "iso:country":"IN",
    "ks:ks_name":"Venkatapuram",
    "ks:ks_pop":59,
    "ks:ks_type":"HABITATION",
    "name:eng_x_preferred":[
        "Venkatapuram"
    ],
    "wof:name":"Venkatapuram",
    "wof:placetype":"locality",
    "wof:population":59
},
  "geometry": {"coordinates":[78.542638,14.118292],"type":"Point"}
}