{
  "type": "Feature",
  "properties": {
    "iso:country":"IN",
    "ks:ks_name":"Visher Ganj",
    "ks:ks_pop":1209,
    "ks:ks_type":"HABITATION",
    "name:eng_x_preferred":[
        "Visher Ganj"
    ],
    "wof:name":"Visher Ganj",
    "wof:placetype":"locality",
    "wof:population":1209
},
  "geometry": {"coordinates":[81.82816099999999,26.164762],"type":"Point"}
}