{
  "type": "Feature",
  "properties": {
    "iso:country":"IN",
    "ks:ks_alt_nam":"V\u0101r\u0101r",
    "ks:ks_name":"Varar",
    "ks:ks_type":"VILLAGE",
    "name:eng_x_preferred":[
        "Varar"
    ],
    "name:eng_x_variant":[
        "V\u0101r\u0101r"
    ],
    "wof:name":"Varar",
    "wof:placetype":"locality"
},
  "geometry": {"coordinates":[69.56009899999999,23.347487],"type":"Point"}
}