{
  "type": "Feature",
  "properties": {
    "iso:country":"IN",
    "ks:ks_name":"Varchiwadi",
    "ks:ks_pop":148,
    "ks:ks_type":"HABITATION",
    "name:eng_x_preferred":[
        "Varchiwadi"
    ],
    "wof:name":"Varchiwadi",
    "wof:placetype":"locality",
    "wof:population":148
},
  "geometry": {"coordinates":[74.01761,17.252677],"type":"Point"}
}