{
  "type": "Feature",
  "properties": {
    "iso:country":"IN",
    "ks:ks_name":"Mondal O Moua Khali Para",
    "ks:ks_pop":600,
    "ks:ks_type":"HABITATION",
    "name:eng_x_preferred":[
        "Mondal O Moua Khali Para"
    ],
    "wof:name":"Mondal O Moua Khali Para",
    "wof:placetype":"locality",
    "wof:population":600
},
  "geometry": {"coordinates":[88.639078,22.111782],"type":"Point"}
}