{
  "type": "Feature",
  "properties": {
    "gn:admin1_code":"10.0",
    "gn:admin2_code":"078",
    "gn:asciiname":"Hijraon Kalan",
    "gn:country_code":"IN",
    "gn:dem":215,
    "gn:feature_class":"P",
    "gn:feature_code":"PPL",
    "gn:name":"Hijr\u0101on Kal\u0101n",
    "gn:population":0,
    "gn:timezone":"Asia/Kolkata",
    "iso:country":"IN",
    "name:und_x_variant":[
        "Hijr\u0101on Kal\u0101n",
        "Hijr\u0101on"
    ],
    "wof:name":"Hijraon Kalan",
    "wof:placetype":"neighbourhood"
},
  "geometry": {"coordinates":[75.40066,29.5619],"type":"Point"}
}