{
  "type": "Feature",
  "properties": {
    "iso:country":"IN",
    "ks:ks_name":"Kaliaposh",
    "ks:ks_pop":251,
    "ks:ks_type":"VILLAGE",
    "name:eng_x_preferred":[
        "Kaliaposh"
    ],
    "wof:name":"Kaliaposh",
    "wof:placetype":"locality",
    "wof:population":251
},
  "geometry": {"coordinates":[85.073798,22.254266],"type":"Point"}
}