{
  "type": "Feature",
  "properties": {
    "iso:country":"IN",
    "ks:ks_name":"Nedumballam",
    "ks:ks_pop":1012,
    "ks:ks_type":"HABITATION",
    "name:eng_x_preferred":[
        "Nedumballam"
    ],
    "wof:name":"Nedumballam",
    "wof:placetype":"neighbourhood",
    "wof:population":1012
},
  "geometry": {"coordinates":[76.747996,10.645318],"type":"Point"}
}