{
  "type": "Feature",
  "properties": {
    "iso:country":"IN",
    "ks:ks_alt_nam":"L\u0101lpuram",
    "ks:ks_name":"Lalpuram",
    "ks:ks_pop":3026,
    "ks:ks_type":"VILLAGE",
    "ks:ks_uagg_main":0,
    "name:eng_x_preferred":[
        "Lalpuram"
    ],
    "name:eng_x_variant":[
        "L\u0101lpuram"
    ],
    "wof:name":"Lalpuram",
    "wof:placetype":"neighbourhood",
    "wof:population":3026
},
  "geometry": {"coordinates":[79.688233,11.417226],"type":"Point"}
}