{
  "type": "Feature",
  "properties": {
    "iso:country":"IN",
    "ks:ks_name":"Koila Belwa",
    "ks:ks_pop":6887,
    "ks:ks_type":"VILLAGE",
    "ks:ks_uagg_main":0,
    "name:eng_x_preferred":[
        "Koila Belwa"
    ],
    "wof:name":"Koila Belwa",
    "wof:placetype":"neighbourhood",
    "wof:population":6887
},
  "geometry": {"coordinates":[85.021944,26.387564],"type":"Point"}
}