{
  "type": "Feature",
  "properties": {
    "iso:country":"IN",
    "ks:ks_name":"Talpangkhola",
    "ks:ks_pop":131,
    "ks:ks_type":"HABITATION",
    "name:eng_x_preferred":[
        "Talpangkhola"
    ],
    "wof:name":"Talpangkhola",
    "wof:placetype":"locality",
    "wof:population":131
},
  "geometry": {"coordinates":[83.21183600000001,19.768672],"type":"Point"}
}