{
  "type": "Feature",
  "properties": {
    "gn:admin1_code":"25.0",
    "gn:admin2_code":"606.0",
    "gn:asciiname":"Vaniyantangal",
    "gn:country_code":"IN",
    "gn:dem":161,
    "gn:feature_class":"P",
    "gn:feature_code":"PPL",
    "gn:name":"V\u0101niyant\u0101ngal",
    "gn:population":0,
    "gn:timezone":"Asia/Kolkata",
    "iso:country":"IN",
    "ks:ks_name":"Vaniyanthangal",
    "ks:ks_pop":688,
    "ks:ks_type":"VILLAGE",
    "ks:ks_uagg_main":0,
    "name:eng_x_preferred":[
        "Vaniyanthangal"
    ],
    "wof:name":"Vaniyanthangal",
    "wof:placetype":"locality",
    "wof:population":688
},
  "geometry": {"coordinates":[79.097549,12.244878],"type":"Point"}
}