{
  "type": "Feature",
  "properties": {
    "iso:country":"IN",
    "ks:ks_name":"Aagarwadi",
    "ks:ks_pop":160,
    "ks:ks_type":"HABITATION",
    "name:eng_x_preferred":[
        "Aagarwadi"
    ],
    "wof:name":"Aagarwadi",
    "wof:placetype":"locality",
    "wof:population":160
},
  "geometry": {"coordinates":[73.220556,17.420833],"type":"Point"}
}