{
  "type": "Feature",
  "properties": {
    "iso:country":"IN",
    "ks:ks_name":"Alawalpur",
    "ks:ks_pop":1163,
    "ks:ks_type":"VILLAGE",
    "ks:ks_uagg_main":1,
    "name:eng_x_preferred":[
        "Alawalpur"
    ],
    "wof:name":"Alawalpur",
    "wof:placetype":"neighbourhood",
    "wof:population":1163
},
  "geometry": {"coordinates":[85.091311,25.497442],"type":"Point"}
}