{
  "type": "Feature",
  "properties": {
    "iso:country":"IN",
    "ks:ks_alt_nam":"MOTEKALE WASTI",
    "ks:ks_name":"Motekale Wasti",
    "ks:ks_pop":120,
    "ks:ks_type":"HABITATION",
    "name:eng_x_preferred":[
        "Motekale Wasti"
    ],
    "wof:name":"Motekale Wasti",
    "wof:placetype":"locality",
    "wof:population":120
},
  "geometry": {"coordinates":[75.14109999999999,17.065649],"type":"Point"}
}