{
  "type": "Feature",
  "properties": {
    "gn:admin1_code":"28.0",
    "gn:admin2_code":"330.0",
    "gn:asciiname":"Patua",
    "gn:country_code":"IN",
    "gn:dem":52,
    "gn:feature_class":"P",
    "gn:feature_code":"PPL",
    "gn:name":"Patua",
    "gn:population":0,
    "gn:timezone":"Asia/Kolkata",
    "iso:country":"IN",
    "name:ben_x_preferred":[
        "\u09aa\u099f\u09c1\u09af\u09bc\u09be"
    ],
    "name:deu_x_preferred":[
        "Patua"
    ],
    "name:hin_x_preferred":[
        "\u092a\u091f\u0941\u0906"
    ],
    "wof:name":"Patua",
    "wof:placetype":"locality"
},
  "geometry": {"coordinates":[87.95647,26.05895],"type":"Point"}
}