{
  "type": "Feature",
  "properties": {
    "iso:country":"IN",
    "ks:ks_name":"Bhankh",
    "ks:ks_pop":942,
    "ks:ks_type":"VILLAGE",
    "name:eng_x_preferred":[
        "Bhankh"
    ],
    "wof:name":"Bhankh",
    "wof:placetype":"locality",
    "wof:population":942
},
  "geometry": {"coordinates":[70.305333,21.843889],"type":"Point"}
}