{
  "type": "Feature",
  "properties": {
    "iso:country":"IN",
    "ks:ks_name":"Mundovmule",
    "ks:ks_pop":250,
    "ks:ks_type":"HABITATION",
    "name:eng_x_preferred":[
        "Mundovmule"
    ],
    "wof:name":"Mundovmule",
    "wof:placetype":"locality",
    "wof:population":250
},
  "geometry": {"coordinates":[75.196949,12.698415],"type":"Point"}
}