{
  "type": "Feature",
  "properties": {
    "iso:country":"IN",
    "ks:ks_name":"Therekatte Beedi",
    "ks:ks_pop":55,
    "ks:ks_type":"HABITATION",
    "name:eng_x_preferred":[
        "Therekatte Beedi"
    ],
    "wof:name":"Therekatte Beedi",
    "wof:placetype":"locality",
    "wof:population":55
},
  "geometry": {"coordinates":[75.263076,13.396861],"type":"Point"}
}