{
  "type": "Feature",
  "properties": {
    "gn:admin1_code":"24.0",
    "gn:admin2_code":"118.0",
    "gn:asciiname":"Khokhri",
    "gn:country_code":"IN",
    "gn:dem":350,
    "gn:feature_class":"P",
    "gn:feature_code":"PPL",
    "gn:name":"Khokhri",
    "gn:population":0,
    "gn:timezone":"Asia/Kolkata",
    "iso:country":"IN",
    "wof:name":"Khokhri",
    "wof:placetype":"locality"
},
  "geometry": {"coordinates":[74.13387,26.16786],"type":"Point"}
}