{
  "type": "Feature",
  "properties": {
    "iso:country":"IN",
    "ks:ks_name":"Tongritola",
    "ks:ks_pop":356,
    "ks:ks_type":"HABITATION",
    "name:eng_x_preferred":[
        "Tongritola"
    ],
    "wof:name":"Tongritola",
    "wof:placetype":"locality",
    "wof:population":356
},
  "geometry": {"coordinates":[85.19750999999999,23.591271],"type":"Point"}
}