{
  "type": "Feature",
  "properties": {
    "iso:country":"IN",
    "ks:ks_alt_nam":"Bheekya guguloth thanda",
    "ks:ks_name":"Bheekya Guguloth Thanda",
    "ks:ks_pop":110,
    "ks:ks_type":"HABITATION",
    "name:eng_x_preferred":[
        "Bheekya Guguloth Thanda"
    ],
    "wof:name":"Bheekya Guguloth Thanda",
    "wof:placetype":"locality",
    "wof:population":110
},
  "geometry": {"coordinates":[79.79340999999999,17.753566],"type":"Point"}
}