{
  "type": "Feature",
  "properties": {
    "iso:country":"IN",
    "ks:ks_name":"24 ML",
    "ks:ks_pop":1538,
    "ks:ks_type":"VILLAGE",
    "name:eng_x_preferred":[
        "24 ML"
    ],
    "wof:name":"24 ML",
    "wof:placetype":"locality",
    "wof:population":1538
},
  "geometry": {"coordinates":[73.840367,29.737225],"type":"Point"}
}