{
  "type": "Feature",
  "properties": {
    "iso:country":"IN",
    "ks:ks_name":"Arasamarathupatti",
    "ks:ks_pop":289,
    "ks:ks_type":"HABITATION",
    "name:eng_x_preferred":[
        "Arasamarathupatti"
    ],
    "wof:name":"Arasamarathupatti",
    "wof:placetype":"locality",
    "wof:population":289
},
  "geometry": {"coordinates":[77.982878,10.517145],"type":"Point"}
}