{
  "type": "Feature",
  "properties": {
    "iso:country":"IN",
    "ks:ks_name":"Kamewal",
    "ks:ks_pop":735,
    "ks:ks_type":"HABITATION",
    "name:eng_x_preferred":[
        "Kamewal"
    ],
    "wof:name":"Kamewal",
    "wof:placetype":"locality",
    "wof:population":735
},
  "geometry": {"coordinates":[75.22972300000001,31.421681],"type":"Point"}
}