{
  "type": "Feature",
  "properties": {
    "iso:country":"IN",
    "ks:ks_alt_nam":"KERWA MATHURA RAY TOLA",
    "ks:ks_name":"Kerwa Mathura Ray Tola",
    "ks:ks_pop":422,
    "ks:ks_type":"HABITATION",
    "name:eng_x_preferred":[
        "Kerwa Mathura Ray Tola"
    ],
    "wof:name":"Kerwa Mathura Ray Tola",
    "wof:placetype":"locality",
    "wof:population":422
},
  "geometry": {"coordinates":[84.84616,26.05424],"type":"Point"}
}