{
  "type": "Feature",
  "properties": {
    "iso:country":"IN",
    "ks:ks_name":"Talkarauti",
    "ks:ks_pop":0,
    "ks:ks_type":"VILLAGE",
    "name:eng_x_preferred":[
        "Talkarauti"
    ],
    "wof:name":"Talkarauti",
    "wof:placetype":"locality",
    "wof:population":0
},
  "geometry": {"coordinates":[83.971645,25.716452],"type":"Point"}
}