{
  "type": "Feature",
  "properties": {
    "iso:country":"IN",
    "ks:ks_name":"Dasapatpur",
    "ks:ks_pop":589,
    "ks:ks_type":"HABITATION",
    "name:eng_x_preferred":[
        "Dasapatpur"
    ],
    "wof:name":"Dasapatpur",
    "wof:placetype":"locality",
    "wof:population":589
},
  "geometry": {"coordinates":[82.81034099999999,25.440687],"type":"Point"}
}