{
  "type": "Feature",
  "properties": {
    "iso:country":"IN",
    "ks:ks_name":"Vellachal",
    "ks:ks_pop":1100,
    "ks:ks_type":"HABITATION",
    "name:eng_x_preferred":[
        "Vellachal"
    ],
    "wof:name":"Vellachal",
    "wof:placetype":"locality",
    "wof:population":1100
},
  "geometry": {"coordinates":[75.19438700000001,12.196817],"type":"Point"}
}