{
  "type": "Feature",
  "properties": {
    "iso:country":"IN",
    "ks:ks_name":"Mail Alias Phakiradih",
    "ks:ks_pop":1512,
    "ks:ks_type":"VILLAGE",
    "name:eng_x_preferred":[
        "Mail Alias Phakiradih"
    ],
    "wof:name":"Mail Alias Phakiradih",
    "wof:placetype":"locality",
    "wof:population":1512
},
  "geometry": {"coordinates":[83.938484,23.85523],"type":"Point"}
}