{
  "type": "Feature",
  "properties": {
    "iso:country":"IN",
    "ks:ks_name":"Sahariya Basti",
    "ks:ks_pop":185,
    "ks:ks_type":"HABITATION",
    "name:eng_x_preferred":[
        "Sahariya Basti"
    ],
    "wof:name":"Sahariya Basti",
    "wof:placetype":"locality",
    "wof:population":185
},
  "geometry": {"coordinates":[78.50985900000001,24.90575],"type":"Point"}
}