{
  "type": "Feature",
  "properties": {
    "gn:admin1_code":"36",
    "gn:admin2_code":"171.0",
    "gn:asciiname":"Deoria",
    "gn:country_code":"IN",
    "gn:dem":142,
    "gn:feature_class":"P",
    "gn:feature_code":"PPL",
    "gn:name":"Deoria",
    "gn:population":0,
    "gn:timezone":"Asia/Kolkata",
    "iso:country":"IN",
    "wof:name":"Deoria",
    "wof:placetype":"locality"
},
  "geometry": {"coordinates":[81.45761,25.10235],"type":"Point"}
}