{
  "type": "Feature",
  "properties": {
    "iso:country":"IN",
    "ks:ks_name":"Yelloor",
    "ks:ks_pop":232,
    "ks:ks_type":"HABITATION",
    "name:eng_x_preferred":[
        "Yelloor"
    ],
    "wof:name":"Yelloor",
    "wof:placetype":"locality",
    "wof:population":232
},
  "geometry": {"coordinates":[74.77190299999999,13.813795],"type":"Point"}
}