{
  "type": "Feature",
  "properties": {
    "gn:admin1_code":"36.0",
    "gn:admin2_code":"179.0",
    "gn:asciiname":"Kalupur",
    "gn:country_code":"IN",
    "gn:dem":107,
    "gn:feature_class":"P",
    "gn:feature_code":"PPL",
    "gn:name":"K\u0101l\u016bpur",
    "gn:population":0,
    "gn:timezone":"Asia/Kolkata",
    "iso:country":"IN",
    "name:guj_x_preferred":[
        "\u0a95\u0abe\u0ab2\u0ac1\u0aaa\u0ac1\u0ab0"
    ],
    "wof:name":"Kalupur",
    "wof:placetype":"locality"
},
  "geometry": {"coordinates":[81.79279,26.24826],"type":"Point"}
}