{
  "type": "Feature",
  "properties": {
    "gn:admin1_code":"2.0",
    "gn:admin2_code":"554.0",
    "gn:asciiname":"Gudipalle",
    "gn:country_code":"IN",
    "gn:dem":723,
    "gn:feature_class":"P",
    "gn:feature_code":"PPL",
    "gn:name":"Gudipalle",
    "gn:population":0,
    "gn:timezone":"Asia/Kolkata",
    "iso:country":"IN",
    "wof:name":"Gudipalle",
    "wof:placetype":"locality"
},
  "geometry": {"coordinates":[78.7218,13.31086],"type":"Point"}
}