{
  "type": "Feature",
  "properties": {
    "gn:admin1_code":"36",
    "gn:admin2_code":"200.0",
    "gn:asciiname":"Sapanian",
    "gn:country_code":"IN",
    "gn:dem":278,
    "gn:feature_class":"P",
    "gn:feature_code":"PPL",
    "gn:name":"Sapanian",
    "gn:population":0,
    "gn:timezone":"Asia/Kolkata",
    "iso:country":"IN",
    "wof:name":"Sapanian",
    "wof:placetype":"locality"
},
  "geometry": {"coordinates":[82.65004,24.70181],"type":"Point"}
}