{
  "type": "Feature",
  "properties": {
    "iso:country":"IN",
    "ks:ks_name":"Brinia",
    "ks:ks_pop":590,
    "ks:ks_type":"HABITATION",
    "name:eng_x_preferred":[
        "Brinia"
    ],
    "wof:name":"Brinia",
    "wof:placetype":"locality",
    "wof:population":590
},
  "geometry": {"coordinates":[87.194577,25.612119],"type":"Point"}
}