{
  "type": "Feature",
  "properties": {
    "iso:country":"IN",
    "ks:ks_name":"Harizan Tola",
    "ks:ks_pop":29,
    "ks:ks_type":"HABITATION",
    "name:eng_x_preferred":[
        "Harizan Tola"
    ],
    "wof:name":"Harizan Tola",
    "wof:placetype":"locality",
    "wof:population":29
},
  "geometry": {"coordinates":[84.184332,26.186889],"type":"Point"}
}