{
  "type": "Feature",
  "properties": {
    "gn:admin1_code":"2",
    "gn:admin2_code":"544.0",
    "gn:asciiname":"Rayapadu",
    "gn:country_code":"IN",
    "gn:dem":540,
    "gn:feature_class":"P",
    "gn:feature_code":"PPL",
    "gn:name":"R\u0101yap\u0101du",
    "gn:population":0,
    "gn:timezone":"Asia/Kolkata",
    "iso:country":"IN",
    "ks:ks_name":"Rayipadu",
    "ks:ks_pop":91,
    "ks:ks_type":"HABITATION",
    "name:eng_x_preferred":[
        "Rayipadu"
    ],
    "name:eng_x_variant":[
        "Rayapadu"
    ],
    "wof:name":"Rayipadu",
    "wof:placetype":"locality",
    "wof:population":91
},
  "geometry": {"coordinates":[82.97192800000001,18.187942],"type":"Point"}
}