{
  "type": "Feature",
  "properties": {
    "gn:admin1_code":"35",
    "gn:admin2_code":"422.0",
    "gn:asciiname":"Pachora Buzurg",
    "gn:country_code":"IN",
    "gn:dem":177,
    "gn:feature_class":"P",
    "gn:feature_code":"PPL",
    "gn:name":"Pachora Buzurg",
    "gn:population":0,
    "gn:timezone":"Asia/Kolkata",
    "iso:country":"IN",
    "ks:ks_name":"Pacherabuzurg",
    "ks:ks_pop":377,
    "ks:ks_type":"VILLAGE",
    "ks:ks_uagg_main":0,
    "name:eng_x_preferred":[
        "Pacherabuzurg"
    ],
    "wof:name":"Pacherabuzurg",
    "wof:placetype":"neighbourhood",
    "wof:population":377
},
  "geometry": {"coordinates":[78.573427,25.997559],"type":"Point"}
}