{
  "type": "Feature",
  "properties": {
    "iso:country":"IN",
    "ks:ks_name":"Mohanbari",
    "ks:ks_pop":1015,
    "ks:ks_type":"HABITATION",
    "name:eng_x_preferred":[
        "Mohanbari"
    ],
    "wof:name":"Mohanbari",
    "wof:placetype":"locality",
    "wof:population":1015
},
  "geometry": {"coordinates":[75.684055,27.098521],"type":"Point"}
}