{
  "type": "Feature",
  "properties": {
    "iso:country":"IN",
    "ks:ks_name":"Vahana",
    "ks:ks_pop":534,
    "ks:ks_type":"VILLAGE",
    "name:eng_x_preferred":[
        "Vahana"
    ],
    "wof:name":"Vahana",
    "wof:placetype":"locality",
    "wof:population":534
},
  "geometry": {"coordinates":[72.179084,24.100933],"type":"Point"}
}