{
  "type": "Feature",
  "properties": {
    "gn:admin1_code":"39.0",
    "gn:admin2_code":"62.0",
    "gn:asciiname":"Bujar",
    "gn:country_code":"IN",
    "gn:dem":1537,
    "gn:feature_class":"P",
    "gn:feature_code":"PPL",
    "gn:name":"Buj\u0101r",
    "gn:population":0,
    "gn:timezone":"Asia/Kolkata",
    "iso:country":"IN",
    "wof:name":"Bujar",
    "wof:placetype":"locality"
},
  "geometry": {"coordinates":[79.99016,29.71967],"type":"Point"}
}