{
  "type": "Feature",
  "properties": {
    "gn:admin1_code":"21.0",
    "gn:admin2_code":"396.0",
    "gn:asciiname":"Pangali",
    "gn:country_code":"IN",
    "gn:dem":265,
    "gn:feature_class":"P",
    "gn:feature_code":"PPL",
    "gn:name":"Pangali",
    "gn:population":0,
    "gn:timezone":"Asia/Kolkata",
    "iso:country":"IN",
    "name:tam_x_preferred":[
        "\u0baa\u0b99\u0bcd\u0b95\u0bbe\u0bb3\u0bbf"
    ],
    "wof:name":"Pangali",
    "wof:placetype":"locality"
},
  "geometry": {"coordinates":[83.48116,19.28066],"type":"Point"}
}