{
  "type": "Feature",
  "properties": {
    "iso:country":"IN",
    "ks:ks_alt_nam":"MUSLIM TOLA",
    "ks:ks_name":"Muslim Tola",
    "ks:ks_pop":375,
    "ks:ks_type":"HABITATION",
    "name:eng_x_preferred":[
        "Muslim Tola"
    ],
    "wof:name":"Muslim Tola",
    "wof:placetype":"locality",
    "wof:population":375
},
  "geometry": {"coordinates":[86.84916699999999,25.183867],"type":"Point"}
}