{
  "type": "Feature",
  "properties": {
    "gn:admin1_code":"19.0",
    "gn:admin2_code":"583.0",
    "gn:asciiname":"Byaderhalli",
    "gn:country_code":"IN",
    "gn:dem":899,
    "gn:feature_class":"P",
    "gn:feature_code":"PPL",
    "gn:name":"Byaderhalli",
    "gn:population":0,
    "gn:timezone":"Asia/Kolkata",
    "iso:country":"IN",
    "ks:ks_name":"Byadarahalli",
    "ks:ks_pop":495,
    "ks:ks_type":"VILLAGE",
    "ks:ks_uagg_main":0,
    "name:eng_x_preferred":[
        "Byadarahalli"
    ],
    "wof:name":"Byadarahalli",
    "wof:placetype":"locality",
    "wof:population":495
},
  "geometry": {"coordinates":[77.371161,13.109974],"type":"Point"}
}