{
  "type": "Feature",
  "properties": {
    "gn:admin1_code":"19.0",
    "gn:admin2_code":"564.0",
    "gn:asciiname":"Akkivalli",
    "gn:country_code":"IN",
    "gn:dem":568,
    "gn:feature_class":"P",
    "gn:feature_code":"PPL",
    "gn:name":"Akkivalli",
    "gn:population":0,
    "gn:timezone":"Asia/Kolkata",
    "iso:country":"IN",
    "name:fas_x_preferred":[
        "\u0627\u06a9\u06cc\u0648\u0627\u0644\u06cc"
    ],
    "name:vie_x_preferred":[
        "Akkivalli"
    ],
    "wof:name":"Akkivalli",
    "wof:placetype":"locality"
},
  "geometry": {"coordinates":[75.16899000000002,14.77776],"type":"Point"}
}