{
  "type": "Feature",
  "properties": {
    "gn:admin1_code":"38.0",
    "gn:asciiname":"Shikarpur",
    "gn:country_code":"IN",
    "gn:dem":171,
    "gn:feature_class":"P",
    "gn:feature_code":"PPL",
    "gn:name":"Shik\u0101rpur",
    "gn:population":0,
    "gn:timezone":"Asia/Kolkata",
    "iso:country":"IN",
    "name:ceb_x_preferred":[
        "Shikarpur"
    ],
    "name:pol_x_preferred":[
        "Shikarpur"
    ],
    "name:pus_x_preferred":[
        "\u0634\u06a9\u0627\u0631\u067e\u0648\u0631"
    ],
    "name:swe_x_preferred":[
        "Shikarpur"
    ],
    "name:urd_x_preferred":[
        "\u0634\u06a9\u0627\u0631\u067e\u0648\u0631"
    ],
    "name:vie_x_preferred":[
        "Shikarpur"
    ],
    "wof:name":"Shikarpur",
    "wof:placetype":"locality"
},
  "geometry": {"coordinates":[84.19161,24.55146],"type":"Point"}
}