{
  "type": "Feature",
  "properties": {
    "iso:country":"IN",
    "ks:ks_name":"Shivakar Wadi",
    "ks:ks_pop":316,
    "ks:ks_type":"VILLAGE",
    "name:eng_x_preferred":[
        "Shivakar Wadi"
    ],
    "wof:name":"Shivakar Wadi",
    "wof:placetype":"locality",
    "wof:population":316
},
  "geometry": {"coordinates":[76.283934,17.96096],"type":"Point"}
}