{
  "type": "Feature",
  "properties": {
    "iso:country":"IN",
    "ks:ks_name":"Brahmapur",
    "ks:ks_pop":258,
    "ks:ks_type":"VILLAGE",
    "ks:ks_uagg_main":0,
    "name:eng_x_preferred":[
        "Brahmapur"
    ],
    "wof:name":"Brahmapur",
    "wof:placetype":"neighbourhood",
    "wof:population":258
},
  "geometry": {"coordinates":[86.040544,20.236639],"type":"Point"}
}