{
  "type": "Feature",
  "properties": {
    "iso:country":"IN",
    "ks:ks_name":"Rawatepada",
    "ks:ks_pop":130,
    "ks:ks_type":"HABITATION",
    "name:eng_x_preferred":[
        "Rawatepada"
    ],
    "wof:name":"Rawatepada",
    "wof:placetype":"locality",
    "wof:population":130
},
  "geometry": {"coordinates":[73.13981200000001,19.535762],"type":"Point"}
}