{
  "type": "Feature",
  "properties": {
    "iso:country":"IN",
    "ks:ks_name":"Ketela T E 27 112",
    "ks:ks_pop":873,
    "ks:ks_type":"HABITATION",
    "ks:ks_uagg_main":0,
    "name:eng_x_preferred":[
        "Ketela T E 27 112"
    ],
    "wof:name":"Ketela T E 27 112",
    "wof:placetype":"neighbourhood",
    "wof:population":873
},
  "geometry": {"coordinates":[93.297783,26.837044],"type":"Point"}
}