{
  "type": "Feature",
  "properties": {
    "gn:admin1_code":"2.0",
    "gn:admin2_code":"554.0",
    "gn:asciiname":"Marrimakulapalle",
    "gn:country_code":"IN",
    "gn:dem":734,
    "gn:feature_class":"P",
    "gn:feature_code":"PPL",
    "gn:name":"Marrim\u0101kulapalle",
    "gn:population":0,
    "gn:timezone":"Asia/Kolkata",
    "iso:country":"IN",
    "wof:name":"Marrimakulapalle",
    "wof:placetype":"locality"
},
  "geometry": {"coordinates":[78.61272,13.35629],"type":"Point"}
}