{
  "type": "Feature",
  "properties": {
    "gn:admin1_code":"37",
    "gn:admin2_code":"404.0",
    "gn:asciiname":"Bhadrapara",
    "gn:country_code":"IN",
    "gn:dem":335,
    "gn:feature_class":"P",
    "gn:feature_code":"PPL",
    "gn:name":"Bhadr\u0101p\u0101ra",
    "gn:population":0,
    "gn:timezone":"Asia/Kolkata",
    "iso:country":"IN",
    "wof:name":"Bhadrapara",
    "wof:placetype":"locality"
},
  "geometry": {"coordinates":[82.20969000000002,22.41085],"type":"Point"}
}