{
  "type": "Feature",
  "properties": {
    "gn:admin1_code":"19.0",
    "gn:admin2_code":"570.0",
    "gn:asciiname":"Aradavalli",
    "gn:country_code":"IN",
    "gn:dem":664,
    "gn:feature_class":"P",
    "gn:feature_code":"PPL",
    "gn:name":"Aradavalli",
    "gn:population":0,
    "gn:timezone":"Asia/Kolkata",
    "iso:country":"IN",
    "ks:ks_name":"Agaravalli",
    "ks:ks_pop":68,
    "ks:ks_type":"HABITATION",
    "name:eng_x_preferred":[
        "Agaravalli"
    ],
    "name:eng_x_variant":[
        "Aradavalli"
    ],
    "wof:name":"Agaravalli",
    "wof:placetype":"locality",
    "wof:population":68
},
  "geometry": {"coordinates":[75.32170600000001,13.440025],"type":"Point"}
}