{
  "type": "Feature",
  "properties": {
    "iso:country":"IN",
    "ks:ks_alt_nam":"Mudump\u0101du Slopes Reserved Forest",
    "ks:ks_alt_nam_2":"Mudumpadu Slopes Reserved Forest",
    "ks:ks_name":"Mudumpadu Slopes Reserved Fore",
    "ks:ks_type":"VILLAGE",
    "name:eng_x_preferred":[
        "Mudumpadu Slopes Reserved Fore"
    ],
    "name:eng_x_variant":[
        "Mudump\u0101du Slopes Reserved Forest",
        "Mudumpadu Slopes Reserved Forest"
    ],
    "wof:name":"Mudumpadu Slopes Reserved Fore",
    "wof:placetype":"locality"
},
  "geometry": {"coordinates":[79.106116,13.897537],"type":"Point"}
}