{
  "type": "Feature",
  "properties": {
    "iso:country":"IN",
    "ks:ks_name":"Rautpara",
    "ks:ks_pop":130,
    "ks:ks_type":"HABITATION",
    "name:eng_x_preferred":[
        "Rautpara"
    ],
    "wof:name":"Rautpara",
    "wof:placetype":"locality",
    "wof:population":130
},
  "geometry": {"coordinates":[81.603058,19.137124],"type":"Point"}
}