{
  "type": "Feature",
  "properties": {
    "iso:country":"IN",
    "ks:ks_name":"Kaiti",
    "ks:ks_pop":35,
    "ks:ks_type":"HABITATION",
    "name:eng_x_preferred":[
        "Kaiti"
    ],
    "wof:name":"Kaiti",
    "wof:placetype":"locality",
    "wof:population":35
},
  "geometry": {"coordinates":[80.26581299999999,30.087389],"type":"Point"}
}