{
  "type": "Feature",
  "properties": {
    "gn:admin1_code":"36",
    "gn:admin2_code":"159.0",
    "gn:asciiname":"Behta Ballu",
    "gn:country_code":"IN",
    "gn:dem":150,
    "gn:feature_class":"P",
    "gn:feature_code":"PPL",
    "gn:name":"Behta Ballu",
    "gn:population":0,
    "gn:timezone":"Asia/Kolkata",
    "iso:country":"IN",
    "ks:ks_name":"Behta Ballu",
    "ks:ks_pop":850,
    "ks:ks_type":"VILLAGE",
    "name:eng_x_preferred":[
        "Behta Ballu"
    ],
    "wof:name":"Behta Ballu",
    "wof:placetype":"locality",
    "wof:population":850
},
  "geometry": {"coordinates":[79.43027499999999,27.608534],"type":"Point"}
}