{
  "type": "Feature",
  "properties": {
    "gn:admin1_code":"36.0",
    "gn:admin2_code":"182.0",
    "gn:asciiname":"Katia",
    "gn:country_code":"IN",
    "gn:dem":108,
    "gn:feature_class":"P",
    "gn:feature_code":"PPL",
    "gn:name":"Katia",
    "gn:population":0,
    "gn:timezone":"Asia/Kolkata",
    "iso:country":"IN",
    "name:deu_x_preferred":[
        "Katia"
    ],
    "name:fra_x_preferred":[
        "Katia"
    ],
    "name:ita_x_preferred":[
        "Katia"
    ],
    "wof:name":"Katia",
    "wof:placetype":"locality"
},
  "geometry": {"coordinates":[82.27856,27.39095],"type":"Point"}
}