{
  "type": "Feature",
  "properties": {
    "gn:admin1_code":"40.0",
    "gn:admin2_code":"532.0",
    "gn:asciiname":"Devaigura",
    "gn:country_code":"IN",
    "gn:dem":239,
    "gn:feature_class":"P",
    "gn:feature_code":"PPL",
    "gn:name":"Devaigura",
    "gn:population":0,
    "gn:timezone":"Asia/Kolkata",
    "iso:country":"IN",
    "ks:ks_name":"Devaiguda",
    "ks:ks_pop":776,
    "ks:ks_type":"VILLAGE",
    "name:eng_x_preferred":[
        "Devaiguda"
    ],
    "name:eng_x_variant":[
        "Devaigura"
    ],
    "wof:name":"Devaiguda",
    "wof:placetype":"locality",
    "wof:population":776
},
  "geometry": {"coordinates":[79.265914,19.262127],"type":"Point"}
}