{
  "type": "Feature",
  "properties": {
    "iso:country":"IN",
    "ks:ks_name":"Chitnika Pura",
    "ks:ks_pop":120,
    "ks:ks_type":"HABITATION",
    "name:eng_x_preferred":[
        "Chitnika Pura"
    ],
    "wof:name":"Chitnika Pura",
    "wof:placetype":"locality",
    "wof:population":120
},
  "geometry": {"coordinates":[81.551905,25.540964],"type":"Point"}
}