{
  "type": "Feature",
  "properties": {
    "iso:country":"IN",
    "ks:ks_name":"Fatehpura",
    "ks:ks_pop":84,
    "ks:ks_type":"VILLAGE",
    "name:eng_x_preferred":[
        "Fatehpura"
    ],
    "wof:name":"Fatehpura",
    "wof:placetype":"locality",
    "wof:population":84
},
  "geometry": {"coordinates":[75.235349,25.200361],"type":"Point"}
}