{
  "type": "Feature",
  "properties": {
    "iso:country":"IN",
    "ks:ks_name":"Nuagaon",
    "ks:ks_pop":617,
    "ks:ks_type":"VILLAGE",
    "ks:ks_uagg_main":0,
    "name:eng_x_preferred":[
        "Nuagaon"
    ],
    "wof:name":"Nuagaon",
    "wof:placetype":"neighbourhood",
    "wof:population":617
},
  "geometry": {"coordinates":[86.28595,20.118701],"type":"Point"}
}