{
  "type": "Feature",
  "properties": {
    "iso:country":"IN",
    "ks:ks_name":"Akhabuda",
    "ks:ks_pop":68,
    "ks:ks_type":"VILLAGE",
    "name:eng_x_preferred":[
        "Akhabuda"
    ],
    "wof:name":"Akhabuda",
    "wof:placetype":"locality",
    "wof:population":68
},
  "geometry": {"coordinates":[84.615207,21.296942],"type":"Point"}
}