{
  "type": "Feature",
  "properties": {
    "iso:country":"IN",
    "ks:ks_name":"Nagla Pal",
    "ks:ks_pop":200,
    "ks:ks_type":"HABITATION",
    "name:eng_x_preferred":[
        "Nagla Pal"
    ],
    "wof:name":"Nagla Pal",
    "wof:placetype":"locality",
    "wof:population":200
},
  "geometry": {"coordinates":[79.633808,27.240221],"type":"Point"}
}