{
  "type": "Feature",
  "properties": {
    "iso:country":"IN",
    "ks:ks_name":"Dhangarwadi",
    "ks:ks_pop":70,
    "ks:ks_type":"HABITATION",
    "name:eng_x_preferred":[
        "Dhangarwadi"
    ],
    "wof:name":"Dhangarwadi",
    "wof:placetype":"locality",
    "wof:population":70
},
  "geometry": {"coordinates":[73.450153,17.803867],"type":"Point"}
}