{
  "type": "Feature",
  "properties": {
    "iso:country":"IN",
    "ks:ks_name":"Anantadahi",
    "ks:ks_pop":128,
    "ks:ks_type":"HABITATION",
    "name:eng_x_preferred":[
        "Anantadahi"
    ],
    "wof:name":"Anantadahi",
    "wof:placetype":"locality",
    "wof:population":128
},
  "geometry": {"coordinates":[86.606345,21.469295],"type":"Point"}
}