{
  "type": "Feature",
  "properties": {
    "iso:country":"IN",
    "ks:ks_name":"Langalbhanga",
    "ks:ks_pop":968,
    "ks:ks_type":"VILLAGE",
    "name:eng_x_preferred":[
        "Langalbhanga"
    ],
    "wof:name":"Langalbhanga",
    "wof:placetype":"locality",
    "wof:population":968
},
  "geometry": {"coordinates":[87.56481100000001,24.039661],"type":"Point"}
}