{
  "type": "Feature",
  "properties": {
    "iso:country":"IN",
    "ks:ks_alt_nam":"yale/Kolpewasti",
    "ks:ks_name":"Yale/kolpewasti",
    "ks:ks_pop":72,
    "ks:ks_type":"HABITATION",
    "name:eng_x_preferred":[
        "Yale/kolpewasti"
    ],
    "wof:name":"Yale/kolpewasti",
    "wof:placetype":"locality",
    "wof:population":72
},
  "geometry": {"coordinates":[74.24783100000001,18.080581],"type":"Point"}
}