{
  "type": "Feature",
  "properties": {
    "iso:country":"IN",
    "ks:ks_name":"Bhalukkhuliya",
    "ks:ks_pop":41,
    "ks:ks_type":"VILLAGE",
    "ks:ks_uagg_main":0,
    "name:eng_x_preferred":[
        "Bhalukkhuliya"
    ],
    "wof:name":"Bhalukkhuliya",
    "wof:placetype":"neighbourhood",
    "wof:population":41
},
  "geometry": {"coordinates":[86.416847,22.662548],"type":"Point"}
}