{
  "type": "Feature",
  "properties": {
    "iso:country":"IN",
    "ks:ks_alt_nam":"Kurushummoodu jn",
    "ks:ks_name":"Kurushummoodu Jn",
    "ks:ks_pop":550,
    "ks:ks_type":"HABITATION",
    "name:eng_x_preferred":[
        "Kurushummoodu Jn"
    ],
    "wof:name":"Kurushummoodu Jn",
    "wof:placetype":"locality",
    "wof:population":550
},
  "geometry": {"coordinates":[76.532923,9.29333],"type":"Point"}
}