{
  "type": "Feature",
  "properties": {
    "gn:admin1_code":"25.0",
    "gn:admin2_code":"617.0",
    "gn:asciiname":"Pelandurai",
    "gn:country_code":"IN",
    "gn:dem":55,
    "gn:feature_class":"P",
    "gn:feature_code":"PPL",
    "gn:name":"Pel\u0101ndurai",
    "gn:population":0,
    "gn:timezone":"Asia/Kolkata",
    "iso:country":"IN",
    "wof:name":"Pelandurai",
    "wof:placetype":"locality"
},
  "geometry": {"coordinates":[79.27979999999999,11.40485],"type":"Point"}
}