{
  "type": "Feature",
  "properties": {
    "gn:admin1_code":"24.0",
    "gn:admin2_code":"112",
    "gn:asciiname":"Khajwana",
    "gn:country_code":"IN",
    "gn:dem":337,
    "gn:feature_class":"P",
    "gn:feature_code":"PPL",
    "gn:name":"Khajw\u0101na",
    "gn:population":0,
    "gn:timezone":"Asia/Kolkata",
    "iso:country":"IN",
    "name:und_x_variant":[
        "Khaju\u0101na",
        "Khajw\u0101na"
    ],
    "wof:name":"Khajwana",
    "wof:placetype":"locality"
},
  "geometry": {"coordinates":[73.84393,26.9136],"type":"Point"}
}