{
  "type": "Feature",
  "properties": {
    "gn:admin1_code":"36.0",
    "gn:admin2_code":"195.0",
    "gn:asciiname":"Hasanpur",
    "gn:country_code":"IN",
    "gn:dem":74,
    "gn:feature_class":"P",
    "gn:feature_code":"PPL",
    "gn:name":"Hasanpur",
    "gn:population":0,
    "gn:timezone":"Asia/Kolkata",
    "iso:country":"IN",
    "name:und_x_variant":[
        "Karmunpur"
    ],
    "wof:name":"Hasanpur",
    "wof:placetype":"locality"
},
  "geometry": {"coordinates":[83.68141,25.73252],"type":"Point"}
}