{
  "type": "Feature",
  "properties": {
    "gn:admin1_code":"24.0",
    "gn:admin2_code":"109.0",
    "gn:asciiname":"Jarnat",
    "gn:country_code":"IN",
    "gn:dem":307,
    "gn:feature_class":"P",
    "gn:feature_code":"PPL",
    "gn:name":"Jarn\u0101t",
    "gn:population":0,
    "gn:timezone":"Asia/Kolkata",
    "iso:country":"IN",
    "name:und_x_variant":[
        "Jarn\u0101t",
        "T\u0101lra"
    ],
    "wof:name":"Jarnat",
    "wof:placetype":"locality"
},
  "geometry": {"coordinates":[76.32079,26.55211],"type":"Point"}
}