{
  "type": "Feature",
  "properties": {
    "iso:country":"IN",
    "ks:ks_name":"Kanyamala",
    "ks:ks_pop":750,
    "ks:ks_type":"HABITATION",
    "name:eng_x_preferred":[
        "Kanyamala"
    ],
    "wof:name":"Kanyamala",
    "wof:placetype":"locality",
    "wof:population":750
},
  "geometry": {"coordinates":[76.75370599999999,9.830174],"type":"Point"}
}