{
  "type": "Feature",
  "properties": {
    "gn:admin1_code":"34.0",
    "gn:admin2_code":"231.0",
    "gn:asciiname":"Bela",
    "gn:country_code":"IN",
    "gn:dem":64,
    "gn:feature_class":"P",
    "gn:feature_code":"PPL",
    "gn:name":"Bela",
    "gn:population":0,
    "gn:timezone":"Asia/Kolkata",
    "iso:country":"IN",
    "name:bos_x_preferred":[
        "Bela"
    ],
    "name:cat_x_preferred":[
        "Bela"
    ],
    "name:ceb_x_preferred":[
        "Bela"
    ],
    "name:deu_x_preferred":[
        "Bela"
    ],
    "name:eus_x_preferred":[
        "Bela"
    ],
    "name:fra_x_preferred":[
        "Bela"
    ],
    "name:heb_x_preferred":[
        "\u05d1\u05dc\u05e2"
    ],
    "name:hrv_x_preferred":[
        "Bela"
    ],
    "name:ita_x_preferred":[
        "Bela"
    ],
    "name:nld_x_preferred":[
        "Bela"
    ],
    "name:pol_x_preferred":[
        "Bela"
    ],
    "name:por_x_preferred":[
        "Bela"
    ],
    "name:slv_x_preferred":[
        "Bela"
    ],
    "name:srp_x_preferred":[
        "\u0411\u0435\u043b\u0430"
    ],
    "name:swe_x_preferred":[
        "Bela"
    ],
    "name:tgl_x_preferred":[
        "Bela"
    ],
    "wof:name":"Bela",
    "wof:placetype":"locality"
},
  "geometry": {"coordinates":[84.43078,25.55707],"type":"Point"}
}