{
  "type": "Feature",
  "properties": {
    "gn:admin1_code":"2",
    "gn:admin2_code":"546.0",
    "gn:asciiname":"Mallavaram",
    "gn:country_code":"IN",
    "gn:dem":23,
    "gn:feature_class":"P",
    "gn:feature_code":"PPL",
    "gn:name":"Mallavaram",
    "gn:population":0,
    "gn:timezone":"Asia/Kolkata",
    "iso:country":"IN",
    "wof:name":"Mallavaram",
    "wof:placetype":"locality"
},
  "geometry": {"coordinates":[81.69938,16.96923],"type":"Point"}
}