{
  "type": "Feature",
  "properties": {
    "gn:admin1_code":"16",
    "gn:admin2_code":"507.0",
    "gn:asciiname":"Banjari",
    "gn:country_code":"IN",
    "gn:dem":426,
    "gn:feature_class":"P",
    "gn:feature_code":"PPL",
    "gn:name":"Banj\u0101r\u012b",
    "gn:population":0,
    "gn:timezone":"Asia/Kolkata",
    "iso:country":"IN",
    "name:tat_x_preferred":[
        "\u0411\u0430\u043d\u0434\u0436\u0430\u0440\u0438"
    ],
    "wof:name":"Banjari",
    "wof:placetype":"locality"
},
  "geometry": {"coordinates":[80.62742,21.27074],"type":"Point"}
}