{
  "type": "Feature",
  "properties": {
    "iso:country":"IN",
    "ks:ks_name":"Belakhand",
    "ks:ks_pop":44,
    "ks:ks_type":"HABITATION",
    "name:eng_x_preferred":[
        "Belakhand"
    ],
    "wof:name":"Belakhand",
    "wof:placetype":"locality",
    "wof:population":44
},
  "geometry": {"coordinates":[74.72865,14.891833],"type":"Point"}
}