{
  "type": "Feature",
  "properties": {
    "gn:admin1_code":"40.0",
    "gn:admin2_code":"532.0",
    "gn:asciiname":"Bhatpalli",
    "gn:country_code":"IN",
    "gn:dem":176,
    "gn:feature_class":"P",
    "gn:feature_code":"PPL",
    "gn:name":"Bhatpalli",
    "gn:population":0,
    "gn:timezone":"Asia/Kolkata",
    "iso:country":"IN",
    "wof:name":"Bhatpalli",
    "wof:placetype":"locality"
},
  "geometry": {"coordinates":[79.50295,19.33451],"type":"Point"}
}