{
  "type": "Feature",
  "properties": {
    "iso:country":"IN",
    "ks:ks_name":"Badirigochha",
    "ks:ks_pop":18,
    "ks:ks_type":"VILLAGE",
    "name:eng_x_preferred":[
        "Badirigochha"
    ],
    "wof:name":"Badirigochha",
    "wof:placetype":"locality",
    "wof:population":18
},
  "geometry": {"coordinates":[84.532095,20.380697],"type":"Point"}
}