{
  "type": "Feature",
  "properties": {
    "iso:country":"IN",
    "ks:ks_name":"Kadvawadi",
    "ks:ks_pop":148,
    "ks:ks_type":"HABITATION",
    "name:eng_x_preferred":[
        "Kadvawadi"
    ],
    "wof:name":"Kadvawadi",
    "wof:placetype":"locality",
    "wof:population":148
},
  "geometry": {"coordinates":[73.615556,17.447222],"type":"Point"}
}