{
  "type": "Feature",
  "properties": {
    "iso:country":"IN",
    "ks:ks_name":"Vallichira",
    "ks:ks_pop":13455,
    "ks:ks_type":"VILLAGE",
    "name:eng_x_preferred":[
        "Vallichira"
    ],
    "wof:name":"Vallichira",
    "wof:placetype":"locality",
    "wof:population":13455
},
  "geometry": {"coordinates":[76.646062,9.748451],"type":"Point"}
}