{
  "type": "Feature",
  "properties": {
    "gn:admin1_code":"16",
    "gn:admin2_code":"530.0",
    "gn:asciiname":"Top",
    "gn:country_code":"IN",
    "gn:dem":599,
    "gn:feature_class":"P",
    "gn:feature_code":"PPL",
    "gn:name":"Top",
    "gn:population":0,
    "gn:timezone":"Asia/Kolkata",
    "iso:country":"IN",
    "wof:name":"Top",
    "wof:placetype":"locality"
},
  "geometry": {"coordinates":[74.28479,16.79055],"type":"Point"}
}