{
  "type": "Feature",
  "properties": {
    "iso:country":"IN",
    "ks:ks_name":"Hatibandha Pam",
    "ks:ks_pop":716,
    "ks:ks_type":"VILLAGE",
    "ks:ks_uagg_main":0,
    "name:eng_x_preferred":[
        "Hatibandha Pam"
    ],
    "wof:name":"Hatibandha Pam",
    "wof:placetype":"locality",
    "wof:population":716
},
  "geometry": {"coordinates":[93.58776,26.857001],"type":"Point"}
}