{
  "type": "Feature",
  "properties": {
    "iso:country":"IN",
    "ks:ks_name":"Domra",
    "ks:ks_pop":543,
    "ks:ks_type":"VILLAGE",
    "name:eng_x_preferred":[
        "Domra"
    ],
    "wof:name":"Domra",
    "wof:placetype":"locality",
    "wof:population":543
},
  "geometry": {"coordinates":[85.75916100000001,22.686575],"type":"Point"}
}