{
  "type": "Feature",
  "properties": {
    "gn:admin1_code":"12",
    "gn:admin2_code":"15.0",
    "gn:asciiname":"Badur",
    "gn:country_code":"IN",
    "gn:dem":1629,
    "gn:feature_class":"P",
    "gn:feature_code":"PPL",
    "gn:name":"Badur",
    "gn:population":0,
    "gn:timezone":"Asia/Kolkata",
    "iso:country":"IN",
    "name:deu_x_preferred":[
        "Badur"
    ],
    "name:nds_x_preferred":[
        "Badur"
    ],
    "name:nld_x_preferred":[
        "Badur"
    ],
    "wof:name":"Badur",
    "wof:placetype":"locality"
},
  "geometry": {"coordinates":[75.03008,33.73652],"type":"Point"}
}