{
  "type": "Feature",
  "properties": {
    "iso:country":"IN",
    "ks:ks_alt_nam":"PURE BASTI",
    "ks:ks_name":"Pure Basti",
    "ks:ks_pop":699,
    "ks:ks_type":"HABITATION",
    "name:eng_x_preferred":[
        "Pure Basti"
    ],
    "wof:name":"Pure Basti",
    "wof:placetype":"locality",
    "wof:population":699
},
  "geometry": {"coordinates":[81.80639499999999,26.360801],"type":"Point"}
}