{
  "type": "Feature",
  "properties": {
    "iso:country":"IN",
    "ks:ks_name":"Tetariya",
    "ks:ks_pop":190,
    "ks:ks_type":"VILLAGE",
    "name:eng_x_preferred":[
        "Tetariya"
    ],
    "wof:name":"Tetariya",
    "wof:placetype":"locality",
    "wof:population":190
},
  "geometry": {"coordinates":[87.380301,24.921612],"type":"Point"}
}