{
  "type": "Feature",
  "properties": {
    "gn:admin1_code":"34.0",
    "gn:admin2_code":"221.0",
    "gn:asciiname":"Udaippur",
    "gn:country_code":"IN",
    "gn:dem":50,
    "gn:feature_class":"P",
    "gn:feature_code":"PPL",
    "gn:name":"Udaippur",
    "gn:population":0,
    "gn:timezone":"Asia/Kolkata",
    "iso:country":"IN",
    "ks:ks_name":"Udaipur",
    "ks:ks_pop":1406,
    "ks:ks_type":"VILLAGE",
    "ks:ks_uagg_main":0,
    "name:eng_x_preferred":[
        "Udaipur"
    ],
    "wof:name":"Udaipur",
    "wof:placetype":"neighbourhood",
    "wof:population":1406
},
  "geometry": {"coordinates":[86.080281,25.730813],"type":"Point"}
}