{
  "type": "Feature",
  "properties": {
    "gn:admin1_code":"2.0",
    "gn:admin2_code":"553.0",
    "gn:asciiname":"Maddipi",
    "gn:country_code":"IN",
    "gn:dem":660,
    "gn:feature_class":"P",
    "gn:feature_code":"PPL",
    "gn:name":"Maddipi",
    "gn:population":0,
    "gn:timezone":"Asia/Kolkata",
    "iso:country":"IN",
    "wof:name":"Maddipi",
    "wof:placetype":"locality"
},
  "geometry": {"coordinates":[77.60184,13.7671],"type":"Point"}
}