{
  "type": "Feature",
  "properties": {
    "iso:country":"IN",
    "ks:ks_alt_nam":"Kan\u0101wada Protected Forest",
    "ks:ks_name":"Kanawada Protected Forest",
    "ks:ks_type":"VILLAGE",
    "name:eng_x_preferred":[
        "Kanawada Protected Forest"
    ],
    "name:eng_x_variant":[
        "Kan\u0101wada Protected Forest"
    ],
    "wof:name":"Kanawada Protected Forest",
    "wof:placetype":"locality"
},
  "geometry": {"coordinates":[77.562101,25.145192],"type":"Point"}
}