{
  "type": "Feature",
  "properties": {
    "iso:country":"IN",
    "ks:ks_name":"Dopere",
    "ks:ks_pop":3314,
    "ks:ks_type":"VILLAGE",
    "ks:ks_uagg_main":0,
    "name:eng_x_preferred":[
        "Dopere"
    ],
    "wof:name":"Dopere",
    "wof:placetype":"locality",
    "wof:population":3314
},
  "geometry": {"coordinates":[88.403735,22.72955],"type":"Point"}
}