{
  "type": "Feature",
  "properties": {
    "iso:country":"IN",
    "ks:ks_alt_nam":"Nagla B\u012brsah\u0101i",
    "ks:ks_name":"Nagla Birsahai",
    "ks:ks_type":"VILLAGE",
    "name:eng_x_preferred":[
        "Nagla Birsahai"
    ],
    "name:eng_x_variant":[
        "Nagla B\u012brsah\u0101i"
    ],
    "wof:name":"Nagla Birsahai",
    "wof:placetype":"locality"
},
  "geometry": {"coordinates":[78.657488,27.441681],"type":"Point"}
}