{
  "type": "Feature",
  "properties": {
    "gn:admin1_code":"16",
    "gn:admin2_code":"502.0",
    "gn:asciiname":"Pimpalgaon Buzurg",
    "gn:country_code":"IN",
    "gn:dem":325,
    "gn:feature_class":"P",
    "gn:feature_code":"PPL",
    "gn:name":"Pimpalgaon Buzurg",
    "gn:population":0,
    "gn:timezone":"Asia/Kolkata",
    "iso:country":"IN",
    "wof:name":"Pimpalgaon Buzurg",
    "wof:placetype":"locality"
},
  "geometry": {"coordinates":[77.56941999999999,20.65982],"type":"Point"}
}