{
  "type": "Feature",
  "properties": {
    "gn:admin1_code":"35",
    "gn:admin2_code":"456.0",
    "gn:asciiname":"Hathigarh",
    "gn:country_code":"IN",
    "gn:dem":362,
    "gn:feature_class":"P",
    "gn:feature_code":"PPL",
    "gn:name":"H\u0101th\u012bgarh",
    "gn:population":0,
    "gn:timezone":"Asia/Kolkata",
    "iso:country":"IN",
    "ks:ks_alt_nam":"H\u0101th\u012bgarh",
    "ks:ks_name":"Hathigarh",
    "ks:ks_pop":110,
    "ks:ks_type":"VILLAGE",
    "name:eng_x_preferred":[
        "Hathigarh"
    ],
    "name:eng_x_variant":[
        "H\u0101th\u012bgarh"
    ],
    "wof:name":"Hathigarh",
    "wof:placetype":"locality",
    "wof:population":110
},
  "geometry": {"coordinates":[79.524359,21.639084],"type":"Point"}
}