{
  "type": "Feature",
  "properties": {
    "iso:country":"IN",
    "ks:ks_alt_nam":"edaiyur kattuthangal",
    "ks:ks_name":"Edaiyur Kattuthangal",
    "ks:ks_pop":257,
    "ks:ks_type":"HABITATION",
    "name:eng_x_preferred":[
        "Edaiyur Kattuthangal"
    ],
    "wof:name":"Edaiyur Kattuthangal",
    "wof:placetype":"locality",
    "wof:population":257
},
  "geometry": {"coordinates":[79.099126,11.94527],"type":"Point"}
}