{
  "type": "Feature",
  "properties": {
    "iso:country":"IN",
    "ks:ks_name":"Deodhai Kopowhuwa",
    "ks:ks_pop":1003,
    "ks:ks_type":"VILLAGE",
    "ks:ks_uagg_main":0,
    "name:eng_x_preferred":[
        "Deodhai Kopowhuwa"
    ],
    "wof:name":"Deodhai Kopowhuwa",
    "wof:placetype":"neighbourhood",
    "wof:population":1003
},
  "geometry": {"coordinates":[95.161182,27.491241],"type":"Point"}
}