{
  "type": "Feature",
  "properties": {
    "iso:country":"IN",
    "ks:ks_name":"Umrapar",
    "ks:ks_pop":0,
    "ks:ks_type":"VILLAGE",
    "name:eng_x_preferred":[
        "Umrapar"
    ],
    "wof:name":"Umrapar",
    "wof:placetype":"locality",
    "wof:population":0
},
  "geometry": {"coordinates":[69.199652,23.442258],"type":"Point"}
}