{
  "type": "Feature",
  "properties": {
    "gn:admin1_code":"36.0",
    "gn:admin2_code":"169.0",
    "gn:asciiname":"Kania",
    "gn:country_code":"IN",
    "gn:dem":175,
    "gn:feature_class":"P",
    "gn:feature_code":"PPL",
    "gn:name":"Kania",
    "gn:population":0,
    "gn:timezone":"Asia/Kolkata",
    "iso:country":"IN",
    "name:ceb_x_preferred":[
        "Kania"
    ],
    "name:ces_x_preferred":[
        "Kania"
    ],
    "name:deu_x_preferred":[
        "Kania"
    ],
    "name:fra_x_preferred":[
        "Kania"
    ],
    "name:ita_x_preferred":[
        "Kania"
    ],
    "name:nld_x_preferred":[
        "Kania"
    ],
    "name:pol_x_preferred":[
        "Kania"
    ],
    "name:rus_x_preferred":[
        "\u041a\u0430\u043d\u044f"
    ],
    "name:swe_x_preferred":[
        "Kania"
    ],
    "name:ukr_x_preferred":[
        "\u041a\u0430\u043d\u044f"
    ],
    "wof:name":"Kania",
    "wof:placetype":"neighbourhood"
},
  "geometry": {"coordinates":[79.49711000000001,25.40165],"type":"Point"}
}