{
  "type": "Feature",
  "properties": {
    "iso:country":"IN",
    "ks:ks_name":"Konnapara",
    "ks:ks_pop":1248,
    "ks:ks_type":"HABITATION",
    "name:eng_x_preferred":[
        "Konnapara"
    ],
    "wof:name":"Konnapara",
    "wof:placetype":"locality",
    "wof:population":1248
},
  "geometry": {"coordinates":[76.864608,9.264512],"type":"Point"}
}