{
  "type": "Feature",
  "properties": {
    "gn:admin1_code":"35.0",
    "gn:admin2_code":"450.0",
    "gn:asciiname":"Jarwahi",
    "gn:country_code":"IN",
    "gn:dem":418,
    "gn:feature_class":"P",
    "gn:feature_code":"PPL",
    "gn:name":"Jarw\u0101hi",
    "gn:population":0,
    "gn:timezone":"Asia/Kolkata",
    "iso:country":"IN",
    "ks:ks_alt_nam":"Jarw\u0101hi",
    "ks:ks_name":"Jarwahi",
    "ks:ks_pop":3109,
    "ks:ks_type":"VILLAGE",
    "name:eng_x_preferred":[
        "Jarwahi"
    ],
    "name:eng_x_variant":[
        "Jarw\u0101hi"
    ],
    "wof:name":"Jarwahi",
    "wof:placetype":"locality",
    "wof:population":3109
},
  "geometry": {"coordinates":[80.34484,23.739385],"type":"Point"}
}