{
  "type": "Feature",
  "properties": {
    "iso:country":"IN",
    "ks:ks_name":"Mankhuna",
    "ks:ks_pop":12,
    "ks:ks_type":"HABITATION",
    "name:eng_x_preferred":[
        "Mankhuna"
    ],
    "wof:name":"Mankhuna",
    "wof:placetype":"locality",
    "wof:population":12
},
  "geometry": {"coordinates":[82.19985800000001,19.434224],"type":"Point"}
}