{
  "type": "Feature",
  "properties": {
    "iso:country":"IN",
    "ks:ks_name":"N.rawri",
    "ks:ks_pop":479,
    "ks:ks_type":"HABITATION",
    "name:eng_x_preferred":[
        "N.rawri"
    ],
    "wof:name":"N.rawri",
    "wof:placetype":"locality",
    "wof:population":479
},
  "geometry": {"coordinates":[78.948779,27.011564],"type":"Point"}
}