{
  "type": "Feature",
  "properties": {
    "gn:admin1_code":"16.0",
    "gn:admin2_code":"521",
    "gn:asciiname":"Giravali",
    "gn:country_code":"IN",
    "gn:dem":693,
    "gn:feature_class":"P",
    "gn:feature_code":"PPL",
    "gn:name":"Giravali",
    "gn:population":0,
    "gn:timezone":"Asia/Kolkata",
    "iso:country":"IN",
    "name:und_x_variant":[
        "Girawali",
        "Giravali"
    ],
    "wof:name":"Giravali",
    "wof:placetype":"locality"
},
  "geometry": {"coordinates":[73.8562,19.0826],"type":"Point"}
}