{
  "type": "Feature",
  "properties": {
    "gn:admin1_code":"36.0",
    "gn:admin2_code":"162",
    "gn:asciiname":"Nawada Mahipat Shah",
    "gn:country_code":"IN",
    "gn:dem":140,
    "gn:feature_class":"P",
    "gn:feature_code":"PPL",
    "gn:name":"Naw\u0101da Mahipat Sh\u0101h",
    "gn:population":0,
    "gn:timezone":"Asia/Kolkata",
    "iso:country":"IN",
    "wof:name":"Nawada Mahipat Shah",
    "wof:placetype":"locality"
},
  "geometry": {"coordinates":[79.3039,26.4688],"type":"Point"}
}