{
  "type": "Feature",
  "properties": {
    "gn:admin1_code":"3.0",
    "gn:admin2_code":"303.0",
    "gn:asciiname":"Bhella",
    "gn:country_code":"IN",
    "gn:dem":44,
    "gn:feature_class":"P",
    "gn:feature_code":"PPL",
    "gn:name":"Bhella",
    "gn:population":0,
    "gn:timezone":"Asia/Kolkata",
    "iso:country":"IN",
    "ks:ks_name":"Bhella",
    "ks:ks_pop":398,
    "ks:ks_type":"VILLAGE",
    "ks:ks_uagg_main":0,
    "name:eng_x_preferred":[
        "Bhella"
    ],
    "wof:name":"Bhella",
    "wof:placetype":"neighbourhood",
    "wof:population":398
},
  "geometry": {"coordinates":[91.072081,26.300705],"type":"Point"}
}