{
  "type": "Feature",
  "properties": {
    "iso:country":"IN",
    "ks:ks_name":"Jagadewadi",
    "ks:ks_pop":55,
    "ks:ks_type":"HABITATION",
    "name:eng_x_preferred":[
        "Jagadewadi"
    ],
    "wof:name":"Jagadewadi",
    "wof:placetype":"locality",
    "wof:population":55
},
  "geometry": {"coordinates":[73.429922,17.832797],"type":"Point"}
}