{
  "type": "Feature",
  "properties": {
    "iso:country":"IN",
    "ks:ks_name":"Musuvinakallu",
    "ks:ks_pop":21,
    "ks:ks_type":"VILLAGE",
    "name:eng_x_preferred":[
        "Musuvinakallu"
    ],
    "wof:name":"Musuvinakallu",
    "wof:placetype":"locality",
    "wof:population":21
},
  "geometry": {"coordinates":[77.232896,13.542888],"type":"Point"}
}