{
  "type": "Feature",
  "properties": {
    "iso:country":"IN",
    "ks:ks_name":"Salampur",
    "ks:ks_pop":5,
    "ks:ks_type":"HABITATION",
    "name:eng_x_preferred":[
        "Salampur"
    ],
    "wof:name":"Salampur",
    "wof:placetype":"locality",
    "wof:population":5
},
  "geometry": {"coordinates":[76.71777,23.437662],"type":"Point"}
}