{
  "type": "Feature",
  "properties": {
    "iso:country":"IN",
    "ks:ks_name":"Itlaicha Dhanagarwada",
    "ks:ks_pop":295,
    "ks:ks_type":"HABITATION",
    "name:eng_x_preferred":[
        "Itlaicha Dhanagarwada"
    ],
    "wof:name":"Itlaicha Dhanagarwada",
    "wof:placetype":"locality",
    "wof:population":295
},
  "geometry": {"coordinates":[73.83720599999999,17.104714],"type":"Point"}
}