{
  "type": "Feature",
  "properties": {
    "iso:country":"IN",
    "ks:ks_name":"Naduthoppur",
    "ks:ks_pop":120,
    "ks:ks_type":"HABITATION",
    "name:eng_x_preferred":[
        "Naduthoppur"
    ],
    "wof:name":"Naduthoppur",
    "wof:placetype":"locality",
    "wof:population":120
},
  "geometry": {"coordinates":[78.08972300000001,10.598858],"type":"Point"}
}