{
  "type": "Feature",
  "properties": {
    "gn:admin1_code":"36.0",
    "gn:admin2_code":"183.0",
    "gn:asciiname":"Chandardip Ghat",
    "gn:country_code":"IN",
    "gn:dem":98,
    "gn:feature_class":"P",
    "gn:feature_code":"PPL",
    "gn:name":"Chandardip Gh\u0101t",
    "gn:population":0,
    "gn:timezone":"Asia/Kolkata",
    "iso:country":"IN",
    "wof:name":"Chandardip Ghat",
    "wof:placetype":"locality"
},
  "geometry": {"coordinates":[82.49800999999999,27.13133],"type":"Point"}
}