{
  "type": "Feature",
  "properties": {
    "gn:admin1_code":"35.0",
    "gn:admin2_code":"436.0",
    "gn:asciiname":"Soyatkalan",
    "gn:country_code":"IN",
    "gn:dem":339,
    "gn:feature_class":"P",
    "gn:feature_code":"PPL",
    "gn:name":"Soyatkalan",
    "gn:population":0,
    "gn:timezone":"Asia/Kolkata",
    "iso:country":"IN",
    "name:ben_x_preferred":[
        "\u09b8\u09cb\u09af\u09bc\u09be\u09a4\u0995\u09be\u09b2\u09be\u09a8"
    ],
    "name:bpy_x_preferred":[
        "\u09b8\u09cb\u09af\u09bc\u09be\u09a4\u0995\u09be\u09b2\u09be\u09a8"
    ],
    "name:ita_x_preferred":[
        "Soyatkalan"
    ],
    "name:mlg_x_preferred":[
        "Soyatkalan"
    ],
    "name:msa_x_preferred":[
        "Soyatkalan"
    ],
    "name:nld_x_preferred":[
        "Soyatkalan"
    ],
    "name:por_x_preferred":[
        "Soyatkalan"
    ],
    "name:vie_x_preferred":[
        "Soyatkalan"
    ],
    "name:zho_x_preferred":[
        "\u7d22\u8036\u7279\u5361\u5170"
    ],
    "wof:name":"Soyatkalan",
    "wof:placetype":"locality"
},
  "geometry": {"coordinates":[76.1778,24.1886],"type":"Point"}
}