{
  "type": "Feature",
  "properties": {
    "iso:country":"IN",
    "ks:ks_alt_nam":"sawaiganj",
    "ks:ks_name":"Sawaiganj",
    "ks:ks_pop":394,
    "ks:ks_type":"HABITATION",
    "name:eng_x_preferred":[
        "Sawaiganj"
    ],
    "wof:name":"Sawaiganj",
    "wof:placetype":"locality",
    "wof:population":394
},
  "geometry": {"coordinates":[76.303901,25.977058],"type":"Point"}
}