{
  "type": "Feature",
  "properties": {
    "iso:country":"IN",
    "ks:ks_alt_nam":"K\u0101nkat\u0101",
    "ks:ks_name":"Kankata",
    "ks:ks_pop":409,
    "ks:ks_type":"VILLAGE",
    "name:eng_x_preferred":[
        "Kankata"
    ],
    "name:eng_x_variant":[
        "K\u0101nkat\u0101"
    ],
    "wof:name":"Kankata",
    "wof:placetype":"locality",
    "wof:population":409
},
  "geometry": {"coordinates":[85.58137000000001,23.276453],"type":"Point"}
}