{
  "type": "Feature",
  "properties": {
    "iso:country":"IN",
    "name:ara_x_preferred":[
        "\u0646\u0627\u062f\u0627\u0643\u0627\u0641\u0648 \u0627\u0644\u0634\u0631\u0642\u064a\u0629"
    ],
    "name:ben_bn_x_preferred":[
        "\u09aa\u09c2\u09b0\u09cd\u09ac \u09a8\u09be\u09a6\u09be\u0995\u09cd\u0995\u09be\u09ad\u09c1"
    ],
    "name:ben_in_x_preferred":[
        "\u09aa\u09c2\u09b0\u09cd\u09ac \u09a8\u09be\u09a6\u09be\u0995\u09cd\u0995\u09be\u09ad\u09c1"
    ],
    "name:eng_x_preferred":[
        "Nadakkavu"
    ],
    "name:guj_x_preferred":[
        "\u0aaa\u0ac2\u0ab0\u0acd\u0ab5 \u0aa8\u0abe\u0aa1\u0abe\u0a95\u0acd\u0a95\u0abe\u0ab5\u0ac1"
    ],
    "name:hin_x_preferred":[
        "\u092a\u0942\u0930\u094d\u0935 \u0928\u093e\u0926\u093e\u0915\u094d\u0915\u093e\u0935\u0941"
    ],
    "name:kan_x_preferred":[
        "\u0c88\u0cb8\u0ccd\u0c9f\u0ccd"
    ],
    "name:mal_x_preferred":[
        "\u0d15\u0d3f\u0d34\u0d15\u0d4d\u0d15\u0d7b \u0d28\u0d3e\u0d1f\u0d3e\u0d15\u0d4d\u0d15\u0d3e\u0d35\u0d4d"
    ],
    "name:mal_x_variant":[
        "\u0d28\u0d1f\u0d15\u0d4d\u0d15\u0d3e\u0d35\u0d4d"
    ],
    "name:mar_x_preferred":[
        "\u092a\u0942\u0930\u094d\u0935 \u0928\u093e\u0926\u0915\u094d\u0915\u0935\u0941"
    ],
    "name:pan_x_preferred":[
        "\u0a08\u0a38\u0a1f \u0a28\u0a3e\u0a26\u0a3e\u0a15\u0a3e\u0a35\u0a42"
    ],
    "name:tam_x_preferred":[
        "\u0b95\u0bbf\u0bb4\u0b95\u0bcd\u0b95\u0bc1 \u0ba8\u0b9f\u0b95\u0bcd\u0b95\u0bbe\u0bb5\u0bc1"
    ],
    "name:tel_x_preferred":[
        "\u0c08\u0c38\u0c4d\u0c1f\u0c4d \u0c28\u0c21\u0c15\u0c4d\u0c15\u0c35\u0c41"
    ],
    "name:urd_x_preferred":[
        "\u0645\u0634\u0631\u0642\u06cc \u0646\u0627\u062f\u0627\u06a9\u0651\u0627\u0648\u0631"
    ],
    "qs:name":"East Nadakkavu",
    "qs:name_adm0":"India",
    "qs:name_adm1":"Kerala",
    "qs:photos":18,
    "qs:photos_1k":4,
    "qs:photos_9k":1,
    "qs:photos_9r":1,
    "qs:photos_all":18,
    "qs:photos_sr":1,
    "qs:placetype":"Suburb",
    "qs:pop_sr":"0",
    "wd:wordcount":234,
    "wof:name":"East Nadakkavu",
    "wof:placetype":"neighbourhood"
},
  "geometry": {"coordinates":[75.773702,11.277707],"type":"Point"}
}