{
  "type": "Feature",
  "properties": {
    "iso:country":"IN",
    "name:eng_x_preferred":[
        "Nadakkavu"
    ],
    "qs:name":"East Nadakkavu",
    "qs:name_adm0":"India",
    "qs:name_adm1":"Kerala",
    "qs:photos":18,
    "qs:photos_1k":4,
    "qs:photos_9k":1,
    "qs:photos_9r":1,
    "qs:photos_all":18,
    "qs:photos_sr":1,
    "qs:placetype":"Suburb",
    "qs:pop_sr":"0",
    "wd:wordcount":234,
    "wof:name":"East Nadakkavu",
    "wof:placetype":"neighbourhood"
},
  "geometry": {"coordinates":[75.773702,11.2777065],"type":"Point"}
}