{
  "type": "Feature",
  "properties": {
    "gn:admin1_code":"16.0",
    "gn:admin2_code":"507.0",
    "gn:asciiname":"Dalli",
    "gn:country_code":"IN",
    "gn:dem":293,
    "gn:feature_class":"P",
    "gn:feature_code":"PPL",
    "gn:name":"Dall\u012b",
    "gn:population":0,
    "gn:timezone":"Asia/Kolkata",
    "iso:country":"IN",
    "name:deu_x_preferred":[
        "Dalli"
    ],
    "name:ita_x_preferred":[
        "Dalli"
    ],
    "wof:name":"Dalli",
    "wof:placetype":"locality"
},
  "geometry": {"coordinates":[80.22389,21.09316],"type":"Point"}
}