{
  "type": "Feature",
  "properties": {
    "gn:admin1_code":"25",
    "gn:admin2_code":"628.0",
    "gn:asciiname":"Vijayapati",
    "gn:country_code":"IN",
    "gn:dem":9,
    "gn:feature_class":"P",
    "gn:feature_code":"PPL",
    "gn:name":"Vijay\u0101pati",
    "gn:population":0,
    "gn:timezone":"Asia/Kolkata",
    "iso:country":"IN",
    "wof:name":"Vijayapati",
    "wof:placetype":"locality"
},
  "geometry": {"coordinates":[77.74762,8.19135],"type":"Point"}
}