{
  "type": "Feature",
  "properties": {
    "iso:country":"IN",
    "ks:ks_name":"Sonu Pod",
    "ks:ks_pop":261,
    "ks:ks_type":"HABITATION",
    "name:eng_x_preferred":[
        "Sonu Pod"
    ],
    "wof:name":"Sonu Pod",
    "wof:placetype":"locality",
    "wof:population":261
},
  "geometry": {"coordinates":[78.69199399999999,20.086134],"type":"Point"}
}