{
  "type": "Feature",
  "properties": {
    "iso:country":"IN",
    "ks:ks_name":"Ganeshkhorwadi",
    "ks:ks_pop":337,
    "ks:ks_type":"HABITATION",
    "name:eng_x_preferred":[
        "Ganeshkhorwadi"
    ],
    "wof:name":"Ganeshkhorwadi",
    "wof:placetype":"locality",
    "wof:population":337
},
  "geometry": {"coordinates":[73.707222,16.859722],"type":"Point"}
}