{
  "type": "Feature",
  "properties": {
    "gn:admin1_code":"36",
    "gn:admin2_code":"201.0",
    "gn:asciiname":"Pabra",
    "gn:country_code":"IN",
    "gn:dem":175,
    "gn:feature_class":"P",
    "gn:feature_code":"PPL",
    "gn:name":"Pabra",
    "gn:population":0,
    "gn:timezone":"Asia/Kolkata",
    "iso:country":"IN",
    "name:est_x_preferred":[
        "Pabra j\u00e4rv"
    ],
    "name:fin_x_preferred":[
        "Pabra j\u00e4rv"
    ],
    "name:ita_x_preferred":[
        "Pabra"
    ],
    "name:rus_x_preferred":[
        "\u0411\u043e\u0431\u0440\u043e\u0432\u0441\u043a\u043e\u0435 \u043e\u0437\u0435\u0440\u043e"
    ],
    "name:zho_x_preferred":[
        "\u5e15\u5e03\u62c9\u6e56"
    ],
    "wof:name":"Pabra",
    "wof:placetype":"locality"
},
  "geometry": {"coordinates":[78.22915,27.50296],"type":"Point"}
}