{
  "type": "Feature",
  "properties": {
    "iso:country":"IN",
    "ks:ks_name":"Uzan Donka",
    "ks:ks_pop":295,
    "ks:ks_type":"HABITATION",
    "name:eng_x_preferred":[
        "Uzan Donka"
    ],
    "wof:name":"Uzan Donka",
    "wof:placetype":"locality",
    "wof:population":295
},
  "geometry": {"coordinates":[92.60430100000001,25.93908],"type":"Point"}
}