{
  "type": "Feature",
  "properties": {
    "gn:country":"IN",
    "gn:fcode":"PPL",
    "gn:population":12415,
    "iso:country":"IN",
    "name:bpy_x_preferred":[
        "\u09b8\u09be\u09af\u09bc\u09be\u09b2\u0997\u09c1\u09a1\u09bc\u09bf"
    ],
    "name:ceb_x_preferred":[
        "S\u0101yalkudi"
    ],
    "name:eng_x_preferred":[
        "Sayalgudi"
    ],
    "name:fra_x_preferred":[
        "Sayalgudi"
    ],
    "name:hin_x_preferred":[
        "\u0938\u093e\u092f\u0932\u0917\u0941\u0921\u093c\u0940"
    ],
    "name:ita_x_preferred":[
        "Sayalgudi"
    ],
    "name:msa_x_preferred":[
        "Sayalgudi"
    ],
    "name:nan_x_preferred":[
        "Sayalgudi"
    ],
    "name:nld_x_preferred":[
        "Sayalgudi"
    ],
    "name:por_x_preferred":[
        "Sayalgudi"
    ],
    "name:spa_x_preferred":[
        "Sayalgudi"
    ],
    "name:swe_x_preferred":[
        "S\u0101yalkudi"
    ],
    "name:tam_x_preferred":[
        "\u0b9a\u0bbe\u0baf\u0bb2\u0bcd\u0b95\u0bc1\u0b9f\u0bbf"
    ],
    "name:vie_x_preferred":[
        "Sayalgudi"
    ],
    "name:zho_x_preferred":[
        "\u8428\u8036\u5c14\u53e4\u8fea"
    ],
    "qs:name":"S\u0101yalkudi",
    "qs:photos_9r":0,
    "qs:photos_sr":0,
    "qs:pop_sr":"6",
    "wof:name":"S\u0101yalkudi",
    "wof:placetype":"locality",
    "wof:population":12415
},
  "geometry": {"coordinates":[78.44708,9.16931],"type":"Point"}
}