{
  "type": "Feature",
  "properties": {
    "iso:country":"IN",
    "ks:ks_name":"Silaiyaneri",
    "ks:ks_type":"VILLAGE",
    "ks:ks_uagg_main":0,
    "name:eng_x_preferred":[
        "Silaiyaneri"
    ],
    "wof:name":"Silaiyaneri",
    "wof:placetype":"neighbourhood"
},
  "geometry": {"coordinates":[78.106527,9.961569],"type":"Point"}
}