{
  "type": "Feature",
  "properties": {
    "gn:admin1_code":"34.0",
    "gn:admin2_code":"230.0",
    "gn:asciiname":"Hasanpura",
    "gn:country_code":"IN",
    "gn:dem":63,
    "gn:feature_class":"P",
    "gn:feature_code":"PPL",
    "gn:name":"Hasanpura",
    "gn:population":0,
    "gn:timezone":"Asia/Kolkata",
    "iso:country":"IN",
    "name:bih_x_preferred":[
        "\u0939\u0938\u0928\u092a\u0941\u0930\u093e"
    ],
    "name:hin_x_preferred":[
        "\u0939\u0938\u0928\u092a\u0941\u0930 \u092a\u094d\u0930\u0916\u0923\u094d\u0921"
    ],
    "wof:name":"Hasanpura",
    "wof:placetype":"locality"
},
  "geometry": {"coordinates":[85.04838000000002,25.32095],"type":"Point"}
}