{
  "type": "Feature",
  "properties": {
    "iso:country":"IN",
    "ks:ks_name":"Ganjhudih",
    "ks:ks_pop":183,
    "ks:ks_type":"HABITATION",
    "name:eng_x_preferred":[
        "Ganjhudih"
    ],
    "wof:name":"Ganjhudih",
    "wof:placetype":"locality",
    "wof:population":183
},
  "geometry": {"coordinates":[85.52339499999999,24.229899],"type":"Point"}
}