{
  "type": "Feature",
  "properties": {
    "gn:admin1_code":"34.0",
    "gn:admin2_code":"229.0",
    "gn:asciiname":"Chandasi",
    "gn:country_code":"IN",
    "gn:dem":58,
    "gn:feature_class":"P",
    "gn:feature_code":"PPL",
    "gn:name":"Chand\u0101si",
    "gn:population":0,
    "gn:timezone":"Asia/Kolkata",
    "iso:country":"IN",
    "ks:ks_alt_nam":"Chand\u0101si",
    "ks:ks_name":"Chandasi",
    "ks:ks_pop":2510,
    "ks:ks_type":"VILLAGE",
    "ks:ks_uagg_main":0,
    "name:eng_x_preferred":[
        "Chandasi"
    ],
    "name:eng_x_variant":[
        "Chand\u0101si"
    ],
    "wof:name":"Chandasi",
    "wof:placetype":"neighbourhood",
    "wof:population":2510
},
  "geometry": {"coordinates":[85.466092,25.267961],"type":"Point"}
}