{
  "type": "Feature",
  "properties": {
    "iso:country":"IN",
    "ks:ks_name":"Tambemala",
    "ks:ks_pop":281,
    "ks:ks_type":"HABITATION",
    "name:eng_x_preferred":[
        "Tambemala"
    ],
    "wof:name":"Tambemala",
    "wof:placetype":"locality",
    "wof:population":281
},
  "geometry": {"coordinates":[74.872663,18.862156],"type":"Point"}
}