{
  "type": "Feature",
  "properties": {
    "iso:country":"IN",
    "ks:ks_name":"Kalur",
    "ks:ks_pop":135,
    "ks:ks_type":"HABITATION",
    "name:eng_x_preferred":[
        "Kalur"
    ],
    "wof:name":"Kalur",
    "wof:placetype":"locality",
    "wof:population":135
},
  "geometry": {"coordinates":[74.819069,14.357778],"type":"Point"}
}