{
  "type": "Feature",
  "properties": {
    "iso:country":"IN",
    "ks:ks_name":"Halugondanahalli",
    "ks:ks_pop":200,
    "ks:ks_type":"VILLAGE",
    "name:eng_x_preferred":[
        "Halugondanahalli"
    ],
    "wof:name":"Halugondanahalli",
    "wof:placetype":"locality",
    "wof:population":200
},
  "geometry": {"coordinates":[76.77007,13.253248],"type":"Point"}
}