{
  "type": "Feature",
  "properties": {
    "iso:country":"IN",
    "ks:ks_name":"Malwadi",
    "ks:ks_pop":300,
    "ks:ks_type":"HABITATION",
    "name:eng_x_preferred":[
        "Malwadi"
    ],
    "wof:name":"Malwadi",
    "wof:placetype":"locality",
    "wof:population":300
},
  "geometry": {"coordinates":[74.49142399999999,18.833497],"type":"Point"}
}