{
  "type": "Feature",
  "properties": {
    "iso:country":"IN",
    "ks:ks_alt_nam":"SARWAN OUR",
    "ks:ks_name":"Sarwan Our",
    "ks:ks_pop":287,
    "ks:ks_type":"HABITATION",
    "name:eng_x_preferred":[
        "Sarwan Our"
    ],
    "wof:name":"Sarwan Our",
    "wof:placetype":"locality",
    "wof:population":287
},
  "geometry": {"coordinates":[81.818659,26.140978],"type":"Point"}
}