{
  "type": "Feature",
  "properties": {
    "iso:country":"IN",
    "ks:ks_name":"Dhobi Tola",
    "ks:ks_pop":146,
    "ks:ks_type":"HABITATION",
    "name:eng_x_preferred":[
        "Dhobi Tola"
    ],
    "wof:name":"Dhobi Tola",
    "wof:placetype":"locality",
    "wof:population":146
},
  "geometry": {"coordinates":[83.516823,24.144304],"type":"Point"}
}