{
  "type": "Feature",
  "properties": {
    "iso:country":"IN",
    "ks:ks_name":"Useta",
    "ks:ks_pop":974,
    "ks:ks_type":"VILLAGE",
    "name:eng_x_preferred":[
        "Useta"
    ],
    "wof:name":"Useta",
    "wof:placetype":"locality",
    "wof:population":974
},
  "geometry": {"coordinates":[79.112543,28.250092],"type":"Point"}
}