{
  "type": "Feature",
  "properties": {
    "iso:country":"IN",
    "ks:ks_name":"Inamatiwasti",
    "ks:ks_pop":283,
    "ks:ks_type":"HABITATION",
    "name:eng_x_preferred":[
        "Inamatiwasti"
    ],
    "wof:name":"Inamatiwasti",
    "wof:placetype":"locality",
    "wof:population":283
},
  "geometry": {"coordinates":[74.15760899999999,19.035925],"type":"Point"}
}