{
  "type": "Feature",
  "properties": {
    "gn:admin1_code":"23.0",
    "gn:admin2_code":"41.0",
    "gn:asciiname":"Shahbazpur",
    "gn:country_code":"IN",
    "gn:dem":255,
    "gn:feature_class":"P",
    "gn:feature_code":"PPL",
    "gn:name":"Sh\u0101hb\u0101zpur",
    "gn:population":0,
    "gn:timezone":"Asia/Kolkata",
    "iso:country":"IN",
    "wof:name":"Shahbazpur",
    "wof:placetype":"locality"
},
  "geometry": {"coordinates":[76.22024999999999,30.94535],"type":"Point"}
}