{
  "type": "Feature",
  "properties": {
    "iso:country":"IN",
    "ks:ks_name":"Hebbanale",
    "ks:ks_pop":31,
    "ks:ks_type":"HABITATION",
    "name:eng_x_preferred":[
        "Hebbanale"
    ],
    "wof:name":"Hebbanale",
    "wof:placetype":"locality",
    "wof:population":31
},
  "geometry": {"coordinates":[74.71663100000001,14.001637],"type":"Point"}
}