{
  "type": "Feature",
  "properties": {
    "iso:country":"IN",
    "ks:ks_name":"Rajyadharpur",
    "ks:ks_pop":1516,
    "ks:ks_type":"VILLAGE",
    "name:eng_x_preferred":[
        "Rajyadharpur"
    ],
    "wof:name":"Rajyadharpur",
    "wof:placetype":"locality",
    "wof:population":1516
},
  "geometry": {"coordinates":[87.58646400000001,23.978969],"type":"Point"}
}