{
  "type": "Feature",
  "properties": {
    "iso:country":"IN",
    "ks:ks_name":"Longsoo",
    "ks:ks_pop":1218,
    "ks:ks_type":"HABITATION",
    "name:eng_x_preferred":[
        "Longsoo"
    ],
    "wof:name":"Longsoo",
    "wof:placetype":"locality",
    "wof:population":1218
},
  "geometry": {"coordinates":[95.065337,27.46573],"type":"Point"}
}