{
  "type": "Feature",
  "properties": {
    "iso:country":"IN",
    "ks:ks_name":"Kadahari",
    "ks:ks_pop":700,
    "ks:ks_type":"HABITATION",
    "name:eng_x_preferred":[
        "Kadahari"
    ],
    "wof:name":"Kadahari",
    "wof:placetype":"locality",
    "wof:population":700
},
  "geometry": {"coordinates":[81.774283,26.046275],"type":"Point"}
}