{
  "type": "Feature",
  "properties": {
    "iso:country":"IN",
    "ks:ks_alt_nam":"BIN TOLA",
    "ks:ks_name":"Bin Tola",
    "ks:ks_pop":74,
    "ks:ks_type":"HABITATION",
    "ks:ks_uagg_main":0,
    "name:eng_x_preferred":[
        "Bin Tola"
    ],
    "wof:name":"Bin Tola",
    "wof:placetype":"neighbourhood",
    "wof:population":74
},
  "geometry": {"coordinates":[84.76816700000001,26.280354],"type":"Point"}
}