{
  "type": "Feature",
  "properties": {
    "iso:country":"IN",
    "ks:ks_name":"Badiyanpurwa",
    "ks:ks_pop":82,
    "ks:ks_type":"HABITATION",
    "name:eng_x_preferred":[
        "Badiyanpurwa"
    ],
    "wof:name":"Badiyanpurwa",
    "wof:placetype":"locality",
    "wof:population":82
},
  "geometry": {"coordinates":[80.960936,28.006827],"type":"Point"}
}