{
  "type": "Feature",
  "properties": {
    "iso:country":"IN",
    "ks:ks_name":"Singimari",
    "ks:ks_pop":590,
    "ks:ks_type":"HABITATION",
    "name:eng_x_preferred":[
        "Singimari"
    ],
    "wof:name":"Singimari",
    "wof:placetype":"locality",
    "wof:population":590
},
  "geometry": {"coordinates":[91.14194999999999,26.55684],"type":"Point"}
}