{
  "type": "Feature",
  "properties": {
    "iso:country":"IN",
    "ks:ks_name":"East Halahali",
    "ks:ks_pop":372,
    "ks:ks_type":"HABITATION",
    "name:eng_x_preferred":[
        "East Halahali"
    ],
    "wof:name":"East Halahali",
    "wof:placetype":"locality",
    "wof:population":372
},
  "geometry": {"coordinates":[91.822952,24.097778],"type":"Point"}
}