{
  "type": "Feature",
  "properties": {
    "iso:country":"IN",
    "ks:ks_name":"Oorvani",
    "ks:ks_pop":1086,
    "ks:ks_type":"HABITATION",
    "name:eng_x_preferred":[
        "Oorvani"
    ],
    "wof:name":"Oorvani",
    "wof:placetype":"locality",
    "wof:population":1086
},
  "geometry": {"coordinates":[79.000865,10.14514],"type":"Point"}
}