{
  "type": "Feature",
  "properties": {
    "gn:admin1_code":"11",
    "gn:admin2_code":"24.0",
    "gn:asciiname":"Rajot Uparla",
    "gn:country_code":"IN",
    "gn:dem":959,
    "gn:feature_class":"P",
    "gn:feature_code":"PPL",
    "gn:name":"Rajot Uparla",
    "gn:population":0,
    "gn:timezone":"Asia/Kolkata",
    "iso:country":"IN",
    "wof:name":"Rajot Uparla",
    "wof:placetype":"locality"
},
  "geometry": {"coordinates":[76.59293000000002,32.03624],"type":"Point"}
}