{
  "type": "Feature",
  "properties": {
    "iso:country":"IN",
    "ks:ks_name":"Dadijigi",
    "ks:ks_pop":35,
    "ks:ks_type":"HABITATION",
    "name:eng_x_preferred":[
        "Dadijigi"
    ],
    "wof:name":"Dadijigi",
    "wof:placetype":"locality",
    "wof:population":35
},
  "geometry": {"coordinates":[84.083125,19.423812],"type":"Point"}
}