{
  "type": "Feature",
  "properties": {
    "iso:country":"IN",
    "ks:ks_name":"Middle Tola Dhamna",
    "ks:ks_pop":288,
    "ks:ks_type":"HABITATION",
    "name:eng_x_preferred":[
        "Middle Tola Dhamna"
    ],
    "wof:name":"Middle Tola Dhamna",
    "wof:placetype":"locality",
    "wof:population":288
},
  "geometry": {"coordinates":[86.482788,24.860337],"type":"Point"}
}