{
  "type": "Feature",
  "properties": {
    "gn:admin1_code":"16",
    "gn:admin2_code":"520.0",
    "gn:asciiname":"Parhur",
    "gn:country_code":"IN",
    "gn:dem":35,
    "gn:feature_class":"P",
    "gn:feature_code":"PPL",
    "gn:name":"Parhur",
    "gn:population":0,
    "gn:timezone":"Asia/Kolkata",
    "iso:country":"IN",
    "name:und_x_variant":[
        "Parh\u016br",
        "Parhur"
    ],
    "wof:name":"Parhur",
    "wof:placetype":"locality"
},
  "geometry": {"coordinates":[72.9187,18.70954],"type":"Point"}
}