{
  "type": "Feature",
  "properties": {
    "iso:country":"IN",
    "ks:ks_name":"Sevariyapura",
    "ks:ks_pop":651,
    "ks:ks_type":"HABITATION",
    "name:eng_x_preferred":[
        "Sevariyapura"
    ],
    "wof:name":"Sevariyapura",
    "wof:placetype":"locality",
    "wof:population":651
},
  "geometry": {"coordinates":[72.767056,22.5705],"type":"Point"}
}