{
  "type": "Feature",
  "properties": {
    "iso:country":"IN",
    "ks:ks_alt_nam":"prabhatkeri",
    "ks:ks_name":"Prabhatkeri",
    "ks:ks_pop":72,
    "ks:ks_type":"HABITATION",
    "name:eng_x_preferred":[
        "Prabhatkeri"
    ],
    "wof:name":"Prabhatkeri",
    "wof:placetype":"locality",
    "wof:population":72
},
  "geometry": {"coordinates":[74.52993600000001,14.246505],"type":"Point"}
}