{
  "type": "Feature",
  "properties": {
    "iso:country":"IN",
    "ks:ks_name":"Sonkhlasari",
    "ks:ks_pop":101,
    "ks:ks_type":"HABITATION",
    "name:eng_x_preferred":[
        "Sonkhlasari"
    ],
    "wof:name":"Sonkhlasari",
    "wof:placetype":"locality",
    "wof:population":101
},
  "geometry": {"coordinates":[70.79533600000001,23.541403],"type":"Point"}
}