{
  "type": "Feature",
  "properties": {
    "iso:country":"IN",
    "ks:ks_name":"Jagesar Kanwara",
    "ks:ks_pop":0,
    "ks:ks_type":"VILLAGE",
    "name:eng_x_preferred":[
        "Jagesar Kanwara"
    ],
    "wof:name":"Jagesar Kanwara",
    "wof:placetype":"locality",
    "wof:population":0
},
  "geometry": {"coordinates":[85.809926,24.760234],"type":"Point"}
}