{
  "type": "Feature",
  "properties": {
    "iso:country":"IN",
    "ks:ks_alt_nam":"ALLA PURWA",
    "ks:ks_name":"Alla Purwa",
    "ks:ks_pop":389,
    "ks:ks_type":"HABITATION",
    "ks:ks_uagg_main":0,
    "name:eng_x_preferred":[
        "Alla Purwa"
    ],
    "wof:name":"Alla Purwa",
    "wof:placetype":"locality",
    "wof:population":389
},
  "geometry": {"coordinates":[81.62729299999999,27.572183],"type":"Point"}
}