{
  "type": "Feature",
  "properties": {
    "gn:admin1_code":"24.0",
    "gn:admin2_code":"128.0",
    "gn:asciiname":"Ahmadpura",
    "gn:country_code":"IN",
    "gn:dem":393,
    "gn:feature_class":"P",
    "gn:feature_code":"PPL",
    "gn:name":"Ahmadpura",
    "gn:population":0,
    "gn:timezone":"Asia/Kolkata",
    "iso:country":"IN",
    "ks:ks_name":"Ahamadpura",
    "ks:ks_pop":603,
    "ks:ks_type":"VILLAGE",
    "name:eng_x_preferred":[
        "Ahamadpura"
    ],
    "name:eng_x_variant":[
        "Ahmadpura"
    ],
    "wof:name":"Ahamadpura",
    "wof:placetype":"locality",
    "wof:population":603
},
  "geometry": {"coordinates":[76.98572900000001,24.58497],"type":"Point"}
}