{
  "type": "Feature",
  "properties": {
    "gn:admin1_code":"35.0",
    "gn:admin2_code":"425",
    "gn:asciiname":"Bachhaun",
    "gn:country_code":"IN",
    "gn:dem":187,
    "gn:feature_class":"P",
    "gn:feature_code":"PPL",
    "gn:name":"Bachhaun",
    "gn:population":0,
    "gn:timezone":"Asia/Kolkata",
    "iso:country":"IN",
    "name:und_x_variant":[
        "Bachhion",
        "Bachhon",
        "Bachhaun"
    ],
    "wof:name":"Bachhaun",
    "wof:placetype":"locality"
},
  "geometry": {"coordinates":[80.10176,24.98562],"type":"Point"}
}