{
  "type": "Feature",
  "properties": {
    "iso:country":"IN",
    "ks:ks_name":"Ghodmarg",
    "ks:ks_pop":370,
    "ks:ks_type":"HABITATION",
    "name:eng_x_preferred":[
        "Ghodmarg"
    ],
    "wof:name":"Ghodmarg",
    "wof:placetype":"locality",
    "wof:population":370
},
  "geometry": {"coordinates":[74.284066,21.688603],"type":"Point"}
}