{
  "type": "Feature",
  "properties": {
    "gn:admin1_code":"21.0",
    "gn:admin2_code":"396.0",
    "gn:asciiname":"Pongini",
    "gn:country_code":"IN",
    "gn:dem":513,
    "gn:feature_class":"P",
    "gn:feature_code":"PPL",
    "gn:name":"Pongini",
    "gn:population":0,
    "gn:timezone":"Asia/Kolkata",
    "iso:country":"IN",
    "name:cat_x_preferred":[
        "Ponginis"
    ],
    "name:eus_x_preferred":[
        "Pongini"
    ],
    "name:nld_x_preferred":[
        "Pongini"
    ],
    "name:spa_x_preferred":[
        "Pongini"
    ],
    "wof:name":"Pongini",
    "wof:placetype":"locality"
},
  "geometry": {"coordinates":[83.62073000000002,19.45909],"type":"Point"}
}