{
  "type": "Feature",
  "properties": {
    "iso:country":"IN",
    "ks:ks_name":"Jarlodipara",
    "ks:ks_pop":170,
    "ks:ks_type":"HABITATION",
    "name:eng_x_preferred":[
        "Jarlodipara"
    ],
    "wof:name":"Jarlodipara",
    "wof:placetype":"locality",
    "wof:population":170
},
  "geometry": {"coordinates":[81.596209,18.48012],"type":"Point"}
}