{
  "type": "Feature",
  "properties": {
    "gn:admin1_code":"10.0",
    "gn:admin2_code":"87.0",
    "gn:asciiname":"Patkhori",
    "gn:country_code":"IN",
    "gn:dem":227,
    "gn:feature_class":"P",
    "gn:feature_code":"PPL",
    "gn:name":"P\u0101tkhori",
    "gn:population":0,
    "gn:timezone":"Asia/Kolkata",
    "iso:country":"IN",
    "wof:name":"Patkhori",
    "wof:placetype":"locality"
},
  "geometry": {"coordinates":[76.9195,27.73851],"type":"Point"}
}