{
  "type": "Feature",
  "properties": {
    "iso:country":"IN",
    "ks:ks_name":"Kashipara",
    "ks:ks_pop":1346,
    "ks:ks_type":"VILLAGE",
    "name:eng_x_preferred":[
        "Kashipara"
    ],
    "wof:name":"Kashipara",
    "wof:placetype":"locality",
    "wof:population":1346
},
  "geometry": {"coordinates":[88.01466499999999,25.32771],"type":"Point"}
}