{
  "type": "Feature",
  "properties": {
    "gn:admin1_code":"16.0",
    "gn:admin2_code":"509.0",
    "gn:asciiname":"Gwalaheti",
    "gn:country_code":"IN",
    "gn:dem":207,
    "gn:feature_class":"P",
    "gn:feature_code":"PPL",
    "gn:name":"Gw\u0101l\u0101het\u012b",
    "gn:population":0,
    "gn:timezone":"Asia/Kolkata",
    "iso:country":"IN",
    "wof:name":"Gwalaheti",
    "wof:placetype":"locality"
},
  "geometry": {"coordinates":[79.68091,20.19011],"type":"Point"}
}