{
  "type": "Feature",
  "properties": {
    "iso:country":"IN",
    "ks:ks_name":"Matia",
    "ks:ks_pop":190,
    "ks:ks_type":"VILLAGE",
    "name:eng_x_preferred":[
        "Matia"
    ],
    "wof:name":"Matia",
    "wof:placetype":"locality",
    "wof:population":190
},
  "geometry": {"coordinates":[82.212755,24.150786],"type":"Point"}
}