{
  "type": "Feature",
  "properties": {
    "iso:country":"IN",
    "ks:ks_name":"Kosala R.F.",
    "ks:ks_pop":2,
    "ks:ks_type":"VILLAGE",
    "name:eng_x_preferred":[
        "Kosala R.F."
    ],
    "wof:name":"Kosala R.F.",
    "wof:placetype":"locality",
    "wof:population":2
},
  "geometry": {"coordinates":[84.90737300000001,21.014195],"type":"Point"}
}