{
  "type": "Feature",
  "properties": {
    "gn:admin1_code":"37.0",
    "gn:admin2_code":"404",
    "gn:asciiname":"Kartala",
    "gn:country_code":"IN",
    "gn:dem":313,
    "gn:feature_class":"P",
    "gn:feature_code":"PPL",
    "gn:name":"Kartala",
    "gn:population":0,
    "gn:timezone":"Asia/Kolkata",
    "iso:country":"IN",
    "name:und_x_variant":[
        "Kartala-Chak",
        "Kartala"
    ],
    "wof:name":"Kartala",
    "wof:placetype":"locality"
},
  "geometry": {"coordinates":[82.95784999999999,22.30102],"type":"Point"}
}