{
  "type": "Feature",
  "properties": {
    "gn:admin1_code":"37.0",
    "gn:admin2_code":"404",
    "gn:asciiname":"Kartala",
    "gn:country_code":"IN",
    "gn:dem":313,
    "gn:feature_class":"P",
    "gn:feature_code":"PPL",
    "gn:name":"Kartala",
    "gn:population":0,
    "gn:timezone":"Asia/Kolkata",
    "iso:country":"IN",
    "name:ara_x_preferred":[
        "\u0643\u0627\u0631\u062a\u0627\u0644\u0627"
    ],
    "name:ben_x_preferred":[
        "\u0995\u09be\u09b0\u09a4\u09be\u09b2\u09be"
    ],
    "name:deu_x_preferred":[
        "Kartala"
    ],
    "name:ell_x_preferred":[
        "\u039a\u03b1\u03c1\u03c4\u03ac\u03bb\u03b1"
    ],
    "name:eng_x_preferred":[
        "Kartala"
    ],
    "name:fas_x_preferred":[
        "\u06a9\u0627\u0631\u0627\u062a\u0627\u0644\u0627"
    ],
    "name:fra_x_preferred":[
        "Kartala"
    ],
    "name:heb_x_preferred":[
        "\u05e7\u05e8\u05d8\u05dc\u05d4"
    ],
    "name:hin_x_preferred":[
        "\u0915\u0930\u0924\u093e\u0932"
    ],
    "name:hun_x_preferred":[
        "Kartala"
    ],
    "name:ind_x_preferred":[
        "Kartala"
    ],
    "name:ita_x_preferred":[
        "Kartala"
    ],
    "name:jpn_x_preferred":[
        "\u30ab\u30eb\u30bf\u30e9\u5c71"
    ],
    "name:kor_x_preferred":[
        "\uce74\ub974\ud0c8\ub77c"
    ],
    "name:nld_x_preferred":[
        "Kartala"
    ],
    "name:pol_x_preferred":[
        "Kartala"
    ],
    "name:por_x_preferred":[
        "Kartala"
    ],
    "name:rus_x_preferred":[
        "\u0433\u043e\u0440\u0430 \u041a\u0430\u0440\u0442\u0430\u043b\u0430"
    ],
    "name:spa_x_preferred":[
        "Kartala"
    ],
    "name:swe_x_preferred":[
        "Kartala"
    ],
    "name:tur_x_preferred":[
        "Kartala"
    ],
    "name:ukr_x_preferred":[
        "\u041a\u0430\u0440\u0442\u0430\u043b\u0430"
    ],
    "name:und_x_variant":[
        "Kartala-Chak",
        "Kartala"
    ],
    "name:urd_x_preferred":[
        "\u06a9\u0627\u0631\u062a\u0627\u0644\u06c1"
    ],
    "name:vie_x_preferred":[
        "N\u00fai Kartala"
    ],
    "name:zho_cn_x_preferred":[
        "\u5361\u5c14\u5854\u62c9\u706b\u5c71"
    ],
    "name:zho_tw_x_preferred":[
        "\u5361\u5854\u62c9\u5c71"
    ],
    "wof:name":"Kartala",
    "wof:placetype":"locality"
},
  "geometry": {"coordinates":[82.95784999999999,22.30102],"type":"Point"}
}