{
  "type": "Feature",
  "properties": {
    "iso:country":"IN",
    "ks:ks_name":"Mahmwapur",
    "ks:ks_pop":1210,
    "ks:ks_type":"HABITATION",
    "ks:ks_uagg_main":0,
    "name:eng_x_preferred":[
        "Mahmwapur"
    ],
    "wof:name":"Mahmwapur",
    "wof:placetype":"neighbourhood",
    "wof:population":1210
},
  "geometry": {"coordinates":[83.722002,27.396179],"type":"Point"}
}