{
  "type": "Feature",
  "properties": {
    "iso:country":"IN",
    "ks:ks_name":"Purunia",
    "ks:ks_pop":1187,
    "ks:ks_type":"VILLAGE",
    "ks:ks_uagg_main":0,
    "name:eng_x_preferred":[
        "Purunia"
    ],
    "wof:name":"Purunia",
    "wof:placetype":"neighbourhood",
    "wof:population":1187
},
  "geometry": {"coordinates":[88.189483,23.389614],"type":"Point"}
}