{
  "type": "Feature",
  "properties": {
    "iso:country":"IN",
    "ks:ks_name":"Lekhra",
    "ks:ks_pop":554,
    "ks:ks_type":"HABITATION",
    "name:eng_x_preferred":[
        "Lekhra"
    ],
    "wof:name":"Lekhra",
    "wof:placetype":"locality",
    "wof:population":554
},
  "geometry": {"coordinates":[74.48667,21.946165],"type":"Point"}
}