{
  "type": "Feature",
  "properties": {
    "gn:admin1_code":"40.0",
    "gn:admin2_code":"541.0",
    "gn:asciiname":"Perur",
    "gn:country_code":"IN",
    "gn:dem":99,
    "gn:feature_class":"P",
    "gn:feature_code":"PPL",
    "gn:name":"Per\u016br",
    "gn:population":0,
    "gn:timezone":"Asia/Kolkata",
    "iso:country":"IN",
    "name:bpy_x_preferred":[
        "\u09aa\u09c7\u09b0\u09c1\u09b0"
    ],
    "name:ceb_x_preferred":[
        "Per\u016br"
    ],
    "name:ita_x_preferred":[
        "Perur"
    ],
    "name:msa_x_preferred":[
        "Perur"
    ],
    "name:nld_x_preferred":[
        "Perur"
    ],
    "name:por_x_preferred":[
        "Perur"
    ],
    "name:swe_x_preferred":[
        "Per\u016br"
    ],
    "name:tam_x_preferred":[
        "\u0baa\u0bc7\u0bb0\u0bc2\u0bb0\u0bcd"
    ],
    "name:vie_x_preferred":[
        "Perur"
    ],
    "name:zho_x_preferred":[
        "\u4f69\u9c81\u5c14"
    ],
    "wof:name":"Perur",
    "wof:placetype":"locality"
},
  "geometry": {"coordinates":[80.39766999999998,18.53125],"type":"Point"}
}