{
  "type": "Feature",
  "properties": {
    "iso:country":"IN",
    "ks:ks_name":"Tubulbhadu",
    "ks:ks_pop":139,
    "ks:ks_type":"VILLAGE",
    "name:eng_x_preferred":[
        "Tubulbhadu"
    ],
    "wof:name":"Tubulbhadu",
    "wof:placetype":"locality",
    "wof:population":139
},
  "geometry": {"coordinates":[86.782623,22.103355],"type":"Point"}
}