{
  "type": "Feature",
  "properties": {
    "iso:country":"IN",
    "ks:ks_name":"Ambeth Nagar",
    "ks:ks_pop":279,
    "ks:ks_type":"HABITATION",
    "ks:ks_uagg_main":0,
    "name:eng_x_preferred":[
        "Ambeth Nagar"
    ],
    "wof:name":"Ambeth Nagar",
    "wof:placetype":"neighbourhood",
    "wof:population":279
},
  "geometry": {"coordinates":[77.531238,9.464725],"type":"Point"}
}