{
  "type": "Feature",
  "properties": {
    "iso:country":"IN",
    "ks:ks_name":"Deoria Bandh",
    "ks:ks_pop":56,
    "ks:ks_type":"HABITATION",
    "ks:ks_uagg_main":0,
    "name:eng_x_preferred":[
        "Deoria Bandh"
    ],
    "wof:name":"Deoria Bandh",
    "wof:placetype":"neighbourhood",
    "wof:population":56
},
  "geometry": {"coordinates":[83.542525,25.504427],"type":"Point"}
}