{
  "type": "Feature",
  "properties": {
    "gn:admin1_code":"19.0",
    "gn:admin2_code":"568.0",
    "gn:asciiname":"Nagarbhavi",
    "gn:country_code":"IN",
    "gn:dem":663,
    "gn:feature_class":"P",
    "gn:feature_code":"PPL",
    "gn:name":"Nagarbh\u0101vi",
    "gn:population":0,
    "gn:timezone":"Asia/Kolkata",
    "iso:country":"IN",
    "ks:ks_name":"Nagarabavi",
    "ks:ks_pop":52,
    "ks:ks_type":"VILLAGE",
    "name:eng_x_preferred":[
        "Nagarabavi"
    ],
    "name:eng_x_variant":[
        "Nagarbhavi"
    ],
    "wof:name":"Nagarabavi",
    "wof:placetype":"locality",
    "wof:population":52
},
  "geometry": {"coordinates":[75.455153,14.029325],"type":"Point"}
}