{
  "type": "Feature",
  "properties": {
    "gn:admin1_code":"19.0",
    "gn:admin2_code":"568.0",
    "gn:asciiname":"Nagarbhavi",
    "gn:country_code":"IN",
    "gn:dem":663,
    "gn:feature_class":"P",
    "gn:feature_code":"PPL",
    "gn:name":"Nagarbh\u0101vi",
    "gn:population":0,
    "gn:timezone":"Asia/Kolkata",
    "iso:country":"IN",
    "wof:name":"Nagarbhavi",
    "wof:placetype":"locality"
},
  "geometry": {"coordinates":[75.45518,14.02914],"type":"Point"}
}