{
  "type": "Feature",
  "properties": {
    "iso:country":"IN",
    "ks:ks_alt_nam":"RAMOV KI PAYU",
    "ks:ks_name":"Ramov Ki Payu",
    "ks:ks_pop":100,
    "ks:ks_type":"HABITATION",
    "name:eng_x_preferred":[
        "Ramov Ki Payu"
    ],
    "wof:name":"Ramov Ki Payu",
    "wof:placetype":"locality",
    "wof:population":100
},
  "geometry": {"coordinates":[71.102272,25.525289],"type":"Point"}
}