{
  "type": "Feature",
  "properties": {
    "iso:country":"IN",
    "ks:ks_alt_nam":"BHASKO",
    "ks:ks_name":"Bhasko",
    "ks:ks_pop":154,
    "ks:ks_type":"HABITATION",
    "name:eng_x_preferred":[
        "Bhasko"
    ],
    "wof:name":"Bhasko",
    "wof:placetype":"locality",
    "wof:population":154
},
  "geometry": {"coordinates":[81.913195,22.559712],"type":"Point"}
}