{
  "type": "Feature",
  "properties": {
    "gn:admin1_code":"36",
    "gn:admin2_code":"160.0",
    "gn:asciiname":"Mahsona Purwa",
    "gn:country_code":"IN",
    "gn:dem":146,
    "gn:feature_class":"P",
    "gn:feature_code":"PPL",
    "gn:name":"Mahsona Purwa",
    "gn:population":0,
    "gn:timezone":"Asia/Kolkata",
    "iso:country":"IN",
    "name:und_x_variant":[
        "Majra Tirmukha"
    ],
    "wof:name":"Mahsona Purwa",
    "wof:placetype":"neighbourhood"
},
  "geometry": {"coordinates":[79.76123,26.91069],"type":"Point"}
}