{
  "type": "Feature",
  "properties": {
    "iso:country":"IN",
    "ks:ks_name":"Harva Pachor",
    "ks:ks_pop":671,
    "ks:ks_type":"VILLAGE",
    "name:eng_x_preferred":[
        "Harva Pachor"
    ],
    "wof:name":"Harva Pachor",
    "wof:placetype":"locality",
    "wof:population":671
},
  "geometry": {"coordinates":[73.85113200000001,23.686614],"type":"Point"}
}