{
  "type": "Feature",
  "properties": {
    "iso:country":"IN",
    "ks:ks_name":"Kander",
    "ks:ks_pop":483,
    "ks:ks_type":"VILLAGE",
    "name:eng_x_preferred":[
        "Kander"
    ],
    "wof:name":"Kander",
    "wof:placetype":"locality",
    "wof:population":483
},
  "geometry": {"coordinates":[85.39473099999999,22.889846],"type":"Point"}
}