{
  "type": "Feature",
  "properties": {
    "gn:admin1_code":"35.0",
    "gn:admin2_code":"451.0",
    "gn:asciiname":"Mandubar",
    "gn:country_code":"IN",
    "gn:dem":391,
    "gn:feature_class":"P",
    "gn:feature_code":"PPL",
    "gn:name":"Mand\u016bbar",
    "gn:population":0,
    "gn:timezone":"Asia/Kolkata",
    "iso:country":"IN",
    "wof:name":"Mandubar",
    "wof:placetype":"locality"
},
  "geometry": {"coordinates":[80.15425999999999,23.41082],"type":"Point"}
}