{
  "type": "Feature",
  "properties": {
    "gn:admin1_code":"19.0",
    "gn:admin2_code":"573.0",
    "gn:asciiname":"Settinayakanakoppal",
    "gn:country_code":"IN",
    "gn:dem":831,
    "gn:feature_class":"P",
    "gn:feature_code":"PPL",
    "gn:name":"Settin\u0101yakanakoppal",
    "gn:population":0,
    "gn:timezone":"Asia/Kolkata",
    "iso:country":"IN",
    "wof:name":"Settinayakanakoppal",
    "wof:placetype":"locality"
},
  "geometry": {"coordinates":[76.5274,12.70466],"type":"Point"}
}