{
  "type": "Feature",
  "properties": {
    "iso:country":"IN",
    "ks:ks_alt_nam":"Jara Sal F.V. 3",
    "ks:ks_name":"Jara Sal F.v. 3",
    "ks:ks_pop":20,
    "ks:ks_type":"HABITATION",
    "name:eng_x_preferred":[
        "Jara Sal F.v. 3"
    ],
    "wof:name":"Jara Sal F.v. 3",
    "wof:placetype":"locality",
    "wof:population":20
},
  "geometry": {"coordinates":[91.516177,25.98448],"type":"Point"}
}