{
  "type": "Feature",
  "properties": {
    "gn:admin1_code":"36.0",
    "gn:admin2_code":"135.0",
    "gn:asciiname":"Mohendarnagar",
    "gn:country_code":"IN",
    "gn:dem":227,
    "gn:feature_class":"P",
    "gn:feature_code":"PPL",
    "gn:name":"Mohendarnagar",
    "gn:population":0,
    "gn:timezone":"Asia/Kolkata",
    "iso:country":"IN",
    "ks:ks_name":"Mohendarnagar",
    "ks:ks_type":"VILLAGE",
    "name:eng_x_preferred":[
        "Mohendarnagar"
    ],
    "wof:name":"Mohendarnagar",
    "wof:placetype":"locality"
},
  "geometry": {"coordinates":[78.72857399999999,29.271318],"type":"Point"}
}