{
  "type": "Feature",
  "properties": {
    "iso:country":"IN",
    "ks:ks_name":"Koliposi",
    "ks:ks_pop":1087,
    "ks:ks_type":"VILLAGE",
    "ks:ks_uagg_main":0,
    "name:eng_x_preferred":[
        "Koliposi"
    ],
    "wof:name":"Koliposi",
    "wof:placetype":"neighbourhood",
    "wof:population":1087
},
  "geometry": {"coordinates":[86.048024,21.758258],"type":"Point"}
}