{
  "type": "Feature",
  "properties": {
    "iso:country":"IN",
    "ks:ks_name":"J. Awwal",
    "ks:ks_pop":214,
    "ks:ks_type":"HABITATION",
    "name:eng_x_preferred":[
        "J. Awwal"
    ],
    "wof:name":"J. Awwal",
    "wof:placetype":"locality",
    "wof:population":214
},
  "geometry": {"coordinates":[83.160793,26.708098],"type":"Point"}
}