{
  "type": "Feature",
  "properties": {
    "gn:admin1_code":"39.0",
    "gn:admin2_code":"59.0",
    "gn:asciiname":"Nakurchi",
    "gn:country_code":"IN",
    "gn:dem":1567,
    "gn:feature_class":"P",
    "gn:feature_code":"PPL",
    "gn:name":"Nakurchi",
    "gn:population":0,
    "gn:timezone":"Asia/Kolkata",
    "iso:country":"IN",
    "wof:name":"Nakurchi",
    "wof:placetype":"locality"
},
  "geometry": {"coordinates":[78.24218,30.4519],"type":"Point"}
}