{
  "type": "Feature",
  "properties": {
    "iso:country":"IN",
    "ks:ks_alt_nam":"B.Village",
    "ks:ks_name":"B.village",
    "ks:ks_pop":37,
    "ks:ks_type":"HABITATION",
    "name:eng_x_preferred":[
        "B.village"
    ],
    "wof:name":"B.village",
    "wof:placetype":"locality",
    "wof:population":37
},
  "geometry": {"coordinates":[75.7475,12.237778],"type":"Point"}
}