{
  "type": "Feature",
  "properties": {
    "iso:country":"IN",
    "ks:ks_name":"Valliyadappuppara",
    "ks:ks_pop":3008,
    "ks:ks_type":"HABITATION",
    "name:eng_x_preferred":[
        "Valliyadappuppara"
    ],
    "wof:name":"Valliyadappuppara",
    "wof:placetype":"locality",
    "wof:population":3008
},
  "geometry": {"coordinates":[77.008832,8.742211],"type":"Point"}
}