{
  "type": "Feature",
  "properties": {
    "gn:admin1_code":"35",
    "gn:admin2_code":"455.0",
    "gn:asciiname":"Barelipar",
    "gn:country_code":"IN",
    "gn:dem":497,
    "gn:feature_class":"P",
    "gn:feature_code":"PPL",
    "gn:name":"Barel\u012bp\u0101r",
    "gn:population":0,
    "gn:timezone":"Asia/Kolkata",
    "iso:country":"IN",
    "ks:ks_name":"Birolipar",
    "ks:ks_pop":332,
    "ks:ks_type":"VILLAGE",
    "name:eng_x_preferred":[
        "Birolipar"
    ],
    "name:eng_x_variant":[
        "Barelipar"
    ],
    "wof:name":"Birolipar",
    "wof:placetype":"locality",
    "wof:population":332
},
  "geometry": {"coordinates":[78.644189,21.738368],"type":"Point"}
}