{
  "type": "Feature",
  "properties": {
    "iso:country":"IN",
    "ks:ks_name":"Bharrya",
    "ks:ks_pop":144,
    "ks:ks_type":"HABITATION",
    "name:eng_x_preferred":[
        "Bharrya"
    ],
    "wof:name":"Bharrya",
    "wof:placetype":"locality",
    "wof:population":144
},
  "geometry": {"coordinates":[78.60768299999999,25.017691],"type":"Point"}
}