{
  "type": "Feature",
  "properties": {
    "gn:admin1_code":"36.0",
    "gn:admin2_code":"180.0",
    "gn:asciiname":"Birahimpur Bhilaura",
    "gn:country_code":"IN",
    "gn:dem":111,
    "gn:feature_class":"P",
    "gn:feature_code":"PPL",
    "gn:name":"Bir\u0101h\u012bmpur Bhilaura",
    "gn:population":0,
    "gn:timezone":"Asia/Kolkata",
    "iso:country":"IN",
    "wof:name":"Birahimpur Bhilaura",
    "wof:placetype":"locality"
},
  "geometry": {"coordinates":[81.62805,27.22259],"type":"Point"}
}