{
  "type": "Feature",
  "properties": {
    "iso:country":"IN",
    "ks:ks_name":"Manaksar",
    "ks:ks_pop":39,
    "ks:ks_type":"VILLAGE",
    "name:eng_x_preferred":[
        "Manaksar"
    ],
    "wof:name":"Manaksar",
    "wof:placetype":"locality",
    "wof:population":39
},
  "geometry": {"coordinates":[73.544239,27.732408],"type":"Point"}
}