{
  "type": "Feature",
  "properties": {
    "iso:country":"IN",
    "ks:ks_name":"Mansurpur",
    "ks:ks_pop":1528,
    "ks:ks_type":"VILLAGE",
    "name:eng_x_preferred":[
        "Mansurpur"
    ],
    "wof:name":"Mansurpur",
    "wof:placetype":"locality",
    "wof:population":1528
},
  "geometry": {"coordinates":[85.184798,26.213475],"type":"Point"}
}