{
  "type": "Feature",
  "properties": {
    "iso:country":"IN",
    "ks:ks_name":"Ramjiguda",
    "ks:ks_pop":117,
    "ks:ks_type":"HABITATION",
    "name:eng_x_preferred":[
        "Ramjiguda"
    ],
    "wof:name":"Ramjiguda",
    "wof:placetype":"locality",
    "wof:population":117
},
  "geometry": {"coordinates":[78.52929399999999,19.537845],"type":"Point"}
}