{
  "type": "Feature",
  "properties": {
    "iso:country":"IN",
    "ks:ks_name":"Sujapur",
    "ks:ks_pop":510,
    "ks:ks_type":"VILLAGE",
    "ks:ks_uagg_main":0,
    "name:eng_x_preferred":[
        "Sujapur"
    ],
    "wof:name":"Sujapur",
    "wof:placetype":"neighbourhood",
    "wof:population":510
},
  "geometry": {"coordinates":[88.221098,23.975062],"type":"Point"}
}