{
  "type": "Feature",
  "properties": {
    "gn:admin1_code":"36",
    "gn:admin2_code":"132.0",
    "gn:asciiname":"Muhammadpur Chhadhara",
    "gn:country_code":"IN",
    "gn:dem":345,
    "gn:feature_class":"P",
    "gn:feature_code":"PPL",
    "gn:name":"Muhammadpur Chh\u0101dhara",
    "gn:population":0,
    "gn:timezone":"Asia/Kolkata",
    "iso:country":"IN",
    "wof:name":"Muhammadpur Chhadhara",
    "wof:placetype":"neighbourhood"
},
  "geometry": {"coordinates":[77.66108,30.24705],"type":"Point"}
}