{
  "type": "Feature",
  "properties": {
    "iso:country":"IN",
    "ks:ks_name":"Narharpur",
    "ks:ks_pop":1136,
    "ks:ks_type":"VILLAGE",
    "ks:ks_uagg_main":0,
    "name:eng_x_preferred":[
        "Narharpur"
    ],
    "wof:name":"Narharpur",
    "wof:placetype":"neighbourhood",
    "wof:population":1136
},
  "geometry": {"coordinates":[80.699083,27.737572],"type":"Point"}
}