{
  "type": "Feature",
  "properties": {
    "iso:country":"IN",
    "ks:ks_name":"Manipura",
    "ks:ks_pop":45,
    "ks:ks_type":"HABITATION",
    "name:eng_x_preferred":[
        "Manipura"
    ],
    "wof:name":"Manipura",
    "wof:placetype":"locality",
    "wof:population":45
},
  "geometry": {"coordinates":[76.843339,13.392425],"type":"Point"}
}