{
  "type": "Feature",
  "properties": {
    "iso:country":"IN",
    "ks:ks_name":"Baldega",
    "ks:ks_pop":1135,
    "ks:ks_type":"VILLAGE",
    "name:eng_x_preferred":[
        "Baldega"
    ],
    "wof:name":"Baldega",
    "wof:placetype":"locality",
    "wof:population":1135
},
  "geometry": {"coordinates":[84.759601,22.568675],"type":"Point"}
}