{
  "type": "Feature",
  "properties": {
    "iso:country":"IN",
    "ks:ks_name":"Valvapur",
    "ks:ks_pop":322,
    "ks:ks_type":"HABITATION",
    "name:eng_x_preferred":[
        "Valvapur"
    ],
    "wof:name":"Valvapur",
    "wof:placetype":"locality",
    "wof:population":322
},
  "geometry": {"coordinates":[78.476283,17.904998],"type":"Point"}
}