{
  "type": "Feature",
  "properties": {
    "gn:admin1_code":"19.0",
    "gn:admin2_code":"563.0",
    "gn:asciiname":"Hadlur",
    "gn:country_code":"IN",
    "gn:dem":56,
    "gn:feature_class":"P",
    "gn:feature_code":"PPL",
    "gn:name":"Hadl\u016br",
    "gn:population":0,
    "gn:timezone":"Asia/Kolkata",
    "iso:country":"IN",
    "ks:ks_alt_nam":"Hadl\u016br",
    "ks:ks_name":"Hadlur",
    "ks:ks_pop":222,
    "ks:ks_type":"VILLAGE",
    "name:eng_x_preferred":[
        "Hadlur"
    ],
    "name:eng_x_variant":[
        "Hadl\u016br"
    ],
    "wof:name":"Hadlur",
    "wof:placetype":"locality",
    "wof:population":222
},
  "geometry": {"coordinates":[74.615809,13.979792],"type":"Point"}
}