{
  "type": "Feature",
  "properties": {
    "iso:country":"IN",
    "ks:ks_name":"Gokulpura",
    "ks:ks_pop":614,
    "ks:ks_type":"HABITATION",
    "name:eng_x_preferred":[
        "Gokulpura"
    ],
    "wof:name":"Gokulpura",
    "wof:placetype":"locality",
    "wof:population":614
},
  "geometry": {"coordinates":[75.492385,26.951884],"type":"Point"}
}