{
  "type": "Feature",
  "properties": {
    "iso:country":"IN",
    "ks:ks_alt_nam":"BANGRA",
    "ks:ks_name":"Bangra",
    "ks:ks_pop":650,
    "ks:ks_type":"HABITATION",
    "ks:ks_uagg_main":0,
    "name:eng_x_preferred":[
        "Bangra"
    ],
    "wof:name":"Bangra",
    "wof:placetype":"neighbourhood",
    "wof:population":650
},
  "geometry": {"coordinates":[84.684333,25.955308],"type":"Point"}
}