{
  "type": "Feature",
  "properties": {
    "iso:country":"IN",
    "ks:ks_name":"Lataura Dabka Khoda",
    "ks:ks_pop":300,
    "ks:ks_type":"HABITATION",
    "name:eng_x_preferred":[
        "Lataura Dabka Khoda"
    ],
    "wof:name":"Lataura Dabka Khoda",
    "wof:placetype":"locality",
    "wof:population":300
},
  "geometry": {"coordinates":[79.72881700000001,25.506185],"type":"Point"}
}