{
  "type": "Feature",
  "properties": {
    "iso:country":"IN",
    "ks:ks_name":"Devlijal",
    "ks:ks_pop":335,
    "ks:ks_type":"HABITATION",
    "name:eng_x_preferred":[
        "Devlijal"
    ],
    "wof:name":"Devlijal",
    "wof:placetype":"locality",
    "wof:population":335
},
  "geometry": {"coordinates":[72.600309,27.387979],"type":"Point"}
}