{
  "type": "Feature",
  "properties": {
    "iso:country":"IN",
    "ks:ks_name":"Dilalpurwadi",
    "ks:ks_pop":690,
    "ks:ks_type":"HABITATION",
    "name:eng_x_preferred":[
        "Dilalpurwadi"
    ],
    "wof:name":"Dilalpurwadi",
    "wof:placetype":"locality",
    "wof:population":690
},
  "geometry": {"coordinates":[74.45492900000001,16.514286],"type":"Point"}
}