{
  "type": "Feature",
  "properties": {
    "iso:country":"IN",
    "ks:ks_name":"Pattamangalam",
    "ks:ks_pop":182,
    "ks:ks_type":"HABITATION",
    "name:eng_x_preferred":[
        "Pattamangalam"
    ],
    "wof:name":"Pattamangalam",
    "wof:placetype":"locality",
    "wof:population":182
},
  "geometry": {"coordinates":[79.064499,9.967761],"type":"Point"}
}