{
  "type": "Feature",
  "properties": {
    "iso:country":"IN",
    "ks:ks_name":"S Gollahalli",
    "ks:ks_pop":592,
    "ks:ks_type":"HABITATION",
    "ks:ks_uagg_main":0,
    "name:eng_x_preferred":[
        "S Gollahalli"
    ],
    "wof:name":"S Gollahalli",
    "wof:placetype":"neighbourhood",
    "wof:population":592
},
  "geometry": {"coordinates":[77.362494,12.894745],"type":"Point"}
}