{
  "type": "Feature",
  "properties": {
    "iso:country":"IN",
    "ks:ks_alt_nam":"Mochi tola",
    "ks:ks_name":"Mochi Tola",
    "ks:ks_pop":99,
    "ks:ks_type":"HABITATION",
    "name:eng_x_preferred":[
        "Mochi Tola"
    ],
    "wof:name":"Mochi Tola",
    "wof:placetype":"locality",
    "wof:population":99
},
  "geometry": {"coordinates":[86.41909,25.94527],"type":"Point"}
}