{
  "type": "Feature",
  "properties": {
    "iso:country":"IN",
    "ks:ks_name":"Poonkudikadu",
    "ks:ks_pop":211,
    "ks:ks_type":"HABITATION",
    "name:eng_x_preferred":[
        "Poonkudikadu"
    ],
    "wof:name":"Poonkudikadu",
    "wof:placetype":"locality",
    "wof:population":211
},
  "geometry": {"coordinates":[79.280359,10.303905],"type":"Point"}
}