{
  "type": "Feature",
  "properties": {
    "iso:country":"IN",
    "ks:ks_name":"Chheprapara",
    "ks:ks_pop":148,
    "ks:ks_type":"HABITATION",
    "name:eng_x_preferred":[
        "Chheprapara"
    ],
    "wof:name":"Chheprapara",
    "wof:placetype":"locality",
    "wof:population":148
},
  "geometry": {"coordinates":[81.656193,19.817329],"type":"Point"}
}