{
  "type": "Feature",
  "properties": {
    "gn:admin1_code":"37",
    "gn:admin2_code":"402.0",
    "gn:asciiname":"Tapkora",
    "gn:country_code":"IN",
    "gn:dem":369,
    "gn:feature_class":"P",
    "gn:feature_code":"PPL",
    "gn:name":"Tapkora",
    "gn:population":0,
    "gn:timezone":"Asia/Kolkata",
    "iso:country":"IN",
    "name:und_x_variant":[
        "Tapkara",
        "Tapkora"
    ],
    "wof:name":"Tapkora",
    "wof:placetype":"locality"
},
  "geometry": {"coordinates":[83.95005,22.50449],"type":"Point"}
}