{
  "type": "Feature",
  "properties": {
    "gn:admin1_code":"35",
    "gn:admin2_code":"427.0",
    "gn:asciiname":"Simaria",
    "gn:country_code":"IN",
    "gn:dem":492,
    "gn:feature_class":"P",
    "gn:feature_code":"PPL",
    "gn:name":"Simaria",
    "gn:population":0,
    "gn:timezone":"Asia/Kolkata",
    "iso:country":"IN",
    "wof:name":"Simaria",
    "wof:placetype":"locality"
},
  "geometry": {"coordinates":[78.8937,23.92289],"type":"Point"}
}