{
  "type": "Feature",
  "properties": {
    "iso:country":"IN",
    "ks:ks_name":"Piparjoria",
    "ks:ks_pop":141,
    "ks:ks_type":"VILLAGE",
    "name:eng_x_preferred":[
        "Piparjoria"
    ],
    "wof:name":"Piparjoria",
    "wof:placetype":"locality",
    "wof:population":141
},
  "geometry": {"coordinates":[87.445605,24.797968],"type":"Point"}
}