{
  "type": "Feature",
  "properties": {
    "iso:country":"IN",
    "ks:ks_name":"Baraitoli Pt IV",
    "ks:ks_pop":273,
    "ks:ks_type":"VILLAGE",
    "name:eng_x_preferred":[
        "Baraitoli Pt IV"
    ],
    "wof:name":"Baraitoli Pt IV",
    "wof:placetype":"locality",
    "wof:population":273
},
  "geometry": {"coordinates":[92.552857,24.921288],"type":"Point"}
}