{
  "type": "Feature",
  "properties": {
    "iso:country":"IN",
    "ks:ks_alt_nam":"shakti dahi",
    "ks:ks_name":"Shakti Dahi",
    "ks:ks_pop":138,
    "ks:ks_type":"HABITATION",
    "name:eng_x_preferred":[
        "Shakti Dahi"
    ],
    "wof:name":"Shakti Dahi",
    "wof:placetype":"locality",
    "wof:population":138
},
  "geometry": {"coordinates":[82.004411,24.965579],"type":"Point"}
}