{
  "type": "Feature",
  "properties": {
    "iso:country":"IN",
    "ks:ks_alt_nam":"Padmapur II",
    "ks:ks_name":"Padmapur Ii",
    "ks:ks_pop":30,
    "ks:ks_type":"HABITATION",
    "name:eng_x_preferred":[
        "Padmapur Ii"
    ],
    "wof:name":"Padmapur Ii",
    "wof:placetype":"locality",
    "wof:population":30
},
  "geometry": {"coordinates":[84.457004,19.265439],"type":"Point"}
}