{
  "type": "Feature",
  "properties": {
    "iso:country":"IN",
    "ks:ks_name":"Chapadihi",
    "ks:ks_pop":154,
    "ks:ks_type":"HABITATION",
    "name:eng_x_preferred":[
        "Chapadihi"
    ],
    "wof:name":"Chapadihi",
    "wof:placetype":"locality",
    "wof:population":154
},
  "geometry": {"coordinates":[86.512259,22.005727],"type":"Point"}
}