{
  "type": "Feature",
  "properties": {
    "gn:admin1_code":"39",
    "gn:admin2_code":"61.0",
    "gn:asciiname":"Kamleshwar",
    "gn:country_code":"IN",
    "gn:dem":544,
    "gn:feature_class":"P",
    "gn:feature_code":"PPL",
    "gn:name":"Kamleshwar",
    "gn:population":0,
    "gn:timezone":"Asia/Kolkata",
    "iso:country":"IN",
    "name:hin_x_preferred":[
        "\u0915\u092e\u0932\u0947\u0936\u094d\u0935\u0930"
    ],
    "name:nor_x_preferred":[
        "Kamleshwar"
    ],
    "name:pan_x_preferred":[
        "\u0a15\u0a2e\u0a32\u0a47\u0a38\u0a3c\u0a35\u0a30"
    ],
    "name:san_x_preferred":[
        "\u0915\u092e\u0932\u0947\u0936\u094d\u0935\u0930\u0903"
    ],
    "name:ukr_x_preferred":[
        "\u041a\u0430\u043c\u0430\u043b\u0435\u0448\u0432\u0430\u0440"
    ],
    "name:urd_x_preferred":[
        "\u06a9\u0645\u0644\u06cc\u0634\u0648\u0631"
    ],
    "wof:name":"Kamleshwar",
    "wof:placetype":"locality"
},
  "geometry": {"coordinates":[78.77967,30.22374000000001],"type":"Point"}
}