{
  "type": "Feature",
  "properties": {
    "iso:country":"IN",
    "ks:ks_alt_nam":"Ar\u0101zi Patharha",
    "ks:ks_name":"Arazi Patharha",
    "ks:ks_type":"VILLAGE",
    "name:eng_x_preferred":[
        "Arazi Patharha"
    ],
    "name:eng_x_variant":[
        "Ar\u0101zi Patharha"
    ],
    "wof:name":"Arazi Patharha",
    "wof:placetype":"locality"
},
  "geometry": {"coordinates":[82.30230299999999,25.043524],"type":"Point"}
}