{
  "type": "Feature",
  "properties": {
    "iso:country":"IN",
    "ks:ks_name":"Dhurwatola",
    "ks:ks_pop":71,
    "ks:ks_type":"HABITATION",
    "name:eng_x_preferred":[
        "Dhurwatola"
    ],
    "wof:name":"Dhurwatola",
    "wof:placetype":"locality",
    "wof:population":71
},
  "geometry": {"coordinates":[80.571268,20.624082],"type":"Point"}
}