{
  "type": "Feature",
  "properties": {
    "iso:country":"IN",
    "ks:ks_alt_nam":"Chandabila-I",
    "ks:ks_name":"Chandabila-i",
    "ks:ks_pop":523,
    "ks:ks_type":"HABITATION",
    "ks:ks_uagg_main":0,
    "name:eng_x_preferred":[
        "Chandabila-i"
    ],
    "wof:name":"Chandabila-i",
    "wof:placetype":"neighbourhood",
    "wof:population":523
},
  "geometry": {"coordinates":[87.212784,22.603355],"type":"Point"}
}