{
  "type": "Feature",
  "properties": {
    "gn:admin1_code":"34.0",
    "gn:admin2_code":"220.0",
    "gn:asciiname":"Sirsa Biran",
    "gn:country_code":"IN",
    "gn:dem":59,
    "gn:feature_class":"P",
    "gn:feature_code":"PPL",
    "gn:name":"Sirsa Biran",
    "gn:population":0,
    "gn:timezone":"Asia/Kolkata",
    "iso:country":"IN",
    "wof:name":"Sirsa Biran",
    "wof:placetype":"locality"
},
  "geometry": {"coordinates":[85.22683000000001,25.8483],"type":"Point"}
}