{
  "type": "Feature",
  "properties": {
    "gn:admin1_code":"34.0",
    "gn:admin2_code":"220.0",
    "gn:asciiname":"Sirsa Biran",
    "gn:country_code":"IN",
    "gn:dem":59,
    "gn:feature_class":"P",
    "gn:feature_code":"PPL",
    "gn:name":"Sirsa Biran",
    "gn:population":0,
    "gn:timezone":"Asia/Kolkata",
    "iso:country":"IN",
    "ks:ks_name":"Sirsa Biran",
    "ks:ks_pop":4787,
    "ks:ks_type":"VILLAGE",
    "name:eng_x_preferred":[
        "Sirsa Biran"
    ],
    "wof:name":"Sirsa Biran",
    "wof:placetype":"locality",
    "wof:population":4787
},
  "geometry": {"coordinates":[85.226831,25.848305],"type":"Point"}
}