{
  "type": "Feature",
  "properties": {
    "gn:admin1_code":"40",
    "gn:admin2_code":"535.0",
    "gn:asciiname":"Tudkapalli",
    "gn:country_code":"IN",
    "gn:dem":518,
    "gn:feature_class":"P",
    "gn:feature_code":"PPL",
    "gn:name":"Tudkapalli",
    "gn:population":0,
    "gn:timezone":"Asia/Kolkata",
    "iso:country":"IN",
    "wof:name":"Tudkapalli",
    "wof:placetype":"locality"
},
  "geometry": {"coordinates":[78.80396999999998,18.06299],"type":"Point"}
}