{
  "type": "Feature",
  "properties": {
    "iso:country":"IN",
    "ks:ks_name":"Mamail",
    "ks:ks_pop":459,
    "ks:ks_type":"VILLAGE",
    "name:eng_x_preferred":[
        "Mamail"
    ],
    "wof:name":"Mamail",
    "wof:placetype":"locality",
    "wof:population":459
},
  "geometry": {"coordinates":[85.26070199999999,22.759202],"type":"Point"}
}