{
  "type": "Feature",
  "properties": {
    "gn:admin1_code":"34.0",
    "gn:admin2_code":"204.0",
    "gn:asciiname":"Bhada",
    "gn:country_code":"IN",
    "gn:dem":71,
    "gn:feature_class":"P",
    "gn:feature_code":"PPL",
    "gn:name":"Bh\u0101da",
    "gn:population":0,
    "gn:timezone":"Asia/Kolkata",
    "iso:country":"IN",
    "ks:ks_alt_nam":"Bh\u0101da",
    "ks:ks_name":"Bhada",
    "ks:ks_pop":929,
    "ks:ks_type":"VILLAGE",
    "ks:ks_uagg_main":0,
    "name:eng_x_preferred":[
        "Bhada"
    ],
    "name:eng_x_variant":[
        "Bh\u0101da"
    ],
    "wof:name":"Bhada",
    "wof:placetype":"neighbourhood",
    "wof:population":929
},
  "geometry": {"coordinates":[84.723674,26.553487],"type":"Point"}
}