{
  "type": "Feature",
  "properties": {
    "iso:country":"IN",
    "ks:ks_name":"Bariari",
    "ks:ks_pop":1156,
    "ks:ks_type":"VILLAGE",
    "name:eng_x_preferred":[
        "Bariari"
    ],
    "wof:name":"Bariari",
    "wof:placetype":"locality",
    "wof:population":1156
},
  "geometry": {"coordinates":[86.43578599999999,26.031611],"type":"Point"}
}