{
  "type": "Feature",
  "properties": {
    "iso:country":"IN",
    "ks:ks_name":"Jantal Berya",
    "ks:ks_pop":627,
    "ks:ks_type":"HABITATION",
    "name:eng_x_preferred":[
        "Jantal Berya"
    ],
    "wof:name":"Jantal Berya",
    "wof:placetype":"locality",
    "wof:population":627
},
  "geometry": {"coordinates":[86.65836,22.585697],"type":"Point"}
}