{
  "type": "Feature",
  "properties": {
    "iso:country":"IN",
    "ks:ks_name":"Singhawali",
    "ks:ks_pop":1589,
    "ks:ks_type":"VILLAGE",
    "name:eng_x_preferred":[
        "Singhawali"
    ],
    "wof:name":"Singhawali",
    "wof:placetype":"locality",
    "wof:population":1589
},
  "geometry": {"coordinates":[77.981033,26.758158],"type":"Point"}
}