{
  "type": "Feature",
  "properties": {
    "iso:country":"IN",
    "ks:ks_name":"Agoya",
    "ks:ks_pop":321,
    "ks:ks_type":"VILLAGE",
    "ks:ks_uagg_main":0,
    "name:eng_x_preferred":[
        "Agoya"
    ],
    "wof:name":"Agoya",
    "wof:placetype":"neighbourhood",
    "wof:population":321
},
  "geometry": {"coordinates":[86.483812,23.410512],"type":"Point"}
}