{
  "type": "Feature",
  "properties": {
    "gn:admin1_code":"19.0",
    "gn:admin2_code":"561.0",
    "gn:asciiname":"Mallikarjunpur",
    "gn:country_code":"IN",
    "gn:dem":538,
    "gn:feature_class":"P",
    "gn:feature_code":"PPL",
    "gn:name":"Mallik\u0101rjunpur",
    "gn:population":0,
    "gn:timezone":"Asia/Kolkata",
    "iso:country":"IN",
    "wof:name":"Mallikarjunpur",
    "wof:placetype":"locality"
},
  "geometry": {"coordinates":[75.75,15.0898],"type":"Point"}
}