{
  "type": "Feature",
  "properties": {
    "iso:country":"IN",
    "ks:ks_name":"Kumbalikoppa",
    "ks:ks_pop":35,
    "ks:ks_type":"HABITATION",
    "name:eng_x_preferred":[
        "Kumbalikoppa"
    ],
    "wof:name":"Kumbalikoppa",
    "wof:placetype":"locality",
    "wof:population":35
},
  "geometry": {"coordinates":[74.964512,13.918834],"type":"Point"}
}