{
  "type": "Feature",
  "properties": {
    "iso:country":"IN",
    "ks:ks_name":"Ashoka",
    "ks:ks_pop":50,
    "ks:ks_type":"VILLAGE",
    "name:eng_x_preferred":[
        "Ashoka"
    ],
    "wof:name":"Ashoka",
    "wof:placetype":"locality",
    "wof:population":50
},
  "geometry": {"coordinates":[84.317956,19.411888],"type":"Point"}
}