{
  "type": "Feature",
  "properties": {
    "gn:admin1_code":"36",
    "gn:admin2_code":"133.0",
    "gn:asciiname":"Budhupura",
    "gn:country_code":"IN",
    "gn:dem":245,
    "gn:feature_class":"P",
    "gn:feature_code":"PPL",
    "gn:name":"Budhupura",
    "gn:population":0,
    "gn:timezone":"Asia/Kolkata",
    "iso:country":"IN",
    "wof:name":"Budhupura",
    "wof:placetype":"locality"
},
  "geometry": {"coordinates":[77.2407,29.47446],"type":"Point"}
}