{
  "type": "Feature",
  "properties": {
    "iso:country":"IN",
    "ks:ks_name":"Jialgaria",
    "ks:ks_pop":659,
    "ks:ks_type":"VILLAGE",
    "ks:ks_uagg_main":0,
    "name:eng_x_preferred":[
        "Jialgaria"
    ],
    "wof:name":"Jialgaria",
    "wof:placetype":"neighbourhood",
    "wof:population":659
},
  "geometry": {"coordinates":[88.26029,23.355062],"type":"Point"}
}