{
  "type": "Feature",
  "properties": {
    "gn:admin1_code":"11.0",
    "gn:admin2_code":"24.0",
    "gn:asciiname":"Jhikkawal",
    "gn:country_code":"IN",
    "gn:dem":457,
    "gn:feature_class":"P",
    "gn:feature_code":"PPL",
    "gn:name":"Jhikkaw\u0101l",
    "gn:population":0,
    "gn:timezone":"Asia/Kolkata",
    "iso:country":"IN",
    "wof:name":"Jhikkawal",
    "wof:placetype":"locality"
},
  "geometry": {"coordinates":[75.87394,32.29821],"type":"Point"}
}