{
  "type": "Feature",
  "properties": {
    "iso:country":"IN",
    "ks:ks_name":"Kasapur",
    "ks:ks_pop":0,
    "ks:ks_type":"VILLAGE",
    "name:eng_x_preferred":[
        "Kasapur"
    ],
    "wof:name":"Kasapur",
    "wof:placetype":"locality",
    "wof:population":0
},
  "geometry": {"coordinates":[78.794256,20.411265],"type":"Point"}
}