{
  "type": "Feature",
  "properties": {
    "iso:country":"IN",
    "ks:ks_name":"Tilaiyamajhiana",
    "ks:ks_pop":950,
    "ks:ks_type":"VILLAGE",
    "name:eng_x_preferred":[
        "Tilaiyamajhiana"
    ],
    "wof:name":"Tilaiyamajhiana",
    "wof:placetype":"locality",
    "wof:population":950
},
  "geometry": {"coordinates":[86.827332,24.445805],"type":"Point"}
}