{
  "type": "Feature",
  "properties": {
    "iso:country":"IN",
    "ks:ks_name":"Mukkamthodu",
    "ks:ks_pop":1394,
    "ks:ks_type":"HABITATION",
    "name:eng_x_preferred":[
        "Mukkamthodu"
    ],
    "wof:name":"Mukkamthodu",
    "wof:placetype":"locality",
    "wof:population":1394
},
  "geometry": {"coordinates":[76.838261,9.087911],"type":"Point"}
}