{
  "type": "Feature",
  "properties": {
    "gn:admin1_code":"37",
    "gn:admin2_code":"406.0",
    "gn:asciiname":"Lawar",
    "gn:country_code":"IN",
    "gn:dem":257,
    "gn:feature_class":"P",
    "gn:feature_code":"PPL",
    "gn:name":"L\u0101war",
    "gn:population":0,
    "gn:timezone":"Asia/Kolkata",
    "iso:country":"IN",
    "ks:ks_alt_nam":"L\u0101war",
    "ks:ks_name":"Lawar",
    "ks:ks_type":"VILLAGE",
    "ks:ks_uagg_main":0,
    "name:bpy_x_preferred":[
        "\u09b2\u09be\u09f1\u09be\u09b0 \u098f\u09a8\u09aa\u09bf"
    ],
    "name:ceb_x_preferred":[
        "L\u0101war Kh\u0101s"
    ],
    "name:eng_x_preferred":[
        "Lawar"
    ],
    "name:eng_x_variant":[
        "L\u0101war"
    ],
    "name:ita_x_preferred":[
        "Lawar"
    ],
    "name:msa_x_preferred":[
        "Lawar"
    ],
    "name:nld_x_preferred":[
        "Lawar"
    ],
    "name:pol_x_preferred":[
        "Lawar"
    ],
    "name:por_x_preferred":[
        "Lawar"
    ],
    "name:swe_x_preferred":[
        "L\u0101war Kh\u0101s"
    ],
    "name:urd_x_preferred":[
        "\u0644\u0627\u0648\u0631"
    ],
    "name:vie_x_preferred":[
        "Lawar"
    ],
    "name:zho_x_preferred":[
        "\u62c9\u74e6\u5c14\u6069\u666e"
    ],
    "wof:name":"Lawar",
    "wof:placetype":"neighbourhood"
},
  "geometry": {"coordinates":[82.22897500000001,21.999831],"type":"Point"}
}