{
  "type": "Feature",
  "properties": {
    "gn:admin1_code":"35.0",
    "gn:admin2_code":"454.0",
    "gn:asciiname":"Imliatola",
    "gn:country_code":"IN",
    "gn:dem":476,
    "gn:feature_class":"P",
    "gn:feature_code":"PPL",
    "gn:name":"Imli\u0101tol\u0101",
    "gn:population":0,
    "gn:timezone":"Asia/Kolkata",
    "iso:country":"IN",
    "wof:name":"Imliatola",
    "wof:placetype":"locality"
},
  "geometry": {"coordinates":[80.53133000000003,22.44481],"type":"Point"}
}