{
  "type": "Feature",
  "properties": {
    "iso:country":"IN",
    "ks:ks_alt_nam":"SONAR BASTI",
    "ks:ks_name":"Sonar Basti",
    "ks:ks_pop":113,
    "ks:ks_type":"HABITATION",
    "ks:ks_uagg_main":0,
    "name:eng_x_preferred":[
        "Sonar Basti"
    ],
    "wof:name":"Sonar Basti",
    "wof:placetype":"neighbourhood",
    "wof:population":113
},
  "geometry": {"coordinates":[82.188523,25.501036],"type":"Point"}
}