{
  "type": "Feature",
  "properties": {
    "iso:country":"IN",
    "ks:ks_name":"Arosbagwadi",
    "ks:ks_pop":481,
    "ks:ks_type":"HABITATION",
    "name:eng_x_preferred":[
        "Arosbagwadi"
    ],
    "wof:name":"Arosbagwadi",
    "wof:placetype":"locality",
    "wof:population":481
},
  "geometry": {"coordinates":[73.853319,15.816006],"type":"Point"}
}