{
  "type": "Feature",
  "properties": {
    "iso:country":"IN",
    "ks:ks_alt_nam":"lembra",
    "ks:ks_name":"Lembra",
    "ks:ks_pop":357,
    "ks:ks_type":"HABITATION",
    "name:eng_x_preferred":[
        "Lembra"
    ],
    "wof:name":"Lembra",
    "wof:placetype":"locality",
    "wof:population":357
},
  "geometry": {"coordinates":[85.331228,22.284972],"type":"Point"}
}