{
  "type": "Feature",
  "properties": {
    "iso:country":"IN",
    "ks:ks_name":"Kathieralga No. I",
    "ks:ks_pop":758,
    "ks:ks_type":"HABITATION",
    "name:eng_x_preferred":[
        "Kathieralga No. I"
    ],
    "wof:name":"Kathieralga No. I",
    "wof:placetype":"locality",
    "wof:population":758
},
  "geometry": {"coordinates":[89.933375,25.943333],"type":"Point"}
}