{
  "type": "Feature",
  "properties": {
    "gn:admin1_code":"19.0",
    "gn:admin2_code":"582.0",
    "gn:asciiname":"Mittanahalli",
    "gn:country_code":"IN",
    "gn:dem":884,
    "gn:feature_class":"P",
    "gn:feature_code":"PPL",
    "gn:name":"Mittanahalli",
    "gn:population":0,
    "gn:timezone":"Asia/Kolkata",
    "iso:country":"IN",
    "ks:ks_name":"Mithanahalli",
    "ks:ks_pop":384,
    "ks:ks_type":"VILLAGE",
    "name:eng_x_preferred":[
        "Mithanahalli"
    ],
    "name:eng_x_variant":[
        "Mittanahalli"
    ],
    "wof:name":"Mithanahalli",
    "wof:placetype":"locality",
    "wof:population":384
},
  "geometry": {"coordinates":[77.818943,13.292479],"type":"Point"}
}