{
  "type": "Feature",
  "properties": {
    "gn:admin1_code":"37.0",
    "gn:admin2_code":"414.0",
    "gn:asciiname":"Murkera",
    "gn:country_code":"IN",
    "gn:dem":630,
    "gn:feature_class":"P",
    "gn:feature_code":"PPL",
    "gn:name":"Murkera",
    "gn:population":0,
    "gn:timezone":"Asia/Kolkata",
    "iso:country":"IN",
    "wof:name":"Murkera",
    "wof:placetype":"locality"
},
  "geometry": {"coordinates":[81.76883000000002,19.97328],"type":"Point"}
}