{
  "type": "Feature",
  "properties": {
    "iso:country":"IN",
    "ks:ks_name":"Khutuguda",
    "ks:ks_pop":286,
    "ks:ks_type":"HABITATION",
    "name:eng_x_preferred":[
        "Khutuguda"
    ],
    "wof:name":"Khutuguda",
    "wof:placetype":"locality",
    "wof:population":286
},
  "geometry": {"coordinates":[82.594374,19.003914],"type":"Point"}
}