{
  "type": "Feature",
  "properties": {
    "iso:country":"IN",
    "ks:ks_name":"Sotkhali",
    "ks:ks_pop":937,
    "ks:ks_type":"VILLAGE",
    "ks:ks_uagg_main":0,
    "name:eng_x_preferred":[
        "Sotkhali"
    ],
    "wof:name":"Sotkhali",
    "wof:placetype":"neighbourhood",
    "wof:population":937
},
  "geometry": {"coordinates":[87.925983,23.405502],"type":"Point"}
}