{
  "type": "Feature",
  "properties": {
    "gn:admin1_code":"19.0",
    "gn:admin2_code":"568.0",
    "gn:asciiname":"Navilare",
    "gn:country_code":"IN",
    "gn:dem":623,
    "gn:feature_class":"P",
    "gn:feature_code":"PPL",
    "gn:name":"Navil\u0101re",
    "gn:population":0,
    "gn:timezone":"Asia/Kolkata",
    "iso:country":"IN",
    "wof:name":"Navilare",
    "wof:placetype":"locality"
},
  "geometry": {"coordinates":[75.35906999999997,13.7951],"type":"Point"}
}