{
  "type": "Feature",
  "properties": {
    "gn:admin1_code":"36.0",
    "gn:admin2_code":"189.0",
    "gn:asciiname":"Hata",
    "gn:country_code":"IN",
    "gn:dem":84,
    "gn:feature_class":"P",
    "gn:feature_code":"PPL",
    "gn:name":"H\u0101ta",
    "gn:population":0,
    "gn:timezone":"Asia/Kolkata",
    "iso:country":"IN",
    "name:ceb_x_preferred":[
        "Hata"
    ],
    "name:deu_x_preferred":[
        "Hata"
    ],
    "name:fra_x_preferred":[
        "Hata"
    ],
    "name:rus_x_preferred":[
        "\u0425\u0430\u0442\u0430"
    ],
    "name:tur_x_preferred":[
        "Hata"
    ],
    "name:ukr_x_preferred":[
        "\u0425\u0430\u0442\u0430"
    ],
    "name:vie_x_preferred":[
        "Hata"
    ],
    "wof:name":"Hata",
    "wof:placetype":"locality"
},
  "geometry": {"coordinates":[84.03561999999999,26.7256],"type":"Point"}
}