{
  "type": "Feature",
  "properties": {
    "gn:admin1_code":"11",
    "gn:admin2_code":"23.0",
    "gn:asciiname":"Indal",
    "gn:country_code":"IN",
    "gn:dem":1508,
    "gn:feature_class":"P",
    "gn:feature_code":"PPL",
    "gn:name":"Indal",
    "gn:population":0,
    "gn:timezone":"Asia/Kolkata",
    "iso:country":"IN",
    "wof:name":"Indal",
    "wof:placetype":"locality"
},
  "geometry": {"coordinates":[76.09976999999998,32.83184],"type":"Point"}
}