{
  "type": "Feature",
  "properties": {
    "gn:admin1_code":"2.0",
    "gn:admin2_code":"544.0",
    "gn:asciiname":"Valasamamidi",
    "gn:country_code":"IN",
    "gn:dem":948,
    "gn:feature_class":"P",
    "gn:feature_code":"PPL",
    "gn:name":"Valasam\u0101midi",
    "gn:population":0,
    "gn:timezone":"Asia/Kolkata",
    "iso:country":"IN",
    "wof:name":"Valasamamidi",
    "wof:placetype":"locality"
},
  "geometry": {"coordinates":[82.45288000000002,18.03836],"type":"Point"}
}