{
  "type": "Feature",
  "properties": {
    "gn:admin1_code":"2.0",
    "gn:admin2_code":"544.0",
    "gn:asciiname":"Valasamamidi",
    "gn:country_code":"IN",
    "gn:dem":948,
    "gn:feature_class":"P",
    "gn:feature_code":"PPL",
    "gn:name":"Valasam\u0101midi",
    "gn:population":0,
    "gn:timezone":"Asia/Kolkata",
    "iso:country":"IN",
    "ks:ks_alt_nam":"Valasam\u0101midi",
    "ks:ks_name":"Valasamamidi",
    "ks:ks_pop":250,
    "ks:ks_type":"VILLAGE",
    "name:eng_x_preferred":[
        "Valasamamidi"
    ],
    "name:eng_x_variant":[
        "Valasam\u0101midi"
    ],
    "wof:name":"Valasamamidi",
    "wof:placetype":"locality",
    "wof:population":250
},
  "geometry": {"coordinates":[82.452884,18.03836],"type":"Point"}
}