{
  "type": "Feature",
  "properties": {
    "gn:admin1_code":"24.0",
    "gn:admin2_code":"116.0",
    "gn:asciiname":"Ganga",
    "gn:country_code":"IN",
    "gn:dem":198,
    "gn:feature_class":"P",
    "gn:feature_code":"PPL",
    "gn:name":"Gang\u0101",
    "gn:population":0,
    "gn:timezone":"Asia/Kolkata",
    "iso:country":"IN",
    "wof:name":"Ganga",
    "wof:placetype":"locality"
},
  "geometry": {"coordinates":[72.84394,25.33963],"type":"Point"}
}