{
  "type": "Feature",
  "properties": {
    "iso:country":"IN",
    "ks:ks_name":"Jasaidih",
    "ks:ks_pop":590,
    "ks:ks_type":"VILLAGE",
    "name:eng_x_preferred":[
        "Jasaidih"
    ],
    "wof:name":"Jasaidih",
    "wof:placetype":"locality",
    "wof:population":590
},
  "geometry": {"coordinates":[86.705277,24.052704],"type":"Point"}
}