{
  "type": "Feature",
  "properties": {
    "iso:country":"IN",
    "ks:ks_name":"Kurmajodi",
    "ks:ks_pop":232,
    "ks:ks_type":"VILLAGE",
    "name:eng_x_preferred":[
        "Kurmajodi"
    ],
    "wof:name":"Kurmajodi",
    "wof:placetype":"locality",
    "wof:population":232
},
  "geometry": {"coordinates":[83.60030500000001,19.637043],"type":"Point"}
}