{
  "type": "Feature",
  "properties": {
    "iso:country":"IN",
    "ks:ks_alt_nam":"BORATEMALA",
    "ks:ks_name":"Boratemala",
    "ks:ks_pop":75,
    "ks:ks_type":"HABITATION",
    "ks:ks_uagg_main":0,
    "name:eng_x_preferred":[
        "Boratemala"
    ],
    "wof:name":"Boratemala",
    "wof:placetype":"neighbourhood",
    "wof:population":75
},
  "geometry": {"coordinates":[74.89452799999999,17.381648],"type":"Point"}
}