{
  "type": "Feature",
  "properties": {
    "gn:admin1_code":"19.0",
    "gn:admin2_code":"574.0",
    "gn:asciiname":"Honnasettihalli",
    "gn:country_code":"IN",
    "gn:dem":842,
    "gn:feature_class":"P",
    "gn:feature_code":"PPL",
    "gn:name":"Honnasettihalli",
    "gn:population":0,
    "gn:timezone":"Asia/Kolkata",
    "iso:country":"IN",
    "wof:name":"Honnasettihalli",
    "wof:placetype":"locality"
},
  "geometry": {"coordinates":[76.31755,13.29533],"type":"Point"}
}