{
  "type": "Feature",
  "properties": {
    "iso:country":"IN",
    "ks:ks_name":"Nandhae",
    "ks:ks_pop":220,
    "ks:ks_type":"HABITATION",
    "name:eng_x_preferred":[
        "Nandhae"
    ],
    "wof:name":"Nandhae",
    "wof:placetype":"locality",
    "wof:population":220
},
  "geometry": {"coordinates":[72.7642,20.011133],"type":"Point"}
}