{
  "type": "Feature",
  "properties": {
    "iso:country":"IN",
    "ks:ks_name":"Kubaladi",
    "ks:ks_pop":216,
    "ks:ks_type":"HABITATION",
    "name:eng_x_preferred":[
        "Kubaladi"
    ],
    "wof:name":"Kubaladi",
    "wof:placetype":"locality",
    "wof:population":216
},
  "geometry": {"coordinates":[75.46024300000001,12.771883],"type":"Point"}
}