{
  "type": "Feature",
  "properties": {
    "iso:country":"IN",
    "ks:ks_alt_nam":"kol  basti",
    "ks:ks_name":"Kol Basti",
    "ks:ks_pop":500,
    "ks:ks_type":"HABITATION",
    "name:eng_x_preferred":[
        "Kol Basti"
    ],
    "name:eng_x_variant":[
        "kol  basti"
    ],
    "wof:name":"Kol Basti",
    "wof:placetype":"locality",
    "wof:population":500
},
  "geometry": {"coordinates":[82.076184,25.158134],"type":"Point"}
}