{
  "type": "Feature",
  "properties": {
    "gn:admin1_code":"38.0",
    "gn:admin2_code":"353.0",
    "gn:asciiname":"Amarjola",
    "gn:country_code":"IN",
    "gn:dem":120,
    "gn:feature_class":"P",
    "gn:feature_code":"PPL",
    "gn:name":"\u0100marjola",
    "gn:population":0,
    "gn:timezone":"Asia/Kolkata",
    "iso:country":"IN",
    "ks:ks_name":"Amirjola",
    "ks:ks_pop":313,
    "ks:ks_type":"VILLAGE",
    "name:eng_x_preferred":[
        "Amirjola"
    ],
    "name:eng_x_variant":[
        "Amarjola"
    ],
    "wof:name":"Amirjola",
    "wof:placetype":"locality",
    "wof:population":313
},
  "geometry": {"coordinates":[87.575062,24.539537],"type":"Point"}
}