{
  "type": "Feature",
  "properties": {
    "gn:admin1_code":"25.0",
    "gn:admin2_code":"616.0",
    "gn:asciiname":"Alliyur",
    "gn:country_code":"IN",
    "gn:dem":19,
    "gn:feature_class":"P",
    "gn:feature_code":"PPL",
    "gn:name":"Alliy\u016br",
    "gn:population":0,
    "gn:timezone":"Asia/Kolkata",
    "iso:country":"IN",
    "ks:ks_name":"Alliiyur",
    "ks:ks_pop":174,
    "ks:ks_type":"HABITATION",
    "name:eng_x_preferred":[
        "Alliiyur"
    ],
    "name:eng_x_variant":[
        "Alliyur"
    ],
    "wof:name":"Alliiyur",
    "wof:placetype":"locality",
    "wof:population":174
},
  "geometry": {"coordinates":[79.49129000000001,11.183445],"type":"Point"}
}