{
  "type": "Feature",
  "properties": {
    "gn:admin1_code":"19.0",
    "gn:admin2_code":"581.0",
    "gn:asciiname":"Alamagiri",
    "gn:country_code":"IN",
    "gn:dem":839,
    "gn:feature_class":"P",
    "gn:feature_code":"PPL",
    "gn:name":"\u0100lamagiri",
    "gn:population":0,
    "gn:timezone":"Asia/Kolkata",
    "iso:country":"IN",
    "wof:name":"Alamagiri",
    "wof:placetype":"locality"
},
  "geometry": {"coordinates":[78.16214000000002,13.36088],"type":"Point"}
}