{
  "type": "Feature",
  "properties": {
    "gn:admin1_code":"36.0",
    "gn:admin2_code":"189.0",
    "gn:asciiname":"Sahodarpatti",
    "gn:country_code":"IN",
    "gn:dem":90,
    "gn:feature_class":"P",
    "gn:feature_code":"PPL",
    "gn:name":"Sahodarpatti",
    "gn:population":0,
    "gn:timezone":"Asia/Kolkata",
    "iso:country":"IN",
    "ks:ks_name":"Sahodarpatti",
    "ks:ks_type":"VILLAGE",
    "name:eng_x_preferred":[
        "Sahodarpatti"
    ],
    "wof:name":"Sahodarpatti",
    "wof:placetype":"locality"
},
  "geometry": {"coordinates":[83.99153699999999,26.978425],"type":"Point"}
}