{
  "type": "Feature",
  "properties": {
    "iso:country":"IN",
    "ks:ks_name":"Gyan Khorka",
    "ks:ks_pop":459,
    "ks:ks_type":"HABITATION",
    "name:eng_x_preferred":[
        "Gyan Khorka"
    ],
    "wof:name":"Gyan Khorka",
    "wof:placetype":"locality",
    "wof:population":459
},
  "geometry": {"coordinates":[91.579437,26.765913],"type":"Point"}
}