{
  "type": "Feature",
  "properties": {
    "iso:country":"IN",
    "qs:name":"Munirabad Project  Area",
    "qs:name_adm0":"India",
    "qs:name_adm1":"Karnataka",
    "qs:photos":102,
    "qs:photos_1k":21,
    "qs:photos_9k":1,
    "qs:photos_9r":3,
    "qs:photos_all":102,
    "qs:photos_sr":3,
    "qs:placetype":"Town",
    "qs:pop_sr":"0",
    "wof:name":"Munirabad Project  Area",
    "wof:placetype":"locality"
},
  "geometry": {"coordinates":[76.392059,15.358356],"type":"Point"}
}