{
  "type": "Feature",
  "properties": {
    "iso:country":"IN",
    "ks:ks_name":"Gokul Adda",
    "ks:ks_pop":100,
    "ks:ks_type":"HABITATION",
    "name:eng_x_preferred":[
        "Gokul Adda"
    ],
    "wof:name":"Gokul Adda",
    "wof:placetype":"locality",
    "wof:population":100
},
  "geometry": {"coordinates":[77.594386,27.790624],"type":"Point"}
}