{
  "type": "Feature",
  "properties": {
    "iso:country":"IN",
    "ks:ks_name":"Jualia",
    "ks:ks_pop":920,
    "ks:ks_type":"VILLAGE",
    "name:eng_x_preferred":[
        "Jualia"
    ],
    "wof:name":"Jualia",
    "wof:placetype":"locality",
    "wof:population":920
},
  "geometry": {"coordinates":[86.593659,21.606931],"type":"Point"}
}