{
  "type": "Feature",
  "properties": {
    "gn:admin1_code":"16.0",
    "gn:admin2_code":"511.0",
    "gn:asciiname":"Ara",
    "gn:country_code":"IN",
    "gn:dem":406,
    "gn:feature_class":"P",
    "gn:feature_code":"PPL",
    "gn:name":"\u0100ra",
    "gn:population":0,
    "gn:timezone":"Asia/Kolkata",
    "iso:country":"IN",
    "wof:name":"Ara",
    "wof:placetype":"locality"
},
  "geometry": {"coordinates":[77.60688,19.54419],"type":"Point"}
}