{
  "type": "Feature",
  "properties": {
    "gn:admin1_code":"35.0",
    "gn:admin2_code":"432.0",
    "gn:asciiname":"Sonadi",
    "gn:country_code":"IN",
    "gn:dem":399,
    "gn:feature_class":"P",
    "gn:feature_code":"PPL",
    "gn:name":"Sonadi",
    "gn:population":0,
    "gn:timezone":"Asia/Kolkata",
    "iso:country":"IN",
    "wof:name":"Sonadi",
    "wof:placetype":"locality"
},
  "geometry": {"coordinates":[75.44899000000002,24.42113],"type":"Point"}
}