{
  "type": "Feature",
  "properties": {
    "gn:admin1_code":"36.0",
    "gn:admin2_code":"192.0",
    "gn:asciiname":"Barahimpur",
    "gn:country_code":"IN",
    "gn:dem":70,
    "gn:feature_class":"P",
    "gn:feature_code":"PPL",
    "gn:name":"Barahimpur",
    "gn:population":0,
    "gn:timezone":"Asia/Kolkata",
    "iso:country":"IN",
    "wof:name":"Barahimpur",
    "wof:placetype":"locality"
},
  "geometry": {"coordinates":[83.74460999999999,26.18125],"type":"Point"}
}