{
  "type": "Feature",
  "properties": {
    "iso:country":"IN",
    "ks:ks_name":"Udavayal",
    "ks:ks_pop":285,
    "ks:ks_type":"HABITATION",
    "name:eng_x_preferred":[
        "Udavayal"
    ],
    "wof:name":"Udavayal",
    "wof:placetype":"locality",
    "wof:population":285
},
  "geometry": {"coordinates":[78.57020300000001,9.839967],"type":"Point"}
}