{
  "type": "Feature",
  "properties": {
    "gn:admin1_code":"35.0",
    "gn:admin2_code":"447.0",
    "gn:asciiname":"Khirki Buzurg",
    "gn:country_code":"IN",
    "gn:dem":739,
    "gn:feature_class":"P",
    "gn:feature_code":"PPL",
    "gn:name":"Khirki Buzurg",
    "gn:population":0,
    "gn:timezone":"Asia/Kolkata",
    "iso:country":"IN",
    "wof:name":"Khirki Buzurg",
    "wof:placetype":"neighbourhood"
},
  "geometry": {"coordinates":[78.13133999999999,21.94438],"type":"Point"}
}