{
  "type": "Feature",
  "properties": {
    "gn:admin1_code":"21",
    "gn:admin2_code":"388.0",
    "gn:asciiname":"Taptapani",
    "gn:country_code":"IN",
    "gn:dem":417,
    "gn:feature_class":"P",
    "gn:feature_code":"PPL",
    "gn:name":"Taptap\u0101ni",
    "gn:population":0,
    "gn:timezone":"Asia/Kolkata",
    "iso:country":"IN",
    "name:ori_x_preferred":[
        "\u0b24\u0b2a\u0b4d\u0b24\u0b2a\u0b3e\u0b23\u0b3f"
    ],
    "wof:name":"Taptapani",
    "wof:placetype":"locality"
},
  "geometry": {"coordinates":[84.39471999999998,19.49007000000001],"type":"Point"}
}