{
  "type": "Feature",
  "properties": {
    "gn:admin1_code":"19.0",
    "gn:admin2_code":"568.0",
    "gn:asciiname":"Tenkabail",
    "gn:country_code":"IN",
    "gn:dem":575,
    "gn:feature_class":"P",
    "gn:feature_code":"PPL",
    "gn:name":"Tenkabail",
    "gn:population":0,
    "gn:timezone":"Asia/Kolkata",
    "iso:country":"IN",
    "wof:name":"Tenkabail",
    "wof:placetype":"locality"
},
  "geometry": {"coordinates":[75.0389,13.90304],"type":"Point"}
}