{
  "type": "Feature",
  "properties": {
    "gn:country":"IN",
    "gn:fcode":"PPL",
    "gn:pop":0,
    "iso:country":"IN",
    "qs:name":"Chatnahalli",
    "qs:name_adm0":"India",
    "qs:name_adm1":"Karnataka",
    "qs:photos":7,
    "qs:photos_1k":1,
    "qs:photos_9k":1,
    "qs:photos_9r":1,
    "qs:photos_all":7,
    "qs:photos_sr":1,
    "qs:placetype":"Town",
    "qs:pop_sr":"0",
    "wof:name":"Chatnahalli",
    "wof:placetype":"locality",
    "wof:population":0
},
  "geometry": {"coordinates":[76.55474,12.20422],"type":"Point"}
}