{
  "type": "Feature",
  "properties": {
    "gn:admin1_code":"11.0",
    "gn:admin2_code":"27.0",
    "gn:asciiname":"Lamba Thach",
    "gn:country_code":"IN",
    "gn:dem":2146,
    "gn:feature_class":"P",
    "gn:feature_code":"PPL",
    "gn:name":"Lamba Th\u0101ch",
    "gn:population":0,
    "gn:timezone":"Asia/Kolkata",
    "iso:country":"IN",
    "wof:name":"Lamba Thach",
    "wof:placetype":"locality"
},
  "geometry": {"coordinates":[77.2186,31.51036],"type":"Point"}
}