{
  "type": "Feature",
  "properties": {
    "iso:country":"IN",
    "ks:ks_name":"Pipaliya Viran",
    "ks:ks_pop":122,
    "ks:ks_type":"HABITATION",
    "name:eng_x_preferred":[
        "Pipaliya Viran"
    ],
    "wof:name":"Pipaliya Viran",
    "wof:placetype":"locality",
    "wof:population":122
},
  "geometry": {"coordinates":[77.843497,23.156019],"type":"Point"}
}