{
  "type": "Feature",
  "properties": {
    "iso:country":"IN",
    "ks:ks_name":"Palakasa",
    "ks:ks_pop":132,
    "ks:ks_type":"HABITATION",
    "name:eng_x_preferred":[
        "Palakasa"
    ],
    "wof:name":"Palakasa",
    "wof:placetype":"locality",
    "wof:population":132
},
  "geometry": {"coordinates":[81.25437700000001,19.836772],"type":"Point"}
}