{
  "type": "Feature",
  "properties": {
    "iso:country":"IN",
    "ks:ks_name":"Gulariya",
    "ks:ks_pop":520,
    "ks:ks_type":"HABITATION",
    "name:eng_x_preferred":[
        "Gulariya"
    ],
    "wof:name":"Gulariya",
    "wof:placetype":"locality",
    "wof:population":520
},
  "geometry": {"coordinates":[79.78998799999999,26.931004],"type":"Point"}
}