{
  "type": "Feature",
  "properties": {
    "gn:admin1_code":"19.0",
    "gn:admin2_code":"581.0",
    "gn:asciiname":"Himsarapalli",
    "gn:country_code":"IN",
    "gn:dem":865,
    "gn:feature_class":"P",
    "gn:feature_code":"PPL",
    "gn:name":"Hims\u0101rapalli",
    "gn:population":0,
    "gn:timezone":"Asia/Kolkata",
    "iso:country":"IN",
    "wof:name":"Himsarapalli",
    "wof:placetype":"locality"
},
  "geometry": {"coordinates":[78.37576999999997,13.57893],"type":"Point"}
}