{
  "type": "Feature",
  "properties": {
    "gn:admin1_code":"35.0",
    "gn:admin2_code":"456.0",
    "gn:asciiname":"Dukli",
    "gn:country_code":"IN",
    "gn:dem":578,
    "gn:feature_class":"P",
    "gn:feature_code":"PPL",
    "gn:name":"Dukli",
    "gn:population":0,
    "gn:timezone":"Asia/Kolkata",
    "iso:country":"IN",
    "name:tam_x_preferred":[
        "\u0ba4\u0bc1\u0b95\u0bcd\u0bb2\u0bbf"
    ],
    "wof:name":"Dukli",
    "wof:placetype":"locality"
},
  "geometry": {"coordinates":[79.48233,22.30357],"type":"Point"}
}