{
  "type": "Feature",
  "properties": {
    "gn:admin1_code":"37.0",
    "gn:admin2_code":"414.0",
    "gn:asciiname":"Dilmili",
    "gn:country_code":"IN",
    "gn:dem":645,
    "gn:feature_class":"P",
    "gn:feature_code":"PPLL",
    "gn:name":"Dilmili",
    "gn:population":0,
    "gn:timezone":"Asia/Kolkata",
    "iso:country":"IN",
    "ks:ks_name":"Dilmili",
    "ks:ks_pop":2721,
    "ks:ks_type":"VILLAGE",
    "name:eng_x_preferred":[
        "Dilmili"
    ],
    "wof:name":"Dilmili",
    "wof:placetype":"locality",
    "wof:population":2721
},
  "geometry": {"coordinates":[81.771636,18.98843],"type":"Point"}
}