{
  "type": "Feature",
  "properties": {
    "gn:admin1_code":"35",
    "gn:admin2_code":"420.0",
    "gn:asciiname":"Chhonda",
    "gn:country_code":"IN",
    "gn:dem":152,
    "gn:feature_class":"P",
    "gn:feature_code":"PPL",
    "gn:name":"Chhonda",
    "gn:population":0,
    "gn:timezone":"Asia/Kolkata",
    "iso:country":"IN",
    "ks:ks_name":"Chhounda",
    "ks:ks_pop":447,
    "ks:ks_type":"HABITATION",
    "name:eng_x_preferred":[
        "Chhounda"
    ],
    "name:eng_x_variant":[
        "Chhonda"
    ],
    "wof:name":"Chhounda",
    "wof:placetype":"locality",
    "wof:population":447
},
  "geometry": {"coordinates":[78.550974,26.700227],"type":"Point"}
}