{
  "type": "Feature",
  "properties": {
    "iso:country":"IN",
    "ks:ks_name":"Uttar Saruchakabaha",
    "ks:ks_pop":578,
    "ks:ks_type":"HABITATION",
    "name:eng_x_preferred":[
        "Uttar Saruchakabaha"
    ],
    "wof:name":"Uttar Saruchakabaha",
    "wof:placetype":"locality",
    "wof:population":578
},
  "geometry": {"coordinates":[92.41537099999999,26.300005],"type":"Point"}
}