{
  "type": "Feature",
  "properties": {
    "iso:country":"IN",
    "ks:ks_name":"M V P Harijanawada",
    "ks:ks_pop":116,
    "ks:ks_type":"HABITATION",
    "name:eng_x_preferred":[
        "M V P Harijanawada"
    ],
    "wof:name":"M V P Harijanawada",
    "wof:placetype":"locality",
    "wof:population":116
},
  "geometry": {"coordinates":[79.07170600000001,13.624638],"type":"Point"}
}