{
  "type": "Feature",
  "properties": {
    "iso:country":"IN",
    "ks:ks_name":"Paikpada",
    "ks:ks_pop":219,
    "ks:ks_type":"HABITATION",
    "name:eng_x_preferred":[
        "Paikpada"
    ],
    "wof:name":"Paikpada",
    "wof:placetype":"locality",
    "wof:population":219
},
  "geometry": {"coordinates":[83.278706,19.711548],"type":"Point"}
}