{
  "type": "Feature",
  "properties": {
    "iso:country":"IN",
    "ks:ks_name":"Ouguri Kapahua No 1",
    "ks:ks_pop":421,
    "ks:ks_type":"HABITATION",
    "name:eng_x_preferred":[
        "Ouguri Kapahua No 1"
    ],
    "wof:name":"Ouguri Kapahua No 1",
    "wof:placetype":"locality",
    "wof:population":421
},
  "geometry": {"coordinates":[95.09348300000001,27.261869],"type":"Point"}
}