{
  "type": "Feature",
  "properties": {
    "gn:admin1_code":"28.0",
    "gn:admin2_code":"334.0",
    "gn:asciiname":"Nandigram",
    "gn:country_code":"IN",
    "gn:dem":35,
    "gn:feature_class":"P",
    "gn:feature_code":"PPL",
    "gn:name":"Nandigr\u0101m",
    "gn:population":0,
    "gn:timezone":"Asia/Kolkata",
    "iso:country":"IN",
    "name:ben_x_preferred":[
        "\u09a8\u09a8\u09cd\u09a6\u09c0\u0997\u09cd\u09b0\u09be\u09ae"
    ],
    "name:hin_x_preferred":[
        "\u0928\u0902\u0926\u0940\u0917\u094d\u0930\u093e\u092e"
    ],
    "name:mal_x_preferred":[
        "\u0d28\u0d28\u0d4d\u0d26\u0d3f\u0d17\u0d4d\u0d30\u0d3e\u0d02"
    ],
    "name:pan_x_preferred":[
        "\u0a28\u0a70\u0a26\u0a40\u0a17\u0a30\u0a3e\u0a2e"
    ],
    "wof:name":"Nandigram",
    "wof:placetype":"locality"
},
  "geometry": {"coordinates":[87.89273,24.49745],"type":"Point"}
}