{
  "type": "Feature",
  "properties": {
    "iso:country":"IN",
    "ks:ks_name":"Ramchandrapur",
    "ks:ks_pop":203,
    "ks:ks_type":"VILLAGE",
    "name:eng_x_preferred":[
        "Ramchandrapur"
    ],
    "wof:name":"Ramchandrapur",
    "wof:placetype":"locality",
    "wof:population":203
},
  "geometry": {"coordinates":[86.576954,22.222141],"type":"Point"}
}