{
  "type": "Feature",
  "properties": {
    "iso:country":"IN",
    "ks:ks_name":"Sikaria Urf Ramnagar Khas",
    "ks:ks_pop":238,
    "ks:ks_type":"HABITATION",
    "ks:ks_uagg_main":0,
    "name:eng_x_preferred":[
        "Sikaria Urf Ramnagar Khas"
    ],
    "wof:name":"Sikaria Urf Ramnagar Khas",
    "wof:placetype":"neighbourhood",
    "wof:population":238
},
  "geometry": {"coordinates":[83.889788,26.74252],"type":"Point"}
}