{
  "type": "Feature",
  "properties": {
    "iso:country":"IN",
    "ks:ks_alt_nam":"BABA FALI",
    "ks:ks_name":"Baba Fali",
    "ks:ks_pop":100,
    "ks:ks_type":"HABITATION",
    "name:eng_x_preferred":[
        "Baba Fali"
    ],
    "wof:name":"Baba Fali",
    "wof:placetype":"locality",
    "wof:population":100
},
  "geometry": {"coordinates":[72.970161,24.489111],"type":"Point"}
}