{
  "type": "Feature",
  "properties": {
    "iso:country":"IN",
    "ks:ks_alt_nam":"UPPERTOLA",
    "ks:ks_name":"Uppertola",
    "ks:ks_pop":314,
    "ks:ks_type":"HABITATION",
    "name:eng_x_preferred":[
        "Uppertola"
    ],
    "wof:name":"Uppertola",
    "wof:placetype":"locality",
    "wof:population":314
},
  "geometry": {"coordinates":[85.769964,22.691178],"type":"Point"}
}