{
  "type": "Feature",
  "properties": {
    "iso:country":"IN",
    "ks:ks_alt_nam":"Patel gamatji",
    "ks:ks_name":"Patel Gamatji",
    "ks:ks_pop":155,
    "ks:ks_type":"HABITATION",
    "name:eng_x_preferred":[
        "Patel Gamatji"
    ],
    "wof:name":"Patel Gamatji",
    "wof:placetype":"locality",
    "wof:population":155
},
  "geometry": {"coordinates":[72.88959800000001,20.304337],"type":"Point"}
}