{
  "type": "Feature",
  "properties": {
    "iso:country":"IN",
    "ks:ks_name":"Ashokanagara-2",
    "ks:ks_pop":695,
    "ks:ks_type":"HABITATION",
    "name:eng_x_preferred":[
        "Ashokanagara-2"
    ],
    "wof:name":"Ashokanagara-2",
    "wof:placetype":"locality",
    "wof:population":695
},
  "geometry": {"coordinates":[75.755308,14.002549],"type":"Point"}
}