{
  "type": "Feature",
  "properties": {
    "iso:country":"IN",
    "ks:ks_name":"Pindra",
    "ks:ks_pop":140,
    "ks:ks_type":"VILLAGE",
    "ks:ks_uagg_main":0,
    "name:eng_x_preferred":[
        "Pindra"
    ],
    "wof:name":"Pindra",
    "wof:placetype":"locality",
    "wof:population":140
},
  "geometry": {"coordinates":[86.725008,24.521887],"type":"Point"}
}