{
  "type": "Feature",
  "properties": {
    "gn:admin1_code":"36",
    "gn:admin2_code":"157.0",
    "gn:asciiname":"Newan",
    "gn:country_code":"IN",
    "gn:dem":125,
    "gn:feature_class":"P",
    "gn:feature_code":"PPL",
    "gn:name":"New\u0101n",
    "gn:population":0,
    "gn:timezone":"Asia/Kolkata",
    "iso:country":"IN",
    "wof:name":"Newan",
    "wof:placetype":"locality"
},
  "geometry": {"coordinates":[80.87004,26.68039000000001],"type":"Point"}
}