{
  "type": "Feature",
  "properties": {
    "iso:country":"IN",
    "ks:ks_name":"Anjani",
    "ks:ks_pop":380,
    "ks:ks_type":"VILLAGE",
    "name:eng_x_preferred":[
        "Anjani"
    ],
    "wof:name":"Anjani",
    "wof:placetype":"locality",
    "wof:population":380
},
  "geometry": {"coordinates":[83.07043400000001,23.530847],"type":"Point"}
}