{
  "type": "Feature",
  "properties": {
    "iso:country":"IN",
    "ks:ks_name":"Jamkhar",
    "ks:ks_pop":29,
    "ks:ks_type":"VILLAGE",
    "ks:ks_uagg_main":0,
    "name:eng_x_preferred":[
        "Jamkhar"
    ],
    "wof:name":"Jamkhar",
    "wof:placetype":"neighbourhood",
    "wof:population":29
},
  "geometry": {"coordinates":[80.402636,22.54896],"type":"Point"}
}