{
  "type": "Feature",
  "properties": {
    "gn:admin1_code":"16.0",
    "gn:admin2_code":"505.0",
    "gn:asciiname":"Brahmani",
    "gn:country_code":"IN",
    "gn:dem":335,
    "gn:feature_class":"P",
    "gn:feature_code":"PPL",
    "gn:name":"Br\u0101hmani",
    "gn:population":0,
    "gn:timezone":"Asia/Kolkata",
    "iso:country":"IN",
    "name:kan_x_preferred":[
        "\u0cac\u0ccd\u0cb0\u0cb9\u0ccd\u0cae\u0cbe\u0ca3\u0cbf"
    ],
    "name:pan_x_preferred":[
        "\u0a2c\u0a4d\u0a30\u0a3e\u0a39\u0a2e\u0a23\u0a40"
    ],
    "name:sin_x_preferred":[
        "\u0db6\u0dca\u200d\u0dbb\u0dc4\u0dca\u0db8\u0dab\u0dd3"
    ],
    "name:tam_x_preferred":[
        "\u0baa\u0bbf\u0bb0\u0bbe\u0bae\u0bcd\u0bae\u0bbf"
    ],
    "name:tha_x_preferred":[
        "\u0e1e\u0e23\u0e30\u0e41\u0e21\u0e48\u0e1e\u0e23\u0e2b\u0e21\u0e32\u0e13\u0e35"
    ],
    "wof:name":"Brahmani",
    "wof:placetype":"locality"
},
  "geometry": {"coordinates":[78.90647,21.24767],"type":"Point"}
}