{
  "type": "Feature",
  "properties": {
    "iso:country":"IN",
    "ks:ks_name":"Rameswar Chak",
    "ks:ks_pop":213,
    "ks:ks_type":"VILLAGE",
    "name:eng_x_preferred":[
        "Rameswar Chak"
    ],
    "wof:name":"Rameswar Chak",
    "wof:placetype":"locality",
    "wof:population":213
},
  "geometry": {"coordinates":[87.44972300000001,22.466565],"type":"Point"}
}