{
  "type": "Feature",
  "properties": {
    "iso:country":"IN",
    "ks:ks_name":"Ghoramari",
    "ks:ks_pop":433,
    "ks:ks_type":"VILLAGE",
    "name:eng_x_preferred":[
        "Ghoramari"
    ],
    "wof:name":"Ghoramari",
    "wof:placetype":"locality",
    "wof:population":433
},
  "geometry": {"coordinates":[90.190257,26.467371],"type":"Point"}
}