{
  "type": "Feature",
  "properties": {
    "iso:country":"IN",
    "ks:ks_name":"Hanagar",
    "ks:ks_pop":92,
    "ks:ks_type":"HABITATION",
    "name:eng_x_preferred":[
        "Hanagar"
    ],
    "wof:name":"Hanagar",
    "wof:placetype":"locality",
    "wof:population":92
},
  "geometry": {"coordinates":[74.66122,14.777093],"type":"Point"}
}