{
  "type": "Feature",
  "properties": {
    "iso:country":"IN",
    "ks:ks_name":"Chain Pur No.2",
    "ks:ks_pop":0,
    "ks:ks_type":"VILLAGE",
    "name:eng_x_preferred":[
        "Chain Pur No.2"
    ],
    "wof:name":"Chain Pur No.2",
    "wof:placetype":"locality",
    "wof:population":0
},
  "geometry": {"coordinates":[85.670266,22.684233],"type":"Point"}
}