{
  "type": "Feature",
  "properties": {
    "gn:admin1_code":"36",
    "gn:admin2_code":"176.0",
    "gn:asciiname":"Munera",
    "gn:country_code":"IN",
    "gn:dem":118,
    "gn:feature_class":"P",
    "gn:feature_code":"PPL",
    "gn:name":"Munera",
    "gn:population":0,
    "gn:timezone":"Asia/Kolkata",
    "iso:country":"IN",
    "name:ara_x_preferred":[
        "\u0645\u0646\u064a\u0631\u0629"
    ],
    "name:arg_x_preferred":[
        "Munera"
    ],
    "name:ast_x_preferred":[
        "Munera"
    ],
    "name:azb_x_preferred":[
        "\u0645\u0648\u0646\u0631\u0627"
    ],
    "name:cat_x_preferred":[
        "Munera"
    ],
    "name:ceb_x_preferred":[
        "Munera"
    ],
    "name:eus_x_preferred":[
        "Munera"
    ],
    "name:fas_x_preferred":[
        "\u0645\u0648\u0646\u0631\u0627"
    ],
    "name:fra_x_preferred":[
        "Munera"
    ],
    "name:hun_x_preferred":[
        "Munera"
    ],
    "name:ina_x_preferred":[
        "Munera"
    ],
    "name:ita_x_preferred":[
        "Munera"
    ],
    "name:msa_x_preferred":[
        "Munera"
    ],
    "name:nld_x_preferred":[
        "Munera"
    ],
    "name:oci_x_preferred":[
        "Munera"
    ],
    "name:pol_x_preferred":[
        "Munera"
    ],
    "name:por_x_preferred":[
        "Munera"
    ],
    "name:ron_x_preferred":[
        "Munera"
    ],
    "name:rus_x_preferred":[
        "\u041c\u0443\u043d\u0435\u0440\u0430"
    ],
    "name:spa_x_preferred":[
        "Munera"
    ],
    "name:swe_x_preferred":[
        "Munera"
    ],
    "name:ukr_x_preferred":[
        "\u041c\u0443\u043d\u0435\u0440\u0430"
    ],
    "name:vie_x_preferred":[
        "Munera"
    ],
    "name:war_x_preferred":[
        "Munera"
    ],
    "name:zho_x_preferred":[
        "\u7a46\u5185\u62c9"
    ],
    "wof:name":"Munera",
    "wof:placetype":"locality"
},
  "geometry": {"coordinates":[81.19279,26.88351],"type":"Point"}
}