{
  "type": "Feature",
  "properties": {
    "gn:admin1_code":"16.0",
    "gn:admin2_code":"515.0",
    "gn:asciiname":"Dhamni",
    "gn:country_code":"IN",
    "gn:dem":718,
    "gn:feature_class":"P",
    "gn:feature_code":"PPL",
    "gn:name":"Dh\u0101mni",
    "gn:population":0,
    "gn:timezone":"Asia/Kolkata",
    "iso:country":"IN",
    "wof:name":"Dhamni",
    "wof:placetype":"neighbourhood"
},
  "geometry": {"coordinates":[75.25095,20.35575],"type":"Point"}
}