{
  "type": "Feature",
  "properties": {
    "iso:country":"IN",
    "ks:ks_name":"Bhurtigarh",
    "ks:ks_pop":203,
    "ks:ks_type":"VILLAGE",
    "name:eng_x_preferred":[
        "Bhurtigarh"
    ],
    "wof:name":"Bhurtigarh",
    "wof:placetype":"locality",
    "wof:population":203
},
  "geometry": {"coordinates":[83.47592899999999,19.976066],"type":"Point"}
}