{
  "type": "Feature",
  "properties": {
    "gn:admin1_code":"16.0",
    "gn:admin2_code":"510.0",
    "gn:asciiname":"Kopra",
    "gn:country_code":"IN",
    "gn:dem":272,
    "gn:feature_class":"P",
    "gn:feature_code":"PPL",
    "gn:name":"Kopra",
    "gn:population":0,
    "gn:timezone":"Asia/Kolkata",
    "iso:country":"IN",
    "ks:ks_name":"Kopra",
    "ks:ks_pop":497,
    "ks:ks_type":"VILLAGE",
    "name:eng_x_preferred":[
        "Kopra"
    ],
    "wof:name":"Kopra",
    "wof:placetype":"locality",
    "wof:population":497
},
  "geometry": {"coordinates":[78.054312,20.62296],"type":"Point"}
}