{
  "type": "Feature",
  "properties": {
    "iso:country":"IN",
    "ks:ks_name":"Dhangadpada",
    "ks:ks_pop":91,
    "ks:ks_type":"HABITATION",
    "name:eng_x_preferred":[
        "Dhangadpada"
    ],
    "wof:name":"Dhangadpada",
    "wof:placetype":"locality",
    "wof:population":91
},
  "geometry": {"coordinates":[73.074011,19.852053],"type":"Point"}
}