{
  "type": "Feature",
  "properties": {
    "iso:country":"IN",
    "ks:ks_name":"Khadipara",
    "ks:ks_pop":118,
    "ks:ks_type":"HABITATION",
    "name:eng_x_preferred":[
        "Khadipara"
    ],
    "wof:name":"Khadipara",
    "wof:placetype":"locality",
    "wof:population":118
},
  "geometry": {"coordinates":[82.344776,22.742454],"type":"Point"}
}