{
  "type": "Feature",
  "properties": {
    "iso:country":"IN",
    "ks:ks_name":"Pengaraspara",
    "ks:ks_pop":210,
    "ks:ks_type":"HABITATION",
    "name:eng_x_preferred":[
        "Pengaraspara"
    ],
    "wof:name":"Pengaraspara",
    "wof:placetype":"locality",
    "wof:population":210
},
  "geometry": {"coordinates":[82.07775100000001,18.844355],"type":"Point"}
}