{
  "type": "Feature",
  "properties": {
    "iso:country":"IN",
    "ks:ks_alt_nam":"5 E RURAL",
    "ks:ks_name":"5 E Rural",
    "ks:ks_pop":643,
    "ks:ks_type":"HABITATION",
    "name:eng_x_preferred":[
        "5 E Rural"
    ],
    "wof:name":"5 E Rural",
    "wof:placetype":"locality",
    "wof:population":643
},
  "geometry": {"coordinates":[73.90365,29.8987],"type":"Point"}
}