{
  "type": "Feature",
  "properties": {
    "gn:admin1_code":"34.0",
    "gn:admin2_code":"207",
    "gn:asciiname":"Basopatti",
    "gn:country_code":"IN",
    "gn:dem":72,
    "gn:feature_class":"P",
    "gn:feature_code":"PPL",
    "gn:name":"B\u0101sopatti",
    "gn:population":0,
    "gn:timezone":"Asia/Kolkata",
    "iso:country":"IN",
    "name:und_x_variant":[
        "Basopati Bazar",
        "B\u0101sopatti"
    ],
    "wof:name":"Basopatti",
    "wof:placetype":"locality"
},
  "geometry": {"coordinates":[86.00521999999999,26.57804],"type":"Point"}
}