{
  "type": "Feature",
  "properties": {
    "gn:admin1_code":"11.0",
    "gn:admin2_code":"32.0",
    "gn:asciiname":"Sawar",
    "gn:country_code":"IN",
    "gn:dem":1391,
    "gn:feature_class":"P",
    "gn:feature_code":"PPL",
    "gn:name":"Saw\u0101r",
    "gn:population":0,
    "gn:timezone":"Asia/Kolkata",
    "iso:country":"IN",
    "wof:name":"Sawar",
    "wof:placetype":"locality"
},
  "geometry": {"coordinates":[77.32641,30.67748],"type":"Point"}
}