{
  "type": "Feature",
  "properties": {
    "iso:country":"IN",
    "ks:ks_alt_nam":"BAHIRWASTI3",
    "ks:ks_name":"Bahirwasti3",
    "ks:ks_pop":62,
    "ks:ks_type":"HABITATION",
    "ks:ks_uagg_main":0,
    "name:eng_x_preferred":[
        "Bahirwasti3"
    ],
    "wof:name":"Bahirwasti3",
    "wof:placetype":"neighbourhood",
    "wof:population":62
},
  "geometry": {"coordinates":[75.635008,18.997427],"type":"Point"}
}