{
  "type": "Feature",
  "properties": {
    "gn:admin1_code":"16",
    "gn:admin2_code":"503.0",
    "gn:asciiname":"Isegaon",
    "gn:country_code":"IN",
    "gn:dem":339,
    "gn:feature_class":"P",
    "gn:feature_code":"PPL",
    "gn:name":"\u012asegaon",
    "gn:population":0,
    "gn:timezone":"Asia/Kolkata",
    "iso:country":"IN",
    "wof:name":"Isegaon",
    "wof:placetype":"locality"
},
  "geometry": {"coordinates":[77.49521,21.16279],"type":"Point"}
}