{
  "type": "Feature",
  "properties": {
    "iso:country":"IN",
    "ks:ks_alt_nam":"Bharat pur",
    "ks:ks_name":"Bharat Pur",
    "ks:ks_pop":537,
    "ks:ks_type":"HABITATION",
    "name:eng_x_preferred":[
        "Bharat Pur"
    ],
    "wof:name":"Bharat Pur",
    "wof:placetype":"locality",
    "wof:population":537
},
  "geometry": {"coordinates":[77.17804700000001,25.397408],"type":"Point"}
}