{
  "type": "Feature",
  "properties": {
    "gn:admin1_code":"23.0",
    "gn:admin2_code":"51.0",
    "gn:asciiname":"Atari",
    "gn:country_code":"IN",
    "gn:dem":260,
    "gn:feature_class":"P",
    "gn:feature_code":"PPL",
    "gn:name":"At\u0101ri",
    "gn:population":0,
    "gn:timezone":"Asia/Kolkata",
    "iso:country":"IN",
    "name:ara_x_preferred":[
        "\u0622\u062a\u0627\u0631\u064a"
    ],
    "name:azb_x_preferred":[
        "\u0622\u062a\u0627\u0631\u06cc"
    ],
    "name:bos_x_preferred":[
        "Atari"
    ],
    "name:bul_x_preferred":[
        "\u0410\u0442\u0430\u0440\u0438"
    ],
    "name:cat_x_preferred":[
        "Atari"
    ],
    "name:ces_x_preferred":[
        "Atari"
    ],
    "name:dan_x_preferred":[
        "Atari"
    ],
    "name:deu_x_preferred":[
        "Atari"
    ],
    "name:epo_x_preferred":[
        "Atari"
    ],
    "name:eus_x_preferred":[
        "Atari"
    ],
    "name:fas_x_preferred":[
        "\u0622\u062a\u0627\u0631\u06cc"
    ],
    "name:fin_x_preferred":[
        "Atari"
    ],
    "name:fra_x_preferred":[
        "Atari"
    ],
    "name:glg_x_preferred":[
        "Atari"
    ],
    "name:heb_x_preferred":[
        "\u05d0\u05d8\u05d0\u05e8\u05d9"
    ],
    "name:hrv_x_preferred":[
        "Atari"
    ],
    "name:hun_x_preferred":[
        "Atari"
    ],
    "name:hye_x_preferred":[
        "\u0531\u0569\u0561\u0580\u056b"
    ],
    "name:ind_x_preferred":[
        "Atari"
    ],
    "name:isl_x_preferred":[
        "Atari"
    ],
    "name:ita_x_preferred":[
        "Atari"
    ],
    "name:jpn_x_preferred":[
        "\u30a2\u30bf\u30ea"
    ],
    "name:kor_x_preferred":[
        "\uc544\ud0c0\ub9ac"
    ],
    "name:lit_x_preferred":[
        "Atari"
    ],
    "name:nld_x_preferred":[
        "Atari"
    ],
    "name:nno_x_preferred":[
        "Atari"
    ],
    "name:nor_x_preferred":[
        "Atari"
    ],
    "name:pol_x_preferred":[
        "Atari"
    ],
    "name:por_x_preferred":[
        "Atari"
    ],
    "name:ron_x_preferred":[
        "Atari"
    ],
    "name:rus_x_preferred":[
        "Atari"
    ],
    "name:slk_x_preferred":[
        "Atari"
    ],
    "name:spa_x_preferred":[
        "Atari"
    ],
    "name:srp_x_preferred":[
        "\u0410\u0442\u0430\u0440\u0438"
    ],
    "name:swe_x_preferred":[
        "Atari"
    ],
    "name:tha_x_preferred":[
        "\u0e2d\u0e32\u0e15\u0e32\u0e23\u0e34"
    ],
    "name:tur_x_preferred":[
        "Atari"
    ],
    "name:ukr_x_preferred":[
        "Atari"
    ],
    "name:wuu_x_preferred":[
        "\u96c5\u8fbe\u5229"
    ],
    "name:zho_x_preferred":[
        "\u96c5\u9054\u5229"
    ],
    "wof:name":"Atari",
    "wof:placetype":"locality"
},
  "geometry": {"coordinates":[76.40188000000001,30.947],"type":"Point"}
}