{
  "type": "Feature",
  "properties": {
    "iso:country":"IN",
    "ks:ks_name":"Madiyan",
    "ks:ks_pop":247,
    "ks:ks_type":"HABITATION",
    "name:eng_x_preferred":[
        "Madiyan"
    ],
    "wof:name":"Madiyan",
    "wof:placetype":"locality",
    "wof:population":247
},
  "geometry": {"coordinates":[78.34864899999999,24.926792],"type":"Point"}
}