{
  "type": "Feature",
  "properties": {
    "iso:country":"IN",
    "ks:ks_name":"Rampur Bujurg",
    "ks:ks_pop":877,
    "ks:ks_type":"VILLAGE",
    "ks:ks_uagg_main":0,
    "name:eng_x_preferred":[
        "Rampur Bujurg"
    ],
    "wof:name":"Rampur Bujurg",
    "wof:placetype":"neighbourhood",
    "wof:population":877
},
  "geometry": {"coordinates":[83.606008,26.742305],"type":"Point"}
}