{
  "type": "Feature",
  "properties": {
    "iso:country":"IN",
    "ks:ks_name":"Sahjira Pure Dukhi",
    "ks:ks_pop":127,
    "ks:ks_type":"HABITATION",
    "name:eng_x_preferred":[
        "Sahjira Pure Dukhi"
    ],
    "wof:name":"Sahjira Pure Dukhi",
    "wof:placetype":"locality",
    "wof:population":127
},
  "geometry": {"coordinates":[82.354035,26.699441],"type":"Point"}
}