{
  "type": "Feature",
  "properties": {
    "iso:country":"IN",
    "ks:ks_name":"Balra",
    "ks:ks_pop":0,
    "ks:ks_type":"VILLAGE",
    "name:eng_x_preferred":[
        "Balra"
    ],
    "wof:name":"Balra",
    "wof:placetype":"locality",
    "wof:population":0
},
  "geometry": {"coordinates":[84.769924,25.445764],"type":"Point"}
}