{
  "type": "Feature",
  "properties": {
    "iso:country":"IN",
    "ks:ks_name":"Bijaypur",
    "ks:ks_pop":1061,
    "ks:ks_type":"HABITATION",
    "name:eng_x_preferred":[
        "Bijaypur"
    ],
    "wof:name":"Bijaypur",
    "wof:placetype":"locality",
    "wof:population":1061
},
  "geometry": {"coordinates":[94.070632,26.311239],"type":"Point"}
}