{
  "type": "Feature",
  "properties": {
    "gn:admin1_code":"36.0",
    "gn:admin2_code":"176.0",
    "gn:asciiname":"Sahni",
    "gn:country_code":"IN",
    "gn:dem":115,
    "gn:feature_class":"P",
    "gn:feature_code":"PPL",
    "gn:name":"Sahni",
    "gn:population":0,
    "gn:timezone":"Asia/Kolkata",
    "iso:country":"IN",
    "name:deu_x_preferred":[
        "Sahni"
    ],
    "name:hin_x_preferred":[
        "\u0938\u093e\u0939\u0928\u0940"
    ],
    "name:rus_x_preferred":[
        "\u0421\u0430\u0445\u043d\u0438"
    ],
    "wof:name":"Sahni",
    "wof:placetype":"locality"
},
  "geometry": {"coordinates":[81.56056,26.75063],"type":"Point"}
}