{
  "type": "Feature",
  "properties": {
    "gn:admin1_code":"36",
    "gn:admin2_code":"155.0",
    "gn:asciiname":"Nawada",
    "gn:country_code":"IN",
    "gn:dem":146,
    "gn:feature_class":"P",
    "gn:feature_code":"PPL",
    "gn:name":"Naw\u0101da",
    "gn:population":0,
    "gn:timezone":"Asia/Kolkata",
    "iso:country":"IN",
    "ks:ks_alt_nam":"Naw\u0101da",
    "ks:ks_name":"Nawada",
    "ks:ks_type":"VILLAGE",
    "ks:ks_uagg_main":0,
    "name:ara_x_preferred":[
        "\u0646\u0648\u0627\u062f\u0627"
    ],
    "name:ben_bn_x_preferred":[
        "\u09a8\u09be\u0993\u09af\u09bc\u09be\u09a6\u09be"
    ],
    "name:ben_in_x_preferred":[
        "\u09a8\u09be\u0993\u09af\u09bc\u09be\u09a6\u09be"
    ],
    "name:ben_x_preferred":[
        "\u09a8\u0993\u09af\u09bc\u09be\u09a6\u09be"
    ],
    "name:bih_x_preferred":[
        "\u0928\u0935\u093e\u0926\u093e"
    ],
    "name:bpy_x_preferred":[
        "\u09a8\u09be\u09f1\u09be\u09a6\u09be"
    ],
    "name:ceb_x_preferred":[
        "Naw\u0101da"
    ],
    "name:eng_x_preferred":[
        "Nawada"
    ],
    "name:eng_x_variant":[
        "Naw\u0101da"
    ],
    "name:fas_x_preferred":[
        "\u0646\u0627\u0648\u0627\u062f\u0627"
    ],
    "name:guj_x_preferred":[
        "\u0aa8\u0abe\u0ab5\u0aa1\u0abe"
    ],
    "name:hif_x_preferred":[
        "Nawada"
    ],
    "name:hin_x_preferred":[
        "\u0928\u0935\u093e\u0921\u093e"
    ],
    "name:hin_x_variant":[
        "\u0928\u0935\u093e\u0926\u093e"
    ],
    "name:ita_x_preferred":[
        "Nawada"
    ],
    "name:kan_x_preferred":[
        "\u0ca8\u0cb5\u0cbe\u0ca1\u0cbe"
    ],
    "name:mal_x_preferred":[
        "\u0d28\u0d35\u0d3e\u0d21"
    ],
    "name:mar_x_preferred":[
        "\u0928\u0935\u093e\u0926\u093e"
    ],
    "name:mlg_x_preferred":[
        "Nawada"
    ],
    "name:msa_x_preferred":[
        "Nawada"
    ],
    "name:nep_x_preferred":[
        "\u0928\u0935\u093e\u0926\u093e"
    ],
    "name:new_x_preferred":[
        "\u0928\u0935\u093e\u0926\u093e"
    ],
    "name:ori_x_preferred":[
        "\u0b28\u0b3e\u0b71\u0b3e\u0b21\u0b3c\u0b3e"
    ],
    "name:pan_x_preferred":[
        "\u0a28\u0a35\u0a3e\u0a26\u0a3e"
    ],
    "name:por_x_preferred":[
        "Nawada"
    ],
    "name:rus_x_preferred":[
        "\u041d\u0430\u0432\u0430\u0434\u0430"
    ],
    "name:san_x_preferred":[
        "\u0928\u0935\u093e\u0926\u093e"
    ],
    "name:spa_x_preferred":[
        "Nawada"
    ],
    "name:swe_x_preferred":[
        "Nawada"
    ],
    "name:tam_x_preferred":[
        "\u0ba8\u0bb5\u0bbe\u0b9f\u0bbe"
    ],
    "name:tel_x_preferred":[
        "\u0c28\u0c35\u0c3e\u0c21\u0c3e"
    ],
    "name:urd_x_preferred":[
        "\u0646\u0648\u0627\u062f\u06c1"
    ],
    "name:vie_x_preferred":[
        "Nawada"
    ],
    "name:zho_x_preferred":[
        "\u7eb3\u74e6\u8fbe"
    ],
    "wof:name":"Nawada",
    "wof:placetype":"neighbourhood"
},
  "geometry": {"coordinates":[79.87161,27.637514],"type":"Point"}
}