{
  "type": "Feature",
  "properties": {
    "iso:country":"IN",
    "ks:ks_name":"Wadgaon Alias Ganeshpur",
    "ks:ks_pop":317,
    "ks:ks_type":"VILLAGE",
    "ks:ks_uagg_main":0,
    "name:eng_x_preferred":[
        "Wadgaon Alias Ganeshpur"
    ],
    "wof:name":"Wadgaon Alias Ganeshpur",
    "wof:placetype":"neighbourhood",
    "wof:population":317
},
  "geometry": {"coordinates":[80.5386,20.682928],"type":"Point"}
}