{
  "type": "Feature",
  "properties": {
    "iso:country":"IN",
    "ks:ks_name":"Koldomari",
    "ks:ks_pop":6469,
    "ks:ks_type":"HABITATION",
    "name:eng_x_preferred":[
        "Koldomari"
    ],
    "wof:name":"Koldomari",
    "wof:placetype":"locality",
    "wof:population":6469
},
  "geometry": {"coordinates":[82.964406,24.283322],"type":"Point"}
}