{
  "type": "Feature",
  "properties": {
    "iso:country":"IN",
    "ks:ks_name":"Ved Falia",
    "ks:ks_pop":242,
    "ks:ks_type":"HABITATION",
    "ks:ks_uagg_main":0,
    "name:eng_x_preferred":[
        "Ved Falia"
    ],
    "wof:name":"Ved Falia",
    "wof:placetype":"neighbourhood",
    "wof:population":242
},
  "geometry": {"coordinates":[73.865278,22.62225],"type":"Point"}
}