{
  "type": "Feature",
  "properties": {
    "iso:country":"IN",
    "ks:ks_name":"Tinikuria",
    "ks:ks_pop":239,
    "ks:ks_type":"VILLAGE",
    "name:eng_x_preferred":[
        "Tinikuria"
    ],
    "wof:name":"Tinikuria",
    "wof:placetype":"locality",
    "wof:population":239
},
  "geometry": {"coordinates":[95.199699,27.398126],"type":"Point"}
}