{
  "type": "Feature",
  "properties": {
    "gn:admin1_code":"35",
    "gn:admin2_code":"455.0",
    "gn:asciiname":"Harrakol",
    "gn:country_code":"IN",
    "gn:dem":701,
    "gn:feature_class":"P",
    "gn:feature_code":"PPL",
    "gn:name":"Harr\u0101kol",
    "gn:population":0,
    "gn:timezone":"Asia/Kolkata",
    "iso:country":"IN",
    "ks:ks_alt_nam":"Harr\u0101kol",
    "ks:ks_name":"Harrakol",
    "ks:ks_type":"VILLAGE",
    "name:eng_x_preferred":[
        "Harrakol"
    ],
    "name:eng_x_variant":[
        "Harr\u0101kol"
    ],
    "wof:name":"Harrakol",
    "wof:placetype":"locality"
},
  "geometry": {"coordinates":[79.117227,22.471102],"type":"Point"}
}