{
  "type": "Feature",
  "properties": {
    "iso:country":"IN",
    "ks:ks_name":"Magudiha",
    "ks:ks_pop":29,
    "ks:ks_type":"VILLAGE",
    "name:eng_x_preferred":[
        "Magudiha"
    ],
    "wof:name":"Magudiha",
    "wof:placetype":"locality",
    "wof:population":29
},
  "geometry": {"coordinates":[86.77638399999999,22.27459],"type":"Point"}
}