{
  "type": "Feature",
  "properties": {
    "gn:admin1_code":"36.0",
    "gn:admin2_code":"138.0",
    "gn:asciiname":"Kheri Kalan",
    "gn:country_code":"IN",
    "gn:dem":231,
    "gn:feature_class":"P",
    "gn:feature_code":"PPL",
    "gn:name":"Kheri Kal\u0101n",
    "gn:population":0,
    "gn:timezone":"Asia/Kolkata",
    "iso:country":"IN",
    "name:ara_x_preferred":[
        "\u062e\u064a\u0631\u064a \u0643\u0627\u0644\u0627\u0646"
    ],
    "name:ben_bn_x_preferred":[
        "\u0996\u09c7\u09b0\u09bf \u0995\u09be\u09b2\u09be\u09a8"
    ],
    "name:ben_in_x_preferred":[
        "\u0996\u09c7\u09b0\u09bf \u0995\u09be\u09b2\u09be\u09a8"
    ],
    "name:guj_x_preferred":[
        "\u0a96\u0ac7\u0ab0\u0ac0 \u0a95\u0ab2\u0abe\u0aa8"
    ],
    "name:hin_x_preferred":[
        "\u0916\u0947\u0930\u0940 \u0915\u0932\u093e\u0902"
    ],
    "name:kan_x_preferred":[
        "\u0c96\u0cc7\u0cb0\u0cbf \u0c95\u0cb2\u0ca8\u0ccd"
    ],
    "name:mal_x_preferred":[
        "\u0d16\u0d47\u0d30\u0d3f \u0d15\u0d32\u0d7b"
    ],
    "name:mar_x_preferred":[
        "\u0916\u0947\u0930\u0940 \u0915\u0932\u093e\u0928"
    ],
    "name:pan_x_preferred":[
        "\u0a16\u0a47\u0a5c\u0a40 \u0a15\u0a32\u0a3e\u0a02"
    ],
    "name:tam_x_preferred":[
        "\u0b95\u0bc7\u0bb0\u0bbf \u0b95\u0bb2\u0ba9\u0bcd"
    ],
    "name:tel_x_preferred":[
        "\u0c16\u0c46\u0c30\u0c3f \u0c15\u0c32\u0c3e\u0c28\u0c4d"
    ],
    "name:urd_x_preferred":[
        "\u06a9\u06be\u06cc\u0691\u06cc \u06a9\u0644\u0627\u06ba"
    ],
    "wof:name":"Kheri Kalan",
    "wof:placetype":"locality"
},
  "geometry": {"coordinates":[77.4787,29.1166],"type":"Point"}
}