{
  "type": "Feature",
  "properties": {
    "iso:country":"IN",
    "ks:ks_name":"Tindni Ramgarh",
    "ks:ks_pop":505,
    "ks:ks_type":"VILLAGE",
    "name:eng_x_preferred":[
        "Tindni Ramgarh"
    ],
    "wof:name":"Tindni Ramgarh",
    "wof:placetype":"locality",
    "wof:population":505
},
  "geometry": {"coordinates":[79.210369,23.433155],"type":"Point"}
}