{
  "type": "Feature",
  "properties": {
    "iso:country":"IN",
    "ks:ks_name":"Pangabaju",
    "ks:ks_pop":136,
    "ks:ks_type":"VILLAGE",
    "name:eng_x_preferred":[
        "Pangabaju"
    ],
    "wof:name":"Pangabaju",
    "wof:placetype":"locality",
    "wof:population":136
},
  "geometry": {"coordinates":[83.734358,20.206768],"type":"Point"}
}