{
  "type": "Feature",
  "properties": {
    "iso:country":"IN",
    "ks:ks_name":"Kharaya",
    "ks:ks_pop":0,
    "ks:ks_type":"VILLAGE",
    "name:eng_x_preferred":[
        "Kharaya"
    ],
    "wof:name":"Kharaya",
    "wof:placetype":"locality",
    "wof:population":0
},
  "geometry": {"coordinates":[75.63869099999999,21.667093],"type":"Point"}
}