{
  "type": "Feature",
  "properties": {
    "iso:country":"IN",
    "ks:ks_name":"Ninha",
    "ks:ks_pop":60,
    "ks:ks_type":"HABITATION",
    "ks:ks_uagg_main":0,
    "name:eng_x_preferred":[
        "Ninha"
    ],
    "wof:name":"Ninha",
    "wof:placetype":"neighbourhood",
    "wof:population":60
},
  "geometry": {"coordinates":[81.622044,26.496619],"type":"Point"}
}