{
  "type": "Feature",
  "properties": {
    "iso:country":"IN",
    "ks:ks_name":"Machipara I",
    "ks:ks_pop":407,
    "ks:ks_type":"HABITATION",
    "name:eng_x_preferred":[
        "Machipara I"
    ],
    "wof:name":"Machipara I",
    "wof:placetype":"locality",
    "wof:population":407
},
  "geometry": {"coordinates":[90.081937,26.135294],"type":"Point"}
}