{
  "type": "Feature",
  "properties": {
    "gn:admin1_code":"35.0",
    "gn:admin2_code":"450.0",
    "gn:asciiname":"Tola",
    "gn:country_code":"IN",
    "gn:dem":424,
    "gn:feature_class":"P",
    "gn:feature_code":"PPL",
    "gn:name":"Tola",
    "gn:population":0,
    "gn:timezone":"Asia/Kolkata",
    "iso:country":"IN",
    "name:ceb_x_preferred":[
        "Tola"
    ],
    "name:deu_x_preferred":[
        "Tola"
    ],
    "name:fra_x_preferred":[
        "Tola"
    ],
    "name:ita_x_preferred":[
        "Tola"
    ],
    "name:nld_x_preferred":[
        "Tola"
    ],
    "name:pol_x_preferred":[
        "Tola"
    ],
    "name:por_x_preferred":[
        "Tola"
    ],
    "name:rus_x_preferred":[
        "\u0422\u043e\u043b\u0430"
    ],
    "name:spa_x_preferred":[
        "Tola"
    ],
    "name:swe_x_preferred":[
        "Tola"
    ],
    "name:ukr_x_preferred":[
        "\u0422\u043e\u043b\u0430"
    ],
    "name:vie_x_preferred":[
        "Tola"
    ],
    "wof:name":"Tola",
    "wof:placetype":"locality"
},
  "geometry": {"coordinates":[80.02498,23.9637],"type":"Point"}
}