{
  "type": "Feature",
  "properties": {
    "iso:country":"IN",
    "ks:ks_name":"Fuljhariya",
    "ks:ks_pop":222,
    "ks:ks_type":"HABITATION",
    "name:eng_x_preferred":[
        "Fuljhariya"
    ],
    "wof:name":"Fuljhariya",
    "wof:placetype":"locality",
    "wof:population":222
},
  "geometry": {"coordinates":[82.21538700000001,24.712424],"type":"Point"}
}