{
  "type": "Feature",
  "properties": {
    "gn:country":"IN",
    "gn:fcode":"PPL",
    "gn:pop":9514,
    "iso:country":"IN",
    "name:unk_x_variant":[
        "Mah\u0101ban"
    ],
    "qs:name":"Mahaban",
    "qs:name_adm0":"India",
    "qs:name_adm1":"Uttar Pradesh",
    "qs:photos_9r":0,
    "qs:photos_sr":0,
    "qs:placetype":"Town",
    "qs:pop_sr":"5",
    "wd:wordcount":158,
    "wof:name":"Mahaban",
    "wof:placetype":"locality",
    "wof:population":9514
},
  "geometry": {"coordinates":[77.74153,27.43282],"type":"Point"}
}