{
  "type": "Feature",
  "properties": {
    "gn:country":"IN",
    "gn:fcode":"PPL",
    "gn:population":9514,
    "iso:country":"IN",
    "name:bpy_x_preferred":[
        "\u09ae\u09b9\u09be\u09ac\u09a8"
    ],
    "name:cat_x_preferred":[
        "Mahaban"
    ],
    "name:ceb_x_preferred":[
        "Mah\u0101ban"
    ],
    "name:eng_x_preferred":[
        "Mahaban"
    ],
    "name:fra_x_preferred":[
        "Mahaban"
    ],
    "name:ita_x_preferred":[
        "Mahaban"
    ],
    "name:mlg_x_preferred":[
        "Mahaban"
    ],
    "name:msa_x_preferred":[
        "Mahaban"
    ],
    "name:nan_x_preferred":[
        "Mahaban"
    ],
    "name:new_x_preferred":[
        "\u092e\u0939\u093e\u092c\u0928"
    ],
    "name:nld_x_preferred":[
        "Mahaban"
    ],
    "name:pol_x_preferred":[
        "Mahaban"
    ],
    "name:por_x_preferred":[
        "Mahaban"
    ],
    "name:rus_x_preferred":[
        "\u041c\u0430\u0445\u0430\u0432\u0430\u043d"
    ],
    "name:swe_x_preferred":[
        "Mah\u0101ban"
    ],
    "name:urd_x_preferred":[
        "\u0645\u06c1\u0627\u0628\u0646"
    ],
    "name:vie_x_preferred":[
        "Mahaban"
    ],
    "name:zho_x_preferred":[
        "\u9a6c\u54c8\u73ed"
    ],
    "qs:name":"Mahaban",
    "qs:name_adm0":"India",
    "qs:name_adm1":"Uttar Pradesh",
    "qs:photos_9r":0,
    "qs:photos_sr":0,
    "qs:placetype":"Town",
    "qs:pop_sr":"5",
    "wd:wordcount":158,
    "wof:name":"Mahaban",
    "wof:placetype":"locality",
    "wof:population":9514
},
  "geometry": {"coordinates":[77.74153,27.43282],"type":"Point"}
}