{
  "type": "Feature",
  "properties": {
    "iso:country":"IN",
    "ks:ks_name":"Liki Dhangarwadi",
    "ks:ks_pop":47,
    "ks:ks_type":"HABITATION",
    "name:eng_x_preferred":[
        "Liki Dhangarwadi"
    ],
    "wof:name":"Liki Dhangarwadi",
    "wof:placetype":"locality",
    "wof:population":47
},
  "geometry": {"coordinates":[73.56215,16.464138],"type":"Point"}
}