{
  "type": "Feature",
  "properties": {
    "iso:country":"IN",
    "ks:ks_name":"Majan Ramkripal",
    "ks:ks_pop":209,
    "ks:ks_type":"HABITATION",
    "name:eng_x_preferred":[
        "Majan Ramkripal"
    ],
    "wof:name":"Majan Ramkripal",
    "wof:placetype":"locality",
    "wof:population":209
},
  "geometry": {"coordinates":[81.986509,24.710015],"type":"Point"}
}