{
  "type": "Feature",
  "properties": {
    "gn:admin1_code":"35",
    "gn:admin2_code":"467.0",
    "gn:asciiname":"Kankaria",
    "gn:country_code":"IN",
    "gn:dem":335,
    "gn:feature_class":"P",
    "gn:feature_code":"PPL",
    "gn:name":"Kankaria",
    "gn:population":0,
    "gn:timezone":"Asia/Kolkata",
    "iso:country":"IN",
    "wof:name":"Kankaria",
    "wof:placetype":"locality"
},
  "geometry": {"coordinates":[76.3425,21.53149],"type":"Point"}
}