{
  "type": "Feature",
  "properties": {
    "iso:country":"IN",
    "ks:ks_name":"Jamsara",
    "ks:ks_pop":683,
    "ks:ks_type":"VILLAGE",
    "name:eng_x_preferred":[
        "Jamsara"
    ],
    "wof:name":"Jamsara",
    "wof:placetype":"neighbourhood",
    "wof:population":683
},
  "geometry": {"coordinates":[84.917304,22.274409],"type":"Point"}
}