{
  "type": "Feature",
  "properties": {
    "iso:country":"IN",
    "ks:ks_name":"Pure Teeka",
    "ks:ks_pop":125,
    "ks:ks_type":"HABITATION",
    "name:eng_x_preferred":[
        "Pure Teeka"
    ],
    "wof:name":"Pure Teeka",
    "wof:placetype":"locality",
    "wof:population":125
},
  "geometry": {"coordinates":[81.50417400000001,26.466954],"type":"Point"}
}