{
  "type": "Feature",
  "properties": {
    "iso:country":"IN",
    "ks:ks_name":"Guza",
    "ks:ks_pop":1294,
    "ks:ks_type":"HABITATION",
    "name:eng_x_preferred":[
        "Guza"
    ],
    "wof:name":"Guza",
    "wof:placetype":"locality",
    "wof:population":1294
},
  "geometry": {"coordinates":[80.30583300000001,26.116944],"type":"Point"}
}