{
  "type": "Feature",
  "properties": {
    "iso:country":"IN",
    "ks:ks_name":"Manjha",
    "ks:ks_pop":475,
    "ks:ks_type":"VILLAGE",
    "ks:ks_uagg_main":0,
    "name:eng_x_preferred":[
        "Manjha"
    ],
    "wof:name":"Manjha",
    "wof:placetype":"neighbourhood",
    "wof:population":475
},
  "geometry": {"coordinates":[76.43349600000001,28.736015],"type":"Point"}
}