{
  "type": "Feature",
  "properties": {
    "iso:country":"IN",
    "ks:ks_name":"Anaipatti",
    "ks:ks_pop":517,
    "ks:ks_type":"HABITATION",
    "name:eng_x_preferred":[
        "Anaipatti"
    ],
    "wof:name":"Anaipatti",
    "wof:placetype":"locality",
    "wof:population":517
},
  "geometry": {"coordinates":[78.483878,10.956583],"type":"Point"}
}