{
  "type": "Feature",
  "properties": {
    "iso:country":"IN",
    "ks:ks_name":"Parbatpur Makhdompur",
    "ks:ks_pop":2526,
    "ks:ks_type":"VILLAGE",
    "ks:ks_uagg_main":0,
    "name:eng_x_preferred":[
        "Parbatpur Makhdompur"
    ],
    "wof:name":"Parbatpur Makhdompur",
    "wof:placetype":"locality",
    "wof:population":2526
},
  "geometry": {"coordinates":[78.360258,29.603882],"type":"Point"}
}