{
  "type": "Feature",
  "properties": {
    "gn:admin1_code":"16.0",
    "gn:admin2_code":"510.0",
    "gn:asciiname":"Yeheldari",
    "gn:country_code":"IN",
    "gn:dem":416,
    "gn:feature_class":"P",
    "gn:feature_code":"PPL",
    "gn:name":"Yeheldari",
    "gn:population":0,
    "gn:timezone":"Asia/Kolkata",
    "iso:country":"IN",
    "wof:name":"Yeheldari",
    "wof:placetype":"locality"
},
  "geometry": {"coordinates":[77.48868,19.92519],"type":"Point"}
}