{
  "type": "Feature",
  "properties": {
    "gn:admin1_code":"21.0",
    "gn:admin2_code":"375",
    "gn:asciiname":"Gurda",
    "gn:country_code":"IN",
    "gn:dem":648,
    "gn:feature_class":"P",
    "gn:feature_code":"PPL",
    "gn:name":"Gurda",
    "gn:population":0,
    "gn:timezone":"Asia/Kolkata",
    "iso:country":"IN",
    "ks:ks_name":"Guruda",
    "ks:ks_pop":2051,
    "ks:ks_type":"VILLAGE",
    "name:eng_x_preferred":[
        "Guruda"
    ],
    "name:eng_x_variant":[
        "Gurda"
    ],
    "wof:name":"Guruda",
    "wof:placetype":"locality",
    "wof:population":2051
},
  "geometry": {"coordinates":[85.382217,21.91356],"type":"Point"}
}