{
  "type": "Feature",
  "properties": {
    "gn:admin1_code":"21.0",
    "gn:admin2_code":"375",
    "gn:asciiname":"Gurda",
    "gn:country_code":"IN",
    "gn:dem":648,
    "gn:feature_class":"P",
    "gn:feature_code":"PPL",
    "gn:name":"Gurda",
    "gn:population":0,
    "gn:timezone":"Asia/Kolkata",
    "iso:country":"IN",
    "wof:name":"Gurda",
    "wof:placetype":"locality"
},
  "geometry": {"coordinates":[85.38731,21.92249],"type":"Point"}
}