{
  "type": "Feature",
  "properties": {
    "iso:country":"IN",
    "ks:ks_name":"Bilakoppa",
    "ks:ks_pop":47,
    "ks:ks_type":"HABITATION",
    "name:eng_x_preferred":[
        "Bilakoppa"
    ],
    "wof:name":"Bilakoppa",
    "wof:placetype":"locality",
    "wof:population":47
},
  "geometry": {"coordinates":[75.073257,13.781174],"type":"Point"}
}