{
  "type": "Feature",
  "properties": {
    "iso:country":"IN",
    "ks:ks_alt_nam":"UPERKILABADI",
    "ks:ks_name":"Uperkilabadi",
    "ks:ks_pop":53,
    "ks:ks_type":"HABITATION",
    "name:eng_x_preferred":[
        "Uperkilabadi"
    ],
    "wof:name":"Uperkilabadi",
    "wof:placetype":"locality",
    "wof:population":53
},
  "geometry": {"coordinates":[84.25605,19.894174],"type":"Point"}
}