{
  "type": "Feature",
  "properties": {
    "iso:country":"IN",
    "ks:ks_name":"Kinkel",
    "ks:ks_type":"VILLAGE",
    "name:eng_x_preferred":[
        "Kinkel"
    ],
    "wof:name":"Kinkel",
    "wof:placetype":"locality"
},
  "geometry": {"coordinates":[84.061722,22.824036],"type":"Point"}
}