{
  "type": "Feature",
  "properties": {
    "iso:country":"IN",
    "ks:ks_name":"Tuppdasara",
    "ks:ks_pop":70,
    "ks:ks_type":"HABITATION",
    "name:eng_x_preferred":[
        "Tuppdasara"
    ],
    "wof:name":"Tuppdasara",
    "wof:placetype":"locality",
    "wof:population":70
},
  "geometry": {"coordinates":[74.883644,14.530793],"type":"Point"}
}