{
  "type": "Feature",
  "properties": {
    "iso:country":"IN",
    "ks:ks_alt_nam":"Basavana jeddi",
    "ks:ks_name":"Basavana Jeddi",
    "ks:ks_pop":38,
    "ks:ks_type":"HABITATION",
    "name:eng_x_preferred":[
        "Basavana Jeddi"
    ],
    "wof:name":"Basavana Jeddi",
    "wof:placetype":"locality",
    "wof:population":38
},
  "geometry": {"coordinates":[74.917664,14.798789],"type":"Point"}
}