{
  "type": "Feature",
  "properties": {
    "iso:country":"IN",
    "ks:ks_name":"Zillaguntha",
    "ks:ks_pop":50,
    "ks:ks_type":"HABITATION",
    "name:eng_x_preferred":[
        "Zillaguntha"
    ],
    "wof:name":"Zillaguntha",
    "wof:placetype":"locality",
    "wof:population":50
},
  "geometry": {"coordinates":[82.93894299999999,18.459556],"type":"Point"}
}