{
  "type": "Feature",
  "properties": {
    "gn:admin1_code":"36",
    "gn:admin2_code":"179.0",
    "gn:asciiname":"Bishnagarpur Bhatpura",
    "gn:country_code":"IN",
    "gn:dem":96,
    "gn:feature_class":"P",
    "gn:feature_code":"PPL",
    "gn:name":"Bishn\u0101garpur Bhatpura",
    "gn:population":0,
    "gn:timezone":"Asia/Kolkata",
    "iso:country":"IN",
    "wof:name":"Bishnagarpur Bhatpura",
    "wof:placetype":"locality"
},
  "geometry": {"coordinates":[82.38027,26.33363],"type":"Point"}
}