{
  "type": "Feature",
  "properties": {
    "gn:admin1_code":"39.0",
    "gn:admin2_code":"66.0",
    "gn:asciiname":"Lohriasal Malla",
    "gn:country_code":"IN",
    "gn:dem":426,
    "gn:feature_class":"P",
    "gn:feature_code":"PPL",
    "gn:name":"Lohrias\u0101l Malla",
    "gn:population":0,
    "gn:timezone":"Asia/Kolkata",
    "iso:country":"IN",
    "ks:ks_name":"Loharia Salmalla",
    "ks:ks_pop":3336,
    "ks:ks_type":"VILLAGE",
    "ks:ks_uagg_main":0,
    "name:eng_x_preferred":[
        "Loharia Salmalla"
    ],
    "wof:name":"Loharia Salmalla",
    "wof:placetype":"neighbourhood",
    "wof:population":3336
},
  "geometry": {"coordinates":[79.481979,29.233974],"type":"Point"}
}