{
  "type": "Feature",
  "properties": {
    "iso:country":"IN",
    "ks:ks_name":"Ganjraha",
    "ks:ks_pop":501,
    "ks:ks_type":"VILLAGE",
    "ks:ks_uagg_main":0,
    "name:eng_x_preferred":[
        "Ganjraha"
    ],
    "wof:name":"Ganjraha",
    "wof:placetype":"neighbourhood",
    "wof:population":501
},
  "geometry": {"coordinates":[79.858932,28.454096],"type":"Point"}
}