{
  "type": "Feature",
  "properties": {
    "iso:country":"IN",
    "ks:ks_name":"Naya Parana",
    "ks:ks_pop":125,
    "ks:ks_type":"HABITATION",
    "name:eng_x_preferred":[
        "Naya Parana"
    ],
    "wof:name":"Naya Parana",
    "wof:placetype":"locality",
    "wof:population":125
},
  "geometry": {"coordinates":[75.173411,24.93726],"type":"Point"}
}