{
  "type": "Feature",
  "properties": {
    "iso:country":"IN",
    "ks:ks_name":"Amara",
    "ks:ks_pop":638,
    "ks:ks_type":"VILLAGE",
    "ks:ks_uagg_main":0,
    "name:eng_x_preferred":[
        "Amara"
    ],
    "wof:name":"Amara",
    "wof:placetype":"neighbourhood",
    "wof:population":638
},
  "geometry": {"coordinates":[86.980548,21.562109],"type":"Point"}
}