{
  "type": "Feature",
  "properties": {
    "gn:country":"IN",
    "gn:fcode":"PPL",
    "gn:pop":60271,
    "iso:country":"IN",
    "name:ben_x_preferred":[
        "\u09ac\u09a1\u09bc\u09b8\u09be\u09a6"
    ],
    "name:bpy_x_preferred":[
        "\u09ac\u09b0\u09b8\u09be\u09a6"
    ],
    "name:bul_x_preferred":[
        "\u0411\u043e\u0440\u0441\u0430\u0434"
    ],
    "name:ceb_x_preferred":[
        "Borsad"
    ],
    "name:deu_x_preferred":[
        "Borsad"
    ],
    "name:eng_x_preferred":[
        "Borsad"
    ],
    "name:fra_x_preferred":[
        "Borsad"
    ],
    "name:guj_x_preferred":[
        "\u0aac\u0acb\u0ab0\u0ab8\u0aa6"
    ],
    "name:hin_x_preferred":[
        "\u092c\u094b\u0930\u0938\u0926"
    ],
    "name:ita_x_preferred":[
        "Borsad"
    ],
    "name:jpn_x_preferred":[
        "\u30dc\u30fc\u30b5\u30c3\u30c9"
    ],
    "name:kan_x_preferred":[
        "\u0cac\u0cca\u0cb0\u0ccd\u0cb8\u0cbe\u0ca6\u0ccd"
    ],
    "name:kor_x_preferred":[
        "\ubcf4\ub974\uc0ac\ub4dc"
    ],
    "name:mar_x_preferred":[
        "\u092c\u094b\u0930\u0938\u0926"
    ],
    "name:msa_x_preferred":[
        "Borsad"
    ],
    "name:new_x_preferred":[
        "\u092c\u094b\u0930\u094d\u0938\u093e\u0926"
    ],
    "name:nld_x_preferred":[
        "Borsad"
    ],
    "name:ori_x_preferred":[
        "\u0b2c\u0b4b\u0b30\u0b38\u0b26"
    ],
    "name:por_x_preferred":[
        "Borsad"
    ],
    "name:rus_x_preferred":[
        "\u0411\u043e\u0440\u0441\u0430\u0434"
    ],
    "name:spa_x_preferred":[
        "Borsad"
    ],
    "name:swe_x_preferred":[
        "Borsad"
    ],
    "name:tam_x_preferred":[
        "\u0baa\u0bcb\u0bb0\u0bcd\u0b9a\u0b9f\u0bcd"
    ],
    "name:tel_x_preferred":[
        "\u0c2c\u0c4b\u0c30\u0c4d\u0c38\u0c3e\u0c26\u0c4d"
    ],
    "name:urd_x_preferred":[
        "\u0628\u0648\u0631\u0633\u0627\u062f"
    ],
    "name:vie_x_preferred":[
        "Borsad"
    ],
    "name:zho_x_preferred":[
        "\u535a\u5c14\u8428\u5fb7"
    ],
    "qs:name":"Borsad",
    "qs:name_adm0":"India",
    "qs:name_adm1":"Gujarat",
    "qs:photos_9r":0,
    "qs:photos_sr":0,
    "qs:placetype":"Town",
    "qs:pop_sr":"8",
    "wd:wordcount":506,
    "wof:name":"Borsad",
    "wof:placetype":"locality",
    "wof:population":60271
},
  "geometry": {"coordinates":[72.89816999999999,22.40788],"type":"Point"}
}