{
  "type": "Feature",
  "properties": {
    "iso:country":"IN",
    "ks:ks_name":"Jamola",
    "ks:ks_pop":351,
    "ks:ks_type":"VILLAGE",
    "name:eng_x_preferred":[
        "Jamola"
    ],
    "wof:name":"Jamola",
    "wof:placetype":"locality",
    "wof:population":351
},
  "geometry": {"coordinates":[78.45554300000001,30.204461],"type":"Point"}
}