{
  "type": "Feature",
  "properties": {
    "gn:admin1_code":"36",
    "gn:admin2_code":"155.0",
    "gn:asciiname":"Daryabad",
    "gn:country_code":"IN",
    "gn:dem":152,
    "gn:feature_class":"P",
    "gn:feature_code":"PPL",
    "gn:name":"Dary\u0101b\u0101d",
    "gn:population":0,
    "gn:timezone":"Asia/Kolkata",
    "iso:country":"IN",
    "wof:name":"Daryabad",
    "wof:placetype":"locality"
},
  "geometry": {"coordinates":[79.75105000000001,27.68563],"type":"Point"}
}