{
  "type": "Feature",
  "properties": {
    "iso:country":"IN",
    "ks:ks_name":"Sawant Wasti",
    "ks:ks_pop":268,
    "ks:ks_type":"HABITATION",
    "name:eng_x_preferred":[
        "Sawant Wasti"
    ],
    "wof:name":"Sawant Wasti",
    "wof:placetype":"locality",
    "wof:population":268
},
  "geometry": {"coordinates":[75.36807,17.983661],"type":"Point"}
}