{
  "type": "Feature",
  "properties": {
    "iso:country":"IN",
    "ks:ks_name":"Bidyadharpur-1",
    "ks:ks_pop":198,
    "ks:ks_type":"VILLAGE",
    "name:eng_x_preferred":[
        "Bidyadharpur-1"
    ],
    "wof:name":"Bidyadharpur-1",
    "wof:placetype":"locality",
    "wof:population":198
},
  "geometry": {"coordinates":[87.04728799999999,21.701978],"type":"Point"}
}