{
  "type": "Feature",
  "properties": {
    "gn:admin1_code":"37.0",
    "gn:admin2_code":"417.0",
    "gn:asciiname":"Aded",
    "gn:country_code":"IN",
    "gn:dem":205,
    "gn:feature_class":"P",
    "gn:feature_code":"PPL",
    "gn:name":"\u0100ded",
    "gn:population":0,
    "gn:timezone":"Asia/Kolkata",
    "iso:country":"IN",
    "ks:ks_alt_nam":"\u0100ded",
    "ks:ks_name":"Aded",
    "ks:ks_pop":211,
    "ks:ks_type":"VILLAGE",
    "name:eng_x_preferred":[
        "Aded"
    ],
    "name:eng_x_variant":[
        "\u0100ded"
    ],
    "wof:name":"Aded",
    "wof:placetype":"locality",
    "wof:population":211
},
  "geometry": {"coordinates":[80.68779499999999,18.824573],"type":"Point"}
}