{
  "type": "Feature",
  "properties": {
    "gn:admin1_code":"36.0",
    "gn:admin2_code":"133.0",
    "gn:asciiname":"Tajpur Khurd",
    "gn:country_code":"IN",
    "gn:dem":252,
    "gn:feature_class":"P",
    "gn:feature_code":"PPL",
    "gn:name":"T\u0101jpur Khurd",
    "gn:population":0,
    "gn:timezone":"Asia/Kolkata",
    "iso:country":"IN",
    "name:ara_x_preferred":[
        "\u062a\u0627\u062c\u0628\u0648\u0631 \u062e\u0648\u0631\u062f"
    ],
    "name:ben_bn_x_preferred":[
        "\u09a4\u09be\u099c\u09aa\u09c1\u09b0 \u0996\u09c1\u09b0\u09cd\u09a6"
    ],
    "name:ben_in_x_preferred":[
        "\u09a4\u09be\u099c\u09aa\u09c1\u09b0 \u0996\u09c1\u09b0\u09cd\u09a6"
    ],
    "name:guj_x_preferred":[
        "\u0aa4\u0abe\u0a9c\u0aaa\u0ac1\u0ab0 \u0a96\u0ac1\u0ab0\u0acd\u0aa6"
    ],
    "name:hin_x_preferred":[
        "\u0924\u093e\u091c\u092a\u0941\u0930 \u0916\u0941\u0930\u094d\u0926"
    ],
    "name:kan_x_preferred":[
        "\u0ca4\u0cbe\u0cb9\u0ccd"
    ],
    "name:mal_x_preferred":[
        "\u0d24\u0d3e\u0d1c\u0d4d\u0d2a\u0d42\u0d7c \u0d16\u0d41\u0d7c\u0d26\u0d4d"
    ],
    "name:mar_x_preferred":[
        "\u0924\u093e\u091c\u092a\u0942\u0930 \u0916\u0941\u0930\u094d\u0926"
    ],
    "name:pan_x_preferred":[
        "\u0a24\u0a3e\u0a1c\u0a3c\u0a2a\u0a41\u0a30 \u0a16\u0a41\u0a30\u0a26"
    ],
    "name:tam_x_preferred":[
        "\u0ba4\u0bbe\u0b9c\u0bcd\u0baa\u0bc2\u0bb0\u0bcd \u0b95\u0bc1\u0bb0\u0bcd\u0ba4\u0bcd"
    ],
    "name:tel_x_preferred":[
        "\u0c24\u0c3e\u0c1c\u0c4d"
    ],
    "name:urd_x_preferred":[
        "\u062a\u0627\u062c\u067e\u0648\u0631 \u062e\u0631\u062f"
    ],
    "wof:name":"Tajpur Khurd",
    "wof:placetype":"neighbourhood"
},
  "geometry": {"coordinates":[77.79982,29.59259],"type":"Point"}
}