{
  "type": "Feature",
  "properties": {
    "iso:country":"IN",
    "ks:ks_name":"Koldarwasti",
    "ks:ks_pop":510,
    "ks:ks_type":"HABITATION",
    "name:eng_x_preferred":[
        "Koldarwasti"
    ],
    "wof:name":"Koldarwasti",
    "wof:placetype":"locality",
    "wof:population":510
},
  "geometry": {"coordinates":[75.371101,18.076948],"type":"Point"}
}