{
  "type": "Feature",
  "properties": {
    "gn:admin1_code":"39.0",
    "gn:admin2_code":"66.0",
    "gn:asciiname":"Kanth",
    "gn:country_code":"IN",
    "gn:dem":797,
    "gn:feature_class":"P",
    "gn:feature_code":"PPL",
    "gn:name":"K\u0101nth",
    "gn:population":0,
    "gn:timezone":"Asia/Kolkata",
    "iso:country":"IN",
    "name:bpy_x_preferred":[
        "\u0995\u09be\u09a8\u09cd\u09a5"
    ],
    "name:ceb_x_preferred":[
        "Kanth"
    ],
    "name:ita_x_preferred":[
        "Kanth"
    ],
    "name:new_x_preferred":[
        "\u0915\u0928\u094d\u0925"
    ],
    "name:nld_x_preferred":[
        "Kanth"
    ],
    "name:pol_x_preferred":[
        "Kanth"
    ],
    "name:swe_x_preferred":[
        "Kanth"
    ],
    "wof:name":"Kanth",
    "wof:placetype":"locality"
},
  "geometry": {"coordinates":[79.67428000000002,29.2759],"type":"Point"}
}