{
  "type": "Feature",
  "properties": {
    "iso:country":"IN",
    "ks:ks_name":"Kankadpada",
    "ks:ks_pop":362,
    "ks:ks_type":"VILLAGE",
    "name:eng_x_preferred":[
        "Kankadpada"
    ],
    "wof:name":"Kankadpada",
    "wof:placetype":"locality",
    "wof:population":362
},
  "geometry": {"coordinates":[74.798959,22.696863],"type":"Point"}
}