{
  "type": "Feature",
  "properties": {
    "iso:country":"IN",
    "ks:ks_name":"Sagar",
    "ks:ks_pop":150,
    "ks:ks_type":"VILLAGE",
    "name:eng_x_preferred":[
        "Sagar"
    ],
    "wof:name":"Sagar",
    "wof:placetype":"locality",
    "wof:population":150
},
  "geometry": {"coordinates":[80.224632,29.393372],"type":"Point"}
}