{
  "type": "Feature",
  "properties": {
    "iso:country":"IN",
    "ks:ks_name":"Jalasohuriachak",
    "ks:ks_pop":0,
    "ks:ks_type":"VILLAGE",
    "name:eng_x_preferred":[
        "Jalasohuriachak"
    ],
    "wof:name":"Jalasohuriachak",
    "wof:placetype":"locality",
    "wof:population":0
},
  "geometry": {"coordinates":[87.45912,21.668963],"type":"Point"}
}