{
  "type": "Feature",
  "properties": {
    "iso:country":"IN",
    "ks:ks_name":"Kotha",
    "ks:ks_pop":152,
    "ks:ks_type":"VILLAGE",
    "ks:ks_uagg_main":0,
    "name:eng_x_preferred":[
        "Kotha"
    ],
    "wof:name":"Kotha",
    "wof:placetype":"neighbourhood",
    "wof:population":152
},
  "geometry": {"coordinates":[79.39516999999999,27.842779],"type":"Point"}
}