{
  "type": "Feature",
  "properties": {
    "iso:country":"IN",
    "ks:ks_name":"Bhore Wasti",
    "ks:ks_pop":89,
    "ks:ks_type":"HABITATION",
    "name:eng_x_preferred":[
        "Bhore Wasti"
    ],
    "wof:name":"Bhore Wasti",
    "wof:placetype":"locality",
    "wof:population":89
},
  "geometry": {"coordinates":[75.537128,18.336378],"type":"Point"}
}