{
  "type": "Feature",
  "properties": {
    "iso:country":"IN",
    "ks:ks_name":"Nai Bastti Tola",
    "ks:ks_pop":171,
    "ks:ks_type":"HABITATION",
    "ks:ks_uagg_main":0,
    "name:eng_x_preferred":[
        "Nai Bastti Tola"
    ],
    "wof:name":"Nai Bastti Tola",
    "wof:placetype":"neighbourhood",
    "wof:population":171
},
  "geometry": {"coordinates":[84.030204,26.821647],"type":"Point"}
}