{
  "type": "Feature",
  "properties": {
    "iso:country":"IN",
    "ks:ks_name":"Dakhin Lumding",
    "ks:ks_pop":827,
    "ks:ks_type":"VILLAGE",
    "ks:ks_uagg_main":0,
    "name:eng_x_preferred":[
        "Dakhin Lumding"
    ],
    "wof:name":"Dakhin Lumding",
    "wof:placetype":"neighbourhood",
    "wof:population":827
},
  "geometry": {"coordinates":[93.169393,25.742191],"type":"Point"}
}