{
  "type": "Feature",
  "properties": {
    "iso:country":"IN",
    "ks:ks_name":"Laduapura",
    "ks:ks_pop":30,
    "ks:ks_type":"VILLAGE",
    "name:eng_x_preferred":[
        "Laduapura"
    ],
    "wof:name":"Laduapura",
    "wof:placetype":"locality",
    "wof:population":30
},
  "geometry": {"coordinates":[78.405446,26.201785],"type":"Point"}
}