{
  "type": "Feature",
  "properties": {
    "iso:country":"IN",
    "ks:ks_name":"Uggmgoyyi",
    "ks:ks_pop":127,
    "ks:ks_type":"HABITATION",
    "name:eng_x_preferred":[
        "Uggmgoyyi"
    ],
    "wof:name":"Uggmgoyyi",
    "wof:placetype":"locality",
    "wof:population":127
},
  "geometry": {"coordinates":[82.658271,18.047136],"type":"Point"}
}