{
  "type": "Feature",
  "properties": {
    "gn:admin1_code":"40",
    "gn:admin2_code":"541.0",
    "gn:asciiname":"Kottagudem",
    "gn:country_code":"IN",
    "gn:dem":60,
    "gn:feature_class":"P",
    "gn:feature_code":"PPL",
    "gn:name":"Kottag\u016bdem",
    "gn:population":0,
    "gn:timezone":"Asia/Kolkata",
    "iso:country":"IN",
    "name:ben_x_preferred":[
        "\u0995\u09be\u09a0\u0997\u09cb\u09a6\u09be\u09ae"
    ],
    "name:hin_x_preferred":[
        "\u0915\u094b\u091f\u094d\u091f\u093e\u0917\u0941\u0921\u0947\u092e"
    ],
    "wof:name":"Kottagudem",
    "wof:placetype":"locality"
},
  "geometry": {"coordinates":[80.89704999999999,17.9056],"type":"Point"}
}