{
  "type": "Feature",
  "properties": {
    "iso:country":"IN",
    "ks:ks_name":"Jamuwa",
    "ks:ks_pop":426,
    "ks:ks_type":"VILLAGE",
    "name:eng_x_preferred":[
        "Jamuwa"
    ],
    "wof:name":"Jamuwa",
    "wof:placetype":"locality",
    "wof:population":426
},
  "geometry": {"coordinates":[86.74512900000001,24.367702],"type":"Point"}
}