{
  "type": "Feature",
  "properties": {
    "gn:admin1_code":"25.0",
    "gn:admin2_code":"630.0",
    "gn:asciiname":"Gengisettihalli",
    "gn:country_code":"IN",
    "gn:dem":451,
    "gn:feature_class":"P",
    "gn:feature_code":"PPL",
    "gn:name":"Gengisettihalli",
    "gn:population":0,
    "gn:timezone":"Asia/Kolkata",
    "iso:country":"IN",
    "wof:name":"Gengisettihalli",
    "wof:placetype":"neighbourhood"
},
  "geometry": {"coordinates":[78.20871,12.22548],"type":"Point"}
}