{
  "type": "Feature",
  "properties": {
    "iso:country":"IN",
    "ks:ks_name":"Muslimwadi",
    "ks:ks_pop":108,
    "ks:ks_type":"HABITATION",
    "name:eng_x_preferred":[
        "Muslimwadi"
    ],
    "wof:name":"Muslimwadi",
    "wof:placetype":"locality",
    "wof:population":108
},
  "geometry": {"coordinates":[73.32638900000001,17.453611],"type":"Point"}
}