{
  "type": "Feature",
  "properties": {
    "gn:admin1_code":"12.0",
    "gn:admin2_code":"7.0",
    "gn:asciiname":"Dhar",
    "gn:country_code":"IN",
    "gn:dem":940,
    "gn:feature_class":"P",
    "gn:feature_code":"PPL",
    "gn:name":"Dh\u0101r",
    "gn:population":0,
    "gn:timezone":"Asia/Kolkata",
    "iso:country":"IN",
    "name:ara_x_preferred":[
        "\u062f\u0627\u0631"
    ],
    "name:ben_bn_x_preferred":[
        "\u09a7\u09b0"
    ],
    "name:ben_in_x_preferred":[
        "\u09a7\u09b0"
    ],
    "name:bih_x_preferred":[
        "\u0927\u093e\u0930"
    ],
    "name:cat_x_preferred":[
        "Dhar"
    ],
    "name:ces_x_preferred":[
        "Dh\u00e1r"
    ],
    "name:deu_x_preferred":[
        "Dhar"
    ],
    "name:ell_x_preferred":[
        "\u039d\u03c4\u03b1\u03c1"
    ],
    "name:fra_x_preferred":[
        "Dhar"
    ],
    "name:guj_x_preferred":[
        "\u0aa7\u0abe\u0ab0"
    ],
    "name:hin_x_preferred":[
        "\u0927\u093e\u0930"
    ],
    "name:ita_x_preferred":[
        "Dhar"
    ],
    "name:jpn_x_preferred":[
        "\u30c0\u30fc\u30eb"
    ],
    "name:kan_x_preferred":[
        "\u0ca7\u0cb0\u0ccd"
    ],
    "name:mal_x_preferred":[
        "\u0d27\u0d3e\u0d7c"
    ],
    "name:mar_x_preferred":[
        "\u0927\u093e\u0930"
    ],
    "name:mlg_x_preferred":[
        "Dhar"
    ],
    "name:msa_x_preferred":[
        "Dhar"
    ],
    "name:new_x_preferred":[
        "\u0927\u093e\u0930"
    ],
    "name:nld_x_preferred":[
        "Dhar"
    ],
    "name:pam_x_preferred":[
        "Dhar"
    ],
    "name:pan_x_preferred":[
        "\u0a27\u0a3e\u0a30"
    ],
    "name:pol_x_preferred":[
        "Dhar"
    ],
    "name:por_x_preferred":[
        "Dhar"
    ],
    "name:san_x_preferred":[
        "\u0927\u093e\u0930"
    ],
    "name:spa_x_preferred":[
        "Dhar"
    ],
    "name:swe_x_preferred":[
        "Dhar"
    ],
    "name:tam_x_preferred":[
        "\u0ba4\u0bb0\u0bcd"
    ],
    "name:tel_x_preferred":[
        "\u0c22\u0c30\u0c4d"
    ],
    "name:ukr_x_preferred":[
        "\u0414\u0445\u0430\u0440"
    ],
    "name:urd_x_preferred":[
        "\u062f\u06be\u0627\u0631"
    ],
    "name:urd_x_variant":[
        "\u062f\u06be\u0631"
    ],
    "name:vie_x_preferred":[
        "Dhar"
    ],
    "wof:name":"Dhar",
    "wof:placetype":"locality"
},
  "geometry": {"coordinates":[75.37909000000001,32.60612],"type":"Point"}
}