{
  "type": "Feature",
  "properties": {
    "iso:country":"IN",
    "ks:ks_alt_nam":"Karandipalayam pudur",
    "ks:ks_name":"Karandipalayam Pudur",
    "ks:ks_pop":245,
    "ks:ks_type":"HABITATION",
    "name:eng_x_preferred":[
        "Karandipalayam Pudur"
    ],
    "wof:name":"Karandipalayam Pudur",
    "wof:placetype":"locality",
    "wof:population":245
},
  "geometry": {"coordinates":[77.506057,11.276817],"type":"Point"}
}