{
  "type": "Feature",
  "properties": {
    "iso:country":"IN",
    "ks:ks_name":"Parnagar",
    "ks:ks_pop":284,
    "ks:ks_type":"HABITATION",
    "name:eng_x_preferred":[
        "Parnagar"
    ],
    "wof:name":"Parnagar",
    "wof:placetype":"locality",
    "wof:population":284
},
  "geometry": {"coordinates":[78.476333,10.252524],"type":"Point"}
}