{
  "type": "Feature",
  "properties": {
    "iso:country":"IN",
    "ks:ks_name":"Hosakari",
    "ks:ks_pop":27,
    "ks:ks_type":"HABITATION",
    "name:eng_x_preferred":[
        "Hosakari"
    ],
    "wof:name":"Hosakari",
    "wof:placetype":"locality",
    "wof:population":27
},
  "geometry": {"coordinates":[74.710832,14.064515],"type":"Point"}
}