{
  "type": "Feature",
  "properties": {
    "gn:admin1_code":"11",
    "gn:admin2_code":"23.0",
    "gn:asciiname":"Jungrar",
    "gn:country_code":"IN",
    "gn:dem":2515,
    "gn:feature_class":"P",
    "gn:feature_code":"PPL",
    "gn:name":"Jungr\u0101r",
    "gn:population":0,
    "gn:timezone":"Asia/Kolkata",
    "iso:country":"IN",
    "wof:name":"Jungrar",
    "wof:placetype":"locality"
},
  "geometry": {"coordinates":[76.18595999999999,32.71219],"type":"Point"}
}