{
  "type": "Feature",
  "properties": {
    "gn:admin1_code":"16.0",
    "gn:admin2_code":"523.0",
    "gn:asciiname":"Dakupimpri",
    "gn:country_code":"IN",
    "gn:dem":400,
    "gn:feature_class":"P",
    "gn:feature_code":"PPL",
    "gn:name":"D\u0101kupimpri",
    "gn:population":0,
    "gn:timezone":"Asia/Kolkata",
    "iso:country":"IN",
    "wof:name":"Dakupimpri",
    "wof:placetype":"locality"
},
  "geometry": {"coordinates":[76.33555,19.09736],"type":"Point"}
}