{
  "type": "Feature",
  "properties": {
    "iso:country":"IN",
    "ks:ks_name":"Garadamaha",
    "ks:ks_pop":0,
    "ks:ks_type":"VILLAGE",
    "name:eng_x_preferred":[
        "Garadamaha"
    ],
    "wof:name":"Garadamaha",
    "wof:placetype":"locality",
    "wof:population":0
},
  "geometry": {"coordinates":[83.801508,19.722623],"type":"Point"}
}