{
  "type": "Feature",
  "properties": {
    "iso:country":"IN",
    "ks:ks_name":"Koldhari",
    "ks:ks_pop":240,
    "ks:ks_type":"HABITATION",
    "name:eng_x_preferred":[
        "Koldhari"
    ],
    "wof:name":"Koldhari",
    "wof:placetype":"locality",
    "wof:population":240
},
  "geometry": {"coordinates":[84.189977,22.584824],"type":"Point"}
}