{
  "type": "Feature",
  "properties": {
    "iso:country":"IN",
    "ks:ks_name":"Atarauli Khurd",
    "ks:ks_pop":45,
    "ks:ks_type":"VILLAGE",
    "name:eng_x_preferred":[
        "Atarauli Khurd"
    ],
    "wof:name":"Atarauli Khurd",
    "wof:placetype":"locality",
    "wof:population":45
},
  "geometry": {"coordinates":[83.11081900000001,24.659646],"type":"Point"}
}