{
  "type": "Feature",
  "properties": {
    "iso:country":"IN",
    "ks:ks_name":"Tormekumbri",
    "ks:ks_pop":7,
    "ks:ks_type":"HABITATION",
    "name:eng_x_preferred":[
        "Tormekumbri"
    ],
    "wof:name":"Tormekumbri",
    "wof:placetype":"locality",
    "wof:population":7
},
  "geometry": {"coordinates":[74.69937,14.324989],"type":"Point"}
}