{
  "type": "Feature",
  "properties": {
    "gn:admin1_code":"24",
    "gn:admin2_code":"125.0",
    "gn:asciiname":"Chhota Chora",
    "gn:country_code":"IN",
    "gn:dem":265,
    "gn:feature_class":"P",
    "gn:feature_code":"PPL",
    "gn:name":"Chhota Chora",
    "gn:population":0,
    "gn:timezone":"Asia/Kolkata",
    "iso:country":"IN",
    "wof:name":"Chhota Chora",
    "wof:placetype":"locality"
},
  "geometry": {"coordinates":[74.34193,23.07729],"type":"Point"}
}