{
  "type": "Feature",
  "properties": {
    "iso:country":"IN",
    "ks:ks_alt_nam":"BARAI KA PURWA",
    "ks:ks_name":"Barai Ka Purwa",
    "ks:ks_pop":195,
    "ks:ks_type":"HABITATION",
    "ks:ks_uagg_main":0,
    "name:eng_x_preferred":[
        "Barai Ka Purwa"
    ],
    "wof:name":"Barai Ka Purwa",
    "wof:placetype":"neighbourhood",
    "wof:population":195
},
  "geometry": {"coordinates":[82.021664,26.232844],"type":"Point"}
}