{
  "type": "Feature",
  "properties": {
    "iso:country":"IN",
    "ks:ks_alt_nam":"Dhakane wasti",
    "ks:ks_name":"Dhakane Wasti",
    "ks:ks_pop":150,
    "ks:ks_type":"HABITATION",
    "name:eng_x_preferred":[
        "Dhakane Wasti"
    ],
    "wof:name":"Dhakane Wasti",
    "wof:placetype":"locality",
    "wof:population":150
},
  "geometry": {"coordinates":[74.58851300000001,20.058711],"type":"Point"}
}