{
  "type": "Feature",
  "properties": {
    "iso:country":"IN",
    "ks:ks_name":"Damorni Muvadi",
    "ks:ks_pop":256,
    "ks:ks_type":"HABITATION",
    "name:eng_x_preferred":[
        "Damorni Muvadi"
    ],
    "wof:name":"Damorni Muvadi",
    "wof:placetype":"locality",
    "wof:population":256
},
  "geometry": {"coordinates":[73.66036099999999,23.191],"type":"Point"}
}