{
  "type": "Feature",
  "properties": {
    "iso:country":"IN",
    "ks:ks_name":"Adiwasiwadi",
    "ks:ks_pop":80,
    "ks:ks_type":"HABITATION",
    "name:eng_x_preferred":[
        "Adiwasiwadi"
    ],
    "wof:name":"Adiwasiwadi",
    "wof:placetype":"locality",
    "wof:population":80
},
  "geometry": {"coordinates":[73.289295,19.387606],"type":"Point"}
}