{
  "type": "Feature",
  "properties": {
    "iso:country":"IN",
    "ks:ks_name":"Amri Khat",
    "ks:ks_pop":213,
    "ks:ks_type":"HABITATION",
    "name:eng_x_preferred":[
        "Amri Khat"
    ],
    "wof:name":"Amri Khat",
    "wof:placetype":"locality",
    "wof:population":213
},
  "geometry": {"coordinates":[92.39416900000001,26.063305],"type":"Point"}
}