{
  "type": "Feature",
  "properties": {
    "iso:country":"IN",
    "ks:ks_alt_nam":"DHAVTE VASTI",
    "ks:ks_name":"Dhavte Vasti",
    "ks:ks_pop":105,
    "ks:ks_type":"HABITATION",
    "name:eng_x_preferred":[
        "Dhavte Vasti"
    ],
    "wof:name":"Dhavte Vasti",
    "wof:placetype":"locality",
    "wof:population":105
},
  "geometry": {"coordinates":[74.829838,19.388517],"type":"Point"}
}