{
  "type": "Feature",
  "properties": {
    "gn:admin1_code":"35.0",
    "gn:admin2_code":"427.0",
    "gn:asciiname":"Bijora",
    "gn:country_code":"IN",
    "gn:dem":442,
    "gn:feature_class":"P",
    "gn:feature_code":"PPL",
    "gn:name":"Bijora",
    "gn:population":0,
    "gn:timezone":"Asia/Kolkata",
    "iso:country":"IN",
    "wof:name":"Bijora",
    "wof:placetype":"locality"
},
  "geometry": {"coordinates":[78.91703000000003,23.56957],"type":"Point"}
}