{
  "type": "Feature",
  "properties": {
    "gn:admin1_code":"21.0",
    "gn:admin2_code":"398.0",
    "gn:asciiname":"Gadikamara",
    "gn:country_code":"IN",
    "gn:dem":898,
    "gn:feature_class":"P",
    "gn:feature_code":"PPL",
    "gn:name":"G\u0101dikamara",
    "gn:population":0,
    "gn:timezone":"Asia/Kolkata",
    "iso:country":"IN",
    "wof:name":"Gadikamara",
    "wof:placetype":"locality"
},
  "geometry": {"coordinates":[82.86985,18.58632],"type":"Point"}
}