{
  "type": "Feature",
  "properties": {
    "iso:country":"IN",
    "ks:ks_name":"No.163 Grant",
    "ks:ks_pop":1554,
    "ks:ks_type":"HABITATION",
    "name:eng_x_preferred":[
        "No.163 Grant"
    ],
    "wof:name":"No.163 Grant",
    "wof:placetype":"locality",
    "wof:population":1554
},
  "geometry": {"coordinates":[94.377591,26.679397],"type":"Point"}
}