{
  "type": "Feature",
  "properties": {
    "gn:admin1_code":"19.0",
    "gn:admin2_code":"576.0",
    "gn:asciiname":"Kysarahalli",
    "gn:country_code":"IN",
    "gn:dem":968,
    "gn:feature_class":"P",
    "gn:feature_code":"PPL",
    "gn:name":"Kysarahalli",
    "gn:population":0,
    "gn:timezone":"Asia/Kolkata",
    "iso:country":"IN",
    "ks:ks_name":"Kyasarahalli",
    "ks:ks_pop":123,
    "ks:ks_type":"HABITATION",
    "name:eng_x_preferred":[
        "Kyasarahalli"
    ],
    "name:eng_x_variant":[
        "Kysarahalli"
    ],
    "wof:name":"Kyasarahalli",
    "wof:placetype":"locality",
    "wof:population":123
},
  "geometry": {"coordinates":[75.959444,12.704444],"type":"Point"}
}