{
  "type": "Feature",
  "properties": {
    "iso:country":"IN",
    "ks:ks_name":"Bantia",
    "ks:ks_pop":101,
    "ks:ks_type":"HABITATION",
    "name:eng_x_preferred":[
        "Bantia"
    ],
    "wof:name":"Bantia",
    "wof:placetype":"locality",
    "wof:population":101
},
  "geometry": {"coordinates":[85.432244,22.937829],"type":"Point"}
}