{
  "type": "Feature",
  "properties": {
    "iso:country":"IN",
    "ks:ks_name":"Bakaitari Pt-III",
    "ks:ks_pop":598,
    "ks:ks_type":"VILLAGE",
    "ks:ks_uagg_main":0,
    "name:eng_x_preferred":[
        "Bakaitari Pt-III"
    ],
    "wof:name":"Bakaitari Pt-III",
    "wof:placetype":"neighbourhood",
    "wof:population":598
},
  "geometry": {"coordinates":[90.811734,26.057777],"type":"Point"}
}