{
  "type": "Feature",
  "properties": {
    "gn:admin1_code":"18.0",
    "gn:admin2_code":"296.0",
    "gn:asciiname":"Ukiam",
    "gn:country_code":"IN",
    "gn:dem":110,
    "gn:feature_class":"P",
    "gn:feature_code":"PPL",
    "gn:name":"Ukiam",
    "gn:population":0,
    "gn:timezone":"Asia/Kolkata",
    "iso:country":"IN",
    "wof:name":"Ukiam",
    "wof:placetype":"locality"
},
  "geometry": {"coordinates":[91.32496999999999,25.81635],"type":"Point"}
}