{
  "type": "Feature",
  "properties": {
    "iso:country":"IN",
    "ks:ks_name":"Patharguda",
    "ks:ks_pop":13,
    "ks:ks_type":"HABITATION",
    "name:eng_x_preferred":[
        "Patharguda"
    ],
    "wof:name":"Patharguda",
    "wof:placetype":"locality",
    "wof:population":13
},
  "geometry": {"coordinates":[78.98906599999999,19.321257],"type":"Point"}
}