{
  "type": "Feature",
  "properties": {
    "gn:admin1_code":"2.0",
    "gn:admin2_code":"554",
    "gn:asciiname":"Kanakammachattram",
    "gn:country_code":"IN",
    "gn:dem":56,
    "gn:feature_class":"P",
    "gn:feature_code":"PPL",
    "gn:name":"Kanakammachattram",
    "gn:population":0,
    "gn:timezone":"Asia/Kolkata",
    "iso:country":"IN",
    "name:und_x_variant":[
        "Kanakamachutram",
        "Kanakammachattram"
    ],
    "wof:name":"Kanakammachattram",
    "wof:placetype":"locality"
},
  "geometry": {"coordinates":[79.75057,13.20683],"type":"Point"}
}