{
  "type": "Feature",
  "properties": {
    "iso:country":"IN",
    "ks:ks_name":"Rauthgram Pt III",
    "ks:ks_pop":859,
    "ks:ks_type":"VILLAGE",
    "name:eng_x_preferred":[
        "Rauthgram Pt III"
    ],
    "wof:name":"Rauthgram Pt III",
    "wof:placetype":"locality",
    "wof:population":859
},
  "geometry": {"coordinates":[92.421226,24.77438],"type":"Point"}
}