{
  "type": "Feature",
  "properties": {
    "iso:country":"IN",
    "ks:ks_alt_nam":"NATH PARA",
    "ks:ks_name":"Nath Para",
    "ks:ks_pop":638,
    "ks:ks_type":"HABITATION",
    "name:eng_x_preferred":[
        "Nath Para"
    ],
    "wof:name":"Nath Para",
    "wof:placetype":"locality",
    "wof:population":638
},
  "geometry": {"coordinates":[91.61377899999999,23.893344],"type":"Point"}
}