{
  "type": "Feature",
  "properties": {
    "iso:country":"IN",
    "ks:ks_alt_nam":"madhopur middle harijan tola",
    "ks:ks_name":"Madhopur Middle Harijan Tola",
    "ks:ks_pop":150,
    "ks:ks_type":"HABITATION",
    "name:eng_x_preferred":[
        "Madhopur Middle Harijan Tola"
    ],
    "wof:name":"Madhopur Middle Harijan Tola",
    "wof:placetype":"locality",
    "wof:population":150
},
  "geometry": {"coordinates":[86.52809999999999,24.665691],"type":"Point"}
}