{
  "type": "Feature",
  "properties": {
    "iso:country":"IN",
    "ks:ks_name":"Girijanawada",
    "ks:ks_pop":164,
    "ks:ks_type":"HABITATION",
    "name:eng_x_preferred":[
        "Girijanawada"
    ],
    "wof:name":"Girijanawada",
    "wof:placetype":"locality",
    "wof:population":164
},
  "geometry": {"coordinates":[80.074433,14.822475],"type":"Point"}
}