{
  "type": "Feature",
  "properties": {
    "gn:admin1_code":"11.0",
    "gn:admin2_code":"031",
    "gn:asciiname":"Shilli",
    "gn:country_code":"IN",
    "gn:dem":1290,
    "gn:feature_class":"P",
    "gn:feature_code":"PPL",
    "gn:name":"Shilli",
    "gn:population":0,
    "gn:timezone":"Asia/Kolkata",
    "iso:country":"IN",
    "wof:name":"Shilli",
    "wof:placetype":"locality"
},
  "geometry": {"coordinates":[77.01056,31.15917],"type":"Point"}
}