{
  "type": "Feature",
  "properties": {
    "iso:country":"IN",
    "ks:ks_name":"Dhanaiam",
    "ks:ks_pop":119,
    "ks:ks_type":"VILLAGE",
    "name:eng_x_preferred":[
        "Dhanaiam"
    ],
    "wof:name":"Dhanaiam",
    "wof:placetype":"locality",
    "wof:population":119
},
  "geometry": {"coordinates":[86.849237,22.425633],"type":"Point"}
}