{
  "type": "Feature",
  "properties": {
    "gn:admin1_code":"2.0",
    "gn:admin2_code":"549.0",
    "gn:asciiname":"Chinnaobanayanipalle",
    "gn:country_code":"IN",
    "gn:dem":185,
    "gn:feature_class":"P",
    "gn:feature_code":"PPL",
    "gn:name":"Chinnaoban\u0101yanipalle",
    "gn:population":0,
    "gn:timezone":"Asia/Kolkata",
    "iso:country":"IN",
    "wof:name":"Chinnaobanayanipalle",
    "wof:placetype":"neighbourhood"
},
  "geometry": {"coordinates":[79.18358000000001,15.55709],"type":"Point"}
}