{
  "type": "Feature",
  "properties": {
    "iso:country":"IN",
    "ks:ks_name":"Talwalewasti",
    "ks:ks_pop":157,
    "ks:ks_type":"HABITATION",
    "name:eng_x_preferred":[
        "Talwalewasti"
    ],
    "wof:name":"Talwalewasti",
    "wof:placetype":"locality",
    "wof:population":157
},
  "geometry": {"coordinates":[74.59915100000001,17.536579],"type":"Point"}
}