{
  "type": "Feature",
  "properties": {
    "iso:country":"IN",
    "ks:ks_name":"Kaluthara",
    "ks:ks_pop":560,
    "ks:ks_type":"VILLAGE",
    "name:eng_x_preferred":[
        "Kaluthara"
    ],
    "wof:name":"Kaluthara",
    "wof:placetype":"locality",
    "wof:population":560
},
  "geometry": {"coordinates":[74.03840599999999,24.096397],"type":"Point"}
}