{
  "type": "Feature",
  "properties": {
    "iso:country":"IN",
    "ks:ks_name":"Nethaji Nagar",
    "ks:ks_pop":402,
    "ks:ks_type":"HABITATION",
    "ks:ks_uagg_main":0,
    "name:eng_x_preferred":[
        "Nethaji Nagar"
    ],
    "wof:name":"Nethaji Nagar",
    "wof:placetype":"neighbourhood",
    "wof:population":402
},
  "geometry": {"coordinates":[79.645904,12.784614],"type":"Point"}
}