{
  "type": "Feature",
  "properties": {
    "gn:admin1_code":"36",
    "gn:admin2_code":"195.0",
    "gn:asciiname":"Kalyani",
    "gn:country_code":"IN",
    "gn:dem":70,
    "gn:feature_class":"P",
    "gn:feature_code":"PPL",
    "gn:name":"Kaly\u0101ni",
    "gn:population":0,
    "gn:timezone":"Asia/Kolkata",
    "iso:country":"IN",
    "name:ben_x_preferred":[
        "\u0995\u09b2\u09cd\u09af\u09be\u09a3\u09c0"
    ],
    "name:bih_x_preferred":[
        "\u0915\u0932\u094d\u092f\u093e\u0923\u0940"
    ],
    "name:mal_x_preferred":[
        "\u0d15\u0d32\u0d4d\u0d2f\u0d3e\u0d23\u0d3f"
    ],
    "name:new_x_preferred":[
        "\u0915\u0932\u094d\u092f\u093e\u0923\u0940"
    ],
    "wof:name":"Kalyani",
    "wof:placetype":"locality"
},
  "geometry": {"coordinates":[83.59834000000002,25.87621],"type":"Point"}
}