{
  "type": "Feature",
  "properties": {
    "gn:admin1_code":"16",
    "gn:admin2_code":"509.0",
    "gn:asciiname":"Satara",
    "gn:country_code":"IN",
    "gn:dem":241,
    "gn:feature_class":"P",
    "gn:feature_code":"PPL",
    "gn:name":"Sat\u0101ra",
    "gn:population":0,
    "gn:timezone":"Asia/Kolkata",
    "iso:country":"IN",
    "name:ara_x_preferred":[
        "\u0633\u0627\u062a\u0627\u0631\u0627"
    ],
    "name:ben_bn_x_preferred":[
        "\u09b8\u09be\u09a4\u09be\u09b0\u09be"
    ],
    "name:ben_in_x_preferred":[
        "\u09b8\u09be\u09a4\u09be\u09b0\u09be"
    ],
    "name:bih_x_preferred":[
        "\u0938\u0924\u093e\u0930\u093e"
    ],
    "name:ceb_x_preferred":[
        "Satara"
    ],
    "name:deu_x_preferred":[
        "Satara"
    ],
    "name:guj_x_preferred":[
        "\u0ab8\u0aa4\u0abe\u0ab0\u0abe"
    ],
    "name:hin_x_preferred":[
        "\u0938\u0924\u093e\u0930\u093e"
    ],
    "name:kan_x_preferred":[
        "\u0cb8\u0ca4\u0cbe\u0cb0\u0cbe"
    ],
    "name:mal_x_preferred":[
        "\u0d38\u0d24\u0d3e\u0d30"
    ],
    "name:mar_x_preferred":[
        "\u0938\u093e\u0924\u093e\u0930\u093e"
    ],
    "name:nld_x_preferred":[
        "Satara"
    ],
    "name:pan_x_preferred":[
        "\u0a38\u0a24\u0a3e\u0a30\u0a3e"
    ],
    "name:ron_x_preferred":[
        "Satara"
    ],
    "name:swe_x_preferred":[
        "Satara"
    ],
    "name:tam_x_preferred":[
        "\u0b9a\u0ba4\u0bbe\u0bb0\u0bbe"
    ],
    "name:tel_x_preferred":[
        "\u0c38\u0c24\u0c3e\u0c30\u0c3e"
    ],
    "name:urd_x_preferred":[
        "\u0633\u062a\u0627\u0631\u0627"
    ],
    "wof:name":"Satara",
    "wof:placetype":"locality"
},
  "geometry": {"coordinates":[79.08235999999999,20.41332],"type":"Point"}
}