{
  "type": "Feature",
  "properties": {
    "iso:country":"IN",
    "ks:ks_name":"Donsapara",
    "ks:ks_pop":263,
    "ks:ks_type":"HABITATION",
    "name:eng_x_preferred":[
        "Donsapara"
    ],
    "wof:name":"Donsapara",
    "wof:placetype":"locality",
    "wof:population":263
},
  "geometry": {"coordinates":[90.596306,26.496971],"type":"Point"}
}