{
  "type": "Feature",
  "properties": {
    "iso:country":"IN",
    "ks:ks_alt_nam":"\u0100dhe",
    "ks:ks_name":"Adhe",
    "ks:ks_pop":232,
    "ks:ks_type":"VILLAGE",
    "name:eng_x_preferred":[
        "Adhe"
    ],
    "name:eng_x_variant":[
        "\u0100dhe"
    ],
    "wof:name":"Adhe",
    "wof:placetype":"locality",
    "wof:population":232
},
  "geometry": {"coordinates":[84.19808399999999,23.555322],"type":"Point"}
}