{
  "type": "Feature",
  "properties": {
    "iso:country":"IN",
    "ks:ks_name":"Uttar Anukha",
    "ks:ks_pop":449,
    "ks:ks_type":"VILLAGE",
    "name:eng_x_preferred":[
        "Uttar Anukha"
    ],
    "wof:name":"Uttar Anukha",
    "wof:placetype":"locality",
    "wof:population":449
},
  "geometry": {"coordinates":[87.761976,22.258893],"type":"Point"}
}