{
  "type": "Feature",
  "properties": {
    "iso:country":"IN",
    "ks:ks_name":"China Gangudi",
    "ks:ks_pop":31,
    "ks:ks_type":"HABITATION",
    "name:eng_x_preferred":[
        "China Gangudi"
    ],
    "wof:name":"China Gangudi",
    "wof:placetype":"locality",
    "wof:population":31
},
  "geometry": {"coordinates":[82.96078,18.273177],"type":"Point"}
}