{
  "type": "Feature",
  "properties": {
    "iso:country":"IN",
    "ks:ks_name":"Revri",
    "ks:ks_pop":430,
    "ks:ks_type":"HABITATION",
    "name:eng_x_preferred":[
        "Revri"
    ],
    "wof:name":"Revri",
    "wof:placetype":"locality",
    "wof:population":430
},
  "geometry": {"coordinates":[81.4314,26.3238],"type":"Point"}
}