{
  "type": "Feature",
  "properties": {
    "iso:country":"IN",
    "ks:ks_name":"43 NGC",
    "ks:ks_pop":226,
    "ks:ks_type":"VILLAGE",
    "name:eng_x_preferred":[
        "43 NGC"
    ],
    "wof:name":"43 NGC",
    "wof:placetype":"locality",
    "wof:population":226
},
  "geometry": {"coordinates":[74.344278,29.602006],"type":"Point"}
}