{
  "type": "Feature",
  "properties": {
    "gn:admin1_code":"24.0",
    "gn:admin2_code":"113",
    "gn:asciiname":"Mithriya",
    "gn:country_code":"IN",
    "gn:dem":245,
    "gn:feature_class":"P",
    "gn:feature_code":"PPL",
    "gn:name":"Mithr\u012bya",
    "gn:population":0,
    "gn:timezone":"Asia/Kolkata",
    "iso:country":"IN",
    "name:und_x_variant":[
        "Mithr\u012bya",
        "Mithriya"
    ],
    "wof:name":"Mithriya",
    "wof:placetype":"locality"
},
  "geometry": {"coordinates":[72.78936999999998,27.50086],"type":"Point"}
}