{
  "type": "Feature",
  "properties": {
    "iso:country":"IN",
    "ks:ks_name":"Hiroli",
    "ks:ks_pop":115,
    "ks:ks_type":"VILLAGE",
    "name:eng_x_preferred":[
        "Hiroli"
    ],
    "wof:name":"Hiroli",
    "wof:placetype":"locality",
    "wof:population":115
},
  "geometry": {"coordinates":[81.424195,19.020543],"type":"Point"}
}