{
  "type": "Feature",
  "properties": {
    "iso:country":"IN",
    "ks:ks_name":"Ziaudinpur",
    "ks:ks_type":"VILLAGE",
    "name:eng_x_preferred":[
        "Ziaudinpur"
    ],
    "wof:name":"Ziaudinpur",
    "wof:placetype":"locality"
},
  "geometry": {"coordinates":[76.92119,28.902529],"type":"Point"}
}