{
  "type": "Feature",
  "properties": {
    "iso:country":"IN",
    "ks:ks_name":"1 KNM I-A",
    "ks:ks_pop":72,
    "ks:ks_type":"VILLAGE",
    "name:eng_x_preferred":[
        "1 KNM I-A"
    ],
    "wof:name":"1 KNM I-A",
    "wof:placetype":"locality",
    "wof:population":72
},
  "geometry": {"coordinates":[72.75712300000001,28.912067],"type":"Point"}
}