{
  "type": "Feature",
  "properties": {
    "gn:admin1_code":"19.0",
    "gn:admin2_code":"568.0",
    "gn:asciiname":"Kabbinadukoppa",
    "gn:country_code":"IN",
    "gn:dem":589,
    "gn:feature_class":"P",
    "gn:feature_code":"PPL",
    "gn:name":"Kabbinadukoppa",
    "gn:population":0,
    "gn:timezone":"Asia/Kolkata",
    "iso:country":"IN",
    "ks:ks_name":"Kabbanadakoppa",
    "ks:ks_pop":238,
    "ks:ks_type":"VILLAGE",
    "name:eng_x_preferred":[
        "Kabbanadakoppa"
    ],
    "name:eng_x_variant":[
        "Kabbinadukoppa"
    ],
    "wof:name":"Kabbanadakoppa",
    "wof:placetype":"locality",
    "wof:population":238
},
  "geometry": {"coordinates":[75.002759,14.017741],"type":"Point"}
}