{
  "type": "Feature",
  "properties": {
    "iso:country":"IN",
    "ks:ks_name":"Dharampur Gyani",
    "ks:ks_pop":861,
    "ks:ks_type":"HABITATION",
    "name:eng_x_preferred":[
        "Dharampur Gyani"
    ],
    "wof:name":"Dharampur Gyani",
    "wof:placetype":"locality",
    "wof:population":861
},
  "geometry": {"coordinates":[79.696639,26.746246],"type":"Point"}
}