{
  "type": "Feature",
  "properties": {
    "iso:country":"IN",
    "ks:ks_name":"Achak Purwa",
    "ks:ks_pop":101,
    "ks:ks_type":"HABITATION",
    "name:eng_x_preferred":[
        "Achak Purwa"
    ],
    "wof:name":"Achak Purwa",
    "wof:placetype":"locality",
    "wof:population":101
},
  "geometry": {"coordinates":[80.30078,26.525396],"type":"Point"}
}