{
  "type": "Feature",
  "properties": {
    "iso:country":"IN",
    "ks:ks_name":"Sagadasahi",
    "ks:ks_pop":153,
    "ks:ks_type":"HABITATION",
    "name:eng_x_preferred":[
        "Sagadasahi"
    ],
    "wof:name":"Sagadasahi",
    "wof:placetype":"locality",
    "wof:population":153
},
  "geometry": {"coordinates":[84.470495,20.282834],"type":"Point"}
}