{
  "type": "Feature",
  "properties": {
    "iso:country":"IN",
    "ks:ks_name":"Damodarpur",
    "ks:ks_pop":439,
    "ks:ks_type":"VILLAGE",
    "ks:ks_uagg_main":0,
    "name:eng_x_preferred":[
        "Damodarpur"
    ],
    "wof:name":"Damodarpur",
    "wof:placetype":"neighbourhood",
    "wof:population":439
},
  "geometry": {"coordinates":[87.6285,22.43261],"type":"Point"}
}