{
  "type": "Feature",
  "properties": {
    "iso:country":"IN",
    "ks:ks_name":"Maduranpudukkottai",
    "ks:ks_pop":179,
    "ks:ks_type":"HABITATION",
    "name:eng_x_preferred":[
        "Maduranpudukkottai"
    ],
    "wof:name":"Maduranpudukkottai",
    "wof:placetype":"locality",
    "wof:population":179
},
  "geometry": {"coordinates":[78.98763700000001,10.742414],"type":"Point"}
}