{
  "type": "Feature",
  "properties": {
    "gn:admin1_code":"19.0",
    "gn:admin2_code":"574.0",
    "gn:asciiname":"Gejjegaranahalli",
    "gn:country_code":"IN",
    "gn:dem":864,
    "gn:feature_class":"P",
    "gn:feature_code":"PPL",
    "gn:name":"Gejjegaranahalli",
    "gn:population":0,
    "gn:timezone":"Asia/Kolkata",
    "iso:country":"IN",
    "ks:ks_name":"Gejjegaranahalli",
    "ks:ks_pop":334,
    "ks:ks_type":"VILLAGE",
    "name:eng_x_preferred":[
        "Gejjegaranahalli"
    ],
    "wof:name":"Gejjegaranahalli",
    "wof:placetype":"locality",
    "wof:population":334
},
  "geometry": {"coordinates":[76.338189,12.936454],"type":"Point"}
}