{
  "type": "Feature",
  "properties": {
    "iso:country":"IN",
    "ks:ks_name":"Dhangarawadi",
    "ks:ks_pop":78,
    "ks:ks_type":"HABITATION",
    "name:eng_x_preferred":[
        "Dhangarawadi"
    ],
    "wof:name":"Dhangarawadi",
    "wof:placetype":"locality",
    "wof:population":78
},
  "geometry": {"coordinates":[73.365611,17.124365],"type":"Point"}
}