{
  "type": "Feature",
  "properties": {
    "gn:admin1_code":"18",
    "gn:admin2_code":"297.0",
    "gn:asciiname":"Mawlyngkhung",
    "gn:country_code":"IN",
    "gn:dem":1012,
    "gn:feature_class":"P",
    "gn:feature_code":"PPL",
    "gn:name":"Mawlyngkhung",
    "gn:population":0,
    "gn:timezone":"Asia/Kolkata",
    "iso:country":"IN",
    "name:und_x_variant":[
        "Mawiyngkhung",
        "Mawlyngkhung"
    ],
    "wof:name":"Mawlyngkhung",
    "wof:placetype":"locality"
},
  "geometry": {"coordinates":[91.90492,25.66942],"type":"Point"}
}