{
  "type": "Feature",
  "properties": {
    "iso:country":"IN",
    "ks:ks_name":"Maravanvayal",
    "ks:ks_pop":249,
    "ks:ks_type":"HABITATION",
    "name:eng_x_preferred":[
        "Maravanvayal"
    ],
    "wof:name":"Maravanvayal",
    "wof:placetype":"locality",
    "wof:population":249
},
  "geometry": {"coordinates":[78.97707200000001,10.045738],"type":"Point"}
}