{
  "type": "Feature",
  "properties": {
    "iso:country":"IN",
    "ks:ks_alt_nam":"Sesh\u0101chalam Extension Reserved Forest",
    "ks:ks_alt_nam_2":"Seshachalam Extension Reserved Forest",
    "ks:ks_name":"Seshachalam Extension Reserved",
    "ks:ks_type":"VILLAGE",
    "name:eng_x_preferred":[
        "Seshachalam Extension Reserved"
    ],
    "name:eng_x_variant":[
        "Sesh\u0101chalam Extension Reserved Forest",
        "Seshachalam Extension Reserved Forest"
    ],
    "wof:name":"Seshachalam Extension Reserved",
    "wof:placetype":"locality"
},
  "geometry": {"coordinates":[79.026275,13.965857],"type":"Point"}
}