{
  "type": "Feature",
  "properties": {
    "gn:admin1_code":"16.0",
    "gn:admin2_code":"513",
    "gn:asciiname":"Kekarjavla",
    "gn:country_code":"IN",
    "gn:dem":413,
    "gn:feature_class":"P",
    "gn:feature_code":"PPL",
    "gn:name":"Kekarjavla",
    "gn:population":0,
    "gn:timezone":"Asia/Kolkata",
    "iso:country":"IN",
    "name:und_x_variant":[
        "Kokarjaola"
    ],
    "wof:name":"Kekarjavla",
    "wof:placetype":"locality"
},
  "geometry": {"coordinates":[76.50230000000001,19.18928],"type":"Point"}
}