{
  "type": "Feature",
  "properties": {
    "gn:admin1_code":"19.0",
    "gn:admin2_code":"573.0",
    "gn:asciiname":"Somanahalli",
    "gn:country_code":"IN",
    "gn:dem":882,
    "gn:feature_class":"P",
    "gn:feature_code":"PPL",
    "gn:name":"Somanahalli",
    "gn:population":0,
    "gn:timezone":"Asia/Kolkata",
    "iso:country":"IN",
    "ks:ks_alt_nam":"somana hally",
    "ks:ks_name":"Somana Hally",
    "ks:ks_pop":220,
    "ks:ks_type":"HABITATION",
    "name:eng_x_preferred":[
        "Somana Hally"
    ],
    "name:eng_x_variant":[
        "Somanahalli"
    ],
    "wof:name":"Somana Hally",
    "wof:placetype":"locality",
    "wof:population":220
},
  "geometry": {"coordinates":[76.682154,12.712024],"type":"Point"}
}