{
  "type": "Feature",
  "properties": {
    "iso:country":"IN",
    "ks:ks_alt_nam":"Molandubi pt II",
    "ks:ks_name":"Molandubi Pt Ii",
    "ks:ks_pop":65,
    "ks:ks_type":"HABITATION",
    "name:eng_x_preferred":[
        "Molandubi Pt Ii"
    ],
    "wof:name":"Molandubi Pt Ii",
    "wof:placetype":"locality",
    "wof:population":65
},
  "geometry": {"coordinates":[90.194857,26.380346],"type":"Point"}
}