{
  "type": "Feature",
  "properties": {
    "iso:country":"IN",
    "ks:ks_name":"Dahitane",
    "ks:ks_pop":1203,
    "ks:ks_type":"VILLAGE",
    "name:eng_x_preferred":[
        "Dahitane"
    ],
    "wof:name":"Dahitane",
    "wof:placetype":"locality",
    "wof:population":1203
},
  "geometry": {"coordinates":[75.964367,17.70361],"type":"Point"}
}