{
  "type": "Feature",
  "properties": {
    "gn:admin1_code":"35",
    "gn:admin2_code":"467.0",
    "gn:asciiname":"Phopnar Kalan",
    "gn:country_code":"IN",
    "gn:dem":271,
    "gn:feature_class":"P",
    "gn:feature_code":"PPL",
    "gn:name":"Phopn\u0101r Kal\u0101n",
    "gn:population":0,
    "gn:timezone":"Asia/Kolkata",
    "iso:country":"IN",
    "name:und_x_variant":[
        "Phopn\u0101r",
        "Phopn\u0101r Kal\u0101n"
    ],
    "wof:name":"Phopnar Kalan",
    "wof:placetype":"locality"
},
  "geometry": {"coordinates":[76.32683,21.23654],"type":"Point"}
}