{
  "type": "Feature",
  "properties": {
    "gn:admin1_code":"35",
    "gn:admin2_code":"467.0",
    "gn:asciiname":"Phopnar Kalan",
    "gn:country_code":"IN",
    "gn:dem":271,
    "gn:feature_class":"P",
    "gn:feature_code":"PPL",
    "gn:name":"Phopn\u0101r Kal\u0101n",
    "gn:population":0,
    "gn:timezone":"Asia/Kolkata",
    "iso:country":"IN",
    "ks:ks_name":"Fopnar Kalan",
    "ks:ks_pop":6459,
    "ks:ks_type":"VILLAGE",
    "name:eng_x_preferred":[
        "Fopnar Kalan"
    ],
    "name:eng_x_variant":[
        "Phopnar Kalan"
    ],
    "name:und_x_variant":[
        "Phopn\u0101r",
        "Phopn\u0101r Kal\u0101n"
    ],
    "wof:name":"Fopnar Kalan",
    "wof:placetype":"locality",
    "wof:population":6459
},
  "geometry": {"coordinates":[76.314414,21.236061],"type":"Point"}
}