{
  "type": "Feature",
  "properties": {
    "iso:country":"IN",
    "ks:ks_name":"Dulal Madhab",
    "ks:ks_pop":727,
    "ks:ks_type":"VILLAGE",
    "ks:ks_uagg_main":0,
    "name:eng_x_preferred":[
        "Dulal Madhab"
    ],
    "wof:name":"Dulal Madhab",
    "wof:placetype":"neighbourhood",
    "wof:population":727
},
  "geometry": {"coordinates":[92.965042,26.58826],"type":"Point"}
}