{
  "type": "Feature",
  "properties": {
    "iso:country":"IN",
    "ks:ks_name":"Uttar Pakhirbada",
    "ks:ks_pop":594,
    "ks:ks_type":"HABITATION",
    "name:eng_x_preferred":[
        "Uttar Pakhirbada"
    ],
    "wof:name":"Uttar Pakhirbada",
    "wof:placetype":"locality",
    "wof:population":594
},
  "geometry": {"coordinates":[92.029785,24.326189],"type":"Point"}
}