{
  "type": "Feature",
  "properties": {
    "iso:country":"IN",
    "ks:ks_name":"Pashtepada",
    "ks:ks_pop":119,
    "ks:ks_type":"HABITATION",
    "name:eng_x_preferred":[
        "Pashtepada"
    ],
    "wof:name":"Pashtepada",
    "wof:placetype":"locality",
    "wof:population":119
},
  "geometry": {"coordinates":[73.41333299999999,19.349444],"type":"Point"}
}