{
  "type": "Feature",
  "properties": {
    "iso:country":"IN",
    "ks:ks_name":"Thakurnuapada",
    "ks:ks_pop":2570,
    "ks:ks_type":"VILLAGE",
    "ks:ks_uagg_main":0,
    "name:eng_x_preferred":[
        "Thakurnuapada"
    ],
    "wof:name":"Thakurnuapada",
    "wof:placetype":"neighbourhood",
    "wof:population":2570
},
  "geometry": {"coordinates":[82.533253,20.810016],"type":"Point"}
}