{
  "type": "Feature",
  "properties": {
    "iso:country":"IN",
    "ks:ks_name":"Karivane",
    "ks:ks_pop":258,
    "ks:ks_type":"HABITATION",
    "name:eng_x_preferred":[
        "Karivane"
    ],
    "wof:name":"Karivane",
    "wof:placetype":"locality",
    "wof:population":258
},
  "geometry": {"coordinates":[73.451362,16.232729],"type":"Point"}
}