{
  "type": "Feature",
  "properties": {
    "iso:country":"IN",
    "ks:ks_name":"Madan Pokhra",
    "ks:ks_pop":20,
    "ks:ks_type":"HABITATION",
    "name:eng_x_preferred":[
        "Madan Pokhra"
    ],
    "wof:name":"Madan Pokhra",
    "wof:placetype":"locality",
    "wof:population":20
},
  "geometry": {"coordinates":[80.50405499999999,24.468178],"type":"Point"}
}