{
  "type": "Feature",
  "properties": {
    "iso:country":"IN",
    "ks:ks_alt_nam":"Brahmanpally thanda",
    "ks:ks_name":"Brahmanpally Thanda",
    "ks:ks_pop":115,
    "ks:ks_type":"HABITATION",
    "ks:ks_uagg_main":0,
    "name:eng_x_preferred":[
        "Brahmanpally Thanda"
    ],
    "wof:name":"Brahmanpally Thanda",
    "wof:placetype":"neighbourhood",
    "wof:population":115
},
  "geometry": {"coordinates":[77.819616,18.27104],"type":"Point"}
}