{
  "type": "Feature",
  "properties": {
    "iso:country":"IN",
    "ks:ks_name":"Kalabanara",
    "ks:ks_pop":538,
    "ks:ks_type":"VILLAGE",
    "name:eng_x_preferred":[
        "Kalabanara"
    ],
    "wof:name":"Kalabanara",
    "wof:placetype":"locality",
    "wof:population":538
},
  "geometry": {"coordinates":[72.499211,26.268183],"type":"Point"}
}