{
  "type": "Feature",
  "properties": {
    "iso:country":"IN",
    "ks:ks_name":"Setti Vayal",
    "ks:ks_pop":102,
    "ks:ks_type":"HABITATION",
    "name:eng_x_preferred":[
        "Setti Vayal"
    ],
    "wof:name":"Setti Vayal",
    "wof:placetype":"locality",
    "wof:population":102
},
  "geometry": {"coordinates":[79.004727,10.145193],"type":"Point"}
}