{
  "type": "Feature",
  "properties": {
    "gn:admin1_code":"16.0",
    "gn:admin2_code":"526",
    "gn:asciiname":"Jamgaon Buzurg",
    "gn:country_code":"IN",
    "gn:dem":469,
    "gn:feature_class":"P",
    "gn:feature_code":"PPL",
    "gn:name":"J\u0101mgaon Buzurg",
    "gn:population":0,
    "gn:timezone":"Asia/Kolkata",
    "iso:country":"IN",
    "wof:name":"Jamgaon Buzurg",
    "wof:placetype":"locality"
},
  "geometry": {"coordinates":[75.68704,17.57063],"type":"Point"}
}