{
  "type": "Feature",
  "properties": {
    "iso:country":"IN",
    "ks:ks_name":"Teleria",
    "ks:ks_pop":1201,
    "ks:ks_type":"VILLAGE",
    "name:eng_x_preferred":[
        "Teleria"
    ],
    "wof:name":"Teleria",
    "wof:placetype":"locality",
    "wof:population":1201
},
  "geometry": {"coordinates":[91.09430399999999,26.394549],"type":"Point"}
}