{
  "type": "Feature",
  "properties": {
    "iso:country":"IN",
    "ks:ks_name":"Bhonaislam Nagar",
    "ks:ks_pop":3197,
    "ks:ks_type":"VILLAGE",
    "ks:ks_uagg_main":0,
    "name:eng_x_preferred":[
        "Bhonaislam Nagar"
    ],
    "wof:name":"Bhonaislam Nagar",
    "wof:placetype":"neighbourhood",
    "wof:population":3197
},
  "geometry": {"coordinates":[79.154205,29.1694],"type":"Point"}
}