{
  "type": "Feature",
  "properties": {
    "gn:admin1_code":"39",
    "gn:admin2_code":"61.0",
    "gn:asciiname":"Patoti",
    "gn:country_code":"IN",
    "gn:dem":1320,
    "gn:feature_class":"P",
    "gn:feature_code":"PPL",
    "gn:name":"Patoti",
    "gn:population":0,
    "gn:timezone":"Asia/Kolkata",
    "iso:country":"IN",
    "ks:ks_name":"Patoti",
    "ks:ks_pop":41,
    "ks:ks_type":"VILLAGE",
    "name:eng_x_preferred":[
        "Patoti"
    ],
    "wof:name":"Patoti",
    "wof:placetype":"locality",
    "wof:population":41
},
  "geometry": {"coordinates":[78.904146,29.856229],"type":"Point"}
}