{
  "type": "Feature",
  "properties": {
    "gn:admin1_code":"21.0",
    "gn:admin2_code":"396.0",
    "gn:asciiname":"Sirasapadu",
    "gn:country_code":"IN",
    "gn:dem":398,
    "gn:feature_class":"P",
    "gn:feature_code":"PPL",
    "gn:name":"Siras\u0101p\u0101du",
    "gn:population":0,
    "gn:timezone":"Asia/Kolkata",
    "iso:country":"IN",
    "ks:ks_name":"Sirisapadu",
    "ks:ks_pop":76,
    "ks:ks_type":"VILLAGE",
    "name:eng_x_preferred":[
        "Sirisapadu"
    ],
    "name:eng_x_variant":[
        "Sirasapadu"
    ],
    "wof:name":"Sirisapadu",
    "wof:placetype":"locality",
    "wof:population":76
},
  "geometry": {"coordinates":[83.33487100000001,19.251635],"type":"Point"}
}