{
  "type": "Feature",
  "properties": {
    "gn:admin1_code":"21.0",
    "gn:admin2_code":"396.0",
    "gn:asciiname":"Sirasapadu",
    "gn:country_code":"IN",
    "gn:dem":398,
    "gn:feature_class":"P",
    "gn:feature_code":"PPL",
    "gn:name":"Siras\u0101p\u0101du",
    "gn:population":0,
    "gn:timezone":"Asia/Kolkata",
    "iso:country":"IN",
    "wof:name":"Sirasapadu",
    "wof:placetype":"locality"
},
  "geometry": {"coordinates":[83.3349,19.25151],"type":"Point"}
}