{
  "type": "Feature",
  "properties": {
    "iso:country":"IN",
    "ks:ks_name":"Khamancheru",
    "ks:ks_pop":1290,
    "ks:ks_type":"VILLAGE",
    "name:eng_x_preferred":[
        "Khamancheru"
    ],
    "wof:name":"Khamancheru",
    "wof:placetype":"locality",
    "wof:population":1290
},
  "geometry": {"coordinates":[80.012829,19.446895],"type":"Point"}
}