{
  "type": "Feature",
  "properties": {
    "gn:admin1_code":"38",
    "gn:admin2_code":"357.0",
    "gn:asciiname":"Maubhandar",
    "gn:country_code":"IN",
    "gn:dem":104,
    "gn:feature_class":"P",
    "gn:feature_code":"PPL",
    "gn:name":"Maubhand\u0101r",
    "gn:population":0,
    "gn:timezone":"Asia/Kolkata",
    "iso:country":"IN",
    "ks:ks_alt_nam":"Maubhand\u0101r",
    "ks:ks_name":"Maubhandar",
    "ks:ks_type":"VILLAGE",
    "ks:ks_uagg_main":0,
    "name:eng_x_preferred":[
        "Maubhandar"
    ],
    "name:eng_x_variant":[
        "Maubhand\u0101r"
    ],
    "name:und_x_variant":[
        "Moubhander",
        "Maubhand\u0101r"
    ],
    "wof:name":"Maubhandar",
    "wof:placetype":"locality"
},
  "geometry": {"coordinates":[86.4472,22.600129],"type":"Point"}
}