{
  "type": "Feature",
  "properties": {
    "iso:country":"IN",
    "ks:ks_alt_nam":"CHAK BHAGWANWALA",
    "ks:ks_name":"Chak Bhagwanwala",
    "ks:ks_pop":37,
    "ks:ks_type":"HABITATION",
    "name:eng_x_preferred":[
        "Chak Bhagwanwala"
    ],
    "wof:name":"Chak Bhagwanwala",
    "wof:placetype":"locality",
    "wof:population":37
},
  "geometry": {"coordinates":[73.952147,29.180914],"type":"Point"}
}