{
  "type": "Feature",
  "properties": {
    "gn:admin1_code":"35",
    "gn:admin2_code":"430.0",
    "gn:asciiname":"Pachpahara",
    "gn:country_code":"IN",
    "gn:dem":312,
    "gn:feature_class":"P",
    "gn:feature_code":"PPL",
    "gn:name":"Pachpahara",
    "gn:population":0,
    "gn:timezone":"Asia/Kolkata",
    "iso:country":"IN",
    "ks:ks_name":"Pachpahara",
    "ks:ks_pop":936,
    "ks:ks_type":"VILLAGE",
    "name:eng_x_preferred":[
        "Pachpahara"
    ],
    "wof:name":"Pachpahara",
    "wof:placetype":"locality",
    "wof:population":936
},
  "geometry": {"coordinates":[81.567426,24.698014],"type":"Point"}
}