{
  "type": "Feature",
  "properties": {
    "iso:country":"IN",
    "ks:ks_name":"Vijaypur",
    "ks:ks_pop":332,
    "ks:ks_type":"HABITATION",
    "name:eng_x_preferred":[
        "Vijaypur"
    ],
    "wof:name":"Vijaypur",
    "wof:placetype":"locality",
    "wof:population":332
},
  "geometry": {"coordinates":[78.948317,25.077396],"type":"Point"}
}