{
  "type": "Feature",
  "properties": {
    "iso:country":"IN",
    "ks:ks_name":"Puliboinapalle",
    "ks:ks_pop":92,
    "ks:ks_type":"VILLAGE",
    "ks:ks_uagg_main":0,
    "name:eng_x_preferred":[
        "Puliboinapalle"
    ],
    "wof:name":"Puliboinapalle",
    "wof:placetype":"neighbourhood",
    "wof:population":92
},
  "geometry": {"coordinates":[80.790688,18.069669],"type":"Point"}
}