{
  "type": "Feature",
  "properties": {
    "iso:country":"IN",
    "ks:ks_name":"Kudabeeru",
    "ks:ks_pop":160,
    "ks:ks_type":"HABITATION",
    "name:eng_x_preferred":[
        "Kudabeeru"
    ],
    "wof:name":"Kudabeeru",
    "wof:placetype":"locality",
    "wof:population":160
},
  "geometry": {"coordinates":[82.771119,18.166602],"type":"Point"}
}