{
  "type": "Feature",
  "properties": {
    "gn:admin1_code":"23.0",
    "gn:admin2_code":"42.0",
    "gn:asciiname":"Bhagpur",
    "gn:country_code":"IN",
    "gn:dem":216,
    "gn:feature_class":"P",
    "gn:feature_code":"PPL",
    "gn:name":"Bh\u0101gpur",
    "gn:population":0,
    "gn:timezone":"Asia/Kolkata",
    "iso:country":"IN",
    "name:und_x_variant":[
        "Bh\u0101gpur",
        "Gagra"
    ],
    "wof:name":"Bhagpur",
    "wof:placetype":"locality"
},
  "geometry": {"coordinates":[75.15321,30.92141],"type":"Point"}
}