{
  "type": "Feature",
  "properties": {
    "iso:country":"IN",
    "ks:ks_name":"Karlo",
    "ks:ks_pop":6,
    "ks:ks_type":"HABITATION",
    "name:eng_x_preferred":[
        "Karlo"
    ],
    "wof:name":"Karlo",
    "wof:placetype":"locality",
    "wof:population":6
},
  "geometry": {"coordinates":[86.13097500000001,24.055532],"type":"Point"}
}