{
  "type": "Feature",
  "properties": {
    "iso:country":"IN",
    "ks:ks_name":"Kakaravada",
    "ks:ks_pop":1292,
    "ks:ks_type":"VILLAGE",
    "ks:ks_uagg_main":0,
    "name:eng_x_preferred":[
        "Kakaravada"
    ],
    "wof:name":"Kakaravada",
    "wof:placetype":"neighbourhood",
    "wof:population":1292
},
  "geometry": {"coordinates":[81.145099,16.410944],"type":"Point"}
}