{
  "type": "Feature",
  "properties": {
    "iso:country":"IN",
    "ks:ks_name":"Anvarpura",
    "ks:ks_pop":650,
    "ks:ks_type":"HABITATION",
    "name:eng_x_preferred":[
        "Anvarpura"
    ],
    "wof:name":"Anvarpura",
    "wof:placetype":"locality",
    "wof:population":650
},
  "geometry": {"coordinates":[72.81311100000001,23.409944],"type":"Point"}
}