{
  "type": "Feature",
  "properties": {
    "gn:admin1_code":"37",
    "gn:admin2_code":"407.0",
    "gn:asciiname":"Talpur",
    "gn:country_code":"IN",
    "gn:dem":356,
    "gn:feature_class":"P",
    "gn:feature_code":"PPL",
    "gn:name":"T\u0101lpur",
    "gn:population":0,
    "gn:timezone":"Asia/Kolkata",
    "iso:country":"IN",
    "name:cat_x_preferred":[
        "Talpur"
    ],
    "name:snd_x_preferred":[
        "\u067d\u0627\u0644\u067e\u0631"
    ],
    "name:urd_x_preferred":[
        "\u062a\u0627\u0644\u067e\u0648\u0631"
    ],
    "wof:name":"Talpur",
    "wof:placetype":"locality"
},
  "geometry": {"coordinates":[81.23028000000002,22.03478],"type":"Point"}
}