{
  "type": "Feature",
  "properties": {
    "iso:country":"IN",
    "ks:ks_name":"Hiremarthur",
    "ks:ks_pop":62,
    "ks:ks_type":"HABITATION",
    "name:eng_x_preferred":[
        "Hiremarthur"
    ],
    "wof:name":"Hiremarthur",
    "wof:placetype":"locality",
    "wof:population":62
},
  "geometry": {"coordinates":[74.955613,14.098313],"type":"Point"}
}