{
  "type": "Feature",
  "properties": {
    "gn:country":"IN",
    "gn:fcode":"PPL",
    "gn:pop":29995,
    "iso:country":"IN",
    "name:ben_x_preferred":[
        "\u0986\u09ae\u09b2\u09be"
    ],
    "name:bul_x_preferred":[
        "\u0410\u043c\u043b\u0430"
    ],
    "name:eng_x_preferred":[
        "Amla"
    ],
    "name:fas_x_preferred":[
        "\u0627\u0645\u0644\u0627\u060c \u0645\u062f\u0647\u06cc\u0627 \u067e\u0631\u0627\u062f\u0634"
    ],
    "name:hin_x_preferred":[
        "\u0906\u092e\u0932\u093e"
    ],
    "name:ita_x_preferred":[
        "Amla"
    ],
    "name:min_x_preferred":[
        "Amla"
    ],
    "name:msa_x_preferred":[
        "Amla"
    ],
    "name:nld_x_preferred":[
        "Amla"
    ],
    "name:por_x_preferred":[
        "Amla"
    ],
    "name:spa_x_preferred":[
        "Amla"
    ],
    "name:swe_x_preferred":[
        "Amla"
    ],
    "name:vie_x_preferred":[
        "Amla"
    ],
    "name:zho_x_preferred":[
        "\u963f\u59c6\u62c9"
    ],
    "qs:name":"Amla",
    "qs:name_adm0":"India",
    "qs:name_adm1":"Madhya Pradesh",
    "qs:photos_9k":1,
    "qs:photos_9r":1,
    "qs:photos_all":1,
    "qs:photos_sr":0,
    "qs:placetype":"Town",
    "qs:pop_sr":"7",
    "wd:wordcount":44,
    "wof:name":"Amla",
    "wof:placetype":"locality",
    "wof:population":29995
},
  "geometry": {"coordinates":[78.12766000000001,21.92429],"type":"Point"}
}