{
  "type": "Feature",
  "properties": {
    "iso:country":"IN",
    "ks:ks_name":"Imliya",
    "ks:ks_pop":74,
    "ks:ks_type":"HABITATION",
    "name:eng_x_preferred":[
        "Imliya"
    ],
    "wof:name":"Imliya",
    "wof:placetype":"locality",
    "wof:population":74
},
  "geometry": {"coordinates":[79.815273,23.110255],"type":"Point"}
}