{
  "type": "Feature",
  "properties": {
    "iso:country":"IN",
    "ks:ks_name":"Aalesur",
    "ks:ks_pop":293,
    "ks:ks_type":"HABITATION",
    "name:eng_x_preferred":[
        "Aalesur"
    ],
    "wof:name":"Aalesur",
    "wof:placetype":"locality",
    "wof:population":293
},
  "geometry": {"coordinates":[78.88145,21.731937],"type":"Point"}
}