{
  "type": "Feature",
  "properties": {
    "iso:country":"IN",
    "ks:ks_alt_nam":"Beemudi tanda",
    "ks:ks_name":"Beemudi Tanda",
    "ks:ks_pop":120,
    "ks:ks_type":"HABITATION",
    "name:eng_x_preferred":[
        "Beemudi Tanda"
    ],
    "wof:name":"Beemudi Tanda",
    "wof:placetype":"locality",
    "wof:population":120
},
  "geometry": {"coordinates":[78.108582,16.509226],"type":"Point"}
}