{
  "type": "Feature",
  "properties": {
    "gn:admin1_code":"19.0",
    "gn:admin2_code":"555.0",
    "gn:asciiname":"Mudenkop",
    "gn:country_code":"IN",
    "gn:dem":603,
    "gn:feature_class":"P",
    "gn:feature_code":"PPL",
    "gn:name":"Mudenkop",
    "gn:population":0,
    "gn:timezone":"Asia/Kolkata",
    "iso:country":"IN",
    "wof:name":"Mudenkop",
    "wof:placetype":"locality"
},
  "geometry": {"coordinates":[75.30403000000003,15.86872],"type":"Point"}
}