{
  "type": "Feature",
  "properties": {
    "iso:country":"IN",
    "ks:ks_name":"Masudanpur Arazi",
    "ks:ks_pop":319,
    "ks:ks_type":"VILLAGE",
    "ks:ks_uagg_main":0,
    "name:eng_x_preferred":[
        "Masudanpur Arazi"
    ],
    "wof:name":"Masudanpur Arazi",
    "wof:placetype":"neighbourhood",
    "wof:population":319
},
  "geometry": {"coordinates":[86.705162,25.178529],"type":"Point"}
}