{
  "type": "Feature",
  "properties": {
    "gn:admin1_code":"23",
    "gn:admin2_code":"40.0",
    "gn:asciiname":"Chanarthal Khurd",
    "gn:country_code":"IN",
    "gn:dem":261,
    "gn:feature_class":"P",
    "gn:feature_code":"PPL",
    "gn:name":"Chanarthal Khurd",
    "gn:population":0,
    "gn:timezone":"Asia/Kolkata",
    "iso:country":"IN",
    "wof:name":"Chanarthal Khurd",
    "wof:placetype":"locality"
},
  "geometry": {"coordinates":[76.35608000000001,30.52756],"type":"Point"}
}