{
  "type": "Feature",
  "properties": {
    "gn:admin1_code":"37",
    "gn:admin2_code":"408.0",
    "gn:asciiname":"Bhursatola",
    "gn:country_code":"IN",
    "gn:dem":396,
    "gn:feature_class":"P",
    "gn:feature_code":"PPL",
    "gn:name":"Bhurs\u0101tola",
    "gn:population":0,
    "gn:timezone":"Asia/Kolkata",
    "iso:country":"IN",
    "ks:ks_alt_nam":"Bhurs\u0101tola",
    "ks:ks_name":"Bhursatola",
    "ks:ks_type":"VILLAGE",
    "name:eng_x_preferred":[
        "Bhursatola"
    ],
    "name:eng_x_variant":[
        "Bhurs\u0101tola"
    ],
    "wof:name":"Bhursatola",
    "wof:placetype":"locality"
},
  "geometry": {"coordinates":[80.735946,20.564086],"type":"Point"}
}