{
  "type": "Feature",
  "properties": {
    "iso:country":"IN",
    "ks:ks_name":"Uskuda",
    "ks:ks_pop":567,
    "ks:ks_type":"VILLAGE",
    "name:eng_x_preferred":[
        "Uskuda"
    ],
    "wof:name":"Uskuda",
    "wof:placetype":"locality",
    "wof:population":567
},
  "geometry": {"coordinates":[85.161063,21.738155],"type":"Point"}
}