{
  "type": "Feature",
  "properties": {
    "iso:country":"IN",
    "ks:ks_name":"Bujwara",
    "ks:ks_pop":159,
    "ks:ks_type":"VILLAGE",
    "name:eng_x_preferred":[
        "Bujwara"
    ],
    "wof:name":"Bujwara",
    "wof:placetype":"locality",
    "wof:population":159
},
  "geometry": {"coordinates":[73.966263,23.407289],"type":"Point"}
}