{
  "type": "Feature",
  "properties": {
    "iso:country":"IN",
    "ks:ks_name":"Madanpura",
    "ks:ks_pop":74,
    "ks:ks_type":"VILLAGE",
    "name:eng_x_preferred":[
        "Madanpura"
    ],
    "wof:name":"Madanpura",
    "wof:placetype":"locality",
    "wof:population":74
},
  "geometry": {"coordinates":[86.208679,24.091521],"type":"Point"}
}