{
  "type": "Feature",
  "properties": {
    "gn:admin1_code":"1.0",
    "gn:admin2_code":"639.0",
    "gn:asciiname":"Kishorinagar",
    "gn:country_code":"IN",
    "gn:dem":12,
    "gn:feature_class":"P",
    "gn:feature_code":"PPL",
    "gn:name":"Kishorinagar",
    "gn:population":0,
    "gn:timezone":"Asia/Kolkata",
    "iso:country":"IN",
    "wof:name":"Kishorinagar",
    "wof:placetype":"locality"
},
  "geometry": {"coordinates":[92.87777,13.15525],"type":"Point"}
}