{
  "type": "Feature",
  "properties": {
    "gn:admin1_code":"25.0",
    "gn:admin2_code":"604.0",
    "gn:asciiname":"Devanur",
    "gn:country_code":"IN",
    "gn:dem":21,
    "gn:feature_class":"P",
    "gn:feature_code":"PPL",
    "gn:name":"Dev\u0101n\u016br",
    "gn:population":0,
    "gn:timezone":"Asia/Kolkata",
    "iso:country":"IN",
    "name:tam_x_preferred":[
        "\u0ba4\u0bc7\u0bb5\u0ba9\u0bc1\u0bb0\u0bcd"
    ],
    "name:vie_x_preferred":[
        "Devanur"
    ],
    "wof:name":"Devanur",
    "wof:placetype":"locality"
},
  "geometry": {"coordinates":[79.98484999999999,12.3762],"type":"Point"}
}