{
  "type": "Feature",
  "properties": {
    "iso:country":"IN",
    "ks:ks_name":"Alampatti",
    "ks:ks_pop":586,
    "ks:ks_type":"HABITATION",
    "name:eng_x_preferred":[
        "Alampatti"
    ],
    "wof:name":"Alampatti",
    "wof:placetype":"locality",
    "wof:population":586
},
  "geometry": {"coordinates":[78.36493299999999,10.328961],"type":"Point"}
}