{
  "type": "Feature",
  "properties": {
    "iso:country":"IN",
    "ks:ks_name":"Bakal",
    "ks:ks_pop":1193,
    "ks:ks_type":"VILLAGE",
    "ks:ks_uagg_main":0,
    "name:eng_x_preferred":[
        "Bakal"
    ],
    "wof:name":"Bakal",
    "wof:placetype":"neighbourhood",
    "wof:population":1193
},
  "geometry": {"coordinates":[94.579724,27.466827],"type":"Point"}
}