{
  "type": "Feature",
  "properties": {
    "iso:country":"IN",
    "ks:ks_name":"Namatara",
    "ks:ks_pop":3601,
    "ks:ks_type":"VILLAGE",
    "ks:ks_uagg_main":0,
    "name:eng_x_preferred":[
        "Namatara"
    ],
    "wof:name":"Namatara",
    "wof:placetype":"neighbourhood",
    "wof:population":3601
},
  "geometry": {"coordinates":[86.588465,20.72188],"type":"Point"}
}