{
  "type": "Feature",
  "properties": {
    "iso:country":"IN",
    "ks:ks_name":"Mathurapos",
    "ks:ks_pop":194,
    "ks:ks_type":"VILLAGE",
    "name:eng_x_preferred":[
        "Mathurapos"
    ],
    "wof:name":"Mathurapos",
    "wof:placetype":"locality",
    "wof:population":194
},
  "geometry": {"coordinates":[85.173427,22.453884],"type":"Point"}
}