{
  "type": "Feature",
  "properties": {
    "iso:country":"IN",
    "ks:ks_name":"Syunura",
    "ks:ks_pop":457,
    "ks:ks_type":"VILLAGE",
    "name:eng_x_preferred":[
        "Syunura"
    ],
    "wof:name":"Syunura",
    "wof:placetype":"locality",
    "wof:population":457
},
  "geometry": {"coordinates":[80.00921200000001,29.69449],"type":"Point"}
}