{
  "type": "Feature",
  "properties": {
    "iso:country":"IN",
    "ks:ks_name":"Mangammasalai",
    "ks:ks_pop":152,
    "ks:ks_type":"HABITATION",
    "name:eng_x_preferred":[
        "Mangammasalai"
    ],
    "wof:name":"Mangammasalai",
    "wof:placetype":"locality",
    "wof:population":152
},
  "geometry": {"coordinates":[78.54671,12.322983],"type":"Point"}
}