{
  "type": "Feature",
  "properties": {
    "iso:country":"IN",
    "ks:ks_name":"Khanrhara",
    "ks:ks_pop":238,
    "ks:ks_type":"VILLAGE",
    "ks:ks_uagg_main":0,
    "name:eng_x_preferred":[
        "Khanrhara"
    ],
    "wof:name":"Khanrhara",
    "wof:placetype":"neighbourhood",
    "wof:population":238
},
  "geometry": {"coordinates":[85.95071299999999,24.338164],"type":"Point"}
}