{
  "type": "Feature",
  "properties": {
    "iso:country":"IN",
    "ks:ks_alt_nam":"Durgaram para",
    "ks:ks_name":"Durgaram Para",
    "ks:ks_pop":432,
    "ks:ks_type":"HABITATION",
    "name:eng_x_preferred":[
        "Durgaram Para"
    ],
    "wof:name":"Durgaram Para",
    "wof:placetype":"locality",
    "wof:population":432
},
  "geometry": {"coordinates":[91.67488,23.415203],"type":"Point"}
}