{
  "type": "Feature",
  "properties": {
    "iso:country":"IN",
    "ks:ks_name":"Baladmari Char Pt-II",
    "ks:ks_pop":5164,
    "ks:ks_type":"VILLAGE",
    "name:eng_x_preferred":[
        "Baladmari Char Pt-II"
    ],
    "wof:name":"Baladmari Char Pt-II",
    "wof:placetype":"locality",
    "wof:population":5164
},
  "geometry": {"coordinates":[90.65991200000001,26.158661],"type":"Point"}
}