{
  "type": "Feature",
  "properties": {
    "iso:country":"IN",
    "ks:ks_name":"Gorait Purwa",
    "ks:ks_pop":27,
    "ks:ks_type":"HABITATION",
    "name:eng_x_preferred":[
        "Gorait Purwa"
    ],
    "wof:name":"Gorait Purwa",
    "wof:placetype":"locality",
    "wof:population":27
},
  "geometry": {"coordinates":[81.61484799999999,27.217375],"type":"Point"}
}