{
  "type": "Feature",
  "properties": {
    "iso:country":"IN",
    "ks:ks_alt_nam":"Ahiran purwa",
    "ks:ks_name":"Ahiran Purwa",
    "ks:ks_pop":96,
    "ks:ks_type":"HABITATION",
    "ks:ks_uagg_main":0,
    "name:eng_x_preferred":[
        "Ahiran Purwa"
    ],
    "wof:name":"Ahiran Purwa",
    "wof:placetype":"neighbourhood",
    "wof:population":96
},
  "geometry": {"coordinates":[81.36198,27.644912],"type":"Point"}
}