{
  "type": "Feature",
  "properties": {
    "gn:admin1_code":"12",
    "gn:admin2_code":"4.0",
    "gn:asciiname":"Matayan",
    "gn:country_code":"IN",
    "gn:dem":3247,
    "gn:feature_class":"P",
    "gn:feature_code":"PPL",
    "gn:name":"Mat\u0101y\u0101n",
    "gn:population":0,
    "gn:timezone":"Asia/Kolkata",
    "iso:country":"IN",
    "wof:name":"Matayan",
    "wof:placetype":"locality"
},
  "geometry": {"coordinates":[75.5907,34.3669],"type":"Point"}
}