{
  "type": "Feature",
  "properties": {
    "iso:country":"IN",
    "ks:ks_name":"Tepwadi",
    "ks:ks_pop":21,
    "ks:ks_type":"HABITATION",
    "name:eng_x_preferred":[
        "Tepwadi"
    ],
    "wof:name":"Tepwadi",
    "wof:placetype":"locality",
    "wof:population":21
},
  "geometry": {"coordinates":[73.63436400000001,17.627808],"type":"Point"}
}