{
  "type": "Feature",
  "properties": {
    "iso:country":"IN",
    "ks:ks_name":"Hantarpur",
    "ks:ks_pop":620,
    "ks:ks_type":"VILLAGE",
    "name:eng_x_preferred":[
        "Hantarpur"
    ],
    "wof:name":"Hantarpur",
    "wof:placetype":"locality",
    "wof:population":620
},
  "geometry": {"coordinates":[69.97967,21.378724],"type":"Point"}
}