{
  "type": "Feature",
  "properties": {
    "gn:admin1_code":"36",
    "gn:admin2_code":"176.0",
    "gn:asciiname":"Narauli",
    "gn:country_code":"IN",
    "gn:dem":120,
    "gn:feature_class":"P",
    "gn:feature_code":"PPL",
    "gn:name":"Narauli",
    "gn:population":0,
    "gn:timezone":"Asia/Kolkata",
    "iso:country":"IN",
    "name:bpy_x_preferred":[
        "\u09a8\u09be\u09b0\u09be\u0989\u09b2\u09bf"
    ],
    "name:ceb_x_preferred":[
        "Narauli"
    ],
    "name:ita_x_preferred":[
        "Narauli"
    ],
    "name:mlg_x_preferred":[
        "Narauli"
    ],
    "name:msa_x_preferred":[
        "Narauli"
    ],
    "name:new_x_preferred":[
        "\u0928\u0930\u094c\u0932\u0940"
    ],
    "name:nld_x_preferred":[
        "Narauli"
    ],
    "name:pol_x_preferred":[
        "Narauli"
    ],
    "name:por_x_preferred":[
        "Narauli"
    ],
    "name:swe_x_preferred":[
        "Narauli"
    ],
    "name:urd_x_preferred":[
        "\u0646\u0631\u0648\u0644\u06cc"
    ],
    "name:vie_x_preferred":[
        "Narauli"
    ],
    "name:zho_x_preferred":[
        "\u7eb3\u52b3\u5229"
    ],
    "wof:name":"Narauli",
    "wof:placetype":"locality"
},
  "geometry": {"coordinates":[81.22277,26.82555],"type":"Point"}
}