{
  "type": "Feature",
  "properties": {
    "gn:admin1_code":"19.0",
    "gn:admin2_code":"584.0",
    "gn:asciiname":"Udandhalli",
    "gn:country_code":"IN",
    "gn:dem":923,
    "gn:feature_class":"P",
    "gn:feature_code":"PPL",
    "gn:name":"Ud\u0101ndhalli",
    "gn:population":0,
    "gn:timezone":"Asia/Kolkata",
    "iso:country":"IN",
    "wof:name":"Udandhalli",
    "wof:placetype":"locality"
},
  "geometry": {"coordinates":[77.25192,13.04881],"type":"Point"}
}