{
  "type": "Feature",
  "properties": {
    "iso:country":"IN",
    "ks:ks_alt_nam":"mundatoli",
    "ks:ks_name":"Mundatoli",
    "ks:ks_pop":204,
    "ks:ks_type":"HABITATION",
    "name:eng_x_preferred":[
        "Mundatoli"
    ],
    "wof:name":"Mundatoli",
    "wof:placetype":"locality",
    "wof:population":204
},
  "geometry": {"coordinates":[84.89934100000001,23.178205],"type":"Point"}
}