{
  "type": "Feature",
  "properties": {
    "iso:country":"IN",
    "ks:ks_name":"Pedagullapalem",
    "ks:ks_pop":581,
    "ks:ks_type":"HABITATION",
    "name:eng_x_preferred":[
        "Pedagullapalem"
    ],
    "wof:name":"Pedagullapalem",
    "wof:placetype":"locality",
    "wof:population":581
},
  "geometry": {"coordinates":[81.872979,16.731819],"type":"Point"}
}