{
  "type": "Feature",
  "properties": {
    "gn:admin1_code":"2.0",
    "gn:admin2_code":"549",
    "gn:asciiname":"Kanuparti",
    "gn:country_code":"IN",
    "gn:dem":8,
    "gn:feature_class":"P",
    "gn:feature_code":"PPL",
    "gn:name":"Kanuparti",
    "gn:population":0,
    "gn:timezone":"Asia/Kolkata",
    "iso:country":"IN",
    "wof:name":"Kanuparti",
    "wof:placetype":"neighbourhood"
},
  "geometry": {"coordinates":[80.21223000000001,15.58236],"type":"Point"}
}