{
  "type": "Feature",
  "properties": {
    "iso:country":"IN",
    "ks:ks_alt_nam":"KESARU POKHARPUR",
    "ks:ks_name":"Kesaru Pokharpur",
    "ks:ks_pop":510,
    "ks:ks_type":"HABITATION",
    "name:eng_x_preferred":[
        "Kesaru Pokharpur"
    ],
    "wof:name":"Kesaru Pokharpur",
    "wof:placetype":"locality",
    "wof:population":510
},
  "geometry": {"coordinates":[84.939436,24.871324],"type":"Point"}
}