{
  "type": "Feature",
  "properties": {
    "gn:admin1_code":"11",
    "gn:admin2_code":"27.0",
    "gn:asciiname":"Hilog",
    "gn:country_code":"IN",
    "gn:dem":1014,
    "gn:feature_class":"P",
    "gn:feature_code":"PPL",
    "gn:name":"H\u012blog",
    "gn:population":0,
    "gn:timezone":"Asia/Kolkata",
    "iso:country":"IN",
    "wof:name":"Hilog",
    "wof:placetype":"locality"
},
  "geometry": {"coordinates":[76.98817,31.77583],"type":"Point"}
}