{
  "type": "Feature",
  "properties": {
    "gn:admin1_code":"36",
    "gn:admin2_code":"154.0",
    "gn:asciiname":"Nawapur",
    "gn:country_code":"IN",
    "gn:dem":132,
    "gn:feature_class":"P",
    "gn:feature_code":"PPL",
    "gn:name":"Naw\u0101pur",
    "gn:population":0,
    "gn:timezone":"Asia/Kolkata",
    "iso:country":"IN",
    "name:ben_x_preferred":[
        "\u09a8\u0993\u09af\u09bc\u09be\u09aa\u09c1\u09b0"
    ],
    "name:bpy_x_preferred":[
        "\u09a8\u09f1\u09be\u09aa\u09c1\u09b0"
    ],
    "name:ita_x_preferred":[
        "Nawapur"
    ],
    "name:msa_x_preferred":[
        "Nawapur"
    ],
    "name:new_x_preferred":[
        "\u0928\u0935\u092a\u0941\u0930"
    ],
    "name:nld_x_preferred":[
        "Nawapur"
    ],
    "name:por_x_preferred":[
        "Nawapur"
    ],
    "name:vie_x_preferred":[
        "Nawapur"
    ],
    "name:zho_x_preferred":[
        "\u7eb3\u74e6\u666e\u5c14"
    ],
    "wof:name":"Nawapur",
    "wof:placetype":"locality"
},
  "geometry": {"coordinates":[80.96681,27.26773],"type":"Point"}
}