{
  "type": "Feature",
  "properties": {
    "gn:country":"IN",
    "gn:fcode":"PPL",
    "gn:population":18057,
    "iso:country":"IN",
    "name:ben_x_preferred":[
        "\u099d\u09be\u09b2\u09a6\u09be"
    ],
    "name:eng_x_preferred":[
        "Jhalda"
    ],
    "name:fra_x_preferred":[
        "Jhalda"
    ],
    "name:hin_x_preferred":[
        "\u091d\u093e\u0932\u0926\u093e"
    ],
    "name:ita_x_preferred":[
        "Jhalda"
    ],
    "name:msa_x_preferred":[
        "Jhalda"
    ],
    "name:new_x_preferred":[
        "\u091d\u093e\u0932\u094d\u0926\u093e"
    ],
    "name:nld_x_preferred":[
        "Jhalda"
    ],
    "name:por_x_preferred":[
        "Jhalda"
    ],
    "name:vie_x_preferred":[
        "Jhalda"
    ],
    "qs:name":"Jhalda",
    "qs:name_adm0":"India",
    "qs:name_adm1":"West Bengal",
    "qs:photos_9k":1,
    "qs:photos_9r":1,
    "qs:photos_all":17,
    "qs:photos_sr":0,
    "qs:placetype":"Town",
    "qs:pop_sr":"6",
    "wd:wordcount":349,
    "wof:name":"Jhalda",
    "wof:placetype":"locality",
    "wof:population":18057
},
  "geometry": {"coordinates":[85.97581,23.36541],"type":"Point"}
}