{
  "type": "Feature",
  "properties": {
    "gn:admin1_code":"11",
    "gn:admin2_code":"23.0",
    "gn:asciiname":"Palani",
    "gn:country_code":"IN",
    "gn:dem":2529,
    "gn:feature_class":"P",
    "gn:feature_code":"PPL",
    "gn:name":"P\u0101lani",
    "gn:population":0,
    "gn:timezone":"Asia/Kolkata",
    "iso:country":"IN",
    "wof:name":"Palani",
    "wof:placetype":"locality"
},
  "geometry": {"coordinates":[76.50461,32.46979],"type":"Point"}
}