{
  "type": "Feature",
  "properties": {
    "gn:admin1_code":"11",
    "gn:admin2_code":"23.0",
    "gn:asciiname":"Palani",
    "gn:country_code":"IN",
    "gn:dem":2529,
    "gn:feature_class":"P",
    "gn:feature_code":"PPL",
    "gn:name":"P\u0101lani",
    "gn:population":0,
    "gn:timezone":"Asia/Kolkata",
    "iso:country":"IN",
    "name:ben_x_preferred":[
        "\u09aa\u09be\u09b2\u09be\u09a8\u09bf"
    ],
    "name:bpy_x_preferred":[
        "\u09aa\u09be\u09b2\u09be\u09a8\u09bf"
    ],
    "name:cat_x_preferred":[
        "Palani"
    ],
    "name:ceb_x_preferred":[
        "Palani"
    ],
    "name:deu_x_preferred":[
        "Palani"
    ],
    "name:hin_x_preferred":[
        "\u092a\u0932\u0928\u0940"
    ],
    "name:ita_x_preferred":[
        "Palani"
    ],
    "name:mal_x_preferred":[
        "\u0d2a\u0d34\u0d28\u0d3f"
    ],
    "name:mar_x_preferred":[
        "\u092a\u0933\u0923\u0940"
    ],
    "name:mlg_x_preferred":[
        "Palani"
    ],
    "name:msa_x_preferred":[
        "Palani"
    ],
    "name:ori_x_preferred":[
        "\u0b2a\u0b3e\u0b32\u0b3e\u0b28\u0b3f"
    ],
    "name:san_x_preferred":[
        "\u092a\u0933\u0928\u0940"
    ],
    "name:swe_x_preferred":[
        "Palani"
    ],
    "name:tam_x_preferred":[
        "\u0baa\u0bb4\u0ba9\u0bbf"
    ],
    "name:tel_x_preferred":[
        "\u0c2a\u0c33\u0c28\u0c3f"
    ],
    "name:vie_x_preferred":[
        "Palani"
    ],
    "name:zho_x_preferred":[
        "\u5e15\u62c9\u5c3c"
    ],
    "wof:name":"Palani",
    "wof:placetype":"locality"
},
  "geometry": {"coordinates":[76.50461,32.46979],"type":"Point"}
}