{
  "type": "Feature",
  "properties": {
    "iso:country":"IN",
    "ks:ks_name":"Rampuriya",
    "ks:ks_pop":418,
    "ks:ks_type":"VILLAGE",
    "name:eng_x_preferred":[
        "Rampuriya"
    ],
    "wof:name":"Rampuriya",
    "wof:placetype":"locality",
    "wof:population":418
},
  "geometry": {"coordinates":[75.99125600000001,25.850125],"type":"Point"}
}