{
  "type": "Feature",
  "properties": {
    "iso:country":"IN",
    "ks:ks_name":"Bithi Panyali",
    "ks:ks_pop":206,
    "ks:ks_type":"HABITATION",
    "name:eng_x_preferred":[
        "Bithi Panyali"
    ],
    "wof:name":"Bithi Panyali",
    "wof:placetype":"locality",
    "wof:population":206
},
  "geometry": {"coordinates":[79.87069700000001,29.945556],"type":"Point"}
}