{
  "type": "Feature",
  "properties": {
    "iso:country":"IN",
    "ks:ks_name":"Pottikuzhi Road",
    "ks:ks_pop":1140,
    "ks:ks_type":"HABITATION",
    "name:eng_x_preferred":[
        "Pottikuzhi Road"
    ],
    "wof:name":"Pottikuzhi Road",
    "wof:placetype":"locality",
    "wof:population":1140
},
  "geometry": {"coordinates":[76.311049,11.203149],"type":"Point"}
}