{
  "type": "Feature",
  "properties": {
    "gn:admin1_code":"2.0",
    "gn:admin2_code":"543.0",
    "gn:asciiname":"Pasupuvanivalasa",
    "gn:country_code":"IN",
    "gn:dem":164,
    "gn:feature_class":"P",
    "gn:feature_code":"PPL",
    "gn:name":"Pasupuv\u0101nivalasa",
    "gn:population":0,
    "gn:timezone":"Asia/Kolkata",
    "iso:country":"IN",
    "ks:ks_name":"Pasupuvanivalasa",
    "ks:ks_pop":107,
    "ks:ks_type":"HABITATION",
    "name:eng_x_preferred":[
        "Pasupuvanivalasa"
    ],
    "wof:name":"Pasupuvanivalasa",
    "wof:placetype":"locality",
    "wof:population":107
},
  "geometry": {"coordinates":[83.202337,18.598439],"type":"Point"}
}