{
  "type": "Feature",
  "properties": {
    "iso:country":"IN",
    "ks:ks_alt_nam":"PURE KAPSA",
    "ks:ks_name":"Pure Kapsa",
    "ks:ks_pop":120,
    "ks:ks_type":"HABITATION",
    "ks:ks_uagg_main":0,
    "name:eng_x_preferred":[
        "Pure Kapsa"
    ],
    "wof:name":"Pure Kapsa",
    "wof:placetype":"neighbourhood",
    "wof:population":120
},
  "geometry": {"coordinates":[81.825114,26.507473],"type":"Point"}
}