{
  "type": "Feature",
  "properties": {
    "iso:country":"IN",
    "ks:ks_alt_nam":"PARASIA",
    "ks:ks_name":"Parasia",
    "ks:ks_pop":259,
    "ks:ks_type":"HABITATION",
    "name:eng_x_preferred":[
        "Parasia"
    ],
    "wof:name":"Parasia",
    "wof:placetype":"locality",
    "wof:population":259
},
  "geometry": {"coordinates":[84.07778,24.66714],"type":"Point"}
}