{
  "type": "Feature",
  "properties": {
    "iso:country":"IN",
    "ks:ks_alt_nam":"BADNIJOR",
    "ks:ks_name":"Badnijor",
    "ks:ks_pop":129,
    "ks:ks_type":"HABITATION",
    "name:eng_x_preferred":[
        "Badnijor"
    ],
    "wof:name":"Badnijor",
    "wof:placetype":"locality",
    "wof:population":129
},
  "geometry": {"coordinates":[84.210561,22.714708],"type":"Point"}
}