{
  "type": "Feature",
  "properties": {
    "iso:country":"IN",
    "ks:ks_name":"Krishnapur Camp",
    "ks:ks_pop":210,
    "ks:ks_type":"HABITATION",
    "name:eng_x_preferred":[
        "Krishnapur Camp"
    ],
    "wof:name":"Krishnapur Camp",
    "wof:placetype":"locality",
    "wof:population":210
},
  "geometry": {"coordinates":[76.637032,15.535731],"type":"Point"}
}