{
  "type": "Feature",
  "properties": {
    "gn:admin1_code":"2.0",
    "gn:admin2_code":"544.0",
    "gn:asciiname":"Moyalagumma",
    "gn:country_code":"IN",
    "gn:dem":1037,
    "gn:feature_class":"P",
    "gn:feature_code":"PPL",
    "gn:name":"Moyalagumma",
    "gn:population":0,
    "gn:timezone":"Asia/Kolkata",
    "iso:country":"IN",
    "ks:ks_name":"Moyyalagummi",
    "ks:ks_pop":81,
    "ks:ks_type":"HABITATION",
    "name:eng_x_preferred":[
        "Moyyalagummi"
    ],
    "name:eng_x_variant":[
        "Moyalagumma"
    ],
    "wof:name":"Moyyalagummi",
    "wof:placetype":"locality",
    "wof:population":81
},
  "geometry": {"coordinates":[82.481824,18.196779],"type":"Point"}
}