{
  "type": "Feature",
  "properties": {
    "gn:admin1_code":"2.0",
    "gn:admin2_code":"544.0",
    "gn:asciiname":"Moyalagumma",
    "gn:country_code":"IN",
    "gn:dem":1037,
    "gn:feature_class":"P",
    "gn:feature_code":"PPL",
    "gn:name":"Moyalagumma",
    "gn:population":0,
    "gn:timezone":"Asia/Kolkata",
    "iso:country":"IN",
    "wof:name":"Moyalagumma",
    "wof:placetype":"locality"
},
  "geometry": {"coordinates":[82.48182,18.19699],"type":"Point"}
}