{
  "type": "Feature",
  "properties": {
    "iso:country":"IN",
    "ks:ks_name":"Sunnari",
    "ks:ks_pop":244,
    "ks:ks_type":"HABITATION",
    "name:eng_x_preferred":[
        "Sunnari"
    ],
    "wof:name":"Sunnari",
    "wof:placetype":"locality",
    "wof:population":244
},
  "geometry": {"coordinates":[74.76417600000001,13.583956],"type":"Point"}
}