{
  "type": "Feature",
  "properties": {
    "gn:admin1_code":"36",
    "gn:admin2_code":"179.0",
    "gn:asciiname":"Sonsaripur",
    "gn:country_code":"IN",
    "gn:dem":100,
    "gn:feature_class":"P",
    "gn:feature_code":"PPL",
    "gn:name":"Sons\u0101ripur",
    "gn:population":0,
    "gn:timezone":"Asia/Kolkata",
    "iso:country":"IN",
    "ks:ks_name":"Sansari Pur",
    "ks:ks_pop":491,
    "ks:ks_type":"VILLAGE",
    "ks:ks_uagg_main":0,
    "name:eng_x_preferred":[
        "Sansari Pur"
    ],
    "wof:name":"Sansari Pur",
    "wof:placetype":"neighbourhood",
    "wof:population":491
},
  "geometry": {"coordinates":[82.04155900000001,26.101771],"type":"Point"}
}