{
  "type": "Feature",
  "properties": {
    "iso:country":"IN",
    "ks:ks_name":"Manikavali",
    "ks:ks_pop":320,
    "ks:ks_type":"HABITATION",
    "name:eng_x_preferred":[
        "Manikavali"
    ],
    "wof:name":"Manikavali",
    "wof:placetype":"locality",
    "wof:population":320
},
  "geometry": {"coordinates":[79.21804400000001,12.525313],"type":"Point"}
}