{
  "type": "Feature",
  "properties": {
    "iso:country":"IN",
    "ks:ks_name":"Telanga",
    "ks:ks_pop":436,
    "ks:ks_type":"VILLAGE",
    "name:eng_x_preferred":[
        "Telanga"
    ],
    "wof:name":"Telanga",
    "wof:placetype":"locality",
    "wof:population":436
},
  "geometry": {"coordinates":[81.393455,19.887339],"type":"Point"}
}