{
  "type": "Feature",
  "properties": {
    "iso:country":"IN",
    "ks:ks_name":"Falyat",
    "ks:ks_pop":332,
    "ks:ks_type":"VILLAGE",
    "name:eng_x_preferred":[
        "Falyat"
    ],
    "wof:name":"Falyat",
    "wof:placetype":"locality",
    "wof:population":332
},
  "geometry": {"coordinates":[79.898083,29.586713],"type":"Point"}
}