{
  "type": "Feature",
  "properties": {
    "gn:admin1_code":"28.0",
    "gn:admin2_code":"329.0",
    "gn:asciiname":"Falimari",
    "gn:country_code":"IN",
    "gn:dem":44,
    "gn:feature_class":"P",
    "gn:feature_code":"PPL",
    "gn:name":"Falim\u0101ri",
    "gn:population":0,
    "gn:timezone":"Asia/Kolkata",
    "iso:country":"IN",
    "wof:name":"Falimari",
    "wof:placetype":"locality"
},
  "geometry": {"coordinates":[89.82224000000002,26.39617],"type":"Point"}
}