{
  "type": "Feature",
  "properties": {
    "iso:country":"IN",
    "ks:ks_name":"Baladbandha",
    "ks:ks_type":"VILLAGE",
    "name:eng_x_preferred":[
        "Baladbandha"
    ],
    "wof:name":"Baladbandha",
    "wof:placetype":"locality"
},
  "geometry": {"coordinates":[84.251304,21.661877],"type":"Point"}
}