{
  "type": "Feature",
  "properties": {
    "gn:admin1_code":"11.0",
    "gn:admin2_code":"24.0",
    "gn:asciiname":"Dhaulpur",
    "gn:country_code":"IN",
    "gn:dem":339,
    "gn:feature_class":"P",
    "gn:feature_code":"PPL",
    "gn:name":"Dhaulpur",
    "gn:population":0,
    "gn:timezone":"Asia/Kolkata",
    "iso:country":"IN",
    "name:ara_x_preferred":[
        "\u062f\u0648\u0644\u0628\u0648\u0631"
    ],
    "name:ben_bn_x_preferred":[
        "\u09a7\u09be\u0989\u09b2\u09aa\u09c1\u09b0"
    ],
    "name:ben_in_x_preferred":[
        "\u09a7\u09be\u0989\u09b2\u09aa\u09c1\u09b0"
    ],
    "name:guj_x_preferred":[
        "\u0aa7\u0acc\u0ab2\u0aaa\u0ac1\u0ab0"
    ],
    "name:hin_x_preferred":[
        "\u0927\u094c\u0932\u092a\u0941\u0930"
    ],
    "name:kan_x_preferred":[
        "\u0ca6\u0ccc\u0cb2\u0ccd"
    ],
    "name:mal_x_preferred":[
        "\u0d27\u0d57\u0d7e\u0d2a\u0d42\u0d7c"
    ],
    "name:mar_x_preferred":[
        "\u0927\u094c\u0932\u092a\u0942\u0930"
    ],
    "name:pan_x_preferred":[
        "\u0a27\u0a4c\u0a32\u0a2a\u0a41\u0a30"
    ],
    "name:tam_x_preferred":[
        "\u0ba4\u0bcc\u0bb2\u0bcd\u0baa\u0bc2\u0bb0\u0bcd"
    ],
    "name:tel_x_preferred":[
        "\u0c27\u0c35\u0c41\u0c32\u0c4d"
    ],
    "name:urd_x_preferred":[
        "\u062f\u06be\u0648\u0644\u0627 \u067e\u0648\u0631"
    ],
    "wof:name":"Dhaulpur",
    "wof:placetype":"locality"
},
  "geometry": {"coordinates":[75.83777000000001,32.01025],"type":"Point"}
}