{
  "type": "Feature",
  "properties": {
    "iso:country":"IN",
    "ks:ks_name":"Bar Para",
    "ks:ks_pop":841,
    "ks:ks_type":"HABITATION",
    "name:eng_x_preferred":[
        "Bar Para"
    ],
    "wof:name":"Bar Para",
    "wof:placetype":"locality",
    "wof:population":841
},
  "geometry": {"coordinates":[88.692774,22.118928],"type":"Point"}
}