{
  "type": "Feature",
  "properties": {
    "iso:country":"IN",
    "ks:ks_name":"Kalidih",
    "ks:ks_pop":489,
    "ks:ks_type":"VILLAGE",
    "ks:ks_uagg_main":0,
    "name:eng_x_preferred":[
        "Kalidih"
    ],
    "wof:name":"Kalidih",
    "wof:placetype":"neighbourhood",
    "wof:population":489
},
  "geometry": {"coordinates":[85.80137999999999,24.727786],"type":"Point"}
}