{
  "type": "Feature",
  "properties": {
    "gn:admin1_code":"12.0",
    "gn:admin2_code":"008",
    "gn:asciiname":"Takia Batpur",
    "gn:country_code":"IN",
    "gn:dem":1755,
    "gn:feature_class":"P",
    "gn:feature_code":"PPL",
    "gn:name":"Takia Batpur",
    "gn:population":0,
    "gn:timezone":"Asia/Kolkata",
    "iso:country":"IN",
    "wof:name":"Takia Batpur",
    "wof:placetype":"locality"
},
  "geometry": {"coordinates":[74.51585,34.08582],"type":"Point"}
}