{
  "type": "Feature",
  "properties": {
    "iso:country":"IN",
    "ks:ks_alt_nam":"ambedkar nagar",
    "ks:ks_name":"Ambedkar Nagar",
    "ks:ks_pop":261,
    "ks:ks_type":"HABITATION",
    "name:eng_x_preferred":[
        "Ambedkar Nagar"
    ],
    "wof:name":"Ambedkar Nagar",
    "wof:placetype":"locality",
    "wof:population":261
},
  "geometry": {"coordinates":[80.201778,13.44288],"type":"Point"}
}