{
  "type": "Feature",
  "properties": {
    "iso:country":"IN",
    "ks:ks_alt_nam":"Gollahalli State Plantation",
    "ks:ks_name":"Gollahalli",
    "ks:ks_type":"VILLAGE",
    "name:eng_x_preferred":[
        "Gollahalli"
    ],
    "name:eng_x_variant":[
        "Gollahalli State Plantation"
    ],
    "wof:name":"Gollahalli",
    "wof:placetype":"locality"
},
  "geometry": {"coordinates":[77.19492099999999,13.345488],"type":"Point"}
}