{
  "type": "Feature",
  "properties": {
    "iso:country":"IN",
    "ks:ks_name":"Deval Falia",
    "ks:ks_pop":95,
    "ks:ks_type":"HABITATION",
    "ks:ks_uagg_main":0,
    "name:eng_x_preferred":[
        "Deval Falia"
    ],
    "wof:name":"Deval Falia",
    "wof:placetype":"neighbourhood",
    "wof:population":95
},
  "geometry": {"coordinates":[73.384972,20.795278],"type":"Point"}
}