{
  "type": "Feature",
  "properties": {
    "gn:admin1_code":"19",
    "gn:admin2_code":"569.0",
    "gn:asciiname":"Mudanagudde",
    "gn:country_code":"IN",
    "gn:dem":22,
    "gn:feature_class":"P",
    "gn:feature_code":"PPL",
    "gn:name":"Mudanagudde",
    "gn:population":0,
    "gn:timezone":"Asia/Kolkata",
    "iso:country":"IN",
    "ks:ks_name":"Mudanagadde",
    "ks:ks_pop":129,
    "ks:ks_type":"HABITATION",
    "name:eng_x_preferred":[
        "Mudanagadde"
    ],
    "name:eng_x_variant":[
        "Mudanagudde"
    ],
    "wof:name":"Mudanagadde",
    "wof:placetype":"locality",
    "wof:population":129
},
  "geometry": {"coordinates":[74.73702299999999,13.713602],"type":"Point"}
}