{
  "type": "Feature",
  "properties": {
    "gn:admin1_code":"19.0",
    "gn:admin2_code":"583.0",
    "gn:asciiname":"Hanchanhalli",
    "gn:country_code":"IN",
    "gn:dem":930,
    "gn:feature_class":"P",
    "gn:feature_code":"PPL",
    "gn:name":"Hanchanhalli",
    "gn:population":0,
    "gn:timezone":"Asia/Kolkata",
    "iso:country":"IN",
    "wof:name":"Hanchanhalli",
    "wof:placetype":"locality"
},
  "geometry": {"coordinates":[77.61554,13.33087],"type":"Point"}
}