{
  "type": "Feature",
  "properties": {
    "iso:country":"IN",
    "ks:ks_name":"Majhipada",
    "ks:ks_pop":61,
    "ks:ks_type":"HABITATION",
    "name:eng_x_preferred":[
        "Majhipada"
    ],
    "wof:name":"Majhipada",
    "wof:placetype":"locality",
    "wof:population":61
},
  "geometry": {"coordinates":[83.368426,19.835174],"type":"Point"}
}