{
  "type": "Feature",
  "properties": {
    "gn:admin1_code":"35.0",
    "gn:admin2_code":"441",
    "gn:asciiname":"Baygor",
    "gn:country_code":"IN",
    "gn:dem":317,
    "gn:feature_class":"P",
    "gn:feature_code":"PPL",
    "gn:name":"Baygor",
    "gn:population":0,
    "gn:timezone":"Asia/Kolkata",
    "iso:country":"IN",
    "name:und_x_variant":[
        "Baigore",
        "B\u0101ygor",
        "Baygor"
    ],
    "wof:name":"Baygor",
    "wof:placetype":"locality"
},
  "geometry": {"coordinates":[74.53798,21.7497],"type":"Point"}
}