{
  "type": "Feature",
  "properties": {
    "gn:admin1_code":"35.0",
    "gn:admin2_code":"441",
    "gn:asciiname":"Baygor",
    "gn:country_code":"IN",
    "gn:dem":317,
    "gn:feature_class":"P",
    "gn:feature_code":"PPL",
    "gn:name":"Baygor",
    "gn:population":0,
    "gn:timezone":"Asia/Kolkata",
    "iso:country":"IN",
    "ks:ks_name":"Baygore",
    "ks:ks_pop":1123,
    "ks:ks_type":"VILLAGE",
    "name:eng_x_preferred":[
        "Baygore"
    ],
    "name:eng_x_variant":[
        "Baygor"
    ],
    "name:und_x_variant":[
        "Baigore",
        "B\u0101ygor",
        "Baygor"
    ],
    "wof:name":"Baygore",
    "wof:placetype":"locality",
    "wof:population":1123
},
  "geometry": {"coordinates":[74.540087,21.746979],"type":"Point"}
}