{
  "type": "Feature",
  "properties": {
    "iso:country":"IN",
    "ks:ks_alt_nam":"GONDHALI WASTI",
    "ks:ks_name":"Gondhali Wasti",
    "ks:ks_pop":298,
    "ks:ks_type":"HABITATION",
    "name:eng_x_preferred":[
        "Gondhali Wasti"
    ],
    "wof:name":"Gondhali Wasti",
    "wof:placetype":"locality",
    "wof:population":298
},
  "geometry": {"coordinates":[74.201364,17.092248],"type":"Point"}
}