{
  "type": "Feature",
  "properties": {
    "iso:country":"IN",
    "ks:ks_name":"Magan Patha",
    "ks:ks_pop":284,
    "ks:ks_type":"HABITATION",
    "name:eng_x_preferred":[
        "Magan Patha"
    ],
    "wof:name":"Magan Patha",
    "wof:placetype":"locality",
    "wof:population":284
},
  "geometry": {"coordinates":[78.40205899999999,24.983668],"type":"Point"}
}