{
  "type": "Feature",
  "properties": {
    "gn:admin1_code":"36",
    "gn:admin2_code":"200.0",
    "gn:asciiname":"Muther",
    "gn:country_code":"IN",
    "gn:dem":323,
    "gn:feature_class":"P",
    "gn:feature_code":"PPL",
    "gn:name":"Muther",
    "gn:population":0,
    "gn:timezone":"Asia/Kolkata",
    "iso:country":"IN",
    "name:dan_x_preferred":[
        "Muther"
    ],
    "name:rus_x_preferred":[
        "\u041c\u0443\u0442\u0435\u0440"
    ],
    "name:swe_x_preferred":[
        "Muther"
    ],
    "wof:name":"Muther",
    "wof:placetype":"locality"
},
  "geometry": {"coordinates":[83.01522,24.68701],"type":"Point"}
}