{
  "type": "Feature",
  "properties": {
    "gn:admin1_code":"24.0",
    "gn:admin2_code":"110",
    "gn:asciiname":"Bhaislana",
    "gn:country_code":"IN",
    "gn:dem":402,
    "gn:feature_class":"P",
    "gn:feature_code":"PPL",
    "gn:name":"Bhaisl\u0101na",
    "gn:population":0,
    "gn:timezone":"Asia/Kolkata",
    "iso:country":"IN",
    "name:und_x_variant":[
        "Bhaisl\u0101na",
        "Bhesl\u0101na"
    ],
    "wof:name":"Bhaislana",
    "wof:placetype":"locality"
},
  "geometry": {"coordinates":[75.29512,27.05776],"type":"Point"}
}