{
  "type": "Feature",
  "properties": {
    "gn:admin1_code":"24.0",
    "gn:admin2_code":"129",
    "gn:asciiname":"Gangdhar",
    "gn:country_code":"IN",
    "gn:dem":430,
    "gn:feature_class":"P",
    "gn:feature_code":"PPL",
    "gn:name":"Gangdh\u0101r",
    "gn:population":0,
    "gn:timezone":"Asia/Kolkata",
    "iso:country":"IN",
    "name:und_x_variant":[
        "Angdhar",
        "Gangdhor",
        "Gangdh\u0101r"
    ],
    "wof:name":"Gangdhar",
    "wof:placetype":"locality"
},
  "geometry": {"coordinates":[75.62164,23.94072],"type":"Point"}
}