{
  "type": "Feature",
  "properties": {
    "iso:country":"IN",
    "ks:ks_name":"Ramagali",
    "ks:ks_pop":46,
    "ks:ks_type":"HABITATION",
    "name:eng_x_preferred":[
        "Ramagali"
    ],
    "wof:name":"Ramagali",
    "wof:placetype":"locality",
    "wof:population":46
},
  "geometry": {"coordinates":[74.743022,14.999414],"type":"Point"}
}