{
  "type": "Feature",
  "properties": {
    "gn:admin1_code":"23.0",
    "gn:admin2_code":"38.0",
    "gn:asciiname":"Molla",
    "gn:country_code":"IN",
    "gn:dem":251,
    "gn:feature_class":"P",
    "gn:feature_code":"PPL",
    "gn:name":"Molla",
    "gn:population":0,
    "gn:timezone":"Asia/Kolkata",
    "iso:country":"IN",
    "name:ceb_x_preferred":[
        "Molla"
    ],
    "name:deu_x_preferred":[
        "Molla"
    ],
    "name:fra_x_preferred":[
        "Molla"
    ],
    "name:rus_x_preferred":[
        "\u041c\u043e\u043b\u043b\u0430"
    ],
    "wof:name":"Molla",
    "wof:placetype":"locality"
},
  "geometry": {"coordinates":[75.59456999999998,32.06873],"type":"Point"}
}