{
  "type": "Feature",
  "properties": {
    "iso:country":"IN",
    "ks:ks_name":"Chhatrakana",
    "ks:ks_pop":0,
    "ks:ks_type":"VILLAGE",
    "name:eng_x_preferred":[
        "Chhatrakana"
    ],
    "wof:name":"Chhatrakana",
    "wof:placetype":"locality",
    "wof:population":0
},
  "geometry": {"coordinates":[85.903443,20.850341],"type":"Point"}
}