{
  "type": "Feature",
  "properties": {
    "iso:country":"IN",
    "ks:ks_name":"Diguvatamarapalli",
    "ks:ks_pop":111,
    "ks:ks_type":"HABITATION",
    "name:eng_x_preferred":[
        "Diguvatamarapalli"
    ],
    "wof:name":"Diguvatamarapalli",
    "wof:placetype":"locality",
    "wof:population":111
},
  "geometry": {"coordinates":[82.681898,18.035227],"type":"Point"}
}