{
  "type": "Feature",
  "properties": {
    "iso:country":"IN",
    "ks:ks_name":"Bangla Gopalpur",
    "ks:ks_pop":547,
    "ks:ks_type":"HABITATION",
    "name:eng_x_preferred":[
        "Bangla Gopalpur"
    ],
    "wof:name":"Bangla Gopalpur",
    "wof:placetype":"locality",
    "wof:population":547
},
  "geometry": {"coordinates":[80.184444,26.134444],"type":"Point"}
}