{
  "type": "Feature",
  "properties": {
    "iso:country":"IN",
    "ks:ks_name":"Sarbania",
    "ks:ks_pop":172,
    "ks:ks_type":"VILLAGE",
    "name:eng_x_preferred":[
        "Sarbania"
    ],
    "wof:name":"Sarbania",
    "wof:placetype":"locality",
    "wof:population":172
},
  "geometry": {"coordinates":[86.402064,22.063727],"type":"Point"}
}