{
  "type": "Feature",
  "properties": {
    "iso:country":"IN",
    "ks:ks_name":"Kakrau",
    "ks:ks_pop":1810,
    "ks:ks_type":"VILLAGE",
    "ks:ks_uagg_main":0,
    "name:eng_x_preferred":[
        "Kakrau"
    ],
    "wof:name":"Kakrau",
    "wof:placetype":"neighbourhood",
    "wof:population":1810
},
  "geometry": {"coordinates":[78.38757200000001,27.177087],"type":"Point"}
}