{
  "type": "Feature",
  "properties": {
    "gn:admin1_code":"36",
    "gn:admin2_code":"172.0",
    "gn:asciiname":"Banarsi",
    "gn:country_code":"IN",
    "gn:dem":121,
    "gn:feature_class":"P",
    "gn:feature_code":"PPL",
    "gn:name":"Banarsi",
    "gn:population":0,
    "gn:timezone":"Asia/Kolkata",
    "iso:country":"IN",
    "name:ben_x_preferred":[
        "\u09ac\u09be\u09a8\u09b0\u09b8\u09bf"
    ],
    "name:bpy_x_preferred":[
        "\u09ac\u09be\u09a8\u09b0\u09b8\u09bf"
    ],
    "name:ita_x_preferred":[
        "Banarsi"
    ],
    "name:mlg_x_preferred":[
        "Banarsi"
    ],
    "name:msa_x_preferred":[
        "Banarsi"
    ],
    "name:new_x_preferred":[
        "\u092c\u0928\u093e\u0930\u0938\u0940"
    ],
    "name:nld_x_preferred":[
        "Banarsi"
    ],
    "name:por_x_preferred":[
        "Banarsi"
    ],
    "name:tgl_x_preferred":[
        "Banarsi"
    ],
    "name:urd_x_preferred":[
        "\u0628\u0646\u0627\u0631\u0633\u06cc"
    ],
    "name:vie_x_preferred":[
        "Banarsi"
    ],
    "name:zho_x_preferred":[
        "\u5df4\u7eb3\u5c14\u897f"
    ],
    "wof:name":"Banarsi",
    "wof:placetype":"locality"
},
  "geometry": {"coordinates":[80.67623,25.89205],"type":"Point"}
}