{
  "type": "Feature",
  "properties": {
    "gn:admin1_code":"21.0",
    "gn:admin2_code":"398.0",
    "gn:asciiname":"Nadimi Itike",
    "gn:country_code":"IN",
    "gn:dem":264,
    "gn:feature_class":"P",
    "gn:feature_code":"PPL",
    "gn:name":"Nadimi Itike",
    "gn:population":0,
    "gn:timezone":"Asia/Kolkata",
    "iso:country":"IN",
    "wof:name":"Nadimi Itike",
    "wof:placetype":"locality"
},
  "geometry": {"coordinates":[83.24079999999999,18.84195],"type":"Point"}
}