{
  "type": "Feature",
  "properties": {
    "gn:admin1_code":"40.0",
    "gn:admin2_code":"534.0",
    "gn:asciiname":"Koheda",
    "gn:country_code":"IN",
    "gn:dem":339,
    "gn:feature_class":"P",
    "gn:feature_code":"PPL",
    "gn:name":"Koheda",
    "gn:population":0,
    "gn:timezone":"Asia/Kolkata",
    "iso:country":"IN",
    "name:ara_x_preferred":[
        "\u0643\u0648\u0647\u064a\u062f\u0627"
    ],
    "name:ben_bn_x_preferred":[
        "\u0995\u09cb\u09b9\u09c7\u09a6\u09be"
    ],
    "name:ben_in_x_preferred":[
        "\u0995\u09cb\u09b9\u09c7\u09a6\u09be"
    ],
    "name:guj_x_preferred":[
        "\u0a95\u0acb\u0ab9\u0ac7\u0aa1\u0abe"
    ],
    "name:hin_x_preferred":[
        "\u0915\u094b\u0939\u0947\u0926\u093e"
    ],
    "name:kan_x_preferred":[
        "\u0c95\u0cca\u0cb9\u0cc6\u0ca6\u0cbe"
    ],
    "name:mal_x_preferred":[
        "\u0d15\u0d4a\u0d39\u0d47\u0d21"
    ],
    "name:mar_x_preferred":[
        "\u0915\u094b\u0939\u0947\u0921\u093e"
    ],
    "name:pan_x_preferred":[
        "\u0a15\u0a4b\u0a39\u0a47\u0a26\u0a3e"
    ],
    "name:tam_x_preferred":[
        "\u0b95\u0bcb\u0bb9\u0bc6\u0b9f\u0bbe"
    ],
    "name:tel_x_preferred":[
        "\u0c15\u0c4a\u0c39\u0c46\u0c21\u0c3e"
    ],
    "name:urd_x_preferred":[
        "\u06a9\u0648\u06c1\u06cc\u0688\u0627"
    ],
    "wof:name":"Koheda",
    "wof:placetype":"locality"
},
  "geometry": {"coordinates":[79.09338000000002,18.17091],"type":"Point"}
}