{
  "type": "Feature",
  "properties": {
    "iso:country":"IN",
    "ks:ks_name":"Santirathapatana",
    "ks:ks_pop":0,
    "ks:ks_type":"VILLAGE",
    "name:eng_x_preferred":[
        "Santirathapatana"
    ],
    "wof:name":"Santirathapatana",
    "wof:placetype":"locality",
    "wof:population":0
},
  "geometry": {"coordinates":[86.11876599999999,20.675951],"type":"Point"}
}