{
  "type": "Feature",
  "properties": {
    "iso:country":"IN",
    "ks:ks_alt_nam":"JADAHAV WASTI",
    "ks:ks_name":"Jadahav Wasti",
    "ks:ks_pop":173,
    "ks:ks_type":"HABITATION",
    "name:eng_x_preferred":[
        "Jadahav Wasti"
    ],
    "wof:name":"Jadahav Wasti",
    "wof:placetype":"locality",
    "wof:population":173
},
  "geometry": {"coordinates":[75.18548199999999,17.244641],"type":"Point"}
}