{
  "type": "Feature",
  "properties": {
    "iso:country":"IN",
    "ks:ks_name":"Hosapura",
    "ks:ks_pop":237,
    "ks:ks_type":"HABITATION",
    "name:eng_x_preferred":[
        "Hosapura"
    ],
    "wof:name":"Hosapura",
    "wof:placetype":"locality",
    "wof:population":237
},
  "geometry": {"coordinates":[75.722131,13.082025],"type":"Point"}
}