{
  "type": "Feature",
  "properties": {
    "iso:country":"IN",
    "ks:ks_name":"Kalusanivari Gudem",
    "ks:ks_pop":48,
    "ks:ks_type":"HABITATION",
    "name:eng_x_preferred":[
        "Kalusanivari Gudem"
    ],
    "wof:name":"Kalusanivari Gudem",
    "wof:placetype":"locality",
    "wof:population":48
},
  "geometry": {"coordinates":[79.12245,16.653596],"type":"Point"}
}