{
  "type": "Feature",
  "properties": {
    "iso:country":"IN",
    "ks:ks_name":"Naganahalli",
    "ks:ks_pop":85,
    "ks:ks_type":"VILLAGE",
    "name:eng_x_preferred":[
        "Naganahalli"
    ],
    "wof:name":"Naganahalli",
    "wof:placetype":"locality",
    "wof:population":85
},
  "geometry": {"coordinates":[77.080726,12.740487],"type":"Point"}
}