{
  "type": "Feature",
  "properties": {
    "iso:country":"IN",
    "ks:ks_name":"Singara",
    "ks:ks_pop":1012,
    "ks:ks_type":"VILLAGE",
    "ks:ks_uagg_main":0,
    "name:eng_x_preferred":[
        "Singara"
    ],
    "wof:name":"Singara",
    "wof:placetype":"neighbourhood",
    "wof:population":1012
},
  "geometry": {"coordinates":[87.98814900000001,22.503688],"type":"Point"}
}