{
  "type": "Feature",
  "properties": {
    "gn:admin1_code":"36",
    "gn:admin2_code":"198.0",
    "gn:asciiname":"Bagahi",
    "gn:country_code":"IN",
    "gn:dem":92,
    "gn:feature_class":"P",
    "gn:feature_code":"PPL",
    "gn:name":"Bagahi",
    "gn:population":0,
    "gn:timezone":"Asia/Kolkata",
    "iso:country":"IN",
    "name:fra_x_preferred":[
        "Bagahi"
    ],
    "name:pol_x_preferred":[
        "Bagahi"
    ],
    "wof:name":"Bagahi",
    "wof:placetype":"neighbourhood"
},
  "geometry": {"coordinates":[82.48486,25.47116],"type":"Point"}
}