{
  "type": "Feature",
  "properties": {
    "iso:country":"IN",
    "ks:ks_name":"Chauki",
    "ks:ks_pop":61,
    "ks:ks_type":"HABITATION",
    "name:eng_x_preferred":[
        "Chauki"
    ],
    "wof:name":"Chauki",
    "wof:placetype":"locality",
    "wof:population":61
},
  "geometry": {"coordinates":[80.625499,27.38952],"type":"Point"}
}