{
  "type": "Feature",
  "properties": {
    "iso:country":"IN",
    "ks:ks_alt_nam":"SADAKPARA  G",
    "ks:ks_name":"Sadakpara G",
    "ks:ks_pop":733,
    "ks:ks_type":"HABITATION",
    "name:eng_x_preferred":[
        "Sadakpara G"
    ],
    "name:eng_x_variant":[
        "SADAKPARA  G"
    ],
    "wof:name":"Sadakpara G",
    "wof:placetype":"locality",
    "wof:population":733
},
  "geometry": {"coordinates":[82.144662,22.189215],"type":"Point"}
}