{
  "type": "Feature",
  "properties": {
    "gn:admin1_code":"36.0",
    "gn:admin2_code":"136.0",
    "gn:asciiname":"Mandaiyan Kali",
    "gn:country_code":"IN",
    "gn:dem":184,
    "gn:feature_class":"P",
    "gn:feature_code":"PPL",
    "gn:name":"Mandaiy\u0101n Kali",
    "gn:population":0,
    "gn:timezone":"Asia/Kolkata",
    "iso:country":"IN",
    "wof:name":"Mandaiyan Kali",
    "wof:placetype":"locality"
},
  "geometry": {"coordinates":[78.99939999999999,28.68003],"type":"Point"}
}