{
  "type": "Feature",
  "properties": {
    "iso:country":"IN",
    "ks:ks_name":"Mokoiram",
    "ks:ks_pop":147,
    "ks:ks_type":"HABITATION",
    "name:eng_x_preferred":[
        "Mokoiram"
    ],
    "wof:name":"Mokoiram",
    "wof:placetype":"locality",
    "wof:population":147
},
  "geometry": {"coordinates":[92.408092,25.74557],"type":"Point"}
}