{
  "type": "Feature",
  "properties": {
    "iso:country":"IN",
    "ks:ks_name":"Narayanapatnam",
    "ks:ks_pop":53,
    "ks:ks_type":"VILLAGE",
    "name:eng_x_preferred":[
        "Narayanapatnam"
    ],
    "wof:name":"Narayanapatnam",
    "wof:placetype":"locality",
    "wof:population":53
},
  "geometry": {"coordinates":[83.725792,18.175023],"type":"Point"}
}