{
  "type": "Feature",
  "properties": {
    "iso:country":"IN",
    "ks:ks_name":"Biranamunda",
    "ks:ks_pop":345,
    "ks:ks_type":"VILLAGE",
    "name:eng_x_preferred":[
        "Biranamunda"
    ],
    "wof:name":"Biranamunda",
    "wof:placetype":"locality",
    "wof:population":345
},
  "geometry": {"coordinates":[85.271153,21.29191],"type":"Point"}
}