{
  "type": "Feature",
  "properties": {
    "gn:admin1_code":"37",
    "gn:admin2_code":"407.0",
    "gn:asciiname":"Jhalmala",
    "gn:country_code":"IN",
    "gn:dem":755,
    "gn:feature_class":"P",
    "gn:feature_code":"PPL",
    "gn:name":"Jhalmala",
    "gn:population":0,
    "gn:timezone":"Asia/Kolkata",
    "iso:country":"IN",
    "wof:name":"Jhalmala",
    "wof:placetype":"locality"
},
  "geometry": {"coordinates":[81.00374000000002,22.04924],"type":"Point"}
}