{
  "type": "Feature",
  "properties": {
    "gn:admin1_code":"35.0",
    "gn:admin2_code":"427.0",
    "gn:asciiname":"Deori Pathak",
    "gn:country_code":"IN",
    "gn:dem":438,
    "gn:feature_class":"P",
    "gn:feature_code":"PPL",
    "gn:name":"Deori P\u0101thak",
    "gn:population":0,
    "gn:timezone":"Asia/Kolkata",
    "iso:country":"IN",
    "ks:ks_alt_nam":"Deori P\u0101thak",
    "ks:ks_name":"Deori Pathak",
    "ks:ks_pop":108,
    "ks:ks_type":"VILLAGE",
    "name:eng_x_preferred":[
        "Deori Pathak"
    ],
    "name:eng_x_variant":[
        "Deori P\u0101thak"
    ],
    "wof:name":"Deori Pathak",
    "wof:placetype":"locality",
    "wof:population":108
},
  "geometry": {"coordinates":[78.983176,23.337134],"type":"Point"}
}