{
  "type": "Feature",
  "properties": {
    "iso:country":"IN",
    "ks:ks_name":"Chiddi Purwa",
    "ks:ks_pop":221,
    "ks:ks_type":"HABITATION",
    "name:eng_x_preferred":[
        "Chiddi Purwa"
    ],
    "wof:name":"Chiddi Purwa",
    "wof:placetype":"locality",
    "wof:population":221
},
  "geometry": {"coordinates":[79.705601,26.62183],"type":"Point"}
}