{
  "type": "Feature",
  "properties": {
    "gn:admin1_code":"39.0",
    "gn:admin2_code":"64.0",
    "gn:asciiname":"Dhunga Dhara",
    "gn:country_code":"IN",
    "gn:dem":1277,
    "gn:feature_class":"P",
    "gn:feature_code":"PPL",
    "gn:name":"Dhunga Dh\u0101ra",
    "gn:population":0,
    "gn:timezone":"Asia/Kolkata",
    "iso:country":"IN",
    "wof:name":"Dhunga Dhara",
    "wof:placetype":"locality"
},
  "geometry": {"coordinates":[79.36135999999998,29.8347],"type":"Point"}
}