{
  "type": "Feature",
  "properties": {
    "gn:admin1_code":"39.0",
    "gn:admin2_code":"64.0",
    "gn:asciiname":"Dhunga Dhara",
    "gn:country_code":"IN",
    "gn:dem":1277,
    "gn:feature_class":"P",
    "gn:feature_code":"PPL",
    "gn:name":"Dhunga Dh\u0101ra",
    "gn:population":0,
    "gn:timezone":"Asia/Kolkata",
    "iso:country":"IN",
    "ks:ks_alt_nam":"Dhunga Dh\u0101ra",
    "ks:ks_name":"Dhunga Dhara",
    "ks:ks_type":"VILLAGE",
    "name:eng_x_preferred":[
        "Dhunga Dhara"
    ],
    "name:eng_x_variant":[
        "Dhunga Dh\u0101ra"
    ],
    "wof:name":"Dhunga Dhara",
    "wof:placetype":"locality"
},
  "geometry": {"coordinates":[79.361363,29.834698],"type":"Point"}
}