{
  "type": "Feature",
  "properties": {
    "gn:admin1_code":"39.0",
    "gn:asciiname":"Dadupur",
    "gn:country_code":"IN",
    "gn:dem":235,
    "gn:feature_class":"P",
    "gn:feature_code":"PPL",
    "gn:name":"D\u0101d\u016bpur",
    "gn:population":0,
    "gn:timezone":"Asia/Kolkata",
    "iso:country":"IN",
    "ks:ks_alt_nam":"D\u0101d\u016bpur",
    "ks:ks_name":"Dadupur",
    "ks:ks_pop":326,
    "ks:ks_type":"VILLAGE",
    "ks:ks_uagg_main":0,
    "name:eng_x_preferred":[
        "Dadupur"
    ],
    "name:eng_x_variant":[
        "D\u0101d\u016bpur"
    ],
    "wof:name":"Dadupur",
    "wof:placetype":"neighbourhood",
    "wof:population":326
},
  "geometry": {"coordinates":[77.942922,29.692168],"type":"Point"}
}