{
  "type": "Feature",
  "properties": {
    "iso:country":"IN",
    "ks:ks_name":"Biskurwa",
    "ks:ks_pop":1754,
    "ks:ks_type":"VILLAGE",
    "ks:ks_uagg_main":0,
    "name:eng_x_preferred":[
        "Biskurwa"
    ],
    "wof:name":"Biskurwa",
    "wof:placetype":"neighbourhood",
    "wof:population":1754
},
  "geometry": {"coordinates":[85.551254,25.204707],"type":"Point"}
}