{
  "type": "Feature",
  "properties": {
    "iso:country":"IN",
    "ks:ks_name":"Dhaital",
    "ks:ks_pop":778,
    "ks:ks_type":"VILLAGE",
    "ks:ks_uagg_main":0,
    "name:eng_x_preferred":[
        "Dhaital"
    ],
    "wof:name":"Dhaital",
    "wof:placetype":"neighbourhood",
    "wof:population":778
},
  "geometry": {"coordinates":[76.286733,27.376992],"type":"Point"}
}