{
  "type": "Feature",
  "properties": {
    "gn:admin1_code":"39.0",
    "gn:admin2_code":"64.0",
    "gn:asciiname":"Son Silang",
    "gn:country_code":"IN",
    "gn:dem":1666,
    "gn:feature_class":"P",
    "gn:feature_code":"PPL",
    "gn:name":"Son Silang",
    "gn:population":0,
    "gn:timezone":"Asia/Kolkata",
    "iso:country":"IN",
    "wof:name":"Son Silang",
    "wof:placetype":"locality"
},
  "geometry": {"coordinates":[79.89856999999998,29.58016],"type":"Point"}
}