{
  "type": "Feature",
  "properties": {
    "iso:country":"IN",
    "ks:ks_name":"Harakodu",
    "ks:ks_pop":22,
    "ks:ks_type":"HABITATION",
    "name:eng_x_preferred":[
        "Harakodu"
    ],
    "wof:name":"Harakodu",
    "wof:placetype":"locality",
    "wof:population":22
},
  "geometry": {"coordinates":[75.220637,13.417095],"type":"Point"}
}