{
  "type": "Feature",
  "properties": {
    "gn:admin1_code":"11.0",
    "gn:admin2_code":"32.0",
    "gn:asciiname":"Kuphor",
    "gn:country_code":"IN",
    "gn:dem":1446,
    "gn:feature_class":"P",
    "gn:feature_code":"PPL",
    "gn:name":"Kuphor",
    "gn:population":0,
    "gn:timezone":"Asia/Kolkata",
    "iso:country":"IN",
    "wof:name":"Kuphor",
    "wof:placetype":"locality"
},
  "geometry": {"coordinates":[77.70539000000002,30.61479000000001],"type":"Point"}
}