{
  "type": "Feature",
  "properties": {
    "iso:country":"IN",
    "ks:ks_name":"Wadakarwada",
    "ks:ks_pop":54,
    "ks:ks_type":"HABITATION",
    "name:eng_x_preferred":[
        "Wadakarwada"
    ],
    "wof:name":"Wadakarwada",
    "wof:placetype":"locality",
    "wof:population":54
},
  "geometry": {"coordinates":[74.37980399999999,15.421334],"type":"Point"}
}