{
  "type": "Feature",
  "properties": {
    "iso:country":"IN",
    "ks:ks_name":"Mohachi Mali",
    "ks:ks_pop":112,
    "ks:ks_type":"HABITATION",
    "name:eng_x_preferred":[
        "Mohachi Mali"
    ],
    "wof:name":"Mohachi Mali",
    "wof:placetype":"locality",
    "wof:population":112
},
  "geometry": {"coordinates":[73.40294400000001,20.380889],"type":"Point"}
}