{
  "type": "Feature",
  "properties": {
    "iso:country":"IN",
    "ks:ks_name":"Jannaudi",
    "ks:ks_pop":330,
    "ks:ks_type":"VILLAGE",
    "name:eng_x_preferred":[
        "Jannaudi"
    ],
    "wof:name":"Jannaudi",
    "wof:placetype":"locality",
    "wof:population":330
},
  "geometry": {"coordinates":[81.315702,23.643119],"type":"Point"}
}