{
  "type": "Feature",
  "properties": {
    "iso:country":"IN",
    "ks:ks_name":"Sirakihawa",
    "ks:ks_pop":353,
    "ks:ks_type":"HABITATION",
    "name:eng_x_preferred":[
        "Sirakihawa"
    ],
    "wof:name":"Sirakihawa",
    "wof:placetype":"locality",
    "wof:population":353
},
  "geometry": {"coordinates":[82.839574,27.330641],"type":"Point"}
}