{
  "type": "Feature",
  "properties": {
    "iso:country":"IN",
    "ks:ks_name":"Dombatagiri",
    "ks:ks_pop":308,
    "ks:ks_type":"HABITATION",
    "name:eng_x_preferred":[
        "Dombatagiri"
    ],
    "wof:name":"Dombatagiri",
    "wof:placetype":"locality",
    "wof:population":308
},
  "geometry": {"coordinates":[75.214389,12.642539],"type":"Point"}
}