{
  "type": "Feature",
  "properties": {
    "iso:country":"IN",
    "ks:ks_name":"Patarhatu",
    "ks:ks_pop":568,
    "ks:ks_type":"VILLAGE",
    "name:eng_x_preferred":[
        "Patarhatu"
    ],
    "wof:name":"Patarhatu",
    "wof:placetype":"locality",
    "wof:population":568
},
  "geometry": {"coordinates":[85.988651,22.147949],"type":"Point"}
}