{
  "type": "Feature",
  "properties": {
    "gn:admin1_code":"11",
    "gn:admin2_code":"23.0",
    "gn:asciiname":"Drumka",
    "gn:country_code":"IN",
    "gn:dem":1543,
    "gn:feature_class":"P",
    "gn:feature_code":"PPL",
    "gn:name":"Drumka",
    "gn:population":0,
    "gn:timezone":"Asia/Kolkata",
    "iso:country":"IN",
    "wof:name":"Drumka",
    "wof:placetype":"locality"
},
  "geometry": {"coordinates":[76.04173,32.39137],"type":"Point"}
}