{
  "type": "Feature",
  "properties": {
    "gn:admin1_code":"19.0",
    "gn:admin2_code":"563.0",
    "gn:asciiname":"Kote",
    "gn:country_code":"IN",
    "gn:dem":69,
    "gn:feature_class":"P",
    "gn:feature_code":"PPL",
    "gn:name":"Kote",
    "gn:population":0,
    "gn:timezone":"Asia/Kolkata",
    "iso:country":"IN",
    "name:ceb_x_preferred":[
        "Kote"
    ],
    "name:deu_x_preferred":[
        "Kote"
    ],
    "name:swe_x_preferred":[
        "Kote"
    ],
    "wof:name":"Kote",
    "wof:placetype":"locality"
},
  "geometry": {"coordinates":[74.27463,14.94846],"type":"Point"}
}