{
  "type": "Feature",
  "properties": {
    "gn:admin1_code":"19.0",
    "gn:admin2_code":"563.0",
    "gn:asciiname":"Kote",
    "gn:country_code":"IN",
    "gn:dem":69,
    "gn:feature_class":"P",
    "gn:feature_code":"PPL",
    "gn:name":"Kote",
    "gn:population":0,
    "gn:timezone":"Asia/Kolkata",
    "iso:country":"IN",
    "ks:ks_name":"Kote",
    "ks:ks_pop":62,
    "ks:ks_type":"HABITATION",
    "name:ceb_x_preferred":[
        "Kote"
    ],
    "name:deu_x_preferred":[
        "Kote"
    ],
    "name:eng_x_preferred":[
        "Kote"
    ],
    "name:swe_x_preferred":[
        "Kote"
    ],
    "wof:name":"Kote",
    "wof:placetype":"locality",
    "wof:population":62
},
  "geometry": {"coordinates":[74.27507300000001,14.948409],"type":"Point"}
}