{
  "type": "Feature",
  "properties": {
    "iso:country":"IN",
    "ks:ks_alt_nam":"CRP kunnu",
    "ks:ks_name":"Crp Kunnu",
    "ks:ks_pop":150,
    "ks:ks_type":"HABITATION",
    "name:eng_x_preferred":[
        "Crp Kunnu"
    ],
    "wof:name":"Crp Kunnu",
    "wof:placetype":"locality",
    "wof:population":150
},
  "geometry": {"coordinates":[75.8879,11.844841],"type":"Point"}
}