{
  "type": "Feature",
  "properties": {
    "gn:admin1_code":"36",
    "gn:admin2_code":"157.0",
    "gn:asciiname":"Amethi",
    "gn:country_code":"IN",
    "gn:dem":117,
    "gn:feature_class":"P",
    "gn:feature_code":"PPL",
    "gn:name":"Amethi",
    "gn:population":0,
    "gn:timezone":"Asia/Kolkata",
    "iso:country":"IN",
    "ks:ks_name":"Amethi",
    "ks:ks_pop":313,
    "ks:ks_type":"VILLAGE",
    "ks:ks_uagg_main":0,
    "name:bih_x_preferred":[
        "\u0905\u092e\u0947\u0920\u0940"
    ],
    "name:bpy_x_preferred":[
        "\u0986\u09ae\u09c7\u09a5\u09bf"
    ],
    "name:cat_x_preferred":[
        "Amethi"
    ],
    "name:ceb_x_preferred":[
        "Amethi"
    ],
    "name:deu_x_preferred":[
        "Amethi"
    ],
    "name:eng_x_preferred":[
        "Amethi"
    ],
    "name:fas_x_preferred":[
        "\u0627\u0645\u062a\u06cc"
    ],
    "name:guj_x_preferred":[
        "\u0a85\u0aae\u0ac7\u0aa0\u0ac0"
    ],
    "name:hin_x_preferred":[
        "\u0905\u092e\u0947\u0920\u0940"
    ],
    "name:ita_x_preferred":[
        "Amethi"
    ],
    "name:kan_x_preferred":[
        "\u0c85\u0cae\u0cc7\u0ca5\u0cbf"
    ],
    "name:mal_x_preferred":[
        "\u0d05\u0d2e\u0d47\u0d20\u0d3f"
    ],
    "name:mar_x_preferred":[
        "\u0905\u092e\u0947\u0920\u0940"
    ],
    "name:min_x_preferred":[
        "Amethi"
    ],
    "name:msa_x_preferred":[
        "Amethi"
    ],
    "name:nep_x_preferred":[
        "\u0905\u092e\u0947\u0920\u0940"
    ],
    "name:new_x_preferred":[
        "\u0905\u092e\u0947\u0920\u0940"
    ],
    "name:nld_x_preferred":[
        "Amethi"
    ],
    "name:pan_x_preferred":[
        "\u0a05\u0a2e\u0a47\u0a20\u0a40"
    ],
    "name:pol_x_preferred":[
        "Amethi"
    ],
    "name:tam_x_preferred":[
        "\u0b85\u0bae\u0bc7\u0ba4\u0bbf"
    ],
    "name:tel_x_preferred":[
        "\u0c05\u0c2e\u0c47\u0c25\u0c40"
    ],
    "name:urd_x_preferred":[
        "\u0627\u0645\u06cc\u0679\u06be\u06cc"
    ],
    "name:vie_x_preferred":[
        "Amethi"
    ],
    "name:zho_x_preferred":[
        "\u963f\u6885\u8482"
    ],
    "wof:name":"Amethi",
    "wof:placetype":"neighbourhood",
    "wof:population":313
},
  "geometry": {"coordinates":[81.159982,26.755472],"type":"Point"}
}