{
  "type": "Feature",
  "properties": {
    "iso:country":"IN",
    "ks:ks_name":"Holekattu",
    "ks:ks_pop":17,
    "ks:ks_type":"HABITATION",
    "name:eng_x_preferred":[
        "Holekattu"
    ],
    "wof:name":"Holekattu",
    "wof:placetype":"locality",
    "wof:population":17
},
  "geometry": {"coordinates":[74.73372999999999,14.29612],"type":"Point"}
}