{
  "type": "Feature",
  "properties": {
    "gn:country":"IN",
    "gn:fcode":"PPL",
    "gn:pop":14384,
    "iso:country":"IN",
    "name:ben_x_preferred":[
        "\u0986\u09b9\u09c7\u09b0\u09bf"
    ],
    "name:cat_x_preferred":[
        "Ahiri"
    ],
    "name:ceb_x_preferred":[
        "Ahiri"
    ],
    "name:deu_x_preferred":[
        "Aheri"
    ],
    "name:eng_x_preferred":[
        "Aheri"
    ],
    "name:fas_x_preferred":[
        "\u0627\u0647\u0631\u06cc\u060c \u06af\u0627\u062f\u0686\u06cc\u0631\u0648\u0644\u06cc"
    ],
    "name:fas_x_variant":[
        "\u0627\u0647\u0631\u06cc"
    ],
    "name:fra_x_preferred":[
        "Aheri"
    ],
    "name:guj_x_preferred":[
        "\u0a85\u0ab9\u0ac7\u0ab0\u0ac0"
    ],
    "name:hin_x_preferred":[
        "\u0905\u0939\u0947\u0930\u0940"
    ],
    "name:ita_x_preferred":[
        "Ahiri"
    ],
    "name:jpn_x_preferred":[
        "\u30a2\u30d8\u30ea"
    ],
    "name:kan_x_preferred":[
        "\u0c85\u0cb9\u0cc6\u0cb0\u0cbf"
    ],
    "name:kor_x_preferred":[
        "\uc544\uc5d0\ub9ac"
    ],
    "name:mar_x_preferred":[
        "\u0905\u0939\u0947\u0930\u0940"
    ],
    "name:nld_x_preferred":[
        "Aheri"
    ],
    "name:por_x_preferred":[
        "Aheri"
    ],
    "name:rus_x_preferred":[
        "\u0410\u0445\u0435\u0440\u0438"
    ],
    "name:spa_x_preferred":[
        "Aheri"
    ],
    "name:swe_x_preferred":[
        "Ahiri"
    ],
    "name:tam_x_preferred":[
        "\u0b85\u0bb9\u0bc0\u0bb0\u0bbf"
    ],
    "name:tel_x_preferred":[
        "\u0c05\u0c39\u0c47\u0c30\u0c3f"
    ],
    "name:urd_x_preferred":[
        "\u0627\u06c1\u0631\u06cc\u060c \u06af\u0691\u06be \u0686\u0631\u0648\u0644\u06cc"
    ],
    "name:urd_x_variant":[
        "\u0627\u06c1\u0631\u06cc"
    ],
    "qs:name":"Aheri",
    "qs:name_adm0":"India",
    "qs:name_adm1":"Maharashtra",
    "qs:photos_9r":0,
    "qs:photos_sr":0,
    "qs:placetype":"Town",
    "qs:pop_sr":"6",
    "wd:wordcount":28,
    "wof:name":"Aheri",
    "wof:placetype":"locality",
    "wof:population":14384
},
  "geometry": {"coordinates":[80.00359,19.41386],"type":"Point"}
}