{
  "type": "Feature",
  "properties": {
    "gn:admin1_code":"19",
    "gn:admin2_code":"559.0",
    "gn:asciiname":"Hire Lakkihal",
    "gn:country_code":"IN",
    "gn:dem":525,
    "gn:feature_class":"P",
    "gn:feature_code":"PPL",
    "gn:name":"Hire Lakkih\u0101l",
    "gn:population":0,
    "gn:timezone":"Asia/Kolkata",
    "iso:country":"IN",
    "wof:name":"Hire Lakkihal",
    "wof:placetype":"locality"
},
  "geometry": {"coordinates":[76.32491,16.04146],"type":"Point"}
}