{
  "type": "Feature",
  "properties": {
    "gn:admin1_code":"36",
    "gn:admin2_code":"178.0",
    "gn:asciiname":"Hisamuddinpur Pipra",
    "gn:country_code":"IN",
    "gn:dem":88,
    "gn:feature_class":"P",
    "gn:feature_code":"PPL",
    "gn:name":"His\u0101mudd\u012bnpur Pipra",
    "gn:population":0,
    "gn:timezone":"Asia/Kolkata",
    "iso:country":"IN",
    "wof:name":"Hisamuddinpur Pipra",
    "wof:placetype":"locality"
},
  "geometry": {"coordinates":[82.85427,26.48701],"type":"Point"}
}