{
  "type": "Feature",
  "properties": {
    "iso:country":"IN",
    "ks:ks_name":"Sevaniya",
    "ks:ks_pop":381,
    "ks:ks_type":"HABITATION",
    "name:eng_x_preferred":[
        "Sevaniya"
    ],
    "wof:name":"Sevaniya",
    "wof:placetype":"locality",
    "wof:population":381
},
  "geometry": {"coordinates":[73.504278,23.233639],"type":"Point"}
}