{
  "type": "Feature",
  "properties": {
    "iso:country":"IN",
    "ks:ks_alt_nam":"Rudraw\u0101r Khurd",
    "ks:ks_alt_nam_2":"Rudrawar Khurd",
    "ks:ks_name":"Kudarwar Khurd",
    "ks:ks_pop":175,
    "ks:ks_type":"VILLAGE",
    "ks:ks_uagg_main":0,
    "name:eng_x_preferred":[
        "Kudarwar Khurd"
    ],
    "name:eng_x_variant":[
        "Rudraw\u0101r Khurd",
        "Rudrawar Khurd"
    ],
    "wof:name":"Kudarwar Khurd",
    "wof:placetype":"neighbourhood",
    "wof:population":175
},
  "geometry": {"coordinates":[83.67853599999999,24.988181],"type":"Point"}
}