{
  "type": "Feature",
  "properties": {
    "gn:admin1_code":"36.0",
    "gn:asciiname":"Behta",
    "gn:country_code":"IN",
    "gn:dem":153,
    "gn:feature_class":"P",
    "gn:feature_code":"PPL",
    "gn:name":"Beht\u0101",
    "gn:population":0,
    "gn:timezone":"Asia/Kolkata",
    "iso:country":"IN",
    "ks:ks_alt_nam":"Beht\u0101",
    "ks:ks_name":"Behta",
    "ks:ks_pop":409,
    "ks:ks_type":"VILLAGE",
    "name:eng_x_preferred":[
        "Behta"
    ],
    "name:eng_x_variant":[
        "Beht\u0101"
    ],
    "wof:name":"Behta",
    "wof:placetype":"locality",
    "wof:population":409
},
  "geometry": {"coordinates":[79.003507,26.081457],"type":"Point"}
}