{
  "type": "Feature",
  "properties": {
    "iso:country":"IN",
    "ks:ks_name":"Badasailur",
    "ks:ks_pop":80,
    "ks:ks_type":"VILLAGE",
    "name:eng_x_preferred":[
        "Badasailur"
    ],
    "wof:name":"Badasailur",
    "wof:placetype":"locality",
    "wof:population":80
},
  "geometry": {"coordinates":[81.69998699999999,17.996767],"type":"Point"}
}