{
  "type": "Feature",
  "properties": {
    "iso:country":"IN",
    "ks:ks_name":"Holesalu",
    "ks:ks_pop":361,
    "ks:ks_type":"HABITATION",
    "name:eng_x_preferred":[
        "Holesalu"
    ],
    "wof:name":"Holesalu",
    "wof:placetype":"locality",
    "wof:population":361
},
  "geometry": {"coordinates":[74.76450199999999,13.416502],"type":"Point"}
}