{
  "type": "Feature",
  "properties": {
    "iso:country":"IN",
    "ks:ks_alt_nam":"NAWAPARA",
    "ks:ks_name":"Nawapara",
    "ks:ks_pop":1010,
    "ks:ks_type":"HABITATION",
    "name:eng_x_preferred":[
        "Nawapara"
    ],
    "wof:name":"Nawapara",
    "wof:placetype":"locality",
    "wof:population":1010
},
  "geometry": {"coordinates":[83.688829,23.124518],"type":"Point"}
}