{
  "type": "Feature",
  "properties": {
    "iso:country":"IN",
    "ks:ks_name":"Bamunirpar",
    "ks:ks_pop":55,
    "ks:ks_type":"HABITATION",
    "name:eng_x_preferred":[
        "Bamunirpar"
    ],
    "wof:name":"Bamunirpar",
    "wof:placetype":"locality",
    "wof:population":55
},
  "geometry": {"coordinates":[90.05259100000001,25.99237],"type":"Point"}
}