{
  "type": "Feature",
  "properties": {
    "gn:admin1_code":"34.0",
    "gn:admin2_code":"231.0",
    "gn:asciiname":"Kashidih",
    "gn:country_code":"IN",
    "gn:dem":80,
    "gn:feature_class":"P",
    "gn:feature_code":"PPL",
    "gn:name":"K\u0101shidih",
    "gn:population":0,
    "gn:timezone":"Asia/Kolkata",
    "iso:country":"IN",
    "wof:name":"Kashidih",
    "wof:placetype":"locality"
},
  "geometry": {"coordinates":[84.51021999999998,25.32185],"type":"Point"}
}