{
  "type": "Feature",
  "properties": {
    "iso:country":"IN",
    "ks:ks_alt_nam":"Pohap singh ka Pura",
    "ks:ks_name":"Pohap Singh Ka Pura",
    "ks:ks_pop":262,
    "ks:ks_type":"HABITATION",
    "name:eng_x_preferred":[
        "Pohap Singh Ka Pura"
    ],
    "wof:name":"Pohap Singh Ka Pura",
    "wof:placetype":"locality",
    "wof:population":262
},
  "geometry": {"coordinates":[77.583433,26.726428],"type":"Point"}
}