{
  "type": "Feature",
  "properties": {
    "iso:country":"IN",
    "ks:ks_name":"Agraharam",
    "ks:ks_pop":188,
    "ks:ks_type":"HABITATION",
    "name:eng_x_preferred":[
        "Agraharam"
    ],
    "wof:name":"Agraharam",
    "wof:placetype":"locality",
    "wof:population":188
},
  "geometry": {"coordinates":[79.061457,10.223078],"type":"Point"}
}