{
  "type": "Feature",
  "properties": {
    "iso:country":"IN",
    "ks:ks_alt_nam":"HARIZAN BASTI",
    "ks:ks_name":"Harizan Basti",
    "ks:ks_pop":304,
    "ks:ks_type":"HABITATION",
    "name:eng_x_preferred":[
        "Harizan Basti"
    ],
    "wof:name":"Harizan Basti",
    "wof:placetype":"locality",
    "wof:population":304
},
  "geometry": {"coordinates":[82.90431,25.337113],"type":"Point"}
}