{
  "type": "Feature",
  "properties": {
    "gn:admin1_code":"34",
    "gn:admin2_code":"233.0",
    "gn:asciiname":"Kolhua",
    "gn:country_code":"IN",
    "gn:dem":507,
    "gn:feature_class":"P",
    "gn:feature_code":"PPL",
    "gn:name":"Kolhua",
    "gn:population":0,
    "gn:timezone":"Asia/Kolkata",
    "iso:country":"IN",
    "ks:ks_name":"Kolhua",
    "ks:ks_pop":207,
    "ks:ks_type":"VILLAGE",
    "name:eng_x_preferred":[
        "Kolhua"
    ],
    "wof:name":"Kolhua",
    "wof:placetype":"locality",
    "wof:population":207
},
  "geometry": {"coordinates":[83.64367900000001,24.629573],"type":"Point"}
}