{
  "type": "Feature",
  "properties": {
    "gn:admin1_code":"36.0",
    "gn:admin2_code":"174.0",
    "gn:asciiname":"Naubasta",
    "gn:country_code":"IN",
    "gn:dem":104,
    "gn:feature_class":"P",
    "gn:feature_code":"PPL",
    "gn:name":"Naubasta",
    "gn:population":0,
    "gn:timezone":"Asia/Kolkata",
    "iso:country":"IN",
    "name:ceb_x_preferred":[
        "Naubasta"
    ],
    "name:mai_x_preferred":[
        "\u0928\u094c\u092c\u0938\u094d\u0924\u093e"
    ],
    "name:msa_x_preferred":[
        "Naubasta"
    ],
    "name:nep_x_preferred":[
        "\u0928\u094c\u092c\u0938\u094d\u0924\u093e"
    ],
    "name:new_x_preferred":[
        "\u0928\u094c\u092c\u0938\u094d\u0924\u093e"
    ],
    "name:pol_x_preferred":[
        "Naubasta"
    ],
    "wof:name":"Naubasta",
    "wof:placetype":"locality"
},
  "geometry": {"coordinates":[81.51787,25.42176],"type":"Point"}
}