{
  "type": "Feature",
  "properties": {
    "iso:country":"IN",
    "ks:ks_name":"No 2 Oxiguri",
    "ks:ks_pop":380,
    "ks:ks_type":"HABITATION",
    "name:eng_x_preferred":[
        "No 2 Oxiguri"
    ],
    "wof:name":"No 2 Oxiguri",
    "wof:placetype":"locality",
    "wof:population":380
},
  "geometry": {"coordinates":[90.552719,26.735635],"type":"Point"}
}