{
  "type": "Feature",
  "properties": {
    "iso:country":"IN",
    "ks:ks_name":"Sikhon Ki Dhani",
    "ks:ks_pop":60,
    "ks:ks_type":"HABITATION",
    "name:eng_x_preferred":[
        "Sikhon Ki Dhani"
    ],
    "wof:name":"Sikhon Ki Dhani",
    "wof:placetype":"locality",
    "wof:population":60
},
  "geometry": {"coordinates":[74.446269,29.794283],"type":"Point"}
}