{
  "type": "Feature",
  "properties": {
    "iso:country":"IN",
    "ks:ks_name":"Cholenahalli",
    "ks:ks_type":"VILLAGE",
    "name:eng_x_preferred":[
        "Cholenahalli"
    ],
    "wof:name":"Cholenahalli",
    "wof:placetype":"locality"
},
  "geometry": {"coordinates":[76.499965,12.437428],"type":"Point"}
}