{
  "type": "Feature",
  "properties": {
    "gn:admin1_code":"40",
    "gn:admin2_code":"541.0",
    "gn:asciiname":"Sindur Tanda",
    "gn:country_code":"IN",
    "gn:dem":175,
    "gn:feature_class":"P",
    "gn:feature_code":"PPL",
    "gn:name":"Sindur T\u0101nda",
    "gn:population":0,
    "gn:timezone":"Asia/Kolkata",
    "iso:country":"IN",
    "name:eng_x_preferred":[
        "Sindur T\u0101nda"
    ],
    "wof:name":"Sindur Tanda",
    "wof:placetype":"locality"
},
  "geometry": {"coordinates":[79.93897,17.36317],"type":"Point"}
}