{
  "type": "Feature",
  "properties": {
    "gn:admin1_code":"36.0",
    "gn:admin2_code":"174.0",
    "gn:asciiname":"Sobhanan",
    "gn:country_code":"IN",
    "gn:dem":100,
    "gn:feature_class":"P",
    "gn:feature_code":"PPL",
    "gn:name":"Sobhan\u0101n",
    "gn:population":0,
    "gn:timezone":"Asia/Kolkata",
    "iso:country":"IN",
    "ks:ks_alt_nam":"Sobhan\u0101n",
    "ks:ks_name":"Sobhanan",
    "ks:ks_type":"VILLAGE",
    "ks:ks_uagg_main":0,
    "name:eng_x_preferred":[
        "Sobhanan"
    ],
    "name:eng_x_variant":[
        "Sobhan\u0101n"
    ],
    "wof:name":"Sobhanan",
    "wof:placetype":"neighbourhood"
},
  "geometry": {"coordinates":[81.606184,25.574955],"type":"Point"}
}