{
  "type": "Feature",
  "properties": {
    "gn:admin1_code":"21.0",
    "gn:admin2_code":"370.0",
    "gn:asciiname":"Samardarha",
    "gn:country_code":"IN",
    "gn:dem":234,
    "gn:feature_class":"P",
    "gn:feature_code":"PPL",
    "gn:name":"Samardarha",
    "gn:population":0,
    "gn:timezone":"Asia/Kolkata",
    "iso:country":"IN",
    "ks:ks_name":"Samardarha",
    "ks:ks_pop":278,
    "ks:ks_type":"VILLAGE",
    "name:eng_x_preferred":[
        "Samardarha"
    ],
    "wof:name":"Samardarha",
    "wof:placetype":"locality",
    "wof:population":278
},
  "geometry": {"coordinates":[83.511262,21.554121],"type":"Point"}
}