{
  "type": "Feature",
  "properties": {
    "gn:admin1_code":"19.0",
    "gn:admin2_code":"578.0",
    "gn:asciiname":"Kodsoge",
    "gn:country_code":"IN",
    "gn:dem":859,
    "gn:feature_class":"P",
    "gn:feature_code":"PPL",
    "gn:name":"Kodsoge",
    "gn:population":0,
    "gn:timezone":"Asia/Kolkata",
    "iso:country":"IN",
    "wof:name":"Kodsoge",
    "wof:placetype":"locality"
},
  "geometry": {"coordinates":[76.75115,11.7371],"type":"Point"}
}