{
  "type": "Feature",
  "properties": {
    "iso:country":"IN",
    "ks:ks_alt_nam":"Venkatagiri X road",
    "ks:ks_name":"Venkatagiri X Road",
    "ks:ks_pop":25,
    "ks:ks_type":"HABITATION",
    "ks:ks_uagg_main":0,
    "name:eng_x_preferred":[
        "Venkatagiri X Road"
    ],
    "wof:name":"Venkatagiri X Road",
    "wof:placetype":"neighbourhood",
    "wof:population":25
},
  "geometry": {"coordinates":[80.114341,17.213777],"type":"Point"}
}