{
  "type": "Feature",
  "properties": {
    "iso:country":"IN",
    "ks:ks_name":"Tamaguda",
    "ks:ks_pop":43,
    "ks:ks_type":"HABITATION",
    "name:eng_x_preferred":[
        "Tamaguda"
    ],
    "wof:name":"Tamaguda",
    "wof:placetype":"locality",
    "wof:population":43
},
  "geometry": {"coordinates":[82.331676,18.572789],"type":"Point"}
}