{
  "type": "Feature",
  "properties": {
    "iso:country":"IN",
    "ks:ks_name":"Nakulabaspur",
    "ks:ks_pop":57,
    "ks:ks_type":"VILLAGE",
    "name:eng_x_preferred":[
        "Nakulabaspur"
    ],
    "wof:name":"Nakulabaspur",
    "wof:placetype":"locality",
    "wof:population":57
},
  "geometry": {"coordinates":[85.175358,20.96444],"type":"Point"}
}