{
  "type": "Feature",
  "properties": {
    "iso:country":"IN",
    "ks:ks_name":"Devari Uttar",
    "ks:ks_pop":144,
    "ks:ks_type":"VILLAGE",
    "name:eng_x_preferred":[
        "Devari Uttar"
    ],
    "wof:name":"Devari Uttar",
    "wof:placetype":"locality",
    "wof:population":144
},
  "geometry": {"coordinates":[82.209915,24.864618],"type":"Point"}
}