{
  "type": "Feature",
  "properties": {
    "iso:country":"IN",
    "ks:ks_name":"Puria",
    "ks:ks_pop":1922,
    "ks:ks_type":"VILLAGE",
    "ks:ks_uagg_main":0,
    "name:eng_x_preferred":[
        "Puria"
    ],
    "wof:name":"Puria",
    "wof:placetype":"neighbourhood",
    "wof:population":1922
},
  "geometry": {"coordinates":[88.382212,25.614387],"type":"Point"}
}