{
  "type": "Feature",
  "properties": {
    "iso:country":"IN",
    "ks:ks_name":"Devinagar",
    "ks:ks_pop":463,
    "ks:ks_type":"HABITATION",
    "name:eng_x_preferred":[
        "Devinagar"
    ],
    "wof:name":"Devinagar",
    "wof:placetype":"locality",
    "wof:population":463
},
  "geometry": {"coordinates":[72.276914,26.800689],"type":"Point"}
}