{
  "type": "Feature",
  "properties": {
    "iso:country":"IN",
    "name:ara_x_preferred":[
        "\u0627\u0644\u0642\u0637\u0627\u0639 18"
    ],
    "name:ben_bn_x_preferred":[
        "\u09b8\u09c7\u0995\u09cd\u099f\u09b0 18"
    ],
    "name:ben_in_x_preferred":[
        "\u09b8\u09c7\u0995\u09cd\u099f\u09b0 18"
    ],
    "name:eng_x_preferred":[
        "Sector 18"
    ],
    "name:guj_x_preferred":[
        "\u0ab8\u0ac7\u0a95\u0acd\u0a9f\u0ab0 18"
    ],
    "name:hin_x_preferred":[
        "\u0938\u0947\u0915\u094d\u091f\u0930 18"
    ],
    "name:kan_x_preferred":[
        "\u0cb8\u0cc6\u0c95\u0ccd\u0c9f\u0cb0\u0ccd 18"
    ],
    "name:mal_x_preferred":[
        "\u0d38\u0d46\u0d15\u0d4d\u0d1f\u0d30\u0d4d\u200d\u200c 18"
    ],
    "name:mar_x_preferred":[
        "\u0938\u0947\u0915\u094d\u091f\u0930 \u0967\u096e"
    ],
    "name:pan_x_preferred":[
        "\u0a38\u0a48\u0a15\u0a1f\u0a30 18"
    ],
    "name:tam_x_preferred":[
        "\u0baa\u0bbf\u0bb0\u0bbf\u0bb5\u0bc1 18"
    ],
    "name:tel_x_preferred":[
        "\u0c38\u0c46\u0c15\u0c4d\u0c1f\u0c30\u0c4d\u200c 18"
    ],
    "name:urd_x_preferred":[
        "\u0633\u06cc\u06a9\u0679\u0631 18"
    ],
    "qs:gn_local":0,
    "qs:local_max":676,
    "qs:local_sum":2010,
    "qs:localhoods":13,
    "qs:name":"Sector 18",
    "qs:name_adm0":"India",
    "qs:name_adm1":"Uttar Pradesh",
    "qs:name_adm2":"Gautam Buddha Nagar",
    "qs:name_local":"Noida",
    "qs:photo_max":160,
    "qs:photo_sum":424,
    "qs:placetype":"Suburb",
    "qs:quad_count":15,
    "qs:woe_adm0":23424848,
    "qs:woe_adm1":2345760,
    "qs:woe_adm2":12586743,
    "qs:woe_lau":0,
    "qs:woe_local":24505179,
    "qs:woe_ver":"7.10.0",
    "wof:lang":[
        "eng"
    ],
    "wof:name":"Sector 18",
    "wof:placetype":"neighbourhood"
},
  "geometry": {"coordinates":[77.323142,28.569897],"type":"Point"}
}