{
  "type": "Feature",
  "properties": {
    "iso:country":"IN",
    "name:eng_x_preferred":[
        "Dona Paula"
    ],
    "name:gom_x_preferred":[
        "\u0926\u094b\u0928\u093e \u092a\u094b\u0932"
    ],
    "name:nld_x_preferred":[
        "Dona Paula"
    ],
    "name:und_x_variant":[
        "Donna Paulaho"
    ],
    "qs:gn_adm0_cc":"IN",
    "qs:gn_fcode":"PPL",
    "qs:gn_local":0,
    "qs:gn_namadm1":"33",
    "qs:gn_name":"Dona Paula",
    "qs:local_max":400,
    "qs:local_sum":576,
    "qs:localhoods":4,
    "qs:name":"Dona Paula",
    "qs:name_adm0":"India",
    "qs:name_adm1":"Goa",
    "qs:name_adm2":"North Goa",
    "qs:name_local":"Calapor",
    "qs:photo_max":241,
    "qs:photo_sum":400,
    "qs:placetype":"Suburb",
    "qs:quad_count":11,
    "qs:woe_adm0":23424848,
    "qs:woe_adm1":2345764,
    "qs:woe_adm2":12586827,
    "qs:woe_lau":0,
    "qs:woe_local":28999225,
    "qs:woe_ver":"7.10.0",
    "wd:wordcount":648,
    "wof:lang":[
        "eng"
    ],
    "wof:name":"Dona Paula",
    "wof:placetype":"neighbourhood"
},
  "geometry": {"coordinates":[73.815158,15.457185],"type":"Point"}
}