{
  "type": "Feature",
  "properties": {
    "iso:country":"IN",
    "name:ara_x_preferred":[
        "\u062f\u0648\u0646\u0627 \u0628\u0627\u0648\u0644\u0627"
    ],
    "name:ben_bn_x_preferred":[
        "\u09a1\u09cb\u09a8\u09be \u09aa\u09b2\u09be"
    ],
    "name:ben_in_x_preferred":[
        "\u09a1\u09cb\u09a8\u09be \u09aa\u09b2\u09be"
    ],
    "name:eng_x_preferred":[
        "Dona Paula"
    ],
    "name:gom_x_preferred":[
        "\u0926\u094b\u0928\u093e \u092a\u094b\u0932"
    ],
    "name:guj_x_preferred":[
        "\u0aa6\u0acb\u0aa8\u0abe \u0aaa\u0acc\u0ab2\u0abe"
    ],
    "name:hin_x_preferred":[
        "\u0921\u094b\u0928\u093e \u092a\u0949\u0932\u093e"
    ],
    "name:kan_x_preferred":[
        "\u0ca1\u0ccb\u0ca8\u0cbe \u0caa\u0ccc\u0cb2\u0cbe"
    ],
    "name:mal_x_preferred":[
        "\u0d21\u0d4b\u0d23 \u0d2a\u0d4b\u0d33"
    ],
    "name:mar_x_preferred":[
        "\u0921\u094b\u0928\u093e \u092a\u093e\u0909\u0932\u093e"
    ],
    "name:nld_x_preferred":[
        "Dona Paula"
    ],
    "name:pan_x_preferred":[
        "\u0a21\u0a4b\u0a28\u0a3e \u0a2a\u0a4c\u0a32\u0a3e"
    ],
    "name:tam_x_preferred":[
        "\u0ba4\u0bcb\u0ba9\u0bbe \u0baa\u0bcc\u0bb2\u0bbe"
    ],
    "name:tel_x_preferred":[
        "\u0c21\u0c4b\u0c28\u0c3e \u0c2a\u0c4c\u0c32\u0c3e"
    ],
    "name:und_x_variant":[
        "Donna Paulaho"
    ],
    "name:urd_x_preferred":[
        "\u0688\u0648\u0646\u0627 \u067e\u0627\u0624\u0644\u0627"
    ],
    "qs:gn_adm0_cc":"IN",
    "qs:gn_fcode":"PPL",
    "qs:gn_local":0,
    "qs:gn_namadm1":"33",
    "qs:gn_name":"Dona Paula",
    "qs:local_max":400,
    "qs:local_sum":576,
    "qs:localhoods":4,
    "qs:name":"Dona Paula",
    "qs:name_adm0":"India",
    "qs:name_adm1":"Goa",
    "qs:name_adm2":"North Goa",
    "qs:name_local":"Calapor",
    "qs:photo_max":241,
    "qs:photo_sum":400,
    "qs:placetype":"Suburb",
    "qs:quad_count":11,
    "qs:woe_adm0":23424848,
    "qs:woe_adm1":2345764,
    "qs:woe_adm2":12586827,
    "qs:woe_lau":0,
    "qs:woe_local":28999225,
    "qs:woe_ver":"7.10.0",
    "wd:wordcount":648,
    "wof:lang":[
        "eng"
    ],
    "wof:name":"Dona Paula",
    "wof:placetype":"neighbourhood"
},
  "geometry": {"coordinates":[73.815158,15.457185],"type":"Point"}
}