{
  "type": "Feature",
  "properties": {
    "iso:country":"IN",
    "ks:ks_name":"Pure Dham Kot",
    "ks:ks_pop":184,
    "ks:ks_type":"HABITATION",
    "ks:ks_uagg_main":0,
    "name:eng_x_preferred":[
        "Pure Dham Kot"
    ],
    "wof:name":"Pure Dham Kot",
    "wof:placetype":"neighbourhood",
    "wof:population":184
},
  "geometry": {"coordinates":[81.818811,26.565607],"type":"Point"}
}