{
  "type": "Feature",
  "properties": {
    "gn:admin1_code":"36",
    "gn:admin2_code":"196.0",
    "gn:asciiname":"Rangauli",
    "gn:country_code":"IN",
    "gn:dem":84,
    "gn:feature_class":"P",
    "gn:feature_code":"PPL",
    "gn:name":"Rangauli",
    "gn:population":0,
    "gn:timezone":"Asia/Kolkata",
    "iso:country":"IN",
    "wof:name":"Rangauli",
    "wof:placetype":"locality"
},
  "geometry": {"coordinates":[83.08809000000002,25.24227],"type":"Point"}
}