{
  "type": "Feature",
  "properties": {
    "gn:admin1_code":"11",
    "gn:admin2_code":"24.0",
    "gn:asciiname":"Rin",
    "gn:country_code":"IN",
    "gn:dem":1058,
    "gn:feature_class":"P",
    "gn:feature_code":"PPL",
    "gn:name":"Rin",
    "gn:population":0,
    "gn:timezone":"Asia/Kolkata",
    "iso:country":"IN",
    "name:deu_x_preferred":[
        "Rin"
    ],
    "name:isl_x_preferred":[
        "R\u00edn"
    ],
    "name:jpn_x_preferred":[
        "\u30ea\u30f3"
    ],
    "name:mkd_x_preferred":[
        "\u0420\u0438\u043d"
    ],
    "name:pol_x_preferred":[
        "Rin"
    ],
    "name:rus_x_preferred":[
        "\u0420\u0438\u043d"
    ],
    "name:spa_x_preferred":[
        "Rin"
    ],
    "name:srp_x_preferred":[
        "\u0420\u0438\u043d"
    ],
    "name:tha_x_preferred":[
        "\u0e23\u0e34\u0e19"
    ],
    "name:ukr_x_preferred":[
        "\u0420\u0456\u043d"
    ],
    "name:vie_x_preferred":[
        "Rin"
    ],
    "name:wln_x_preferred":[
        "Rin"
    ],
    "wof:name":"Rin",
    "wof:placetype":"locality"
},
  "geometry": {"coordinates":[76.36249000000002,32.16133],"type":"Point"}
}