{
  "type": "Feature",
  "properties": {
    "gn:admin1_code":"34.0",
    "gn:admin2_code":"207.0",
    "gn:asciiname":"Dahibhat Narotam",
    "gn:country_code":"IN",
    "gn:dem":58,
    "gn:feature_class":"P",
    "gn:feature_code":"PPL",
    "gn:name":"Dahibh\u0101t Narotam",
    "gn:population":0,
    "gn:timezone":"Asia/Kolkata",
    "iso:country":"IN",
    "wof:name":"Dahibhat Narotam",
    "wof:placetype":"locality"
},
  "geometry": {"coordinates":[86.09359000000001,26.28105],"type":"Point"}
}