{
  "type": "Feature",
  "properties": {
    "gn:admin1_code":"19.0",
    "gn:admin2_code":"584.0",
    "gn:asciiname":"Kapanigowdanapalya",
    "gn:country_code":"IN",
    "gn:dem":838,
    "gn:feature_class":"P",
    "gn:feature_code":"PPL",
    "gn:name":"Kapanigowdanap\u0101lya",
    "gn:population":0,
    "gn:timezone":"Asia/Kolkata",
    "iso:country":"IN",
    "wof:name":"Kapanigowdanapalya",
    "wof:placetype":"neighbourhood"
},
  "geometry": {"coordinates":[77.14033999999999,12.99555],"type":"Point"}
}