{
  "type": "Feature",
  "properties": {
    "iso:country":"IN",
    "ks:ks_alt_nam":"DAWAN TOLA",
    "ks:ks_name":"Dawan Tola",
    "ks:ks_pop":383,
    "ks:ks_type":"HABITATION",
    "ks:ks_uagg_main":0,
    "name:eng_x_preferred":[
        "Dawan Tola"
    ],
    "wof:name":"Dawan Tola",
    "wof:placetype":"neighbourhood",
    "wof:population":383
},
  "geometry": {"coordinates":[84.811875,26.171723],"type":"Point"}
}