{
  "type": "Feature",
  "properties": {
    "iso:country":"IN",
    "ks:ks_name":"Bhandhli",
    "ks:ks_pop":310,
    "ks:ks_type":"HABITATION",
    "name:eng_x_preferred":[
        "Bhandhli"
    ],
    "wof:name":"Bhandhli",
    "wof:placetype":"locality",
    "wof:population":310
},
  "geometry": {"coordinates":[72.42867200000001,28.132117],"type":"Point"}
}