{
  "type": "Feature",
  "properties": {
    "iso:country":"IN",
    "ks:ks_name":"Chakchapra",
    "ks:ks_pop":95,
    "ks:ks_type":"VILLAGE",
    "name:eng_x_preferred":[
        "Chakchapra"
    ],
    "wof:name":"Chakchapra",
    "wof:placetype":"locality",
    "wof:population":95
},
  "geometry": {"coordinates":[88.446623,23.314343],"type":"Point"}
}