{
  "type": "Feature",
  "properties": {
    "iso:country":"IN",
    "ks:ks_name":"Gelapukhuri Gaon",
    "ks:ks_pop":2811,
    "ks:ks_type":"VILLAGE",
    "ks:ks_uagg_main":0,
    "name:eng_x_preferred":[
        "Gelapukhuri Gaon"
    ],
    "wof:name":"Gelapukhuri Gaon",
    "wof:placetype":"locality",
    "wof:population":2811
},
  "geometry": {"coordinates":[95.35524700000001,27.522435],"type":"Point"}
}