{
  "type": "Feature",
  "properties": {
    "iso:country":"IN",
    "ks:ks_name":"Devalapura",
    "ks:ks_pop":1201,
    "ks:ks_type":"HABITATION",
    "name:eng_x_preferred":[
        "Devalapura"
    ],
    "wof:name":"Devalapura",
    "wof:placetype":"locality",
    "wof:population":1201
},
  "geometry": {"coordinates":[76.346209,15.124653],"type":"Point"}
}