{
  "type": "Feature",
  "properties": {
    "iso:country":"IN",
    "ks:ks_name":"Ajut Teron",
    "ks:ks_pop":190,
    "ks:ks_type":"HABITATION",
    "name:eng_x_preferred":[
        "Ajut Teron"
    ],
    "wof:name":"Ajut Teron",
    "wof:placetype":"locality",
    "wof:population":190
},
  "geometry": {"coordinates":[93.026864,26.305352],"type":"Point"}
}