{
  "type": "Feature",
  "properties": {
    "iso:country":"IN",
    "ks:ks_name":"Barwa Doongri",
    "ks:ks_pop":342,
    "ks:ks_type":"VILLAGE",
    "name:eng_x_preferred":[
        "Barwa Doongri"
    ],
    "wof:name":"Barwa Doongri",
    "wof:placetype":"locality",
    "wof:population":342
},
  "geometry": {"coordinates":[76.35553899999999,27.134622],"type":"Point"}
}