{
  "type": "Feature",
  "properties": {
    "gn:admin1_code":"2.0",
    "gn:admin2_code":"554.0",
    "gn:asciiname":"Kosuvaripalle",
    "gn:country_code":"IN",
    "gn:dem":597,
    "gn:feature_class":"P",
    "gn:feature_code":"PPL",
    "gn:name":"Kosuv\u0101ripalle",
    "gn:population":0,
    "gn:timezone":"Asia/Kolkata",
    "iso:country":"IN",
    "name:tel_x_preferred":[
        "\u0c15\u0c4a\u0c38\u0c41\u0c35\u0c3e\u0c30\u0c3f\u0c2a\u0c32\u0c4d\u0c32\u0c46"
    ],
    "wof:name":"Kosuvaripalle",
    "wof:placetype":"locality"
},
  "geometry": {"coordinates":[78.43628000000002,13.74891],"type":"Point"}
}