{
  "type": "Feature",
  "properties": {
    "iso:country":"IN",
    "ks:ks_name":"Hirlewadi",
    "ks:ks_pop":688,
    "ks:ks_type":"VILLAGE",
    "name:eng_x_preferred":[
        "Hirlewadi"
    ],
    "wof:name":"Hirlewadi",
    "wof:placetype":"locality",
    "wof:population":688
},
  "geometry": {"coordinates":[73.450075,16.190512],"type":"Point"}
}