{
  "type": "Feature",
  "properties": {
    "iso:country":"IN",
    "name:eng_x_preferred":[
        "Mahabubnagar"
    ],
    "wof:name":"Mahabubnagar",
    "wof:placetype":"neighbourhood"
},
  "geometry": {"coordinates":[78.00059,16.748341],"type":"Point"}
}