{
  "type": "Feature",
  "properties": {
    "iso:country":"IN",
    "ks:ks_name":"Telanchipa",
    "ks:ks_pop":78,
    "ks:ks_type":"VILLAGE",
    "name:eng_x_preferred":[
        "Telanchipa"
    ],
    "wof:name":"Telanchipa",
    "wof:placetype":"locality",
    "wof:population":78
},
  "geometry": {"coordinates":[86.161061,24.001572],"type":"Point"}
}