{
  "type": "Feature",
  "properties": {
    "iso:country":"IN",
    "ks:ks_name":"Tiwari Tola",
    "ks:ks_pop":378,
    "ks:ks_type":"HABITATION",
    "ks:ks_uagg_main":0,
    "name:eng_x_preferred":[
        "Tiwari Tola"
    ],
    "wof:name":"Tiwari Tola",
    "wof:placetype":"neighbourhood",
    "wof:population":378
},
  "geometry": {"coordinates":[86.267561,23.57956],"type":"Point"}
}