{
  "type": "Feature",
  "properties": {
    "iso:country":"IN",
    "ks:ks_name":"Brahmanwadi",
    "ks:ks_pop":76,
    "ks:ks_type":"HABITATION",
    "name:eng_x_preferred":[
        "Brahmanwadi"
    ],
    "wof:name":"Brahmanwadi",
    "wof:placetype":"locality",
    "wof:population":76
},
  "geometry": {"coordinates":[73.151967,17.727853],"type":"Point"}
}