{
  "type": "Feature",
  "properties": {
    "gn:admin1_code":"19.0",
    "gn:admin2_code":"577.0",
    "gn:asciiname":"Halganhalli",
    "gn:country_code":"IN",
    "gn:dem":832,
    "gn:feature_class":"P",
    "gn:feature_code":"PPL",
    "gn:name":"Halganhalli",
    "gn:population":0,
    "gn:timezone":"Asia/Kolkata",
    "iso:country":"IN",
    "wof:name":"Halganhalli",
    "wof:placetype":"locality"
},
  "geometry": {"coordinates":[76.16589999999999,12.32269],"type":"Point"}
}