{
  "type": "Feature",
  "properties": {
    "gn:admin1_code":"12.0",
    "gn:asciiname":"Lam",
    "gn:country_code":"IN",
    "gn:dem":276,
    "gn:feature_class":"P",
    "gn:feature_code":"PPL",
    "gn:name":"L\u0101m",
    "gn:population":0,
    "gn:timezone":"Asia/Kolkata",
    "iso:country":"IN",
    "name:ara_x_preferred":[
        "\u0644\u0627\u0645"
    ],
    "name:ben_bn_x_preferred":[
        "\u09b2\u09be\u09ae"
    ],
    "name:ben_in_x_preferred":[
        "\u09b2\u09be\u09ae"
    ],
    "name:ceb_x_preferred":[
        "Lam"
    ],
    "name:dan_x_preferred":[
        "Lam"
    ],
    "name:fra_x_preferred":[
        "Lam"
    ],
    "name:guj_x_preferred":[
        "\u0ab2\u0abe\u0aae"
    ],
    "name:hin_x_preferred":[
        "\u0932\u093e\u092e"
    ],
    "name:kan_x_preferred":[
        "\u0cb2\u0ccd\u0caf\u0cbe\u0cae\u0ccd"
    ],
    "name:mal_x_preferred":[
        "\u0d32\u0d3e\u0d02"
    ],
    "name:mar_x_preferred":[
        "\u0932\u0945\u092e"
    ],
    "name:nld_x_preferred":[
        "Lam"
    ],
    "name:nor_x_preferred":[
        "Lam"
    ],
    "name:pan_x_preferred":[
        "\u0a32\u0a48\u0a2e"
    ],
    "name:pol_x_preferred":[
        "Lam"
    ],
    "name:por_x_preferred":[
        "Lam"
    ],
    "name:swe_x_preferred":[
        "Lam"
    ],
    "name:tam_x_preferred":[
        "\u0bb2\u0bbe\u0bae\u0bcd"
    ],
    "name:tel_x_preferred":[
        "\u0c32\u0c3e\u0c2e\u0c4d"
    ],
    "name:und_x_variant":[
        "L\u0101m"
    ],
    "name:urd_x_preferred":[
        "\u0644\u0627\u0645"
    ],
    "name:vie_x_preferred":[
        "Lam"
    ],
    "wof:name":"Lam",
    "wof:placetype":"locality"
},
  "geometry": {"coordinates":[74.48223,32.83483],"type":"Point"}
}