{
  "type": "Feature",
  "properties": {
    "gn:admin1_code":"12.0",
    "gn:asciiname":"Lam",
    "gn:country_code":"IN",
    "gn:dem":276,
    "gn:feature_class":"P",
    "gn:feature_code":"PPL",
    "gn:name":"L\u0101m",
    "gn:population":0,
    "gn:timezone":"Asia/Kolkata",
    "iso:country":"IN",
    "name:ceb_x_preferred":[
        "Lam"
    ],
    "name:dan_x_preferred":[
        "Lam"
    ],
    "name:fra_x_preferred":[
        "Lam"
    ],
    "name:nld_x_preferred":[
        "Lam"
    ],
    "name:nor_x_preferred":[
        "Lam"
    ],
    "name:pol_x_preferred":[
        "Lam"
    ],
    "name:por_x_preferred":[
        "Lam"
    ],
    "name:swe_x_preferred":[
        "Lam"
    ],
    "name:und_x_variant":[
        "L\u0101m"
    ],
    "name:vie_x_preferred":[
        "Lam"
    ],
    "wof:name":"Lam",
    "wof:placetype":"locality"
},
  "geometry": {"coordinates":[74.48223,32.83483],"type":"Point"}
}