{
  "type": "Feature",
  "properties": {
    "iso:country":"IN",
    "ks:ks_name":"Ravuthampatti",
    "ks:ks_pop":374,
    "ks:ks_type":"HABITATION",
    "name:eng_x_preferred":[
        "Ravuthampatti"
    ],
    "wof:name":"Ravuthampatti",
    "wof:placetype":"locality",
    "wof:population":374
},
  "geometry": {"coordinates":[78.785663,10.24023],"type":"Point"}
}