{
  "type": "Feature",
  "properties": {
    "iso:country":"IN",
    "ks:ks_name":"Chainpur",
    "ks:ks_pop":1574,
    "ks:ks_type":"VILLAGE",
    "ks:ks_uagg_main":0,
    "name:eng_x_preferred":[
        "Chainpur"
    ],
    "wof:name":"Chainpur",
    "wof:placetype":"neighbourhood",
    "wof:population":1574
},
  "geometry": {"coordinates":[85.604609,23.727068],"type":"Point"}
}