{
  "type": "Feature",
  "properties": {
    "gn:admin1_code":"2.0",
    "gn:admin2_code":"554",
    "gn:asciiname":"Karvetnagar",
    "gn:country_code":"IN",
    "gn:dem":236,
    "gn:feature_class":"P",
    "gn:feature_code":"PPL",
    "gn:name":"K\u0101rvetnagar",
    "gn:population":0,
    "gn:timezone":"Asia/Kolkata",
    "iso:country":"IN",
    "wof:name":"Karvetnagar",
    "wof:placetype":"locality"
},
  "geometry": {"coordinates":[79.44838,13.42136],"type":"Point"}
}