{
  "type": "Feature",
  "properties": {
    "gn:admin1_code":"23.0",
    "gn:admin2_code":"35.0",
    "gn:asciiname":"Naushehra",
    "gn:country_code":"IN",
    "gn:dem":270,
    "gn:feature_class":"P",
    "gn:feature_code":"PPL",
    "gn:name":"Naushehra",
    "gn:population":0,
    "gn:timezone":"Asia/Kolkata",
    "iso:country":"IN",
    "ks:ks_name":"Naushehra",
    "ks:ks_pop":2513,
    "ks:ks_type":"VILLAGE",
    "ks:ks_uagg_main":0,
    "name:eng_x_preferred":[
        "Naushehra"
    ],
    "wof:name":"Naushehra",
    "wof:placetype":"neighbourhood",
    "wof:population":2513
},
  "geometry": {"coordinates":[75.464944,32.006684],"type":"Point"}
}