{
  "type": "Feature",
  "properties": {
    "iso:country":"IN",
    "ks:ks_name":"Baman Kheri",
    "ks:ks_pop":251,
    "ks:ks_type":"VILLAGE",
    "name:eng_x_preferred":[
        "Baman Kheri"
    ],
    "wof:name":"Baman Kheri",
    "wof:placetype":"locality",
    "wof:population":251
},
  "geometry": {"coordinates":[74.773584,23.673592],"type":"Point"}
}