{
  "type": "Feature",
  "properties": {
    "iso:country":"IN",
    "ks:ks_name":"Makhadum Pura",
    "ks:ks_pop":806,
    "ks:ks_type":"VILLAGE",
    "ks:ks_uagg_main":0,
    "name:eng_x_preferred":[
        "Makhadum Pura"
    ],
    "wof:name":"Makhadum Pura",
    "wof:placetype":"locality",
    "wof:population":806
},
  "geometry": {"coordinates":[80.50076,27.053886],"type":"Point"}
}