{
  "type": "Feature",
  "properties": {
    "iso:country":"IN",
    "ks:ks_name":"Kukurmara",
    "ks:ks_pop":1700,
    "ks:ks_type":"VILLAGE",
    "ks:ks_uagg_main":0,
    "name:eng_x_preferred":[
        "Kukurmara"
    ],
    "wof:name":"Kukurmara",
    "wof:placetype":"neighbourhood",
    "wof:population":1700
},
  "geometry": {"coordinates":[91.42885,26.072235],"type":"Point"}
}