{
  "type": "Feature",
  "properties": {
    "iso:country":"IN",
    "ks:ks_name":"Kali Makvana",
    "ks:ks_pop":1074,
    "ks:ks_type":"VILLAGE",
    "name:eng_x_preferred":[
        "Kali Makvana"
    ],
    "wof:name":"Kali Makvana",
    "wof:placetype":"locality",
    "wof:population":1074
},
  "geometry": {"coordinates":[73.58118899999999,21.878944],"type":"Point"}
}