{
  "type": "Feature",
  "properties": {
    "iso:country":"IN",
    "ks:ks_name":"Chupi",
    "ks:ks_pop":5856,
    "ks:ks_type":"VILLAGE",
    "ks:ks_uagg_main":0,
    "name:eng_x_preferred":[
        "Chupi"
    ],
    "wof:name":"Chupi",
    "wof:placetype":"locality",
    "wof:population":5856
},
  "geometry": {"coordinates":[88.34527300000001,23.465209],"type":"Point"}
}