{
  "type": "Feature",
  "properties": {
    "gn:admin1_code":"35.0",
    "gn:admin2_code":"447",
    "gn:asciiname":"Bhaunra",
    "gn:country_code":"IN",
    "gn:dem":379,
    "gn:feature_class":"P",
    "gn:feature_code":"PPL",
    "gn:name":"Bhaunra",
    "gn:population":0,
    "gn:timezone":"Asia/Kolkata",
    "iso:country":"IN",
    "name:und_x_variant":[
        "Bh\u0101wra"
    ],
    "wof:name":"Bhaunra",
    "wof:placetype":"neighbourhood"
},
  "geometry": {"coordinates":[77.86944,22.27997],"type":"Point"}
}