{
  "type": "Feature",
  "properties": {
    "gn:admin1_code":"39.0",
    "gn:admin2_code":"66.0",
    "gn:asciiname":"Chorpani",
    "gn:country_code":"IN",
    "gn:dem":339,
    "gn:feature_class":"P",
    "gn:feature_code":"PPL",
    "gn:name":"Chorp\u0101ni",
    "gn:population":0,
    "gn:timezone":"Asia/Kolkata",
    "iso:country":"IN",
    "ks:ks_name":"Chorpani",
    "ks:ks_pop":2251,
    "ks:ks_type":"VILLAGE",
    "ks:ks_uagg_main":0,
    "name:eng_x_preferred":[
        "Chorpani"
    ],
    "wof:name":"Chorpani",
    "wof:placetype":"locality",
    "wof:population":2251
},
  "geometry": {"coordinates":[79.10783499999999,29.39358],"type":"Point"}
}