{
  "type": "Feature",
  "properties": {
    "gn:admin1_code":"39.0",
    "gn:admin2_code":"64.0",
    "gn:asciiname":"Khunt",
    "gn:country_code":"IN",
    "gn:dem":1401,
    "gn:feature_class":"P",
    "gn:feature_code":"PPL",
    "gn:name":"Khunt",
    "gn:population":0,
    "gn:timezone":"Asia/Kolkata",
    "iso:country":"IN",
    "ks:ks_name":"Khunt",
    "ks:ks_pop":467,
    "ks:ks_type":"VILLAGE",
    "name:eng_x_preferred":[
        "Khunt"
    ],
    "wof:name":"Khunt",
    "wof:placetype":"locality",
    "wof:population":467
},
  "geometry": {"coordinates":[79.597245,29.606534],"type":"Point"}
}