{
  "type": "Feature",
  "properties": {
    "iso:country":"IN",
    "ks:ks_name":"Bhagdewa",
    "ks:ks_type":"VILLAGE",
    "name:eng_x_preferred":[
        "Bhagdewa"
    ],
    "wof:name":"Bhagdewa",
    "wof:placetype":"locality"
},
  "geometry": {"coordinates":[81.962509,25.143105],"type":"Point"}
}