{
  "type": "Feature",
  "properties": {
    "iso:country":"IN",
    "ks:ks_alt_nam":"Ashokpawar wasti",
    "ks:ks_name":"Ashokpawar Wasti",
    "ks:ks_pop":99,
    "ks:ks_type":"HABITATION",
    "name:eng_x_preferred":[
        "Ashokpawar Wasti"
    ],
    "wof:name":"Ashokpawar Wasti",
    "wof:placetype":"locality",
    "wof:population":99
},
  "geometry": {"coordinates":[74.39393,17.11432],"type":"Point"}
}