{
  "type": "Feature",
  "properties": {
    "gn:admin1_code":"11.0",
    "gn:admin2_code":"29.0",
    "gn:asciiname":"Pango Rajput",
    "gn:country_code":"IN",
    "gn:dem":596,
    "gn:feature_class":"P",
    "gn:feature_code":"PPL",
    "gn:name":"Pango Rajput",
    "gn:population":0,
    "gn:timezone":"Asia/Kolkata",
    "iso:country":"IN",
    "wof:name":"Pango Rajput",
    "wof:placetype":"locality"
},
  "geometry": {"coordinates":[75.99112,31.72237],"type":"Point"}
}