{
  "type": "Feature",
  "properties": {
    "iso:country":"IN",
    "ks:ks_name":"Dhaukla Purwa",
    "ks:ks_pop":138,
    "ks:ks_type":"HABITATION",
    "name:eng_x_preferred":[
        "Dhaukla Purwa"
    ],
    "wof:name":"Dhaukla Purwa",
    "wof:placetype":"locality",
    "wof:population":138
},
  "geometry": {"coordinates":[81.829345,27.212553],"type":"Point"}
}