{
  "type": "Feature",
  "properties": {
    "gn:admin1_code":"36.0",
    "gn:admin2_code":"137.0",
    "gn:asciiname":"Baldana Hirasingh",
    "gn:country_code":"IN",
    "gn:dem":215,
    "gn:feature_class":"P",
    "gn:feature_code":"PPL",
    "gn:name":"Bald\u0101na H\u012br\u0101singh",
    "gn:population":0,
    "gn:timezone":"Asia/Kolkata",
    "iso:country":"IN",
    "wof:name":"Baldana Hirasingh",
    "wof:placetype":"locality"
},
  "geometry": {"coordinates":[78.32995,28.87296],"type":"Point"}
}