{
  "type": "Feature",
  "properties": {
    "iso:country":"IN",
    "ks:ks_name":"Kunduchi",
    "ks:ks_pop":1253,
    "ks:ks_type":"HABITATION",
    "name:eng_x_preferred":[
        "Kunduchi"
    ],
    "wof:name":"Kunduchi",
    "wof:placetype":"locality",
    "wof:population":1253
},
  "geometry": {"coordinates":[75.171712,12.485659],"type":"Point"}
}