{
  "type": "Feature",
  "properties": {
    "iso:country":"IN",
    "ks:ks_name":"Chitbisw Khurd",
    "ks:ks_pop":860,
    "ks:ks_type":"HABITATION",
    "name:eng_x_preferred":[
        "Chitbisw Khurd"
    ],
    "wof:name":"Chitbisw Khurd",
    "wof:placetype":"locality",
    "wof:population":860
},
  "geometry": {"coordinates":[84.313757,25.892133],"type":"Point"}
}