{
  "type": "Feature",
  "properties": {
    "iso:country":"IN",
    "ks:ks_alt_nam":"SANENAHALLI KOPPALU",
    "ks:ks_name":"Sanenahalli Koppalu",
    "ks:ks_pop":112,
    "ks:ks_type":"HABITATION",
    "name:eng_x_preferred":[
        "Sanenahalli Koppalu"
    ],
    "wof:name":"Sanenahalli Koppalu",
    "wof:placetype":"locality",
    "wof:population":112
},
  "geometry": {"coordinates":[76.520556,12.877222],"type":"Point"}
}