{
  "type": "Feature",
  "properties": {
    "gn:admin1_code":"11",
    "gn:admin2_code":"24.0",
    "gn:asciiname":"Dol",
    "gn:country_code":"IN",
    "gn:dem":901,
    "gn:feature_class":"P",
    "gn:feature_code":"PPL",
    "gn:name":"Dol",
    "gn:population":0,
    "gn:timezone":"Asia/Kolkata",
    "iso:country":"IN",
    "name:aze_x_preferred":[
        "Dol"
    ],
    "name:bos_x_preferred":[
        "Dol"
    ],
    "name:ceb_x_preferred":[
        "Dol"
    ],
    "name:ces_x_preferred":[
        "Dol"
    ],
    "name:deu_x_preferred":[
        "Dol"
    ],
    "name:fra_x_preferred":[
        "Dol"
    ],
    "name:hrv_x_preferred":[
        "Dol"
    ],
    "name:hun_x_preferred":[
        "Dol"
    ],
    "name:nld_x_preferred":[
        "Dol"
    ],
    "name:pol_x_preferred":[
        "Dol"
    ],
    "name:rus_x_preferred":[
        "\u0414\u043e\u043b"
    ],
    "name:slk_x_preferred":[
        "Dol"
    ],
    "name:slv_x_preferred":[
        "Dol"
    ],
    "name:srp_x_preferred":[
        "\u0414\u043e\u043b"
    ],
    "name:swe_x_preferred":[
        "Dol"
    ],
    "name:ukr_x_preferred":[
        "\u0414\u043e\u043b"
    ],
    "wof:name":"Dol",
    "wof:placetype":"locality"
},
  "geometry": {"coordinates":[76.38661,32.05511],"type":"Point"}
}