{
  "type": "Feature",
  "properties": {
    "gn:admin1_code":"36.0",
    "gn:admin2_code":"175.0",
    "gn:asciiname":"Lohra",
    "gn:country_code":"IN",
    "gn:dem":107,
    "gn:feature_class":"P",
    "gn:feature_code":"PPL",
    "gn:name":"Lohra",
    "gn:population":0,
    "gn:timezone":"Asia/Kolkata",
    "iso:country":"IN",
    "name:deu_x_preferred":[
        "Lohra"
    ],
    "name:epo_x_preferred":[
        "Lohra"
    ],
    "name:eus_x_preferred":[
        "Lohra"
    ],
    "name:fas_x_preferred":[
        "\u0644\u0648\u0647\u0631\u0627"
    ],
    "name:fra_x_preferred":[
        "Lohra"
    ],
    "name:hun_x_preferred":[
        "Lohra"
    ],
    "name:ita_x_preferred":[
        "Lohra"
    ],
    "name:jpn_x_preferred":[
        "\u30ed\u30fc\u30e9"
    ],
    "name:kaz_x_preferred":[
        "\u041b\u043e\u0440\u0430"
    ],
    "name:kir_x_preferred":[
        "\u041b\u043e\u0440\u0430"
    ],
    "name:msa_x_preferred":[
        "Lohra"
    ],
    "name:nld_x_preferred":[
        "Lohra"
    ],
    "name:pol_x_preferred":[
        "Lohra"
    ],
    "name:por_x_preferred":[
        "Lohra"
    ],
    "name:ron_x_preferred":[
        "Lohra"
    ],
    "name:rus_x_preferred":[
        "\u041b\u043e\u0440\u0430"
    ],
    "name:spa_x_preferred":[
        "Lohra"
    ],
    "name:srp_x_preferred":[
        "\u041b\u043e\u0440\u0430"
    ],
    "name:ukr_x_preferred":[
        "\u041b\u043e\u0440\u0430"
    ],
    "name:uzb_x_preferred":[
        "Lohra"
    ],
    "name:vol_x_preferred":[
        "Lohra"
    ],
    "name:war_x_preferred":[
        "Lohra"
    ],
    "name:zho_x_preferred":[
        "\u6d1b\u62c9"
    ],
    "wof:name":"Lohra",
    "wof:placetype":"locality"
},
  "geometry": {"coordinates":[81.73801999999998,25.05358],"type":"Point"}
}