{
  "type": "Feature",
  "properties": {
    "iso:country":"IN",
    "ks:ks_name":"Dhanagarwada Bormala",
    "ks:ks_pop":133,
    "ks:ks_type":"HABITATION",
    "name:eng_x_preferred":[
        "Dhanagarwada Bormala"
    ],
    "wof:name":"Dhanagarwada Bormala",
    "wof:placetype":"locality",
    "wof:population":133
},
  "geometry": {"coordinates":[73.868272,16.819192],"type":"Point"}
}