{
  "type": "Feature",
  "properties": {
    "iso:country":"IN",
    "ks:ks_alt_nam":"MPV 67",
    "ks:ks_name":"Mpv 67",
    "ks:ks_pop":546,
    "ks:ks_type":"HABITATION",
    "name:eng_x_preferred":[
        "Mpv 67"
    ],
    "wof:name":"Mpv 67",
    "wof:placetype":"locality",
    "wof:population":546
},
  "geometry": {"coordinates":[81.582244,18.155059],"type":"Point"}
}