{
  "type": "Feature",
  "properties": {
    "iso:country":"IN",
    "ks:ks_name":"Loharn Dih",
    "ks:ks_pop":450,
    "ks:ks_type":"HABITATION",
    "name:eng_x_preferred":[
        "Loharn Dih"
    ],
    "wof:name":"Loharn Dih",
    "wof:placetype":"locality",
    "wof:population":450
},
  "geometry": {"coordinates":[82.33689200000001,27.322685],"type":"Point"}
}