{
  "type": "Feature",
  "properties": {
    "iso:country":"IN",
    "ks:ks_name":"Mungulvalsa",
    "ks:ks_pop":22,
    "ks:ks_type":"HABITATION",
    "name:eng_x_preferred":[
        "Mungulvalsa"
    ],
    "wof:name":"Mungulvalsa",
    "wof:placetype":"locality",
    "wof:population":22
},
  "geometry": {"coordinates":[82.944862,18.391583],"type":"Point"}
}