{
  "type": "Feature",
  "properties": {
    "iso:country":"IN",
    "ks:ks_name":"Kondwadi",
    "ks:ks_pop":137,
    "ks:ks_type":"HABITATION",
    "name:eng_x_preferred":[
        "Kondwadi"
    ],
    "wof:name":"Kondwadi",
    "wof:placetype":"locality",
    "wof:population":137
},
  "geometry": {"coordinates":[73.48540300000001,16.240695],"type":"Point"}
}