{
  "type": "Feature",
  "properties": {
    "iso:country":"IN",
    "ks:ks_name":"Nerolpalke S C Colony",
    "ks:ks_pop":300,
    "ks:ks_type":"HABITATION",
    "name:eng_x_preferred":[
        "Nerolpalke S C Colony"
    ],
    "wof:name":"Nerolpalke S C Colony",
    "wof:placetype":"locality",
    "wof:population":300
},
  "geometry": {"coordinates":[75.330186,12.880638],"type":"Point"}
}