{
  "type": "Feature",
  "properties": {
    "gn:admin1_code":"28.0",
    "gn:admin2_code":"343",
    "gn:asciiname":"Ghazipur",
    "gn:country_code":"IN",
    "gn:dem":7,
    "gn:feature_class":"P",
    "gn:feature_code":"PPL",
    "gn:name":"Ghazipur",
    "gn:population":0,
    "gn:timezone":"Asia/Kolkata",
    "iso:country":"IN",
    "wof:name":"Ghazipur",
    "wof:placetype":"locality"
},
  "geometry": {"coordinates":[88.56416999999998,22.59722],"type":"Point"}
}