{
  "type": "Feature",
  "properties": {
    "gn:admin1_code":"35",
    "gn:admin2_code":"466.0",
    "gn:asciiname":"Bhilkheri",
    "gn:country_code":"IN",
    "gn:dem":371,
    "gn:feature_class":"P",
    "gn:feature_code":"PPL",
    "gn:name":"Bh\u012blkheri",
    "gn:population":0,
    "gn:timezone":"Asia/Kolkata",
    "iso:country":"IN",
    "name:und_x_variant":[
        "Bh\u012blkheri",
        "Tubai"
    ],
    "wof:name":"Bhilkheri",
    "wof:placetype":"neighbourhood"
},
  "geometry": {"coordinates":[76.16152,21.78263],"type":"Point"}
}