{
  "type": "Feature",
  "properties": {
    "gn:admin1_code":"16",
    "gn:admin2_code":"498.0",
    "gn:asciiname":"Aklad",
    "gn:country_code":"IN",
    "gn:dem":328,
    "gn:feature_class":"P",
    "gn:feature_code":"PPL",
    "gn:name":"Aklad",
    "gn:population":0,
    "gn:timezone":"Asia/Kolkata",
    "iso:country":"IN",
    "wof:name":"Aklad",
    "wof:placetype":"locality"
},
  "geometry": {"coordinates":[74.56013,20.93037],"type":"Point"}
}