{
  "type": "Feature",
  "properties": {
    "gn:admin1_code":"25.0",
    "gn:admin2_code":"632.0",
    "gn:asciiname":"Attikatti",
    "gn:country_code":"IN",
    "gn:dem":935,
    "gn:feature_class":"P",
    "gn:feature_code":"PPL",
    "gn:name":"Attikatti",
    "gn:population":0,
    "gn:timezone":"Asia/Kolkata",
    "iso:country":"IN",
    "wof:name":"Attikatti",
    "wof:placetype":"locality"
},
  "geometry": {"coordinates":[76.98541,10.44403],"type":"Point"}
}