{
  "type": "Feature",
  "properties": {
    "iso:country":"IN",
    "ks:ks_name":"China Anjada",
    "ks:ks_pop":163,
    "ks:ks_type":"HABITATION",
    "name:eng_x_preferred":[
        "China Anjada"
    ],
    "wof:name":"China Anjada",
    "wof:placetype":"locality",
    "wof:population":163
},
  "geometry": {"coordinates":[82.824557,18.347699],"type":"Point"}
}