{
  "type": "Feature",
  "properties": {
    "iso:country":"IN",
    "ks:ks_name":"Annanagar",
    "ks:ks_pop":105,
    "ks:ks_type":"HABITATION",
    "name:eng_x_preferred":[
        "Annanagar"
    ],
    "wof:name":"Annanagar",
    "wof:placetype":"locality",
    "wof:population":105
},
  "geometry": {"coordinates":[78.043673,11.425002],"type":"Point"}
}