{
  "type": "Feature",
  "properties": {
    "iso:country":"IN",
    "ks:ks_name":"Murdhuva",
    "ks:ks_pop":282,
    "ks:ks_type":"HABITATION",
    "name:eng_x_preferred":[
        "Murdhuva"
    ],
    "wof:name":"Murdhuva",
    "wof:placetype":"locality",
    "wof:population":282
},
  "geometry": {"coordinates":[82.50525,22.497332],"type":"Point"}
}