{
  "type": "Feature",
  "properties": {
    "iso:country":"IN",
    "ks:ks_name":"Alasuli",
    "ks:ks_pop":1251,
    "ks:ks_type":"VILLAGE",
    "name:eng_x_preferred":[
        "Alasuli"
    ],
    "wof:name":"Alasuli",
    "wof:placetype":"locality",
    "wof:population":1251
},
  "geometry": {"coordinates":[87.91466800000001,22.24775],"type":"Point"}
}