{
  "type": "Feature",
  "properties": {
    "iso:country":"IN",
    "ks:ks_name":"Thakur Bari",
    "ks:ks_pop":200,
    "ks:ks_type":"HABITATION",
    "name:eng_x_preferred":[
        "Thakur Bari"
    ],
    "wof:name":"Thakur Bari",
    "wof:placetype":"locality",
    "wof:population":200
},
  "geometry": {"coordinates":[92.95687599999999,25.85176],"type":"Point"}
}