{
  "type": "Feature",
  "properties": {
    "iso:country":"IN",
    "ks:ks_name":"Nelligudde",
    "ks:ks_pop":260,
    "ks:ks_type":"HABITATION",
    "name:eng_x_preferred":[
        "Nelligudde"
    ],
    "wof:name":"Nelligudde",
    "wof:placetype":"locality",
    "wof:population":260
},
  "geometry": {"coordinates":[75.139312,13.044577],"type":"Point"}
}