{
  "type": "Feature",
  "properties": {
    "iso:country":"IN",
    "ks:ks_name":"Jafarpur",
    "ks:ks_pop":1399,
    "ks:ks_type":"VILLAGE",
    "ks:ks_uagg_main":0,
    "name:eng_x_preferred":[
        "Jafarpur"
    ],
    "wof:name":"Jafarpur",
    "wof:placetype":"neighbourhood",
    "wof:population":1399
},
  "geometry": {"coordinates":[85.32920300000001,26.342975],"type":"Point"}
}