{
  "type": "Feature",
  "properties": {
    "gn:admin1_code":"35.0",
    "gn:admin2_code":"450.0",
    "gn:asciiname":"Gadonha",
    "gn:country_code":"IN",
    "gn:dem":379,
    "gn:feature_class":"P",
    "gn:feature_code":"PPL",
    "gn:name":"Gadonha",
    "gn:population":0,
    "gn:timezone":"Asia/Kolkata",
    "iso:country":"IN",
    "wof:name":"Gadonha",
    "wof:placetype":"neighbourhood"
},
  "geometry": {"coordinates":[80.75913,23.87398],"type":"Point"}
}