{
  "type": "Feature",
  "properties": {
    "gn:admin1_code":"36.0",
    "gn:admin2_code":"149",
    "gn:asciiname":"Phulecha",
    "gn:country_code":"IN",
    "gn:dem":163,
    "gn:feature_class":"P",
    "gn:feature_code":"PPL",
    "gn:name":"Phulecha",
    "gn:population":0,
    "gn:timezone":"Asia/Kolkata",
    "iso:country":"IN",
    "name:und_x_variant":[
        "\u012as\u0101pur",
        "Phulecha"
    ],
    "wof:name":"Phulecha",
    "wof:placetype":"neighbourhood"
},
  "geometry": {"coordinates":[79.28422999999999,27.95697],"type":"Point"}
}