{
  "type": "Feature",
  "properties": {
    "iso:country":"IN",
    "ks:ks_name":"Pathaguda",
    "ks:ks_pop":112,
    "ks:ks_type":"HABITATION",
    "name:eng_x_preferred":[
        "Pathaguda"
    ],
    "wof:name":"Pathaguda",
    "wof:placetype":"locality",
    "wof:population":112
},
  "geometry": {"coordinates":[78.67486700000001,19.412334],"type":"Point"}
}