{
  "type": "Feature",
  "properties": {
    "gn:admin1_code":"36",
    "gn:admin2_code":"176.0",
    "gn:asciiname":"Shahpur Patti",
    "gn:country_code":"IN",
    "gn:dem":116,
    "gn:feature_class":"P",
    "gn:feature_code":"PPL",
    "gn:name":"Sh\u0101hpur Patti",
    "gn:population":0,
    "gn:timezone":"Asia/Kolkata",
    "iso:country":"IN",
    "ks:ks_alt_nam":"Sh\u0101hpur Patti",
    "ks:ks_name":"Shahpur Patti",
    "ks:ks_pop":148,
    "ks:ks_type":"VILLAGE",
    "ks:ks_uagg_main":0,
    "name:eng_x_preferred":[
        "Shahpur Patti"
    ],
    "name:eng_x_variant":[
        "Sh\u0101hpur Patti"
    ],
    "wof:name":"Shahpur Patti",
    "wof:placetype":"neighbourhood",
    "wof:population":148
},
  "geometry": {"coordinates":[81.505802,26.916977],"type":"Point"}
}