{
  "type": "Feature",
  "properties": {
    "iso:country":"IN",
    "ks:ks_name":"Jharoda",
    "ks:ks_pop":96,
    "ks:ks_type":"VILLAGE",
    "ks:ks_uagg_main":0,
    "name:eng_x_preferred":[
        "Jharoda"
    ],
    "wof:name":"Jharoda",
    "wof:placetype":"locality",
    "wof:population":96
},
  "geometry": {"coordinates":[76.271548,27.90532],"type":"Point"}
}