{
  "type": "Feature",
  "properties": {
    "iso:country":"IN",
    "ks:ks_name":"Bhattanagadde",
    "ks:ks_pop":13,
    "ks:ks_type":"HABITATION",
    "name:eng_x_preferred":[
        "Bhattanagadde"
    ],
    "wof:name":"Bhattanagadde",
    "wof:placetype":"locality",
    "wof:population":13
},
  "geometry": {"coordinates":[74.786191,14.55398],"type":"Point"}
}