{
  "type": "Feature",
  "properties": {
    "iso:country":"IN",
    "ks:ks_name":"Poochakadu",
    "ks:ks_pop":188,
    "ks:ks_type":"HABITATION",
    "name:eng_x_preferred":[
        "Poochakadu"
    ],
    "wof:name":"Poochakadu",
    "wof:placetype":"locality",
    "wof:population":188
},
  "geometry": {"coordinates":[77.86867599999999,11.435143],"type":"Point"}
}