{
  "type": "Feature",
  "properties": {
    "iso:country":"IN",
    "ks:ks_name":"Khedi Kalyanpura",
    "ks:ks_pop":813,
    "ks:ks_type":"HABITATION",
    "name:eng_x_preferred":[
        "Khedi Kalyanpura"
    ],
    "wof:name":"Khedi Kalyanpura",
    "wof:placetype":"locality",
    "wof:population":813
},
  "geometry": {"coordinates":[74.62060099999999,22.874217],"type":"Point"}
}