{
  "type": "Feature",
  "properties": {
    "gn:admin1_code":"36",
    "gn:admin2_code":"134.0",
    "gn:asciiname":"Simli",
    "gn:country_code":"IN",
    "gn:dem":225,
    "gn:feature_class":"P",
    "gn:feature_code":"PPL",
    "gn:name":"S\u012bmli",
    "gn:population":0,
    "gn:timezone":"Asia/Kolkata",
    "iso:country":"IN",
    "name:ceb_x_preferred":[
        "Simli"
    ],
    "name:fra_x_preferred":[
        "Simli"
    ],
    "name:mai_x_preferred":[
        "\u0938\u093f\u092e\u094d\u0932\u0940"
    ],
    "name:msa_x_preferred":[
        "Simli"
    ],
    "name:nep_x_preferred":[
        "\u0938\u093f\u092e\u094d\u0932\u0940"
    ],
    "name:new_x_preferred":[
        "\u0938\u093f\u092e\u094d\u0932\u0940"
    ],
    "name:pol_x_preferred":[
        "Simli"
    ],
    "wof:name":"Simli",
    "wof:placetype":"locality"
},
  "geometry": {"coordinates":[78.22511999999998,29.14281],"type":"Point"}
}