{
  "type": "Feature",
  "properties": {
    "gn:admin1_code":"36",
    "gn:admin2_code":"134.0",
    "gn:asciiname":"Simli",
    "gn:country_code":"IN",
    "gn:dem":225,
    "gn:feature_class":"P",
    "gn:feature_code":"PPL",
    "gn:name":"S\u012bmli",
    "gn:population":0,
    "gn:timezone":"Asia/Kolkata",
    "iso:country":"IN",
    "name:ara_x_preferred":[
        "\u0633\u064a\u0645\u0644\u064a"
    ],
    "name:ben_bn_x_preferred":[
        "\u09b8\u09bf\u09ae\u09b2\u09bf"
    ],
    "name:ben_in_x_preferred":[
        "\u09b8\u09bf\u09ae\u09b2\u09bf"
    ],
    "name:ceb_x_preferred":[
        "Simli"
    ],
    "name:fra_x_preferred":[
        "Simli"
    ],
    "name:guj_x_preferred":[
        "\u0ab8\u0abf\u0aae\u0ab2\u0ac0"
    ],
    "name:hin_x_preferred":[
        "\u0938\u093f\u092e\u0932\u0940"
    ],
    "name:kan_x_preferred":[
        "\u0cb8\u0cbf\u0cae\u0ccd\u0cb2\u0cbf"
    ],
    "name:mai_x_preferred":[
        "\u0938\u093f\u092e\u094d\u0932\u0940"
    ],
    "name:mal_x_preferred":[
        "\u0d38\u0d3f\u0d02\u0d32\u0d3f"
    ],
    "name:mar_x_preferred":[
        "\u0938\u093f\u092e\u0932\u0940"
    ],
    "name:msa_x_preferred":[
        "Simli"
    ],
    "name:nep_x_preferred":[
        "\u0938\u093f\u092e\u094d\u0932\u0940"
    ],
    "name:new_x_preferred":[
        "\u0938\u093f\u092e\u094d\u0932\u0940"
    ],
    "name:pan_x_preferred":[
        "\u0a38\u0a3f\u0a2e\u0a32\u0a40"
    ],
    "name:pol_x_preferred":[
        "Simli"
    ],
    "name:tam_x_preferred":[
        "\u0b9a\u0bbf\u0bae\u0bcd\u0bb2\u0bbf"
    ],
    "name:tel_x_preferred":[
        "\u0c38\u0c3f\u0c2e\u0c4d\u0c32\u0c3f"
    ],
    "name:urd_x_preferred":[
        "\u0633\u0645\u0644\u06cc"
    ],
    "wof:name":"Simli",
    "wof:placetype":"locality"
},
  "geometry": {"coordinates":[78.22511999999998,29.14281],"type":"Point"}
}