{
  "type": "Feature",
  "properties": {
    "iso:country":"IN",
    "ks:ks_name":"Bhakusa South",
    "ks:ks_pop":703,
    "ks:ks_type":"HABITATION",
    "name:eng_x_preferred":[
        "Bhakusa South"
    ],
    "wof:name":"Bhakusa South",
    "wof:placetype":"locality",
    "wof:population":703
},
  "geometry": {"coordinates":[79.393007,27.587064],"type":"Point"}
}