{
  "type": "Feature",
  "properties": {
    "gn:admin1_code":"16",
    "gn:admin2_code":"506.0",
    "gn:asciiname":"Dawejhari",
    "gn:country_code":"IN",
    "gn:dem":291,
    "gn:feature_class":"P",
    "gn:feature_code":"PPL",
    "gn:name":"D\u0101wejhar\u012b",
    "gn:population":0,
    "gn:timezone":"Asia/Kolkata",
    "iso:country":"IN",
    "ks:ks_alt_nam":"D\u0101wejhar\u012b",
    "ks:ks_name":"Dawejhari",
    "ks:ks_pop":1216,
    "ks:ks_type":"VILLAGE",
    "ks:ks_uagg_main":0,
    "name:eng_x_preferred":[
        "Dawejhari"
    ],
    "name:eng_x_variant":[
        "D\u0101wejhar\u012b"
    ],
    "wof:name":"Dawejhari",
    "wof:placetype":"neighbourhood",
    "wof:population":1216
},
  "geometry": {"coordinates":[79.785944,21.461333],"type":"Point"}
}