{
  "type": "Feature",
  "properties": {
    "gn:admin1_code":"36",
    "gn:admin2_code":"199.0",
    "gn:asciiname":"Madra",
    "gn:country_code":"IN",
    "gn:dem":83,
    "gn:feature_class":"P",
    "gn:feature_code":"PPL",
    "gn:name":"Madra",
    "gn:population":0,
    "gn:timezone":"Asia/Kolkata",
    "iso:country":"IN",
    "name:zho_x_preferred":[
        "\u6469\u5fb7\u7f85"
    ],
    "wof:name":"Madra",
    "wof:placetype":"locality"
},
  "geometry": {"coordinates":[83.08203,25.17375],"type":"Point"}
}