{
  "type": "Feature",
  "properties": {
    "gn:admin1_code":"34.0",
    "gn:admin2_code":"214.0",
    "gn:asciiname":"Mahishi",
    "gn:country_code":"IN",
    "gn:dem":47,
    "gn:feature_class":"P",
    "gn:feature_code":"PPL",
    "gn:name":"Mahishi",
    "gn:population":0,
    "gn:timezone":"Asia/Kolkata",
    "iso:country":"IN",
    "name:hin_x_preferred":[
        "\u092e\u0939\u093f\u0937\u0940"
    ],
    "name:tam_x_preferred":[
        "\u0bae\u0b95\u0bbf\u0bb7\u0bbf"
    ],
    "name:und_x_variant":[
        "Mahisi"
    ],
    "wof:name":"Mahishi",
    "wof:placetype":"locality"
},
  "geometry": {"coordinates":[86.46998000000001,25.85403],"type":"Point"}
}