{
  "type": "Feature",
  "properties": {
    "iso:country":"IN",
    "ks:ks_name":"Tantiamara",
    "ks:ks_pop":252,
    "ks:ks_type":"HABITATION",
    "name:eng_x_preferred":[
        "Tantiamara"
    ],
    "wof:name":"Tantiamara",
    "wof:placetype":"locality",
    "wof:population":252
},
  "geometry": {"coordinates":[86.00756199999999,21.242961],"type":"Point"}
}