{
  "type": "Feature",
  "properties": {
    "iso:country":"IN",
    "ks:ks_name":"Kodegaon Reserved Forest",
    "ks:ks_pop":341,
    "ks:ks_type":"VILLAGE",
    "name:eng_x_preferred":[
        "Kodegaon Reserved Forest"
    ],
    "wof:name":"Kodegaon Reserved Forest",
    "wof:placetype":"locality",
    "wof:population":341
},
  "geometry": {"coordinates":[81.487483,20.545402],"type":"Point"}
}