{
  "type": "Feature",
  "properties": {
    "iso:country":"IN",
    "ks:ks_name":"Tentul Berya",
    "ks:ks_pop":1321,
    "ks:ks_type":"VILLAGE",
    "name:eng_x_preferred":[
        "Tentul Berya"
    ],
    "wof:name":"Tentul Berya",
    "wof:placetype":"locality",
    "wof:population":1321
},
  "geometry": {"coordinates":[88.06188400000001,22.186264],"type":"Point"}
}