{
  "type": "Feature",
  "properties": {
    "gn:admin1_code":"34.0",
    "gn:admin2_code":"225.0",
    "gn:asciiname":"Loharia",
    "gn:country_code":"IN",
    "gn:dem":73,
    "gn:feature_class":"P",
    "gn:feature_code":"PPL",
    "gn:name":"Loharia",
    "gn:population":0,
    "gn:timezone":"Asia/Kolkata",
    "iso:country":"IN",
    "ks:ks_name":"Loharia",
    "ks:ks_type":"VILLAGE",
    "name:eng_x_preferred":[
        "Loharia"
    ],
    "wof:name":"Loharia",
    "wof:placetype":"locality"
},
  "geometry": {"coordinates":[87.00542,24.925776],"type":"Point"}
}