{
  "type": "Feature",
  "properties": {
    "gn:admin1_code":"39",
    "gn:admin2_code":"61.0",
    "gn:asciiname":"Margaon",
    "gn:country_code":"IN",
    "gn:dem":659,
    "gn:feature_class":"P",
    "gn:feature_code":"PPL",
    "gn:name":"Margaon",
    "gn:population":0,
    "gn:timezone":"Asia/Kolkata",
    "iso:country":"IN",
    "wof:name":"Margaon",
    "wof:placetype":"locality"
},
  "geometry": {"coordinates":[78.85531999999998,30.24922],"type":"Point"}
}