{
  "type": "Feature",
  "properties": {
    "gn:admin1_code":"35.0",
    "gn:admin2_code":"442.0",
    "gn:asciiname":"Abhepur",
    "gn:country_code":"IN",
    "gn:dem":397,
    "gn:feature_class":"P",
    "gn:feature_code":"PPL",
    "gn:name":"Abhepur",
    "gn:population":0,
    "gn:timezone":"Asia/Kolkata",
    "iso:country":"IN",
    "name:ara_x_preferred":[
        "\u0627\u0628\u0647\u064a \u0628\u0648\u0631"
    ],
    "name:ben_bn_x_preferred":[
        "\u0985\u09ad\u09df\u09aa\u09c1\u09b0"
    ],
    "name:ben_in_x_preferred":[
        "\u0985\u09ad\u09c7\u09aa\u09c1\u09b0"
    ],
    "name:guj_x_preferred":[
        "\u0a85\u0aad\u0ac7\u0aaa\u0ac1\u0ab0"
    ],
    "name:hin_x_preferred":[
        "\u0905\u092d\u0947\u092a\u0941\u0930"
    ],
    "name:kan_x_preferred":[
        "\u0c85\u0cad\u0cc7\u0caa\u0cc1\u0cb0\u0ccd"
    ],
    "name:mal_x_preferred":[
        "\u0d05\u0d2d\u0d47\u0d2a\u0d42\u0d7c"
    ],
    "name:mar_x_preferred":[
        "\u0905\u092d\u0947\u092a\u0942\u0930"
    ],
    "name:pan_x_preferred":[
        "\u0a05\u0a2d\u0a48\u0a2a\u0a41\u0a30"
    ],
    "name:tam_x_preferred":[
        "\u0b85\u0baa\u0bc6\u0baa\u0bc2\u0bb0\u0bcd"
    ],
    "name:tel_x_preferred":[
        "\u0c05\u0c2d\u0c46\u0c2a\u0c42\u0c30\u0c4d"
    ],
    "name:urd_x_preferred":[
        "\u0627\u0628\u06be\u06d2 \u067e\u0648\u0631"
    ],
    "wof:name":"Abhepur",
    "wof:placetype":"locality"
},
  "geometry": {"coordinates":[76.80329999999999,23.92766],"type":"Point"}
}