{
  "type": "Feature",
  "properties": {
    "gn:admin1_code":"35",
    "gn:admin2_code":"426.0",
    "gn:asciiname":"Purwa",
    "gn:country_code":"IN",
    "gn:dem":314,
    "gn:feature_class":"P",
    "gn:feature_code":"PPL",
    "gn:name":"Purwa",
    "gn:population":0,
    "gn:timezone":"Asia/Kolkata",
    "iso:country":"IN",
    "name:eng_x_preferred":[
        "Purwa"
    ],
    "wof:name":"Purwa",
    "wof:placetype":"locality"
},
  "geometry": {"coordinates":[79.94803,24.32805],"type":"Point"}
}