{
  "type": "Feature",
  "properties": {
    "gn:admin1_code":"2.0",
    "gn:admin2_code":"550",
    "gn:asciiname":"Kovurupalli",
    "gn:country_code":"IN",
    "gn:dem":10,
    "gn:feature_class":"P",
    "gn:feature_code":"PPL",
    "gn:name":"Kov\u016brupalli",
    "gn:population":0,
    "gn:timezone":"Asia/Kolkata",
    "iso:country":"IN",
    "name:und_x_variant":[
        "Kov\u016brupalli",
        "Kov\u016brupalle"
    ],
    "wof:name":"Kovurupalli",
    "wof:placetype":"locality"
},
  "geometry": {"coordinates":[79.99993000000001,14.7772],"type":"Point"}
}