{
  "type": "Feature",
  "properties": {
    "iso:country":"IN",
    "ks:ks_name":"Gadwalgad",
    "ks:ks_pop":966,
    "ks:ks_type":"VILLAGE",
    "name:eng_x_preferred":[
        "Gadwalgad"
    ],
    "wof:name":"Gadwalgad",
    "wof:placetype":"locality",
    "wof:population":966
},
  "geometry": {"coordinates":[78.41664,30.514375],"type":"Point"}
}