{
  "type": "Feature",
  "properties": {
    "iso:country":"IN",
    "ks:ks_alt_nam":"Malleshwara camp",
    "ks:ks_name":"Malleshwara Camp",
    "ks:ks_pop":671,
    "ks:ks_type":"HABITATION",
    "name:eng_x_preferred":[
        "Malleshwara Camp"
    ],
    "wof:name":"Malleshwara Camp",
    "wof:placetype":"locality",
    "wof:population":671
},
  "geometry": {"coordinates":[76.89926800000001,15.350517],"type":"Point"}
}