{
  "type": "Feature",
  "properties": {
    "gn:admin1_code":"39",
    "gn:admin2_code":"60.0",
    "gn:asciiname":"Daiyan",
    "gn:country_code":"IN",
    "gn:dem":1909,
    "gn:feature_class":"P",
    "gn:feature_code":"PPL",
    "gn:name":"Daiy\u0101n",
    "gn:population":0,
    "gn:timezone":"Asia/Kolkata",
    "iso:country":"IN",
    "wof:name":"Daiyan",
    "wof:placetype":"locality"
},
  "geometry": {"coordinates":[77.85404,30.81875],"type":"Point"}
}