{
  "type": "Feature",
  "properties": {
    "iso:country":"IN",
    "ks:ks_name":"Parasigaria",
    "ks:ks_pop":0,
    "ks:ks_type":"VILLAGE",
    "name:eng_x_preferred":[
        "Parasigaria"
    ],
    "wof:name":"Parasigaria",
    "wof:placetype":"locality",
    "wof:population":0
},
  "geometry": {"coordinates":[86.83659,23.585328],"type":"Point"}
}