{
  "type": "Feature",
  "properties": {
    "gn:admin1_code":"19.0",
    "gn:admin2_code":"574.0",
    "gn:asciiname":"Tippanahalli",
    "gn:country_code":"IN",
    "gn:dem":845,
    "gn:feature_class":"P",
    "gn:feature_code":"PPL",
    "gn:name":"Tippanahalli",
    "gn:population":0,
    "gn:timezone":"Asia/Kolkata",
    "iso:country":"IN",
    "wof:name":"Tippanahalli",
    "wof:placetype":"locality"
},
  "geometry": {"coordinates":[76.31662,13.26107],"type":"Point"}
}