{
  "type": "Feature",
  "properties": {
    "iso:country":"IN",
    "ks:ks_name":"Mundawas",
    "ks:ks_type":"VILLAGE",
    "name:eng_x_preferred":[
        "Mundawas"
    ],
    "wof:name":"Mundawas",
    "wof:placetype":"locality"
},
  "geometry": {"coordinates":[76.573843,28.289944],"type":"Point"}
}