{
  "type": "Feature",
  "properties": {
    "iso:country":"IN",
    "ks:ks_name":"Uraihan Kheda",
    "ks:ks_pop":425,
    "ks:ks_type":"HABITATION",
    "name:eng_x_preferred":[
        "Uraihan Kheda"
    ],
    "wof:name":"Uraihan Kheda",
    "wof:placetype":"locality",
    "wof:population":425
},
  "geometry": {"coordinates":[80.253472,26.772057],"type":"Point"}
}