{
  "type": "Feature",
  "properties": {
    "iso:country":"IN",
    "ks:ks_name":"Berikheda",
    "ks:ks_pop":0,
    "ks:ks_type":"VILLAGE",
    "name:eng_x_preferred":[
        "Berikheda"
    ],
    "wof:name":"Berikheda",
    "wof:placetype":"locality",
    "wof:population":0
},
  "geometry": {"coordinates":[79.756749,25.436419],"type":"Point"}
}