{
  "type": "Feature",
  "properties": {
    "iso:country":"IN",
    "ks:ks_name":"Sanabeda",
    "ks:ks_pop":128,
    "ks:ks_type":"VILLAGE",
    "name:eng_x_preferred":[
        "Sanabeda"
    ],
    "wof:name":"Sanabeda",
    "wof:placetype":"locality",
    "wof:population":128
},
  "geometry": {"coordinates":[84.36304699999999,20.311787],"type":"Point"}
}