{
  "type": "Feature",
  "properties": {
    "iso:country":"IN",
    "ks:ks_name":"Andharjora",
    "ks:ks_pop":204,
    "ks:ks_type":"HABITATION",
    "name:eng_x_preferred":[
        "Andharjora"
    ],
    "wof:name":"Andharjora",
    "wof:placetype":"locality",
    "wof:population":204
},
  "geometry": {"coordinates":[87.077477,22.513515],"type":"Point"}
}