{
  "type": "Feature",
  "properties": {
    "iso:country":"IN",
    "ks:ks_name":"Elamagge",
    "ks:ks_pop":112,
    "ks:ks_type":"HABITATION",
    "ks:ks_uagg_main":0,
    "name:eng_x_preferred":[
        "Elamagge"
    ],
    "wof:name":"Elamagge",
    "wof:placetype":"neighbourhood",
    "wof:population":112
},
  "geometry": {"coordinates":[75.25814800000001,13.416464],"type":"Point"}
}