{
  "type": "Feature",
  "properties": {
    "iso:country":"IN",
    "ks:ks_alt_nam":"Kaln\u0101d Reserved Forest",
    "ks:ks_name":"Kalnad Reserved Forest",
    "ks:ks_type":"VILLAGE",
    "name:eng_x_preferred":[
        "Kalnad Reserved Forest"
    ],
    "name:eng_x_variant":[
        "Kaln\u0101d Reserved Forest"
    ],
    "wof:name":"Kalnad Reserved Forest",
    "wof:placetype":"locality"
},
  "geometry": {"coordinates":[78.530619,11.855769],"type":"Point"}
}