{
  "type": "Feature",
  "properties": {
    "iso:country":"IN",
    "ks:ks_name":"Pura Pokhar",
    "ks:ks_pop":106,
    "ks:ks_type":"HABITATION",
    "name:eng_x_preferred":[
        "Pura Pokhar"
    ],
    "wof:name":"Pura Pokhar",
    "wof:placetype":"locality",
    "wof:population":106
},
  "geometry": {"coordinates":[78.50940799999999,26.889884],"type":"Point"}
}