{
  "type": "Feature",
  "properties": {
    "iso:country":"IN",
    "ks:ks_name":"Ambai",
    "ks:ks_pop":92,
    "ks:ks_type":"VILLAGE",
    "ks:ks_uagg_main":0,
    "name:eng_x_preferred":[
        "Ambai"
    ],
    "wof:name":"Ambai",
    "wof:placetype":"neighbourhood",
    "wof:population":92
},
  "geometry": {"coordinates":[86.975741,25.214906],"type":"Point"}
}