{
  "type": "Feature",
  "properties": {
    "gn:admin1_code":"37",
    "gn:admin2_code":"406.0",
    "gn:asciiname":"Sirgitti",
    "gn:country_code":"IN",
    "gn:dem":272,
    "gn:feature_class":"P",
    "gn:feature_code":"PPL",
    "gn:name":"Sirgitt\u012b",
    "gn:population":0,
    "gn:timezone":"Asia/Kolkata",
    "iso:country":"IN",
    "ks:ks_alt_nam":"Sirgitt\u012b",
    "ks:ks_name":"Sirgitti",
    "ks:ks_type":"VILLAGE",
    "ks:ks_uagg_main":0,
    "name:eng_x_preferred":[
        "Sirgitti"
    ],
    "name:eng_x_variant":[
        "Sirgitt\u012b"
    ],
    "wof:name":"Sirgitti",
    "wof:placetype":"locality"
},
  "geometry": {"coordinates":[82.148715,22.047133],"type":"Point"}
}