{
  "type": "Feature",
  "properties": {
    "gn:admin1_code":"19.0",
    "gn:admin2_code":"576.0",
    "gn:asciiname":"Chikkatolur",
    "gn:country_code":"IN",
    "gn:dem":1067,
    "gn:feature_class":"P",
    "gn:feature_code":"PPL",
    "gn:name":"Chikkatolur",
    "gn:population":0,
    "gn:timezone":"Asia/Kolkata",
    "iso:country":"IN",
    "ks:ks_name":"Chikka Tholur",
    "ks:ks_pop":564,
    "ks:ks_type":"VILLAGE",
    "name:eng_x_preferred":[
        "Chikka Tholur"
    ],
    "name:eng_x_variant":[
        "Chikkatolur"
    ],
    "wof:name":"Chikka Tholur",
    "wof:placetype":"locality",
    "wof:population":564
},
  "geometry": {"coordinates":[75.847452,12.66179],"type":"Point"}
}