{
  "type": "Feature",
  "properties": {
    "iso:country":"IN",
    "ks:ks_name":"Kasitanr",
    "ks:ks_pop":214,
    "ks:ks_type":"VILLAGE",
    "name:eng_x_preferred":[
        "Kasitanr"
    ],
    "wof:name":"Kasitanr",
    "wof:placetype":"locality",
    "wof:population":214
},
  "geometry": {"coordinates":[86.476034,23.841908],"type":"Point"}
}