{
  "type": "Feature",
  "properties": {
    "gn:admin1_code":"36",
    "gn:admin2_code":"187.0",
    "gn:asciiname":"Pokharbhinda",
    "gn:country_code":"IN",
    "gn:dem":91,
    "gn:feature_class":"P",
    "gn:feature_code":"PPL",
    "gn:name":"Pokharbhinda",
    "gn:population":0,
    "gn:timezone":"Asia/Kolkata",
    "iso:country":"IN",
    "name:bih_x_preferred":[
        "\u092a\u094b\u0916\u0930\u092d\u093f\u0928\u094d\u0921\u093e"
    ],
    "name:ceb_x_preferred":[
        "Pokharbhinda"
    ],
    "name:dty_x_preferred":[
        "\u092a\u094b\u0916\u0930\u092d\u093f\u0928\u094d\u0921\u093e"
    ],
    "name:mai_x_preferred":[
        "\u092a\u094b\u0916\u0930\u092d\u093f\u0928\u094d\u0921\u093e"
    ],
    "name:msa_x_preferred":[
        "Pokharbhinda"
    ],
    "name:nep_x_preferred":[
        "\u092a\u094b\u0916\u0930\u092d\u093f\u0928\u094d\u0921\u093e"
    ],
    "name:new_x_preferred":[
        "\u092a\u094b\u0916\u0930\u094d\u092d\u093f\u0928\u094d\u0926\u093e"
    ],
    "name:pol_x_preferred":[
        "Pokharbhinda"
    ],
    "wof:name":"Pokharbhinda",
    "wof:placetype":"locality"
},
  "geometry": {"coordinates":[83.55099,27.06568],"type":"Point"}
}