{
  "type": "Feature",
  "properties": {
    "iso:country":"IN",
    "ks:ks_name":"Chetrori",
    "ks:ks_pop":1542,
    "ks:ks_type":"HABITATION",
    "name:eng_x_preferred":[
        "Chetrori"
    ],
    "wof:name":"Chetrori",
    "wof:placetype":"locality",
    "wof:population":1542
},
  "geometry": {"coordinates":[70.68710799999999,26.001583],"type":"Point"}
}