{
  "type": "Feature",
  "properties": {
    "gn:admin1_code":"35",
    "gn:admin2_code":"456.0",
    "gn:asciiname":"Borgaon",
    "gn:country_code":"IN",
    "gn:dem":411,
    "gn:feature_class":"P",
    "gn:feature_code":"PPL",
    "gn:name":"Borgaon",
    "gn:population":0,
    "gn:timezone":"Asia/Kolkata",
    "iso:country":"IN",
    "ks:ks_name":"Borgaon",
    "ks:ks_type":"VILLAGE",
    "name:eng_x_preferred":[
        "Borgaon"
    ],
    "wof:name":"Borgaon",
    "wof:placetype":"locality"
},
  "geometry": {"coordinates":[79.52051400000001,21.796614],"type":"Point"}
}