{
  "type": "Feature",
  "properties": {
    "iso:country":"IN",
    "ks:ks_name":"Biahigarhha",
    "ks:ks_pop":216,
    "ks:ks_type":"VILLAGE",
    "name:eng_x_preferred":[
        "Biahigarhha"
    ],
    "wof:name":"Biahigarhha",
    "wof:placetype":"locality",
    "wof:population":216
},
  "geometry": {"coordinates":[86.66862500000001,24.322214],"type":"Point"}
}