{
  "type": "Feature",
  "properties": {
    "iso:country":"IN",
    "ks:ks_name":"Bharsing Parbara",
    "ks:ks_pop":60,
    "ks:ks_type":"VILLAGE",
    "ks:ks_uagg_main":0,
    "name:eng_x_preferred":[
        "Bharsing Parbara"
    ],
    "wof:name":"Bharsing Parbara",
    "wof:placetype":"neighbourhood",
    "wof:population":60
},
  "geometry": {"coordinates":[87.45178900000001,25.109106],"type":"Point"}
}