{
  "type": "Feature",
  "properties": {
    "iso:country":"IN",
    "ks:ks_name":"Chamar Toli",
    "ks:ks_pop":190,
    "ks:ks_type":"HABITATION",
    "name:eng_x_preferred":[
        "Chamar Toli"
    ],
    "wof:name":"Chamar Toli",
    "wof:placetype":"locality",
    "wof:population":190
},
  "geometry": {"coordinates":[84.934192,26.519782],"type":"Point"}
}