{
  "type": "Feature",
  "properties": {
    "iso:country":"IN",
    "ks:ks_name":"Samal Falia",
    "ks:ks_pop":850,
    "ks:ks_type":"HABITATION",
    "name:eng_x_preferred":[
        "Samal Falia"
    ],
    "wof:name":"Samal Falia",
    "wof:placetype":"locality",
    "wof:population":850
},
  "geometry": {"coordinates":[73.133194,20.754056],"type":"Point"}
}