{
  "type": "Feature",
  "properties": {
    "iso:country":"IN",
    "ks:ks_name":"Roopla Thanda",
    "ks:ks_pop":69,
    "ks:ks_type":"HABITATION",
    "name:eng_x_preferred":[
        "Roopla Thanda"
    ],
    "wof:name":"Roopla Thanda",
    "wof:placetype":"locality",
    "wof:population":69
},
  "geometry": {"coordinates":[77.588646,18.107723],"type":"Point"}
}