{
  "type": "Feature",
  "properties": {
    "iso:country":"IN",
    "ks:ks_alt_nam":"Hosadu proper",
    "ks:ks_name":"Hosadu Proper",
    "ks:ks_pop":942,
    "ks:ks_type":"HABITATION",
    "name:eng_x_preferred":[
        "Hosadu Proper"
    ],
    "wof:name":"Hosadu Proper",
    "wof:placetype":"locality",
    "wof:population":942
},
  "geometry": {"coordinates":[74.708783,13.784298],"type":"Point"}
}