{
  "type": "Feature",
  "properties": {
    "iso:country":"IN",
    "ks:ks_name":"Kuthampuzha",
    "ks:ks_pop":576,
    "ks:ks_type":"HABITATION",
    "name:eng_x_preferred":[
        "Kuthampuzha"
    ],
    "wof:name":"Kuthampuzha",
    "wof:placetype":"locality",
    "wof:population":576
},
  "geometry": {"coordinates":[76.61784,10.795048],"type":"Point"}
}