{
  "type": "Feature",
  "properties": {
    "gn:admin1_code":"35.0",
    "gn:admin2_code":"453.0",
    "gn:asciiname":"Matka",
    "gn:country_code":"IN",
    "gn:dem":578,
    "gn:feature_class":"P",
    "gn:feature_code":"PPL",
    "gn:name":"Matka",
    "gn:population":0,
    "gn:timezone":"Asia/Kolkata",
    "iso:country":"IN",
    "name:bul_x_preferred":[
        "\u041c\u0430\u0442\u043a\u0430"
    ],
    "name:ceb_x_preferred":[
        "Matka"
    ],
    "name:ces_x_preferred":[
        "Matka"
    ],
    "name:fin_x_preferred":[
        "Matka"
    ],
    "name:heb_x_preferred":[
        "\u05de\u05d8\u05e7\u05d4"
    ],
    "name:mkd_x_preferred":[
        "\u041c\u0430\u0442\u043a\u0430"
    ],
    "name:nld_x_preferred":[
        "Matka"
    ],
    "name:pol_x_preferred":[
        "Matka"
    ],
    "name:rus_x_preferred":[
        "\u041c\u0430\u0442\u043a\u0430"
    ],
    "name:slk_x_preferred":[
        "Matka"
    ],
    "name:srp_x_preferred":[
        "\u041c\u0430\u0442\u043a\u0430"
    ],
    "name:swe_x_preferred":[
        "Matka"
    ],
    "name:ukr_x_preferred":[
        "\u041c\u0430\u0442\u043a\u0430"
    ],
    "wof:name":"Matka",
    "wof:placetype":"locality"
},
  "geometry": {"coordinates":[80.53440999999999,23.18421],"type":"Point"}
}