{
  "type": "Feature",
  "properties": {
    "iso:country":"IN",
    "ks:ks_alt_nam":"Bandariya pur",
    "ks:ks_name":"Bandariya Pur",
    "ks:ks_pop":373,
    "ks:ks_type":"HABITATION",
    "ks:ks_uagg_main":0,
    "name:eng_x_preferred":[
        "Bandariya Pur"
    ],
    "wof:name":"Bandariya Pur",
    "wof:placetype":"neighbourhood",
    "wof:population":373
},
  "geometry": {"coordinates":[79.882749,26.848053],"type":"Point"}
}