{
  "type": "Feature",
  "properties": {
    "gn:admin1_code":"19.0",
    "gn:admin2_code":"567.0",
    "gn:asciiname":"Chikkamallanahole",
    "gn:country_code":"IN",
    "gn:dem":616,
    "gn:feature_class":"P",
    "gn:feature_code":"PPL",
    "gn:name":"Chikkamallanahole",
    "gn:population":0,
    "gn:timezone":"Asia/Kolkata",
    "iso:country":"IN",
    "wof:name":"Chikkamallanahole",
    "wof:placetype":"locality"
},
  "geometry": {"coordinates":[76.50015999999999,14.54696],"type":"Point"}
}