{
  "type": "Feature",
  "properties": {
    "iso:country":"IN",
    "ks:ks_name":"Vadamalaigoundanur",
    "ks:ks_pop":151,
    "ks:ks_type":"HABITATION",
    "ks:ks_uagg_main":0,
    "name:eng_x_preferred":[
        "Vadamalaigoundanur"
    ],
    "wof:name":"Vadamalaigoundanur",
    "wof:placetype":"neighbourhood",
    "wof:population":151
},
  "geometry": {"coordinates":[78.018693,10.994984],"type":"Point"}
}