{
  "type": "Feature",
  "properties": {
    "iso:country":"IN",
    "ks:ks_name":"Kandigai",
    "ks:ks_pop":877,
    "ks:ks_type":"HABITATION",
    "name:eng_x_preferred":[
        "Kandigai"
    ],
    "wof:name":"Kandigai",
    "wof:placetype":"locality",
    "wof:population":877
},
  "geometry": {"coordinates":[80.13561300000001,12.853471],"type":"Point"}
}