{
  "type": "Feature",
  "properties": {
    "iso:country":"IN",
    "ks:ks_name":"Kanhawapur",
    "ks:ks_pop":326,
    "ks:ks_type":"VILLAGE",
    "name:eng_x_preferred":[
        "Kanhawapur"
    ],
    "wof:name":"Kanhawapur",
    "wof:placetype":"locality",
    "wof:population":326
},
  "geometry": {"coordinates":[80.363803,26.519094],"type":"Point"}
}