{
  "type": "Feature",
  "properties": {
    "iso:country":"IN",
    "ks:ks_name":"Kashipukur",
    "ks:ks_pop":125,
    "ks:ks_type":"VILLAGE",
    "name:eng_x_preferred":[
        "Kashipukur"
    ],
    "wof:name":"Kashipukur",
    "wof:placetype":"locality",
    "wof:population":125
},
  "geometry": {"coordinates":[88.73238499999999,25.305127],"type":"Point"}
}