{
  "type": "Feature",
  "properties": {
    "iso:country":"IN",
    "ks:ks_name":"Khadpadi",
    "ks:ks_pop":391,
    "ks:ks_type":"VILLAGE",
    "name:eng_x_preferred":[
        "Khadpadi"
    ],
    "wof:name":"Khadpadi",
    "wof:placetype":"locality",
    "wof:population":391
},
  "geometry": {"coordinates":[81.629959,19.275111],"type":"Point"}
}