{
  "type": "Feature",
  "properties": {
    "gn:admin1_code":"2.0",
    "gn:admin2_code":"551.0",
    "gn:asciiname":"Suddamalla",
    "gn:country_code":"IN",
    "gn:dem":351,
    "gn:feature_class":"P",
    "gn:feature_code":"PPL",
    "gn:name":"Suddamalla",
    "gn:population":0,
    "gn:timezone":"Asia/Kolkata",
    "iso:country":"IN",
    "wof:name":"Suddamalla",
    "wof:placetype":"locality"
},
  "geometry": {"coordinates":[78.72402,14.22753],"type":"Point"}
}