{
  "type": "Feature",
  "properties": {
    "iso:country":"IN",
    "ks:ks_alt_nam":"A ROTTAGUTTA",
    "ks:ks_name":"A Rottagutta",
    "ks:ks_pop":138,
    "ks:ks_type":"HABITATION",
    "name:eng_x_preferred":[
        "A Rottagutta"
    ],
    "wof:name":"A Rottagutta",
    "wof:placetype":"locality",
    "wof:population":138
},
  "geometry": {"coordinates":[81.036721,17.57818],"type":"Point"}
}