{
  "type": "Feature",
  "properties": {
    "iso:country":"IN",
    "ks:ks_name":"Padukudru",
    "ks:ks_pop":382,
    "ks:ks_type":"HABITATION",
    "name:eng_x_preferred":[
        "Padukudru"
    ],
    "wof:name":"Padukudru",
    "wof:placetype":"locality",
    "wof:population":382
},
  "geometry": {"coordinates":[74.713802,13.410373],"type":"Point"}
}