{
  "type": "Feature",
  "properties": {
    "iso:country":"IN",
    "ks:ks_name":"Koritand",
    "ks:ks_pop":573,
    "ks:ks_type":"HABITATION",
    "name:eng_x_preferred":[
        "Koritand"
    ],
    "wof:name":"Koritand",
    "wof:placetype":"locality",
    "wof:population":573
},
  "geometry": {"coordinates":[86.04875800000001,24.113856],"type":"Point"}
}