{
  "type": "Feature",
  "properties": {
    "gn:admin1_code":"03",
    "gn:admin2_code":"311.0",
    "gn:asciiname":"Salaguri",
    "gn:country_code":"IN",
    "gn:dem":100,
    "gn:feature_class":"P",
    "gn:feature_code":"PPL",
    "gn:name":"Salaguri",
    "gn:population":0,
    "gn:timezone":"Asia/Kolkata",
    "iso:country":"IN",
    "wof:name":"Salaguri",
    "wof:placetype":"locality"
},
  "geometry": {"coordinates":[94.82705,27.06463],"type":"Point"}
}