{
  "type": "Feature",
  "properties": {
    "iso:country":"IN",
    "ks:ks_name":"Arjunberia",
    "ks:ks_pop":302,
    "ks:ks_type":"HABITATION",
    "name:eng_x_preferred":[
        "Arjunberia"
    ],
    "wof:name":"Arjunberia",
    "wof:placetype":"locality",
    "wof:population":302
},
  "geometry": {"coordinates":[87.461181,22.866258],"type":"Point"}
}