{
  "type": "Feature",
  "properties": {
    "gn:admin1_code":"19",
    "gn:admin2_code":"557.0",
    "gn:asciiname":"Mulvad",
    "gn:country_code":"IN",
    "gn:dem":628,
    "gn:feature_class":"P",
    "gn:feature_code":"PPL",
    "gn:name":"Mulv\u0101d",
    "gn:population":0,
    "gn:timezone":"Asia/Kolkata",
    "iso:country":"IN",
    "name:und_x_variant":[
        "Mulawad",
        "Mulv\u0101d"
    ],
    "wof:name":"Mulvad",
    "wof:placetype":"locality"
},
  "geometry": {"coordinates":[75.7337,16.59163],"type":"Point"}
}