{
  "type": "Feature",
  "properties": {
    "iso:country":"IN",
    "ks:ks_name":"Jamaguda",
    "ks:ks_pop":176,
    "ks:ks_type":"VILLAGE",
    "name:eng_x_preferred":[
        "Jamaguda"
    ],
    "wof:name":"Jamaguda",
    "wof:placetype":"locality",
    "wof:population":176
},
  "geometry": {"coordinates":[84.04822900000001,19.325605],"type":"Point"}
}