{
  "type": "Feature",
  "properties": {
    "iso:country":"IN",
    "ks:ks_name":"Enatimulagam",
    "ks:ks_pop":109,
    "ks:ks_type":"VILLAGE",
    "name:eng_x_preferred":[
        "Enatimulagam"
    ],
    "wof:name":"Enatimulagam",
    "wof:placetype":"locality",
    "wof:population":109
},
  "geometry": {"coordinates":[83.701626,19.23372],"type":"Point"}
}