{
  "type": "Feature",
  "properties": {
    "iso:country":"IN",
    "ks:ks_name":"Pathrai",
    "ks:ks_pop":651,
    "ks:ks_type":"VILLAGE",
    "name:eng_x_preferred":[
        "Pathrai"
    ],
    "wof:name":"Pathrai",
    "wof:placetype":"locality",
    "wof:population":651
},
  "geometry": {"coordinates":[83.45296500000001,22.937894],"type":"Point"}
}