{
  "type": "Feature",
  "properties": {
    "iso:country":"IN",
    "ks:ks_name":"Sarasmal",
    "ks:ks_pop":357,
    "ks:ks_type":"HABITATION",
    "name:eng_x_preferred":[
        "Sarasmal"
    ],
    "wof:name":"Sarasmal",
    "wof:placetype":"locality",
    "wof:population":357
},
  "geometry": {"coordinates":[73.292278,20.333222],"type":"Point"}
}