{
  "type": "Feature",
  "properties": {
    "iso:country":"IN",
    "ks:ks_name":"Sindurapur",
    "ks:ks_pop":95,
    "ks:ks_type":"VILLAGE",
    "name:eng_x_preferred":[
        "Sindurapur"
    ],
    "wof:name":"Sindurapur",
    "wof:placetype":"locality",
    "wof:population":95
},
  "geometry": {"coordinates":[84.379751,19.13271],"type":"Point"}
}