{
  "type": "Feature",
  "properties": {
    "iso:country":"IN",
    "ks:ks_name":"Gaurwatanr",
    "ks:ks_pop":259,
    "ks:ks_type":"VILLAGE",
    "name:eng_x_preferred":[
        "Gaurwatanr"
    ],
    "wof:name":"Gaurwatanr",
    "wof:placetype":"locality",
    "wof:population":259
},
  "geometry": {"coordinates":[84.40651099999999,24.130706],"type":"Point"}
}