{
  "type": "Feature",
  "properties": {
    "iso:country":"IN",
    "ks:ks_alt_nam":"GODIYANA",
    "ks:ks_name":"Godiyana",
    "ks:ks_pop":553,
    "ks:ks_type":"HABITATION",
    "ks:ks_uagg_main":0,
    "name:eng_x_preferred":[
        "Godiyana"
    ],
    "wof:name":"Godiyana",
    "wof:placetype":"neighbourhood",
    "wof:population":553
},
  "geometry": {"coordinates":[83.269491,26.295854],"type":"Point"}
}