{
  "type": "Feature",
  "properties": {
    "gn:admin1_code":"2.0",
    "gn:admin2_code":"547.0",
    "gn:asciiname":"Chinnakomira",
    "gn:country_code":"IN",
    "gn:dem":75,
    "gn:feature_class":"P",
    "gn:feature_code":"PPL",
    "gn:name":"Chinnakomira",
    "gn:population":0,
    "gn:timezone":"Asia/Kolkata",
    "iso:country":"IN",
    "ks:ks_name":"China Komira",
    "ks:ks_pop":907,
    "ks:ks_type":"HABITATION",
    "ks:ks_uagg_main":0,
    "name:eng_x_preferred":[
        "China Komira"
    ],
    "wof:name":"China Komira",
    "wof:placetype":"neighbourhood",
    "wof:population":907
},
  "geometry": {"coordinates":[80.501006,16.972053],"type":"Point"}
}