{
  "type": "Feature",
  "properties": {
    "gn:admin1_code":"11.0",
    "gn:admin2_code":"27.0",
    "gn:asciiname":"Shushan",
    "gn:country_code":"IN",
    "gn:dem":1993,
    "gn:feature_class":"P",
    "gn:feature_code":"PPL",
    "gn:name":"Shushan",
    "gn:population":0,
    "gn:timezone":"Asia/Kolkata",
    "iso:country":"IN",
    "wof:name":"Shushan",
    "wof:placetype":"locality"
},
  "geometry": {"coordinates":[77.35849,31.39833],"type":"Point"}
}