{
  "type": "Feature",
  "properties": {
    "gn:admin1_code":"16.0",
    "gn:admin2_code":"526.0",
    "gn:asciiname":"Digewadi",
    "gn:country_code":"IN",
    "gn:dem":506,
    "gn:feature_class":"P",
    "gn:feature_code":"PPL",
    "gn:name":"Digew\u0101di",
    "gn:population":0,
    "gn:timezone":"Asia/Kolkata",
    "iso:country":"IN",
    "wof:name":"Digewadi",
    "wof:placetype":"locality"
},
  "geometry": {"coordinates":[76.16814000000002,17.4767],"type":"Point"}
}