{
  "type": "Feature",
  "properties": {
    "gn:admin1_code":"35",
    "gn:admin2_code":"426.0",
    "gn:asciiname":"Pateria",
    "gn:country_code":"IN",
    "gn:dem":410,
    "gn:feature_class":"P",
    "gn:feature_code":"PPL",
    "gn:name":"Pateria",
    "gn:population":0,
    "gn:timezone":"Asia/Kolkata",
    "iso:country":"IN",
    "ks:ks_name":"Pateriya",
    "ks:ks_pop":144,
    "ks:ks_type":"VILLAGE",
    "name:eng_x_preferred":[
        "Pateriya"
    ],
    "name:eng_x_variant":[
        "Pateria"
    ],
    "wof:name":"Pateriya",
    "wof:placetype":"locality",
    "wof:population":144
},
  "geometry": {"coordinates":[80.03258599999999,23.99996],"type":"Point"}
}