{
  "type": "Feature",
  "properties": {
    "gn:admin1_code":"21",
    "gn:admin2_code":"370.0",
    "gn:asciiname":"Amdahan",
    "gn:country_code":"IN",
    "gn:dem":284,
    "gn:feature_class":"P",
    "gn:feature_code":"PPL",
    "gn:name":"Amdahan",
    "gn:population":0,
    "gn:timezone":"Asia/Kolkata",
    "iso:country":"IN",
    "wof:name":"Amdahan",
    "wof:placetype":"locality"
},
  "geometry": {"coordinates":[83.07753000000002,20.86744],"type":"Point"}
}