{
  "type": "Feature",
  "properties": {
    "iso:country":"IN",
    "ks:ks_name":"Rasulapur",
    "ks:ks_pop":2,
    "ks:ks_type":"VILLAGE",
    "name:eng_x_preferred":[
        "Rasulapur"
    ],
    "wof:name":"Rasulapur",
    "wof:placetype":"locality",
    "wof:population":2
},
  "geometry": {"coordinates":[77.480794,20.732806],"type":"Point"}
}