{
  "type": "Feature",
  "properties": {
    "gn:admin1_code":"35.0",
    "gn:admin2_code":"456.0",
    "gn:asciiname":"Bamhni",
    "gn:country_code":"IN",
    "gn:dem":575,
    "gn:feature_class":"P",
    "gn:feature_code":"PPL",
    "gn:name":"Bamhn\u012b",
    "gn:population":0,
    "gn:timezone":"Asia/Kolkata",
    "iso:country":"IN",
    "ks:ks_name":"Bamhani",
    "ks:ks_pop":760,
    "ks:ks_type":"VILLAGE",
    "name:eng_x_preferred":[
        "Bamhani"
    ],
    "name:eng_x_variant":[
        "Bamhni"
    ],
    "wof:name":"Bamhani",
    "wof:placetype":"locality",
    "wof:population":760
},
  "geometry": {"coordinates":[80.178618,22.683621],"type":"Point"}
}