{
  "type": "Feature",
  "properties": {
    "iso:country":"IN",
    "ks:ks_name":"Rallavanka",
    "ks:ks_pop":265,
    "ks:ks_type":"HABITATION",
    "name:eng_x_preferred":[
        "Rallavanka"
    ],
    "wof:name":"Rallavanka",
    "wof:placetype":"locality",
    "wof:population":265
},
  "geometry": {"coordinates":[78.90992799999999,13.141207],"type":"Point"}
}