{
  "type": "Feature",
  "properties": {
    "gn:admin1_code":"36",
    "gn:admin2_code":"173.0",
    "gn:asciiname":"Pura Bansati",
    "gn:country_code":"IN",
    "gn:dem":98,
    "gn:feature_class":"P",
    "gn:feature_code":"PPL",
    "gn:name":"Pura Bansati",
    "gn:population":0,
    "gn:timezone":"Asia/Kolkata",
    "iso:country":"IN",
    "wof:name":"Pura Bansati",
    "wof:placetype":"locality"
},
  "geometry": {"coordinates":[81.72169,26.02976],"type":"Point"}
}