{
  "type": "Feature",
  "properties": {
    "gn:admin1_code":"39",
    "gn:admin2_code":"61.0",
    "gn:asciiname":"Pandiana",
    "gn:country_code":"IN",
    "gn:dem":1771,
    "gn:feature_class":"P",
    "gn:feature_code":"PPL",
    "gn:name":"Pandi\u0101na",
    "gn:population":0,
    "gn:timezone":"Asia/Kolkata",
    "iso:country":"IN",
    "wof:name":"Pandiana",
    "wof:placetype":"locality"
},
  "geometry": {"coordinates":[78.93881999999998,30.16985],"type":"Point"}
}