{
  "type": "Feature",
  "properties": {
    "iso:country":"IN",
    "ks:ks_alt_nam":"Pottan\u016br",
    "ks:ks_alt_nam_2":"Pottanur",
    "ks:ks_name":"Pothanur",
    "ks:ks_pop":13728,
    "ks:ks_type":"URBAN",
    "ks:ks_uagg_main":0,
    "name:eng_x_preferred":[
        "Pothanur"
    ],
    "name:eng_x_variant":[
        "Pottan\u016br",
        "Pottanur"
    ],
    "wof:name":"Pothanur",
    "wof:placetype":"neighbourhood",
    "wof:population":13728
},
  "geometry": {"coordinates":[77.99820099999999,11.111341],"type":"Point"}
}