{
  "type": "Feature",
  "properties": {
    "iso:country":"IN",
    "ks:ks_name":"Ghuriagaon",
    "ks:ks_pop":79,
    "ks:ks_type":"VILLAGE",
    "name:eng_x_preferred":[
        "Ghuriagaon"
    ],
    "wof:name":"Ghuriagaon",
    "wof:placetype":"locality",
    "wof:population":79
},
  "geometry": {"coordinates":[93.857258,26.799328],"type":"Point"}
}