{
  "type": "Feature",
  "properties": {
    "iso:country":"IN",
    "ks:ks_alt_nam":"Ramgowdna keri",
    "ks:ks_name":"Ramgowdna Keri",
    "ks:ks_pop":49,
    "ks:ks_type":"HABITATION",
    "name:eng_x_preferred":[
        "Ramgowdna Keri"
    ],
    "wof:name":"Ramgowdna Keri",
    "wof:placetype":"locality",
    "wof:population":49
},
  "geometry": {"coordinates":[74.474434,14.357967],"type":"Point"}
}