{
  "type": "Feature",
  "properties": {
    "gn:admin1_code":"39.0",
    "gn:admin2_code":"60.0",
    "gn:asciiname":"Maidan",
    "gn:country_code":"IN",
    "gn:dem":1030,
    "gn:feature_class":"P",
    "gn:feature_code":"PPL",
    "gn:name":"Maidan",
    "gn:population":0,
    "gn:timezone":"Asia/Kolkata",
    "iso:country":"IN",
    "name:ara_x_preferred":[
        "\u0627\u0644\u0645\u064a\u062f\u0627\u0646"
    ],
    "name:ceb_x_preferred":[
        "Maidan"
    ],
    "name:est_x_preferred":[
        "Maidan"
    ],
    "name:fas_x_preferred":[
        "\u0645\u06cc\u062f\u0627\u0646"
    ],
    "name:fra_x_preferred":[
        "Ma\u00efdan"
    ],
    "name:hye_x_preferred":[
        "\u0544\u0561\u0575\u0564\u0561\u0576"
    ],
    "name:ita_x_preferred":[
        "Maidan"
    ],
    "name:por_x_preferred":[
        "Maidan"
    ],
    "name:spa_x_preferred":[
        "Maid\u00e1n"
    ],
    "name:swe_x_preferred":[
        "Maidan"
    ],
    "wof:name":"Maidan",
    "wof:placetype":"neighbourhood"
},
  "geometry": {"coordinates":[78.21303,30.25653],"type":"Point"}
}