{
  "type": "Feature",
  "properties": {
    "iso:country":"IN",
    "ks:ks_name":"Shindewadi",
    "ks:ks_pop":35,
    "ks:ks_type":"HABITATION",
    "name:eng_x_preferred":[
        "Shindewadi"
    ],
    "wof:name":"Shindewadi",
    "wof:placetype":"locality",
    "wof:population":35
},
  "geometry": {"coordinates":[75.11533,19.26645],"type":"Point"}
}