{
  "type": "Feature",
  "properties": {
    "iso:country":"IN",
    "ks:ks_name":"Hazarika Chuburi",
    "ks:ks_pop":407,
    "ks:ks_type":"HABITATION",
    "name:eng_x_preferred":[
        "Hazarika Chuburi"
    ],
    "wof:name":"Hazarika Chuburi",
    "wof:placetype":"locality",
    "wof:population":407
},
  "geometry": {"coordinates":[95.110376,27.023337],"type":"Point"}
}