{
  "type": "Feature",
  "properties": {
    "gn:admin1_code":"34.0",
    "gn:admin2_code":"219.0",
    "gn:asciiname":"Mahesh Chhapra",
    "gn:country_code":"IN",
    "gn:dem":60,
    "gn:feature_class":"P",
    "gn:feature_code":"PPL",
    "gn:name":"Mahesh Chh\u0101pra",
    "gn:population":0,
    "gn:timezone":"Asia/Kolkata",
    "iso:country":"IN",
    "ks:ks_alt_nam":"Mahesh Chh\u0101pra",
    "ks:ks_name":"Mahesh Chhapra",
    "ks:ks_pop":42,
    "ks:ks_type":"VILLAGE",
    "ks:ks_uagg_main":0,
    "name:eng_x_preferred":[
        "Mahesh Chhapra"
    ],
    "name:eng_x_variant":[
        "Mahesh Chh\u0101pra"
    ],
    "wof:name":"Mahesh Chhapra",
    "wof:placetype":"neighbourhood",
    "wof:population":42
},
  "geometry": {"coordinates":[84.76478400000001,26.05119],"type":"Point"}
}