{
  "type": "Feature",
  "properties": {
    "iso:country":"IN",
    "ks:ks_alt_nam":"Jaman pada",
    "ks:ks_name":"Jaman Pada",
    "ks:ks_pop":239,
    "ks:ks_type":"HABITATION",
    "name:eng_x_preferred":[
        "Jaman Pada"
    ],
    "wof:name":"Jaman Pada",
    "wof:placetype":"locality",
    "wof:population":239
},
  "geometry": {"coordinates":[73.444,20.518389],"type":"Point"}
}