{
  "type": "Feature",
  "properties": {
    "iso:country":"IN",
    "ks:ks_name":"Dheeng",
    "ks:ks_pop":155,
    "ks:ks_type":"VILLAGE",
    "name:eng_x_preferred":[
        "Dheeng"
    ],
    "wof:name":"Dheeng",
    "wof:placetype":"locality",
    "wof:population":155
},
  "geometry": {"coordinates":[80.162724,29.39659],"type":"Point"}
}