{
  "type": "Feature",
  "properties": {
    "gn:admin1_code":"36",
    "gn:admin2_code":"188.0",
    "gn:asciiname":"Bhuindhra Buzurg",
    "gn:country_code":"IN",
    "gn:dem":81,
    "gn:feature_class":"P",
    "gn:feature_code":"PPL",
    "gn:name":"Bhuindhra Buzurg",
    "gn:population":0,
    "gn:timezone":"Asia/Kolkata",
    "iso:country":"IN",
    "ks:ks_name":"Bhuindhra Buzurg",
    "ks:ks_type":"VILLAGE",
    "ks:ks_uagg_main":0,
    "name:eng_x_preferred":[
        "Bhuindhra Buzurg"
    ],
    "wof:name":"Bhuindhra Buzurg",
    "wof:placetype":"neighbourhood"
},
  "geometry": {"coordinates":[83.240422,26.447995],"type":"Point"}
}