{
  "type": "Feature",
  "properties": {
    "gn:admin1_code":"36.0",
    "gn:admin2_code":"182.0",
    "gn:asciiname":"Piare Dih",
    "gn:country_code":"IN",
    "gn:dem":114,
    "gn:feature_class":"P",
    "gn:feature_code":"PPL",
    "gn:name":"Pi\u0101re D\u012bh",
    "gn:population":0,
    "gn:timezone":"Asia/Kolkata",
    "iso:country":"IN",
    "ks:ks_name":"Pyare Dih",
    "ks:ks_pop":651,
    "ks:ks_type":"HABITATION",
    "name:eng_x_preferred":[
        "Pyare Dih"
    ],
    "name:eng_x_variant":[
        "Piare Dih"
    ],
    "wof:name":"Pyare Dih",
    "wof:placetype":"locality",
    "wof:population":651
},
  "geometry": {"coordinates":[82.20161,27.55235],"type":"Point"}
}