{
  "type": "Feature",
  "properties": {
    "iso:country":"IN",
    "ks:ks_name":"Nichetola",
    "ks:ks_pop":48,
    "ks:ks_type":"HABITATION",
    "name:eng_x_preferred":[
        "Nichetola"
    ],
    "wof:name":"Nichetola",
    "wof:placetype":"locality",
    "wof:population":48
},
  "geometry": {"coordinates":[85.369488,23.175996],"type":"Point"}
}