{
  "type": "Feature",
  "properties": {
    "iso:country":"IN",
    "ks:ks_name":"Mandlik Akhada",
    "ks:ks_pop":806,
    "ks:ks_type":"HABITATION",
    "name:eng_x_preferred":[
        "Mandlik Akhada"
    ],
    "wof:name":"Mandlik Akhada",
    "wof:placetype":"locality",
    "wof:population":806
},
  "geometry": {"coordinates":[74.597781,19.35154],"type":"Point"}
}