{
  "type": "Feature",
  "properties": {
    "gn:admin1_code":"40.0",
    "gn:admin2_code":"534.0",
    "gn:asciiname":"Jupak",
    "gn:country_code":"IN",
    "gn:dem":251,
    "gn:feature_class":"P",
    "gn:feature_code":"PPL",
    "gn:name":"J\u016bp\u0101k",
    "gn:population":0,
    "gn:timezone":"Asia/Kolkata",
    "iso:country":"IN",
    "wof:name":"Jupak",
    "wof:placetype":"locality"
},
  "geometry": {"coordinates":[79.45255,18.21518],"type":"Point"}
}