{
  "type": "Feature",
  "properties": {
    "iso:country":"IN",
    "ks:ks_name":"Anu Basti Sonahi",
    "ks:ks_pop":163,
    "ks:ks_type":"HABITATION",
    "name:eng_x_preferred":[
        "Anu Basti Sonahi"
    ],
    "wof:name":"Anu Basti Sonahi",
    "wof:placetype":"locality",
    "wof:population":163
},
  "geometry": {"coordinates":[82.051855,25.9281],"type":"Point"}
}