{
  "type": "Feature",
  "properties": {
    "gn:admin1_code":"34.0",
    "gn:admin2_code":"208.0",
    "gn:asciiname":"Parsa Kalan",
    "gn:country_code":"IN",
    "gn:dem":74,
    "gn:feature_class":"P",
    "gn:feature_code":"PPL",
    "gn:name":"Parsa Kal\u0101n",
    "gn:population":0,
    "gn:timezone":"Asia/Kolkata",
    "iso:country":"IN",
    "wof:name":"Parsa Kalan",
    "wof:placetype":"locality"
},
  "geometry": {"coordinates":[87.07361999999998,26.40648],"type":"Point"}
}