{
  "type": "Feature",
  "properties": {
    "gn:admin1_code":"11",
    "gn:admin2_code":"24.0",
    "gn:asciiname":"Kandhela",
    "gn:country_code":"IN",
    "gn:dem":880,
    "gn:feature_class":"P",
    "gn:feature_code":"PPL",
    "gn:name":"Kandhela",
    "gn:population":0,
    "gn:timezone":"Asia/Kolkata",
    "iso:country":"IN",
    "wof:name":"Kandhela",
    "wof:placetype":"locality"
},
  "geometry": {"coordinates":[76.41853,31.93436],"type":"Point"}
}