{
  "type": "Feature",
  "properties": {
    "gn:admin1_code":"37.0",
    "gn:admin2_code":"414.0",
    "gn:asciiname":"Karmari",
    "gn:country_code":"IN",
    "gn:dem":650,
    "gn:feature_class":"P",
    "gn:feature_code":"PPL",
    "gn:name":"Karmari",
    "gn:population":0,
    "gn:timezone":"Asia/Kolkata",
    "iso:country":"IN",
    "ks:ks_name":"Karmari",
    "ks:ks_pop":485,
    "ks:ks_type":"VILLAGE",
    "name:eng_x_preferred":[
        "Karmari"
    ],
    "wof:name":"Karmari",
    "wof:placetype":"locality",
    "wof:population":485
},
  "geometry": {"coordinates":[81.432883,20.005922],"type":"Point"}
}