{
  "type": "Feature",
  "properties": {
    "gn:admin1_code":"37",
    "gn:admin2_code":"410.0",
    "gn:asciiname":"Ghoghra",
    "gn:country_code":"IN",
    "gn:dem":372,
    "gn:feature_class":"P",
    "gn:feature_code":"PPL",
    "gn:name":"Ghoghra",
    "gn:population":0,
    "gn:timezone":"Asia/Kolkata",
    "iso:country":"IN",
    "ks:ks_name":"Ghoghra",
    "ks:ks_type":"VILLAGE",
    "name:eng_x_preferred":[
        "Ghoghra"
    ],
    "wof:name":"Ghoghra",
    "wof:placetype":"locality"
},
  "geometry": {"coordinates":[82.322429,20.870346],"type":"Point"}
}