{
  "type": "Feature",
  "properties": {
    "iso:country":"IN",
    "ks:ks_name":"Chetraphalwadi",
    "ks:ks_pop":42,
    "ks:ks_type":"HABITATION",
    "name:eng_x_preferred":[
        "Chetraphalwadi"
    ],
    "wof:name":"Chetraphalwadi",
    "wof:placetype":"locality",
    "wof:population":42
},
  "geometry": {"coordinates":[73.68856700000001,15.802922],"type":"Point"}
}