{
  "type": "Feature",
  "properties": {
    "iso:country":"IN",
    "ks:ks_alt_nam":"S\u0101dikpur Jogi",
    "ks:ks_name":"Sadikpur Jogi",
    "ks:ks_type":"VILLAGE",
    "ks:ks_uagg_main":0,
    "name:eng_x_preferred":[
        "Sadikpur Jogi"
    ],
    "name:eng_x_variant":[
        "S\u0101dikpur Jogi"
    ],
    "wof:name":"Sadikpur Jogi",
    "wof:placetype":"neighbourhood"
},
  "geometry": {"coordinates":[85.16699699999999,25.599904],"type":"Point"}
}