{
  "type": "Feature",
  "properties": {
    "iso:country":"IN",
    "ks:ks_name":"Rakhyasini Jhar Pt-I",
    "ks:ks_pop":425,
    "ks:ks_type":"VILLAGE",
    "ks:ks_uagg_main":0,
    "name:eng_x_preferred":[
        "Rakhyasini Jhar Pt-I"
    ],
    "wof:name":"Rakhyasini Jhar Pt-I",
    "wof:placetype":"locality",
    "wof:population":425
},
  "geometry": {"coordinates":[90.654787,26.117546],"type":"Point"}
}