{
  "type": "Feature",
  "properties": {
    "gn:admin1_code":"40",
    "gn:admin2_code":"535.0",
    "gn:asciiname":"Serimallareddipalli",
    "gn:country_code":"IN",
    "gn:dem":516,
    "gn:feature_class":"P",
    "gn:feature_code":"PPL",
    "gn:name":"Serimall\u0101reddipalli",
    "gn:population":0,
    "gn:timezone":"Asia/Kolkata",
    "iso:country":"IN",
    "ks:ks_name":"Serimallareddipalle",
    "ks:ks_pop":563,
    "ks:ks_type":"VILLAGE",
    "ks:ks_uagg_main":0,
    "name:eng_x_preferred":[
        "Serimallareddipalle"
    ],
    "wof:name":"Serimallareddipalle",
    "wof:placetype":"neighbourhood",
    "wof:population":563
},
  "geometry": {"coordinates":[77.99238099999999,17.87238],"type":"Point"}
}