{
  "type": "Feature",
  "properties": {
    "gn:admin1_code":"19.0",
    "gn:admin2_code":"569.0",
    "gn:asciiname":"Bedradi",
    "gn:country_code":"IN",
    "gn:dem":14,
    "gn:feature_class":"P",
    "gn:feature_code":"PPL",
    "gn:name":"Bedradi",
    "gn:population":0,
    "gn:timezone":"Asia/Kolkata",
    "iso:country":"IN",
    "ks:ks_name":"Bidradi",
    "ks:ks_pop":240,
    "ks:ks_type":"HABITATION",
    "name:eng_x_preferred":[
        "Bidradi"
    ],
    "name:eng_x_variant":[
        "Bedradi"
    ],
    "wof:name":"Bidradi",
    "wof:placetype":"locality",
    "wof:population":240
},
  "geometry": {"coordinates":[74.81969700000001,13.616364],"type":"Point"}
}