{
  "type": "Feature",
  "properties": {
    "gn:admin1_code":"36",
    "gn:admin2_code":"200.0",
    "gn:asciiname":"Bardia",
    "gn:country_code":"IN",
    "gn:dem":312,
    "gn:feature_class":"P",
    "gn:feature_code":"PPL",
    "gn:name":"Bardia",
    "gn:population":0,
    "gn:timezone":"Asia/Kolkata",
    "iso:country":"IN",
    "name:ara_x_preferred":[
        "\u0627\u0644\u0628\u0631\u062f\u064a\u0629"
    ],
    "name:azb_x_preferred":[
        "\u0628\u0631\u062f\u06cc\u0647"
    ],
    "name:bul_x_preferred":[
        "\u0411\u0430\u0440\u0434\u0438\u044f"
    ],
    "name:cym_x_preferred":[
        "Bardia"
    ],
    "name:deu_x_preferred":[
        "Bardia"
    ],
    "name:epo_x_preferred":[
        "Bardia"
    ],
    "name:fas_x_preferred":[
        "\u0628\u0631\u062f\u06cc\u0647"
    ],
    "name:fra_x_preferred":[
        "Bardia"
    ],
    "name:heb_x_preferred":[
        "\u05d1\u05e8\u05d3\u05d9\u05d4"
    ],
    "name:ita_x_preferred":[
        "Bardia"
    ],
    "name:kat_x_preferred":[
        "\u10d1\u10d0\u10e0\u10d3\u10d8\u10d0"
    ],
    "name:pol_x_preferred":[
        "Al-Bardijja"
    ],
    "name:swe_x_preferred":[
        "Bardia"
    ],
    "name:tam_x_preferred":[
        "\u0baa\u0bbe\u0bb0\u0bcd\u0b9f\u0bbf\u0baf\u0bbe"
    ],
    "name:ukr_x_preferred":[
        "\u0411\u0430\u0440\u0434\u0456\u044f"
    ],
    "wof:name":"Bardia",
    "wof:placetype":"locality"
},
  "geometry": {"coordinates":[82.73387,24.67342],"type":"Point"}
}