{
  "type": "Feature",
  "properties": {
    "iso:country":"IN",
    "ks:ks_name":"Prajau",
    "ks:ks_pop":831,
    "ks:ks_type":"VILLAGE",
    "name:eng_x_preferred":[
        "Prajau"
    ],
    "wof:name":"Prajau",
    "wof:placetype":"locality",
    "wof:population":831
},
  "geometry": {"coordinates":[68.829931,23.151872],"type":"Point"}
}