{
  "type": "Feature",
  "properties": {
    "iso:country":"IN",
    "ks:ks_name":"Simali Mangari",
    "ks:ks_pop":28,
    "ks:ks_type":"VILLAGE",
    "name:eng_x_preferred":[
        "Simali Mangari"
    ],
    "wof:name":"Simali Mangari",
    "wof:placetype":"locality",
    "wof:population":28
},
  "geometry": {"coordinates":[79.353568,30.316864],"type":"Point"}
}