{
  "type": "Feature",
  "properties": {
    "iso:country":"IN",
    "ks:ks_name":"Biren Teron Gaon",
    "ks:ks_pop":38,
    "ks:ks_type":"HABITATION",
    "ks:ks_uagg_main":0,
    "name:eng_x_preferred":[
        "Biren Teron Gaon"
    ],
    "wof:name":"Biren Teron Gaon",
    "wof:placetype":"neighbourhood",
    "wof:population":38
},
  "geometry": {"coordinates":[93.29371999999999,26.335781],"type":"Point"}
}