{
  "type": "Feature",
  "properties": {
    "iso:country":"IN",
    "ks:ks_name":"Chikramguda",
    "ks:ks_pop":68,
    "ks:ks_type":"HABITATION",
    "name:eng_x_preferred":[
        "Chikramguda"
    ],
    "wof:name":"Chikramguda",
    "wof:placetype":"locality",
    "wof:population":68
},
  "geometry": {"coordinates":[79.366179,19.096633],"type":"Point"}
}