{
  "type": "Feature",
  "properties": {
    "iso:country":"IN",
    "ks:ks_name":"17 SJM-A",
    "ks:ks_pop":228,
    "ks:ks_type":"VILLAGE",
    "name:eng_x_preferred":[
        "17 SJM-A"
    ],
    "wof:name":"17 SJM-A",
    "wof:placetype":"locality",
    "wof:population":228
},
  "geometry": {"coordinates":[73.245317,29.336968],"type":"Point"}
}