{
  "type": "Feature",
  "properties": {
    "iso:country":"IN",
    "ks:ks_alt_nam":"PANDIT KA PURWA",
    "ks:ks_name":"Pandit Ka Purwa",
    "ks:ks_pop":200,
    "ks:ks_type":"HABITATION",
    "name:eng_x_preferred":[
        "Pandit Ka Purwa"
    ],
    "wof:name":"Pandit Ka Purwa",
    "wof:placetype":"locality",
    "wof:population":200
},
  "geometry": {"coordinates":[81.57324300000001,26.442133],"type":"Point"}
}