{
  "type": "Feature",
  "properties": {
    "iso:country":"IN",
    "ks:ks_name":"Bongadar",
    "ks:ks_pop":404,
    "ks:ks_type":"VILLAGE",
    "name:eng_x_preferred":[
        "Bongadar"
    ],
    "wof:name":"Bongadar",
    "wof:placetype":"locality",
    "wof:population":404
},
  "geometry": {"coordinates":[85.853375,23.179512],"type":"Point"}
}