{
  "type": "Feature",
  "properties": {
    "iso:country":"IN",
    "ks:ks_name":"Gobardhanpur",
    "ks:ks_pop":327,
    "ks:ks_type":"VILLAGE",
    "name:eng_x_preferred":[
        "Gobardhanpur"
    ],
    "wof:name":"Gobardhanpur",
    "wof:placetype":"locality",
    "wof:population":327
},
  "geometry": {"coordinates":[87.628877,22.034942],"type":"Point"}
}