{
  "type": "Feature",
  "properties": {
    "iso:country":"IN",
    "ks:ks_name":"Somatan",
    "ks:ks_pop":64,
    "ks:ks_type":"HABITATION",
    "name:eng_x_preferred":[
        "Somatan"
    ],
    "wof:name":"Somatan",
    "wof:placetype":"locality",
    "wof:population":64
},
  "geometry": {"coordinates":[92.534145,25.664864],"type":"Point"}
}