{
  "type": "Feature",
  "properties": {
    "gn:admin1_code":"24.0",
    "gn:admin2_code":"104.0",
    "gn:asciiname":"Asaka",
    "gn:country_code":"IN",
    "gn:dem":225,
    "gn:feature_class":"P",
    "gn:feature_code":"PPL",
    "gn:name":"As\u0101ka",
    "gn:population":0,
    "gn:timezone":"Asia/Kolkata",
    "iso:country":"IN",
    "name:bel_x_preferred":[
        "\u0410\u0441\u0430\u043a\u0430"
    ],
    "name:ceb_x_preferred":[
        "Asaka"
    ],
    "name:deu_x_preferred":[
        "Asaka"
    ],
    "name:ita_x_preferred":[
        "Asaka"
    ],
    "name:jpn_x_preferred":[
        "\u30a2\u30b5\u30ab"
    ],
    "name:pol_x_preferred":[
        "Asaka"
    ],
    "name:rus_x_preferred":[
        "\u0410\u0441\u0430\u043a\u0430"
    ],
    "name:spa_x_preferred":[
        "Asaka"
    ],
    "name:swe_x_preferred":[
        "Asaka"
    ],
    "name:tur_x_preferred":[
        "Asaka"
    ],
    "name:ukr_x_preferred":[
        "\u0410\u0441\u0430\u043a\u0430"
    ],
    "name:uzb_x_preferred":[
        "Asaka"
    ],
    "wof:name":"Asaka",
    "wof:placetype":"locality"
},
  "geometry": {"coordinates":[76.95824,27.50383],"type":"Point"}
}