{
  "type": "Feature",
  "properties": {
    "iso:country":"IN",
    "ks:ks_name":"Chakundi",
    "ks:ks_pop":3540,
    "ks:ks_type":"VILLAGE",
    "ks:ks_uagg_main":0,
    "name:eng_x_preferred":[
        "Chakundi"
    ],
    "wof:name":"Chakundi",
    "wof:placetype":"locality",
    "wof:population":3540
},
  "geometry": {"coordinates":[88.29843099999999,22.70303],"type":"Point"}
}