{
  "type": "Feature",
  "properties": {
    "gn:admin1_code":"36",
    "gn:admin2_code":"175.0",
    "gn:asciiname":"Samhan",
    "gn:country_code":"IN",
    "gn:dem":94,
    "gn:feature_class":"P",
    "gn:feature_code":"PPL",
    "gn:name":"Samh\u0101n",
    "gn:population":0,
    "gn:timezone":"Asia/Kolkata",
    "iso:country":"IN",
    "name:ara_x_preferred":[
        "\u0633\u0627\u0645\u0647\u0627\u0646"
    ],
    "name:dan_x_preferred":[
        "Samhan"
    ],
    "name:deu_x_preferred":[
        "Samhan"
    ],
    "name:fas_x_preferred":[
        "\u0633\u0645\u200c\u0647\u0627\u0646"
    ],
    "name:fra_x_preferred":[
        "Samhan"
    ],
    "name:hun_x_preferred":[
        "Szamhan"
    ],
    "name:ind_x_preferred":[
        "Samhan"
    ],
    "name:kur_x_preferred":[
        "Samhan"
    ],
    "name:por_x_preferred":[
        "Samhan"
    ],
    "name:rus_x_preferred":[
        "\u0421\u0430\u043c\u0445\u0430\u043d"
    ],
    "name:spa_x_preferred":[
        "Samhan"
    ],
    "name:tur_x_preferred":[
        "Samhan"
    ],
    "name:ukr_x_preferred":[
        "\u0421\u0430\u043c\u0445\u0430\u043d"
    ],
    "name:vie_x_preferred":[
        "Tam H\u00e0n"
    ],
    "wof:name":"Samhan",
    "wof:placetype":"locality"
},
  "geometry": {"coordinates":[82.04543000000002,25.2288],"type":"Point"}
}