{
  "type": "Feature",
  "properties": {
    "iso:country":"IN",
    "ks:ks_name":"Biria Narainpur",
    "ks:ks_type":"VILLAGE",
    "name:eng_x_preferred":[
        "Biria Narainpur"
    ],
    "wof:name":"Biria Narainpur",
    "wof:placetype":"neighbourhood"
},
  "geometry": {"coordinates":[79.37482900000001,28.331715],"type":"Point"}
}