{
  "type": "Feature",
  "properties": {
    "iso:country":"IN",
    "ks:ks_name":"Velliyamkallu",
    "ks:ks_pop":2080,
    "ks:ks_type":"HABITATION",
    "name:eng_x_preferred":[
        "Velliyamkallu"
    ],
    "wof:name":"Velliyamkallu",
    "wof:placetype":"locality",
    "wof:population":2080
},
  "geometry": {"coordinates":[76.118042,10.809369],"type":"Point"}
}