{
  "type": "Feature",
  "properties": {
    "gn:admin1_code":"36",
    "gn:admin2_code":"134.0",
    "gn:asciiname":"Parmawala",
    "gn:country_code":"IN",
    "gn:dem":237,
    "gn:feature_class":"P",
    "gn:feature_code":"PPL",
    "gn:name":"Parm\u0101w\u0101la",
    "gn:population":0,
    "gn:timezone":"Asia/Kolkata",
    "iso:country":"IN",
    "name:und_x_variant":[
        "Parm\u0101w\u0101la",
        "Mahm\u016bdpur Parma"
    ],
    "wof:name":"Parmawala",
    "wof:placetype":"locality"
},
  "geometry": {"coordinates":[78.4653,29.29415],"type":"Point"}
}