{
  "type": "Feature",
  "properties": {
    "iso:country":"IN",
    "ks:ks_name":"Sutharon Ki Beri",
    "ks:ks_pop":718,
    "ks:ks_type":"HABITATION",
    "name:eng_x_preferred":[
        "Sutharon Ki Beri"
    ],
    "wof:name":"Sutharon Ki Beri",
    "wof:placetype":"locality",
    "wof:population":718
},
  "geometry": {"coordinates":[71.662272,25.474392],"type":"Point"}
}