{
  "type": "Feature",
  "properties": {
    "iso:country":"IN",
    "ks:ks_name":"Chhote Bedma",
    "ks:ks_pop":419,
    "ks:ks_type":"VILLAGE",
    "name:eng_x_preferred":[
        "Chhote Bedma"
    ],
    "wof:name":"Chhote Bedma",
    "wof:placetype":"locality",
    "wof:population":419
},
  "geometry": {"coordinates":[81.43118200000001,18.635859],"type":"Point"}
}