{
  "type": "Feature",
  "properties": {
    "iso:country":"IN",
    "ks:ks_name":"Dharmaram",
    "ks:ks_pop":747,
    "ks:ks_type":"VILLAGE",
    "ks:ks_uagg_main":0,
    "name:eng_x_preferred":[
        "Dharmaram"
    ],
    "wof:name":"Dharmaram",
    "wof:placetype":"neighbourhood",
    "wof:population":747
},
  "geometry": {"coordinates":[79.33060399999999,18.338649],"type":"Point"}
}