{
  "type": "Feature",
  "properties": {
    "iso:country":"IN",
    "ks:ks_name":"Bamalkera",
    "ks:ks_pop":800,
    "ks:ks_type":"VILLAGE",
    "name:eng_x_preferred":[
        "Bamalkera"
    ],
    "wof:name":"Bamalkera",
    "wof:placetype":"locality",
    "wof:population":800
},
  "geometry": {"coordinates":[84.356245,22.78785],"type":"Point"}
}