{
  "type": "Feature",
  "properties": {
    "gn:admin1_code":"34.0",
    "gn:admin2_code":"220.0",
    "gn:asciiname":"Muhammadpur Gangti",
    "gn:country_code":"IN",
    "gn:dem":58,
    "gn:feature_class":"P",
    "gn:feature_code":"PPL",
    "gn:name":"Muhammadpur Gangti",
    "gn:population":0,
    "gn:timezone":"Asia/Kolkata",
    "iso:country":"IN",
    "ks:ks_name":"Mohammadpur Gangti",
    "ks:ks_pop":695,
    "ks:ks_type":"VILLAGE",
    "name:eng_x_preferred":[
        "Mohammadpur Gangti"
    ],
    "name:eng_x_variant":[
        "Muhammadpur Gangti"
    ],
    "wof:name":"Mohammadpur Gangti",
    "wof:placetype":"locality",
    "wof:population":695
},
  "geometry": {"coordinates":[85.42031299999999,25.890569],"type":"Point"}
}