{
  "type": "Feature",
  "properties": {
    "gn:admin1_code":"24.0",
    "gn:admin2_code":"103.0",
    "gn:asciiname":"Dailwas",
    "gn:country_code":"IN",
    "gn:dem":299,
    "gn:feature_class":"P",
    "gn:feature_code":"PPL",
    "gn:name":"Dailw\u0101s",
    "gn:population":0,
    "gn:timezone":"Asia/Kolkata",
    "iso:country":"IN",
    "wof:name":"Dailwas",
    "wof:placetype":"neighbourhood"
},
  "geometry": {"coordinates":[75.95612,28.177],"type":"Point"}
}