{
  "type": "Feature",
  "properties": {
    "iso:country":"IN",
    "ks:ks_name":"Suqauli Tola",
    "ks:ks_pop":127,
    "ks:ks_type":"HABITATION",
    "ks:ks_uagg_main":0,
    "name:eng_x_preferred":[
        "Suqauli Tola"
    ],
    "wof:name":"Suqauli Tola",
    "wof:placetype":"neighbourhood",
    "wof:population":127
},
  "geometry": {"coordinates":[83.954497,27.051666],"type":"Point"}
}