{
  "type": "Feature",
  "properties": {
    "iso:country":"IN",
    "ks:ks_name":"Tulya Chak",
    "ks:ks_pop":0,
    "ks:ks_type":"VILLAGE",
    "name:eng_x_preferred":[
        "Tulya Chak"
    ],
    "wof:name":"Tulya Chak",
    "wof:placetype":"locality",
    "wof:population":0
},
  "geometry": {"coordinates":[87.392503,22.201847],"type":"Point"}
}