{
  "type": "Feature",
  "properties": {
    "iso:country":"IN",
    "ks:ks_name":"Ballipur",
    "ks:ks_pop":454,
    "ks:ks_type":"HABITATION",
    "name:eng_x_preferred":[
        "Ballipur"
    ],
    "wof:name":"Ballipur",
    "wof:placetype":"locality",
    "wof:population":454
},
  "geometry": {"coordinates":[83.297292,27.216863],"type":"Point"}
}