{
  "type": "Feature",
  "properties": {
    "gn:gn_country":"IN",
    "gn:gn_fcode":"PPL",
    "gn:gn_pop":20752,
    "gn:population":20752,
    "iso:country":"IN",
    "name:ben_x_preferred":[
        "\u0986\u09b2\u09bf\u09ac\u09be\u0997"
    ],
    "name:bpy_x_preferred":[
        "\u0986\u09b2\u09bf\u09ac\u09be\u0997"
    ],
    "name:cat_x_preferred":[
        "Alibag"
    ],
    "name:ceb_x_preferred":[
        "Al\u012bb\u0101g"
    ],
    "name:deu_x_preferred":[
        "Alibag"
    ],
    "name:eng_x_preferred":[
        "Alibag"
    ],
    "name:fas_x_preferred":[
        "\u0639\u0644\u06cc\u0628\u06af"
    ],
    "name:fra_x_preferred":[
        "Alibag"
    ],
    "name:hin_x_preferred":[
        "\u0905\u0932\u0940\u092c\u093e\u0917"
    ],
    "name:hun_x_preferred":[
        "Alib\u00e1g"
    ],
    "name:ita_x_preferred":[
        "Alibag"
    ],
    "name:mar_x_preferred":[
        "\u0905\u0932\u093f\u092c\u093e\u0917"
    ],
    "name:min_x_preferred":[
        "Alibag"
    ],
    "name:mlg_x_preferred":[
        "Alibag"
    ],
    "name:msa_x_preferred":[
        "Alibag"
    ],
    "name:nan_x_preferred":[
        "Alibag"
    ],
    "name:new_x_preferred":[
        "\u0905\u0932\u093f\u092c\u093e\u0917"
    ],
    "name:nld_x_preferred":[
        "Alibag"
    ],
    "name:rus_x_preferred":[
        "\u0410\u043b\u0438\u0431\u0430\u0433"
    ],
    "name:san_x_preferred":[
        "\u0905\u0932\u093f\u092c\u093e\u0917\u094d"
    ],
    "name:swe_x_preferred":[
        "Alibag"
    ],
    "name:unk_x_variant":[
        "Alib\u00e1gh"
    ],
    "name:urd_x_preferred":[
        "\u0639\u0644\u06cc \u0628\u0627\u063a"
    ],
    "name:vie_x_preferred":[
        "Alibag"
    ],
    "name:zho_x_preferred":[
        "\u963f\u5229\u5df4\u683c"
    ],
    "qs_pg:aaroncc":"IN",
    "qs_pg:gn_country":"IN",
    "qs_pg:gn_fcode":"PPL",
    "qs_pg:gn_pop":20752,
    "qs_pg:name":"Alibag",
    "qs_pg:name_adm0":"India",
    "qs_pg:name_adm1":"Maharashtra",
    "qs_pg:photos":853,
    "qs_pg:photos_1k":173,
    "qs_pg:photos_9k":4,
    "qs_pg:photos_9r":6,
    "qs_pg:photos_all":853,
    "qs_pg:photos_sr":10,
    "qs_pg:pop_sr":7,
    "qs_pg:qs_pg_placetype":"locality",
    "qs_pg:qs_pg_placetype_gp":"Town",
    "qs_pg:woe_adm0":23424848,
    "woe:adm0_id":23424848,
    "woe:name_adm0":"India",
    "woe:name_adm1":"Maharashtra",
    "woe:placetype":"Town",
    "wof:name":"Alibag",
    "wof:placetype":"locality",
    "wof:population":20752
},
  "geometry": {"coordinates":[72.87578999999999,18.64813],"type":"Point"}
}