{
  "type": "Feature",
  "properties": {
    "iso:country":"IN",
    "ks:ks_name":"Chhindih",
    "ks:ks_pop":605,
    "ks:ks_type":"HABITATION",
    "name:eng_x_preferred":[
        "Chhindih"
    ],
    "wof:name":"Chhindih",
    "wof:placetype":"locality",
    "wof:population":605
},
  "geometry": {"coordinates":[81.66278800000001,19.942037],"type":"Point"}
}