{
  "type": "Feature",
  "properties": {
    "gn:admin1_code":"16",
    "gn:admin2_code":"526.0",
    "gn:asciiname":"Sade",
    "gn:country_code":"IN",
    "gn:dem":540,
    "gn:feature_class":"P",
    "gn:feature_code":"PPL",
    "gn:name":"Sade",
    "gn:population":0,
    "gn:timezone":"Asia/Kolkata",
    "iso:country":"IN",
    "name:und_x_variant":[
        "Sada",
        "Sade"
    ],
    "wof:name":"Sade",
    "wof:placetype":"locality"
},
  "geometry": {"coordinates":[75.27993000000002,18.28335],"type":"Point"}
}