{
  "type": "Feature",
  "properties": {
    "gn:admin1_code":"16",
    "gn:admin2_code":"526.0",
    "gn:asciiname":"Sade",
    "gn:country_code":"IN",
    "gn:dem":540,
    "gn:feature_class":"P",
    "gn:feature_code":"PPL",
    "gn:name":"Sade",
    "gn:population":0,
    "gn:timezone":"Asia/Kolkata",
    "iso:country":"IN",
    "name:ces_x_preferred":[
        "Sade"
    ],
    "name:deu_x_preferred":[
        "Sade"
    ],
    "name:fas_x_preferred":[
        "\u0634\u0627\u062f\u0647"
    ],
    "name:fin_x_preferred":[
        "Sade"
    ],
    "name:fra_x_preferred":[
        "Sade"
    ],
    "name:hun_x_preferred":[
        "Sade"
    ],
    "name:ind_x_preferred":[
        "Sade"
    ],
    "name:ita_x_preferred":[
        "Sade"
    ],
    "name:lav_x_preferred":[
        "Sade"
    ],
    "name:nld_x_preferred":[
        "Sade"
    ],
    "name:oci_x_preferred":[
        "Sade"
    ],
    "name:por_x_preferred":[
        "Sade"
    ],
    "name:spa_x_preferred":[
        "Sade"
    ],
    "name:tur_x_preferred":[
        "Sade"
    ],
    "name:und_x_variant":[
        "Sada"
    ],
    "wof:name":"Sade",
    "wof:placetype":"locality"
},
  "geometry": {"coordinates":[75.27993000000002,18.28335],"type":"Point"}
}