{
  "type": "Feature",
  "properties": {
    "iso:country":"IN",
    "ks:ks_alt_nam":"YEDIVINAKOPPA",
    "ks:ks_name":"Yedivinakoppa",
    "ks:ks_pop":105,
    "ks:ks_type":"HABITATION",
    "name:eng_x_preferred":[
        "Yedivinakoppa"
    ],
    "wof:name":"Yedivinakoppa",
    "wof:placetype":"locality",
    "wof:population":105
},
  "geometry": {"coordinates":[75.31599199999999,13.676554],"type":"Point"}
}