{
  "type": "Feature",
  "properties": {
    "iso:country":"IN",
    "ks:ks_name":"Panch Mahudi",
    "ks:ks_pop":2077,
    "ks:ks_type":"HABITATION",
    "name:eng_x_preferred":[
        "Panch Mahudi"
    ],
    "wof:name":"Panch Mahudi",
    "wof:placetype":"locality",
    "wof:population":2077
},
  "geometry": {"coordinates":[73.62594799999999,23.727294],"type":"Point"}
}