{
  "type": "Feature",
  "properties": {
    "gn:admin1_code":"36.0",
    "gn:admin2_code":"189.0",
    "gn:asciiname":"Mathia Bhokaria",
    "gn:country_code":"IN",
    "gn:dem":82,
    "gn:feature_class":"P",
    "gn:feature_code":"PPL",
    "gn:name":"Mathi\u0101 Bhokari\u0101",
    "gn:population":0,
    "gn:timezone":"Asia/Kolkata",
    "iso:country":"IN",
    "ks:ks_alt_nam":"Mathi\u0101 Bhokari\u0101",
    "ks:ks_name":"Mathia Bhokaria",
    "ks:ks_type":"VILLAGE",
    "name:eng_x_preferred":[
        "Mathia Bhokaria"
    ],
    "name:eng_x_variant":[
        "Mathi\u0101 Bhokari\u0101"
    ],
    "wof:name":"Mathia Bhokaria",
    "wof:placetype":"locality"
},
  "geometry": {"coordinates":[84.152609,26.757005],"type":"Point"}
}