{
  "type": "Feature",
  "properties": {
    "gn:admin1_code":"19.0",
    "gn:admin2_code":"581.0",
    "gn:asciiname":"Kuthandahalli",
    "gn:country_code":"IN",
    "gn:dem":842,
    "gn:feature_class":"P",
    "gn:feature_code":"PPL",
    "gn:name":"K\u016bth\u0101ndahalli",
    "gn:population":0,
    "gn:timezone":"Asia/Kolkata",
    "iso:country":"IN",
    "wof:name":"Kuthandahalli",
    "wof:placetype":"locality"
},
  "geometry": {"coordinates":[78.34487,13.20557],"type":"Point"}
}