{
  "type": "Feature",
  "properties": {
    "gn:admin1_code":"39.0",
    "gn:admin2_code":"64.0",
    "gn:asciiname":"Ratrau",
    "gn:country_code":"IN",
    "gn:dem":1400,
    "gn:feature_class":"P",
    "gn:feature_code":"PPL",
    "gn:name":"Ratrau",
    "gn:population":0,
    "gn:timezone":"Asia/Kolkata",
    "iso:country":"IN",
    "wof:name":"Ratrau",
    "wof:placetype":"locality"
},
  "geometry": {"coordinates":[79.79631999999999,29.5208],"type":"Point"}
}