{
  "type": "Feature",
  "properties": {
    "gn:admin1_code":"37",
    "gn:admin2_code":"413.0",
    "gn:asciiname":"Putarwahi",
    "gn:country_code":"IN",
    "gn:dem":391,
    "gn:feature_class":"P",
    "gn:feature_code":"PPL",
    "gn:name":"Putarw\u0101hi",
    "gn:population":0,
    "gn:timezone":"Asia/Kolkata",
    "iso:country":"IN",
    "ks:ks_alt_nam":"Putarw\u0101hi",
    "ks:ks_name":"Putarwahi",
    "ks:ks_type":"VILLAGE",
    "name:eng_x_preferred":[
        "Putarwahi"
    ],
    "name:eng_x_variant":[
        "Putarw\u0101hi"
    ],
    "wof:name":"Putarwahi",
    "wof:placetype":"locality"
},
  "geometry": {"coordinates":[81.059049,20.24487],"type":"Point"}
}