{
  "type": "Feature",
  "properties": {
    "iso:country":"IN",
    "ks:ks_name":"Gavthanwadi",
    "ks:ks_pop":73,
    "ks:ks_type":"HABITATION",
    "name:eng_x_preferred":[
        "Gavthanwadi"
    ],
    "wof:name":"Gavthanwadi",
    "wof:placetype":"locality",
    "wof:population":73
},
  "geometry": {"coordinates":[73.626794,16.097866],"type":"Point"}
}