{
  "type": "Feature",
  "properties": {
    "gn:admin1_code":"21",
    "gn:admin2_code":"371.0",
    "gn:asciiname":"Kuraloi",
    "gn:country_code":"IN",
    "gn:dem":236,
    "gn:feature_class":"P",
    "gn:feature_code":"PPL",
    "gn:name":"Kur\u0101loi",
    "gn:population":0,
    "gn:timezone":"Asia/Kolkata",
    "iso:country":"IN",
    "ks:ks_name":"Kudaloi",
    "ks:ks_pop":3374,
    "ks:ks_type":"VILLAGE",
    "name:eng_x_preferred":[
        "Kudaloi"
    ],
    "name:eng_x_variant":[
        "Kuraloi"
    ],
    "wof:name":"Kudaloi",
    "wof:placetype":"locality",
    "wof:population":3374
},
  "geometry": {"coordinates":[83.830872,21.780969],"type":"Point"}
}