{
  "type": "Feature",
  "properties": {
    "gn:admin1_code":"34.0",
    "gn:admin2_code":"224.0",
    "gn:asciiname":"Babupur",
    "gn:country_code":"IN",
    "gn:dem":61,
    "gn:feature_class":"P",
    "gn:feature_code":"PPL",
    "gn:name":"B\u0101bupur",
    "gn:population":0,
    "gn:timezone":"Asia/Kolkata",
    "iso:country":"IN",
    "ks:ks_alt_nam":"B\u0101bupur",
    "ks:ks_name":"Babupur",
    "ks:ks_pop":903,
    "ks:ks_type":"VILLAGE",
    "ks:ks_uagg_main":0,
    "name:ara_x_preferred":[
        "\u0628\u0627\u0628\u0648\u0628\u0648\u0631"
    ],
    "name:ben_bn_x_preferred":[
        "\u09ac\u09be\u09ac\u09c1\u09aa\u09c1\u09b0"
    ],
    "name:ben_in_x_preferred":[
        "\u09ac\u09be\u09ac\u09c1\u09aa\u09c1\u09b0"
    ],
    "name:eng_x_preferred":[
        "Babupur"
    ],
    "name:eng_x_variant":[
        "B\u0101bupur"
    ],
    "name:guj_x_preferred":[
        "\u0aac\u0abe\u0aaa\u0ac1\u0aa8\u0a97\u0ab0"
    ],
    "name:hin_x_preferred":[
        "\u092c\u093e\u092c\u0942\u092a\u0941\u0930"
    ],
    "name:kan_x_preferred":[
        "\u0cac\u0cbe\u0cac\u0cc1\u0caa\u0cc1\u0cb0"
    ],
    "name:mal_x_preferred":[
        "\u0d2c\u0d3e\u0d2c\u0d41\u0d2a\u0d42\u0d7c"
    ],
    "name:mar_x_preferred":[
        "\u092c\u093e\u092a\u0941\u092a\u0942\u0930"
    ],
    "name:pan_x_preferred":[
        "\u0a2c\u0a3e\u0a2c\u0a42\u0a2a\u0a41\u0a30"
    ],
    "name:tam_x_preferred":[
        "\u0baa\u0bbe\u0baa\u0bc1\u0baa\u0bcd\u0baa\u0bc2\u0bb0\u0bcd"
    ],
    "name:tel_x_preferred":[
        "\u0c2c\u0c3e\u0c2c\u0c41\u0c2a\u0c42\u0c30\u0c4d"
    ],
    "name:urd_x_preferred":[
        "\u0628\u0627\u0628\u0648 \u067e\u0648\u0631"
    ],
    "wof:name":"Babupur",
    "wof:placetype":"neighbourhood",
    "wof:population":903
},
  "geometry": {"coordinates":[87.380256,25.223516],"type":"Point"}
}