{
  "type": "Feature",
  "properties": {
    "iso:country":"IN",
    "ks:ks_name":"Palpurwa",
    "ks:ks_pop":274,
    "ks:ks_type":"HABITATION",
    "ks:ks_uagg_main":0,
    "name:eng_x_preferred":[
        "Palpurwa"
    ],
    "wof:name":"Palpurwa",
    "wof:placetype":"neighbourhood",
    "wof:population":274
},
  "geometry": {"coordinates":[79.688238,27.039913],"type":"Point"}
}