{
  "type": "Feature",
  "properties": {
    "gn:admin1_code":"35.0",
    "gn:admin2_code":"421.0",
    "gn:asciiname":"Khurdpura",
    "gn:country_code":"IN",
    "gn:dem":175,
    "gn:feature_class":"P",
    "gn:feature_code":"PPL",
    "gn:name":"Khurdpura",
    "gn:population":0,
    "gn:timezone":"Asia/Kolkata",
    "iso:country":"IN",
    "name:eng_x_preferred":[
        "Khurdpura"
    ],
    "wof:name":"Khurdpura",
    "wof:placetype":"locality"
},
  "geometry": {"coordinates":[78.34121999999998,26.28208],"type":"Point"}
}