{
  "type": "Feature",
  "properties": {
    "iso:country":"IN",
    "ks:ks_name":"Khuntiya",
    "ks:ks_pop":400,
    "ks:ks_type":"VILLAGE",
    "name:eng_x_preferred":[
        "Khuntiya"
    ],
    "wof:name":"Khuntiya",
    "wof:placetype":"locality",
    "wof:population":400
},
  "geometry": {"coordinates":[73.639639,22.304861],"type":"Point"}
}