{
  "type": "Feature",
  "properties": {
    "iso:country":"IN",
    "ks:ks_name":"Ahamadpur",
    "ks:ks_pop":0,
    "ks:ks_type":"VILLAGE",
    "name:eng_x_preferred":[
        "Ahamadpur"
    ],
    "wof:name":"Ahamadpur",
    "wof:placetype":"locality",
    "wof:population":0
},
  "geometry": {"coordinates":[83.043648,25.143189],"type":"Point"}
}