{
  "type": "Feature",
  "properties": {
    "iso:country":"IN",
    "ks:ks_name":"Chhedi Bigha",
    "ks:ks_pop":286,
    "ks:ks_type":"HABITATION",
    "name:eng_x_preferred":[
        "Chhedi Bigha"
    ],
    "wof:name":"Chhedi Bigha",
    "wof:placetype":"locality",
    "wof:population":286
},
  "geometry": {"coordinates":[84.715479,24.875139],"type":"Point"}
}