{
  "type": "Feature",
  "properties": {
    "gn:admin1_code":"23.0",
    "gn:admin2_code":"35.0",
    "gn:asciiname":"Phul Prara",
    "gn:country_code":"IN",
    "gn:dem":313,
    "gn:feature_class":"P",
    "gn:feature_code":"PPL",
    "gn:name":"Phul Pr\u0101ra",
    "gn:population":0,
    "gn:timezone":"Asia/Kolkata",
    "iso:country":"IN",
    "wof:name":"Phul Prara",
    "wof:placetype":"locality"
},
  "geometry": {"coordinates":[75.57231999999998,32.30058],"type":"Point"}
}