{
  "type": "Feature",
  "properties": {
    "iso:country":"IN",
    "ks:ks_name":"Baman Para",
    "ks:ks_pop":111,
    "ks:ks_type":"HABITATION",
    "name:eng_x_preferred":[
        "Baman Para"
    ],
    "wof:name":"Baman Para",
    "wof:placetype":"locality",
    "wof:population":111
},
  "geometry": {"coordinates":[81.75639700000001,19.259504],"type":"Point"}
}