{
  "type": "Feature",
  "properties": {
    "iso:country":"IN",
    "ks:ks_name":"Khaspara",
    "ks:ks_pop":1129,
    "ks:ks_type":"HABITATION",
    "name:eng_x_preferred":[
        "Khaspara"
    ],
    "wof:name":"Khaspara",
    "wof:placetype":"locality",
    "wof:population":1129
},
  "geometry": {"coordinates":[81.816993,19.434049],"type":"Point"}
}