{
  "type": "Feature",
  "properties": {
    "iso:country":"IN",
    "ks:ks_name":"Waladgaon",
    "ks:ks_pop":2782,
    "ks:ks_type":"VILLAGE",
    "ks:ks_uagg_main":0,
    "name:eng_x_preferred":[
        "Waladgaon"
    ],
    "wof:name":"Waladgaon",
    "wof:placetype":"neighbourhood",
    "wof:population":2782
},
  "geometry": {"coordinates":[75.255014,19.831923],"type":"Point"}
}