{
  "type": "Feature",
  "properties": {
    "iso:country":"IN",
    "ks:ks_name":"Jhalora Hemawas",
    "ks:ks_pop":394,
    "ks:ks_type":"HABITATION",
    "name:eng_x_preferred":[
        "Jhalora Hemawas"
    ],
    "wof:name":"Jhalora Hemawas",
    "wof:placetype":"locality",
    "wof:population":394
},
  "geometry": {"coordinates":[71.804647,26.539267],"type":"Point"}
}