{
  "type": "Feature",
  "properties": {
    "iso:country":"IN",
    "ks:ks_name":"Kuravapalle",
    "ks:ks_pop":354,
    "ks:ks_type":"HABITATION",
    "name:eng_x_preferred":[
        "Kuravapalle"
    ],
    "wof:name":"Kuravapalle",
    "wof:placetype":"locality",
    "wof:population":354
},
  "geometry": {"coordinates":[78.83885100000001,13.489841],"type":"Point"}
}