{
  "type": "Feature",
  "properties": {
    "gn:admin1_code":"11.0",
    "gn:admin2_code":"26.0",
    "gn:asciiname":"Narku",
    "gn:country_code":"IN",
    "gn:dem":2429,
    "gn:feature_class":"P",
    "gn:feature_code":"PPL",
    "gn:name":"N\u0101rku",
    "gn:population":0,
    "gn:timezone":"Asia/Kolkata",
    "iso:country":"IN",
    "name:ceb_x_preferred":[
        "Narku"
    ],
    "name:fra_x_preferred":[
        "Narku"
    ],
    "name:mai_x_preferred":[
        "\u0928\u0930\u094d\u0915\u0941"
    ],
    "name:msa_x_preferred":[
        "Narku"
    ],
    "name:nep_x_preferred":[
        "\u0928\u0930\u094d\u0915\u0941"
    ],
    "name:pol_x_preferred":[
        "Narku"
    ],
    "wof:name":"Narku",
    "wof:placetype":"locality"
},
  "geometry": {"coordinates":[77.66622,31.51769],"type":"Point"}
}