{
  "type": "Feature",
  "properties": {
    "iso:country":"IN",
    "ks:ks_alt_nam":"Kambala kunta thanda",
    "ks:ks_name":"Kambala Kunta Thanda",
    "ks:ks_pop":177,
    "ks:ks_type":"HABITATION",
    "name:eng_x_preferred":[
        "Kambala Kunta Thanda"
    ],
    "wof:name":"Kambala Kunta Thanda",
    "wof:placetype":"locality",
    "wof:population":177
},
  "geometry": {"coordinates":[79.68422,17.767201],"type":"Point"}
}