{
  "type": "Feature",
  "properties": {
    "iso:country":"IN",
    "ks:ks_name":"Nilegodipara",
    "ks:ks_pop":216,
    "ks:ks_type":"HABITATION",
    "name:eng_x_preferred":[
        "Nilegodipara"
    ],
    "wof:name":"Nilegodipara",
    "wof:placetype":"locality",
    "wof:population":216
},
  "geometry": {"coordinates":[81.693225,18.905148],"type":"Point"}
}