{
  "type": "Feature",
  "properties": {
    "iso:country":"IN",
    "ks:ks_name":"Hunda Dev",
    "ks:ks_pop":493,
    "ks:ks_type":"HABITATION",
    "name:eng_x_preferred":[
        "Hunda Dev"
    ],
    "wof:name":"Hunda Dev",
    "wof:placetype":"locality",
    "wof:population":493
},
  "geometry": {"coordinates":[80.087424,26.311669],"type":"Point"}
}