{
  "type": "Feature",
  "properties": {
    "iso:country":"IN",
    "ks:ks_name":"Nirisha",
    "ks:ks_pop":793,
    "ks:ks_type":"VILLAGE",
    "name:eng_x_preferred":[
        "Nirisha"
    ],
    "wof:name":"Nirisha",
    "wof:placetype":"locality",
    "wof:population":793
},
  "geometry": {"coordinates":[87.663957,23.858092],"type":"Point"}
}