{
  "type": "Feature",
  "properties": {
    "iso:country":"IN",
    "name:eng_x_preferred":[
        "Mahalakshmi"
    ],
    "name:eng_x_variant":[
        "Mahalaxmi",
        "Mahaluxmi"
    ],
    "name:unk_x_variant":[
        "Mahalaxmi",
        "Mahalakshmi"
    ],
    "qs:gn_adm0_cc":"IN",
    "qs:gn_fcode":"PPLX",
    "qs:gn_local":1275339,
    "qs:gn_namadm1":"16",
    "qs:gn_name":"Mahalakshmi",
    "qs:local_max":3819,
    "qs:local_sum":50908,
    "qs:localhoods":70,
    "qs:name":"Mahalakshmi",
    "qs:name_adm0":"India",
    "qs:name_adm1":"Maharashtra",
    "qs:name_adm2":"Mumbai",
    "qs:name_local":"Mumbai",
    "qs:photo_max":310,
    "qs:photo_sum":2048,
    "qs:placetype":"Suburb",
    "qs:quad_count":57,
    "qs:woe_adm0":23424848,
    "qs:woe_adm1":2345750,
    "qs:woe_adm2":12586539,
    "qs:woe_lau":0,
    "qs:woe_local":2295411,
    "qs:woe_ver":"7.10.0",
    "wof:lang":[
        "eng"
    ],
    "wof:name":"Mahalakshmi",
    "wof:placetype":"neighbourhood"
},
  "geometry": {"coordinates":[72.81818199999999,18.989385],"type":"Point"}
}