{
  "type": "Feature",
  "properties": {
    "gn:admin1_code":"35.0",
    "gn:admin2_code":"453.0",
    "gn:asciiname":"Chhindgaontola",
    "gn:country_code":"IN",
    "gn:dem":659,
    "gn:feature_class":"P",
    "gn:feature_code":"PPL",
    "gn:name":"Chhindgaontol\u0101",
    "gn:population":0,
    "gn:timezone":"Asia/Kolkata",
    "iso:country":"IN",
    "wof:name":"Chhindgaontola",
    "wof:placetype":"locality"
},
  "geometry": {"coordinates":[80.93968000000002,22.9988],"type":"Point"}
}