{
  "type": "Feature",
  "properties": {
    "gn:admin1_code":"35.0",
    "gn:admin2_code":"453.0",
    "gn:asciiname":"Chhindgaontola",
    "gn:country_code":"IN",
    "gn:dem":659,
    "gn:feature_class":"P",
    "gn:feature_code":"PPL",
    "gn:name":"Chhindgaontol\u0101",
    "gn:population":0,
    "gn:timezone":"Asia/Kolkata",
    "iso:country":"IN",
    "ks:ks_name":"Chhindgaon Mal.",
    "ks:ks_pop":603,
    "ks:ks_type":"VILLAGE",
    "name:eng_x_preferred":[
        "Chhindgaon Mal."
    ],
    "name:eng_x_variant":[
        "Chhindgaontola"
    ],
    "wof:name":"Chhindgaon Mal.",
    "wof:placetype":"locality",
    "wof:population":603
},
  "geometry": {"coordinates":[80.92504599999999,23.004433],"type":"Point"}
}