{
  "type": "Feature",
  "properties": {
    "iso:country":"IN",
    "ks:ks_name":"Obaraha",
    "ks:ks_pop":1224,
    "ks:ks_type":"HABITATION",
    "name:eng_x_preferred":[
        "Obaraha"
    ],
    "wof:name":"Obaraha",
    "wof:placetype":"locality",
    "wof:population":1224
},
  "geometry": {"coordinates":[81.729929,24.347437],"type":"Point"}
}