{
  "type": "Feature",
  "properties": {
    "iso:country":"IN",
    "ks:ks_name":"Podapadar",
    "ks:ks_pop":139,
    "ks:ks_type":"HABITATION",
    "name:eng_x_preferred":[
        "Podapadar"
    ],
    "wof:name":"Podapadar",
    "wof:placetype":"locality",
    "wof:population":139
},
  "geometry": {"coordinates":[82.185919,18.728111],"type":"Point"}
}