{
  "type": "Feature",
  "properties": {
    "gn:admin1_code":"36",
    "gn:admin2_code":"180.0",
    "gn:asciiname":"Raghunath Singh",
    "gn:country_code":"IN",
    "gn:dem":119,
    "gn:feature_class":"P",
    "gn:feature_code":"PPL",
    "gn:name":"Raghun\u0101th Singh",
    "gn:population":0,
    "gn:timezone":"Asia/Kolkata",
    "iso:country":"IN",
    "name:hin_x_preferred":[
        "\u0930\u0918\u0941\u0928\u093e\u0925 \u0938\u093f\u0902\u0939"
    ],
    "wof:name":"Raghunath Singh",
    "wof:placetype":"neighbourhood"
},
  "geometry": {"coordinates":[81.54084,27.62801],"type":"Point"}
}