{
  "type": "Feature",
  "properties": {
    "iso:country":"IN",
    "ks:ks_name":"Periyakulathupatti Keelur",
    "ks:ks_pop":1024,
    "ks:ks_type":"HABITATION",
    "name:eng_x_preferred":[
        "Periyakulathupatti Keelur"
    ],
    "wof:name":"Periyakulathupatti Keelur",
    "wof:placetype":"locality",
    "wof:population":1024
},
  "geometry": {"coordinates":[77.764049,9.530439],"type":"Point"}
}