{
  "type": "Feature",
  "properties": {
    "iso:country":"IN",
    "ks:ks_name":"Satgechhe",
    "ks:ks_pop":672,
    "ks:ks_type":"VILLAGE",
    "name:eng_x_preferred":[
        "Satgechhe"
    ],
    "wof:name":"Satgechhe",
    "wof:placetype":"locality",
    "wof:population":672
},
  "geometry": {"coordinates":[87.433577,23.194268],"type":"Point"}
}