{
  "type": "Feature",
  "properties": {
    "iso:country":"IN",
    "ks:ks_name":"Bahar Chura",
    "ks:ks_pop":638,
    "ks:ks_type":"VILLAGE",
    "name:eng_x_preferred":[
        "Bahar Chura"
    ],
    "wof:name":"Bahar Chura",
    "wof:placetype":"locality",
    "wof:population":638
},
  "geometry": {"coordinates":[83.45090500000001,23.914062],"type":"Point"}
}