{
  "type": "Feature",
  "properties": {
    "iso:country":"IN",
    "ks:ks_name":"Fattupur Purwa",
    "ks:ks_pop":651,
    "ks:ks_type":"HABITATION",
    "name:eng_x_preferred":[
        "Fattupur Purwa"
    ],
    "wof:name":"Fattupur Purwa",
    "wof:placetype":"locality",
    "wof:population":651
},
  "geometry": {"coordinates":[81.978362,27.508188],"type":"Point"}
}