{
  "type": "Feature",
  "properties": {
    "gn:admin1_code":"35",
    "gn:admin2_code":"466.0",
    "gn:asciiname":"Vikrampur",
    "gn:country_code":"IN",
    "gn:dem":443,
    "gn:feature_class":"P",
    "gn:feature_code":"PPL",
    "gn:name":"Vikrampur",
    "gn:population":0,
    "gn:timezone":"Asia/Kolkata",
    "iso:country":"IN",
    "ks:ks_name":"Vikarampur",
    "ks:ks_pop":517,
    "ks:ks_type":"VILLAGE",
    "name:eng_x_preferred":[
        "Vikarampur"
    ],
    "name:eng_x_variant":[
        "Vikrampur"
    ],
    "wof:name":"Vikarampur",
    "wof:placetype":"locality",
    "wof:population":517
},
  "geometry": {"coordinates":[77.12372000000001,21.926233],"type":"Point"}
}