{
  "type": "Feature",
  "properties": {
    "iso:country":"IN",
    "ks:ks_name":"Eka Bhatiyan",
    "ks:ks_pop":1527,
    "ks:ks_type":"HABITATION",
    "name:eng_x_preferred":[
        "Eka Bhatiyan"
    ],
    "wof:name":"Eka Bhatiyan",
    "wof:placetype":"locality",
    "wof:population":1527
},
  "geometry": {"coordinates":[72.341419,27.100969],"type":"Point"}
}