{
  "type": "Feature",
  "properties": {
    "iso:country":"IN",
    "ks:ks_alt_nam":"BABA NAGAR",
    "ks:ks_name":"Baba Nagar",
    "ks:ks_pop":53,
    "ks:ks_type":"HABITATION",
    "name:eng_x_preferred":[
        "Baba Nagar"
    ],
    "wof:name":"Baba Nagar",
    "wof:placetype":"locality",
    "wof:population":53
},
  "geometry": {"coordinates":[75.53227,17.045063],"type":"Point"}
}