{
  "type": "Feature",
  "properties": {
    "iso:country":"IN",
    "ks:ks_name":"Batalada",
    "ks:ks_pop":200,
    "ks:ks_type":"HABITATION",
    "name:eng_x_preferred":[
        "Batalada"
    ],
    "wof:name":"Batalada",
    "wof:placetype":"locality",
    "wof:population":200
},
  "geometry": {"coordinates":[76.73609399999999,11.48674],"type":"Point"}
}