{
  "type": "Feature",
  "properties": {
    "gn:admin1_code":"23.0",
    "gn:admin2_code":"41.0",
    "gn:asciiname":"Sange",
    "gn:country_code":"IN",
    "gn:dem":258,
    "gn:feature_class":"P",
    "gn:feature_code":"PPL",
    "gn:name":"Sange",
    "gn:population":0,
    "gn:timezone":"Asia/Kolkata",
    "iso:country":"IN",
    "name:ceb_x_preferred":[
        "Sange"
    ],
    "name:deu_x_preferred":[
        "Sange"
    ],
    "name:fra_x_preferred":[
        "Sange"
    ],
    "name:swe_x_preferred":[
        "Sange"
    ],
    "wof:name":"Sange",
    "wof:placetype":"locality"
},
  "geometry": {"coordinates":[76.11254,30.88909],"type":"Point"}
}