{
  "type": "Feature",
  "properties": {
    "gn:admin1_code":"03",
    "gn:admin2_code":"315.0",
    "gn:asciiname":"Thingje",
    "gn:country_code":"IN",
    "gn:dem":1288,
    "gn:feature_class":"P",
    "gn:feature_code":"PPL",
    "gn:name":"Thingje",
    "gn:population":0,
    "gn:timezone":"Asia/Kolkata",
    "iso:country":"IN",
    "wof:name":"Thingje",
    "wof:placetype":"locality"
},
  "geometry": {"coordinates":[93.37043,25.26321],"type":"Point"}
}