{
  "type": "Feature",
  "properties": {
    "iso:country":"IN",
    "ks:ks_alt_nam":"GANHARIYA",
    "ks:ks_name":"Ganhariya",
    "ks:ks_pop":592,
    "ks:ks_type":"HABITATION",
    "name:eng_x_preferred":[
        "Ganhariya"
    ],
    "wof:name":"Ganhariya",
    "wof:placetype":"locality",
    "wof:population":592
},
  "geometry": {"coordinates":[84.08346,24.6225],"type":"Point"}
}