{
  "type": "Feature",
  "properties": {
    "gn:admin1_code":"16.0",
    "gn:admin2_code":"523.0",
    "gn:asciiname":"Shindewadi",
    "gn:country_code":"IN",
    "gn:dem":442,
    "gn:feature_class":"P",
    "gn:feature_code":"PPL",
    "gn:name":"Shindew\u0101di",
    "gn:population":0,
    "gn:timezone":"Asia/Kolkata",
    "iso:country":"IN",
    "name:ara_x_preferred":[
        "\u0634\u064a\u0646\u062f\u0641\u0627\u062f\u064a"
    ],
    "name:ben_bn_x_preferred":[
        "\u09b6\u09bf\u09a8\u09cd\u09a1\u09c7\u0993\u09df\u09be\u09dc\u09bf"
    ],
    "name:ben_in_x_preferred":[
        "\u09b6\u09bf\u09a8\u09cd\u09a1\u09c7\u0993\u09df\u09be\u09dc\u09bf"
    ],
    "name:guj_x_preferred":[
        "\u0ab6\u0abf\u0a82\u0aa6\u0ac7\u0ab5\u0abe\u0aa1\u0ac0"
    ],
    "name:hin_x_preferred":[
        "\u0936\u093f\u0902\u0926\u0935\u093e\u095c\u0940"
    ],
    "name:kan_x_preferred":[
        "\u0cb6\u0cbf\u0c82\u0ca6\u0cc6\u0cb5\u0cbe\u0ca1\u0cbf"
    ],
    "name:mal_x_preferred":[
        "\u0d37\u0d3f\u0d7b\u0d21\u0d47\u0d35\u0d3e\u0d1f\u0d3f"
    ],
    "name:mar_x_preferred":[
        "\u0936\u093f\u0902\u0926\u0947\u0935\u093e\u0921\u0940"
    ],
    "name:pan_x_preferred":[
        "\u0a36\u0a3f\u0a70\u0a26\u0a47\u0a35\u0a3e\u0a5c\u0a40"
    ],
    "name:tam_x_preferred":[
        "\u0bb7\u0bbf\u0ba9\u0bcd\u0b9f\u0bc6\u0bb5\u0bbe\u0b9f\u0bbf"
    ],
    "name:tel_x_preferred":[
        "\u0c37\u0c3f\u0c02\u0c26\u0c46\u0c35\u0c3e\u0c21\u0c3f"
    ],
    "name:urd_x_preferred":[
        "\u0634\u0646\u062f\u06cc\u0648\u0627\u0691\u06cc"
    ],
    "wof:name":"Shindewadi",
    "wof:placetype":"locality"
},
  "geometry": {"coordinates":[76.20716999999998,19.0556],"type":"Point"}
}