{
  "type": "Feature",
  "properties": {
    "iso:country":"IN",
    "ks:ks_name":"Pardhipada",
    "ks:ks_pop":334,
    "ks:ks_type":"HABITATION",
    "name:eng_x_preferred":[
        "Pardhipada"
    ],
    "wof:name":"Pardhipada",
    "wof:placetype":"locality",
    "wof:population":334
},
  "geometry": {"coordinates":[73.04984899999999,19.769331],"type":"Point"}
}