{
  "type": "Feature",
  "properties": {
    "iso:country":"IN",
    "ks:ks_alt_nam":"Khapi\u0101",
    "ks:ks_name":"Khapia",
    "ks:ks_pop":851,
    "ks:ks_type":"VILLAGE",
    "ks:ks_uagg_main":0,
    "name:eng_x_preferred":[
        "Khapia"
    ],
    "name:eng_x_variant":[
        "Khapi\u0101"
    ],
    "wof:name":"Khapia",
    "wof:placetype":"neighbourhood",
    "wof:population":851
},
  "geometry": {"coordinates":[84.94027199999999,24.036487],"type":"Point"}
}