{
  "type": "Feature",
  "properties": {
    "iso:country":"IN",
    "ks:ks_name":"Doman Chhapra",
    "ks:ks_pop":200,
    "ks:ks_type":"HABITATION",
    "name:eng_x_preferred":[
        "Doman Chhapra"
    ],
    "wof:name":"Doman Chhapra",
    "wof:placetype":"locality",
    "wof:population":200
},
  "geometry": {"coordinates":[83.824894,26.79714],"type":"Point"}
}