{
  "type": "Feature",
  "properties": {
    "gn:admin1_code":"21.0",
    "gn:admin2_code":"399.0",
    "gn:asciiname":"Antamguda",
    "gn:country_code":"IN",
    "gn:dem":770,
    "gn:feature_class":"P",
    "gn:feature_code":"PPL",
    "gn:name":"Antamg\u016bda",
    "gn:population":0,
    "gn:timezone":"Asia/Kolkata",
    "iso:country":"IN",
    "wof:name":"Antamguda",
    "wof:placetype":"locality"
},
  "geometry": {"coordinates":[82.32788000000002,18.4858],"type":"Point"}
}