{
  "type": "Feature",
  "properties": {
    "gn:admin1_code":"19.0",
    "gn:admin2_code":"565.0",
    "gn:asciiname":"Talakal",
    "gn:country_code":"IN",
    "gn:dem":613,
    "gn:feature_class":"P",
    "gn:feature_code":"PPL",
    "gn:name":"Talakal",
    "gn:population":0,
    "gn:timezone":"Asia/Kolkata",
    "iso:country":"IN",
    "wof:name":"Talakal",
    "wof:placetype":"neighbourhood"
},
  "geometry": {"coordinates":[76.04398,14.93815],"type":"Point"}
}