{
  "type": "Feature",
  "properties": {
    "iso:country":"IN",
    "ks:ks_name":"Karubaru",
    "ks:ks_pop":90,
    "ks:ks_type":"VILLAGE",
    "name:eng_x_preferred":[
        "Karubaru"
    ],
    "wof:name":"Karubaru",
    "wof:placetype":"locality",
    "wof:population":90
},
  "geometry": {"coordinates":[83.452995,19.93482],"type":"Point"}
}