{
  "type": "Feature",
  "properties": {
    "gn:admin1_code":"40",
    "gn:admin2_code":"541.0",
    "gn:asciiname":"Vairadhari Annavaram",
    "gn:country_code":"IN",
    "gn:dem":53,
    "gn:feature_class":"P",
    "gn:feature_code":"PPL",
    "gn:name":"Vairadh\u0101ri Ann\u0101varam",
    "gn:population":0,
    "gn:timezone":"Asia/Kolkata",
    "iso:country":"IN",
    "wof:name":"Vairadhari Annavaram",
    "wof:placetype":"locality"
},
  "geometry": {"coordinates":[80.39010999999998,16.85734],"type":"Point"}
}