{
  "type": "Feature",
  "properties": {
    "iso:country":"IN",
    "ks:ks_name":"Patterpuram",
    "ks:ks_pop":570,
    "ks:ks_type":"HABITATION",
    "name:eng_x_preferred":[
        "Patterpuram"
    ],
    "wof:name":"Patterpuram",
    "wof:placetype":"locality",
    "wof:population":570
},
  "geometry": {"coordinates":[77.67719,8.446993],"type":"Point"}
}