{
  "type": "Feature",
  "properties": {
    "iso:country":"IN",
    "ks:ks_name":"Dhulewadi",
    "ks:ks_pop":230,
    "ks:ks_type":"HABITATION",
    "name:eng_x_preferred":[
        "Dhulewadi"
    ],
    "wof:name":"Dhulewadi",
    "wof:placetype":"locality",
    "wof:population":230
},
  "geometry": {"coordinates":[73.369502,18.951681],"type":"Point"}
}