{
  "type": "Feature",
  "properties": {
    "gn:admin1_code":"21",
    "gn:admin2_code":"396.0",
    "gn:asciiname":"Pokkirigam",
    "gn:country_code":"IN",
    "gn:dem":399,
    "gn:feature_class":"P",
    "gn:feature_code":"PPL",
    "gn:name":"Pokkirig\u0101m",
    "gn:population":0,
    "gn:timezone":"Asia/Kolkata",
    "iso:country":"IN",
    "ks:ks_name":"Pakhirigam",
    "ks:ks_pop":144,
    "ks:ks_type":"VILLAGE",
    "name:eng_x_preferred":[
        "Pakhirigam"
    ],
    "name:eng_x_variant":[
        "Pokkirigam"
    ],
    "wof:name":"Pakhirigam",
    "wof:placetype":"locality",
    "wof:population":144
},
  "geometry": {"coordinates":[83.42912699999999,19.85867],"type":"Point"}
}