{
  "type": "Feature",
  "properties": {
    "iso:country":"IN",
    "ks:ks_name":"Dhingani",
    "ks:ks_pop":11,
    "ks:ks_type":"HABITATION",
    "name:eng_x_preferred":[
        "Dhingani"
    ],
    "wof:name":"Dhingani",
    "wof:placetype":"locality",
    "wof:population":11
},
  "geometry": {"coordinates":[78.92593599999999,30.212893],"type":"Point"}
}