{
  "type": "Feature",
  "properties": {
    "iso:country":"IN",
    "ks:ks_alt_nam":"tokepada",
    "ks:ks_name":"Tokepada",
    "ks:ks_pop":159,
    "ks:ks_type":"HABITATION",
    "name:eng_x_preferred":[
        "Tokepada"
    ],
    "wof:name":"Tokepada",
    "wof:placetype":"locality",
    "wof:population":159
},
  "geometry": {"coordinates":[72.723697,19.680767],"type":"Point"}
}