{
  "type": "Feature",
  "properties": {
    "iso:country":"IN",
    "ks:ks_name":"Hariharpur",
    "ks:ks_pop":174,
    "ks:ks_type":"VILLAGE",
    "name:eng_x_preferred":[
        "Hariharpur"
    ],
    "wof:name":"Hariharpur",
    "wof:placetype":"locality",
    "wof:population":174
},
  "geometry": {"coordinates":[86.27251,24.269878],"type":"Point"}
}