{
  "type": "Feature",
  "properties": {
    "gn:admin1_code":"2.0",
    "gn:admin2_code":"546.0",
    "gn:asciiname":"Bodugudem",
    "gn:country_code":"IN",
    "gn:dem":140,
    "gn:feature_class":"P",
    "gn:feature_code":"PPL",
    "gn:name":"Bodug\u016bdem",
    "gn:population":0,
    "gn:timezone":"Asia/Kolkata",
    "iso:country":"IN",
    "ks:ks_name":"Bodigudem",
    "ks:ks_pop":111,
    "ks:ks_type":"HABITATION",
    "name:eng_x_preferred":[
        "Bodigudem"
    ],
    "name:eng_x_variant":[
        "Bodugudem"
    ],
    "wof:name":"Bodigudem",
    "wof:placetype":"locality",
    "wof:population":111
},
  "geometry": {"coordinates":[81.377309,17.208974],"type":"Point"}
}