{
  "type": "Feature",
  "properties": {
    "iso:country":"IN",
    "ks:ks_alt_nam":"S\u0101b\u0101pur",
    "ks:ks_name":"Sabapur",
    "ks:ks_type":"VILLAGE",
    "name:eng_x_preferred":[
        "Sabapur"
    ],
    "name:eng_x_variant":[
        "S\u0101b\u0101pur"
    ],
    "wof:name":"Sabapur",
    "wof:placetype":"locality"
},
  "geometry": {"coordinates":[78.189652,21.164646],"type":"Point"}
}