{
  "type": "Feature",
  "properties": {
    "iso:country":"IN",
    "ks:ks_alt_nam":"CHOUTHAIYA",
    "ks:ks_name":"Chouthaiya",
    "ks:ks_pop":59,
    "ks:ks_type":"HABITATION",
    "name:eng_x_preferred":[
        "Chouthaiya"
    ],
    "wof:name":"Chouthaiya",
    "wof:placetype":"locality",
    "wof:population":59
},
  "geometry": {"coordinates":[82.50952700000001,25.98404],"type":"Point"}
}