{
  "type": "Feature",
  "properties": {
    "iso:country":"IN",
    "ks:ks_name":"Suklivasan",
    "ks:ks_pop":506,
    "ks:ks_type":"VILLAGE",
    "name:eng_x_preferred":[
        "Suklivasan"
    ],
    "wof:name":"Suklivasan",
    "wof:placetype":"locality",
    "wof:population":506
},
  "geometry": {"coordinates":[73.815555,21.948006],"type":"Point"}
}