{
  "type": "Feature",
  "properties": {
    "iso:country":"IN",
    "ks:ks_name":"7 SKM-B",
    "ks:ks_pop":70,
    "ks:ks_type":"VILLAGE",
    "name:eng_x_preferred":[
        "7 SKM-B"
    ],
    "wof:name":"7 SKM-B",
    "wof:placetype":"locality",
    "wof:population":70
},
  "geometry": {"coordinates":[72.85866799999999,28.970916],"type":"Point"}
}