{
  "type": "Feature",
  "properties": {
    "iso:country":"IN",
    "ks:ks_alt_nam":"nirathukadavu",
    "ks:ks_name":"Nirathukadavu",
    "ks:ks_pop":448,
    "ks:ks_type":"HABITATION",
    "name:eng_x_preferred":[
        "Nirathukadavu"
    ],
    "wof:name":"Nirathukadavu",
    "wof:placetype":"locality",
    "wof:population":448
},
  "geometry": {"coordinates":[75.763949,11.610415],"type":"Point"}
}