{
  "type": "Feature",
  "properties": {
    "gn:admin1_code":"19.0",
    "gn:admin2_code":"572",
    "gn:asciiname":"Kudlu Gate Hosur Road",
    "gn:country_code":"IN",
    "gn:dem":912,
    "gn:feature_class":"P",
    "gn:feature_code":"PPL",
    "gn:name":"Kudlu Gate Hosur Road",
    "gn:population":0,
    "gn:timezone":"Asia/Kolkata",
    "iso:country":"IN",
    "wof:name":"Kudlu Gate Hosur Road",
    "wof:placetype":"locality"
},
  "geometry": {"coordinates":[77.64115,12.88879],"type":"Point"}
}