{
  "type": "Feature",
  "properties": {
    "iso:country":"IN",
    "ks:ks_name":"Nagla Duck",
    "ks:ks_pop":782,
    "ks:ks_type":"HABITATION",
    "ks:ks_uagg_main":0,
    "name:eng_x_preferred":[
        "Nagla Duck"
    ],
    "wof:name":"Nagla Duck",
    "wof:placetype":"neighbourhood",
    "wof:population":782
},
  "geometry": {"coordinates":[78.494947,27.24002],"type":"Point"}
}