{
  "type": "Feature",
  "properties": {
    "iso:country":"IN",
    "ks:ks_name":"Bela Matiya",
    "ks:ks_pop":85,
    "ks:ks_type":"HABITATION",
    "name:eng_x_preferred":[
        "Bela Matiya"
    ],
    "wof:name":"Bela Matiya",
    "wof:placetype":"locality",
    "wof:population":85
},
  "geometry": {"coordinates":[86.325928,25.011041],"type":"Point"}
}