{
  "type": "Feature",
  "properties": {
    "iso:country":"IN",
    "ks:ks_name":"Phillobari Na Gaon Forest Vill",
    "ks:ks_pop":1105,
    "ks:ks_type":"HABITATION",
    "name:eng_x_preferred":[
        "Phillobari Na Gaon Forest Vill"
    ],
    "wof:name":"Phillobari Na Gaon Forest Vill",
    "wof:placetype":"locality",
    "wof:population":1105
},
  "geometry": {"coordinates":[95.758932,27.564582],"type":"Point"}
}