{
  "type": "Feature",
  "properties": {
    "iso:country":"IN",
    "ks:ks_alt_nam":"vanoshiwadi",
    "ks:ks_name":"Vanoshiwadi",
    "ks:ks_pop":562,
    "ks:ks_type":"HABITATION",
    "name:eng_x_preferred":[
        "Vanoshiwadi"
    ],
    "wof:name":"Vanoshiwadi",
    "wof:placetype":"locality",
    "wof:population":562
},
  "geometry": {"coordinates":[73.988972,15.726806],"type":"Point"}
}