{
  "type": "Feature",
  "properties": {
    "iso:country":"IN",
    "ks:ks_name":"Katan",
    "ks:ks_pop":116,
    "ks:ks_type":"HABITATION",
    "name:eng_x_preferred":[
        "Katan"
    ],
    "wof:name":"Katan",
    "wof:placetype":"locality",
    "wof:population":116
},
  "geometry": {"coordinates":[81.542125,24.822061],"type":"Point"}
}