{
  "type": "Feature",
  "properties": {
    "gn:admin1_code":"21",
    "gn:admin2_code":"396.0",
    "gn:asciiname":"Panchokodi",
    "gn:country_code":"IN",
    "gn:dem":601,
    "gn:feature_class":"P",
    "gn:feature_code":"PPL",
    "gn:name":"Panchokodi",
    "gn:population":0,
    "gn:timezone":"Asia/Kolkata",
    "iso:country":"IN",
    "ks:ks_name":"Panchakudi",
    "ks:ks_pop":298,
    "ks:ks_type":"VILLAGE",
    "name:eng_x_preferred":[
        "Panchakudi"
    ],
    "name:eng_x_variant":[
        "Panchokodi"
    ],
    "wof:name":"Panchakudi",
    "wof:placetype":"locality",
    "wof:population":298
},
  "geometry": {"coordinates":[83.386233,19.533213],"type":"Point"}
}