{
  "type": "Feature",
  "properties": {
    "gn:admin1_code":"39.0",
    "gn:admin2_code":"57.0",
    "gn:asciiname":"Lamabagar",
    "gn:country_code":"IN",
    "gn:dem":1336,
    "gn:feature_class":"P",
    "gn:feature_code":"PPL",
    "gn:name":"L\u0101m\u0101bagar",
    "gn:population":0,
    "gn:timezone":"Asia/Kolkata",
    "iso:country":"IN",
    "ks:ks_name":"Lam Bagar",
    "ks:ks_pop":730,
    "ks:ks_type":"VILLAGE",
    "name:bih_x_preferred":[
        "\u0932\u093e\u092e\u093e\u092c\u0917\u0930"
    ],
    "name:ceb_x_preferred":[
        "Lamabagar"
    ],
    "name:eng_x_preferred":[
        "Lam Bagar"
    ],
    "name:eng_x_variant":[
        "Lamabagar"
    ],
    "name:mai_x_preferred":[
        "\u0932\u093e\u092e\u093e\u092c\u0917\u0930"
    ],
    "name:msa_x_preferred":[
        "Lamabagar"
    ],
    "name:nep_x_preferred":[
        "\u0932\u093e\u092e\u093e\u092c\u0917\u0930"
    ],
    "name:new_x_preferred":[
        "\u0932\u093e\u092e\u093e\u0935\u0917\u0930"
    ],
    "name:pol_x_preferred":[
        "Lamabagar"
    ],
    "name:urd_x_preferred":[
        "\u0644\u0627\u0645\u0627\u0628\u0627\u063a\u0627\u0631"
    ],
    "wof:name":"Lam Bagar",
    "wof:placetype":"locality",
    "wof:population":730
},
  "geometry": {"coordinates":[79.417974,29.947517],"type":"Point"}
}