{
  "type": "Feature",
  "properties": {
    "gn:admin1_code":"39.0",
    "gn:admin2_code":"57.0",
    "gn:asciiname":"Lamabagar",
    "gn:country_code":"IN",
    "gn:dem":1336,
    "gn:feature_class":"P",
    "gn:feature_code":"PPL",
    "gn:name":"L\u0101m\u0101bagar",
    "gn:population":0,
    "gn:timezone":"Asia/Kolkata",
    "iso:country":"IN",
    "wof:name":"Lamabagar",
    "wof:placetype":"locality"
},
  "geometry": {"coordinates":[79.41981,29.94758],"type":"Point"}
}