{
  "type": "Feature",
  "properties": {
    "gn:admin1_code":"39.0",
    "gn:admin2_code":"57.0",
    "gn:asciiname":"Lamabagar",
    "gn:country_code":"IN",
    "gn:dem":1336,
    "gn:feature_class":"P",
    "gn:feature_code":"PPL",
    "gn:name":"L\u0101m\u0101bagar",
    "gn:population":0,
    "gn:timezone":"Asia/Kolkata",
    "iso:country":"IN",
    "name:bih_x_preferred":[
        "\u0932\u093e\u092e\u093e\u092c\u0917\u0930"
    ],
    "name:ceb_x_preferred":[
        "Lamabagar"
    ],
    "name:mai_x_preferred":[
        "\u0932\u093e\u092e\u093e\u092c\u0917\u0930"
    ],
    "name:msa_x_preferred":[
        "Lamabagar"
    ],
    "name:nep_x_preferred":[
        "\u0932\u093e\u092e\u093e\u092c\u0917\u0930"
    ],
    "name:new_x_preferred":[
        "\u0932\u093e\u092e\u093e\u0935\u0917\u0930"
    ],
    "name:pol_x_preferred":[
        "Lamabagar"
    ],
    "name:urd_x_preferred":[
        "\u0644\u0627\u0645\u0627\u0628\u0627\u063a\u0627\u0631"
    ],
    "wof:name":"Lamabagar",
    "wof:placetype":"locality"
},
  "geometry": {"coordinates":[79.41981,29.94758],"type":"Point"}
}