{
  "type": "Feature",
  "properties": {
    "iso:country":"IN",
    "ks:ks_alt_nam":"pulickakavala",
    "ks:ks_name":"Pulickakavala",
    "ks:ks_pop":301,
    "ks:ks_type":"HABITATION",
    "name:eng_x_preferred":[
        "Pulickakavala"
    ],
    "wof:name":"Pulickakavala",
    "wof:placetype":"locality",
    "wof:population":301
},
  "geometry": {"coordinates":[77.02196600000001,9.929287],"type":"Point"}
}