{
  "type": "Feature",
  "properties": {
    "iso:country":"IN",
    "ks:ks_name":"Rang Kimi Chupa",
    "ks:ks_pop":562,
    "ks:ks_type":"HABITATION",
    "name:eng_x_preferred":[
        "Rang Kimi Chupa"
    ],
    "wof:name":"Rang Kimi Chupa",
    "wof:placetype":"locality",
    "wof:population":562
},
  "geometry": {"coordinates":[91.984802,26.041711],"type":"Point"}
}