{
  "type": "Feature",
  "properties": {
    "gn:admin1_code":"12.0",
    "gn:asciiname":"Khatah",
    "gn:country_code":"IN",
    "gn:dem":332,
    "gn:feature_class":"P",
    "gn:feature_code":"PPL",
    "gn:name":"Khat\u0101h",
    "gn:population":0,
    "gn:timezone":"Asia/Kolkata",
    "iso:country":"IN",
    "name:und_x_variant":[
        "Dal",
        "Khat\u0101h",
        "Khar\u0101h"
    ],
    "wof:name":"Khatah",
    "wof:placetype":"locality"
},
  "geometry": {"coordinates":[74.37158000000002,32.94783],"type":"Point"}
}