{
  "type": "Feature",
  "properties": {
    "gn:admin1_code":"36",
    "gn:admin2_code":"149.0",
    "gn:asciiname":"Dabthara Har Lal",
    "gn:country_code":"IN",
    "gn:dem":180,
    "gn:feature_class":"P",
    "gn:feature_code":"PPL",
    "gn:name":"Dabthar\u0101 Har L\u0101l",
    "gn:population":0,
    "gn:timezone":"Asia/Kolkata",
    "iso:country":"IN",
    "ks:ks_alt_nam":"Dabthar\u0101 Har L\u0101l",
    "ks:ks_name":"Dabthara Har Lal",
    "ks:ks_type":"VILLAGE",
    "name:eng_x_preferred":[
        "Dabthara Har Lal"
    ],
    "name:eng_x_variant":[
        "Dabthar\u0101 Har L\u0101l"
    ],
    "wof:name":"Dabthara Har Lal",
    "wof:placetype":"locality"
},
  "geometry": {"coordinates":[78.487601,28.18301],"type":"Point"}
}