{
  "type": "Feature",
  "properties": {
    "iso:country":"IN",
    "ks:ks_name":"Purana Parghat",
    "ks:ks_pop":406,
    "ks:ks_type":"VILLAGE",
    "ks:ks_uagg_main":0,
    "name:eng_x_preferred":[
        "Purana Parghat"
    ],
    "wof:name":"Purana Parghat",
    "wof:placetype":"neighbourhood",
    "wof:population":406
},
  "geometry": {"coordinates":[94.300707,27.401045],"type":"Point"}
}