{
  "type": "Feature",
  "properties": {
    "iso:country":"IN",
    "ks:ks_name":"Rupnavarwasti Tisangi",
    "ks:ks_pop":480,
    "ks:ks_type":"HABITATION",
    "name:eng_x_preferred":[
        "Rupnavarwasti Tisangi"
    ],
    "wof:name":"Rupnavarwasti Tisangi",
    "wof:placetype":"locality",
    "wof:population":480
},
  "geometry": {"coordinates":[75.17981899999999,17.59427],"type":"Point"}
}