{
  "type": "Feature",
  "properties": {
    "iso:country":"IN",
    "ks:ks_name":"Karadlu",
    "ks:ks_pop":42,
    "ks:ks_type":"HABITATION",
    "name:eng_x_preferred":[
        "Karadlu"
    ],
    "wof:name":"Karadlu",
    "wof:placetype":"locality",
    "wof:population":42
},
  "geometry": {"coordinates":[75.984444,12.246389],"type":"Point"}
}