{
  "type": "Feature",
  "properties": {
    "iso:country":"IN",
    "ks:ks_name":"Urukodige",
    "ks:ks_pop":11,
    "ks:ks_type":"HABITATION",
    "name:eng_x_preferred":[
        "Urukodige"
    ],
    "wof:name":"Urukodige",
    "wof:placetype":"locality",
    "wof:population":11
},
  "geometry": {"coordinates":[75.401698,13.599605],"type":"Point"}
}