{
  "type": "Feature",
  "properties": {
    "gn:admin1_code":"12.0",
    "gn:asciiname":"Sikandar Mir",
    "gn:country_code":"IN",
    "gn:dem":3010,
    "gn:feature_class":"P",
    "gn:feature_code":"PPL",
    "gn:name":"Sikandar M\u012br",
    "gn:population":0,
    "gn:timezone":"Asia/Kolkata",
    "iso:country":"IN",
    "wof:name":"Sikandar Mir",
    "wof:placetype":"locality"
},
  "geometry": {"coordinates":[75.05833,34.60556],"type":"Point"}
}