{
  "type": "Feature",
  "properties": {
    "iso:country":"IN",
    "ks:ks_name":"Vanumuvanipeta",
    "ks:ks_pop":210,
    "ks:ks_type":"HABITATION",
    "ks:ks_uagg_main":0,
    "name:eng_x_preferred":[
        "Vanumuvanipeta"
    ],
    "wof:name":"Vanumuvanipeta",
    "wof:placetype":"neighbourhood",
    "wof:population":210
},
  "geometry": {"coordinates":[84.02649,18.277674],"type":"Point"}
}