{
  "type": "Feature",
  "properties": {
    "gn:admin1_code":"36.0",
    "gn:admin2_code":"158.0",
    "gn:asciiname":"Pura Rati",
    "gn:country_code":"IN",
    "gn:dem":117,
    "gn:feature_class":"P",
    "gn:feature_code":"PPL",
    "gn:name":"Pura Rati",
    "gn:population":0,
    "gn:timezone":"Asia/Kolkata",
    "iso:country":"IN",
    "wof:name":"Pura Rati",
    "wof:placetype":"neighbourhood"
},
  "geometry": {"coordinates":[81.17941999999999,26.123],"type":"Point"}
}