{
  "type": "Feature",
  "properties": {
    "iso:country":"IN",
    "ks:ks_name":"Sunderpur",
    "ks:ks_pop":125,
    "ks:ks_type":"HABITATION",
    "name:eng_x_preferred":[
        "Sunderpur"
    ],
    "wof:name":"Sunderpur",
    "wof:placetype":"locality",
    "wof:population":125
},
  "geometry": {"coordinates":[76.327551,23.115403],"type":"Point"}
}