{
  "type": "Feature",
  "properties": {
    "gn:admin1_code":"12.0",
    "gn:admin2_code":"021",
    "gn:asciiname":"Ranjan",
    "gn:country_code":"IN",
    "gn:dem":412,
    "gn:feature_class":"P",
    "gn:feature_code":"PPL",
    "gn:name":"R\u0101njan",
    "gn:population":0,
    "gn:timezone":"Asia/Kolkata",
    "iso:country":"IN",
    "name:ukr_x_preferred":[
        "\u0420\u0430\u043d\u044c\u044f\u043d"
    ],
    "wof:name":"Ranjan",
    "wof:placetype":"locality"
},
  "geometry": {"coordinates":[74.78948000000003,32.88469],"type":"Point"}
}