{
  "type": "Feature",
  "properties": {
    "iso:country":"IN",
    "ks:ks_name":"Thirumalapuram",
    "ks:ks_pop":488,
    "ks:ks_type":"VILLAGE",
    "ks:ks_uagg_main":0,
    "name:eng_x_preferred":[
        "Thirumalapuram"
    ],
    "wof:name":"Thirumalapuram",
    "wof:placetype":"neighbourhood",
    "wof:population":488
},
  "geometry": {"coordinates":[80.04518,17.083736],"type":"Point"}
}