{
  "type": "Feature",
  "properties": {
    "iso:country":"IN",
    "ks:ks_name":"Sasimane",
    "ks:ks_pop":41,
    "ks:ks_type":"HABITATION",
    "name:eng_x_preferred":[
        "Sasimane"
    ],
    "wof:name":"Sasimane",
    "wof:placetype":"locality",
    "wof:population":41
},
  "geometry": {"coordinates":[75.22346,13.381837],"type":"Point"}
}