{
  "type": "Feature",
  "properties": {
    "iso:country":"IN",
    "ks:ks_name":"Ghorbad",
    "ks:ks_pop":508,
    "ks:ks_type":"VILLAGE",
    "name:eng_x_preferred":[
        "Ghorbad"
    ],
    "wof:name":"Ghorbad",
    "wof:placetype":"locality",
    "wof:population":508
},
  "geometry": {"coordinates":[86.20438799999999,24.189397],"type":"Point"}
}