{
  "type": "Feature",
  "properties": {
    "iso:country":"IN",
    "ks:ks_name":"Gigriya",
    "ks:ks_pop":174,
    "ks:ks_type":"HABITATION",
    "name:eng_x_preferred":[
        "Gigriya"
    ],
    "wof:name":"Gigriya",
    "wof:placetype":"locality",
    "wof:population":174
},
  "geometry": {"coordinates":[82.339718,27.10202],"type":"Point"}
}