{
  "type": "Feature",
  "properties": {
    "iso:country":"IN",
    "ks:ks_name":"Uttar Tola",
    "ks:ks_pop":275,
    "ks:ks_type":"HABITATION",
    "ks:ks_uagg_main":0,
    "name:eng_x_preferred":[
        "Uttar Tola"
    ],
    "wof:name":"Uttar Tola",
    "wof:placetype":"neighbourhood",
    "wof:population":275
},
  "geometry": {"coordinates":[83.584729,26.819938],"type":"Point"}
}