{
  "type": "Feature",
  "properties": {
    "iso:country":"IN",
    "ks:ks_name":"Ganeshpur",
    "ks:ks_pop":8183,
    "ks:ks_type":"URBAN",
    "ks:ks_uagg_main":0,
    "name:eng_x_preferred":[
        "Ganeshpur"
    ],
    "wof:name":"Ganeshpur",
    "wof:placetype":"neighbourhood",
    "wof:population":8183
},
  "geometry": {"coordinates":[79.643975,21.152184],"type":"Point"}
}