{
  "type": "Feature",
  "properties": {
    "gn:admin1_code":"16.0",
    "gn:admin2_code":"502.0",
    "gn:asciiname":"Borkheri",
    "gn:country_code":"IN",
    "gn:dem":486,
    "gn:feature_class":"P",
    "gn:feature_code":"PPL",
    "gn:name":"Borkheri",
    "gn:population":0,
    "gn:timezone":"Asia/Kolkata",
    "iso:country":"IN",
    "wof:name":"Borkheri",
    "wof:placetype":"locality"
},
  "geometry": {"coordinates":[77.10698000000002,19.93923],"type":"Point"}
}