{
  "type": "Feature",
  "properties": {
    "gn:admin1_code":"2.0",
    "gn:admin2_code":"552.0",
    "gn:asciiname":"Nagulavaram",
    "gn:country_code":"IN",
    "gn:dem":210,
    "gn:feature_class":"P",
    "gn:feature_code":"PPL",
    "gn:name":"N\u0101gulavaram",
    "gn:population":0,
    "gn:timezone":"Asia/Kolkata",
    "iso:country":"IN",
    "name:und_x_variant":[
        "N\u0101gulavaram",
        "Sirvel"
    ],
    "wof:name":"Nagulavaram",
    "wof:placetype":"locality"
},
  "geometry": {"coordinates":[78.46619,15.3863],"type":"Point"}
}