{
  "type": "Feature",
  "properties": {
    "iso:country":"IN",
    "ks:ks_name":"Ghojing Falia",
    "ks:ks_pop":246,
    "ks:ks_type":"HABITATION",
    "name:eng_x_preferred":[
        "Ghojing Falia"
    ],
    "wof:name":"Ghojing Falia",
    "wof:placetype":"locality",
    "wof:population":246
},
  "geometry": {"coordinates":[74.346667,22.822167],"type":"Point"}
}