{
  "type": "Feature",
  "properties": {
    "gn:admin1_code":"21.0",
    "gn:admin2_code":"396.0",
    "gn:asciiname":"Kasanakhal",
    "gn:country_code":"IN",
    "gn:dem":740,
    "gn:feature_class":"P",
    "gn:feature_code":"PPL",
    "gn:name":"Kasan\u0101kh\u0101l",
    "gn:population":0,
    "gn:timezone":"Asia/Kolkata",
    "iso:country":"IN",
    "ks:ks_alt_nam":"Kasan\u0101kh\u0101l",
    "ks:ks_name":"Kasanakhal",
    "ks:ks_type":"VILLAGE",
    "name:eng_x_preferred":[
        "Kasanakhal"
    ],
    "name:eng_x_variant":[
        "Kasan\u0101kh\u0101l"
    ],
    "wof:name":"Kasanakhal",
    "wof:placetype":"locality"
},
  "geometry": {"coordinates":[83.01115,19.466648],"type":"Point"}
}