{
  "type": "Feature",
  "properties": {
    "gn:admin1_code":"36",
    "gn:admin2_code":"198.0",
    "gn:asciiname":"Singhapur",
    "gn:country_code":"IN",
    "gn:dem":87,
    "gn:feature_class":"P",
    "gn:feature_code":"PPL",
    "gn:name":"Singh\u0101pur",
    "gn:population":0,
    "gn:timezone":"Asia/Kolkata",
    "iso:country":"IN",
    "ks:ks_name":"Singhapur",
    "ks:ks_pop":891,
    "ks:ks_type":"VILLAGE",
    "name:eng_x_preferred":[
        "Singhapur"
    ],
    "wof:name":"Singhapur",
    "wof:placetype":"locality",
    "wof:population":891
},
  "geometry": {"coordinates":[82.67457400000001,25.278557],"type":"Point"}
}