{
  "type": "Feature",
  "properties": {
    "iso:country":"IN",
    "ks:ks_name":"Nimuabagar",
    "ks:ks_pop":20,
    "ks:ks_type":"VILLAGE",
    "name:eng_x_preferred":[
        "Nimuabagar"
    ],
    "wof:name":"Nimuabagar",
    "wof:placetype":"locality",
    "wof:population":20
},
  "geometry": {"coordinates":[79.26833600000001,29.741758],"type":"Point"}
}