{
  "type": "Feature",
  "properties": {
    "iso:country":"IN",
    "ks:ks_name":"Deoli Kurmian",
    "ks:ks_pop":117,
    "ks:ks_type":"HABITATION",
    "ks:ks_uagg_main":0,
    "name:eng_x_preferred":[
        "Deoli Kurmian"
    ],
    "wof:name":"Deoli Kurmian",
    "wof:placetype":"neighbourhood",
    "wof:population":117
},
  "geometry": {"coordinates":[81.84444000000001,25.951845],"type":"Point"}
}