{
  "type": "Feature",
  "properties": {
    "iso:country":"IN",
    "ks:ks_alt_nam":"NAROO KA KHERA",
    "ks:ks_name":"Naroo Ka Khera",
    "ks:ks_pop":768,
    "ks:ks_type":"HABITATION",
    "name:eng_x_preferred":[
        "Naroo Ka Khera"
    ],
    "wof:name":"Naroo Ka Khera",
    "wof:placetype":"locality",
    "wof:population":768
},
  "geometry": {"coordinates":[74.626136,23.764979],"type":"Point"}
}