{
  "type": "Feature",
  "properties": {
    "gn:admin1_code":"36.0",
    "gn:admin2_code":"152.0",
    "gn:asciiname":"Sherapur",
    "gn:country_code":"IN",
    "gn:dem":158,
    "gn:feature_class":"P",
    "gn:feature_code":"PPL",
    "gn:name":"Sher\u0101pur",
    "gn:population":0,
    "gn:timezone":"Asia/Kolkata",
    "iso:country":"IN",
    "name:und_x_variant":[
        "Sher\u0101pur",
        "Gu\u0101r"
    ],
    "wof:name":"Sherapur",
    "wof:placetype":"locality"
},
  "geometry": {"coordinates":[79.76708000000001,28.00625],"type":"Point"}
}