{
  "type": "Feature",
  "properties": {
    "gn:admin1_code":"36",
    "gn:admin2_code":"179.0",
    "gn:asciiname":"Chhatauna",
    "gn:country_code":"IN",
    "gn:dem":100,
    "gn:feature_class":"P",
    "gn:feature_code":"PPL",
    "gn:name":"Chhatauna",
    "gn:population":0,
    "gn:timezone":"Asia/Kolkata",
    "iso:country":"IN",
    "ks:ks_alt_nam":"CHHATAUNA",
    "ks:ks_name":"Chhatauna",
    "ks:ks_pop":127,
    "ks:ks_type":"HABITATION",
    "name:eng_x_preferred":[
        "Chhatauna"
    ],
    "wof:name":"Chhatauna",
    "wof:placetype":"locality",
    "wof:population":127
},
  "geometry": {"coordinates":[82.183498,26.2663],"type":"Point"}
}