{
  "type": "Feature",
  "properties": {
    "gn:admin1_code":"39.0",
    "gn:admin2_code":"68.0",
    "gn:asciiname":"Rajpur",
    "gn:country_code":"IN",
    "gn:dem":232,
    "gn:feature_class":"P",
    "gn:feature_code":"PPL",
    "gn:name":"R\u0101jpur",
    "gn:population":0,
    "gn:timezone":"Asia/Kolkata",
    "iso:country":"IN",
    "name:cat_x_preferred":[
        "Rajpur"
    ],
    "name:ceb_x_preferred":[
        "Rajpur"
    ],
    "name:pol_x_preferred":[
        "Rajpur"
    ],
    "name:spa_x_preferred":[
        "Rajpur"
    ],
    "name:swe_x_preferred":[
        "Rajpur"
    ],
    "wof:name":"Rajpur",
    "wof:placetype":"locality"
},
  "geometry": {"coordinates":[77.98898,29.6957],"type":"Point"}
}