{
  "type": "Feature",
  "properties": {
    "iso:country":"IN",
    "ks:ks_alt_nam":"RAM KUMAR PARA",
    "ks:ks_name":"Ram Kumar Para",
    "ks:ks_pop":45,
    "ks:ks_type":"HABITATION",
    "name:eng_x_preferred":[
        "Ram Kumar Para"
    ],
    "wof:name":"Ram Kumar Para",
    "wof:placetype":"locality",
    "wof:population":45
},
  "geometry": {"coordinates":[91.49757700000001,23.906553],"type":"Point"}
}