{
  "type": "Feature",
  "properties": {
    "iso:country":"IN",
    "ks:ks_name":"Kottaimedu",
    "ks:ks_pop":820,
    "ks:ks_type":"HABITATION",
    "ks:ks_uagg_main":0,
    "name:eng_x_preferred":[
        "Kottaimedu"
    ],
    "wof:name":"Kottaimedu",
    "wof:placetype":"neighbourhood",
    "wof:population":820
},
  "geometry": {"coordinates":[78.379672,9.415992],"type":"Point"}
}