{
  "type": "Feature",
  "properties": {
    "iso:country":"IN",
    "ks:ks_alt_nam":"Amali faliya",
    "ks:ks_name":"Amali Faliya",
    "ks:ks_pop":292,
    "ks:ks_type":"HABITATION",
    "ks:ks_uagg_main":0,
    "name:eng_x_preferred":[
        "Amali Faliya"
    ],
    "wof:name":"Amali Faliya",
    "wof:placetype":"neighbourhood",
    "wof:population":292
},
  "geometry": {"coordinates":[73.167778,20.4825],"type":"Point"}
}