{
  "type": "Feature",
  "properties": {
    "iso:country":"IN",
    "ks:ks_name":"Dudhiware",
    "ks:ks_pop":388,
    "ks:ks_type":"HABITATION",
    "name:eng_x_preferred":[
        "Dudhiware"
    ],
    "wof:name":"Dudhiware",
    "wof:placetype":"locality",
    "wof:population":388
},
  "geometry": {"coordinates":[73.43469,18.704341],"type":"Point"}
}