{
  "type": "Feature",
  "properties": {
    "iso:country":"IN",
    "ks:ks_name":"Tatiguda",
    "ks:ks_pop":100,
    "ks:ks_type":"HABITATION",
    "name:eng_x_preferred":[
        "Tatiguda"
    ],
    "wof:name":"Tatiguda",
    "wof:placetype":"locality",
    "wof:population":100
},
  "geometry": {"coordinates":[78.99218399999999,19.45664],"type":"Point"}
}