{
  "type": "Feature",
  "properties": {
    "gn:admin1_code":"12.0",
    "gn:admin2_code":"2.0",
    "gn:asciiname":"Brenapathar",
    "gn:country_code":"IN",
    "gn:dem":2186,
    "gn:feature_class":"P",
    "gn:feature_code":"PPL",
    "gn:name":"Brenapathar",
    "gn:population":0,
    "gn:timezone":"Asia/Kolkata",
    "iso:country":"IN",
    "wof:name":"Brenapathar",
    "wof:placetype":"locality"
},
  "geometry": {"coordinates":[74.73359000000001,33.83654],"type":"Point"}
}