{
  "type": "Feature",
  "properties": {
    "iso:country":"IN",
    "ks:ks_name":"Vanuguputtu",
    "ks:ks_pop":130,
    "ks:ks_type":"HABITATION",
    "name:eng_x_preferred":[
        "Vanuguputtu"
    ],
    "wof:name":"Vanuguputtu",
    "wof:placetype":"locality",
    "wof:population":130
},
  "geometry": {"coordinates":[82.567452,18.377599],"type":"Point"}
}