{
  "type": "Feature",
  "properties": {
    "iso:country":"IN",
    "ks:ks_name":"Suwabojh",
    "ks:ks_pop":250,
    "ks:ks_type":"VILLAGE",
    "name:eng_x_preferred":[
        "Suwabojh"
    ],
    "wof:name":"Suwabojh",
    "wof:placetype":"locality",
    "wof:population":250
},
  "geometry": {"coordinates":[80.32122,28.2524],"type":"Point"}
}