{
  "type": "Feature",
  "properties": {
    "gn:admin1_code":"19.0",
    "gn:admin2_code":"578.0",
    "gn:asciiname":"Vadayanpur",
    "gn:country_code":"IN",
    "gn:dem":847,
    "gn:feature_class":"P",
    "gn:feature_code":"PPL",
    "gn:name":"Vadayanp\u016br",
    "gn:population":0,
    "gn:timezone":"Asia/Kolkata",
    "iso:country":"IN",
    "wof:name":"Vadayanpur",
    "wof:placetype":"locality"
},
  "geometry": {"coordinates":[76.7358,11.73463],"type":"Point"}
}