{
  "type": "Feature",
  "properties": {
    "iso:country":"IN",
    "ks:ks_name":"Khandinenda Wadi",
    "ks:ks_pop":128,
    "ks:ks_type":"HABITATION",
    "name:eng_x_preferred":[
        "Khandinenda Wadi"
    ],
    "wof:name":"Khandinenda Wadi",
    "wof:placetype":"locality",
    "wof:population":128
},
  "geometry": {"coordinates":[80.46087199999999,19.505969],"type":"Point"}
}