{
  "type": "Feature",
  "properties": {
    "gn:admin1_code":"2.0",
    "gn:admin2_code":"543.0",
    "gn:asciiname":"Venkannapalem",
    "gn:country_code":"IN",
    "gn:dem":94,
    "gn:feature_class":"P",
    "gn:feature_code":"PPL",
    "gn:name":"Venkannap\u0101lem",
    "gn:population":0,
    "gn:timezone":"Asia/Kolkata",
    "iso:country":"IN",
    "ks:ks_name":"Venkayyapalem",
    "ks:ks_pop":115,
    "ks:ks_type":"HABITATION",
    "name:eng_x_preferred":[
        "Venkayyapalem"
    ],
    "name:eng_x_variant":[
        "Venkannapalem"
    ],
    "wof:name":"Venkayyapalem",
    "wof:placetype":"locality",
    "wof:population":115
},
  "geometry": {"coordinates":[83.090755,18.043348],"type":"Point"}
}