{
  "type": "Feature",
  "properties": {
    "gn:admin1_code":"34.0",
    "gn:admin2_code":"240",
    "gn:asciiname":"Arwal",
    "gn:country_code":"IN",
    "gn:dem":80,
    "gn:feature_class":"P",
    "gn:feature_code":"PPL",
    "gn:name":"Arwal",
    "gn:population":0,
    "gn:timezone":"Asia/Kolkata",
    "iso:country":"IN",
    "name:ara_x_preferred":[
        "\u0623\u0631\u0648\u0627\u0644"
    ],
    "name:bih_x_preferred":[
        "\u0905\u0930\u0935\u0932"
    ],
    "name:ceb_x_preferred":[
        "Arwal"
    ],
    "name:fra_x_preferred":[
        "Arwal"
    ],
    "name:guj_x_preferred":[
        "\u0a85\u0ab0\u0ab5\u0ab2"
    ],
    "name:hin_x_preferred":[
        "\u0905\u0930\u0935\u0932"
    ],
    "name:ita_x_preferred":[
        "Arwal"
    ],
    "name:ori_x_preferred":[
        "\u0b05\u0b30\u0b71\u0b32"
    ],
    "name:san_x_preferred":[
        "\u0905\u0930\u0935\u0932"
    ],
    "name:spa_x_preferred":[
        "Arwal"
    ],
    "name:swe_x_preferred":[
        "Arwal"
    ],
    "name:urd_x_preferred":[
        "\u0627\u0631\u0648\u0627\u0644"
    ],
    "wof:name":"Arwal",
    "wof:placetype":"locality"
},
  "geometry": {"coordinates":[84.66571,25.24281],"type":"Point"}
}