{
  "type": "Feature",
  "properties": {
    "gn:admin1_code":"37",
    "gn:admin2_code":"409.0",
    "gn:asciiname":"Deotarai",
    "gn:country_code":"IN",
    "gn:dem":328,
    "gn:feature_class":"P",
    "gn:feature_code":"PPL",
    "gn:name":"Deotar\u0101i",
    "gn:population":0,
    "gn:timezone":"Asia/Kolkata",
    "iso:country":"IN",
    "wof:name":"Deotarai",
    "wof:placetype":"neighbourhood"
},
  "geometry": {"coordinates":[81.20912,20.70566],"type":"Point"}
}