{
  "type": "Feature",
  "properties": {
    "gn:admin1_code":"37.0",
    "gn:admin2_code":"400.0",
    "gn:asciiname":"Dongritola",
    "gn:country_code":"IN",
    "gn:dem":426,
    "gn:feature_class":"P",
    "gn:feature_code":"PPL",
    "gn:name":"Dongritola",
    "gn:population":0,
    "gn:timezone":"Asia/Kolkata",
    "iso:country":"IN",
    "wof:name":"Dongritola",
    "wof:placetype":"locality"
},
  "geometry": {"coordinates":[81.70758000000002,23.7251],"type":"Point"}
}