{
  "type": "Feature",
  "properties": {
    "gn:admin1_code":"1.0",
    "gn:admin2_code":"639",
    "gn:asciiname":"Kartara",
    "gn:country_code":"IN",
    "gn:dem":-9999,
    "gn:feature_class":"P",
    "gn:feature_code":"PPL",
    "gn:name":"Kartara",
    "gn:population":0,
    "gn:timezone":"Asia/Kolkata",
    "iso:country":"IN",
    "wof:name":"Kartara",
    "wof:placetype":"locality"
},
  "geometry": {"coordinates":[92.73121999999999,12.73211],"type":"Point"}
}