{
  "type": "Feature",
  "properties": {
    "gn:admin1_code":"12.0",
    "gn:admin2_code":"005",
    "gn:asciiname":"Nambal",
    "gn:country_code":"IN",
    "gn:dem":1172,
    "gn:feature_class":"P",
    "gn:feature_code":"PPL",
    "gn:name":"Nambal",
    "gn:population":0,
    "gn:timezone":"Asia/Kolkata",
    "iso:country":"IN",
    "wof:name":"Nambal",
    "wof:placetype":"locality"
},
  "geometry": {"coordinates":[74.02308000000002,33.69364],"type":"Point"}
}