{
  "type": "Feature",
  "properties": {
    "gn:admin1_code":"36.0",
    "gn:admin2_code":"163.0",
    "gn:asciiname":"Manpur Gajain",
    "gn:country_code":"IN",
    "gn:dem":139,
    "gn:feature_class":"P",
    "gn:feature_code":"PPL",
    "gn:name":"M\u0101npur Gajain",
    "gn:population":0,
    "gn:timezone":"Asia/Kolkata",
    "iso:country":"IN",
    "name:und_x_variant":[
        "Kamsia",
        "M\u0101npur Gajain"
    ],
    "wof:name":"Manpur Gajain",
    "wof:placetype":"locality"
},
  "geometry": {"coordinates":[79.83903000000002,26.59221],"type":"Point"}
}