{
  "type": "Feature",
  "properties": {
    "gn:admin1_code":"36.0",
    "gn:admin2_code":"163.0",
    "gn:asciiname":"Manpur Gajain",
    "gn:country_code":"IN",
    "gn:dem":139,
    "gn:feature_class":"P",
    "gn:feature_code":"PPL",
    "gn:name":"M\u0101npur Gajain",
    "gn:population":0,
    "gn:timezone":"Asia/Kolkata",
    "iso:country":"IN",
    "ks:ks_name":"Manpur Gajen",
    "ks:ks_pop":1145,
    "ks:ks_type":"VILLAGE",
    "name:eng_x_preferred":[
        "Manpur Gajen"
    ],
    "name:eng_x_variant":[
        "Manpur Gajain"
    ],
    "name:und_x_variant":[
        "Kamsia",
        "M\u0101npur Gajain"
    ],
    "wof:name":"Manpur Gajen",
    "wof:placetype":"locality",
    "wof:population":1145
},
  "geometry": {"coordinates":[79.848896,26.595059],"type":"Point"}
}