{
  "type": "Feature",
  "properties": {
    "iso:country":"IN",
    "ks:ks_alt_nam":"ambatamale",
    "ks:ks_name":"Ambatamale",
    "ks:ks_pop":150,
    "ks:ks_type":"HABITATION",
    "name:eng_x_preferred":[
        "Ambatamale"
    ],
    "wof:name":"Ambatamale",
    "wof:placetype":"locality",
    "wof:population":150
},
  "geometry": {"coordinates":[75.49726,13.043314],"type":"Point"}
}