{
  "type": "Feature",
  "properties": {
    "gn:admin1_code":"12.0",
    "gn:admin2_code":"14.0",
    "gn:asciiname":"Nalikut",
    "gn:country_code":"IN",
    "gn:dem":2633,
    "gn:feature_class":"P",
    "gn:feature_code":"PPL",
    "gn:name":"Nalikut",
    "gn:population":0,
    "gn:timezone":"Asia/Kolkata",
    "iso:country":"IN",
    "wof:name":"Nalikut",
    "wof:placetype":"locality"
},
  "geometry": {"coordinates":[75.50378000000001,33.4808],"type":"Point"}
}