{
  "type": "Feature",
  "properties": {
    "iso:country":"IN",
    "ks:ks_name":"Monda",
    "ks:ks_pop":232,
    "ks:ks_type":"VILLAGE",
    "name:eng_x_preferred":[
        "Monda"
    ],
    "wof:name":"Monda",
    "wof:placetype":"locality",
    "wof:population":232
},
  "geometry": {"coordinates":[77.91221899999999,31.096616],"type":"Point"}
}