{
  "type": "Feature",
  "properties": {
    "iso:country":"IN",
    "ks:ks_name":"Chak Hathiana",
    "ks:ks_pop":295,
    "ks:ks_type":"VILLAGE",
    "name:eng_x_preferred":[
        "Chak Hathiana"
    ],
    "wof:name":"Chak Hathiana",
    "wof:placetype":"locality",
    "wof:population":295
},
  "geometry": {"coordinates":[75.36978999999999,30.998403],"type":"Point"}
}