{
  "type": "Feature",
  "properties": {
    "iso:country":"IN",
    "ks:ks_alt_nam":"PK Savantwasti",
    "ks:ks_name":"Pk Savantwasti",
    "ks:ks_pop":120,
    "ks:ks_type":"HABITATION",
    "name:eng_x_preferred":[
        "Pk Savantwasti"
    ],
    "wof:name":"Pk Savantwasti",
    "wof:placetype":"locality",
    "wof:population":120
},
  "geometry": {"coordinates":[74.720564,17.946328],"type":"Point"}
}