{
  "type": "Feature",
  "properties": {
    "iso:country":"IN",
    "ks:ks_name":"Kumipada",
    "ks:ks_pop":60,
    "ks:ks_type":"HABITATION",
    "name:eng_x_preferred":[
        "Kumipada"
    ],
    "wof:name":"Kumipada",
    "wof:placetype":"locality",
    "wof:population":60
},
  "geometry": {"coordinates":[83.15311199999999,19.437172],"type":"Point"}
}