{
  "type": "Feature",
  "properties": {
    "gn:admin1_code":"19.0",
    "gn:admin2_code":"568.0",
    "gn:asciiname":"Halusale Malavalli",
    "gn:country_code":"IN",
    "gn:dem":581,
    "gn:feature_class":"P",
    "gn:feature_code":"PPL",
    "gn:name":"Halusale Malavalli",
    "gn:population":0,
    "gn:timezone":"Asia/Kolkata",
    "iso:country":"IN",
    "ks:ks_name":"Hulusale Malavalli",
    "ks:ks_pop":426,
    "ks:ks_type":"VILLAGE",
    "name:eng_x_preferred":[
        "Hulusale Malavalli"
    ],
    "name:eng_x_variant":[
        "Halusale Malavalli"
    ],
    "wof:name":"Hulusale Malavalli",
    "wof:placetype":"locality",
    "wof:population":426
},
  "geometry": {"coordinates":[75.107285,14.049872],"type":"Point"}
}