{
  "type": "Feature",
  "properties": {
    "gn:admin1_code":"37",
    "gn:admin2_code":"410.0",
    "gn:asciiname":"Bharuamura",
    "gn:country_code":"IN",
    "gn:dem":344,
    "gn:feature_class":"P",
    "gn:feature_code":"PPL",
    "gn:name":"Bharuamura",
    "gn:population":0,
    "gn:timezone":"Asia/Kolkata",
    "iso:country":"IN",
    "ks:ks_name":"Bharwamuda",
    "ks:ks_pop":428,
    "ks:ks_type":"VILLAGE",
    "name:eng_x_preferred":[
        "Bharwamuda"
    ],
    "name:eng_x_variant":[
        "Bharuamura"
    ],
    "wof:name":"Bharwamuda",
    "wof:placetype":"locality",
    "wof:population":428
},
  "geometry": {"coordinates":[82.24808899999999,20.824875],"type":"Point"}
}