{
  "type": "Feature",
  "properties": {
    "iso:country":"IN",
    "ks:ks_alt_nam":"BELDiPA",
    "ks:ks_name":"Beldipa",
    "ks:ks_pop":109,
    "ks:ks_type":"HABITATION",
    "name:eng_x_preferred":[
        "Beldipa"
    ],
    "wof:name":"Beldipa",
    "wof:placetype":"locality",
    "wof:population":109
},
  "geometry": {"coordinates":[83.99419,22.391455],"type":"Point"}
}