{
  "type": "Feature",
  "properties": {
    "gn:admin1_code":"35.0",
    "gn:admin2_code":"464.0",
    "gn:asciiname":"Garwakheri",
    "gn:country_code":"IN",
    "gn:dem":509,
    "gn:feature_class":"P",
    "gn:feature_code":"PPL",
    "gn:name":"Garwakheri",
    "gn:population":0,
    "gn:timezone":"Asia/Kolkata",
    "iso:country":"IN",
    "wof:name":"Garwakheri",
    "wof:placetype":"locality"
},
  "geometry": {"coordinates":[74.86823000000003,22.85301],"type":"Point"}
}