{
  "type": "Feature",
  "properties": {
    "iso:country":"IN",
    "ks:ks_name":"Dharkari Tola",
    "ks:ks_pop":513,
    "ks:ks_type":"HABITATION",
    "name:eng_x_preferred":[
        "Dharkari Tola"
    ],
    "wof:name":"Dharkari Tola",
    "wof:placetype":"locality",
    "wof:population":513
},
  "geometry": {"coordinates":[83.168959,24.049125],"type":"Point"}
}