{
  "type": "Feature",
  "properties": {
    "iso:country":"IN",
    "ks:ks_alt_nam":"T\u0101ngar",
    "ks:ks_name":"Tangar",
    "ks:ks_pop":2621,
    "ks:ks_type":"VILLAGE",
    "ks:ks_uagg_main":0,
    "name:eng_x_preferred":[
        "Tangar"
    ],
    "name:eng_x_variant":[
        "T\u0101ngar"
    ],
    "wof:name":"Tangar",
    "wof:placetype":"neighbourhood",
    "wof:population":2621
},
  "geometry": {"coordinates":[85.02082799999999,23.481021],"type":"Point"}
}