{
  "type": "Feature",
  "properties": {
    "gn:admin1_code":"19",
    "gn:admin2_code":"568.0",
    "gn:asciiname":"Mel Manji",
    "gn:country_code":"IN",
    "gn:dem":589,
    "gn:feature_class":"P",
    "gn:feature_code":"PPL",
    "gn:name":"Mel Manji",
    "gn:population":0,
    "gn:timezone":"Asia/Kolkata",
    "iso:country":"IN",
    "ks:ks_name":"Melmanji",
    "ks:ks_pop":86,
    "ks:ks_type":"HABITATION",
    "name:eng_x_preferred":[
        "Melmanji"
    ],
    "name:eng_x_variant":[
        "Mel Manji"
    ],
    "wof:name":"Melmanji",
    "wof:placetype":"locality",
    "wof:population":86
},
  "geometry": {"coordinates":[74.74995,14.069976],"type":"Point"}
}