{
  "type": "Feature",
  "properties": {
    "gn:admin1_code":"35",
    "gn:admin2_code":"467.0",
    "gn:asciiname":"Jamniya",
    "gn:country_code":"IN",
    "gn:dem":453,
    "gn:feature_class":"P",
    "gn:feature_code":"PPL",
    "gn:name":"J\u0101mniya",
    "gn:population":0,
    "gn:timezone":"Asia/Kolkata",
    "iso:country":"IN",
    "wof:name":"Jamniya",
    "wof:placetype":"locality"
},
  "geometry": {"coordinates":[76.19065999999999,21.52739],"type":"Point"}
}