{
  "type": "Feature",
  "properties": {
    "gn:admin1_code":"35",
    "gn:admin2_code":"467.0",
    "gn:asciiname":"Jamniya",
    "gn:country_code":"IN",
    "gn:dem":453,
    "gn:feature_class":"P",
    "gn:feature_code":"PPL",
    "gn:name":"J\u0101mniya",
    "gn:population":0,
    "gn:timezone":"Asia/Kolkata",
    "iso:country":"IN",
    "ks:ks_alt_nam":"J\u0101mniya",
    "ks:ks_name":"Jamniya",
    "ks:ks_type":"VILLAGE",
    "name:eng_x_preferred":[
        "Jamniya"
    ],
    "name:eng_x_variant":[
        "J\u0101mniya"
    ],
    "wof:name":"Jamniya",
    "wof:placetype":"locality"
},
  "geometry": {"coordinates":[76.19065999999999,21.527388],"type":"Point"}
}