{
  "type": "Feature",
  "properties": {
    "iso:country":"IN",
    "ks:ks_name":"Khandaj",
    "ks:ks_pop":184,
    "ks:ks_type":"VILLAGE",
    "name:eng_x_preferred":[
        "Khandaj"
    ],
    "wof:name":"Khandaj",
    "wof:placetype":"locality",
    "wof:population":184
},
  "geometry": {"coordinates":[73.58831000000001,18.005177],"type":"Point"}
}