{
  "type": "Feature",
  "properties": {
    "iso:country":"IN",
    "ks:ks_name":"Kaldare",
    "ks:ks_pop":188,
    "ks:ks_type":"HABITATION",
    "name:eng_x_preferred":[
        "Kaldare"
    ],
    "wof:name":"Kaldare",
    "wof:placetype":"locality",
    "wof:population":188
},
  "geometry": {"coordinates":[73.729179,19.213271],"type":"Point"}
}