{
  "type": "Feature",
  "properties": {
    "iso:country":"IN",
    "ks:ks_name":"Ananda Para",
    "ks:ks_pop":217,
    "ks:ks_type":"HABITATION",
    "name:eng_x_preferred":[
        "Ananda Para"
    ],
    "wof:name":"Ananda Para",
    "wof:placetype":"locality",
    "wof:population":217
},
  "geometry": {"coordinates":[91.72986400000001,23.036664],"type":"Point"}
}