{
  "type": "Feature",
  "properties": {
    "iso:country":"IN",
    "ks:ks_alt_nam":"S V K mines camp",
    "ks:ks_name":"S V K Mines Camp",
    "ks:ks_pop":125,
    "ks:ks_type":"HABITATION",
    "name:eng_x_preferred":[
        "S V K Mines Camp"
    ],
    "wof:name":"S V K Mines Camp",
    "wof:placetype":"locality",
    "wof:population":125
},
  "geometry": {"coordinates":[76.40631999999999,15.211673],"type":"Point"}
}