{
  "type": "Feature",
  "properties": {
    "gn:admin1_code":"25.0",
    "gn:admin2_code":"631.0",
    "gn:asciiname":"Girichetti",
    "gn:country_code":"IN",
    "gn:dem":801,
    "gn:feature_class":"P",
    "gn:feature_code":"PPL",
    "gn:name":"Girichetti",
    "gn:population":0,
    "gn:timezone":"Asia/Kolkata",
    "iso:country":"IN",
    "wof:name":"Girichetti",
    "wof:placetype":"locality"
},
  "geometry": {"coordinates":[77.85065,12.54215],"type":"Point"}
}