{
  "type": "Feature",
  "properties": {
    "gn:admin1_code":"39.0",
    "gn:admin2_code":"64.0",
    "gn:asciiname":"Sukna",
    "gn:country_code":"IN",
    "gn:dem":1610,
    "gn:feature_class":"P",
    "gn:feature_code":"PPL",
    "gn:name":"Sukna",
    "gn:population":0,
    "gn:timezone":"Asia/Kolkata",
    "iso:country":"IN",
    "name:zho_x_preferred":[
        "\u8607\u514b\u7d0d\u5c71"
    ],
    "wof:name":"Sukna",
    "wof:placetype":"locality"
},
  "geometry": {"coordinates":[79.94247,29.56949],"type":"Point"}
}