{
  "type": "Feature",
  "properties": {
    "gn:admin1_code":"36.0",
    "gn:admin2_code":"149.0",
    "gn:asciiname":"Badarpur",
    "gn:country_code":"IN",
    "gn:dem":173,
    "gn:feature_class":"P",
    "gn:feature_code":"PPL",
    "gn:name":"Badarpur",
    "gn:population":0,
    "gn:timezone":"Asia/Kolkata",
    "iso:country":"IN",
    "name:urd_x_preferred":[
        "\u0628\u062f\u0631 \u067e\u0648\u0631"
    ],
    "wof:name":"Badarpur",
    "wof:placetype":"locality"
},
  "geometry": {"coordinates":[79.07261,28.04102],"type":"Point"}
}