{
  "type": "Feature",
  "properties": {
    "iso:country":"IN",
    "ks:ks_name":"Khaja Lewa",
    "ks:ks_pop":132,
    "ks:ks_type":"HABITATION",
    "name:eng_x_preferred":[
        "Khaja Lewa"
    ],
    "wof:name":"Khaja Lewa",
    "wof:placetype":"locality",
    "wof:population":132
},
  "geometry": {"coordinates":[82.989833,23.915071],"type":"Point"}
}