{
  "type": "Feature",
  "properties": {
    "iso:country":"IN",
    "ks:ks_name":"Ghagra",
    "ks:ks_pop":0,
    "ks:ks_type":"VILLAGE",
    "name:eng_x_preferred":[
        "Ghagra"
    ],
    "wof:name":"Ghagra",
    "wof:placetype":"locality",
    "wof:population":0
},
  "geometry": {"coordinates":[86.802166,22.953857],"type":"Point"}
}