{
  "type": "Feature",
  "properties": {
    "iso:country":"IN",
    "ks:ks_name":"Salaya Tar Tola",
    "ks:ks_pop":128,
    "ks:ks_type":"HABITATION",
    "name:eng_x_preferred":[
        "Salaya Tar Tola"
    ],
    "wof:name":"Salaya Tar Tola",
    "wof:placetype":"locality",
    "wof:population":128
},
  "geometry": {"coordinates":[86.163527,24.581992],"type":"Point"}
}