{
  "type": "Feature",
  "properties": {
    "gn:admin1_code":"13.0",
    "gn:admin2_code":"594.0",
    "gn:asciiname":"Punnayur",
    "gn:country_code":"IN",
    "gn:dem":11,
    "gn:feature_class":"P",
    "gn:feature_code":"PPL",
    "gn:name":"Punnay\u016br",
    "gn:population":0,
    "gn:timezone":"Asia/Kolkata",
    "iso:country":"IN",
    "ks:ks_alt_nam":"Punnay\u016br",
    "ks:ks_name":"Punnayur",
    "ks:ks_pop":17547,
    "ks:ks_type":"VILLAGE",
    "name:eng_x_preferred":[
        "Punnayur"
    ],
    "name:eng_x_variant":[
        "Punnay\u016br"
    ],
    "name:mal_x_preferred":[
        "\u0d2a\u0d41\u0d28\u0d4d\u0d28\u0d2f\u0d42\u0d7c"
    ],
    "name:msa_x_preferred":[
        "Punnayur"
    ],
    "wof:name":"Punnayur",
    "wof:placetype":"locality",
    "wof:population":17547
},
  "geometry": {"coordinates":[75.976006,10.656156],"type":"Point"}
}