{
  "type": "Feature",
  "properties": {
    "gn:admin1_code":"13.0",
    "gn:admin2_code":"594.0",
    "gn:asciiname":"Punnayur",
    "gn:country_code":"IN",
    "gn:dem":11,
    "gn:feature_class":"P",
    "gn:feature_code":"PPL",
    "gn:name":"Punnay\u016br",
    "gn:population":0,
    "gn:timezone":"Asia/Kolkata",
    "iso:country":"IN",
    "wof:name":"Punnayur",
    "wof:placetype":"locality"
},
  "geometry": {"coordinates":[75.99512,10.65207],"type":"Point"}
}