{
  "type": "Feature",
  "properties": {
    "iso:country":"IN",
    "ks:ks_name":"Purwa Dhobi",
    "ks:ks_pop":124,
    "ks:ks_type":"HABITATION",
    "name:eng_x_preferred":[
        "Purwa Dhobi"
    ],
    "wof:name":"Purwa Dhobi",
    "wof:placetype":"locality",
    "wof:population":124
},
  "geometry": {"coordinates":[79.76413599999999,26.874744],"type":"Point"}
}