{
  "type": "Feature",
  "properties": {
    "iso:country":"IN",
    "ks:ks_name":"Bangowan",
    "ks:ks_pop":832,
    "ks:ks_type":"HABITATION",
    "name:eng_x_preferred":[
        "Bangowan"
    ],
    "wof:name":"Bangowan",
    "wof:placetype":"locality",
    "wof:population":832
},
  "geometry": {"coordinates":[82.79531900000001,27.120036],"type":"Point"}
}