{
  "type": "Feature",
  "properties": {
    "iso:country":"IN",
    "ks:ks_name":"Pure Bhola",
    "ks:ks_pop":42,
    "ks:ks_type":"HABITATION",
    "ks:ks_uagg_main":0,
    "name:eng_x_preferred":[
        "Pure Bhola"
    ],
    "wof:name":"Pure Bhola",
    "wof:placetype":"neighbourhood",
    "wof:population":42
},
  "geometry": {"coordinates":[81.79132799999999,26.348975],"type":"Point"}
}