{
  "type": "Feature",
  "properties": {
    "iso:country":"IN",
    "ks:ks_name":"Chinchghar",
    "ks:ks_pop":1514,
    "ks:ks_type":"VILLAGE",
    "ks:ks_uagg_main":0,
    "name:eng_x_preferred":[
        "Chinchghar"
    ],
    "wof:name":"Chinchghar",
    "wof:placetype":"neighbourhood",
    "wof:population":1514
},
  "geometry": {"coordinates":[73.09117500000001,19.531961],"type":"Point"}
}