{
  "type": "Feature",
  "properties": {
    "iso:country":"IN",
    "ks:ks_name":"Ermetti",
    "ks:ks_pop":24,
    "ks:ks_type":"HABITATION",
    "name:eng_x_preferred":[
        "Ermetti"
    ],
    "wof:name":"Ermetti",
    "wof:placetype":"locality",
    "wof:population":24
},
  "geometry": {"coordinates":[75.47445,12.584882],"type":"Point"}
}