{
  "type": "Feature",
  "properties": {
    "iso:country":"IN",
    "ks:ks_name":"Sunari",
    "ks:ks_pop":174,
    "ks:ks_type":"VILLAGE",
    "ks:ks_uagg_main":0,
    "name:eng_x_preferred":[
        "Sunari"
    ],
    "wof:name":"Sunari",
    "wof:placetype":"neighbourhood",
    "wof:population":174
},
  "geometry": {"coordinates":[86.17552999999999,20.738143],"type":"Point"}
}