{
  "type": "Feature",
  "properties": {
    "gn:admin1_code":"36.0",
    "gn:admin2_code":"161",
    "gn:asciiname":"Dugaoli",
    "gn:country_code":"IN",
    "gn:dem":154,
    "gn:feature_class":"P",
    "gn:feature_code":"PPL",
    "gn:name":"Dugaoli",
    "gn:population":0,
    "gn:timezone":"Asia/Kolkata",
    "iso:country":"IN",
    "name:und_x_variant":[
        "Dug\u0101wali"
    ],
    "wof:name":"Dugaoli",
    "wof:placetype":"neighbourhood"
},
  "geometry": {"coordinates":[79.08795000000001,26.81808],"type":"Point"}
}