{
  "type": "Feature",
  "properties": {
    "iso:country":"IN",
    "ks:ks_name":"Gaddemane",
    "ks:ks_pop":99,
    "ks:ks_type":"HABITATION",
    "name:eng_x_preferred":[
        "Gaddemane"
    ],
    "wof:name":"Gaddemane",
    "wof:placetype":"locality",
    "wof:population":99
},
  "geometry": {"coordinates":[74.830589,14.495744],"type":"Point"}
}