{
  "type": "Feature",
  "properties": {
    "iso:country":"IN",
    "ks:ks_name":"Soledega",
    "ks:ks_pop":477,
    "ks:ks_type":"VILLAGE",
    "name:eng_x_preferred":[
        "Soledega"
    ],
    "wof:name":"Soledega",
    "wof:placetype":"locality",
    "wof:population":477
},
  "geometry": {"coordinates":[84.81141700000001,21.947593],"type":"Point"}
}