{
  "type": "Feature",
  "properties": {
    "iso:country":"IN",
    "ks:ks_name":"Jigri Kulgachhi",
    "ks:ks_pop":4004,
    "ks:ks_type":"VILLAGE",
    "ks:ks_uagg_main":0,
    "name:eng_x_preferred":[
        "Jigri Kulgachhi"
    ],
    "wof:name":"Jigri Kulgachhi",
    "wof:placetype":"neighbourhood",
    "wof:population":4004
},
  "geometry": {"coordinates":[87.924762,24.700624],"type":"Point"}
}