{
  "type": "Feature",
  "properties": {
    "iso:country":"IN",
    "ks:ks_name":"Panch Peepalya",
    "ks:ks_pop":14,
    "ks:ks_type":"VILLAGE",
    "ks:ks_uagg_main":0,
    "name:eng_x_preferred":[
        "Panch Peepalya"
    ],
    "wof:name":"Panch Peepalya",
    "wof:placetype":"neighbourhood",
    "wof:population":14
},
  "geometry": {"coordinates":[76.30964400000001,24.289919],"type":"Point"}
}