{
  "type": "Feature",
  "properties": {
    "iso:country":"IN",
    "ks:ks_name":"Awrasol",
    "ks:ks_pop":10,
    "ks:ks_type":"VILLAGE",
    "name:eng_x_preferred":[
        "Awrasol"
    ],
    "wof:name":"Awrasol",
    "wof:placetype":"locality",
    "wof:population":10
},
  "geometry": {"coordinates":[86.60584299999999,24.16299],"type":"Point"}
}