{
  "type": "Feature",
  "properties": {
    "iso:country":"IN",
    "ks:ks_name":"Karai",
    "ks:ks_pop":409,
    "ks:ks_type":"HABITATION",
    "name:eng_x_preferred":[
        "Karai"
    ],
    "wof:name":"Karai",
    "wof:placetype":"locality",
    "wof:population":409
},
  "geometry": {"coordinates":[76.912083,26.107469],"type":"Point"}
}