{
  "type": "Feature",
  "properties": {
    "iso:country":"IN",
    "ks:ks_alt_nam":"Cheepuruvalasa colony",
    "ks:ks_name":"Cheepuruvalasa Colony",
    "ks:ks_pop":49,
    "ks:ks_type":"HABITATION",
    "name:eng_x_preferred":[
        "Cheepuruvalasa Colony"
    ],
    "wof:name":"Cheepuruvalasa Colony",
    "wof:placetype":"locality",
    "wof:population":49
},
  "geometry": {"coordinates":[83.19061000000001,18.59888],"type":"Point"}
}