{
  "type": "Feature",
  "properties": {
    "gn:admin1_code":"2.0",
    "gn:admin2_code":"553.0",
    "gn:asciiname":"Mallappagaripalle",
    "gn:country_code":"IN",
    "gn:dem":593,
    "gn:feature_class":"P",
    "gn:feature_code":"PPL",
    "gn:name":"Mallappag\u0101ripalle",
    "gn:population":0,
    "gn:timezone":"Asia/Kolkata",
    "iso:country":"IN",
    "wof:name":"Mallappagaripalle",
    "wof:placetype":"locality"
},
  "geometry": {"coordinates":[78.01573,14.10586],"type":"Point"}
}