{
  "type": "Feature",
  "properties": {
    "gn:admin1_code":"36.0",
    "gn:admin2_code":"168.0",
    "gn:asciiname":"Surajpura",
    "gn:country_code":"IN",
    "gn:dem":112,
    "gn:feature_class":"P",
    "gn:feature_code":"PPL",
    "gn:name":"Surajpura",
    "gn:population":0,
    "gn:timezone":"Asia/Kolkata",
    "iso:country":"IN",
    "wof:name":"Surajpura",
    "wof:placetype":"locality"
},
  "geometry": {"coordinates":[80.14714000000002,25.92938],"type":"Point"}
}