{
  "type": "Feature",
  "properties": {
    "iso:country":"IN",
    "ks:ks_name":"Kohandwa(chamar)",
    "ks:ks_pop":178,
    "ks:ks_type":"HABITATION",
    "name:eng_x_preferred":[
        "Kohandwa(chamar)"
    ],
    "wof:name":"Kohandwa(chamar)",
    "wof:placetype":"locality",
    "wof:population":178
},
  "geometry": {"coordinates":[82.61138699999999,26.967348],"type":"Point"}
}