{
  "type": "Feature",
  "properties": {
    "iso:country":"IN",
    "ks:ks_name":"Kalathur",
    "ks:ks_pop":69,
    "ks:ks_type":"HABITATION",
    "name:eng_x_preferred":[
        "Kalathur"
    ],
    "wof:name":"Kalathur",
    "wof:placetype":"locality",
    "wof:population":69
},
  "geometry": {"coordinates":[78.189339,10.856358],"type":"Point"}
}