{
  "type": "Feature",
  "properties": {
    "iso:country":"IN",
    "ks:ks_alt_nam":"KUD.",
    "ks:ks_name":"Kud.",
    "ks:ks_pop":567,
    "ks:ks_type":"HABITATION",
    "name:eng_x_preferred":[
        "Kud."
    ],
    "wof:name":"Kud.",
    "wof:placetype":"locality",
    "wof:population":567
},
  "geometry": {"coordinates":[85.24239300000001,23.97062],"type":"Point"}
}