{
  "type": "Feature",
  "properties": {
    "iso:country":"IN",
    "ks:ks_name":"Dokephodpada",
    "ks:ks_pop":130,
    "ks:ks_type":"HABITATION",
    "name:eng_x_preferred":[
        "Dokephodpada"
    ],
    "wof:name":"Dokephodpada",
    "wof:placetype":"locality",
    "wof:population":130
},
  "geometry": {"coordinates":[73.023398,20.01424],"type":"Point"}
}