{
  "type": "Feature",
  "properties": {
    "gn:admin1_code":"3.0",
    "gn:admin2_code":"304",
    "gn:asciiname":"Banmurigaon",
    "gn:country_code":"IN",
    "gn:dem":60,
    "gn:feature_class":"P",
    "gn:feature_code":"PPL",
    "gn:name":"B\u0101nmurigaon",
    "gn:population":0,
    "gn:timezone":"Asia/Kolkata",
    "iso:country":"IN",
    "wof:name":"Banmurigaon",
    "wof:placetype":"neighbourhood"
},
  "geometry": {"coordinates":[92.23333,26.35],"type":"Point"}
}