{
  "type": "Feature",
  "properties": {
    "iso:country":"IN",
    "ks:ks_name":"Harizon Tola",
    "ks:ks_pop":401,
    "ks:ks_type":"HABITATION",
    "name:eng_x_preferred":[
        "Harizon Tola"
    ],
    "wof:name":"Harizon Tola",
    "wof:placetype":"locality",
    "wof:population":401
},
  "geometry": {"coordinates":[86.884247,25.134329],"type":"Point"}
}