{
  "type": "Feature",
  "properties": {
    "iso:country":"IN",
    "ks:ks_name":"Meerpur",
    "ks:ks_pop":261,
    "ks:ks_type":"HABITATION",
    "name:eng_x_preferred":[
        "Meerpur"
    ],
    "wof:name":"Meerpur",
    "wof:placetype":"locality",
    "wof:population":261
},
  "geometry": {"coordinates":[83.231708,25.692291],"type":"Point"}
}