{
  "type": "Feature",
  "properties": {
    "iso:country":"IN",
    "ks:ks_name":"Dulungdiha",
    "ks:ks_pop":71,
    "ks:ks_type":"HABITATION",
    "name:eng_x_preferred":[
        "Dulungdiha"
    ],
    "wof:name":"Dulungdiha",
    "wof:placetype":"locality",
    "wof:population":71
},
  "geometry": {"coordinates":[86.68607,22.629089],"type":"Point"}
}