{
  "type": "Feature",
  "properties": {
    "iso:country":"IN",
    "ks:ks_name":"Kurmi Tola",
    "ks:ks_pop":441,
    "ks:ks_type":"HABITATION",
    "ks:ks_uagg_main":0,
    "name:eng_x_preferred":[
        "Kurmi Tola"
    ],
    "wof:name":"Kurmi Tola",
    "wof:placetype":"neighbourhood",
    "wof:population":441
},
  "geometry": {"coordinates":[84.62564999999999,27.044043],"type":"Point"}
}