{
  "type": "Feature",
  "properties": {
    "iso:country":"IN",
    "ks:ks_name":"Chhawaripara",
    "ks:ks_pop":259,
    "ks:ks_type":"HABITATION",
    "name:eng_x_preferred":[
        "Chhawaripara"
    ],
    "wof:name":"Chhawaripara",
    "wof:placetype":"locality",
    "wof:population":259
},
  "geometry": {"coordinates":[83.78789999999999,23.598299],"type":"Point"}
}