{
  "type": "Feature",
  "properties": {
    "iso:country":"IN",
    "ks:ks_name":"Madhya Churakuthi",
    "ks:ks_pop":1332,
    "ks:ks_type":"HABITATION",
    "ks:ks_uagg_main":0,
    "name:eng_x_preferred":[
        "Madhya Churakuthi"
    ],
    "wof:name":"Madhya Churakuthi",
    "wof:placetype":"neighbourhood",
    "wof:population":1332
},
  "geometry": {"coordinates":[88.072441,26.083503],"type":"Point"}
}