{
  "type": "Feature",
  "properties": {
    "gn:admin1_code":"24.0",
    "gn:admin2_code":"117.0",
    "gn:asciiname":"Utraj",
    "gn:country_code":"IN",
    "gn:dem":1340,
    "gn:feature_class":"P",
    "gn:feature_code":"PPL",
    "gn:name":"Utraj",
    "gn:population":0,
    "gn:timezone":"Asia/Kolkata",
    "iso:country":"IN",
    "ks:ks_name":"Utraj",
    "ks:ks_pop":290,
    "ks:ks_type":"VILLAGE",
    "name:eng_x_preferred":[
        "Utraj"
    ],
    "wof:name":"Utraj",
    "wof:placetype":"locality",
    "wof:population":290
},
  "geometry": {"coordinates":[72.78515,24.663253],"type":"Point"}
}