{
  "type": "Feature",
  "properties": {
    "iso:country":"IN",
    "ks:ks_name":"Adivarekarwadi",
    "ks:ks_pop":94,
    "ks:ks_type":"HABITATION",
    "name:eng_x_preferred":[
        "Adivarekarwadi"
    ],
    "wof:name":"Adivarekarwadi",
    "wof:placetype":"locality",
    "wof:population":94
},
  "geometry": {"coordinates":[73.58744799999999,16.484851],"type":"Point"}
}