{
  "type": "Feature",
  "properties": {
    "iso:country":"IN",
    "ks:ks_alt_nam":"Cholakura Pt III",
    "ks:ks_name":"Cholakura Pt Iii",
    "ks:ks_pop":1267,
    "ks:ks_type":"HABITATION",
    "name:eng_x_preferred":[
        "Cholakura Pt Iii"
    ],
    "wof:name":"Cholakura Pt Iii",
    "wof:placetype":"locality",
    "wof:population":1267
},
  "geometry": {"coordinates":[90.279731,26.148347],"type":"Point"}
}