{
  "type": "Feature",
  "properties": {
    "iso:country":"IN",
    "ks:ks_name":"Arua Par",
    "ks:ks_pop":204,
    "ks:ks_type":"HABITATION",
    "name:eng_x_preferred":[
        "Arua Par"
    ],
    "wof:name":"Arua Par",
    "wof:placetype":"locality",
    "wof:population":204
},
  "geometry": {"coordinates":[85.81215,25.251864],"type":"Point"}
}