{
  "type": "Feature",
  "properties": {
    "iso:country":"IN",
    "ks:ks_name":"Chaobas",
    "ks:ks_pop":3763,
    "ks:ks_type":"HABITATION",
    "name:eng_x_preferred":[
        "Chaobas"
    ],
    "wof:name":"Chaobas",
    "wof:placetype":"locality",
    "wof:population":3763
},
  "geometry": {"coordinates":[75.745619,30.086351],"type":"Point"}
}