{
  "type": "Feature",
  "properties": {
    "iso:country":"IN",
    "ks:ks_name":"Mohammadpur Narangi",
    "ks:ks_pop":474,
    "ks:ks_type":"VILLAGE",
    "name:eng_x_preferred":[
        "Mohammadpur Narangi"
    ],
    "wof:name":"Mohammadpur Narangi",
    "wof:placetype":"locality",
    "wof:population":474
},
  "geometry": {"coordinates":[85.390283,25.85013],"type":"Point"}
}