{
  "type": "Feature",
  "properties": {
    "iso:country":"IN",
    "ks:ks_name":"Bhada Mal.",
    "ks:ks_pop":690,
    "ks:ks_type":"VILLAGE",
    "name:eng_x_preferred":[
        "Bhada Mal."
    ],
    "wof:name":"Bhada Mal.",
    "wof:placetype":"locality",
    "wof:population":690
},
  "geometry": {"coordinates":[80.394632,22.214742],"type":"Point"}
}