{
  "type": "Feature",
  "properties": {
    "gn:admin1_code":"34.0",
    "gn:admin2_code":"212.0",
    "gn:asciiname":"Babhni",
    "gn:country_code":"IN",
    "gn:dem":31,
    "gn:feature_class":"P",
    "gn:feature_code":"PPL",
    "gn:name":"Babhni",
    "gn:population":0,
    "gn:timezone":"Asia/Kolkata",
    "iso:country":"IN",
    "ks:ks_name":"Babhni",
    "ks:ks_pop":1441,
    "ks:ks_type":"VILLAGE",
    "ks:ks_uagg_main":0,
    "name:eng_x_preferred":[
        "Babhni"
    ],
    "wof:name":"Babhni",
    "wof:placetype":"neighbourhood",
    "wof:population":1441
},
  "geometry": {"coordinates":[87.729738,25.44013],"type":"Point"}
}