{
  "type": "Feature",
  "properties": {
    "iso:country":"IN",
    "ks:ks_name":"Survewasti",
    "ks:ks_pop":177,
    "ks:ks_type":"HABITATION",
    "name:eng_x_preferred":[
        "Survewasti"
    ],
    "wof:name":"Survewasti",
    "wof:placetype":"locality",
    "wof:population":177
},
  "geometry": {"coordinates":[74.999,18.013],"type":"Point"}
}