{
  "type": "Feature",
  "properties": {
    "iso:country":"IN",
    "ks:ks_name":"Kothagajjalavari Palle",
    "ks:ks_pop":824,
    "ks:ks_type":"HABITATION",
    "name:eng_x_preferred":[
        "Kothagajjalavari Palle"
    ],
    "wof:name":"Kothagajjalavari Palle",
    "wof:placetype":"locality",
    "wof:population":824
},
  "geometry": {"coordinates":[78.79675,13.701406],"type":"Point"}
}