{
  "type": "Feature",
  "properties": {
    "iso:country":"IN",
    "ks:ks_alt_nam":"GADONG",
    "ks:ks_name":"Gadong",
    "ks:ks_pop":1451,
    "ks:ks_type":"HABITATION",
    "name:eng_x_preferred":[
        "Gadong"
    ],
    "wof:name":"Gadong",
    "wof:placetype":"locality",
    "wof:population":1451
},
  "geometry": {"coordinates":[89.052329,26.582016],"type":"Point"}
}