{
  "type": "Feature",
  "properties": {
    "gn:admin1_code":"36.0",
    "gn:admin2_code":"189.0",
    "gn:asciiname":"Bariapatti",
    "gn:country_code":"IN",
    "gn:dem":85,
    "gn:feature_class":"P",
    "gn:feature_code":"PPL",
    "gn:name":"Bariapatti",
    "gn:population":0,
    "gn:timezone":"Asia/Kolkata",
    "iso:country":"IN",
    "wof:name":"Bariapatti",
    "wof:placetype":"locality"
},
  "geometry": {"coordinates":[83.97104,26.8679],"type":"Point"}
}