{
  "type": "Feature",
  "properties": {
    "gn:admin1_code":"13",
    "gn:admin2_code":"597.0",
    "gn:asciiname":"Pambadi",
    "gn:cc2":"IN",
    "gn:country_code":"IN",
    "gn:dem":102,
    "gn:feature_class":"P",
    "gn:feature_code":"PPL",
    "gn:name":"P\u0101mb\u0101di",
    "gn:population":0,
    "gn:timezone":"Asia/Kolkata",
    "iso:country":"IN",
    "name:und_x_variant":[
        "Pampadi",
        "P\u0101mb\u0101di",
        "Pampady"
    ],
    "wof:name":"Pambadi",
    "wof:placetype":"locality"
},
  "geometry": {"coordinates":[76.66667,9.56667],"type":"Point"}
}