{
  "type": "Feature",
  "properties": {
    "iso:country":"IN",
    "ks:ks_name":"Ravidiputtu",
    "ks:ks_pop":105,
    "ks:ks_type":"HABITATION",
    "name:eng_x_preferred":[
        "Ravidiputtu"
    ],
    "wof:name":"Ravidiputtu",
    "wof:placetype":"locality",
    "wof:population":105
},
  "geometry": {"coordinates":[82.478324,18.539121],"type":"Point"}
}