{
  "type": "Feature",
  "properties": {
    "gn:admin1_code":"35.0",
    "gn:admin2_code":"449.0",
    "gn:asciiname":"Dhargaon",
    "gn:country_code":"IN",
    "gn:dem":404,
    "gn:feature_class":"P",
    "gn:feature_code":"PPL",
    "gn:name":"Dh\u0101rgaon",
    "gn:population":0,
    "gn:timezone":"Asia/Kolkata",
    "iso:country":"IN",
    "wof:name":"Dhargaon",
    "wof:placetype":"locality"
},
  "geometry": {"coordinates":[78.30386,22.56987],"type":"Point"}
}