{
  "type": "Feature",
  "properties": {
    "gn:admin1_code":"35.0",
    "gn:admin2_code":"449.0",
    "gn:asciiname":"Dhargaon",
    "gn:country_code":"IN",
    "gn:dem":404,
    "gn:feature_class":"P",
    "gn:feature_code":"PPL",
    "gn:name":"Dh\u0101rgaon",
    "gn:population":0,
    "gn:timezone":"Asia/Kolkata",
    "iso:country":"IN",
    "ks:ks_name":"Dhargaon",
    "ks:ks_pop":183,
    "ks:ks_type":"VILLAGE",
    "name:eng_x_preferred":[
        "Dhargaon"
    ],
    "wof:name":"Dhargaon",
    "wof:placetype":"locality",
    "wof:population":183
},
  "geometry": {"coordinates":[78.300916,22.567116],"type":"Point"}
}