{
  "type": "Feature",
  "properties": {
    "iso:country":"IN",
    "ks:ks_alt_nam":"BHAWARON KA WADIYA",
    "ks:ks_name":"Bhawaron Ka Wadiya",
    "ks:ks_pop":330,
    "ks:ks_type":"HABITATION",
    "name:eng_x_preferred":[
        "Bhawaron Ka Wadiya"
    ],
    "wof:name":"Bhawaron Ka Wadiya",
    "wof:placetype":"locality",
    "wof:population":330
},
  "geometry": {"coordinates":[74.037999,25.321291],"type":"Point"}
}