{
  "type": "Feature",
  "properties": {
    "gn:admin1_code":"19.0",
    "gn:admin2_code":"583.0",
    "gn:asciiname":"Bidkere",
    "gn:country_code":"IN",
    "gn:dem":928,
    "gn:feature_class":"P",
    "gn:feature_code":"PPL",
    "gn:name":"Bidkere",
    "gn:population":0,
    "gn:timezone":"Asia/Kolkata",
    "iso:country":"IN",
    "wof:name":"Bidkere",
    "wof:placetype":"neighbourhood"
},
  "geometry": {"coordinates":[77.60773,13.34565],"type":"Point"}
}