{
  "type": "Feature",
  "properties": {
    "iso:country":"IN",
    "ks:ks_alt_nam":"UPER JABLA",
    "ks:ks_name":"Uper Jabla",
    "ks:ks_pop":196,
    "ks:ks_type":"HABITATION",
    "name:eng_x_preferred":[
        "Uper Jabla"
    ],
    "wof:name":"Uper Jabla",
    "wof:placetype":"locality",
    "wof:population":196
},
  "geometry": {"coordinates":[83.71884799999999,22.868384],"type":"Point"}
}