{
  "type": "Feature",
  "properties": {
    "gn:admin1_code":"2.0",
    "gn:admin2_code":"549.0",
    "gn:asciiname":"Jandrapeta",
    "gn:country_code":"IN",
    "gn:dem":11,
    "gn:feature_class":"P",
    "gn:feature_code":"PPL",
    "gn:name":"Jandrapeta",
    "gn:population":0,
    "gn:timezone":"Asia/Kolkata",
    "iso:country":"IN",
    "name:tel_x_preferred":[
        "\u0c1c\u0c3e\u0c02\u0c21\u0c4d\u0c30\u0c2a\u0c47\u0c1f"
    ],
    "wof:name":"Jandrapeta",
    "wof:placetype":"locality"
},
  "geometry": {"coordinates":[80.33388000000002,15.8059],"type":"Point"}
}