{
  "type": "Feature",
  "properties": {
    "iso:country":"IN",
    "ks:ks_name":"Nagla Bhularia",
    "ks:ks_pop":83,
    "ks:ks_type":"HABITATION",
    "name:eng_x_preferred":[
        "Nagla Bhularia"
    ],
    "wof:name":"Nagla Bhularia",
    "wof:placetype":"locality",
    "wof:population":83
},
  "geometry": {"coordinates":[78.188419,27.270364],"type":"Point"}
}