{
  "type": "Feature",
  "properties": {
    "iso:country":"IN",
    "ks:ks_name":"Tentulikalipadar",
    "ks:ks_pop":30,
    "ks:ks_type":"HABITATION",
    "name:eng_x_preferred":[
        "Tentulikalipadar"
    ],
    "wof:name":"Tentulikalipadar",
    "wof:placetype":"locality",
    "wof:population":30
},
  "geometry": {"coordinates":[83.61042399999999,19.354276],"type":"Point"}
}