{
  "type": "Feature",
  "properties": {
    "iso:country":"IN",
    "ks:ks_name":"Varchi Sawantwadi",
    "ks:ks_pop":55,
    "ks:ks_type":"HABITATION",
    "name:eng_x_preferred":[
        "Varchi Sawantwadi"
    ],
    "wof:name":"Varchi Sawantwadi",
    "wof:placetype":"locality",
    "wof:population":55
},
  "geometry": {"coordinates":[73.65055599999999,16.154028],"type":"Point"}
}