{
  "type": "Feature",
  "properties": {
    "iso:country":"IN",
    "ks:ks_alt_nam":"Narakkadavu ST colony",
    "ks:ks_name":"Narakkadavu St Colony",
    "ks:ks_pop":1100,
    "ks:ks_type":"HABITATION",
    "name:eng_x_preferred":[
        "Narakkadavu St Colony"
    ],
    "wof:name":"Narakkadavu St Colony",
    "wof:placetype":"locality",
    "wof:population":1100
},
  "geometry": {"coordinates":[75.937583,11.701464],"type":"Point"}
}