{
  "type": "Feature",
  "properties": {
    "iso:country":"IN",
    "ks:ks_name":"Teganahawa Badaka",
    "ks:ks_pop":163,
    "ks:ks_type":"HABITATION",
    "ks:ks_uagg_main":0,
    "name:eng_x_preferred":[
        "Teganahawa Badaka"
    ],
    "wof:name":"Teganahawa Badaka",
    "wof:placetype":"neighbourhood",
    "wof:population":163
},
  "geometry": {"coordinates":[82.446213,27.043759],"type":"Point"}
}