{
  "type": "Feature",
  "properties": {
    "iso:country":"IN",
    "ks:ks_name":"Ghadiwadi",
    "ks:ks_pop":127,
    "ks:ks_type":"HABITATION",
    "name:eng_x_preferred":[
        "Ghadiwadi"
    ],
    "wof:name":"Ghadiwadi",
    "wof:placetype":"locality",
    "wof:population":127
},
  "geometry": {"coordinates":[73.57468900000001,15.919727],"type":"Point"}
}