{
  "type": "Feature",
  "properties": {
    "gn:admin1_code":"23",
    "gn:admin2_code":"51.0",
    "gn:asciiname":"Taba",
    "gn:country_code":"IN",
    "gn:dem":303,
    "gn:feature_class":"P",
    "gn:feature_code":"PPL",
    "gn:name":"Taba",
    "gn:population":0,
    "gn:timezone":"Asia/Kolkata",
    "iso:country":"IN",
    "name:ceb_x_preferred":[
        "Taba"
    ],
    "name:deu_x_preferred":[
        "Taba"
    ],
    "name:fra_x_preferred":[
        "Taba"
    ],
    "name:nld_x_preferred":[
        "Taba"
    ],
    "name:spa_x_preferred":[
        "Taba"
    ],
    "name:swe_x_preferred":[
        "Taba"
    ],
    "wof:name":"Taba",
    "wof:placetype":"locality"
},
  "geometry": {"coordinates":[76.52311,31.05619],"type":"Point"}
}