{
  "type": "Feature",
  "properties": {
    "gn:admin1_code":"34.0",
    "gn:admin2_code":"235.0",
    "gn:asciiname":"Kusa",
    "gn:country_code":"IN",
    "gn:dem":124,
    "gn:feature_class":"P",
    "gn:feature_code":"PPL",
    "gn:name":"Kus\u0101",
    "gn:population":0,
    "gn:timezone":"Asia/Kolkata",
    "iso:country":"IN",
    "name:ceb_x_preferred":[
        "Kusa"
    ],
    "name:deu_x_preferred":[
        "Kusa"
    ],
    "name:nld_x_preferred":[
        "Kusa"
    ],
    "name:rus_x_preferred":[
        "\u041a\u0443\u0441\u0430"
    ],
    "name:swe_x_preferred":[
        "Kusa"
    ],
    "wof:name":"Kusa",
    "wof:placetype":"locality"
},
  "geometry": {"coordinates":[84.46484,24.69708],"type":"Point"}
}