{
  "type": "Feature",
  "properties": {
    "gn:admin1_code":"16.0",
    "gn:admin2_code":"510.0",
    "gn:asciiname":"Marsul",
    "gn:country_code":"IN",
    "gn:dem":421,
    "gn:feature_class":"P",
    "gn:feature_code":"PPL",
    "gn:name":"Marsul",
    "gn:population":0,
    "gn:timezone":"Asia/Kolkata",
    "iso:country":"IN",
    "wof:name":"Marsul",
    "wof:placetype":"locality"
},
  "geometry": {"coordinates":[77.66308000000002,19.64629],"type":"Point"}
}