{
  "type": "Feature",
  "properties": {
    "gn:admin1_code":"21",
    "gn:admin2_code":"398.0",
    "gn:asciiname":"Adra",
    "gn:country_code":"IN",
    "gn:dem":1033,
    "gn:feature_class":"P",
    "gn:feature_code":"PPL",
    "gn:name":"Adra",
    "gn:population":0,
    "gn:timezone":"Asia/Kolkata",
    "iso:country":"IN",
    "name:ceb_x_preferred":[
        "Adra"
    ],
    "name:fra_x_preferred":[
        "Adra"
    ],
    "name:glg_x_preferred":[
        "Adra"
    ],
    "name:hrv_x_preferred":[
        "Adra"
    ],
    "name:hye_x_preferred":[
        "\u0531\u0564\u0580\u0561"
    ],
    "name:ita_x_preferred":[
        "Adra"
    ],
    "name:jpn_x_preferred":[
        "\u30a2\u30c9\u30e9"
    ],
    "name:msa_x_preferred":[
        "Adra"
    ],
    "name:new_x_preferred":[
        "\u0906\u0926\u094d\u0930\u093e"
    ],
    "name:nld_x_preferred":[
        "Adra"
    ],
    "name:pol_x_preferred":[
        "Adra"
    ],
    "name:ron_x_preferred":[
        "Adra"
    ],
    "name:rus_x_preferred":[
        "\u0410\u0434\u0440\u0430"
    ],
    "name:sco_x_preferred":[
        "Adra"
    ],
    "name:spa_x_preferred":[
        "Adra"
    ],
    "name:swe_x_preferred":[
        "Adra"
    ],
    "name:vie_x_preferred":[
        "Adra"
    ],
    "wof:name":"Adra",
    "wof:placetype":"locality"
},
  "geometry": {"coordinates":[82.75224,18.47466],"type":"Point"}
}