{
  "type": "Feature",
  "properties": {
    "iso:country":"IN",
    "ks:ks_name":"Sagadbhanga",
    "ks:ks_pop":919,
    "ks:ks_type":"VILLAGE",
    "name:eng_x_preferred":[
        "Sagadbhanga"
    ],
    "wof:name":"Sagadbhanga",
    "wof:placetype":"locality",
    "wof:population":919
},
  "geometry": {"coordinates":[85.389955,20.068647],"type":"Point"}
}