{
  "type": "Feature",
  "properties": {
    "iso:country":"IN",
    "ks:ks_name":"Narayanpur",
    "ks:ks_pop":536,
    "ks:ks_type":"VILLAGE",
    "name:eng_x_preferred":[
        "Narayanpur"
    ],
    "wof:name":"Narayanpur",
    "wof:placetype":"locality",
    "wof:population":536
},
  "geometry": {"coordinates":[87.396443,21.648606],"type":"Point"}
}