{
  "type": "Feature",
  "properties": {
    "iso:country":"IN",
    "ks:ks_name":"Bhawana",
    "ks:ks_pop":0,
    "ks:ks_type":"VILLAGE",
    "name:eng_x_preferred":[
        "Bhawana"
    ],
    "wof:name":"Bhawana",
    "wof:placetype":"locality",
    "wof:population":0
},
  "geometry": {"coordinates":[75.20331299999999,32.091336],"type":"Point"}
}