{
  "type": "Feature",
  "properties": {
    "gn:admin1_code":"12",
    "gn:admin2_code":"15.0",
    "gn:asciiname":"Kandimarg",
    "gn:country_code":"IN",
    "gn:dem":2311,
    "gn:feature_class":"P",
    "gn:feature_code":"PPL",
    "gn:name":"K\u0101ndimarg",
    "gn:population":0,
    "gn:timezone":"Asia/Kolkata",
    "iso:country":"IN",
    "wof:name":"Kandimarg",
    "wof:placetype":"locality"
},
  "geometry": {"coordinates":[74.95704000000001,33.54717],"type":"Point"}
}