{
  "type": "Feature",
  "properties": {
    "iso:country":"IN",
    "ks:ks_name":"Bhavuli",
    "ks:ks_pop":71,
    "ks:ks_type":"HABITATION",
    "name:eng_x_preferred":[
        "Bhavuli"
    ],
    "wof:name":"Bhavuli",
    "wof:placetype":"locality",
    "wof:population":71
},
  "geometry": {"coordinates":[75.081388,12.857148],"type":"Point"}
}