{
  "type": "Feature",
  "properties": {
    "gn:admin1_code":"21",
    "gn:admin2_code":"390.0",
    "gn:asciiname":"Sriramapur",
    "gn:country_code":"IN",
    "gn:dem":834,
    "gn:feature_class":"P",
    "gn:feature_code":"PPL",
    "gn:name":"Sr\u012br\u0101mapur",
    "gn:population":0,
    "gn:timezone":"Asia/Kolkata",
    "iso:country":"IN",
    "wof:name":"Sriramapur",
    "wof:placetype":"locality"
},
  "geometry": {"coordinates":[83.90000000000001,19.83333],"type":"Point"}
}