{
  "type": "Feature",
  "properties": {
    "iso:country":"IN",
    "ks:ks_name":"Patil Wasti",
    "ks:ks_pop":132,
    "ks:ks_type":"HABITATION",
    "ks:ks_uagg_main":0,
    "name:eng_x_preferred":[
        "Patil Wasti"
    ],
    "wof:name":"Patil Wasti",
    "wof:placetype":"neighbourhood",
    "wof:population":132
},
  "geometry": {"coordinates":[75.43691,18.056163],"type":"Point"}
}