{
  "type": "Feature",
  "properties": {
    "iso:country":"IN",
    "ks:ks_name":"Regulagudem",
    "ks:ks_pop":273,
    "ks:ks_type":"HABITATION",
    "name:eng_x_preferred":[
        "Regulagudem"
    ],
    "wof:name":"Regulagudem",
    "wof:placetype":"locality",
    "wof:population":273
},
  "geometry": {"coordinates":[80.625333,17.812047],"type":"Point"}
}