{
  "type": "Feature",
  "properties": {
    "gn:admin1_code":"28.0",
    "gn:admin2_code":"327.0",
    "gn:asciiname":"Nokdanda",
    "gn:country_code":"IN",
    "gn:dem":1611,
    "gn:feature_class":"P",
    "gn:feature_code":"PPL",
    "gn:name":"Nokd\u0101nda",
    "gn:population":0,
    "gn:timezone":"Asia/Kolkata",
    "iso:country":"IN",
    "wof:name":"Nokdanda",
    "wof:placetype":"locality"
},
  "geometry": {"coordinates":[88.6249,27.04335],"type":"Point"}
}