{
  "type": "Feature",
  "properties": {
    "gn:admin1_code":"21.0",
    "gn:admin2_code":"398.0",
    "gn:asciiname":"Parli",
    "gn:country_code":"IN",
    "gn:dem":829,
    "gn:feature_class":"P",
    "gn:feature_code":"PPL",
    "gn:name":"Parli",
    "gn:population":0,
    "gn:timezone":"Asia/Kolkata",
    "iso:country":"IN",
    "name:deu_x_preferred":[
        "Parli"
    ],
    "wof:name":"Parli",
    "wof:placetype":"locality"
},
  "geometry": {"coordinates":[82.52953000000002,18.72953],"type":"Point"}
}