{
  "type": "Feature",
  "properties": {
    "iso:country":"IN",
    "ks:ks_name":"Ramapur",
    "ks:ks_pop":1018,
    "ks:ks_type":"VILLAGE",
    "ks:ks_uagg_main":0,
    "name:eng_x_preferred":[
        "Ramapur"
    ],
    "wof:name":"Ramapur",
    "wof:placetype":"neighbourhood",
    "wof:population":1018
},
  "geometry": {"coordinates":[82.029366,26.046126],"type":"Point"}
}