{
  "type": "Feature",
  "properties": {
    "iso:country":"IN",
    "ks:ks_name":"Kajibasan",
    "ks:ks_pop":1364,
    "ks:ks_type":"VILLAGE",
    "ks:ks_uagg_main":0,
    "name:eng_x_preferred":[
        "Kajibasan"
    ],
    "wof:name":"Kajibasan",
    "wof:placetype":"locality",
    "wof:population":1364
},
  "geometry": {"coordinates":[87.831265,21.778849],"type":"Point"}
}