{
  "type": "Feature",
  "properties": {
    "iso:country":"IN",
    "ks:ks_name":"Katdanga Satdubi Pt.II",
    "ks:ks_pop":1893,
    "ks:ks_type":"VILLAGE",
    "name:eng_x_preferred":[
        "Katdanga Satdubi Pt.II"
    ],
    "wof:name":"Katdanga Satdubi Pt.II",
    "wof:placetype":"locality",
    "wof:population":1893
},
  "geometry": {"coordinates":[89.965104,25.838893],"type":"Point"}
}