{
  "type": "Feature",
  "properties": {
    "iso:country":"IN",
    "ks:ks_name":"Nanyathanda",
    "ks:ks_pop":12,
    "ks:ks_type":"HABITATION",
    "name:eng_x_preferred":[
        "Nanyathanda"
    ],
    "wof:name":"Nanyathanda",
    "wof:placetype":"locality",
    "wof:population":12
},
  "geometry": {"coordinates":[79.159159,17.990969],"type":"Point"}
}