{
  "type": "Feature",
  "properties": {
    "gn:admin1_code":"36",
    "gn:admin2_code":"158.0",
    "gn:asciiname":"Chandka Bakhsh Purwa",
    "gn:country_code":"IN",
    "gn:dem":111,
    "gn:feature_class":"P",
    "gn:feature_code":"PPL",
    "gn:name":"Ch\u0101ndka Bakhsh Purwa",
    "gn:population":0,
    "gn:timezone":"Asia/Kolkata",
    "iso:country":"IN",
    "wof:name":"Chandka Bakhsh Purwa",
    "wof:placetype":"locality"
},
  "geometry": {"coordinates":[81.40437,26.01065],"type":"Point"}
}