{
  "type": "Feature",
  "properties": {
    "iso:country":"IN",
    "ks:ks_name":"Nohra",
    "ks:ks_pop":1836,
    "ks:ks_type":"HABITATION",
    "ks:ks_uagg_main":0,
    "name:eng_x_preferred":[
        "Nohra"
    ],
    "wof:name":"Nohra",
    "wof:placetype":"neighbourhood",
    "wof:population":1836
},
  "geometry": {"coordinates":[73.63164999999999,24.531478],"type":"Point"}
}