{
  "type": "Feature",
  "properties": {
    "iso:country":"IN",
    "ks:ks_name":"Karaikudipatti",
    "ks:ks_pop":130,
    "ks:ks_type":"HABITATION",
    "ks:ks_uagg_main":0,
    "name:eng_x_preferred":[
        "Karaikudipatti"
    ],
    "wof:name":"Karaikudipatti",
    "wof:placetype":"neighbourhood",
    "wof:population":130
},
  "geometry": {"coordinates":[78.36291300000001,10.140285],"type":"Point"}
}