{
  "type": "Feature",
  "properties": {
    "gn:admin1_code":"12.0",
    "gn:admin2_code":"9.0",
    "gn:asciiname":"Panzgam",
    "gn:country_code":"IN",
    "gn:dem":1602,
    "gn:feature_class":"P",
    "gn:feature_code":"PPL",
    "gn:name":"Panzgam",
    "gn:population":0,
    "gn:timezone":"Asia/Kolkata",
    "iso:country":"IN",
    "name:eng_x_preferred":[
        "Panzgam"
    ],
    "wof:name":"Panzgam",
    "wof:placetype":"locality"
},
  "geometry": {"coordinates":[74.62236999999998,34.43639],"type":"Point"}
}