{
  "type": "Feature",
  "properties": {
    "iso:country":"IN",
    "ks:ks_name":"Dedharota",
    "ks:ks_pop":3396,
    "ks:ks_type":"HABITATION",
    "name:eng_x_preferred":[
        "Dedharota"
    ],
    "wof:name":"Dedharota",
    "wof:placetype":"locality",
    "wof:population":3396
},
  "geometry": {"coordinates":[72.84699999999999,23.627389],"type":"Point"}
}