{
  "type": "Feature",
  "properties": {
    "iso:country":"IN",
    "ks:ks_name":"Karchewadi",
    "ks:ks_pop":350,
    "ks:ks_type":"HABITATION",
    "name:eng_x_preferred":[
        "Karchewadi"
    ],
    "wof:name":"Karchewadi",
    "wof:placetype":"locality",
    "wof:population":350
},
  "geometry": {"coordinates":[74.65550500000001,17.910825],"type":"Point"}
}