{
  "type": "Feature",
  "properties": {
    "iso:country":"IN",
    "ks:ks_name":"Verey",
    "ks:ks_pop":225,
    "ks:ks_type":"HABITATION",
    "ks:ks_uagg_main":0,
    "name:eng_x_preferred":[
        "Verey"
    ],
    "wof:name":"Verey",
    "wof:placetype":"neighbourhood",
    "wof:population":225
},
  "geometry": {"coordinates":[81.480986,26.123554],"type":"Point"}
}