{
  "type": "Feature",
  "properties": {
    "gn:admin1_code":"19.0",
    "gn:admin2_code":"581.0",
    "gn:asciiname":"Karadagura",
    "gn:country_code":"IN",
    "gn:dem":766,
    "gn:feature_class":"P",
    "gn:feature_code":"PPL",
    "gn:name":"Karadag\u016bra",
    "gn:population":0,
    "gn:timezone":"Asia/Kolkata",
    "iso:country":"IN",
    "wof:name":"Karadagura",
    "wof:placetype":"locality"
},
  "geometry": {"coordinates":[78.40295999999999,12.93828],"type":"Point"}
}