{
  "type": "Feature",
  "properties": {
    "iso:country":"IN",
    "ks:ks_name":"Nuabondiki",
    "ks:ks_pop":186,
    "ks:ks_type":"VILLAGE",
    "name:eng_x_preferred":[
        "Nuabondiki"
    ],
    "wof:name":"Nuabondiki",
    "wof:placetype":"locality",
    "wof:population":186
},
  "geometry": {"coordinates":[81.797164,18.430128],"type":"Point"}
}