{
  "type": "Feature",
  "properties": {
    "iso:country":"IN",
    "ks:ks_name":"Jarga",
    "ks:ks_pop":223,
    "ks:ks_type":"HABITATION",
    "name:eng_x_preferred":[
        "Jarga"
    ],
    "wof:name":"Jarga",
    "wof:placetype":"locality",
    "wof:population":223
},
  "geometry": {"coordinates":[78.05810200000001,26.759263],"type":"Point"}
}