{
  "type": "Feature",
  "properties": {
    "gn:admin1_code":"11.0",
    "gn:admin2_code":"33.0",
    "gn:asciiname":"Khanar",
    "gn:country_code":"IN",
    "gn:dem":1711,
    "gn:feature_class":"P",
    "gn:feature_code":"PPL",
    "gn:name":"Khan\u0101r",
    "gn:population":0,
    "gn:timezone":"Asia/Kolkata",
    "iso:country":"IN",
    "name:bih_x_preferred":[
        "\u0916\u0928\u093e\u0930"
    ],
    "name:ceb_x_preferred":[
        "Khanar"
    ],
    "name:mai_x_preferred":[
        "\u0916\u0928\u093e\u0930"
    ],
    "name:msa_x_preferred":[
        "Khanar"
    ],
    "name:nep_x_preferred":[
        "\u0916\u0928\u093e\u0930"
    ],
    "name:new_x_preferred":[
        "\u0916\u0928\u093e\u0930"
    ],
    "name:pol_x_preferred":[
        "Khanar"
    ],
    "wof:name":"Khanar",
    "wof:placetype":"locality"
},
  "geometry": {"coordinates":[77.40483,31.01776],"type":"Point"}
}