{
  "type": "Feature",
  "properties": {
    "iso:country":"IN",
    "ks:ks_name":"Vasaua",
    "ks:ks_pop":78,
    "ks:ks_type":"HABITATION",
    "name:eng_x_preferred":[
        "Vasaua"
    ],
    "wof:name":"Vasaua",
    "wof:placetype":"locality",
    "wof:population":78
},
  "geometry": {"coordinates":[79.386392,26.787302],"type":"Point"}
}