{
  "type": "Feature",
  "properties": {
    "iso:country":"IN",
    "ks:ks_name":"Ashrafpur",
    "ks:ks_pop":757,
    "ks:ks_type":"HABITATION",
    "name:eng_x_preferred":[
        "Ashrafpur"
    ],
    "wof:name":"Ashrafpur",
    "wof:placetype":"locality",
    "wof:population":757
},
  "geometry": {"coordinates":[79.570297,27.849553],"type":"Point"}
}