{
  "type": "Feature",
  "properties": {
    "gn:admin1_code":"19.0",
    "gn:admin2_code":"570.0",
    "gn:asciiname":"Kalayyanakoppalu",
    "gn:country_code":"IN",
    "gn:dem":775,
    "gn:feature_class":"P",
    "gn:feature_code":"PPL",
    "gn:name":"K\u0101layyanakoppalu",
    "gn:population":0,
    "gn:timezone":"Asia/Kolkata",
    "iso:country":"IN",
    "wof:name":"Kalayyanakoppalu",
    "wof:placetype":"locality"
},
  "geometry": {"coordinates":[76.02081,13.61522],"type":"Point"}
}