{
  "type": "Feature",
  "properties": {
    "gn:admin1_code":"40",
    "gn:admin2_code":"541.0",
    "gn:asciiname":"Ibrahimpeta",
    "gn:country_code":"IN",
    "gn:dem":58,
    "gn:feature_class":"P",
    "gn:feature_code":"PPL",
    "gn:name":"Ibr\u0101h\u012bmpeta",
    "gn:population":0,
    "gn:timezone":"Asia/Kolkata",
    "iso:country":"IN",
    "ks:ks_alt_nam":"Ibr\u0101h\u012bmpeta",
    "ks:ks_name":"Ibrahimpeta",
    "ks:ks_pop":503,
    "ks:ks_type":"VILLAGE",
    "name:eng_x_preferred":[
        "Ibrahimpeta"
    ],
    "name:eng_x_variant":[
        "Ibr\u0101h\u012bmpeta"
    ],
    "wof:name":"Ibrahimpeta",
    "wof:placetype":"locality",
    "wof:population":503
},
  "geometry": {"coordinates":[80.993931,17.633195],"type":"Point"}
}