{
  "type": "Feature",
  "properties": {
    "iso:country":"IN",
    "ks:ks_alt_nam":"CHARAN DAS PARA",
    "ks:ks_name":"Charan Das Para",
    "ks:ks_pop":110,
    "ks:ks_type":"HABITATION",
    "name:eng_x_preferred":[
        "Charan Das Para"
    ],
    "wof:name":"Charan Das Para",
    "wof:placetype":"locality",
    "wof:population":110
},
  "geometry": {"coordinates":[91.548965,24.025229],"type":"Point"}
}