{
  "type": "Feature",
  "properties": {
    "iso:country":"IN",
    "ks:ks_alt_nam":"MADANE WASTI",
    "ks:ks_name":"Madane Wasti",
    "ks:ks_pop":108,
    "ks:ks_type":"HABITATION",
    "name:eng_x_preferred":[
        "Madane Wasti"
    ],
    "wof:name":"Madane Wasti",
    "wof:placetype":"locality",
    "wof:population":108
},
  "geometry": {"coordinates":[74.429148,17.33863],"type":"Point"}
}