{
  "type": "Feature",
  "properties": {
    "gn:admin1_code":"36",
    "gn:admin2_code":"188.0",
    "gn:asciiname":"Tola Kodai Shah",
    "gn:country_code":"IN",
    "gn:dem":84,
    "gn:feature_class":"P",
    "gn:feature_code":"PPL",
    "gn:name":"Tola Kodai Sh\u0101h",
    "gn:population":0,
    "gn:timezone":"Asia/Kolkata",
    "iso:country":"IN",
    "wof:name":"Tola Kodai Shah",
    "wof:placetype":"neighbourhood"
},
  "geometry": {"coordinates":[83.47675,26.78475],"type":"Point"}
}