{
  "type": "Feature",
  "properties": {
    "iso:country":"IN",
    "ks:ks_name":"Karwandedara",
    "ks:ks_pop":48,
    "ks:ks_type":"HABITATION",
    "name:eng_x_preferred":[
        "Karwandedara"
    ],
    "wof:name":"Karwandedara",
    "wof:placetype":"locality",
    "wof:population":48
},
  "geometry": {"coordinates":[73.745324,19.071089],"type":"Point"}
}