{
  "type": "Feature",
  "properties": {
    "gn:admin1_code":"19",
    "gn:admin2_code":"558.0",
    "gn:asciiname":"Tornawadi",
    "gn:country_code":"IN",
    "gn:dem":571,
    "gn:feature_class":"P",
    "gn:feature_code":"PPL",
    "gn:name":"Tornaw\u0101di",
    "gn:population":0,
    "gn:timezone":"Asia/Kolkata",
    "iso:country":"IN",
    "wof:name":"Tornawadi",
    "wof:placetype":"locality"
},
  "geometry": {"coordinates":[77.25129,18.23713],"type":"Point"}
}