{
  "type": "Feature",
  "properties": {
    "iso:country":"IN",
    "ks:ks_name":"Mukundamane",
    "ks:ks_pop":38,
    "ks:ks_type":"HABITATION",
    "name:eng_x_preferred":[
        "Mukundamane"
    ],
    "wof:name":"Mukundamane",
    "wof:placetype":"locality",
    "wof:population":38
},
  "geometry": {"coordinates":[74.640878,14.980523],"type":"Point"}
}