{
  "type": "Feature",
  "properties": {
    "iso:country":"IN",
    "ks:ks_alt_nam":"4 No.line gaon",
    "ks:ks_name":"4 No.line Gaon",
    "ks:ks_pop":127,
    "ks:ks_type":"HABITATION",
    "name:eng_x_preferred":[
        "4 No.line Gaon"
    ],
    "wof:name":"4 No.line Gaon",
    "wof:placetype":"locality",
    "wof:population":127
},
  "geometry": {"coordinates":[94.813475,26.874734],"type":"Point"}
}