{
  "type": "Feature",
  "properties": {
    "iso:country":"IN",
    "ks:ks_alt_nam":"S\u0101digaw\u0101ro",
    "ks:ks_name":"Sadigawaro",
    "ks:ks_pop":811,
    "ks:ks_type":"VILLAGE",
    "name:eng_x_preferred":[
        "Sadigawaro"
    ],
    "name:eng_x_variant":[
        "S\u0101digaw\u0101ro"
    ],
    "wof:name":"Sadigawaro",
    "wof:placetype":"locality",
    "wof:population":811
},
  "geometry": {"coordinates":[86.189449,24.1719],"type":"Point"}
}