{
  "type": "Feature",
  "properties": {
    "gn:admin1_code":"39.0",
    "gn:admin2_code":"66.0",
    "gn:asciiname":"Debi Rampur",
    "gn:country_code":"IN",
    "gn:dem":593,
    "gn:feature_class":"P",
    "gn:feature_code":"PPL",
    "gn:name":"Debi R\u0101mpur",
    "gn:population":0,
    "gn:timezone":"Asia/Kolkata",
    "iso:country":"IN",
    "ks:ks_alt_nam":"Debi R\u0101mpur",
    "ks:ks_name":"Debi Rampur",
    "ks:ks_type":"VILLAGE",
    "name:eng_x_preferred":[
        "Debi Rampur"
    ],
    "name:eng_x_variant":[
        "Debi R\u0101mpur"
    ],
    "wof:name":"Debi Rampur",
    "wof:placetype":"locality"
},
  "geometry": {"coordinates":[79.282747,29.382124],"type":"Point"}
}