{
  "type": "Feature",
  "properties": {
    "gn:country":"IN",
    "gn:fcode":"PPL",
    "gn:pop":11209,
    "iso:country":"IN",
    "name:bpy_x_preferred":[
        "\u09ac\u09be\u09b0\u0996\u09c7\u09b0\u09be"
    ],
    "name:bul_x_preferred":[
        "\u0411\u0430\u0440\u043a\u0445\u0435\u0440\u0430"
    ],
    "name:eng_x_preferred":[
        "Barkhera"
    ],
    "name:fra_x_preferred":[
        "Barkhera"
    ],
    "name:ita_x_preferred":[
        "Barkhera"
    ],
    "name:mlg_x_preferred":[
        "Barkhera"
    ],
    "name:msa_x_preferred":[
        "Barkhera"
    ],
    "name:nan_x_preferred":[
        "Barkhera"
    ],
    "name:new_x_preferred":[
        "\u092c\u0930\u094d\u0916\u0947\u0930\u093e"
    ],
    "name:nld_x_preferred":[
        "Barkhera"
    ],
    "name:pol_x_preferred":[
        "Barkhera"
    ],
    "name:por_x_preferred":[
        "Barkhera"
    ],
    "name:swe_x_preferred":[
        "Barkhera"
    ],
    "name:unk_x_variant":[
        "Barkhera Kala"
    ],
    "name:urd_x_preferred":[
        "\u0628\u0631\u06a9\u06be\u06cc\u0691\u0627"
    ],
    "name:vie_x_preferred":[
        "Barkhera"
    ],
    "name:zho_x_preferred":[
        "\u5df4\u5c14\u51ef\u62c9"
    ],
    "qs:name":"Balkhera",
    "qs:name_adm0":"India",
    "qs:name_adm1":"Uttarakhand",
    "qs:photos_9r":0,
    "qs:photos_sr":0,
    "qs:placetype":"Town",
    "qs:pop_sr":"6",
    "wof:name":"Balkhera",
    "wof:placetype":"locality",
    "wof:population":11209
},
  "geometry": {"coordinates":[79.80477,28.45159],"type":"Point"}
}