{
  "type": "Feature",
  "properties": {
    "iso:country":"IN",
    "ks:ks_name":"Shindewadi",
    "ks:ks_pop":277,
    "ks:ks_type":"HABITATION",
    "name:eng_x_preferred":[
        "Shindewadi"
    ],
    "wof:name":"Shindewadi",
    "wof:placetype":"locality",
    "wof:population":277
},
  "geometry": {"coordinates":[76.170069,18.098334],"type":"Point"}
}