{
  "type": "Feature",
  "properties": {
    "gn:admin1_code":"34.0",
    "gn:admin2_code":"214.0",
    "gn:asciiname":"Bishunpur",
    "gn:country_code":"IN",
    "gn:dem":48,
    "gn:feature_class":"P",
    "gn:feature_code":"PPL",
    "gn:name":"Bishunpur",
    "gn:population":0,
    "gn:timezone":"Asia/Kolkata",
    "iso:country":"IN",
    "name:ceb_x_preferred":[
        "Bishunpur"
    ],
    "name:msa_x_preferred":[
        "Bishunpur"
    ],
    "name:new_x_preferred":[
        "\u0935\u093f\u0937\u094d\u0923\u0941\u092a\u0941\u0930"
    ],
    "name:pol_x_preferred":[
        "Bishunpur"
    ],
    "wof:name":"Bishunpur",
    "wof:placetype":"locality"
},
  "geometry": {"coordinates":[86.61284000000001,25.93909],"type":"Point"}
}