{
  "type": "Feature",
  "properties": {
    "gn:admin1_code":"36",
    "gn:admin2_code":"148.0",
    "gn:asciiname":"Birahimpur",
    "gn:country_code":"IN",
    "gn:dem":157,
    "gn:feature_class":"P",
    "gn:feature_code":"PPL",
    "gn:name":"Birahimpur",
    "gn:population":0,
    "gn:timezone":"Asia/Kolkata",
    "iso:country":"IN",
    "wof:name":"Birahimpur",
    "wof:placetype":"neighbourhood"
},
  "geometry": {"coordinates":[79.2161,27.27111],"type":"Point"}
}