{
  "type": "Feature",
  "properties": {
    "iso:country":"IN",
    "ks:ks_name":"Kardong Chuk",
    "ks:ks_pop":844,
    "ks:ks_type":"HABITATION",
    "name:eng_x_preferred":[
        "Kardong Chuk"
    ],
    "wof:name":"Kardong Chuk",
    "wof:placetype":"locality",
    "wof:population":844
},
  "geometry": {"coordinates":[95.195595,27.769785],"type":"Point"}
}