{
  "type": "Feature",
  "properties": {
    "iso:country":"IN",
    "ks:ks_alt_nam":"HATTALI CHANGOND",
    "ks:ks_name":"Hattali Changond",
    "ks:ks_pop":146,
    "ks:ks_type":"HABITATION",
    "name:eng_x_preferred":[
        "Hattali Changond"
    ],
    "wof:name":"Hattali Changond",
    "wof:placetype":"locality",
    "wof:population":146
},
  "geometry": {"coordinates":[75.44362599999999,17.214059],"type":"Point"}
}