{
  "type": "Feature",
  "properties": {
    "iso:country":"IN",
    "ks:ks_name":"Burugupalli",
    "ks:ks_pop":79,
    "ks:ks_type":"HABITATION",
    "name:eng_x_preferred":[
        "Burugupalli"
    ],
    "wof:name":"Burugupalli",
    "wof:placetype":"locality",
    "wof:population":79
},
  "geometry": {"coordinates":[82.251993,17.550624],"type":"Point"}
}