{
  "type": "Feature",
  "properties": {
    "iso:country":"IN",
    "ks:ks_name":"Sarawa Basti",
    "ks:ks_pop":204,
    "ks:ks_type":"HABITATION",
    "ks:ks_uagg_main":0,
    "name:eng_x_preferred":[
        "Sarawa Basti"
    ],
    "wof:name":"Sarawa Basti",
    "wof:placetype":"neighbourhood",
    "wof:population":204
},
  "geometry": {"coordinates":[82.37325199999999,25.162887],"type":"Point"}
}