{
  "type": "Feature",
  "properties": {
    "gn:admin1_code":"10.0",
    "gn:admin2_code":"081",
    "gn:asciiname":"Badhwana",
    "gn:country_code":"IN",
    "gn:dem":235,
    "gn:feature_class":"P",
    "gn:feature_code":"PPL",
    "gn:name":"Badhw\u0101na",
    "gn:population":0,
    "gn:timezone":"Asia/Kolkata",
    "iso:country":"IN",
    "name:tat_x_preferred":[
        "\u0411\u0430\u0434\u04bb\u0432\u0430\u043d\u0430"
    ],
    "wof:name":"Badhwana",
    "wof:placetype":"locality"
},
  "geometry": {"coordinates":[76.17869,28.46588],"type":"Point"}
}