{
  "type": "Feature",
  "properties": {
    "gn:admin1_code":"35",
    "gn:admin2_code":"437.0",
    "gn:asciiname":"Gurgaria Surdas",
    "gn:country_code":"IN",
    "gn:dem":483,
    "gn:feature_class":"P",
    "gn:feature_code":"PPL",
    "gn:name":"Gurg\u0101ria S\u016brd\u0101s",
    "gn:population":0,
    "gn:timezone":"Asia/Kolkata",
    "iso:country":"IN",
    "ks:ks_name":"Guradiya Surdas",
    "ks:ks_pop":1216,
    "ks:ks_type":"VILLAGE",
    "name:eng_x_preferred":[
        "Guradiya Surdas"
    ],
    "name:eng_x_variant":[
        "Gurgaria Surdas"
    ],
    "wof:name":"Guradiya Surdas",
    "wof:placetype":"locality",
    "wof:population":1216
},
  "geometry": {"coordinates":[76.31323,23.163175],"type":"Point"}
}