{
  "type": "Feature",
  "properties": {
    "iso:country":"IN",
    "ks:ks_name":"Aathgama",
    "ks:ks_pop":2700,
    "ks:ks_type":"HABITATION",
    "ks:ks_uagg_main":0,
    "name:eng_x_preferred":[
        "Aathgama"
    ],
    "wof:name":"Aathgama",
    "wof:placetype":"neighbourhood",
    "wof:population":2700
},
  "geometry": {"coordinates":[87.128276,25.216392],"type":"Point"}
}