{
  "type": "Feature",
  "properties": {
    "iso:country":"IN",
    "ks:ks_name":"Shyal Khet",
    "ks:ks_pop":94,
    "ks:ks_type":"VILLAGE",
    "name:eng_x_preferred":[
        "Shyal Khet"
    ],
    "wof:name":"Shyal Khet",
    "wof:placetype":"locality",
    "wof:population":94
},
  "geometry": {"coordinates":[78.989655,30.197382],"type":"Point"}
}