{
  "type": "Feature",
  "properties": {
    "iso:country":"IN",
    "ks:ks_name":"Gangi No 1",
    "ks:ks_pop":153,
    "ks:ks_type":"VILLAGE",
    "name:eng_x_preferred":[
        "Gangi No 1"
    ],
    "wof:name":"Gangi No 1",
    "wof:placetype":"locality",
    "wof:population":153
},
  "geometry": {"coordinates":[81.695494,24.887787],"type":"Point"}
}