{
  "type": "Feature",
  "properties": {
    "iso:country":"IN",
    "ks:ks_name":"Hariom Nagar",
    "ks:ks_pop":392,
    "ks:ks_type":"HABITATION",
    "name:eng_x_preferred":[
        "Hariom Nagar"
    ],
    "wof:name":"Hariom Nagar",
    "wof:placetype":"locality",
    "wof:population":392
},
  "geometry": {"coordinates":[72.65750800000001,26.489347],"type":"Point"}
}