{
  "type": "Feature",
  "properties": {
    "gn:admin1_code":"36",
    "gn:admin2_code":"191.0",
    "gn:asciiname":"Gobindpur",
    "gn:country_code":"IN",
    "gn:dem":86,
    "gn:feature_class":"P",
    "gn:feature_code":"PPL",
    "gn:name":"Gobindpur",
    "gn:population":0,
    "gn:timezone":"Asia/Kolkata",
    "iso:country":"IN",
    "name:ceb_x_preferred":[
        "Gobindpur"
    ],
    "name:swe_x_preferred":[
        "Gobindpur"
    ],
    "wof:name":"Gobindpur",
    "wof:placetype":"locality"
},
  "geometry": {"coordinates":[82.94945,25.77115],"type":"Point"}
}