{
  "type": "Feature",
  "properties": {
    "iso:country":"IN",
    "ks:ks_name":"Kallkkipal",
    "ks:ks_pop":33,
    "ks:ks_type":"HABITATION",
    "name:eng_x_preferred":[
        "Kallkkipal"
    ],
    "wof:name":"Kallkkipal",
    "wof:placetype":"locality",
    "wof:population":33
},
  "geometry": {"coordinates":[74.694879,14.89283],"type":"Point"}
}