{
  "type": "Feature",
  "properties": {
    "gn:admin1_code":"24.0",
    "gn:admin2_code":"118",
    "gn:asciiname":"Bagrinagar",
    "gn:country_code":"IN",
    "gn:dem":308,
    "gn:feature_class":"P",
    "gn:feature_code":"PPL",
    "gn:name":"Bagr\u012bnagar",
    "gn:population":0,
    "gn:timezone":"Asia/Kolkata",
    "iso:country":"IN",
    "name:und_x_variant":[
        "Bagr\u012bnagar",
        "Bagri"
    ],
    "wof:name":"Bagrinagar",
    "wof:placetype":"locality"
},
  "geometry": {"coordinates":[73.80745999999998,25.89613],"type":"Point"}
}