{
  "type": "Feature",
  "properties": {
    "gn:admin1_code":"23.0",
    "gn:admin2_code":"070",
    "gn:asciiname":"Jodhpur",
    "gn:country_code":"IN",
    "gn:dem":250,
    "gn:feature_class":"P",
    "gn:feature_code":"PPL",
    "gn:name":"Jodhpur",
    "gn:population":0,
    "gn:timezone":"Asia/Kolkata",
    "iso:country":"IN",
    "wof:name":"Jodhpur",
    "wof:placetype":"locality"
},
  "geometry": {"coordinates":[76.61917,30.09527000000001],"type":"Point"}
}