{
  "type": "Feature",
  "properties": {
    "iso:country":"IN",
    "ks:ks_name":"Shikaripalem",
    "ks:ks_pop":117,
    "ks:ks_type":"HABITATION",
    "name:eng_x_preferred":[
        "Shikaripalem"
    ],
    "wof:name":"Shikaripalem",
    "wof:placetype":"locality",
    "wof:population":117
},
  "geometry": {"coordinates":[78.709476,13.728711],"type":"Point"}
}