{
  "type": "Feature",
  "properties": {
    "iso:country":"IN",
    "ks:ks_name":"Chiristian Colony",
    "ks:ks_pop":260,
    "ks:ks_type":"HABITATION",
    "name:eng_x_preferred":[
        "Chiristian Colony"
    ],
    "wof:name":"Chiristian Colony",
    "wof:placetype":"locality",
    "wof:population":260
},
  "geometry": {"coordinates":[79.05819099999999,12.178924],"type":"Point"}
}