{
  "type": "Feature",
  "properties": {
    "gn:admin1_code":"38.0",
    "gn:admin2_code":"358.0",
    "gn:asciiname":"Tatidiri",
    "gn:country_code":"IN",
    "gn:dem":300,
    "gn:feature_class":"P",
    "gn:feature_code":"PPL",
    "gn:name":"T\u0101t\u012bd\u012br\u012b",
    "gn:population":0,
    "gn:timezone":"Asia/Kolkata",
    "iso:country":"IN",
    "ks:ks_name":"Tatidiri",
    "ks:ks_pop":666,
    "ks:ks_type":"VILLAGE",
    "ks:ks_uagg_main":0,
    "name:eng_x_preferred":[
        "Tatidiri"
    ],
    "wof:name":"Tatidiri",
    "wof:placetype":"neighbourhood",
    "wof:population":666
},
  "geometry": {"coordinates":[84.49846100000001,24.031292],"type":"Point"}
}