{
  "type": "Feature",
  "properties": {
    "iso:country":"IN",
    "ks:ks_name":"Bhagatpada",
    "ks:ks_pop":30,
    "ks:ks_type":"HABITATION",
    "name:eng_x_preferred":[
        "Bhagatpada"
    ],
    "wof:name":"Bhagatpada",
    "wof:placetype":"locality",
    "wof:population":30
},
  "geometry": {"coordinates":[73.094166,19.670885],"type":"Point"}
}