{
  "type": "Feature",
  "properties": {
    "gn:country":"IN",
    "gn:fcode":"PPL",
    "gn:pop":33397,
    "iso:country":"IN",
    "name:ben_x_preferred":[
        "\u099c\u09be\u09af\u09bc\u09c7\u09a6\u09aa\u09c1\u09b0"
    ],
    "name:bpy_x_preferred":[
        "\u099c\u09be\u0987\u09a6\u09aa\u09c1\u09b0"
    ],
    "name:bul_x_preferred":[
        "\u0417\u0430\u0438\u0434\u043f\u0443\u0440"
    ],
    "name:eng_x_preferred":[
        "Zaidpur"
    ],
    "name:fas_x_preferred":[
        "\u0632\u06cc\u062f\u067e\u0648\u0631"
    ],
    "name:ita_x_preferred":[
        "Zaidpur"
    ],
    "name:mlg_x_preferred":[
        "Zaidpur"
    ],
    "name:msa_x_preferred":[
        "Zaidpur"
    ],
    "name:nan_x_preferred":[
        "Zaidpur"
    ],
    "name:new_x_preferred":[
        "\u091c\u0948\u0926\u092a\u0941\u0930"
    ],
    "name:nld_x_preferred":[
        "Zaidpur"
    ],
    "name:pnb_x_preferred":[
        "\u0632\u06cc\u062f \u067e\u0648\u0631"
    ],
    "name:pol_x_preferred":[
        "Zaidpur"
    ],
    "name:swe_x_preferred":[
        "Zaidpur"
    ],
    "name:unk_x_variant":[
        "Zaidpur"
    ],
    "name:urd_x_preferred":[
        "\u0632\u06cc\u062f \u067e\u0648\u0631"
    ],
    "name:vie_x_preferred":[
        "Zaidpur"
    ],
    "name:zho_x_preferred":[
        "\u5bb0\u5fb7\u666e\u5c14"
    ],
    "qs:name":"Saidapur",
    "qs:name_adm0":"India",
    "qs:name_adm1":"Uttar Pradesh",
    "qs:photos_9r":0,
    "qs:photos_sr":0,
    "qs:placetype":"Town",
    "qs:pop_sr":"7",
    "wd:wordcount":64,
    "wof:name":"Saidapur",
    "wof:placetype":"locality",
    "wof:population":33397
},
  "geometry": {"coordinates":[81.32978,26.82964],"type":"Point"}
}