{
  "type": "Feature",
  "properties": {
    "iso:country":"IN",
    "ks:ks_name":"Bhawamgarah",
    "ks:ks_pop":267,
    "ks:ks_type":"HABITATION",
    "name:eng_x_preferred":[
        "Bhawamgarah"
    ],
    "wof:name":"Bhawamgarah",
    "wof:placetype":"locality",
    "wof:population":267
},
  "geometry": {"coordinates":[72.64495700000001,24.604794],"type":"Point"}
}