{
  "type": "Feature",
  "properties": {
    "iso:country":"IN",
    "ks:ks_name":"Brindabanpur",
    "ks:ks_pop":2287,
    "ks:ks_type":"VILLAGE",
    "ks:ks_uagg_main":0,
    "name:eng_x_preferred":[
        "Brindabanpur"
    ],
    "wof:name":"Brindabanpur",
    "wof:placetype":"neighbourhood",
    "wof:population":2287
},
  "geometry": {"coordinates":[88.320414,22.122145],"type":"Point"}
}