{
  "type": "Feature",
  "properties": {
    "gn:admin1_code":"36",
    "gn:admin2_code":"183.0",
    "gn:asciiname":"Dinnagar",
    "gn:country_code":"IN",
    "gn:dem":102,
    "gn:feature_class":"P",
    "gn:feature_code":"PPL",
    "gn:name":"D\u012bnnagar",
    "gn:population":0,
    "gn:timezone":"Asia/Kolkata",
    "iso:country":"IN",
    "ks:ks_name":"Din Nagar",
    "ks:ks_pop":769,
    "ks:ks_type":"VILLAGE",
    "ks:ks_uagg_main":0,
    "name:eng_x_preferred":[
        "Din Nagar"
    ],
    "wof:name":"Din Nagar",
    "wof:placetype":"neighbourhood",
    "wof:population":769
},
  "geometry": {"coordinates":[82.389065,26.975667],"type":"Point"}
}