{
  "type": "Feature",
  "properties": {
    "iso:country":"IN",
    "ks:ks_name":"Desaipura",
    "ks:ks_pop":186,
    "ks:ks_type":"HABITATION",
    "name:eng_x_preferred":[
        "Desaipura"
    ],
    "wof:name":"Desaipura",
    "wof:placetype":"locality",
    "wof:population":186
},
  "geometry": {"coordinates":[73.26347199999999,22.762611],"type":"Point"}
}