{
  "type": "Feature",
  "properties": {
    "iso:country":"IN",
    "ks:ks_name":"Wadgaon",
    "ks:ks_pop":348,
    "ks:ks_type":"HABITATION",
    "name:eng_x_preferred":[
        "Wadgaon"
    ],
    "wof:name":"Wadgaon",
    "wof:placetype":"locality",
    "wof:population":348
},
  "geometry": {"coordinates":[80.336838,20.293591],"type":"Point"}
}