{
  "type": "Feature",
  "properties": {
    "iso:country":"IN",
    "ks:ks_name":"Keregadde",
    "ks:ks_pop":13,
    "ks:ks_type":"HABITATION",
    "name:eng_x_preferred":[
        "Keregadde"
    ],
    "wof:name":"Keregadde",
    "wof:placetype":"locality",
    "wof:population":13
},
  "geometry": {"coordinates":[74.66940700000001,14.993636],"type":"Point"}
}