{
  "type": "Feature",
  "properties": {
    "gn:admin1_code":"24",
    "gn:admin2_code":"122.0",
    "gn:asciiname":"Babaji-ka-Khera",
    "gn:country_code":"IN",
    "gn:dem":347,
    "gn:feature_class":"P",
    "gn:feature_code":"PPL",
    "gn:name":"B\u0101b\u0101ji-ka-Khera",
    "gn:population":0,
    "gn:timezone":"Asia/Kolkata",
    "iso:country":"IN",
    "wof:name":"Babaji-ka-Khera",
    "wof:placetype":"locality"
},
  "geometry": {"coordinates":[75.31768000000002,25.5306],"type":"Point"}
}