{
  "type": "Feature",
  "properties": {
    "gn:admin1_code":"19.0",
    "gn:admin2_code":"578.0",
    "gn:asciiname":"Maralkani",
    "gn:country_code":"IN",
    "gn:dem":1093,
    "gn:feature_class":"P",
    "gn:feature_code":"PPL",
    "gn:name":"Maralkani",
    "gn:population":0,
    "gn:timezone":"Asia/Kolkata",
    "iso:country":"IN",
    "wof:name":"Maralkani",
    "wof:placetype":"locality"
},
  "geometry": {"coordinates":[77.36131999999998,11.7851],"type":"Point"}
}