{
  "type": "Feature",
  "properties": {
    "iso:country":"IN",
    "ks:ks_name":"Ramnagar",
    "ks:ks_pop":60,
    "ks:ks_type":"HABITATION",
    "name:eng_x_preferred":[
        "Ramnagar"
    ],
    "name:hin_x_preferred":[
        "\u0930\u093e\u092e\u0928\u0917\u0930"
    ],
    "wof:name":"Ramnagar",
    "wof:placetype":"locality",
    "wof:population":60
},
  "geometry": {"coordinates":[79.47713899999999,17.027802],"type":"Point"}
}