{
  "type": "Feature",
  "properties": {
    "iso:country":"IN",
    "ks:ks_name":"Benagajar",
    "ks:ks_pop":96,
    "ks:ks_type":"VILLAGE",
    "ks:ks_uagg_main":0,
    "name:eng_x_preferred":[
        "Benagajar"
    ],
    "wof:name":"Benagajar",
    "wof:placetype":"locality",
    "wof:population":96
},
  "geometry": {"coordinates":[86.545745,23.820153],"type":"Point"}
}