{
  "type": "Feature",
  "properties": {
    "iso:country":"IN",
    "ks:ks_name":"Doraguda",
    "ks:ks_pop":991,
    "ks:ks_type":"HABITATION",
    "name:eng_x_preferred":[
        "Doraguda"
    ],
    "wof:name":"Doraguda",
    "wof:placetype":"locality",
    "wof:population":991
},
  "geometry": {"coordinates":[81.76548099999999,18.033933],"type":"Point"}
}