{
  "type": "Feature",
  "properties": {
    "gn:admin1_code":"21.0",
    "gn:admin2_code":"398.0",
    "gn:asciiname":"Girliputtu",
    "gn:country_code":"IN",
    "gn:dem":875,
    "gn:feature_class":"P",
    "gn:feature_code":"PPL",
    "gn:name":"Girliputtu",
    "gn:population":0,
    "gn:timezone":"Asia/Kolkata",
    "iso:country":"IN",
    "wof:name":"Girliputtu",
    "wof:placetype":"locality"
},
  "geometry": {"coordinates":[82.62591,18.74599],"type":"Point"}
}