{
  "type": "Feature",
  "properties": {
    "iso:country":"IN",
    "ks:ks_name":"Illigaradoddi",
    "ks:ks_pop":281,
    "ks:ks_type":"HABITATION",
    "name:eng_x_preferred":[
        "Illigaradoddi"
    ],
    "wof:name":"Illigaradoddi",
    "wof:placetype":"locality",
    "wof:population":281
},
  "geometry": {"coordinates":[77.259944,12.814269],"type":"Point"}
}