{
  "type": "Feature",
  "properties": {
    "iso:country":"IN",
    "ks:ks_name":"Jambhlicha Pacha",
    "ks:ks_pop":89,
    "ks:ks_type":"HABITATION",
    "name:eng_x_preferred":[
        "Jambhlicha Pacha"
    ],
    "wof:name":"Jambhlicha Pacha",
    "wof:placetype":"locality",
    "wof:population":89
},
  "geometry": {"coordinates":[73.726186,16.047894],"type":"Point"}
}