{
  "type": "Feature",
  "properties": {
    "iso:country":"IN",
    "ks:ks_name":"Fatehpur Bajaria",
    "ks:ks_pop":8,
    "ks:ks_type":"VILLAGE",
    "name:eng_x_preferred":[
        "Fatehpur Bajaria"
    ],
    "wof:name":"Fatehpur Bajaria",
    "wof:placetype":"locality",
    "wof:population":8
},
  "geometry": {"coordinates":[79.86312100000001,25.323778],"type":"Point"}
}