{
  "type": "Feature",
  "properties": {
    "iso:country":"IN",
    "ks:ks_name":"Naikali",
    "ks:ks_pop":305,
    "ks:ks_type":"VILLAGE",
    "ks:ks_uagg_main":0,
    "name:eng_x_preferred":[
        "Naikali"
    ],
    "wof:name":"Naikali",
    "wof:placetype":"neighbourhood",
    "wof:population":305
},
  "geometry": {"coordinates":[86.586049,22.121786],"type":"Point"}
}