{
  "type": "Feature",
  "properties": {
    "iso:country":"IN",
    "ks:ks_alt_nam":"Muhal khurd",
    "ks:ks_name":"Muhal Khurd",
    "ks:ks_pop":332,
    "ks:ks_type":"HABITATION",
    "name:eng_x_preferred":[
        "Muhal Khurd"
    ],
    "wof:name":"Muhal Khurd",
    "wof:placetype":"locality",
    "wof:population":332
},
  "geometry": {"coordinates":[76.91626599999999,22.209058],"type":"Point"}
}