{
  "type": "Feature",
  "properties": {
    "gn:admin1_code":"35",
    "gn:admin2_code":"453.0",
    "gn:asciiname":"Rujhni Sarai",
    "gn:country_code":"IN",
    "gn:dem":731,
    "gn:feature_class":"P",
    "gn:feature_code":"PPL",
    "gn:name":"Rujhni Sarai",
    "gn:population":0,
    "gn:timezone":"Asia/Kolkata",
    "iso:country":"IN",
    "wof:name":"Rujhni Sarai",
    "wof:placetype":"locality"
},
  "geometry": {"coordinates":[81.22618,22.55259],"type":"Point"}
}