{
  "type": "Feature",
  "properties": {
    "iso:country":"IN",
    "ks:ks_name":"Kheda Falia",
    "ks:ks_pop":466,
    "ks:ks_type":"HABITATION",
    "name:eng_x_preferred":[
        "Kheda Falia"
    ],
    "wof:name":"Kheda Falia",
    "wof:placetype":"locality",
    "wof:population":466
},
  "geometry": {"coordinates":[73.977417,22.731639],"type":"Point"}
}