{
  "type": "Feature",
  "properties": {
    "gn:admin1_code":"36",
    "gn:admin2_code":"147.0",
    "gn:asciiname":"Nadia",
    "gn:country_code":"IN",
    "gn:dem":157,
    "gn:feature_class":"P",
    "gn:feature_code":"PPL",
    "gn:name":"N\u0101dia",
    "gn:population":0,
    "gn:timezone":"Asia/Kolkata",
    "iso:country":"IN",
    "name:ara_x_preferred":[
        "\u0646\u0627\u062f\u064a\u0627"
    ],
    "name:ben_bn_x_preferred":[
        "\u09a8\u09a6\u09c0\u09df\u09be"
    ],
    "name:ben_in_x_preferred":[
        "\u09a8\u09a6\u09c0\u09df\u09be"
    ],
    "name:dan_x_preferred":[
        "Nadia"
    ],
    "name:fra_x_preferred":[
        "Nadia"
    ],
    "name:guj_x_preferred":[
        "\u0aa8\u0aa1\u0ac0\u0aaf\u0abe"
    ],
    "name:hin_x_preferred":[
        "\u0928\u093e\u0926\u093f\u092f\u093e"
    ],
    "name:isl_x_preferred":[
        "Nadia"
    ],
    "name:ita_x_preferred":[
        "Nadia"
    ],
    "name:kan_x_preferred":[
        "\u0ca8\u0cbe\u0ca1\u0cbf\u0caf\u0cbe"
    ],
    "name:mal_x_preferred":[
        "\u0d28\u0d3e\u0d26\u0d3f\u0d2f"
    ],
    "name:mar_x_preferred":[
        "\u0928\u0921\u093f\u092f\u093e"
    ],
    "name:nld_x_preferred":[
        "Nadia"
    ],
    "name:nor_x_preferred":[
        "Nadia"
    ],
    "name:pan_x_preferred":[
        "\u0a28\u0a26\u0a40\u0a06"
    ],
    "name:ron_x_preferred":[
        "Nadia"
    ],
    "name:slv_x_preferred":[
        "Nadia"
    ],
    "name:spa_x_preferred":[
        "Nadia"
    ],
    "name:tam_x_preferred":[
        "\u0ba8\u0b9f\u0bbf\u0baf\u0bbe"
    ],
    "name:tel_x_preferred":[
        "\u0c28\u0c26\u0c3f\u0c2f\u0c3e"
    ],
    "name:urd_x_preferred":[
        "\u0646\u062f\u06cc\u0627"
    ],
    "wof:name":"Nadia",
    "wof:placetype":"locality"
},
  "geometry": {"coordinates":[78.74494,26.96423],"type":"Point"}
}