{
  "type": "Feature",
  "properties": {
    "gn:admin1_code":"36",
    "gn:admin2_code":"147.0",
    "gn:asciiname":"Nadia",
    "gn:country_code":"IN",
    "gn:dem":157,
    "gn:feature_class":"P",
    "gn:feature_code":"PPL",
    "gn:name":"N\u0101dia",
    "gn:population":0,
    "gn:timezone":"Asia/Kolkata",
    "iso:country":"IN",
    "name:dan_x_preferred":[
        "Nadia"
    ],
    "name:fra_x_preferred":[
        "Nadia"
    ],
    "name:isl_x_preferred":[
        "Nadia"
    ],
    "name:ita_x_preferred":[
        "Nadia"
    ],
    "name:nld_x_preferred":[
        "Nadia"
    ],
    "name:nor_x_preferred":[
        "Nadia"
    ],
    "name:ron_x_preferred":[
        "Nadia"
    ],
    "name:slv_x_preferred":[
        "Nadia"
    ],
    "name:spa_x_preferred":[
        "Nadia"
    ],
    "wof:name":"Nadia",
    "wof:placetype":"locality"
},
  "geometry": {"coordinates":[78.74494,26.96423],"type":"Point"}
}