{
  "type": "Feature",
  "properties": {
    "iso:country":"IN",
    "ks:ks_alt_nam":"CHAVANWASTI",
    "ks:ks_name":"Chavanwasti",
    "ks:ks_pop":76,
    "ks:ks_type":"HABITATION",
    "name:eng_x_preferred":[
        "Chavanwasti"
    ],
    "wof:name":"Chavanwasti",
    "wof:placetype":"locality",
    "wof:population":76
},
  "geometry": {"coordinates":[75.018249,17.457412],"type":"Point"}
}