{
  "type": "Feature",
  "properties": {
    "iso:country":"IN",
    "ks:ks_name":"Kameswarpur",
    "ks:ks_pop":45,
    "ks:ks_type":"VILLAGE",
    "ks:ks_uagg_main":0,
    "name:eng_x_preferred":[
        "Kameswarpur"
    ],
    "wof:name":"Kameswarpur",
    "wof:placetype":"neighbourhood",
    "wof:population":45
},
  "geometry": {"coordinates":[86.291889,21.047236],"type":"Point"}
}