{
  "type": "Feature",
  "properties": {
    "iso:country":"IN",
    "ks:ks_name":"Kasmar",
    "ks:ks_pop":113,
    "ks:ks_type":"VILLAGE",
    "name:eng_x_preferred":[
        "Kasmar"
    ],
    "wof:name":"Kasmar",
    "wof:placetype":"locality",
    "wof:population":113
},
  "geometry": {"coordinates":[83.754093,23.899086],"type":"Point"}
}