{
  "type": "Feature",
  "properties": {
    "iso:country":"IN",
    "ks:ks_name":"Sisda",
    "ks:ks_pop":434,
    "ks:ks_type":"HABITATION",
    "name:eng_x_preferred":[
        "Sisda"
    ],
    "wof:name":"Sisda",
    "wof:placetype":"locality",
    "wof:population":434
},
  "geometry": {"coordinates":[86.363854,22.87979],"type":"Point"}
}