{
  "type": "Feature",
  "properties": {
    "iso:country":"IN",
    "ks:ks_name":"Umari Tanda",
    "ks:ks_pop":201,
    "ks:ks_type":"HABITATION",
    "name:eng_x_preferred":[
        "Umari Tanda"
    ],
    "wof:name":"Umari Tanda",
    "wof:placetype":"locality",
    "wof:population":201
},
  "geometry": {"coordinates":[76.18906699999999,19.839887],"type":"Point"}
}