{
  "type": "Feature",
  "properties": {
    "iso:country":"IN",
    "ks:ks_name":"Jondhalewati",
    "ks:ks_pop":100,
    "ks:ks_type":"HABITATION",
    "name:eng_x_preferred":[
        "Jondhalewati"
    ],
    "wof:name":"Jondhalewati",
    "wof:placetype":"locality",
    "wof:population":100
},
  "geometry": {"coordinates":[74.30917700000001,19.593271],"type":"Point"}
}