{
  "type": "Feature",
  "properties": {
    "gn:admin1_code":"25",
    "gn:admin2_code":"609.0",
    "gn:asciiname":"Chinna Sekkadi",
    "gn:country_code":"IN",
    "gn:dem":476,
    "gn:feature_class":"P",
    "gn:feature_code":"PPL",
    "gn:name":"Chinna Sekkadi",
    "gn:population":0,
    "gn:timezone":"Asia/Kolkata",
    "iso:country":"IN",
    "name:und_x_variant":[
        "Sekkadu",
        "Sekkadi",
        "Chinna Sekkadi"
    ],
    "wof:name":"Chinna Sekkadi",
    "wof:placetype":"locality"
},
  "geometry": {"coordinates":[78.35221999999997,11.43625],"type":"Point"}
}