{
  "type": "Feature",
  "properties": {
    "gn:admin1_code":"24",
    "gn:admin2_code":"120.0",
    "gn:asciiname":"Dilwasa",
    "gn:country_code":"IN",
    "gn:dem":313,
    "gn:feature_class":"P",
    "gn:feature_code":"PPL",
    "gn:name":"Dilw\u0101sa",
    "gn:population":0,
    "gn:timezone":"Asia/Kolkata",
    "iso:country":"IN",
    "ks:ks_name":"Dalwasa",
    "ks:ks_pop":1371,
    "ks:ks_type":"VILLAGE",
    "name:eng_x_preferred":[
        "Dalwasa"
    ],
    "name:eng_x_variant":[
        "Dilwasa"
    ],
    "wof:name":"Dalwasa",
    "wof:placetype":"locality",
    "wof:population":1371
},
  "geometry": {"coordinates":[75.360794,25.892892],"type":"Point"}
}