{
  "type": "Feature",
  "properties": {
    "iso:country":"IN",
    "ks:ks_alt_nam":"R\u0101mpur R\u0101ja",
    "ks:ks_alt_nam_2":"Rampur Raja",
    "ks:ks_name":"Rampur",
    "ks:ks_pop":23,
    "ks:ks_type":"VILLAGE",
    "name:eng_x_preferred":[
        "Rampur"
    ],
    "name:eng_x_variant":[
        "R\u0101mpur R\u0101ja",
        "Rampur Raja"
    ],
    "name:hin_x_preferred":[
        "\u0930\u093e\u092e\u092a\u0941\u0930"
    ],
    "wof:name":"Rampur",
    "wof:placetype":"locality",
    "wof:population":23
},
  "geometry": {"coordinates":[82.26594,26.813791],"type":"Point"}
}