{
  "type": "Feature",
  "properties": {
    "iso:country":"IN",
    "ks:ks_name":"Kalewasti",
    "ks:ks_pop":132,
    "ks:ks_type":"HABITATION",
    "name:eng_x_preferred":[
        "Kalewasti"
    ],
    "wof:name":"Kalewasti",
    "wof:placetype":"locality",
    "wof:population":132
},
  "geometry": {"coordinates":[74.78216,18.667606],"type":"Point"}
}