{
  "type": "Feature",
  "properties": {
    "gn:admin1_code":"2.0",
    "gn:admin2_code":"553.0",
    "gn:asciiname":"Bosannagaripalle",
    "gn:country_code":"IN",
    "gn:dem":544,
    "gn:feature_class":"P",
    "gn:feature_code":"PPL",
    "gn:name":"Bosannag\u0101ripalle",
    "gn:population":0,
    "gn:timezone":"Asia/Kolkata",
    "iso:country":"IN",
    "ks:ks_name":"Basannagaripalli",
    "ks:ks_pop":14,
    "ks:ks_type":"HABITATION",
    "name:eng_x_preferred":[
        "Basannagaripalli"
    ],
    "name:eng_x_variant":[
        "Bosannagaripalle"
    ],
    "wof:name":"Basannagaripalli",
    "wof:placetype":"locality",
    "wof:population":14
},
  "geometry": {"coordinates":[78.263077,14.075787],"type":"Point"}
}