{
  "type": "Feature",
  "properties": {
    "iso:country":"IN",
    "ks:ks_name":"Halagaru",
    "ks:ks_pop":26,
    "ks:ks_type":"HABITATION",
    "name:eng_x_preferred":[
        "Halagaru"
    ],
    "wof:name":"Halagaru",
    "wof:placetype":"locality",
    "wof:population":26
},
  "geometry": {"coordinates":[75.398295,13.60105],"type":"Point"}
}