{
  "type": "Feature",
  "properties": {
    "gn:admin1_code":"19",
    "gn:admin2_code":"580.0",
    "gn:asciiname":"Yaktapur",
    "gn:country_code":"IN",
    "gn:dem":546,
    "gn:feature_class":"P",
    "gn:feature_code":"PPL",
    "gn:name":"Yakt\u0101pur",
    "gn:population":0,
    "gn:timezone":"Asia/Kolkata",
    "iso:country":"IN",
    "wof:name":"Yaktapur",
    "wof:placetype":"locality"
},
  "geometry": {"coordinates":[76.43968000000002,16.64912],"type":"Point"}
}