{
  "type": "Feature",
  "properties": {
    "gn:admin1_code":"25.0",
    "gn:admin2_code":"608.0",
    "gn:asciiname":"Kattari",
    "gn:country_code":"IN",
    "gn:dem":202,
    "gn:feature_class":"P",
    "gn:feature_code":"PPL",
    "gn:name":"Katt\u0101ri",
    "gn:population":0,
    "gn:timezone":"Asia/Kolkata",
    "iso:country":"IN",
    "ks:ks_name":"Katteri",
    "ks:ks_pop":8145,
    "ks:ks_type":"VILLAGE",
    "ks:ks_uagg_main":0,
    "name:eng_x_preferred":[
        "Katteri"
    ],
    "wof:name":"Katteri",
    "wof:placetype":"neighbourhood",
    "wof:population":8145
},
  "geometry": {"coordinates":[77.71161600000001,11.458272],"type":"Point"}
}