{
  "type": "Feature",
  "properties": {
    "gn:country":"IN",
    "gn:fcode":"PPL",
    "gn:pop":10406,
    "iso:country":"IN",
    "name:bpy_x_preferred":[
        "\u09a4\u09bf\u09a8\u09cd\u09a6\u09f1\u09be\u09b0\u09bf"
    ],
    "name:chi_x_preferred":[
        "\u5ef7\u5fb7\u74e6\u91cc"
    ],
    "name:dut_x_preferred":[
        "Tindwari"
    ],
    "name:eng_x_preferred":[
        "Tindwari"
    ],
    "name:ita_x_preferred":[
        "Tindwari"
    ],
    "name:may_x_preferred":[
        "Tindwari"
    ],
    "name:mlg_x_preferred":[
        "Tindwari"
    ],
    "name:nan_x_preferred":[
        "Tindwari"
    ],
    "name:pol_x_preferred":[
        "Tindwari"
    ],
    "name:por_x_preferred":[
        "Tindwari"
    ],
    "name:swe_x_preferred":[
        "Tindw\u0101ri"
    ],
    "name:ukr_x_preferred":[
        "\u0422\u0456\u043d\u0434\u0432\u0430\u0440\u0456"
    ],
    "name:urd_x_preferred":[
        "\u0679\u0646\u0688\u0648\u0627\u0631\u06cc"
    ],
    "name:vie_x_preferred":[
        "Tindwari"
    ],
    "qs:name":"Tindw\u0101ri",
    "qs:photos_9r":0,
    "qs:photos_sr":0,
    "qs:pop_sr":"6",
    "wd:wordcount":142,
    "wof:name":"Tindw\u0101ri",
    "wof:placetype":"locality",
    "wof:population":10406
},
  "geometry": {"coordinates":[80.52718,25.61739],"type":"Point"}
}