{
  "type": "Feature",
  "properties": {
    "iso:country":"IN",
    "ks:ks_name":"Bri Ka",
    "ks:ks_pop":230,
    "ks:ks_type":"HABITATION",
    "ks:ks_uagg_main":0,
    "name:eng_x_preferred":[
        "Bri Ka"
    ],
    "wof:name":"Bri Ka",
    "wof:placetype":"neighbourhood",
    "wof:population":230
},
  "geometry": {"coordinates":[82.066496,25.74741],"type":"Point"}
}