{
  "type": "Feature",
  "properties": {
    "iso:country":"IN",
    "ks:ks_name":"Sariahtali",
    "ks:ks_pop":1766,
    "ks:ks_type":"VILLAGE",
    "ks:ks_uagg_main":0,
    "name:eng_x_preferred":[
        "Sariahtali"
    ],
    "wof:name":"Sariahtali",
    "wof:placetype":"neighbourhood",
    "wof:population":1766
},
  "geometry": {"coordinates":[91.42630200000001,26.469401],"type":"Point"}
}