{
  "type": "Feature",
  "properties": {
    "gn:admin1_code":"16",
    "gn:admin2_code":"508.0",
    "gn:asciiname":"Ranbhumi",
    "gn:country_code":"IN",
    "gn:dem":219,
    "gn:feature_class":"P",
    "gn:feature_code":"PPL",
    "gn:name":"R\u0101nbhumi",
    "gn:population":0,
    "gn:timezone":"Asia/Kolkata",
    "iso:country":"IN",
    "ks:ks_alt_nam":"R\u0101nbhumi",
    "ks:ks_name":"Ranbhumi",
    "ks:ks_pop":261,
    "ks:ks_type":"VILLAGE",
    "name:eng_x_preferred":[
        "Ranbhumi"
    ],
    "name:eng_x_variant":[
        "R\u0101nbhumi"
    ],
    "wof:name":"Ranbhumi",
    "wof:placetype":"locality",
    "wof:population":261
},
  "geometry": {"coordinates":[80.109256,20.1565],"type":"Point"}
}