{
  "type": "Feature",
  "properties": {
    "iso:country":"IN",
    "ks:ks_name":"Mogaranewadi",
    "ks:ks_pop":395,
    "ks:ks_type":"HABITATION",
    "name:eng_x_preferred":[
        "Mogaranewadi"
    ],
    "wof:name":"Mogaranewadi",
    "wof:placetype":"locality",
    "wof:population":395
},
  "geometry": {"coordinates":[73.747736,16.196969],"type":"Point"}
}