{
  "type": "Feature",
  "properties": {
    "iso:country":"IN",
    "ks:ks_name":"Bongali Gaon",
    "ks:ks_pop":133,
    "ks:ks_type":"HABITATION",
    "name:eng_x_preferred":[
        "Bongali Gaon"
    ],
    "wof:name":"Bongali Gaon",
    "wof:placetype":"locality",
    "wof:population":133
},
  "geometry": {"coordinates":[94.420061,26.827252],"type":"Point"}
}