{
  "type": "Feature",
  "properties": {
    "iso:country":"IN",
    "ks:ks_name":"Kadholi",
    "ks:ks_pop":67,
    "ks:ks_type":"HABITATION",
    "name:eng_x_preferred":[
        "Kadholi"
    ],
    "wof:name":"Kadholi",
    "wof:placetype":"locality",
    "wof:population":67
},
  "geometry": {"coordinates":[79.26481699999999,29.735156],"type":"Point"}
}