{
  "type": "Feature",
  "properties": {
    "iso:country":"IN",
    "ks:ks_name":"Jharain",
    "ks:ks_pop":305,
    "ks:ks_type":"HABITATION",
    "name:eng_x_preferred":[
        "Jharain"
    ],
    "wof:name":"Jharain",
    "wof:placetype":"locality",
    "wof:population":305
},
  "geometry": {"coordinates":[84.21177400000001,22.580321],"type":"Point"}
}