{
  "type": "Feature",
  "properties": {
    "gn:admin1_code":"19.0",
    "gn:admin2_code":"556.0",
    "gn:asciiname":"Katapur",
    "gn:country_code":"IN",
    "gn:dem":528,
    "gn:feature_class":"P",
    "gn:feature_code":"PPL",
    "gn:name":"K\u0101t\u0101pur",
    "gn:population":0,
    "gn:timezone":"Asia/Kolkata",
    "iso:country":"IN",
    "wof:name":"Katapur",
    "wof:placetype":"locality"
},
  "geometry": {"coordinates":[75.81967,15.9501],"type":"Point"}
}