{
  "type": "Feature",
  "properties": {
    "iso:country":"IN",
    "ks:ks_name":"Rajapura",
    "ks:ks_pop":973,
    "ks:ks_type":"VILLAGE",
    "ks:ks_uagg_main":0,
    "name:eng_x_preferred":[
        "Rajapura"
    ],
    "wof:name":"Rajapura",
    "wof:placetype":"neighbourhood",
    "wof:population":973
},
  "geometry": {"coordinates":[76.097478,12.322077],"type":"Point"}
}