{
  "type": "Feature",
  "properties": {
    "gn:admin1_code":"12",
    "gn:admin2_code":"4.0",
    "gn:asciiname":"Parkaryan",
    "gn:country_code":"IN",
    "gn:dem":3522,
    "gn:feature_class":"P",
    "gn:feature_code":"PPL",
    "gn:name":"Parkaryan",
    "gn:population":0,
    "gn:timezone":"Asia/Kolkata",
    "iso:country":"IN",
    "wof:name":"Parkaryan",
    "wof:placetype":"locality"
},
  "geometry": {"coordinates":[75.99146,34.09031],"type":"Point"}
}