{
  "type": "Feature",
  "properties": {
    "iso:country":"IN",
    "ks:ks_name":"Cheodhara",
    "ks:ks_pop":360,
    "ks:ks_type":"HABITATION",
    "name:eng_x_preferred":[
        "Cheodhara"
    ],
    "wof:name":"Cheodhara",
    "wof:placetype":"locality",
    "wof:population":360
},
  "geometry": {"coordinates":[82.40314600000001,22.583162],"type":"Point"}
}