{
  "type": "Feature",
  "properties": {
    "iso:country":"IN",
    "ks:ks_name":"Sangam",
    "ks:ks_pop":58,
    "ks:ks_type":"VILLAGE",
    "name:eng_x_preferred":[
        "Sangam"
    ],
    "wof:name":"Sangam",
    "wof:placetype":"locality",
    "wof:population":58
},
  "geometry": {"coordinates":[84.467629,19.10967],"type":"Point"}
}