{
  "type": "Feature",
  "properties": {
    "iso:country":"IN",
    "ks:ks_name":"Bagharbari",
    "ks:ks_pop":100,
    "ks:ks_type":"VILLAGE",
    "name:eng_x_preferred":[
        "Bagharbari"
    ],
    "wof:name":"Bagharbari",
    "wof:placetype":"locality",
    "wof:population":100
},
  "geometry": {"coordinates":[91.94422,26.515905],"type":"Point"}
}