{
  "type": "Feature",
  "properties": {
    "gn:admin1_code":"40",
    "gn:admin2_code":"535.0",
    "gn:asciiname":"Gorekal",
    "gn:country_code":"IN",
    "gn:dem":543,
    "gn:feature_class":"P",
    "gn:feature_code":"PPL",
    "gn:name":"Gorekal",
    "gn:population":0,
    "gn:timezone":"Asia/Kolkata",
    "iso:country":"IN",
    "wof:name":"Gorekal",
    "wof:placetype":"locality"
},
  "geometry": {"coordinates":[77.89239000000001,17.89172],"type":"Point"}
}