{
  "type": "Feature",
  "properties": {
    "gn:admin1_code":"37",
    "gn:admin2_code":"410.0",
    "gn:asciiname":"Urla",
    "gn:country_code":"IN",
    "gn:dem":286,
    "gn:feature_class":"P",
    "gn:feature_code":"PPL",
    "gn:name":"Urla",
    "gn:population":0,
    "gn:timezone":"Asia/Kolkata",
    "iso:country":"IN",
    "name:ceb_x_preferred":[
        "Urla"
    ],
    "name:ita_x_preferred":[
        "Urla"
    ],
    "name:lav_x_preferred":[
        "Urla"
    ],
    "name:min_x_preferred":[
        "Urla"
    ],
    "name:msa_x_preferred":[
        "Urla"
    ],
    "name:nld_x_preferred":[
        "Urla"
    ],
    "name:vie_x_preferred":[
        "Urla"
    ],
    "wof:name":"Urla",
    "wof:placetype":"locality"
},
  "geometry": {"coordinates":[81.60638,21.31324],"type":"Point"}
}