{
  "type": "Feature",
  "properties": {
    "iso:country":"IN",
    "ks:ks_name":"Dhani Haripura",
    "ks:ks_pop":65,
    "ks:ks_type":"HABITATION",
    "ks:ks_uagg_main":0,
    "name:eng_x_preferred":[
        "Dhani Haripura"
    ],
    "wof:name":"Dhani Haripura",
    "wof:placetype":"neighbourhood",
    "wof:population":65
},
  "geometry": {"coordinates":[76.512153,25.867433],"type":"Point"}
}