{
  "type": "Feature",
  "properties": {
    "iso:country":"IN",
    "ks:ks_name":"Shivajinagar",
    "ks:ks_pop":826,
    "ks:ks_type":"VILLAGE",
    "name:eng_x_preferred":[
        "Shivajinagar"
    ],
    "wof:name":"Shivajinagar",
    "wof:placetype":"locality",
    "wof:population":826
},
  "geometry": {"coordinates":[73.185579,17.782949],"type":"Point"}
}