{
  "type": "Feature",
  "properties": {
    "gn:admin1_code":"36",
    "gn:admin2_code":"147.0",
    "gn:asciiname":"Marai Kalan",
    "gn:country_code":"IN",
    "gn:dem":133,
    "gn:feature_class":"P",
    "gn:feature_code":"PPL",
    "gn:name":"Marai Kal\u0101n",
    "gn:population":0,
    "gn:timezone":"Asia/Kolkata",
    "iso:country":"IN",
    "ks:ks_name":"Marahai Kalan",
    "ks:ks_pop":37,
    "ks:ks_type":"HABITATION",
    "name:eng_x_preferred":[
        "Marahai Kalan"
    ],
    "name:eng_x_variant":[
        "Marai Kalan"
    ],
    "wof:name":"Marahai Kalan",
    "wof:placetype":"locality",
    "wof:population":37
},
  "geometry": {"coordinates":[78.696428,26.929106],"type":"Point"}
}