{
  "type": "Feature",
  "properties": {
    "gn:admin1_code":"19.0",
    "gn:admin2_code":"583.0",
    "gn:asciiname":"Shakaldevipur",
    "gn:country_code":"IN",
    "gn:dem":896,
    "gn:feature_class":"P",
    "gn:feature_code":"PPL",
    "gn:name":"Shakaldevipur",
    "gn:population":0,
    "gn:timezone":"Asia/Kolkata",
    "iso:country":"IN",
    "wof:name":"Shakaldevipur",
    "wof:placetype":"locality"
},
  "geometry": {"coordinates":[77.42869,13.24704],"type":"Point"}
}