{
  "type": "Feature",
  "properties": {
    "iso:country":"IN",
    "ks:ks_name":"Pedageddavalasa",
    "ks:ks_pop":24,
    "ks:ks_type":"VILLAGE",
    "name:eng_x_preferred":[
        "Pedageddavalasa"
    ],
    "wof:name":"Pedageddavalasa",
    "wof:placetype":"locality",
    "wof:population":24
},
  "geometry": {"coordinates":[83.072704,18.316419],"type":"Point"}
}