{
  "type": "Feature",
  "properties": {
    "iso:country":"IN",
    "ks:ks_name":"Patel Basti",
    "ks:ks_pop":390,
    "ks:ks_type":"HABITATION",
    "name:eng_x_preferred":[
        "Patel Basti"
    ],
    "wof:name":"Patel Basti",
    "wof:placetype":"locality",
    "wof:population":390
},
  "geometry": {"coordinates":[83.02064900000001,25.454476],"type":"Point"}
}