{
  "type": "Feature",
  "properties": {
    "iso:country":"IN",
    "ks:ks_name":"Varan Kavala",
    "ks:ks_pop":2357,
    "ks:ks_type":"HABITATION",
    "name:eng_x_preferred":[
        "Varan Kavala"
    ],
    "wof:name":"Varan Kavala",
    "wof:placetype":"neighbourhood",
    "wof:population":2357
},
  "geometry": {"coordinates":[76.304965,9.589558],"type":"Point"}
}