{
  "type": "Feature",
  "properties": {
    "iso:country":"IN",
    "ks:ks_name":"Lakuriya",
    "ks:ks_pop":81,
    "ks:ks_type":"HABITATION",
    "ks:ks_uagg_main":0,
    "name:eng_x_preferred":[
        "Lakuriya"
    ],
    "wof:name":"Lakuriya",
    "wof:placetype":"neighbourhood",
    "wof:population":81
},
  "geometry": {"coordinates":[84.46364800000001,24.446812],"type":"Point"}
}