{
  "type": "Feature",
  "properties": {
    "gn:admin1_code":"2.0",
    "gn:admin2_code":"553.0",
    "gn:asciiname":"Hanumantarayapalle",
    "gn:country_code":"IN",
    "gn:dem":532,
    "gn:feature_class":"P",
    "gn:feature_code":"PPL",
    "gn:name":"Hanumantar\u0101yapalle",
    "gn:population":0,
    "gn:timezone":"Asia/Kolkata",
    "iso:country":"IN",
    "wof:name":"Hanumantarayapalle",
    "wof:placetype":"locality"
},
  "geometry": {"coordinates":[78.1649,14.16891],"type":"Point"}
}