{
  "type": "Feature",
  "properties": {
    "iso:country":"IN",
    "ks:ks_name":"Mundigada",
    "ks:ks_pop":1711,
    "ks:ks_type":"VILLAGE",
    "name:eng_x_preferred":[
        "Mundigada"
    ],
    "wof:name":"Mundigada",
    "wof:placetype":"locality",
    "wof:population":1711
},
  "geometry": {"coordinates":[83.681622,20.009777],"type":"Point"}
}