{
  "type": "Feature",
  "properties": {
    "iso:country":"IN",
    "ks:ks_name":"Simaldhap",
    "ks:ks_pop":87,
    "ks:ks_type":"VILLAGE",
    "name:eng_x_preferred":[
        "Simaldhap"
    ],
    "wof:name":"Simaldhap",
    "wof:placetype":"locality",
    "wof:population":87
},
  "geometry": {"coordinates":[87.471644,24.674776],"type":"Point"}
}