{
  "type": "Feature",
  "properties": {
    "gn:admin1_code":"12.0",
    "gn:admin2_code":"6.0",
    "gn:asciiname":"Tota Mohra",
    "gn:country_code":"IN",
    "gn:dem":1297,
    "gn:feature_class":"P",
    "gn:feature_code":"PPL",
    "gn:name":"T\u014dta Mohra",
    "gn:population":0,
    "gn:timezone":"Asia/Kolkata",
    "iso:country":"IN",
    "wof:name":"Tota Mohra",
    "wof:placetype":"locality"
},
  "geometry": {"coordinates":[74.34939,33.51888],"type":"Point"}
}