{
  "type": "Feature",
  "properties": {
    "gn:admin1_code":"16",
    "gn:admin2_code":"511.0",
    "gn:asciiname":"Dhangarwadi",
    "gn:country_code":"IN",
    "gn:dem":466,
    "gn:feature_class":"P",
    "gn:feature_code":"PPL",
    "gn:name":"Dhangarw\u0101di",
    "gn:population":0,
    "gn:timezone":"Asia/Kolkata",
    "iso:country":"IN",
    "wof:name":"Dhangarwadi",
    "wof:placetype":"locality"
},
  "geometry": {"coordinates":[77.4772,18.39103],"type":"Point"}
}