{
  "type": "Feature",
  "properties": {
    "iso:country":"IN",
    "ks:ks_name":"Tendukheda",
    "ks:ks_pop":14,
    "ks:ks_type":"VILLAGE",
    "name:eng_x_preferred":[
        "Tendukheda"
    ],
    "wof:name":"Tendukheda",
    "wof:placetype":"locality",
    "wof:population":14
},
  "geometry": {"coordinates":[79.42693199999999,22.905445],"type":"Point"}
}