{
  "type": "Feature",
  "properties": {
    "gn:admin1_code":"10.0",
    "gn:admin2_code":"76.0",
    "gn:asciiname":"Badh Malak",
    "gn:country_code":"IN",
    "gn:dem":217,
    "gn:feature_class":"P",
    "gn:feature_code":"PPL",
    "gn:name":"Badh Malak",
    "gn:population":0,
    "gn:timezone":"Asia/Kolkata",
    "iso:country":"IN",
    "ks:ks_name":"Badh Malak",
    "ks:ks_pop":6938,
    "ks:ks_type":"VILLAGE",
    "ks:ks_uagg_main":0,
    "name:eng_x_preferred":[
        "Badh Malak"
    ],
    "wof:name":"Badh Malak",
    "wof:placetype":"neighbourhood",
    "wof:population":6938
},
  "geometry": {"coordinates":[77.094849,28.920132],"type":"Point"}
}