{
  "type": "Feature",
  "properties": {
    "iso:country":"IN",
    "ks:ks_name":"Malavalli",
    "ks:ks_pop":56,
    "ks:ks_type":"HABITATION",
    "name:eng_x_preferred":[
        "Malavalli"
    ],
    "wof:name":"Malavalli",
    "wof:placetype":"locality",
    "wof:population":56
},
  "geometry": {"coordinates":[74.893686,14.35682],"type":"Point"}
}