{
  "type": "Feature",
  "properties": {
    "gn:admin1_code":"13.0",
    "gn:admin2_code":"600.0",
    "gn:asciiname":"Pallikkal",
    "gn:country_code":"IN",
    "gn:dem":38,
    "gn:feature_class":"P",
    "gn:feature_code":"PPL",
    "gn:name":"Pallikkal",
    "gn:population":0,
    "gn:timezone":"Asia/Kolkata",
    "iso:country":"IN",
    "ks:ks_name":"Pallikal",
    "ks:ks_pop":565,
    "ks:ks_type":"HABITATION",
    "name:eng_x_preferred":[
        "Pallikal"
    ],
    "name:eng_x_variant":[
        "Pallikkal"
    ],
    "wof:name":"Pallikal",
    "wof:placetype":"locality",
    "wof:population":565
},
  "geometry": {"coordinates":[76.76190800000001,9.024697],"type":"Point"}
}