{
  "type": "Feature",
  "properties": {
    "iso:country":"IN",
    "qs:name":"Ramnaspura",
    "qs:name_adm0":"India",
    "qs:name_adm1":"Andhra Pradesh",
    "qs:photos":37,
    "qs:photos_1k":7,
    "qs:photos_9k":1,
    "qs:photos_9r":2,
    "qs:photos_all":37,
    "qs:photos_sr":2,
    "qs:placetype":"Suburb",
    "qs:pop_sr":"0",
    "wof:name":"Ramnaspura",
    "wof:placetype":"neighbourhood"
},
  "geometry": {"coordinates":[78.44924899999999,17.351211],"type":"Point"}
}