{
  "type": "Feature",
  "properties": {
    "iso:country":"IN",
    "ks:ks_name":"Ballari",
    "ks:ks_pop":44,
    "ks:ks_type":"HABITATION",
    "name:eng_x_preferred":[
        "Ballari"
    ],
    "wof:name":"Ballari",
    "wof:placetype":"locality",
    "wof:population":44
},
  "geometry": {"coordinates":[82.419539,18.132987],"type":"Point"}
}