{
  "type": "Feature",
  "properties": {
    "gn:admin1_code":"12.0",
    "gn:admin2_code":"011",
    "gn:asciiname":"Khanan",
    "gn:country_code":"IN",
    "gn:dem":2027,
    "gn:feature_class":"P",
    "gn:feature_code":"PPL",
    "gn:name":"Kh\u0101nan",
    "gn:population":0,
    "gn:timezone":"Asia/Kolkata",
    "iso:country":"IN",
    "wof:name":"Khanan",
    "wof:placetype":"locality"
},
  "geometry": {"coordinates":[74.92681999999998,34.29974],"type":"Point"}
}