{
  "type": "Feature",
  "properties": {
    "iso:country":"IN",
    "ks:ks_name":"Dipakpura",
    "ks:ks_pop":946,
    "ks:ks_type":"HABITATION",
    "name:eng_x_preferred":[
        "Dipakpura"
    ],
    "wof:name":"Dipakpura",
    "wof:placetype":"locality",
    "wof:population":946
},
  "geometry": {"coordinates":[73.226083,22.846472],"type":"Point"}
}