{
  "type": "Feature",
  "properties": {
    "iso:country":"IN",
    "ks:ks_alt_nam":"Man\u012bpur",
    "ks:ks_name":"Manipur",
    "ks:ks_pop":158,
    "ks:ks_type":"VILLAGE",
    "name:eng_x_preferred":[
        "Manipur"
    ],
    "name:eng_x_variant":[
        "Man\u012bpur"
    ],
    "wof:name":"Manipur",
    "wof:placetype":"locality",
    "wof:population":158
},
  "geometry": {"coordinates":[81.47723499999999,25.469329],"type":"Point"}
}