{
  "type": "Feature",
  "properties": {
    "gn:admin1_code":"36.0",
    "gn:admin2_code":"135.0",
    "gn:asciiname":"Umarpur",
    "gn:country_code":"IN",
    "gn:dem":210,
    "gn:feature_class":"P",
    "gn:feature_code":"PPL",
    "gn:name":"Umarpur",
    "gn:population":0,
    "gn:timezone":"Asia/Kolkata",
    "iso:country":"IN",
    "name:urd_x_preferred":[
        "\u0639\u0645\u0631\u067e\u0648\u0631"
    ],
    "wof:name":"Umarpur",
    "wof:placetype":"neighbourhood"
},
  "geometry": {"coordinates":[78.45123,28.77605],"type":"Point"}
}