{
  "type": "Feature",
  "properties": {
    "iso:country":"IN",
    "ks:ks_name":"Dhuma",
    "ks:ks_pop":29,
    "ks:ks_type":"HABITATION",
    "name:eng_x_preferred":[
        "Dhuma"
    ],
    "wof:name":"Dhuma",
    "wof:placetype":"locality",
    "wof:population":29
},
  "geometry": {"coordinates":[76.50092100000001,20.395383],"type":"Point"}
}