{
  "type": "Feature",
  "properties": {
    "iso:country":"IN",
    "ks:ks_name":"Barna Airi",
    "ks:ks_pop":118,
    "ks:ks_type":"HABITATION",
    "name:eng_x_preferred":[
        "Barna Airi"
    ],
    "wof:name":"Barna Airi",
    "wof:placetype":"locality",
    "wof:population":118
},
  "geometry": {"coordinates":[80.272232,29.848115],"type":"Point"}
}