{
  "type": "Feature",
  "properties": {
    "iso:country":"IN",
    "ks:ks_name":"Gobardih",
    "ks:ks_pop":545,
    "ks:ks_type":"HABITATION",
    "name:eng_x_preferred":[
        "Gobardih"
    ],
    "wof:name":"Gobardih",
    "wof:placetype":"locality",
    "wof:population":545
},
  "geometry": {"coordinates":[85.728942,23.516903],"type":"Point"}
}