{
  "type": "Feature",
  "properties": {
    "gn:admin1_code":"23.0",
    "gn:admin2_code":"052",
    "gn:asciiname":"Bhankarpur",
    "gn:country_code":"IN",
    "gn:dem":299,
    "gn:feature_class":"P",
    "gn:feature_code":"PPL",
    "gn:name":"Bhankarpur",
    "gn:population":0,
    "gn:timezone":"Asia/Kolkata",
    "iso:country":"IN",
    "ks:ks_name":"Bhankharpur",
    "ks:ks_pop":9216,
    "ks:ks_type":"URBAN",
    "ks:ks_uagg_main":0,
    "name:eng_x_preferred":[
        "Bhankharpur"
    ],
    "wof:name":"Bhankharpur",
    "wof:placetype":"neighbourhood",
    "wof:population":9216
},
  "geometry": {"coordinates":[76.835341,30.605767],"type":"Point"}
}