{
  "type": "Feature",
  "properties": {
    "gn:admin1_code":"16.0",
    "gn:admin2_code":"507.0",
    "gn:asciiname":"Telitola",
    "gn:country_code":"IN",
    "gn:dem":332,
    "gn:feature_class":"P",
    "gn:feature_code":"PPL",
    "gn:name":"Tel\u012btol\u0101",
    "gn:population":0,
    "gn:timezone":"Asia/Kolkata",
    "iso:country":"IN",
    "wof:name":"Telitola",
    "wof:placetype":"neighbourhood"
},
  "geometry": {"coordinates":[80.14917,21.31835],"type":"Point"}
}