{
  "type": "Feature",
  "properties": {
    "iso:country":"IN",
    "ks:ks_name":"Nandakheda Ryt",
    "ks:ks_pop":701,
    "ks:ks_type":"HABITATION",
    "name:eng_x_preferred":[
        "Nandakheda Ryt"
    ],
    "wof:name":"Nandakheda Ryt",
    "wof:placetype":"locality",
    "wof:population":701
},
  "geometry": {"coordinates":[76.37370300000001,22.199317],"type":"Point"}
}