{
  "type": "Feature",
  "properties": {
    "gn:admin1_code":"16",
    "gn:admin2_code":"509.0",
    "gn:asciiname":"Dewara",
    "gn:country_code":"IN",
    "gn:dem":235,
    "gn:feature_class":"P",
    "gn:feature_code":"PPL",
    "gn:name":"Dew\u0101ra",
    "gn:population":0,
    "gn:timezone":"Asia/Kolkata",
    "iso:country":"IN",
    "ks:ks_name":"Dewada",
    "ks:ks_pop":302,
    "ks:ks_type":"VILLAGE",
    "name:eng_x_preferred":[
        "Dewada"
    ],
    "name:eng_x_variant":[
        "Dewara"
    ],
    "wof:name":"Dewada",
    "wof:placetype":"locality",
    "wof:population":302
},
  "geometry": {"coordinates":[79.367256,20.137179],"type":"Point"}
}