{
  "type": "Feature",
  "properties": {
    "iso:country":"IN",
    "ks:ks_alt_nam":"Kud\u0101purti",
    "ks:ks_name":"Kudapurti",
    "ks:ks_type":"VILLAGE",
    "name:eng_x_preferred":[
        "Kudapurti"
    ],
    "name:eng_x_variant":[
        "Kud\u0101purti"
    ],
    "wof:name":"Kudapurti",
    "wof:placetype":"locality"
},
  "geometry": {"coordinates":[85.461107,22.999087],"type":"Point"}
}