{
  "type": "Feature",
  "properties": {
    "iso:country":"IN",
    "ks:ks_name":"Saidour Nawada",
    "ks:ks_pop":879,
    "ks:ks_type":"HABITATION",
    "name:eng_x_preferred":[
        "Saidour Nawada"
    ],
    "wof:name":"Saidour Nawada",
    "wof:placetype":"locality",
    "wof:population":879
},
  "geometry": {"coordinates":[85.099553,25.728498],"type":"Point"}
}