{
  "type": "Feature",
  "properties": {
    "gn:admin1_code":"39",
    "gn:admin2_code":"61.0",
    "gn:asciiname":"Charkandai",
    "gn:country_code":"IN",
    "gn:dem":1818,
    "gn:feature_class":"P",
    "gn:feature_code":"PPL",
    "gn:name":"Charkand\u0101i",
    "gn:population":0,
    "gn:timezone":"Asia/Kolkata",
    "iso:country":"IN",
    "ks:ks_alt_nam":"Charkand\u0101i",
    "ks:ks_name":"Charkandai",
    "ks:ks_type":"VILLAGE",
    "name:eng_x_preferred":[
        "Charkandai"
    ],
    "name:eng_x_variant":[
        "Charkand\u0101i"
    ],
    "wof:name":"Charkandai",
    "wof:placetype":"locality"
},
  "geometry": {"coordinates":[78.954992,29.892194],"type":"Point"}
}