{
  "type": "Feature",
  "properties": {
    "gn:admin1_code":"39",
    "gn:admin2_code":"61.0",
    "gn:asciiname":"Charkandai",
    "gn:country_code":"IN",
    "gn:dem":1818,
    "gn:feature_class":"P",
    "gn:feature_code":"PPL",
    "gn:name":"Charkand\u0101i",
    "gn:population":0,
    "gn:timezone":"Asia/Kolkata",
    "iso:country":"IN",
    "wof:name":"Charkandai",
    "wof:placetype":"locality"
},
  "geometry": {"coordinates":[78.95499000000002,29.89219000000001],"type":"Point"}
}