{
  "type": "Feature",
  "properties": {
    "gn:admin1_code":"36",
    "gn:admin2_code":"200.0",
    "gn:asciiname":"Jagdishpur",
    "gn:country_code":"IN",
    "gn:dem":326,
    "gn:feature_class":"P",
    "gn:feature_code":"PPL",
    "gn:name":"Jagd\u012bshpur",
    "gn:population":0,
    "gn:timezone":"Asia/Kolkata",
    "iso:country":"IN",
    "name:pol_x_preferred":[
        "Jagdishpur"
    ],
    "wof:name":"Jagdishpur",
    "wof:placetype":"locality"
},
  "geometry": {"coordinates":[83.23921,24.64781],"type":"Point"}
}