{
  "type": "Feature",
  "properties": {
    "iso:country":"IN",
    "ks:ks_name":"Ammavaripeta",
    "ks:ks_pop":220,
    "ks:ks_type":"VILLAGE",
    "name:eng_x_preferred":[
        "Ammavaripeta"
    ],
    "wof:name":"Ammavaripeta",
    "wof:placetype":"locality",
    "wof:population":220
},
  "geometry": {"coordinates":[78.443269,12.851741],"type":"Point"}
}