{
  "type": "Feature",
  "properties": {
    "iso:country":"IN",
    "ks:ks_alt_nam":"chmaran purwa",
    "ks:ks_name":"Chmaran Purwa",
    "ks:ks_pop":551,
    "ks:ks_type":"HABITATION",
    "ks:ks_uagg_main":0,
    "name:eng_x_preferred":[
        "Chmaran Purwa"
    ],
    "wof:name":"Chmaran Purwa",
    "wof:placetype":"neighbourhood",
    "wof:population":551
},
  "geometry": {"coordinates":[81.42778300000001,27.368702],"type":"Point"}
}