{
  "type": "Feature",
  "properties": {
    "gn:admin1_code":"40.0",
    "gn:admin2_code":"540",
    "gn:asciiname":"Kannai",
    "gn:country_code":"IN",
    "gn:dem":492,
    "gn:feature_class":"P",
    "gn:feature_code":"PPL",
    "gn:name":"Kannai",
    "gn:population":0,
    "gn:timezone":"Asia/Kolkata",
    "iso:country":"IN",
    "name:rus_x_preferred":[
        "\u041a\u0430\u043d\u043d\u0430\u0439"
    ],
    "name:zho_x_preferred":[
        "\u5173\u5167"
    ],
    "wof:name":"Kannai",
    "wof:placetype":"locality"
},
  "geometry": {"coordinates":[78.95534000000001,17.81667999999999],"type":"Point"}
}