{
  "type": "Feature",
  "properties": {
    "iso:country":"IN",
    "ks:ks_name":"Ratna",
    "ks:ks_pop":1793,
    "ks:ks_type":"VILLAGE",
    "name:eng_x_preferred":[
        "Ratna"
    ],
    "wof:name":"Ratna",
    "wof:placetype":"locality",
    "wof:population":1793
},
  "geometry": {"coordinates":[88.37915,22.320264],"type":"Point"}
}