{
  "type": "Feature",
  "properties": {
    "gn:admin1_code":"21.0",
    "gn:admin2_code":"396.0",
    "gn:asciiname":"Dukhunayakaguda",
    "gn:country_code":"IN",
    "gn:dem":223,
    "gn:feature_class":"P",
    "gn:feature_code":"PPL",
    "gn:name":"Dukhun\u0101yakaguda",
    "gn:population":0,
    "gn:timezone":"Asia/Kolkata",
    "iso:country":"IN",
    "name:und_x_variant":[
        "Dukhun\u0101yakaguda",
        "Gavuduguda"
    ],
    "wof:name":"Dukhunayakaguda",
    "wof:placetype":"locality"
},
  "geometry": {"coordinates":[83.42649,19.22307],"type":"Point"}
}