{
  "type": "Feature",
  "properties": {
    "iso:country":"IN",
    "ks:ks_name":"Taparpurwa",
    "ks:ks_pop":200,
    "ks:ks_type":"HABITATION",
    "name:eng_x_preferred":[
        "Taparpurwa"
    ],
    "wof:name":"Taparpurwa",
    "wof:placetype":"locality",
    "wof:population":200
},
  "geometry": {"coordinates":[81.053647,28.129776],"type":"Point"}
}