{
  "type": "Feature",
  "properties": {
    "iso:country":"IN",
    "ks:ks_name":"Bilhar",
    "ks:ks_pop":1,
    "ks:ks_type":"VILLAGE",
    "name:eng_x_preferred":[
        "Bilhar"
    ],
    "wof:name":"Bilhar",
    "wof:placetype":"locality",
    "wof:population":1
},
  "geometry": {"coordinates":[78.450884,25.5687],"type":"Point"}
}