{
  "type": "Feature",
  "properties": {
    "gn:admin1_code":"36",
    "gn:asciiname":"Bambari",
    "gn:country_code":"IN",
    "gn:dem":185,
    "gn:feature_class":"P",
    "gn:feature_code":"PPL",
    "gn:name":"Bamb\u0101ri",
    "gn:population":0,
    "gn:timezone":"Asia/Kolkata",
    "iso:country":"IN",
    "name:ara_x_preferred":[
        "\u0628\u0627\u0645\u0628\u0627\u0631\u064a"
    ],
    "name:azb_x_preferred":[
        "\u0628\u0627\u0645\u0628\u0627\u0631\u06cc"
    ],
    "name:bel_x_preferred":[
        "\u0411\u0430\u043c\u0431\u0430\u0440\u044b"
    ],
    "name:ceb_x_preferred":[
        "Bambari"
    ],
    "name:dan_x_preferred":[
        "Bambari"
    ],
    "name:deu_x_preferred":[
        "Bambari"
    ],
    "name:est_x_preferred":[
        "Bambari"
    ],
    "name:fas_x_preferred":[
        "\u0628\u0627\u0645\u0628\u0627\u0631\u06cc"
    ],
    "name:fin_x_preferred":[
        "Bambari"
    ],
    "name:fra_x_preferred":[
        "Bambari"
    ],
    "name:frr_x_preferred":[
        "Bambari"
    ],
    "name:heb_x_preferred":[
        "\u05d1\u05de\u05d1\u05d0\u05e8\u05d9"
    ],
    "name:ind_x_preferred":[
        "Bambari"
    ],
    "name:ita_x_preferred":[
        "Bambari"
    ],
    "name:jpn_x_preferred":[
        "\u30d0\u30f3\u30d0\u30ea"
    ],
    "name:kaz_x_preferred":[
        "\u0411\u0430\u043c\u0431\u0430\u0440\u0438"
    ],
    "name:kor_x_preferred":[
        "\ubc24\ubc14\ub9ac"
    ],
    "name:lit_x_preferred":[
        "Bambaris"
    ],
    "name:nld_x_preferred":[
        "Bambari"
    ],
    "name:pol_x_preferred":[
        "Bambari"
    ],
    "name:por_x_preferred":[
        "Bambari"
    ],
    "name:ron_x_preferred":[
        "Bambari"
    ],
    "name:rus_x_preferred":[
        "\u0411\u0430\u043c\u0431\u0430\u0440\u0438"
    ],
    "name:sag_x_preferred":[
        "B\u00e4mb\u00e4r\u00ee"
    ],
    "name:sqi_x_preferred":[
        "Bambari"
    ],
    "name:swe_x_preferred":[
        "Bambari"
    ],
    "name:tur_x_preferred":[
        "Bambari"
    ],
    "name:ukr_x_preferred":[
        "\u0411\u0430\u043c\u0431\u0430\u0440\u0456"
    ],
    "name:urd_x_preferred":[
        "\u0628\u0627\u0645\u0628\u0627\u0631\u06cc"
    ],
    "name:xmf_x_preferred":[
        "\u10d1\u10d0\u10db\u10d1\u10d0\u10e0\u10d8"
    ],
    "name:zho_x_preferred":[
        "\u73ed\u5df4\u91cc"
    ],
    "wof:name":"Bambari",
    "wof:placetype":"locality"
},
  "geometry": {"coordinates":[77.30553,27.76091],"type":"Point"}
}