{
  "type": "Feature",
  "properties": {
    "gn:admin1_code":"11",
    "gn:admin2_code":"23.0",
    "gn:asciiname":"Kakrauta",
    "gn:country_code":"IN",
    "gn:dem":1272,
    "gn:feature_class":"P",
    "gn:feature_code":"PPL",
    "gn:name":"Kakrauta",
    "gn:population":0,
    "gn:timezone":"Asia/Kolkata",
    "iso:country":"IN",
    "wof:name":"Kakrauta",
    "wof:placetype":"locality"
},
  "geometry": {"coordinates":[76.02129000000002,32.66911],"type":"Point"}
}