{
  "type": "Feature",
  "properties": {
    "gn:admin1_code":"34.0",
    "gn:admin2_code":"229.0",
    "gn:asciiname":"Kurthaul",
    "gn:country_code":"IN",
    "gn:dem":65,
    "gn:feature_class":"P",
    "gn:feature_code":"PPL",
    "gn:name":"Kurthaul",
    "gn:population":0,
    "gn:timezone":"Asia/Kolkata",
    "iso:country":"IN",
    "wof:name":"Kurthaul",
    "wof:placetype":"locality"
},
  "geometry": {"coordinates":[85.39397,25.08532],"type":"Point"}
}