{
  "type": "Feature",
  "properties": {
    "iso:country":"IN",
    "ks:ks_name":"Dakashni Mathna",
    "ks:ks_pop":80,
    "ks:ks_type":"HABITATION",
    "name:eng_x_preferred":[
        "Dakashni Mathna"
    ],
    "wof:name":"Dakashni Mathna",
    "wof:placetype":"locality",
    "wof:population":80
},
  "geometry": {"coordinates":[82.486541,27.23],"type":"Point"}
}