{
  "type": "Feature",
  "properties": {
    "iso:country":"IN",
    "ks:ks_name":"Pisadevi",
    "ks:ks_pop":3929,
    "ks:ks_type":"VILLAGE",
    "name:eng_x_preferred":[
        "Pisadevi"
    ],
    "wof:name":"Pisadevi",
    "wof:placetype":"neighbourhood",
    "wof:population":3929
},
  "geometry": {"coordinates":[75.38471199999999,19.913694],"type":"Point"}
}