{
  "type": "Feature",
  "properties": {
    "iso:country":"IN",
    "ks:ks_name":"Chavarcode",
    "ks:ks_pop":1218,
    "ks:ks_type":"HABITATION",
    "name:eng_x_preferred":[
        "Chavarcode"
    ],
    "wof:name":"Chavarcode",
    "wof:placetype":"locality",
    "wof:population":1218
},
  "geometry": {"coordinates":[76.757131,8.786952],"type":"Point"}
}