{
  "type": "Feature",
  "properties": {
    "iso:country":"IN",
    "ks:ks_name":"Rajepur Manjha",
    "ks:ks_pop":63,
    "ks:ks_type":"VILLAGE",
    "name:eng_x_preferred":[
        "Rajepur Manjha"
    ],
    "wof:name":"Rajepur Manjha",
    "wof:placetype":"locality",
    "wof:population":63
},
  "geometry": {"coordinates":[82.274855,26.71691],"type":"Point"}
}