{
  "type": "Feature",
  "properties": {
    "iso:country":"IN",
    "ks:ks_alt_nam":"BANSA",
    "ks:ks_name":"Bansa",
    "ks:ks_pop":156,
    "ks:ks_type":"HABITATION",
    "name:eng_x_preferred":[
        "Bansa"
    ],
    "wof:name":"Bansa",
    "wof:placetype":"locality",
    "wof:population":156
},
  "geometry": {"coordinates":[84.411503,24.164656],"type":"Point"}
}