{
  "type": "Feature",
  "properties": {
    "iso:country":"IN",
    "ks:ks_name":"Roopbas",
    "ks:ks_pop":649,
    "ks:ks_type":"VILLAGE",
    "name:eng_x_preferred":[
        "Roopbas"
    ],
    "wof:name":"Roopbas",
    "wof:placetype":"locality",
    "wof:population":649
},
  "geometry": {"coordinates":[76.842015,27.717607],"type":"Point"}
}