{
  "type": "Feature",
  "properties": {
    "iso:country":"IN",
    "ks:ks_name":"Kuzhinakkippara",
    "ks:ks_pop":450,
    "ks:ks_type":"HABITATION",
    "name:eng_x_preferred":[
        "Kuzhinakkippara"
    ],
    "wof:name":"Kuzhinakkippara",
    "wof:placetype":"locality",
    "wof:population":450
},
  "geometry": {"coordinates":[76.124878,11.244802],"type":"Point"}
}