{
  "type": "Feature",
  "properties": {
    "iso:country":"IN",
    "ks:ks_name":"Bhaurgarh",
    "ks:ks_pop":272,
    "ks:ks_type":"VILLAGE",
    "name:eng_x_preferred":[
        "Bhaurgarh"
    ],
    "wof:name":"Bhaurgarh",
    "wof:placetype":"locality",
    "wof:population":272
},
  "geometry": {"coordinates":[79.41674999999999,22.392762],"type":"Point"}
}