{
  "type": "Feature",
  "properties": {
    "iso:country":"IN",
    "ks:ks_name":"Shree Rampur Ka Drea",
    "ks:ks_pop":307,
    "ks:ks_type":"HABITATION",
    "name:eng_x_preferred":[
        "Shree Rampur Ka Drea"
    ],
    "wof:name":"Shree Rampur Ka Drea",
    "wof:placetype":"locality",
    "wof:population":307
},
  "geometry": {"coordinates":[79.76553699999999,25.714979],"type":"Point"}
}