{
  "type": "Feature",
  "properties": {
    "iso:country":"IN",
    "ks:ks_name":"Laktiguda",
    "ks:ks_pop":18,
    "ks:ks_type":"HABITATION",
    "name:eng_x_preferred":[
        "Laktiguda"
    ],
    "wof:name":"Laktiguda",
    "wof:placetype":"locality",
    "wof:population":18
},
  "geometry": {"coordinates":[82.307196,18.997693],"type":"Point"}
}