{
  "type": "Feature",
  "properties": {
    "gn:admin1_code":"16",
    "gn:admin2_code":"510.0",
    "gn:asciiname":"Rasa",
    "gn:country_code":"IN",
    "gn:dem":304,
    "gn:feature_class":"P",
    "gn:feature_code":"PPL",
    "gn:name":"R\u0101sa",
    "gn:population":0,
    "gn:timezone":"Asia/Kolkata",
    "iso:country":"IN",
    "name:cat_x_preferred":[
        "Rasa"
    ],
    "name:ceb_x_preferred":[
        "Rasa"
    ],
    "name:ces_x_preferred":[
        "Rasa"
    ],
    "name:deu_x_preferred":[
        "Rasa"
    ],
    "name:fra_x_preferred":[
        "Rasa"
    ],
    "name:ita_x_preferred":[
        "Rasa"
    ],
    "name:lav_x_preferred":[
        "Rase"
    ],
    "name:lit_x_preferred":[
        "Rasa"
    ],
    "name:lmo_x_preferred":[
        "Rasa"
    ],
    "name:nld_x_preferred":[
        "Rasa"
    ],
    "name:pol_x_preferred":[
        "Rasa"
    ],
    "name:rus_x_preferred":[
        "\u0420\u0430\u0441\u0430"
    ],
    "name:slk_x_preferred":[
        "Rasa"
    ],
    "name:swe_x_preferred":[
        "Rasa"
    ],
    "name:tat_x_preferred":[
        "\u0420\u0430\u0441\u0430"
    ],
    "wof:name":"Rasa",
    "wof:placetype":"locality"
},
  "geometry": {"coordinates":[78.34591999999998,20.42071],"type":"Point"}
}