{
  "type": "Feature",
  "properties": {
    "iso:country":"IN",
    "ks:ks_name":"Garkinabena",
    "ks:ks_pop":26,
    "ks:ks_type":"HABITATION",
    "name:eng_x_preferred":[
        "Garkinabena"
    ],
    "wof:name":"Garkinabena",
    "wof:placetype":"locality",
    "wof:population":26
},
  "geometry": {"coordinates":[74.70152,14.583711],"type":"Point"}
}