{
  "type": "Feature",
  "properties": {
    "iso:country":"IN",
    "ks:ks_name":"Manihara",
    "ks:ks_pop":1315,
    "ks:ks_type":"VILLAGE",
    "ks:ks_uagg_main":0,
    "name:eng_x_preferred":[
        "Manihara"
    ],
    "wof:name":"Manihara",
    "wof:placetype":"neighbourhood",
    "wof:population":1315
},
  "geometry": {"coordinates":[83.238725,25.365094],"type":"Point"}
}