{
  "type": "Feature",
  "properties": {
    "iso:country":"IN",
    "ks:ks_name":"Nani Bhamari",
    "ks:ks_pop":25,
    "ks:ks_type":"VILLAGE",
    "name:eng_x_preferred":[
        "Nani Bhamari"
    ],
    "wof:name":"Nani Bhamari",
    "wof:placetype":"locality",
    "wof:population":25
},
  "geometry": {"coordinates":[73.506354,21.738215],"type":"Point"}
}