{
  "type": "Feature",
  "properties": {
    "iso:country":"IN",
    "ks:ks_name":"Jinenahalli",
    "ks:ks_pop":413,
    "ks:ks_type":"HABITATION",
    "name:eng_x_preferred":[
        "Jinenahalli"
    ],
    "wof:name":"Jinenahalli",
    "wof:placetype":"locality",
    "wof:population":413
},
  "geometry": {"coordinates":[76.08281599999999,12.858707],"type":"Point"}
}