{
  "type": "Feature",
  "properties": {
    "iso:country":"IN",
    "ks:ks_name":"Madaiyinipatti",
    "ks:ks_pop":121,
    "ks:ks_type":"HABITATION",
    "name:eng_x_preferred":[
        "Madaiyinipatti"
    ],
    "wof:name":"Madaiyinipatti",
    "wof:placetype":"locality",
    "wof:population":121
},
  "geometry": {"coordinates":[78.34520500000001,10.160852],"type":"Point"}
}