{
  "type": "Feature",
  "properties": {
    "gn:admin1_code":"35",
    "gn:admin2_code":"436.0",
    "gn:asciiname":"Nazar Khera",
    "gn:country_code":"IN",
    "gn:dem":400,
    "gn:feature_class":"P",
    "gn:feature_code":"PPL",
    "gn:name":"Nazar Khera",
    "gn:population":0,
    "gn:timezone":"Asia/Kolkata",
    "iso:country":"IN",
    "ks:ks_name":"Najarkheda",
    "ks:ks_pop":394,
    "ks:ks_type":"VILLAGE",
    "name:eng_x_preferred":[
        "Najarkheda"
    ],
    "name:eng_x_variant":[
        "Nazar Khera"
    ],
    "wof:name":"Najarkheda",
    "wof:placetype":"locality",
    "wof:population":394
},
  "geometry": {"coordinates":[76.21450299999999,23.827654],"type":"Point"}
}