{
  "type": "Feature",
  "properties": {
    "gn:admin1_code":"12.0",
    "gn:admin2_code":"001",
    "gn:asciiname":"Ghumri",
    "gn:country_code":"IN",
    "gn:dem":2839,
    "gn:feature_class":"P",
    "gn:feature_code":"PPL",
    "gn:name":"Ghumri",
    "gn:population":0,
    "gn:timezone":"Asia/Kolkata",
    "iso:country":"IN",
    "wof:name":"Ghumri",
    "wof:placetype":"locality"
},
  "geometry": {"coordinates":[73.97983000000001,34.38734],"type":"Point"}
}