{
  "type": "Feature",
  "properties": {
    "gn:admin1_code":"36",
    "gn:admin2_code":"200.0",
    "gn:asciiname":"Pasahi Kalan",
    "gn:country_code":"IN",
    "gn:dem":305,
    "gn:feature_class":"P",
    "gn:feature_code":"PPL",
    "gn:name":"Pasahi Kal\u0101n",
    "gn:population":0,
    "gn:timezone":"Asia/Kolkata",
    "iso:country":"IN",
    "ks:ks_name":"Pashi Kalana",
    "ks:ks_pop":587,
    "ks:ks_type":"VILLAGE",
    "name:eng_x_preferred":[
        "Pashi Kalana"
    ],
    "name:eng_x_variant":[
        "Pasahi Kalan"
    ],
    "wof:name":"Pashi Kalana",
    "wof:placetype":"locality",
    "wof:population":587
},
  "geometry": {"coordinates":[83.056363,24.755185],"type":"Point"}
}