{
  "type": "Feature",
  "properties": {
    "iso:country":"IN",
    "ks:ks_name":"Lolampada",
    "ks:ks_pop":150,
    "ks:ks_type":"HABITATION",
    "name:eng_x_preferred":[
        "Lolampada"
    ],
    "wof:name":"Lolampada",
    "wof:placetype":"locality",
    "wof:population":150
},
  "geometry": {"coordinates":[73.08839,19.560158],"type":"Point"}
}