{
  "type": "Feature",
  "properties": {
    "iso:country":"IN",
    "ks:ks_name":"Bala Khoh",
    "ks:ks_pop":52,
    "ks:ks_type":"VILLAGE",
    "name:eng_x_preferred":[
        "Bala Khoh"
    ],
    "wof:name":"Bala Khoh",
    "wof:placetype":"locality",
    "wof:population":52
},
  "geometry": {"coordinates":[83.543363,24.800637],"type":"Point"}
}