{
  "type": "Feature",
  "properties": {
    "iso:country":"IN",
    "ks:ks_alt_nam":"T\u0101ka",
    "ks:ks_name":"Taka",
    "ks:ks_pop":4,
    "ks:ks_type":"VILLAGE",
    "name:eng_x_preferred":[
        "Taka"
    ],
    "name:eng_x_variant":[
        "T\u0101ka"
    ],
    "wof:name":"Taka",
    "wof:placetype":"locality",
    "wof:population":4
},
  "geometry": {"coordinates":[76.373079,20.884109],"type":"Point"}
}