{
  "type": "Feature",
  "properties": {
    "iso:country":"IN",
    "ks:ks_name":"Siya Bhata",
    "ks:ks_pop":0,
    "ks:ks_type":"VILLAGE",
    "name:eng_x_preferred":[
        "Siya Bhata"
    ],
    "wof:name":"Siya Bhata",
    "wof:placetype":"locality",
    "wof:population":0
},
  "geometry": {"coordinates":[78.794247,25.263752],"type":"Point"}
}