{
  "type": "Feature",
  "properties": {
    "iso:country":"IN",
    "ks:ks_alt_nam":"PANRRIA",
    "ks:ks_name":"Panrria",
    "ks:ks_pop":306,
    "ks:ks_type":"HABITATION",
    "name:eng_x_preferred":[
        "Panrria"
    ],
    "wof:name":"Panrria",
    "wof:placetype":"locality",
    "wof:population":306
},
  "geometry": {"coordinates":[86.996792,24.150358],"type":"Point"}
}