{
  "type": "Feature",
  "properties": {
    "iso:country":"IN",
    "ks:ks_name":"Rurwa Khas",
    "ks:ks_pop":438,
    "ks:ks_type":"VILLAGE",
    "ks:ks_uagg_main":0,
    "name:eng_x_preferred":[
        "Rurwa Khas"
    ],
    "wof:name":"Rurwa Khas",
    "wof:placetype":"neighbourhood",
    "wof:population":438
},
  "geometry": {"coordinates":[78.36292899999999,29.441409],"type":"Point"}
}