{
  "type": "Feature",
  "properties": {
    "iso:country":"IN",
    "ks:ks_name":"Sukharyt",
    "ks:ks_pop":395,
    "ks:ks_type":"VILLAGE",
    "name:eng_x_preferred":[
        "Sukharyt"
    ],
    "wof:name":"Sukharyt",
    "wof:placetype":"locality",
    "wof:population":395
},
  "geometry": {"coordinates":[79.515794,22.46144],"type":"Point"}
}