{
  "type": "Feature",
  "properties": {
    "iso:country":"IN",
    "ks:ks_name":"Koothadivayal",
    "ks:ks_pop":115,
    "ks:ks_type":"HABITATION",
    "name:eng_x_preferred":[
        "Koothadivayal"
    ],
    "wof:name":"Koothadivayal",
    "wof:placetype":"locality",
    "wof:population":115
},
  "geometry": {"coordinates":[79.21695200000001,10.187588],"type":"Point"}
}