{
  "type": "Feature",
  "properties": {
    "iso:country":"IN",
    "ks:ks_name":"Agampadu",
    "ks:ks_pop":157,
    "ks:ks_type":"VILLAGE",
    "name:eng_x_preferred":[
        "Agampadu"
    ],
    "wof:name":"Agampadu",
    "wof:placetype":"locality",
    "wof:population":157
},
  "geometry": {"coordinates":[82.510459,18.056044],"type":"Point"}
}