{
  "type": "Feature",
  "properties": {
    "gn:admin1_code":"25.0",
    "gn:admin2_code":"611.0",
    "gn:asciiname":"Melkavai",
    "gn:country_code":"IN",
    "gn:dem":2148,
    "gn:feature_class":"P",
    "gn:feature_code":"PPL",
    "gn:name":"M\u0113lkavai",
    "gn:population":0,
    "gn:timezone":"Asia/Kolkata",
    "iso:country":"IN",
    "wof:name":"Melkavai",
    "wof:placetype":"neighbourhood"
},
  "geometry": {"coordinates":[76.65834,11.38561],"type":"Point"}
}