{
  "type": "Feature",
  "properties": {
    "gn:admin1_code":"36.0",
    "gn:admin2_code":"190.0",
    "gn:asciiname":"Tharra",
    "gn:country_code":"IN",
    "gn:dem":72,
    "gn:feature_class":"P",
    "gn:feature_code":"PPL",
    "gn:name":"Tharra",
    "gn:population":0,
    "gn:timezone":"Asia/Kolkata",
    "iso:country":"IN",
    "ks:ks_name":"Thara",
    "ks:ks_pop":128,
    "ks:ks_type":"VILLAGE",
    "name:ceb_x_preferred":[
        "Tharra"
    ],
    "name:eng_x_preferred":[
        "Thara"
    ],
    "name:eng_x_variant":[
        "Tharra"
    ],
    "name:hin_x_preferred":[
        "\u0920\u0930\u094d\u0930\u093e"
    ],
    "name:swe_x_preferred":[
        "Tharra"
    ],
    "name:urd_x_preferred":[
        "\u0679\u06be\u0631\u0627"
    ],
    "name:war_x_preferred":[
        "Tharra"
    ],
    "wof:name":"Thara",
    "wof:placetype":"locality",
    "wof:population":128
},
  "geometry": {"coordinates":[83.97783699999999,26.24436],"type":"Point"}
}