{
  "type": "Feature",
  "properties": {
    "gn:admin1_code":"16.0",
    "gn:admin2_code":"514.0",
    "gn:asciiname":"Khatgaon",
    "gn:country_code":"IN",
    "gn:dem":582,
    "gn:feature_class":"P",
    "gn:feature_code":"PPL",
    "gn:name":"Kh\u0101tgaon",
    "gn:population":0,
    "gn:timezone":"Asia/Kolkata",
    "iso:country":"IN",
    "wof:name":"Khatgaon",
    "wof:placetype":"locality"
},
  "geometry": {"coordinates":[75.68079,20.11094],"type":"Point"}
}