{
  "type": "Feature",
  "properties": {
    "iso:country":"IN",
    "ks:ks_name":"Padmet Nagar",
    "ks:ks_pop":349,
    "ks:ks_type":"HABITATION",
    "name:eng_x_preferred":[
        "Padmet Nagar"
    ],
    "wof:name":"Padmet Nagar",
    "wof:placetype":"locality",
    "wof:population":349
},
  "geometry": {"coordinates":[72.109764,27.3343],"type":"Point"}
}