{
  "type": "Feature",
  "properties": {
    "iso:country":"IN",
    "ks:ks_name":"Ghamandia Barani",
    "ks:ks_pop":70,
    "ks:ks_type":"HABITATION",
    "name:eng_x_preferred":[
        "Ghamandia Barani"
    ],
    "wof:name":"Ghamandia Barani",
    "wof:placetype":"locality",
    "wof:population":70
},
  "geometry": {"coordinates":[73.797792,29.569964],"type":"Point"}
}