{
  "type": "Feature",
  "properties": {
    "iso:country":"IN",
    "ks:ks_name":"Sarsa Pachhimpatti",
    "ks:ks_pop":291,
    "ks:ks_type":"VILLAGE",
    "name:eng_x_preferred":[
        "Sarsa Pachhimpatti"
    ],
    "wof:name":"Sarsa Pachhimpatti",
    "wof:placetype":"locality",
    "wof:population":291
},
  "geometry": {"coordinates":[87.11390900000001,24.557446],"type":"Point"}
}