{
  "type": "Feature",
  "properties": {
    "iso:country":"IN",
    "ks:ks_alt_nam":"D.KOTHURU",
    "ks:ks_name":"D.kothuru",
    "ks:ks_pop":171,
    "ks:ks_type":"HABITATION",
    "name:eng_x_preferred":[
        "D.kothuru"
    ],
    "wof:name":"D.kothuru",
    "wof:placetype":"locality",
    "wof:population":171
},
  "geometry": {"coordinates":[82.42431500000001,17.643766],"type":"Point"}
}