{
  "type": "Feature",
  "properties": {
    "gn:country":"IN",
    "gn:fcode":"PPL",
    "gn:pop":15818,
    "iso:country":"IN",
    "name:ben_x_preferred":[
        "\u0995\u09be\u09ae\u09be\u0995\u09cd\u09b7\u09cd\u09af\u09be\u09a8\u0997\u09b0"
    ],
    "name:bpy_x_preferred":[
        "\u0995\u09be\u09ae\u09be\u0995\u09cd\u09b7\u09cd\u09af\u09be\u09a8\u0997\u09b0"
    ],
    "name:ceb_x_preferred":[
        "K\u0101m\u0101khy\u0101nagar"
    ],
    "name:deu_x_preferred":[
        "Kamakshyanagar"
    ],
    "name:eng_x_preferred":[
        "Kamakshyanagar"
    ],
    "name:fra_x_preferred":[
        "Kamakshyanagar"
    ],
    "name:guj_x_preferred":[
        "\u0a95\u0abe\u0aae\u0abe\u0a95\u0acd\u0ab7\u0acd\u0aaf\u0abe\u0aa8\u0a97\u0ab0"
    ],
    "name:ita_x_preferred":[
        "Kamakshyanagar"
    ],
    "name:jpn_x_preferred":[
        "\u30ab\u30de\u30c3\u30af\u30b7\u30e5\u30e4\u30ca\u30ac\u30fc\u30eb"
    ],
    "name:kan_x_preferred":[
        "\u0c95\u0cbe\u0cae\u0cbe\u0c95\u0ccd\u0cb7\u0cbf\u0ca8\u0c97\u0cb0\u0ccd"
    ],
    "name:kor_x_preferred":[
        "\uce74\ub9c8\uc26c\uc544\ub098\uac00\ub974"
    ],
    "name:msa_x_preferred":[
        "Kamakshyanagar"
    ],
    "name:nan_x_preferred":[
        "Kamakshyanagar"
    ],
    "name:nld_x_preferred":[
        "Kamakshyanagar"
    ],
    "name:ori_x_preferred":[
        "\u0b15\u0b3e\u0b2e\u0b3e\u0b15\u0b4d\u0b37\u0b3e\u0b28\u0b17\u0b30"
    ],
    "name:por_x_preferred":[
        "Kamakshyanagar"
    ],
    "name:rus_x_preferred":[
        "\u041a\u0430\u043c\u0430\u043a\u0448\u044c\u044f\u043d\u0430\u0433\u0430\u0440"
    ],
    "name:spa_x_preferred":[
        "Kamakshyanagar"
    ],
    "name:swe_x_preferred":[
        "K\u0101m\u0101khy\u0101nagar"
    ],
    "name:tam_x_preferred":[
        "\u0b95\u0bbe\u0bae\u0bbe\u0b95\u0bcd\u0bb7\u0bbf\u0baf\u0bbe\u0ba8\u0b95\u0bb0\u0bcd"
    ],
    "name:tel_x_preferred":[
        "\u0c15\u0c3e\u0c2e\u0c3e\u0c15\u0c4d\u0c37\u0c4d\u0c2f\u0c28\u0c17\u0c30\u0c4d"
    ],
    "name:unk_x_variant":[
        "Murhi"
    ],
    "name:urd_x_preferred":[
        "\u06a9\u0627\u0645\u0627\u06a9\u0634\u06cc\u0627\u0646\u06af\u0631"
    ],
    "name:vie_x_preferred":[
        "Kamakshyanagar"
    ],
    "name:zho_x_preferred":[
        "\u5361\u9a6c\u514b\u65af\u5e0c\u4e9a\u7eb3\u52a0\u5c14"
    ],
    "qs:name":"K\u0101m\u0101khy\u0101nagar",
    "qs:photos_9r":0,
    "qs:photos_sr":0,
    "qs:pop_sr":"6",
    "wof:name":"K\u0101m\u0101khy\u0101nagar",
    "wof:placetype":"locality",
    "wof:population":15818
},
  "geometry": {"coordinates":[85.5449,20.93385],"type":"Point"}
}