{
  "type": "Feature",
  "properties": {
    "gn:admin1_code":"16",
    "gn:admin2_code":"511.0",
    "gn:asciiname":"Ambulgaon",
    "gn:country_code":"IN",
    "gn:dem":444,
    "gn:feature_class":"P",
    "gn:feature_code":"PPL",
    "gn:name":"Ambulgaon",
    "gn:population":0,
    "gn:timezone":"Asia/Kolkata",
    "iso:country":"IN",
    "wof:name":"Ambulgaon",
    "wof:placetype":"locality"
},
  "geometry": {"coordinates":[77.50438,18.39335],"type":"Point"}
}