{
  "type": "Feature",
  "properties": {
    "iso:country":"IN",
    "ks:ks_name":"Pahantoli",
    "ks:ks_pop":185,
    "ks:ks_type":"HABITATION",
    "name:eng_x_preferred":[
        "Pahantoli"
    ],
    "wof:name":"Pahantoli",
    "wof:placetype":"locality",
    "wof:population":185
},
  "geometry": {"coordinates":[84.343947,22.542298],"type":"Point"}
}