{
  "type": "Feature",
  "properties": {
    "gn:admin1_code":"02",
    "gn:admin2_code":"545.0",
    "gn:asciiname":"Ravutulapudi",
    "gn:country_code":"IN",
    "gn:dem":69,
    "gn:feature_class":"P",
    "gn:feature_code":"PPL",
    "gn:name":"Ravutulap\u016bdi",
    "gn:population":0,
    "gn:timezone":"Asia/Kolkata",
    "iso:country":"IN",
    "name:und_x_variant":[
        "Ravutalapudi",
        "Ravutulap\u016bdi"
    ],
    "wof:name":"Ravutulapudi",
    "wof:placetype":"neighbourhood"
},
  "geometry": {"coordinates":[82.37134,17.37643],"type":"Point"}
}