{
  "type": "Feature",
  "properties": {
    "iso:country":"IN",
    "ks:ks_name":"Fud Bigha",
    "ks:ks_pop":133,
    "ks:ks_type":"HABITATION",
    "name:eng_x_preferred":[
        "Fud Bigha"
    ],
    "wof:name":"Fud Bigha",
    "wof:placetype":"locality",
    "wof:population":133
},
  "geometry": {"coordinates":[85.616585,25.244349],"type":"Point"}
}