{
  "type": "Feature",
  "properties": {
    "iso:country":"IN",
    "ks:ks_alt_nam":"SASITHOTA",
    "ks:ks_name":"Sasithota",
    "ks:ks_pop":189,
    "ks:ks_type":"HABITATION",
    "name:eng_x_preferred":[
        "Sasithota"
    ],
    "wof:name":"Sasithota",
    "wof:placetype":"locality",
    "wof:population":189
},
  "geometry": {"coordinates":[75.323593,13.640847],"type":"Point"}
}