{
  "type": "Feature",
  "properties": {
    "iso:country":"IN",
    "ks:ks_name":"Dolatpura Abbal",
    "ks:ks_pop":0,
    "ks:ks_type":"VILLAGE",
    "name:eng_x_preferred":[
        "Dolatpura Abbal"
    ],
    "wof:name":"Dolatpura Abbal",
    "wof:placetype":"locality",
    "wof:population":0
},
  "geometry": {"coordinates":[78.864187,26.261582],"type":"Point"}
}