{
  "type": "Feature",
  "properties": {
    "iso:country":"IN",
    "ks:ks_name":"Naya Kher",
    "ks:ks_pop":478,
    "ks:ks_type":"HABITATION",
    "name:eng_x_preferred":[
        "Naya Kher"
    ],
    "wof:name":"Naya Kher",
    "wof:placetype":"locality",
    "wof:population":478
},
  "geometry": {"coordinates":[81.10126700000001,25.008821],"type":"Point"}
}