{
  "type": "Feature",
  "properties": {
    "gn:admin1_code":"19.0",
    "gn:admin2_code":"579.0",
    "gn:asciiname":"Gangapur",
    "gn:country_code":"IN",
    "gn:dem":408,
    "gn:feature_class":"P",
    "gn:feature_code":"PPL",
    "gn:name":"G\u0101ng\u0101pur",
    "gn:population":0,
    "gn:timezone":"Asia/Kolkata",
    "iso:country":"IN",
    "name:bih_x_preferred":[
        "\u0917\u0902\u0917\u093e\u092a\u0941\u0930"
    ],
    "name:ceb_x_preferred":[
        "Gangapur"
    ],
    "name:ita_x_preferred":[
        "Gangapur"
    ],
    "name:pol_x_preferred":[
        "Gangapur"
    ],
    "name:swe_x_preferred":[
        "Gangapur"
    ],
    "name:und_x_variant":[
        "G\u0101ng\u0101pur",
        "G\u0101nag\u0101pur"
    ],
    "name:vie_x_preferred":[
        "Gangapur"
    ],
    "wof:name":"Gangapur",
    "wof:placetype":"locality"
},
  "geometry": {"coordinates":[76.53327,17.18031],"type":"Point"}
}