{
  "type": "Feature",
  "properties": {
    "iso:country":"IN",
    "ks:ks_name":"Saroapur",
    "ks:ks_pop":682,
    "ks:ks_type":"VILLAGE",
    "name:eng_x_preferred":[
        "Saroapur"
    ],
    "wof:name":"Saroapur",
    "wof:placetype":"locality",
    "wof:population":682
},
  "geometry": {"coordinates":[87.781841,24.910273],"type":"Point"}
}