{
  "type": "Feature",
  "properties": {
    "iso:country":"IN",
    "ks:ks_name":"Moxenmansingh",
    "ks:ks_pop":9,
    "ks:ks_type":"VILLAGE",
    "name:eng_x_preferred":[
        "Moxenmansingh"
    ],
    "wof:name":"Moxenmansingh",
    "wof:placetype":"locality",
    "wof:population":9
},
  "geometry": {"coordinates":[79.02143100000001,29.65484],"type":"Point"}
}