{
  "type": "Feature",
  "properties": {
    "gn:admin1_code":"11",
    "gn:admin2_code":"23.0",
    "gn:asciiname":"Luharka",
    "gn:country_code":"IN",
    "gn:dem":1582,
    "gn:feature_class":"P",
    "gn:feature_code":"PPL",
    "gn:name":"Luh\u0101rka",
    "gn:population":0,
    "gn:timezone":"Asia/Kolkata",
    "iso:country":"IN",
    "wof:name":"Luharka",
    "wof:placetype":"locality"
},
  "geometry": {"coordinates":[76.24783000000002,32.47689],"type":"Point"}
}