{
  "type": "Feature",
  "properties": {
    "iso:country":"IN",
    "ks:ks_name":"South Boragila",
    "ks:ks_pop":1397,
    "ks:ks_type":"HABITATION",
    "name:eng_x_preferred":[
        "South Boragila"
    ],
    "wof:name":"South Boragila",
    "wof:placetype":"locality",
    "wof:population":1397
},
  "geometry": {"coordinates":[89.510717,26.464188],"type":"Point"}
}