{
  "type": "Feature",
  "properties": {
    "iso:country":"IN",
    "ks:ks_name":"Parbbatipur",
    "ks:ks_pop":2079,
    "ks:ks_type":"VILLAGE",
    "ks:ks_uagg_main":0,
    "name:eng_x_preferred":[
        "Parbbatipur"
    ],
    "wof:name":"Parbbatipur",
    "wof:placetype":"neighbourhood",
    "wof:population":2079
},
  "geometry": {"coordinates":[88.14130900000001,22.667707],"type":"Point"}
}