{
  "type": "Feature",
  "properties": {
    "iso:country":"IN",
    "ks:ks_name":"Kulang",
    "ks:ks_pop":169,
    "ks:ks_type":"VILLAGE",
    "name:eng_x_preferred":[
        "Kulang"
    ],
    "wof:name":"Kulang",
    "wof:placetype":"locality",
    "wof:population":169
},
  "geometry": {"coordinates":[83.991696,19.047932],"type":"Point"}
}