{
  "type": "Feature",
  "properties": {
    "iso:country":"IN",
    "ks:ks_name":"Banamahari",
    "ks:ks_pop":482,
    "ks:ks_type":"VILLAGE",
    "name:eng_x_preferred":[
        "Banamahari"
    ],
    "wof:name":"Banamahari",
    "wof:placetype":"locality",
    "wof:population":482
},
  "geometry": {"coordinates":[82.967913,24.086019],"type":"Point"}
}