{
  "type": "Feature",
  "properties": {
    "gn:admin1_code":"36.0",
    "gn:admin2_code":"132.0",
    "gn:asciiname":"Mughal Mazra",
    "gn:country_code":"IN",
    "gn:dem":271,
    "gn:feature_class":"P",
    "gn:feature_code":"PPL",
    "gn:name":"Mughal M\u0101zra",
    "gn:population":0,
    "gn:timezone":"Asia/Kolkata",
    "iso:country":"IN",
    "ks:ks_alt_nam":"Mughal M\u0101zra",
    "ks:ks_name":"Mughal Mazra",
    "ks:ks_type":"VILLAGE",
    "name:eng_x_preferred":[
        "Mughal Mazra"
    ],
    "name:eng_x_variant":[
        "Mughal M\u0101zra"
    ],
    "wof:name":"Mughal Mazra",
    "wof:placetype":"locality"
},
  "geometry": {"coordinates":[77.496684,29.87216],"type":"Point"}
}