{
  "type": "Feature",
  "properties": {
    "iso:country":"IN",
    "ks:ks_name":"Beli Kalan",
    "ks:ks_pop":0,
    "ks:ks_type":"VILLAGE",
    "name:eng_x_preferred":[
        "Beli Kalan"
    ],
    "wof:name":"Beli Kalan",
    "wof:placetype":"locality",
    "wof:population":0
},
  "geometry": {"coordinates":[76.40933,30.960177],"type":"Point"}
}