{
  "type": "Feature",
  "properties": {
    "iso:country":"IN",
    "ks:ks_name":"Anantapur",
    "ks:ks_pop":1000,
    "ks:ks_type":"VILLAGE",
    "name:eng_x_preferred":[
        "Anantapur"
    ],
    "name:hin_x_preferred":[
        "\u0905\u0928\u0902\u0924\u092a\u0941\u0930"
    ],
    "name:tel_x_preferred":[
        "\u0c05\u0c28\u0c02\u0c24\u0c2a\u0c41\u0c30\u0c02"
    ],
    "name:urd_x_preferred":[
        "\u0627\u0646\u0646\u062a\u067e\u0648\u0631"
    ],
    "wof:name":"Anantapur",
    "wof:placetype":"locality",
    "wof:population":1000
},
  "geometry": {"coordinates":[86.480008,21.625397],"type":"Point"}
}