{
  "type": "Feature",
  "properties": {
    "iso:country":"IN",
    "ks:ks_name":"Anantapur",
    "ks:ks_pop":1000,
    "ks:ks_type":"VILLAGE",
    "name:eng_x_preferred":[
        "Anantapur"
    ],
    "wof:name":"Anantapur",
    "wof:placetype":"locality",
    "wof:population":1000
},
  "geometry": {"coordinates":[86.480008,21.625397],"type":"Point"}
}