{
  "type": "Feature",
  "properties": {
    "gn:admin1_code":"2.0",
    "gn:admin2_code":"554",
    "gn:asciiname":"Damalcheruvu",
    "gn:country_code":"IN",
    "gn:dem":391,
    "gn:feature_class":"P",
    "gn:feature_code":"PPL",
    "gn:name":"Damalcheruvu",
    "gn:population":0,
    "gn:timezone":"Asia/Kolkata",
    "iso:country":"IN",
    "name:ceb_x_preferred":[
        "D\u0101malcheruvu"
    ],
    "name:jpn_x_preferred":[
        "\u30c0\u30fc\u30de\u30eb\u30c1\u30a7\u30eb\u30f4"
    ],
    "name:swe_x_preferred":[
        "D\u0101malcheruvu"
    ],
    "name:tel_x_preferred":[
        "\u0c26\u0c3e\u0c2e\u0c32\u0c4d\u0c1a\u0c46\u0c30\u0c41\u0c35\u0c41"
    ],
    "wof:name":"Damalcheruvu",
    "wof:placetype":"locality"
},
  "geometry": {"coordinates":[79.05218000000001,13.47593],"type":"Point"}
}