{
  "type": "Feature",
  "properties": {
    "iso:country":"IN",
    "ks:ks_name":"Baratikar",
    "ks:ks_pop":419,
    "ks:ks_type":"VILLAGE",
    "ks:ks_uagg_main":0,
    "name:eng_x_preferred":[
        "Baratikar"
    ],
    "wof:name":"Baratikar",
    "wof:placetype":"locality",
    "wof:population":419
},
  "geometry": {"coordinates":[86.71364199999999,24.508261],"type":"Point"}
}