{
  "type": "Feature",
  "properties": {
    "iso:country":"IN",
    "ks:ks_name":"Devalekoppa",
    "ks:ks_pop":120,
    "ks:ks_type":"HABITATION",
    "name:eng_x_preferred":[
        "Devalekoppa"
    ],
    "wof:name":"Devalekoppa",
    "wof:placetype":"locality",
    "wof:population":120
},
  "geometry": {"coordinates":[75.179636,13.482679],"type":"Point"}
}