{
  "type": "Feature",
  "properties": {
    "iso:country":"IN",
    "ks:ks_name":"Garhitanr",
    "ks:ks_pop":181,
    "ks:ks_type":"VILLAGE",
    "name:eng_x_preferred":[
        "Garhitanr"
    ],
    "wof:name":"Garhitanr",
    "wof:placetype":"locality",
    "wof:population":181
},
  "geometry": {"coordinates":[86.93755400000001,24.438371],"type":"Point"}
}