{
  "type": "Feature",
  "properties": {
    "gn:admin1_code":"2",
    "gn:admin2_code":"545.0",
    "gn:asciiname":"Pusivada",
    "gn:country_code":"IN",
    "gn:dem":929,
    "gn:feature_class":"P",
    "gn:feature_code":"PPL",
    "gn:name":"Pusiv\u0101da",
    "gn:population":0,
    "gn:timezone":"Asia/Kolkata",
    "iso:country":"IN",
    "wof:name":"Pusivada",
    "wof:placetype":"locality"
},
  "geometry": {"coordinates":[81.86835000000001,17.85773],"type":"Point"}
}