{
  "type": "Feature",
  "properties": {
    "gn:admin1_code":"40.0",
    "gn:admin2_code":"539.0",
    "gn:asciiname":"Sadhupalli",
    "gn:country_code":"IN",
    "gn:dem":416,
    "gn:feature_class":"P",
    "gn:feature_code":"PPL",
    "gn:name":"S\u0101dhupalli",
    "gn:population":0,
    "gn:timezone":"Asia/Kolkata",
    "iso:country":"IN",
    "wof:name":"Sadhupalli",
    "wof:placetype":"locality"
},
  "geometry": {"coordinates":[78.96576999999998,17.66156],"type":"Point"}
}