{
  "type": "Feature",
  "properties": {
    "iso:country":"IN",
    "ks:ks_alt_nam":"AHIRPARA",
    "ks:ks_name":"Ahirpara",
    "ks:ks_pop":499,
    "ks:ks_type":"HABITATION",
    "name:eng_x_preferred":[
        "Ahirpara"
    ],
    "wof:name":"Ahirpara",
    "wof:placetype":"locality",
    "wof:population":499
},
  "geometry": {"coordinates":[83.294455,22.859225],"type":"Point"}
}