{
  "type": "Feature",
  "properties": {
    "gn:admin1_code":"21",
    "gn:admin2_code":"396.0",
    "gn:asciiname":"Boriguda",
    "gn:country_code":"IN",
    "gn:dem":458,
    "gn:feature_class":"P",
    "gn:feature_code":"PPL",
    "gn:name":"Boriguda",
    "gn:population":0,
    "gn:timezone":"Asia/Kolkata",
    "iso:country":"IN",
    "ks:ks_name":"Boroguda",
    "ks:ks_pop":40,
    "ks:ks_type":"HABITATION",
    "name:eng_x_preferred":[
        "Boroguda"
    ],
    "name:eng_x_variant":[
        "Boriguda"
    ],
    "wof:name":"Boroguda",
    "wof:placetype":"locality",
    "wof:population":40
},
  "geometry": {"coordinates":[83.46324199999999,19.565525],"type":"Point"}
}