{
  "type": "Feature",
  "properties": {
    "iso:country":"IN",
    "ks:ks_name":"Pawarwasti",
    "ks:ks_pop":78,
    "ks:ks_type":"HABITATION",
    "name:eng_x_preferred":[
        "Pawarwasti"
    ],
    "wof:name":"Pawarwasti",
    "wof:placetype":"locality",
    "wof:population":78
},
  "geometry": {"coordinates":[74.63772299999999,17.94073],"type":"Point"}
}