{
  "type": "Feature",
  "properties": {
    "iso:country":"IN",
    "ks:ks_name":"Mukundpura",
    "ks:ks_pop":44,
    "ks:ks_type":"HABITATION",
    "name:eng_x_preferred":[
        "Mukundpura"
    ],
    "wof:name":"Mukundpura",
    "wof:placetype":"locality",
    "wof:population":44
},
  "geometry": {"coordinates":[76.720968,25.724405],"type":"Point"}
}