{
  "type": "Feature",
  "properties": {
    "iso:country":"IN",
    "ks:ks_name":"Peddammagaripalle",
    "ks:ks_pop":105,
    "ks:ks_type":"HABITATION",
    "name:eng_x_preferred":[
        "Peddammagaripalle"
    ],
    "wof:name":"Peddammagaripalle",
    "wof:placetype":"locality",
    "wof:population":105
},
  "geometry": {"coordinates":[79.01388799999999,13.587771],"type":"Point"}
}