{
  "type": "Feature",
  "properties": {
    "iso:country":"IN",
    "ks:ks_name":"Bishanpur Majra Gunarsi",
    "ks:ks_pop":181,
    "ks:ks_type":"VILLAGE",
    "name:eng_x_preferred":[
        "Bishanpur Majra Gunarsi"
    ],
    "wof:name":"Bishanpur Majra Gunarsi",
    "wof:placetype":"locality",
    "wof:population":181
},
  "geometry": {"coordinates":[77.676879,29.649716],"type":"Point"}
}