{
  "type": "Feature",
  "properties": {
    "gn:admin1_code":"35",
    "gn:admin2_code":"428.0",
    "gn:asciiname":"Dukarsata",
    "gn:country_code":"IN",
    "gn:dem":378,
    "gn:feature_class":"P",
    "gn:feature_code":"PPL",
    "gn:name":"Dukarsata",
    "gn:population":0,
    "gn:timezone":"Asia/Kolkata",
    "iso:country":"IN",
    "ks:ks_name":"Dukarsata",
    "ks:ks_pop":491,
    "ks:ks_type":"HABITATION",
    "name:eng_x_preferred":[
        "Dukarsata"
    ],
    "wof:name":"Dukarsata",
    "wof:placetype":"locality",
    "wof:population":491
},
  "geometry": {"coordinates":[79.420332,23.488401],"type":"Point"}
}