{
  "type": "Feature",
  "properties": {
    "iso:country":"IN",
    "ks:ks_alt_nam":"Adibandaruvari cheruvu",
    "ks:ks_name":"Adibandaruvari Cheruvu",
    "ks:ks_pop":592,
    "ks:ks_type":"HABITATION",
    "name:eng_x_preferred":[
        "Adibandaruvari Cheruvu"
    ],
    "wof:name":"Adibandaruvari Cheruvu",
    "wof:placetype":"locality",
    "wof:population":592
},
  "geometry": {"coordinates":[81.773231,16.543888],"type":"Point"}
}