{
  "type": "Feature",
  "properties": {
    "iso:country":"IN",
    "ks:ks_name":"Surengelpada",
    "ks:ks_pop":95,
    "ks:ks_type":"HABITATION",
    "name:eng_x_preferred":[
        "Surengelpada"
    ],
    "wof:name":"Surengelpada",
    "wof:placetype":"locality",
    "wof:population":95
},
  "geometry": {"coordinates":[82.523866,18.610944],"type":"Point"}
}