{
  "type": "Feature",
  "properties": {
    "iso:country":"IN",
    "ks:ks_name":"Paraswar",
    "ks:ks_pop":45,
    "ks:ks_type":"VILLAGE",
    "ks:ks_uagg_main":0,
    "name:eng_x_preferred":[
        "Paraswar"
    ],
    "wof:name":"Paraswar",
    "wof:placetype":"neighbourhood",
    "wof:population":45
},
  "geometry": {"coordinates":[82.103883,24.573628],"type":"Point"}
}