{
  "type": "Feature",
  "properties": {
    "iso:country":"IN",
    "ks:ks_name":"Anabari",
    "ks:ks_pop":226,
    "ks:ks_type":"VILLAGE",
    "name:eng_x_preferred":[
        "Anabari"
    ],
    "wof:name":"Anabari",
    "wof:placetype":"locality",
    "wof:population":226
},
  "geometry": {"coordinates":[83.339631,19.077736],"type":"Point"}
}