{
  "type": "Feature",
  "properties": {
    "gn:admin1_code":"35.0",
    "gn:admin2_code":"450.0",
    "gn:asciiname":"Bargawan",
    "gn:country_code":"IN",
    "gn:dem":401,
    "gn:feature_class":"P",
    "gn:feature_code":"PPL",
    "gn:name":"Bargaw\u0101n",
    "gn:population":0,
    "gn:timezone":"Asia/Kolkata",
    "iso:country":"IN",
    "ks:ks_alt_nam":"Bargaw\u0101n",
    "ks:ks_name":"Bargawan",
    "ks:ks_pop":683,
    "ks:ks_type":"VILLAGE",
    "name:eng_x_preferred":[
        "Bargawan"
    ],
    "name:eng_x_variant":[
        "Bargaw\u0101n"
    ],
    "wof:name":"Bargawan",
    "wof:placetype":"locality",
    "wof:population":683
},
  "geometry": {"coordinates":[80.605062,23.737322],"type":"Point"}
}