{
  "type": "Feature",
  "properties": {
    "iso:country":"IN",
    "ks:ks_name":"Porairi",
    "ks:ks_pop":568,
    "ks:ks_type":"VILLAGE",
    "name:eng_x_preferred":[
        "Porairi"
    ],
    "wof:name":"Porairi",
    "wof:placetype":"locality",
    "wof:population":568
},
  "geometry": {"coordinates":[87.47001899999999,22.982447],"type":"Point"}
}