{
  "type": "Feature",
  "properties": {
    "iso:country":"IN",
    "ks:ks_name":"Musahri Tola",
    "ks:ks_pop":2020,
    "ks:ks_type":"HABITATION",
    "name:eng_x_preferred":[
        "Musahri Tola"
    ],
    "wof:name":"Musahri Tola",
    "wof:placetype":"locality",
    "wof:population":2020
},
  "geometry": {"coordinates":[87.083118,25.4772],"type":"Point"}
}