{
  "type": "Feature",
  "properties": {
    "gn:admin1_code":"02",
    "gn:admin2_code":"546.0",
    "gn:asciiname":"Mogalturru",
    "gn:country_code":"IN",
    "gn:dem":14,
    "gn:feature_class":"P",
    "gn:feature_code":"PPL",
    "gn:name":"Mogalturru",
    "gn:population":0,
    "gn:timezone":"Asia/Kolkata",
    "iso:country":"IN",
    "name:und_x_variant":[
        "Mogaltur",
        "Mogalturru"
    ],
    "wof:name":"Mogalturru",
    "wof:placetype":"locality"
},
  "geometry": {"coordinates":[81.60773,16.41232999999999],"type":"Point"}
}