{
  "type": "Feature",
  "properties": {
    "iso:country":"IN",
    "ks:ks_alt_nam":"SAI TOLA",
    "ks:ks_name":"Sai Tola",
    "ks:ks_pop":423,
    "ks:ks_type":"HABITATION",
    "name:eng_x_preferred":[
        "Sai Tola"
    ],
    "wof:name":"Sai Tola",
    "wof:placetype":"locality",
    "wof:population":423
},
  "geometry": {"coordinates":[84.79386100000001,26.260462],"type":"Point"}
}