{
  "type": "Feature",
  "properties": {
    "gn:admin1_code":"36",
    "gn:admin2_code":"191.0",
    "gn:asciiname":"Gandi",
    "gn:country_code":"IN",
    "gn:dem":89,
    "gn:feature_class":"P",
    "gn:feature_code":"PPL",
    "gn:name":"Gandi",
    "gn:population":0,
    "gn:timezone":"Asia/Kolkata",
    "iso:country":"IN",
    "name:fra_x_preferred":[
        "Gandi"
    ],
    "name:jpn_x_preferred":[
        "Gandi"
    ],
    "name:swe_x_preferred":[
        "Gandi"
    ],
    "wof:name":"Gandi",
    "wof:placetype":"locality"
},
  "geometry": {"coordinates":[82.87094999999999,26.04123],"type":"Point"}
}