{
  "type": "Feature",
  "properties": {
    "iso:country":"IN",
    "ks:ks_name":"Doluipara",
    "ks:ks_pop":452,
    "ks:ks_type":"HABITATION",
    "name:eng_x_preferred":[
        "Doluipara"
    ],
    "wof:name":"Doluipara",
    "wof:placetype":"locality",
    "wof:population":452
},
  "geometry": {"coordinates":[88.009642,22.628431],"type":"Point"}
}