{
  "type": "Feature",
  "properties": {
    "iso:country":"IN",
    "ks:ks_alt_nam":"Yanadipalem (E&W)",
    "ks:ks_name":"Yanadipalem (e&w)",
    "ks:ks_pop":150,
    "ks:ks_type":"HABITATION",
    "ks:ks_uagg_main":0,
    "name:eng_x_preferred":[
        "Yanadipalem (e&w)"
    ],
    "wof:name":"Yanadipalem (e&w)",
    "wof:placetype":"neighbourhood",
    "wof:population":150
},
  "geometry": {"coordinates":[80.040333,15.079603],"type":"Point"}
}