{
  "type": "Feature",
  "properties": {
    "iso:country":"IN",
    "ks:ks_name":"Mottur Anaibogi",
    "ks:ks_pop":116,
    "ks:ks_type":"HABITATION",
    "name:eng_x_preferred":[
        "Mottur Anaibogi"
    ],
    "wof:name":"Mottur Anaibogi",
    "wof:placetype":"locality",
    "wof:population":116
},
  "geometry": {"coordinates":[79.48241,12.542221],"type":"Point"}
}