{
  "type": "Feature",
  "properties": {
    "iso:country":"IN",
    "ks:ks_alt_nam":"SARDARPURA KHARTHA",
    "ks:ks_name":"Sardarpura Khartha",
    "ks:ks_pop":294,
    "ks:ks_type":"HABITATION",
    "name:eng_x_preferred":[
        "Sardarpura Khartha"
    ],
    "wof:name":"Sardarpura Khartha",
    "wof:placetype":"locality",
    "wof:population":294
},
  "geometry": {"coordinates":[74.22666700000001,29.255278],"type":"Point"}
}