{
  "type": "Feature",
  "properties": {
    "gn:admin1_code":"36",
    "gn:admin2_code":"134.0",
    "gn:asciiname":"Begrajpur Gadol",
    "gn:country_code":"IN",
    "gn:dem":238,
    "gn:feature_class":"P",
    "gn:feature_code":"PPL",
    "gn:name":"Begr\u0101jpur G\u0101dol",
    "gn:population":0,
    "gn:timezone":"Asia/Kolkata",
    "iso:country":"IN",
    "wof:name":"Begrajpur Gadol",
    "wof:placetype":"neighbourhood"
},
  "geometry": {"coordinates":[78.33599,29.31575],"type":"Point"}
}