{
  "type": "Feature",
  "properties": {
    "gn:admin1_code":"11",
    "gn:admin2_code":"23.0",
    "gn:asciiname":"Tarroga",
    "gn:country_code":"IN",
    "gn:dem":1919,
    "gn:feature_class":"P",
    "gn:feature_code":"PPL",
    "gn:name":"Tarroga",
    "gn:population":0,
    "gn:timezone":"Asia/Kolkata",
    "iso:country":"IN",
    "wof:name":"Tarroga",
    "wof:placetype":"locality"
},
  "geometry": {"coordinates":[76.06936,32.83467],"type":"Point"}
}