{
  "type": "Feature",
  "properties": {
    "iso:country":"IN",
    "ks:ks_name":"Temki",
    "ks:ks_pop":1057,
    "ks:ks_type":"VILLAGE",
    "name:eng_x_preferred":[
        "Temki"
    ],
    "wof:name":"Temki",
    "wof:placetype":"locality",
    "wof:population":1057
},
  "geometry": {"coordinates":[84.61458399999999,23.794507],"type":"Point"}
}