{
  "type": "Feature",
  "properties": {
    "iso:country":"IN",
    "ks:ks_alt_nam":"ADELI",
    "ks:ks_name":"Adeli",
    "ks:ks_pop":2,
    "ks:ks_type":"HABITATION",
    "name:eng_x_preferred":[
        "Adeli"
    ],
    "wof:name":"Adeli",
    "wof:placetype":"locality",
    "wof:population":2
},
  "geometry": {"coordinates":[84.237201,19.967948],"type":"Point"}
}