{
  "type": "Feature",
  "properties": {
    "iso:country":"IN",
    "ks:ks_name":"Ghagharwa",
    "ks:ks_pop":57,
    "ks:ks_type":"HABITATION",
    "name:eng_x_preferred":[
        "Ghagharwa"
    ],
    "wof:name":"Ghagharwa",
    "wof:placetype":"locality",
    "wof:population":57
},
  "geometry": {"coordinates":[82.923239,27.211555],"type":"Point"}
}