{
  "type": "Feature",
  "properties": {
    "iso:country":"IN",
    "ks:ks_name":"Tandola",
    "ks:ks_pop":32,
    "ks:ks_type":"VILLAGE",
    "name:eng_x_preferred":[
        "Tandola"
    ],
    "wof:name":"Tandola",
    "wof:placetype":"locality",
    "wof:population":32
},
  "geometry": {"coordinates":[79.082866,29.815038],"type":"Point"}
}