{
  "type": "Feature",
  "properties": {
    "iso:country":"IN",
    "ks:ks_name":"Mandakakkunnu Rd Jnc",
    "ks:ks_pop":521,
    "ks:ks_type":"HABITATION",
    "name:eng_x_preferred":[
        "Mandakakkunnu Rd Jnc"
    ],
    "wof:name":"Mandakakkunnu Rd Jnc",
    "wof:placetype":"locality",
    "wof:population":521
},
  "geometry": {"coordinates":[76.21284199999999,11.130124],"type":"Point"}
}