{
  "type": "Feature",
  "properties": {
    "gn:admin1_code":"36",
    "gn:admin2_code":"198.0",
    "gn:asciiname":"Khanapur",
    "gn:country_code":"IN",
    "gn:dem":90,
    "gn:feature_class":"P",
    "gn:feature_code":"PPL",
    "gn:name":"Kh\u0101n\u0101pur",
    "gn:population":0,
    "gn:timezone":"Asia/Kolkata",
    "iso:country":"IN",
    "ks:ks_name":"Khanapur",
    "ks:ks_pop":852,
    "ks:ks_type":"HABITATION",
    "name:ben_x_preferred":[
        "\u0996\u09be\u09a8\u09be\u09aa\u09c1\u09b0"
    ],
    "name:bpy_x_preferred":[
        "\u0996\u09be\u09a8\u09be\u09aa\u09c1\u09b0"
    ],
    "name:ceb_x_preferred":[
        "Kh\u0101n\u0101pur"
    ],
    "name:eng_x_preferred":[
        "Khanapur"
    ],
    "name:ita_x_preferred":[
        "Khanapur"
    ],
    "name:kan_x_preferred":[
        "\u0c96\u0cbe\u0ca8\u0cbe\u0caa\u0cc1\u0cb0"
    ],
    "name:mar_x_preferred":[
        "\u0916\u093e\u0928\u093e\u092a\u0942\u0930"
    ],
    "name:mlg_x_preferred":[
        "Khanapur"
    ],
    "name:msa_x_preferred":[
        "Khanapur"
    ],
    "name:new_x_preferred":[
        "\u0916\u093e\u0928\u093e\u092a\u0941\u0930"
    ],
    "name:nld_x_preferred":[
        "Khanapur"
    ],
    "name:pam_x_preferred":[
        "Khanapur"
    ],
    "name:por_x_preferred":[
        "Khanapur"
    ],
    "name:san_x_preferred":[
        "\u0916\u093e\u0928\u093e\u092a\u0941\u0930\u092e\u094d"
    ],
    "name:swe_x_preferred":[
        "Kh\u0101n\u0101pur"
    ],
    "name:tam_x_preferred":[
        "\u0b95\u0bbe\u0ba9\u0bbe\u0baa\u0bc2\u0bb0\u0bcd"
    ],
    "name:vie_x_preferred":[
        "Khanapur"
    ],
    "name:zho_x_preferred":[
        "\u5361\u7eb3\u666e\u5c14"
    ],
    "wof:name":"Khanapur",
    "wof:placetype":"locality",
    "wof:population":852
},
  "geometry": {"coordinates":[82.398625,25.31813],"type":"Point"}
}