{
  "type": "Feature",
  "properties": {
    "iso:country":"IN",
    "ks:ks_alt_nam":"KaharToli   South",
    "ks:ks_name":"Kahartoli South",
    "ks:ks_pop":178,
    "ks:ks_type":"HABITATION",
    "name:eng_x_preferred":[
        "Kahartoli South"
    ],
    "name:eng_x_variant":[
        "KaharToli   South"
    ],
    "wof:name":"Kahartoli South",
    "wof:placetype":"locality",
    "wof:population":178
},
  "geometry": {"coordinates":[86.908608,25.611394],"type":"Point"}
}