{
  "type": "Feature",
  "properties": {
    "iso:country":"IN",
    "ks:ks_name":"Aroskarwadi",
    "ks:ks_pop":22,
    "ks:ks_type":"HABITATION",
    "name:eng_x_preferred":[
        "Aroskarwadi"
    ],
    "wof:name":"Aroskarwadi",
    "wof:placetype":"locality",
    "wof:population":22
},
  "geometry": {"coordinates":[73.763957,15.79732],"type":"Point"}
}