{
  "type": "Feature",
  "properties": {
    "gn:admin1_code":"23.0",
    "gn:admin2_code":"37.0",
    "gn:asciiname":"Yusufpur Aliwal",
    "gn:country_code":"IN",
    "gn:dem":213,
    "gn:feature_class":"P",
    "gn:feature_code":"PPL",
    "gn:name":"Y\u016bsufpur Al\u012bw\u0101l",
    "gn:population":0,
    "gn:timezone":"Asia/Kolkata",
    "iso:country":"IN",
    "ks:ks_alt_nam":"Y\u016bsufpur Al\u012bw\u0101l",
    "ks:ks_name":"Yusufpur Aliwal",
    "ks:ks_pop":263,
    "ks:ks_type":"VILLAGE",
    "name:eng_x_preferred":[
        "Yusufpur Aliwal"
    ],
    "name:eng_x_variant":[
        "Y\u016bsufpur Al\u012bw\u0101l"
    ],
    "wof:name":"Yusufpur Aliwal",
    "wof:placetype":"locality",
    "wof:population":263
},
  "geometry": {"coordinates":[75.105997,31.147289],"type":"Point"}
}