{
  "type": "Feature",
  "properties": {
    "iso:country":"IN",
    "ks:ks_name":"Sathewasti",
    "ks:ks_pop":107,
    "ks:ks_type":"HABITATION",
    "ks:ks_uagg_main":0,
    "name:eng_x_preferred":[
        "Sathewasti"
    ],
    "wof:name":"Sathewasti",
    "wof:placetype":"neighbourhood",
    "wof:population":107
},
  "geometry": {"coordinates":[74.49534800000001,19.023921],"type":"Point"}
}