{
  "type": "Feature",
  "properties": {
    "iso:country":"IN",
    "ks:ks_name":"Methadaka",
    "ks:ks_pop":280,
    "ks:ks_type":"HABITATION",
    "name:eng_x_preferred":[
        "Methadaka"
    ],
    "wof:name":"Methadaka",
    "wof:placetype":"locality",
    "wof:population":280
},
  "geometry": {"coordinates":[75.482597,12.564467],"type":"Point"}
}