{
  "type": "Feature",
  "properties": {
    "iso:country":"IN",
    "ks:ks_name":"Ladilapur",
    "ks:ks_pop":739,
    "ks:ks_type":"VILLAGE",
    "ks:ks_uagg_main":0,
    "name:eng_x_preferred":[
        "Ladilapur"
    ],
    "wof:name":"Ladilapur",
    "wof:placetype":"neighbourhood",
    "wof:population":739
},
  "geometry": {"coordinates":[81.272357,27.509108],"type":"Point"}
}