{
  "type": "Feature",
  "properties": {
    "gn:admin1_code":"21.0",
    "gn:admin2_code":"396.0",
    "gn:asciiname":"Kankubadi",
    "gn:country_code":"IN",
    "gn:dem":391,
    "gn:feature_class":"P",
    "gn:feature_code":"PPL",
    "gn:name":"Kankub\u0101di",
    "gn:population":0,
    "gn:timezone":"Asia/Kolkata",
    "iso:country":"IN",
    "ks:ks_alt_nam":"Kankub\u0101di",
    "ks:ks_name":"Kankubadi",
    "ks:ks_pop":213,
    "ks:ks_type":"VILLAGE",
    "name:eng_x_preferred":[
        "Kankubadi"
    ],
    "name:eng_x_variant":[
        "Kankub\u0101di"
    ],
    "wof:name":"Kankubadi",
    "wof:placetype":"locality",
    "wof:population":213
},
  "geometry": {"coordinates":[83.593951,19.293681],"type":"Point"}
}