{
  "type": "Feature",
  "properties": {
    "iso:country":"IN",
    "ks:ks_name":"Navi Nagari Vasahat",
    "ks:ks_pop":1519,
    "ks:ks_type":"HABITATION",
    "name:eng_x_preferred":[
        "Navi Nagari Vasahat"
    ],
    "wof:name":"Navi Nagari Vasahat",
    "wof:placetype":"locality",
    "wof:population":1519
},
  "geometry": {"coordinates":[73.035083,20.836222],"type":"Point"}
}