{
  "type": "Feature",
  "properties": {
    "iso:country":"IN",
    "ks:ks_name":"South Tola",
    "ks:ks_pop":425,
    "ks:ks_type":"HABITATION",
    "ks:ks_uagg_main":0,
    "name:eng_x_preferred":[
        "South Tola"
    ],
    "wof:name":"South Tola",
    "wof:placetype":"neighbourhood",
    "wof:population":425
},
  "geometry": {"coordinates":[87.83262499999999,26.336072],"type":"Point"}
}