{
  "type": "Feature",
  "properties": {
    "gn:admin1_code":"35",
    "gn:admin2_code":"449.0",
    "gn:asciiname":"Nipaniya",
    "gn:country_code":"IN",
    "gn:dem":313,
    "gn:feature_class":"P",
    "gn:feature_code":"PPL",
    "gn:name":"Nip\u0101niya",
    "gn:population":0,
    "gn:timezone":"Asia/Kolkata",
    "iso:country":"IN",
    "wof:name":"Nipaniya",
    "wof:placetype":"locality"
},
  "geometry": {"coordinates":[77.42185000000001,22.46365],"type":"Point"}
}