{
  "type": "Feature",
  "properties": {
    "iso:country":"IN",
    "ks:ks_name":"Adivashiwadi Dhankanhe",
    "ks:ks_pop":428,
    "ks:ks_type":"HABITATION",
    "name:eng_x_preferred":[
        "Adivashiwadi Dhankanhe"
    ],
    "wof:name":"Adivashiwadi Dhankanhe",
    "wof:placetype":"locality",
    "wof:population":428
},
  "geometry": {"coordinates":[73.17353900000001,18.455778],"type":"Point"}
}