{
  "type": "Feature",
  "properties": {
    "iso:country":"IN",
    "ks:ks_name":"Baburajapuram",
    "ks:ks_pop":664,
    "ks:ks_type":"VILLAGE",
    "ks:ks_uagg_main":0,
    "name:eng_x_preferred":[
        "Baburajapuram"
    ],
    "wof:name":"Baburajapuram",
    "wof:placetype":"neighbourhood",
    "wof:population":664
},
  "geometry": {"coordinates":[79.34315700000001,10.963055],"type":"Point"}
}