{
  "type": "Feature",
  "properties": {
    "gn:admin1_code":"39.0",
    "gn:admin2_code":"65.0",
    "gn:asciiname":"Banauli",
    "gn:country_code":"IN",
    "gn:dem":1435,
    "gn:feature_class":"P",
    "gn:feature_code":"PPL",
    "gn:name":"Banauli",
    "gn:population":0,
    "gn:timezone":"Asia/Kolkata",
    "iso:country":"IN",
    "name:bih_x_preferred":[
        "\u092c\u0928\u094c\u0932\u0940"
    ],
    "name:ceb_x_preferred":[
        "Banauli"
    ],
    "name:dty_x_preferred":[
        "\u092c\u0928\u094c\u0932\u0940 \u0917\u093e\u0935\u093f\u0938"
    ],
    "name:fra_x_preferred":[
        "Banauli"
    ],
    "name:hin_x_preferred":[
        "\u092c\u0928\u094c\u0932\u0940"
    ],
    "name:mai_x_preferred":[
        "\u092c\u0928\u094c\u0932\u0940"
    ],
    "name:msa_x_preferred":[
        "Banauli"
    ],
    "name:nep_x_preferred":[
        "\u092c\u0928\u094c\u0932\u0940"
    ],
    "name:new_x_preferred":[
        "\u092c\u0928\u094c\u0932\u0940"
    ],
    "name:pol_x_preferred":[
        "Banauli"
    ],
    "wof:name":"Banauli",
    "wof:placetype":"locality"
},
  "geometry": {"coordinates":[79.87613,29.44758],"type":"Point"}
}