{
  "type": "Feature",
  "properties": {
    "iso:country":"IN",
    "ks:ks_name":"Walsure",
    "ks:ks_pop":54,
    "ks:ks_type":"VILLAGE",
    "name:eng_x_preferred":[
        "Walsure"
    ],
    "wof:name":"Walsure",
    "wof:placetype":"locality",
    "wof:population":54
},
  "geometry": {"coordinates":[73.416027,18.22088],"type":"Point"}
}