{
  "type": "Feature",
  "properties": {
    "iso:country":"IN",
    "ks:ks_name":"1 A-A",
    "ks:ks_pop":515,
    "ks:ks_type":"VILLAGE",
    "name:eng_x_preferred":[
        "1 A-A"
    ],
    "wof:name":"1 A-A",
    "wof:placetype":"locality",
    "wof:population":515
},
  "geometry": {"coordinates":[73.337773,29.130312],"type":"Point"}
}