{
  "type": "Feature",
  "properties": {
    "iso:country":"IN",
    "ks:ks_name":"Bergi",
    "ks:ks_pop":543,
    "ks:ks_type":"VILLAGE",
    "ks:ks_uagg_main":0,
    "name:eng_x_preferred":[
        "Bergi"
    ],
    "wof:name":"Bergi",
    "wof:placetype":"locality",
    "wof:population":543
},
  "geometry": {"coordinates":[86.33838299999999,24.20265],"type":"Point"}
}