{
  "type": "Feature",
  "properties": {
    "iso:country":"IN",
    "ks:ks_name":"Bara Chetro",
    "ks:ks_pop":97,
    "ks:ks_type":"VILLAGE",
    "name:eng_x_preferred":[
        "Bara Chetro"
    ],
    "wof:name":"Bara Chetro",
    "wof:placetype":"locality",
    "wof:population":97
},
  "geometry": {"coordinates":[87.560095,24.730599],"type":"Point"}
}