{
  "type": "Feature",
  "properties": {
    "iso:country":"IN",
    "ks:ks_name":"Majher Para",
    "ks:ks_pop":681,
    "ks:ks_type":"HABITATION",
    "name:eng_x_preferred":[
        "Majher Para"
    ],
    "wof:name":"Majher Para",
    "wof:placetype":"locality",
    "wof:population":681
},
  "geometry": {"coordinates":[88.713189,22.173675],"type":"Point"}
}