{
  "type": "Feature",
  "properties": {
    "iso:country":"IN",
    "ks:ks_name":"Gundi Faliya",
    "ks:ks_pop":1071,
    "ks:ks_type":"HABITATION",
    "name:eng_x_preferred":[
        "Gundi Faliya"
    ],
    "wof:name":"Gundi Faliya",
    "wof:placetype":"locality",
    "wof:population":1071
},
  "geometry": {"coordinates":[74.294111,23.067833],"type":"Point"}
}