{
  "type": "Feature",
  "properties": {
    "iso:country":"IN",
    "ks:ks_name":"Luhakhan",
    "ks:ks_pop":484,
    "ks:ks_type":"HABITATION",
    "name:eng_x_preferred":[
        "Luhakhan"
    ],
    "wof:name":"Luhakhan",
    "wof:placetype":"locality",
    "wof:population":484
},
  "geometry": {"coordinates":[84.552937,22.194607],"type":"Point"}
}