{
  "type": "Feature",
  "properties": {
    "gn:admin1_code":"36.0",
    "gn:admin2_code":"179.0",
    "gn:asciiname":"Khukhipur",
    "gn:country_code":"IN",
    "gn:dem":106,
    "gn:feature_class":"P",
    "gn:feature_code":"PPL",
    "gn:name":"Kh\u016bkhipur",
    "gn:population":0,
    "gn:timezone":"Asia/Kolkata",
    "iso:country":"IN",
    "ks:ks_name":"Khokhipur",
    "ks:ks_pop":900,
    "ks:ks_type":"VILLAGE",
    "ks:ks_uagg_main":0,
    "name:eng_x_preferred":[
        "Khokhipur"
    ],
    "wof:name":"Khokhipur",
    "wof:placetype":"neighbourhood",
    "wof:population":900
},
  "geometry": {"coordinates":[81.892385,26.31742],"type":"Point"}
}