{
  "type": "Feature",
  "properties": {
    "gn:admin1_code":"11",
    "gn:admin2_code":"23.0",
    "gn:asciiname":"Baretara",
    "gn:country_code":"IN",
    "gn:dem":2372,
    "gn:feature_class":"P",
    "gn:feature_code":"PPL",
    "gn:name":"Baretara",
    "gn:population":0,
    "gn:timezone":"Asia/Kolkata",
    "iso:country":"IN",
    "wof:name":"Baretara",
    "wof:placetype":"locality"
},
  "geometry": {"coordinates":[76.28046999999999,32.72769],"type":"Point"}
}