{
  "type": "Feature",
  "properties": {
    "gn:admin1_code":"38.0",
    "gn:admin2_code":"358.0",
    "gn:asciiname":"Bansdih",
    "gn:country_code":"IN",
    "gn:dem":239,
    "gn:feature_class":"P",
    "gn:feature_code":"PPL",
    "gn:name":"B\u0101nsd\u012bh",
    "gn:population":0,
    "gn:timezone":"Asia/Kolkata",
    "iso:country":"IN",
    "name:bih_x_preferred":[
        "\u092c\u093e\u0901\u0938\u0921\u0940\u0939"
    ],
    "name:bpy_x_preferred":[
        "\u09ac\u09be\u09a8\u09b8\u09a6\u09bf\u09b9"
    ],
    "name:ceb_x_preferred":[
        "B\u0101nsd\u012bh"
    ],
    "name:hin_x_preferred":[
        "\u092c\u093e\u0901\u0938\u0921\u0940\u0939"
    ],
    "name:ita_x_preferred":[
        "Bansdih"
    ],
    "name:msa_x_preferred":[
        "Bansdih"
    ],
    "name:new_x_preferred":[
        "\u092c\u093e\u0901\u0938\u0921\u0940\u0939"
    ],
    "name:nld_x_preferred":[
        "Bansdih"
    ],
    "name:pol_x_preferred":[
        "Bansdih"
    ],
    "name:por_x_preferred":[
        "Bansdih"
    ],
    "name:swe_x_preferred":[
        "B\u0101nsd\u012bh"
    ],
    "name:urd_x_preferred":[
        "\u0628\u0627\u0646\u0633 \u062f\u06c1"
    ],
    "name:vie_x_preferred":[
        "Bansdih"
    ],
    "name:zho_x_preferred":[
        "\u73ed\u65af\u8fea"
    ],
    "wof:name":"Bansdih",
    "wof:placetype":"locality"
},
  "geometry": {"coordinates":[84.01635999999998,24.06086],"type":"Point"}
}