{
  "type": "Feature",
  "properties": {
    "iso:country":"IN",
    "ks:ks_name":"Karaikurichi",
    "ks:ks_pop":1479,
    "ks:ks_type":"VILLAGE",
    "ks:ks_uagg_main":0,
    "name:eng_x_preferred":[
        "Karaikurichi"
    ],
    "wof:name":"Karaikurichi",
    "wof:placetype":"neighbourhood",
    "wof:population":1479
},
  "geometry": {"coordinates":[79.35888,11.078682],"type":"Point"}
}