{
  "type": "Feature",
  "properties": {
    "iso:country":"IN",
    "ks:ks_name":"Ihdlavi",
    "ks:ks_pop":410,
    "ks:ks_type":"VILLAGE",
    "name:eng_x_preferred":[
        "Ihdlavi"
    ],
    "wof:name":"Ihdlavi",
    "wof:placetype":"locality",
    "wof:population":410
},
  "geometry": {"coordinates":[73.625631,21.493796],"type":"Point"}
}