{
  "type": "Feature",
  "properties": {
    "iso:country":"IN",
    "ks:ks_name":"Khakhra",
    "ks:ks_type":"VILLAGE",
    "name:eng_x_preferred":[
        "Khakhra"
    ],
    "wof:name":"Khakhra",
    "wof:placetype":"locality"
},
  "geometry": {"coordinates":[86.819911,24.221978],"type":"Point"}
}