{
  "type": "Feature",
  "properties": {
    "iso:country":"IN",
    "ks:ks_name":"Papila",
    "ks:ks_pop":2004,
    "ks:ks_type":"VILLAGE",
    "ks:ks_uagg_main":0,
    "name:eng_x_preferred":[
        "Papila"
    ],
    "wof:name":"Papila",
    "wof:placetype":"locality",
    "wof:population":2004
},
  "geometry": {"coordinates":[88.782282,22.837096],"type":"Point"}
}