{
  "type": "Feature",
  "properties": {
    "iso:country":"IN",
    "ks:ks_name":"Rayli",
    "ks:ks_pop":1203,
    "ks:ks_type":"HABITATION",
    "name:eng_x_preferred":[
        "Rayli"
    ],
    "wof:name":"Rayli",
    "wof:placetype":"locality",
    "wof:population":1203
},
  "geometry": {"coordinates":[76.426219,27.793944],"type":"Point"}
}