{
  "type": "Feature",
  "properties": {
    "gn:admin1_code":"34.0",
    "gn:admin2_code":"240.0",
    "gn:asciiname":"Sherpur",
    "gn:country_code":"IN",
    "gn:dem":81,
    "gn:feature_class":"P",
    "gn:feature_code":"PPL",
    "gn:name":"Sherpur",
    "gn:population":0,
    "gn:timezone":"Asia/Kolkata",
    "iso:country":"IN",
    "wof:name":"Sherpur",
    "wof:placetype":"locality"
},
  "geometry": {"coordinates":[84.73061,25.13827],"type":"Point"}
}