{
  "type": "Feature",
  "properties": {
    "gn:admin1_code":"11",
    "gn:admin2_code":"27.0",
    "gn:asciiname":"Serla Khabu",
    "gn:country_code":"IN",
    "gn:dem":1494,
    "gn:feature_class":"P",
    "gn:feature_code":"PPL",
    "gn:name":"Serla Kh\u0101bu",
    "gn:population":0,
    "gn:timezone":"Asia/Kolkata",
    "iso:country":"IN",
    "wof:name":"Serla Khabu",
    "wof:placetype":"locality"
},
  "geometry": {"coordinates":[76.83088000000002,31.65026],"type":"Point"}
}