{
  "type": "Feature",
  "properties": {
    "iso:country":"IN",
    "ks:ks_alt_nam":"Gauh\u0101ni Khurd",
    "ks:ks_name":"Gauhani Khurd",
    "ks:ks_type":"VILLAGE",
    "name:eng_x_preferred":[
        "Gauhani Khurd"
    ],
    "name:eng_x_variant":[
        "Gauh\u0101ni Khurd"
    ],
    "wof:name":"Gauhani Khurd",
    "wof:placetype":"locality"
},
  "geometry": {"coordinates":[81.02422300000001,25.409993],"type":"Point"}
}