{
  "type": "Feature",
  "properties": {
    "gn:admin1_code":"40",
    "gn:admin2_code":"537.0",
    "gn:asciiname":"Chandanagar",
    "gn:country_code":"IN",
    "gn:dem":568,
    "gn:feature_class":"P",
    "gn:feature_code":"PPL",
    "gn:name":"Chand\u0101nagar",
    "gn:population":0,
    "gn:timezone":"Asia/Kolkata",
    "iso:country":"IN",
    "ks:ks_alt_nam":"Chand\u0101nagar",
    "ks:ks_name":"Chandanagar",
    "ks:ks_type":"VILLAGE",
    "ks:ks_uagg_main":0,
    "wof:name":"Chandanagar",
    "wof:placetype":"neighbourhood"
},
  "geometry": {"coordinates":[78.33172999999999,17.49377],"type":"Point"}
}