{
  "type": "Feature",
  "properties": {
    "iso:country":"IN",
    "ks:ks_name":"Dakdungri",
    "ks:ks_pop":69,
    "ks:ks_type":"HABITATION",
    "name:eng_x_preferred":[
        "Dakdungri"
    ],
    "wof:name":"Dakdungri",
    "wof:placetype":"locality",
    "wof:population":69
},
  "geometry": {"coordinates":[83.03917,20.078484],"type":"Point"}
}