{
  "type": "Feature",
  "properties": {
    "gn:admin1_code":"36.0",
    "gn:asciiname":"Baseri",
    "gn:country_code":"IN",
    "gn:dem":208,
    "gn:feature_class":"P",
    "gn:feature_code":"PPL",
    "gn:name":"Baseri",
    "gn:population":0,
    "gn:timezone":"Asia/Kolkata",
    "iso:country":"IN",
    "name:ceb_x_preferred":[
        "Baseri"
    ],
    "name:msa_x_preferred":[
        "Baseri"
    ],
    "name:pol_x_preferred":[
        "Baseri"
    ],
    "wof:name":"Baseri",
    "wof:placetype":"locality"
},
  "geometry": {"coordinates":[77.53944,26.74836],"type":"Point"}
}