{
  "type": "Feature",
  "properties": {
    "iso:country":"IN",
    "ks:ks_name":"Asramam",
    "ks:ks_pop":85,
    "ks:ks_type":"HABITATION",
    "name:eng_x_preferred":[
        "Asramam"
    ],
    "wof:name":"Asramam",
    "wof:placetype":"locality",
    "wof:population":85
},
  "geometry": {"coordinates":[77.638042,12.527985],"type":"Point"}
}