{
  "type": "Feature",
  "properties": {
    "iso:country":"IN",
    "ks:ks_name":"4 GM-B",
    "ks:ks_pop":65,
    "ks:ks_type":"VILLAGE",
    "name:eng_x_preferred":[
        "4 GM-B"
    ],
    "wof:name":"4 GM-B",
    "wof:placetype":"locality",
    "wof:population":65
},
  "geometry": {"coordinates":[72.992684,28.973777],"type":"Point"}
}