{
  "type": "Feature",
  "properties": {
    "gn:admin1_code":"35.0",
    "gn:admin2_code":"453.0",
    "gn:asciiname":"Bankatola",
    "gn:country_code":"IN",
    "gn:dem":696,
    "gn:feature_class":"P",
    "gn:feature_code":"PPL",
    "gn:name":"B\u0101nk\u0101tol\u0101",
    "gn:population":0,
    "gn:timezone":"Asia/Kolkata",
    "iso:country":"IN",
    "ks:ks_alt_nam":"B\u0101nk\u0101tol\u0101",
    "ks:ks_name":"Bankatola",
    "ks:ks_type":"VILLAGE",
    "name:eng_x_preferred":[
        "Bankatola"
    ],
    "name:eng_x_variant":[
        "B\u0101nk\u0101tol\u0101"
    ],
    "wof:name":"Bankatola",
    "wof:placetype":"locality"
},
  "geometry": {"coordinates":[80.948077,22.811505],"type":"Point"}
}