{
  "type": "Feature",
  "properties": {
    "gn:admin1_code":"36",
    "gn:admin2_code":"185.0",
    "gn:asciiname":"Pagar Khas",
    "gn:country_code":"IN",
    "gn:dem":88,
    "gn:feature_class":"P",
    "gn:feature_code":"PPL",
    "gn:name":"Pag\u0101r Kh\u0101s",
    "gn:population":0,
    "gn:timezone":"Asia/Kolkata",
    "iso:country":"IN",
    "ks:ks_name":"Pagar Khash",
    "ks:ks_pop":663,
    "ks:ks_type":"VILLAGE",
    "ks:ks_uagg_main":0,
    "name:eng_x_preferred":[
        "Pagar Khash"
    ],
    "wof:name":"Pagar Khash",
    "wof:placetype":"neighbourhood",
    "wof:population":663
},
  "geometry": {"coordinates":[82.857418,26.699445],"type":"Point"}
}