{
  "type": "Feature",
  "properties": {
    "iso:country":"IN",
    "ks:ks_name":"Uchhola",
    "ks:ks_pop":867,
    "ks:ks_type":"VILLAGE",
    "name:eng_x_preferred":[
        "Uchhola"
    ],
    "wof:name":"Uchhola",
    "wof:placetype":"locality",
    "wof:population":867
},
  "geometry": {"coordinates":[79.010204,30.471449],"type":"Point"}
}