{
  "type": "Feature",
  "properties": {
    "iso:country":"IN",
    "ks:ks_name":"Karumathur",
    "ks:ks_pop":451,
    "ks:ks_type":"HABITATION",
    "name:eng_x_preferred":[
        "Karumathur"
    ],
    "wof:name":"Karumathur",
    "wof:placetype":"locality",
    "wof:population":451
},
  "geometry": {"coordinates":[77.92601500000001,9.938244],"type":"Point"}
}