{
  "type": "Feature",
  "properties": {
    "iso:country":"IN",
    "ks:ks_name":"Kuranwadi",
    "ks:ks_pop":100,
    "ks:ks_type":"HABITATION",
    "name:eng_x_preferred":[
        "Kuranwadi"
    ],
    "wof:name":"Kuranwadi",
    "wof:placetype":"locality",
    "wof:population":100
},
  "geometry": {"coordinates":[74.26495,19.058412],"type":"Point"}
}