{
  "type": "Feature",
  "properties": {
    "gn:admin1_code":"2.0",
    "gn:admin2_code":"554.0",
    "gn:asciiname":"Bodinayanipalle",
    "gn:country_code":"IN",
    "gn:dem":745,
    "gn:feature_class":"P",
    "gn:feature_code":"PPL",
    "gn:name":"Bodin\u0101yanipalle",
    "gn:population":0,
    "gn:timezone":"Asia/Kolkata",
    "iso:country":"IN",
    "wof:name":"Bodinayanipalle",
    "wof:placetype":"locality"
},
  "geometry": {"coordinates":[78.55098000000002,13.3864],"type":"Point"}
}