{
  "type": "Feature",
  "properties": {
    "iso:country":"IN",
    "ks:ks_name":"Navapura Falia",
    "ks:ks_pop":322,
    "ks:ks_type":"HABITATION",
    "ks:ks_uagg_main":0,
    "name:eng_x_preferred":[
        "Navapura Falia"
    ],
    "wof:name":"Navapura Falia",
    "wof:placetype":"neighbourhood",
    "wof:population":322
},
  "geometry": {"coordinates":[73.64700000000001,22.65905],"type":"Point"}
}