{
  "type": "Feature",
  "properties": {
    "gn:admin1_code":"16",
    "gn:admin2_code":"499.0",
    "gn:asciiname":"Partal",
    "gn:country_code":"IN",
    "gn:dem":248,
    "gn:feature_class":"P",
    "gn:feature_code":"PPL",
    "gn:name":"P\u0101rtal",
    "gn:population":0,
    "gn:timezone":"Asia/Kolkata",
    "iso:country":"IN",
    "wof:name":"Partal",
    "wof:placetype":"locality"
},
  "geometry": {"coordinates":[76.35698000000002,20.98328],"type":"Point"}
}