{
  "type": "Feature",
  "properties": {
    "gn:admin1_code":"35",
    "gn:admin2_code":"426.0",
    "gn:asciiname":"Ranwaha",
    "gn:country_code":"IN",
    "gn:dem":333,
    "gn:feature_class":"P",
    "gn:feature_code":"PPL",
    "gn:name":"Ranw\u0101ha",
    "gn:population":0,
    "gn:timezone":"Asia/Kolkata",
    "iso:country":"IN",
    "ks:ks_alt_nam":"Ranw\u0101ha",
    "ks:ks_name":"Ranwaha",
    "ks:ks_pop":1097,
    "ks:ks_type":"VILLAGE",
    "ks:ks_uagg_main":0,
    "name:eng_x_preferred":[
        "Ranwaha"
    ],
    "name:eng_x_variant":[
        "Ranw\u0101ha"
    ],
    "wof:name":"Ranwaha",
    "wof:placetype":"neighbourhood",
    "wof:population":1097
},
  "geometry": {"coordinates":[80.211641,24.545735],"type":"Point"}
}