{
  "type": "Feature",
  "properties": {
    "iso:country":"IN",
    "ks:ks_name":"Maivayal",
    "ks:ks_pop":390,
    "ks:ks_type":"VILLAGE",
    "name:eng_x_preferred":[
        "Maivayal"
    ],
    "wof:name":"Maivayal",
    "wof:placetype":"locality",
    "wof:population":390
},
  "geometry": {"coordinates":[79.11621700000001,10.131214],"type":"Point"}
}