{
  "type": "Feature",
  "properties": {
    "iso:country":"IN",
    "ks:ks_name":"Awaspara",
    "ks:ks_pop":248,
    "ks:ks_type":"HABITATION",
    "name:eng_x_preferred":[
        "Awaspara"
    ],
    "wof:name":"Awaspara",
    "wof:placetype":"locality",
    "wof:population":248
},
  "geometry": {"coordinates":[80.695735,18.572974],"type":"Point"}
}