{
  "type": "Feature",
  "properties": {
    "gn:admin1_code":"35.0",
    "gn:admin2_code":"439.0",
    "gn:asciiname":"Hasnabad",
    "gn:country_code":"IN",
    "gn:dem":535,
    "gn:feature_class":"P",
    "gn:feature_code":"PPL",
    "gn:name":"Hasn\u0101b\u0101d",
    "gn:population":0,
    "gn:timezone":"Asia/Kolkata",
    "iso:country":"IN",
    "name:ben_x_preferred":[
        "\u09b9\u09be\u09b8\u09a8\u09be\u09ac\u09be\u09a6"
    ],
    "wof:name":"Hasnabad",
    "wof:placetype":"locality"
},
  "geometry": {"coordinates":[75.60276,22.81926],"type":"Point"}
}