{
  "type": "Feature",
  "properties": {
    "iso:country":"IN",
    "ks:ks_name":"Shirgalle",
    "ks:ks_pop":110,
    "ks:ks_type":"HABITATION",
    "name:eng_x_preferred":[
        "Shirgalle"
    ],
    "wof:name":"Shirgalle",
    "wof:placetype":"locality",
    "wof:population":110
},
  "geometry": {"coordinates":[74.92824400000001,14.347646],"type":"Point"}
}