{
  "type": "Feature",
  "properties": {
    "iso:country":"IN",
    "ks:ks_name":"Hatwadurgaprasad",
    "ks:ks_pop":30,
    "ks:ks_type":"HABITATION",
    "name:eng_x_preferred":[
        "Hatwadurgaprasad"
    ],
    "wof:name":"Hatwadurgaprasad",
    "wof:placetype":"locality",
    "wof:population":30
},
  "geometry": {"coordinates":[82.006703,24.727266],"type":"Point"}
}