{
  "type": "Feature",
  "properties": {
    "iso:country":"IN",
    "ks:ks_name":"Muthugoundenpalayam",
    "ks:ks_pop":58,
    "ks:ks_type":"HABITATION",
    "ks:ks_uagg_main":0,
    "name:eng_x_preferred":[
        "Muthugoundenpalayam"
    ],
    "wof:name":"Muthugoundenpalayam",
    "wof:placetype":"neighbourhood",
    "wof:population":58
},
  "geometry": {"coordinates":[77.734442,11.01055],"type":"Point"}
}