{
  "type": "Feature",
  "properties": {
    "iso:country":"IN",
    "ks:ks_name":"Baliya Khurd",
    "ks:ks_pop":487,
    "ks:ks_type":"VILLAGE",
    "name:eng_x_preferred":[
        "Baliya Khurd"
    ],
    "wof:name":"Baliya Khurd",
    "wof:placetype":"locality",
    "wof:population":487
},
  "geometry": {"coordinates":[85.53999399999999,24.74183],"type":"Point"}
}