{
  "type": "Feature",
  "properties": {
    "iso:country":"IN",
    "ks:ks_name":"Hitchkad",
    "ks:ks_pop":201,
    "ks:ks_type":"HABITATION",
    "name:eng_x_preferred":[
        "Hitchkad"
    ],
    "wof:name":"Hitchkad",
    "wof:placetype":"locality",
    "wof:population":201
},
  "geometry": {"coordinates":[74.355339,14.606677],"type":"Point"}
}