{
  "type": "Feature",
  "properties": {
    "iso:country":"IN",
    "ks:ks_name":"Shardapura",
    "ks:ks_pop":104,
    "ks:ks_type":"HABITATION",
    "name:eng_x_preferred":[
        "Shardapura"
    ],
    "wof:name":"Shardapura",
    "wof:placetype":"locality",
    "wof:population":104
},
  "geometry": {"coordinates":[73.344111,22.781028],"type":"Point"}
}