{
  "type": "Feature",
  "properties": {
    "iso:country":"IN",
    "ks:ks_name":"Faldwari",
    "ks:ks_pop":307,
    "ks:ks_type":"VILLAGE",
    "name:eng_x_preferred":[
        "Faldwari"
    ],
    "wof:name":"Faldwari",
    "wof:placetype":"locality",
    "wof:population":307
},
  "geometry": {"coordinates":[79.387315,29.787357],"type":"Point"}
}