{
  "type": "Feature",
  "properties": {
    "iso:country":"IN",
    "ks:ks_name":"Chhati",
    "ks:ks_pop":191,
    "ks:ks_type":"HABITATION",
    "name:eng_x_preferred":[
        "Chhati"
    ],
    "wof:name":"Chhati",
    "wof:placetype":"locality",
    "wof:population":191
},
  "geometry": {"coordinates":[84.03184299999999,25.896157],"type":"Point"}
}