{
  "type": "Feature",
  "properties": {
    "iso:country":"IN",
    "ks:ks_name":"Bhatpur",
    "ks:ks_pop":520,
    "ks:ks_type":"VILLAGE",
    "ks:ks_uagg_main":0,
    "name:eng_x_preferred":[
        "Bhatpur"
    ],
    "wof:name":"Bhatpur",
    "wof:placetype":"locality",
    "wof:population":520
},
  "geometry": {"coordinates":[87.46745,21.627338],"type":"Point"}
}