{
  "type": "Feature",
  "properties": {
    "iso:country":"IN",
    "ks:ks_name":"Karumbukattupathi",
    "ks:ks_pop":110,
    "ks:ks_type":"HABITATION",
    "name:eng_x_preferred":[
        "Karumbukattupathi"
    ],
    "wof:name":"Karumbukattupathi",
    "wof:placetype":"locality",
    "wof:population":110
},
  "geometry": {"coordinates":[76.75428700000001,10.964757],"type":"Point"}
}