{
  "type": "Feature",
  "properties": {
    "gn:admin1_code":"38.0",
    "gn:admin2_code":"348.0",
    "gn:asciiname":"Makatpur",
    "gn:country_code":"IN",
    "gn:dem":365,
    "gn:feature_class":"P",
    "gn:feature_code":"PPL",
    "gn:name":"Makatpur",
    "gn:population":0,
    "gn:timezone":"Asia/Kolkata",
    "iso:country":"IN",
    "ks:ks_name":"Makatpur",
    "ks:ks_pop":1659,
    "ks:ks_type":"VILLAGE",
    "ks:ks_uagg_main":0,
    "name:eng_x_preferred":[
        "Makatpur"
    ],
    "wof:name":"Makatpur",
    "wof:placetype":"neighbourhood",
    "wof:population":1659
},
  "geometry": {"coordinates":[85.725049,24.329966],"type":"Point"}
}