{
  "type": "Feature",
  "properties": {
    "gn:admin1_code":"36",
    "gn:admin2_code":"155.0",
    "gn:asciiname":"Surapur",
    "gn:country_code":"IN",
    "gn:dem":136,
    "gn:feature_class":"P",
    "gn:feature_code":"PPL",
    "gn:name":"S\u016br\u0101pur",
    "gn:population":0,
    "gn:timezone":"Asia/Kolkata",
    "iso:country":"IN",
    "ks:ks_name":"Sura Pur",
    "ks:ks_pop":745,
    "ks:ks_type":"HABITATION",
    "name:eng_x_preferred":[
        "Sura Pur"
    ],
    "name:eng_x_variant":[
        "Surapur"
    ],
    "wof:name":"Sura Pur",
    "wof:placetype":"locality",
    "wof:population":745
},
  "geometry": {"coordinates":[79.824443,27.291068],"type":"Point"}
}