{
  "type": "Feature",
  "properties": {
    "gn:admin1_code":"36",
    "gn:admin2_code":"155.0",
    "gn:asciiname":"Surapur",
    "gn:country_code":"IN",
    "gn:dem":136,
    "gn:feature_class":"P",
    "gn:feature_code":"PPL",
    "gn:name":"S\u016br\u0101pur",
    "gn:population":0,
    "gn:timezone":"Asia/Kolkata",
    "iso:country":"IN",
    "wof:name":"Surapur",
    "wof:placetype":"locality"
},
  "geometry": {"coordinates":[79.82614000000002,27.29067],"type":"Point"}
}