{
  "type": "Feature",
  "properties": {
    "iso:country":"IN",
    "ks:ks_name":"Jakuapaara",
    "ks:ks_pop":220,
    "ks:ks_type":"VILLAGE",
    "name:eng_x_preferred":[
        "Jakuapaara"
    ],
    "wof:name":"Jakuapaara",
    "wof:placetype":"locality",
    "wof:population":220
},
  "geometry": {"coordinates":[90.88293299999999,26.444438],"type":"Point"}
}