{
  "type": "Feature",
  "properties": {
    "iso:country":"IN",
    "ks:ks_name":"Khetawal Misra",
    "ks:ks_pop":1406,
    "ks:ks_type":"VILLAGE",
    "name:eng_x_preferred":[
        "Khetawal Misra"
    ],
    "wof:name":"Khetawal Misra",
    "wof:placetype":"locality",
    "wof:population":1406
},
  "geometry": {"coordinates":[82.939404,27.321794],"type":"Point"}
}