{
  "type": "Feature",
  "properties": {
    "iso:country":"IN",
    "ks:ks_name":"Archanapuram",
    "ks:ks_pop":151,
    "ks:ks_type":"HABITATION",
    "name:eng_x_preferred":[
        "Archanapuram"
    ],
    "wof:name":"Archanapuram",
    "wof:placetype":"locality",
    "wof:population":151
},
  "geometry": {"coordinates":[77.708226,11.064512],"type":"Point"}
}