{
  "type": "Feature",
  "properties": {
    "iso:country":"IN",
    "ks:ks_name":"Kolakebailu",
    "ks:ks_pop":392,
    "ks:ks_type":"HABITATION",
    "name:eng_x_preferred":[
        "Kolakebailu"
    ],
    "wof:name":"Kolakebailu",
    "wof:placetype":"locality",
    "wof:population":392
},
  "geometry": {"coordinates":[75.151146,12.955642],"type":"Point"}
}