{
  "type": "Feature",
  "properties": {
    "iso:country":"IN",
    "ks:ks_name":"Nadibettu Mudrady",
    "ks:ks_pop":305,
    "ks:ks_type":"HABITATION",
    "name:eng_x_preferred":[
        "Nadibettu Mudrady"
    ],
    "wof:name":"Nadibettu Mudrady",
    "wof:placetype":"locality",
    "wof:population":305
},
  "geometry": {"coordinates":[75.015717,13.436614],"type":"Point"}
}