{
  "type": "Feature",
  "properties": {
    "gn:admin1_code":"35.0",
    "gn:admin2_code":"447.0",
    "gn:asciiname":"Semjhira",
    "gn:country_code":"IN",
    "gn:dem":708,
    "gn:feature_class":"P",
    "gn:feature_code":"PPL",
    "gn:name":"Semjhira",
    "gn:population":0,
    "gn:timezone":"Asia/Kolkata",
    "iso:country":"IN",
    "wof:name":"Semjhira",
    "wof:placetype":"locality"
},
  "geometry": {"coordinates":[78.15831,21.79282000000001],"type":"Point"}
}