{
  "type": "Feature",
  "properties": {
    "gn:admin1_code":"39.0",
    "gn:admin2_code":"61.0",
    "gn:asciiname":"Magson Ranjit",
    "gn:country_code":"IN",
    "gn:dem":1371,
    "gn:feature_class":"P",
    "gn:feature_code":"PPL",
    "gn:name":"Magson Ranj\u012bt",
    "gn:population":0,
    "gn:timezone":"Asia/Kolkata",
    "iso:country":"IN",
    "wof:name":"Magson Ranjit",
    "wof:placetype":"locality"
},
  "geometry": {"coordinates":[79.02276999999999,29.65473],"type":"Point"}
}