{
  "type": "Feature",
  "properties": {
    "iso:country":"IN",
    "ks:ks_name":"Chadada",
    "ks:ks_pop":839,
    "ks:ks_type":"VILLAGE",
    "name:eng_x_preferred":[
        "Chadada"
    ],
    "wof:name":"Chadada",
    "wof:placetype":"locality",
    "wof:population":839
},
  "geometry": {"coordinates":[86.556485,21.66626],"type":"Point"}
}