{
  "type": "Feature",
  "properties": {
    "iso:country":"IN",
    "ks:ks_alt_nam":"BICHALGHATI",
    "ks:ks_name":"Bichalghati",
    "ks:ks_pop":370,
    "ks:ks_type":"HABITATION",
    "name:eng_x_preferred":[
        "Bichalghati"
    ],
    "wof:name":"Bichalghati",
    "wof:placetype":"locality",
    "wof:population":370
},
  "geometry": {"coordinates":[83.014118,22.835567],"type":"Point"}
}