{
  "type": "Feature",
  "properties": {
    "iso:country":"IN",
    "ks:ks_name":"Kothanur",
    "ks:ks_pop":712,
    "ks:ks_type":"HABITATION",
    "name:eng_x_preferred":[
        "Kothanur"
    ],
    "wof:name":"Kothanur",
    "wof:placetype":"locality",
    "wof:population":712
},
  "geometry": {"coordinates":[79.435407,11.089776],"type":"Point"}
}