{
  "type": "Feature",
  "properties": {
    "iso:country":"IN",
    "ks:ks_alt_nam":"KODGAKONA",
    "ks:ks_name":"Kodgakona",
    "ks:ks_pop":191,
    "ks:ks_type":"HABITATION",
    "name:eng_x_preferred":[
        "Kodgakona"
    ],
    "wof:name":"Kodgakona",
    "wof:placetype":"locality",
    "wof:population":191
},
  "geometry": {"coordinates":[83.92187300000001,23.011122],"type":"Point"}
}