{
  "type": "Feature",
  "properties": {
    "iso:country":"IN",
    "ks:ks_alt_nam":"BANJALWASTI",
    "ks:ks_name":"Banjalwasti",
    "ks:ks_pop":146,
    "ks:ks_type":"HABITATION",
    "name:eng_x_preferred":[
        "Banjalwasti"
    ],
    "wof:name":"Banjalwasti",
    "wof:placetype":"locality",
    "wof:population":146
},
  "geometry": {"coordinates":[75.570103,17.122622],"type":"Point"}
}