{
  "type": "Feature",
  "properties": {
    "gn:admin1_code":"34.0",
    "gn:admin2_code":"213.0",
    "gn:asciiname":"Panre",
    "gn:country_code":"IN",
    "gn:dem":51,
    "gn:feature_class":"P",
    "gn:feature_code":"PPL",
    "gn:name":"Panre",
    "gn:population":0,
    "gn:timezone":"Asia/Kolkata",
    "iso:country":"IN",
    "wof:name":"Panre",
    "wof:placetype":"neighbourhood"
},
  "geometry": {"coordinates":[86.69593,25.99594],"type":"Point"}
}