{
  "type": "Feature",
  "properties": {
    "iso:country":"IN",
    "ks:ks_name":"Teejwar",
    "ks:ks_pop":1025,
    "ks:ks_type":"VILLAGE",
    "ks:ks_uagg_main":0,
    "name:eng_x_preferred":[
        "Teejwar"
    ],
    "wof:name":"Teejwar",
    "wof:placetype":"neighbourhood",
    "wof:population":1025
},
  "geometry": {"coordinates":[73.75829299999999,23.839655],"type":"Point"}
}