{
  "type": "Feature",
  "properties": {
    "gn:admin1_code":"16.0",
    "gn:admin2_code":"515",
    "gn:asciiname":"Bhos",
    "gn:country_code":"IN",
    "gn:dem":502,
    "gn:feature_class":"P",
    "gn:feature_code":"PPL",
    "gn:name":"Bhos",
    "gn:population":0,
    "gn:timezone":"Asia/Kolkata",
    "iso:country":"IN",
    "wof:name":"Bhos",
    "wof:placetype":"locality"
},
  "geometry": {"coordinates":[75.45,19.61667000000001],"type":"Point"}
}