{
  "type": "Feature",
  "properties": {
    "iso:country":"IN",
    "ks:ks_name":"Betijharan",
    "ks:ks_pop":211,
    "ks:ks_type":"VILLAGE",
    "name:eng_x_preferred":[
        "Betijharan"
    ],
    "wof:name":"Betijharan",
    "wof:placetype":"locality",
    "wof:population":211
},
  "geometry": {"coordinates":[85.021592,22.134187],"type":"Point"}
}