{
  "type": "Feature",
  "properties": {
    "iso:country":"IN",
    "ks:ks_name":"Aigalakoppa",
    "ks:ks_pop":89,
    "ks:ks_type":"HABITATION",
    "name:eng_x_preferred":[
        "Aigalakoppa"
    ],
    "wof:name":"Aigalakoppa",
    "wof:placetype":"locality",
    "wof:population":89
},
  "geometry": {"coordinates":[74.92803000000001,14.238376],"type":"Point"}
}