{
  "type": "Feature",
  "properties": {
    "iso:country":"IN",
    "ks:ks_name":"Olakallu",
    "ks:ks_pop":60,
    "ks:ks_type":"HABITATION",
    "name:eng_x_preferred":[
        "Olakallu"
    ],
    "wof:name":"Olakallu",
    "wof:placetype":"locality",
    "wof:population":60
},
  "geometry": {"coordinates":[76.827437,13.816615],"type":"Point"}
}