{
  "type": "Feature",
  "properties": {
    "gn:admin1_code":"36.0",
    "gn:admin2_code":"149.0",
    "gn:asciiname":"Pawsara",
    "gn:country_code":"IN",
    "gn:dem":193,
    "gn:feature_class":"P",
    "gn:feature_code":"PPL",
    "gn:name":"Pawsara",
    "gn:population":0,
    "gn:timezone":"Asia/Kolkata",
    "iso:country":"IN",
    "ks:ks_name":"Pawsara",
    "ks:ks_type":"VILLAGE",
    "name:eng_x_preferred":[
        "Pawsara"
    ],
    "name:und_x_variant":[
        "Abdulw\u0101hidpur"
    ],
    "wof:name":"Pawsara",
    "wof:placetype":"locality"
},
  "geometry": {"coordinates":[78.746954,28.323365],"type":"Point"}
}