{
  "type": "Feature",
  "properties": {
    "iso:country":"IN",
    "ks:ks_name":"Mahuawa",
    "ks:ks_pop":123,
    "ks:ks_type":"HABITATION",
    "name:eng_x_preferred":[
        "Mahuawa"
    ],
    "wof:name":"Mahuawa",
    "wof:placetype":"locality",
    "wof:population":123
},
  "geometry": {"coordinates":[84.055662,26.758933],"type":"Point"}
}