{
  "type": "Feature",
  "properties": {
    "iso:country":"IN",
    "ks:ks_name":"Kundsebara",
    "ks:ks_pop":1136,
    "ks:ks_type":"VILLAGE",
    "ks:ks_uagg_main":0,
    "name:eng_x_preferred":[
        "Kundsebara"
    ],
    "wof:name":"Kundsebara",
    "wof:placetype":"locality",
    "wof:population":1136
},
  "geometry": {"coordinates":[79.00728100000001,29.188428],"type":"Point"}
}