{
  "type": "Feature",
  "properties": {
    "gn:admin1_code":"19.0",
    "gn:admin2_code":"581.0",
    "gn:asciiname":"Punyahalli",
    "gn:country_code":"IN",
    "gn:dem":741,
    "gn:feature_class":"P",
    "gn:feature_code":"PPL",
    "gn:name":"Punyahalli",
    "gn:population":0,
    "gn:timezone":"Asia/Kolkata",
    "iso:country":"IN",
    "wof:name":"Punyahalli",
    "wof:placetype":"locality"
},
  "geometry": {"coordinates":[78.54163,13.26387],"type":"Point"}
}