{
  "type": "Feature",
  "properties": {
    "iso:country":"IN",
    "ks:ks_alt_nam":"SITA RAMPUR",
    "ks:ks_name":"Sita Rampur",
    "ks:ks_pop":1165,
    "ks:ks_type":"HABITATION",
    "name:eng_x_preferred":[
        "Sita Rampur"
    ],
    "wof:name":"Sita Rampur",
    "wof:placetype":"locality",
    "wof:population":1165
},
  "geometry": {"coordinates":[85.527698,24.977318],"type":"Point"}
}