{
  "type": "Feature",
  "properties": {
    "gn:admin1_code":"36.0",
    "gn:admin2_code":"137.0",
    "gn:asciiname":"Agapur Kalan",
    "gn:country_code":"IN",
    "gn:dem":208,
    "gn:feature_class":"P",
    "gn:feature_code":"PPL",
    "gn:name":"\u0100g\u0101pur Kal\u0101n",
    "gn:population":0,
    "gn:timezone":"Asia/Kolkata",
    "iso:country":"IN",
    "name:und_x_variant":[
        "\u0100g\u0101pur Kal\u0101n",
        "Y\u0101q\u016bbpur"
    ],
    "wof:name":"Agapur Kalan",
    "wof:placetype":"locality"
},
  "geometry": {"coordinates":[78.28766,28.76574],"type":"Point"}
}