{
  "type": "Feature",
  "properties": {
    "iso:country":"IN",
    "ks:ks_alt_nam":"MOHITEWASTI",
    "ks:ks_name":"Mohitewasti",
    "ks:ks_pop":110,
    "ks:ks_type":"HABITATION",
    "name:eng_x_preferred":[
        "Mohitewasti"
    ],
    "wof:name":"Mohitewasti",
    "wof:placetype":"locality",
    "wof:population":110
},
  "geometry": {"coordinates":[74.507198,17.113454],"type":"Point"}
}