{
  "type": "Feature",
  "properties": {
    "iso:country":"IN",
    "ks:ks_name":"Kandikatlavari Group",
    "ks:ks_pop":975,
    "ks:ks_type":"HABITATION",
    "name:eng_x_preferred":[
        "Kandikatlavari Group"
    ],
    "wof:name":"Kandikatlavari Group",
    "wof:placetype":"locality",
    "wof:population":975
},
  "geometry": {"coordinates":[81.864391,16.471406],"type":"Point"}
}