{
  "type": "Feature",
  "properties": {
    "gn:admin1_code":"12",
    "gn:asciiname":"Nago Nari",
    "gn:country_code":"IN",
    "gn:dem":1717,
    "gn:feature_class":"P",
    "gn:feature_code":"PPL",
    "gn:name":"N\u0101go N\u0101ri",
    "gn:population":0,
    "gn:timezone":"Asia/Kolkata",
    "iso:country":"IN",
    "wof:name":"Nago Nari",
    "wof:placetype":"locality"
},
  "geometry": {"coordinates":[74.2377,34.18613],"type":"Point"}
}