{
  "type": "Feature",
  "properties": {
    "gn:admin1_code":"2.0",
    "gn:admin2_code":"543.0",
    "gn:asciiname":"Eguva Gunada",
    "gn:country_code":"IN",
    "gn:dem":210,
    "gn:feature_class":"P",
    "gn:feature_code":"PPL",
    "gn:name":"Eguva Gunada",
    "gn:population":0,
    "gn:timezone":"Asia/Kolkata",
    "iso:country":"IN",
    "ks:ks_name":"Yeguvagunada",
    "ks:ks_pop":105,
    "ks:ks_type":"HABITATION",
    "name:eng_x_preferred":[
        "Yeguvagunada"
    ],
    "name:eng_x_variant":[
        "Eguva Gunada"
    ],
    "wof:name":"Yeguvagunada",
    "wof:placetype":"locality",
    "wof:population":105
},
  "geometry": {"coordinates":[83.501,18.954771],"type":"Point"}
}