{
  "type": "Feature",
  "properties": {
    "gn:admin1_code":"34.0",
    "gn:admin2_code":"203.0",
    "gn:asciiname":"Pararauna",
    "gn:country_code":"IN",
    "gn:dem":104,
    "gn:feature_class":"P",
    "gn:feature_code":"PPL",
    "gn:name":"Pararauna",
    "gn:population":0,
    "gn:timezone":"Asia/Kolkata",
    "iso:country":"IN",
    "ks:ks_name":"Pararauna",
    "ks:ks_pop":1101,
    "ks:ks_type":"VILLAGE",
    "name:eng_x_preferred":[
        "Pararauna"
    ],
    "wof:name":"Pararauna",
    "wof:placetype":"locality",
    "wof:population":1101
},
  "geometry": {"coordinates":[84.54325799999999,27.212619],"type":"Point"}
}