{
  "type": "Feature",
  "properties": {
    "gn:admin1_code":"21",
    "gn:admin2_code":"372.0",
    "gn:asciiname":"Satupali",
    "gn:country_code":"IN",
    "gn:dem":160,
    "gn:feature_class":"P",
    "gn:feature_code":"PPL",
    "gn:name":"Satup\u0101li",
    "gn:population":0,
    "gn:timezone":"Asia/Kolkata",
    "iso:country":"IN",
    "wof:name":"Satupali",
    "wof:placetype":"locality"
},
  "geometry": {"coordinates":[83.88506,21.37344],"type":"Point"}
}