{
  "type": "Feature",
  "properties": {
    "iso:country":"IN",
    "ks:ks_name":"Mahata",
    "ks:ks_pop":1,
    "ks:ks_type":"VILLAGE",
    "name:eng_x_preferred":[
        "Mahata"
    ],
    "wof:name":"Mahata",
    "wof:placetype":"locality",
    "wof:population":1
},
  "geometry": {"coordinates":[87.419247,22.825127],"type":"Point"}
}