{
  "type": "Feature",
  "properties": {
    "iso:country":"IN",
    "ks:ks_name":"Ganeshwadi",
    "ks:ks_pop":151,
    "ks:ks_type":"HABITATION",
    "name:eng_x_preferred":[
        "Ganeshwadi"
    ],
    "wof:name":"Ganeshwadi",
    "wof:placetype":"locality",
    "wof:population":151
},
  "geometry": {"coordinates":[73.412401,16.746988],"type":"Point"}
}