{
  "type": "Feature",
  "properties": {
    "iso:country":"IN",
    "ks:ks_name":"Chunakkara",
    "ks:ks_pop":22436,
    "ks:ks_type":"VILLAGE",
    "name:eng_x_preferred":[
        "Chunakkara"
    ],
    "wof:name":"Chunakkara",
    "wof:placetype":"locality",
    "wof:population":22436
},
  "geometry": {"coordinates":[76.58282800000001,9.186408],"type":"Point"}
}