{
  "type": "Feature",
  "properties": {
    "iso:country":"IN",
    "ks:ks_name":"Phiphiyara",
    "ks:ks_pop":208,
    "ks:ks_type":"VILLAGE",
    "name:eng_x_preferred":[
        "Phiphiyara"
    ],
    "wof:name":"Phiphiyara",
    "wof:placetype":"locality",
    "wof:population":208
},
  "geometry": {"coordinates":[78.080466,30.704978],"type":"Point"}
}