{
  "type": "Feature",
  "properties": {
    "gn:admin1_code":"10",
    "gn:admin2_code":"81.0",
    "gn:asciiname":"Chanda Bas Chak",
    "gn:country_code":"IN",
    "gn:dem":226,
    "gn:feature_class":"P",
    "gn:feature_code":"PPL",
    "gn:name":"Chanda B\u0101s Chak",
    "gn:population":0,
    "gn:timezone":"Asia/Kolkata",
    "iso:country":"IN",
    "wof:name":"Chanda Bas Chak",
    "wof:placetype":"locality"
},
  "geometry": {"coordinates":[75.89894,28.67178],"type":"Point"}
}