{
  "type": "Feature",
  "properties": {
    "iso:country":"IN",
    "name:dan_x_preferred":[
        "Koregaon Park"
    ],
    "name:eng_x_preferred":[
        "Koregaon Park"
    ],
    "name:mar_x_preferred":[
        "\u0915\u094b\u0930\u0947\u0917\u093e\u0935 \u092a\u093e\u0930\u094d\u0915"
    ],
    "qs:name":"Koregaon park",
    "qs:name_adm0":"India",
    "qs:name_adm1":"Maharashtra",
    "qs:photos":755,
    "qs:photos_1k":153,
    "qs:photos_9k":3,
    "qs:photos_9r":6,
    "qs:photos_all":755,
    "qs:photos_sr":9,
    "qs:placetype":"Suburb",
    "qs:pop_sr":"0",
    "wd:wordcount":320,
    "wof:name":"Koregaon park",
    "wof:placetype":"neighbourhood"
},
  "geometry": {"coordinates":[73.853843,18.531709],"type":"Point"}
}