{
  "type": "Feature",
  "properties": {
    "iso:country":"IN",
    "name:ara_x_preferred":[
        "\u0643\u0648\u0631\u064a\u063a\u0627\u0648\u0646 \u0628\u0627\u0631\u0643"
    ],
    "name:ben_bn_x_preferred":[
        "\u0995\u09cb\u09b0\u09c7\u0997\u09be\u0981\u0993 \u09aa\u09be\u09b0\u09cd\u0995"
    ],
    "name:ben_in_x_preferred":[
        "\u0995\u09cb\u09b0\u09c7\u0997\u09be\u0981\u0993 \u09aa\u09be\u09b0\u09cd\u0995"
    ],
    "name:dan_x_preferred":[
        "Koregaon Park"
    ],
    "name:ell_x_preferred":[
        "\u039a\u03bf\u03c1\u03ad\u03b3\u03ba\u03b1\u03bf\u03bd \u03a0\u03b1\u03c1\u03ba"
    ],
    "name:eng_x_preferred":[
        "Koregaon Park"
    ],
    "name:eng_x_variant":[
        "Koregaon park"
    ],
    "name:guj_x_preferred":[
        "\u0a95\u0acb\u0ab0\u0ac7\u0a97\u0abe\u0a82\u0ab5 \u0aaa\u0abe\u0ab0\u0acd\u0a95"
    ],
    "name:hin_x_preferred":[
        "\u0915\u094b\u0930\u0947\u0917\u093e\u0902\u0935 \u092a\u093e\u0930\u094d\u0915"
    ],
    "name:kan_x_preferred":[
        "\u0c95\u0ccb\u0cb0\u0cc6\u0c97\u0cbe\u0c82\u0cb5\u0ccd \u0caa\u0cbe\u0cb0\u0ccd\u0c95\u0ccd"
    ],
    "name:mal_x_preferred":[
        "\u0d15\u0d4a\u0d31\u0d46\u0d17\u0d3e\u0d35\u0d4d \u0d2a\u0d3e\u0d7c\u0d15\u0d4d\u0d15\u0d4d"
    ],
    "name:mar_x_preferred":[
        "\u0915\u094b\u0930\u0947\u0917\u093e\u0935 \u092a\u093e\u0930\u094d\u0915"
    ],
    "name:nld_x_preferred":[
        "Koregaon Park"
    ],
    "name:pan_x_preferred":[
        "\u0a15\u0a4b\u0a30\u0a47\u0a17\u0a3e\u0a13\u0a02 \u0a2a\u0a3e\u0a30\u0a15"
    ],
    "name:tam_x_preferred":[
        "\u0b95\u0bcb\u0bb0\u0bc6\u0b95\u0bbe\u0bb5\u0bcd\u0ba9\u0bcd \u0baa\u0bc2\u0b99\u0bcd\u0b95\u0bbe"
    ],
    "name:tel_x_preferred":[
        "\u0c15\u0c4b\u0c30\u0c46\u0c17\u0c3e\u0c02\u0c35\u0c4d \u0c2a\u0c3e\u0c30\u0c4d\u0c15\u0c4d"
    ],
    "name:urd_x_preferred":[
        "\u06a9\u0648\u0631\u06cc\u06af\u0627\u0624\u06ba \u067e\u0627\u0631\u06a9"
    ],
    "qs:name":"Koregaon park",
    "qs:name_adm0":"India",
    "qs:name_adm1":"Maharashtra",
    "qs:photos":755,
    "qs:photos_1k":153,
    "qs:photos_9k":3,
    "qs:photos_9r":6,
    "qs:photos_all":755,
    "qs:photos_sr":9,
    "qs:placetype":"Suburb",
    "qs:pop_sr":"0",
    "wd:wordcount":320,
    "wof:name":"Koregaon Park",
    "wof:placetype":"neighbourhood"
},
  "geometry": {"coordinates":[73.89116199999999,18.537181],"type":"Point"}
}