{
  "type": "Feature",
  "properties": {
    "iso:country":"IN",
    "ks:ks_name":"Tarsimiya",
    "ks:ks_pop":2591,
    "ks:ks_type":"VILLAGE",
    "name:eng_x_preferred":[
        "Tarsimiya"
    ],
    "wof:name":"Tarsimiya",
    "wof:placetype":"locality",
    "wof:population":2591
},
  "geometry": {"coordinates":[72.166415,21.737142],"type":"Point"}
}