{
  "type": "Feature",
  "properties": {
    "iso:country":"IN",
    "ks:ks_name":"Badon",
    "ks:ks_pop":365,
    "ks:ks_type":"VILLAGE",
    "name:eng_x_preferred":[
        "Badon"
    ],
    "wof:name":"Badon",
    "wof:placetype":"locality",
    "wof:population":365
},
  "geometry": {"coordinates":[78.733935,30.275356],"type":"Point"}
}