{
  "type": "Feature",
  "properties": {
    "iso:country":"IN",
    "ks:ks_name":"Nereduvalasa",
    "ks:ks_pop":79,
    "ks:ks_type":"HABITATION",
    "name:eng_x_preferred":[
        "Nereduvalasa"
    ],
    "wof:name":"Nereduvalasa",
    "wof:placetype":"locality",
    "wof:population":79
},
  "geometry": {"coordinates":[83.099581,18.26291],"type":"Point"}
}