{
  "type": "Feature",
  "properties": {
    "iso:country":"IN",
    "ks:ks_name":"Borgoan",
    "ks:ks_pop":133,
    "ks:ks_type":"HABITATION",
    "name:eng_x_preferred":[
        "Borgoan"
    ],
    "wof:name":"Borgoan",
    "wof:placetype":"locality",
    "wof:population":133
},
  "geometry": {"coordinates":[79.747986,29.82291],"type":"Point"}
}