{
  "type": "Feature",
  "properties": {
    "gn:admin1_code":"38",
    "gn:admin2_code":"347.0",
    "gn:asciiname":"Tutilawa",
    "gn:country_code":"IN",
    "gn:dem":589,
    "gn:feature_class":"P",
    "gn:feature_code":"PPL",
    "gn:name":"Tutil\u0101wa",
    "gn:population":0,
    "gn:timezone":"Asia/Kolkata",
    "iso:country":"IN",
    "name:und_x_variant":[
        "Tutil\u0101wa"
    ],
    "wof:name":"Tutilawa",
    "wof:placetype":"locality"
},
  "geometry": {"coordinates":[85.03378000000002,24.03916],"type":"Point"}
}