{
  "type": "Feature",
  "properties": {
    "iso:country":"IN",
    "ks:ks_alt_nam":"kanatipali",
    "ks:ks_name":"Kanatipali",
    "ks:ks_pop":367,
    "ks:ks_type":"HABITATION",
    "name:eng_x_preferred":[
        "Kanatipali"
    ],
    "wof:name":"Kanatipali",
    "wof:placetype":"locality",
    "wof:population":367
},
  "geometry": {"coordinates":[75.76888700000001,11.614382],"type":"Point"}
}