{
  "type": "Feature",
  "properties": {
    "iso:country":"IN",
    "ks:ks_name":"Limbaguda",
    "ks:ks_pop":62,
    "ks:ks_type":"HABITATION",
    "name:eng_x_preferred":[
        "Limbaguda"
    ],
    "wof:name":"Limbaguda",
    "wof:placetype":"locality",
    "wof:population":62
},
  "geometry": {"coordinates":[82.997711,18.27527],"type":"Point"}
}