{
  "type": "Feature",
  "properties": {
    "iso:country":"IN",
    "ks:ks_alt_nam":"Niz-Panbari No2",
    "ks:ks_name":"Niz-panbari No2",
    "ks:ks_pop":121,
    "ks:ks_type":"HABITATION",
    "name:eng_x_preferred":[
        "Niz-panbari No2"
    ],
    "wof:name":"Niz-panbari No2",
    "wof:placetype":"locality",
    "wof:population":121
},
  "geometry": {"coordinates":[91.979399,26.194863],"type":"Point"}
}