{
  "type": "Feature",
  "properties": {
    "iso:country":"IN",
    "ks:ks_name":"Taran",
    "ks:ks_pop":30,
    "ks:ks_type":"HABITATION",
    "name:eng_x_preferred":[
        "Taran"
    ],
    "wof:name":"Taran",
    "wof:placetype":"locality",
    "wof:population":30
},
  "geometry": {"coordinates":[86.768372,24.570364],"type":"Point"}
}