{
  "type": "Feature",
  "properties": {
    "iso:country":"IN",
    "ks:ks_name":"Nalangwadi",
    "ks:ks_pop":125,
    "ks:ks_type":"HABITATION",
    "name:eng_x_preferred":[
        "Nalangwadi"
    ],
    "wof:name":"Nalangwadi",
    "wof:placetype":"locality",
    "wof:population":125
},
  "geometry": {"coordinates":[73.72454399999999,16.042546],"type":"Point"}
}