{
  "type": "Feature",
  "properties": {
    "gn:admin1_code":"36.0",
    "gn:admin2_code":"149.0",
    "gn:asciiname":"Puraini",
    "gn:country_code":"IN",
    "gn:dem":158,
    "gn:feature_class":"P",
    "gn:feature_code":"PPL",
    "gn:name":"P\u016braini",
    "gn:population":0,
    "gn:timezone":"Asia/Kolkata",
    "iso:country":"IN",
    "wof:name":"Puraini",
    "wof:placetype":"locality"
},
  "geometry": {"coordinates":[79.41925999999999,28.03476],"type":"Point"}
}