{
  "type": "Feature",
  "properties": {
    "gn:admin1_code":"36.0",
    "gn:admin2_code":"183.0",
    "gn:asciiname":"Ukra",
    "gn:country_code":"IN",
    "gn:dem":112,
    "gn:feature_class":"P",
    "gn:feature_code":"PPL",
    "gn:name":"Ukra",
    "gn:population":0,
    "gn:timezone":"Asia/Kolkata",
    "iso:country":"IN",
    "name:ara_x_preferred":[
        "\u0623\u0648\u0643\u0631\u0627"
    ],
    "name:azb_x_preferred":[
        "\u0627\u0648\u06a9\u0631\u0627"
    ],
    "name:bul_x_preferred":[
        "\u0423\u043a\u0440\u0430"
    ],
    "name:deu_x_preferred":[
        "Ukra"
    ],
    "name:fas_x_preferred":[
        "\u0627\u0648\u06a9\u0631\u0627"
    ],
    "name:fra_x_preferred":[
        "Ukra"
    ],
    "name:hye_x_preferred":[
        "\u0548\u0582\u056f\u0580\u0561"
    ],
    "name:ita_x_preferred":[
        "Ukra"
    ],
    "name:jpn_x_preferred":[
        "\u30a2\u30f3\u30c9\u30ec\u30fb\u30d5\u30a3\u30ea\u30da\u30fb\u30a2\u30a6\u30f4\u30a7\u30b9\u30fb\u30e2\u30f3\u30c6\u30a4\u30ed"
    ],
    "name:nor_x_preferred":[
        "Ukra"
    ],
    "name:rus_x_preferred":[
        "\u0423\u043a\u0440\u0430"
    ],
    "name:tur_x_preferred":[
        "Ukra"
    ],
    "name:ukr_x_preferred":[
        "\u0423\u043a\u0440\u0430"
    ],
    "wof:name":"Ukra",
    "wof:placetype":"locality"
},
  "geometry": {"coordinates":[82.03305,27.20176],"type":"Point"}
}