{
  "type": "Feature",
  "properties": {
    "iso:country":"IN",
    "ks:ks_name":"Kutti Ka Nagla",
    "ks:ks_pop":306,
    "ks:ks_type":"HABITATION",
    "name:eng_x_preferred":[
        "Kutti Ka Nagla"
    ],
    "wof:name":"Kutti Ka Nagla",
    "wof:placetype":"locality",
    "wof:population":306
},
  "geometry": {"coordinates":[77.624955,27.733088],"type":"Point"}
}