{
  "type": "Feature",
  "properties": {
    "iso:country":"IN",
    "ks:ks_name":"Nau Basti",
    "ks:ks_pop":250,
    "ks:ks_type":"HABITATION",
    "name:eng_x_preferred":[
        "Nau Basti"
    ],
    "wof:name":"Nau Basti",
    "wof:placetype":"locality",
    "wof:population":250
},
  "geometry": {"coordinates":[81.80584500000001,25.696594],"type":"Point"}
}