{
  "type": "Feature",
  "properties": {
    "iso:country":"IN",
    "ks:ks_name":"Dumurta",
    "ks:ks_pop":409,
    "ks:ks_type":"HABITATION",
    "name:eng_x_preferred":[
        "Dumurta"
    ],
    "wof:name":"Dumurta",
    "wof:placetype":"locality",
    "wof:population":409
},
  "geometry": {"coordinates":[85.336251,22.078145],"type":"Point"}
}