{
  "type": "Feature",
  "properties": {
    "gn:admin1_code":"26.0",
    "gn:admin2_code":"292.0",
    "gn:asciiname":"Takirambari",
    "gn:country_code":"IN",
    "gn:dem":66,
    "gn:feature_class":"P",
    "gn:feature_code":"PPL",
    "gn:name":"Takir\u0101mb\u0101ri",
    "gn:population":0,
    "gn:timezone":"Asia/Kolkata",
    "iso:country":"IN",
    "wof:name":"Takirambari",
    "wof:placetype":"locality"
},
  "geometry": {"coordinates":[91.95294,24.22703],"type":"Point"}
}