{
  "type": "Feature",
  "properties": {
    "iso:country":"IN",
    "ks:ks_alt_nam":"Kharediya(K)",
    "ks:ks_name":"Kharediya(k)",
    "ks:ks_pop":156,
    "ks:ks_type":"HABITATION",
    "name:eng_x_preferred":[
        "Kharediya(k)"
    ],
    "wof:name":"Kharediya(k)",
    "wof:placetype":"locality",
    "wof:population":156
},
  "geometry": {"coordinates":[72.874472,23.942833],"type":"Point"}
}