{
  "type": "Feature",
  "properties": {
    "iso:country":"IN",
    "ks:ks_name":"Durgabati",
    "ks:ks_pop":876,
    "ks:ks_type":"VILLAGE",
    "ks:ks_uagg_main":0,
    "name:eng_x_preferred":[
        "Durgabati"
    ],
    "wof:name":"Durgabati",
    "wof:placetype":"neighbourhood",
    "wof:population":876
},
  "geometry": {"coordinates":[87.82448100000001,23.014282],"type":"Point"}
}