{
  "type": "Feature",
  "properties": {
    "iso:country":"IN",
    "ks:ks_name":"Dube Deharia",
    "ks:ks_pop":79,
    "ks:ks_type":"VILLAGE",
    "ks:ks_uagg_main":0,
    "name:eng_x_preferred":[
        "Dube Deharia"
    ],
    "wof:name":"Dube Deharia",
    "wof:placetype":"neighbourhood",
    "wof:population":79
},
  "geometry": {"coordinates":[83.716178,25.195952],"type":"Point"}
}