{
  "type": "Feature",
  "properties": {
    "gn:admin1_code":"36.0",
    "gn:admin2_code":"172.0",
    "gn:asciiname":"Karanpur",
    "gn:country_code":"IN",
    "gn:dem":115,
    "gn:feature_class":"P",
    "gn:feature_code":"PPL",
    "gn:name":"Karanpur",
    "gn:population":0,
    "gn:timezone":"Asia/Kolkata",
    "iso:country":"IN",
    "wof:name":"Karanpur",
    "wof:placetype":"locality"
},
  "geometry": {"coordinates":[81.0891,25.95178],"type":"Point"}
}