{
  "type": "Feature",
  "properties": {
    "iso:country":"IN",
    "ks:ks_name":"Kolhua",
    "ks:ks_pop":30,
    "ks:ks_type":"VILLAGE",
    "name:eng_x_preferred":[
        "Kolhua"
    ],
    "wof:name":"Kolhua",
    "wof:placetype":"locality",
    "wof:population":30
},
  "geometry": {"coordinates":[83.87199099999999,25.734833],"type":"Point"}
}