{
  "type": "Feature",
  "properties": {
    "iso:country":"IN",
    "ks:ks_name":"Madikebe",
    "ks:ks_pop":120,
    "ks:ks_type":"HABITATION",
    "name:eng_x_preferred":[
        "Madikebe"
    ],
    "wof:name":"Madikebe",
    "wof:placetype":"locality",
    "wof:population":120
},
  "geometry": {"coordinates":[75.97194399999999,12.182222],"type":"Point"}
}