{
  "type": "Feature",
  "properties": {
    "gn:admin1_code":"28.0",
    "gn:admin2_code":"334.0",
    "gn:asciiname":"Srikantapur",
    "gn:country_code":"IN",
    "gn:dem":80,
    "gn:feature_class":"P",
    "gn:feature_code":"PPL",
    "gn:name":"Srik\u0101ntapur",
    "gn:population":0,
    "gn:timezone":"Asia/Kolkata",
    "iso:country":"IN",
    "ks:ks_alt_nam":"Srik\u0101ntapur",
    "ks:ks_name":"Srikantapur",
    "ks:ks_pop":987,
    "ks:ks_type":"VILLAGE",
    "name:eng_x_preferred":[
        "Srikantapur"
    ],
    "name:eng_x_variant":[
        "Srik\u0101ntapur"
    ],
    "wof:name":"Srikantapur",
    "wof:placetype":"locality",
    "wof:population":987
},
  "geometry": {"coordinates":[87.533378,24.032739],"type":"Point"}
}