{
  "type": "Feature",
  "properties": {
    "gn:admin1_code":"16.0",
    "gn:admin2_code":"521",
    "gn:asciiname":"Kapurwahal",
    "gn:country_code":"IN",
    "gn:dem":630,
    "gn:feature_class":"P",
    "gn:feature_code":"PPL",
    "gn:name":"Kap\u016brw\u0101h\u0101l",
    "gn:population":0,
    "gn:timezone":"Asia/Kolkata",
    "iso:country":"IN",
    "wof:name":"Kapurwahal",
    "wof:placetype":"neighbourhood"
},
  "geometry": {"coordinates":[73.91182000000001,18.2314],"type":"Point"}
}