{
  "type": "Feature",
  "properties": {
    "gn:admin1_code":"19.0",
    "gn:admin2_code":"571.0",
    "gn:asciiname":"Aladmaradpalya",
    "gn:country_code":"IN",
    "gn:dem":895,
    "gn:feature_class":"P",
    "gn:feature_code":"PPL",
    "gn:name":"Aladmaradp\u0101lya",
    "gn:population":0,
    "gn:timezone":"Asia/Kolkata",
    "iso:country":"IN",
    "wof:name":"Aladmaradpalya",
    "wof:placetype":"locality"
},
  "geometry": {"coordinates":[77.20350999999999,13.33568],"type":"Point"}
}