{
  "type": "Feature",
  "properties": {
    "gn:admin1_code":"19.0",
    "gn:admin2_code":"571.0",
    "gn:asciiname":"Aladmaradpalya",
    "gn:country_code":"IN",
    "gn:dem":895,
    "gn:feature_class":"P",
    "gn:feature_code":"PPL",
    "gn:name":"Aladmaradp\u0101lya",
    "gn:population":0,
    "gn:timezone":"Asia/Kolkata",
    "iso:country":"IN",
    "ks:ks_name":"Aladamaradapalya",
    "ks:ks_pop":140,
    "ks:ks_type":"HABITATION",
    "name:eng_x_preferred":[
        "Aladamaradapalya"
    ],
    "name:eng_x_variant":[
        "Aladmaradpalya"
    ],
    "wof:name":"Aladamaradapalya",
    "wof:placetype":"locality",
    "wof:population":140
},
  "geometry": {"coordinates":[77.20105100000001,13.335859],"type":"Point"}
}