{
  "type": "Feature",
  "properties": {
    "gn:admin1_code":"36",
    "gn:admin2_code":"137.0",
    "gn:asciiname":"Bauhara",
    "gn:country_code":"IN",
    "gn:dem":221,
    "gn:feature_class":"P",
    "gn:feature_code":"PPL",
    "gn:name":"Bauhara",
    "gn:population":0,
    "gn:timezone":"Asia/Kolkata",
    "iso:country":"IN",
    "wof:name":"Bauhara",
    "wof:placetype":"locality"
},
  "geometry": {"coordinates":[78.38249999999999,29.01772],"type":"Point"}
}