{
  "type": "Feature",
  "properties": {
    "gn:admin1_code":"24.0",
    "gn:admin2_code":"107.0",
    "gn:asciiname":"Simar",
    "gn:country_code":"IN",
    "gn:dem":239,
    "gn:feature_class":"P",
    "gn:feature_code":"PPL",
    "gn:name":"Simar",
    "gn:population":0,
    "gn:timezone":"Asia/Kolkata",
    "iso:country":"IN",
    "name:ido_x_preferred":[
        "Simaro"
    ],
    "name:nor_x_preferred":[
        "Simar"
    ],
    "name:rus_x_preferred":[
        "\u0414\u0437\u0438\u043c\u0430\u0440\u0440\u0430"
    ],
    "name:ukr_x_preferred":[
        "\u0414\u0437\u0456\u043c\u0430\u0440\u0440\u0430"
    ],
    "wof:name":"Simar",
    "wof:placetype":"locality"
},
  "geometry": {"coordinates":[76.67816999999999,26.2173],"type":"Point"}
}