{
  "type": "Feature",
  "properties": {
    "iso:country":"IN",
    "ks:ks_name":"Chhit Bara Khangir",
    "ks:ks_pop":0,
    "ks:ks_type":"VILLAGE",
    "name:eng_x_preferred":[
        "Chhit Bara Khangir"
    ],
    "wof:name":"Chhit Bara Khangir",
    "wof:placetype":"locality",
    "wof:population":0
},
  "geometry": {"coordinates":[89.01470999999999,26.335985],"type":"Point"}
}