{
  "type": "Feature",
  "properties": {
    "gn:admin1_code":"16.0",
    "gn:admin2_code":"509.0",
    "gn:asciiname":"Julbardi",
    "gn:country_code":"IN",
    "gn:dem":244,
    "gn:feature_class":"P",
    "gn:feature_code":"PPL",
    "gn:name":"Julbardi",
    "gn:population":0,
    "gn:timezone":"Asia/Kolkata",
    "iso:country":"IN",
    "ks:ks_name":"Zulbardi",
    "ks:ks_pop":25,
    "ks:ks_type":"VILLAGE",
    "name:eng_x_preferred":[
        "Zulbardi"
    ],
    "name:eng_x_variant":[
        "Julbardi"
    ],
    "wof:name":"Zulbardi",
    "wof:placetype":"locality",
    "wof:population":25
},
  "geometry": {"coordinates":[79.104561,19.720258],"type":"Point"}
}