{
  "type": "Feature",
  "properties": {
    "iso:country":"IN",
    "ks:ks_alt_nam":"MAHUA TOLI",
    "ks:ks_name":"Mahua Toli",
    "ks:ks_pop":151,
    "ks:ks_type":"HABITATION",
    "name:eng_x_preferred":[
        "Mahua Toli"
    ],
    "wof:name":"Mahua Toli",
    "wof:placetype":"locality",
    "wof:population":151
},
  "geometry": {"coordinates":[85.156575,22.994008],"type":"Point"}
}