{
  "type": "Feature",
  "properties": {
    "iso:country":"IN",
    "ks:ks_name":"Hanumantiya",
    "ks:ks_pop":689,
    "ks:ks_type":"VILLAGE",
    "name:eng_x_preferred":[
        "Hanumantiya"
    ],
    "wof:name":"Hanumantiya",
    "wof:placetype":"locality",
    "wof:population":689
},
  "geometry": {"coordinates":[75.196648,22.226197],"type":"Point"}
}