{
  "type": "Feature",
  "properties": {
    "iso:country":"IN",
    "ks:ks_name":"Purungigudde",
    "ks:ks_pop":471,
    "ks:ks_type":"HABITATION",
    "name:eng_x_preferred":[
        "Purungigudde"
    ],
    "wof:name":"Purungigudde",
    "wof:placetype":"locality",
    "wof:population":471
},
  "geometry": {"coordinates":[74.862004,13.119151],"type":"Point"}
}