{
  "type": "Feature",
  "properties": {
    "iso:country":"IN",
    "ks:ks_name":"Paunan",
    "ks:ks_pop":1835,
    "ks:ks_type":"VILLAGE",
    "name:eng_x_preferred":[
        "Paunan"
    ],
    "wof:name":"Paunan",
    "wof:placetype":"locality",
    "wof:population":1835
},
  "geometry": {"coordinates":[88.255062,22.846773],"type":"Point"}
}