{
  "type": "Feature",
  "properties": {
    "gn:admin1_code":"38.0",
    "gn:admin2_code":"353.0",
    "gn:asciiname":"Rolajiwanpur",
    "gn:country_code":"IN",
    "gn:dem":75,
    "gn:feature_class":"P",
    "gn:feature_code":"PPL",
    "gn:name":"Rol\u0101jiwanpur",
    "gn:population":0,
    "gn:timezone":"Asia/Kolkata",
    "iso:country":"IN",
    "wof:name":"Rolajiwanpur",
    "wof:placetype":"locality"
},
  "geometry": {"coordinates":[87.69365999999999,24.46787],"type":"Point"}
}