{
  "type": "Feature",
  "properties": {
    "gn:admin1_code":"11.0",
    "gn:admin2_code":"33.0",
    "gn:asciiname":"Naya Jubbar",
    "gn:country_code":"IN",
    "gn:dem":1882,
    "gn:feature_class":"P",
    "gn:feature_code":"PPL",
    "gn:name":"Naya Jubbar",
    "gn:population":0,
    "gn:timezone":"Asia/Kolkata",
    "iso:country":"IN",
    "wof:name":"Naya Jubbar",
    "wof:placetype":"locality"
},
  "geometry": {"coordinates":[77.2855,31.06075],"type":"Point"}
}