{
  "type": "Feature",
  "properties": {
    "iso:country":"IN",
    "ks:ks_alt_nam":"GHATSAI",
    "ks:ks_name":"Ghatsai",
    "ks:ks_pop":476,
    "ks:ks_type":"HABITATION",
    "name:eng_x_preferred":[
        "Ghatsai"
    ],
    "wof:name":"Ghatsai",
    "wof:placetype":"locality",
    "wof:population":476
},
  "geometry": {"coordinates":[85.600326,22.298525],"type":"Point"}
}