{
  "type": "Feature",
  "properties": {
    "iso:country":"IN",
    "ks:ks_name":"Khapatiya Purwa",
    "ks:ks_pop":250,
    "ks:ks_type":"HABITATION",
    "name:eng_x_preferred":[
        "Khapatiya Purwa"
    ],
    "wof:name":"Khapatiya Purwa",
    "wof:placetype":"locality",
    "wof:population":250
},
  "geometry": {"coordinates":[80.76603900000001,25.192215],"type":"Point"}
}