{
  "type": "Feature",
  "properties": {
    "gn:admin1_code":"12.0",
    "gn:admin2_code":"004",
    "gn:asciiname":"Darchiks",
    "gn:country_code":"IN",
    "gn:dem":3517,
    "gn:feature_class":"P",
    "gn:feature_code":"PPL",
    "gn:name":"Darchiks",
    "gn:population":0,
    "gn:timezone":"Asia/Kolkata",
    "iso:country":"IN",
    "wof:name":"Darchiks",
    "wof:placetype":"locality"
},
  "geometry": {"coordinates":[76.40139000000001,34.61684],"type":"Point"}
}