{
  "type": "Feature",
  "properties": {
    "iso:country":"IN",
    "ks:ks_name":"Katali",
    "ks:ks_pop":1474,
    "ks:ks_type":"VILLAGE",
    "name:eng_x_preferred":[
        "Katali"
    ],
    "wof:name":"Katali",
    "wof:placetype":"locality",
    "wof:population":1474
},
  "geometry": {"coordinates":[73.39283,16.513567],"type":"Point"}
}