{
  "type": "Feature",
  "properties": {
    "iso:country":"IN",
    "ks:ks_name":"Kelaginamugravalli",
    "ks:ks_pop":104,
    "ks:ks_type":"HABITATION",
    "name:eng_x_preferred":[
        "Kelaginamugravalli"
    ],
    "wof:name":"Kelaginamugravalli",
    "wof:placetype":"locality",
    "wof:population":104
},
  "geometry": {"coordinates":[75.058261,14.120844],"type":"Point"}
}