{
  "type": "Feature",
  "properties": {
    "iso:country":"IN",
    "ks:ks_name":"Hebar Hittlu",
    "ks:ks_pop":664,
    "ks:ks_type":"HABITATION",
    "name:eng_x_preferred":[
        "Hebar Hittlu"
    ],
    "wof:name":"Hebar Hittlu",
    "wof:placetype":"locality",
    "wof:population":664
},
  "geometry": {"coordinates":[74.47997599999999,14.226908],"type":"Point"}
}