{
  "type": "Feature",
  "properties": {
    "iso:country":"IN",
    "ks:ks_name":"Daraali",
    "ks:ks_pop":3148,
    "ks:ks_type":"VILLAGE",
    "ks:ks_uagg_main":0,
    "name:eng_x_preferred":[
        "Daraali"
    ],
    "wof:name":"Daraali",
    "wof:placetype":"neighbourhood",
    "wof:population":3148
},
  "geometry": {"coordinates":[77.534083,29.988308],"type":"Point"}
}