{
  "type": "Feature",
  "properties": {
    "iso:country":"IN",
    "ks:ks_name":"Kelwangaon",
    "ks:ks_pop":133,
    "ks:ks_type":"VILLAGE",
    "name:eng_x_preferred":[
        "Kelwangaon"
    ],
    "wof:name":"Kelwangaon",
    "wof:placetype":"locality",
    "wof:population":133
},
  "geometry": {"coordinates":[78.27010199999999,30.365255],"type":"Point"}
}