{
  "type": "Feature",
  "properties": {
    "iso:country":"IN",
    "ks:ks_name":"Bojyathanda",
    "ks:ks_pop":194,
    "ks:ks_type":"HABITATION",
    "name:eng_x_preferred":[
        "Bojyathanda"
    ],
    "wof:name":"Bojyathanda",
    "wof:placetype":"locality",
    "wof:population":194
},
  "geometry": {"coordinates":[79.926815,17.227591],"type":"Point"}
}