{
  "type": "Feature",
  "properties": {
    "iso:country":"IN",
    "ks:ks_name":"Banamalipurpatna",
    "ks:ks_pop":312,
    "ks:ks_type":"VILLAGE",
    "ks:ks_uagg_main":0,
    "name:eng_x_preferred":[
        "Banamalipurpatna"
    ],
    "wof:name":"Banamalipurpatna",
    "wof:placetype":"neighbourhood",
    "wof:population":312
},
  "geometry": {"coordinates":[85.49919300000001,19.680237],"type":"Point"}
}