{
  "type": "Feature",
  "properties": {
    "gn:admin1_code":"11.0",
    "gn:admin2_code":"27.0",
    "gn:asciiname":"Matlehr",
    "gn:country_code":"IN",
    "gn:dem":1725,
    "gn:feature_class":"P",
    "gn:feature_code":"PPL",
    "gn:name":"Matlehr",
    "gn:population":0,
    "gn:timezone":"Asia/Kolkata",
    "iso:country":"IN",
    "wof:name":"Matlehr",
    "wof:placetype":"locality"
},
  "geometry": {"coordinates":[77.30039000000002,31.30407],"type":"Point"}
}