{
  "type": "Feature",
  "properties": {
    "iso:country":"IN",
    "ks:ks_name":"Sonarwadi",
    "ks:ks_pop":100,
    "ks:ks_type":"HABITATION",
    "name:eng_x_preferred":[
        "Sonarwadi"
    ],
    "wof:name":"Sonarwadi",
    "wof:placetype":"locality",
    "wof:population":100
},
  "geometry": {"coordinates":[73.602289,16.761803],"type":"Point"}
}