{
  "type": "Feature",
  "properties": {
    "iso:country":"IN",
    "ks:ks_alt_nam":"BARISIKAR",
    "ks:ks_name":"Barisikar",
    "ks:ks_pop":159,
    "ks:ks_type":"HABITATION",
    "name:eng_x_preferred":[
        "Barisikar"
    ],
    "wof:name":"Barisikar",
    "wof:placetype":"locality",
    "wof:population":159
},
  "geometry": {"coordinates":[85.803545,23.932464],"type":"Point"}
}