{
  "type": "Feature",
  "properties": {
    "iso:country":"IN",
    "ks:ks_name":"Chenimari Pt-II",
    "ks:ks_type":"VILLAGE",
    "name:eng_x_preferred":[
        "Chenimari Pt-II"
    ],
    "wof:name":"Chenimari Pt-II",
    "wof:placetype":"locality"
},
  "geometry": {"coordinates":[90.686404,25.963342],"type":"Point"}
}