{
  "type": "Feature",
  "properties": {
    "iso:country":"IN",
    "ks:ks_name":"Navamuvada",
    "ks:ks_pop":432,
    "ks:ks_type":"HABITATION",
    "name:eng_x_preferred":[
        "Navamuvada"
    ],
    "wof:name":"Navamuvada",
    "wof:placetype":"locality",
    "wof:population":432
},
  "geometry": {"coordinates":[72.887778,22.864056],"type":"Point"}
}