{
  "type": "Feature",
  "properties": {
    "iso:country":"IN",
    "ks:ks_name":"Bhotgaon Medhipara",
    "ks:ks_pop":584,
    "ks:ks_type":"VILLAGE",
    "name:eng_x_preferred":[
        "Bhotgaon Medhipara"
    ],
    "wof:name":"Bhotgaon Medhipara",
    "wof:placetype":"locality",
    "wof:population":584
},
  "geometry": {"coordinates":[90.23531800000001,26.335914],"type":"Point"}
}