{
  "type": "Feature",
  "properties": {
    "iso:country":"IN",
    "ks:ks_name":"Padumoni",
    "ks:ks_pop":950,
    "ks:ks_type":"HABITATION",
    "name:eng_x_preferred":[
        "Padumoni"
    ],
    "wof:name":"Padumoni",
    "wof:placetype":"locality",
    "wof:population":950
},
  "geometry": {"coordinates":[92.938676,26.819541],"type":"Point"}
}