{
  "type": "Feature",
  "properties": {
    "gn:admin1_code":"35",
    "gn:admin2_code":"463.0",
    "gn:asciiname":"Kasar",
    "gn:country_code":"IN",
    "gn:dem":379,
    "gn:feature_class":"P",
    "gn:feature_code":"PPL",
    "gn:name":"Kasar",
    "gn:population":0,
    "gn:timezone":"Asia/Kolkata",
    "iso:country":"IN",
    "ks:ks_name":"Kasar",
    "ks:ks_pop":2378,
    "ks:ks_type":"VILLAGE",
    "name:eng_x_preferred":[
        "Kasar"
    ],
    "wof:name":"Kasar",
    "wof:placetype":"locality",
    "wof:population":2378
},
  "geometry": {"coordinates":[82.543375,24.219338],"type":"Point"}
}