{
  "type": "Feature",
  "properties": {
    "iso:country":"IN",
    "ks:ks_name":"Vikhare Gothane",
    "ks:ks_pop":882,
    "ks:ks_type":"VILLAGE",
    "name:eng_x_preferred":[
        "Vikhare Gothane"
    ],
    "wof:name":"Vikhare Gothane",
    "wof:placetype":"locality",
    "wof:population":882
},
  "geometry": {"coordinates":[73.525256,16.60501],"type":"Point"}
}