{
  "type": "Feature",
  "properties": {
    "iso:country":"IN",
    "ks:ks_name":"Dhantari",
    "ks:ks_pop":1815,
    "ks:ks_type":"VILLAGE",
    "ks:ks_uagg_main":0,
    "name:eng_x_preferred":[
        "Dhantari"
    ],
    "wof:name":"Dhantari",
    "wof:placetype":"neighbourhood",
    "wof:population":1815
},
  "geometry": {"coordinates":[88.580715,22.827365],"type":"Point"}
}