{
  "type": "Feature",
  "properties": {
    "gn:admin1_code":"34.0",
    "gn:admin2_code":"216.0",
    "gn:asciiname":"Subudhia Nathan",
    "gn:country_code":"IN",
    "gn:dem":57,
    "gn:feature_class":"P",
    "gn:feature_code":"PPL",
    "gn:name":"Subudhia Nathan",
    "gn:population":0,
    "gn:timezone":"Asia/Kolkata",
    "iso:country":"IN",
    "ks:ks_name":"Subudho Nathan",
    "ks:ks_pop":680,
    "ks:ks_type":"VILLAGE",
    "name:eng_x_preferred":[
        "Subudho Nathan"
    ],
    "name:eng_x_variant":[
        "Subudhia Nathan"
    ],
    "wof:name":"Subudho Nathan",
    "wof:placetype":"locality",
    "wof:population":680
},
  "geometry": {"coordinates":[85.40683199999999,25.954097],"type":"Point"}
}