{
  "type": "Feature",
  "properties": {
    "iso:country":"IN",
    "ks:ks_name":"Gojina",
    "ks:ks_pop":3794,
    "ks:ks_type":"VILLAGE",
    "ks:ks_uagg_main":0,
    "name:eng_x_preferred":[
        "Gojina"
    ],
    "wof:name":"Gojina",
    "wof:placetype":"neighbourhood",
    "wof:population":3794
},
  "geometry": {"coordinates":[87.774248,22.208441],"type":"Point"}
}