{
  "type": "Feature",
  "properties": {
    "iso:country":"IN",
    "ks:ks_name":"Bheemunipanuku",
    "ks:ks_pop":255,
    "ks:ks_type":"HABITATION",
    "name:eng_x_preferred":[
        "Bheemunipanuku"
    ],
    "wof:name":"Bheemunipanuku",
    "wof:placetype":"locality",
    "wof:population":255
},
  "geometry": {"coordinates":[82.423399,18.019889],"type":"Point"}
}