{
  "type": "Feature",
  "properties": {
    "gn:admin1_code":"35.0",
    "gn:admin2_code":"422.0",
    "gn:asciiname":"Baniyan ka Chhar",
    "gn:country_code":"IN",
    "gn:dem":194,
    "gn:feature_class":"P",
    "gn:feature_code":"PPL",
    "gn:name":"Baniy\u0101n ka Chh\u0101r",
    "gn:population":0,
    "gn:timezone":"Asia/Kolkata",
    "iso:country":"IN",
    "wof:name":"Baniyan ka Chhar",
    "wof:placetype":"locality"
},
  "geometry": {"coordinates":[78.34581999999997,25.81125],"type":"Point"}
}