{
  "type": "Feature",
  "properties": {
    "gn:admin1_code":"19.0",
    "gn:admin2_code":"583.0",
    "gn:asciiname":"Guttadagra",
    "gn:country_code":"IN",
    "gn:dem":900,
    "gn:feature_class":"P",
    "gn:feature_code":"PPL",
    "gn:name":"Guttadagra",
    "gn:population":0,
    "gn:timezone":"Asia/Kolkata",
    "iso:country":"IN",
    "wof:name":"Guttadagra",
    "wof:placetype":"neighbourhood"
},
  "geometry": {"coordinates":[77.45386999999999,13.25441],"type":"Point"}
}