{
  "type": "Feature",
  "properties": {
    "iso:country":"IN",
    "ks:ks_name":"Bapsai Mala",
    "ks:ks_pop":157,
    "ks:ks_type":"HABITATION",
    "name:eng_x_preferred":[
        "Bapsai Mala"
    ],
    "wof:name":"Bapsai Mala",
    "wof:placetype":"locality",
    "wof:population":157
},
  "geometry": {"coordinates":[74.12949500000001,18.203832],"type":"Point"}
}