{
  "type": "Feature",
  "properties": {
    "iso:country":"IN",
    "ks:ks_name":"Wakanwasti",
    "ks:ks_pop":185,
    "ks:ks_type":"HABITATION",
    "ks:ks_uagg_main":0,
    "name:eng_x_preferred":[
        "Wakanwasti"
    ],
    "wof:name":"Wakanwasti",
    "wof:placetype":"neighbourhood",
    "wof:population":185
},
  "geometry": {"coordinates":[74.255332,19.552181],"type":"Point"}
}