{
  "type": "Feature",
  "properties": {
    "iso:country":"IN",
    "ks:ks_alt_nam":"Murikkum vayal",
    "ks:ks_name":"Murikkum Vayal",
    "ks:ks_pop":2823,
    "ks:ks_type":"HABITATION",
    "ks:ks_uagg_main":0,
    "name:eng_x_preferred":[
        "Murikkum Vayal"
    ],
    "wof:name":"Murikkum Vayal",
    "wof:placetype":"neighbourhood",
    "wof:population":2823
},
  "geometry": {"coordinates":[76.895961,9.50584],"type":"Point"}
}