{
  "type": "Feature",
  "properties": {
    "iso:country":"IN",
    "ks:ks_name":"Nangli",
    "ks:ks_pop":542,
    "ks:ks_type":"VILLAGE",
    "name:eng_x_preferred":[
        "Nangli"
    ],
    "wof:name":"Nangli",
    "wof:placetype":"locality",
    "wof:population":542
},
  "geometry": {"coordinates":[76.98571200000001,27.801034],"type":"Point"}
}