{
  "type": "Feature",
  "properties": {
    "gn:admin1_code":"2.0",
    "gn:admin2_code":"554.0",
    "gn:asciiname":"Avanigunta",
    "gn:country_code":"IN",
    "gn:dem":733,
    "gn:feature_class":"P",
    "gn:feature_code":"PPL",
    "gn:name":"\u0100vanigunta",
    "gn:population":0,
    "gn:timezone":"Asia/Kolkata",
    "iso:country":"IN",
    "wof:name":"Avanigunta",
    "wof:placetype":"locality"
},
  "geometry": {"coordinates":[78.70118000000002,13.43824],"type":"Point"}
}