{
  "type": "Feature",
  "properties": {
    "iso:country":"IN",
    "ks:ks_name":"Bhurushi Khamar",
    "ks:ks_pop":149,
    "ks:ks_type":"VILLAGE",
    "name:eng_x_preferred":[
        "Bhurushi Khamar"
    ],
    "wof:name":"Bhurushi Khamar",
    "wof:placetype":"locality",
    "wof:population":149
},
  "geometry": {"coordinates":[83.47951999999999,19.675211],"type":"Point"}
}