{
  "type": "Feature",
  "properties": {
    "iso:country":"IN",
    "ks:ks_name":"Chartha",
    "ks:ks_pop":1055,
    "ks:ks_type":"VILLAGE",
    "ks:ks_uagg_main":0,
    "name:eng_x_preferred":[
        "Chartha"
    ],
    "wof:name":"Chartha",
    "wof:placetype":"neighbourhood",
    "wof:population":1055
},
  "geometry": {"coordinates":[75.590498,19.994133],"type":"Point"}
}