{
  "type": "Feature",
  "properties": {
    "iso:country":"IN",
    "ks:ks_name":"Chinchpada",
    "ks:ks_pop":318,
    "ks:ks_type":"HABITATION",
    "name:eng_x_preferred":[
        "Chinchpada"
    ],
    "wof:name":"Chinchpada",
    "wof:placetype":"locality",
    "wof:population":318
},
  "geometry": {"coordinates":[73.10471800000001,20.05261],"type":"Point"}
}