{
  "type": "Feature",
  "properties": {
    "gn:country":"IN",
    "gn:fcode":"PPL",
    "gn:population":9349,
    "iso:country":"IN",
    "name:ben_x_preferred":[
        "\u09b9\u09be\u09a4\u09cb\u09a1\u09bc"
    ],
    "name:bpy_x_preferred":[
        "\u09b9\u09be\u09a4\u09cb\u09a1\u09bc"
    ],
    "name:ceb_x_preferred":[
        "H\u0101tod"
    ],
    "name:eng_x_preferred":[
        "Hatod"
    ],
    "name:fra_x_preferred":[
        "Hatod"
    ],
    "name:ita_x_preferred":[
        "Hatod"
    ],
    "name:mlg_x_preferred":[
        "Hatod"
    ],
    "name:msa_x_preferred":[
        "Hatod"
    ],
    "name:nan_x_preferred":[
        "Hatod"
    ],
    "name:new_x_preferred":[
        "\u0939\u0924\u094b\u0926"
    ],
    "name:nld_x_preferred":[
        "Hatod"
    ],
    "name:por_x_preferred":[
        "Hatod"
    ],
    "name:sco_x_preferred":[
        "Hatod"
    ],
    "name:spa_x_preferred":[
        "Hatod"
    ],
    "name:swe_x_preferred":[
        "H\u0101tod"
    ],
    "name:vie_x_preferred":[
        "Hatod"
    ],
    "name:zho_x_preferred":[
        "\u54c8\u6258\u5fb7"
    ],
    "qs:name":"Hatod",
    "qs:name_adm0":"India",
    "qs:name_adm1":"Madhya Pradesh",
    "qs:photos_9r":0,
    "qs:photos_sr":0,
    "qs:placetype":"Town",
    "qs:pop_sr":"5",
    "wd:wordcount":142,
    "wof:name":"Hatod",
    "wof:placetype":"locality",
    "wof:population":9349
},
  "geometry": {"coordinates":[75.74009,22.7943],"type":"Point"}
}