{
  "type": "Feature",
  "properties": {
    "iso:country":"IN",
    "ks:ks_name":"Bassi Bahadar",
    "ks:ks_pop":26,
    "ks:ks_type":"VILLAGE",
    "name:eng_x_preferred":[
        "Bassi Bahadar"
    ],
    "wof:name":"Bassi Bahadar",
    "wof:placetype":"locality",
    "wof:population":26
},
  "geometry": {"coordinates":[75.873431,31.659347],"type":"Point"}
}