{
  "type": "Feature",
  "properties": {
    "iso:country":"IN",
    "ks:ks_alt_nam":"Naw\u0101dih",
    "ks:ks_name":"Nawadih",
    "ks:ks_pop":2006,
    "ks:ks_type":"VILLAGE",
    "ks:ks_uagg_main":0,
    "name:eng_x_preferred":[
        "Nawadih"
    ],
    "name:eng_x_variant":[
        "Naw\u0101dih"
    ],
    "wof:name":"Nawadih",
    "wof:placetype":"neighbourhood",
    "wof:population":2006
},
  "geometry": {"coordinates":[85.60744200000001,23.725811],"type":"Point"}
}