{
  "type": "Feature",
  "properties": {
    "iso:country":"IN",
    "ks:ks_name":"Parasnath Hill",
    "ks:ks_pop":169,
    "ks:ks_type":"VILLAGE",
    "name:eng_x_preferred":[
        "Parasnath Hill"
    ],
    "wof:name":"Parasnath Hill",
    "wof:placetype":"locality",
    "wof:population":169
},
  "geometry": {"coordinates":[86.125232,23.96881],"type":"Point"}
}