{
  "type": "Feature",
  "properties": {
    "iso:country":"IN",
    "ks:ks_name":"Moleyurukaval",
    "ks:ks_pop":181,
    "ks:ks_type":"VILLAGE",
    "name:eng_x_preferred":[
        "Moleyurukaval"
    ],
    "wof:name":"Moleyurukaval",
    "wof:placetype":"locality",
    "wof:population":181
},
  "geometry": {"coordinates":[76.379614,11.866154],"type":"Point"}
}