{
  "type": "Feature",
  "properties": {
    "iso:country":"IN",
    "ks:ks_alt_nam":"GHANSIYADHAP",
    "ks:ks_name":"Ghansiyadhap",
    "ks:ks_pop":143,
    "ks:ks_type":"HABITATION",
    "name:eng_x_preferred":[
        "Ghansiyadhap"
    ],
    "wof:name":"Ghansiyadhap",
    "wof:placetype":"locality",
    "wof:population":143
},
  "geometry": {"coordinates":[83.845415,22.477785],"type":"Point"}
}