{
  "type": "Feature",
  "properties": {
    "iso:country":"IN",
    "ks:ks_name":"13 HMH",
    "ks:ks_pop":537,
    "ks:ks_type":"VILLAGE",
    "ks:ks_uagg_main":0,
    "name:eng_x_preferred":[
        "13 HMH"
    ],
    "wof:name":"13 HMH",
    "wof:placetype":"neighbourhood",
    "wof:population":537
},
  "geometry": {"coordinates":[74.354315,29.581622],"type":"Point"}
}