{
  "type": "Feature",
  "properties": {
    "gn:admin1_code":"36",
    "gn:admin2_code":"194.0",
    "gn:asciiname":"Pura Rangai",
    "gn:country_code":"IN",
    "gn:dem":90,
    "gn:feature_class":"P",
    "gn:feature_code":"PPL",
    "gn:name":"Pura Rangai",
    "gn:population":0,
    "gn:timezone":"Asia/Kolkata",
    "iso:country":"IN",
    "wof:name":"Pura Rangai",
    "wof:placetype":"locality"
},
  "geometry": {"coordinates":[82.65606,26.15529],"type":"Point"}
}