{
  "type": "Feature",
  "properties": {
    "iso:country":"IN",
    "ks:ks_name":"Sallotar",
    "ks:ks_pop":264,
    "ks:ks_type":"HABITATION",
    "name:eng_x_preferred":[
        "Sallotar"
    ],
    "wof:name":"Sallotar",
    "wof:placetype":"locality",
    "wof:population":264
},
  "geometry": {"coordinates":[75.368538,32.31652],"type":"Point"}
}