{
  "type": "Feature",
  "properties": {
    "iso:country":"IN",
    "ks:ks_name":"Jojodih",
    "ks:ks_pop":296,
    "ks:ks_type":"VILLAGE",
    "name:eng_x_preferred":[
        "Jojodih"
    ],
    "wof:name":"Jojodih",
    "wof:placetype":"locality",
    "wof:population":296
},
  "geometry": {"coordinates":[85.558626,22.971032],"type":"Point"}
}