{
  "type": "Feature",
  "properties": {
    "iso:country":"IN",
    "ks:ks_name":"Challavanivalasa",
    "ks:ks_pop":27,
    "ks:ks_type":"HABITATION",
    "name:eng_x_preferred":[
        "Challavanivalasa"
    ],
    "wof:name":"Challavanivalasa",
    "wof:placetype":"locality",
    "wof:population":27
},
  "geometry": {"coordinates":[83.22267600000001,18.380967],"type":"Point"}
}