{
  "type": "Feature",
  "properties": {
    "gn:admin1_code":"11",
    "gn:admin2_code":"33.0",
    "gn:asciiname":"Narpa Dogri",
    "gn:country_code":"IN",
    "gn:dem":2046,
    "gn:feature_class":"P",
    "gn:feature_code":"PPL",
    "gn:name":"N\u0101rpa Dogri",
    "gn:population":0,
    "gn:timezone":"Asia/Kolkata",
    "iso:country":"IN",
    "wof:name":"Narpa Dogri",
    "wof:placetype":"locality"
},
  "geometry": {"coordinates":[77.76459,31.15967],"type":"Point"}
}