{
  "type": "Feature",
  "properties": {
    "gn:admin1_code":"34.0",
    "gn:admin2_code":"238.0",
    "gn:asciiname":"Barmasia",
    "gn:country_code":"IN",
    "gn:dem":168,
    "gn:feature_class":"P",
    "gn:feature_code":"PPL",
    "gn:name":"Barmasia",
    "gn:population":0,
    "gn:timezone":"Asia/Kolkata",
    "iso:country":"IN",
    "ks:ks_name":"Barmasia",
    "ks:ks_type":"VILLAGE",
    "name:eng_x_preferred":[
        "Barmasia"
    ],
    "wof:name":"Barmasia",
    "wof:placetype":"locality"
},
  "geometry": {"coordinates":[86.11412,24.755355],"type":"Point"}
}