{
  "type": "Feature",
  "properties": {
    "gn:admin1_code":"36.0",
    "gn:admin2_code":"182.0",
    "gn:asciiname":"Basti",
    "gn:country_code":"IN",
    "gn:dem":104,
    "gn:feature_class":"P",
    "gn:feature_code":"PPL",
    "gn:name":"Basti",
    "gn:population":0,
    "gn:timezone":"Asia/Kolkata",
    "iso:country":"IN",
    "name:ceb_x_preferred":[
        "Basti"
    ],
    "name:deu_x_preferred":[
        "Basti"
    ],
    "name:fra_x_preferred":[
        "Basti"
    ],
    "name:hin_x_preferred":[
        "\u092c\u0938\u094d\u0924\u0940"
    ],
    "name:ita_x_preferred":[
        "Basti"
    ],
    "name:nld_x_preferred":[
        "Basti"
    ],
    "name:pnb_x_preferred":[
        "\u0628\u0633\u062a\u06cc"
    ],
    "name:pol_x_preferred":[
        "Basti"
    ],
    "name:spa_x_preferred":[
        "Basti"
    ],
    "name:swe_x_preferred":[
        "Basti"
    ],
    "name:urd_x_preferred":[
        "\u0628\u0633\u062a\u06cc"
    ],
    "wof:name":"Basti",
    "wof:placetype":"locality"
},
  "geometry": {"coordinates":[82.36666,27.25999],"type":"Point"}
}