{
  "type": "Feature",
  "properties": {
    "iso:country":"IN",
    "ks:ks_alt_nam":"HAMBIRAO NAGAR",
    "ks:ks_name":"Hambirao Nagar",
    "ks:ks_pop":202,
    "ks:ks_type":"HABITATION",
    "name:eng_x_preferred":[
        "Hambirao Nagar"
    ],
    "wof:name":"Hambirao Nagar",
    "wof:placetype":"locality",
    "wof:population":202
},
  "geometry": {"coordinates":[74.247894,16.419001],"type":"Point"}
}