{
  "type": "Feature",
  "properties": {
    "iso:country":"IN",
    "ks:ks_name":"Irulkunnu",
    "ks:ks_pop":557,
    "ks:ks_type":"HABITATION",
    "name:eng_x_preferred":[
        "Irulkunnu"
    ],
    "wof:name":"Irulkunnu",
    "wof:placetype":"locality",
    "wof:population":557
},
  "geometry": {"coordinates":[75.969033,11.421824],"type":"Point"}
}