{
  "type": "Feature",
  "properties": {
    "gn:admin1_code":"19.0",
    "gn:admin2_code":"574.0",
    "gn:asciiname":"Kadabgal",
    "gn:country_code":"IN",
    "gn:dem":921,
    "gn:feature_class":"P",
    "gn:feature_code":"PPL",
    "gn:name":"Kadabgal",
    "gn:population":0,
    "gn:timezone":"Asia/Kolkata",
    "iso:country":"IN",
    "name:und_x_variant":[
        "Kadab\u0101g\u0101la"
    ],
    "wof:name":"Kadabgal",
    "wof:placetype":"locality"
},
  "geometry": {"coordinates":[75.99178000000001,12.90559],"type":"Point"}
}