{
  "type": "Feature",
  "properties": {
    "iso:country":"IN",
    "ks:ks_alt_nam":"sankhasor",
    "ks:ks_name":"Sankhasor",
    "ks:ks_pop":151,
    "ks:ks_type":"HABITATION",
    "name:eng_x_preferred":[
        "Sankhasor"
    ],
    "wof:name":"Sankhasor",
    "wof:placetype":"locality",
    "wof:population":151
},
  "geometry": {"coordinates":[86.01123699999999,21.677532],"type":"Point"}
}