{
  "type": "Feature",
  "properties": {
    "iso:country":"IN",
    "ks:ks_alt_nam":"katkarwadi",
    "ks:ks_name":"Katkarwadi",
    "ks:ks_pop":304,
    "ks:ks_type":"HABITATION",
    "name:eng_x_preferred":[
        "Katkarwadi"
    ],
    "wof:name":"Katkarwadi",
    "wof:placetype":"locality",
    "wof:population":304
},
  "geometry": {"coordinates":[73.12029099999999,18.605439],"type":"Point"}
}