{
  "type": "Feature",
  "properties": {
    "iso:country":"IN",
    "ks:ks_name":"Alagdiha",
    "ks:ks_pop":0,
    "ks:ks_type":"VILLAGE",
    "name:eng_x_preferred":[
        "Alagdiha"
    ],
    "wof:name":"Alagdiha",
    "wof:placetype":"locality",
    "wof:population":0
},
  "geometry": {"coordinates":[86.849569,24.398377],"type":"Point"}
}