{
  "type": "Feature",
  "properties": {
    "gn:admin1_code":"35.0",
    "gn:admin2_code":"466.0",
    "gn:asciiname":"Nandiyakheri",
    "gn:country_code":"IN",
    "gn:dem":227,
    "gn:feature_class":"P",
    "gn:feature_code":"PPL",
    "gn:name":"N\u0101ndiy\u0101kheri",
    "gn:population":0,
    "gn:timezone":"Asia/Kolkata",
    "iso:country":"IN",
    "wof:name":"Nandiyakheri",
    "wof:placetype":"locality"
},
  "geometry": {"coordinates":[76.31962,22.20007],"type":"Point"}
}