{
  "type": "Feature",
  "properties": {
    "iso:country":"IN",
    "ks:ks_name":"Madhupur",
    "ks:ks_pop":470,
    "ks:ks_type":"HABITATION",
    "ks:ks_uagg_main":0,
    "name:eng_x_preferred":[
        "Madhupur"
    ],
    "wof:name":"Madhupur",
    "wof:placetype":"neighbourhood",
    "wof:population":470
},
  "geometry": {"coordinates":[95.18851600000001,27.753701],"type":"Point"}
}