{
  "type": "Feature",
  "properties": {
    "iso:country":"IN",
    "ks:ks_name":"Maahulabada",
    "ks:ks_pop":183,
    "ks:ks_type":"HABITATION",
    "name:eng_x_preferred":[
        "Maahulabada"
    ],
    "wof:name":"Maahulabada",
    "wof:placetype":"locality",
    "wof:population":183
},
  "geometry": {"coordinates":[84.513114,19.134469],"type":"Point"}
}