{
  "type": "Feature",
  "properties": {
    "iso:country":"IN",
    "ks:ks_name":"Lamapadar",
    "ks:ks_pop":328,
    "ks:ks_type":"VILLAGE",
    "name:eng_x_preferred":[
        "Lamapadar"
    ],
    "wof:name":"Lamapadar",
    "wof:placetype":"locality",
    "wof:population":328
},
  "geometry": {"coordinates":[84.204937,20.30459],"type":"Point"}
}