{
  "type": "Feature",
  "properties": {
    "iso:country":"IN",
    "ks:ks_name":"Frejarpur",
    "ks:ks_pop":750,
    "ks:ks_type":"VILLAGE",
    "name:eng_x_preferred":[
        "Frejarpur"
    ],
    "wof:name":"Frejarpur",
    "wof:placetype":"locality",
    "wof:population":750
},
  "geometry": {"coordinates":[82.870064,20.978855],"type":"Point"}
}