{
  "type": "Feature",
  "properties": {
    "iso:country":"IN",
    "ks:ks_name":"Bedapat",
    "ks:ks_pop":626,
    "ks:ks_type":"VILLAGE",
    "name:eng_x_preferred":[
        "Bedapat"
    ],
    "wof:name":"Bedapat",
    "wof:placetype":"locality",
    "wof:population":626
},
  "geometry": {"coordinates":[81.937127,22.320637],"type":"Point"}
}