{
  "type": "Feature",
  "properties": {
    "iso:country":"IN",
    "ks:ks_alt_nam":"BETWASTI",
    "ks:ks_name":"Betwasti",
    "ks:ks_pop":145,
    "ks:ks_type":"HABITATION",
    "name:eng_x_preferred":[
        "Betwasti"
    ],
    "wof:name":"Betwasti",
    "wof:placetype":"locality",
    "wof:population":145
},
  "geometry": {"coordinates":[74.48624700000001,18.769162],"type":"Point"}
}