{
  "type": "Feature",
  "properties": {
    "iso:country":"IN",
    "ks:ks_name":"Pasi Tola",
    "ks:ks_pop":289,
    "ks:ks_type":"HABITATION",
    "ks:ks_uagg_main":0,
    "name:eng_x_preferred":[
        "Pasi Tola"
    ],
    "wof:name":"Pasi Tola",
    "wof:placetype":"neighbourhood",
    "wof:population":289
},
  "geometry": {"coordinates":[83.607139,27.154837],"type":"Point"}
}