{
  "type": "Feature",
  "properties": {
    "gn:admin1_code":"37.0",
    "gn:admin2_code":"416.0",
    "gn:asciiname":"Masenar",
    "gn:country_code":"IN",
    "gn:dem":433,
    "gn:feature_class":"P",
    "gn:feature_code":"PPL",
    "gn:name":"Masen\u0101r",
    "gn:population":0,
    "gn:timezone":"Asia/Kolkata",
    "iso:country":"IN",
    "ks:ks_alt_nam":"Masen\u0101r",
    "ks:ks_name":"Masenar",
    "ks:ks_pop":903,
    "ks:ks_type":"VILLAGE",
    "name:eng_x_preferred":[
        "Masenar"
    ],
    "name:eng_x_variant":[
        "Masen\u0101r"
    ],
    "wof:name":"Masenar",
    "wof:placetype":"locality",
    "wof:population":903
},
  "geometry": {"coordinates":[81.363041,18.789609],"type":"Point"}
}