{
  "type": "Feature",
  "properties": {
    "gn:admin1_code":"23",
    "gn:admin2_code":"48.0",
    "gn:asciiname":"Batta",
    "gn:country_code":"IN",
    "gn:dem":257,
    "gn:feature_class":"P",
    "gn:feature_code":"PPL",
    "gn:name":"Batta",
    "gn:population":0,
    "gn:timezone":"Asia/Kolkata",
    "iso:country":"IN",
    "name:spa_x_preferred":[
        "Batta"
    ],
    "wof:name":"Batta",
    "wof:placetype":"locality"
},
  "geometry": {"coordinates":[76.54807,30.28662000000001],"type":"Point"}
}