{
  "type": "Feature",
  "properties": {
    "iso:country":"IN",
    "ks:ks_name":"9 SKM-B",
    "ks:ks_pop":52,
    "ks:ks_type":"VILLAGE",
    "name:eng_x_preferred":[
        "9 SKM-B"
    ],
    "wof:name":"9 SKM-B",
    "wof:placetype":"locality",
    "wof:population":52
},
  "geometry": {"coordinates":[72.834858,28.962809],"type":"Point"}
}