{
  "type": "Feature",
  "properties": {
    "gn:admin1_code":"36",
    "gn:admin2_code":"154.0",
    "gn:asciiname":"God Purwa",
    "gn:country_code":"IN",
    "gn:dem":121,
    "gn:feature_class":"P",
    "gn:feature_code":"PPL",
    "gn:name":"God Purwa",
    "gn:population":0,
    "gn:timezone":"Asia/Kolkata",
    "iso:country":"IN",
    "ks:ks_name":"Lodpurwa",
    "ks:ks_pop":75,
    "ks:ks_type":"HABITATION",
    "name:eng_x_preferred":[
        "Lodpurwa"
    ],
    "name:eng_x_variant":[
        "God Purwa"
    ],
    "wof:name":"Lodpurwa",
    "wof:placetype":"locality",
    "wof:population":75
},
  "geometry": {"coordinates":[81.238809,27.547518],"type":"Point"}
}