{
  "type": "Feature",
  "properties": {
    "gn:admin1_code":"16.0",
    "gn:admin2_code":"508.0",
    "gn:asciiname":"Jafrabad",
    "gn:country_code":"IN",
    "gn:dem":124,
    "gn:feature_class":"P",
    "gn:feature_code":"PPL",
    "gn:name":"Jafrab\u0101d",
    "gn:population":0,
    "gn:timezone":"Asia/Kolkata",
    "iso:country":"IN",
    "name:guj_x_preferred":[
        "\u0a9c\u0abe\u0aab\u0ab0\u0abe\u0aac\u0abe\u0aa6"
    ],
    "name:ita_x_preferred":[
        "Jafrabad"
    ],
    "name:por_x_preferred":[
        "Jafrabad"
    ],
    "name:spa_x_preferred":[
        "Jafrabad"
    ],
    "name:vie_x_preferred":[
        "Jafrabad"
    ],
    "name:zho_x_preferred":[
        "\u8d3e\u592b\u62c9\u5df4\u5fb7"
    ],
    "wof:name":"Jafrabad",
    "wof:placetype":"locality"
},
  "geometry": {"coordinates":[79.96269000000002,19.00025],"type":"Point"}
}