{
  "type": "Feature",
  "properties": {
    "gn:admin1_code":"16.0",
    "gn:admin2_code":"516",
    "gn:asciiname":"Kalvan",
    "gn:country_code":"IN",
    "gn:dem":605,
    "gn:feature_class":"P",
    "gn:feature_code":"PPL",
    "gn:name":"Kalv\u0101n",
    "gn:population":0,
    "gn:timezone":"Asia/Kolkata",
    "iso:country":"IN",
    "wof:name":"Kalvan",
    "wof:placetype":"locality"
},
  "geometry": {"coordinates":[74.02535999999998,20.49041],"type":"Point"}
}