{
  "type": "Feature",
  "properties": {
    "gn:admin1_code":"19.0",
    "gn:admin2_code":"578.0",
    "gn:asciiname":"Cheluvanahalli",
    "gn:country_code":"IN",
    "gn:dem":652,
    "gn:feature_class":"P",
    "gn:feature_code":"PPL",
    "gn:name":"Cheluvanahalli",
    "gn:population":0,
    "gn:timezone":"Asia/Kolkata",
    "iso:country":"IN",
    "wof:name":"Cheluvanahalli",
    "wof:placetype":"locality"
},
  "geometry": {"coordinates":[77.14869,12.20051],"type":"Point"}
}