{
  "type": "Feature",
  "properties": {
    "gn:admin1_code":"2.0",
    "gn:asciiname":"Baluvanahalli",
    "gn:country_code":"IN",
    "gn:dem":791,
    "gn:feature_class":"P",
    "gn:feature_code":"PPL",
    "gn:name":"Baluvanahalli",
    "gn:population":0,
    "gn:timezone":"Asia/Kolkata",
    "iso:country":"IN",
    "wof:name":"Baluvanahalli",
    "wof:placetype":"neighbourhood"
},
  "geometry": {"coordinates":[78.45358,12.89539],"type":"Point"}
}