{
  "type": "Feature",
  "properties": {
    "iso:country":"IN",
    "ks:ks_name":"Gadegaon",
    "ks:ks_pop":0,
    "ks:ks_type":"VILLAGE",
    "name:eng_x_preferred":[
        "Gadegaon"
    ],
    "wof:name":"Gadegaon",
    "wof:placetype":"locality",
    "wof:population":0
},
  "geometry": {"coordinates":[78.70814,20.523466],"type":"Point"}
}