{
  "type": "Feature",
  "properties": {
    "iso:country":"IN",
    "ks:ks_name":"Kayyam Vanka",
    "ks:ks_pop":6,
    "ks:ks_type":"HABITATION",
    "name:eng_x_preferred":[
        "Kayyam Vanka"
    ],
    "wof:name":"Kayyam Vanka",
    "wof:placetype":"locality",
    "wof:population":6
},
  "geometry": {"coordinates":[78.52118400000001,13.74913],"type":"Point"}
}