{
  "type": "Feature",
  "properties": {
    "iso:country":"IN",
    "ks:ks_alt_nam":"SOPARAM",
    "ks:ks_name":"Soparam",
    "ks:ks_pop":144,
    "ks:ks_type":"HABITATION",
    "name:eng_x_preferred":[
        "Soparam"
    ],
    "wof:name":"Soparam",
    "wof:placetype":"locality",
    "wof:population":144
},
  "geometry": {"coordinates":[84.918932,23.918125],"type":"Point"}
}