{
  "type": "Feature",
  "properties": {
    "iso:country":"IN",
    "ks:ks_name":"Dyanpuri",
    "ks:ks_pop":209,
    "ks:ks_type":"HABITATION",
    "name:eng_x_preferred":[
        "Dyanpuri"
    ],
    "wof:name":"Dyanpuri",
    "wof:placetype":"locality",
    "wof:population":209
},
  "geometry": {"coordinates":[74.162218,17.621062],"type":"Point"}
}