{
  "type": "Feature",
  "properties": {
    "gn:admin1_code":"19.0",
    "gn:admin2_code":"568.0",
    "gn:asciiname":"Kogari",
    "gn:country_code":"IN",
    "gn:dem":568,
    "gn:feature_class":"P",
    "gn:feature_code":"PPL",
    "gn:name":"Kogari",
    "gn:population":0,
    "gn:timezone":"Asia/Kolkata",
    "iso:country":"IN",
    "wof:name":"Kogari",
    "wof:placetype":"locality"
},
  "geometry": {"coordinates":[75.00990999999998,13.88691],"type":"Point"}
}