{
  "type": "Feature",
  "properties": {
    "iso:country":"IN",
    "ks:ks_alt_nam":"N\u0101rsala",
    "ks:ks_name":"Narsala",
    "ks:ks_pop":5127,
    "ks:ks_type":"URBAN",
    "ks:ks_uagg_main":0,
    "name:eng_x_preferred":[
        "Narsala"
    ],
    "name:eng_x_variant":[
        "N\u0101rsala"
    ],
    "wof:name":"Narsala",
    "wof:placetype":"neighbourhood",
    "wof:population":5127
},
  "geometry": {"coordinates":[79.13476,21.089201],"type":"Point"}
}