{
  "type": "Feature",
  "properties": {
    "iso:country":"IN",
    "ks:ks_alt_nam":"Galabji na mu",
    "ks:ks_name":"Galabji Na Mu",
    "ks:ks_pop":454,
    "ks:ks_type":"HABITATION",
    "name:eng_x_preferred":[
        "Galabji Na Mu"
    ],
    "wof:name":"Galabji Na Mu",
    "wof:placetype":"locality",
    "wof:population":454
},
  "geometry": {"coordinates":[73.280083,22.954917],"type":"Point"}
}