{
  "type": "Feature",
  "properties": {
    "iso:country":"IN",
    "ks:ks_name":"Patla",
    "ks:ks_pop":52,
    "ks:ks_type":"HABITATION",
    "name:eng_x_preferred":[
        "Patla"
    ],
    "wof:name":"Patla",
    "wof:placetype":"locality",
    "wof:population":52
},
  "geometry": {"coordinates":[74.877495,13.138037],"type":"Point"}
}