{
  "type": "Feature",
  "properties": {
    "gn:admin1_code":"25.0",
    "gn:admin2_code":"632.0",
    "gn:asciiname":"Kuppepalaiyam",
    "gn:country_code":"IN",
    "gn:dem":490,
    "gn:feature_class":"P",
    "gn:feature_code":"PPL",
    "gn:name":"Kuppep\u0101laiyam",
    "gn:population":0,
    "gn:timezone":"Asia/Kolkata",
    "iso:country":"IN",
    "wof:name":"Kuppepalaiyam",
    "wof:placetype":"locality"
},
  "geometry": {"coordinates":[76.81685,11.0106],"type":"Point"}
}