{
  "type": "Feature",
  "properties": {
    "gn:admin1_code":"23.0",
    "gn:admin2_code":"44.0",
    "gn:asciiname":"Ude Karan",
    "gn:country_code":"IN",
    "gn:dem":200,
    "gn:feature_class":"P",
    "gn:feature_code":"PPL",
    "gn:name":"Ud\u0113 Karan",
    "gn:population":0,
    "gn:timezone":"Asia/Kolkata",
    "iso:country":"IN",
    "ks:ks_name":"Udekaran",
    "ks:ks_pop":3940,
    "ks:ks_type":"VILLAGE",
    "ks:ks_uagg_main":0,
    "name:eng_x_preferred":[
        "Udekaran"
    ],
    "wof:name":"Udekaran",
    "wof:placetype":"locality",
    "wof:population":3940
},
  "geometry": {"coordinates":[74.54958999999999,30.494856],"type":"Point"}
}