{
  "type": "Feature",
  "properties": {
    "gn:admin1_code":"25.0",
    "gn:admin2_code":"614.0",
    "gn:asciiname":"Karthigaipatti",
    "gn:country_code":"IN",
    "gn:dem":102,
    "gn:feature_class":"P",
    "gn:feature_code":"PPL",
    "gn:name":"Karthigaipatti",
    "gn:population":0,
    "gn:timezone":"Asia/Kolkata",
    "iso:country":"IN",
    "wof:name":"Karthigaipatti",
    "wof:placetype":"locality"
},
  "geometry": {"coordinates":[78.31650999999999,10.99221],"type":"Point"}
}