{
  "type": "Feature",
  "properties": {
    "gn:admin1_code":"2.0",
    "gn:admin2_code":"549.0",
    "gn:asciiname":"Vemulapadu",
    "gn:country_code":"IN",
    "gn:dem":172,
    "gn:feature_class":"P",
    "gn:feature_code":"PPL",
    "gn:name":"Vemulap\u0101du",
    "gn:population":0,
    "gn:timezone":"Asia/Kolkata",
    "iso:country":"IN",
    "wof:name":"Vemulapadu",
    "wof:placetype":"locality"
},
  "geometry": {"coordinates":[79.34019000000001,15.5321],"type":"Point"}
}