{
  "type": "Feature",
  "properties": {
    "iso:country":"IN",
    "ks:ks_name":"Shewrampur",
    "ks:ks_pop":734,
    "ks:ks_type":"VILLAGE",
    "ks:ks_uagg_main":0,
    "name:eng_x_preferred":[
        "Shewrampur"
    ],
    "wof:name":"Shewrampur",
    "wof:placetype":"neighbourhood",
    "wof:population":734
},
  "geometry": {"coordinates":[86.829843,25.170256],"type":"Point"}
}