{
  "type": "Feature",
  "properties": {
    "iso:country":"IN",
    "ks:ks_name":"Poonipeta",
    "ks:ks_pop":264,
    "ks:ks_type":"HABITATION",
    "name:eng_x_preferred":[
        "Poonipeta"
    ],
    "wof:name":"Poonipeta",
    "wof:placetype":"locality",
    "wof:population":264
},
  "geometry": {"coordinates":[83.997732,18.619313],"type":"Point"}
}