{
  "type": "Feature",
  "properties": {
    "gn:admin1_code":"24.0",
    "gn:admin2_code":"130.0",
    "gn:asciiname":"Banal",
    "gn:country_code":"IN",
    "gn:dem":398,
    "gn:feature_class":"P",
    "gn:feature_code":"PPL",
    "gn:name":"Ban\u0101l",
    "gn:population":0,
    "gn:timezone":"Asia/Kolkata",
    "iso:country":"IN",
    "ks:ks_alt_nam":"BANAL",
    "ks:ks_name":"Banal",
    "ks:ks_pop":822,
    "ks:ks_type":"HABITATION",
    "name:ceb_x_preferred":[
        "Banal"
    ],
    "name:deu_x_preferred":[
        "Banal"
    ],
    "name:eng_x_preferred":[
        "Banal"
    ],
    "name:swe_x_preferred":[
        "Banal"
    ],
    "wof:name":"Banal",
    "wof:placetype":"locality",
    "wof:population":822
},
  "geometry": {"coordinates":[73.6735,24.180589],"type":"Point"}
}