{
  "type": "Feature",
  "properties": {
    "iso:country":"IN",
    "ks:ks_name":"Banta",
    "ks:ks_pop":66,
    "ks:ks_type":"VILLAGE",
    "name:eng_x_preferred":[
        "Banta"
    ],
    "wof:name":"Banta",
    "wof:placetype":"locality",
    "wof:population":66
},
  "geometry": {"coordinates":[87.008206,21.58056],"type":"Point"}
}