{
  "type": "Feature",
  "properties": {
    "iso:country":"IN",
    "ks:ks_name":"Thattekkadu",
    "ks:ks_pop":1350,
    "ks:ks_type":"HABITATION",
    "name:eng_x_preferred":[
        "Thattekkadu"
    ],
    "wof:name":"Thattekkadu",
    "wof:placetype":"locality",
    "wof:population":1350
},
  "geometry": {"coordinates":[76.90706299999999,9.326788],"type":"Point"}
}