{
  "type": "Feature",
  "properties": {
    "iso:country":"IN",
    "ks:ks_name":"Aphlepur",
    "ks:ks_pop":1435,
    "ks:ks_type":"VILLAGE",
    "ks:ks_uagg_main":0,
    "name:eng_x_preferred":[
        "Aphlepur"
    ],
    "wof:name":"Aphlepur",
    "wof:placetype":"neighbourhood",
    "wof:population":1435
},
  "geometry": {"coordinates":[82.62500799999999,25.862475],"type":"Point"}
}