{
  "type": "Feature",
  "properties": {
    "gn:admin1_code":"38.0",
    "gn:admin2_code":"351.0",
    "gn:asciiname":"Bhera",
    "gn:country_code":"IN",
    "gn:dem":86,
    "gn:feature_class":"P",
    "gn:feature_code":"PPL",
    "gn:name":"Bhera",
    "gn:population":0,
    "gn:timezone":"Asia/Kolkata",
    "iso:country":"IN",
    "name:cat_x_preferred":[
        "Bhera"
    ],
    "name:ceb_x_preferred":[
        "Bhera"
    ],
    "name:fas_x_preferred":[
        "\u062a\u062d\u0635\u06cc\u0644 \u0628\u0647\u06cc\u0631\u0647"
    ],
    "name:fra_x_preferred":[
        "Bhera"
    ],
    "name:pol_x_preferred":[
        "Bhera"
    ],
    "name:por_x_preferred":[
        "Bhera"
    ],
    "name:swe_x_preferred":[
        "Bhera"
    ],
    "name:urd_x_preferred":[
        "\u0628\u06be\u06cc\u0631\u06c1"
    ],
    "wof:name":"Bhera",
    "wof:placetype":"locality"
},
  "geometry": {"coordinates":[87.24701,24.84106],"type":"Point"}
}