{
  "type": "Feature",
  "properties": {
    "iso:country":"IN",
    "ks:ks_name":"Saharasi Chak",
    "ks:ks_pop":0,
    "ks:ks_type":"VILLAGE",
    "name:eng_x_preferred":[
        "Saharasi Chak"
    ],
    "wof:name":"Saharasi Chak",
    "wof:placetype":"locality",
    "wof:population":0
},
  "geometry": {"coordinates":[83.467269,25.288704],"type":"Point"}
}