{
  "type": "Feature",
  "properties": {
    "gn:admin1_code":"39",
    "gn:admin2_code":"61.0",
    "gn:asciiname":"Naula",
    "gn:country_code":"IN",
    "gn:dem":1335,
    "gn:feature_class":"P",
    "gn:feature_code":"PPL",
    "gn:name":"Naula",
    "gn:population":0,
    "gn:timezone":"Asia/Kolkata",
    "iso:country":"IN",
    "name:sin_x_preferred":[
        "\u0db1\u0dcf\u0d8b\u0dbd"
    ],
    "wof:name":"Naula",
    "wof:placetype":"locality"
},
  "geometry": {"coordinates":[78.8668,29.91615],"type":"Point"}
}