{
  "type": "Feature",
  "properties": {
    "gn:admin1_code":"39",
    "gn:admin2_code":"61.0",
    "gn:asciiname":"Naula",
    "gn:country_code":"IN",
    "gn:dem":1335,
    "gn:feature_class":"P",
    "gn:feature_code":"PPL",
    "gn:name":"Naula",
    "gn:population":0,
    "gn:timezone":"Asia/Kolkata",
    "iso:country":"IN",
    "ks:ks_name":"Naula",
    "ks:ks_pop":63,
    "ks:ks_type":"VILLAGE",
    "name:eng_x_preferred":[
        "Naula"
    ],
    "name:sin_x_preferred":[
        "\u0db1\u0dcf\u0d8b\u0dbd"
    ],
    "wof:name":"Naula",
    "wof:placetype":"locality",
    "wof:population":63
},
  "geometry": {"coordinates":[78.864571,29.916065],"type":"Point"}
}