{
  "type": "Feature",
  "properties": {
    "iso:country":"IN",
    "ks:ks_alt_nam":"MAHKULTOLI",
    "ks:ks_name":"Mahkultoli",
    "ks:ks_pop":267,
    "ks:ks_type":"HABITATION",
    "name:eng_x_preferred":[
        "Mahkultoli"
    ],
    "wof:name":"Mahkultoli",
    "wof:placetype":"locality",
    "wof:population":267
},
  "geometry": {"coordinates":[83.883593,22.544287],"type":"Point"}
}