{
  "type": "Feature",
  "properties": {
    "iso:country":"IN",
    "ks:ks_alt_nam":"HALA PUR",
    "ks:ks_name":"Hala Pur",
    "ks:ks_pop":534,
    "ks:ks_type":"HABITATION",
    "name:eng_x_preferred":[
        "Hala Pur"
    ],
    "wof:name":"Hala Pur",
    "wof:placetype":"locality",
    "wof:population":534
},
  "geometry": {"coordinates":[81.823796,26.166016],"type":"Point"}
}