{
  "type": "Feature",
  "properties": {
    "iso:country":"IN",
    "ks:ks_name":"Lahoripam N",
    "ks:ks_pop":2000,
    "ks:ks_type":"HABITATION",
    "ks:ks_uagg_main":0,
    "name:eng_x_preferred":[
        "Lahoripam N"
    ],
    "wof:name":"Lahoripam N",
    "wof:placetype":"neighbourhood",
    "wof:population":2000
},
  "geometry": {"coordinates":[92.351941,26.34326],"type":"Point"}
}