{
  "type": "Feature",
  "properties": {
    "iso:country":"IN",
    "ks:ks_name":"Bugyanaik T",
    "ks:ks_pop":250,
    "ks:ks_type":"HABITATION",
    "name:eng_x_preferred":[
        "Bugyanaik T"
    ],
    "wof:name":"Bugyanaik T",
    "wof:placetype":"locality",
    "wof:population":250
},
  "geometry": {"coordinates":[77.88386,18.166279],"type":"Point"}
}