{
  "type": "Feature",
  "properties": {
    "gn:admin1_code":"19.0",
    "gn:admin2_code":"577.0",
    "gn:asciiname":"Kuppe",
    "gn:country_code":"IN",
    "gn:dem":787,
    "gn:feature_class":"P",
    "gn:feature_code":"PPL",
    "gn:name":"Kuppe",
    "gn:population":0,
    "gn:timezone":"Asia/Kolkata",
    "iso:country":"IN",
    "wof:name":"Kuppe",
    "wof:placetype":"locality"
},
  "geometry": {"coordinates":[76.40238000000002,12.34561],"type":"Point"}
}