{
  "type": "Feature",
  "properties": {
    "gn:admin1_code":"28.0",
    "gn:admin2_code":"337",
    "gn:asciiname":"Ramapur",
    "gn:country_code":"IN",
    "gn:dem":2,
    "gn:feature_class":"P",
    "gn:feature_code":"PPL",
    "gn:name":"R\u0101mapur",
    "gn:population":0,
    "gn:timezone":"Asia/Kolkata",
    "iso:country":"IN",
    "ks:ks_alt_nam":"R\u0101mapur",
    "ks:ks_name":"Ramapur",
    "ks:ks_pop":5622,
    "ks:ks_type":"VILLAGE",
    "name:eng_x_preferred":[
        "Ramapur"
    ],
    "name:eng_x_variant":[
        "R\u0101mapur"
    ],
    "wof:name":"Ramapur",
    "wof:placetype":"locality",
    "wof:population":5622
},
  "geometry": {"coordinates":[88.951778,22.301531],"type":"Point"}
}