{
  "type": "Feature",
  "properties": {
    "iso:country":"IN",
    "ks:ks_name":"Saliguda",
    "ks:ks_pop":80,
    "ks:ks_type":"HABITATION",
    "name:eng_x_preferred":[
        "Saliguda"
    ],
    "wof:name":"Saliguda",
    "wof:placetype":"locality",
    "wof:population":80
},
  "geometry": {"coordinates":[82.096293,18.651027],"type":"Point"}
}