{
  "type": "Feature",
  "properties": {
    "iso:country":"IN",
    "ks:ks_alt_nam":"pokharia",
    "ks:ks_name":"Pokharia",
    "ks:ks_pop":1144,
    "ks:ks_type":"HABITATION",
    "name:eng_x_preferred":[
        "Pokharia"
    ],
    "wof:name":"Pokharia",
    "wof:placetype":"locality",
    "wof:population":1144
},
  "geometry": {"coordinates":[86.878015,24.119687],"type":"Point"}
}