{
  "type": "Feature",
  "properties": {
    "iso:country":"IN",
    "ks:ks_alt_nam":"KALANDARPUR",
    "ks:ks_name":"Kalandarpur",
    "ks:ks_pop":252,
    "ks:ks_type":"HABITATION",
    "name:eng_x_preferred":[
        "Kalandarpur"
    ],
    "wof:name":"Kalandarpur",
    "wof:placetype":"locality",
    "wof:population":252
},
  "geometry": {"coordinates":[81.446955,27.87513],"type":"Point"}
}