{
  "type": "Feature",
  "properties": {
    "gn:admin1_code":"19.0",
    "gn:admin2_code":"573.0",
    "gn:asciiname":"Biranahalli",
    "gn:country_code":"IN",
    "gn:dem":983,
    "gn:feature_class":"P",
    "gn:feature_code":"PPL",
    "gn:name":"B\u012branahalli",
    "gn:population":0,
    "gn:timezone":"Asia/Kolkata",
    "iso:country":"IN",
    "wof:name":"Biranahalli",
    "wof:placetype":"locality"
},
  "geometry": {"coordinates":[76.64314,12.76615],"type":"Point"}
}