{
  "type": "Feature",
  "properties": {
    "iso:country":"IN",
    "ks:ks_name":"Bishunpura",
    "ks:ks_pop":791,
    "ks:ks_type":"VILLAGE",
    "ks:ks_uagg_main":0,
    "name:eng_x_preferred":[
        "Bishunpura"
    ],
    "wof:name":"Bishunpura",
    "wof:placetype":"neighbourhood",
    "wof:population":791
},
  "geometry": {"coordinates":[84.263094,26.433486],"type":"Point"}
}