{
  "type": "Feature",
  "properties": {
    "iso:country":"IN",
    "ks:ks_name":"Dogiyalon Ki Dhani",
    "ks:ks_pop":65,
    "ks:ks_type":"VILLAGE",
    "name:eng_x_preferred":[
        "Dogiyalon Ki Dhani"
    ],
    "wof:name":"Dogiyalon Ki Dhani",
    "wof:placetype":"locality",
    "wof:population":65
},
  "geometry": {"coordinates":[71.79693899999999,25.746333],"type":"Point"}
}