{
  "type": "Feature",
  "properties": {
    "gn:admin1_code":"36",
    "gn:admin2_code":"150.0",
    "gn:asciiname":"Tisua",
    "gn:country_code":"IN",
    "gn:dem":163,
    "gn:feature_class":"P",
    "gn:feature_code":"PPL",
    "gn:name":"Tisua",
    "gn:population":0,
    "gn:timezone":"Asia/Kolkata",
    "iso:country":"IN",
    "wof:name":"Tisua",
    "wof:placetype":"locality"
},
  "geometry": {"coordinates":[79.6031,28.13619000000001],"type":"Point"}
}