{
  "type": "Feature",
  "properties": {
    "iso:country":"IN",
    "ks:ks_name":"Mundol",
    "ks:ks_pop":1532,
    "ks:ks_type":"HABITATION",
    "name:eng_x_preferred":[
        "Mundol"
    ],
    "wof:name":"Mundol",
    "wof:placetype":"locality",
    "wof:population":1532
},
  "geometry": {"coordinates":[75.149373,12.552334],"type":"Point"}
}