{
  "type": "Feature",
  "properties": {
    "iso:country":"IN",
    "ks:ks_name":"Makodu",
    "ks:ks_pop":46,
    "ks:ks_type":"HABITATION",
    "name:eng_x_preferred":[
        "Makodu"
    ],
    "wof:name":"Makodu",
    "wof:placetype":"locality",
    "wof:population":46
},
  "geometry": {"coordinates":[75.092967,14.004192],"type":"Point"}
}