{
  "type": "Feature",
  "properties": {
    "gn:admin1_code":"24",
    "gn:admin2_code":"119.0",
    "gn:asciiname":"Kalinjar",
    "gn:country_code":"IN",
    "gn:dem":493,
    "gn:feature_class":"P",
    "gn:feature_code":"PPL",
    "gn:name":"K\u0101linjar",
    "gn:population":0,
    "gn:timezone":"Asia/Kolkata",
    "iso:country":"IN",
    "wof:name":"Kalinjar",
    "wof:placetype":"locality"
},
  "geometry": {"coordinates":[74.27083,26.00748],"type":"Point"}
}