{
  "type": "Feature",
  "properties": {
    "iso:country":"IN",
    "ks:ks_name":"Karrivanirevu",
    "ks:ks_pop":1843,
    "ks:ks_type":"HABITATION",
    "name:eng_x_preferred":[
        "Karrivanirevu"
    ],
    "wof:name":"Karrivanirevu",
    "wof:placetype":"locality",
    "wof:population":1843
},
  "geometry": {"coordinates":[82.157678,16.65857],"type":"Point"}
}