{
  "type": "Feature",
  "properties": {
    "iso:country":"IN",
    "ks:ks_name":"Bidarigaruvu",
    "ks:ks_pop":6,
    "ks:ks_type":"HABITATION",
    "name:eng_x_preferred":[
        "Bidarigaruvu"
    ],
    "wof:name":"Bidarigaruvu",
    "wof:placetype":"locality",
    "wof:population":6
},
  "geometry": {"coordinates":[82.85182500000001,18.145686],"type":"Point"}
}