{
  "type": "Feature",
  "properties": {
    "gn:admin1_code":"35",
    "gn:admin2_code":"446.0",
    "gn:asciiname":"Ajayabnagar",
    "gn:country_code":"IN",
    "gn:dem":439,
    "gn:feature_class":"P",
    "gn:feature_code":"PPL",
    "gn:name":"Aj\u0101yabnagar",
    "gn:population":0,
    "gn:timezone":"Asia/Kolkata",
    "iso:country":"IN",
    "ks:ks_name":"Ajayab Nagar",
    "ks:ks_pop":480,
    "ks:ks_type":"HABITATION",
    "name:eng_x_preferred":[
        "Ajayab Nagar"
    ],
    "name:eng_x_variant":[
        "Ajayabnagar"
    ],
    "name:und_x_variant":[
        "Aj\u0101yabnagar",
        "S\u016bnd"
    ],
    "wof:name":"Ajayab Nagar",
    "wof:placetype":"locality",
    "wof:population":480
},
  "geometry": {"coordinates":[77.803147,23.382178],"type":"Point"}
}