{
  "type": "Feature",
  "properties": {
    "gn:admin1_code":"35",
    "gn:admin2_code":"446.0",
    "gn:asciiname":"Ajayabnagar",
    "gn:country_code":"IN",
    "gn:dem":439,
    "gn:feature_class":"P",
    "gn:feature_code":"PPL",
    "gn:name":"Aj\u0101yabnagar",
    "gn:population":0,
    "gn:timezone":"Asia/Kolkata",
    "iso:country":"IN",
    "name:und_x_variant":[
        "Aj\u0101yabnagar",
        "S\u016bnd"
    ],
    "wof:name":"Ajayabnagar",
    "wof:placetype":"locality"
},
  "geometry": {"coordinates":[77.80446999999999,23.38259],"type":"Point"}
}