{
  "type": "Feature",
  "properties": {
    "gn:admin1_code":"19.0",
    "gn:admin2_code":"574.0",
    "gn:asciiname":"Timmayakoppal",
    "gn:country_code":"IN",
    "gn:dem":972,
    "gn:feature_class":"P",
    "gn:feature_code":"PPL",
    "gn:name":"Timm\u0101yakoppal",
    "gn:population":0,
    "gn:timezone":"Asia/Kolkata",
    "iso:country":"IN",
    "wof:name":"Timmayakoppal",
    "wof:placetype":"locality"
},
  "geometry": {"coordinates":[76.09787,13.02334],"type":"Point"}
}