{
  "type": "Feature",
  "properties": {
    "iso:country":"IN",
    "ks:ks_name":"Goatgaria",
    "ks:ks_pop":128,
    "ks:ks_type":"HABITATION",
    "name:eng_x_preferred":[
        "Goatgaria"
    ],
    "wof:name":"Goatgaria",
    "wof:placetype":"locality",
    "wof:population":128
},
  "geometry": {"coordinates":[87.50230500000001,22.366838],"type":"Point"}
}