{
  "type": "Feature",
  "properties": {
    "gn:admin1_code":"25.0",
    "gn:admin2_code":"610.0",
    "gn:asciiname":"Vellakavundanvalasu",
    "gn:country_code":"IN",
    "gn:dem":238,
    "gn:feature_class":"P",
    "gn:feature_code":"PPL",
    "gn:name":"Vellakavundanvalasu",
    "gn:population":0,
    "gn:timezone":"Asia/Kolkata",
    "iso:country":"IN",
    "wof:name":"Vellakavundanvalasu",
    "wof:placetype":"neighbourhood"
},
  "geometry": {"coordinates":[77.70238000000001,11.17956],"type":"Point"}
}