{
  "type": "Feature",
  "properties": {
    "gn:admin1_code":"35",
    "gn:admin2_code":"426.0",
    "gn:asciiname":"Banjari",
    "gn:country_code":"IN",
    "gn:dem":379,
    "gn:feature_class":"P",
    "gn:feature_code":"PPL",
    "gn:name":"Banj\u0101ri",
    "gn:population":0,
    "gn:timezone":"Asia/Kolkata",
    "iso:country":"IN",
    "ks:ks_alt_nam":"Banj\u0101ri",
    "ks:ks_name":"Banjari",
    "ks:ks_pop":284,
    "ks:ks_type":"VILLAGE",
    "name:eng_x_preferred":[
        "Banjari"
    ],
    "name:eng_x_variant":[
        "Banj\u0101ri"
    ],
    "name:tat_x_preferred":[
        "\u0411\u0430\u043d\u0434\u0436\u0430\u0440\u0438"
    ],
    "wof:name":"Banjari",
    "wof:placetype":"locality",
    "wof:population":284
},
  "geometry": {"coordinates":[80.45155099999999,24.121671],"type":"Point"}
}