{
  "type": "Feature",
  "properties": {
    "iso:country":"IN",
    "ks:ks_name":"Musudi",
    "ks:ks_pop":104,
    "ks:ks_type":"VILLAGE",
    "name:eng_x_preferred":[
        "Musudi"
    ],
    "wof:name":"Musudi",
    "wof:placetype":"locality",
    "wof:population":104
},
  "geometry": {"coordinates":[83.391266,19.463503],"type":"Point"}
}