{
  "type": "Feature",
  "properties": {
    "iso:country":"IN",
    "ks:ks_name":"Bathinavaripalle",
    "ks:ks_pop":6,
    "ks:ks_type":"HABITATION",
    "ks:ks_uagg_main":0,
    "name:eng_x_preferred":[
        "Bathinavaripalle"
    ],
    "wof:name":"Bathinavaripalle",
    "wof:placetype":"neighbourhood",
    "wof:population":6
},
  "geometry": {"coordinates":[78.772193,13.601199],"type":"Point"}
}