{
  "type": "Feature",
  "properties": {
    "iso:country":"IN",
    "ks:ks_name":"Halud Bari",
    "ks:ks_pop":2849,
    "ks:ks_type":"VILLAGE",
    "ks:ks_uagg_main":0,
    "name:eng_x_preferred":[
        "Halud Bari"
    ],
    "wof:name":"Halud Bari",
    "wof:placetype":"neighbourhood",
    "wof:population":2849
},
  "geometry": {"coordinates":[87.88691799999999,21.907215],"type":"Point"}
}