{
  "type": "Feature",
  "properties": {
    "iso:country":"IN",
    "ks:ks_name":"Puthimari",
    "ks:ks_pop":1663,
    "ks:ks_type":"VILLAGE",
    "name:eng_x_preferred":[
        "Puthimari"
    ],
    "wof:name":"Puthimari",
    "wof:placetype":"locality",
    "wof:population":1663
},
  "geometry": {"coordinates":[91.142617,26.549315],"type":"Point"}
}