{
  "type": "Feature",
  "properties": {
    "gn:admin1_code":"36",
    "gn:admin2_code":"192.0",
    "gn:asciiname":"Mohan Sarai",
    "gn:country_code":"IN",
    "gn:dem":73,
    "gn:feature_class":"P",
    "gn:feature_code":"PPL",
    "gn:name":"Mohan Sar\u0101i",
    "gn:population":0,
    "gn:timezone":"Asia/Kolkata",
    "iso:country":"IN",
    "wof:name":"Mohan Sarai",
    "wof:placetype":"locality"
},
  "geometry": {"coordinates":[83.74746999999998,25.96608],"type":"Point"}
}