{
  "type": "Feature",
  "properties": {
    "iso:country":"IN",
    "ks:ks_name":"Kathrihalli",
    "ks:ks_pop":250,
    "ks:ks_type":"VILLAGE",
    "name:eng_x_preferred":[
        "Kathrihalli"
    ],
    "wof:name":"Kathrihalli",
    "wof:placetype":"locality",
    "wof:population":250
},
  "geometry": {"coordinates":[77.987566,12.88113],"type":"Point"}
}