{
  "type": "Feature",
  "properties": {
    "gn:admin1_code":"12.0",
    "gn:admin2_code":"006",
    "gn:asciiname":"Paliari",
    "gn:country_code":"IN",
    "gn:dem":781,
    "gn:feature_class":"P",
    "gn:feature_code":"PPL",
    "gn:name":"Paliari",
    "gn:population":0,
    "gn:timezone":"Asia/Kolkata",
    "iso:country":"IN",
    "wof:name":"Paliari",
    "wof:placetype":"locality"
},
  "geometry": {"coordinates":[74.37860000000001,33.2109],"type":"Point"}
}