{
  "type": "Feature",
  "properties": {
    "iso:country":"IN",
    "ks:ks_name":"Nam Tol",
    "ks:ks_pop":286,
    "ks:ks_type":"VILLAGE",
    "name:eng_x_preferred":[
        "Nam Tol"
    ],
    "wof:name":"Nam Tol",
    "wof:placetype":"locality",
    "wof:population":286
},
  "geometry": {"coordinates":[79.407128,30.097222],"type":"Point"}
}