{
  "type": "Feature",
  "properties": {
    "iso:country":"IN",
    "ks:ks_alt_nam":"VAINGOKHAS",
    "ks:ks_name":"Vaingokhas",
    "ks:ks_pop":162,
    "ks:ks_type":"HABITATION",
    "name:eng_x_preferred":[
        "Vaingokhas"
    ],
    "wof:name":"Vaingokhas",
    "wof:placetype":"locality",
    "wof:population":162
},
  "geometry": {"coordinates":[83.272357,23.806429],"type":"Point"}
}