{
  "type": "Feature",
  "properties": {
    "iso:country":"IN",
    "ks:ks_name":"Tilaia",
    "ks:ks_pop":161,
    "ks:ks_type":"VILLAGE",
    "ks:ks_uagg_main":0,
    "name:eng_x_preferred":[
        "Tilaia"
    ],
    "wof:name":"Tilaia",
    "wof:placetype":"neighbourhood",
    "wof:population":161
},
  "geometry": {"coordinates":[86.001909,24.425669],"type":"Point"}
}