{
  "type": "Feature",
  "properties": {
    "iso:country":"IN",
    "ks:ks_name":"Paygani Purwa",
    "ks:ks_pop":100,
    "ks:ks_type":"HABITATION",
    "name:eng_x_preferred":[
        "Paygani Purwa"
    ],
    "wof:name":"Paygani Purwa",
    "wof:placetype":"locality",
    "wof:population":100
},
  "geometry": {"coordinates":[82.458752,27.528878],"type":"Point"}
}