{
  "type": "Feature",
  "properties": {
    "gn:admin1_code":"39.0",
    "gn:admin2_code":"64.0",
    "gn:asciiname":"Golkhal",
    "gn:country_code":"IN",
    "gn:dem":1307,
    "gn:feature_class":"P",
    "gn:feature_code":"PPL",
    "gn:name":"Golkh\u0101l",
    "gn:population":0,
    "gn:timezone":"Asia/Kolkata",
    "iso:country":"IN",
    "ks:ks_alt_nam":"Golkh\u0101l",
    "ks:ks_name":"Golkhal",
    "ks:ks_type":"VILLAGE",
    "name:eng_x_preferred":[
        "Golkhal"
    ],
    "name:eng_x_variant":[
        "Golkh\u0101l"
    ],
    "wof:name":"Golkhal",
    "wof:placetype":"locality"
},
  "geometry": {"coordinates":[79.432689,29.872961],"type":"Point"}
}