{
  "type": "Feature",
  "properties": {
    "gn:admin1_code":"24.0",
    "gn:admin2_code":"130.0",
    "gn:asciiname":"Ondra",
    "gn:country_code":"IN",
    "gn:dem":508,
    "gn:feature_class":"P",
    "gn:feature_code":"PPL",
    "gn:name":"Ondra",
    "gn:population":0,
    "gn:timezone":"Asia/Kolkata",
    "iso:country":"IN",
    "ks:ks_name":"Undra",
    "ks:ks_pop":290,
    "ks:ks_type":"VILLAGE",
    "name:ces_x_preferred":[
        "Ondra"
    ],
    "name:deu_x_preferred":[
        "Ondra"
    ],
    "name:eng_x_preferred":[
        "Undra"
    ],
    "name:eng_x_variant":[
        "Ondra"
    ],
    "name:fra_x_preferred":[
        "Ondra"
    ],
    "name:ita_x_preferred":[
        "Ondra"
    ],
    "name:rus_x_preferred":[
        "\u041e\u043d\u0434\u0440\u0430"
    ],
    "name:ukr_x_preferred":[
        "\u041e\u043d\u0434\u0440\u0430"
    ],
    "wof:name":"Undra",
    "wof:placetype":"locality",
    "wof:population":290
},
  "geometry": {"coordinates":[73.381197,24.4979],"type":"Point"}
}