{
  "type": "Feature",
  "properties": {
    "iso:country":"IN",
    "ks:ks_name":"Baratali",
    "ks:ks_pop":103,
    "ks:ks_type":"VILLAGE",
    "name:eng_x_preferred":[
        "Baratali"
    ],
    "wof:name":"Baratali",
    "wof:placetype":"locality",
    "wof:population":103
},
  "geometry": {"coordinates":[87.36107699999999,24.378142],"type":"Point"}
}