{
  "type": "Feature",
  "properties": {
    "gn:admin1_code":"35.0",
    "gn:admin2_code":"451.0",
    "gn:asciiname":"Mahgawan",
    "gn:country_code":"IN",
    "gn:dem":444,
    "gn:feature_class":"P",
    "gn:feature_code":"PPL",
    "gn:name":"Mahgaw\u0101n",
    "gn:population":0,
    "gn:timezone":"Asia/Kolkata",
    "iso:country":"IN",
    "wof:name":"Mahgawan",
    "wof:placetype":"locality"
},
  "geometry": {"coordinates":[80.11091,23.10882],"type":"Point"}
}