{
  "type": "Feature",
  "properties": {
    "iso:country":"IN",
    "ks:ks_name":"Ranasingipadu",
    "ks:ks_pop":127,
    "ks:ks_type":"HABITATION",
    "name:eng_x_preferred":[
        "Ranasingipadu"
    ],
    "wof:name":"Ranasingipadu",
    "wof:placetype":"locality",
    "wof:population":127
},
  "geometry": {"coordinates":[83.10767300000001,18.60534],"type":"Point"}
}