{
  "type": "Feature",
  "properties": {
    "iso:country":"IN",
    "ks:ks_name":"Tokarepada",
    "ks:ks_pop":128,
    "ks:ks_type":"HABITATION",
    "name:eng_x_preferred":[
        "Tokarepada"
    ],
    "wof:name":"Tokarepada",
    "wof:placetype":"locality",
    "wof:population":128
},
  "geometry": {"coordinates":[73.31444,19.688439],"type":"Point"}
}