{
  "type": "Feature",
  "properties": {
    "gn:admin1_code":"36.0",
    "gn:admin2_code":"149",
    "gn:asciiname":"Nawada Madhkar",
    "gn:country_code":"IN",
    "gn:dem":157,
    "gn:feature_class":"P",
    "gn:feature_code":"PPL",
    "gn:name":"Naw\u0101da Madhkar",
    "gn:population":0,
    "gn:timezone":"Asia/Kolkata",
    "iso:country":"IN",
    "ks:ks_name":"Nabada Madhukar",
    "ks:ks_pop":760,
    "ks:ks_type":"VILLAGE",
    "ks:ks_uagg_main":0,
    "name:eng_x_preferred":[
        "Nabada Madhukar"
    ],
    "wof:name":"Nabada Madhukar",
    "wof:placetype":"neighbourhood",
    "wof:population":760
},
  "geometry": {"coordinates":[79.402202,27.929405],"type":"Point"}
}