{
  "type": "Feature",
  "properties": {
    "gn:admin1_code":"37.0",
    "gn:admin2_code":"416.0",
    "gn:asciiname":"Suganghat",
    "gn:country_code":"IN",
    "gn:dem":251,
    "gn:feature_class":"P",
    "gn:feature_code":"PPL",
    "gn:name":"Suganghat",
    "gn:population":0,
    "gn:timezone":"Asia/Kolkata",
    "iso:country":"IN",
    "ks:ks_name":"Sagunghat",
    "ks:ks_pop":294,
    "ks:ks_type":"VILLAGE",
    "name:eng_x_preferred":[
        "Sagunghat"
    ],
    "name:eng_x_variant":[
        "Suganghat"
    ],
    "wof:name":"Sagunghat",
    "wof:placetype":"locality",
    "wof:population":294
},
  "geometry": {"coordinates":[81.84194100000001,18.699359],"type":"Point"}
}