{
  "type": "Feature",
  "properties": {
    "iso:country":"IN",
    "ks:ks_name":"Kalugasalapuram",
    "ks:ks_pop":330,
    "ks:ks_type":"HABITATION",
    "name:eng_x_preferred":[
        "Kalugasalapuram"
    ],
    "wof:name":"Kalugasalapuram",
    "wof:placetype":"locality",
    "wof:population":330
},
  "geometry": {"coordinates":[77.86390299999999,9.052452],"type":"Point"}
}