{
  "type": "Feature",
  "properties": {
    "iso:country":"IN",
    "ks:ks_alt_nam":"Geeta camp",
    "ks:ks_name":"Geeta Camp",
    "ks:ks_pop":498,
    "ks:ks_type":"HABITATION",
    "name:eng_x_preferred":[
        "Geeta Camp"
    ],
    "wof:name":"Geeta Camp",
    "wof:placetype":"locality",
    "wof:population":498
},
  "geometry": {"coordinates":[76.710003,15.791315],"type":"Point"}
}