{
  "type": "Feature",
  "properties": {
    "iso:country":"IN",
    "ks:ks_name":"Kallar Colony",
    "ks:ks_pop":486,
    "ks:ks_type":"HABITATION",
    "ks:ks_uagg_main":0,
    "name:eng_x_preferred":[
        "Kallar Colony"
    ],
    "wof:name":"Kallar Colony",
    "wof:placetype":"neighbourhood",
    "wof:population":486
},
  "geometry": {"coordinates":[77.014852,9.577647],"type":"Point"}
}