{
  "type": "Feature",
  "properties": {
    "iso:country":"IN",
    "ks:ks_name":"Jalalpur Mafi",
    "ks:ks_pop":0,
    "ks:ks_type":"VILLAGE",
    "name:eng_x_preferred":[
        "Jalalpur Mafi"
    ],
    "wof:name":"Jalalpur Mafi",
    "wof:placetype":"locality",
    "wof:population":0
},
  "geometry": {"coordinates":[78.70609899999999,29.059405],"type":"Point"}
}