{
  "type": "Feature",
  "properties": {
    "gn:admin1_code":"38.0",
    "gn:admin2_code":"347.0",
    "gn:asciiname":"Ghatdhari",
    "gn:country_code":"IN",
    "gn:dem":329,
    "gn:feature_class":"P",
    "gn:feature_code":"PPL",
    "gn:name":"Gh\u0101tdhari",
    "gn:population":0,
    "gn:timezone":"Asia/Kolkata",
    "iso:country":"IN",
    "ks:ks_alt_nam":"Gh\u0101tdhari",
    "ks:ks_name":"Ghatdhari",
    "ks:ks_pop":175,
    "ks:ks_type":"VILLAGE",
    "name:eng_x_preferred":[
        "Ghatdhari"
    ],
    "name:eng_x_variant":[
        "Gh\u0101tdhari"
    ],
    "wof:name":"Ghatdhari",
    "wof:placetype":"locality",
    "wof:population":175
},
  "geometry": {"coordinates":[84.743498,24.286693],"type":"Point"}
}