{
  "type": "Feature",
  "properties": {
    "iso:country":"IN",
    "ks:ks_name":"Nakatitoli",
    "ks:ks_pop":388,
    "ks:ks_type":"HABITATION",
    "name:eng_x_preferred":[
        "Nakatitoli"
    ],
    "wof:name":"Nakatitoli",
    "wof:placetype":"locality",
    "wof:population":388
},
  "geometry": {"coordinates":[84.681588,23.018297],"type":"Point"}
}