{
  "type": "Feature",
  "properties": {
    "gn:admin1_code":"12.0",
    "gn:admin2_code":"004",
    "gn:asciiname":"Kharbu",
    "gn:country_code":"IN",
    "gn:dem":2981,
    "gn:feature_class":"P",
    "gn:feature_code":"PPL",
    "gn:name":"Kharbu",
    "gn:population":0,
    "gn:timezone":"Asia/Kolkata",
    "iso:country":"IN",
    "wof:name":"Kharbu",
    "wof:placetype":"locality"
},
  "geometry": {"coordinates":[75.99365,34.54205],"type":"Point"}
}