{
  "type": "Feature",
  "properties": {
    "iso:country":"IN",
    "ks:ks_name":"Khakarpur Pt V",
    "ks:ks_pop":771,
    "ks:ks_type":"VILLAGE",
    "name:eng_x_preferred":[
        "Khakarpur Pt V"
    ],
    "wof:name":"Khakarpur Pt V",
    "wof:placetype":"locality",
    "wof:population":771
},
  "geometry": {"coordinates":[90.560255,26.373339],"type":"Point"}
}