{
  "type": "Feature",
  "properties": {
    "iso:country":"IN",
    "ks:ks_name":"Malkachiwadi",
    "ks:ks_pop":1216,
    "ks:ks_type":"HABITATION",
    "name:eng_x_preferred":[
        "Malkachiwadi"
    ],
    "wof:name":"Malkachiwadi",
    "wof:placetype":"locality",
    "wof:population":1216
},
  "geometry": {"coordinates":[75.564735,18.961615],"type":"Point"}
}