{
  "type": "Feature",
  "properties": {
    "gn:admin1_code":"36",
    "gn:admin2_code":"185.0",
    "gn:asciiname":"Bhuani Arazi",
    "gn:country_code":"IN",
    "gn:dem":90,
    "gn:feature_class":"P",
    "gn:feature_code":"PPL",
    "gn:name":"Bhuani Ar\u0101zi",
    "gn:population":0,
    "gn:timezone":"Asia/Kolkata",
    "iso:country":"IN",
    "wof:name":"Bhuani Arazi",
    "wof:placetype":"neighbourhood"
},
  "geometry": {"coordinates":[82.79761999999999,26.72702],"type":"Point"}
}