{
  "type": "Feature",
  "properties": {
    "gn:admin1_code":"23.0",
    "gn:admin2_code":"38.0",
    "gn:asciiname":"Ror",
    "gn:country_code":"IN",
    "gn:dem":322,
    "gn:feature_class":"P",
    "gn:feature_code":"PPL",
    "gn:name":"Ror",
    "gn:population":0,
    "gn:timezone":"Asia/Kolkata",
    "iso:country":"IN",
    "wof:name":"Ror",
    "wof:placetype":"locality"
},
  "geometry": {"coordinates":[75.82595999999999,31.69782],"type":"Point"}
}