{
  "type": "Feature",
  "properties": {
    "gn:admin1_code":"36.0",
    "gn:admin2_code":"183.0",
    "gn:asciiname":"Khatikpurwa",
    "gn:country_code":"IN",
    "gn:dem":108,
    "gn:feature_class":"P",
    "gn:feature_code":"PPL",
    "gn:name":"Khat\u012bkpurwa",
    "gn:population":0,
    "gn:timezone":"Asia/Kolkata",
    "iso:country":"IN",
    "wof:name":"Khatikpurwa",
    "wof:placetype":"locality"
},
  "geometry": {"coordinates":[82.07855000000001,27.11422],"type":"Point"}
}