{
  "type": "Feature",
  "properties": {
    "iso:country":"IN",
    "ks:ks_name":"Yetala",
    "ks:ks_pop":7,
    "ks:ks_type":"VILLAGE",
    "name:eng_x_preferred":[
        "Yetala"
    ],
    "wof:name":"Yetala",
    "wof:placetype":"locality",
    "wof:population":7
},
  "geometry": {"coordinates":[78.774693,20.504792],"type":"Point"}
}