{
  "type": "Feature",
  "properties": {
    "iso:country":"IN",
    "ks:ks_alt_nam":"Avli thakar",
    "ks:ks_name":"Avli Thakar",
    "ks:ks_pop":136,
    "ks:ks_type":"HABITATION",
    "ks:ks_uagg_main":0,
    "name:eng_x_preferred":[
        "Avli Thakar"
    ],
    "wof:name":"Avli Thakar",
    "wof:placetype":"neighbourhood",
    "wof:population":136
},
  "geometry": {"coordinates":[73.840278,18.872778],"type":"Point"}
}