{
  "type": "Feature",
  "properties": {
    "iso:country":"IN",
    "ks:ks_name":"Chennareddypally",
    "ks:ks_pop":235,
    "ks:ks_type":"HABITATION",
    "name:eng_x_preferred":[
        "Chennareddypally"
    ],
    "wof:name":"Chennareddypally",
    "wof:placetype":"locality",
    "wof:population":235
},
  "geometry": {"coordinates":[77.98121399999999,17.067494],"type":"Point"}
}