{
  "type": "Feature",
  "properties": {
    "gn:admin1_code":"16.0",
    "gn:admin2_code":"500",
    "gn:asciiname":"Fathkhelda",
    "gn:country_code":"IN",
    "gn:dem":582,
    "gn:feature_class":"P",
    "gn:feature_code":"PPL",
    "gn:name":"Fathkhelda",
    "gn:population":0,
    "gn:timezone":"Asia/Kolkata",
    "iso:country":"IN",
    "wof:name":"Fathkhelda",
    "wof:placetype":"locality"
},
  "geometry": {"coordinates":[76.39823,20.2087],"type":"Point"}
}