{
  "type": "Feature",
  "properties": {
    "iso:country":"IN",
    "ks:ks_name":"Depot",
    "ks:ks_pop":221,
    "ks:ks_type":"HABITATION",
    "name:eng_x_preferred":[
        "Depot"
    ],
    "wof:name":"Depot",
    "wof:placetype":"locality",
    "wof:population":221
},
  "geometry": {"coordinates":[74.58176,14.226044],"type":"Point"}
}