{
  "type": "Feature",
  "properties": {
    "iso:country":"IN",
    "name:ara_x_preferred":[
        "\u0645\u0633\u062a\u0639\u0645\u0631\u0629 \u0628\u0627\u062a\u064a\u0644 \u0646\u0627\u062c\u0627\u0631"
    ],
    "name:ben_bn_x_preferred":[
        "\u09aa\u09cd\u09af\u09be\u099f\u09c7\u09b2 \u09a8\u0997\u09b0 \u0995\u09b2\u09cb\u09a8\u09c0"
    ],
    "name:ben_in_x_preferred":[
        "\u09aa\u09cd\u09af\u09be\u099f\u09c7\u09b2 \u09a8\u0997\u09b0 \u0995\u09b2\u09cb\u09a8\u09c0"
    ],
    "name:eng_x_preferred":[
        "Patel Nagar Colony"
    ],
    "name:guj_x_preferred":[
        "\u0aaa\u0a9f\u0ac7\u0ab2 \u0aa8\u0a97\u0ab0 \u0a95\u0acb\u0ab2\u0acb\u0aa8\u0ac0"
    ],
    "name:hin_x_preferred":[
        "\u092a\u091f\u0947\u0932 \u0928\u0917\u0930 \u0915\u0949\u0932\u094b\u0928\u0940"
    ],
    "name:kan_x_preferred":[
        "\u0caa\u0c9f\u0cc7\u0cb2\u0ccd"
    ],
    "name:mal_x_preferred":[
        "\u0d2a\u0d1f\u0d4d\u0d1f\u0d47\u0d7d \u0d28\u0d17\u0d7c \u0d15\u0d4b\u0d33\u0d28\u0d3f"
    ],
    "name:mar_x_preferred":[
        "\u092a\u091f\u0947\u0932 \u0928\u0917\u0930 \u0915\u0949\u0932\u0928\u0940"
    ],
    "name:pan_x_preferred":[
        "\u0a2a\u0a1f\u0a47\u0a32 \u0a28\u0a17\u0a30 \u0a15\u0a32\u0a4c\u0a28\u0a40"
    ],
    "name:tam_x_preferred":[
        "\u0baa\u0b9f\u0bc7\u0bb2\u0bcd \u0ba8\u0b95\u0bb0\u0bcd \u0b95\u0bc1\u0b9f\u0bbf\u0baf\u0bbf\u0bb0\u0bc1\u0baa\u0bcd\u0baa\u0bc1"
    ],
    "name:tel_x_preferred":[
        "\u0c2a\u0c1f\u0c47\u0c32\u0c4d \u0c28\u0c17\u0c30\u0c4d \u0c15\u0c3e\u0c32\u0c28\u0c40"
    ],
    "name:urd_x_preferred":[
        "\u067e\u0679\u06cc\u0644 \u0646\u06af\u0631 \u06a9\u0627\u0644\u0648\u0646\u06cc"
    ],
    "qs:gn_adm0_cc":"IN",
    "qs:gn_local":1253405,
    "qs:gn_nam_loc":"Varanasi, Varanasi, Uttar Pradesh, IN",
    "qs:gn_namadm1":"36",
    "qs:local_max":11649,
    "qs:local_sum":17228,
    "qs:localhoods":15,
    "qs:name":"Patel Nagar Colony",
    "qs:name_adm0":"India",
    "qs:name_adm1":"Uttar Pradesh",
    "qs:name_adm2":"Varanasi",
    "qs:name_local":"Varanasi",
    "qs:photo_max":27,
    "qs:photo_sum":65,
    "qs:placetype":"Suburb",
    "qs:quad_count":5,
    "qs:woe_adm0":23424848,
    "qs:woe_adm1":2345760,
    "qs:woe_adm2":12586794,
    "qs:woe_lau":0,
    "qs:woe_local":2295380,
    "qs:woe_ver":"7.10.0",
    "wof:lang":[
        "eng"
    ],
    "wof:name":"Patel Nagar Colony",
    "wof:placetype":"neighbourhood"
},
  "geometry": {"coordinates":[82.997131,25.329614],"type":"Point"}
}