{
  "type": "Feature",
  "properties": {
    "iso:country":"IN",
    "name:eng_x_preferred":[
        "Patel Nagar Colony"
    ],
    "name:unk_x_variant":[
        "Patel Nagar Colony"
    ],
    "qs:gn_adm0_cc":"IN",
    "qs:gn_local":1253405,
    "qs:gn_nam_loc":"Varanasi, Varanasi, Uttar Pradesh, IN",
    "qs:gn_namadm1":"36",
    "qs:local_max":11649,
    "qs:local_sum":17228,
    "qs:localhoods":15,
    "qs:name":"Patel Nagar Colony",
    "qs:name_adm0":"India",
    "qs:name_adm1":"Uttar Pradesh",
    "qs:name_adm2":"Varanasi",
    "qs:name_local":"Varanasi",
    "qs:photo_max":27,
    "qs:photo_sum":65,
    "qs:placetype":"Suburb",
    "qs:quad_count":5,
    "qs:woe_adm0":23424848,
    "qs:woe_adm1":2345760,
    "qs:woe_adm2":12586794,
    "qs:woe_lau":0,
    "qs:woe_local":2295380,
    "qs:woe_ver":"7.10.0",
    "wof:lang":[
        "eng"
    ],
    "wof:name":"Patel Nagar Colony",
    "wof:placetype":"neighbourhood"
},
  "geometry": {"coordinates":[82.997131,25.329614],"type":"Point"}
}