{
  "type": "Feature",
  "properties": {
    "iso:country":"IN",
    "ks:ks_name":"Kodaria",
    "ks:ks_pop":1804,
    "ks:ks_type":"VILLAGE",
    "name:eng_x_preferred":[
        "Kodaria"
    ],
    "wof:name":"Kodaria",
    "wof:placetype":"locality",
    "wof:population":1804
},
  "geometry": {"coordinates":[85.05652600000001,26.128217],"type":"Point"}
}