{
  "type": "Feature",
  "properties": {
    "iso:country":"IN",
    "ks:ks_name":"Kottaipatti",
    "ks:ks_pop":410,
    "ks:ks_type":"HABITATION",
    "name:eng_x_preferred":[
        "Kottaipatti"
    ],
    "wof:name":"Kottaipatti",
    "wof:placetype":"locality",
    "wof:population":410
},
  "geometry": {"coordinates":[77.92546299999999,10.298487],"type":"Point"}
}