{
  "type": "Feature",
  "properties": {
    "iso:country":"IN",
    "ks:ks_name":"Ballaputtuga",
    "ks:ks_pop":270,
    "ks:ks_type":"HABITATION",
    "name:eng_x_preferred":[
        "Ballaputtuga"
    ],
    "wof:name":"Ballaputtuga",
    "wof:placetype":"locality",
    "wof:population":270
},
  "geometry": {"coordinates":[84.659265,19.020284],"type":"Point"}
}