{
  "type": "Feature",
  "properties": {
    "gn:admin1_code":"11.0",
    "gn:admin2_code":"32.0",
    "gn:asciiname":"Kuina Katli",
    "gn:country_code":"IN",
    "gn:dem":1000,
    "gn:feature_class":"P",
    "gn:feature_code":"PPL",
    "gn:name":"K\u016bina K\u0101tli",
    "gn:population":0,
    "gn:timezone":"Asia/Kolkata",
    "iso:country":"IN",
    "wof:name":"Kuina Katli",
    "wof:placetype":"locality"
},
  "geometry": {"coordinates":[77.11951999999999,30.74344],"type":"Point"}
}