{
  "type": "Feature",
  "properties": {
    "iso:country":"IN",
    "ks:ks_name":"Chamar Tola East",
    "ks:ks_pop":38,
    "ks:ks_type":"HABITATION",
    "ks:ks_uagg_main":0,
    "name:eng_x_preferred":[
        "Chamar Tola East"
    ],
    "wof:name":"Chamar Tola East",
    "wof:placetype":"neighbourhood",
    "wof:population":38
},
  "geometry": {"coordinates":[85.29567900000001,26.537841],"type":"Point"}
}