{
  "type": "Feature",
  "properties": {
    "gn:admin1_code":"36.0",
    "gn:admin2_code":"154.0",
    "gn:asciiname":"Unai",
    "gn:country_code":"IN",
    "gn:dem":135,
    "gn:feature_class":"P",
    "gn:feature_code":"PPL",
    "gn:name":"Unai",
    "gn:population":0,
    "gn:timezone":"Asia/Kolkata",
    "iso:country":"IN",
    "name:jpn_x_preferred":[
        "\u30a6\u30ca\u30a4"
    ],
    "wof:name":"Unai",
    "wof:placetype":"locality"
},
  "geometry": {"coordinates":[80.88748000000002,27.21517],"type":"Point"}
}