{
  "type": "Feature",
  "properties": {
    "iso:country":"IN",
    "ks:ks_alt_nam":"CHANAHAURA",
    "ks:ks_name":"Chanahaura",
    "ks:ks_pop":1579,
    "ks:ks_type":"HABITATION",
    "name:eng_x_preferred":[
        "Chanahaura"
    ],
    "wof:name":"Chanahaura",
    "wof:placetype":"locality",
    "wof:population":1579
},
  "geometry": {"coordinates":[84.54461999999999,25.927798],"type":"Point"}
}