{
  "type": "Feature",
  "properties": {
    "gn:admin1_code":"09",
    "gn:admin2_code":"469.0",
    "gn:asciiname":"Mudetha",
    "gn:country_code":"IN",
    "gn:dem":101,
    "gn:feature_class":"P",
    "gn:feature_code":"PPL",
    "gn:name":"Mudetha",
    "gn:population":0,
    "gn:timezone":"Asia/Kolkata",
    "iso:country":"IN",
    "wof:name":"Mudetha",
    "wof:placetype":"locality"
},
  "geometry": {"coordinates":[71.98196,24.15023],"type":"Point"}
}