{
  "type": "Feature",
  "properties": {
    "iso:country":"IN",
    "ks:ks_name":"Kuandaudi",
    "ks:ks_pop":64,
    "ks:ks_type":"VILLAGE",
    "name:eng_x_preferred":[
        "Kuandaudi"
    ],
    "wof:name":"Kuandaudi",
    "wof:placetype":"locality",
    "wof:population":64
},
  "geometry": {"coordinates":[83.68406400000001,19.64882],"type":"Point"}
}