{
  "type": "Feature",
  "properties": {
    "gn:admin1_code":"25.0",
    "gn:admin2_code":"631.0",
    "gn:asciiname":"Periyakamakshippatti",
    "gn:country_code":"IN",
    "gn:dem":407,
    "gn:feature_class":"P",
    "gn:feature_code":"PPL",
    "gn:name":"Periyak\u0101m\u0101kshippatti",
    "gn:population":0,
    "gn:timezone":"Asia/Kolkata",
    "iso:country":"IN",
    "wof:name":"Periyakamakshippatti",
    "wof:placetype":"locality"
},
  "geometry": {"coordinates":[78.36766999999998,12.24585],"type":"Point"}
}