{
  "type": "Feature",
  "properties": {
    "iso:country":"IN",
    "ks:ks_name":"Kallal",
    "ks:ks_pop":1689,
    "ks:ks_type":"HABITATION",
    "name:eng_x_preferred":[
        "Kallal"
    ],
    "wof:name":"Kallal",
    "wof:placetype":"locality",
    "wof:population":1689
},
  "geometry": {"coordinates":[74.798267,16.709592],"type":"Point"}
}