{
  "type": "Feature",
  "properties": {
    "iso:country":"IN",
    "ks:ks_name":"Kattur",
    "ks:ks_pop":1673,
    "ks:ks_type":"HABITATION",
    "ks:ks_uagg_main":0,
    "name:eng_x_preferred":[
        "Kattur"
    ],
    "wof:name":"Kattur",
    "wof:placetype":"neighbourhood",
    "wof:population":1673
},
  "geometry": {"coordinates":[78.856208,10.892408],"type":"Point"}
}