{
  "type": "Feature",
  "properties": {
    "iso:country":"IN",
    "ks:ks_name":"Pokhaiwala",
    "ks:ks_pop":36,
    "ks:ks_type":"VILLAGE",
    "name:eng_x_preferred":[
        "Pokhaiwala"
    ],
    "wof:name":"Pokhaiwala",
    "wof:placetype":"locality",
    "wof:population":36
},
  "geometry": {"coordinates":[81.703046,24.763461],"type":"Point"}
}