{
  "type": "Feature",
  "properties": {
    "iso:country":"IN",
    "ks:ks_name":"Madaya",
    "ks:ks_pop":375,
    "ks:ks_type":"HABITATION",
    "name:eng_x_preferred":[
        "Madaya"
    ],
    "wof:name":"Madaya",
    "wof:placetype":"locality",
    "wof:population":375
},
  "geometry": {"coordinates":[82.86419600000001,25.206412],"type":"Point"}
}