{
  "type": "Feature",
  "properties": {
    "iso:country":"IN",
    "ks:ks_name":"Uppar Vasti",
    "ks:ks_pop":153,
    "ks:ks_type":"HABITATION",
    "name:eng_x_preferred":[
        "Uppar Vasti"
    ],
    "wof:name":"Uppar Vasti",
    "wof:placetype":"locality",
    "wof:population":153
},
  "geometry": {"coordinates":[75.76179399999999,17.055737],"type":"Point"}
}