{
  "type": "Feature",
  "properties": {
    "gn:admin1_code":"36",
    "gn:admin2_code":"158.0",
    "gn:asciiname":"Nagdaiyapur",
    "gn:country_code":"IN",
    "gn:dem":112,
    "gn:feature_class":"P",
    "gn:feature_code":"PPL",
    "gn:name":"Nagdaiy\u0101pur",
    "gn:population":0,
    "gn:timezone":"Asia/Kolkata",
    "iso:country":"IN",
    "ks:ks_name":"Nakdaiyapur",
    "ks:ks_pop":540,
    "ks:ks_type":"VILLAGE",
    "ks:ks_uagg_main":0,
    "name:eng_x_preferred":[
        "Nakdaiyapur"
    ],
    "wof:name":"Nakdaiyapur",
    "wof:placetype":"neighbourhood",
    "wof:population":540
},
  "geometry": {"coordinates":[81.56301999999999,26.24463],"type":"Point"}
}