{
  "type": "Feature",
  "properties": {
    "gn:admin1_code":"37.0",
    "gn:admin2_code":"414.0",
    "gn:asciiname":"Jorekera",
    "gn:country_code":"IN",
    "gn:dem":657,
    "gn:feature_class":"P",
    "gn:feature_code":"PPL",
    "gn:name":"Jorekera",
    "gn:population":0,
    "gn:timezone":"Asia/Kolkata",
    "iso:country":"IN",
    "ks:ks_name":"Jodekera",
    "ks:ks_pop":601,
    "ks:ks_type":"VILLAGE",
    "name:eng_x_preferred":[
        "Jodekera"
    ],
    "name:eng_x_variant":[
        "Jorekera"
    ],
    "wof:name":"Jodekera",
    "wof:placetype":"locality",
    "wof:population":601
},
  "geometry": {"coordinates":[81.797603,19.894042],"type":"Point"}
}