{
  "type": "Feature",
  "properties": {
    "iso:country":"IN",
    "ks:ks_alt_nam":"B.KOTHAPALLEVODDEPALLE",
    "ks:ks_name":"B.kothapallevoddepalle",
    "ks:ks_pop":220,
    "ks:ks_type":"HABITATION",
    "ks:ks_uagg_main":0,
    "name:eng_x_preferred":[
        "B.kothapallevoddepalle"
    ],
    "wof:name":"B.kothapallevoddepalle",
    "wof:placetype":"neighbourhood",
    "wof:population":220
},
  "geometry": {"coordinates":[78.787592,13.868199],"type":"Point"}
}