{
  "type": "Feature",
  "properties": {
    "iso:country":"IN",
    "ks:ks_name":"Bhelki Khurd",
    "ks:ks_pop":1207,
    "ks:ks_type":"VILLAGE",
    "name:eng_x_preferred":[
        "Bhelki Khurd"
    ],
    "wof:name":"Bhelki Khurd",
    "wof:placetype":"locality",
    "wof:population":1207
},
  "geometry": {"coordinates":[81.78700600000001,24.438819],"type":"Point"}
}