{
  "type": "Feature",
  "properties": {
    "iso:country":"IN",
    "ks:ks_name":"Pajeeru Guttu",
    "ks:ks_pop":500,
    "ks:ks_type":"HABITATION",
    "name:eng_x_preferred":[
        "Pajeeru Guttu"
    ],
    "wof:name":"Pajeeru Guttu",
    "wof:placetype":"locality",
    "wof:population":500
},
  "geometry": {"coordinates":[74.94268700000001,12.833944],"type":"Point"}
}