{
  "type": "Feature",
  "properties": {
    "gn:admin1_code":"12.0",
    "gn:asciiname":"Ahweiba",
    "gn:country_code":"IN",
    "gn:dem":2654,
    "gn:feature_class":"P",
    "gn:feature_code":"PPL",
    "gn:name":"Ahweiba",
    "gn:population":0,
    "gn:timezone":"Asia/Kolkata",
    "iso:country":"IN",
    "wof:name":"Ahweiba",
    "wof:placetype":"locality"
},
  "geometry": {"coordinates":[75.04167,34.55833],"type":"Point"}
}