{
  "type": "Feature",
  "properties": {
    "iso:country":"IN",
    "ks:ks_name":"Sunar Gaon",
    "ks:ks_pop":412,
    "ks:ks_type":"VILLAGE",
    "name:eng_x_preferred":[
        "Sunar Gaon"
    ],
    "wof:name":"Sunar Gaon",
    "wof:placetype":"locality",
    "wof:population":412
},
  "geometry": {"coordinates":[79.050608,30.099462],"type":"Point"}
}