{
  "type": "Feature",
  "properties": {
    "gn:admin1_code":"35",
    "gn:admin2_code":"437.0",
    "gn:asciiname":"Taklikhera",
    "gn:country_code":"IN",
    "gn:dem":316,
    "gn:feature_class":"P",
    "gn:feature_code":"PPL",
    "gn:name":"T\u0101klikhera",
    "gn:population":0,
    "gn:timezone":"Asia/Kolkata",
    "iso:country":"IN",
    "ks:ks_name":"Takalikheda",
    "ks:ks_pop":653,
    "ks:ks_type":"VILLAGE",
    "name:eng_x_preferred":[
        "Takalikheda"
    ],
    "name:eng_x_variant":[
        "Taklikhera"
    ],
    "wof:name":"Takalikheda",
    "wof:placetype":"locality",
    "wof:population":653
},
  "geometry": {"coordinates":[76.831366,22.637132],"type":"Point"}
}