{
  "type": "Feature",
  "properties": {
    "iso:country":"IN",
    "ks:ks_name":"Subdi",
    "ks:ks_pop":5615,
    "ks:ks_type":"VILLAGE",
    "ks:ks_uagg_main":0,
    "name:eng_x_preferred":[
        "Subdi"
    ],
    "wof:name":"Subdi",
    "wof:placetype":"neighbourhood",
    "wof:population":5615
},
  "geometry": {"coordinates":[87.88200999999999,21.970273],"type":"Point"}
}