{
  "type": "Feature",
  "properties": {
    "iso:country":"IN",
    "ks:ks_name":"Muksudpur",
    "ks:ks_pop":290,
    "ks:ks_type":"VILLAGE",
    "name:eng_x_preferred":[
        "Muksudpur"
    ],
    "wof:name":"Muksudpur",
    "wof:placetype":"locality",
    "wof:population":290
},
  "geometry": {"coordinates":[87.623913,22.26191],"type":"Point"}
}