{
  "type": "Feature",
  "properties": {
    "iso:country":"IN",
    "ks:ks_name":"Baraha Kalan",
    "ks:ks_pop":353,
    "ks:ks_type":"VILLAGE",
    "name:eng_x_preferred":[
        "Baraha Kalan"
    ],
    "wof:name":"Baraha Kalan",
    "wof:placetype":"locality",
    "wof:population":353
},
  "geometry": {"coordinates":[81.160883,24.875151],"type":"Point"}
}