{
  "type": "Feature",
  "properties": {
    "gn:admin1_code":"23",
    "gn:admin2_code":"38.0",
    "gn:asciiname":"Haler",
    "gn:country_code":"IN",
    "gn:dem":405,
    "gn:feature_class":"P",
    "gn:feature_code":"PPL",
    "gn:name":"Haler",
    "gn:population":0,
    "gn:timezone":"Asia/Kolkata",
    "iso:country":"IN",
    "name:ceb_x_preferred":[
        "Haler"
    ],
    "name:fra_x_preferred":[
        "Haler"
    ],
    "name:lim_x_preferred":[
        "Haalder"
    ],
    "name:nld_x_preferred":[
        "Haler"
    ],
    "wof:name":"Haler",
    "wof:placetype":"locality"
},
  "geometry": {"coordinates":[75.88878000000003,31.92917000000001],"type":"Point"}
}