{
  "type": "Feature",
  "properties": {
    "iso:country":"IN",
    "ks:ks_alt_nam":"PUJARIMALA",
    "ks:ks_name":"Pujarimala",
    "ks:ks_pop":85,
    "ks:ks_type":"HABITATION",
    "name:eng_x_preferred":[
        "Pujarimala"
    ],
    "wof:name":"Pujarimala",
    "wof:placetype":"locality",
    "wof:population":85
},
  "geometry": {"coordinates":[74.767656,17.229565],"type":"Point"}
}