{
  "type": "Feature",
  "properties": {
    "iso:country":"IN",
    "ks:ks_name":"Nunamati No. I",
    "ks:ks_pop":14,
    "ks:ks_type":"HABITATION",
    "name:eng_x_preferred":[
        "Nunamati No. I"
    ],
    "wof:name":"Nunamati No. I",
    "wof:placetype":"locality",
    "wof:population":14
},
  "geometry": {"coordinates":[87.064682,24.314813],"type":"Point"}
}