{
  "type": "Feature",
  "properties": {
    "iso:country":"IN",
    "ks:ks_name":"Sarnoo Chimanji",
    "ks:ks_pop":1150,
    "ks:ks_type":"VILLAGE",
    "name:eng_x_preferred":[
        "Sarnoo Chimanji"
    ],
    "wof:name":"Sarnoo Chimanji",
    "wof:placetype":"locality",
    "wof:population":1150
},
  "geometry": {"coordinates":[71.714364,25.642133],"type":"Point"}
}