{
  "type": "Feature",
  "properties": {
    "iso:country":"IN",
    "ks:ks_name":"Dhadhad Chak",
    "ks:ks_pop":83,
    "ks:ks_type":"VILLAGE",
    "name:eng_x_preferred":[
        "Dhadhad Chak"
    ],
    "wof:name":"Dhadhad Chak",
    "wof:placetype":"locality",
    "wof:population":83
},
  "geometry": {"coordinates":[79.032544,30.277181],"type":"Point"}
}