{
  "type": "Feature",
  "properties": {
    "gn:admin1_code":"12.0",
    "gn:admin2_code":"7.0",
    "gn:asciiname":"Kukhwai",
    "gn:country_code":"IN",
    "gn:dem":1302,
    "gn:feature_class":"P",
    "gn:feature_code":"PPL",
    "gn:name":"Kukhwai",
    "gn:population":0,
    "gn:timezone":"Asia/Kolkata",
    "iso:country":"IN",
    "wof:name":"Kukhwai",
    "wof:placetype":"locality"
},
  "geometry": {"coordinates":[75.65038,32.70027],"type":"Point"}
}