{
  "type": "Feature",
  "properties": {
    "iso:country":"IN",
    "ks:ks_name":"Misari Yado",
    "ks:ks_pop":1385,
    "ks:ks_type":"VILLAGE",
    "name:eng_x_preferred":[
        "Misari Yado"
    ],
    "wof:name":"Misari Yado",
    "wof:placetype":"locality",
    "wof:population":1385
},
  "geometry": {"coordinates":[69.78728099999999,23.633958],"type":"Point"}
}