{
  "type": "Feature",
  "properties": {
    "iso:country":"IN",
    "ks:ks_name":"Gojegaon",
    "ks:ks_pop":0,
    "ks:ks_type":"VILLAGE",
    "name:eng_x_preferred":[
        "Gojegaon"
    ],
    "wof:name":"Gojegaon",
    "wof:placetype":"locality",
    "wof:population":0
},
  "geometry": {"coordinates":[73.79826,17.448324],"type":"Point"}
}