{
  "type": "Feature",
  "properties": {
    "iso:country":"IN",
    "ks:ks_name":"Khaliabahal",
    "ks:ks_pop":180,
    "ks:ks_type":"HABITATION",
    "name:eng_x_preferred":[
        "Khaliabahal"
    ],
    "wof:name":"Khaliabahal",
    "wof:placetype":"locality",
    "wof:population":180
},
  "geometry": {"coordinates":[83.70383,21.843135],"type":"Point"}
}