{
  "type": "Feature",
  "properties": {
    "gn:admin1_code":"3.0",
    "gn:admin2_code":"306.0",
    "gn:asciiname":"Ghahigaon",
    "gn:country_code":"IN",
    "gn:dem":83,
    "gn:feature_class":"P",
    "gn:feature_code":"PPL",
    "gn:name":"Gh\u0101hig\u0101on",
    "gn:population":0,
    "gn:timezone":"Asia/Kolkata",
    "iso:country":"IN",
    "wof:name":"Ghahigaon",
    "wof:placetype":"locality"
},
  "geometry": {"coordinates":[93.51978,26.8292],"type":"Point"}
}