{
  "type": "Feature",
  "properties": {
    "iso:country":"IN",
    "ks:ks_name":"Malebail",
    "ks:ks_pop":248,
    "ks:ks_type":"HABITATION",
    "name:eng_x_preferred":[
        "Malebail"
    ],
    "wof:name":"Malebail",
    "wof:placetype":"locality",
    "wof:population":248
},
  "geometry": {"coordinates":[74.751688,16.101094],"type":"Point"}
}