{
  "type": "Feature",
  "properties": {
    "iso:country":"IN",
    "ks:ks_name":"Rampur Bhaso",
    "ks:ks_pop":97,
    "ks:ks_type":"VILLAGE",
    "ks:ks_uagg_main":0,
    "name:eng_x_preferred":[
        "Rampur Bhaso"
    ],
    "wof:name":"Rampur Bhaso",
    "wof:placetype":"neighbourhood",
    "wof:population":97
},
  "geometry": {"coordinates":[81.609227,25.912515],"type":"Point"}
}