{
  "type": "Feature",
  "properties": {
    "iso:country":"IN",
    "ks:ks_name":"Belagadia",
    "ks:ks_pop":247,
    "ks:ks_type":"VILLAGE",
    "name:eng_x_preferred":[
        "Belagadia"
    ],
    "wof:name":"Belagadia",
    "wof:placetype":"locality",
    "wof:population":247
},
  "geometry": {"coordinates":[86.450666,21.254242],"type":"Point"}
}