{
  "type": "Feature",
  "properties": {
    "gn:admin1_code":"25.0",
    "gn:admin2_code":"620.0",
    "gn:asciiname":"Tiruvaiyattukkudi",
    "gn:country_code":"IN",
    "gn:dem":34,
    "gn:feature_class":"P",
    "gn:feature_code":"PPL",
    "gn:name":"Tiruvaiy\u0101ttukkudi",
    "gn:population":0,
    "gn:timezone":"Asia/Kolkata",
    "iso:country":"IN",
    "ks:ks_name":"Thiruvaiyathukudi",
    "ks:ks_pop":388,
    "ks:ks_type":"VILLAGE",
    "name:eng_x_preferred":[
        "Thiruvaiyathukudi"
    ],
    "name:eng_x_variant":[
        "Tiruvaiyattukkudi"
    ],
    "wof:name":"Thiruvaiyathukudi",
    "wof:placetype":"locality",
    "wof:population":388
},
  "geometry": {"coordinates":[79.25962800000001,10.902382],"type":"Point"}
}