{
  "type": "Feature",
  "properties": {
    "gn:admin1_code":"25.0",
    "gn:admin2_code":"620.0",
    "gn:asciiname":"Tiruvaiyattukkudi",
    "gn:country_code":"IN",
    "gn:dem":34,
    "gn:feature_class":"P",
    "gn:feature_code":"PPL",
    "gn:name":"Tiruvaiy\u0101ttukkudi",
    "gn:population":0,
    "gn:timezone":"Asia/Kolkata",
    "iso:country":"IN",
    "wof:name":"Tiruvaiyattukkudi",
    "wof:placetype":"locality"
},
  "geometry": {"coordinates":[79.25735999999998,10.90062],"type":"Point"}
}