{
  "type": "Feature",
  "properties": {
    "gn:admin1_code":"40",
    "gn:admin2_code":"539.0",
    "gn:asciiname":"Pillalamarri",
    "gn:country_code":"IN",
    "gn:dem":186,
    "gn:feature_class":"P",
    "gn:feature_code":"PPL",
    "gn:name":"Pillalamarri",
    "gn:population":0,
    "gn:timezone":"Asia/Kolkata",
    "iso:country":"IN",
    "name:mal_x_preferred":[
        "\u0d2a\u0d3f\u0d32\u0d4d\u0d32\u0d32\u0d2e\u0d3e\u0d30\u0d3f"
    ],
    "name:tel_x_preferred":[
        "\u0c2a\u0c3f\u0c32\u0c4d\u0c32\u0c32\u0c2e\u0c30\u0c4d\u0c30\u0c3f"
    ],
    "wof:name":"Pillalamarri",
    "wof:placetype":"locality"
},
  "geometry": {"coordinates":[79.58365999999999,17.1688],"type":"Point"}
}