{
  "type": "Feature",
  "properties": {
    "gn:admin1_code":"37.0",
    "gn:admin2_code":"417.0",
    "gn:asciiname":"Regalgura",
    "gn:country_code":"IN",
    "gn:dem":123,
    "gn:feature_class":"P",
    "gn:feature_code":"PPL",
    "gn:name":"Regalgura",
    "gn:population":0,
    "gn:timezone":"Asia/Kolkata",
    "iso:country":"IN",
    "ks:ks_name":"Regalgura",
    "ks:ks_type":"VILLAGE",
    "name:eng_x_preferred":[
        "Regalgura"
    ],
    "wof:name":"Regalgura",
    "wof:placetype":"locality"
},
  "geometry": {"coordinates":[80.27171800000001,18.733886],"type":"Point"}
}