{
  "type": "Feature",
  "properties": {
    "gn:admin1_code":"12",
    "gn:asciiname":"Bela Salamabad",
    "gn:country_code":"IN",
    "gn:dem":1553,
    "gn:feature_class":"P",
    "gn:feature_code":"PPL",
    "gn:name":"Bela Sal\u0101m\u0101b\u0101d",
    "gn:population":0,
    "gn:timezone":"Asia/Kolkata",
    "iso:country":"IN",
    "wof:name":"Bela Salamabad",
    "wof:placetype":"locality"
},
  "geometry": {"coordinates":[74.18791999999998,34.1227],"type":"Point"}
}