{
  "type": "Feature",
  "properties": {
    "iso:country":"IN",
    "ks:ks_name":"Ghuthiya",
    "ks:ks_pop":471,
    "ks:ks_type":"VILLAGE",
    "ks:ks_uagg_main":0,
    "name:eng_x_preferred":[
        "Ghuthiya"
    ],
    "wof:name":"Ghuthiya",
    "wof:placetype":"neighbourhood",
    "wof:population":471
},
  "geometry": {"coordinates":[85.2636,23.249117],"type":"Point"}
}