{
  "type": "Feature",
  "properties": {
    "iso:country":"IN",
    "ks:ks_name":"Narayanalanka",
    "ks:ks_pop":374,
    "ks:ks_type":"HABITATION",
    "name:eng_x_preferred":[
        "Narayanalanka"
    ],
    "wof:name":"Narayanalanka",
    "wof:placetype":"locality",
    "wof:population":374
},
  "geometry": {"coordinates":[81.925337,16.704418],"type":"Point"}
}