{
  "type": "Feature",
  "properties": {
    "iso:country":"IN",
    "ks:ks_name":"Sonarwadi",
    "ks:ks_pop":28,
    "ks:ks_type":"HABITATION",
    "name:eng_x_preferred":[
        "Sonarwadi"
    ],
    "wof:name":"Sonarwadi",
    "wof:placetype":"locality",
    "wof:population":28
},
  "geometry": {"coordinates":[73.39511899999999,17.669506],"type":"Point"}
}