{
  "type": "Feature",
  "properties": {
    "gn:admin1_code":"36",
    "gn:admin2_code":"199.0",
    "gn:asciiname":"Shukla",
    "gn:country_code":"IN",
    "gn:dem":86,
    "gn:feature_class":"P",
    "gn:feature_code":"PPL",
    "gn:name":"Shukla",
    "gn:population":0,
    "gn:timezone":"Asia/Kolkata",
    "iso:country":"IN",
    "name:deu_x_preferred":[
        "Shukla"
    ],
    "wof:name":"Shukla",
    "wof:placetype":"neighbourhood"
},
  "geometry": {"coordinates":[82.58056999999999,25.13462],"type":"Point"}
}