{
  "type": "Feature",
  "properties": {
    "gn:admin1_code":"39",
    "gn:admin2_code":"58.0",
    "gn:asciiname":"Khorkhi Talla",
    "gn:country_code":"IN",
    "gn:dem":2419,
    "gn:feature_class":"P",
    "gn:feature_code":"PPL",
    "gn:name":"Khorkhi Talla",
    "gn:population":0,
    "gn:timezone":"Asia/Kolkata",
    "iso:country":"IN",
    "wof:name":"Khorkhi Talla",
    "wof:placetype":"locality"
},
  "geometry": {"coordinates":[79.14560999999998,30.55826],"type":"Point"}
}