{
  "type": "Feature",
  "properties": {
    "gn:admin1_code":"35",
    "gn:admin2_code":"429.0",
    "gn:asciiname":"Panihai",
    "gn:country_code":"IN",
    "gn:dem":523,
    "gn:feature_class":"P",
    "gn:feature_code":"PPL",
    "gn:name":"Panih\u0101i",
    "gn:population":0,
    "gn:timezone":"Asia/Kolkata",
    "iso:country":"IN",
    "ks:ks_alt_nam":"Panih\u0101i",
    "ks:ks_name":"Panihai",
    "ks:ks_pop":245,
    "ks:ks_type":"VILLAGE",
    "name:eng_x_preferred":[
        "Panihai"
    ],
    "name:eng_x_variant":[
        "Panih\u0101i"
    ],
    "wof:name":"Panihai",
    "wof:placetype":"locality",
    "wof:population":245
},
  "geometry": {"coordinates":[80.60992400000001,24.227397],"type":"Point"}
}