{
  "type": "Feature",
  "properties": {
    "iso:country":"IN",
    "ks:ks_name":"Kakati Suba",
    "ks:ks_pop":209,
    "ks:ks_type":"HABITATION",
    "name:eng_x_preferred":[
        "Kakati Suba"
    ],
    "wof:name":"Kakati Suba",
    "wof:placetype":"locality",
    "wof:population":209
},
  "geometry": {"coordinates":[91.793644,26.343151],"type":"Point"}
}