{
  "type": "Feature",
  "properties": {
    "iso:country":"IN",
    "ks:ks_alt_nam":"Bhil Was II",
    "ks:ks_name":"Bhil Was Ii",
    "ks:ks_pop":146,
    "ks:ks_type":"HABITATION",
    "name:eng_x_preferred":[
        "Bhil Was Ii"
    ],
    "wof:name":"Bhil Was Ii",
    "wof:placetype":"locality",
    "wof:population":146
},
  "geometry": {"coordinates":[72.809264,24.524028],"type":"Point"}
}