{
  "type": "Feature",
  "properties": {
    "gn:admin1_code":"12.0",
    "gn:asciiname":"Manglat",
    "gn:country_code":"IN",
    "gn:dem":957,
    "gn:feature_class":"P",
    "gn:feature_code":"PPL",
    "gn:name":"Mangl\u0101t",
    "gn:population":0,
    "gn:timezone":"Asia/Kolkata",
    "iso:country":"IN",
    "name:und_x_variant":[
        "Mangl\u0101t",
        "Mangi\u0101l"
    ],
    "wof:name":"Manglat",
    "wof:placetype":"locality"
},
  "geometry": {"coordinates":[74.06111,33.21944000000001],"type":"Point"}
}