{
  "type": "Feature",
  "properties": {
    "iso:country":"IN",
    "ks:ks_name":"Bhanwatola",
    "ks:ks_pop":156,
    "ks:ks_type":"HABITATION",
    "name:eng_x_preferred":[
        "Bhanwatola"
    ],
    "wof:name":"Bhanwatola",
    "wof:placetype":"locality",
    "wof:population":156
},
  "geometry": {"coordinates":[83.158365,24.521622],"type":"Point"}
}