{
  "type": "Feature",
  "properties": {
    "gn:admin1_code":"16",
    "gn:admin2_code":"523.0",
    "gn:asciiname":"Adalgaon",
    "gn:country_code":"IN",
    "gn:dem":609,
    "gn:feature_class":"P",
    "gn:feature_code":"PPL",
    "gn:name":"\u0100dalgaon",
    "gn:population":0,
    "gn:timezone":"Asia/Kolkata",
    "iso:country":"IN",
    "wof:name":"Adalgaon",
    "wof:placetype":"locality"
},
  "geometry": {"coordinates":[76.46659,18.52131],"type":"Point"}
}