{
  "type": "Feature",
  "properties": {
    "iso:country":"IN",
    "ks:ks_name":"Ramsaranpurwa",
    "ks:ks_pop":157,
    "ks:ks_type":"HABITATION",
    "ks:ks_uagg_main":0,
    "name:eng_x_preferred":[
        "Ramsaranpurwa"
    ],
    "wof:name":"Ramsaranpurwa",
    "wof:placetype":"neighbourhood",
    "wof:population":157
},
  "geometry": {"coordinates":[81.319737,27.331083],"type":"Point"}
}