{
  "type": "Feature",
  "properties": {
    "iso:country":"IN",
    "ks:ks_name":"Dehati",
    "ks:ks_pop":758,
    "ks:ks_type":"VILLAGE",
    "name:eng_x_preferred":[
        "Dehati"
    ],
    "wof:name":"Dehati",
    "wof:placetype":"locality",
    "wof:population":758
},
  "geometry": {"coordinates":[87.754448,22.425483],"type":"Point"}
}