{
  "type": "Feature",
  "properties": {
    "iso:country":"IN",
    "ks:ks_name":"Kolgarh",
    "ks:ks_pop":67,
    "ks:ks_type":"HABITATION",
    "name:eng_x_preferred":[
        "Kolgarh"
    ],
    "wof:name":"Kolgarh",
    "wof:placetype":"locality",
    "wof:population":67
},
  "geometry": {"coordinates":[81.027259,24.118521],"type":"Point"}
}