{
  "type": "Feature",
  "properties": {
    "iso:country":"IN",
    "ks:ks_name":"Jagannathpura",
    "ks:ks_pop":685,
    "ks:ks_type":"VILLAGE",
    "name:eng_x_preferred":[
        "Jagannathpura"
    ],
    "wof:name":"Jagannathpura",
    "wof:placetype":"locality",
    "wof:population":685
},
  "geometry": {"coordinates":[75.636256,21.719494],"type":"Point"}
}