{
  "type": "Feature",
  "properties": {
    "iso:country":"IN",
    "ks:ks_name":"Baragadia",
    "ks:ks_pop":211,
    "ks:ks_type":"VILLAGE",
    "name:eng_x_preferred":[
        "Baragadia"
    ],
    "wof:name":"Baragadia",
    "wof:placetype":"locality",
    "wof:population":211
},
  "geometry": {"coordinates":[84.59742300000001,21.552321],"type":"Point"}
}