{
  "type": "Feature",
  "properties": {
    "gn:admin1_code":"21.0",
    "gn:admin2_code":"398.0",
    "gn:asciiname":"Lanjisunku",
    "gn:country_code":"IN",
    "gn:dem":875,
    "gn:feature_class":"P",
    "gn:feature_code":"PPL",
    "gn:name":"Lanjisunku",
    "gn:population":0,
    "gn:timezone":"Asia/Kolkata",
    "iso:country":"IN",
    "name:und_x_variant":[
        "Lanjiputtu"
    ],
    "wof:name":"Lanjisunku",
    "wof:placetype":"locality"
},
  "geometry": {"coordinates":[82.85217,18.7479],"type":"Point"}
}