{
  "type": "Feature",
  "properties": {
    "gn:admin1_code":"24.0",
    "gn:admin2_code":"130.0",
    "gn:asciiname":"Gani ka Gurha",
    "gn:country_code":"IN",
    "gn:dem":837,
    "gn:feature_class":"P",
    "gn:feature_code":"PPL",
    "gn:name":"Gani ka G\u016brha",
    "gn:population":0,
    "gn:timezone":"Asia/Kolkata",
    "iso:country":"IN",
    "wof:name":"Gani ka Gurha",
    "wof:placetype":"locality"
},
  "geometry": {"coordinates":[73.54751999999998,24.77186],"type":"Point"}
}