{
  "type": "Feature",
  "properties": {
    "gn:admin1_code":"21.0",
    "gn:admin2_code":"398.0",
    "gn:asciiname":"Sampaput",
    "gn:country_code":"IN",
    "gn:dem":866,
    "gn:feature_class":"P",
    "gn:feature_code":"PPL",
    "gn:name":"Samp\u0101put",
    "gn:population":0,
    "gn:timezone":"Asia/Kolkata",
    "iso:country":"IN",
    "wof:name":"Sampaput",
    "wof:placetype":"neighbourhood"
},
  "geometry": {"coordinates":[82.52915,18.53952],"type":"Point"}
}