{
  "type": "Feature",
  "properties": {
    "gn:admin1_code":"35.0",
    "gn:admin2_code":"442.0",
    "gn:asciiname":"Malipura",
    "gn:country_code":"IN",
    "gn:dem":412,
    "gn:feature_class":"P",
    "gn:feature_code":"PPL",
    "gn:name":"M\u0101l\u012bpura",
    "gn:population":0,
    "gn:timezone":"Asia/Kolkata",
    "iso:country":"IN",
    "name:hin_x_preferred":[
        "\u092e\u093e\u0932\u0940\u092a\u0941\u0930\u093e"
    ],
    "wof:name":"Malipura",
    "wof:placetype":"locality"
},
  "geometry": {"coordinates":[76.47284999999999,24.17561],"type":"Point"}
}