{
  "type": "Feature",
  "properties": {
    "iso:country":"IN",
    "ks:ks_name":"Pratap Ghar T.E. 92/156",
    "ks:ks_pop":35,
    "ks:ks_type":"VILLAGE",
    "ks:ks_uagg_main":0,
    "name:eng_x_preferred":[
        "Pratap Ghar T.E. 92/156"
    ],
    "wof:name":"Pratap Ghar T.E. 92/156",
    "wof:placetype":"neighbourhood",
    "wof:population":35
},
  "geometry": {"coordinates":[93.104223,26.75013],"type":"Point"}
}