{
  "type": "Feature",
  "properties": {
    "iso:country":"IN",
    "ks:ks_alt_nam":"Kasthurinaidu Kandriga UI",
    "ks:ks_name":"Kasthurinaidu Kandriga Ui",
    "ks:ks_pop":1,
    "ks:ks_type":"HABITATION",
    "name:eng_x_preferred":[
        "Kasthurinaidu Kandriga Ui"
    ],
    "wof:name":"Kasthurinaidu Kandriga Ui",
    "wof:placetype":"locality",
    "wof:population":1
},
  "geometry": {"coordinates":[79.567616,13.659827],"type":"Point"}
}