{
  "type": "Feature",
  "properties": {
    "iso:country":"IN",
    "ks:ks_alt_nam":"handguli",
    "ks:ks_name":"Handguli",
    "ks:ks_pop":65,
    "ks:ks_type":"HABITATION",
    "name:eng_x_preferred":[
        "Handguli"
    ],
    "wof:name":"Handguli",
    "wof:placetype":"locality",
    "wof:population":65
},
  "geometry": {"coordinates":[74.782177,14.453624],"type":"Point"}
}