{
  "type": "Feature",
  "properties": {
    "iso:country":"IN",
    "ks:ks_name":"Kot Eshwar",
    "ks:ks_pop":239,
    "ks:ks_type":"VILLAGE",
    "ks:ks_uagg_main":0,
    "name:eng_x_preferred":[
        "Kot Eshwar"
    ],
    "wof:name":"Kot Eshwar",
    "wof:placetype":"neighbourhood",
    "wof:population":239
},
  "geometry": {"coordinates":[78.823537,30.236951],"type":"Point"}
}