{
  "type": "Feature",
  "properties": {
    "gn:admin1_code":"10",
    "gn:admin2_code":"73.0",
    "gn:asciiname":"Faranswala",
    "gn:country_code":"IN",
    "gn:dem":236,
    "gn:feature_class":"P",
    "gn:feature_code":"PPL",
    "gn:name":"Far\u0101nsw\u0101la",
    "gn:population":0,
    "gn:timezone":"Asia/Kolkata",
    "iso:country":"IN",
    "wof:name":"Faranswala",
    "wof:placetype":"locality"
},
  "geometry": {"coordinates":[76.35508,29.7872],"type":"Point"}
}