{
  "type": "Feature",
  "properties": {
    "iso:country":"IN",
    "ks:ks_name":"Pura Barjir",
    "ks:ks_pop":380,
    "ks:ks_type":"HABITATION",
    "name:eng_x_preferred":[
        "Pura Barjir"
    ],
    "wof:name":"Pura Barjir",
    "wof:placetype":"locality",
    "wof:population":380
},
  "geometry": {"coordinates":[81.59380299999999,26.515536],"type":"Point"}
}