{
  "type": "Feature",
  "properties": {
    "iso:country":"IN",
    "ks:ks_name":"Ganesh Kheda",
    "ks:ks_pop":953,
    "ks:ks_type":"HABITATION",
    "name:eng_x_preferred":[
        "Ganesh Kheda"
    ],
    "wof:name":"Ganesh Kheda",
    "wof:placetype":"locality",
    "wof:population":953
},
  "geometry": {"coordinates":[77.419241,25.444564],"type":"Point"}
}