{
  "type": "Feature",
  "properties": {
    "gn:admin1_code":"16",
    "gn:admin2_code":"499.0",
    "gn:asciiname":"Nalkheda",
    "gn:country_code":"IN",
    "gn:dem":170,
    "gn:feature_class":"P",
    "gn:feature_code":"PPL",
    "gn:name":"N\u0101lkheda",
    "gn:population":0,
    "gn:timezone":"Asia/Kolkata",
    "iso:country":"IN",
    "name:ben_x_preferred":[
        "\u09a8\u09b2\u0996\u09c7\u09a6\u09be"
    ],
    "name:bpy_x_preferred":[
        "\u09a8\u09b2\u0996\u09c7\u09a6\u09be"
    ],
    "name:ita_x_preferred":[
        "Nalkheda"
    ],
    "name:msa_x_preferred":[
        "Nalkheda"
    ],
    "name:new_x_preferred":[
        "\u0928\u0932\u094d\u0916\u0947\u0926\u093e"
    ],
    "name:nld_x_preferred":[
        "Nalkheda"
    ],
    "name:por_x_preferred":[
        "Nalkheda"
    ],
    "name:spa_x_preferred":[
        "Nalkheda"
    ],
    "name:vie_x_preferred":[
        "Nalkheda"
    ],
    "name:zho_x_preferred":[
        "\u7eb3\u5c14\u51ef\u8fbe"
    ],
    "wof:name":"Nalkheda",
    "wof:placetype":"locality"
},
  "geometry": {"coordinates":[75.19043000000001,21.16589],"type":"Point"}
}