{
  "type": "Feature",
  "properties": {
    "gn:admin1_code":"37",
    "gn:admin2_code":"408.0",
    "gn:asciiname":"Jarahi",
    "gn:country_code":"IN",
    "gn:dem":323,
    "gn:feature_class":"P",
    "gn:feature_code":"PPL",
    "gn:name":"Jar\u0101hi",
    "gn:population":0,
    "gn:timezone":"Asia/Kolkata",
    "iso:country":"IN",
    "name:kur_x_preferred":[
        "Kurdistan"
    ],
    "wof:name":"Jarahi",
    "wof:placetype":"locality"
},
  "geometry": {"coordinates":[81.10072,21.19248],"type":"Point"}
}