{
  "type": "Feature",
  "properties": {
    "iso:country":"IN",
    "ks:ks_name":"Aruna Fali",
    "ks:ks_pop":286,
    "ks:ks_type":"HABITATION",
    "name:eng_x_preferred":[
        "Aruna Fali"
    ],
    "wof:name":"Aruna Fali",
    "wof:placetype":"locality",
    "wof:population":286
},
  "geometry": {"coordinates":[73.08903100000001,24.672809],"type":"Point"}
}