{
  "type": "Feature",
  "properties": {
    "gn:admin1_code":"35",
    "gn:admin2_code":"424.0",
    "gn:asciiname":"Gandharabganj",
    "gn:country_code":"IN",
    "gn:dem":237,
    "gn:feature_class":"P",
    "gn:feature_code":"PPL",
    "gn:name":"Gandharabganj",
    "gn:population":0,
    "gn:timezone":"Asia/Kolkata",
    "iso:country":"IN",
    "wof:name":"Gandharabganj",
    "wof:placetype":"neighbourhood"
},
  "geometry": {"coordinates":[79.07163,25.14614],"type":"Point"}
}