{
  "type": "Feature",
  "properties": {
    "gn:admin1_code":"12",
    "gn:admin2_code":"15.0",
    "gn:asciiname":"Kolapur",
    "gn:country_code":"IN",
    "gn:dem":1656,
    "gn:feature_class":"P",
    "gn:feature_code":"PPL",
    "gn:name":"Kolapur",
    "gn:population":0,
    "gn:timezone":"Asia/Kolkata",
    "iso:country":"IN",
    "wof:name":"Kolapur",
    "wof:placetype":"locality"
},
  "geometry": {"coordinates":[75.05861999999998,33.67595],"type":"Point"}
}