{
  "type": "Feature",
  "properties": {
    "gn:admin1_code":"36.0",
    "gn:admin2_code":"148.0",
    "gn:asciiname":"Nagla Bale",
    "gn:country_code":"IN",
    "gn:dem":150,
    "gn:feature_class":"P",
    "gn:feature_code":"PPL",
    "gn:name":"Nagla B\u0101le",
    "gn:population":0,
    "gn:timezone":"Asia/Kolkata",
    "iso:country":"IN",
    "wof:name":"Nagla Bale",
    "wof:placetype":"neighbourhood"
},
  "geometry": {"coordinates":[79.32652,26.96397],"type":"Point"}
}