{
  "type": "Feature",
  "properties": {
    "iso:country":"IN",
    "ks:ks_name":"Khajuria",
    "ks:ks_pop":560,
    "ks:ks_type":"VILLAGE",
    "ks:ks_uagg_main":0,
    "name:eng_x_preferred":[
        "Khajuria"
    ],
    "wof:name":"Khajuria",
    "wof:placetype":"locality",
    "wof:population":560
},
  "geometry": {"coordinates":[86.704295,24.521637],"type":"Point"}
}