{
  "type": "Feature",
  "properties": {
    "iso:country":"IN",
    "ks:ks_name":"Bachhnar",
    "ks:ks_pop":859,
    "ks:ks_type":"VILLAGE",
    "name:eng_x_preferred":[
        "Bachhnar"
    ],
    "wof:name":"Bachhnar",
    "wof:placetype":"locality",
    "wof:population":859
},
  "geometry": {"coordinates":[82.695452,24.27837],"type":"Point"}
}