{
  "type": "Feature",
  "properties": {
    "gn:admin1_code":"11.0",
    "gn:admin2_code":"33.0",
    "gn:asciiname":"Dalan",
    "gn:country_code":"IN",
    "gn:dem":1730,
    "gn:feature_class":"P",
    "gn:feature_code":"PPL",
    "gn:name":"Dal\u0101n",
    "gn:population":0,
    "gn:timezone":"Asia/Kolkata",
    "iso:country":"IN",
    "name:ceb_x_preferred":[
        "Dalan"
    ],
    "name:swe_x_preferred":[
        "Dalan"
    ],
    "wof:name":"Dalan",
    "wof:placetype":"locality"
},
  "geometry": {"coordinates":[77.47953000000003,31.3333],"type":"Point"}
}