{
  "type": "Feature",
  "properties": {
    "iso:country":"IN",
    "ks:ks_name":"Salanti",
    "ks:ks_pop":124,
    "ks:ks_type":"VILLAGE",
    "name:eng_x_preferred":[
        "Salanti"
    ],
    "wof:name":"Salanti",
    "wof:placetype":"locality",
    "wof:population":124
},
  "geometry": {"coordinates":[86.151601,20.186004],"type":"Point"}
}