{
  "type": "Feature",
  "properties": {
    "iso:country":"IN",
    "ks:ks_name":"Annavaram",
    "ks:ks_pop":812,
    "ks:ks_type":"VILLAGE",
    "name:eng_x_preferred":[
        "Annavaram"
    ],
    "wof:name":"Annavaram",
    "wof:placetype":"locality",
    "wof:population":812
},
  "geometry": {"coordinates":[82.950079,17.826949],"type":"Point"}
}