{
  "type": "Feature",
  "properties": {
    "iso:country":"IN",
    "ks:ks_name":"Kandanbahali",
    "ks:ks_pop":420,
    "ks:ks_type":"HABITATION",
    "name:eng_x_preferred":[
        "Kandanbahali"
    ],
    "wof:name":"Kandanbahali",
    "wof:placetype":"locality",
    "wof:population":420
},
  "geometry": {"coordinates":[83.356983,20.45059],"type":"Point"}
}