{
  "type": "Feature",
  "properties": {
    "gn:admin1_code":"36",
    "gn:admin2_code":"168.0",
    "gn:asciiname":"Kulkuwan",
    "gn:country_code":"IN",
    "gn:dem":135,
    "gn:feature_class":"P",
    "gn:feature_code":"PPL",
    "gn:name":"Kulkuw\u0101n",
    "gn:population":0,
    "gn:timezone":"Asia/Kolkata",
    "iso:country":"IN",
    "name:eng_x_preferred":[
        "Kulkuw\u0101n"
    ],
    "wof:name":"Kulkuwan",
    "wof:placetype":"locality"
},
  "geometry": {"coordinates":[80.11296999999998,25.49302],"type":"Point"}
}