{
  "type": "Feature",
  "properties": {
    "gn:admin1_code":"34.0",
    "gn:admin2_code":"220.0",
    "gn:asciiname":"Paterha Buzurg",
    "gn:country_code":"IN",
    "gn:dem":59,
    "gn:feature_class":"P",
    "gn:feature_code":"PPL",
    "gn:name":"Paterha Buzurg",
    "gn:population":0,
    "gn:timezone":"Asia/Kolkata",
    "iso:country":"IN",
    "ks:ks_name":"Paterha Buzurg",
    "ks:ks_pop":2114,
    "ks:ks_type":"VILLAGE",
    "name:eng_x_preferred":[
        "Paterha Buzurg"
    ],
    "wof:name":"Paterha Buzurg",
    "wof:placetype":"locality",
    "wof:population":2114
},
  "geometry": {"coordinates":[85.23169900000001,25.950512],"type":"Point"}
}