{
  "type": "Feature",
  "properties": {
    "iso:country":"IN",
    "ks:ks_name":"Gori Tola",
    "ks:ks_pop":409,
    "ks:ks_type":"HABITATION",
    "name:eng_x_preferred":[
        "Gori Tola"
    ],
    "wof:name":"Gori Tola",
    "wof:placetype":"locality",
    "wof:population":409
},
  "geometry": {"coordinates":[87.055328,25.797289],"type":"Point"}
}