{
  "type": "Feature",
  "properties": {
    "gn:admin1_code":"36",
    "gn:admin2_code":"142.0",
    "gn:asciiname":"Kamalpur",
    "gn:country_code":"IN",
    "gn:dem":207,
    "gn:feature_class":"P",
    "gn:feature_code":"PPL",
    "gn:name":"Kam\u0101lpur",
    "gn:population":0,
    "gn:timezone":"Asia/Kolkata",
    "iso:country":"IN",
    "ks:ks_alt_nam":"Kam\u0101lpur",
    "ks:ks_name":"Kamalpur",
    "ks:ks_pop":3285,
    "ks:ks_type":"VILLAGE",
    "ks:ks_uagg_main":0,
    "name:cat_x_preferred":[
        "Kamalpur"
    ],
    "name:ceb_x_preferred":[
        "Kamalpur"
    ],
    "name:fra_x_preferred":[
        "Kamalpur"
    ],
    "name:swe_x_preferred":[
        "Kamalpur"
    ],
    "name:tam_x_preferred":[
        "\u0b95\u0bae\u0bb2\u0bcd\u0baa\u0bc2\u0bb0\u0bcd"
    ],
    "wof:name":"Kamalpur",
    "wof:placetype":"neighbourhood"
},
  "geometry": {"coordinates":[77.81852000000001,28.42802],"type":"Point"}
}