{
  "type": "Feature",
  "properties": {
    "iso:country":"IN",
    "ks:ks_name":"Yangpalli",
    "ks:ks_pop":463,
    "ks:ks_type":"HABITATION",
    "name:eng_x_preferred":[
        "Yangpalli"
    ],
    "wof:name":"Yangpalli",
    "wof:placetype":"locality",
    "wof:population":463
},
  "geometry": {"coordinates":[80.645107,18.659886],"type":"Point"}
}