{
  "type": "Feature",
  "properties": {
    "gn:admin1_code":"21.0",
    "gn:admin2_code":"396.0",
    "gn:asciiname":"Kallapai",
    "gn:country_code":"IN",
    "gn:dem":487,
    "gn:feature_class":"P",
    "gn:feature_code":"PPL",
    "gn:name":"Kallapai",
    "gn:population":0,
    "gn:timezone":"Asia/Kolkata",
    "iso:country":"IN",
    "ks:ks_name":"Kalapai",
    "ks:ks_pop":347,
    "ks:ks_type":"VILLAGE",
    "name:eng_x_preferred":[
        "Kalapai"
    ],
    "name:eng_x_variant":[
        "Kallapai"
    ],
    "wof:name":"Kalapai",
    "wof:placetype":"locality",
    "wof:population":347
},
  "geometry": {"coordinates":[83.569326,19.340921],"type":"Point"}
}