{
  "type": "Feature",
  "properties": {
    "iso:country":"IN",
    "ks:ks_name":"Mohd.pur Rampur",
    "ks:ks_pop":743,
    "ks:ks_type":"HABITATION",
    "name:eng_x_preferred":[
        "Mohd.pur Rampur"
    ],
    "wof:name":"Mohd.pur Rampur",
    "wof:placetype":"locality",
    "wof:population":743
},
  "geometry": {"coordinates":[77.819389,28.176431],"type":"Point"}
}