{
  "type": "Feature",
  "properties": {
    "gn:admin1_code":"36",
    "gn:admin2_code":"152.0",
    "gn:asciiname":"Gadai Sharif",
    "gn:country_code":"IN",
    "gn:dem":147,
    "gn:feature_class":"P",
    "gn:feature_code":"PPL",
    "gn:name":"Gad\u0101i Shar\u012bf",
    "gn:population":0,
    "gn:timezone":"Asia/Kolkata",
    "iso:country":"IN",
    "ks:ks_name":"Gadai Sharif",
    "ks:ks_pop":0,
    "ks:ks_type":"VILLAGE",
    "name:eng_x_preferred":[
        "Gadai Sharif"
    ],
    "wof:name":"Gadai Sharif",
    "wof:placetype":"locality",
    "wof:population":0
},
  "geometry": {"coordinates":[79.524907,27.79186],"type":"Point"}
}