{
  "type": "Feature",
  "properties": {
    "gn:admin1_code":"19.0",
    "gn:admin2_code":"581.0",
    "gn:asciiname":"Chavadanahalli",
    "gn:country_code":"IN",
    "gn:dem":840,
    "gn:feature_class":"P",
    "gn:feature_code":"PPL",
    "gn:name":"Chavadanahalli",
    "gn:population":0,
    "gn:timezone":"Asia/Kolkata",
    "iso:country":"IN",
    "wof:name":"Chavadanahalli",
    "wof:placetype":"neighbourhood"
},
  "geometry": {"coordinates":[78.13876,13.34406],"type":"Point"}
}