{
  "type": "Feature",
  "properties": {
    "iso:country":"IN",
    "ks:ks_name":"Peringara",
    "ks:ks_pop":500,
    "ks:ks_type":"HABITATION",
    "name:eng_x_preferred":[
        "Peringara"
    ],
    "wof:name":"Peringara",
    "wof:placetype":"locality",
    "wof:population":500
},
  "geometry": {"coordinates":[76.850599,9.448378],"type":"Point"}
}