{
  "type": "Feature",
  "properties": {
    "gn:admin1_code":"10.0",
    "gn:admin2_code":"79.0",
    "gn:asciiname":"Kishanpura",
    "gn:country_code":"IN",
    "gn:dem":195,
    "gn:feature_class":"P",
    "gn:feature_code":"PPL",
    "gn:name":"Kishanpura",
    "gn:population":0,
    "gn:timezone":"Asia/Kolkata",
    "iso:country":"IN",
    "name:ara_x_preferred":[
        "\u0643\u064a\u0634\u0627\u0646\u0628\u0648\u0631\u0627"
    ],
    "name:ben_bn_x_preferred":[
        "\u0995\u09bf\u09b7\u09be\u09a8\u09aa\u09c1\u09b0\u09be"
    ],
    "name:ben_in_x_preferred":[
        "\u0995\u09bf\u09b7\u09be\u09a8\u09aa\u09c1\u09b0\u09be"
    ],
    "name:guj_x_preferred":[
        "\u0a95\u0abf\u0ab6\u0aa8\u0aaa\u0ac1\u0ab0\u0abe"
    ],
    "name:hin_x_preferred":[
        "\u0915\u093f\u0936\u0928\u092a\u0941\u0930\u093e"
    ],
    "name:kan_x_preferred":[
        "\u0c95\u0cbf\u0cb7\u0ca8\u0ccd"
    ],
    "name:mal_x_preferred":[
        "\u0d15\u0d3f\u0d37\u0d7b\u0d2a\u0d41\u0d30"
    ],
    "name:mar_x_preferred":[
        "\u0915\u093f\u0936\u0928\u092a\u0941\u0930\u093e"
    ],
    "name:pan_x_preferred":[
        "\u0a15\u0a3f\u0a36\u0a28\u0a2a\u0a41\u0a30\u0a3e"
    ],
    "name:tam_x_preferred":[
        "\u0b95\u0bbf\u0bb7\u0ba9\u0bcd\u0baa\u0bc1\u0bb0\u0bbe"
    ],
    "name:tel_x_preferred":[
        "\u0c15\u0c3f\u0c37\u0c28\u0c4d"
    ],
    "name:urd_x_preferred":[
        "\u06a9\u0634\u0646 \u067e\u0648\u0631\u06c1"
    ],
    "wof:name":"Kishanpura",
    "wof:placetype":"neighbourhood"
},
  "geometry": {"coordinates":[74.65449,29.41686],"type":"Point"}
}