{
  "type": "Feature",
  "properties": {
    "iso:country":"IN",
    "ks:ks_name":"Mudushedde",
    "ks:ks_pop":7417,
    "ks:ks_type":"VILLAGE",
    "name:eng_x_preferred":[
        "Mudushedde"
    ],
    "wof:name":"Mudushedde",
    "wof:placetype":"neighbourhood",
    "wof:population":7417
},
  "geometry": {"coordinates":[74.89333999999999,12.929918],"type":"Point"}
}