{
  "type": "Feature",
  "properties": {
    "iso:country":"IN",
    "ks:ks_name":"Chourang No 3 A",
    "ks:ks_pop":300,
    "ks:ks_type":"HABITATION",
    "ks:ks_uagg_main":0,
    "name:eng_x_preferred":[
        "Chourang No 3 A"
    ],
    "wof:name":"Chourang No 3 A",
    "wof:placetype":"neighbourhood",
    "wof:population":300
},
  "geometry": {"coordinates":[90.822282,26.621489],"type":"Point"}
}