{
  "type": "Feature",
  "properties": {
    "iso:country":"IN",
    "ks:ks_name":"Aral",
    "ks:ks_pop":0,
    "ks:ks_type":"VILLAGE",
    "name:eng_x_preferred":[
        "Aral"
    ],
    "wof:name":"Aral",
    "wof:placetype":"locality",
    "wof:population":0
},
  "geometry": {"coordinates":[87.582865,23.972063],"type":"Point"}
}