{
  "type": "Feature",
  "properties": {
    "gn:admin1_code":"19.0",
    "gn:admin2_code":"563.0",
    "gn:asciiname":"Belangi",
    "gn:country_code":"IN",
    "gn:dem":53,
    "gn:feature_class":"P",
    "gn:feature_code":"PPL",
    "gn:name":"Belangi",
    "gn:population":0,
    "gn:timezone":"Asia/Kolkata",
    "iso:country":"IN",
    "ks:ks_name":"Bellangi",
    "ks:ks_pop":356,
    "ks:ks_type":"VILLAGE",
    "name:eng_x_preferred":[
        "Bellangi"
    ],
    "name:eng_x_variant":[
        "Belangi"
    ],
    "wof:name":"Bellangi",
    "wof:placetype":"locality",
    "wof:population":356
},
  "geometry": {"coordinates":[74.510988,14.525105],"type":"Point"}
}