{
  "type": "Feature",
  "properties": {
    "iso:country":"IN",
    "ks:ks_name":"Santhaipatti",
    "ks:ks_pop":123,
    "ks:ks_type":"HABITATION",
    "name:eng_x_preferred":[
        "Santhaipatti"
    ],
    "wof:name":"Santhaipatti",
    "wof:placetype":"locality",
    "wof:population":123
},
  "geometry": {"coordinates":[77.808561,9.907695],"type":"Point"}
}