{
  "type": "Feature",
  "properties": {
    "iso:country":"IN",
    "ks:ks_name":"Kondharpada",
    "ks:ks_pop":764,
    "ks:ks_type":"HABITATION",
    "name:eng_x_preferred":[
        "Kondharpada"
    ],
    "wof:name":"Kondharpada",
    "wof:placetype":"locality",
    "wof:population":764
},
  "geometry": {"coordinates":[72.887118,20.112108],"type":"Point"}
}