{
  "type": "Feature",
  "properties": {
    "gn:admin1_code":"39.0",
    "gn:asciiname":"Mehdipur",
    "gn:country_code":"IN",
    "gn:dem":202,
    "gn:feature_class":"P",
    "gn:feature_code":"PPL",
    "gn:name":"Mehdipur",
    "gn:population":0,
    "gn:timezone":"Asia/Kolkata",
    "iso:country":"IN",
    "ks:ks_name":"Mehdipur",
    "ks:ks_type":"VILLAGE",
    "name:eng_x_preferred":[
        "Mehdipur"
    ],
    "wof:name":"Mehdipur",
    "wof:placetype":"locality"
},
  "geometry": {"coordinates":[79.28761299999999,28.961408],"type":"Point"}
}