{
  "type": "Feature",
  "properties": {
    "iso:country":"IN",
    "ks:ks_name":"1 LK",
    "ks:ks_pop":219,
    "ks:ks_type":"VILLAGE",
    "name:eng_x_preferred":[
        "1 LK"
    ],
    "wof:name":"1 LK",
    "wof:placetype":"locality",
    "wof:population":219
},
  "geometry": {"coordinates":[74.39641399999999,29.3724],"type":"Point"}
}