{
  "type": "Feature",
  "properties": {
    "iso:country":"IN",
    "ks:ks_name":"3 KKW-A",
    "ks:ks_pop":382,
    "ks:ks_type":"VILLAGE",
    "name:eng_x_preferred":[
        "3 KKW-A"
    ],
    "wof:name":"3 KKW-A",
    "wof:placetype":"locality",
    "wof:population":382
},
  "geometry": {"coordinates":[74.32899500000001,29.72137],"type":"Point"}
}