{
  "type": "Feature",
  "properties": {
    "iso:country":"IN",
    "ks:ks_name":"Mukhchuma",
    "ks:ks_pop":62,
    "ks:ks_type":"HABITATION",
    "name:eng_x_preferred":[
        "Mukhchuma"
    ],
    "wof:name":"Mukhchuma",
    "wof:placetype":"locality",
    "wof:population":62
},
  "geometry": {"coordinates":[85.667554,23.89224],"type":"Point"}
}