{
  "type": "Feature",
  "properties": {
    "iso:country":"IN",
    "ks:ks_name":"Bhandartikuri",
    "ks:ks_pop":1086,
    "ks:ks_type":"VILLAGE",
    "ks:ks_uagg_main":0,
    "name:eng_x_preferred":[
        "Bhandartikuri"
    ],
    "wof:name":"Bhandartikuri",
    "wof:placetype":"locality",
    "wof:population":1086
},
  "geometry": {"coordinates":[88.334733,23.430489],"type":"Point"}
}