{
  "type": "Feature",
  "properties": {
    "iso:country":"IN",
    "ks:ks_name":"Palli",
    "ks:ks_pop":260,
    "ks:ks_type":"HABITATION",
    "ks:ks_uagg_main":0,
    "name:eng_x_preferred":[
        "Palli"
    ],
    "wof:name":"Palli",
    "wof:placetype":"locality",
    "wof:population":260
},
  "geometry": {"coordinates":[76.16539400000001,10.64029],"type":"Point"}
}