{
  "type": "Feature",
  "properties": {
    "iso:country":"IN",
    "ks:ks_name":"Kuradi",
    "ks:ks_pop":172,
    "ks:ks_type":"HABITATION",
    "name:eng_x_preferred":[
        "Kuradi"
    ],
    "wof:name":"Kuradi",
    "wof:placetype":"locality",
    "wof:population":172
},
  "geometry": {"coordinates":[74.79264000000001,13.467551],"type":"Point"}
}