{
  "type": "Feature",
  "properties": {
    "gn:admin1_code":"7.0",
    "gn:admin2_code":"98.0",
    "gn:asciiname":"Begampur",
    "gn:country_code":"IN",
    "gn:dem":230,
    "gn:feature_class":"P",
    "gn:feature_code":"PPL",
    "gn:name":"Begampur",
    "gn:population":0,
    "gn:timezone":"Asia/Kolkata",
    "iso:country":"IN",
    "wof:name":"Begampur",
    "wof:placetype":"locality"
},
  "geometry": {"coordinates":[77.20804,28.53981],"type":"Point"}
}