{
  "type": "Feature",
  "properties": {
    "iso:country":"IN",
    "name:fra_x_preferred":[
        "Dera"
    ],
    "name:snd_x_preferred":[
        "\u062f\u064a\u0631\u0648"
    ],
    "name:urd_x_preferred":[
        "\u0688\u06cc\u0631\u06c1"
    ],
    "qs:name":"Dehra",
    "qs:name_adm0":"India",
    "qs:name_adm1":"Himachal Pradesh",
    "qs:photos":1,
    "qs:photos_1k":1,
    "qs:photos_9k":1,
    "qs:photos_9r":1,
    "qs:photos_all":1,
    "qs:photos_sr":1,
    "qs:placetype":"Suburb",
    "qs:pop_sr":"0",
    "wd:wordcount":219,
    "wof:name":"Dehra",
    "wof:placetype":"neighbourhood"
},
  "geometry": {"coordinates":[77.198448,30.97516],"type":"Point"}
}