{
  "type": "Feature",
  "properties": {
    "iso:country":"IN",
    "name:ara_x_preferred":[
        "\u062f\u064a\u0647\u0631\u0627"
    ],
    "name:ben_bn_x_preferred":[
        "\u09a6\u09c7\u09b9\u09b0\u09be"
    ],
    "name:ben_in_x_preferred":[
        "\u09a6\u09c7\u09b9\u09b0\u09be"
    ],
    "name:fra_x_preferred":[
        "Dera"
    ],
    "name:guj_x_preferred":[
        "\u0aa6\u0ac7\u0ab9\u0ab0\u0abe"
    ],
    "name:hin_x_preferred":[
        "\u0926\u0947\u0939\u0930\u093e"
    ],
    "name:kan_x_preferred":[
        "\u0ca6\u0cc7\u0cb9\u0ccd\u0cb0\u0cbe"
    ],
    "name:mal_x_preferred":[
        "\u0d21\u0d46\u0d31\u0d3e"
    ],
    "name:mar_x_preferred":[
        "\u0921\u0947\u0939\u0930\u093e"
    ],
    "name:pan_x_preferred":[
        "\u0a26\u0a47\u0a39\u0a30\u0a3e"
    ],
    "name:snd_x_preferred":[
        "\u062f\u064a\u0631\u0648"
    ],
    "name:tam_x_preferred":[
        "\u0b9f\u0bc6\u0bb9\u0bcd\u0bb0\u0bbe"
    ],
    "name:tel_x_preferred":[
        "\u0c21\u0c46\u0c39\u0c4d\u0c30\u0c3e"
    ],
    "name:urd_x_preferred":[
        "\u0688\u06cc\u06c1\u0631\u0627"
    ],
    "name:urd_x_variant":[
        "\u0688\u06cc\u0631\u06c1"
    ],
    "qs:name":"Dehra",
    "qs:name_adm0":"India",
    "qs:name_adm1":"Himachal Pradesh",
    "qs:photos":1,
    "qs:photos_1k":1,
    "qs:photos_9k":1,
    "qs:photos_9r":1,
    "qs:photos_all":1,
    "qs:photos_sr":1,
    "qs:placetype":"Suburb",
    "qs:pop_sr":"0",
    "wd:wordcount":219,
    "wof:name":"Dehra",
    "wof:placetype":"neighbourhood"
},
  "geometry": {"coordinates":[77.198448,30.97516],"type":"Point"}
}