{
  "type": "Feature",
  "properties": {
    "iso:country":"IN",
    "ks:ks_name":"Nagla Baheri",
    "ks:ks_pop":402,
    "ks:ks_type":"VILLAGE",
    "name:eng_x_preferred":[
        "Nagla Baheri"
    ],
    "wof:name":"Nagla Baheri",
    "wof:placetype":"locality",
    "wof:population":402
},
  "geometry": {"coordinates":[77.346856,28.85641],"type":"Point"}
}