{
  "type": "Feature",
  "properties": {
    "iso:country":"IN",
    "ks:ks_name":"Kondesal",
    "ks:ks_pop":129,
    "ks:ks_type":"HABITATION",
    "name:eng_x_preferred":[
        "Kondesal"
    ],
    "wof:name":"Kondesal",
    "wof:placetype":"locality",
    "wof:population":129
},
  "geometry": {"coordinates":[74.722768,14.669205],"type":"Point"}
}