{
  "type": "Feature",
  "properties": {
    "iso:country":"IN",
    "ks:ks_name":"Dhara Pramanikpara",
    "ks:ks_pop":347,
    "ks:ks_type":"HABITATION",
    "name:eng_x_preferred":[
        "Dhara Pramanikpara"
    ],
    "wof:name":"Dhara Pramanikpara",
    "wof:placetype":"locality",
    "wof:population":347
},
  "geometry": {"coordinates":[88.08390900000001,22.506207],"type":"Point"}
}