{
  "type": "Feature",
  "properties": {
    "iso:country":"IN",
    "ks:ks_name":"Sonar Tola",
    "ks:ks_pop":100,
    "ks:ks_type":"HABITATION",
    "name:eng_x_preferred":[
        "Sonar Tola"
    ],
    "wof:name":"Sonar Tola",
    "wof:placetype":"locality",
    "wof:population":100
},
  "geometry": {"coordinates":[84.32517799999999,26.680162],"type":"Point"}
}