{
  "type": "Feature",
  "properties": {
    "iso:country":"IN",
    "ks:ks_name":"Kuladapare",
    "ks:ks_pop":1183,
    "ks:ks_type":"HABITATION",
    "name:eng_x_preferred":[
        "Kuladapare"
    ],
    "wof:name":"Kuladapare",
    "wof:placetype":"locality",
    "wof:population":1183
},
  "geometry": {"coordinates":[75.19505100000001,12.621989],"type":"Point"}
}