{
  "type": "Feature",
  "properties": {
    "gn:admin1_code":"35.0",
    "gn:admin2_code":"457.0",
    "gn:asciiname":"Saraitola",
    "gn:country_code":"IN",
    "gn:dem":553,
    "gn:feature_class":"P",
    "gn:feature_code":"PPL",
    "gn:name":"Sara\u012btol\u0101",
    "gn:population":0,
    "gn:timezone":"Asia/Kolkata",
    "iso:country":"IN",
    "wof:name":"Saraitola",
    "wof:placetype":"locality"
},
  "geometry": {"coordinates":[80.65858,21.91159],"type":"Point"}
}