{
  "type": "Feature",
  "properties": {
    "iso:country":"IN",
    "ks:ks_name":"Mahishgot",
    "ks:ks_pop":1290,
    "ks:ks_type":"VILLAGE",
    "name:eng_x_preferred":[
        "Mahishgot"
    ],
    "wof:name":"Mahishgot",
    "wof:placetype":"locality",
    "wof:population":1290
},
  "geometry": {"coordinates":[87.866056,22.233022],"type":"Point"}
}