{
  "type": "Feature",
  "properties": {
    "iso:country":"IN",
    "ks:ks_name":"Melpada",
    "ks:ks_pop":323,
    "ks:ks_type":"VILLAGE",
    "name:eng_x_preferred":[
        "Melpada"
    ],
    "wof:name":"Melpada",
    "wof:placetype":"locality",
    "wof:population":323
},
  "geometry": {"coordinates":[74.60531,22.71323],"type":"Point"}
}