{
  "type": "Feature",
  "properties": {
    "gn:admin1_code":"24.0",
    "gn:admin2_code":"123.0",
    "gn:asciiname":"Khanko ka Gurha",
    "gn:country_code":"IN",
    "gn:dem":713,
    "gn:feature_class":"P",
    "gn:feature_code":"PPL",
    "gn:name":"Kh\u0101nko ka G\u016brha",
    "gn:population":0,
    "gn:timezone":"Asia/Kolkata",
    "iso:country":"IN",
    "wof:name":"Khanko ka Gurha",
    "wof:placetype":"locality"
},
  "geometry": {"coordinates":[73.72804000000002,25.25983],"type":"Point"}
}