{
  "type": "Feature",
  "properties": {
    "iso:country":"IN",
    "ks:ks_alt_nam":"Fanas pada falia",
    "ks:ks_name":"Fanas Pada Falia",
    "ks:ks_pop":390,
    "ks:ks_type":"HABITATION",
    "name:eng_x_preferred":[
        "Fanas Pada Falia"
    ],
    "wof:name":"Fanas Pada Falia",
    "wof:placetype":"locality",
    "wof:population":390
},
  "geometry": {"coordinates":[73.270861,20.274778],"type":"Point"}
}