{
  "type": "Feature",
  "properties": {
    "gn:admin1_code":"36",
    "gn:admin2_code":"180.0",
    "gn:asciiname":"Jiginian Mahipal Singh",
    "gn:country_code":"IN",
    "gn:dem":115,
    "gn:feature_class":"P",
    "gn:feature_code":"PPL",
    "gn:name":"Jigini\u0101n Mahip\u0101l Singh",
    "gn:population":0,
    "gn:timezone":"Asia/Kolkata",
    "iso:country":"IN",
    "wof:name":"Jiginian Mahipal Singh",
    "wof:placetype":"locality"
},
  "geometry": {"coordinates":[81.65961999999998,27.41661],"type":"Point"}
}