{
  "type": "Feature",
  "properties": {
    "iso:country":"IN",
    "ks:ks_name":"Pathaguda",
    "ks:ks_pop":194,
    "ks:ks_type":"HABITATION",
    "name:eng_x_preferred":[
        "Pathaguda"
    ],
    "wof:name":"Pathaguda",
    "wof:placetype":"locality",
    "wof:population":194
},
  "geometry": {"coordinates":[79.15493499999999,19.130287],"type":"Point"}
}