{
  "type": "Feature",
  "properties": {
    "gn:admin1_code":"37",
    "gn:admin2_code":"406.0",
    "gn:asciiname":"Surhi",
    "gn:country_code":"IN",
    "gn:dem":384,
    "gn:feature_class":"P",
    "gn:feature_code":"PPL",
    "gn:name":"Surhi",
    "gn:population":0,
    "gn:timezone":"Asia/Kolkata",
    "iso:country":"IN",
    "wof:name":"Surhi",
    "wof:placetype":"locality"
},
  "geometry": {"coordinates":[81.6942,22.40627000000001],"type":"Point"}
}