{
  "type": "Feature",
  "properties": {
    "gn:admin1_code":"37",
    "gn:admin2_code":"406.0",
    "gn:asciiname":"Surhi",
    "gn:country_code":"IN",
    "gn:dem":384,
    "gn:feature_class":"P",
    "gn:feature_code":"PPL",
    "gn:name":"Surhi",
    "gn:population":0,
    "gn:timezone":"Asia/Kolkata",
    "iso:country":"IN",
    "ks:ks_name":"Surhi",
    "ks:ks_pop":604,
    "ks:ks_type":"VILLAGE",
    "name:eng_x_preferred":[
        "Surhi"
    ],
    "wof:name":"Surhi",
    "wof:placetype":"locality",
    "wof:population":604
},
  "geometry": {"coordinates":[81.694202,22.40627],"type":"Point"}
}