{
  "type": "Feature",
  "properties": {
    "gn:admin1_code":"39.0",
    "gn:admin2_code":"63.0",
    "gn:asciiname":"Chirang",
    "gn:country_code":"IN",
    "gn:dem":1173,
    "gn:feature_class":"P",
    "gn:feature_code":"PPL",
    "gn:name":"Chirang",
    "gn:population":0,
    "gn:timezone":"Asia/Kolkata",
    "iso:country":"IN",
    "ks:ks_name":"Chirang",
    "ks:ks_type":"VILLAGE",
    "name:ara_x_preferred":[
        "\u062a\u0634\u064a\u0631\u0627\u0646\u062c"
    ],
    "name:ben_bn_x_preferred":[
        "\u099a\u09bf\u09b0\u09be\u0982"
    ],
    "name:ben_in_x_preferred":[
        "\u099a\u09bf\u09b0\u09be\u0982"
    ],
    "name:ceb_x_preferred":[
        "Chirang"
    ],
    "name:eng_x_preferred":[
        "Chirang"
    ],
    "name:guj_x_preferred":[
        "\u0a9a\u0abf\u0ab0\u0a82\u0a97"
    ],
    "name:hin_x_preferred":[
        "\u091a\u093f\u0930\u093e\u0902\u0917"
    ],
    "name:hin_x_variant":[
        "\u091a\u093f\u0930\u0902\u0917"
    ],
    "name:kan_x_preferred":[
        "\u0c9a\u0cbf\u0cb0\u0c82\u0c97\u0ccd"
    ],
    "name:mal_x_preferred":[
        "\u0d1a\u0d3f\u0d30\u0d02\u0d17\u0d4d"
    ],
    "name:mar_x_preferred":[
        "\u091a\u093f\u0930\u0902\u0917"
    ],
    "name:pan_x_preferred":[
        "\u0a1a\u0a3f\u0a30\u0a3e\u0a02\u0a17"
    ],
    "name:swe_x_preferred":[
        "Chirang"
    ],
    "name:tam_x_preferred":[
        "\u0b9a\u0bbf\u0bb0\u0bbe\u0b99\u0bcd\u0b95\u0bcd"
    ],
    "name:tel_x_preferred":[
        "\u0c1a\u0c3f\u0c30\u0c02\u0c17\u0c4d"
    ],
    "name:tur_x_preferred":[
        "Chirang"
    ],
    "name:urd_x_preferred":[
        "\u0686\u0631\u0627\u0646\u06af"
    ],
    "name:vie_x_preferred":[
        "Chirang"
    ],
    "wof:name":"Chirang",
    "wof:placetype":"locality"
},
  "geometry": {"coordinates":[79.81930800000001,29.873676],"type":"Point"}
}