{
  "type": "Feature",
  "properties": {
    "gn:admin1_code":"39.0",
    "gn:admin2_code":"63.0",
    "gn:asciiname":"Chirang",
    "gn:country_code":"IN",
    "gn:dem":1173,
    "gn:feature_class":"P",
    "gn:feature_code":"PPL",
    "gn:name":"Chirang",
    "gn:population":0,
    "gn:timezone":"Asia/Kolkata",
    "iso:country":"IN",
    "name:ceb_x_preferred":[
        "Chirang"
    ],
    "name:swe_x_preferred":[
        "Chirang"
    ],
    "wof:name":"Chirang",
    "wof:placetype":"locality"
},
  "geometry": {"coordinates":[79.81931,29.87368],"type":"Point"}
}