{
  "type": "Feature",
  "properties": {
    "gn:admin1_code":"19.0",
    "gn:admin2_code":"581.0",
    "gn:asciiname":"Guntiganipalli",
    "gn:country_code":"IN",
    "gn:dem":754,
    "gn:feature_class":"P",
    "gn:feature_code":"PPL",
    "gn:name":"Guntig\u0101nipalli",
    "gn:population":0,
    "gn:timezone":"Asia/Kolkata",
    "iso:country":"IN",
    "wof:name":"Guntiganipalli",
    "wof:placetype":"locality"
},
  "geometry": {"coordinates":[78.27202,13.52156],"type":"Point"}
}