{
  "type": "Feature",
  "properties": {
    "iso:country":"IN",
    "ks:ks_name":"Hardia",
    "ks:ks_pop":841,
    "ks:ks_type":"HABITATION",
    "ks:ks_uagg_main":0,
    "name:eng_x_preferred":[
        "Hardia"
    ],
    "wof:name":"Hardia",
    "wof:placetype":"neighbourhood",
    "wof:population":841
},
  "geometry": {"coordinates":[84.942761,26.81983],"type":"Point"}
}