{
  "type": "Feature",
  "properties": {
    "iso:country":"IN",
    "ks:ks_name":"Kasba Mehsi",
    "ks:ks_pop":5953,
    "ks:ks_type":"VILLAGE",
    "ks:ks_uagg_main":0,
    "name:eng_x_preferred":[
        "Kasba Mehsi"
    ],
    "wof:name":"Kasba Mehsi",
    "wof:placetype":"neighbourhood",
    "wof:population":5953
},
  "geometry": {"coordinates":[85.11936900000001,26.356172],"type":"Point"}
}