{
  "type": "Feature",
  "properties": {
    "iso:country":"IN",
    "ks:ks_name":"Indrasan Tola (harij.basti)",
    "ks:ks_pop":60,
    "ks:ks_type":"HABITATION",
    "ks:ks_uagg_main":0,
    "name:eng_x_preferred":[
        "Indrasan Tola (harij.basti)"
    ],
    "wof:name":"Indrasan Tola (harij.basti)",
    "wof:placetype":"neighbourhood",
    "wof:population":60
},
  "geometry": {"coordinates":[83.56450700000001,26.629873],"type":"Point"}
}