{
  "type": "Feature",
  "properties": {
    "gn:admin1_code":"23.0",
    "gn:admin2_code":"41.0",
    "gn:asciiname":"Bhaurla",
    "gn:country_code":"IN",
    "gn:dem":263,
    "gn:feature_class":"P",
    "gn:feature_code":"PPL",
    "gn:name":"Bhaurla",
    "gn:population":0,
    "gn:timezone":"Asia/Kolkata",
    "iso:country":"IN",
    "ks:ks_name":"Bhaurla",
    "ks:ks_pop":1152,
    "ks:ks_type":"VILLAGE",
    "ks:ks_uagg_main":0,
    "name:eng_x_preferred":[
        "Bhaurla"
    ],
    "wof:name":"Bhaurla",
    "wof:placetype":"neighbourhood",
    "wof:population":1152
},
  "geometry": {"coordinates":[76.13006799999999,30.760842],"type":"Point"}
}