{
  "type": "Feature",
  "properties": {
    "iso:country":"IN",
    "ks:ks_name":"Bhelewadi",
    "ks:ks_pop":225,
    "ks:ks_type":"HABITATION",
    "name:eng_x_preferred":[
        "Bhelewadi"
    ],
    "wof:name":"Bhelewadi",
    "wof:placetype":"locality",
    "wof:population":225
},
  "geometry": {"coordinates":[73.275278,17.563056],"type":"Point"}
}