{
  "type": "Feature",
  "properties": {
    "gn:admin1_code":"24.0",
    "gn:admin2_code":"105.0",
    "gn:asciiname":"Kanchan Ka Nagla",
    "gn:country_code":"IN",
    "gn:dem":221,
    "gn:feature_class":"P",
    "gn:feature_code":"PPL",
    "gn:name":"Kanchan Ka Nagla",
    "gn:population":0,
    "gn:timezone":"Asia/Kolkata",
    "iso:country":"IN",
    "wof:name":"Kanchan Ka Nagla",
    "wof:placetype":"locality"
},
  "geometry": {"coordinates":[77.31596999999999,26.83514000000001],"type":"Point"}
}