{
  "type": "Feature",
  "properties": {
    "iso:country":"IN",
    "ks:ks_name":"Kalingadibba",
    "ks:ks_pop":382,
    "ks:ks_type":"HABITATION",
    "name:eng_x_preferred":[
        "Kalingadibba"
    ],
    "wof:name":"Kalingadibba",
    "wof:placetype":"locality",
    "wof:population":382
},
  "geometry": {"coordinates":[80.75633999999999,16.345102],"type":"Point"}
}