{
  "type": "Feature",
  "properties": {
    "iso:country":"IN",
    "ks:ks_name":"Bhali Chhapara",
    "ks:ks_pop":1022,
    "ks:ks_type":"VILLAGE",
    "ks:ks_uagg_main":0,
    "name:eng_x_preferred":[
        "Bhali Chhapara"
    ],
    "wof:name":"Bhali Chhapara",
    "wof:placetype":"neighbourhood",
    "wof:population":1022
},
  "geometry": {"coordinates":[84.05980099999999,26.325062],"type":"Point"}
}