{
  "type": "Feature",
  "properties": {
    "iso:country":"IN",
    "ks:ks_name":"Burugundala",
    "ks:ks_pop":52,
    "ks:ks_type":"HABITATION",
    "name:eng_x_preferred":[
        "Burugundala"
    ],
    "wof:name":"Burugundala",
    "wof:placetype":"locality",
    "wof:population":52
},
  "geometry": {"coordinates":[79.168736,16.138898],"type":"Point"}
}