{
  "type": "Feature",
  "properties": {
    "gn:admin1_code":"16",
    "gn:admin2_code":"514.0",
    "gn:asciiname":"Talni",
    "gn:country_code":"IN",
    "gn:dem":500,
    "gn:feature_class":"P",
    "gn:feature_code":"PPL",
    "gn:name":"Talni",
    "gn:population":0,
    "gn:timezone":"Asia/Kolkata",
    "iso:country":"IN",
    "wof:name":"Talni",
    "wof:placetype":"locality"
},
  "geometry": {"coordinates":[76.47311999999999,19.88224],"type":"Point"}
}