{
  "type": "Feature",
  "properties": {
    "iso:country":"IN",
    "ks:ks_name":"Vadakkukadu",
    "ks:ks_pop":110,
    "ks:ks_type":"HABITATION",
    "name:eng_x_preferred":[
        "Vadakkukadu"
    ],
    "wof:name":"Vadakkukadu",
    "wof:placetype":"locality",
    "wof:population":110
},
  "geometry": {"coordinates":[77.720814,11.498075],"type":"Point"}
}