{
  "type": "Feature",
  "properties": {
    "iso:country":"IN",
    "ks:ks_name":"Sirali F.1",
    "ks:ks_pop":294,
    "ks:ks_type":"HABITATION",
    "name:eng_x_preferred":[
        "Sirali F.1"
    ],
    "wof:name":"Sirali F.1",
    "wof:placetype":"locality",
    "wof:population":294
},
  "geometry": {"coordinates":[77.093681,22.854438],"type":"Point"}
}