{
  "type": "Feature",
  "properties": {
    "iso:country":"IN",
    "ks:ks_alt_nam":"KesarKhaspara",
    "ks:ks_name":"Kesarkhaspara",
    "ks:ks_pop":373,
    "ks:ks_type":"HABITATION",
    "name:eng_x_preferred":[
        "Kesarkhaspara"
    ],
    "wof:name":"Kesarkhaspara",
    "wof:placetype":"locality",
    "wof:population":373
},
  "geometry": {"coordinates":[82.751448,23.777795],"type":"Point"}
}