{
  "type": "Feature",
  "properties": {
    "gn:admin1_code":"34.0",
    "gn:admin2_code":"203.0",
    "gn:asciiname":"Bariarpur Khuntahi",
    "gn:country_code":"IN",
    "gn:dem":75,
    "gn:feature_class":"P",
    "gn:feature_code":"PPL",
    "gn:name":"Bari\u0101rpur Khuntahi",
    "gn:population":0,
    "gn:timezone":"Asia/Kolkata",
    "iso:country":"IN",
    "ks:ks_alt_nam":"Bari\u0101rpur Khuntahi",
    "ks:ks_name":"Bariarpur Khuntahi",
    "ks:ks_pop":214,
    "ks:ks_type":"VILLAGE",
    "name:eng_x_preferred":[
        "Bariarpur Khuntahi"
    ],
    "name:eng_x_variant":[
        "Bari\u0101rpur Khuntahi"
    ],
    "wof:name":"Bariarpur Khuntahi",
    "wof:placetype":"locality",
    "wof:population":214
},
  "geometry": {"coordinates":[84.470185,26.637244],"type":"Point"}
}