{
  "type": "Feature",
  "properties": {
    "iso:country":"IN",
    "ks:ks_alt_nam":"UPOR BASTY",
    "ks:ks_name":"Upor Basty",
    "ks:ks_pop":248,
    "ks:ks_type":"HABITATION",
    "name:eng_x_preferred":[
        "Upor Basty"
    ],
    "wof:name":"Upor Basty",
    "wof:placetype":"locality",
    "wof:population":248
},
  "geometry": {"coordinates":[89.799716,26.613437],"type":"Point"}
}