{
  "type": "Feature",
  "properties": {
    "iso:country":"IN",
    "ks:ks_alt_nam":"D.Koppalu",
    "ks:ks_name":"D.koppalu",
    "ks:ks_pop":15,
    "ks:ks_type":"HABITATION",
    "name:eng_x_preferred":[
        "D.koppalu"
    ],
    "wof:name":"D.koppalu",
    "wof:placetype":"locality",
    "wof:population":15
},
  "geometry": {"coordinates":[75.83529,13.17922],"type":"Point"}
}