{
  "type": "Feature",
  "properties": {
    "iso:country":"IN",
    "ks:ks_name":"Loharan Purwa",
    "ks:ks_pop":196,
    "ks:ks_type":"HABITATION",
    "name:eng_x_preferred":[
        "Loharan Purwa"
    ],
    "wof:name":"Loharan Purwa",
    "wof:placetype":"locality",
    "wof:population":196
},
  "geometry": {"coordinates":[80.792687,25.358687],"type":"Point"}
}