{
  "type": "Feature",
  "properties": {
    "iso:country":"IN",
    "ks:ks_alt_nam":"Santhosh nagar",
    "ks:ks_name":"Santhosh Nagar",
    "ks:ks_pop":280,
    "ks:ks_type":"HABITATION",
    "ks:ks_uagg_main":0,
    "name:eng_x_preferred":[
        "Santhosh Nagar"
    ],
    "wof:name":"Santhosh Nagar",
    "wof:placetype":"neighbourhood",
    "wof:population":280
},
  "geometry": {"coordinates":[78.610365,10.756597],"type":"Point"}
}