{
  "type": "Feature",
  "properties": {
    "gn:admin1_code":"19",
    "gn:admin2_code":"579.0",
    "gn:asciiname":"Madri",
    "gn:country_code":"IN",
    "gn:dem":400,
    "gn:feature_class":"P",
    "gn:feature_code":"PPL",
    "gn:name":"Madri",
    "gn:population":0,
    "gn:timezone":"Asia/Kolkata",
    "iso:country":"IN",
    "name:ben_x_preferred":[
        "\u09ae\u09be\u09a6\u09cd\u09b0\u09c0"
    ],
    "name:deu_x_preferred":[
        "Madri"
    ],
    "name:epo_x_preferred":[
        "Madri"
    ],
    "name:fra_x_preferred":[
        "Madri"
    ],
    "name:guj_x_preferred":[
        "\u0aae\u0abe\u0aa6\u0acd\u0ab0\u0ac0"
    ],
    "name:hin_x_preferred":[
        "\u092e\u093e\u0926\u094d\u0930\u0940"
    ],
    "name:ind_x_preferred":[
        "Madri"
    ],
    "name:ita_x_preferred":[
        "Madri"
    ],
    "name:jav_x_preferred":[
        "Madrim"
    ],
    "name:kan_x_preferred":[
        "\u0cae\u0cbe\u0ca6\u0ccd\u0cb0\u0cbf"
    ],
    "name:mal_x_preferred":[
        "\u0d2e\u0d3e\u0d26\u0d4d\u0d30\u0d3f"
    ],
    "name:mar_x_preferred":[
        "\u092e\u093e\u0926\u094d\u0930\u0940"
    ],
    "name:nep_x_preferred":[
        "\u092e\u093e\u0926\u094d\u0930\u0940"
    ],
    "name:pol_x_preferred":[
        "Madri"
    ],
    "name:rus_x_preferred":[
        "\u041c\u0430\u0434\u0440\u0438"
    ],
    "name:san_x_preferred":[
        "\u092e\u093e\u0926\u094d\u0930\u0940"
    ],
    "name:spa_x_preferred":[
        "Madri"
    ],
    "name:sun_x_preferred":[
        "Madrim"
    ],
    "name:swe_x_preferred":[
        "Madri"
    ],
    "name:tam_x_preferred":[
        "\u0bae\u0bbe\u0ba4\u0bc1\u0bb0\u0bbf"
    ],
    "name:tel_x_preferred":[
        "\u0c2e\u0c3e\u0c26\u0c4d\u0c30\u0c3f"
    ],
    "name:zho_x_preferred":[
        "\u739b\u5fb7\u5229"
    ],
    "wof:name":"Madri",
    "wof:placetype":"locality"
},
  "geometry": {"coordinates":[76.86917,17.0469],"type":"Point"}
}