{
  "type": "Feature",
  "properties": {
    "gn:admin1_code":"19.0",
    "gn:admin2_code":"575.0",
    "gn:asciiname":"Kudupu",
    "gn:country_code":"IN",
    "gn:dem":57,
    "gn:feature_class":"P",
    "gn:feature_code":"PPLL",
    "gn:name":"Kudupu",
    "gn:population":0,
    "gn:timezone":"Asia/Kolkata",
    "iso:country":"IN",
    "name:tcy_x_preferred":[
        "\u0c95\u0cc1\u0ca1\u0ccd\u0caa\u0cc1"
    ],
    "wof:name":"Kudupu",
    "wof:placetype":"locality"
},
  "geometry": {"coordinates":[74.89343000000002,12.90241],"type":"Point"}
}