{
  "type": "Feature",
  "properties": {
    "gn:admin1_code":"9.0",
    "gn:admin2_code":"472.0",
    "gn:asciiname":"Kutan",
    "gn:country_code":"IN",
    "gn:dem":214,
    "gn:feature_class":"P",
    "gn:feature_code":"PPL",
    "gn:name":"Kutan",
    "gn:population":0,
    "gn:timezone":"Asia/Kolkata",
    "iso:country":"IN",
    "name:ceb_x_preferred":[
        "Kutan"
    ],
    "name:deu_x_preferred":[
        "Kutan"
    ],
    "wof:name":"Kutan",
    "wof:placetype":"locality"
},
  "geometry": {"coordinates":[73.61419000000002,23.597],"type":"Point"}
}