{
  "type": "Feature",
  "properties": {
    "gn:admin1_code":"11.0",
    "gn:admin2_code":"27.0",
    "gn:asciiname":"Bharkainu",
    "gn:country_code":"IN",
    "gn:dem":1311,
    "gn:feature_class":"P",
    "gn:feature_code":"PPL",
    "gn:name":"Bharkainu",
    "gn:population":0,
    "gn:timezone":"Asia/Kolkata",
    "iso:country":"IN",
    "wof:name":"Bharkainu",
    "wof:placetype":"locality"
},
  "geometry": {"coordinates":[77.12059000000001,31.26668],"type":"Point"}
}