{
  "type": "Feature",
  "properties": {
    "iso:country":"IN",
    "ks:ks_name":"Lurgi Khurd",
    "ks:ks_pop":737,
    "ks:ks_type":"VILLAGE",
    "name:eng_x_preferred":[
        "Lurgi Khurd"
    ],
    "wof:name":"Lurgi Khurd",
    "wof:placetype":"locality",
    "wof:population":737
},
  "geometry": {"coordinates":[83.352806,23.543636],"type":"Point"}
}