{
  "type": "Feature",
  "properties": {
    "gn:admin1_code":"36.0",
    "gn:admin2_code":"179.0",
    "gn:asciiname":"Tilokpur",
    "gn:country_code":"IN",
    "gn:dem":98,
    "gn:feature_class":"P",
    "gn:feature_code":"PPL",
    "gn:name":"Tilokpur",
    "gn:population":0,
    "gn:timezone":"Asia/Kolkata",
    "iso:country":"IN",
    "ks:ks_alt_nam":"Trilok pur",
    "ks:ks_name":"Trilok Pur",
    "ks:ks_pop":218,
    "ks:ks_type":"HABITATION",
    "name:eng_x_preferred":[
        "Trilok Pur"
    ],
    "name:eng_x_variant":[
        "Tilokpur"
    ],
    "name:hin_x_preferred":[
        "\u0924\u093f\u0932\u094b\u0915\u092a\u0941\u0930"
    ],
    "wof:name":"Trilok Pur",
    "wof:placetype":"locality",
    "wof:population":218
},
  "geometry": {"coordinates":[81.992546,26.07517],"type":"Point"}
}