{
  "type": "Feature",
  "properties": {
    "gn:admin1_code":"12.0",
    "gn:admin2_code":"011",
    "gn:asciiname":"Rangwar",
    "gn:country_code":"IN",
    "gn:dem":3311,
    "gn:feature_class":"P",
    "gn:feature_code":"PPL",
    "gn:name":"Rangw\u0101r",
    "gn:population":0,
    "gn:timezone":"Asia/Kolkata",
    "iso:country":"IN",
    "wof:name":"Rangwar",
    "wof:placetype":"locality"
},
  "geometry": {"coordinates":[74.98376999999998,34.2835],"type":"Point"}
}