{
  "type": "Feature",
  "properties": {
    "iso:country":"IN",
    "ks:ks_name":"Yeragahalli",
    "ks:ks_pop":246,
    "ks:ks_type":"HABITATION",
    "name:eng_x_preferred":[
        "Yeragahalli"
    ],
    "wof:name":"Yeragahalli",
    "wof:placetype":"locality",
    "wof:population":246
},
  "geometry": {"coordinates":[76.444058,12.138695],"type":"Point"}
}