{
  "type": "Feature",
  "properties": {
    "iso:country":"IN",
    "ks:ks_name":"Bara Kati",
    "ks:ks_pop":266,
    "ks:ks_type":"VILLAGE",
    "ks:ks_uagg_main":0,
    "name:eng_x_preferred":[
        "Bara Kati"
    ],
    "wof:name":"Bara Kati",
    "wof:placetype":"neighbourhood",
    "wof:population":266
},
  "geometry": {"coordinates":[87.115334,21.989319],"type":"Point"}
}