{
  "type": "Feature",
  "properties": {
    "gn:admin1_code":"16.0",
    "gn:admin2_code":"510.0",
    "gn:asciiname":"Murti",
    "gn:country_code":"IN",
    "gn:dem":196,
    "gn:feature_class":"P",
    "gn:feature_code":"PPL",
    "gn:name":"Murti",
    "gn:population":0,
    "gn:timezone":"Asia/Kolkata",
    "iso:country":"IN",
    "name:ara_x_preferred":[
        "\u0645\u0648\u0631\u062a\u064a"
    ],
    "name:ben_x_preferred":[
        "\u09ae\u09c2\u09b0\u09cd\u09a4\u09bf"
    ],
    "name:cat_x_preferred":[
        "Murti"
    ],
    "name:fra_x_preferred":[
        "Murti"
    ],
    "name:guj_x_preferred":[
        "\u0aae\u0ac2\u0ab0\u0acd\u0aa4\u0abf"
    ],
    "name:hin_x_preferred":[
        "\u092e\u0942\u0930\u094d\u0924\u093f"
    ],
    "name:hun_x_preferred":[
        "M\u00farti"
    ],
    "name:ind_x_preferred":[
        "Arca"
    ],
    "name:ita_x_preferred":[
        "Murti"
    ],
    "name:kan_x_preferred":[
        "\u0cae\u0cc2\u0cb0\u0ccd\u0ca4\u0cbf"
    ],
    "name:lit_x_preferred":[
        "M\u016brti"
    ],
    "name:mar_x_preferred":[
        "\u092e\u0942\u0930\u094d\u0924\u093f"
    ],
    "name:nld_x_preferred":[
        "Moerti"
    ],
    "name:pol_x_preferred":[
        "Murti"
    ],
    "name:por_x_preferred":[
        "Murti"
    ],
    "name:rus_x_preferred":[
        "\u041c\u0443\u0440\u0442\u0438"
    ],
    "name:sin_x_preferred":[
        "\u0dc4\u0dd2\u0db1\u0dca\u0daf\u0dd4 \u0db8\u0dd6\u0dbb\u0dca\u0dad\u0dd2"
    ],
    "name:spa_x_preferred":[
        "Murti"
    ],
    "name:sun_x_preferred":[
        "Arca"
    ],
    "name:tam_x_preferred":[
        "\u0bae\u0bc2\u0bb0\u0bcd\u0ba4\u0bcd\u0ba4\u0bbf"
    ],
    "name:tcy_x_preferred":[
        "\u0cae\u0cc2\u0cb0\u0ccd\u0ca4\u0cc6"
    ],
    "name:tha_x_preferred":[
        "\u0e21\u0e39\u0e23\u0e15\u0e34"
    ],
    "name:ukr_x_preferred":[
        "\u041c\u0443\u0440\u0442\u0456"
    ],
    "wof:name":"Murti",
    "wof:placetype":"locality"
},
  "geometry": {"coordinates":[79.02288,19.80252],"type":"Point"}
}