{
  "type": "Feature",
  "properties": {
    "iso:country":"IN",
    "ks:ks_name":"Haran Fa",
    "ks:ks_pop":687,
    "ks:ks_type":"HABITATION",
    "name:eng_x_preferred":[
        "Haran Fa"
    ],
    "wof:name":"Haran Fa",
    "wof:placetype":"locality",
    "wof:population":687
},
  "geometry": {"coordinates":[72.95650000000001,20.430111],"type":"Point"}
}