{
  "type": "Feature",
  "properties": {
    "iso:country":"IN",
    "ks:ks_name":"Sohdag Kalan",
    "ks:ks_pop":1076,
    "ks:ks_type":"VILLAGE",
    "name:eng_x_preferred":[
        "Sohdag Kalan"
    ],
    "wof:name":"Sohdag Kalan",
    "wof:placetype":"locality",
    "wof:population":1076
},
  "geometry": {"coordinates":[84.014484,24.282796],"type":"Point"}
}