{
  "type": "Feature",
  "properties": {
    "gn:admin1_code":"24.0",
    "gn:admin2_code":"104.0",
    "gn:asciiname":"Duona Ka Gadra",
    "gn:country_code":"IN",
    "gn:dem":438,
    "gn:feature_class":"P",
    "gn:feature_code":"PPL",
    "gn:name":"Du\u014dna Ka Gadra",
    "gn:population":0,
    "gn:timezone":"Asia/Kolkata",
    "iso:country":"IN",
    "wof:name":"Duona Ka Gadra",
    "wof:placetype":"locality"
},
  "geometry": {"coordinates":[76.26869000000001,27.36963],"type":"Point"}
}