{
  "type": "Feature",
  "properties": {
    "iso:country":"IN",
    "ks:ks_name":"Mallahan Tola",
    "ks:ks_pop":280,
    "ks:ks_type":"HABITATION",
    "ks:ks_uagg_main":0,
    "name:eng_x_preferred":[
        "Mallahan Tola"
    ],
    "wof:name":"Mallahan Tola",
    "wof:placetype":"neighbourhood",
    "wof:population":280
},
  "geometry": {"coordinates":[80.621557,28.467169],"type":"Point"}
}