{
  "type": "Feature",
  "properties": {
    "gn:admin1_code":"36.0",
    "gn:admin2_code":"150.0",
    "gn:asciiname":"Khajuria Ilaka Shiupuri",
    "gn:country_code":"IN",
    "gn:dem":163,
    "gn:feature_class":"P",
    "gn:feature_code":"PPL",
    "gn:name":"Khajuria Il\u0101ka Shiupuri",
    "gn:population":0,
    "gn:timezone":"Asia/Kolkata",
    "iso:country":"IN",
    "wof:name":"Khajuria Ilaka Shiupuri",
    "wof:placetype":"locality"
},
  "geometry": {"coordinates":[79.58526999999999,28.09071],"type":"Point"}
}