{
  "type": "Feature",
  "properties": {
    "gn:admin1_code":"34.0",
    "gn:admin2_code":"219.0",
    "gn:asciiname":"Bande",
    "gn:country_code":"IN",
    "gn:dem":57,
    "gn:feature_class":"P",
    "gn:feature_code":"PPL",
    "gn:name":"Bande",
    "gn:population":0,
    "gn:timezone":"Asia/Kolkata",
    "iso:country":"IN",
    "ks:ks_name":"Bande",
    "ks:ks_pop":972,
    "ks:ks_type":"VILLAGE",
    "ks:ks_uagg_main":0,
    "name:ara_x_preferred":[
        "\u0628\u0627\u0646\u062f\u064a"
    ],
    "name:bre_x_preferred":[
        "Bande"
    ],
    "name:cat_x_preferred":[
        "Bande"
    ],
    "name:ceb_x_preferred":[
        "Bande"
    ],
    "name:eng_x_preferred":[
        "Bande"
    ],
    "name:eus_x_preferred":[
        "Bande"
    ],
    "name:fra_x_preferred":[
        "Bande"
    ],
    "name:glg_x_preferred":[
        "Bande"
    ],
    "name:hun_x_preferred":[
        "Bande"
    ],
    "name:ita_x_preferred":[
        "Bande"
    ],
    "name:jpn_x_preferred":[
        "\u30d0\u30f3\u30c7"
    ],
    "name:lmo_x_preferred":[
        "Bande"
    ],
    "name:msa_x_preferred":[
        "Bande"
    ],
    "name:nld_x_preferred":[
        "Bande"
    ],
    "name:oci_x_preferred":[
        "Bande"
    ],
    "name:pol_x_preferred":[
        "Bande"
    ],
    "name:por_x_preferred":[
        "Bande"
    ],
    "name:rus_x_preferred":[
        "\u0411\u0430\u043d\u0434\u0435"
    ],
    "name:spa_x_preferred":[
        "Bande"
    ],
    "name:swe_x_preferred":[
        "Bande"
    ],
    "name:tur_x_preferred":[
        "Bande"
    ],
    "name:ukr_x_preferred":[
        "\u0411\u0430\u043d\u0434\u0435"
    ],
    "name:vie_x_preferred":[
        "Bande"
    ],
    "name:war_x_preferred":[
        "Bande"
    ],
    "name:zho_x_preferred":[
        "\u73ed\u5fb7"
    ],
    "wof:name":"Bande",
    "wof:placetype":"neighbourhood",
    "wof:population":972
},
  "geometry": {"coordinates":[84.92553599999999,25.956381],"type":"Point"}
}