{
  "type": "Feature",
  "properties": {
    "gn:admin1_code":"11",
    "gn:admin2_code":"33.0",
    "gn:asciiname":"Dhoanli",
    "gn:country_code":"IN",
    "gn:dem":2262,
    "gn:feature_class":"P",
    "gn:feature_code":"PPL",
    "gn:name":"Dho\u0101nli",
    "gn:population":0,
    "gn:timezone":"Asia/Kolkata",
    "iso:country":"IN",
    "wof:name":"Dhoanli",
    "wof:placetype":"locality"
},
  "geometry": {"coordinates":[77.64024000000001,30.99564],"type":"Point"}
}