{
  "type": "Feature",
  "properties": {
    "iso:country":"IN",
    "ks:ks_name":"Subhedarwadi",
    "ks:ks_pop":197,
    "ks:ks_type":"HABITATION",
    "ks:ks_uagg_main":0,
    "name:eng_x_preferred":[
        "Subhedarwadi"
    ],
    "wof:name":"Subhedarwadi",
    "wof:placetype":"neighbourhood",
    "wof:population":197
},
  "geometry": {"coordinates":[73.725138,15.730562],"type":"Point"}
}