{
  "type": "Feature",
  "properties": {
    "gn:country":"IN",
    "gn:fcode":"PPL",
    "gn:population":99462,
    "iso:country":"IN",
    "name:ben_x_preferred":[
        "\u0995\u09be\u09b6\u0997\u099e\u09cd\u099c"
    ],
    "name:ben_x_variant":[
        "\u0995\u09be\u09b8\u0997\u099e\u09cd\u099c"
    ],
    "name:bho_x_preferred":[
        "\u0915\u093e\u0938\u0917\u0902\u091c"
    ],
    "name:bpy_x_preferred":[
        "\u0995\u09be\u09b8\u0997\u099e\u09cd\u099c"
    ],
    "name:ceb_x_preferred":[
        "K\u0101sganj"
    ],
    "name:deu_x_preferred":[
        "Kasganj"
    ],
    "name:eng_x_preferred":[
        "Kasganj"
    ],
    "name:fra_x_preferred":[
        "Kasganj"
    ],
    "name:guj_x_preferred":[
        "\u0a95\u0abe\u0ab8\u0a97\u0a82\u0a9c"
    ],
    "name:hin_x_preferred":[
        "\u0915\u093e\u0938\u0917\u0902\u091c"
    ],
    "name:ita_x_preferred":[
        "Kasganj"
    ],
    "name:jpn_x_preferred":[
        "\u30ab\u30b9\u30ac\u30f3\u30b8"
    ],
    "name:kan_x_preferred":[
        "\u0c95\u0cbe\u0cb8\u0ccd\u0c97\u0ca8\u0ccd\u0c9c\u0ccd"
    ],
    "name:kor_x_preferred":[
        "\uce74\uc2a4\uac04\uc988"
    ],
    "name:mlg_x_preferred":[
        "Kasganj"
    ],
    "name:msa_x_preferred":[
        "Kasganj"
    ],
    "name:nan_x_preferred":[
        "Kasganj"
    ],
    "name:nep_x_preferred":[
        "\u0915\u093e\u0938\u0917\u0902\u091c"
    ],
    "name:new_x_preferred":[
        "\u0915\u0938\u094d\u0917\u091e\u094d\u091c"
    ],
    "name:nld_x_preferred":[
        "Kasganj"
    ],
    "name:pan_x_preferred":[
        "\u0a15\u0a3e\u0a38\u0a17\u0a70\u0a1c"
    ],
    "name:pol_x_preferred":[
        "Kasganj"
    ],
    "name:por_x_preferred":[
        "Kasganj"
    ],
    "name:rus_x_preferred":[
        "\u041a\u0430\u0441\u0433\u0430\u043d\u0434\u0436"
    ],
    "name:san_x_preferred":[
        "\u0915\u093e\u0938\u0917\u091e\u094d\u091c"
    ],
    "name:spa_x_preferred":[
        "Kasganj"
    ],
    "name:swe_x_preferred":[
        "Kasganj"
    ],
    "name:tam_x_preferred":[
        "\u0b95\u0bbe\u0bb8\u0bcd\u0b95\u0b9e\u0bcd"
    ],
    "name:tel_x_preferred":[
        "\u0c15\u0c3e\u0c38\u0c4d \u0c17\u0c02\u0c1c\u0c4d"
    ],
    "name:tha_x_preferred":[
        "\u0e01\u0e31\u0e2a\u0e04\u0e31\u0e19\u0e0a\u0e4c"
    ],
    "name:urd_x_preferred":[
        "\u06a9\u0627\u0633\u06af\u0646\u062c"
    ],
    "name:vie_x_preferred":[
        "Kasganj"
    ],
    "name:zho_x_preferred":[
        "\u5361\u65af\u7518\u6770"
    ],
    "qs:name":"K\u0101sganj",
    "qs:photos_9r":0,
    "qs:photos_sr":0,
    "qs:pop_sr":"8",
    "wd:wordcount":317,
    "wof:name":"K\u0101sganj",
    "wof:placetype":"locality",
    "wof:population":99462
},
  "geometry": {"coordinates":[78.64601999999999,27.80544],"type":"Point"}
}