{
  "type": "Feature",
  "properties": {
    "iso:country":"IN",
    "ks:ks_name":"Ambezara",
    "ks:ks_pop":104,
    "ks:ks_type":"HABITATION",
    "name:eng_x_preferred":[
        "Ambezara"
    ],
    "wof:name":"Ambezara",
    "wof:placetype":"locality",
    "wof:population":104
},
  "geometry": {"coordinates":[79.993803,19.144868],"type":"Point"}
}