{
  "type": "Feature",
  "properties": {
    "gn:admin1_code":"12.0",
    "gn:admin2_code":"018",
    "gn:asciiname":"Devigol",
    "gn:country_code":"IN",
    "gn:dem":2458,
    "gn:feature_class":"P",
    "gn:feature_code":"PPL",
    "gn:name":"D\u0113vig\u014dl",
    "gn:population":0,
    "gn:timezone":"Asia/Kolkata",
    "iso:country":"IN",
    "name:und_x_variant":[
        "D\u0113vig\u014dl",
        "Devigol"
    ],
    "wof:name":"Devigol",
    "wof:placetype":"locality"
},
  "geometry": {"coordinates":[75.96668000000003,33.14187],"type":"Point"}
}