{
  "type": "Feature",
  "properties": {
    "iso:country":"IN",
    "ks:ks_name":"Dakhin Nonoi",
    "ks:ks_pop":279,
    "ks:ks_type":"HABITATION",
    "name:eng_x_preferred":[
        "Dakhin Nonoi"
    ],
    "wof:name":"Dakhin Nonoi",
    "wof:placetype":"locality",
    "wof:population":279
},
  "geometry": {"coordinates":[91.497253,26.405609],"type":"Point"}
}