{
  "type": "Feature",
  "properties": {
    "iso:country":"IN",
    "ks:ks_name":"Naya Sanawara",
    "ks:ks_pop":1102,
    "ks:ks_type":"HABITATION",
    "name:eng_x_preferred":[
        "Naya Sanawara"
    ],
    "wof:name":"Naya Sanawara",
    "wof:placetype":"locality",
    "wof:population":1102
},
  "geometry": {"coordinates":[71.634596,26.832781],"type":"Point"}
}