{
  "type": "Feature",
  "properties": {
    "iso:country":"IN",
    "ks:ks_name":"Tewaridih",
    "ks:ks_pop":423,
    "ks:ks_type":"VILLAGE",
    "name:eng_x_preferred":[
        "Tewaridih"
    ],
    "wof:name":"Tewaridih",
    "wof:placetype":"locality",
    "wof:population":423
},
  "geometry": {"coordinates":[86.66108699999999,24.461977],"type":"Point"}
}