{
  "type": "Feature",
  "properties": {
    "gn:admin1_code":"39.0",
    "gn:admin2_code":"68.0",
    "gn:asciiname":"Nasirpur",
    "gn:country_code":"IN",
    "gn:dem":260,
    "gn:feature_class":"P",
    "gn:feature_code":"PPL",
    "gn:name":"Nas\u012brpur",
    "gn:population":0,
    "gn:timezone":"Asia/Kolkata",
    "iso:country":"IN",
    "name:fas_x_preferred":[
        "\u0646\u0635\u06cc\u0631\u067e\u0648\u0631"
    ],
    "name:fra_x_preferred":[
        "Nasirpur"
    ],
    "name:pan_x_preferred":[
        "\u0a28\u0a38\u0a30\u0a2a\u0a41\u0a30"
    ],
    "name:snd_x_preferred":[
        "\u0646\u0635\u0631 \u067e\u0648\u0631"
    ],
    "name:und_x_variant":[
        "Nas\u012brpur",
        "Afzalpur"
    ],
    "wof:name":"Nasirpur",
    "wof:placetype":"locality"
},
  "geometry": {"coordinates":[77.86606999999999,29.73847],"type":"Point"}
}