{
  "type": "Feature",
  "properties": {
    "iso:country":"IN",
    "ks:ks_name":"Aralkola",
    "ks:ks_pop":826,
    "ks:ks_type":"VILLAGE",
    "name:eng_x_preferred":[
        "Aralkola"
    ],
    "wof:name":"Aralkola",
    "wof:placetype":"locality",
    "wof:population":826
},
  "geometry": {"coordinates":[87.29465399999999,23.236331],"type":"Point"}
}