{
  "type": "Feature",
  "properties": {
    "iso:country":"IN",
    "ks:ks_name":"Kenjalewasti",
    "ks:ks_pop":293,
    "ks:ks_type":"HABITATION",
    "name:eng_x_preferred":[
        "Kenjalewasti"
    ],
    "wof:name":"Kenjalewasti",
    "wof:placetype":"locality",
    "wof:population":293
},
  "geometry": {"coordinates":[74.43422700000001,18.009745],"type":"Point"}
}