{
  "type": "Feature",
  "properties": {
    "iso:country":"IN",
    "ks:ks_name":"Suttalabail",
    "ks:ks_pop":31,
    "ks:ks_type":"HABITATION",
    "name:eng_x_preferred":[
        "Suttalabail"
    ],
    "wof:name":"Suttalabail",
    "wof:placetype":"locality",
    "wof:population":31
},
  "geometry": {"coordinates":[74.811834,14.472353],"type":"Point"}
}