{
  "type": "Feature",
  "properties": {
    "iso:country":"IN",
    "ks:ks_alt_nam":"IB Pada",
    "ks:ks_name":"Ib Pada",
    "ks:ks_pop":229,
    "ks:ks_type":"HABITATION",
    "name:eng_x_preferred":[
        "Ib Pada"
    ],
    "wof:name":"Ib Pada",
    "wof:placetype":"locality",
    "wof:population":229
},
  "geometry": {"coordinates":[82.796374,19.70556],"type":"Point"}
}