{
  "type": "Feature",
  "properties": {
    "iso:country":"IN",
    "ks:ks_name":"Chokyal Gaon",
    "ks:ks_pop":33,
    "ks:ks_type":"HABITATION",
    "name:eng_x_preferred":[
        "Chokyal Gaon"
    ],
    "wof:name":"Chokyal Gaon",
    "wof:placetype":"locality",
    "wof:population":33
},
  "geometry": {"coordinates":[80.260554,29.655967],"type":"Point"}
}