{
  "type": "Feature",
  "properties": {
    "iso:country":"IN",
    "ks:ks_name":"Padinyarepanam",
    "ks:ks_pop":150,
    "ks:ks_type":"HABITATION",
    "name:eng_x_preferred":[
        "Padinyarepanam"
    ],
    "wof:name":"Padinyarepanam",
    "wof:placetype":"locality",
    "wof:population":150
},
  "geometry": {"coordinates":[76.513857,10.541693],"type":"Point"}
}