{
  "type": "Feature",
  "properties": {
    "iso:country":"IN",
    "ks:ks_name":"Dhapara",
    "ks:ks_pop":30,
    "ks:ks_type":"VILLAGE",
    "name:eng_x_preferred":[
        "Dhapara"
    ],
    "wof:name":"Dhapara",
    "wof:placetype":"locality",
    "wof:population":30
},
  "geometry": {"coordinates":[88.27366000000001,23.635803],"type":"Point"}
}