{
  "type": "Feature",
  "properties": {
    "iso:country":"IN",
    "ks:ks_name":"Bhonynipura",
    "ks:ks_pop":153,
    "ks:ks_type":"VILLAGE",
    "ks:ks_uagg_main":0,
    "name:eng_x_preferred":[
        "Bhonynipura"
    ],
    "wof:name":"Bhonynipura",
    "wof:placetype":"neighbourhood",
    "wof:population":153
},
  "geometry": {"coordinates":[72.23095600000001,23.358165],"type":"Point"}
}