{
  "type": "Feature",
  "properties": {
    "iso:country":"IN",
    "ks:ks_name":"Jamani",
    "ks:ks_pop":179,
    "ks:ks_type":"HABITATION",
    "name:eng_x_preferred":[
        "Jamani"
    ],
    "wof:name":"Jamani",
    "wof:placetype":"locality",
    "wof:population":179
},
  "geometry": {"coordinates":[78.319372,30.542701],"type":"Point"}
}