{
  "type": "Feature",
  "properties": {
    "iso:country":"IN",
    "ks:ks_name":"Atagurla",
    "ks:ks_pop":16,
    "ks:ks_type":"VILLAGE",
    "name:eng_x_preferred":[
        "Atagurla"
    ],
    "wof:name":"Atagurla",
    "wof:placetype":"locality",
    "wof:population":16
},
  "geometry": {"coordinates":[83.209264,19.779116],"type":"Point"}
}