{
  "type": "Feature",
  "properties": {
    "gn:admin1_code":"34.0",
    "gn:admin2_code":"236.0",
    "gn:asciiname":"Kunin",
    "gn:country_code":"IN",
    "gn:dem":88,
    "gn:feature_class":"P",
    "gn:feature_code":"PPL",
    "gn:name":"Kunin",
    "gn:population":0,
    "gn:timezone":"Asia/Kolkata",
    "iso:country":"IN",
    "name:ceb_x_preferred":[
        "Kunin"
    ],
    "name:deu_x_preferred":[
        "Kunin"
    ],
    "name:rus_x_preferred":[
        "\u041a\u0443\u043d\u0438\u043d"
    ],
    "name:swe_x_preferred":[
        "Kunin"
    ],
    "name:ukr_x_preferred":[
        "\u041a\u0443\u043d\u0456\u043d"
    ],
    "wof:name":"Kunin",
    "wof:placetype":"locality"
},
  "geometry": {"coordinates":[84.75291999999997,25.02108],"type":"Point"}
}