{
  "type": "Feature",
  "properties": {
    "gn:admin1_code":"36",
    "gn:admin2_code":"145.0",
    "gn:asciiname":"Shahzadpur Gujjar",
    "gn:country_code":"IN",
    "gn:dem":177,
    "gn:feature_class":"P",
    "gn:feature_code":"PPL",
    "gn:name":"Shahz\u0101dpur Gujjar",
    "gn:population":0,
    "gn:timezone":"Asia/Kolkata",
    "iso:country":"IN",
    "ks:ks_name":"Shahzoopur Gujar",
    "ks:ks_pop":1077,
    "ks:ks_type":"VILLAGE",
    "ks:ks_uagg_main":0,
    "name:eng_x_preferred":[
        "Shahzoopur Gujar"
    ],
    "wof:name":"Shahzoopur Gujar",
    "wof:placetype":"neighbourhood",
    "wof:population":1077
},
  "geometry": {"coordinates":[77.654692,27.272116],"type":"Point"}
}