{
  "type": "Feature",
  "properties": {
    "gn:admin1_code":"19.0",
    "gn:admin2_code":"574.0",
    "gn:asciiname":"Heddurga",
    "gn:country_code":"IN",
    "gn:dem":952,
    "gn:feature_class":"P",
    "gn:feature_code":"PPL",
    "gn:name":"Heddurga",
    "gn:population":0,
    "gn:timezone":"Asia/Kolkata",
    "iso:country":"IN",
    "wof:name":"Heddurga",
    "wof:placetype":"locality"
},
  "geometry": {"coordinates":[75.91475,12.97219],"type":"Point"}
}