{
  "type": "Feature",
  "properties": {
    "iso:country":"IN",
    "ks:ks_name":"Saraswati Nagar",
    "ks:ks_pop":825,
    "ks:ks_type":"VILLAGE",
    "name:eng_x_preferred":[
        "Saraswati Nagar"
    ],
    "wof:name":"Saraswati Nagar",
    "wof:placetype":"locality",
    "wof:population":825
},
  "geometry": {"coordinates":[73.037144,26.970728],"type":"Point"}
}