{
  "type": "Feature",
  "properties": {
    "iso:country":"IN",
    "ks:ks_name":"Kurkuti",
    "ks:ks_pop":197,
    "ks:ks_type":"VILLAGE",
    "name:eng_x_preferred":[
        "Kurkuti"
    ],
    "wof:name":"Kurkuti",
    "wof:placetype":"locality",
    "wof:population":197
},
  "geometry": {"coordinates":[81.56154600000001,23.572762],"type":"Point"}
}