{
  "type": "Feature",
  "properties": {
    "iso:country":"IN",
    "ks:ks_name":"Sana Hansa",
    "ks:ks_pop":144,
    "ks:ks_type":"HABITATION",
    "name:eng_x_preferred":[
        "Sana Hansa"
    ],
    "wof:name":"Sana Hansa",
    "wof:placetype":"locality",
    "wof:population":144
},
  "geometry": {"coordinates":[83.422738,19.06689],"type":"Point"}
}