{
  "type": "Feature",
  "properties": {
    "iso:country":"IN",
    "ks:ks_alt_nam":"Gramby factory JN",
    "ks:ks_name":"Gramby Factory Jn",
    "ks:ks_pop":1230,
    "ks:ks_type":"HABITATION",
    "name:eng_x_preferred":[
        "Gramby Factory Jn"
    ],
    "wof:name":"Gramby Factory Jn",
    "wof:placetype":"locality",
    "wof:population":1230
},
  "geometry": {"coordinates":[77.044229,9.540987],"type":"Point"}
}