{
  "type": "Feature",
  "properties": {
    "gn:admin1_code":"24.0",
    "gn:admin2_code":"119.0",
    "gn:asciiname":"Jaitgarh",
    "gn:country_code":"IN",
    "gn:dem":423,
    "gn:feature_class":"P",
    "gn:feature_code":"PPL",
    "gn:name":"Jaitgarh",
    "gn:population":0,
    "gn:timezone":"Asia/Kolkata",
    "iso:country":"IN",
    "ks:ks_name":"Jetgarh",
    "ks:ks_pop":653,
    "ks:ks_type":"VILLAGE",
    "name:eng_x_preferred":[
        "Jetgarh"
    ],
    "name:eng_x_variant":[
        "Jaitgarh"
    ],
    "wof:name":"Jetgarh",
    "wof:placetype":"locality",
    "wof:population":653
},
  "geometry": {"coordinates":[74.31981399999999,26.298372],"type":"Point"}
}