{
  "type": "Feature",
  "properties": {
    "iso:country":"IN",
    "ks:ks_alt_nam":"Raja ka purwa",
    "ks:ks_name":"Raja Ka Purwa",
    "ks:ks_pop":264,
    "ks:ks_type":"HABITATION",
    "ks:ks_uagg_main":0,
    "name:eng_x_preferred":[
        "Raja Ka Purwa"
    ],
    "wof:name":"Raja Ka Purwa",
    "wof:placetype":"neighbourhood",
    "wof:population":264
},
  "geometry": {"coordinates":[79.482608,26.66711],"type":"Point"}
}