{
  "type": "Feature",
  "properties": {
    "iso:country":"IN",
    "ks:ks_name":"Thathagankottai",
    "ks:ks_pop":105,
    "ks:ks_type":"HABITATION",
    "name:eng_x_preferred":[
        "Thathagankottai"
    ],
    "wof:name":"Thathagankottai",
    "wof:placetype":"locality",
    "wof:population":105
},
  "geometry": {"coordinates":[78.99355199999999,9.894481],"type":"Point"}
}