{
  "type": "Feature",
  "properties": {
    "iso:country":"IN",
    "ks:ks_name":"Parmeshwarpur",
    "ks:ks_pop":1194,
    "ks:ks_type":"VILLAGE",
    "name:eng_x_preferred":[
        "Parmeshwarpur"
    ],
    "wof:name":"Parmeshwarpur",
    "wof:placetype":"locality",
    "wof:population":1194
},
  "geometry": {"coordinates":[83.05059300000001,23.480553],"type":"Point"}
}