{
  "type": "Feature",
  "properties": {
    "gn:admin1_code":"25.0",
    "gn:admin2_code":"633.0",
    "gn:asciiname":"Veppankuttaipalaiyampudur",
    "gn:country_code":"IN",
    "gn:dem":429,
    "gn:feature_class":"P",
    "gn:feature_code":"PPL",
    "gn:name":"Veppankuttaip\u0101laiyampud\u016br",
    "gn:population":0,
    "gn:timezone":"Asia/Kolkata",
    "iso:country":"IN",
    "wof:name":"Veppankuttaipalaiyampudur",
    "wof:placetype":"locality"
},
  "geometry": {"coordinates":[77.21023000000002,10.95181],"type":"Point"}
}