{
  "type": "Feature",
  "properties": {
    "iso:country":"IN",
    "ks:ks_name":"Upar Kuai",
    "ks:ks_pop":886,
    "ks:ks_type":"VILLAGE",
    "name:eng_x_preferred":[
        "Upar Kuai"
    ],
    "wof:name":"Upar Kuai",
    "wof:placetype":"locality",
    "wof:population":886
},
  "geometry": {"coordinates":[87.49562400000001,22.641196],"type":"Point"}
}