{
  "type": "Feature",
  "properties": {
    "iso:country":"IN",
    "ks:ks_name":"Ladda",
    "ks:ks_pop":107,
    "ks:ks_type":"VILLAGE",
    "name:eng_x_preferred":[
        "Ladda"
    ],
    "wof:name":"Ladda",
    "wof:placetype":"locality",
    "wof:population":107
},
  "geometry": {"coordinates":[86.658141,22.949712],"type":"Point"}
}