{
  "type": "Feature",
  "properties": {
    "gn:admin1_code":"36",
    "gn:admin2_code":"179.0",
    "gn:asciiname":"Ugharpur",
    "gn:country_code":"IN",
    "gn:dem":100,
    "gn:feature_class":"P",
    "gn:feature_code":"PPL",
    "gn:name":"Ugharpur",
    "gn:population":0,
    "gn:timezone":"Asia/Kolkata",
    "iso:country":"IN",
    "ks:ks_alt_nam":"UGHARPUR",
    "ks:ks_name":"Ugharpur",
    "ks:ks_pop":898,
    "ks:ks_type":"HABITATION",
    "name:eng_x_preferred":[
        "Ugharpur"
    ],
    "wof:name":"Ugharpur",
    "wof:placetype":"locality",
    "wof:population":898
},
  "geometry": {"coordinates":[82.17913799999999,26.264176],"type":"Point"}
}