{
  "type": "Feature",
  "properties": {
    "gn:admin1_code":"25.0",
    "gn:admin2_code":"606.0",
    "gn:asciiname":"Alatturai",
    "gn:country_code":"IN",
    "gn:dem":65,
    "gn:feature_class":"P",
    "gn:feature_code":"PPL",
    "gn:name":"Alatturai",
    "gn:population":0,
    "gn:timezone":"Asia/Kolkata",
    "iso:country":"IN",
    "wof:name":"Alatturai",
    "wof:placetype":"locality"
},
  "geometry": {"coordinates":[79.68321,12.56594],"type":"Point"}
}