{
  "type": "Feature",
  "properties": {
    "iso:country":"IN",
    "ks:ks_name":"Kothakapupeta",
    "ks:ks_pop":177,
    "ks:ks_type":"HABITATION",
    "name:eng_x_preferred":[
        "Kothakapupeta"
    ],
    "wof:name":"Kothakapupeta",
    "wof:placetype":"locality",
    "wof:population":177
},
  "geometry": {"coordinates":[83.374527,18.058347],"type":"Point"}
}