{
  "type": "Feature",
  "properties": {
    "iso:country":"IN",
    "ks:ks_name":"Chandan Khera",
    "ks:ks_pop":255,
    "ks:ks_type":"HABITATION",
    "name:eng_x_preferred":[
        "Chandan Khera"
    ],
    "wof:name":"Chandan Khera",
    "wof:placetype":"locality",
    "wof:population":255
},
  "geometry": {"coordinates":[80.463437,27.140899],"type":"Point"}
}