{
  "type": "Feature",
  "properties": {
    "gn:admin1_code":"16.0",
    "gn:admin2_code":"517",
    "gn:asciiname":"Kahoj Khuntivli",
    "gn:country_code":"IN",
    "gn:dem":21,
    "gn:feature_class":"P",
    "gn:feature_code":"PPL",
    "gn:name":"Kahoj Khuntivli",
    "gn:population":0,
    "gn:timezone":"Asia/Kolkata",
    "iso:country":"IN",
    "wof:name":"Kahoj Khuntivli",
    "wof:placetype":"neighbourhood"
},
  "geometry": {"coordinates":[73.18333,19.21667],"type":"Point"}
}