{
  "type": "Feature",
  "properties": {
    "iso:country":"IN",
    "ks:ks_name":"Kanshi Nagar",
    "ks:ks_pop":548,
    "ks:ks_type":"HABITATION",
    "name:eng_x_preferred":[
        "Kanshi Nagar"
    ],
    "wof:name":"Kanshi Nagar",
    "wof:placetype":"locality",
    "wof:population":548
},
  "geometry": {"coordinates":[75.743393,31.245755],"type":"Point"}
}