{
  "type": "Feature",
  "properties": {
    "iso:country":"IN",
    "ks:ks_name":"Amapatra",
    "ks:ks_pop":726,
    "ks:ks_type":"HABITATION",
    "name:eng_x_preferred":[
        "Amapatra"
    ],
    "wof:name":"Amapatra",
    "wof:placetype":"locality",
    "wof:population":726
},
  "geometry": {"coordinates":[83.54595,21.1833],"type":"Point"}
}