{
  "type": "Feature",
  "properties": {
    "iso:country":"IN",
    "ks:ks_name":"Golpur",
    "ks:ks_pop":300,
    "ks:ks_type":"VILLAGE",
    "name:eng_x_preferred":[
        "Golpur"
    ],
    "wof:name":"Golpur",
    "wof:placetype":"locality",
    "wof:population":300
},
  "geometry": {"coordinates":[75.463994,25.271015],"type":"Point"}
}