{
  "type": "Feature",
  "properties": {
    "gn:admin1_code":"12.0",
    "gn:admin2_code":"18.0",
    "gn:asciiname":"Garoba",
    "gn:country_code":"IN",
    "gn:dem":2848,
    "gn:feature_class":"P",
    "gn:feature_code":"PPL",
    "gn:name":"Gar\u014dba",
    "gn:population":0,
    "gn:timezone":"Asia/Kolkata",
    "iso:country":"IN",
    "wof:name":"Garoba",
    "wof:placetype":"locality"
},
  "geometry": {"coordinates":[75.87034,33.30568],"type":"Point"}
}