{
  "type": "Feature",
  "properties": {
    "iso:country":"IN",
    "ks:ks_name":"Kharianala",
    "ks:ks_pop":43,
    "ks:ks_type":"VILLAGE",
    "name:eng_x_preferred":[
        "Kharianala"
    ],
    "wof:name":"Kharianala",
    "wof:placetype":"locality",
    "wof:population":43
},
  "geometry": {"coordinates":[84.488043,19.122149],"type":"Point"}
}