{
  "type": "Feature",
  "properties": {
    "iso:country":"IN",
    "ks:ks_alt_nam":"HALWAI TOLA",
    "ks:ks_name":"Halwai Tola",
    "ks:ks_pop":152,
    "ks:ks_type":"HABITATION",
    "ks:ks_uagg_main":0,
    "name:eng_x_preferred":[
        "Halwai Tola"
    ],
    "wof:name":"Halwai Tola",
    "wof:placetype":"neighbourhood",
    "wof:population":152
},
  "geometry": {"coordinates":[86.722617,26.41062],"type":"Point"}
}