{
  "type": "Feature",
  "properties": {
    "iso:country":"IN",
    "ks:ks_name":"Chari Newada",
    "ks:ks_pop":390,
    "ks:ks_type":"HABITATION",
    "name:eng_x_preferred":[
        "Chari Newada"
    ],
    "wof:name":"Chari Newada",
    "wof:placetype":"locality",
    "wof:population":390
},
  "geometry": {"coordinates":[80.185158,26.633245],"type":"Point"}
}