{
  "type": "Feature",
  "properties": {
    "iso:country":"IN",
    "ks:ks_name":"Chiranjibpur",
    "ks:ks_pop":599,
    "ks:ks_type":"VILLAGE",
    "name:eng_x_preferred":[
        "Chiranjibpur"
    ],
    "wof:name":"Chiranjibpur",
    "wof:placetype":"locality",
    "wof:population":599
},
  "geometry": {"coordinates":[87.78759700000001,22.192897],"type":"Point"}
}