{
  "type": "Feature",
  "properties": {
    "iso:country":"IN",
    "ks:ks_name":"Lingapura D",
    "ks:ks_pop":96,
    "ks:ks_type":"HABITATION",
    "name:eng_x_preferred":[
        "Lingapura D"
    ],
    "wof:name":"Lingapura D",
    "wof:placetype":"locality",
    "wof:population":96
},
  "geometry": {"coordinates":[76.910124,15.760841],"type":"Point"}
}