{
  "type": "Feature",
  "properties": {
    "iso:country":"IN",
    "ks:ks_name":"Banamalipur",
    "ks:ks_pop":346,
    "ks:ks_type":"VILLAGE",
    "name:eng_x_preferred":[
        "Banamalipur"
    ],
    "wof:name":"Banamalipur",
    "wof:placetype":"locality",
    "wof:population":346
},
  "geometry": {"coordinates":[85.873158,19.98798],"type":"Point"}
}