{
  "type": "Feature",
  "properties": {
    "iso:country":"IN",
    "ks:ks_name":"Bajo Chak",
    "ks:ks_pop":959,
    "ks:ks_type":"HABITATION",
    "name:eng_x_preferred":[
        "Bajo Chak"
    ],
    "wof:name":"Bajo Chak",
    "wof:placetype":"locality",
    "wof:population":959
},
  "geometry": {"coordinates":[85.038487,24.761246],"type":"Point"}
}