{
  "type": "Feature",
  "properties": {
    "iso:country":"IN",
    "ks:ks_name":"Block No.29",
    "ks:ks_pop":400,
    "ks:ks_type":"VILLAGE",
    "name:eng_x_preferred":[
        "Block No.29"
    ],
    "wof:name":"Block No.29",
    "wof:placetype":"locality",
    "wof:population":400
},
  "geometry": {"coordinates":[92.250653,26.27951],"type":"Point"}
}