{
  "type": "Feature",
  "properties": {
    "iso:country":"IN",
    "ks:ks_alt_nam":"K\u0101nda",
    "ks:ks_name":"Kanda",
    "ks:ks_pop":395,
    "ks:ks_type":"VILLAGE",
    "name:eng_x_preferred":[
        "Kanda"
    ],
    "name:eng_x_variant":[
        "K\u0101nda"
    ],
    "wof:name":"Kanda",
    "wof:placetype":"locality",
    "wof:population":395
},
  "geometry": {"coordinates":[78.91576499999999,29.634842],"type":"Point"}
}