{
  "type": "Feature",
  "properties": {
    "iso:country":"IN",
    "ks:ks_alt_nam":"Tajpur  pt I",
    "ks:ks_name":"Tajpur Pt I",
    "ks:ks_pop":480,
    "ks:ks_type":"HABITATION",
    "name:eng_x_preferred":[
        "Tajpur Pt I"
    ],
    "name:eng_x_variant":[
        "Tajpur  pt I"
    ],
    "wof:name":"Tajpur Pt I",
    "wof:placetype":"locality",
    "wof:population":480
},
  "geometry": {"coordinates":[92.32288,24.845674],"type":"Point"}
}