{
  "type": "Feature",
  "properties": {
    "iso:country":"IN",
    "ks:ks_name":"Merdha",
    "ks:ks_pop":1405,
    "ks:ks_type":"VILLAGE",
    "ks:ks_uagg_main":0,
    "name:eng_x_preferred":[
        "Merdha"
    ],
    "wof:name":"Merdha",
    "wof:placetype":"neighbourhood",
    "wof:population":1405
},
  "geometry": {"coordinates":[86.464715,20.825585],"type":"Point"}
}