{
  "type": "Feature",
  "properties": {
    "iso:country":"IN",
    "ks:ks_name":"C Radhanagaqr",
    "ks:ks_pop":2213,
    "ks:ks_type":"HABITATION",
    "name:eng_x_preferred":[
        "C Radhanagaqr"
    ],
    "wof:name":"C Radhanagaqr",
    "wof:placetype":"locality",
    "wof:population":2213
},
  "geometry": {"coordinates":[88.708338,22.439254],"type":"Point"}
}