{
  "type": "Feature",
  "properties": {
    "gn:country":"IN",
    "gn:fcode":"PPL",
    "gn:pop":30049,
    "iso:country":"IN",
    "name:ben_x_preferred":[
        "\u09a7\u09a8\u09a7\u09c1\u0995\u09be"
    ],
    "name:bpy_x_preferred":[
        "\u09a7\u09be\u09a8\u09a7\u09c1\u0995\u09be"
    ],
    "name:bul_x_preferred":[
        "\u0414\u0445\u0430\u043d\u0434\u0445\u0443\u043a\u0430"
    ],
    "name:chi_x_preferred":[
        "\u8fbe\u6069\u675c\u5361"
    ],
    "name:dut_x_preferred":[
        "Dhandhuka"
    ],
    "name:eng_x_preferred":[
        "Dhandhuka"
    ],
    "name:fre_x_preferred":[
        "Dhandhuka"
    ],
    "name:ger_x_preferred":[
        "Dhandhuka"
    ],
    "name:guj_x_preferred":[
        "\u0aa7\u0a82\u0aa7\u0ac1\u0a95\u0abe"
    ],
    "name:ita_x_preferred":[
        "Dhandhuka"
    ],
    "name:jpn_x_preferred":[
        "\u30c0\u30f3\u30c9\u30a5\u30ab"
    ],
    "name:kan_x_preferred":[
        "\u0ca7\u0c82\u0ca7\u0cc1\u0c95"
    ],
    "name:kor_x_preferred":[
        "\ub2e4\ub450\uce74"
    ],
    "name:may_x_preferred":[
        "Dhandhuka"
    ],
    "name:new_x_preferred":[
        "\u0927\u0928\u094d\u0927\u0941\u0915\u093e"
    ],
    "name:por_x_preferred":[
        "Dhandhuka"
    ],
    "name:rus_x_preferred":[
        "\u0414\u0445\u0430\u043d\u0434\u0445\u0443\u043a\u0430"
    ],
    "name:spa_x_preferred":[
        "Dhandhuka"
    ],
    "name:swe_x_preferred":[
        "Dhandhuka"
    ],
    "name:tam_x_preferred":[
        "\u0ba4\u0ba8\u0bcd\u0ba4\u0bc1\u0b95\u0bbe"
    ],
    "name:tel_x_preferred":[
        "\u0c26\u0c02\u0c21\u0c41\u0c15"
    ],
    "name:unk_x_variant":[
        "Dhandhuka"
    ],
    "name:urd_x_preferred":[
        "\u062f\u06c1\u06cc\u0646\u0688\u06c1\u0648\u06a9\u0627"
    ],
    "name:vie_x_preferred":[
        "Dhandhuka"
    ],
    "qs:name":"Daduka",
    "qs:name_adm0":"India",
    "qs:name_adm1":"Gujarat",
    "qs:photos_9r":0,
    "qs:photos_sr":0,
    "qs:placetype":"Town",
    "qs:pop_sr":"7",
    "wof:name":"Daduka",
    "wof:placetype":"locality",
    "wof:population":30049
},
  "geometry": {"coordinates":[71.98663999999999,22.38185],"type":"Point"}
}