{
  "type": "Feature",
  "properties": {
    "iso:country":"IN",
    "ks:ks_name":"Chak Hazi",
    "ks:ks_pop":2297,
    "ks:ks_type":"VILLAGE",
    "name:eng_x_preferred":[
        "Chak Hazi"
    ],
    "wof:name":"Chak Hazi",
    "wof:placetype":"locality",
    "wof:population":2297
},
  "geometry": {"coordinates":[87.87369200000001,22.921387],"type":"Point"}
}