{
  "type": "Feature",
  "properties": {
    "iso:country":"IN",
    "ks:ks_name":"Gorhai",
    "ks:ks_pop":1683,
    "ks:ks_type":"VILLAGE",
    "ks:ks_uagg_main":0,
    "name:eng_x_preferred":[
        "Gorhai"
    ],
    "wof:name":"Gorhai",
    "wof:placetype":"neighbourhood",
    "wof:population":1683
},
  "geometry": {"coordinates":[81.069039,24.222746],"type":"Point"}
}