{
  "type": "Feature",
  "properties": {
    "iso:country":"IN",
    "ks:ks_name":"Baghalorawa",
    "ks:ks_pop":300,
    "ks:ks_type":"HABITATION",
    "name:eng_x_preferred":[
        "Baghalorawa"
    ],
    "wof:name":"Baghalorawa",
    "wof:placetype":"locality",
    "wof:population":300
},
  "geometry": {"coordinates":[82.731256,24.873874],"type":"Point"}
}