{
  "type": "Feature",
  "properties": {
    "gn:admin1_code":"10.0",
    "gn:admin2_code":"72.0",
    "gn:asciiname":"Mehra",
    "gn:country_code":"IN",
    "gn:dem":264,
    "gn:feature_class":"P",
    "gn:feature_code":"PPL",
    "gn:name":"Mehra",
    "gn:population":0,
    "gn:timezone":"Asia/Kolkata",
    "iso:country":"IN",
    "wof:name":"Mehra",
    "wof:placetype":"neighbourhood"
},
  "geometry": {"coordinates":[77.07334,30.03521],"type":"Point"}
}