{
  "type": "Feature",
  "properties": {
    "iso:country":"IN",
    "ks:ks_alt_nam":"SANJAY RAM LAL GIDHA RAM KI DHANI",
    "ks:ks_name":"Sanjay Ram Lal Gidha Ram Ki Dhani",
    "ks:ks_pop":63,
    "ks:ks_type":"HABITATION",
    "name:eng_x_preferred":[
        "Sanjay Ram Lal Gidha Ram Ki Dhani"
    ],
    "wof:name":"Sanjay Ram Lal Gidha Ram Ki Dhani",
    "wof:placetype":"locality",
    "wof:population":63
},
  "geometry": {"coordinates":[73.93347799999999,30.082317],"type":"Point"}
}