{
  "type": "Feature",
  "properties": {
    "iso:country":"IN",
    "ks:ks_name":"Mulijhara",
    "ks:ks_pop":190,
    "ks:ks_type":"VILLAGE",
    "name:eng_x_preferred":[
        "Mulijhara"
    ],
    "wof:name":"Mulijhara",
    "wof:placetype":"locality",
    "wof:population":190
},
  "geometry": {"coordinates":[86.03933499999999,20.613248],"type":"Point"}
}