{
  "type": "Feature",
  "properties": {
    "iso:country":"IN",
    "ks:ks_name":"Ramayyaputtuga",
    "ks:ks_pop":460,
    "ks:ks_type":"HABITATION",
    "ks:ks_uagg_main":0,
    "name:eng_x_preferred":[
        "Ramayyaputtuga"
    ],
    "wof:name":"Ramayyaputtuga",
    "wof:placetype":"neighbourhood",
    "wof:population":460
},
  "geometry": {"coordinates":[84.695801,19.017334],"type":"Point"}
}