{
  "type": "Feature",
  "properties": {
    "iso:country":"IN",
    "ks:ks_name":"Sirasing",
    "ks:ks_pop":554,
    "ks:ks_type":"VILLAGE",
    "name:eng_x_preferred":[
        "Sirasing"
    ],
    "wof:name":"Sirasing",
    "wof:placetype":"locality",
    "wof:population":554
},
  "geometry": {"coordinates":[87.857552,24.851236],"type":"Point"}
}