{
  "type": "Feature",
  "properties": {
    "iso:country":"IN",
    "ks:ks_name":"Bhat Tola",
    "ks:ks_pop":294,
    "ks:ks_type":"HABITATION",
    "ks:ks_uagg_main":0,
    "name:eng_x_preferred":[
        "Bhat Tola"
    ],
    "wof:name":"Bhat Tola",
    "wof:placetype":"neighbourhood",
    "wof:population":294
},
  "geometry": {"coordinates":[85.72402200000001,25.449172],"type":"Point"}
}