{
  "type": "Feature",
  "properties": {
    "gn:admin1_code":"35",
    "gn:admin2_code":"467.0",
    "gn:asciiname":"Dhamangaon",
    "gn:country_code":"IN",
    "gn:dem":264,
    "gn:feature_class":"P",
    "gn:feature_code":"PPL",
    "gn:name":"Dh\u0101mangaon",
    "gn:population":0,
    "gn:timezone":"Asia/Kolkata",
    "iso:country":"IN",
    "wof:name":"Dhamangaon",
    "wof:placetype":"locality"
},
  "geometry": {"coordinates":[76.21326999999999,21.17273],"type":"Point"}
}