{
  "type": "Feature",
  "properties": {
    "gn:admin1_code":"23.0",
    "gn:admin2_code":"052",
    "gn:asciiname":"Devinagar",
    "gn:country_code":"IN",
    "gn:dem":300,
    "gn:feature_class":"P",
    "gn:feature_code":"PPL",
    "gn:name":"Dev\u012bnagar",
    "gn:population":0,
    "gn:timezone":"Asia/Kolkata",
    "iso:country":"IN",
    "name:ara_x_preferred":[
        "\u062f\u064a\u0641\u064a \u0646\u0627\u062c\u0627\u0631"
    ],
    "name:ben_bn_x_preferred":[
        "\u09a6\u09c7\u09ac\u09c0\u09a8\u0997\u09b0"
    ],
    "name:ben_in_x_preferred":[
        "\u09a6\u09c7\u09ac\u09c0\u09a8\u0997\u09b0"
    ],
    "name:ceb_x_preferred":[
        "Devinagar"
    ],
    "name:guj_x_preferred":[
        "\u0aa6\u0ac7\u0ab5\u0ac0\u0aa8\u0a97\u0ab0"
    ],
    "name:hin_x_preferred":[
        "\u0926\u0947\u0935\u0940\u0928\u0917\u0930"
    ],
    "name:kan_x_preferred":[
        "\u0ca6\u0cc7\u0cb5\u0cbf\u0ca8\u0c97\u0cb0"
    ],
    "name:mal_x_preferred":[
        "\u0d26\u0d47\u0d35\u0d3f\u0d28\u0d17\u0d7c"
    ],
    "name:mar_x_preferred":[
        "\u0926\u0947\u0935\u0940\u0928\u0917\u0930"
    ],
    "name:msa_x_preferred":[
        "Devinagar"
    ],
    "name:nep_x_preferred":[
        "\u0926\u0947\u0935\u0940\u0928\u0917\u0930"
    ],
    "name:new_x_preferred":[
        "\u0926\u0947\u0935\u0940\u0928\u0917\u0930"
    ],
    "name:pan_x_preferred":[
        "\u0a26\u0a47\u0a35\u0a40\u0a28\u0a17\u0a30"
    ],
    "name:pol_x_preferred":[
        "Devinagar"
    ],
    "name:tam_x_preferred":[
        "\u0ba4\u0bc7\u0bb5\u0bbf\u0ba8\u0b95\u0bb0\u0bcd"
    ],
    "name:tel_x_preferred":[
        "\u0c26\u0c47\u0c35\u0c3f\u0c28\u0c17\u0c30\u0c4d"
    ],
    "name:urd_x_preferred":[
        "\u062f\u06cc\u0648\u06cc \u0646\u06af\u0631"
    ],
    "wof:name":"Devinagar",
    "wof:placetype":"locality"
},
  "geometry": {"coordinates":[76.83763,30.56305],"type":"Point"}
}