{
  "type": "Feature",
  "properties": {
    "gn:admin1_code":"23.0",
    "gn:admin2_code":"052",
    "gn:asciiname":"Devinagar",
    "gn:country_code":"IN",
    "gn:dem":300,
    "gn:feature_class":"P",
    "gn:feature_code":"PPL",
    "gn:name":"Dev\u012bnagar",
    "gn:population":0,
    "gn:timezone":"Asia/Kolkata",
    "iso:country":"IN",
    "wof:name":"Devinagar",
    "wof:placetype":"locality"
},
  "geometry": {"coordinates":[76.83763,30.56305],"type":"Point"}
}