{
  "type": "Feature",
  "properties": {
    "iso:country":"IN",
    "ks:ks_name":"Mupparajupalem",
    "ks:ks_pop":301,
    "ks:ks_type":"HABITATION",
    "ks:ks_uagg_main":0,
    "name:eng_x_preferred":[
        "Mupparajupalem"
    ],
    "wof:name":"Mupparajupalem",
    "wof:placetype":"neighbourhood",
    "wof:population":301
},
  "geometry": {"coordinates":[79.878077,15.434645],"type":"Point"}
}