{
  "type": "Feature",
  "properties": {
    "iso:country":"IN",
    "ks:ks_name":"Beniwalon Ki Dhani",
    "ks:ks_pop":1364,
    "ks:ks_type":"HABITATION",
    "name:eng_x_preferred":[
        "Beniwalon Ki Dhani"
    ],
    "wof:name":"Beniwalon Ki Dhani",
    "wof:placetype":"locality",
    "wof:population":1364
},
  "geometry": {"coordinates":[73.257245,26.902281],"type":"Point"}
}