{
  "type": "Feature",
  "properties": {
    "iso:country":"IN",
    "ks:ks_name":"Anakall Rd Start",
    "ks:ks_pop":668,
    "ks:ks_type":"HABITATION",
    "ks:ks_uagg_main":0,
    "name:eng_x_preferred":[
        "Anakall Rd Start"
    ],
    "wof:name":"Anakall Rd Start",
    "wof:placetype":"neighbourhood",
    "wof:population":668
},
  "geometry": {"coordinates":[76.229478,10.462148],"type":"Point"}
}