{
  "type": "Feature",
  "properties": {
    "iso:country":"IN",
    "ks:ks_name":"Rukni Pt IV",
    "ks:ks_pop":2079,
    "ks:ks_type":"VILLAGE",
    "name:eng_x_preferred":[
        "Rukni Pt IV"
    ],
    "wof:name":"Rukni Pt IV",
    "wof:placetype":"locality",
    "wof:population":2079
},
  "geometry": {"coordinates":[92.91878800000001,24.616013],"type":"Point"}
}