{
  "type": "Feature",
  "properties": {
    "iso:country":"IN",
    "ks:ks_alt_nam":"savarkut",
    "ks:ks_name":"Savarkut",
    "ks:ks_pop":114,
    "ks:ks_type":"HABITATION",
    "name:eng_x_preferred":[
        "Savarkut"
    ],
    "wof:name":"Savarkut",
    "wof:placetype":"locality",
    "wof:population":114
},
  "geometry": {"coordinates":[73.422944,19.703236],"type":"Point"}
}