{
  "type": "Feature",
  "properties": {
    "gn:admin1_code":"39.0",
    "gn:admin2_code":"132",
    "gn:asciiname":"Sodinagar Tongia",
    "gn:country_code":"IN",
    "gn:dem":449,
    "gn:feature_class":"P",
    "gn:feature_code":"PPL",
    "gn:name":"Sod\u012bnagar Tongia",
    "gn:population":0,
    "gn:timezone":"Asia/Kolkata",
    "iso:country":"IN",
    "name:und_x_variant":[
        "Sod\u012bnagar Tongia",
        "Sad\u012bnagor Tongia"
    ],
    "wof:name":"Sodinagar Tongia",
    "wof:placetype":"locality"
},
  "geometry": {"coordinates":[77.88704,30.17689],"type":"Point"}
}