{
  "type": "Feature",
  "properties": {
    "gn:admin1_code":"36.0",
    "gn:admin2_code":"155",
    "gn:asciiname":"Chandrampur",
    "gn:country_code":"IN",
    "gn:dem":138,
    "gn:feature_class":"P",
    "gn:feature_code":"PPL",
    "gn:name":"Chandr\u0101mpur",
    "gn:population":0,
    "gn:timezone":"Asia/Kolkata",
    "iso:country":"IN",
    "ks:ks_alt_nam":"Chandr\u0101mpur",
    "ks:ks_name":"Chandrampur",
    "ks:ks_pop":1087,
    "ks:ks_type":"VILLAGE",
    "name:eng_x_preferred":[
        "Chandrampur"
    ],
    "name:eng_x_variant":[
        "Chandr\u0101mpur"
    ],
    "wof:name":"Chandrampur",
    "wof:placetype":"locality",
    "wof:population":1087
},
  "geometry": {"coordinates":[79.811046,27.216598],"type":"Point"}
}