{
  "type": "Feature",
  "properties": {
    "gn:admin1_code":"36.0",
    "gn:admin2_code":"155",
    "gn:asciiname":"Chandrampur",
    "gn:country_code":"IN",
    "gn:dem":138,
    "gn:feature_class":"P",
    "gn:feature_code":"PPL",
    "gn:name":"Chandr\u0101mpur",
    "gn:population":0,
    "gn:timezone":"Asia/Kolkata",
    "iso:country":"IN",
    "wof:name":"Chandrampur",
    "wof:placetype":"locality"
},
  "geometry": {"coordinates":[79.81104999999999,27.2166],"type":"Point"}
}