{
  "type": "Feature",
  "properties": {
    "iso:country":"IN",
    "ks:ks_name":"39 GB",
    "ks:ks_pop":379,
    "ks:ks_type":"VILLAGE",
    "name:eng_x_preferred":[
        "39 GB"
    ],
    "wof:name":"39 GB",
    "wof:placetype":"locality",
    "wof:population":379
},
  "geometry": {"coordinates":[73.457245,29.224098],"type":"Point"}
}