{
  "type": "Feature",
  "properties": {
    "iso:country":"IN",
    "ks:ks_name":"Bardela",
    "ks:ks_pop":233,
    "ks:ks_type":"HABITATION",
    "name:eng_x_preferred":[
        "Bardela"
    ],
    "wof:name":"Bardela",
    "wof:placetype":"locality",
    "wof:population":233
},
  "geometry": {"coordinates":[80.905692,18.979931],"type":"Point"}
}