{
  "type": "Feature",
  "properties": {
    "iso:country":"IN",
    "ks:ks_alt_nam":"PAROMSAI",
    "ks:ks_name":"Paromsai",
    "ks:ks_pop":149,
    "ks:ks_type":"HABITATION",
    "name:eng_x_preferred":[
        "Paromsai"
    ],
    "wof:name":"Paromsai",
    "wof:placetype":"locality",
    "wof:population":149
},
  "geometry": {"coordinates":[85.39842400000001,22.229212],"type":"Point"}
}