{
  "type": "Feature",
  "properties": {
    "iso:country":"IN",
    "ks:ks_name":"Taratikar",
    "ks:ks_pop":319,
    "ks:ks_type":"VILLAGE",
    "name:eng_x_preferred":[
        "Taratikar"
    ],
    "wof:name":"Taratikar",
    "wof:placetype":"locality",
    "wof:population":319
},
  "geometry": {"coordinates":[87.286655,24.437585],"type":"Point"}
}