{
  "type": "Feature",
  "properties": {
    "iso:country":"IN",
    "ks:ks_alt_nam":"Neelamvari punta",
    "ks:ks_name":"Neelamvari Punta",
    "ks:ks_pop":272,
    "ks:ks_type":"HABITATION",
    "name:eng_x_preferred":[
        "Neelamvari Punta"
    ],
    "wof:name":"Neelamvari Punta",
    "wof:placetype":"locality",
    "wof:population":272
},
  "geometry": {"coordinates":[82.148453,16.602296],"type":"Point"}
}