{
  "type": "Feature",
  "properties": {
    "gn:admin1_code":"11",
    "gn:admin2_code":"23.0",
    "gn:asciiname":"Deoki",
    "gn:country_code":"IN",
    "gn:dem":2006,
    "gn:feature_class":"P",
    "gn:feature_code":"PPL",
    "gn:name":"Deoki",
    "gn:population":0,
    "gn:timezone":"Asia/Kolkata",
    "iso:country":"IN",
    "wof:name":"Deoki",
    "wof:placetype":"locality"
},
  "geometry": {"coordinates":[76.48338000000003,32.4564],"type":"Point"}
}