{
  "type": "Feature",
  "properties": {
    "gn:admin1_code":"13.0",
    "gn:admin2_code":"600.0",
    "gn:asciiname":"Kulakkada Kizhakku",
    "gn:country_code":"IN",
    "gn:dem":31,
    "gn:feature_class":"P",
    "gn:feature_code":"PPL",
    "gn:name":"Kulakkada Kizhakku",
    "gn:population":0,
    "gn:timezone":"Asia/Kolkata",
    "iso:country":"IN",
    "wof:name":"Kulakkada Kizhakku",
    "wof:placetype":"locality"
},
  "geometry": {"coordinates":[76.74024,9.07612],"type":"Point"}
}