{
  "type": "Feature",
  "properties": {
    "iso:country":"IN",
    "ks:ks_name":"Kadapada",
    "ks:ks_pop":149,
    "ks:ks_type":"HABITATION",
    "name:eng_x_preferred":[
        "Kadapada"
    ],
    "wof:name":"Kadapada",
    "wof:placetype":"locality",
    "wof:population":149
},
  "geometry": {"coordinates":[73.031037,19.962542],"type":"Point"}
}