{
  "type": "Feature",
  "properties": {
    "iso:country":"IN",
    "ks:ks_name":"Sanjeevipuram",
    "ks:ks_pop":310,
    "ks:ks_type":"HABITATION",
    "name:eng_x_preferred":[
        "Sanjeevipuram"
    ],
    "wof:name":"Sanjeevipuram",
    "wof:placetype":"locality",
    "wof:population":310
},
  "geometry": {"coordinates":[79.46402399999999,13.185871],"type":"Point"}
}