{
  "type": "Feature",
  "properties": {
    "gn:admin1_code":"36",
    "gn:admin2_code":"142.0",
    "gn:asciiname":"Agarpur",
    "gn:country_code":"IN",
    "gn:dem":203,
    "gn:feature_class":"P",
    "gn:feature_code":"PPL",
    "gn:name":"Agarpur",
    "gn:population":0,
    "gn:timezone":"Asia/Kolkata",
    "iso:country":"IN",
    "name:und_x_variant":[
        "Mirz\u0101pur"
    ],
    "wof:name":"Agarpur",
    "wof:placetype":"neighbourhood"
},
  "geometry": {"coordinates":[77.95489999999999,28.42119],"type":"Point"}
}