{
  "type": "Feature",
  "properties": {
    "gn:admin1_code":"35.0",
    "gn:admin2_code":"427",
    "gn:asciiname":"Nauraj",
    "gn:country_code":"IN",
    "gn:dem":499,
    "gn:feature_class":"P",
    "gn:feature_code":"PPL",
    "gn:name":"Naur\u0101j",
    "gn:population":0,
    "gn:timezone":"Asia/Kolkata",
    "iso:country":"IN",
    "wof:name":"Nauraj",
    "wof:placetype":"locality"
},
  "geometry": {"coordinates":[78.94346999999998,24.11479],"type":"Point"}
}