{
  "type": "Feature",
  "properties": {
    "iso:country":"IN",
    "ks:ks_name":"Sohara",
    "ks:ks_pop":1231,
    "ks:ks_type":"VILLAGE",
    "name:eng_x_preferred":[
        "Sohara"
    ],
    "wof:name":"Sohara",
    "wof:placetype":"locality",
    "wof:population":1231
},
  "geometry": {"coordinates":[71.951139,26.172164],"type":"Point"}
}