{
  "type": "Feature",
  "properties": {
    "gn:admin1_code":"35",
    "gn:admin2_code":"463.0",
    "gn:asciiname":"Baheraha",
    "gn:country_code":"IN",
    "gn:dem":367,
    "gn:feature_class":"P",
    "gn:feature_code":"PPL",
    "gn:name":"Baheraha",
    "gn:population":0,
    "gn:timezone":"Asia/Kolkata",
    "iso:country":"IN",
    "ks:ks_name":"Baheraha",
    "ks:ks_pop":451,
    "ks:ks_type":"VILLAGE",
    "name:eng_x_preferred":[
        "Baheraha"
    ],
    "name:eng_x_variant":[
        "Beheraha"
    ],
    "wof:name":"Baheraha",
    "wof:placetype":"locality",
    "wof:population":451
},
  "geometry": {"coordinates":[82.25543,24.20691],"type":"Point"}
}