{
  "type": "Feature",
  "properties": {
    "iso:country":"IN",
    "ks:ks_name":"Baidarchakla",
    "ks:ks_pop":102,
    "ks:ks_type":"HABITATION",
    "name:eng_x_preferred":[
        "Baidarchakla"
    ],
    "wof:name":"Baidarchakla",
    "wof:placetype":"locality",
    "wof:population":102
},
  "geometry": {"coordinates":[86.722281,26.290958],"type":"Point"}
}