{
  "type": "Feature",
  "properties": {
    "iso:country":"IN",
    "ks:ks_name":"Sonaia",
    "ks:ks_pop":300,
    "ks:ks_type":"VILLAGE",
    "name:eng_x_preferred":[
        "Sonaia"
    ],
    "wof:name":"Sonaia",
    "wof:placetype":"locality",
    "wof:population":300
},
  "geometry": {"coordinates":[86.551928,24.630739],"type":"Point"}
}