{
  "type": "Feature",
  "properties": {
    "iso:country":"IN",
    "ks:ks_name":"Tilmani",
    "ks:ks_pop":521,
    "ks:ks_type":"HABITATION",
    "name:eng_x_preferred":[
        "Tilmani"
    ],
    "wof:name":"Tilmani",
    "wof:placetype":"locality",
    "wof:population":521
},
  "geometry": {"coordinates":[81.895355,24.279125],"type":"Point"}
}