{
  "type": "Feature",
  "properties": {
    "gn:admin1_code":"38.0",
    "gn:admin2_code":"352.0",
    "gn:asciiname":"Bara Tetria",
    "gn:country_code":"IN",
    "gn:dem":46,
    "gn:feature_class":"P",
    "gn:feature_code":"PPL",
    "gn:name":"Bara Tetria",
    "gn:population":0,
    "gn:timezone":"Asia/Kolkata",
    "iso:country":"IN",
    "ks:ks_name":"Bara Tetariya",
    "ks:ks_pop":147,
    "ks:ks_type":"VILLAGE",
    "ks:ks_uagg_main":0,
    "name:eng_x_preferred":[
        "Bara Tetariya"
    ],
    "wof:name":"Bara Tetariya",
    "wof:placetype":"neighbourhood",
    "wof:population":147
},
  "geometry": {"coordinates":[87.675442,25.217502],"type":"Point"}
}