{
  "type": "Feature",
  "properties": {
    "iso:country":"IN",
    "ks:ks_name":"Brahmapanga A",
    "ks:ks_pop":158,
    "ks:ks_type":"HABITATION",
    "name:eng_x_preferred":[
        "Brahmapanga A"
    ],
    "wof:name":"Brahmapanga A",
    "wof:placetype":"locality",
    "wof:population":158
},
  "geometry": {"coordinates":[84.007176,19.953983],"type":"Point"}
}