{
  "type": "Feature",
  "properties": {
    "iso:country":"IN",
    "ks:ks_name":"Beechanahalli",
    "ks:ks_pop":91,
    "ks:ks_type":"HABITATION",
    "name:eng_x_preferred":[
        "Beechanahalli"
    ],
    "wof:name":"Beechanahalli",
    "wof:placetype":"locality",
    "wof:population":91
},
  "geometry": {"coordinates":[75.96096,12.951115],"type":"Point"}
}