{
  "type": "Feature",
  "properties": {
    "iso:country":"IN",
    "ks:ks_alt_nam":"Chounki FV",
    "ks:ks_name":"Chounki Fv",
    "ks:ks_pop":189,
    "ks:ks_type":"HABITATION",
    "name:eng_x_preferred":[
        "Chounki Fv"
    ],
    "wof:name":"Chounki Fv",
    "wof:placetype":"locality",
    "wof:population":189
},
  "geometry": {"coordinates":[80.090543,23.014591],"type":"Point"}
}