{
  "type": "Feature",
  "properties": {
    "iso:country":"IN",
    "ks:ks_alt_nam":"Chintaram para",
    "ks:ks_name":"Chintaram Para",
    "ks:ks_pop":191,
    "ks:ks_type":"HABITATION",
    "name:eng_x_preferred":[
        "Chintaram Para"
    ],
    "wof:name":"Chintaram Para",
    "wof:placetype":"locality",
    "wof:population":191
},
  "geometry": {"coordinates":[91.77003499999999,23.129535],"type":"Point"}
}