{
  "type": "Feature",
  "properties": {
    "iso:country":"IN",
    "ks:ks_name":"Eerandoddy",
    "ks:ks_pop":84,
    "ks:ks_type":"HABITATION",
    "name:eng_x_preferred":[
        "Eerandoddy"
    ],
    "wof:name":"Eerandoddy",
    "wof:placetype":"locality",
    "wof:population":84
},
  "geometry": {"coordinates":[77.592735,12.321883],"type":"Point"}
}