{
  "type": "Feature",
  "properties": {
    "gn:admin1_code":"31",
    "gn:admin2_code":"283.0",
    "gn:asciiname":"Zemabawk",
    "gn:country_code":"IN",
    "gn:dem":891,
    "gn:feature_class":"P",
    "gn:feature_code":"PPL",
    "gn:name":"Zem\u0101bawk",
    "gn:population":0,
    "gn:timezone":"Asia/Kolkata",
    "iso:country":"IN",
    "wof:name":"Zemabawk",
    "wof:placetype":"neighbourhood"
},
  "geometry": {"coordinates":[92.74523000000001,23.73916],"type":"Point"}
}