{
  "type": "Feature",
  "properties": {
    "iso:country":"IN",
    "ks:ks_name":"Chilko",
    "ks:ks_pop":96,
    "ks:ks_type":"HABITATION",
    "name:eng_x_preferred":[
        "Chilko"
    ],
    "wof:name":"Chilko",
    "wof:placetype":"locality",
    "wof:population":96
},
  "geometry": {"coordinates":[86.405924,24.776416],"type":"Point"}
}