{
  "type": "Feature",
  "properties": {
    "gn:admin1_code":"34.0",
    "gn:admin2_code":"230.0",
    "gn:asciiname":"Sain",
    "gn:country_code":"IN",
    "gn:dem":64,
    "gn:feature_class":"P",
    "gn:feature_code":"PPL",
    "gn:name":"S\u0101in",
    "gn:population":0,
    "gn:timezone":"Asia/Kolkata",
    "iso:country":"IN",
    "name:bre_x_preferred":[
        "Sain"
    ],
    "name:rus_x_preferred":[
        "Sain Records"
    ],
    "wof:name":"Sain",
    "wof:placetype":"locality"
},
  "geometry": {"coordinates":[85.10836,25.36009],"type":"Point"}
}