{
  "type": "Feature",
  "properties": {
    "iso:country":"IN",
    "ks:ks_name":"Bodhan Purwa",
    "ks:ks_pop":56,
    "ks:ks_type":"HABITATION",
    "name:eng_x_preferred":[
        "Bodhan Purwa"
    ],
    "wof:name":"Bodhan Purwa",
    "wof:placetype":"locality",
    "wof:population":56
},
  "geometry": {"coordinates":[81.025109,25.619071],"type":"Point"}
}