{
  "type": "Feature",
  "properties": {
    "iso:country":"IN",
    "ks:ks_alt_nam":"CHAMAR  TOLA",
    "ks:ks_name":"Chamar Tola",
    "ks:ks_pop":117,
    "ks:ks_type":"HABITATION",
    "name:eng_x_preferred":[
        "Chamar Tola"
    ],
    "name:eng_x_variant":[
        "CHAMAR  TOLA"
    ],
    "wof:name":"Chamar Tola",
    "wof:placetype":"locality",
    "wof:population":117
},
  "geometry": {"coordinates":[83.921215,26.480984],"type":"Point"}
}