{
  "type": "Feature",
  "properties": {
    "iso:country":"IN",
    "ks:ks_alt_nam":"Sh\u0101hjah\u0101npur",
    "ks:ks_name":"Shahjahanpur",
    "ks:ks_type":"VILLAGE",
    "name:eng_x_preferred":[
        "Shahjahanpur"
    ],
    "name:eng_x_variant":[
        "Sh\u0101hjah\u0101npur"
    ],
    "wof:name":"Shahjahanpur",
    "wof:placetype":"locality"
},
  "geometry": {"coordinates":[78.621301,29.421906],"type":"Point"}
}