{
  "type": "Feature",
  "properties": {
    "iso:country":"IN",
    "ks:ks_name":"Pujari Betta",
    "ks:ks_pop":9,
    "ks:ks_type":"HABITATION",
    "name:eng_x_preferred":[
        "Pujari Betta"
    ],
    "wof:name":"Pujari Betta",
    "wof:placetype":"locality",
    "wof:population":9
},
  "geometry": {"coordinates":[75.719722,12.62],"type":"Point"}
}