{
  "type": "Feature",
  "properties": {
    "iso:country":"IN",
    "ks:ks_name":"Garh Bisora Khamhariya",
    "ks:ks_pop":846,
    "ks:ks_type":"HABITATION",
    "name:eng_x_preferred":[
        "Garh Bisora Khamhariya"
    ],
    "wof:name":"Garh Bisora Khamhariya",
    "wof:placetype":"locality",
    "wof:population":846
},
  "geometry": {"coordinates":[80.451381,23.130472],"type":"Point"}
}