{
  "type": "Feature",
  "properties": {
    "iso:country":"IN",
    "ks:ks_name":"Raotaratola 2",
    "ks:ks_pop":1628,
    "ks:ks_type":"HABITATION",
    "name:eng_x_preferred":[
        "Raotaratola 2"
    ],
    "wof:name":"Raotaratola 2",
    "wof:placetype":"locality",
    "wof:population":1628
},
  "geometry": {"coordinates":[86.613996,22.589066],"type":"Point"}
}