{
  "type": "Feature",
  "properties": {
    "iso:country":"IN",
    "ks:ks_name":"Kotda",
    "ks:ks_pop":264,
    "ks:ks_type":"HABITATION",
    "name:eng_x_preferred":[
        "Kotda"
    ],
    "wof:name":"Kotda",
    "wof:placetype":"locality",
    "wof:population":264
},
  "geometry": {"coordinates":[76.32029199999999,23.937822],"type":"Point"}
}