{
  "type": "Feature",
  "properties": {
    "iso:country":"IN",
    "ks:ks_name":"Aadiwasi Tola",
    "ks:ks_pop":272,
    "ks:ks_type":"HABITATION",
    "name:eng_x_preferred":[
        "Aadiwasi Tola"
    ],
    "wof:name":"Aadiwasi Tola",
    "wof:placetype":"locality",
    "wof:population":272
},
  "geometry": {"coordinates":[84.214073,24.008996],"type":"Point"}
}