{
  "type": "Feature",
  "properties": {
    "iso:country":"IN",
    "ks:ks_name":"Khantakhola",
    "ks:ks_pop":8,
    "ks:ks_type":"VILLAGE",
    "name:eng_x_preferred":[
        "Khantakhola"
    ],
    "wof:name":"Khantakhola",
    "wof:placetype":"locality",
    "wof:population":8
},
  "geometry": {"coordinates":[85.69486000000001,20.893286],"type":"Point"}
}