{
  "type": "Feature",
  "properties": {
    "gn:admin1_code":"24",
    "gn:admin2_code":"115.0",
    "gn:asciiname":"Semarkhia",
    "gn:country_code":"IN",
    "gn:dem":143,
    "gn:feature_class":"P",
    "gn:feature_code":"PPL",
    "gn:name":"Semarkhia",
    "gn:population":0,
    "gn:timezone":"Asia/Kolkata",
    "iso:country":"IN",
    "wof:name":"Semarkhia",
    "wof:placetype":"locality"
},
  "geometry": {"coordinates":[72.40541,26.17414],"type":"Point"}
}