{
  "type": "Feature",
  "properties": {
    "iso:country":"IN",
    "ks:ks_name":"Char Salikadaha",
    "ks:ks_pop":0,
    "ks:ks_type":"VILLAGE",
    "name:eng_x_preferred":[
        "Char Salikadaha"
    ],
    "wof:name":"Char Salikadaha",
    "wof:placetype":"locality",
    "wof:population":0
},
  "geometry": {"coordinates":[88.49511800000001,24.054103],"type":"Point"}
}