{
  "type": "Feature",
  "properties": {
    "gn:admin1_code":"35.0",
    "gn:admin2_code":"456.0",
    "gn:asciiname":"Potalpani",
    "gn:country_code":"IN",
    "gn:dem":613,
    "gn:feature_class":"P",
    "gn:feature_code":"PPL",
    "gn:name":"Pot\u0101lp\u0101ni",
    "gn:population":0,
    "gn:timezone":"Asia/Kolkata",
    "iso:country":"IN",
    "wof:name":"Potalpani",
    "wof:placetype":"locality"
},
  "geometry": {"coordinates":[79.4144,22.26748],"type":"Point"}
}