{
  "type": "Feature",
  "properties": {
    "gn:admin1_code":"35",
    "gn:admin2_code":"440.0",
    "gn:asciiname":"Piplia Buzurg",
    "gn:country_code":"IN",
    "gn:dem":189,
    "gn:feature_class":"P",
    "gn:feature_code":"PPL",
    "gn:name":"P\u012bpli\u0101 Buzurg",
    "gn:population":0,
    "gn:timezone":"Asia/Kolkata",
    "iso:country":"IN",
    "name:und_x_variant":[
        "P\u012bpli\u0101 Buzurg",
        "P\u012bplia"
    ],
    "wof:name":"Piplia Buzurg",
    "wof:placetype":"locality"
},
  "geometry": {"coordinates":[75.85982,22.23496],"type":"Point"}
}