{
  "type": "Feature",
  "properties": {
    "gn:admin1_code":"35",
    "gn:admin2_code":"428.0",
    "gn:asciiname":"Harduapanji",
    "gn:country_code":"IN",
    "gn:dem":411,
    "gn:feature_class":"P",
    "gn:feature_code":"PPL",
    "gn:name":"Hardu\u0101p\u0101nji",
    "gn:population":0,
    "gn:timezone":"Asia/Kolkata",
    "iso:country":"IN",
    "ks:ks_name":"Hardua Panji",
    "ks:ks_pop":899,
    "ks:ks_type":"VILLAGE",
    "name:eng_x_preferred":[
        "Hardua Panji"
    ],
    "name:eng_x_variant":[
        "Harduapanji"
    ],
    "wof:name":"Hardua Panji",
    "wof:placetype":"locality",
    "wof:population":899
},
  "geometry": {"coordinates":[79.500674,23.45207],"type":"Point"}
}