{
  "type": "Feature",
  "properties": {
    "gn:admin1_code":"35",
    "gn:admin2_code":"455.0",
    "gn:asciiname":"Bankatawa",
    "gn:country_code":"IN",
    "gn:dem":502,
    "gn:feature_class":"P",
    "gn:feature_code":"PPL",
    "gn:name":"B\u0101nk\u0101tawa",
    "gn:population":0,
    "gn:timezone":"Asia/Kolkata",
    "iso:country":"IN",
    "ks:ks_name":"Bakatawa",
    "ks:ks_pop":430,
    "ks:ks_type":"VILLAGE",
    "name:eng_x_preferred":[
        "Bakatawa"
    ],
    "name:eng_x_variant":[
        "Bankatawa"
    ],
    "wof:name":"Bakatawa",
    "wof:placetype":"locality",
    "wof:population":430
},
  "geometry": {"coordinates":[78.356403,22.117769],"type":"Point"}
}