{
  "type": "Feature",
  "properties": {
    "iso:country":"IN",
    "ks:ks_name":"Mouman",
    "ks:ks_pop":835,
    "ks:ks_type":"VILLAGE",
    "ks:ks_uagg_main":0,
    "name:eng_x_preferred":[
        "Mouman"
    ],
    "wof:name":"Mouman",
    "wof:placetype":"neighbourhood",
    "wof:population":835
},
  "geometry": {"coordinates":[91.218785,25.950605],"type":"Point"}
}