{
  "type": "Feature",
  "properties": {
    "gn:admin1_code":"11.0",
    "gn:admin2_code":"31.0",
    "gn:asciiname":"Malga",
    "gn:country_code":"IN",
    "gn:dem":1264,
    "gn:feature_class":"P",
    "gn:feature_code":"PPL",
    "gn:name":"M\u0101lga",
    "gn:population":0,
    "gn:timezone":"Asia/Kolkata",
    "iso:country":"IN",
    "wof:name":"Malga",
    "wof:placetype":"locality"
},
  "geometry": {"coordinates":[77.06562,30.9925],"type":"Point"}
}