{
  "type": "Feature",
  "properties": {
    "iso:country":"IN",
    "ks:ks_alt_nam":"Moti mal faliya",
    "ks:ks_name":"Moti Mal Faliya",
    "ks:ks_pop":198,
    "ks:ks_type":"HABITATION",
    "name:eng_x_preferred":[
        "Moti Mal Faliya"
    ],
    "wof:name":"Moti Mal Faliya",
    "wof:placetype":"locality",
    "wof:population":198
},
  "geometry": {"coordinates":[73.455611,20.568472],"type":"Point"}
}