{
  "type": "Feature",
  "properties": {
    "gn:admin1_code":"35.0",
    "gn:admin2_code":"455.0",
    "gn:asciiname":"Satnur",
    "gn:country_code":"IN",
    "gn:dem":672,
    "gn:feature_class":"P",
    "gn:feature_code":"PPL",
    "gn:name":"Satn\u016br",
    "gn:population":0,
    "gn:timezone":"Asia/Kolkata",
    "iso:country":"IN",
    "wof:name":"Satnur",
    "wof:placetype":"neighbourhood"
},
  "geometry": {"coordinates":[78.82998000000001,21.91371],"type":"Point"}
}