{
  "type": "Feature",
  "properties": {
    "iso:country":"IN",
    "ks:ks_name":"Kumblady",
    "ks:ks_pop":177,
    "ks:ks_type":"HABITATION",
    "name:eng_x_preferred":[
        "Kumblady"
    ],
    "wof:name":"Kumblady",
    "wof:placetype":"locality",
    "wof:population":177
},
  "geometry": {"coordinates":[75.375681,12.750308],"type":"Point"}
}