{
  "type": "Feature",
  "properties": {
    "iso:country":"IN",
    "ks:ks_name":"Garubasti",
    "ks:ks_pop":355,
    "ks:ks_type":"HABITATION",
    "name:eng_x_preferred":[
        "Garubasti"
    ],
    "wof:name":"Garubasti",
    "wof:placetype":"locality",
    "wof:population":355
},
  "geometry": {"coordinates":[94.810649,27.066538],"type":"Point"}
}