{
  "type": "Feature",
  "properties": {
    "gn:admin1_code":"25.0",
    "gn:admin2_code":"605.0",
    "gn:asciiname":"Ramacharikottayi",
    "gn:country_code":"IN",
    "gn:dem":289,
    "gn:feature_class":"P",
    "gn:feature_code":"PPL",
    "gn:name":"R\u0101macharikottayi",
    "gn:population":0,
    "gn:timezone":"Asia/Kolkata",
    "iso:country":"IN",
    "ks:ks_name":"Ramachari Kottayi",
    "ks:ks_pop":316,
    "ks:ks_type":"HABITATION",
    "ks:ks_uagg_main":0,
    "name:eng_x_preferred":[
        "Ramachari Kottayi"
    ],
    "wof:name":"Ramachari Kottayi",
    "wof:placetype":"neighbourhood",
    "wof:population":316
},
  "geometry": {"coordinates":[78.91539400000001,12.842354],"type":"Point"}
}