{
  "type": "Feature",
  "properties": {
    "iso:country":"IN",
    "ks:ks_name":"Sekdapura",
    "ks:ks_pop":19,
    "ks:ks_type":"HABITATION",
    "name:eng_x_preferred":[
        "Sekdapura"
    ],
    "wof:name":"Sekdapura",
    "wof:placetype":"locality",
    "wof:population":19
},
  "geometry": {"coordinates":[76.746904,22.973953],"type":"Point"}
}