{
  "type": "Feature",
  "properties": {
    "iso:country":"IN",
    "ks:ks_name":"Maundaur Khas",
    "ks:ks_pop":2533,
    "ks:ks_type":"HABITATION",
    "name:eng_x_preferred":[
        "Maundaur Khas"
    ],
    "wof:name":"Maundaur Khas",
    "wof:placetype":"locality",
    "wof:population":2533
},
  "geometry": {"coordinates":[82.031177,25.421463],"type":"Point"}
}