{
  "type": "Feature",
  "properties": {
    "iso:country":"IN",
    "ks:ks_name":"Nawada",
    "ks:ks_pop":984,
    "ks:ks_type":"VILLAGE",
    "ks:ks_uagg_main":0,
    "name:eng_x_preferred":[
        "Nawada"
    ],
    "name:hin_x_preferred":[
        "\u0928\u0935\u093e\u0926\u093e"
    ],
    "wof:name":"Nawada",
    "wof:placetype":"neighbourhood",
    "wof:population":984
},
  "geometry": {"coordinates":[85.041867,24.862514],"type":"Point"}
}