{
  "type": "Feature",
  "properties": {
    "iso:country":"IN",
    "ks:ks_name":"Baunsapani",
    "ks:ks_pop":1035,
    "ks:ks_type":"HABITATION",
    "name:eng_x_preferred":[
        "Baunsapani"
    ],
    "wof:name":"Baunsapani",
    "wof:placetype":"locality",
    "wof:population":1035
},
  "geometry": {"coordinates":[86.203047,21.301889],"type":"Point"}
}