{
  "type": "Feature",
  "properties": {
    "iso:country":"IN",
    "ks:ks_alt_nam":"JATRA TARH",
    "ks:ks_name":"Jatra Tarh",
    "ks:ks_pop":185,
    "ks:ks_type":"HABITATION",
    "name:eng_x_preferred":[
        "Jatra Tarh"
    ],
    "wof:name":"Jatra Tarh",
    "wof:placetype":"locality",
    "wof:population":185
},
  "geometry": {"coordinates":[85.516733,24.223617],"type":"Point"}
}