{
  "type": "Feature",
  "properties": {
    "iso:country":"IN",
    "ks:ks_name":"Kuppe Hosahalli",
    "ks:ks_pop":22,
    "ks:ks_type":"HABITATION",
    "name:eng_x_preferred":[
        "Kuppe Hosahalli"
    ],
    "wof:name":"Kuppe Hosahalli",
    "wof:placetype":"locality",
    "wof:population":22
},
  "geometry": {"coordinates":[75.9357,13.040481],"type":"Point"}
}