{
  "type": "Feature",
  "properties": {
    "iso:country":"IN",
    "ks:ks_name":"Dangapara",
    "ks:ks_pop":300,
    "ks:ks_type":"HABITATION",
    "name:eng_x_preferred":[
        "Dangapara"
    ],
    "wof:name":"Dangapara",
    "wof:placetype":"locality",
    "wof:population":300
},
  "geometry": {"coordinates":[88.283354,26.390234],"type":"Point"}
}