{
  "type": "Feature",
  "properties": {
    "iso:country":"IN",
    "ks:ks_name":"Erular Colony",
    "ks:ks_pop":104,
    "ks:ks_type":"HABITATION",
    "name:eng_x_preferred":[
        "Erular Colony"
    ],
    "wof:name":"Erular Colony",
    "wof:placetype":"locality",
    "wof:population":104
},
  "geometry": {"coordinates":[78.931083,12.840613],"type":"Point"}
}