{
  "type": "Feature",
  "properties": {
    "gn:admin1_code":"11.0",
    "gn:admin2_code":"025",
    "gn:asciiname":"Jilang",
    "gn:country_code":"IN",
    "gn:dem":3518,
    "gn:feature_class":"P",
    "gn:feature_code":"PPL",
    "gn:name":"Jilang",
    "gn:population":0,
    "gn:timezone":"Asia/Kolkata",
    "iso:country":"IN",
    "wof:name":"Jilang",
    "wof:placetype":"locality"
},
  "geometry": {"coordinates":[77.44266,32.30262],"type":"Point"}
}