{
  "type": "Feature",
  "properties": {
    "iso:country":"IN",
    "ks:ks_alt_nam":"Nagwar kothar",
    "ks:ks_name":"Nagwar Kothar",
    "ks:ks_pop":161,
    "ks:ks_type":"HABITATION",
    "name:eng_x_preferred":[
        "Nagwar Kothar"
    ],
    "wof:name":"Nagwar Kothar",
    "wof:placetype":"locality",
    "wof:population":161
},
  "geometry": {"coordinates":[81.005392,24.798585],"type":"Point"}
}