{
  "type": "Feature",
  "properties": {
    "iso:country":"IN",
    "ks:ks_name":"Haleyelekere",
    "ks:ks_pop":756,
    "ks:ks_type":"HABITATION",
    "name:eng_x_preferred":[
        "Haleyelekere"
    ],
    "wof:name":"Haleyelekere",
    "wof:placetype":"locality",
    "wof:population":756
},
  "geometry": {"coordinates":[76.63274,12.467434],"type":"Point"}
}