{
  "type": "Feature",
  "properties": {
    "iso:country":"IN",
    "ks:ks_name":"Nender",
    "ks:ks_pop":194,
    "ks:ks_type":"HABITATION",
    "name:eng_x_preferred":[
        "Nender"
    ],
    "wof:name":"Nender",
    "wof:placetype":"locality",
    "wof:population":194
},
  "geometry": {"coordinates":[80.424718,19.620881],"type":"Point"}
}