{
  "type": "Feature",
  "properties": {
    "iso:country":"IN",
    "ks:ks_name":"Pundal Gunth",
    "ks:ks_pop":73,
    "ks:ks_type":"VILLAGE",
    "name:eng_x_preferred":[
        "Pundal Gunth"
    ],
    "wof:name":"Pundal Gunth",
    "wof:placetype":"locality",
    "wof:population":73
},
  "geometry": {"coordinates":[78.617491,30.14832],"type":"Point"}
}