{
  "type": "Feature",
  "properties": {
    "iso:country":"IN",
    "ks:ks_name":"Kumbhani",
    "ks:ks_pop":1350,
    "ks:ks_type":"VILLAGE",
    "name:eng_x_preferred":[
        "Kumbhani"
    ],
    "wof:name":"Kumbhani",
    "wof:placetype":"locality",
    "wof:population":1350
},
  "geometry": {"coordinates":[74.027113,22.483427],"type":"Point"}
}