{
  "type": "Feature",
  "properties": {
    "iso:country":"IN",
    "ks:ks_name":"No.3 Phatihabam",
    "ks:ks_pop":81,
    "ks:ks_type":"HABITATION",
    "name:eng_x_preferred":[
        "No.3 Phatihabam"
    ],
    "wof:name":"No.3 Phatihabam",
    "wof:placetype":"locality",
    "wof:population":81
},
  "geometry": {"coordinates":[94.561639,27.400265],"type":"Point"}
}