{
  "type": "Feature",
  "properties": {
    "iso:country":"IN",
    "ks:ks_name":"Jagniguda",
    "ks:ks_pop":166,
    "ks:ks_type":"HABITATION",
    "ks:ks_uagg_main":0,
    "name:eng_x_preferred":[
        "Jagniguda"
    ],
    "wof:name":"Jagniguda",
    "wof:placetype":"neighbourhood",
    "wof:population":166
},
  "geometry": {"coordinates":[82.407725,19.170521],"type":"Point"}
}