{
  "type": "Feature",
  "properties": {
    "iso:country":"IN",
    "ks:ks_name":"Kamol Falia",
    "ks:ks_pop":771,
    "ks:ks_type":"HABITATION",
    "name:eng_x_preferred":[
        "Kamol Falia"
    ],
    "wof:name":"Kamol Falia",
    "wof:placetype":"locality",
    "wof:population":771
},
  "geometry": {"coordinates":[74.209222,23.131417],"type":"Point"}
}