{
  "type": "Feature",
  "properties": {
    "gn:admin1_code":"2.0",
    "gn:admin2_code":"552.0",
    "gn:asciiname":"Jalavadi",
    "gn:country_code":"IN",
    "gn:dem":362,
    "gn:feature_class":"P",
    "gn:feature_code":"PPL",
    "gn:name":"J\u0101lav\u0101di",
    "gn:population":0,
    "gn:timezone":"Asia/Kolkata",
    "iso:country":"IN",
    "wof:name":"Jalavadi",
    "wof:placetype":"locality"
},
  "geometry": {"coordinates":[77.37805,15.79618],"type":"Point"}
}