{
  "type": "Feature",
  "properties": {
    "iso:country":"IN",
    "ks:ks_name":"Chhira",
    "ks:ks_pop":1778,
    "ks:ks_type":"HABITATION",
    "name:eng_x_preferred":[
        "Chhira"
    ],
    "wof:name":"Chhira",
    "wof:placetype":"locality",
    "wof:population":1778
},
  "geometry": {"coordinates":[86.628739,24.821507],"type":"Point"}
}