{
  "type": "Feature",
  "properties": {
    "iso:country":"IN",
    "ks:ks_name":"Pachamba",
    "ks:ks_pop":312,
    "ks:ks_type":"VILLAGE",
    "name:eng_x_preferred":[
        "Pachamba"
    ],
    "wof:name":"Pachamba",
    "wof:placetype":"locality",
    "wof:population":312
},
  "geometry": {"coordinates":[75.62396099999999,21.667805],"type":"Point"}
}