{
  "type": "Feature",
  "properties": {
    "gn:admin1_code":"35.0",
    "gn:admin2_code":"438.0",
    "gn:asciiname":"Narwali",
    "gn:country_code":"IN",
    "gn:dem":374,
    "gn:feature_class":"P",
    "gn:feature_code":"PPL",
    "gn:name":"Narwali",
    "gn:population":0,
    "gn:timezone":"Asia/Kolkata",
    "iso:country":"IN",
    "ks:ks_name":"Narwali",
    "ks:ks_pop":1189,
    "ks:ks_type":"VILLAGE",
    "name:eng_x_preferred":[
        "Narwali"
    ],
    "wof:name":"Narwali",
    "wof:placetype":"locality",
    "wof:population":1189
},
  "geometry": {"coordinates":[74.778666,22.514729],"type":"Point"}
}