{
  "type": "Feature",
  "properties": {
    "iso:country":"IN",
    "ks:ks_name":"Kolabila",
    "ks:ks_pop":245,
    "ks:ks_type":"HABITATION",
    "name:eng_x_preferred":[
        "Kolabila"
    ],
    "wof:name":"Kolabila",
    "wof:placetype":"locality",
    "wof:population":245
},
  "geometry": {"coordinates":[86.068696,21.24028],"type":"Point"}
}