{
  "type": "Feature",
  "properties": {
    "gn:admin1_code":"38.0",
    "gn:admin2_code":"348.0",
    "gn:asciiname":"Jhanpa",
    "gn:country_code":"IN",
    "gn:dem":408,
    "gn:feature_class":"P",
    "gn:feature_code":"PPL",
    "gn:name":"Jh\u0101np\u0101",
    "gn:population":0,
    "gn:timezone":"Asia/Kolkata",
    "iso:country":"IN",
    "ks:ks_alt_nam":"Jh\u0101np\u0101",
    "ks:ks_name":"Jhanpa",
    "ks:ks_type":"VILLAGE",
    "ks:ks_uagg_main":0,
    "name:eng_x_preferred":[
        "Jhanpa"
    ],
    "name:eng_x_variant":[
        "Jh\u0101np\u0101"
    ],
    "wof:name":"Jhanpa",
    "wof:placetype":"neighbourhood"
},
  "geometry": {"coordinates":[85.198936,24.349675],"type":"Point"}
}