{
  "type": "Feature",
  "properties": {
    "gn:admin1_code":"9.0",
    "gn:admin2_code":"469.0",
    "gn:asciiname":"Kumbaria",
    "gn:country_code":"IN",
    "gn:dem":431,
    "gn:feature_class":"P",
    "gn:feature_code":"PPL",
    "gn:name":"Kumbaria",
    "gn:population":0,
    "gn:timezone":"Asia/Kolkata",
    "iso:country":"IN",
    "ks:ks_name":"Kumbhariya",
    "ks:ks_pop":3482,
    "ks:ks_type":"VILLAGE",
    "ks:ks_uagg_main":0,
    "name:eng_x_preferred":[
        "Kumbhariya"
    ],
    "wof:name":"Kumbhariya",
    "wof:placetype":"neighbourhood",
    "wof:population":3482
},
  "geometry": {"coordinates":[72.860336,24.323665],"type":"Point"}
}