{
  "type": "Feature",
  "properties": {
    "iso:country":"IN",
    "ks:ks_name":"Kabbinakumbri",
    "ks:ks_pop":101,
    "ks:ks_type":"HABITATION",
    "name:eng_x_preferred":[
        "Kabbinakumbri"
    ],
    "wof:name":"Kabbinakumbri",
    "wof:placetype":"locality",
    "wof:population":101
},
  "geometry": {"coordinates":[74.719775,14.89504],"type":"Point"}
}