{
  "type": "Feature",
  "properties": {
    "gn:admin1_code":"35",
    "gn:admin2_code":"448.0",
    "gn:asciiname":"Nimdhana",
    "gn:country_code":"IN",
    "gn:dem":399,
    "gn:feature_class":"P",
    "gn:feature_code":"PPL",
    "gn:name":"N\u012bmdh\u0101na",
    "gn:population":0,
    "gn:timezone":"Asia/Kolkata",
    "iso:country":"IN",
    "ks:ks_alt_nam":"N\u012bmdh\u0101na",
    "ks:ks_name":"Nimdhana",
    "ks:ks_pop":669,
    "ks:ks_type":"VILLAGE",
    "name:eng_x_preferred":[
        "Nimdhana"
    ],
    "name:eng_x_variant":[
        "N\u012bmdh\u0101na"
    ],
    "wof:name":"Nimdhana",
    "wof:placetype":"locality",
    "wof:population":669
},
  "geometry": {"coordinates":[77.147988,22.043891],"type":"Point"}
}