{
  "type": "Feature",
  "properties": {
    "gn:admin1_code":"16",
    "gn:admin2_code":"511.0",
    "gn:asciiname":"Belapur",
    "gn:country_code":"IN",
    "gn:dem":346,
    "gn:feature_class":"P",
    "gn:feature_code":"PPL",
    "gn:name":"Bel\u0101pur",
    "gn:population":0,
    "gn:timezone":"Asia/Kolkata",
    "iso:country":"IN",
    "name:ara_x_preferred":[
        "\u0628\u064a\u0644\u0627\u0628\u0648\u0631"
    ],
    "name:ben_bn_x_preferred":[
        "\u09ac\u09c7\u09b2\u09be\u09aa\u09c1\u09b0"
    ],
    "name:ben_in_x_preferred":[
        "\u09ac\u09c7\u09b2\u09be\u09aa\u09c1\u09b0"
    ],
    "name:guj_x_preferred":[
        "\u0aac\u0ac7\u0ab2\u0abe\u0aaa\u0ac1\u0ab0"
    ],
    "name:hin_x_preferred":[
        "\u092c\u0947\u0932\u093e\u092a\u0941\u0930"
    ],
    "name:kan_x_preferred":[
        "\u0cac\u0cc7\u0cb2\u0cbe\u0caa\u0cc1\u0cb0\u0ccd"
    ],
    "name:mal_x_preferred":[
        "\u0d2c\u0d47\u0d32\u0d3e\u0d2a\u0d42\u0d7c"
    ],
    "name:mar_x_preferred":[
        "\u092c\u0947\u0932\u093e\u092a\u0942\u0930"
    ],
    "name:mar_x_variant":[
        "\u092c\u0947\u0932\u093e\u092a\u092a\u0942\u0930"
    ],
    "name:pan_x_preferred":[
        "\u0a2c\u0a47\u0a32\u0a3e\u0a2a\u0a41\u0a30"
    ],
    "name:tam_x_preferred":[
        "\u0baa\u0bc6\u0bb2\u0bbe\u0baa\u0bc2\u0bb0\u0bcd"
    ],
    "name:tel_x_preferred":[
        "\u0c2c\u0c47\u0c32\u0c3e\u0c2a\u0c42\u0c30\u0c4d"
    ],
    "name:urd_x_preferred":[
        "\u0628\u06cc\u0644\u0627 \u067e\u0648\u0631"
    ],
    "wof:name":"Belapur",
    "wof:placetype":"locality"
},
  "geometry": {"coordinates":[77.68926,18.89969],"type":"Point"}
}