{
  "type": "Feature",
  "properties": {
    "iso:country":"IN",
    "ks:ks_name":"Chakuli Gaon",
    "ks:ks_pop":1889,
    "ks:ks_type":"VILLAGE",
    "name:eng_x_preferred":[
        "Chakuli Gaon"
    ],
    "wof:name":"Chakuli Gaon",
    "wof:placetype":"locality",
    "wof:population":1889
},
  "geometry": {"coordinates":[94.375435,27.238905],"type":"Point"}
}