{
  "type": "Feature",
  "properties": {
    "iso:country":"IN",
    "ks:ks_name":"Gowrimale",
    "ks:ks_pop":68,
    "ks:ks_type":"HABITATION",
    "name:eng_x_preferred":[
        "Gowrimale"
    ],
    "wof:name":"Gowrimale",
    "wof:placetype":"locality",
    "wof:population":68
},
  "geometry": {"coordinates":[75.96388899999999,12.143611],"type":"Point"}
}