{
  "type": "Feature",
  "properties": {
    "iso:country":"IN",
    "ks:ks_name":"Ganganiyon Ki Dhani",
    "ks:ks_pop":131,
    "ks:ks_type":"VILLAGE",
    "name:eng_x_preferred":[
        "Ganganiyon Ki Dhani"
    ],
    "wof:name":"Ganganiyon Ki Dhani",
    "wof:placetype":"locality",
    "wof:population":131
},
  "geometry": {"coordinates":[71.10124399999999,25.691167],"type":"Point"}
}