{
  "type": "Feature",
  "properties": {
    "iso:country":"IN",
    "ks:ks_name":"Bhaliapalli",
    "ks:ks_pop":344,
    "ks:ks_type":"VILLAGE",
    "ks:ks_uagg_main":0,
    "name:eng_x_preferred":[
        "Bhaliapalli"
    ],
    "wof:name":"Bhaliapalli",
    "wof:placetype":"neighbourhood",
    "wof:population":344
},
  "geometry": {"coordinates":[84.60718199999999,19.6476],"type":"Point"}
}