{
  "type": "Feature",
  "properties": {
    "gn:admin1_code":"19.0",
    "gn:admin2_code":"581.0",
    "gn:asciiname":"Madamuttanahalli",
    "gn:country_code":"IN",
    "gn:dem":822,
    "gn:feature_class":"P",
    "gn:feature_code":"PPL",
    "gn:name":"M\u0101damuttanahalli",
    "gn:population":0,
    "gn:timezone":"Asia/Kolkata",
    "iso:country":"IN",
    "wof:name":"Madamuttanahalli",
    "wof:placetype":"locality"
},
  "geometry": {"coordinates":[78.24460999999999,13.0375],"type":"Point"}
}