{
  "type": "Feature",
  "properties": {
    "iso:country":"IN",
    "ks:ks_name":"Chhuriya",
    "ks:ks_pop":37,
    "ks:ks_type":"VILLAGE",
    "name:eng_x_preferred":[
        "Chhuriya"
    ],
    "wof:name":"Chhuriya",
    "wof:placetype":"locality",
    "wof:population":37
},
  "geometry": {"coordinates":[79.84724799999999,29.928362],"type":"Point"}
}