{
  "type": "Feature",
  "properties": {
    "gn:admin1_code":"7.0",
    "gn:admin2_code":"93.0",
    "gn:asciiname":"Kishanganj",
    "gn:country_code":"IN",
    "gn:dem":210,
    "gn:feature_class":"P",
    "gn:feature_code":"PPL",
    "gn:name":"Kishanganj",
    "gn:population":0,
    "gn:timezone":"Asia/Kolkata",
    "iso:country":"IN",
    "name:ara_x_preferred":[
        "\u0643\u064a\u0634\u0646\u062c\u0627\u0646\u064a"
    ],
    "name:ben_x_preferred":[
        "\u0995\u09bf\u09b6\u09be\u09a8\u0997\u099e\u09cd\u099c"
    ],
    "name:bih_x_preferred":[
        "\u0915\u093f\u0936\u0928\u0917\u0902\u091c"
    ],
    "name:bpy_x_preferred":[
        "\u0995\u09bf\u09b7\u09a3\u0997\u099e\u09cd\u099c"
    ],
    "name:fas_x_preferred":[
        "\u06a9\u06cc\u0634\u0627\u0646\u06af\u0646\u062c"
    ],
    "name:hin_x_preferred":[
        "\u0915\u093f\u0936\u0928\u0917\u0902\u091c"
    ],
    "name:ita_x_preferred":[
        "Kishanganj"
    ],
    "name:mar_x_preferred":[
        "\u0915\u093f\u0936\u0928\u0917\u0902\u091c"
    ],
    "name:msa_x_preferred":[
        "Kishanganj"
    ],
    "name:nep_x_preferred":[
        "\u0915\u093f\u0936\u0928\u0917\u0902\u091c"
    ],
    "name:new_x_preferred":[
        "\u0915\u093f\u0936\u093e\u0928\u0917\u091e\u094d\u091c"
    ],
    "name:nld_x_preferred":[
        "Kishanganj"
    ],
    "name:ori_x_preferred":[
        "\u0b15\u0b3f\u0b36\u0b3e\u0b28\u0b17\u0b1e\u0b4d\u0b1c"
    ],
    "name:pan_x_preferred":[
        "\u0a15\u0a3f\u0a38\u0a3c\u0a28\u0a17\u0a70\u0a1c"
    ],
    "name:por_x_preferred":[
        "Kishanganj"
    ],
    "name:rus_x_preferred":[
        "\u041a\u0438\u0448\u0430\u043d\u0433\u0430\u043d\u0434\u0436"
    ],
    "name:san_x_preferred":[
        "\u0915\u093f\u0936\u0928\u0917\u091e\u094d\u091c"
    ],
    "name:spa_x_preferred":[
        "Kishanganj"
    ],
    "name:swe_x_preferred":[
        "Kishanganj"
    ],
    "name:urd_x_preferred":[
        "\u06a9\u0634\u0646 \u06af\u0646\u062c"
    ],
    "name:vie_x_preferred":[
        "Kishanganj"
    ],
    "name:zho_x_preferred":[
        "\u57fa\u65af\u676d\u683c\u963f\u6069\u6770"
    ],
    "wof:name":"Kishanganj",
    "wof:placetype":"locality"
},
  "geometry": {"coordinates":[77.27811,28.639],"type":"Point"}
}