{
  "type": "Feature",
  "properties": {
    "gn:admin1_code":"2.0",
    "gn:admin2_code":"547.0",
    "gn:asciiname":"Simhadripuram",
    "gn:country_code":"IN",
    "gn:dem":91,
    "gn:feature_class":"P",
    "gn:feature_code":"PPL",
    "gn:name":"Simh\u0101dripuram",
    "gn:population":0,
    "gn:timezone":"Asia/Kolkata",
    "iso:country":"IN",
    "name:new_x_preferred":[
        "\u0938\u093f\u0902\u0939\u093e\u0926\u094d\u0930\u093f\u092a\u0941\u0930\u0902 \u092e\u0923\u094d\u0921\u0932"
    ],
    "name:pam_x_preferred":[
        "Simhadripuram"
    ],
    "name:tel_x_preferred":[
        "\u0c38\u0c3f\u0c02\u0c39\u0c3e\u0c26\u0c4d\u0c30\u0c3f\u0c2a\u0c41\u0c30\u0c02"
    ],
    "name:tgl_x_preferred":[
        "Simhadripuram"
    ],
    "name:urd_x_preferred":[
        "\u0633\u0645\u06c1\u0627\u062f\u0631\u06cc \u067e\u0648\u0631\u0645"
    ],
    "wof:name":"Simhadripuram",
    "wof:placetype":"locality"
},
  "geometry": {"coordinates":[80.89286,16.81411],"type":"Point"}
}