{
  "type": "Feature",
  "properties": {
    "iso:country":"IN",
    "ks:ks_name":"Yogda Tumlabong",
    "ks:ks_pop":446,
    "ks:ks_type":"HABITATION",
    "name:eng_x_preferred":[
        "Yogda Tumlabong"
    ],
    "wof:name":"Yogda Tumlabong",
    "wof:placetype":"locality",
    "wof:population":446
},
  "geometry": {"coordinates":[88.51317299999999,27.110473],"type":"Point"}
}