{
  "type": "Feature",
  "properties": {
    "iso:country":"IN",
    "ks:ks_alt_nam":"Karlyach galu",
    "ks:ks_name":"Karlyach Galu",
    "ks:ks_pop":175,
    "ks:ks_type":"HABITATION",
    "name:eng_x_preferred":[
        "Karlyach Galu"
    ],
    "wof:name":"Karlyach Galu",
    "wof:placetype":"locality",
    "wof:population":175
},
  "geometry": {"coordinates":[73.737544,16.082994],"type":"Point"}
}