{
  "type": "Feature",
  "properties": {
    "iso:country":"IN",
    "ks:ks_name":"Sariketa",
    "ks:ks_pop":38,
    "ks:ks_type":"VILLAGE",
    "name:eng_x_preferred":[
        "Sariketa"
    ],
    "wof:name":"Sariketa",
    "wof:placetype":"locality",
    "wof:population":38
},
  "geometry": {"coordinates":[83.919768,20.075411],"type":"Point"}
}