{
  "type": "Feature",
  "properties": {
    "iso:country":"IN",
    "ks:ks_name":"Majuraposi",
    "ks:ks_pop":21,
    "ks:ks_type":"HABITATION",
    "name:eng_x_preferred":[
        "Majuraposi"
    ],
    "wof:name":"Majuraposi",
    "wof:placetype":"locality",
    "wof:population":21
},
  "geometry": {"coordinates":[85.81634200000001,21.894922],"type":"Point"}
}