{
  "type": "Feature",
  "properties": {
    "iso:country":"IN",
    "ks:ks_alt_nam":"RAI RAM TOLA",
    "ks:ks_name":"Rai Ram Tola",
    "ks:ks_pop":228,
    "ks:ks_type":"HABITATION",
    "ks:ks_uagg_main":0,
    "name:eng_x_preferred":[
        "Rai Ram Tola"
    ],
    "wof:name":"Rai Ram Tola",
    "wof:placetype":"neighbourhood",
    "wof:population":228
},
  "geometry": {"coordinates":[84.756851,26.276068],"type":"Point"}
}