{
  "type": "Feature",
  "properties": {
    "gn:admin1_code":"21",
    "gn:admin2_code":"376.0",
    "gn:asciiname":"Satkosia",
    "gn:country_code":"IN",
    "gn:dem":221,
    "gn:feature_class":"P",
    "gn:feature_code":"PPL",
    "gn:name":"S\u0101tkosia",
    "gn:population":0,
    "gn:timezone":"Asia/Kolkata",
    "iso:country":"IN",
    "ks:ks_alt_nam":"S\u0101tkosia",
    "ks:ks_name":"Satkosia",
    "ks:ks_type":"VILLAGE",
    "name:eng_x_preferred":[
        "Satkosia"
    ],
    "name:eng_x_variant":[
        "S\u0101tkosia"
    ],
    "wof:name":"Satkosia",
    "wof:placetype":"locality"
},
  "geometry": {"coordinates":[86.145319,21.360165],"type":"Point"}
}