{
  "type": "Feature",
  "properties": {
    "gn:admin1_code":"21",
    "gn:admin2_code":"376.0",
    "gn:asciiname":"Satkosia",
    "gn:country_code":"IN",
    "gn:dem":221,
    "gn:feature_class":"P",
    "gn:feature_code":"PPL",
    "gn:name":"S\u0101tkosia",
    "gn:population":0,
    "gn:timezone":"Asia/Kolkata",
    "iso:country":"IN",
    "wof:name":"Satkosia",
    "wof:placetype":"locality"
},
  "geometry": {"coordinates":[86.14532,21.36016],"type":"Point"}
}