{
  "type": "Feature",
  "properties": {
    "iso:country":"IN",
    "ks:ks_name":"Gopalpura",
    "ks:ks_pop":331,
    "ks:ks_type":"VILLAGE",
    "name:eng_x_preferred":[
        "Gopalpura"
    ],
    "wof:name":"Gopalpura",
    "wof:placetype":"locality",
    "wof:population":331
},
  "geometry": {"coordinates":[75.69441,27.541724],"type":"Point"}
}