{
  "type": "Feature",
  "properties": {
    "gn:admin1_code":"16",
    "gn:admin2_code":"502.0",
    "gn:asciiname":"Ramtek",
    "gn:country_code":"IN",
    "gn:dem":317,
    "gn:feature_class":"P",
    "gn:feature_code":"PPL",
    "gn:name":"R\u0101mtek",
    "gn:population":0,
    "gn:timezone":"Asia/Kolkata",
    "iso:country":"IN",
    "name:ben_x_preferred":[
        "\u09b0\u09be\u09ae\u099f\u09c7\u0995"
    ],
    "name:bpy_x_preferred":[
        "\u09b0\u09be\u09ae\u09a4\u09c7\u0995"
    ],
    "name:ceb_x_preferred":[
        "R\u0101mtek"
    ],
    "name:hif_x_preferred":[
        "Ramtek"
    ],
    "name:hin_x_preferred":[
        "\u0930\u093e\u092e\u091f\u0947\u0915"
    ],
    "name:ind_x_preferred":[
        "Ramtek"
    ],
    "name:ita_x_preferred":[
        "Ramtek"
    ],
    "name:mar_x_preferred":[
        "\u0930\u093e\u092e\u091f\u0947\u0915"
    ],
    "name:msa_x_preferred":[
        "Ramtek"
    ],
    "name:nld_x_preferred":[
        "Ramtek"
    ],
    "name:ori_x_preferred":[
        "\u0b30\u0b3e\u0b2e\u0b1f\u0b47\u0b15"
    ],
    "name:por_x_preferred":[
        "Ramtek"
    ],
    "name:swe_x_preferred":[
        "R\u0101mtek"
    ],
    "name:tam_x_preferred":[
        "\u0bb0\u0bbe\u0bae\u0bcd\u0b9f\u0bc6\u0b95\u0bcd"
    ],
    "name:urd_x_preferred":[
        "\u0631\u0627\u0645\u0679\u06cc\u06a9"
    ],
    "name:vie_x_preferred":[
        "Ramtek"
    ],
    "name:zho_x_preferred":[
        "\u62c9\u59c6\u6cf0\u514b"
    ],
    "wof:name":"Ramtek",
    "wof:placetype":"locality"
},
  "geometry": {"coordinates":[77.62193000000001,20.7044],"type":"Point"}
}