{
  "type": "Feature",
  "properties": {
    "iso:country":"IN",
    "ks:ks_name":"Vejalpur",
    "ks:ks_pop":113445,
    "ks:ks_type":"VILLAGE",
    "ks:ks_uagg_main":0,
    "name:eng_x_preferred":[
        "Vejalpur"
    ],
    "wof:name":"Vejalpur",
    "wof:placetype":"neighbourhood",
    "wof:population":113445
},
  "geometry": {"coordinates":[72.51785,23.003416],"type":"Point"}
}