{
  "type": "Feature",
  "properties": {
    "iso:country":"IN",
    "ks:ks_name":"Baremarcha",
    "ks:ks_pop":143,
    "ks:ks_type":"HABITATION",
    "name:eng_x_preferred":[
        "Baremarcha"
    ],
    "wof:name":"Baremarcha",
    "wof:placetype":"locality",
    "wof:population":143
},
  "geometry": {"coordinates":[85.754367,22.916881],"type":"Point"}
}