{
  "type": "Feature",
  "properties": {
    "iso:country":"IN",
    "ks:ks_name":"Purba Prasadpur",
    "ks:ks_pop":909,
    "ks:ks_type":"VILLAGE",
    "name:eng_x_preferred":[
        "Purba Prasadpur"
    ],
    "wof:name":"Purba Prasadpur",
    "wof:placetype":"locality",
    "wof:population":909
},
  "geometry": {"coordinates":[88.00576700000001,25.862938],"type":"Point"}
}