{
  "type": "Feature",
  "properties": {
    "iso:country":"IN",
    "ks:ks_alt_nam":"Thalla kunta tanda",
    "ks:ks_name":"Thalla Kunta Tanda",
    "ks:ks_pop":77,
    "ks:ks_type":"HABITATION",
    "name:eng_x_preferred":[
        "Thalla Kunta Tanda"
    ],
    "wof:name":"Thalla Kunta Tanda",
    "wof:placetype":"locality",
    "wof:population":77
},
  "geometry": {"coordinates":[78.473373,18.712226],"type":"Point"}
}