{
  "type": "Feature",
  "properties": {
    "gn:admin1_code":"34.0",
    "gn:admin2_code":"217.0",
    "gn:asciiname":"Samail",
    "gn:country_code":"IN",
    "gn:dem":73,
    "gn:feature_class":"P",
    "gn:feature_code":"PPL",
    "gn:name":"Sam\u0101il",
    "gn:population":0,
    "gn:timezone":"Asia/Kolkata",
    "iso:country":"IN",
    "name:ara_x_preferred":[
        "\u0648\u0644\u0627\u064a\u0629 \u0633\u0645\u0627\u0626\u0644"
    ],
    "name:ces_x_preferred":[
        "Sam\u00e1jl"
    ],
    "name:fas_x_preferred":[
        "\u0633\u0645\u0627\u0626\u0644"
    ],
    "name:fra_x_preferred":[
        "Sama'il"
    ],
    "name:ita_x_preferred":[
        "Samail"
    ],
    "name:nno_x_preferred":[
        "Samail"
    ],
    "name:pol_x_preferred":[
        "Sama\u2019il"
    ],
    "name:por_x_preferred":[
        "Samail"
    ],
    "name:und_x_variant":[
        "Sam\u0101il",
        "Q\u0101sim"
    ],
    "name:urd_x_preferred":[
        "\u0633\u0645\u0627\u0626\u0644"
    ],
    "wof:name":"Samail",
    "wof:placetype":"neighbourhood"
},
  "geometry": {"coordinates":[84.22153,26.38954],"type":"Point"}
}