{
  "type": "Feature",
  "properties": {
    "gn:admin1_code":"39.0",
    "gn:admin2_code":"63.0",
    "gn:asciiname":"Musauli",
    "gn:country_code":"IN",
    "gn:dem":1457,
    "gn:feature_class":"P",
    "gn:feature_code":"PPL",
    "gn:name":"Musauli",
    "gn:population":0,
    "gn:timezone":"Asia/Kolkata",
    "iso:country":"IN",
    "name:ceb_x_preferred":[
        "Musauli"
    ],
    "name:mai_x_preferred":[
        "\u092e\u0941\u0938\u0948\u0932\u0940"
    ],
    "name:new_x_preferred":[
        "\u092e\u0941\u0938\u094c\u0932\u0940"
    ],
    "name:pol_x_preferred":[
        "Musauli"
    ],
    "wof:name":"Musauli",
    "wof:placetype":"locality"
},
  "geometry": {"coordinates":[79.85562,29.82528],"type":"Point"}
}