{
  "type": "Feature",
  "properties": {
    "gn:admin1_code":"39.0",
    "gn:admin2_code":"63.0",
    "gn:asciiname":"Musauli",
    "gn:country_code":"IN",
    "gn:dem":1457,
    "gn:feature_class":"P",
    "gn:feature_code":"PPL",
    "gn:name":"Musauli",
    "gn:population":0,
    "gn:timezone":"Asia/Kolkata",
    "iso:country":"IN",
    "wof:name":"Musauli",
    "wof:placetype":"locality"
},
  "geometry": {"coordinates":[79.85562,29.82528],"type":"Point"}
}