{
  "type": "Feature",
  "properties": {
    "iso:country":"IN",
    "ks:ks_name":"Jalalpur",
    "ks:ks_pop":0,
    "ks:ks_type":"VILLAGE",
    "name:eng_x_preferred":[
        "Jalalpur"
    ],
    "wof:name":"Jalalpur",
    "wof:placetype":"locality",
    "wof:population":0
},
  "geometry": {"coordinates":[77.150879,29.572216],"type":"Point"}
}