{
  "type": "Feature",
  "properties": {
    "iso:country":"IN",
    "ks:ks_name":"Mallampalli",
    "ks:ks_type":"VILLAGE",
    "name:eng_x_preferred":[
        "Mallampalli"
    ],
    "wof:name":"Mallampalli",
    "wof:placetype":"locality"
},
  "geometry": {"coordinates":[78.297453,13.424889],"type":"Point"}
}