{
  "type": "Feature",
  "properties": {
    "iso:country":"IN",
    "ks:ks_name":"Parajaguda",
    "ks:ks_pop":110,
    "ks:ks_type":"VILLAGE",
    "name:eng_x_preferred":[
        "Parajaguda"
    ],
    "wof:name":"Parajaguda",
    "wof:placetype":"locality",
    "wof:population":110
},
  "geometry": {"coordinates":[82.106623,18.290565],"type":"Point"}
}