{
  "type": "Feature",
  "properties": {
    "gn:admin1_code":"23.0",
    "gn:admin2_code":"043",
    "gn:asciiname":"Arniwala",
    "gn:country_code":"IN",
    "gn:dem":193,
    "gn:feature_class":"P",
    "gn:feature_code":"PPL",
    "gn:name":"Arniw\u0101la",
    "gn:population":0,
    "gn:timezone":"Asia/Kolkata",
    "iso:country":"IN",
    "name:und_x_variant":[
        "Arniw\u0101la",
        "Shekh Subh\u0101n"
    ],
    "wof:name":"Arniwala",
    "wof:placetype":"locality"
},
  "geometry": {"coordinates":[74.25782,30.3472],"type":"Point"}
}