{
  "type": "Feature",
  "properties": {
    "iso:country":"IN",
    "ks:ks_name":"Pavariwathar",
    "ks:ks_pop":180,
    "ks:ks_type":"HABITATION",
    "name:eng_x_preferred":[
        "Pavariwathar"
    ],
    "wof:name":"Pavariwathar",
    "wof:placetype":"locality",
    "wof:population":180
},
  "geometry": {"coordinates":[73.289672,17.266144],"type":"Point"}
}