{
  "type": "Feature",
  "properties": {
    "iso:country":"IN",
    "ks:ks_name":"Vellowatergaon 2",
    "ks:ks_pop":83,
    "ks:ks_type":"HABITATION",
    "name:eng_x_preferred":[
        "Vellowatergaon 2"
    ],
    "wof:name":"Vellowatergaon 2",
    "wof:placetype":"locality",
    "wof:population":83
},
  "geometry": {"coordinates":[92.62226099999999,26.799852],"type":"Point"}
}