{
  "type": "Feature",
  "properties": {
    "iso:country":"IN",
    "ks:ks_name":"Nuti Patana",
    "ks:ks_pop":256,
    "ks:ks_type":"VILLAGE",
    "ks:ks_uagg_main":0,
    "name:eng_x_preferred":[
        "Nuti Patana"
    ],
    "wof:name":"Nuti Patana",
    "wof:placetype":"neighbourhood",
    "wof:population":256
},
  "geometry": {"coordinates":[86.88118,21.469851],"type":"Point"}
}