{
  "type": "Feature",
  "properties": {
    "iso:country":"IN",
    "ks:ks_name":"Kumrawan Purwa",
    "ks:ks_pop":441,
    "ks:ks_type":"HABITATION",
    "name:eng_x_preferred":[
        "Kumrawan Purwa"
    ],
    "wof:name":"Kumrawan Purwa",
    "wof:placetype":"neighbourhood",
    "wof:population":441
},
  "geometry": {"coordinates":[81.086872,26.865518],"type":"Point"}
}