{
  "type": "Feature",
  "properties": {
    "iso:country":"IN",
    "ks:ks_name":"Perunangupatti",
    "ks:ks_pop":110,
    "ks:ks_type":"HABITATION",
    "name:eng_x_preferred":[
        "Perunangupatti"
    ],
    "wof:name":"Perunangupatti",
    "wof:placetype":"locality",
    "wof:population":110
},
  "geometry": {"coordinates":[78.81780999999999,10.348269],"type":"Point"}
}