{
  "type": "Feature",
  "properties": {
    "gn:admin1_code":"36.0",
    "gn:admin2_code":"173.0",
    "gn:asciiname":"Ramchandapur",
    "gn:country_code":"IN",
    "gn:dem":105,
    "gn:feature_class":"P",
    "gn:feature_code":"PPL",
    "gn:name":"R\u0101mchand\u0101pur",
    "gn:population":0,
    "gn:timezone":"Asia/Kolkata",
    "iso:country":"IN",
    "ks:ks_name":"Ramchandra Pur",
    "ks:ks_pop":403,
    "ks:ks_type":"VILLAGE",
    "name:eng_x_preferred":[
        "Ramchandra Pur"
    ],
    "name:eng_x_variant":[
        "Ramchandapur"
    ],
    "wof:name":"Ramchandra Pur",
    "wof:placetype":"locality",
    "wof:population":403
},
  "geometry": {"coordinates":[81.78487199999999,25.795517],"type":"Point"}
}