{
  "type": "Feature",
  "properties": {
    "iso:country":"IN",
    "ks:ks_alt_nam":"kondakinda Gokulapuram",
    "ks:ks_name":"Kondakinda Gokulapuram",
    "ks:ks_pop":39,
    "ks:ks_type":"HABITATION",
    "name:eng_x_preferred":[
        "Kondakinda Gokulapuram"
    ],
    "wof:name":"Kondakinda Gokulapuram",
    "wof:placetype":"locality",
    "wof:population":39
},
  "geometry": {"coordinates":[79.146867,13.514919],"type":"Point"}
}