{
  "type": "Feature",
  "properties": {
    "gn:admin1_code":"34.0",
    "gn:admin2_code":"217.0",
    "gn:asciiname":"Kabliswa",
    "gn:country_code":"IN",
    "gn:dem":70,
    "gn:feature_class":"P",
    "gn:feature_code":"PPL",
    "gn:name":"Kabliswa",
    "gn:population":0,
    "gn:timezone":"Asia/Kolkata",
    "iso:country":"IN",
    "ks:ks_name":"Kabliswa",
    "ks:ks_pop":1034,
    "ks:ks_type":"VILLAGE",
    "ks:ks_uagg_main":0,
    "name:eng_x_preferred":[
        "Kabliswa"
    ],
    "wof:name":"Kabliswa",
    "wof:placetype":"neighbourhood",
    "wof:population":1034
},
  "geometry": {"coordinates":[84.228994,26.343725],"type":"Point"}
}