{
  "type": "Feature",
  "properties": {
    "iso:country":"IN",
    "ks:ks_name":"Janisahi",
    "ks:ks_pop":62,
    "ks:ks_type":"VILLAGE",
    "name:eng_x_preferred":[
        "Janisahi"
    ],
    "wof:name":"Janisahi",
    "wof:placetype":"locality",
    "wof:population":62
},
  "geometry": {"coordinates":[84.178006,19.243279],"type":"Point"}
}