{
  "type": "Feature",
  "properties": {
    "iso:country":"IN",
    "ks:ks_name":"Chandeshwar",
    "ks:ks_pop":579,
    "ks:ks_type":"VILLAGE",
    "name:eng_x_preferred":[
        "Chandeshwar"
    ],
    "wof:name":"Chandeshwar",
    "wof:placetype":"locality",
    "wof:population":579
},
  "geometry": {"coordinates":[79.853375,19.831937],"type":"Point"}
}