{
  "type": "Feature",
  "properties": {
    "gn:admin1_code":"35.0",
    "gn:admin2_code":"457.0",
    "gn:asciiname":"Orma",
    "gn:country_code":"IN",
    "gn:dem":321,
    "gn:feature_class":"P",
    "gn:feature_code":"PPL",
    "gn:name":"Orm\u0101",
    "gn:population":0,
    "gn:timezone":"Asia/Kolkata",
    "iso:country":"IN",
    "name:ceb_x_preferred":[
        "Orma"
    ],
    "name:fra_x_preferred":[
        "Orma"
    ],
    "name:heb_x_preferred":[
        "\u05d0\u05d5\u05e8\u05de\u05d4"
    ],
    "name:ita_x_preferred":[
        "Orma"
    ],
    "name:swe_x_preferred":[
        "Orma"
    ],
    "wof:name":"Orma",
    "wof:placetype":"locality"
},
  "geometry": {"coordinates":[80.14716,21.94973],"type":"Point"}
}