{
  "type": "Feature",
  "properties": {
    "iso:country":"IN",
    "ks:ks_name":"Gund",
    "ks:ks_pop":119,
    "ks:ks_type":"VILLAGE",
    "name:eng_x_preferred":[
        "Gund"
    ],
    "wof:name":"Gund",
    "wof:placetype":"locality",
    "wof:population":119
},
  "geometry": {"coordinates":[74.548407,15.077715],"type":"Point"}
}