{
  "type": "Feature",
  "properties": {
    "iso:country":"IN",
    "ks:ks_name":"Bajjigere",
    "ks:ks_pop":206,
    "ks:ks_type":"HABITATION",
    "name:eng_x_preferred":[
        "Bajjigere"
    ],
    "wof:name":"Bajjigere",
    "wof:placetype":"locality",
    "wof:population":206
},
  "geometry": {"coordinates":[74.581895,14.216831],"type":"Point"}
}