{
  "type": "Feature",
  "properties": {
    "gn:admin1_code":"12.0",
    "gn:admin2_code":"002",
    "gn:asciiname":"Dafpur",
    "gn:country_code":"IN",
    "gn:dem":1604,
    "gn:feature_class":"P",
    "gn:feature_code":"PPL",
    "gn:name":"Dafpur",
    "gn:population":0,
    "gn:timezone":"Asia/Kolkata",
    "iso:country":"IN",
    "wof:name":"Dafpur",
    "wof:placetype":"locality"
},
  "geometry": {"coordinates":[74.70612,34.04217],"type":"Point"}
}