{
  "type": "Feature",
  "properties": {
    "gn:admin1_code":"24.0",
    "gn:admin2_code":"119.0",
    "gn:asciiname":"Sanganer",
    "gn:country_code":"IN",
    "gn:dem":359,
    "gn:feature_class":"P",
    "gn:feature_code":"PPL",
    "gn:name":"S\u0101ng\u0101ner",
    "gn:population":0,
    "gn:timezone":"Asia/Kolkata",
    "iso:country":"IN",
    "name:ori_x_preferred":[
        "\u0b38\u0b3e\u0b19\u0b4d\u0b17\u0b3e\u0b28\u0b47\u0b30"
    ],
    "wof:name":"Sanganer",
    "wof:placetype":"locality"
},
  "geometry": {"coordinates":[74.93028000000002,26.09358],"type":"Point"}
}