{
  "type": "Feature",
  "properties": {
    "gn:admin1_code":"12.0",
    "gn:admin2_code":"006",
    "gn:asciiname":"Khan Gala",
    "gn:country_code":"IN",
    "gn:dem":990,
    "gn:feature_class":"P",
    "gn:feature_code":"PPL",
    "gn:name":"Khan G\u0101la",
    "gn:population":0,
    "gn:timezone":"Asia/Kolkata",
    "iso:country":"IN",
    "wof:name":"Khan Gala",
    "wof:placetype":"locality"
},
  "geometry": {"coordinates":[74.38056,33.24583],"type":"Point"}
}