{
  "type": "Feature",
  "properties": {
    "iso:country":"IN",
    "ks:ks_name":"Malwadi",
    "ks:ks_pop":291,
    "ks:ks_type":"HABITATION",
    "name:eng_x_preferred":[
        "Malwadi"
    ],
    "wof:name":"Malwadi",
    "wof:placetype":"locality",
    "wof:population":291
},
  "geometry": {"coordinates":[73.65272400000001,18.672708],"type":"Point"}
}