{
  "type": "Feature",
  "properties": {
    "iso:country":"IN",
    "ks:ks_name":"Ranigudapara",
    "ks:ks_pop":365,
    "ks:ks_type":"HABITATION",
    "ks:ks_uagg_main":0,
    "name:eng_x_preferred":[
        "Ranigudapara"
    ],
    "wof:name":"Ranigudapara",
    "wof:placetype":"neighbourhood",
    "wof:population":365
},
  "geometry": {"coordinates":[81.836268,19.357479],"type":"Point"}
}