{
  "type": "Feature",
  "properties": {
    "iso:country":"IN",
    "ks:ks_name":"Dakshin Maharani",
    "ks:ks_pop":1719,
    "ks:ks_type":"VILLAGE",
    "name:eng_x_preferred":[
        "Dakshin Maharani"
    ],
    "wof:name":"Dakshin Maharani",
    "wof:placetype":"locality",
    "wof:population":1719
},
  "geometry": {"coordinates":[91.66520300000001,23.916943],"type":"Point"}
}