{
  "type": "Feature",
  "properties": {
    "iso:country":"IN",
    "ks:ks_name":"Kharagpura",
    "ks:ks_pop":516,
    "ks:ks_type":"HABITATION",
    "name:eng_x_preferred":[
        "Kharagpura"
    ],
    "wof:name":"Kharagpura",
    "wof:placetype":"locality",
    "wof:population":516
},
  "geometry": {"coordinates":[78.041431,26.717273],"type":"Point"}
}