{
  "type": "Feature",
  "properties": {
    "iso:country":"IN",
    "ks:ks_name":"Navakkallu",
    "ks:ks_pop":481,
    "ks:ks_type":"HABITATION",
    "name:eng_x_preferred":[
        "Navakkallu"
    ],
    "wof:name":"Navakkallu",
    "wof:placetype":"locality",
    "wof:population":481
},
  "geometry": {"coordinates":[77.25443799999999,10.168542],"type":"Point"}
}