{
  "type": "Feature",
  "properties": {
    "iso:country":"IN",
    "ks:ks_name":"Kendupal",
    "ks:ks_pop":189,
    "ks:ks_type":"VILLAGE",
    "name:eng_x_preferred":[
        "Kendupal"
    ],
    "wof:name":"Kendupal",
    "wof:placetype":"locality",
    "wof:population":189
},
  "geometry": {"coordinates":[84.773302,21.250929],"type":"Point"}
}