{
  "type": "Feature",
  "properties": {
    "iso:country":"IN",
    "ks:ks_name":"Pipalipada",
    "ks:ks_pop":246,
    "ks:ks_type":"VILLAGE",
    "name:eng_x_preferred":[
        "Pipalipada"
    ],
    "wof:name":"Pipalipada",
    "wof:placetype":"locality",
    "wof:population":246
},
  "geometry": {"coordinates":[74.99448599999999,22.98993],"type":"Point"}
}