{
  "type": "Feature",
  "properties": {
    "iso:country":"IN",
    "ks:ks_name":"Chaniyon Ki Dhani",
    "ks:ks_pop":100,
    "ks:ks_type":"HABITATION",
    "name:eng_x_preferred":[
        "Chaniyon Ki Dhani"
    ],
    "wof:name":"Chaniyon Ki Dhani",
    "wof:placetype":"locality",
    "wof:population":100
},
  "geometry": {"coordinates":[70.766492,25.644511],"type":"Point"}
}