{
  "type": "Feature",
  "properties": {
    "gn:admin1_code":"37.0",
    "gn:admin2_code":"416.0",
    "gn:asciiname":"Andumpal",
    "gn:country_code":"IN",
    "gn:dem":267,
    "gn:feature_class":"P",
    "gn:feature_code":"PPL",
    "gn:name":"Andump\u0101l",
    "gn:population":0,
    "gn:timezone":"Asia/Kolkata",
    "iso:country":"IN",
    "ks:ks_alt_nam":"Andump\u0101l",
    "ks:ks_name":"Andumpal",
    "ks:ks_pop":381,
    "ks:ks_type":"VILLAGE",
    "name:eng_x_preferred":[
        "Andumpal"
    ],
    "name:eng_x_variant":[
        "Andump\u0101l"
    ],
    "wof:name":"Andumpal",
    "wof:placetype":"locality",
    "wof:population":381
},
  "geometry": {"coordinates":[81.688408,18.577599],"type":"Point"}
}