{
  "type": "Feature",
  "properties": {
    "iso:country":"IN",
    "ks:ks_name":"Nagla Sati",
    "ks:ks_pop":123,
    "ks:ks_type":"HABITATION",
    "name:eng_x_preferred":[
        "Nagla Sati"
    ],
    "wof:name":"Nagla Sati",
    "wof:placetype":"locality",
    "wof:population":123
},
  "geometry": {"coordinates":[77.86347000000001,27.738757],"type":"Point"}
}