{
  "type": "Feature",
  "properties": {
    "iso:country":"IN",
    "ks:ks_alt_nam":"HARIZAN TOLA",
    "ks:ks_name":"Harizan Tola",
    "ks:ks_pop":278,
    "ks:ks_type":"HABITATION",
    "name:eng_x_preferred":[
        "Harizan Tola"
    ],
    "wof:name":"Harizan Tola",
    "wof:placetype":"locality",
    "wof:population":278
},
  "geometry": {"coordinates":[86.00633000000001,25.1494],"type":"Point"}
}