{
  "type": "Feature",
  "properties": {
    "iso:country":"IN",
    "ks:ks_name":"Tekulagudem Chalk-II",
    "ks:ks_pop":60,
    "ks:ks_type":"VILLAGE",
    "name:eng_x_preferred":[
        "Tekulagudem Chalk-II"
    ],
    "wof:name":"Tekulagudem Chalk-II",
    "wof:placetype":"locality",
    "wof:population":60
},
  "geometry": {"coordinates":[80.406041,18.551741],"type":"Point"}
}