{
  "type": "Feature",
  "properties": {
    "iso:country":"IN",
    "ks:ks_name":"Dadhisinga",
    "ks:ks_pop":100,
    "ks:ks_type":"VILLAGE",
    "name:eng_x_preferred":[
        "Dadhisinga"
    ],
    "wof:name":"Dadhisinga",
    "wof:placetype":"locality",
    "wof:population":100
},
  "geometry": {"coordinates":[85.857972,20.904925],"type":"Point"}
}