{
  "type": "Feature",
  "properties": {
    "iso:country":"IN",
    "ks:ks_name":"Chak Hatisala",
    "ks:ks_pop":4245,
    "ks:ks_type":"VILLAGE",
    "ks:ks_uagg_main":0,
    "name:eng_x_preferred":[
        "Chak Hatisala"
    ],
    "wof:name":"Chak Hatisala",
    "wof:placetype":"neighbourhood",
    "wof:population":4245
},
  "geometry": {"coordinates":[88.39701700000001,23.589745],"type":"Point"}
}