{
  "type": "Feature",
  "properties": {
    "iso:country":"IN",
    "ks:ks_name":"Aghai",
    "ks:ks_pop":335,
    "ks:ks_type":"VILLAGE",
    "name:eng_x_preferred":[
        "Aghai"
    ],
    "wof:name":"Aghai",
    "wof:placetype":"locality",
    "wof:population":335
},
  "geometry": {"coordinates":[73.240436,18.708954],"type":"Point"}
}