{
  "type": "Feature",
  "properties": {
    "gn:admin1_code":"35",
    "gn:admin2_code":"436.0",
    "gn:asciiname":"Mahuriya",
    "gn:country_code":"IN",
    "gn:dem":460,
    "gn:feature_class":"P",
    "gn:feature_code":"PPL",
    "gn:name":"Mahuriya",
    "gn:population":0,
    "gn:timezone":"Asia/Kolkata",
    "iso:country":"IN",
    "name:und_x_variant":[
        "Mahuria"
    ],
    "wof:name":"Mahuriya",
    "wof:placetype":"locality"
},
  "geometry": {"coordinates":[76.08601999999998,23.8156],"type":"Point"}
}