{
  "type": "Feature",
  "properties": {
    "iso:country":"IN",
    "ks:ks_name":"Tola Naudihwa",
    "ks:ks_pop":517,
    "ks:ks_type":"HABITATION",
    "name:eng_x_preferred":[
        "Tola Naudihwa"
    ],
    "wof:name":"Tola Naudihwa",
    "wof:placetype":"locality",
    "wof:population":517
},
  "geometry": {"coordinates":[82.965581,27.270344],"type":"Point"}
}