{
  "type": "Feature",
  "properties": {
    "gn:admin1_code":"16",
    "gn:admin2_code":"501.0",
    "gn:asciiname":"Sonala",
    "gn:country_code":"IN",
    "gn:dem":322,
    "gn:feature_class":"P",
    "gn:feature_code":"PPL",
    "gn:name":"Son\u0101la",
    "gn:population":0,
    "gn:timezone":"Asia/Kolkata",
    "iso:country":"IN",
    "name:new_x_preferred":[
        "\u0938\u0902\u0917\u094d\u0930\u093e\u092e\u092a\u0941\u0930"
    ],
    "wof:name":"Sonala",
    "wof:placetype":"locality"
},
  "geometry": {"coordinates":[77.15583000000002,20.65439],"type":"Point"}
}