{
  "type": "Feature",
  "properties": {
    "gn:admin1_code":"34.0",
    "gn:admin2_code":"213.0",
    "gn:asciiname":"Mohiuddinpur",
    "gn:country_code":"IN",
    "gn:dem":40,
    "gn:feature_class":"P",
    "gn:feature_code":"PPL",
    "gn:name":"Mohiudd\u012bnpur",
    "gn:population":0,
    "gn:timezone":"Asia/Kolkata",
    "iso:country":"IN",
    "wof:name":"Mohiuddinpur",
    "wof:placetype":"locality"
},
  "geometry": {"coordinates":[86.89805,25.61497],"type":"Point"}
}