{
  "type": "Feature",
  "properties": {
    "iso:country":"IN",
    "ks:ks_name":"4 MMK",
    "ks:ks_pop":229,
    "ks:ks_type":"VILLAGE",
    "name:eng_x_preferred":[
        "4 MMK"
    ],
    "wof:name":"4 MMK",
    "wof:placetype":"locality",
    "wof:population":229
},
  "geometry": {"coordinates":[74.400499,29.718196],"type":"Point"}
}