{
  "type": "Feature",
  "properties": {
    "gn:admin1_code":"23.0",
    "gn:admin2_code":"043",
    "gn:asciiname":"Maujgarh",
    "gn:country_code":"IN",
    "gn:dem":181,
    "gn:feature_class":"P",
    "gn:feature_code":"PPL",
    "gn:name":"Maujgarh",
    "gn:population":0,
    "gn:timezone":"Asia/Kolkata",
    "iso:country":"IN",
    "wof:name":"Maujgarh",
    "wof:placetype":"locality"
},
  "geometry": {"coordinates":[73.98611,30.0625],"type":"Point"}
}