{
  "type": "Feature",
  "properties": {
    "iso:country":"IN",
    "ks:ks_alt_nam":"DAMODARPUR",
    "ks:ks_name":"Damodarpur",
    "ks:ks_pop":189,
    "ks:ks_type":"HABITATION",
    "name:eng_x_preferred":[
        "Damodarpur"
    ],
    "wof:name":"Damodarpur",
    "wof:placetype":"locality",
    "wof:population":189
},
  "geometry": {"coordinates":[86.707787,25.171866],"type":"Point"}
}