{
  "type": "Feature",
  "properties": {
    "gn:admin1_code":"36.0",
    "gn:admin2_code":"152.0",
    "gn:asciiname":"Naugawan Gobindpur",
    "gn:country_code":"IN",
    "gn:dem":158,
    "gn:feature_class":"P",
    "gn:feature_code":"PPL",
    "gn:name":"Naugaw\u0101n Gobindpur",
    "gn:population":0,
    "gn:timezone":"Asia/Kolkata",
    "iso:country":"IN",
    "wof:name":"Naugawan Gobindpur",
    "wof:placetype":"locality"
},
  "geometry": {"coordinates":[79.55429000000002,28.00246],"type":"Point"}
}