{
  "type": "Feature",
  "properties": {
    "gn:admin1_code":"23.0",
    "gn:admin2_code":"48.0",
    "gn:asciiname":"Harigarh Buta Singhwala",
    "gn:country_code":"IN",
    "gn:dem":240,
    "gn:feature_class":"P",
    "gn:feature_code":"PPL",
    "gn:name":"Har\u012bgarh B\u016bta Singhw\u0101la",
    "gn:population":0,
    "gn:timezone":"Asia/Kolkata",
    "iso:country":"IN",
    "wof:name":"Harigarh Buta Singhwala",
    "wof:placetype":"neighbourhood"
},
  "geometry": {"coordinates":[76.15088,30.02989],"type":"Point"}
}