{
  "type": "Feature",
  "properties": {
    "iso:country":"IN",
    "ks:ks_name":"Shiv Garh",
    "ks:ks_pop":5,
    "ks:ks_type":"HABITATION",
    "name:eng_x_preferred":[
        "Shiv Garh"
    ],
    "wof:name":"Shiv Garh",
    "wof:placetype":"locality",
    "wof:population":5
},
  "geometry": {"coordinates":[82.361277,26.700264],"type":"Point"}
}