{
  "type": "Feature",
  "properties": {
    "iso:country":"IN",
    "ks:ks_name":"Tagadaiana",
    "ks:ks_pop":155,
    "ks:ks_type":"HABITATION",
    "name:eng_x_preferred":[
        "Tagadaiana"
    ],
    "wof:name":"Tagadaiana",
    "wof:placetype":"locality",
    "wof:population":155
},
  "geometry": {"coordinates":[77.22466799999999,12.355987],"type":"Point"}
}