{
  "type": "Feature",
  "properties": {
    "gn:admin1_code":"11",
    "gn:admin2_code":"27.0",
    "gn:asciiname":"Sarmana",
    "gn:country_code":"IN",
    "gn:dem":1065,
    "gn:feature_class":"P",
    "gn:feature_code":"PPL",
    "gn:name":"Sarm\u0101na",
    "gn:population":0,
    "gn:timezone":"Asia/Kolkata",
    "iso:country":"IN",
    "wof:name":"Sarmana",
    "wof:placetype":"locality"
},
  "geometry": {"coordinates":[76.81941999999999,31.85726],"type":"Point"}
}