{
  "type": "Feature",
  "properties": {
    "iso:country":"IN",
    "ks:ks_name":"Mirjapur",
    "ks:ks_pop":2089,
    "ks:ks_type":"VILLAGE",
    "name:eng_x_preferred":[
        "Mirjapur"
    ],
    "wof:name":"Mirjapur",
    "wof:placetype":"locality",
    "wof:population":2089
},
  "geometry": {"coordinates":[86.42684800000001,20.801491],"type":"Point"}
}