{
  "type": "Feature",
  "properties": {
    "gn:admin1_code":"11",
    "gn:admin2_code":"23.0",
    "gn:asciiname":"Garehr",
    "gn:country_code":"IN",
    "gn:dem":1469,
    "gn:feature_class":"P",
    "gn:feature_code":"PPL",
    "gn:name":"Garehr",
    "gn:population":0,
    "gn:timezone":"Asia/Kolkata",
    "iso:country":"IN",
    "wof:name":"Garehr",
    "wof:placetype":"locality"
},
  "geometry": {"coordinates":[76.53466,32.45618],"type":"Point"}
}