{
  "type": "Feature",
  "properties": {
    "iso:country":"IN",
    "ks:ks_name":"Badalu Purwa",
    "ks:ks_pop":256,
    "ks:ks_type":"HABITATION",
    "name:eng_x_preferred":[
        "Badalu Purwa"
    ],
    "wof:name":"Badalu Purwa",
    "wof:placetype":"locality",
    "wof:population":256
},
  "geometry": {"coordinates":[81.07845399999999,25.239254],"type":"Point"}
}