{
  "type": "Feature",
  "properties": {
    "iso:country":"IN",
    "ks:ks_alt_nam":"PARIHARPUR N",
    "ks:ks_name":"Pariharpur N",
    "ks:ks_pop":1243,
    "ks:ks_type":"HABITATION",
    "name:eng_x_preferred":[
        "Pariharpur N"
    ],
    "wof:name":"Pariharpur N",
    "wof:placetype":"locality",
    "wof:population":1243
},
  "geometry": {"coordinates":[88.155644,25.724047],"type":"Point"}
}