{
  "type": "Feature",
  "properties": {
    "iso:country":"IN",
    "ks:ks_name":"Ramwadi",
    "ks:ks_pop":218,
    "ks:ks_type":"HABITATION",
    "name:eng_x_preferred":[
        "Ramwadi"
    ],
    "wof:name":"Ramwadi",
    "wof:placetype":"locality",
    "wof:population":218
},
  "geometry": {"coordinates":[73.765603,16.719619],"type":"Point"}
}