{
  "type": "Feature",
  "properties": {
    "iso:country":"IN",
    "ks:ks_name":"Sultanpur",
    "ks:ks_pop":6512,
    "ks:ks_type":"VILLAGE",
    "ks:ks_uagg_main":0,
    "name:eng_x_preferred":[
        "Sultanpur"
    ],
    "wof:name":"Sultanpur",
    "wof:placetype":"neighbourhood",
    "wof:population":6512
},
  "geometry": {"coordinates":[87.916499,25.627945],"type":"Point"}
}