{
  "type": "Feature",
  "properties": {
    "iso:country":"IN",
    "ks:ks_name":"Baliand",
    "ks:ks_pop":436,
    "ks:ks_type":"VILLAGE",
    "ks:ks_uagg_main":0,
    "name:eng_x_preferred":[
        "Baliand"
    ],
    "wof:name":"Baliand",
    "wof:placetype":"neighbourhood",
    "wof:population":436
},
  "geometry": {"coordinates":[85.322639,24.006267],"type":"Point"}
}