{
  "type": "Feature",
  "properties": {
    "iso:country":"IN",
    "ks:ks_name":"Singapad",
    "ks:ks_pop":228,
    "ks:ks_type":"HABITATION",
    "name:eng_x_preferred":[
        "Singapad"
    ],
    "wof:name":"Singapad",
    "wof:placetype":"locality",
    "wof:population":228
},
  "geometry": {"coordinates":[81.176278,18.084899],"type":"Point"}
}