{
  "type": "Feature",
  "properties": {
    "gn:admin1_code":"19.0",
    "gn:admin2_code":"572.0",
    "gn:asciiname":"Shivanhalli",
    "gn:country_code":"IN",
    "gn:dem":937,
    "gn:feature_class":"P",
    "gn:feature_code":"PPL",
    "gn:name":"Shivanhalli",
    "gn:population":0,
    "gn:timezone":"Asia/Kolkata",
    "iso:country":"IN",
    "wof:name":"Shivanhalli",
    "wof:placetype":"locality"
},
  "geometry": {"coordinates":[77.57481,12.72264],"type":"Point"}
}