{
  "type": "Feature",
  "properties": {
    "iso:country":"IN",
    "ks:ks_name":"Kunnathully",
    "ks:ks_pop":721,
    "ks:ks_type":"HABITATION",
    "name:eng_x_preferred":[
        "Kunnathully"
    ],
    "wof:name":"Kunnathully",
    "wof:placetype":"locality",
    "wof:population":721
},
  "geometry": {"coordinates":[76.42403400000001,11.01153],"type":"Point"}
}