{
  "type": "Feature",
  "properties": {
    "iso:country":"IN",
    "ks:ks_alt_nam":"baghav vasti",
    "ks:ks_name":"Baghav Vasti",
    "ks:ks_pop":100,
    "ks:ks_type":"HABITATION",
    "name:eng_x_preferred":[
        "Baghav Vasti"
    ],
    "wof:name":"Baghav Vasti",
    "wof:placetype":"locality",
    "wof:population":100
},
  "geometry": {"coordinates":[74.476517,18.069003],"type":"Point"}
}