{
  "type": "Feature",
  "properties": {
    "gn:admin1_code":"35",
    "gn:admin2_code":"455.0",
    "gn:asciiname":"Piparia Fetehpur",
    "gn:country_code":"IN",
    "gn:dem":679,
    "gn:feature_class":"P",
    "gn:feature_code":"PPL",
    "gn:name":"Piparia Fetehpur",
    "gn:population":0,
    "gn:timezone":"Asia/Kolkata",
    "iso:country":"IN",
    "wof:name":"Piparia Fetehpur",
    "wof:placetype":"locality"
},
  "geometry": {"coordinates":[79.2958,22.18156],"type":"Point"}
}