{
  "type": "Feature",
  "properties": {
    "iso:country":"IN",
    "ks:ks_name":"Katerbata",
    "ks:ks_pop":427,
    "ks:ks_type":"VILLAGE",
    "name:eng_x_preferred":[
        "Katerbata"
    ],
    "wof:name":"Katerbata",
    "wof:placetype":"locality",
    "wof:population":427
},
  "geometry": {"coordinates":[83.80399199999999,20.262172],"type":"Point"}
}