{
  "type": "Feature",
  "properties": {
    "gn:admin1_code":"34.0",
    "gn:admin2_code":"215.0",
    "gn:asciiname":"Karaund",
    "gn:country_code":"IN",
    "gn:dem":50,
    "gn:feature_class":"P",
    "gn:feature_code":"PPL",
    "gn:name":"Karaund",
    "gn:population":0,
    "gn:timezone":"Asia/Kolkata",
    "iso:country":"IN",
    "wof:name":"Karaund",
    "wof:placetype":"locality"
},
  "geometry": {"coordinates":[86.23433,25.97414],"type":"Point"}
}