{
  "type": "Feature",
  "properties": {
    "iso:country":"IN",
    "ks:ks_name":"Seri Faizabad",
    "ks:ks_pop":425,
    "ks:ks_type":"VILLAGE",
    "name:eng_x_preferred":[
        "Seri Faizabad"
    ],
    "wof:name":"Seri Faizabad",
    "wof:placetype":"locality",
    "wof:population":425
},
  "geometry": {"coordinates":[78.139572,17.857099],"type":"Point"}
}