{
  "type": "Feature",
  "properties": {
    "iso:country":"IN",
    "ks:ks_alt_nam":"Thadathil purai",
    "ks:ks_name":"Thadathil Purai",
    "ks:ks_pop":458,
    "ks:ks_type":"HABITATION",
    "name:eng_x_preferred":[
        "Thadathil Purai"
    ],
    "wof:name":"Thadathil Purai",
    "wof:placetype":"locality",
    "wof:population":458
},
  "geometry": {"coordinates":[75.79250500000001,11.414626],"type":"Point"}
}