{
  "type": "Feature",
  "properties": {
    "iso:country":"IN",
    "ks:ks_name":"Chamar Deeh",
    "ks:ks_pop":79,
    "ks:ks_type":"HABITATION",
    "name:eng_x_preferred":[
        "Chamar Deeh"
    ],
    "wof:name":"Chamar Deeh",
    "wof:placetype":"locality",
    "wof:population":79
},
  "geometry": {"coordinates":[83.21234200000001,27.306957],"type":"Point"}
}