{
  "type": "Feature",
  "properties": {
    "gn:admin1_code":"35",
    "gn:asciiname":"Lawada",
    "gn:country_code":"IN",
    "gn:dem":856,
    "gn:feature_class":"P",
    "gn:feature_code":"PPL",
    "gn:name":"Law\u0101da",
    "gn:population":0,
    "gn:timezone":"Asia/Kolkata",
    "iso:country":"IN",
    "ks:ks_alt_nam":"Law\u0101da",
    "ks:ks_name":"Lawada",
    "ks:ks_type":"VILLAGE",
    "name:eng_x_preferred":[
        "Lawada"
    ],
    "name:eng_x_variant":[
        "Law\u0101da"
    ],
    "wof:name":"Lawada",
    "wof:placetype":"locality"
},
  "geometry": {"coordinates":[77.47014900000001,21.437202],"type":"Point"}
}