{
  "type": "Feature",
  "properties": {
    "iso:country":"IN",
    "ks:ks_name":"Nizampur",
    "ks:ks_pop":2,
    "ks:ks_type":"HABITATION",
    "name:eng_x_preferred":[
        "Nizampur"
    ],
    "wof:name":"Nizampur",
    "wof:placetype":"locality",
    "wof:population":2
},
  "geometry": {"coordinates":[77.045265,20.698839],"type":"Point"}
}