{
  "type": "Feature",
  "properties": {
    "gn:admin1_code":"39.0",
    "gn:admin2_code":"66.0",
    "gn:asciiname":"Kharak Dhura",
    "gn:country_code":"IN",
    "gn:dem":1892,
    "gn:feature_class":"P",
    "gn:feature_code":"PPL",
    "gn:name":"Kharak Dhura",
    "gn:population":0,
    "gn:timezone":"Asia/Kolkata",
    "iso:country":"IN",
    "wof:name":"Kharak Dhura",
    "wof:placetype":"locality"
},
  "geometry": {"coordinates":[79.58544999999999,29.47519],"type":"Point"}
}