{
  "type": "Feature",
  "properties": {
    "gn:admin1_code":"12.0",
    "gn:admin2_code":"008",
    "gn:asciiname":"Gund Ibrahim",
    "gn:country_code":"IN",
    "gn:dem":1583,
    "gn:feature_class":"P",
    "gn:feature_code":"PPL",
    "gn:name":"Gund Ibr\u0101h\u012bm",
    "gn:population":0,
    "gn:timezone":"Asia/Kolkata",
    "iso:country":"IN",
    "wof:name":"Gund Ibrahim",
    "wof:placetype":"locality"
},
  "geometry": {"coordinates":[74.58323,34.17941],"type":"Point"}
}