{
  "type": "Feature",
  "properties": {
    "gn:admin1_code":"36",
    "gn:admin2_code":"159.0",
    "gn:asciiname":"Karimnagar",
    "gn:country_code":"IN",
    "gn:dem":161,
    "gn:feature_class":"P",
    "gn:feature_code":"PPL",
    "gn:name":"Kar\u012bmnagar",
    "gn:population":0,
    "gn:timezone":"Asia/Kolkata",
    "iso:country":"IN",
    "name:ara_x_preferred":[
        "\u0643\u0631\u064a\u0645 \u0646\u062c\u0631"
    ],
    "name:ben_x_preferred":[
        "\u0995\u09b0\u09bf\u09ae\u09a8\u0997\u09b0"
    ],
    "name:bih_x_preferred":[
        "\u0915\u0930\u0940\u092e\u0928\u0917\u0930"
    ],
    "name:bpy_x_preferred":[
        "\u0995\u09b0\u09bf\u09ae\u09a8\u0997\u09b0"
    ],
    "name:ceb_x_preferred":[
        "Kar\u012bmnagar"
    ],
    "name:deu_x_preferred":[
        "Karimnagar"
    ],
    "name:fas_x_preferred":[
        "\u06a9\u0631\u06cc\u0645\u200c\u0646\u06af\u0631"
    ],
    "name:fin_x_preferred":[
        "Karimnagar"
    ],
    "name:fra_x_preferred":[
        "Karimnagar"
    ],
    "name:hin_x_preferred":[
        "\u0915\u0930\u0940\u092e\u0928\u0917\u0930"
    ],
    "name:ind_x_preferred":[
        "Karimnagar"
    ],
    "name:ita_x_preferred":[
        "Karimnagar"
    ],
    "name:jpn_x_preferred":[
        "\u30ab\u30ea\u30fc\u30e0\u30ca\u30ac\u30eb"
    ],
    "name:mar_x_preferred":[
        "\u0915\u0930\u0940\u092e\u0928\u0917\u0930"
    ],
    "name:mlg_x_preferred":[
        "Karimnagar"
    ],
    "name:msa_x_preferred":[
        "Karimnagar"
    ],
    "name:nep_x_preferred":[
        "\u0915\u0930\u0940\u092e\u0928\u0917\u0930"
    ],
    "name:new_x_preferred":[
        "\u0915\u0930\u093f\u092e\u0928\u0917\u0930"
    ],
    "name:ori_x_preferred":[
        "\u0b15\u0b30\u0b3f\u0b2e\u0b28\u0b17\u0b30"
    ],
    "name:pam_x_preferred":[
        "Karimnagar"
    ],
    "name:pan_x_preferred":[
        "\u0a15\u0a30\u0a40\u0a2e\u0a28\u0a17\u0a30"
    ],
    "name:pnb_x_preferred":[
        "\u06a9\u0631\u06cc\u0645\u0646\u06af\u0631"
    ],
    "name:pol_x_preferred":[
        "Karimnagar"
    ],
    "name:por_x_preferred":[
        "Karimnagar"
    ],
    "name:rus_x_preferred":[
        "\u041a\u0430\u0440\u0438\u043c\u043d\u0430\u0433\u0430\u0440"
    ],
    "name:san_x_preferred":[
        "\u0915\u0930\u0940\u092e\u0928\u0917\u0930\u092e\u094d"
    ],
    "name:spa_x_preferred":[
        "Karimnagar"
    ],
    "name:srp_x_preferred":[
        "\u041a\u0430\u0440\u0438\u043c\u043d\u0430\u0433\u0430\u0440"
    ],
    "name:swe_x_preferred":[
        "Karimnagar"
    ],
    "name:tam_x_preferred":[
        "\u0b95\u0bb0\u0bc0\u0bae\u0bcd\u0ba8\u0b95\u0bb0\u0bcd"
    ],
    "name:tel_x_preferred":[
        "\u0c15\u0c30\u0c40\u0c02\u0c28\u0c17\u0c30\u0c4d \u0c1c\u0c3f\u0c32\u0c4d\u0c32\u0c3e"
    ],
    "name:urd_x_preferred":[
        "\u06a9\u0631\u06cc\u0645 \u0646\u06af\u0631"
    ],
    "name:vie_x_preferred":[
        "Karimnagar"
    ],
    "name:war_x_preferred":[
        "Karimnagar"
    ],
    "name:zho_x_preferred":[
        "\u5361\u56e0\u7d0d\u52a0\u723e"
    ],
    "wof:name":"Karimnagar",
    "wof:placetype":"locality"
},
  "geometry": {"coordinates":[79.3199,27.56879],"type":"Point"}
}