{
  "type": "Feature",
  "properties": {
    "iso:country":"IN",
    "ks:ks_alt_nam":"NAYAN PARA",
    "ks:ks_name":"Nayan Para",
    "ks:ks_pop":16,
    "ks:ks_type":"HABITATION",
    "ks:ks_uagg_main":0,
    "name:eng_x_preferred":[
        "Nayan Para"
    ],
    "wof:name":"Nayan Para",
    "wof:placetype":"neighbourhood",
    "wof:population":16
},
  "geometry": {"coordinates":[91.415187,23.672062],"type":"Point"}
}