{
  "type": "Feature",
  "properties": {
    "iso:country":"IN",
    "ks:ks_alt_nam":"Leprocy colony",
    "ks:ks_name":"Leprocy Colony",
    "ks:ks_pop":95,
    "ks:ks_type":"HABITATION",
    "name:eng_x_preferred":[
        "Leprocy Colony"
    ],
    "wof:name":"Leprocy Colony",
    "wof:placetype":"locality",
    "wof:population":95
},
  "geometry": {"coordinates":[79.576722,14.198341],"type":"Point"}
}