{
  "type": "Feature",
  "properties": {
    "iso:country":"IN",
    "ks:ks_name":"Dhawalewadi",
    "ks:ks_pop":69,
    "ks:ks_type":"HABITATION",
    "name:eng_x_preferred":[
        "Dhawalewadi"
    ],
    "wof:name":"Dhawalewadi",
    "wof:placetype":"locality",
    "wof:population":69
},
  "geometry": {"coordinates":[73.600869,16.0989],"type":"Point"}
}