{
  "type": "Feature",
  "properties": {
    "iso:country":"IN",
    "ks:ks_name":"Harinmara",
    "ks:ks_pop":851,
    "ks:ks_type":"VILLAGE",
    "name:eng_x_preferred":[
        "Harinmara"
    ],
    "wof:name":"Harinmara",
    "wof:placetype":"locality",
    "wof:population":851
},
  "geometry": {"coordinates":[89.43685600000001,26.448601],"type":"Point"}
}