{
  "type": "Feature",
  "properties": {
    "iso:country":"IN",
    "ks:ks_name":"Bhimarayunicheruvu",
    "ks:ks_pop":112,
    "ks:ks_type":"HABITATION",
    "name:eng_x_preferred":[
        "Bhimarayunicheruvu"
    ],
    "wof:name":"Bhimarayunicheruvu",
    "wof:placetype":"locality",
    "wof:population":112
},
  "geometry": {"coordinates":[78.90558,15.697398],"type":"Point"}
}