{
  "type": "Feature",
  "properties": {
    "iso:country":"IN",
    "ks:ks_name":"Nandi",
    "ks:ks_type":"VILLAGE",
    "name:eng_x_preferred":[
        "Nandi"
    ],
    "wof:name":"Nandi",
    "wof:placetype":"locality"
},
  "geometry": {"coordinates":[79.88194900000001,23.215912],"type":"Point"}
}