{
  "type": "Feature",
  "properties": {
    "iso:country":"IN",
    "ks:ks_name":"Dodiapara",
    "ks:ks_pop":236,
    "ks:ks_type":"HABITATION",
    "name:eng_x_preferred":[
        "Dodiapara"
    ],
    "wof:name":"Dodiapara",
    "wof:placetype":"locality",
    "wof:population":236
},
  "geometry": {"coordinates":[72.252071,22.338141],"type":"Point"}
}