{
  "type": "Feature",
  "properties": {
    "iso:country":"IN",
    "ks:ks_name":"K R Peta",
    "ks:ks_pop":65,
    "ks:ks_type":"HABITATION",
    "name:eng_x_preferred":[
        "K R Peta"
    ],
    "wof:name":"K R Peta",
    "wof:placetype":"locality",
    "wof:population":65
},
  "geometry": {"coordinates":[83.63670999999999,18.327089],"type":"Point"}
}