{
  "type": "Feature",
  "properties": {
    "iso:country":"IN",
    "ks:ks_alt_nam":"MEHRANGARH",
    "ks:ks_name":"Mehrangarh",
    "ks:ks_pop":381,
    "ks:ks_type":"HABITATION",
    "name:eng_x_preferred":[
        "Mehrangarh"
    ],
    "wof:name":"Mehrangarh",
    "wof:placetype":"locality",
    "wof:population":381
},
  "geometry": {"coordinates":[71.08567499999999,25.364131],"type":"Point"}
}