{
  "type": "Feature",
  "properties": {
    "gn:admin1_code":"38.0",
    "gn:admin2_code":"352.0",
    "gn:asciiname":"Rangamatia",
    "gn:country_code":"IN",
    "gn:dem":100,
    "gn:feature_class":"P",
    "gn:feature_code":"PPL",
    "gn:name":"R\u0101ng\u0101m\u0101tia",
    "gn:population":0,
    "gn:timezone":"Asia/Kolkata",
    "iso:country":"IN",
    "ks:ks_name":"Rangmatia",
    "ks:ks_pop":447,
    "ks:ks_type":"VILLAGE",
    "name:eng_x_preferred":[
        "Rangmatia"
    ],
    "name:eng_x_variant":[
        "Rangamatia"
    ],
    "wof:name":"Rangmatia",
    "wof:placetype":"locality",
    "wof:population":447
},
  "geometry": {"coordinates":[87.557166,25.079316],"type":"Point"}
}