{
  "type": "Feature",
  "properties": {
    "iso:country":"IN",
    "ks:ks_name":"Ichhlampur",
    "ks:ks_pop":5012,
    "ks:ks_type":"VILLAGE",
    "ks:ks_uagg_main":0,
    "name:eng_x_preferred":[
        "Ichhlampur"
    ],
    "wof:name":"Ichhlampur",
    "wof:placetype":"neighbourhood",
    "wof:population":5012
},
  "geometry": {"coordinates":[88.04877399999999,24.581554],"type":"Point"}
}