{
  "type": "Feature",
  "properties": {
    "gn:admin1_code":"39.0",
    "gn:admin2_code":"64.0",
    "gn:asciiname":"Pipal Tanda",
    "gn:country_code":"IN",
    "gn:dem":1153,
    "gn:feature_class":"P",
    "gn:feature_code":"PPL",
    "gn:name":"P\u012bpal T\u0101nda",
    "gn:population":0,
    "gn:timezone":"Asia/Kolkata",
    "iso:country":"IN",
    "ks:ks_name":"Pipal Tana",
    "ks:ks_pop":159,
    "ks:ks_type":"VILLAGE",
    "name:eng_x_preferred":[
        "Pipal Tana"
    ],
    "name:eng_x_variant":[
        "Pipal Tanda"
    ],
    "wof:name":"Pipal Tana",
    "wof:placetype":"locality",
    "wof:population":159
},
  "geometry": {"coordinates":[79.44688499999999,29.686092],"type":"Point"}
}