{
  "type": "Feature",
  "properties": {
    "iso:country":"IN",
    "name:eng_x_preferred":[
        "Kalbadevi"
    ],
    "name:kan_x_preferred":[
        "\u0c95\u0cb2\u0ccd\u0cac\u0cbe\u0ca6\u0cc7\u0cb5\u0cbf"
    ],
    "name:mar_x_preferred":[
        "\u0915\u093e\u0933\u092c\u093e\u0926\u0947\u0935\u0940"
    ],
    "name:nld_x_preferred":[
        "Kalbadevi"
    ],
    "qs:gn_adm0_cc":"IN",
    "qs:gn_local":1275339,
    "qs:local_max":3819,
    "qs:local_sum":50908,
    "qs:localhoods":70,
    "qs:name":"Kalbadevi",
    "qs:name_adm0":"India",
    "qs:name_adm1":"Maharashtra",
    "qs:name_adm2":"Mumbai",
    "qs:name_local":"Mumbai",
    "qs:photo_max":241,
    "qs:photo_sum":548,
    "qs:placetype":"Suburb",
    "qs:quad_count":4,
    "qs:woe_adm0":23424848,
    "qs:woe_adm1":2345750,
    "qs:woe_adm2":12586539,
    "qs:woe_lau":0,
    "qs:woe_local":2295411,
    "qs:woe_ver":"7.10.0",
    "wd:wordcount":596,
    "wof:lang":[
        "eng"
    ],
    "wof:name":"Kalbadevi",
    "wof:placetype":"neighbourhood"
},
  "geometry": {"coordinates":[72.829341,18.94759],"type":"Point"}
}