{
  "type": "Feature",
  "properties": {
    "iso:country":"IN",
    "ks:ks_alt_nam":"CHIA TOLA",
    "ks:ks_name":"Chia Tola",
    "ks:ks_pop":540,
    "ks:ks_type":"HABITATION",
    "name:eng_x_preferred":[
        "Chia Tola"
    ],
    "wof:name":"Chia Tola",
    "wof:placetype":"locality",
    "wof:population":540
},
  "geometry": {"coordinates":[87.38936099999999,25.935782],"type":"Point"}
}