{
  "type": "Feature",
  "properties": {
    "iso:country":"IN",
    "ks:ks_name":"Amoda",
    "ks:ks_pop":7,
    "ks:ks_type":"VILLAGE",
    "name:eng_x_preferred":[
        "Amoda"
    ],
    "wof:name":"Amoda",
    "wof:placetype":"locality",
    "wof:population":7
},
  "geometry": {"coordinates":[79.446247,23.967952],"type":"Point"}
}