{
  "type": "Feature",
  "properties": {
    "iso:country":"IN",
    "ks:ks_name":"Jagatipur",
    "ks:ks_pop":717,
    "ks:ks_type":"HABITATION",
    "name:eng_x_preferred":[
        "Jagatipur"
    ],
    "wof:name":"Jagatipur",
    "wof:placetype":"locality",
    "wof:population":717
},
  "geometry": {"coordinates":[82.50600300000001,25.440134],"type":"Point"}
}