{
  "type": "Feature",
  "properties": {
    "iso:country":"IN",
    "ks:ks_name":"Michbeda",
    "ks:ks_pop":33,
    "ks:ks_type":"HABITATION",
    "name:eng_x_preferred":[
        "Michbeda"
    ],
    "wof:name":"Michbeda",
    "wof:placetype":"locality",
    "wof:population":33
},
  "geometry": {"coordinates":[80.96574200000001,19.513734],"type":"Point"}
}