{
  "type": "Feature",
  "properties": {
    "gn:admin1_code":"36",
    "gn:admin2_code":"134.0",
    "gn:asciiname":"Takhtpur",
    "gn:country_code":"IN",
    "gn:dem":221,
    "gn:feature_class":"P",
    "gn:feature_code":"PPL",
    "gn:name":"Takhtpur",
    "gn:population":0,
    "gn:timezone":"Asia/Kolkata",
    "iso:country":"IN",
    "wof:name":"Takhtpur",
    "wof:placetype":"locality"
},
  "geometry": {"coordinates":[78.15534,29.13216],"type":"Point"}
}