{
  "type": "Feature",
  "properties": {
    "iso:country":"IN",
    "ks:ks_name":"Khadakohol",
    "ks:ks_pop":375,
    "ks:ks_type":"VILLAGE",
    "name:eng_x_preferred":[
        "Khadakohol"
    ],
    "wof:name":"Khadakohol",
    "wof:placetype":"locality",
    "wof:population":375
},
  "geometry": {"coordinates":[73.303095,20.144061],"type":"Point"}
}