{
  "type": "Feature",
  "properties": {
    "gn:admin1_code":"2",
    "gn:admin2_code":"545.0",
    "gn:asciiname":"Donalanka",
    "gn:country_code":"IN",
    "gn:dem":126,
    "gn:feature_class":"P",
    "gn:feature_code":"PPL",
    "gn:name":"Donalanka",
    "gn:population":0,
    "gn:timezone":"Asia/Kolkata",
    "iso:country":"IN",
    "ks:ks_name":"Donalanka",
    "ks:ks_pop":341,
    "ks:ks_type":"VILLAGE",
    "name:eng_x_preferred":[
        "Donalanka"
    ],
    "wof:name":"Donalanka",
    "wof:placetype":"locality",
    "wof:population":341
},
  "geometry": {"coordinates":[81.708236,17.384356],"type":"Point"}
}