{
  "type": "Feature",
  "properties": {
    "gn:admin1_code":"36",
    "gn:admin2_code":"191.0",
    "gn:asciiname":"Asilpur",
    "gn:country_code":"IN",
    "gn:dem":84,
    "gn:feature_class":"P",
    "gn:feature_code":"PPL",
    "gn:name":"Asilpur",
    "gn:population":0,
    "gn:timezone":"Asia/Kolkata",
    "iso:country":"IN",
    "ks:ks_name":"Asilpur",
    "ks:ks_pop":766,
    "ks:ks_type":"VILLAGE",
    "ks:ks_uagg_main":0,
    "name:eng_x_preferred":[
        "Asilpur"
    ],
    "wof:name":"Asilpur",
    "wof:placetype":"neighbourhood",
    "wof:population":766
},
  "geometry": {"coordinates":[83.01662899999999,25.998642],"type":"Point"}
}