{
  "type": "Feature",
  "properties": {
    "gn:admin1_code":"36",
    "gn:admin2_code":"177.0",
    "gn:asciiname":"Sarai Bairisal",
    "gn:country_code":"IN",
    "gn:dem":100,
    "gn:feature_class":"P",
    "gn:feature_code":"PPL",
    "gn:name":"Sar\u0101i Bairis\u0101l",
    "gn:population":0,
    "gn:timezone":"Asia/Kolkata",
    "iso:country":"IN",
    "ks:ks_name":"Sarai Bairisal",
    "ks:ks_pop":223,
    "ks:ks_type":"HABITATION",
    "ks:ks_uagg_main":0,
    "name:eng_x_preferred":[
        "Sarai Bairisal"
    ],
    "wof:name":"Sarai Bairisal",
    "wof:placetype":"neighbourhood",
    "wof:population":223
},
  "geometry": {"coordinates":[82.314036,26.663101],"type":"Point"}
}