{
  "type": "Feature",
  "properties": {
    "iso:country":"IN",
    "ks:ks_name":"Bannikatta",
    "ks:ks_pop":60,
    "ks:ks_type":"HABITATION",
    "name:eng_x_preferred":[
        "Bannikatta"
    ],
    "wof:name":"Bannikatta",
    "wof:placetype":"locality",
    "wof:population":60
},
  "geometry": {"coordinates":[74.770816,14.578907],"type":"Point"}
}