{
  "type": "Feature",
  "properties": {
    "iso:country":"IN",
    "ks:ks_name":"Hariabad Chak",
    "ks:ks_pop":1846,
    "ks:ks_type":"VILLAGE",
    "name:eng_x_preferred":[
        "Hariabad Chak"
    ],
    "wof:name":"Hariabad Chak",
    "wof:placetype":"locality",
    "wof:population":1846
},
  "geometry": {"coordinates":[85.92872300000001,25.852988],"type":"Point"}
}