{
  "type": "Feature",
  "properties": {
    "iso:country":"IN",
    "ks:ks_name":"Mawaiya",
    "ks:ks_pop":63,
    "ks:ks_type":"HABITATION",
    "name:eng_x_preferred":[
        "Mawaiya"
    ],
    "wof:name":"Mawaiya",
    "wof:placetype":"locality",
    "wof:population":63
},
  "geometry": {"coordinates":[82.748232,25.655775],"type":"Point"}
}