{
  "type": "Feature",
  "properties": {
    "iso:country":"IN",
    "ks:ks_name":"Takurichuk",
    "ks:ks_pop":290,
    "ks:ks_type":"HABITATION",
    "name:eng_x_preferred":[
        "Takurichuk"
    ],
    "wof:name":"Takurichuk",
    "wof:placetype":"locality",
    "wof:population":290
},
  "geometry": {"coordinates":[94.01491799999999,26.627306],"type":"Point"}
}