{
  "type": "Feature",
  "properties": {
    "iso:country":"IN",
    "ks:ks_alt_nam":"P\u0101l Devi",
    "ks:ks_name":"Pal Devi",
    "ks:ks_type":"VILLAGE",
    "name:eng_x_preferred":[
        "Pal Devi"
    ],
    "name:eng_x_variant":[
        "P\u0101l Devi"
    ],
    "wof:name":"Pal Devi",
    "wof:placetype":"locality"
},
  "geometry": {"coordinates":[80.585064,19.094131],"type":"Point"}
}