{
  "type": "Feature",
  "properties": {
    "gn:admin1_code":"36",
    "gn:admin2_code":"175.0",
    "gn:asciiname":"Sadhupur",
    "gn:country_code":"IN",
    "gn:dem":98,
    "gn:feature_class":"P",
    "gn:feature_code":"PPL",
    "gn:name":"S\u0101dhupur",
    "gn:population":0,
    "gn:timezone":"Asia/Kolkata",
    "iso:country":"IN",
    "name:und_x_variant":[
        "S\u0101dhupur",
        "Chak Shaikhl\u0101l"
    ],
    "wof:name":"Sadhupur",
    "wof:placetype":"locality"
},
  "geometry": {"coordinates":[82.02091999999998,25.65223],"type":"Point"}
}