{
  "type": "Feature",
  "properties": {
    "iso:country":"IN",
    "ks:ks_name":"Jambulingapuram",
    "ks:ks_pop":245,
    "ks:ks_type":"HABITATION",
    "name:eng_x_preferred":[
        "Jambulingapuram"
    ],
    "wof:name":"Jambulingapuram",
    "wof:placetype":"locality",
    "wof:population":245
},
  "geometry": {"coordinates":[77.70675,9.10809],"type":"Point"}
}