{
  "type": "Feature",
  "properties": {
    "gn:admin1_code":"38.0",
    "gn:admin2_code":"351.0",
    "gn:asciiname":"Ithari",
    "gn:country_code":"IN",
    "gn:dem":79,
    "gn:feature_class":"P",
    "gn:feature_code":"PPL",
    "gn:name":"Ithari",
    "gn:population":0,
    "gn:timezone":"Asia/Kolkata",
    "iso:country":"IN",
    "ks:ks_name":"Itahari",
    "ks:ks_pop":1314,
    "ks:ks_type":"VILLAGE",
    "name:eng_x_preferred":[
        "Itahari"
    ],
    "name:eng_x_variant":[
        "Ithari"
    ],
    "wof:name":"Itahari",
    "wof:placetype":"locality",
    "wof:population":1314
},
  "geometry": {"coordinates":[87.42633600000001,25.070177],"type":"Point"}
}