{
  "type": "Feature",
  "properties": {
    "gn:admin1_code":"35",
    "gn:admin2_code":"437.0",
    "gn:asciiname":"Janoikheri",
    "gn:country_code":"IN",
    "gn:dem":521,
    "gn:feature_class":"P",
    "gn:feature_code":"PPL",
    "gn:name":"Janoikheri",
    "gn:population":0,
    "gn:timezone":"Asia/Kolkata",
    "iso:country":"IN",
    "wof:name":"Janoikheri",
    "wof:placetype":"locality"
},
  "geometry": {"coordinates":[76.06813000000002,23.06595],"type":"Point"}
}