{
  "type": "Feature",
  "properties": {
    "gn:admin1_code":"16",
    "gn:admin2_code":"509.0",
    "gn:asciiname":"Bormara",
    "gn:country_code":"IN",
    "gn:dem":211,
    "gn:feature_class":"P",
    "gn:feature_code":"PPL",
    "gn:name":"Borm\u0101ra",
    "gn:population":0,
    "gn:timezone":"Asia/Kolkata",
    "iso:country":"IN",
    "wof:name":"Bormara",
    "wof:placetype":"locality"
},
  "geometry": {"coordinates":[79.97075,20.22849],"type":"Point"}
}