{
  "type": "Feature",
  "properties": {
    "iso:country":"IN",
    "ks:ks_name":"Jangal Faliyu",
    "ks:ks_pop":116,
    "ks:ks_type":"HABITATION",
    "name:eng_x_preferred":[
        "Jangal Faliyu"
    ],
    "wof:name":"Jangal Faliyu",
    "wof:placetype":"locality",
    "wof:population":116
},
  "geometry": {"coordinates":[72.85813899999999,20.350222],"type":"Point"}
}