{
  "type": "Feature",
  "properties": {
    "gn:admin1_code":"35.0",
    "gn:admin2_code":"452.0",
    "gn:asciiname":"Amara",
    "gn:country_code":"IN",
    "gn:dem":358,
    "gn:feature_class":"P",
    "gn:feature_code":"PPL",
    "gn:name":"Am\u0101ra",
    "gn:population":0,
    "gn:timezone":"Asia/Kolkata",
    "iso:country":"IN",
    "name:ara_x_preferred":[
        "\u0627\u0644\u0639\u0645\u0627\u0631\u0629"
    ],
    "name:ast_x_preferred":[
        "Amara"
    ],
    "name:cat_x_preferred":[
        "Amara"
    ],
    "name:ceb_x_preferred":[
        "Amara"
    ],
    "name:deu_x_preferred":[
        "Amara"
    ],
    "name:eus_x_preferred":[
        "Amara"
    ],
    "name:fra_x_preferred":[
        "Amara"
    ],
    "name:hun_x_preferred":[
        "Amara"
    ],
    "name:ita_x_preferred":[
        "Amara"
    ],
    "name:kur_x_preferred":[
        "Amara"
    ],
    "name:nld_x_preferred":[
        "Amara"
    ],
    "name:pol_x_preferred":[
        "Amara"
    ],
    "name:por_x_preferred":[
        "Amara"
    ],
    "name:ron_x_preferred":[
        "Amara"
    ],
    "name:rus_x_preferred":[
        "\u0410\u043c\u0430\u0440\u0430"
    ],
    "name:spa_x_preferred":[
        "Amara"
    ],
    "name:srp_x_preferred":[
        "\u0410\u043c\u0430\u0440\u0430"
    ],
    "name:swe_x_preferred":[
        "Amara"
    ],
    "name:ukr_x_preferred":[
        "\u0410\u043c\u0430\u0440\u0430"
    ],
    "name:vie_x_preferred":[
        "Amara"
    ],
    "wof:name":"Amara",
    "wof:placetype":"locality"
},
  "geometry": {"coordinates":[78.70345999999998,22.82052],"type":"Point"}
}