{
  "type": "Feature",
  "properties": {
    "iso:country":"IN",
    "ks:ks_name":"Barghat",
    "ks:ks_pop":269,
    "ks:ks_type":"HABITATION",
    "name:eng_x_preferred":[
        "Barghat"
    ],
    "wof:name":"Barghat",
    "wof:placetype":"locality",
    "wof:population":269
},
  "geometry": {"coordinates":[83.328906,22.247283],"type":"Point"}
}