{
  "type": "Feature",
  "properties": {
    "gn:admin1_code":"36.0",
    "gn:admin2_code":"184.0",
    "gn:asciiname":"Kamharia Buzurg",
    "gn:country_code":"IN",
    "gn:dem":94,
    "gn:feature_class":"P",
    "gn:feature_code":"PPL",
    "gn:name":"Kamharia Buzurg",
    "gn:population":0,
    "gn:timezone":"Asia/Kolkata",
    "iso:country":"IN",
    "ks:ks_name":"Kamharia Buzurg",
    "ks:ks_pop":1807,
    "ks:ks_type":"HABITATION",
    "name:eng_x_preferred":[
        "Kamharia Buzurg"
    ],
    "wof:name":"Kamharia Buzurg",
    "wof:placetype":"locality",
    "wof:population":1807
},
  "geometry": {"coordinates":[82.81825600000001,27.157518],"type":"Point"}
}