{
  "type": "Feature",
  "properties": {
    "iso:country":"IN",
    "ks:ks_name":"Neereri",
    "ks:ks_pop":127,
    "ks:ks_type":"HABITATION",
    "name:eng_x_preferred":[
        "Neereri"
    ],
    "wof:name":"Neereri",
    "wof:placetype":"locality",
    "wof:population":127
},
  "geometry": {"coordinates":[75.166873,13.973342],"type":"Point"}
}