{
  "type": "Feature",
  "properties": {
    "iso:country":"IN",
    "ks:ks_alt_nam":"M D MANGALAM AGR FAM",
    "ks:ks_name":"M D Mangalam Agr Fam",
    "ks:ks_pop":8,
    "ks:ks_type":"HABITATION",
    "name:eng_x_preferred":[
        "M D Mangalam Agr Fam"
    ],
    "wof:name":"M D Mangalam Agr Fam",
    "wof:placetype":"locality",
    "wof:population":8
},
  "geometry": {"coordinates":[79.222269,13.208839],"type":"Point"}
}