{
  "type": "Feature",
  "properties": {
    "iso:country":"IN",
    "ks:ks_name":"Talashibramchak",
    "ks:ks_pop":198,
    "ks:ks_type":"VILLAGE",
    "name:eng_x_preferred":[
        "Talashibramchak"
    ],
    "wof:name":"Talashibramchak",
    "wof:placetype":"locality",
    "wof:population":198
},
  "geometry": {"coordinates":[87.408511,22.308429],"type":"Point"}
}