{
  "type": "Feature",
  "properties": {
    "iso:country":"IN",
    "ks:ks_alt_nam":"MPV 43",
    "ks:ks_name":"Mpv 43",
    "ks:ks_pop":471,
    "ks:ks_type":"HABITATION",
    "name:eng_x_preferred":[
        "Mpv 43"
    ],
    "wof:name":"Mpv 43",
    "wof:placetype":"locality",
    "wof:population":471
},
  "geometry": {"coordinates":[81.579545,18.024462],"type":"Point"}
}