{
  "type": "Feature",
  "properties": {
    "gn:admin1_code":"24.0",
    "gn:admin2_code":"114.0",
    "gn:asciiname":"Mithrao",
    "gn:country_code":"IN",
    "gn:dem":71,
    "gn:feature_class":"P",
    "gn:feature_code":"PPL",
    "gn:name":"Mithrao",
    "gn:population":0,
    "gn:timezone":"Asia/Kolkata",
    "iso:country":"IN",
    "wof:name":"Mithrao",
    "wof:placetype":"locality"
},
  "geometry": {"coordinates":[70.15983,26.16034],"type":"Point"}
}