{
  "type": "Feature",
  "properties": {
    "gn:admin1_code":"11.0",
    "gn:admin2_code":"33.0",
    "gn:asciiname":"Kareli",
    "gn:country_code":"IN",
    "gn:dem":2506,
    "gn:feature_class":"P",
    "gn:feature_code":"PPL",
    "gn:name":"Kareli",
    "gn:population":0,
    "gn:timezone":"Asia/Kolkata",
    "iso:country":"IN",
    "name:ceb_x_preferred":[
        "Kareli"
    ],
    "name:deu_x_preferred":[
        "Kareli"
    ],
    "name:nld_x_preferred":[
        "Kareli"
    ],
    "name:swe_x_preferred":[
        "Kareli"
    ],
    "wof:name":"Kareli",
    "wof:placetype":"locality"
},
  "geometry": {"coordinates":[77.71826999999998,31.33932],"type":"Point"}
}