{
  "type": "Feature",
  "properties": {
    "iso:country":"IN",
    "ks:ks_name":"Sohalpur",
    "ks:ks_type":"VILLAGE",
    "name:eng_x_preferred":[
        "Sohalpur"
    ],
    "wof:name":"Sohalpur",
    "wof:placetype":"locality"
},
  "geometry": {"coordinates":[77.952456,29.876086],"type":"Point"}
}