{
  "type": "Feature",
  "properties": {
    "iso:country":"IN",
    "ks:ks_name":"Raju Bigha",
    "ks:ks_pop":377,
    "ks:ks_type":"HABITATION",
    "name:eng_x_preferred":[
        "Raju Bigha"
    ],
    "wof:name":"Raju Bigha",
    "wof:placetype":"locality",
    "wof:population":377
},
  "geometry": {"coordinates":[85.39208000000001,25.269873],"type":"Point"}
}