{
  "type": "Feature",
  "properties": {
    "iso:country":"IN",
    "ks:ks_alt_nam":"kalagara",
    "ks:ks_name":"Kalagara",
    "ks:ks_pop":281,
    "ks:ks_type":"HABITATION",
    "name:eng_x_preferred":[
        "Kalagara"
    ],
    "wof:name":"Kalagara",
    "wof:placetype":"locality",
    "wof:population":281
},
  "geometry": {"coordinates":[75.267073,13.666416],"type":"Point"}
}