{
  "type": "Feature",
  "properties": {
    "iso:country":"IN",
    "ks:ks_name":"Dhondu Kondu Tanda",
    "ks:ks_pop":110,
    "ks:ks_type":"HABITATION",
    "name:eng_x_preferred":[
        "Dhondu Kondu Tanda"
    ],
    "wof:name":"Dhondu Kondu Tanda",
    "wof:placetype":"locality",
    "wof:population":110
},
  "geometry": {"coordinates":[74.94947500000001,20.243604],"type":"Point"}
}