{
  "type": "Feature",
  "properties": {
    "gn:admin1_code":"36",
    "gn:admin2_code":"146.0",
    "gn:asciiname":"Salemabad",
    "gn:country_code":"IN",
    "gn:dem":172,
    "gn:feature_class":"P",
    "gn:feature_code":"PPL",
    "gn:name":"Salem\u0101b\u0101d",
    "gn:population":0,
    "gn:timezone":"Asia/Kolkata",
    "iso:country":"IN",
    "name:ceb_x_preferred":[
        "R\u016bst\u0101-ye S\u0101lem\u0101b\u0101d"
    ],
    "name:fas_x_preferred":[
        "\u0633\u0627\u0644\u0645\u200c\u0622\u0628\u0627\u062f"
    ],
    "name:msa_x_preferred":[
        "Salemabad"
    ],
    "name:swe_x_preferred":[
        "R\u016bst\u0101-ye S\u0101lem\u0101b\u0101d"
    ],
    "wof:name":"Salemabad",
    "wof:placetype":"locality"
},
  "geometry": {"coordinates":[78.01203000000002,27.07324],"type":"Point"}
}