{
  "type": "Feature",
  "properties": {
    "iso:country":"IN",
    "ks:ks_name":"4 Q",
    "ks:ks_pop":4,
    "ks:ks_type":"HABITATION",
    "name:eng_x_preferred":[
        "4 Q"
    ],
    "wof:name":"4 Q",
    "wof:placetype":"locality",
    "wof:population":4
},
  "geometry": {"coordinates":[73.803675,30.021192],"type":"Point"}
}