{
  "type": "Feature",
  "properties": {
    "iso:country":"IN",
    "ks:ks_name":"Sindriguya",
    "ks:ks_pop":1540,
    "ks:ks_type":"VILLAGE",
    "name:eng_x_preferred":[
        "Sindriguya"
    ],
    "wof:name":"Sindriguya",
    "wof:placetype":"locality",
    "wof:population":1540
},
  "geometry": {"coordinates":[85.797376,22.287907],"type":"Point"}
}