{
  "type": "Feature",
  "properties": {
    "gn:admin1_code":"09",
    "gn:admin2_code":"484.0",
    "gn:asciiname":"Pingli",
    "gn:country_code":"IN",
    "gn:dem":88,
    "gn:feature_class":"P",
    "gn:feature_code":"PPL",
    "gn:name":"Pingli",
    "gn:population":0,
    "gn:timezone":"Asia/Kolkata",
    "iso:country":"IN",
    "wof:name":"Pingli",
    "wof:placetype":"locality"
},
  "geometry": {"coordinates":[73.46934,22.6584],"type":"Point"}
}