{
  "type": "Feature",
  "properties": {
    "iso:country":"IN",
    "ks:ks_name":"Atharaganda",
    "ks:ks_pop":65,
    "ks:ks_type":"VILLAGE",
    "name:eng_x_preferred":[
        "Atharaganda"
    ],
    "wof:name":"Atharaganda",
    "wof:placetype":"locality",
    "wof:population":65
},
  "geometry": {"coordinates":[84.933131,20.209662],"type":"Point"}
}