{
  "type": "Feature",
  "properties": {
    "iso:country":"IN",
    "ks:ks_alt_nam":"Dungaria RYT",
    "ks:ks_name":"Dungaria Ryt",
    "ks:ks_pop":199,
    "ks:ks_type":"HABITATION",
    "name:eng_x_preferred":[
        "Dungaria Ryt"
    ],
    "wof:name":"Dungaria Ryt",
    "wof:placetype":"locality",
    "wof:population":199
},
  "geometry": {"coordinates":[80.300191,22.869882],"type":"Point"}
}