{
  "type": "Feature",
  "properties": {
    "iso:country":"IN",
    "ks:ks_name":"Hasim Pur",
    "ks:ks_pop":2934,
    "ks:ks_type":"VILLAGE",
    "name:eng_x_preferred":[
        "Hasim Pur"
    ],
    "wof:name":"Hasim Pur",
    "wof:placetype":"locality",
    "wof:population":2934
},
  "geometry": {"coordinates":[87.244221,22.092786],"type":"Point"}
}