{
  "type": "Feature",
  "properties": {
    "gn:admin1_code":"12",
    "gn:admin2_code":"13.0",
    "gn:asciiname":"Tsak Mushid",
    "gn:country_code":"IN",
    "gn:dem":2056,
    "gn:feature_class":"P",
    "gn:feature_code":"PPL",
    "gn:name":"Tsak Mush\u012bd",
    "gn:population":0,
    "gn:timezone":"Asia/Kolkata",
    "iso:country":"IN",
    "wof:name":"Tsak Mushid",
    "wof:placetype":"locality"
},
  "geometry": {"coordinates":[74.86224,33.65414000000001],"type":"Point"}
}