{
  "type": "Feature",
  "properties": {
    "iso:country":"IN",
    "ks:ks_name":"Srigamput",
    "ks:ks_pop":280,
    "ks:ks_type":"HABITATION",
    "name:eng_x_preferred":[
        "Srigamput"
    ],
    "wof:name":"Srigamput",
    "wof:placetype":"locality",
    "wof:population":280
},
  "geometry": {"coordinates":[82.598488,18.423237],"type":"Point"}
}