{
  "type": "Feature",
  "properties": {
    "iso:country":"IN",
    "ks:ks_name":"Mand Kalan",
    "ks:ks_pop":1272,
    "ks:ks_type":"VILLAGE",
    "name:eng_x_preferred":[
        "Mand Kalan"
    ],
    "wof:name":"Mand Kalan",
    "wof:placetype":"locality",
    "wof:population":1272
},
  "geometry": {"coordinates":[74.524428,24.201758],"type":"Point"}
}