{
  "type": "Feature",
  "properties": {
    "iso:country":"IN",
    "ks:ks_name":"Tharha",
    "ks:ks_pop":1752,
    "ks:ks_type":"VILLAGE",
    "ks:ks_uagg_main":0,
    "name:eng_x_preferred":[
        "Tharha"
    ],
    "wof:name":"Tharha",
    "wof:placetype":"neighbourhood",
    "wof:population":1752
},
  "geometry": {"coordinates":[87.434645,25.702338],"type":"Point"}
}