{
  "type": "Feature",
  "properties": {
    "iso:country":"IN",
    "ks:ks_name":"Kariguria",
    "ks:ks_pop":508,
    "ks:ks_type":"VILLAGE",
    "name:eng_x_preferred":[
        "Kariguria"
    ],
    "wof:name":"Kariguria",
    "wof:placetype":"locality",
    "wof:population":508
},
  "geometry": {"coordinates":[85.684313,22.139385],"type":"Point"}
}