{
  "type": "Feature",
  "properties": {
    "iso:country":"IN",
    "ks:ks_name":"Mohan Gaon",
    "ks:ks_pop":176,
    "ks:ks_type":"HABITATION",
    "ks:ks_uagg_main":0,
    "name:eng_x_preferred":[
        "Mohan Gaon"
    ],
    "wof:name":"Mohan Gaon",
    "wof:placetype":"neighbourhood",
    "wof:population":176
},
  "geometry": {"coordinates":[94.861716,27.007746],"type":"Point"}
}