{
  "type": "Feature",
  "properties": {
    "iso:country":"IN",
    "ks:ks_name":"Ghodadora",
    "ks:ks_pop":179,
    "ks:ks_type":"HABITATION",
    "name:eng_x_preferred":[
        "Ghodadora"
    ],
    "wof:name":"Ghodadora",
    "wof:placetype":"locality",
    "wof:population":179
},
  "geometry": {"coordinates":[82.692624,18.908299],"type":"Point"}
}