{
  "type": "Feature",
  "properties": {
    "iso:country":"IN",
    "name:bpy_x_preferred":[
        "\u0986\u09b0\u09be\u09b2\u09ac\u0987\u09ae\u09cb\u099d\u09bf"
    ],
    "name:eng_x_preferred":[
        "Aralvaimozhi"
    ],
    "name:fra_x_preferred":[
        "Aralvaimozhi"
    ],
    "name:ita_x_preferred":[
        "Aralvaimozhi"
    ],
    "name:mlg_x_preferred":[
        "Aralvaimozhi"
    ],
    "name:msa_x_preferred":[
        "Aralvaimozhi"
    ],
    "name:nan_x_preferred":[
        "Aralvaimozhi"
    ],
    "name:new_x_preferred":[
        "\u0905\u0930\u0932\u092d\u0948\u092e\u094b\u091d\u0940"
    ],
    "name:nld_x_preferred":[
        "Aralvaimozhi"
    ],
    "name:tam_x_preferred":[
        "\u0b86\u0bb0\u0bb2\u0bcd\u0bb5\u0bbe\u0baf\u0bcd\u0bae\u0bca\u0bb4\u0bbf"
    ],
    "name:vie_x_preferred":[
        "Aralvaimozhi"
    ],
    "name:zho_x_preferred":[
        "\u963f\u62c9\u5c14\u74e6\u4f0a\u83ab\u9f50"
    ],
    "qs:name":"Aralvaimozhi",
    "qs:name_adm0":"India",
    "qs:name_adm1":"Tamil Nadu",
    "qs:photos":31,
    "qs:photos_1k":6,
    "qs:photos_9k":1,
    "qs:photos_9r":2,
    "qs:photos_all":31,
    "qs:photos_sr":2,
    "qs:placetype":"Town",
    "qs:pop_sr":"0",
    "wd:wordcount":316,
    "wof:name":"Aralvaimozhi",
    "wof:placetype":"locality"
},
  "geometry": {"coordinates":[77.527772,8.250374],"type":"Point"}
}