{
  "type": "Feature",
  "properties": {
    "gn:admin1_code":"37",
    "gn:admin2_code":"410.0",
    "gn:asciiname":"Hatmahuwa",
    "gn:country_code":"IN",
    "gn:dem":381,
    "gn:feature_class":"P",
    "gn:feature_code":"PPL",
    "gn:name":"Hatmahuwa",
    "gn:population":0,
    "gn:timezone":"Asia/Kolkata",
    "iso:country":"IN",
    "ks:ks_name":"Hatmahuwa",
    "ks:ks_type":"VILLAGE",
    "name:eng_x_preferred":[
        "Hatmahuwa"
    ],
    "wof:name":"Hatmahuwa",
    "wof:placetype":"locality"
},
  "geometry": {"coordinates":[82.244956,20.584091],"type":"Point"}
}