{
  "type": "Feature",
  "properties": {
    "iso:country":"IN",
    "ks:ks_name":"Dissang Kinar Bangali",
    "ks:ks_pop":1020,
    "ks:ks_type":"VILLAGE",
    "name:eng_x_preferred":[
        "Dissang Kinar Bangali"
    ],
    "wof:name":"Dissang Kinar Bangali",
    "wof:placetype":"locality",
    "wof:population":1020
},
  "geometry": {"coordinates":[95.337614,27.208818],"type":"Point"}
}