{
  "type": "Feature",
  "properties": {
    "gn:admin1_code":"13.0",
    "gn:admin2_code":"590.0",
    "gn:asciiname":"Vellamunda",
    "gn:country_code":"IN",
    "gn:dem":775,
    "gn:feature_class":"P",
    "gn:feature_code":"PPL",
    "gn:name":"Vellamunda",
    "gn:population":0,
    "gn:timezone":"Asia/Kolkata",
    "iso:country":"IN",
    "name:fas_x_preferred":[
        "\u0648\u0644\u0645\u0648\u0646\u062f\u0627"
    ],
    "name:mal_x_preferred":[
        "\u0d35\u0d46\u0d33\u0d4d\u0d33\u0d2e\u0d41\u0d23\u0d4d\u0d1f \u0d17\u0d4d\u0d30\u0d3e\u0d2e\u0d2a\u0d1e\u0d4d\u0d1a\u0d3e\u0d2f\u0d24\u0d4d\u0d24\u0d4d"
    ],
    "wof:name":"Vellamunda",
    "wof:placetype":"locality"
},
  "geometry": {"coordinates":[75.95666,11.72381],"type":"Point"}
}