{
  "type": "Feature",
  "properties": {
    "iso:country":"IN",
    "ks:ks_name":"Dasdih",
    "ks:ks_pop":22,
    "ks:ks_type":"VILLAGE",
    "name:eng_x_preferred":[
        "Dasdih"
    ],
    "wof:name":"Dasdih",
    "wof:placetype":"locality",
    "wof:population":22
},
  "geometry": {"coordinates":[84.323728,23.825136],"type":"Point"}
}