{
  "type": "Feature",
  "properties": {
    "iso:country":"IN",
    "ks:ks_name":"Mertekwadi",
    "ks:ks_pop":20,
    "ks:ks_type":"HABITATION",
    "name:eng_x_preferred":[
        "Mertekwadi"
    ],
    "wof:name":"Mertekwadi",
    "wof:placetype":"locality",
    "wof:population":20
},
  "geometry": {"coordinates":[73.627849,17.588202],"type":"Point"}
}