{
  "type": "Feature",
  "properties": {
    "gn:admin1_code":"39.0",
    "gn:admin2_code":"65.0",
    "gn:asciiname":"Sirna",
    "gn:country_code":"IN",
    "gn:dem":1399,
    "gn:feature_class":"P",
    "gn:feature_code":"PPL",
    "gn:name":"Sirna",
    "gn:population":0,
    "gn:timezone":"Asia/Kolkata",
    "iso:country":"IN",
    "ks:ks_name":"Sirna",
    "ks:ks_pop":83,
    "ks:ks_type":"VILLAGE",
    "name:ceb_x_preferred":[
        "Sirna"
    ],
    "name:eng_x_preferred":[
        "Sirna"
    ],
    "name:swe_x_preferred":[
        "Sirna"
    ],
    "wof:name":"Sirna",
    "wof:placetype":"locality",
    "wof:population":83
},
  "geometry": {"coordinates":[79.882649,29.307663],"type":"Point"}
}