{
  "type": "Feature",
  "properties": {
    "iso:country":"IN",
    "ks:ks_name":"Sampolli",
    "ks:ks_pop":167,
    "ks:ks_type":"VILLAGE",
    "name:eng_x_preferred":[
        "Sampolli"
    ],
    "wof:name":"Sampolli",
    "wof:placetype":"locality",
    "wof:population":167
},
  "geometry": {"coordinates":[74.54758699999999,14.154559],"type":"Point"}
}