{
  "type": "Feature",
  "properties": {
    "iso:country":"IN",
    "ks:ks_name":"Azrakbe Pota",
    "ks:ks_pop":492,
    "ks:ks_type":"VILLAGE",
    "name:eng_x_preferred":[
        "Azrakbe Pota"
    ],
    "wof:name":"Azrakbe Pota",
    "wof:placetype":"locality",
    "wof:population":492
},
  "geometry": {"coordinates":[85.28926,26.482385],"type":"Point"}
}