{
  "type": "Feature",
  "properties": {
    "iso:country":"IN",
    "ks:ks_name":"Palewadi",
    "ks:ks_pop":169,
    "ks:ks_type":"HABITATION",
    "name:eng_x_preferred":[
        "Palewadi"
    ],
    "wof:name":"Palewadi",
    "wof:placetype":"locality",
    "wof:population":169
},
  "geometry": {"coordinates":[73.547319,16.304509],"type":"Point"}
}