{
  "type": "Feature",
  "properties": {
    "iso:country":"IN",
    "ks:ks_name":"Byatappanapalya",
    "ks:ks_pop":90,
    "ks:ks_type":"HABITATION",
    "name:eng_x_preferred":[
        "Byatappanapalya"
    ],
    "wof:name":"Byatappanapalya",
    "wof:placetype":"locality",
    "wof:population":90
},
  "geometry": {"coordinates":[77.01177199999999,12.949612],"type":"Point"}
}