{
  "type": "Feature",
  "properties": {
    "iso:country":"IN",
    "ks:ks_name":"Dhangarwadi",
    "ks:ks_pop":176,
    "ks:ks_type":"HABITATION",
    "name:eng_x_preferred":[
        "Dhangarwadi"
    ],
    "wof:name":"Dhangarwadi",
    "wof:placetype":"locality",
    "wof:population":176
},
  "geometry": {"coordinates":[75.481605,17.956457],"type":"Point"}
}