{
  "type": "Feature",
  "properties": {
    "iso:country":"IN",
    "ks:ks_name":"Korangamal",
    "ks:ks_pop":850,
    "ks:ks_type":"VILLAGE",
    "name:eng_x_preferred":[
        "Korangamal"
    ],
    "wof:name":"Korangamal",
    "wof:placetype":"locality",
    "wof:population":850
},
  "geometry": {"coordinates":[83.92128599999999,22.374869],"type":"Point"}
}