{
  "type": "Feature",
  "properties": {
    "gn:admin1_code":"36.0",
    "gn:admin2_code":"175.0",
    "gn:asciiname":"Dal Tiwari ka Purwa",
    "gn:country_code":"IN",
    "gn:dem":99,
    "gn:feature_class":"P",
    "gn:feature_code":"PPL",
    "gn:name":"D\u0101l Tiw\u0101ri ka Purwa",
    "gn:population":0,
    "gn:timezone":"Asia/Kolkata",
    "iso:country":"IN",
    "wof:name":"Dal Tiwari ka Purwa",
    "wof:placetype":"neighbourhood"
},
  "geometry": {"coordinates":[81.88160999999999,25.54379],"type":"Point"}
}