{
  "type": "Feature",
  "properties": {
    "gn:admin1_code":"36.0",
    "gn:admin2_code":"174.0",
    "gn:asciiname":"Kamalpur",
    "gn:country_code":"IN",
    "gn:dem":100,
    "gn:feature_class":"P",
    "gn:feature_code":"PPL",
    "gn:name":"Kam\u0101lpur",
    "gn:population":0,
    "gn:timezone":"Asia/Kolkata",
    "iso:country":"IN",
    "name:cat_x_preferred":[
        "Kamalpur"
    ],
    "name:ceb_x_preferred":[
        "Kamalpur"
    ],
    "name:fra_x_preferred":[
        "Kamalpur"
    ],
    "name:swe_x_preferred":[
        "Kamalpur"
    ],
    "name:tam_x_preferred":[
        "\u0b95\u0bae\u0bb2\u0bcd\u0baa\u0bc2\u0bb0\u0bcd"
    ],
    "wof:name":"Kamalpur",
    "wof:placetype":"locality"
},
  "geometry": {"coordinates":[81.63805000000001,25.37623],"type":"Point"}
}