{
  "type": "Feature",
  "properties": {
    "gn:admin1_code":"36.0",
    "gn:admin2_code":"174.0",
    "gn:asciiname":"Kamalpur",
    "gn:country_code":"IN",
    "gn:dem":100,
    "gn:feature_class":"P",
    "gn:feature_code":"PPL",
    "gn:name":"Kam\u0101lpur",
    "gn:population":0,
    "gn:timezone":"Asia/Kolkata",
    "iso:country":"IN",
    "wof:name":"Kamalpur",
    "wof:placetype":"locality"
},
  "geometry": {"coordinates":[81.63805000000001,25.37623],"type":"Point"}
}