{
  "type": "Feature",
  "properties": {
    "gn:admin1_code":"24.0",
    "gn:admin2_code":"112.0",
    "gn:asciiname":"Bhengsar",
    "gn:country_code":"IN",
    "gn:dem":362,
    "gn:feature_class":"P",
    "gn:feature_code":"PPL",
    "gn:name":"Bhengsar",
    "gn:population":0,
    "gn:timezone":"Asia/Kolkata",
    "iso:country":"IN",
    "ks:ks_name":"Bhengsar",
    "ks:ks_type":"VILLAGE",
    "name:eng_x_preferred":[
        "Bhengsar"
    ],
    "wof:name":"Bhengsar",
    "wof:placetype":"locality"
},
  "geometry": {"coordinates":[74.61576100000001,27.268883],"type":"Point"}
}