{
  "type": "Feature",
  "properties": {
    "gn:admin1_code":"24.0",
    "gn:admin2_code":"113.0",
    "gn:asciiname":"Unchera",
    "gn:country_code":"IN",
    "gn:dem":277,
    "gn:feature_class":"P",
    "gn:feature_code":"PPL",
    "gn:name":"Unchera",
    "gn:population":0,
    "gn:timezone":"Asia/Kolkata",
    "iso:country":"IN",
    "wof:name":"Unchera",
    "wof:placetype":"locality"
},
  "geometry": {"coordinates":[73.72936999999997,26.19166],"type":"Point"}
}