{
  "type": "Feature",
  "properties": {
    "iso:country":"IN",
    "ks:ks_name":"Devadalaguda",
    "ks:ks_pop":655,
    "ks:ks_type":"HABITATION",
    "name:eng_x_preferred":[
        "Devadalaguda"
    ],
    "wof:name":"Devadalaguda",
    "wof:placetype":"locality",
    "wof:population":655
},
  "geometry": {"coordinates":[83.319861,19.184412],"type":"Point"}
}