{
  "type": "Feature",
  "properties": {
    "iso:country":"IN",
    "ks:ks_name":"Pirpur",
    "ks:ks_pop":586,
    "ks:ks_type":"VILLAGE",
    "name:eng_x_preferred":[
        "Pirpur"
    ],
    "wof:name":"Pirpur",
    "wof:placetype":"locality",
    "wof:population":586
},
  "geometry": {"coordinates":[88.030993,22.457518],"type":"Point"}
}