{
  "type": "Feature",
  "properties": {
    "gn:admin1_code":"19",
    "gn:admin2_code":"568.0",
    "gn:asciiname":"Talvata",
    "gn:country_code":"IN",
    "gn:dem":602,
    "gn:feature_class":"P",
    "gn:feature_code":"PPL",
    "gn:name":"Talvata",
    "gn:population":0,
    "gn:timezone":"Asia/Kolkata",
    "iso:country":"IN",
    "ks:ks_name":"Talavata",
    "ks:ks_pop":597,
    "ks:ks_type":"VILLAGE",
    "name:eng_x_preferred":[
        "Talavata"
    ],
    "name:eng_x_variant":[
        "Talvata"
    ],
    "wof:name":"Talavata",
    "wof:placetype":"locality",
    "wof:population":597
},
  "geometry": {"coordinates":[74.870563,14.221023],"type":"Point"}
}