{
  "type": "Feature",
  "properties": {
    "iso:country":"IN",
    "ks:ks_name":"Gosh Nagar",
    "ks:ks_pop":4105,
    "ks:ks_type":"HABITATION",
    "name:eng_x_preferred":[
        "Gosh Nagar"
    ],
    "wof:name":"Gosh Nagar",
    "wof:placetype":"locality",
    "wof:population":4105
},
  "geometry": {"coordinates":[85.736923,25.313982],"type":"Point"}
}