{
  "type": "Feature",
  "properties": {
    "gn:admin1_code":"35",
    "gn:admin2_code":"423.0",
    "gn:asciiname":"Bilupura",
    "gn:country_code":"IN",
    "gn:dem":446,
    "gn:feature_class":"P",
    "gn:feature_code":"PPL",
    "gn:name":"Bilupura",
    "gn:population":0,
    "gn:timezone":"Asia/Kolkata",
    "iso:country":"IN",
    "ks:ks_name":"Bilupura",
    "ks:ks_type":"VILLAGE",
    "name:eng_x_preferred":[
        "Bilupura"
    ],
    "wof:name":"Bilupura",
    "wof:placetype":"locality"
},
  "geometry": {"coordinates":[77.57113200000001,25.546789],"type":"Point"}
}