{
  "type": "Feature",
  "properties": {
    "gn:admin1_code":"19.0",
    "gn:admin2_code":"563.0",
    "gn:asciiname":"Duggimane",
    "gn:country_code":"IN",
    "gn:dem":536,
    "gn:feature_class":"P",
    "gn:feature_code":"PPL",
    "gn:name":"Duggimane",
    "gn:population":0,
    "gn:timezone":"Asia/Kolkata",
    "iso:country":"IN",
    "ks:ks_name":"Nuggimane",
    "ks:ks_pop":60,
    "ks:ks_type":"HABITATION",
    "name:eng_x_preferred":[
        "Nuggimane"
    ],
    "name:eng_x_variant":[
        "Duggimane"
    ],
    "wof:name":"Nuggimane",
    "wof:placetype":"locality",
    "wof:population":60
},
  "geometry": {"coordinates":[74.715935,14.659889],"type":"Point"}
}