{
  "type": "Feature",
  "properties": {
    "iso:country":"IN",
    "ks:ks_name":"Dandekarpada",
    "ks:ks_pop":215,
    "ks:ks_type":"HABITATION",
    "name:eng_x_preferred":[
        "Dandekarpada"
    ],
    "wof:name":"Dandekarpada",
    "wof:placetype":"locality",
    "wof:population":215
},
  "geometry": {"coordinates":[72.85103100000001,19.932478],"type":"Point"}
}