{
  "type": "Feature",
  "properties": {
    "iso:country":"IN",
    "ks:ks_name":"Devkheda",
    "ks:ks_pop":709,
    "ks:ks_type":"VILLAGE",
    "name:eng_x_preferred":[
        "Devkheda"
    ],
    "wof:name":"Devkheda",
    "wof:placetype":"locality",
    "wof:population":709
},
  "geometry": {"coordinates":[76.186246,19.152865],"type":"Point"}
}