{
  "type": "Feature",
  "properties": {
    "iso:country":"IN",
    "ks:ks_name":"Karichuan",
    "ks:ks_pop":330,
    "ks:ks_type":"VILLAGE",
    "name:eng_x_preferred":[
        "Karichuan"
    ],
    "wof:name":"Karichuan",
    "wof:placetype":"locality",
    "wof:population":330
},
  "geometry": {"coordinates":[84.84718599999999,22.90741],"type":"Point"}
}