{
  "type": "Feature",
  "properties": {
    "gn:admin1_code":"11.0",
    "gn:admin2_code":"033",
    "gn:asciiname":"Chounri",
    "gn:country_code":"IN",
    "gn:dem":1321,
    "gn:feature_class":"P",
    "gn:feature_code":"PPL",
    "gn:name":"Cho\u016bnri",
    "gn:population":0,
    "gn:timezone":"Asia/Kolkata",
    "iso:country":"IN",
    "wof:name":"Chounri",
    "wof:placetype":"locality"
},
  "geometry": {"coordinates":[77.05639000000002,31.14333],"type":"Point"}
}