{
  "type": "Feature",
  "properties": {
    "gn:admin1_code":"36.0",
    "gn:admin2_code":"163.0",
    "gn:asciiname":"Jugrajpur Sheoli",
    "gn:country_code":"IN",
    "gn:dem":137,
    "gn:feature_class":"P",
    "gn:feature_code":"PPL",
    "gn:name":"Jugr\u0101jpur Sheoli",
    "gn:population":0,
    "gn:timezone":"Asia/Kolkata",
    "iso:country":"IN",
    "wof:name":"Jugrajpur Sheoli",
    "wof:placetype":"locality"
},
  "geometry": {"coordinates":[79.98035,26.54978],"type":"Point"}
}