{
  "type": "Feature",
  "properties": {
    "iso:country":"IN",
    "ks:ks_name":"Thatanagar",
    "ks:ks_pop":893,
    "ks:ks_type":"VILLAGE",
    "name:eng_x_preferred":[
        "Thatanagar"
    ],
    "wof:name":"Thatanagar",
    "wof:placetype":"locality",
    "wof:population":893
},
  "geometry": {"coordinates":[72.63833099999999,27.019044],"type":"Point"}
}