{
  "type": "Feature",
  "properties": {
    "iso:country":"IN",
    "ks:ks_alt_nam":"Bh\u0101l\u016bkona",
    "ks:ks_name":"Bhalukona",
    "ks:ks_pop":55,
    "ks:ks_type":"VILLAGE",
    "name:eng_x_preferred":[
        "Bhalukona"
    ],
    "name:eng_x_variant":[
        "Bh\u0101l\u016bkona"
    ],
    "wof:name":"Bhalukona",
    "wof:placetype":"locality",
    "wof:population":55
},
  "geometry": {"coordinates":[81.967265,21.493404],"type":"Point"}
}