{
  "type": "Feature",
  "properties": {
    "gn:admin1_code":"19.0",
    "gn:admin2_code":"563.0",
    "gn:asciiname":"Gudeangdi",
    "gn:country_code":"IN",
    "gn:dem":18,
    "gn:feature_class":"P",
    "gn:feature_code":"PPL",
    "gn:name":"Gudeangdi",
    "gn:population":0,
    "gn:timezone":"Asia/Kolkata",
    "iso:country":"IN",
    "ks:ks_name":"Gudeangadi",
    "ks:ks_pop":1741,
    "ks:ks_type":"VILLAGE",
    "name:eng_x_preferred":[
        "Gudeangadi"
    ],
    "name:eng_x_variant":[
        "Gudeangdi"
    ],
    "wof:name":"Gudeangadi",
    "wof:placetype":"locality",
    "wof:population":1741
},
  "geometry": {"coordinates":[74.376507,14.471133],"type":"Point"}
}