{
  "type": "Feature",
  "properties": {
    "iso:country":"IN",
    "ks:ks_name":"Gachhua",
    "ks:ks_pop":99,
    "ks:ks_type":"VILLAGE",
    "name:eng_x_preferred":[
        "Gachhua"
    ],
    "wof:name":"Gachhua",
    "wof:placetype":"locality",
    "wof:population":99
},
  "geometry": {"coordinates":[87.562687,22.980764],"type":"Point"}
}