{
  "type": "Feature",
  "properties": {
    "gn:country":"IN",
    "gn:fcode":"PPL",
    "gn:pop":23654,
    "iso:country":"IN",
    "name:ast_x_preferred":[
        "Penugonda"
    ],
    "name:bul_x_preferred":[
        "\u041f\u0435\u043d\u0443\u0433\u043e\u043d\u0434\u0430"
    ],
    "name:ceb_x_preferred":[
        "Penugonda"
    ],
    "name:eng_x_preferred":[
        "Penugonda"
    ],
    "name:nld_x_preferred":[
        "Penugonda"
    ],
    "name:swe_x_preferred":[
        "Penugonda"
    ],
    "name:tam_x_preferred":[
        "\u0baa\u0bc6\u0ba9\u0bc1\u0b95\u0bca\u0ba3\u0bcd\u0b9f\u0bbe"
    ],
    "name:tel_x_preferred":[
        "\u0c2a\u0c46\u0c28\u0c41\u0c17\u0c4a\u0c02\u0c21"
    ],
    "name:urd_x_preferred":[
        "\u067e\u06cc\u0646\u0648\u06af\u0648\u0646\u0688\u0627"
    ],
    "qs:name":"Penugonda",
    "qs:name_adm0":"India",
    "qs:name_adm1":"Andhra Pradesh",
    "qs:photos_9k":1,
    "qs:photos_9r":1,
    "qs:photos_all":2,
    "qs:photos_sr":0,
    "qs:placetype":"Town",
    "qs:pop_sr":"7",
    "wd:wordcount":88,
    "wof:name":"Penugonda",
    "wof:placetype":"locality",
    "wof:population":23654
},
  "geometry": {"coordinates":[81.74550000000001,16.65363],"type":"Point"}
}