{
  "type": "Feature",
  "properties": {
    "gn:admin1_code":"36.0",
    "gn:admin2_code":"152.0",
    "gn:asciiname":"Kunian Taluka Sarjupur",
    "gn:country_code":"IN",
    "gn:dem":162,
    "gn:feature_class":"P",
    "gn:feature_code":"PPL",
    "gn:name":"Kuni\u0101n Taluka Sarj\u016bpur",
    "gn:population":0,
    "gn:timezone":"Asia/Kolkata",
    "iso:country":"IN",
    "wof:name":"Kunian Taluka Sarjupur",
    "wof:placetype":"neighbourhood"
},
  "geometry": {"coordinates":[79.58162,28.05316],"type":"Point"}
}