{
  "type": "Feature",
  "properties": {
    "iso:country":"IN",
    "ks:ks_name":"Bhosalewasti",
    "ks:ks_pop":280,
    "ks:ks_type":"HABITATION",
    "name:eng_x_preferred":[
        "Bhosalewasti"
    ],
    "wof:name":"Bhosalewasti",
    "wof:placetype":"locality",
    "wof:population":280
},
  "geometry": {"coordinates":[74.96299999999999,18.105],"type":"Point"}
}