{
  "type": "Feature",
  "properties": {
    "iso:country":"IN",
    "ks:ks_alt_nam":"hosadoddi",
    "ks:ks_name":"Hosadoddi",
    "ks:ks_pop":60,
    "ks:ks_type":"HABITATION",
    "name:eng_x_preferred":[
        "Hosadoddi"
    ],
    "wof:name":"Hosadoddi",
    "wof:placetype":"locality",
    "wof:population":60
},
  "geometry": {"coordinates":[77.60456499999999,12.538714],"type":"Point"}
}