{
  "type": "Feature",
  "properties": {
    "gn:admin1_code":"35.0",
    "gn:admin2_code":"424.0",
    "gn:asciiname":"Nanni Tehri Ugad",
    "gn:country_code":"IN",
    "gn:dem":346,
    "gn:feature_class":"P",
    "gn:feature_code":"PPL",
    "gn:name":"Nanni Tehri Ugad",
    "gn:population":0,
    "gn:timezone":"Asia/Kolkata",
    "iso:country":"IN",
    "wof:name":"Nanni Tehri Ugad",
    "wof:placetype":"locality"
},
  "geometry": {"coordinates":[79.05054,24.68212],"type":"Point"}
}