{
  "type": "Feature",
  "properties": {
    "iso:country":"IN",
    "ks:ks_name":"Allitira Family",
    "ks:ks_pop":21,
    "ks:ks_type":"HABITATION",
    "name:eng_x_preferred":[
        "Allitira Family"
    ],
    "wof:name":"Allitira Family",
    "wof:placetype":"locality",
    "wof:population":21
},
  "geometry": {"coordinates":[76.00194399999999,11.963056],"type":"Point"}
}