{
  "type": "Feature",
  "properties": {
    "iso:country":"IN",
    "ks:ks_name":"Garai",
    "ks:ks_pop":81,
    "ks:ks_type":"VILLAGE",
    "name:eng_x_preferred":[
        "Garai"
    ],
    "wof:name":"Garai",
    "wof:placetype":"locality",
    "wof:population":81
},
  "geometry": {"coordinates":[86.161879,24.597742],"type":"Point"}
}