{
  "type": "Feature",
  "properties": {
    "iso:country":"IN",
    "ks:ks_alt_nam":"N\u0101bh\u0101pur",
    "ks:ks_name":"Nabhapur",
    "ks:ks_pop":0,
    "ks:ks_type":"VILLAGE",
    "name:eng_x_preferred":[
        "Nabhapur"
    ],
    "name:eng_x_variant":[
        "N\u0101bh\u0101pur"
    ],
    "wof:name":"Nabhapur",
    "wof:placetype":"locality",
    "wof:population":0
},
  "geometry": {"coordinates":[82.417731,25.26925],"type":"Point"}
}