{
  "type": "Feature",
  "properties": {
    "iso:country":"IN",
    "ks:ks_alt_nam":"Chekkidikkadu kizhakku",
    "ks:ks_name":"Chekkidikkadu Kizhakku",
    "ks:ks_pop":534,
    "ks:ks_type":"HABITATION",
    "name:eng_x_preferred":[
        "Chekkidikkadu Kizhakku"
    ],
    "wof:name":"Chekkidikkadu Kizhakku",
    "wof:placetype":"locality",
    "wof:population":534
},
  "geometry": {"coordinates":[76.450253,9.355167],"type":"Point"}
}