{
  "type": "Feature",
  "properties": {
    "gn:admin1_code":"12",
    "gn:admin2_code":"14.0",
    "gn:asciiname":"Hoksar Baihk",
    "gn:country_code":"IN",
    "gn:dem":3368,
    "gn:feature_class":"P",
    "gn:feature_code":"PPL",
    "gn:name":"H\u014dksar Baihk",
    "gn:population":0,
    "gn:timezone":"Asia/Kolkata",
    "iso:country":"IN",
    "wof:name":"Hoksar Baihk",
    "wof:placetype":"locality"
},
  "geometry": {"coordinates":[75.30915999999998,34.20377],"type":"Point"}
}