{
  "type": "Feature",
  "properties": {
    "gn:admin1_code":"09",
    "gn:admin2_code":"490.0",
    "gn:asciiname":"Vesma",
    "gn:country_code":"IN",
    "gn:dem":22,
    "gn:feature_class":"P",
    "gn:feature_code":"PPL",
    "gn:name":"Vesma",
    "gn:population":0,
    "gn:timezone":"Asia/Kolkata",
    "iso:country":"IN",
    "wof:name":"Vesma",
    "wof:placetype":"locality"
},
  "geometry": {"coordinates":[72.97514,21.03101],"type":"Point"}
}