{
  "type": "Feature",
  "properties": {
    "gn:admin1_code":"16.0",
    "gn:admin2_code":"516.0",
    "gn:asciiname":"Khadak Jamb",
    "gn:country_code":"IN",
    "gn:dem":661,
    "gn:feature_class":"P",
    "gn:feature_code":"PPL",
    "gn:name":"Khadak J\u0101mb",
    "gn:population":0,
    "gn:timezone":"Asia/Kolkata",
    "iso:country":"IN",
    "wof:name":"Khadak Jamb",
    "wof:placetype":"locality"
},
  "geometry": {"coordinates":[74.07746,20.24854],"type":"Point"}
}