{
  "type": "Feature",
  "properties": {
    "iso:country":"IN",
    "ks:ks_name":"Ramsajivan Ka Purwa",
    "ks:ks_pop":140,
    "ks:ks_type":"HABITATION",
    "name:eng_x_preferred":[
        "Ramsajivan Ka Purwa"
    ],
    "wof:name":"Ramsajivan Ka Purwa",
    "wof:placetype":"locality",
    "wof:population":140
},
  "geometry": {"coordinates":[80.78151800000001,25.670359],"type":"Point"}
}