{
  "type": "Feature",
  "properties": {
    "iso:country":"IN",
    "ks:ks_name":"Jagirnatrampalli Colony",
    "ks:ks_pop":263,
    "ks:ks_type":"HABITATION",
    "name:eng_x_preferred":[
        "Jagirnatrampalli Colony"
    ],
    "wof:name":"Jagirnatrampalli Colony",
    "wof:placetype":"locality",
    "wof:population":263
},
  "geometry": {"coordinates":[78.17219299999999,12.519114],"type":"Point"}
}