{
  "type": "Feature",
  "properties": {
    "iso:country":"IN",
    "ks:ks_alt_nam":"AKAUNA",
    "ks:ks_name":"Akauna",
    "ks:ks_pop":368,
    "ks:ks_type":"HABITATION",
    "ks:ks_uagg_main":0,
    "name:eng_x_preferred":[
        "Akauna"
    ],
    "wof:name":"Akauna",
    "wof:placetype":"neighbourhood",
    "wof:population":368
},
  "geometry": {"coordinates":[85.021432,26.681669],"type":"Point"}
}