{
  "type": "Feature",
  "properties": {
    "iso:country":"IN",
    "ks:ks_name":"Jardulpara",
    "ks:ks_pop":418,
    "ks:ks_type":"VILLAGE",
    "ks:ks_uagg_main":0,
    "name:eng_x_preferred":[
        "Jardulpara"
    ],
    "wof:name":"Jardulpara",
    "wof:placetype":"neighbourhood",
    "wof:population":418
},
  "geometry": {"coordinates":[90.170469,26.241316],"type":"Point"}
}