{
  "type": "Feature",
  "properties": {
    "iso:country":"IN",
    "ks:ks_name":"Mattavanicheruvu",
    "ks:ks_pop":545,
    "ks:ks_type":"HABITATION",
    "name:eng_x_preferred":[
        "Mattavanicheruvu"
    ],
    "wof:name":"Mattavanicheruvu",
    "wof:placetype":"locality",
    "wof:population":545
},
  "geometry": {"coordinates":[81.836828,16.547256],"type":"Point"}
}