{
  "type": "Feature",
  "properties": {
    "iso:country":"IN",
    "ks:ks_name":"Anuguba",
    "ks:ks_pop":210,
    "ks:ks_type":"VILLAGE",
    "name:eng_x_preferred":[
        "Anuguba"
    ],
    "wof:name":"Anuguba",
    "wof:placetype":"locality",
    "wof:population":210
},
  "geometry": {"coordinates":[83.782732,20.491349],"type":"Point"}
}