{
  "type": "Feature",
  "properties": {
    "gn:admin1_code":"10",
    "gn:admin2_code":"75.0",
    "gn:asciiname":"Kutani",
    "gn:country_code":"IN",
    "gn:dem":239,
    "gn:feature_class":"P",
    "gn:feature_code":"PPL",
    "gn:name":"Kut\u0101ni",
    "gn:population":0,
    "gn:timezone":"Asia/Kolkata",
    "iso:country":"IN",
    "wof:name":"Kutani",
    "wof:placetype":"locality"
},
  "geometry": {"coordinates":[77.01109,29.41895],"type":"Point"}
}