{
  "type": "Feature",
  "properties": {
    "iso:country":"IN",
    "ks:ks_name":"Trasamatha",
    "ks:ks_pop":78,
    "ks:ks_type":"HABITATION",
    "name:eng_x_preferred":[
        "Trasamatha"
    ],
    "wof:name":"Trasamatha",
    "wof:placetype":"locality",
    "wof:population":78
},
  "geometry": {"coordinates":[75.512455,13.432747],"type":"Point"}
}