{
  "type": "Feature",
  "properties": {
    "iso:country":"IN",
    "ks:ks_name":"Kucha Mari",
    "ks:ks_pop":140,
    "ks:ks_type":"VILLAGE",
    "name:eng_x_preferred":[
        "Kucha Mari"
    ],
    "wof:name":"Kucha Mari",
    "wof:placetype":"locality",
    "wof:population":140
},
  "geometry": {"coordinates":[87.775732,22.49324],"type":"Point"}
}