{
  "type": "Feature",
  "properties": {
    "iso:country":"IN",
    "ks:ks_name":"Amatpani",
    "ks:ks_pop":135,
    "ks:ks_type":"VILLAGE",
    "name:eng_x_preferred":[
        "Amatpani"
    ],
    "wof:name":"Amatpani",
    "wof:placetype":"locality",
    "wof:population":135
},
  "geometry": {"coordinates":[84.093999,22.449153],"type":"Point"}
}