{
  "type": "Feature",
  "properties": {
    "gn:admin1_code":"11",
    "gn:admin2_code":"25.0",
    "gn:asciiname":"Kutha",
    "gn:country_code":"IN",
    "gn:dem":2470,
    "gn:feature_class":"P",
    "gn:feature_code":"PPL",
    "gn:name":"Kutha",
    "gn:population":0,
    "gn:timezone":"Asia/Kolkata",
    "iso:country":"IN",
    "name:ara_x_preferred":[
        "\u0643\u0648\u062b\u0627"
    ],
    "name:bak_x_preferred":[
        "\u041a\u0443\u0442\u0430"
    ],
    "name:cat_x_preferred":[
        "Kutha"
    ],
    "name:fas_x_preferred":[
        "\u06a9\u0648\u062b\u0627"
    ],
    "name:fin_x_preferred":[
        "Cuthah"
    ],
    "name:fra_x_preferred":[
        "Kutha"
    ],
    "name:heb_x_preferred":[
        "\u05db\u05d5\u05ea\u05d4"
    ],
    "name:hun_x_preferred":[
        "K\u00fata"
    ],
    "name:ita_x_preferred":[
        "Kutha"
    ],
    "name:kor_x_preferred":[
        "\ucfe0\ud0c0"
    ],
    "name:kur_x_preferred":[
        "Kutha"
    ],
    "name:pol_x_preferred":[
        "Kuta"
    ],
    "name:rus_x_preferred":[
        "\u041a\u0443\u0442\u0430"
    ],
    "name:slv_x_preferred":[
        "Kuta"
    ],
    "name:spa_x_preferred":[
        "Cutah"
    ],
    "name:ukr_x_preferred":[
        "\u041a\u0443\u0442\u0430"
    ],
    "wof:name":"Kutha",
    "wof:placetype":"locality"
},
  "geometry": {"coordinates":[76.45169,32.75881],"type":"Point"}
}