{
  "type": "Feature",
  "properties": {
    "gn:country":"IN",
    "gn:fcode":"PPL",
    "gn:pop":26114,
    "iso:country":"IN",
    "name:ben_x_preferred":[
        "\u09b0\u09be\u09af\u09bc\u0995\u09cb\u099f"
    ],
    "name:bpy_x_preferred":[
        "\u09b0\u09be\u09af\u09bc\u0995\u09cb\u099f"
    ],
    "name:cat_x_preferred":[
        "Raikot"
    ],
    "name:eng_x_preferred":[
        "Raikot"
    ],
    "name:fra_x_preferred":[
        "Raikot"
    ],
    "name:ita_x_preferred":[
        "Raikot"
    ],
    "name:jpn_x_preferred":[
        "\u30e9\u30fc\u30a4\u30b3\u30fc\u30c8"
    ],
    "name:mlg_x_preferred":[
        "Raikot"
    ],
    "name:msa_x_preferred":[
        "Raikot"
    ],
    "name:nan_x_preferred":[
        "Raikot"
    ],
    "name:nld_x_preferred":[
        "Raikot"
    ],
    "name:ori_x_preferred":[
        "\u0b30\u0b3e\u0b07\u0b15\u0b4b\u0b1f"
    ],
    "name:pan_x_preferred":[
        "\u0a30\u0a3e\u0a0f\u0a15\u0a4b\u0a1f"
    ],
    "name:por_x_preferred":[
        "Raikot"
    ],
    "name:spa_x_preferred":[
        "Raikot"
    ],
    "name:swe_x_preferred":[
        "R\u0101ikot"
    ],
    "name:unk_x_variant":[
        "R\u0101ikot"
    ],
    "name:vie_x_preferred":[
        "Raikot"
    ],
    "name:zho_x_preferred":[
        "\u8d56\u79d1\u7279"
    ],
    "qs:name":"Raikot",
    "qs:name_adm0":"India",
    "qs:name_adm1":"Punjab",
    "qs:photos_9k":1,
    "qs:photos_9r":1,
    "qs:photos_all":1,
    "qs:photos_sr":0,
    "qs:placetype":"Town",
    "qs:pop_sr":"7",
    "wd:wordcount":430,
    "wof:name":"Raikot",
    "wof:placetype":"locality",
    "wof:population":26114
},
  "geometry": {"coordinates":[75.59999999999999,30.65],"type":"Point"}
}