{
  "type": "Feature",
  "properties": {
    "iso:country":"IN",
    "ks:ks_alt_nam":"Gabar pada",
    "ks:ks_name":"Gabar Pada",
    "ks:ks_pop":652,
    "ks:ks_type":"HABITATION",
    "name:eng_x_preferred":[
        "Gabar Pada"
    ],
    "wof:name":"Gabar Pada",
    "wof:placetype":"locality",
    "wof:population":652
},
  "geometry": {"coordinates":[73.38485799999999,20.613102],"type":"Point"}
}