{
  "type": "Feature",
  "properties": {
    "iso:country":"IN",
    "ks:ks_name":"Buraburir Tat",
    "ks:ks_pop":2917,
    "ks:ks_type":"VILLAGE",
    "name:eng_x_preferred":[
        "Buraburir Tat"
    ],
    "wof:name":"Buraburir Tat",
    "wof:placetype":"locality",
    "wof:population":2917
},
  "geometry": {"coordinates":[88.40021400000001,21.629449],"type":"Point"}
}