{
  "type": "Feature",
  "properties": {
    "iso:country":"IN",
    "ks:ks_name":"Konwari Pathar Block",
    "ks:ks_pop":267,
    "ks:ks_type":"HABITATION",
    "name:eng_x_preferred":[
        "Konwari Pathar Block"
    ],
    "wof:name":"Konwari Pathar Block",
    "wof:placetype":"locality",
    "wof:population":267
},
  "geometry": {"coordinates":[95.34263,27.398764],"type":"Point"}
}