{
  "type": "Feature",
  "properties": {
    "gn:admin1_code":"16.0",
    "gn:admin2_code":"526",
    "gn:asciiname":"Ashti",
    "gn:country_code":"IN",
    "gn:dem":483,
    "gn:feature_class":"P",
    "gn:feature_code":"PPL",
    "gn:name":"Ashti",
    "gn:population":0,
    "gn:timezone":"Asia/Kolkata",
    "iso:country":"IN",
    "name:und_x_variant":[
        "Ashta",
        "Ashti"
    ],
    "wof:name":"Ashti",
    "wof:placetype":"locality"
},
  "geometry": {"coordinates":[75.41033,17.84391],"type":"Point"}
}