{
  "type": "Feature",
  "properties": {
    "gn:admin1_code":"2.0",
    "gn:admin2_code":"548.0",
    "gn:asciiname":"Gollapalem",
    "gn:country_code":"IN",
    "gn:dem":5,
    "gn:feature_class":"P",
    "gn:feature_code":"PPL",
    "gn:name":"Gollap\u0101lem",
    "gn:population":0,
    "gn:timezone":"Asia/Kolkata",
    "iso:country":"IN",
    "name:tat_x_preferred":[
        "\u0413\u043e\u043b\u043b\u0430\u043f\u0430\u043b\u0435\u043c"
    ],
    "name:tel_x_preferred":[
        "\u0c17\u0c4a\u0c32\u0c4d\u0c32\u0c2a\u0c3e\u0c32\u0c46\u0c02(\u0c15\u0c43\u0c24\u0c4d\u0c24\u0c3f\u0c35\u0c46\u0c28\u0c4d\u0c28\u0c41)"
    ],
    "wof:name":"Gollapalem",
    "wof:placetype":"locality"
},
  "geometry": {"coordinates":[80.69866999999998,15.98207],"type":"Point"}
}