{
  "type": "Feature",
  "properties": {
    "iso:country":"IN",
    "ks:ks_alt_nam":"Barw\u0101dih",
    "ks:ks_name":"Barwadih",
    "ks:ks_pop":299,
    "ks:ks_type":"VILLAGE",
    "name:eng_x_preferred":[
        "Barwadih"
    ],
    "name:eng_x_variant":[
        "Barw\u0101dih"
    ],
    "wof:name":"Barwadih",
    "wof:placetype":"locality",
    "wof:population":299
},
  "geometry": {"coordinates":[84.88993499999999,23.884636],"type":"Point"}
}