{
  "type": "Feature",
  "properties": {
    "iso:country":"IN",
    "ks:ks_name":"Makundpur",
    "ks:ks_pop":342,
    "ks:ks_type":"VILLAGE",
    "name:eng_x_preferred":[
        "Makundpur"
    ],
    "wof:name":"Makundpur",
    "wof:placetype":"locality",
    "wof:population":342
},
  "geometry": {"coordinates":[84.336432,23.676478],"type":"Point"}
}