{
  "type": "Feature",
  "properties": {
    "gn:admin1_code":"10.0",
    "gn:admin2_code":"75.0",
    "gn:asciiname":"Asan Khurd",
    "gn:country_code":"IN",
    "gn:dem":237,
    "gn:feature_class":"P",
    "gn:feature_code":"PPL",
    "gn:name":"\u0100san Khurd",
    "gn:population":0,
    "gn:timezone":"Asia/Kolkata",
    "iso:country":"IN",
    "name:ben_x_preferred":[
        "\u0986\u09b8\u09be\u09a8 \u0996\u09c1\u09b0\u09cd\u09a6"
    ],
    "name:bpy_x_preferred":[
        "\u0986\u09b8\u09be\u09a8 \u0996\u09c1\u09b0\u09cd\u09a6"
    ],
    "name:hin_x_preferred":[
        "\u0906\u0938\u0928 \u0916\u0941\u0930\u094d\u0926"
    ],
    "name:ita_x_preferred":[
        "Asankhurd"
    ],
    "name:msa_x_preferred":[
        "Asan Khurd"
    ],
    "name:new_x_preferred":[
        "\u0905\u0938\u0928 \u0916\u0941\u0930\u094d\u0926"
    ],
    "name:nld_x_preferred":[
        "Asan Khurd"
    ],
    "name:por_x_preferred":[
        "Asan Khurd"
    ],
    "name:tam_x_preferred":[
        "\u0b85\u0b9a\u0bbe\u0ba9\u0bcd \u0b95\u0bc1\u0bb0\u0bcd\u0ba4\u0bc1"
    ],
    "name:vie_x_preferred":[
        "Asan Khurd"
    ],
    "name:zho_x_preferred":[
        "\u963f\u8428\u6069\u5e93\u5c14\u5fb7"
    ],
    "wof:name":"Asan Khurd",
    "wof:placetype":"locality"
},
  "geometry": {"coordinates":[76.87323000000001,29.40445],"type":"Point"}
}