{
  "type": "Feature",
  "properties": {
    "gn:admin1_code":"36.0",
    "gn:admin2_code":"162.0",
    "gn:asciiname":"Purwa Hiraman",
    "gn:country_code":"IN",
    "gn:dem":143,
    "gn:feature_class":"P",
    "gn:feature_code":"PPL",
    "gn:name":"Purwa H\u012br\u0101man",
    "gn:population":0,
    "gn:timezone":"Asia/Kolkata",
    "iso:country":"IN",
    "ks:ks_name":"Purwa Hiraman",
    "ks:ks_pop":237,
    "ks:ks_type":"HABITATION",
    "name:eng_x_preferred":[
        "Purwa Hiraman"
    ],
    "wof:name":"Purwa Hiraman",
    "wof:placetype":"locality",
    "wof:population":237
},
  "geometry": {"coordinates":[79.604721,26.772359],"type":"Point"}
}