{
  "type": "Feature",
  "properties": {
    "iso:country":"IN",
    "ks:ks_name":"Kevala",
    "ks:ks_pop":227,
    "ks:ks_type":"HABITATION",
    "name:eng_x_preferred":[
        "Kevala"
    ],
    "wof:name":"Kevala",
    "wof:placetype":"locality",
    "wof:population":227
},
  "geometry": {"coordinates":[75.391565,12.787333],"type":"Point"}
}