{
  "type": "Feature",
  "properties": {
    "iso:country":"IN",
    "ks:ks_name":"Azadnagar Bazar",
    "ks:ks_pop":220,
    "ks:ks_type":"HABITATION",
    "ks:ks_uagg_main":0,
    "name:eng_x_preferred":[
        "Azadnagar Bazar"
    ],
    "wof:name":"Azadnagar Bazar",
    "wof:placetype":"neighbourhood",
    "wof:population":220
},
  "geometry": {"coordinates":[82.860664,25.705163],"type":"Point"}
}