{
  "type": "Feature",
  "properties": {
    "iso:country":"IN",
    "ks:ks_name":"Pathradiya",
    "ks:ks_pop":863,
    "ks:ks_type":"VILLAGE",
    "name:eng_x_preferred":[
        "Pathradiya"
    ],
    "wof:name":"Pathradiya",
    "wof:placetype":"locality",
    "wof:population":863
},
  "geometry": {"coordinates":[73.10878200000001,21.060766],"type":"Point"}
}