{
  "type": "Feature",
  "properties": {
    "iso:country":"IN",
    "ks:ks_name":"Gorai",
    "ks:ks_type":"VILLAGE",
    "name:eng_x_preferred":[
        "Gorai"
    ],
    "wof:name":"Gorai",
    "wof:placetype":"neighbourhood"
},
  "geometry": {"coordinates":[72.78322900000001,19.249036],"type":"Point"}
}