{
  "type": "Feature",
  "properties": {
    "gn:admin1_code":"35.0",
    "gn:admin2_code":"464.0",
    "gn:asciiname":"Titaria",
    "gn:country_code":"IN",
    "gn:dem":296,
    "gn:feature_class":"P",
    "gn:feature_code":"PPL",
    "gn:name":"Titaria",
    "gn:population":0,
    "gn:timezone":"Asia/Kolkata",
    "iso:country":"IN",
    "ks:ks_name":"Titariya",
    "ks:ks_pop":572,
    "ks:ks_type":"VILLAGE",
    "name:eng_x_preferred":[
        "Titariya"
    ],
    "name:eng_x_variant":[
        "Titaria"
    ],
    "wof:name":"Titariya",
    "wof:placetype":"locality",
    "wof:population":572
},
  "geometry": {"coordinates":[74.447475,22.974189],"type":"Point"}
}