{
  "type": "Feature",
  "properties": {
    "iso:country":"IN",
    "ks:ks_name":"Oddipalle",
    "ks:ks_pop":56,
    "ks:ks_type":"HABITATION",
    "name:eng_x_preferred":[
        "Oddipalle"
    ],
    "wof:name":"Oddipalle",
    "wof:placetype":"locality",
    "wof:population":56
},
  "geometry": {"coordinates":[78.70119,13.599067],"type":"Point"}
}