{
  "type": "Feature",
  "properties": {
    "iso:country":"IN",
    "ks:ks_name":"Huntthnike",
    "ks:ks_pop":360,
    "ks:ks_type":"HABITATION",
    "name:eng_x_preferred":[
        "Huntthnike"
    ],
    "wof:name":"Huntthnike",
    "wof:placetype":"locality",
    "wof:population":360
},
  "geometry": {"coordinates":[74.886472,13.597397],"type":"Point"}
}