{
  "type": "Feature",
  "properties": {
    "iso:country":"IN",
    "ks:ks_name":"Tondavali",
    "ks:ks_pop":951,
    "ks:ks_type":"VILLAGE",
    "name:eng_x_preferred":[
        "Tondavali"
    ],
    "wof:name":"Tondavali",
    "wof:placetype":"locality",
    "wof:population":951
},
  "geometry": {"coordinates":[73.70384300000001,16.382408],"type":"Point"}
}