{
  "type": "Feature",
  "properties": {
    "gn:admin1_code":"24.0",
    "gn:admin2_code":"122.0",
    "gn:asciiname":"Bharalia",
    "gn:country_code":"IN",
    "gn:dem":461,
    "gn:feature_class":"P",
    "gn:feature_code":"PPL",
    "gn:name":"Bhar\u0101lia",
    "gn:population":0,
    "gn:timezone":"Asia/Kolkata",
    "iso:country":"IN",
    "wof:name":"Bharalia",
    "wof:placetype":"neighbourhood"
},
  "geometry": {"coordinates":[74.35818999999999,25.80193],"type":"Point"}
}