{
  "type": "Feature",
  "properties": {
    "iso:country":"IN",
    "ks:ks_name":"Pancham Singh Nivada",
    "ks:ks_pop":1089,
    "ks:ks_type":"HABITATION",
    "name:eng_x_preferred":[
        "Pancham Singh Nivada"
    ],
    "wof:name":"Pancham Singh Nivada",
    "wof:placetype":"locality",
    "wof:population":1089
},
  "geometry": {"coordinates":[79.776298,26.641471],"type":"Point"}
}