{
  "type": "Feature",
  "properties": {
    "gn:admin1_code":"2",
    "gn:admin2_code":"544.0",
    "gn:asciiname":"Silamgondi",
    "gn:country_code":"IN",
    "gn:dem":1013,
    "gn:feature_class":"P",
    "gn:feature_code":"PPL",
    "gn:name":"Silamgondi",
    "gn:population":0,
    "gn:timezone":"Asia/Kolkata",
    "iso:country":"IN",
    "wof:name":"Silamgondi",
    "wof:placetype":"locality"
},
  "geometry": {"coordinates":[82.81744,18.26849],"type":"Point"}
}