{
  "type": "Feature",
  "properties": {
    "gn:admin1_code":"2",
    "gn:admin2_code":"544.0",
    "gn:asciiname":"Silamgondi",
    "gn:country_code":"IN",
    "gn:dem":1013,
    "gn:feature_class":"P",
    "gn:feature_code":"PPL",
    "gn:name":"Silamgondi",
    "gn:population":0,
    "gn:timezone":"Asia/Kolkata",
    "iso:country":"IN",
    "ks:ks_name":"Seelamgondi",
    "ks:ks_pop":198,
    "ks:ks_type":"HABITATION",
    "name:eng_x_preferred":[
        "Seelamgondi"
    ],
    "name:eng_x_variant":[
        "Silamgondi"
    ],
    "wof:name":"Seelamgondi",
    "wof:placetype":"locality",
    "wof:population":198
},
  "geometry": {"coordinates":[82.816925,18.268609],"type":"Point"}
}