{
  "type": "Feature",
  "properties": {
    "gn:admin1_code":"35.0",
    "gn:admin2_code":"454.0",
    "gn:asciiname":"Dadar Tola",
    "gn:country_code":"IN",
    "gn:dem":473,
    "gn:feature_class":"P",
    "gn:feature_code":"PPL",
    "gn:name":"D\u0101dar Tol\u0101",
    "gn:population":0,
    "gn:timezone":"Asia/Kolkata",
    "iso:country":"IN",
    "name:und_x_variant":[
        "D\u0101dar Tol\u0101",
        "Dongaria"
    ],
    "wof:name":"Dadar Tola",
    "wof:placetype":"locality"
},
  "geometry": {"coordinates":[80.06269,22.85916],"type":"Point"}
}