{
  "type": "Feature",
  "properties": {
    "gn:admin1_code":"11.0",
    "gn:admin2_code":"33.0",
    "gn:asciiname":"Katar Grasu Chak",
    "gn:country_code":"IN",
    "gn:dem":1757,
    "gn:feature_class":"P",
    "gn:feature_code":"PPL",
    "gn:name":"Kat\u0101r Gr\u0101su Chak",
    "gn:population":0,
    "gn:timezone":"Asia/Kolkata",
    "iso:country":"IN",
    "wof:name":"Katar Grasu Chak",
    "wof:placetype":"locality"
},
  "geometry": {"coordinates":[77.60763,31.29866],"type":"Point"}
}