{
  "type": "Feature",
  "properties": {
    "iso:country":"IN",
    "ks:ks_name":"13 ZWM",
    "ks:ks_pop":277,
    "ks:ks_type":"VILLAGE",
    "name:eng_x_preferred":[
        "13 ZWM"
    ],
    "wof:name":"13 ZWM",
    "wof:placetype":"locality",
    "wof:population":277
},
  "geometry": {"coordinates":[73.139714,28.924428],"type":"Point"}
}