{
  "type": "Feature",
  "properties": {
    "iso:country":"IN",
    "ks:ks_name":"Muniboiyandoddy",
    "ks:ks_pop":102,
    "ks:ks_type":"HABITATION",
    "name:eng_x_preferred":[
        "Muniboiyandoddy"
    ],
    "wof:name":"Muniboiyandoddy",
    "wof:placetype":"locality",
    "wof:population":102
},
  "geometry": {"coordinates":[77.725476,12.486425],"type":"Point"}
}