{
  "type": "Feature",
  "properties": {
    "gn:admin1_code":"12.0",
    "gn:admin2_code":"1.0",
    "gn:asciiname":"Mohandkhan",
    "gn:country_code":"IN",
    "gn:dem":2608,
    "gn:feature_class":"P",
    "gn:feature_code":"PPL",
    "gn:name":"Mohandkhan",
    "gn:population":0,
    "gn:timezone":"Asia/Kolkata",
    "iso:country":"IN",
    "wof:name":"Mohandkhan",
    "wof:placetype":"locality"
},
  "geometry": {"coordinates":[74.47320999999999,34.68708],"type":"Point"}
}