{
  "type": "Feature",
  "properties": {
    "iso:country":"IN",
    "ks:ks_name":"Silya",
    "ks:ks_pop":150,
    "ks:ks_type":"HABITATION",
    "name:eng_x_preferred":[
        "Silya"
    ],
    "wof:name":"Silya",
    "wof:placetype":"locality",
    "wof:population":150
},
  "geometry": {"coordinates":[74.308037,14.639406],"type":"Point"}
}