{
  "type": "Feature",
  "properties": {
    "iso:country":"IN",
    "ks:ks_name":"Badar Ka Khera",
    "ks:ks_pop":134,
    "ks:ks_type":"VILLAGE",
    "name:eng_x_preferred":[
        "Badar Ka Khera"
    ],
    "wof:name":"Badar Ka Khera",
    "wof:placetype":"locality",
    "wof:population":134
},
  "geometry": {"coordinates":[74.505675,24.828242],"type":"Point"}
}