{
  "type": "Feature",
  "properties": {
    "iso:country":"IN",
    "ks:ks_name":"Cherukad",
    "ks:ks_pop":1400,
    "ks:ks_type":"HABITATION",
    "name:eng_x_preferred":[
        "Cherukad"
    ],
    "wof:name":"Cherukad",
    "wof:placetype":"locality",
    "wof:population":1400
},
  "geometry": {"coordinates":[76.340559,9.690171],"type":"Point"}
}