{
  "type": "Feature",
  "properties": {
    "iso:country":"IN",
    "ks:ks_name":"Parsons Valley",
    "ks:ks_pop":144,
    "ks:ks_type":"HABITATION",
    "name:eng_x_preferred":[
        "Parsons Valley"
    ],
    "wof:name":"Parsons Valley",
    "wof:placetype":"locality",
    "wof:population":144
},
  "geometry": {"coordinates":[76.637174,11.403394],"type":"Point"}
}