{
  "type": "Feature",
  "properties": {
    "iso:country":"IN",
    "ks:ks_name":"Mogare",
    "ks:ks_pop":707,
    "ks:ks_type":"VILLAGE",
    "name:eng_x_preferred":[
        "Mogare"
    ],
    "wof:name":"Mogare",
    "wof:placetype":"locality",
    "wof:population":707
},
  "geometry": {"coordinates":[73.374156,16.691648],"type":"Point"}
}