{
  "type": "Feature",
  "properties": {
    "iso:country":"IN",
    "ks:ks_alt_nam":"Dhelw\u0101n",
    "ks:ks_alt_nam_2":"Dhelwan",
    "ks:ks_name":"Dhelwa",
    "ks:ks_type":"VILLAGE",
    "ks:ks_uagg_main":0,
    "name:eng_x_preferred":[
        "Dhelwa"
    ],
    "name:eng_x_variant":[
        "Dhelw\u0101n",
        "Dhelwan"
    ],
    "wof:name":"Dhelwa",
    "wof:placetype":"neighbourhood"
},
  "geometry": {"coordinates":[85.13582,25.583073],"type":"Point"}
}