{
  "type": "Feature",
  "properties": {
    "iso:country":"IN",
    "ks:ks_alt_nam":"Ruddin ka Purwa",
    "ks:ks_name":"Ruddin Ka Purwa",
    "ks:ks_pop":200,
    "ks:ks_type":"HABITATION",
    "ks:ks_uagg_main":0,
    "name:eng_x_preferred":[
        "Ruddin Ka Purwa"
    ],
    "wof:name":"Ruddin Ka Purwa",
    "wof:placetype":"neighbourhood",
    "wof:population":200
},
  "geometry": {"coordinates":[81.14242,27.470991],"type":"Point"}
}