{
  "type": "Feature",
  "properties": {
    "iso:country":"IN",
    "ks:ks_name":"Umari Bk.",
    "ks:ks_pop":188,
    "ks:ks_type":"HABITATION",
    "name:eng_x_preferred":[
        "Umari Bk."
    ],
    "wof:name":"Umari Bk.",
    "wof:placetype":"locality",
    "wof:population":188
},
  "geometry": {"coordinates":[77.357838,20.294055],"type":"Point"}
}