{
  "type": "Feature",
  "properties": {
    "gn:admin1_code":"35.0",
    "gn:admin2_code":"464",
    "gn:asciiname":"Kalmora",
    "gn:country_code":"IN",
    "gn:dem":484,
    "gn:feature_class":"P",
    "gn:feature_code":"PPL",
    "gn:name":"Kalmora",
    "gn:population":0,
    "gn:timezone":"Asia/Kolkata",
    "iso:country":"IN",
    "ks:ks_name":"Kalmora",
    "ks:ks_type":"VILLAGE",
    "name:eng_x_preferred":[
        "Kalmora"
    ],
    "name:pol_x_preferred":[
        "Kalmora"
    ],
    "wof:name":"Kalmora",
    "wof:placetype":"locality"
},
  "geometry": {"coordinates":[74.77169499999999,22.614803],"type":"Point"}
}