{
  "type": "Feature",
  "properties": {
    "iso:country":"IN",
    "ks:ks_name":"Madigamalapalli",
    "ks:ks_pop":70,
    "ks:ks_type":"HABITATION",
    "name:eng_x_preferred":[
        "Madigamalapalli"
    ],
    "wof:name":"Madigamalapalli",
    "wof:placetype":"locality",
    "wof:population":70
},
  "geometry": {"coordinates":[79.03187,13.431416],"type":"Point"}
}