{
  "type": "Feature",
  "properties": {
    "iso:country":"IN",
    "ks:ks_alt_nam":"EAST AHIR TOLA",
    "ks:ks_name":"East Ahir Tola",
    "ks:ks_pop":247,
    "ks:ks_type":"HABITATION",
    "name:eng_x_preferred":[
        "East Ahir Tola"
    ],
    "wof:name":"East Ahir Tola",
    "wof:placetype":"locality",
    "wof:population":247
},
  "geometry": {"coordinates":[84.93893799999999,25.93666],"type":"Point"}
}