{
  "type": "Feature",
  "properties": {
    "iso:country":"IN",
    "ks:ks_name":"Sawarpati",
    "ks:ks_pop":77,
    "ks:ks_type":"HABITATION",
    "name:eng_x_preferred":[
        "Sawarpati"
    ],
    "wof:name":"Sawarpati",
    "wof:placetype":"locality",
    "wof:population":77
},
  "geometry": {"coordinates":[73.203603,17.441975],"type":"Point"}
}