{
  "type": "Feature",
  "properties": {
    "iso:country":"IN",
    "ks:ks_name":"Kothuru",
    "ks:ks_pop":82,
    "ks:ks_type":"HABITATION",
    "name:eng_x_preferred":[
        "Kothuru"
    ],
    "wof:name":"Kothuru",
    "wof:placetype":"locality",
    "wof:population":82
},
  "geometry": {"coordinates":[82.665414,18.024481],"type":"Point"}
}