{
  "type": "Feature",
  "properties": {
    "gn:admin1_code":"39.0",
    "gn:admin2_code":"061",
    "gn:asciiname":"Basyur Baman",
    "gn:country_code":"IN",
    "gn:dem":998,
    "gn:feature_class":"P",
    "gn:feature_code":"PPL",
    "gn:name":"Basy\u016br B\u0101man",
    "gn:population":0,
    "gn:timezone":"Asia/Kolkata",
    "iso:country":"IN",
    "wof:name":"Basyur Baman",
    "wof:placetype":"locality"
},
  "geometry": {"coordinates":[78.6418,29.80529000000001],"type":"Point"}
}