{
  "type": "Feature",
  "properties": {
    "iso:country":"IN",
    "ks:ks_name":"Harma",
    "ks:ks_pop":1275,
    "ks:ks_type":"VILLAGE",
    "name:eng_x_preferred":[
        "Harma"
    ],
    "wof:name":"Harma",
    "wof:placetype":"locality",
    "wof:population":1275
},
  "geometry": {"coordinates":[87.66809000000001,22.313536],"type":"Point"}
}