{
  "type": "Feature",
  "properties": {
    "iso:country":"IN",
    "ks:ks_name":"Bazar Para West",
    "ks:ks_pop":646,
    "ks:ks_type":"HABITATION",
    "ks:ks_uagg_main":0,
    "name:eng_x_preferred":[
        "Bazar Para West"
    ],
    "wof:name":"Bazar Para West",
    "wof:placetype":"neighbourhood",
    "wof:population":646
},
  "geometry": {"coordinates":[91.44709,23.531181],"type":"Point"}
}