{
  "type": "Feature",
  "properties": {
    "gn:admin1_code":"3.0",
    "gn:admin2_code":"322.0",
    "gn:asciiname":"Sarusajai",
    "gn:country_code":"IN",
    "gn:dem":58,
    "gn:feature_class":"P",
    "gn:feature_code":"PPL",
    "gn:name":"Sarusajai",
    "gn:population":0,
    "gn:timezone":"Asia/Kolkata",
    "iso:country":"IN",
    "wof:name":"Sarusajai",
    "wof:placetype":"neighbourhood"
},
  "geometry": {"coordinates":[91.76141,26.11033],"type":"Point"}
}