{
  "type": "Feature",
  "properties": {
    "iso:country":"IN",
    "ks:ks_name":"Kotera Biligeri School",
    "ks:ks_pop":47,
    "ks:ks_type":"HABITATION",
    "name:eng_x_preferred":[
        "Kotera Biligeri School"
    ],
    "wof:name":"Kotera Biligeri School",
    "wof:placetype":"locality",
    "wof:population":47
},
  "geometry": {"coordinates":[75.7375,12.367222],"type":"Point"}
}