{
  "type": "Feature",
  "properties": {
    "iso:country":"IN",
    "ks:ks_alt_nam":"Taimong para",
    "ks:ks_name":"Taimong Para",
    "ks:ks_pop":159,
    "ks:ks_type":"HABITATION",
    "ks:ks_uagg_main":0,
    "name:eng_x_preferred":[
        "Taimong Para"
    ],
    "wof:name":"Taimong Para",
    "wof:placetype":"neighbourhood",
    "wof:population":159
},
  "geometry": {"coordinates":[91.60114799999999,23.112856],"type":"Point"}
}