{
  "type": "Feature",
  "properties": {
    "iso:country":"IN",
    "ks:ks_name":"Chhedarjhar",
    "ks:ks_pop":304,
    "ks:ks_type":"VILLAGE",
    "ks:ks_uagg_main":0,
    "name:eng_x_preferred":[
        "Chhedarjhar"
    ],
    "wof:name":"Chhedarjhar",
    "wof:placetype":"neighbourhood",
    "wof:population":304
},
  "geometry": {"coordinates":[89.302474,26.217364],"type":"Point"}
}