{
  "type": "Feature",
  "properties": {
    "iso:country":"IN",
    "ks:ks_name":"Dhoti Ki Todi",
    "ks:ks_pop":257,
    "ks:ks_type":"HABITATION",
    "name:eng_x_preferred":[
        "Dhoti Ki Todi"
    ],
    "wof:name":"Dhoti Ki Todi",
    "wof:placetype":"locality",
    "wof:population":257
},
  "geometry": {"coordinates":[74.295806,23.188175],"type":"Point"}
}