{
  "type": "Feature",
  "properties": {
    "gn:admin1_code":"24.0",
    "gn:admin2_code":"100",
    "gn:asciiname":"Kankarali",
    "gn:country_code":"IN",
    "gn:dem":215,
    "gn:feature_class":"P",
    "gn:feature_code":"PPL",
    "gn:name":"Kankarali",
    "gn:population":0,
    "gn:timezone":"Asia/Kolkata",
    "iso:country":"IN",
    "wof:name":"Kankarali",
    "wof:placetype":"locality"
},
  "geometry": {"coordinates":[74.92423000000002,28.93881],"type":"Point"}
}