{
  "type": "Feature",
  "properties": {
    "iso:country":"IN",
    "ks:ks_name":"Lakhajharana",
    "ks:ks_pop":18,
    "ks:ks_type":"HABITATION",
    "name:eng_x_preferred":[
        "Lakhajharana"
    ],
    "wof:name":"Lakhajharana",
    "wof:placetype":"locality",
    "wof:population":18
},
  "geometry": {"coordinates":[83.25011600000001,19.202437],"type":"Point"}
}