{
  "type": "Feature",
  "properties": {
    "iso:country":"IN",
    "ks:ks_alt_nam":"KOTHAPETA",
    "ks:ks_name":"Kothapeta",
    "ks:ks_pop":37,
    "ks:ks_type":"HABITATION",
    "name:eng_x_preferred":[
        "Kothapeta"
    ],
    "wof:name":"Kothapeta",
    "wof:placetype":"locality",
    "wof:population":37
},
  "geometry": {"coordinates":[80.86021700000001,16.00345],"type":"Point"}
}