{
  "type": "Feature",
  "properties": {
    "gn:admin1_code":"35.0",
    "gn:admin2_code":"456.0",
    "gn:asciiname":"Dighori",
    "gn:country_code":"IN",
    "gn:dem":605,
    "gn:feature_class":"P",
    "gn:feature_code":"PPL",
    "gn:name":"Dighori",
    "gn:population":0,
    "gn:timezone":"Asia/Kolkata",
    "iso:country":"IN",
    "ks:ks_name":"Dighori",
    "ks:ks_pop":408,
    "ks:ks_type":"VILLAGE",
    "name:eng_x_preferred":[
        "Dighori"
    ],
    "name:mar_x_preferred":[
        "\u0926\u093f\u0918\u094b\u0930\u0940"
    ],
    "name:urd_x_preferred":[
        "\u062f\u06af\u06be\u0648\u0631\u06cc"
    ],
    "wof:name":"Dighori",
    "wof:placetype":"locality",
    "wof:population":408
},
  "geometry": {"coordinates":[79.373563,22.403015],"type":"Point"}
}