{
  "type": "Feature",
  "properties": {
    "gn:admin1_code":"34",
    "gn:admin2_code":"233.0",
    "gn:asciiname":"Nonar",
    "gn:country_code":"IN",
    "gn:dem":75,
    "gn:feature_class":"P",
    "gn:feature_code":"PPL",
    "gn:name":"Non\u0101r",
    "gn:population":0,
    "gn:timezone":"Asia/Kolkata",
    "iso:country":"IN",
    "name:fas_x_preferred":[
        "\u0646\u0648\u0646\u0627\u0631"
    ],
    "wof:name":"Nonar",
    "wof:placetype":"locality"
},
  "geometry": {"coordinates":[83.64022,25.32903],"type":"Point"}
}