{
  "type": "Feature",
  "properties": {
    "gn:admin1_code":"36",
    "gn:admin2_code":"200.0",
    "gn:asciiname":"Harnakachar",
    "gn:country_code":"IN",
    "gn:dem":245,
    "gn:feature_class":"P",
    "gn:feature_code":"PPL",
    "gn:name":"Harn\u0101kach\u0101r",
    "gn:population":0,
    "gn:timezone":"Asia/Kolkata",
    "iso:country":"IN",
    "ks:ks_name":"Harana Kachhar",
    "ks:ks_pop":2610,
    "ks:ks_type":"HABITATION",
    "name:eng_x_preferred":[
        "Harana Kachhar"
    ],
    "name:eng_x_variant":[
        "Harnakachar"
    ],
    "wof:name":"Harana Kachhar",
    "wof:placetype":"locality",
    "wof:population":2610
},
  "geometry": {"coordinates":[83.360435,24.260742],"type":"Point"}
}