{
  "type": "Feature",
  "properties": {
    "gn:admin1_code":"19.0",
    "gn:admin2_code":"570.0",
    "gn:asciiname":"Bettada Tavarekere",
    "gn:country_code":"IN",
    "gn:dem":721,
    "gn:feature_class":"P",
    "gn:feature_code":"PPL",
    "gn:name":"Bettada T\u0101varekere",
    "gn:population":0,
    "gn:timezone":"Asia/Kolkata",
    "iso:country":"IN",
    "wof:name":"Bettada Tavarekere",
    "wof:placetype":"locality"
},
  "geometry": {"coordinates":[75.88722,13.71419],"type":"Point"}
}