{
  "type": "Feature",
  "properties": {
    "iso:country":"IN",
    "ks:ks_name":"Panari",
    "ks:ks_pop":535,
    "ks:ks_type":"HABITATION",
    "name:eng_x_preferred":[
        "Panari"
    ],
    "wof:name":"Panari",
    "wof:placetype":"locality",
    "wof:population":535
},
  "geometry": {"coordinates":[82.99586600000001,24.448159],"type":"Point"}
}