{
  "type": "Feature",
  "properties": {
    "iso:country":"IN",
    "ks:ks_name":"Samrehta",
    "ks:ks_pop":560,
    "ks:ks_type":"HABITATION",
    "name:eng_x_preferred":[
        "Samrehta"
    ],
    "wof:name":"Samrehta",
    "wof:placetype":"locality",
    "wof:population":560
},
  "geometry": {"coordinates":[80.275325,27.292627],"type":"Point"}
}