{
  "type": "Feature",
  "properties": {
    "iso:country":"IN",
    "ks:ks_name":"Kharband",
    "ks:ks_pop":1843,
    "ks:ks_type":"VILLAGE",
    "name:eng_x_preferred":[
        "Kharband"
    ],
    "wof:name":"Kharband",
    "wof:placetype":"locality",
    "wof:population":1843
},
  "geometry": {"coordinates":[85.85564599999999,22.240222],"type":"Point"}
}