{
  "type": "Feature",
  "properties": {
    "iso:country":"IN",
    "ks:ks_name":"Autrawa",
    "ks:ks_pop":2035,
    "ks:ks_type":"HABITATION",
    "name:eng_x_preferred":[
        "Autrawa"
    ],
    "wof:name":"Autrawa",
    "wof:placetype":"locality",
    "wof:population":2035
},
  "geometry": {"coordinates":[83.041888,24.587023],"type":"Point"}
}