{
  "type": "Feature",
  "properties": {
    "gn:admin1_code":"35",
    "gn:admin2_code":"428.0",
    "gn:asciiname":"Lakshmikhera",
    "gn:country_code":"IN",
    "gn:dem":320,
    "gn:feature_class":"P",
    "gn:feature_code":"PPL",
    "gn:name":"Lakshm\u012bkhera",
    "gn:population":0,
    "gn:timezone":"Asia/Kolkata",
    "iso:country":"IN",
    "wof:name":"Lakshmikhera",
    "wof:placetype":"locality"
},
  "geometry": {"coordinates":[79.75161999999997,24.10002],"type":"Point"}
}