{
  "type": "Feature",
  "properties": {
    "gn:admin1_code":"16",
    "gn:admin2_code":"511.0",
    "gn:asciiname":"Khodkut",
    "gn:country_code":"IN",
    "gn:dem":359,
    "gn:feature_class":"P",
    "gn:feature_code":"PPL",
    "gn:name":"Khodkut",
    "gn:population":0,
    "gn:timezone":"Asia/Kolkata",
    "iso:country":"IN",
    "ks:ks_name":"Khodkut",
    "ks:ks_pop":1011,
    "ks:ks_type":"VILLAGE",
    "name:eng_x_preferred":[
        "Khodkut"
    ],
    "wof:name":"Khodkut",
    "wof:placetype":"locality",
    "wof:population":1011
},
  "geometry": {"coordinates":[77.373598,19.210746],"type":"Point"}
}