{
  "type": "Feature",
  "properties": {
    "iso:country":"IN",
    "ks:ks_name":"Kharial",
    "ks:ks_pop":3266,
    "ks:ks_type":"VILLAGE",
    "ks:ks_uagg_main":0,
    "name:eng_x_preferred":[
        "Kharial"
    ],
    "wof:name":"Kharial",
    "wof:placetype":"locality",
    "wof:population":3266
},
  "geometry": {"coordinates":[88.30728999999999,22.691208],"type":"Point"}
}