{
  "type": "Feature",
  "properties": {
    "iso:country":"IN",
    "ks:ks_name":"Srikhampali",
    "ks:ks_pop":0,
    "ks:ks_type":"VILLAGE",
    "name:eng_x_preferred":[
        "Srikhampali"
    ],
    "wof:name":"Srikhampali",
    "wof:placetype":"locality",
    "wof:population":0
},
  "geometry": {"coordinates":[84.906953,21.634118],"type":"Point"}
}