{
  "type": "Feature",
  "properties": {
    "iso:country":"IN",
    "ks:ks_name":"Katukodi",
    "ks:ks_pop":300,
    "ks:ks_type":"HABITATION",
    "name:eng_x_preferred":[
        "Katukodi"
    ],
    "wof:name":"Katukodi",
    "wof:placetype":"locality",
    "wof:population":300
},
  "geometry": {"coordinates":[74.92703899999999,12.803845],"type":"Point"}
}