{
  "type": "Feature",
  "properties": {
    "iso:country":"IN",
    "ks:ks_name":"Halegubbi",
    "ks:ks_pop":6,
    "ks:ks_type":"HABITATION",
    "name:eng_x_preferred":[
        "Halegubbi"
    ],
    "wof:name":"Halegubbi",
    "wof:placetype":"locality",
    "wof:population":6
},
  "geometry": {"coordinates":[74.713504,14.303704],"type":"Point"}
}