{
  "type": "Feature",
  "properties": {
    "iso:country":"IN",
    "ks:ks_name":"Chhota Charpa",
    "ks:ks_pop":310,
    "ks:ks_type":"VILLAGE",
    "name:eng_x_preferred":[
        "Chhota Charpa"
    ],
    "wof:name":"Chhota Charpa",
    "wof:placetype":"locality",
    "wof:population":310
},
  "geometry": {"coordinates":[86.565175,24.19792],"type":"Point"}
}