{
  "type": "Feature",
  "properties": {
    "gn:admin1_code":"16.0",
    "gn:admin2_code":"509.0",
    "gn:asciiname":"Panchala",
    "gn:country_code":"IN",
    "gn:dem":182,
    "gn:feature_class":"P",
    "gn:feature_code":"PPL",
    "gn:name":"Panch\u0101la",
    "gn:population":0,
    "gn:timezone":"Asia/Kolkata",
    "iso:country":"IN",
    "name:aze_x_preferred":[
        "Pan\u00e7ala"
    ],
    "name:ben_x_preferred":[
        "\u09aa\u09be\u099e\u09cd\u099a\u09be\u09b2"
    ],
    "name:cat_x_preferred":[
        "Pantxala"
    ],
    "name:ces_x_preferred":[
        "Pa\u0148\u010d\u00e1la"
    ],
    "name:che_x_preferred":[
        "\u041f\u0430\u043d\u0447\u0430\u043b\u0430"
    ],
    "name:hin_x_preferred":[
        "\u092a\u093e\u091e\u094d\u091a\u093e\u0932"
    ],
    "name:ind_x_preferred":[
        "Kerajaan Pancala"
    ],
    "name:ita_x_preferred":[
        "Panchala"
    ],
    "name:jav_x_preferred":[
        "Pancala"
    ],
    "name:jpn_x_preferred":[
        "\u30d1\u30f3\u30c1\u30e3\u30fc\u30e9\u56fd"
    ],
    "name:kan_x_preferred":[
        "\u0caa\u0cbe\u0c82\u0c9a\u0cbe\u0cb2"
    ],
    "name:kor_x_preferred":[
        "\ud310\ucc30\ub77c"
    ],
    "name:lit_x_preferred":[
        "Pan\u010dala"
    ],
    "name:mal_x_preferred":[
        "\u0d2a\u0d3e\u0d1e\u0d4d\u0d1a\u0d3e\u0d32\u0d02"
    ],
    "name:nep_x_preferred":[
        "\u092a\u093e\u091e\u094d\u091a\u093e\u0932"
    ],
    "name:pnb_x_preferred":[
        "\u067e\u0627\u0646\u0686\u0627\u0644"
    ],
    "name:rus_x_preferred":[
        "\u041f\u0430\u043d\u0447\u0430\u043b\u0430"
    ],
    "name:san_x_preferred":[
        "\u092a\u093e\u091e\u094d\u091a\u093e\u0932\u0903"
    ],
    "name:sin_x_preferred":[
        "\u0db4\u0d82\u0da0\u0dcf\u0dbd"
    ],
    "name:spa_x_preferred":[
        "Panchala"
    ],
    "name:tam_x_preferred":[
        "\u0baa\u0bbe\u0b9e\u0bcd\u0b9a\u0bbe\u0bb2\u0bae\u0bcd"
    ],
    "name:zho_x_preferred":[
        "\u822c\u906e\u7f85"
    ],
    "wof:name":"Panchala",
    "wof:placetype":"locality"
},
  "geometry": {"coordinates":[79.45759,19.76836],"type":"Point"}
}