{
  "type": "Feature",
  "properties": {
    "iso:country":"IN",
    "ks:ks_name":"Chakundi",
    "ks:ks_pop":1551,
    "ks:ks_type":"VILLAGE",
    "ks:ks_uagg_main":0,
    "name:eng_x_preferred":[
        "Chakundi"
    ],
    "wof:name":"Chakundi",
    "wof:placetype":"neighbourhood",
    "wof:population":1551
},
  "geometry": {"coordinates":[88.02636099999999,23.27486],"type":"Point"}
}