{
  "type": "Feature",
  "properties": {
    "iso:country":"IN",
    "ks:ks_name":"Ramsohra",
    "ks:ks_pop":134,
    "ks:ks_type":"VILLAGE",
    "name:eng_x_preferred":[
        "Ramsohra"
    ],
    "wof:name":"Ramsohra",
    "wof:placetype":"locality",
    "wof:population":134
},
  "geometry": {"coordinates":[81.46934,23.702542],"type":"Point"}
}