{
  "type": "Feature",
  "properties": {
    "iso:country":"IN",
    "ks:ks_name":"Dih Tola",
    "ks:ks_pop":956,
    "ks:ks_type":"HABITATION",
    "name:eng_x_preferred":[
        "Dih Tola"
    ],
    "wof:name":"Dih Tola",
    "wof:placetype":"locality",
    "wof:population":956
},
  "geometry": {"coordinates":[86.14166400000001,25.358977],"type":"Point"}
}