{
  "type": "Feature",
  "properties": {
    "gn:admin1_code":"17.0",
    "gn:admin2_code":"273.0",
    "gn:asciiname":"Joipi",
    "gn:country_code":"IN",
    "gn:dem":1319,
    "gn:feature_class":"P",
    "gn:feature_code":"PPL",
    "gn:name":"Joipi",
    "gn:population":0,
    "gn:timezone":"Asia/Kolkata",
    "iso:country":"IN",
    "wof:name":"Joipi",
    "wof:placetype":"locality"
},
  "geometry": {"coordinates":[93.43736,25.27972],"type":"Point"}
}