{
  "type": "Feature",
  "properties": {
    "iso:country":"IN",
    "ks:ks_name":"Kitre",
    "ks:ks_pop":226,
    "ks:ks_type":"HABITATION",
    "name:eng_x_preferred":[
        "Kitre"
    ],
    "wof:name":"Kitre",
    "wof:placetype":"locality",
    "wof:population":226
},
  "geometry": {"coordinates":[74.586579,14.021121],"type":"Point"}
}