{
  "type": "Feature",
  "properties": {
    "iso:country":"IN",
    "ks:ks_name":"Kondala Guddar",
    "ks:ks_pop":312,
    "ks:ks_type":"HABITATION",
    "name:eng_x_preferred":[
        "Kondala Guddar"
    ],
    "wof:name":"Kondala Guddar",
    "wof:placetype":"locality",
    "wof:population":312
},
  "geometry": {"coordinates":[74.710019,13.404157],"type":"Point"}
}