{
  "type": "Feature",
  "properties": {
    "iso:country":"IN",
    "ks:ks_alt_nam":"DATTA MALSOM PARA",
    "ks:ks_name":"Datta Malsom Para",
    "ks:ks_pop":173,
    "ks:ks_type":"HABITATION",
    "name:eng_x_preferred":[
        "Datta Malsom Para"
    ],
    "wof:name":"Datta Malsom Para",
    "wof:placetype":"locality",
    "wof:population":173
},
  "geometry": {"coordinates":[91.733525,23.755638],"type":"Point"}
}