{
  "type": "Feature",
  "properties": {
    "iso:country":"IN",
    "ks:ks_name":"Nagoa",
    "ks:ks_pop":2944,
    "ks:ks_type":"VILLAGE",
    "ks:ks_uagg_main":0,
    "name:eng_x_preferred":[
        "Nagoa"
    ],
    "wof:name":"Nagoa",
    "wof:placetype":"neighbourhood",
    "wof:population":2944
},
  "geometry": {"coordinates":[73.924627,15.35489],"type":"Point"}
}