{
  "type": "Feature",
  "properties": {
    "iso:country":"IN",
    "ks:ks_name":"Dodderikoppa",
    "ks:ks_type":"VILLAGE",
    "name:eng_x_preferred":[
        "Dodderikoppa"
    ],
    "wof:name":"Dodderikoppa",
    "wof:placetype":"locality"
},
  "geometry": {"coordinates":[75.094922,14.438096],"type":"Point"}
}