{
  "type": "Feature",
  "properties": {
    "iso:country":"IN",
    "ks:ks_name":"Beduru",
    "ks:ks_pop":24,
    "ks:ks_type":"HABITATION",
    "name:eng_x_preferred":[
        "Beduru"
    ],
    "wof:name":"Beduru",
    "wof:placetype":"locality",
    "wof:population":24
},
  "geometry": {"coordinates":[74.997264,14.110046],"type":"Point"}
}