{
  "type": "Feature",
  "properties": {
    "gn:admin1_code":"39.0",
    "gn:admin2_code":"64.0",
    "gn:asciiname":"Ratgal",
    "gn:country_code":"IN",
    "gn:dem":1217,
    "gn:feature_class":"P",
    "gn:feature_code":"PPL",
    "gn:name":"Ratgal",
    "gn:population":0,
    "gn:timezone":"Asia/Kolkata",
    "iso:country":"IN",
    "ks:ks_name":"Ratgal",
    "ks:ks_pop":230,
    "ks:ks_type":"HABITATION",
    "name:eng_x_preferred":[
        "Ratgal"
    ],
    "wof:name":"Ratgal",
    "wof:placetype":"locality",
    "wof:population":230
},
  "geometry": {"coordinates":[79.501732,29.716563],"type":"Point"}
}