{
  "type": "Feature",
  "properties": {
    "iso:country":"IN",
    "ks:ks_name":"Hawaikendra",
    "ks:ks_pop":101,
    "ks:ks_type":"HABITATION",
    "name:eng_x_preferred":[
        "Hawaikendra"
    ],
    "wof:name":"Hawaikendra",
    "wof:placetype":"locality",
    "wof:population":101
},
  "geometry": {"coordinates":[73.311323,18.828901],"type":"Point"}
}