{
  "type": "Feature",
  "properties": {
    "iso:country":"IN",
    "ks:ks_name":"U Kolndapalli",
    "ks:ks_pop":87,
    "ks:ks_type":"HABITATION",
    "name:eng_x_preferred":[
        "U Kolndapalli"
    ],
    "wof:name":"U Kolndapalli",
    "wof:placetype":"locality",
    "wof:population":87
},
  "geometry": {"coordinates":[82.71850499999999,18.338901],"type":"Point"}
}