{
  "type": "Feature",
  "properties": {
    "gn:admin1_code":"36.0",
    "gn:admin2_code":"149.0",
    "gn:asciiname":"Bhawanipur Sisarka",
    "gn:country_code":"IN",
    "gn:dem":189,
    "gn:feature_class":"P",
    "gn:feature_code":"PPL",
    "gn:name":"Bhaw\u0101nipur Sisarka",
    "gn:population":0,
    "gn:timezone":"Asia/Kolkata",
    "iso:country":"IN",
    "wof:name":"Bhawanipur Sisarka",
    "wof:placetype":"locality"
},
  "geometry": {"coordinates":[78.84224,28.41373],"type":"Point"}
}