{
  "type": "Feature",
  "properties": {
    "iso:country":"IN",
    "ks:ks_name":"Uparpara",
    "ks:ks_pop":177,
    "ks:ks_type":"HABITATION",
    "name:eng_x_preferred":[
        "Uparpara"
    ],
    "wof:name":"Uparpara",
    "wof:placetype":"locality",
    "wof:population":177
},
  "geometry": {"coordinates":[82.67088,19.982575],"type":"Point"}
}