{
  "type": "Feature",
  "properties": {
    "gn:admin1_code":"36",
    "gn:admin2_code":"180.0",
    "gn:asciiname":"Lamri Ahlad Singh",
    "gn:country_code":"IN",
    "gn:dem":124,
    "gn:feature_class":"P",
    "gn:feature_code":"PPL",
    "gn:name":"Lamri Ahl\u0101d Singh",
    "gn:population":0,
    "gn:timezone":"Asia/Kolkata",
    "iso:country":"IN",
    "wof:name":"Lamri Ahlad Singh",
    "wof:placetype":"neighbourhood"
},
  "geometry": {"coordinates":[81.34784000000001,27.6523],"type":"Point"}
}