{
  "type": "Feature",
  "properties": {
    "gn:admin1_code":"6.0",
    "gn:asciiname":"Tanki Complex",
    "gn:country_code":"IN",
    "gn:dem":1618,
    "gn:feature_class":"P",
    "gn:feature_code":"PPL",
    "gn:name":"Tanki Complex",
    "gn:population":0,
    "gn:timezone":"Asia/Kolkata",
    "iso:country":"IN",
    "wof:name":"Tanki Complex",
    "wof:placetype":"locality"
},
  "geometry": {"coordinates":[74.15604,33.81298],"type":"Point"}
}