{
  "type": "Feature",
  "properties": {
    "gn:admin1_code":"16.0",
    "gn:admin2_code":"516.0",
    "gn:asciiname":"Kaulana",
    "gn:country_code":"IN",
    "gn:dem":445,
    "gn:feature_class":"P",
    "gn:feature_code":"PPL",
    "gn:name":"Kaul\u0101na",
    "gn:population":0,
    "gn:timezone":"Asia/Kolkata",
    "iso:country":"IN",
    "wof:name":"Kaulana",
    "wof:placetype":"locality"
},
  "geometry": {"coordinates":[74.50423000000001,20.48721],"type":"Point"}
}