{
  "type": "Feature",
  "properties": {
    "gn:admin1_code":"11",
    "gn:admin2_code":"33.0",
    "gn:asciiname":"Mashraon",
    "gn:country_code":"IN",
    "gn:dem":1983,
    "gn:feature_class":"P",
    "gn:feature_code":"PPL",
    "gn:name":"Mashraon",
    "gn:population":0,
    "gn:timezone":"Asia/Kolkata",
    "iso:country":"IN",
    "wof:name":"Mashraon",
    "wof:placetype":"locality"
},
  "geometry": {"coordinates":[77.55956999999999,30.99733],"type":"Point"}
}