{
  "type": "Feature",
  "properties": {
    "gn:admin1_code":"36.0",
    "gn:admin2_code":"174.0",
    "gn:asciiname":"Imamganj",
    "gn:country_code":"IN",
    "gn:dem":107,
    "gn:feature_class":"P",
    "gn:feature_code":"PPL",
    "gn:name":"Im\u0101mganj",
    "gn:population":0,
    "gn:timezone":"Asia/Kolkata",
    "iso:country":"IN",
    "wof:name":"Imamganj",
    "wof:placetype":"locality"
},
  "geometry": {"coordinates":[81.57886999999999,25.53117],"type":"Point"}
}