{
  "type": "Feature",
  "properties": {
    "iso:country":"IN",
    "ks:ks_alt_nam":"BOGGITIVARIPALLE",
    "ks:ks_name":"Boggitivaripalle",
    "ks:ks_pop":4,
    "ks:ks_type":"HABITATION",
    "name:eng_x_preferred":[
        "Boggitivaripalle"
    ],
    "wof:name":"Boggitivaripalle",
    "wof:placetype":"locality",
    "wof:population":4
},
  "geometry": {"coordinates":[78.46536399999999,13.729536],"type":"Point"}
}