{
  "type": "Feature",
  "properties": {
    "iso:country":"IN",
    "ks:ks_name":"Malipadara",
    "ks:ks_pop":143,
    "ks:ks_type":"VILLAGE",
    "name:eng_x_preferred":[
        "Malipadara"
    ],
    "wof:name":"Malipadara",
    "wof:placetype":"locality",
    "wof:population":143
},
  "geometry": {"coordinates":[83.12290900000001,19.496742],"type":"Point"}
}