{
  "type": "Feature",
  "properties": {
    "iso:country":"IN",
    "ks:ks_name":"College",
    "ks:ks_pop":1322,
    "ks:ks_type":"HABITATION",
    "ks:ks_uagg_main":0,
    "name:eng_x_preferred":[
        "College"
    ],
    "wof:name":"College",
    "wof:placetype":"neighbourhood",
    "wof:population":1322
},
  "geometry": {"coordinates":[76.43925299999999,9.459703],"type":"Point"}
}