{
  "type": "Feature",
  "properties": {
    "gn:admin1_code":"11.0",
    "gn:admin2_code":"026",
    "gn:asciiname":"Duff Dunbar",
    "gn:country_code":"IN",
    "gn:dem":1908,
    "gn:feature_class":"P",
    "gn:feature_code":"PPL",
    "gn:name":"Duff Dunbar",
    "gn:population":0,
    "gn:timezone":"Asia/Kolkata",
    "iso:country":"IN",
    "wof:name":"Duff Dunbar",
    "wof:placetype":"neighbourhood"
},
  "geometry": {"coordinates":[77.18653999999999,32.24481],"type":"Point"}
}