{
  "type": "Feature",
  "properties": {
    "gn:admin1_code":"35.0",
    "gn:admin2_code":"441.0",
    "gn:asciiname":"Takli",
    "gn:country_code":"IN",
    "gn:dem":253,
    "gn:feature_class":"P",
    "gn:feature_code":"PPL",
    "gn:name":"T\u0101kli",
    "gn:population":0,
    "gn:timezone":"Asia/Kolkata",
    "iso:country":"IN",
    "ks:ks_name":"Takali",
    "ks:ks_pop":447,
    "ks:ks_type":"HABITATION",
    "name:eng_x_preferred":[
        "Takali"
    ],
    "name:eng_x_variant":[
        "Takli"
    ],
    "wof:name":"Takali",
    "wof:placetype":"locality",
    "wof:population":447
},
  "geometry": {"coordinates":[74.70056099999999,21.62699],"type":"Point"}
}