{
  "type": "Feature",
  "properties": {
    "iso:country":"IN",
    "ks:ks_name":"Ankurhati",
    "ks:ks_pop":7785,
    "ks:ks_type":"VILLAGE",
    "ks:ks_uagg_main":0,
    "name:eng_x_preferred":[
        "Ankurhati"
    ],
    "wof:name":"Ankurhati",
    "wof:placetype":"neighbourhood",
    "wof:population":7785
},
  "geometry": {"coordinates":[88.239317,22.608142],"type":"Point"}
}