{
  "type": "Feature",
  "properties": {
    "gn:admin1_code":"12.0",
    "gn:admin2_code":"6.0",
    "gn:asciiname":"Lunjhei",
    "gn:country_code":"IN",
    "gn:dem":1459,
    "gn:feature_class":"P",
    "gn:feature_code":"PPL",
    "gn:name":"Lunjhei",
    "gn:population":0,
    "gn:timezone":"Asia/Kolkata",
    "iso:country":"IN",
    "wof:name":"Lunjhei",
    "wof:placetype":"locality"
},
  "geometry": {"coordinates":[74.46436,33.33781],"type":"Point"}
}