{
  "type": "Feature",
  "properties": {
    "gn:admin1_code":"19",
    "gn:admin2_code":"569.0",
    "gn:asciiname":"Udiyavara",
    "gn:country_code":"IN",
    "gn:dem":15,
    "gn:feature_class":"P",
    "gn:feature_code":"PPL",
    "gn:name":"Udiy\u0101vara",
    "gn:population":0,
    "gn:timezone":"Asia/Kolkata",
    "iso:country":"IN",
    "name:und_x_variant":[
        "Udayavara",
        "Udiy\u0101vara"
    ],
    "wof:name":"Udiyavara",
    "wof:placetype":"locality"
},
  "geometry": {"coordinates":[74.73869000000001,13.30247],"type":"Point"}
}