{
  "type": "Feature",
  "properties": {
    "gn:admin1_code":"19",
    "gn:admin2_code":"569.0",
    "gn:asciiname":"Udiyavara",
    "gn:country_code":"IN",
    "gn:dem":15,
    "gn:feature_class":"P",
    "gn:feature_code":"PPL",
    "gn:name":"Udiy\u0101vara",
    "gn:population":0,
    "gn:timezone":"Asia/Kolkata",
    "iso:country":"IN",
    "ks:ks_name":"Udyavara",
    "ks:ks_pop":11386,
    "ks:ks_type":"VILLAGE",
    "name:eng_x_preferred":[
        "Udyavara"
    ],
    "name:eng_x_variant":[
        "Udiyavara"
    ],
    "name:und_x_variant":[
        "Udayavara",
        "Udiy\u0101vara"
    ],
    "wof:name":"Udyavara",
    "wof:placetype":"locality",
    "wof:population":11386
},
  "geometry": {"coordinates":[74.736324,13.296563],"type":"Point"}
}