{
  "type": "Feature",
  "properties": {
    "iso:country":"IN",
    "ks:ks_name":"Goudgad",
    "ks:ks_pop":694,
    "ks:ks_type":"VILLAGE",
    "name:eng_x_preferred":[
        "Goudgad"
    ],
    "wof:name":"Goudgad",
    "wof:placetype":"locality",
    "wof:population":694
},
  "geometry": {"coordinates":[84.06366300000001,21.044581],"type":"Point"}
}