{
  "type": "Feature",
  "properties": {
    "gn:admin1_code":"10",
    "gn:admin2_code":"85.0",
    "gn:asciiname":"Jakhala",
    "gn:country_code":"IN",
    "gn:dem":232,
    "gn:feature_class":"P",
    "gn:feature_code":"PPL",
    "gn:name":"Jakh\u0101la",
    "gn:population":0,
    "gn:timezone":"Asia/Kolkata",
    "iso:country":"IN",
    "wof:name":"Jakhala",
    "wof:placetype":"locality"
},
  "geometry": {"coordinates":[76.53515,28.38476],"type":"Point"}
}