{
  "type": "Feature",
  "properties": {
    "iso:country":"IN",
    "ks:ks_name":"Katara",
    "ks:ks_pop":401,
    "ks:ks_type":"HABITATION",
    "name:eng_x_preferred":[
        "Katara"
    ],
    "wof:name":"Katara",
    "wof:placetype":"locality",
    "wof:population":401
},
  "geometry": {"coordinates":[79.929507,26.731631],"type":"Point"}
}