{
  "type": "Feature",
  "properties": {
    "iso:country":"IN",
    "ks:ks_name":"Bhamoria",
    "ks:ks_pop":73,
    "ks:ks_type":"HABITATION",
    "name:eng_x_preferred":[
        "Bhamoria"
    ],
    "wof:name":"Bhamoria",
    "wof:placetype":"locality",
    "wof:population":73
},
  "geometry": {"coordinates":[79.283323,29.634499],"type":"Point"}
}