{
  "type": "Feature",
  "properties": {
    "gn:admin1_code":"2",
    "gn:admin2_code":"545.0",
    "gn:asciiname":"Marlava",
    "gn:country_code":"IN",
    "gn:dem":36,
    "gn:feature_class":"P",
    "gn:feature_code":"PPL",
    "gn:name":"Marl\u0101va",
    "gn:population":0,
    "gn:timezone":"Asia/Kolkata",
    "iso:country":"IN",
    "name:tel_x_preferred":[
        "\u0c2e\u0c30\u0c4d\u0c32\u0c3e\u0c35"
    ],
    "wof:name":"Marlava",
    "wof:placetype":"locality"
},
  "geometry": {"coordinates":[82.12951,17.15898],"type":"Point"}
}