{
  "type": "Feature",
  "properties": {
    "iso:country":"IN",
    "ks:ks_name":"Suparwadi",
    "ks:ks_pop":158,
    "ks:ks_type":"HABITATION",
    "name:eng_x_preferred":[
        "Suparwadi"
    ],
    "wof:name":"Suparwadi",
    "wof:placetype":"locality",
    "wof:population":158
},
  "geometry": {"coordinates":[73.50666699999999,19.913333],"type":"Point"}
}