{
  "type": "Feature",
  "properties": {
    "iso:country":"IN",
    "ks:ks_name":"Thonikadavu",
    "ks:ks_pop":545,
    "ks:ks_type":"HABITATION",
    "name:eng_x_preferred":[
        "Thonikadavu"
    ],
    "wof:name":"Thonikadavu",
    "wof:placetype":"locality",
    "wof:population":545
},
  "geometry": {"coordinates":[76.22043499999999,10.909746],"type":"Point"}
}