{
  "type": "Feature",
  "properties": {
    "gn:admin1_code":"2",
    "gn:admin2_code":"544.0",
    "gn:asciiname":"Marripalem",
    "gn:country_code":"IN",
    "gn:dem":7,
    "gn:feature_class":"P",
    "gn:feature_code":"PPL",
    "gn:name":"Marrip\u0101lem",
    "gn:population":0,
    "gn:timezone":"Asia/Kolkata",
    "iso:country":"IN",
    "wof:name":"Marripalem",
    "wof:placetype":"locality"
},
  "geometry": {"coordinates":[82.8754,17.48226],"type":"Point"}
}