{
  "type": "Feature",
  "properties": {
    "gn:admin1_code":"38.0",
    "gn:admin2_code":"362.0",
    "gn:asciiname":"Bankjori",
    "gn:country_code":"IN",
    "gn:dem":65,
    "gn:feature_class":"P",
    "gn:feature_code":"PPL",
    "gn:name":"B\u0101nkjori",
    "gn:population":0,
    "gn:timezone":"Asia/Kolkata",
    "iso:country":"IN",
    "wof:name":"Bankjori",
    "wof:placetype":"locality"
},
  "geometry": {"coordinates":[87.63908000000001,24.16126],"type":"Point"}
}