{
  "type": "Feature",
  "properties": {
    "iso:country":"IN",
    "ks:ks_name":"Keelakottai",
    "ks:ks_pop":1345,
    "ks:ks_type":"HABITATION",
    "ks:ks_uagg_main":0,
    "name:eng_x_preferred":[
        "Keelakottai"
    ],
    "wof:name":"Keelakottai",
    "wof:placetype":"neighbourhood",
    "wof:population":1345
},
  "geometry": {"coordinates":[78.001766,9.786211],"type":"Point"}
}