{
  "type": "Feature",
  "properties": {
    "iso:country":"IN",
    "ks:ks_name":"Basing Garjang",
    "ks:ks_pop":173,
    "ks:ks_type":"VILLAGE",
    "name:eng_x_preferred":[
        "Basing Garjang"
    ],
    "wof:name":"Basing Garjang",
    "wof:placetype":"locality",
    "wof:population":173
},
  "geometry": {"coordinates":[83.87535099999999,19.108351],"type":"Point"}
}