{
  "type": "Feature",
  "properties": {
    "gn:admin1_code":"25.0",
    "gn:admin2_code":"630.0",
    "gn:asciiname":"Errasigehalli",
    "gn:country_code":"IN",
    "gn:dem":517,
    "gn:feature_class":"P",
    "gn:feature_code":"PPL",
    "gn:name":"Erras\u012bgehalli",
    "gn:population":0,
    "gn:timezone":"Asia/Kolkata",
    "iso:country":"IN",
    "wof:name":"Errasigehalli",
    "wof:placetype":"locality"
},
  "geometry": {"coordinates":[78.1546,12.36229],"type":"Point"}
}