{
  "type": "Feature",
  "properties": {
    "iso:country":"IN",
    "ks:ks_name":"Tangikiari",
    "ks:ks_pop":8,
    "ks:ks_type":"VILLAGE",
    "name:eng_x_preferred":[
        "Tangikiari"
    ],
    "wof:name":"Tangikiari",
    "wof:placetype":"locality",
    "wof:population":8
},
  "geometry": {"coordinates":[83.56817100000001,19.827331],"type":"Point"}
}