{
  "type": "Feature",
  "properties": {
    "iso:country":"IN",
    "ks:ks_alt_nam":"ATHIGERE",
    "ks:ks_name":"Athigere",
    "ks:ks_pop":253,
    "ks:ks_type":"HABITATION",
    "name:eng_x_preferred":[
        "Athigere"
    ],
    "wof:name":"Athigere",
    "wof:placetype":"locality",
    "wof:population":253
},
  "geometry": {"coordinates":[75.19357599999999,13.757505],"type":"Point"}
}