{
  "type": "Feature",
  "properties": {
    "iso:country":"IN",
    "ks:ks_name":"Bijoypur I",
    "ks:ks_pop":500,
    "ks:ks_type":"HABITATION",
    "name:eng_x_preferred":[
        "Bijoypur I"
    ],
    "wof:name":"Bijoypur I",
    "wof:placetype":"locality",
    "wof:population":500
},
  "geometry": {"coordinates":[92.755776,24.924068],"type":"Point"}
}