{
  "type": "Feature",
  "properties": {
    "iso:country":"IN",
    "ks:ks_name":"Kolhariya",
    "ks:ks_pop":128,
    "ks:ks_type":"VILLAGE",
    "name:eng_x_preferred":[
        "Kolhariya"
    ],
    "wof:name":"Kolhariya",
    "wof:placetype":"locality",
    "wof:population":128
},
  "geometry": {"coordinates":[86.57836500000001,24.103386],"type":"Point"}
}