{
  "type": "Feature",
  "properties": {
    "iso:country":"IN",
    "ks:ks_alt_nam":"Ghutu\u0101",
    "ks:ks_name":"Ghutua",
    "ks:ks_pop":2029,
    "ks:ks_type":"VILLAGE",
    "name:eng_x_preferred":[
        "Ghutua"
    ],
    "name:eng_x_variant":[
        "Ghutu\u0101"
    ],
    "wof:name":"Ghutua",
    "wof:placetype":"locality",
    "wof:population":2029
},
  "geometry": {"coordinates":[84.320531,23.967786],"type":"Point"}
}