{
  "type": "Feature",
  "properties": {
    "iso:country":"IN",
    "ks:ks_name":"Rachavaripalle",
    "ks:ks_pop":44,
    "ks:ks_type":"HABITATION",
    "name:eng_x_preferred":[
        "Rachavaripalle"
    ],
    "wof:name":"Rachavaripalle",
    "wof:placetype":"locality",
    "wof:population":44
},
  "geometry": {"coordinates":[78.65919,13.442441],"type":"Point"}
}