{
  "type": "Feature",
  "properties": {
    "iso:country":"IN",
    "ks:ks_name":"Dumuriguda",
    "ks:ks_pop":41,
    "ks:ks_type":"HABITATION",
    "name:eng_x_preferred":[
        "Dumuriguda"
    ],
    "wof:name":"Dumuriguda",
    "wof:placetype":"locality",
    "wof:population":41
},
  "geometry": {"coordinates":[82.98842,18.438594],"type":"Point"}
}