{
  "type": "Feature",
  "properties": {
    "gn:admin1_code":"24",
    "gn:admin2_code":"106.0",
    "gn:asciiname":"Indon",
    "gn:country_code":"IN",
    "gn:dem":209,
    "gn:feature_class":"P",
    "gn:feature_code":"PPL",
    "gn:name":"Indon",
    "gn:population":0,
    "gn:timezone":"Asia/Kolkata",
    "iso:country":"IN",
    "wof:name":"Indon",
    "wof:placetype":"locality"
},
  "geometry": {"coordinates":[77.50131999999998,26.7916],"type":"Point"}
}