{
  "type": "Feature",
  "properties": {
    "iso:country":"IN",
    "ks:ks_name":"Tachhedi",
    "ks:ks_pop":20,
    "ks:ks_type":"HABITATION",
    "name:eng_x_preferred":[
        "Tachhedi"
    ],
    "wof:name":"Tachhedi",
    "wof:placetype":"locality",
    "wof:population":20
},
  "geometry": {"coordinates":[78.88338,29.92721],"type":"Point"}
}