{
  "type": "Feature",
  "properties": {
    "iso:country":"IN",
    "ks:ks_name":"Fungaram Para",
    "ks:ks_pop":981,
    "ks:ks_type":"HABITATION",
    "name:eng_x_preferred":[
        "Fungaram Para"
    ],
    "wof:name":"Fungaram Para",
    "wof:placetype":"locality",
    "wof:population":981
},
  "geometry": {"coordinates":[92.032813,23.93855],"type":"Point"}
}