{
  "type": "Feature",
  "properties": {
    "iso:country":"IN",
    "ks:ks_name":"Pimpalgaon",
    "ks:ks_pop":1632,
    "ks:ks_type":"HABITATION",
    "name:eng_x_preferred":[
        "Pimpalgaon"
    ],
    "wof:name":"Pimpalgaon",
    "wof:placetype":"locality",
    "wof:population":1632
},
  "geometry": {"coordinates":[78.863024,20.516538],"type":"Point"}
}