{
  "type": "Feature",
  "properties": {
    "iso:country":"IN",
    "ks:ks_name":"Kirarod Afganan",
    "ks:ks_pop":807,
    "ks:ks_type":"HABITATION",
    "name:eng_x_preferred":[
        "Kirarod Afganan"
    ],
    "wof:name":"Kirarod Afganan",
    "wof:placetype":"locality",
    "wof:population":807
},
  "geometry": {"coordinates":[76.08841099999999,28.055503],"type":"Point"}
}