{
  "type": "Feature",
  "properties": {
    "gn:admin1_code":"36",
    "gn:admin2_code":"181.0",
    "gn:asciiname":"Pura Mohan Pasi",
    "gn:country_code":"IN",
    "gn:dem":121,
    "gn:feature_class":"P",
    "gn:feature_code":"PPL",
    "gn:name":"Pura Mohan P\u0101si",
    "gn:population":0,
    "gn:timezone":"Asia/Kolkata",
    "iso:country":"IN",
    "wof:name":"Pura Mohan Pasi",
    "wof:placetype":"locality"
},
  "geometry": {"coordinates":[81.70149000000001,27.46813],"type":"Point"}
}