{
  "type": "Feature",
  "properties": {
    "iso:country":"IN",
    "ks:ks_name":"Binnyachara",
    "ks:ks_pop":1111,
    "ks:ks_type":"HABITATION",
    "name:eng_x_preferred":[
        "Binnyachara"
    ],
    "wof:name":"Binnyachara",
    "wof:placetype":"locality",
    "wof:population":1111
},
  "geometry": {"coordinates":[90.142466,26.418716],"type":"Point"}
}