{
  "type": "Feature",
  "properties": {
    "gn:admin1_code":"19.0",
    "gn:admin2_code":"569.0",
    "gn:asciiname":"Kattingere",
    "gn:country_code":"IN",
    "gn:dem":58,
    "gn:feature_class":"P",
    "gn:feature_code":"PPLL",
    "gn:name":"Kattingere",
    "gn:population":0,
    "gn:timezone":"Asia/Kolkata",
    "iso:country":"IN",
    "ks:ks_name":"Kattingere",
    "ks:ks_type":"VILLAGE",
    "name:eng_x_preferred":[
        "Kattingere"
    ],
    "wof:name":"Kattingere",
    "wof:placetype":"locality"
},
  "geometry": {"coordinates":[74.83216,13.265125],"type":"Point"}
}