{
  "type": "Feature",
  "properties": {
    "iso:country":"IN",
    "ks:ks_name":"Doddamane",
    "ks:ks_pop":11,
    "ks:ks_type":"HABITATION",
    "name:eng_x_preferred":[
        "Doddamane"
    ],
    "wof:name":"Doddamane",
    "wof:placetype":"locality",
    "wof:population":11
},
  "geometry": {"coordinates":[75.007683,13.800775],"type":"Point"}
}