{
  "type": "Feature",
  "properties": {
    "gn:admin1_code":"35.0",
    "gn:admin2_code":"438.0",
    "gn:asciiname":"Toranmal",
    "gn:country_code":"IN",
    "gn:dem":352,
    "gn:feature_class":"P",
    "gn:feature_code":"PPL",
    "gn:name":"Toranm\u0101l",
    "gn:population":0,
    "gn:timezone":"Asia/Kolkata",
    "iso:country":"IN",
    "name:guj_x_preferred":[
        "\u0aa4\u0acb\u0ab0\u0aa3\u0aae\u0abe\u0ab3"
    ],
    "name:mar_x_preferred":[
        "\u0924\u094b\u0930\u0923\u092e\u093e\u0933"
    ],
    "name:san_x_preferred":[
        "\u0924\u094b\u0930\u0923\u092e\u0932\u0903"
    ],
    "wof:name":"Toranmal",
    "wof:placetype":"locality"
},
  "geometry": {"coordinates":[74.53199000000002,22.15989],"type":"Point"}
}