{
  "type": "Feature",
  "properties": {
    "iso:country":"IN",
    "ks:ks_name":"Berkhera Tanda Ahatmali",
    "ks:ks_pop":2300,
    "ks:ks_type":"VILLAGE",
    "ks:ks_uagg_main":0,
    "name:eng_x_preferred":[
        "Berkhera Tanda Ahatmali"
    ],
    "wof:name":"Berkhera Tanda Ahatmali",
    "wof:placetype":"neighbourhood",
    "wof:population":2300
},
  "geometry": {"coordinates":[78.67264299999999,29.255904],"type":"Point"}
}