{
  "type": "Feature",
  "properties": {
    "iso:country":"IN",
    "ks:ks_alt_nam":"Brund\u0101m\u0101l",
    "ks:ks_name":"Brundamal",
    "ks:ks_pop":2934,
    "ks:ks_type":"VILLAGE",
    "ks:ks_uagg_main":0,
    "name:eng_x_preferred":[
        "Brundamal"
    ],
    "name:eng_x_variant":[
        "Brund\u0101m\u0101l"
    ],
    "wof:name":"Brundamal",
    "wof:placetype":"locality",
    "wof:population":2934
},
  "geometry": {"coordinates":[84.022503,21.810591],"type":"Point"}
}