{
  "type": "Feature",
  "properties": {
    "iso:country":"IN",
    "ks:ks_name":"Devadongar",
    "ks:ks_pop":11,
    "ks:ks_type":"HABITATION",
    "name:eng_x_preferred":[
        "Devadongar"
    ],
    "wof:name":"Devadongar",
    "wof:placetype":"locality",
    "wof:population":11
},
  "geometry": {"coordinates":[74.67512499999999,14.93582],"type":"Point"}
}