{
  "type": "Feature",
  "properties": {
    "iso:country":"IN",
    "ks:ks_name":"Goligarady Garadibettu",
    "ks:ks_pop":240,
    "ks:ks_type":"HABITATION",
    "ks:ks_uagg_main":0,
    "name:eng_x_preferred":[
        "Goligarady Garadibettu"
    ],
    "wof:name":"Goligarady Garadibettu",
    "wof:placetype":"neighbourhood",
    "wof:population":240
},
  "geometry": {"coordinates":[74.71507,13.470732],"type":"Point"}
}