{
  "type": "Feature",
  "properties": {
    "gn:admin1_code":"39.0",
    "gn:admin2_code":"64.0",
    "gn:asciiname":"Karget",
    "gn:country_code":"IN",
    "gn:dem":1318,
    "gn:feature_class":"P",
    "gn:feature_code":"PPL",
    "gn:name":"Karget",
    "gn:population":0,
    "gn:timezone":"Asia/Kolkata",
    "iso:country":"IN",
    "ks:ks_name":"Karget",
    "ks:ks_pop":547,
    "ks:ks_type":"VILLAGE",
    "name:eng_x_preferred":[
        "Karget"
    ],
    "wof:name":"Karget",
    "wof:placetype":"locality",
    "wof:population":547
},
  "geometry": {"coordinates":[79.13525199999999,29.633715],"type":"Point"}
}