{
  "type": "Feature",
  "properties": {
    "gn:admin1_code":"36",
    "gn:admin2_code":"176.0",
    "gn:asciiname":"Agasanda",
    "gn:country_code":"IN",
    "gn:dem":125,
    "gn:feature_class":"P",
    "gn:feature_code":"PPL",
    "gn:name":"Ag\u0101sanda",
    "gn:population":0,
    "gn:timezone":"Asia/Kolkata",
    "iso:country":"IN",
    "wof:name":"Agasanda",
    "wof:placetype":"locality"
},
  "geometry": {"coordinates":[81.01054000000001,27.04173],"type":"Point"}
}