{
  "type": "Feature",
  "properties": {
    "iso:country":"IN",
    "ks:ks_name":"Rangamatia",
    "ks:ks_pop":612,
    "ks:ks_type":"VILLAGE",
    "name:eng_x_preferred":[
        "Rangamatia"
    ],
    "wof:name":"Rangamatia",
    "wof:placetype":"locality",
    "wof:population":612
},
  "geometry": {"coordinates":[86.22058699999999,22.42274],"type":"Point"}
}