{
  "type": "Feature",
  "properties": {
    "iso:country":"IN",
    "ks:ks_name":"Selvaperumal Nagar",
    "ks:ks_pop":320,
    "ks:ks_type":"HABITATION",
    "ks:ks_uagg_main":0,
    "name:eng_x_preferred":[
        "Selvaperumal Nagar"
    ],
    "wof:name":"Selvaperumal Nagar",
    "wof:placetype":"neighbourhood",
    "wof:population":320
},
  "geometry": {"coordinates":[78.871173,12.97112],"type":"Point"}
}