{
  "type": "Feature",
  "properties": {
    "gn:admin1_code":"21.0",
    "gn:admin2_code":"375",
    "gn:asciiname":"Kalimatti",
    "gn:country_code":"IN",
    "gn:dem":540,
    "gn:feature_class":"P",
    "gn:feature_code":"PPL",
    "gn:name":"K\u0101limatti",
    "gn:population":0,
    "gn:timezone":"Asia/Kolkata",
    "iso:country":"IN",
    "wof:name":"Kalimatti",
    "wof:placetype":"locality"
},
  "geometry": {"coordinates":[85.40215999999999,21.86594],"type":"Point"}
}