{
  "type": "Feature",
  "properties": {
    "iso:country":"IN",
    "ks:ks_name":"Janipada I",
    "ks:ks_pop":196,
    "ks:ks_type":"HABITATION",
    "name:eng_x_preferred":[
        "Janipada I"
    ],
    "wof:name":"Janipada I",
    "wof:placetype":"locality",
    "wof:population":196
},
  "geometry": {"coordinates":[82.610091,19.58491],"type":"Point"}
}