{
  "type": "Feature",
  "properties": {
    "iso:country":"IN",
    "ks:ks_name":"Chak Jagner",
    "ks:ks_pop":106,
    "ks:ks_type":"VILLAGE",
    "name:eng_x_preferred":[
        "Chak Jagner"
    ],
    "wof:name":"Chak Jagner",
    "wof:placetype":"locality",
    "wof:population":106
},
  "geometry": {"coordinates":[76.228353,26.696787],"type":"Point"}
}