{
  "type": "Feature",
  "properties": {
    "iso:country":"IN",
    "ks:ks_alt_nam":"Ambalapoyil jn",
    "ks:ks_name":"Ambalapoyil Jn",
    "ks:ks_pop":635,
    "ks:ks_type":"HABITATION",
    "name:eng_x_preferred":[
        "Ambalapoyil Jn"
    ],
    "wof:name":"Ambalapoyil Jn",
    "wof:placetype":"locality",
    "wof:population":635
},
  "geometry": {"coordinates":[76.244195,11.344144],"type":"Point"}
}