{
  "type": "Feature",
  "properties": {
    "iso:country":"IN",
    "ks:ks_name":"Velliankattur",
    "ks:ks_pop":30,
    "ks:ks_type":"HABITATION",
    "name:eng_x_preferred":[
        "Velliankattur"
    ],
    "wof:name":"Velliankattur",
    "wof:placetype":"locality",
    "wof:population":30
},
  "geometry": {"coordinates":[77.837011,10.994091],"type":"Point"}
}