{
  "type": "Feature",
  "properties": {
    "gn:admin1_code":"9.0",
    "gn:admin2_code":"484.0",
    "gn:asciiname":"Ambli Mota",
    "gn:country_code":"IN",
    "gn:dem":86,
    "gn:feature_class":"P",
    "gn:feature_code":"PPL",
    "gn:name":"Ambli Mota",
    "gn:population":0,
    "gn:timezone":"Asia/Kolkata",
    "iso:country":"IN",
    "wof:name":"Ambli Mota",
    "wof:placetype":"locality"
},
  "geometry": {"coordinates":[73.59729,23.09729],"type":"Point"}
}