{
  "type": "Feature",
  "properties": {
    "iso:country":"IN",
    "ks:ks_name":"Sujawalpur Chauriwan",
    "ks:ks_pop":1677,
    "ks:ks_type":"VILLAGE",
    "name:eng_x_preferred":[
        "Sujawalpur Chauriwan"
    ],
    "wof:name":"Sujawalpur Chauriwan",
    "wof:placetype":"locality",
    "wof:population":1677
},
  "geometry": {"coordinates":[85.522571,26.004336],"type":"Point"}
}