{
  "type": "Feature",
  "properties": {
    "iso:country":"IN",
    "name:ara_x_preferred":[
        "\u0634\u064a\u062e \u0628\u0648\u0631\u0627"
    ],
    "name:ben_bn_x_preferred":[
        "\u09b6\u09c7\u0996\u09aa\u09c1\u09b0\u09be"
    ],
    "name:ben_in_x_preferred":[
        "\u09b6\u09c7\u0996\u09aa\u09c1\u09b0\u09be"
    ],
    "name:ben_x_preferred":[
        "\u09b6\u09c7\u0996\u09b0\u09aa\u09c1\u09b0\u09be"
    ],
    "name:bpy_x_preferred":[
        "\u09b6\u09c7\u0996\u09b0\u09aa\u09c1\u09b0\u09be"
    ],
    "name:eng_x_preferred":[
        "Shekhpura"
    ],
    "name:fra_x_preferred":[
        "Shekhpura"
    ],
    "name:guj_x_preferred":[
        "\u0ab6\u0ac7\u0a96\u0aaa\u0ac1\u0ab0\u0abe"
    ],
    "name:hin_x_preferred":[
        "\u0936\u0947\u0916\u092a\u0941\u0930\u093e"
    ],
    "name:ita_x_preferred":[
        "Shekhpura"
    ],
    "name:kan_x_preferred":[
        "\u0cb6\u0cc7\u0c96\u0ccd"
    ],
    "name:mal_x_preferred":[
        "\u0d37\u0d46\u0d2f\u0d4d\u0d16\u0d4d\u0d2a\u0d41\u0d30"
    ],
    "name:mar_x_preferred":[
        "\u0936\u0947\u0916\u092a\u0941\u0930\u093e"
    ],
    "name:msa_x_preferred":[
        "Shekhpura"
    ],
    "name:nan_x_preferred":[
        "Shekhpura"
    ],
    "name:nld_x_preferred":[
        "Shekhpura"
    ],
    "name:pan_x_preferred":[
        "\u0a36\u0a47\u0a16\u0a2a\u0a41\u0a30\u0a3e"
    ],
    "name:por_x_preferred":[
        "Shekhpura"
    ],
    "name:tam_x_preferred":[
        "\u0bb7\u0bc7\u0b95\u0bcd\u0baa\u0bc1\u0bb0\u0bbe"
    ],
    "name:tel_x_preferred":[
        "\u0c37\u0c47\u0c15\u0c4d"
    ],
    "name:urd_x_preferred":[
        "\u0634\u06cc\u062d \u067e\u0648\u0631\u06c1"
    ],
    "name:vie_x_preferred":[
        "Shekhpura"
    ],
    "name:zho_x_preferred":[
        "\u65af\u8d6b\u514b\u666e\u62c9"
    ],
    "qs:name":"Shekhpura",
    "qs:name_adm0":"India",
    "qs:name_adm1":"Uttarakhand",
    "qs:photos":1,
    "qs:photos_1k":1,
    "qs:photos_9k":1,
    "qs:photos_9r":1,
    "qs:photos_all":1,
    "qs:photos_sr":1,
    "qs:placetype":"Suburb",
    "qs:pop_sr":"0",
    "wd:wordcount":103,
    "wof:name":"Shekhpura",
    "wof:placetype":"neighbourhood"
},
  "geometry": {"coordinates":[77.877616,29.863978],"type":"Point"}
}