{
  "type": "Feature",
  "properties": {
    "iso:country":"IN",
    "name:ben_x_preferred":[
        "\u09b6\u09c7\u0996\u09b0\u09aa\u09c1\u09b0\u09be"
    ],
    "name:bpy_x_preferred":[
        "\u09b6\u09c7\u0996\u09b0\u09aa\u09c1\u09b0\u09be"
    ],
    "name:eng_x_preferred":[
        "Shekhpura"
    ],
    "name:fra_x_preferred":[
        "Shekhpura"
    ],
    "name:guj_x_preferred":[
        "\u0ab6\u0ac7\u0a96\u0aaa\u0ac1\u0ab0\u0abe"
    ],
    "name:ita_x_preferred":[
        "Shekhpura"
    ],
    "name:msa_x_preferred":[
        "Shekhpura"
    ],
    "name:nan_x_preferred":[
        "Shekhpura"
    ],
    "name:nld_x_preferred":[
        "Shekhpura"
    ],
    "name:por_x_preferred":[
        "Shekhpura"
    ],
    "name:vie_x_preferred":[
        "Shekhpura"
    ],
    "name:zho_x_preferred":[
        "\u65af\u8d6b\u514b\u666e\u62c9"
    ],
    "qs:name":"Shekhpura",
    "qs:name_adm0":"India",
    "qs:name_adm1":"Uttarakhand",
    "qs:photos":1,
    "qs:photos_1k":1,
    "qs:photos_9k":1,
    "qs:photos_9r":1,
    "qs:photos_all":1,
    "qs:photos_sr":1,
    "qs:placetype":"Suburb",
    "qs:pop_sr":"0",
    "wd:wordcount":103,
    "wof:name":"Shekhpura",
    "wof:placetype":"neighbourhood"
},
  "geometry": {"coordinates":[77.877616,29.863978],"type":"Point"}
}