{
  "type": "Feature",
  "properties": {
    "iso:country":"IN",
    "ks:ks_name":"Mittody",
    "ks:ks_pop":21,
    "ks:ks_type":"HABITATION",
    "name:eng_x_preferred":[
        "Mittody"
    ],
    "wof:name":"Mittody",
    "wof:placetype":"locality",
    "wof:population":21
},
  "geometry": {"coordinates":[75.607471,12.576515],"type":"Point"}
}