{
  "type": "Feature",
  "properties": {
    "iso:country":"IN",
    "ks:ks_alt_nam":"MIYA TOLA",
    "ks:ks_name":"Miya Tola",
    "ks:ks_pop":314,
    "ks:ks_type":"HABITATION",
    "name:eng_x_preferred":[
        "Miya Tola"
    ],
    "wof:name":"Miya Tola",
    "wof:placetype":"locality",
    "wof:population":314
},
  "geometry": {"coordinates":[86.753649,25.490946],"type":"Point"}
}