{
  "type": "Feature",
  "properties": {
    "gn:admin1_code":"21.0",
    "gn:admin2_code":"398.0",
    "gn:asciiname":"Lanjiguda",
    "gn:country_code":"IN",
    "gn:dem":914,
    "gn:feature_class":"P",
    "gn:feature_code":"PPL",
    "gn:name":"Lanjiguda",
    "gn:population":0,
    "gn:timezone":"Asia/Kolkata",
    "iso:country":"IN",
    "ks:ks_name":"Lenjiguda",
    "ks:ks_pop":23,
    "ks:ks_type":"HABITATION",
    "name:eng_x_preferred":[
        "Lenjiguda"
    ],
    "name:eng_x_variant":[
        "Lanjiguda"
    ],
    "wof:name":"Lenjiguda",
    "wof:placetype":"locality",
    "wof:population":23
},
  "geometry": {"coordinates":[82.953655,18.560176],"type":"Point"}
}