{
  "type": "Feature",
  "properties": {
    "iso:country":"IN",
    "ks:ks_name":"S Kodihalli",
    "ks:ks_pop":53,
    "ks:ks_type":"HABITATION",
    "name:eng_x_preferred":[
        "S Kodihalli"
    ],
    "wof:name":"S Kodihalli",
    "wof:placetype":"locality",
    "wof:population":53
},
  "geometry": {"coordinates":[76.144997,13.477193],"type":"Point"}
}