{
  "type": "Feature",
  "properties": {
    "gn:admin1_code":"34.0",
    "gn:admin2_code":"209.0",
    "gn:asciiname":"Sawaldeh",
    "gn:country_code":"IN",
    "gn:dem":65,
    "gn:feature_class":"P",
    "gn:feature_code":"PPL",
    "gn:name":"Saw\u0101ldeh",
    "gn:population":0,
    "gn:timezone":"Asia/Kolkata",
    "iso:country":"IN",
    "wof:name":"Sawaldeh",
    "wof:placetype":"locality"
},
  "geometry": {"coordinates":[87.18904000000001,26.25373],"type":"Point"}
}