{
  "type": "Feature",
  "properties": {
    "iso:country":"IN",
    "ks:ks_alt_nam":"Chirakuta II",
    "ks:ks_name":"Chirakuta Ii",
    "ks:ks_pop":962,
    "ks:ks_type":"HABITATION",
    "name:eng_x_preferred":[
        "Chirakuta Ii"
    ],
    "wof:name":"Chirakuta Ii",
    "wof:placetype":"locality",
    "wof:population":962
},
  "geometry": {"coordinates":[90.29858,26.222871],"type":"Point"}
}