{
  "type": "Feature",
  "properties": {
    "gn:admin1_code":"12.0",
    "gn:admin2_code":"5.0",
    "gn:asciiname":"Birnala",
    "gn:country_code":"IN",
    "gn:dem":2650,
    "gn:feature_class":"P",
    "gn:feature_code":"PPL",
    "gn:name":"Birn\u0101la",
    "gn:population":0,
    "gn:timezone":"Asia/Kolkata",
    "iso:country":"IN",
    "wof:name":"Birnala",
    "wof:placetype":"locality"
},
  "geometry": {"coordinates":[74.41166,33.5672],"type":"Point"}
}