{
  "type": "Feature",
  "properties": {
    "gn:admin1_code":"23",
    "gn:admin2_code":"48.0",
    "gn:asciiname":"Naulas",
    "gn:country_code":"IN",
    "gn:dem":275,
    "gn:feature_class":"P",
    "gn:feature_code":"PPL",
    "gn:name":"Naul\u0101s",
    "gn:population":0,
    "gn:timezone":"Asia/Kolkata",
    "iso:country":"IN",
    "ks:ks_alt_nam":"Naul\u0101s",
    "ks:ks_name":"Naulas",
    "ks:ks_pop":786,
    "ks:ks_type":"VILLAGE",
    "ks:ks_uagg_main":0,
    "name:eng_x_preferred":[
        "Naulas"
    ],
    "name:eng_x_variant":[
        "Naul\u0101s"
    ],
    "wof:name":"Naulas",
    "wof:placetype":"neighbourhood",
    "wof:population":786
},
  "geometry": {"coordinates":[76.584844,30.538602],"type":"Point"}
}