{
  "type": "Feature",
  "properties": {
    "iso:country":"IN",
    "ks:ks_name":"Kamedi",
    "ks:ks_pop":37,
    "ks:ks_type":"HABITATION",
    "name:eng_x_preferred":[
        "Kamedi"
    ],
    "wof:name":"Kamedi",
    "wof:placetype":"locality",
    "wof:population":37
},
  "geometry": {"coordinates":[78.860238,30.119845],"type":"Point"}
}