{
  "type": "Feature",
  "properties": {
    "gn:admin1_code":"13.0",
    "gn:admin2_code":"595.0",
    "gn:asciiname":"Nettinampalli",
    "gn:country_code":"IN",
    "gn:dem":12,
    "gn:feature_class":"P",
    "gn:feature_code":"PPL",
    "gn:name":"Nettinampalli",
    "gn:population":0,
    "gn:timezone":"Asia/Kolkata",
    "iso:country":"IN",
    "wof:name":"Nettinampalli",
    "wof:placetype":"locality"
},
  "geometry": {"coordinates":[76.45465,10.18302],"type":"Point"}
}