{
  "type": "Feature",
  "properties": {
    "iso:country":"IN",
    "ks:ks_name":"Indira Nagar",
    "ks:ks_pop":368,
    "ks:ks_type":"HABITATION",
    "name:eng_x_preferred":[
        "Indira Nagar"
    ],
    "wof:name":"Indira Nagar",
    "wof:placetype":"locality",
    "wof:population":368
},
  "geometry": {"coordinates":[75.03651000000001,14.592709],"type":"Point"}
}