{
  "type": "Feature",
  "properties": {
    "iso:country":"IN",
    "ks:ks_name":"Sualmari Nayapara",
    "ks:ks_pop":93,
    "ks:ks_type":"HABITATION",
    "name:eng_x_preferred":[
        "Sualmari Nayapara"
    ],
    "wof:name":"Sualmari Nayapara",
    "wof:placetype":"locality",
    "wof:population":93
},
  "geometry": {"coordinates":[90.513583,25.982731],"type":"Point"}
}