{
  "type": "Feature",
  "properties": {
    "iso:country":"IN",
    "ks:ks_alt_nam":"Rajampalayam ADC",
    "ks:ks_name":"Rajampalayam Adc",
    "ks:ks_pop":410,
    "ks:ks_type":"HABITATION",
    "name:eng_x_preferred":[
        "Rajampalayam Adc"
    ],
    "wof:name":"Rajampalayam Adc",
    "wof:placetype":"locality",
    "wof:population":410
},
  "geometry": {"coordinates":[79.14366200000001,11.944155],"type":"Point"}
}