{
  "type": "Feature",
  "properties": {
    "gn:country":"IN",
    "gn:fcode":"PPL",
    "gn:pop":0,
    "iso:country":"IN",
    "name:eng_x_preferred":[
        "Adesar"
    ],
    "name:guj_x_preferred":[
        "\u0a86\u0aa1\u0ac7\u0ab8\u0ab0"
    ],
    "name:nld_x_preferred":[
        "Adesar"
    ],
    "name:tam_x_preferred":[
        "\u0b86\u0b9f\u0bc7\u0b9a\u0bb0\u0bcd"
    ],
    "qs:name":"Adesar",
    "qs:name_adm0":"India",
    "qs:name_adm1":"Gujarat",
    "qs:photos":5,
    "qs:photos_1k":1,
    "qs:photos_9k":1,
    "qs:photos_9r":1,
    "qs:photos_all":5,
    "qs:photos_sr":1,
    "qs:placetype":"Town",
    "qs:pop_sr":"4",
    "wd:wordcount":103,
    "wof:name":"Adesar",
    "wof:placetype":"locality",
    "wof:population":0
},
  "geometry": {"coordinates":[70.98267,23.55978],"type":"Point"}
}