{
  "type": "Feature",
  "properties": {
    "iso:country":"IN",
    "ks:ks_name":"Ganeshpur",
    "ks:ks_pop":150,
    "ks:ks_type":"HABITATION",
    "name:eng_x_preferred":[
        "Ganeshpur"
    ],
    "wof:name":"Ganeshpur",
    "wof:placetype":"locality",
    "wof:population":150
},
  "geometry": {"coordinates":[84.110801,26.592193],"type":"Point"}
}