{
  "type": "Feature",
  "properties": {
    "iso:country":"IN",
    "ks:ks_name":"No 3 Dokania Reserve",
    "ks:ks_pop":15,
    "ks:ks_type":"HABITATION",
    "ks:ks_uagg_main":0,
    "name:eng_x_preferred":[
        "No 3 Dokania Reserve"
    ],
    "wof:name":"No 3 Dokania Reserve",
    "wof:placetype":"neighbourhood",
    "wof:population":15
},
  "geometry": {"coordinates":[91.478071,26.169013],"type":"Point"}
}