{
  "type": "Feature",
  "properties": {
    "iso:country":"IN",
    "ks:ks_name":"Gouri Fanta",
    "ks:ks_pop":711,
    "ks:ks_type":"HABITATION",
    "ks:ks_uagg_main":0,
    "name:eng_x_preferred":[
        "Gouri Fanta"
    ],
    "wof:name":"Gouri Fanta",
    "wof:placetype":"neighbourhood",
    "wof:population":711
},
  "geometry": {"coordinates":[80.725897,28.559687],"type":"Point"}
}