{
  "type": "Feature",
  "properties": {
    "iso:country":"IN",
    "ks:ks_name":"Baldatanr Urf Gundlidi",
    "ks:ks_pop":563,
    "ks:ks_type":"VILLAGE",
    "name:eng_x_preferred":[
        "Baldatanr Urf Gundlidi"
    ],
    "wof:name":"Baldatanr Urf Gundlidi",
    "wof:placetype":"locality",
    "wof:population":563
},
  "geometry": {"coordinates":[87.154692,23.959485],"type":"Point"}
}