{
  "type": "Feature",
  "properties": {
    "gn:admin1_code":"3.0",
    "gn:admin2_code":"300.0",
    "gn:asciiname":"Pathakata",
    "gn:country_code":"IN",
    "gn:dem":53,
    "gn:feature_class":"P",
    "gn:feature_code":"PPL",
    "gn:name":"P\u0101thak\u0101ta",
    "gn:population":0,
    "gn:timezone":"Asia/Kolkata",
    "iso:country":"IN",
    "ks:ks_name":"Patakata",
    "ks:ks_pop":637,
    "ks:ks_type":"HABITATION",
    "name:eng_x_preferred":[
        "Patakata"
    ],
    "name:eng_x_variant":[
        "Pathakata"
    ],
    "wof:name":"Patakata",
    "wof:placetype":"locality",
    "wof:population":637
},
  "geometry": {"coordinates":[90.089725,26.52084],"type":"Point"}
}