{
  "type": "Feature",
  "properties": {
    "iso:country":"IN",
    "ks:ks_name":"Deuliapada",
    "ks:ks_pop":704,
    "ks:ks_type":"VILLAGE",
    "ks:ks_uagg_main":0,
    "name:eng_x_preferred":[
        "Deuliapada"
    ],
    "wof:name":"Deuliapada",
    "wof:placetype":"neighbourhood",
    "wof:population":704
},
  "geometry": {"coordinates":[84.51788000000001,19.241273],"type":"Point"}
}