{
  "type": "Feature",
  "properties": {
    "iso:country":"IN",
    "ks:ks_name":"Gopalbandha",
    "ks:ks_pop":150,
    "ks:ks_type":"VILLAGE",
    "ks:ks_uagg_main":0,
    "name:eng_x_preferred":[
        "Gopalbandha"
    ],
    "wof:name":"Gopalbandha",
    "wof:placetype":"neighbourhood",
    "wof:population":150
},
  "geometry": {"coordinates":[86.16560699999999,22.242265],"type":"Point"}
}