{
  "type": "Feature",
  "properties": {
    "gn:admin1_code":"19.0",
    "gn:admin2_code":"570.0",
    "gn:asciiname":"Guladamane",
    "gn:country_code":"IN",
    "gn:dem":680,
    "gn:feature_class":"P",
    "gn:feature_code":"PPL",
    "gn:name":"Guladamane",
    "gn:population":0,
    "gn:timezone":"Asia/Kolkata",
    "iso:country":"IN",
    "wof:name":"Guladamane",
    "wof:placetype":"locality"
},
  "geometry": {"coordinates":[75.52553,13.66248],"type":"Point"}
}