{
  "type": "Feature",
  "properties": {
    "gn:admin1_code":"16.0",
    "gn:admin2_code":"512.0",
    "gn:asciiname":"Saod",
    "gn:country_code":"IN",
    "gn:dem":474,
    "gn:feature_class":"P",
    "gn:feature_code":"PPL",
    "gn:name":"Saod",
    "gn:population":0,
    "gn:timezone":"Asia/Kolkata",
    "iso:country":"IN",
    "wof:name":"Saod",
    "wof:placetype":"neighbourhood"
},
  "geometry": {"coordinates":[77.06749000000001,19.73609],"type":"Point"}
}