{
  "type": "Feature",
  "properties": {
    "iso:country":"IN",
    "ks:ks_name":"Chundekadu",
    "ks:ks_pop":47,
    "ks:ks_type":"HABITATION",
    "name:eng_x_preferred":[
        "Chundekadu"
    ],
    "wof:name":"Chundekadu",
    "wof:placetype":"locality",
    "wof:population":47
},
  "geometry": {"coordinates":[75.744167,12.51],"type":"Point"}
}