{
  "type": "Feature",
  "properties": {
    "iso:country":"IN",
    "ks:ks_name":"Adsil",
    "ks:ks_pop":36,
    "ks:ks_type":"HABITATION",
    "name:eng_x_preferred":[
        "Adsil"
    ],
    "wof:name":"Adsil",
    "wof:placetype":"locality",
    "wof:population":36
},
  "geometry": {"coordinates":[86.65913,21.998608],"type":"Point"}
}