{
  "type": "Feature",
  "properties": {
    "gn:admin1_code":"21.0",
    "gn:admin2_code":"397.0",
    "gn:asciiname":"Nuagam",
    "gn:country_code":"IN",
    "gn:dem":664,
    "gn:feature_class":"P",
    "gn:feature_code":"PPL",
    "gn:name":"Nuag\u0101m",
    "gn:population":0,
    "gn:timezone":"Asia/Kolkata",
    "iso:country":"IN",
    "wof:name":"Nuagam",
    "wof:placetype":"locality"
},
  "geometry": {"coordinates":[81.99455,19.95768],"type":"Point"}
}