{
  "type": "Feature",
  "properties": {
    "iso:country":"IN",
    "ks:ks_name":"Sundara Moorthy Nagar",
    "ks:ks_pop":78,
    "ks:ks_type":"HABITATION",
    "name:eng_x_preferred":[
        "Sundara Moorthy Nagar"
    ],
    "wof:name":"Sundara Moorthy Nagar",
    "wof:placetype":"locality",
    "wof:population":78
},
  "geometry": {"coordinates":[78.640113,11.576784],"type":"Point"}
}