{
  "type": "Feature",
  "properties": {
    "iso:country":"IN",
    "ks:ks_name":"Balleruguda",
    "ks:ks_pop":74,
    "ks:ks_type":"HABITATION",
    "name:eng_x_preferred":[
        "Balleruguda"
    ],
    "wof:name":"Balleruguda",
    "wof:placetype":"locality",
    "wof:population":74
},
  "geometry": {"coordinates":[83.608864,18.874529],"type":"Point"}
}