{
  "type": "Feature",
  "properties": {
    "iso:country":"IN",
    "ks:ks_name":"Kantapal",
    "ks:ks_pop":1321,
    "ks:ks_type":"VILLAGE",
    "name:eng_x_preferred":[
        "Kantapal"
    ],
    "wof:name":"Kantapal",
    "wof:placetype":"locality",
    "wof:population":1321
},
  "geometry": {"coordinates":[87.28787800000001,21.690556],"type":"Point"}
}