{
  "type": "Feature",
  "properties": {
    "gn:admin1_code":"21.0",
    "gn:admin2_code":"372.0",
    "gn:asciiname":"Keutiberni",
    "gn:country_code":"IN",
    "gn:dem":152,
    "gn:feature_class":"P",
    "gn:feature_code":"PPL",
    "gn:name":"Keutiberni",
    "gn:population":0,
    "gn:timezone":"Asia/Kolkata",
    "iso:country":"IN",
    "wof:name":"Keutiberni",
    "wof:placetype":"locality"
},
  "geometry": {"coordinates":[84.66622,21.25106],"type":"Point"}
}