{
  "type": "Feature",
  "properties": {
    "iso:country":"IN",
    "ks:ks_name":"Dholla Gaon",
    "ks:ks_pop":493,
    "ks:ks_type":"VILLAGE",
    "ks:ks_uagg_main":0,
    "name:eng_x_preferred":[
        "Dholla Gaon"
    ],
    "wof:name":"Dholla Gaon",
    "wof:placetype":"neighbourhood",
    "wof:population":493
},
  "geometry": {"coordinates":[95.58135,27.736676],"type":"Point"}
}