{
  "type": "Feature",
  "properties": {
    "iso:country":"IN",
    "ks:ks_name":"Joganguda",
    "ks:ks_pop":145,
    "ks:ks_type":"VILLAGE",
    "name:eng_x_preferred":[
        "Joganguda"
    ],
    "wof:name":"Joganguda",
    "wof:placetype":"locality",
    "wof:population":145
},
  "geometry": {"coordinates":[80.034336,19.077749],"type":"Point"}
}