{
  "type": "Feature",
  "properties": {
    "gn:admin1_code":"11.0",
    "gn:admin2_code":"34.0",
    "gn:asciiname":"Yotarang",
    "gn:country_code":"IN",
    "gn:dem":2787,
    "gn:feature_class":"P",
    "gn:feature_code":"PPL",
    "gn:name":"Yotarang",
    "gn:population":0,
    "gn:timezone":"Asia/Kolkata",
    "iso:country":"IN",
    "wof:name":"Yotarang",
    "wof:placetype":"locality"
},
  "geometry": {"coordinates":[78.03363,31.58127],"type":"Point"}
}