{
  "type": "Feature",
  "properties": {
    "iso:country":"IN",
    "ks:ks_alt_nam":"Makoo ka purwa",
    "ks:ks_name":"Makoo Ka Purwa",
    "ks:ks_pop":142,
    "ks:ks_type":"HABITATION",
    "ks:ks_uagg_main":0,
    "name:eng_x_preferred":[
        "Makoo Ka Purwa"
    ],
    "wof:name":"Makoo Ka Purwa",
    "wof:placetype":"neighbourhood",
    "wof:population":142
},
  "geometry": {"coordinates":[79.478334,26.659457],"type":"Point"}
}