{
  "type": "Feature",
  "properties": {
    "gn:admin1_code":"11",
    "gn:admin2_code":"27.0",
    "gn:asciiname":"Giniura",
    "gn:country_code":"IN",
    "gn:dem":886,
    "gn:feature_class":"P",
    "gn:feature_code":"PPL",
    "gn:name":"Gini\u016bra",
    "gn:population":0,
    "gn:timezone":"Asia/Kolkata",
    "iso:country":"IN",
    "wof:name":"Giniura",
    "wof:placetype":"locality"
},
  "geometry": {"coordinates":[76.97251999999997,31.56724],"type":"Point"}
}