{
  "type": "Feature",
  "properties": {
    "iso:country":"IN",
    "ks:ks_name":"Baseta",
    "ks:ks_pop":335,
    "ks:ks_type":"VILLAGE",
    "name:eng_x_preferred":[
        "Baseta"
    ],
    "wof:name":"Baseta",
    "wof:placetype":"locality",
    "wof:population":335
},
  "geometry": {"coordinates":[87.06622,25.106165],"type":"Point"}
}