{
  "type": "Feature",
  "properties": {
    "iso:country":"IN",
    "ks:ks_name":"Guravwadi",
    "ks:ks_pop":275,
    "ks:ks_type":"HABITATION",
    "name:eng_x_preferred":[
        "Guravwadi"
    ],
    "wof:name":"Guravwadi",
    "wof:placetype":"locality",
    "wof:population":275
},
  "geometry": {"coordinates":[73.63583300000001,17.125],"type":"Point"}
}