{
  "type": "Feature",
  "properties": {
    "iso:country":"IN",
    "ks:ks_name":"Jhari Royan",
    "ks:ks_pop":307,
    "ks:ks_type":"VILLAGE",
    "name:eng_x_preferred":[
        "Jhari Royan"
    ],
    "wof:name":"Jhari Royan",
    "wof:placetype":"locality",
    "wof:population":307
},
  "geometry": {"coordinates":[73.238203,24.667586],"type":"Point"}
}