{
  "type": "Feature",
  "properties": {
    "gn:admin1_code":"24.0",
    "gn:admin2_code":"104.0",
    "gn:asciiname":"Kadarnagar",
    "gn:country_code":"IN",
    "gn:dem":316,
    "gn:feature_class":"P",
    "gn:feature_code":"PPL",
    "gn:name":"K\u0101darnagar",
    "gn:population":0,
    "gn:timezone":"Asia/Kolkata",
    "iso:country":"IN",
    "wof:name":"Kadarnagar",
    "wof:placetype":"locality"
},
  "geometry": {"coordinates":[76.55874,27.75957],"type":"Point"}
}