{
  "type": "Feature",
  "properties": {
    "iso:country":"IN",
    "ks:ks_alt_nam":"KASIYARPARA",
    "ks:ks_name":"Kasiyarpara",
    "ks:ks_pop":228,
    "ks:ks_type":"HABITATION",
    "name:eng_x_preferred":[
        "Kasiyarpara"
    ],
    "wof:name":"Kasiyarpara",
    "wof:placetype":"locality",
    "wof:population":228
},
  "geometry": {"coordinates":[82.313907,22.289932],"type":"Point"}
}