{
  "type": "Feature",
  "properties": {
    "gn:admin1_code":"34.0",
    "gn:admin2_code":"222.0",
    "gn:asciiname":"Koria",
    "gn:country_code":"IN",
    "gn:dem":45,
    "gn:feature_class":"P",
    "gn:feature_code":"PPL",
    "gn:name":"Koria",
    "gn:population":0,
    "gn:timezone":"Asia/Kolkata",
    "iso:country":"IN",
    "name:fin_x_preferred":[
        "Koria"
    ],
    "name:kor_x_preferred":[
        "\ucf54\ub9ac\uc544"
    ],
    "name:swe_x_preferred":[
        "Koria"
    ],
    "wof:name":"Koria",
    "wof:placetype":"locality"
},
  "geometry": {"coordinates":[86.19795000000001,25.5364],"type":"Point"}
}