{
  "type": "Feature",
  "properties": {
    "iso:country":"IN",
    "ks:ks_alt_nam":"uddasaval",
    "ks:ks_name":"Uddasaval",
    "ks:ks_pop":36,
    "ks:ks_type":"HABITATION",
    "name:eng_x_preferred":[
        "Uddasaval"
    ],
    "wof:name":"Uddasaval",
    "wof:placetype":"locality",
    "wof:population":36
},
  "geometry": {"coordinates":[74.67943099999999,14.623722],"type":"Point"}
}