{
  "type": "Feature",
  "properties": {
    "iso:country":"IN",
    "ks:ks_name":"Sitari",
    "ks:ks_pop":21,
    "ks:ks_type":"HABITATION",
    "name:eng_x_preferred":[
        "Sitari"
    ],
    "wof:name":"Sitari",
    "wof:placetype":"locality",
    "wof:population":21
},
  "geometry": {"coordinates":[91.964733,26.252486],"type":"Point"}
}