{
  "type": "Feature",
  "properties": {
    "gn:admin1_code":"35.0",
    "gn:admin2_code":"426.0",
    "gn:asciiname":"Dongargama",
    "gn:country_code":"IN",
    "gn:dem":387,
    "gn:feature_class":"P",
    "gn:feature_code":"PPL",
    "gn:name":"Dongargama",
    "gn:population":0,
    "gn:timezone":"Asia/Kolkata",
    "iso:country":"IN",
    "wof:name":"Dongargama",
    "wof:placetype":"locality"
},
  "geometry": {"coordinates":[80.32316999999998,23.9658],"type":"Point"}
}