{
  "type": "Feature",
  "properties": {
    "iso:country":"IN",
    "ks:ks_name":"Thanwa",
    "ks:ks_pop":284,
    "ks:ks_type":"HABITATION",
    "name:eng_x_preferred":[
        "Thanwa"
    ],
    "wof:name":"Thanwa",
    "wof:placetype":"locality",
    "wof:population":284
},
  "geometry": {"coordinates":[81.91516799999999,27.234316],"type":"Point"}
}