{
  "type": "Feature",
  "properties": {
    "gn:admin1_code":"12.0",
    "gn:admin2_code":"9.0",
    "gn:asciiname":"Erin",
    "gn:country_code":"IN",
    "gn:dem":1737,
    "gn:feature_class":"P",
    "gn:feature_code":"PPL",
    "gn:name":"Erin",
    "gn:population":0,
    "gn:timezone":"Asia/Kolkata",
    "iso:country":"IN",
    "name:eng_x_preferred":[
        "Erin"
    ],
    "wof:name":"Erin",
    "wof:placetype":"locality"
},
  "geometry": {"coordinates":[74.69713,34.4173],"type":"Point"}
}