{
  "type": "Feature",
  "properties": {
    "gn:admin1_code":"35.0",
    "gn:admin2_code":"457.0",
    "gn:asciiname":"Katbirkona",
    "gn:country_code":"IN",
    "gn:dem":470,
    "gn:feature_class":"P",
    "gn:feature_code":"PPL",
    "gn:name":"Katbirkon\u0101",
    "gn:population":0,
    "gn:timezone":"Asia/Kolkata",
    "iso:country":"IN",
    "ks:ks_alt_nam":"Katbirkon\u0101",
    "ks:ks_name":"Katbirkona",
    "ks:ks_type":"VILLAGE",
    "name:eng_x_preferred":[
        "Katbirkona"
    ],
    "name:eng_x_variant":[
        "Katbirkon\u0101"
    ],
    "wof:name":"Katbirkona",
    "wof:placetype":"locality"
},
  "geometry": {"coordinates":[80.693853,21.843214],"type":"Point"}
}