{
  "type": "Feature",
  "properties": {
    "iso:country":"IN",
    "ks:ks_name":"Tigiria",
    "ks:ks_pop":339,
    "ks:ks_type":"VILLAGE",
    "name:eng_x_preferred":[
        "Tigiria"
    ],
    "wof:name":"Tigiria",
    "wof:placetype":"locality",
    "wof:population":339
},
  "geometry": {"coordinates":[86.58394699999999,20.514925],"type":"Point"}
}