{
  "type": "Feature",
  "properties": {
    "iso:country":"IN",
    "ks:ks_name":"Maguria",
    "ks:ks_pop":222,
    "ks:ks_type":"VILLAGE",
    "name:eng_x_preferred":[
        "Maguria"
    ],
    "wof:name":"Maguria",
    "wof:placetype":"locality",
    "wof:population":222
},
  "geometry": {"coordinates":[87.43486799999999,22.356954],"type":"Point"}
}