{
  "type": "Feature",
  "properties": {
    "iso:country":"IN",
    "ks:ks_name":"Nadvinhalli",
    "ks:ks_type":"VILLAGE",
    "name:eng_x_preferred":[
        "Nadvinhalli"
    ],
    "wof:name":"Nadvinhalli",
    "wof:placetype":"locality"
},
  "geometry": {"coordinates":[75.087131,15.795219],"type":"Point"}
}