{
  "type": "Feature",
  "properties": {
    "iso:country":"IN",
    "ks:ks_name":"Kaljirua Alis Lutidih",
    "ks:ks_pop":1425,
    "ks:ks_type":"VILLAGE",
    "name:eng_x_preferred":[
        "Kaljirua Alis Lutidih"
    ],
    "wof:name":"Kaljirua Alis Lutidih",
    "wof:placetype":"locality",
    "wof:population":1425
},
  "geometry": {"coordinates":[84.84916,24.049441],"type":"Point"}
}