{
  "type": "Feature",
  "properties": {
    "iso:country":"IN",
    "ks:ks_name":"Kannayyapeta",
    "ks:ks_pop":22,
    "ks:ks_type":"HABITATION",
    "name:eng_x_preferred":[
        "Kannayyapeta"
    ],
    "wof:name":"Kannayyapeta",
    "wof:placetype":"locality",
    "wof:population":22
},
  "geometry": {"coordinates":[84.073522,18.645316],"type":"Point"}
}