{
  "type": "Feature",
  "properties": {
    "iso:country":"IN",
    "ks:ks_name":"Lawphulabari",
    "ks:ks_pop":1329,
    "ks:ks_type":"VILLAGE",
    "ks:ks_uagg_main":0,
    "name:eng_x_preferred":[
        "Lawphulabari"
    ],
    "wof:name":"Lawphulabari",
    "wof:placetype":"neighbourhood",
    "wof:population":1329
},
  "geometry": {"coordinates":[92.463577,26.211646],"type":"Point"}
}