{
  "type": "Feature",
  "properties": {
    "iso:country":"IN",
    "ks:ks_name":"Takarivaripalem",
    "ks:ks_pop":247,
    "ks:ks_type":"HABITATION",
    "name:eng_x_preferred":[
        "Takarivaripalem"
    ],
    "wof:name":"Takarivaripalem",
    "wof:placetype":"locality",
    "wof:population":247
},
  "geometry": {"coordinates":[79.720173,15.580783],"type":"Point"}
}