{
  "type": "Feature",
  "properties": {
    "iso:country":"IN",
    "ks:ks_name":"Gauhaniya",
    "ks:ks_pop":885,
    "ks:ks_type":"HABITATION",
    "name:eng_x_preferred":[
        "Gauhaniya"
    ],
    "wof:name":"Gauhaniya",
    "wof:placetype":"locality",
    "wof:population":885
},
  "geometry": {"coordinates":[81.77565199999999,27.609857],"type":"Point"}
}