{
  "type": "Feature",
  "properties": {
    "gn:admin1_code":"36.0",
    "gn:admin2_code":"194",
    "gn:asciiname":"Bakhsha",
    "gn:country_code":"IN",
    "gn:dem":91,
    "gn:feature_class":"P",
    "gn:feature_code":"PPL",
    "gn:name":"Bakhsha",
    "gn:population":0,
    "gn:timezone":"Asia/Kolkata",
    "iso:country":"IN",
    "wof:name":"Bakhsha",
    "wof:placetype":"locality"
},
  "geometry": {"coordinates":[82.56940999999998,25.78842],"type":"Point"}
}