{
  "type": "Feature",
  "properties": {
    "gn:admin1_code":"02",
    "gn:admin2_code":"553.0",
    "gn:asciiname":"Pasaluru",
    "gn:country_code":"IN",
    "gn:dem":366,
    "gn:feature_class":"P",
    "gn:feature_code":"PPL",
    "gn:name":"Pasal\u016bru",
    "gn:population":0,
    "gn:timezone":"Asia/Kolkata",
    "iso:country":"IN",
    "wof:name":"Pasaluru",
    "wof:placetype":"locality"
},
  "geometry": {"coordinates":[77.67107,14.64743],"type":"Point"}
}