{
  "type": "Feature",
  "properties": {
    "iso:country":"IN",
    "ks:ks_name":"Chandbasi",
    "ks:ks_pop":44,
    "ks:ks_type":"VILLAGE",
    "name:eng_x_preferred":[
        "Chandbasi"
    ],
    "wof:name":"Chandbasi",
    "wof:placetype":"locality",
    "wof:population":44
},
  "geometry": {"coordinates":[87.594731,24.987639],"type":"Point"}
}