{
  "type": "Feature",
  "properties": {
    "iso:country":"IN",
    "ks:ks_alt_nam":"RAJDEV PURWA",
    "ks:ks_name":"Rajdev Purwa",
    "ks:ks_pop":65,
    "ks:ks_type":"HABITATION",
    "ks:ks_uagg_main":0,
    "name:eng_x_preferred":[
        "Rajdev Purwa"
    ],
    "wof:name":"Rajdev Purwa",
    "wof:placetype":"neighbourhood",
    "wof:population":65
},
  "geometry": {"coordinates":[81.271565,28.103198],"type":"Point"}
}