{
  "type": "Feature",
  "properties": {
    "iso:country":"IN",
    "ks:ks_name":"Babu Tola 1",
    "ks:ks_pop":220,
    "ks:ks_type":"HABITATION",
    "name:eng_x_preferred":[
        "Babu Tola 1"
    ],
    "wof:name":"Babu Tola 1",
    "wof:placetype":"locality",
    "wof:population":220
},
  "geometry": {"coordinates":[84.276219,26.572611],"type":"Point"}
}