{
  "type": "Feature",
  "properties": {
    "iso:country":"IN",
    "ks:ks_alt_nam":"FAR YANIMAHTA",
    "ks:ks_name":"Far Yanimahta",
    "ks:ks_pop":412,
    "ks:ks_type":"HABITATION",
    "name:eng_x_preferred":[
        "Far Yanimahta"
    ],
    "wof:name":"Far Yanimahta",
    "wof:placetype":"locality",
    "wof:population":412
},
  "geometry": {"coordinates":[87.418251,25.961887],"type":"Point"}
}