{
  "type": "Feature",
  "properties": {
    "iso:country":"IN",
    "ks:ks_name":"Raul",
    "ks:ks_pop":139,
    "ks:ks_type":"VILLAGE",
    "name:eng_x_preferred":[
        "Raul"
    ],
    "wof:name":"Raul",
    "wof:placetype":"locality",
    "wof:population":139
},
  "geometry": {"coordinates":[80.208704,29.39322],"type":"Point"}
}