{
  "type": "Feature",
  "properties": {
    "iso:country":"IN",
    "ks:ks_name":"Bhatgram",
    "ks:ks_pop":1154,
    "ks:ks_type":"HABITATION",
    "name:eng_x_preferred":[
        "Bhatgram"
    ],
    "wof:name":"Bhatgram",
    "wof:placetype":"locality",
    "wof:population":1154
},
  "geometry": {"coordinates":[92.54780700000001,24.986944],"type":"Point"}
}