{
  "type": "Feature",
  "properties": {
    "iso:country":"IN",
    "ks:ks_name":"Damorfali",
    "ks:ks_pop":176,
    "ks:ks_type":"HABITATION",
    "name:eng_x_preferred":[
        "Damorfali"
    ],
    "wof:name":"Damorfali",
    "wof:placetype":"locality",
    "wof:population":176
},
  "geometry": {"coordinates":[73.63967599999999,23.490359],"type":"Point"}
}