{
  "type": "Feature",
  "properties": {
    "gn:admin1_code":"25.0",
    "gn:admin2_code":"604.0",
    "gn:asciiname":"Melvasalai",
    "gn:country_code":"IN",
    "gn:dem":29,
    "gn:feature_class":"P",
    "gn:feature_code":"PPL",
    "gn:name":"Melvasalai",
    "gn:population":0,
    "gn:timezone":"Asia/Kolkata",
    "iso:country":"IN",
    "ks:ks_alt_nam":"K\u012blvasalai",
    "ks:ks_name":"Kilvasalai",
    "ks:ks_pop":420,
    "ks:ks_type":"VILLAGE",
    "name:eng_x_preferred":[
        "Kilvasalai"
    ],
    "name:eng_x_variant":[
        "Melvasalai",
        "K\u012blvasalai"
    ],
    "wof:name":"Kilvasalai",
    "wof:placetype":"locality",
    "wof:population":420
},
  "geometry": {"coordinates":[79.924668,12.374109],"type":"Point"}
}