{
  "type": "Feature",
  "properties": {
    "gn:admin1_code":"24.0",
    "gn:admin2_code":"108.0",
    "gn:asciiname":"Ramri",
    "gn:country_code":"IN",
    "gn:dem":243,
    "gn:feature_class":"P",
    "gn:feature_code":"PPL",
    "gn:name":"R\u0101mri",
    "gn:population":0,
    "gn:timezone":"Asia/Kolkata",
    "iso:country":"IN",
    "wof:name":"Ramri",
    "wof:placetype":"locality"
},
  "geometry": {"coordinates":[76.41803,26.30786],"type":"Point"}
}