{
  "type": "Feature",
  "properties": {
    "iso:country":"IN",
    "ks:ks_name":"Kochalumoodu",
    "ks:ks_pop":789,
    "ks:ks_type":"HABITATION",
    "name:eng_x_preferred":[
        "Kochalumoodu"
    ],
    "wof:name":"Kochalumoodu",
    "wof:placetype":"locality",
    "wof:population":789
},
  "geometry": {"coordinates":[76.92337499999999,8.776317],"type":"Point"}
}