{
  "type": "Feature",
  "properties": {
    "iso:country":"IN",
    "ks:ks_name":"Kharia Bheta",
    "ks:ks_pop":1683,
    "ks:ks_type":"VILLAGE",
    "name:eng_x_preferred":[
        "Kharia Bheta"
    ],
    "wof:name":"Kharia Bheta",
    "wof:placetype":"locality",
    "wof:population":1683
},
  "geometry": {"coordinates":[95.22376300000001,27.157504],"type":"Point"}
}