{
  "type": "Feature",
  "properties": {
    "iso:country":"IN",
    "ks:ks_alt_nam":"COLONY",
    "ks:ks_name":"Colony",
    "ks:ks_pop":510,
    "ks:ks_type":"HABITATION",
    "ks:ks_uagg_main":0,
    "name:eng_x_preferred":[
        "Colony"
    ],
    "wof:name":"Colony",
    "wof:placetype":"neighbourhood",
    "wof:population":510
},
  "geometry": {"coordinates":[76.789576,9.953482],"type":"Point"}
}