{
  "type": "Feature",
  "properties": {
    "gn:admin1_code":"34.0",
    "gn:admin2_code":"223.0",
    "gn:asciiname":"Godhabani",
    "gn:country_code":"IN",
    "gn:dem":43,
    "gn:feature_class":"P",
    "gn:feature_code":"PPL",
    "gn:name":"Godhabani",
    "gn:population":0,
    "gn:timezone":"Asia/Kolkata",
    "iso:country":"IN",
    "wof:name":"Godhabani",
    "wof:placetype":"neighbourhood"
},
  "geometry": {"coordinates":[86.37893,25.65028],"type":"Point"}
}