{
  "type": "Feature",
  "properties": {
    "gn:country":"IN",
    "gn:fcode":"PPL",
    "gn:population":9994,
    "iso:country":"IN",
    "name:ben_x_preferred":[
        "\u09b2\u09cb\u09a7\u09bf\u0996\u09c7\u09a6\u09be"
    ],
    "name:bpy_x_preferred":[
        "\u09b2\u09cb\u09a7\u09bf\u0996\u09c7\u09a6\u09be"
    ],
    "name:ceb_x_preferred":[
        "Lodh\u012bkheda"
    ],
    "name:eng_x_preferred":[
        "Lodhikheda"
    ],
    "name:ita_x_preferred":[
        "Lodhikheda"
    ],
    "name:msa_x_preferred":[
        "Lodhikheda"
    ],
    "name:nan_x_preferred":[
        "Lodhikheda"
    ],
    "name:new_x_preferred":[
        "\u0932\u094b\u0927\u093f\u0916\u0947\u0926\u093e"
    ],
    "name:nld_x_preferred":[
        "Lodhikheda"
    ],
    "name:por_x_preferred":[
        "Lodhikheda"
    ],
    "name:swe_x_preferred":[
        "Lodh\u012bkheda"
    ],
    "name:und_x_variant":[
        "Lodh\u012bkhera"
    ],
    "name:vie_x_preferred":[
        "Lodhikheda"
    ],
    "name:zho_x_preferred":[
        "\u6d1b\u8fea\u51ef\u8fbe"
    ],
    "qs:name":"Lodh\u012bkhed\u0101",
    "qs:photos_9r":0,
    "qs:photos_sr":0,
    "qs:pop_sr":"5",
    "wd:wordcount":722,
    "wof:name":"Lodh\u012bkhed\u0101",
    "wof:placetype":"locality",
    "wof:population":9994
},
  "geometry": {"coordinates":[78.83333,21.58333],"type":"Point"}
}