{
  "type": "Feature",
  "properties": {
    "iso:country":"IN",
    "ks:ks_name":"Megalakoppalu",
    "ks:ks_pop":490,
    "ks:ks_type":"HABITATION",
    "name:eng_x_preferred":[
        "Megalakoppalu"
    ],
    "wof:name":"Megalakoppalu",
    "wof:placetype":"locality",
    "wof:population":490
},
  "geometry": {"coordinates":[76.530303,13.082828],"type":"Point"}
}