{
  "type": "Feature",
  "properties": {
    "iso:country":"IN",
    "ks:ks_name":"Charaparambu",
    "ks:ks_pop":940,
    "ks:ks_type":"HABITATION",
    "name:eng_x_preferred":[
        "Charaparambu"
    ],
    "wof:name":"Charaparambu",
    "wof:placetype":"locality",
    "wof:population":940
},
  "geometry": {"coordinates":[75.790536,11.651589],"type":"Point"}
}