{
  "type": "Feature",
  "properties": {
    "gn:admin1_code":"34.0",
    "gn:admin2_code":"221.0",
    "gn:asciiname":"Shahpur Barat",
    "gn:country_code":"IN",
    "gn:dem":51,
    "gn:feature_class":"P",
    "gn:feature_code":"PPL",
    "gn:name":"Sh\u0101hpur Bar\u0101t",
    "gn:population":0,
    "gn:timezone":"Asia/Kolkata",
    "iso:country":"IN",
    "name:eng_x_preferred":[
        "Sh\u0101hpur Bar\u0101t"
    ],
    "wof:name":"Shahpur Barat",
    "wof:placetype":"locality"
},
  "geometry": {"coordinates":[85.63558,25.55858],"type":"Point"}
}