{
  "type": "Feature",
  "properties": {
    "iso:country":"IN",
    "ks:ks_alt_nam":"Gp end",
    "ks:ks_name":"Gp End",
    "ks:ks_pop":425,
    "ks:ks_type":"HABITATION",
    "name:eng_x_preferred":[
        "Gp End"
    ],
    "wof:name":"Gp End",
    "wof:placetype":"locality",
    "wof:population":425
},
  "geometry": {"coordinates":[76.735437,9.958883],"type":"Point"}
}