{
  "type": "Feature",
  "properties": {
    "iso:country":"IN",
    "ks:ks_name":"Basgitia",
    "ks:ks_pop":0,
    "ks:ks_type":"VILLAGE",
    "name:eng_x_preferred":[
        "Basgitia"
    ],
    "wof:name":"Basgitia",
    "wof:placetype":"locality",
    "wof:population":0
},
  "geometry": {"coordinates":[84.10137,25.473281],"type":"Point"}
}