{
  "type": "Feature",
  "properties": {
    "iso:country":"IN",
    "ks:ks_name":"Dugila",
    "ks:ks_pop":620,
    "ks:ks_type":"VILLAGE",
    "name:eng_x_preferred":[
        "Dugila"
    ],
    "wof:name":"Dugila",
    "wof:placetype":"locality",
    "wof:population":620
},
  "geometry": {"coordinates":[84.50246199999999,23.770694],"type":"Point"}
}