{
  "type": "Feature",
  "properties": {
    "iso:country":"IN",
    "ks:ks_alt_nam":"simalgarha",
    "ks:ks_name":"Simalgarha",
    "ks:ks_pop":1625,
    "ks:ks_type":"HABITATION",
    "name:eng_x_preferred":[
        "Simalgarha"
    ],
    "wof:name":"Simalgarha",
    "wof:placetype":"locality",
    "wof:population":1625
},
  "geometry": {"coordinates":[86.88050200000001,24.075384],"type":"Point"}
}