{
  "type": "Feature",
  "properties": {
    "iso:country":"IN",
    "ks:ks_name":"Alampattipudur",
    "ks:ks_pop":804,
    "ks:ks_type":"HABITATION",
    "name:eng_x_preferred":[
        "Alampattipudur"
    ],
    "wof:name":"Alampattipudur",
    "wof:placetype":"locality",
    "wof:population":804
},
  "geometry": {"coordinates":[78.526104,10.694282],"type":"Point"}
}