{
  "type": "Feature",
  "properties": {
    "gn:admin1_code":"12.0",
    "gn:admin2_code":"7.0",
    "gn:asciiname":"Palan",
    "gn:country_code":"IN",
    "gn:dem":692,
    "gn:feature_class":"P",
    "gn:feature_code":"PPL",
    "gn:name":"Palan",
    "gn:population":0,
    "gn:timezone":"Asia/Kolkata",
    "iso:country":"IN",
    "name:ceb_x_preferred":[
        "Palan"
    ],
    "name:swe_x_preferred":[
        "Palan"
    ],
    "wof:name":"Palan",
    "wof:placetype":"locality"
},
  "geometry": {"coordinates":[75.57004999999999,32.55845],"type":"Point"}
}