{
  "type": "Feature",
  "properties": {
    "iso:country":"IN",
    "ks:ks_name":"Gadabavalasa",
    "ks:ks_pop":46,
    "ks:ks_type":"HABITATION",
    "name:eng_x_preferred":[
        "Gadabavalasa"
    ],
    "wof:name":"Gadabavalasa",
    "wof:placetype":"locality",
    "wof:population":46
},
  "geometry": {"coordinates":[83.78154600000001,18.622455],"type":"Point"}
}