{
  "type": "Feature",
  "properties": {
    "gn:admin1_code":"19.0",
    "gn:admin2_code":"577.0",
    "gn:asciiname":"Allainpura",
    "gn:country_code":"IN",
    "gn:dem":731,
    "gn:feature_class":"P",
    "gn:feature_code":"PPL",
    "gn:name":"Allainpura",
    "gn:population":0,
    "gn:timezone":"Asia/Kolkata",
    "iso:country":"IN",
    "wof:name":"Allainpura",
    "wof:placetype":"locality"
},
  "geometry": {"coordinates":[76.44379000000001,12.05725],"type":"Point"}
}