{
  "type": "Feature",
  "properties": {
    "iso:country":"IN",
    "ks:ks_name":"Choodupalaka",
    "ks:ks_pop":974,
    "ks:ks_type":"HABITATION",
    "name:eng_x_preferred":[
        "Choodupalaka"
    ],
    "wof:name":"Choodupalaka",
    "wof:placetype":"locality",
    "wof:population":974
},
  "geometry": {"coordinates":[77.08807899999999,8.506939],"type":"Point"}
}