{
  "type": "Feature",
  "properties": {
    "iso:country":"IN",
    "ks:ks_name":"Karmalawadi",
    "ks:ks_pop":70,
    "ks:ks_type":"HABITATION",
    "name:eng_x_preferred":[
        "Karmalawadi"
    ],
    "wof:name":"Karmalawadi",
    "wof:placetype":"locality",
    "wof:population":70
},
  "geometry": {"coordinates":[73.608448,15.990553],"type":"Point"}
}