{
  "type": "Feature",
  "properties": {
    "iso:country":"IN",
    "ks:ks_name":"Nawabpur",
    "ks:ks_pop":12,
    "ks:ks_type":"HABITATION",
    "name:eng_x_preferred":[
        "Nawabpur"
    ],
    "wof:name":"Nawabpur",
    "wof:placetype":"locality",
    "wof:population":12
},
  "geometry": {"coordinates":[77.796081,23.344872],"type":"Point"}
}