{
  "type": "Feature",
  "properties": {
    "gn:admin1_code":"19",
    "gn:admin2_code":"557.0",
    "gn:asciiname":"Sultanpur",
    "gn:country_code":"IN",
    "gn:dem":492,
    "gn:feature_class":"P",
    "gn:feature_code":"PPL",
    "gn:name":"Sult\u0101npur",
    "gn:population":0,
    "gn:timezone":"Asia/Kolkata",
    "iso:country":"IN",
    "ks:ks_alt_nam":"Sult\u0101npur",
    "ks:ks_name":"Sultanpur",
    "ks:ks_pop":1251,
    "ks:ks_type":"VILLAGE",
    "name:ara_x_preferred":[
        "\u0633\u0644\u0637\u0627\u0646 \u0628\u0648\u0631"
    ],
    "name:ben_bn_x_preferred":[
        "\u09b8\u09c1\u09b2\u09a4\u09be\u09a8\u09aa\u09c1\u09b0"
    ],
    "name:ben_in_x_preferred":[
        "\u09b8\u09c1\u09b2\u09a4\u09be\u09a8\u09aa\u09c1\u09b0"
    ],
    "name:ben_x_preferred":[
        "\u09b8\u09c1\u09b2\u09a4\u09be\u09a8\u09aa\u09c1\u09b0"
    ],
    "name:bih_x_preferred":[
        "\u0938\u0941\u0932\u094d\u0924\u093e\u0928\u092a\u0941\u0930"
    ],
    "name:bpy_x_preferred":[
        "\u09b8\u09c1\u09b2\u09a4\u09be\u09a8\u09aa\u09c1\u09b0"
    ],
    "name:ceb_x_preferred":[
        "Sultanpur"
    ],
    "name:deu_x_preferred":[
        "Sultanpur"
    ],
    "name:eng_x_preferred":[
        "Sultanpur"
    ],
    "name:eng_x_variant":[
        "Sult\u0101npur"
    ],
    "name:guj_x_preferred":[
        "\u0ab8\u0ac1\u0ab2\u0acd\u0aa4\u0abe\u0aa8\u0aaa\u0ac1\u0ab0"
    ],
    "name:hin_x_preferred":[
        "\u0938\u0941\u0932\u094d\u0924\u093e\u0928\u092a\u0941\u0930"
    ],
    "name:ita_x_preferred":[
        "Sultanpur"
    ],
    "name:jpn_x_preferred":[
        "\u30b9\u30eb\u30bf\u30fc\u30f3\u30d7\u30eb"
    ],
    "name:kan_x_preferred":[
        "\u0cb8\u0cc1\u0cb2\u0ccd\u0ca4\u0cbe\u0ca8\u0ccd"
    ],
    "name:mal_x_preferred":[
        "\u0d38\u0d41\u0d7d\u0d24\u0d4d\u0d24\u0d3e\u0d7b\u0d2a\u0d42\u0d7c"
    ],
    "name:mar_x_preferred":[
        "\u0938\u0941\u0932\u0924\u093e\u0928\u092a\u0942\u0930"
    ],
    "name:nld_x_preferred":[
        "Sultanpur"
    ],
    "name:pan_x_preferred":[
        "\u0a38\u0a41\u0a32\u0a24\u0a3e\u0a28\u0a2a\u0a41\u0a30"
    ],
    "name:pol_x_preferred":[
        "Sultanpur"
    ],
    "name:rus_x_preferred":[
        "\u0421\u0443\u043b\u0442\u0430\u043d\u043f\u0443\u0440"
    ],
    "name:swe_x_preferred":[
        "Sultanpur"
    ],
    "name:tam_x_preferred":[
        "\u0b9a\u0bc1\u0bb2\u0bcd\u0ba4\u0bbe\u0ba9\u0bcd\u0baa\u0bc2\u0bb0\u0bcd"
    ],
    "name:tel_x_preferred":[
        "\u0c38\u0c41\u0c32\u0c4d\u0c24\u0c3e\u0c28\u0c4d"
    ],
    "name:urd_x_preferred":[
        "\u0633\u0644\u0637\u0627\u0646 \u067e\u0648\u0631"
    ],
    "wof:name":"Sultanpur",
    "wof:placetype":"locality",
    "wof:population":1251
},
  "geometry": {"coordinates":[76.315997,16.198549],"type":"Point"}
}