{
  "type": "Feature",
  "properties": {
    "iso:country":"IN",
    "ks:ks_name":"Oraon Tola",
    "ks:ks_pop":166,
    "ks:ks_type":"HABITATION",
    "name:eng_x_preferred":[
        "Oraon Tola"
    ],
    "wof:name":"Oraon Tola",
    "wof:placetype":"locality",
    "wof:population":166
},
  "geometry": {"coordinates":[83.59224500000001,24.274724],"type":"Point"}
}