{
  "type": "Feature",
  "properties": {
    "iso:country":"IN",
    "ks:ks_alt_nam":"karamo Dhan",
    "ks:ks_name":"Karamo Dhan",
    "ks:ks_pop":235,
    "ks:ks_type":"HABITATION",
    "name:eng_x_preferred":[
        "Karamo Dhan"
    ],
    "wof:name":"Karamo Dhan",
    "wof:placetype":"locality",
    "wof:population":235
},
  "geometry": {"coordinates":[81.829025,27.407207],"type":"Point"}
}