{
  "type": "Feature",
  "properties": {
    "iso:country":"IN",
    "ks:ks_name":"Nishal Falia",
    "ks:ks_pop":277,
    "ks:ks_type":"HABITATION",
    "name:eng_x_preferred":[
        "Nishal Falia"
    ],
    "wof:name":"Nishal Falia",
    "wof:placetype":"locality",
    "wof:population":277
},
  "geometry": {"coordinates":[73.95105599999999,22.668194],"type":"Point"}
}