{
  "type": "Feature",
  "properties": {
    "iso:country":"IN",
    "ks:ks_name":"Twelth Mile Temple",
    "ks:ks_pop":1852,
    "ks:ks_type":"HABITATION",
    "name:eng_x_preferred":[
        "Twelth Mile Temple"
    ],
    "wof:name":"Twelth Mile Temple",
    "wof:placetype":"locality",
    "wof:population":1852
},
  "geometry": {"coordinates":[75.926391,11.312132],"type":"Point"}
}