{
  "type": "Feature",
  "properties": {
    "gn:admin1_code":"2.0",
    "gn:admin2_code":"553.0",
    "gn:asciiname":"Maddireddipalle",
    "gn:country_code":"IN",
    "gn:dem":701,
    "gn:feature_class":"P",
    "gn:feature_code":"PPL",
    "gn:name":"Maddireddipalle",
    "gn:population":0,
    "gn:timezone":"Asia/Kolkata",
    "iso:country":"IN",
    "wof:name":"Maddireddipalle",
    "wof:placetype":"locality"
},
  "geometry": {"coordinates":[77.78654,13.85599],"type":"Point"}
}