{
  "type": "Feature",
  "properties": {
    "iso:country":"IN",
    "ks:ks_name":"Kumpada",
    "ks:ks_pop":347,
    "ks:ks_type":"VILLAGE",
    "name:eng_x_preferred":[
        "Kumpada"
    ],
    "wof:name":"Kumpada",
    "wof:placetype":"locality",
    "wof:population":347
},
  "geometry": {"coordinates":[87.11613,21.927733],"type":"Point"}
}