{
  "type": "Feature",
  "properties": {
    "iso:country":"IN",
    "ks:ks_name":"Nandoor",
    "ks:ks_pop":1504,
    "ks:ks_type":"VILLAGE",
    "name:eng_x_preferred":[
        "Nandoor"
    ],
    "wof:name":"Nandoor",
    "wof:placetype":"locality",
    "wof:population":1504
},
  "geometry": {"coordinates":[86.521047,21.270256],"type":"Point"}
}