{
  "type": "Feature",
  "properties": {
    "iso:country":"IN",
    "ks:ks_name":"Manali",
    "ks:ks_type":"VILLAGE",
    "ks:ks_uagg_main":0,
    "name:eng_x_preferred":[
        "Manali"
    ],
    "wof:name":"Manali",
    "wof:placetype":"neighbourhood"
},
  "geometry": {"coordinates":[80.266667,13.166667],"type":"Point"}
}