{
  "type": "Feature",
  "properties": {
    "gn:admin1_code":"36",
    "gn:admin2_code":"168.0",
    "gn:asciiname":"Khandi Lodhan",
    "gn:country_code":"IN",
    "gn:dem":139,
    "gn:feature_class":"P",
    "gn:feature_code":"PPL",
    "gn:name":"Khandi Lodhan",
    "gn:population":0,
    "gn:timezone":"Asia/Kolkata",
    "iso:country":"IN",
    "wof:name":"Khandi Lodhan",
    "wof:placetype":"locality"
},
  "geometry": {"coordinates":[79.85355,25.69677],"type":"Point"}
}