{
  "type": "Feature",
  "properties": {
    "iso:country":"IN",
    "ks:ks_name":"Hanumanpura",
    "ks:ks_pop":1476,
    "ks:ks_type":"HABITATION",
    "name:eng_x_preferred":[
        "Hanumanpura"
    ],
    "wof:name":"Hanumanpura",
    "wof:placetype":"locality",
    "wof:population":1476
},
  "geometry": {"coordinates":[74.415538,23.647422],"type":"Point"}
}