{
  "type": "Feature",
  "properties": {
    "iso:country":"IN",
    "ks:ks_name":"No 5 Charavidya",
    "ks:ks_pop":2189,
    "ks:ks_type":"HABITATION",
    "name:eng_x_preferred":[
        "No 5 Charavidya"
    ],
    "wof:name":"No 5 Charavidya",
    "wof:placetype":"locality",
    "wof:population":2189
},
  "geometry": {"coordinates":[88.802038,22.320771],"type":"Point"}
}