{
  "type": "Feature",
  "properties": {
    "iso:country":"IN",
    "ks:ks_name":"Pujhariguda",
    "ks:ks_pop":1407,
    "ks:ks_type":"VILLAGE",
    "name:eng_x_preferred":[
        "Pujhariguda"
    ],
    "wof:name":"Pujhariguda",
    "wof:placetype":"locality",
    "wof:population":1407
},
  "geometry": {"coordinates":[82.69516299999999,19.538785],"type":"Point"}
}