{
  "type": "Feature",
  "properties": {
    "gn:admin1_code":"12.0",
    "gn:admin2_code":"010",
    "gn:asciiname":"Burzahom",
    "gn:country_code":"IN",
    "gn:dem":1607,
    "gn:feature_class":"P",
    "gn:feature_code":"PPL",
    "gn:name":"Burzahom",
    "gn:population":0,
    "gn:timezone":"Asia/Kolkata",
    "iso:country":"IN",
    "wof:name":"Burzahom",
    "wof:placetype":"locality"
},
  "geometry": {"coordinates":[74.87704000000002,34.16735],"type":"Point"}
}