{
  "type": "Feature",
  "properties": {
    "iso:country":"IN",
    "ks:ks_alt_nam":"amawa tola",
    "ks:ks_name":"Amawa Tola",
    "ks:ks_pop":542,
    "ks:ks_type":"HABITATION",
    "name:eng_x_preferred":[
        "Amawa Tola"
    ],
    "wof:name":"Amawa Tola",
    "wof:placetype":"locality",
    "wof:population":542
},
  "geometry": {"coordinates":[84.793494,25.382092],"type":"Point"}
}