{
  "type": "Feature",
  "properties": {
    "iso:country":"IN",
    "ks:ks_name":"Vaddeindlu",
    "ks:ks_pop":84,
    "ks:ks_type":"HABITATION",
    "name:eng_x_preferred":[
        "Vaddeindlu"
    ],
    "wof:name":"Vaddeindlu",
    "wof:placetype":"locality",
    "wof:population":84
},
  "geometry": {"coordinates":[79.250423,13.323764],"type":"Point"}
}