{
  "type": "Feature",
  "properties": {
    "iso:country":"IN",
    "ks:ks_name":"Dhanuharpara",
    "ks:ks_pop":299,
    "ks:ks_type":"HABITATION",
    "name:eng_x_preferred":[
        "Dhanuharpara"
    ],
    "wof:name":"Dhanuharpara",
    "wof:placetype":"locality",
    "wof:population":299
},
  "geometry": {"coordinates":[82.505791,22.291436],"type":"Point"}
}