{
  "type": "Feature",
  "properties": {
    "gn:admin1_code":"36",
    "gn:admin2_code":"167.0",
    "gn:asciiname":"Deoran Kalan",
    "gn:country_code":"IN",
    "gn:dem":397,
    "gn:feature_class":"P",
    "gn:feature_code":"PPL",
    "gn:name":"Deor\u0101n Kal\u0101n",
    "gn:population":0,
    "gn:timezone":"Asia/Kolkata",
    "iso:country":"IN",
    "wof:name":"Deoran Kalan",
    "wof:placetype":"locality"
},
  "geometry": {"coordinates":[78.72931,24.41053],"type":"Point"}
}