{
  "type": "Feature",
  "properties": {
    "iso:country":"IN",
    "ks:ks_name":"Mahopara",
    "ks:ks_pop":686,
    "ks:ks_type":"HABITATION",
    "name:eng_x_preferred":[
        "Mahopara"
    ],
    "wof:name":"Mahopara",
    "wof:placetype":"locality",
    "wof:population":686
},
  "geometry": {"coordinates":[80.54416500000001,27.203744],"type":"Point"}
}