{
  "type": "Feature",
  "properties": {
    "iso:country":"IN",
    "ks:ks_name":"Gandlugara",
    "ks:ks_pop":386,
    "ks:ks_type":"VILLAGE",
    "name:eng_x_preferred":[
        "Gandlugara"
    ],
    "wof:name":"Gandlugara",
    "wof:placetype":"locality",
    "wof:population":386
},
  "geometry": {"coordinates":[86.78182,23.153445],"type":"Point"}
}