{
  "type": "Feature",
  "properties": {
    "iso:country":"IN",
    "ks:ks_name":"Naddivaniguda",
    "ks:ks_pop":108,
    "ks:ks_type":"HABITATION",
    "name:eng_x_preferred":[
        "Naddivaniguda"
    ],
    "wof:name":"Naddivaniguda",
    "wof:placetype":"locality",
    "wof:population":108
},
  "geometry": {"coordinates":[79.182941,16.832623],"type":"Point"}
}