{
  "type": "Feature",
  "properties": {
    "iso:country":"IN",
    "name:ast_x_preferred":[
        "Kunnumpuram"
    ],
    "name:eng_x_preferred":[
        "Kunnumpuram"
    ],
    "name:mal_x_preferred":[
        "\u0d15\u0d41\u0d28\u0d4d\u0d28\u0d41\u0d02\u0d2a\u0d41\u0d31\u0d02"
    ],
    "name:nld_x_preferred":[
        "Kunnumpuram"
    ],
    "name:unk_x_variant":[
        "Kunnumpuram"
    ],
    "qs:gn_local":0,
    "qs:local_max":3383,
    "qs:local_sum":8346,
    "qs:localhoods":12,
    "qs:name":"Kunnumpuram",
    "qs:name_adm0":"India",
    "qs:name_adm1":"Kerala",
    "qs:name_adm2":"Ernakulam",
    "qs:name_local":"Kochi",
    "qs:photo_max":48,
    "qs:photo_sum":48,
    "qs:placetype":"Suburb",
    "qs:quad_count":1,
    "qs:woe_adm0":23424848,
    "qs:woe_adm1":2345747,
    "qs:woe_adm2":12586468,
    "qs:woe_lau":0,
    "qs:woe_local":2295423,
    "qs:woe_ver":"7.10.0",
    "wd:wordcount":89,
    "wof:lang":[
        "eng"
    ],
    "wof:name":"Kunnumpuram",
    "wof:placetype":"neighbourhood"
},
  "geometry": {"coordinates":[76.24648999999999,9.964793],"type":"Point"}
}