{
  "type": "Feature",
  "properties": {
    "iso:country":"IN",
    "name:ara_x_preferred":[
        "\u0643\u0648\u0646\u0648\u0645\u0628\u0648\u0631\u0627\u0645"
    ],
    "name:ast_x_preferred":[
        "Kunnumpuram"
    ],
    "name:ben_bn_x_preferred":[
        "\u0995\u09c1\u09a8\u09cd\u09a8\u09c1\u09ae\u09aa\u09c1\u09b0\u09ae"
    ],
    "name:ben_in_x_preferred":[
        "\u0995\u09c1\u09a8\u09cd\u09a8\u09c1\u09ae\u09aa\u09c1\u09b0\u09ae"
    ],
    "name:eng_x_preferred":[
        "Kunnumpuram"
    ],
    "name:guj_x_preferred":[
        "\u0a95\u0ac1\u0aa8\u0acd\u0aa8\u0aae\u0acd\u0aaa\u0ac1\u0ab0\u0aae"
    ],
    "name:hin_x_preferred":[
        "\u0915\u0941\u0928\u094d\u0928\u0941\u092e\u092a\u0941\u0930\u092e"
    ],
    "name:kan_x_preferred":[
        "\u0c95\u0cc1\u0ca8\u0ccd\u0ca8\u0cc1\u0cae\u0ccd"
    ],
    "name:mal_x_preferred":[
        "\u0d15\u0d41\u0d28\u0d4d\u0d28\u0d41\u0d2e\u0d4d\u0d2a\u0d41\u0d31\u0d02"
    ],
    "name:mal_x_variant":[
        "\u0d15\u0d41\u0d28\u0d4d\u0d28\u0d41\u0d02\u0d2a\u0d41\u0d31\u0d02"
    ],
    "name:mar_x_preferred":[
        "\u0915\u0941\u0928\u094d\u0928\u092e\u094d\u092a\u0941\u0930\u092e"
    ],
    "name:nld_x_preferred":[
        "Kunnumpuram"
    ],
    "name:pan_x_preferred":[
        "\u0a15\u0a41\u0a28\u0a41\u0a71\u0a2e\u0a2a\u0a41\u0a30\u0a2e"
    ],
    "name:tam_x_preferred":[
        "\u0b95\u0bc1\u0ba9\u0bcd\u0ba9\u0bc1\u0bae\u0bcd\u0baa\u0bc1\u0bb0\u0bae\u0bcd"
    ],
    "name:tel_x_preferred":[
        "\u0c15\u0c41\u0c28\u0c4d\u0c28\u0c41\u0c02\u0c2a\u0c41\u0c30\u0c02"
    ],
    "name:urd_x_preferred":[
        "\u06a9\u0646\u0651\u0648\u0645\u067e\u0648\u0631\u0645"
    ],
    "qs:gn_local":0,
    "qs:local_max":3383,
    "qs:local_sum":8346,
    "qs:localhoods":12,
    "qs:name":"Kunnumpuram",
    "qs:name_adm0":"India",
    "qs:name_adm1":"Kerala",
    "qs:name_adm2":"Ernakulam",
    "qs:name_local":"Kochi",
    "qs:photo_max":48,
    "qs:photo_sum":48,
    "qs:placetype":"Suburb",
    "qs:quad_count":1,
    "qs:woe_adm0":23424848,
    "qs:woe_adm1":2345747,
    "qs:woe_adm2":12586468,
    "qs:woe_lau":0,
    "qs:woe_local":2295423,
    "qs:woe_ver":"7.10.0",
    "wd:wordcount":89,
    "wof:lang":[
        "eng"
    ],
    "wof:name":"Kunnumpuram",
    "wof:placetype":"neighbourhood"
},
  "geometry": {"coordinates":[76.24648999999999,9.964793],"type":"Point"}
}