{
  "type": "Feature",
  "properties": {
    "iso:country":"IN",
    "ks:ks_name":"Purunaghati",
    "ks:ks_pop":1138,
    "ks:ks_type":"VILLAGE",
    "name:eng_x_preferred":[
        "Purunaghati"
    ],
    "wof:name":"Purunaghati",
    "wof:placetype":"locality",
    "wof:population":1138
},
  "geometry": {"coordinates":[86.209778,21.230197],"type":"Point"}
}