{
  "type": "Feature",
  "properties": {
    "iso:country":"IN",
    "ks:ks_name":"Dallidih",
    "ks:ks_pop":159,
    "ks:ks_type":"VILLAGE",
    "name:eng_x_preferred":[
        "Dallidih"
    ],
    "wof:name":"Dallidih",
    "wof:placetype":"locality",
    "wof:population":159
},
  "geometry": {"coordinates":[81.32538700000001,20.468053],"type":"Point"}
}