{
  "type": "Feature",
  "properties": {
    "gn:admin1_code":"28.0",
    "gn:admin2_code":"328.0",
    "gn:asciiname":"Rajadanga",
    "gn:country_code":"IN",
    "gn:dem":105,
    "gn:feature_class":"P",
    "gn:feature_code":"PPL",
    "gn:name":"Rajadanga",
    "gn:population":0,
    "gn:timezone":"Asia/Kolkata",
    "iso:country":"IN",
    "wof:name":"Rajadanga",
    "wof:placetype":"locality"
},
  "geometry": {"coordinates":[88.72180999999998,26.75227000000001],"type":"Point"}
}