{
  "type": "Feature",
  "properties": {
    "iso:country":"IN",
    "ks:ks_name":"Sangal Dhar",
    "ks:ks_pop":77,
    "ks:ks_type":"VILLAGE",
    "name:eng_x_preferred":[
        "Sangal Dhar"
    ],
    "wof:name":"Sangal Dhar",
    "wof:placetype":"locality",
    "wof:population":77
},
  "geometry": {"coordinates":[78.83135,30.167786],"type":"Point"}
}