{
  "type": "Feature",
  "properties": {
    "iso:country":"IN",
    "ks:ks_name":"Mahesh Pur",
    "ks:ks_pop":301,
    "ks:ks_type":"VILLAGE",
    "ks:ks_uagg_main":0,
    "name:eng_x_preferred":[
        "Mahesh Pur"
    ],
    "wof:name":"Mahesh Pur",
    "wof:placetype":"neighbourhood",
    "wof:population":301
},
  "geometry": {"coordinates":[87.665316,23.081051],"type":"Point"}
}