{
  "type": "Feature",
  "properties": {
    "iso:country":"IN",
    "ks:ks_name":"Bokane Patti",
    "ks:ks_pop":3921,
    "ks:ks_type":"HABITATION",
    "name:eng_x_preferred":[
        "Bokane Patti"
    ],
    "wof:name":"Bokane Patti",
    "wof:placetype":"locality",
    "wof:population":3921
},
  "geometry": {"coordinates":[85.12835699999999,26.527765],"type":"Point"}
}