{
  "type": "Feature",
  "properties": {
    "iso:country":"IN",
    "ks:ks_name":"Birsibpur",
    "ks:ks_pop":1860,
    "ks:ks_type":"VILLAGE",
    "ks:ks_uagg_main":0,
    "name:eng_x_preferred":[
        "Birsibpur"
    ],
    "wof:name":"Birsibpur",
    "wof:placetype":"locality",
    "wof:population":1860
},
  "geometry": {"coordinates":[88.049215,22.451204],"type":"Point"}
}