{
  "type": "Feature",
  "properties": {
    "iso:country":"IN",
    "ks:ks_name":"Tolawada",
    "ks:ks_pop":56,
    "ks:ks_type":"VILLAGE",
    "name:eng_x_preferred":[
        "Tolawada"
    ],
    "wof:name":"Tolawada",
    "wof:placetype":"locality",
    "wof:population":56
},
  "geometry": {"coordinates":[82.11327,18.835719],"type":"Point"}
}