{
  "type": "Feature",
  "properties": {
    "iso:country":"IN",
    "ks:ks_name":"Sanbalijore",
    "ks:ks_pop":556,
    "ks:ks_type":"VILLAGE",
    "name:eng_x_preferred":[
        "Sanbalijore"
    ],
    "wof:name":"Sanbalijore",
    "wof:placetype":"locality",
    "wof:population":556
},
  "geometry": {"coordinates":[85.066778,22.102045],"type":"Point"}
}