{
  "type": "Feature",
  "properties": {
    "gn:admin1_code":"19.0",
    "gn:admin2_code":"559.0",
    "gn:asciiname":"Burdinne",
    "gn:country_code":"IN",
    "gn:dem":327,
    "gn:feature_class":"P",
    "gn:feature_code":"PPL",
    "gn:name":"B\u016brdinne",
    "gn:population":0,
    "gn:timezone":"Asia/Kolkata",
    "iso:country":"IN",
    "name:bre_x_preferred":[
        "Burdinne"
    ],
    "name:bul_x_preferred":[
        "\u0411\u044e\u0440\u0434\u0438\u043d"
    ],
    "name:cat_x_preferred":[
        "Burdinne"
    ],
    "name:ceb_x_preferred":[
        "Burdinne"
    ],
    "name:deu_x_preferred":[
        "Burdinne"
    ],
    "name:epo_x_preferred":[
        "Burdinne"
    ],
    "name:eus_x_preferred":[
        "Burdinne"
    ],
    "name:fas_x_preferred":[
        "\u0628\u0648\u0631\u062f\u06cc\u0646"
    ],
    "name:fra_x_preferred":[
        "Burdinne"
    ],
    "name:ita_x_preferred":[
        "Burdinne"
    ],
    "name:lim_x_preferred":[
        "Burdinne"
    ],
    "name:ltz_x_preferred":[
        "Burdinne"
    ],
    "name:nld_x_preferred":[
        "Burdinne"
    ],
    "name:nor_x_preferred":[
        "Burdinne"
    ],
    "name:oci_x_preferred":[
        "Burdinne"
    ],
    "name:pol_x_preferred":[
        "Burdinne"
    ],
    "name:por_x_preferred":[
        "Burdinne"
    ],
    "name:ron_x_preferred":[
        "Burdinne"
    ],
    "name:rus_x_preferred":[
        "\u0411\u044e\u0440\u0434\u0438\u043d\u043d"
    ],
    "name:slk_x_preferred":[
        "Burdinne"
    ],
    "name:spa_x_preferred":[
        "Burdinne"
    ],
    "name:swe_x_preferred":[
        "Burdinne"
    ],
    "name:vie_x_preferred":[
        "Burdinne"
    ],
    "name:vol_x_preferred":[
        "Burdinne"
    ],
    "name:war_x_preferred":[
        "Burdinne"
    ],
    "name:zho_x_preferred":[
        "\u6bd4\u5c14\u8fea\u8bb7"
    ],
    "wof:name":"Burdinne",
    "wof:placetype":"locality"
},
  "geometry": {"coordinates":[77.44667,15.96408],"type":"Point"}
}