{
  "type": "Feature",
  "properties": {
    "gn:admin1_code":"34.0",
    "gn:admin2_code":"235.0",
    "gn:asciiname":"Makhdumpur",
    "gn:country_code":"IN",
    "gn:dem":101,
    "gn:feature_class":"P",
    "gn:feature_code":"PPL",
    "gn:name":"Makhd\u016bmpur",
    "gn:population":0,
    "gn:timezone":"Asia/Kolkata",
    "iso:country":"IN",
    "ks:ks_alt_nam":"Makhd\u016bmpur",
    "ks:ks_name":"Makhdumpur",
    "ks:ks_pop":64,
    "ks:ks_type":"VILLAGE",
    "name:ben_x_preferred":[
        "\u09ae\u09be\u0996\u09a6\u09c1\u09ae\u09aa\u09c1\u09b0"
    ],
    "name:bpy_x_preferred":[
        "\u09ae\u09be\u0996\u09a6\u09c1\u09ae\u09aa\u09c1\u09b0"
    ],
    "name:eng_x_preferred":[
        "Makhdumpur"
    ],
    "name:eng_x_variant":[
        "Makhd\u016bmpur"
    ],
    "name:ita_x_preferred":[
        "Makhdumpur"
    ],
    "name:msa_x_preferred":[
        "Makhdumpur"
    ],
    "name:new_x_preferred":[
        "\u092e\u0916\u094d\u0926\u0941\u092e\u094d\u092a\u0941\u0930"
    ],
    "name:nld_x_preferred":[
        "Makhdumpur"
    ],
    "name:ori_x_preferred":[
        "\u0b2e\u0b16\u0b21\u0b2e\u0b2a\u0b41\u0b30"
    ],
    "name:por_x_preferred":[
        "Makhdumpur"
    ],
    "name:spa_x_preferred":[
        "Makhdumpur"
    ],
    "name:urd_x_preferred":[
        "\u0645\u062e\u062f\u0648\u0645 \u067e\u0648\u0631"
    ],
    "name:vie_x_preferred":[
        "Makhdumpur"
    ],
    "name:zho_x_preferred":[
        "\u9a6c\u514b\u675c\u59c6\u666e\u5c14"
    ],
    "wof:name":"Makhdumpur",
    "wof:placetype":"locality",
    "wof:population":64
},
  "geometry": {"coordinates":[84.452156,24.812585],"type":"Point"}
}