{
  "type": "Feature",
  "properties": {
    "iso:country":"IN",
    "ks:ks_name":"Mahmadpur",
    "ks:ks_pop":236,
    "ks:ks_type":"VILLAGE",
    "name:eng_x_preferred":[
        "Mahmadpur"
    ],
    "wof:name":"Mahmadpur",
    "wof:placetype":"locality",
    "wof:population":236
},
  "geometry": {"coordinates":[82.840633,25.713487],"type":"Point"}
}