{
  "type": "Feature",
  "properties": {
    "gn:admin1_code":"36.0",
    "gn:admin2_code":"163.0",
    "gn:asciiname":"Purwa Ramdin",
    "gn:country_code":"IN",
    "gn:dem":136,
    "gn:feature_class":"P",
    "gn:feature_code":"PPL",
    "gn:name":"Purwa R\u0101md\u012bn",
    "gn:population":0,
    "gn:timezone":"Asia/Kolkata",
    "iso:country":"IN",
    "wof:name":"Purwa Ramdin",
    "wof:placetype":"neighbourhood"
},
  "geometry": {"coordinates":[79.92102,26.59175],"type":"Point"}
}