{
  "type": "Feature",
  "properties": {
    "iso:country":"IN",
    "ks:ks_name":"Gandhisagar",
    "ks:ks_pop":653,
    "ks:ks_type":"HABITATION",
    "name:eng_x_preferred":[
        "Gandhisagar"
    ],
    "wof:name":"Gandhisagar",
    "wof:placetype":"locality",
    "wof:population":653
},
  "geometry": {"coordinates":[72.747725,27.293519],"type":"Point"}
}