{
  "type": "Feature",
  "properties": {
    "iso:country":"IN",
    "ks:ks_alt_nam":"M\u0101vuttu",
    "ks:ks_name":"Mavuttu",
    "ks:ks_type":"VILLAGE",
    "name:eng_x_preferred":[
        "Mavuttu"
    ],
    "name:eng_x_variant":[
        "M\u0101vuttu"
    ],
    "wof:name":"Mavuttu",
    "wof:placetype":"locality"
},
  "geometry": {"coordinates":[78.328644,11.843189],"type":"Point"}
}