{
  "type": "Feature",
  "properties": {
    "gn:admin1_code":"13.0",
    "gn:admin2_code":"600.0",
    "gn:asciiname":"Peringalavadakkekunnukara",
    "gn:country_code":"IN",
    "gn:dem":10,
    "gn:feature_class":"P",
    "gn:feature_code":"PPL",
    "gn:name":"Pering\u0101lavadakkekunnukara",
    "gn:population":0,
    "gn:timezone":"Asia/Kolkata",
    "iso:country":"IN",
    "wof:name":"Peringalavadakkekunnukara",
    "wof:placetype":"locality"
},
  "geometry": {"coordinates":[76.60777,8.99938],"type":"Point"}
}