{
  "type": "Feature",
  "properties": {
    "iso:country":"IN",
    "ks:ks_name":"Bargadia Khera",
    "ks:ks_pop":552,
    "ks:ks_type":"HABITATION",
    "name:eng_x_preferred":[
        "Bargadia Khera"
    ],
    "wof:name":"Bargadia Khera",
    "wof:placetype":"locality",
    "wof:population":552
},
  "geometry": {"coordinates":[80.46198,27.143326],"type":"Point"}
}