{
  "type": "Feature",
  "properties": {
    "gn:admin1_code":"19.0",
    "gn:admin2_code":"570.0",
    "gn:asciiname":"Krishnarajapet",
    "gn:country_code":"IN",
    "gn:dem":1046,
    "gn:feature_class":"P",
    "gn:feature_code":"PPL",
    "gn:name":"Krishnar\u0101japet",
    "gn:population":0,
    "gn:timezone":"Asia/Kolkata",
    "iso:country":"IN",
    "wof:name":"Krishnarajapet",
    "wof:placetype":"locality"
},
  "geometry": {"coordinates":[75.7615,13.23555],"type":"Point"}
}