{
  "type": "Feature",
  "properties": {
    "iso:country":"IN",
    "ks:ks_alt_nam":"morsaibari",
    "ks:ks_name":"Morsaibari",
    "ks:ks_pop":127,
    "ks:ks_type":"HABITATION",
    "name:eng_x_preferred":[
        "Morsaibari"
    ],
    "wof:name":"Morsaibari",
    "wof:placetype":"locality",
    "wof:population":127
},
  "geometry": {"coordinates":[93.18883700000001,25.280689],"type":"Point"}
}