{
  "type": "Feature",
  "properties": {
    "iso:country":"IN",
    "ks:ks_name":"No.1 Amlakhi",
    "ks:ks_pop":343,
    "ks:ks_type":"VILLAGE",
    "ks:ks_uagg_main":0,
    "name:eng_x_preferred":[
        "No.1 Amlakhi"
    ],
    "wof:name":"No.1 Amlakhi",
    "wof:placetype":"neighbourhood",
    "wof:population":343
},
  "geometry": {"coordinates":[94.66101,27.423625],"type":"Point"}
}