{
  "type": "Feature",
  "properties": {
    "gn:admin1_code":"35.0",
    "gn:admin2_code":"465.0",
    "gn:asciiname":"Dipaki Chowki",
    "gn:country_code":"IN",
    "gn:dem":305,
    "gn:feature_class":"P",
    "gn:feature_code":"PPL",
    "gn:name":"Dip\u00e1ki Chowki",
    "gn:population":0,
    "gn:timezone":"Asia/Kolkata",
    "iso:country":"IN",
    "ks:ks_name":"Dipa Ki Choki",
    "ks:ks_pop":847,
    "ks:ks_type":"VILLAGE",
    "name:eng_x_preferred":[
        "Dipa Ki Choki"
    ],
    "name:eng_x_variant":[
        "Dipaki Chowki"
    ],
    "wof:name":"Dipa Ki Choki",
    "wof:placetype":"locality",
    "wof:population":847
},
  "geometry": {"coordinates":[74.31335300000001,22.322022],"type":"Point"}
}