{
  "type": "Feature",
  "properties": {
    "gn:admin1_code":"35.0",
    "gn:admin2_code":"465.0",
    "gn:asciiname":"Dipaki Chowki",
    "gn:country_code":"IN",
    "gn:dem":305,
    "gn:feature_class":"P",
    "gn:feature_code":"PPL",
    "gn:name":"Dip\u00e1ki Chowki",
    "gn:population":0,
    "gn:timezone":"Asia/Kolkata",
    "iso:country":"IN",
    "wof:name":"Dipaki Chowki",
    "wof:placetype":"locality"
},
  "geometry": {"coordinates":[74.31773000000003,22.31526],"type":"Point"}
}