{
  "type": "Feature",
  "properties": {
    "iso:country":"IN",
    "ks:ks_name":"Kholadi",
    "ks:ks_pop":793,
    "ks:ks_type":"VILLAGE",
    "name:eng_x_preferred":[
        "Kholadi"
    ],
    "wof:name":"Kholadi",
    "wof:placetype":"locality",
    "wof:population":793
},
  "geometry": {"coordinates":[81.758743,22.996356],"type":"Point"}
}