{
  "type": "Feature",
  "properties": {
    "iso:country":"IN",
    "ks:ks_name":"Bishain Tola",
    "ks:ks_pop":934,
    "ks:ks_type":"HABITATION",
    "name:eng_x_preferred":[
        "Bishain Tola"
    ],
    "wof:name":"Bishain Tola",
    "wof:placetype":"locality",
    "wof:population":934
},
  "geometry": {"coordinates":[84.646287,26.258077],"type":"Point"}
}