{
  "type": "Feature",
  "properties": {
    "iso:country":"IN",
    "ks:ks_name":"Manjharpara",
    "ks:ks_pop":363,
    "ks:ks_type":"HABITATION",
    "name:eng_x_preferred":[
        "Manjharpara"
    ],
    "wof:name":"Manjharpara",
    "wof:placetype":"locality",
    "wof:population":363
},
  "geometry": {"coordinates":[81.35973,18.644612],"type":"Point"}
}