{
  "type": "Feature",
  "properties": {
    "iso:country":"IN",
    "ks:ks_name":"Kowaphala Habi",
    "ks:ks_pop":733,
    "ks:ks_type":"VILLAGE",
    "ks:ks_uagg_main":0,
    "name:eng_x_preferred":[
        "Kowaphala Habi"
    ],
    "wof:name":"Kowaphala Habi",
    "wof:placetype":"neighbourhood",
    "wof:population":733
},
  "geometry": {"coordinates":[94.580246,27.451164],"type":"Point"}
}