{
  "type": "Feature",
  "properties": {
    "gn:admin1_code":"16.0",
    "gn:admin2_code":"520",
    "gn:asciiname":"Bhonang",
    "gn:country_code":"IN",
    "gn:dem":22,
    "gn:feature_class":"P",
    "gn:feature_code":"PPL",
    "gn:name":"Bhonang",
    "gn:population":0,
    "gn:timezone":"Asia/Kolkata",
    "iso:country":"IN",
    "ks:ks_name":"Bhonang",
    "ks:ks_pop":802,
    "ks:ks_type":"VILLAGE",
    "name:eng_x_preferred":[
        "Bhonang"
    ],
    "wof:name":"Bhonang",
    "wof:placetype":"locality",
    "wof:population":802
},
  "geometry": {"coordinates":[72.979664,18.539626],"type":"Point"}
}