{
  "type": "Feature",
  "properties": {
    "iso:country":"IN",
    "ks:ks_name":"Kavnalpadi",
    "ks:ks_pop":229,
    "ks:ks_type":"HABITATION",
    "ks:ks_uagg_main":0,
    "name:eng_x_preferred":[
        "Kavnalpadi"
    ],
    "wof:name":"Kavnalpadi",
    "wof:placetype":"neighbourhood",
    "wof:population":229
},
  "geometry": {"coordinates":[76.83281700000001,9.270429],"type":"Point"}
}