{
  "type": "Feature",
  "properties": {
    "iso:country":"IN",
    "ks:ks_name":"S R Palle",
    "ks:ks_pop":132,
    "ks:ks_type":"HABITATION",
    "name:eng_x_preferred":[
        "S R Palle"
    ],
    "wof:name":"S R Palle",
    "wof:placetype":"locality",
    "wof:population":132
},
  "geometry": {"coordinates":[78.231334,13.736185],"type":"Point"}
}