{
  "type": "Feature",
  "properties": {
    "iso:country":"IN",
    "ks:ks_name":"Darginpurwa",
    "ks:ks_pop":221,
    "ks:ks_type":"HABITATION",
    "name:eng_x_preferred":[
        "Darginpurwa"
    ],
    "wof:name":"Darginpurwa",
    "wof:placetype":"locality",
    "wof:population":221
},
  "geometry": {"coordinates":[81.01122100000001,27.728754],"type":"Point"}
}