{
  "type": "Feature",
  "properties": {
    "gn:admin1_code":"36",
    "gn:admin2_code":"134.0",
    "gn:asciiname":"Mankua",
    "gn:country_code":"IN",
    "gn:dem":233,
    "gn:feature_class":"P",
    "gn:feature_code":"PPL",
    "gn:name":"Mankua",
    "gn:population":0,
    "gn:timezone":"Asia/Kolkata",
    "iso:country":"IN",
    "wof:name":"Mankua",
    "wof:placetype":"locality"
},
  "geometry": {"coordinates":[78.49356999999998,29.23972],"type":"Point"}
}