{
  "type": "Feature",
  "properties": {
    "iso:country":"IN",
    "ks:ks_name":"Andhar Taila",
    "ks:ks_pop":29,
    "ks:ks_type":"HABITATION",
    "name:eng_x_preferred":[
        "Andhar Taila"
    ],
    "wof:name":"Andhar Taila",
    "wof:placetype":"locality",
    "wof:population":29
},
  "geometry": {"coordinates":[84.75851,20.344834],"type":"Point"}
}