{
  "type": "Feature",
  "properties": {
    "gn:admin1_code":"39.0",
    "gn:admin2_code":"060",
    "gn:asciiname":"Motipur",
    "gn:country_code":"IN",
    "gn:dem":587,
    "gn:feature_class":"P",
    "gn:feature_code":"PPL",
    "gn:name":"Mot\u012bpur",
    "gn:population":0,
    "gn:timezone":"Asia/Kolkata",
    "iso:country":"IN",
    "wof:name":"Motipur",
    "wof:placetype":"locality"
},
  "geometry": {"coordinates":[77.93315,30.32606],"type":"Point"}
}