{
  "type": "Feature",
  "properties": {
    "gn:admin1_code":"11",
    "gn:admin2_code":"23.0",
    "gn:asciiname":"Melam",
    "gn:country_code":"IN",
    "gn:dem":2557,
    "gn:feature_class":"P",
    "gn:feature_code":"PPL",
    "gn:name":"Mel\u0101m",
    "gn:population":0,
    "gn:timezone":"Asia/Kolkata",
    "iso:country":"IN",
    "name:vie_x_preferred":[
        "Melam"
    ],
    "wof:name":"Melam",
    "wof:placetype":"locality"
},
  "geometry": {"coordinates":[76.55285000000001,32.30795],"type":"Point"}
}