{
  "type": "Feature",
  "properties": {
    "iso:country":"IN",
    "ks:ks_name":"Gandhia Pather",
    "ks:ks_pop":717,
    "ks:ks_type":"VILLAGE",
    "name:eng_x_preferred":[
        "Gandhia Pather"
    ],
    "wof:name":"Gandhia Pather",
    "wof:placetype":"locality",
    "wof:population":717
},
  "geometry": {"coordinates":[91.84370199999999,26.28107],"type":"Point"}
}