{
  "type": "Feature",
  "properties": {
    "gn:admin1_code":"35.0",
    "gn:admin2_code":"440.0",
    "gn:asciiname":"Bairya",
    "gn:country_code":"IN",
    "gn:dem":204,
    "gn:feature_class":"P",
    "gn:feature_code":"PPL",
    "gn:name":"Bairya",
    "gn:population":0,
    "gn:timezone":"Asia/Kolkata",
    "iso:country":"IN",
    "wof:name":"Bairya",
    "wof:placetype":"locality"
},
  "geometry": {"coordinates":[75.59486,22.25093],"type":"Point"}
}