{
  "type": "Feature",
  "properties": {
    "iso:country":"IN",
    "ks:ks_name":"Badamanadhara",
    "ks:ks_pop":569,
    "ks:ks_type":"VILLAGE",
    "name:eng_x_preferred":[
        "Badamanadhara"
    ],
    "wof:name":"Badamanadhara",
    "wof:placetype":"locality",
    "wof:population":569
},
  "geometry": {"coordinates":[83.198244,19.079571],"type":"Point"}
}