{
  "type": "Feature",
  "properties": {
    "iso:country":"IN",
    "ks:ks_name":"Nundurubadi",
    "ks:ks_pop":11,
    "ks:ks_type":"VILLAGE",
    "name:eng_x_preferred":[
        "Nundurubadi"
    ],
    "wof:name":"Nundurubadi",
    "wof:placetype":"locality",
    "wof:population":11
},
  "geometry": {"coordinates":[83.55332300000001,19.835125],"type":"Point"}
}