{
  "type": "Feature",
  "properties": {
    "gn:admin1_code":"35.0",
    "gn:admin2_code":"457.0",
    "gn:asciiname":"Nata",
    "gn:country_code":"IN",
    "gn:dem":528,
    "gn:feature_class":"P",
    "gn:feature_code":"PPL",
    "gn:name":"N\u0101ta",
    "gn:population":0,
    "gn:timezone":"Asia/Kolkata",
    "iso:country":"IN",
    "name:ceb_x_preferred":[
        "Nata"
    ],
    "name:deu_x_preferred":[
        "Nata"
    ],
    "name:ell_x_preferred":[
        "\u039d\u03ac\u03c4\u03b1"
    ],
    "name:fra_x_preferred":[
        "Nata"
    ],
    "name:glg_x_preferred":[
        "Nata"
    ],
    "name:ita_x_preferred":[
        "Nata"
    ],
    "name:por_x_preferred":[
        "Nata"
    ],
    "name:spa_x_preferred":[
        "Nata"
    ],
    "name:swe_x_preferred":[
        "Nata"
    ],
    "wof:name":"Nata",
    "wof:placetype":"locality"
},
  "geometry": {"coordinates":[80.31905999999999,22.2944],"type":"Point"}
}