{
  "type": "Feature",
  "properties": {
    "gn:admin1_code":"35.0",
    "gn:admin2_code":"457.0",
    "gn:asciiname":"Nata",
    "gn:country_code":"IN",
    "gn:dem":528,
    "gn:feature_class":"P",
    "gn:feature_code":"PPL",
    "gn:name":"N\u0101ta",
    "gn:population":0,
    "gn:timezone":"Asia/Kolkata",
    "iso:country":"IN",
    "ks:ks_alt_nam":"N\u0101ta",
    "ks:ks_name":"Nata",
    "ks:ks_pop":719,
    "ks:ks_type":"VILLAGE",
    "name:ara_x_preferred":[
        "\u0646\u0627\u062a\u0627"
    ],
    "name:ben_x_preferred":[
        "\u09a8\u09be\u09a4\u09be"
    ],
    "name:ceb_x_preferred":[
        "Nata"
    ],
    "name:deu_x_preferred":[
        "Nata"
    ],
    "name:ell_x_preferred":[
        "\u039d\u03ac\u03c4\u03b1"
    ],
    "name:eng_x_preferred":[
        "Nata"
    ],
    "name:eng_x_variant":[
        "N\u0101ta"
    ],
    "name:fra_x_preferred":[
        "Nata"
    ],
    "name:glg_x_preferred":[
        "Nata"
    ],
    "name:heb_x_preferred":[
        "\u05e0\u05d8\u05d4"
    ],
    "name:hin_x_preferred":[
        "\u0928\u093e\u0924\u093e"
    ],
    "name:ita_x_preferred":[
        "Nata"
    ],
    "name:kor_x_preferred":[
        "\ub098\ud0c0"
    ],
    "name:por_x_preferred":[
        "Nata"
    ],
    "name:spa_x_preferred":[
        "Nata"
    ],
    "name:swe_x_preferred":[
        "Nata"
    ],
    "name:tur_x_preferred":[
        "Nata"
    ],
    "name:ukr_x_preferred":[
        "\u041d\u0430\u0442\u0430"
    ],
    "name:urd_x_preferred":[
        "\u0646\u06cc\u0679\u0627"
    ],
    "wof:name":"Nata",
    "wof:placetype":"locality",
    "wof:population":719
},
  "geometry": {"coordinates":[80.325311,22.29869],"type":"Point"}
}