{
  "type": "Feature",
  "properties": {
    "gn:admin1_code":"36",
    "gn:admin2_code":"185.0",
    "gn:asciiname":"Kandhauli",
    "gn:country_code":"IN",
    "gn:dem":86,
    "gn:feature_class":"P",
    "gn:feature_code":"PPL",
    "gn:name":"Kandhauli",
    "gn:population":0,
    "gn:timezone":"Asia/Kolkata",
    "iso:country":"IN",
    "name:ara_x_preferred":[
        "\u0643\u0627\u0646\u062f\u0648\u064a\u0644\u064a"
    ],
    "name:ben_bn_x_preferred":[
        "\u0995\u09be\u09a8\u09cd\u09a7\u09be\u0989\u09b2\u09bf"
    ],
    "name:ben_in_x_preferred":[
        "\u0995\u09be\u09a8\u09cd\u09a7\u09be\u0989\u09b2\u09bf"
    ],
    "name:guj_x_preferred":[
        "\u0a95\u0abe\u0a82\u0aa7\u0acc\u0ab2\u0ac0"
    ],
    "name:hin_x_preferred":[
        "\u0915\u0902\u0927\u094c\u0932\u0940"
    ],
    "name:kan_x_preferred":[
        "\u0c95\u0c82\u0ca7\u0ccc\u0cb2\u0cbf"
    ],
    "name:mal_x_preferred":[
        "\u0d15\u0d3e\u0d28\u0d4d\u0d27\u0d57\u0d32\u0d3f"
    ],
    "name:mar_x_preferred":[
        "\u0915\u0902\u0927\u094c\u0932\u0940"
    ],
    "name:pan_x_preferred":[
        "\u0a15\u0a70\u0a27\u0a4c\u0a32\u0a40"
    ],
    "name:tam_x_preferred":[
        "\u0b95\u0ba9\u0bcd\u0b9f\u0bcc\u0bb2\u0bbf"
    ],
    "name:tel_x_preferred":[
        "\u0c15\u0c02\u0c27\u0c4c\u0c32\u0c3f"
    ],
    "name:urd_x_preferred":[
        "\u06a9\u0646\u062f\u06be\u0648\u0644\u06cc"
    ],
    "wof:name":"Kandhauli",
    "wof:placetype":"locality"
},
  "geometry": {"coordinates":[82.6938,26.6994],"type":"Point"}
}