{
  "type": "Feature",
  "properties": {
    "gn:admin1_code":"36",
    "gn:admin2_code":"196.0",
    "gn:asciiname":"Bhujwa",
    "gn:country_code":"IN",
    "gn:dem":82,
    "gn:feature_class":"P",
    "gn:feature_code":"PPL",
    "gn:name":"Bhujwa",
    "gn:population":0,
    "gn:timezone":"Asia/Kolkata",
    "iso:country":"IN",
    "ks:ks_name":"Bhujwa",
    "ks:ks_type":"VILLAGE",
    "name:eng_x_preferred":[
        "Bhujwa"
    ],
    "wof:name":"Bhujwa",
    "wof:placetype":"locality"
},
  "geometry": {"coordinates":[83.077568,25.281605],"type":"Point"}
}