{
  "type": "Feature",
  "properties": {
    "iso:country":"IN",
    "ks:ks_name":"Lang Terang Rongpi Gaon",
    "ks:ks_pop":209,
    "ks:ks_type":"HABITATION",
    "name:eng_x_preferred":[
        "Lang Terang Rongpi Gaon"
    ],
    "wof:name":"Lang Terang Rongpi Gaon",
    "wof:placetype":"locality",
    "wof:population":209
},
  "geometry": {"coordinates":[93.122404,26.139254],"type":"Point"}
}