{
  "type": "Feature",
  "properties": {
    "iso:country":"IN",
    "ks:ks_name":"Kumhiya",
    "ks:ks_pop":1273,
    "ks:ks_type":"VILLAGE",
    "name:eng_x_preferred":[
        "Kumhiya"
    ],
    "wof:name":"Kumhiya",
    "wof:placetype":"locality",
    "wof:population":1273
},
  "geometry": {"coordinates":[82.570516,23.885351],"type":"Point"}
}