{
  "type": "Feature",
  "properties": {
    "gn:admin1_code":"36.0",
    "gn:admin2_code":"171.0",
    "gn:asciiname":"Laureha Muafi",
    "gn:country_code":"IN",
    "gn:dem":130,
    "gn:feature_class":"P",
    "gn:feature_code":"PPL",
    "gn:name":"Laureha Mu\u0101fi",
    "gn:population":0,
    "gn:timezone":"Asia/Kolkata",
    "iso:country":"IN",
    "ks:ks_alt_nam":"Laureha Mu\u0101fi",
    "ks:ks_name":"Laureha Muafi",
    "ks:ks_pop":882,
    "ks:ks_type":"VILLAGE",
    "name:eng_x_preferred":[
        "Laureha Muafi"
    ],
    "name:eng_x_variant":[
        "Laureha Mu\u0101fi"
    ],
    "wof:name":"Laureha Muafi",
    "wof:placetype":"locality",
    "wof:population":882
},
  "geometry": {"coordinates":[81.125607,25.191438],"type":"Point"}
}