{
  "type": "Feature",
  "properties": {
    "gn:admin1_code":"36",
    "gn:admin2_code":"134.0",
    "gn:asciiname":"Chamraula",
    "gn:country_code":"IN",
    "gn:dem":268,
    "gn:feature_class":"P",
    "gn:feature_code":"PPL",
    "gn:name":"Chamraula",
    "gn:population":0,
    "gn:timezone":"Asia/Kolkata",
    "iso:country":"IN",
    "ks:ks_name":"Chamraula",
    "ks:ks_pop":1086,
    "ks:ks_type":"VILLAGE",
    "name:eng_x_preferred":[
        "Chamraula"
    ],
    "wof:name":"Chamraula",
    "wof:placetype":"locality",
    "wof:population":1086
},
  "geometry": {"coordinates":[78.356347,29.582529],"type":"Point"}
}