{
  "type": "Feature",
  "properties": {
    "iso:country":"IN",
    "ks:ks_alt_nam":"Burhi\u0101dih",
    "ks:ks_name":"Burhiadih",
    "ks:ks_pop":1865,
    "ks:ks_type":"VILLAGE",
    "ks:ks_uagg_main":0,
    "name:eng_x_preferred":[
        "Burhiadih"
    ],
    "name:eng_x_variant":[
        "Burhi\u0101dih"
    ],
    "wof:name":"Burhiadih",
    "wof:placetype":"locality",
    "wof:population":1865
},
  "geometry": {"coordinates":[86.32556700000001,24.154538],"type":"Point"}
}