{
  "type": "Feature",
  "properties": {
    "gn:admin1_code":"37",
    "gn:admin2_code":"413.0",
    "gn:asciiname":"Chhindkharak",
    "gn:country_code":"IN",
    "gn:dem":467,
    "gn:feature_class":"P",
    "gn:feature_code":"PPL",
    "gn:name":"Chhindkharak",
    "gn:population":0,
    "gn:timezone":"Asia/Kolkata",
    "iso:country":"IN",
    "wof:name":"Chhindkharak",
    "wof:placetype":"locality"
},
  "geometry": {"coordinates":[81.6913,20.17106],"type":"Point"}
}