{
  "type": "Feature",
  "properties": {
    "iso:country":"IN",
    "ks:ks_name":"Nimyathanda",
    "ks:ks_pop":493,
    "ks:ks_type":"HABITATION",
    "ks:ks_uagg_main":0,
    "name:eng_x_preferred":[
        "Nimyathanda"
    ],
    "wof:name":"Nimyathanda",
    "wof:placetype":"neighbourhood",
    "wof:population":493
},
  "geometry": {"coordinates":[79.801686,16.796826],"type":"Point"}
}