{
  "type": "Feature",
  "properties": {
    "iso:country":"IN",
    "ks:ks_name":"Karemegaladoddi",
    "ks:ks_pop":100,
    "ks:ks_type":"HABITATION",
    "name:eng_x_preferred":[
        "Karemegaladoddi"
    ],
    "wof:name":"Karemegaladoddi",
    "wof:placetype":"locality",
    "wof:population":100
},
  "geometry": {"coordinates":[77.56964600000001,12.40814],"type":"Point"}
}