{
  "type": "Feature",
  "properties": {
    "iso:country":"IN",
    "ks:ks_name":"Mankulipada",
    "ks:ks_pop":194,
    "ks:ks_type":"HABITATION",
    "name:eng_x_preferred":[
        "Mankulipada"
    ],
    "wof:name":"Mankulipada",
    "wof:placetype":"locality",
    "wof:population":194
},
  "geometry": {"coordinates":[73.00829,19.655912],"type":"Point"}
}