{
  "type": "Feature",
  "properties": {
    "iso:country":"IN",
    "ks:ks_name":"Samudrapur Jalpai",
    "ks:ks_pop":0,
    "ks:ks_type":"VILLAGE",
    "name:eng_x_preferred":[
        "Samudrapur Jalpai"
    ],
    "wof:name":"Samudrapur Jalpai",
    "wof:placetype":"locality",
    "wof:population":0
},
  "geometry": {"coordinates":[87.717074,21.699661],"type":"Point"}
}