{
  "type": "Feature",
  "properties": {
    "iso:country":"IN",
    "ks:ks_name":"Hatigarh",
    "ks:ks_pop":1152,
    "ks:ks_type":"VILLAGE",
    "name:eng_x_preferred":[
        "Hatigarh"
    ],
    "wof:name":"Hatigarh",
    "wof:placetype":"locality",
    "wof:population":1152
},
  "geometry": {"coordinates":[92.64566000000001,26.258363],"type":"Point"}
}