{
  "type": "Feature",
  "properties": {
    "iso:country":"IN",
    "ks:ks_alt_nam":"Gurav pada",
    "ks:ks_name":"Gurav Pada",
    "ks:ks_pop":300,
    "ks:ks_type":"HABITATION",
    "name:eng_x_preferred":[
        "Gurav Pada"
    ],
    "wof:name":"Gurav Pada",
    "wof:placetype":"locality",
    "wof:population":300
},
  "geometry": {"coordinates":[73.075571,19.804224],"type":"Point"}
}