{
  "type": "Feature",
  "properties": {
    "gn:admin1_code":"35",
    "gn:admin2_code":"426.0",
    "gn:asciiname":"Talgaon",
    "gn:country_code":"IN",
    "gn:dem":344,
    "gn:feature_class":"P",
    "gn:feature_code":"PPL",
    "gn:name":"T\u0101lgaon",
    "gn:population":0,
    "gn:timezone":"Asia/Kolkata",
    "iso:country":"IN",
    "ks:ks_alt_nam":"T\u0101lgaon",
    "ks:ks_name":"Talgaon",
    "ks:ks_pop":153,
    "ks:ks_type":"VILLAGE",
    "name:eng_x_preferred":[
        "Talgaon"
    ],
    "name:eng_x_variant":[
        "T\u0101lgaon"
    ],
    "wof:name":"Talgaon",
    "wof:placetype":"locality",
    "wof:population":153
},
  "geometry": {"coordinates":[80.148906,24.162383],"type":"Point"}
}