{
  "type": "Feature",
  "properties": {
    "iso:country":"IN",
    "ks:ks_name":"Bherbheri",
    "ks:ks_pop":494,
    "ks:ks_type":"HABITATION",
    "name:eng_x_preferred":[
        "Bherbheri"
    ],
    "wof:name":"Bherbheri",
    "wof:placetype":"locality",
    "wof:population":494
},
  "geometry": {"coordinates":[91.394964,26.000759],"type":"Point"}
}