{
  "type": "Feature",
  "properties": {
    "iso:country":"IN",
    "ks:ks_name":"Seegaron Ka Khera",
    "ks:ks_pop":368,
    "ks:ks_type":"VILLAGE",
    "name:eng_x_preferred":[
        "Seegaron Ka Khera"
    ],
    "wof:name":"Seegaron Ka Khera",
    "wof:placetype":"locality",
    "wof:population":368
},
  "geometry": {"coordinates":[74.730903,23.658058],"type":"Point"}
}