{
  "type": "Feature",
  "properties": {
    "gn:admin1_code":"36.0",
    "gn:admin2_code":"189.0",
    "gn:asciiname":"Pakri",
    "gn:country_code":"IN",
    "gn:dem":82,
    "gn:feature_class":"P",
    "gn:feature_code":"PPL",
    "gn:name":"Pakri",
    "gn:population":0,
    "gn:timezone":"Asia/Kolkata",
    "iso:country":"IN",
    "ks:ks_name":"Pakari",
    "ks:ks_pop":231,
    "ks:ks_type":"VILLAGE",
    "ks:ks_uagg_main":0,
    "name:eng_x_preferred":[
        "Pakari"
    ],
    "name:est_x_preferred":[
        "Pakri"
    ],
    "name:lav_x_preferred":[
        "Pakri"
    ],
    "wof:name":"Pakari",
    "wof:placetype":"neighbourhood",
    "wof:population":231
},
  "geometry": {"coordinates":[83.93454300000001,26.753681],"type":"Point"}
}