{
  "type": "Feature",
  "properties": {
    "iso:country":"IN",
    "ks:ks_name":"Uttar Deeh",
    "ks:ks_pop":150,
    "ks:ks_type":"HABITATION",
    "name:eng_x_preferred":[
        "Uttar Deeh"
    ],
    "wof:name":"Uttar Deeh",
    "wof:placetype":"locality",
    "wof:population":150
},
  "geometry": {"coordinates":[83.236447,27.344947],"type":"Point"}
}