{
  "type": "Feature",
  "properties": {
    "iso:country":"IN",
    "ks:ks_name":"Dighiabeda",
    "ks:ks_pop":356,
    "ks:ks_type":"VILLAGE",
    "name:eng_x_preferred":[
        "Dighiabeda"
    ],
    "wof:name":"Dighiabeda",
    "wof:placetype":"locality",
    "wof:population":356
},
  "geometry": {"coordinates":[86.010524,22.28169],"type":"Point"}
}