{
  "type": "Feature",
  "properties": {
    "iso:country":"IN",
    "ks:ks_alt_nam":"nalavadevasti",
    "ks:ks_name":"Nalavadevasti",
    "ks:ks_pop":180,
    "ks:ks_type":"HABITATION",
    "ks:ks_uagg_main":0,
    "name:eng_x_preferred":[
        "Nalavadevasti"
    ],
    "wof:name":"Nalavadevasti",
    "wof:placetype":"neighbourhood",
    "wof:population":180
},
  "geometry": {"coordinates":[74.292,18.2286],"type":"Point"}
}