{
  "type": "Feature",
  "properties": {
    "gn:admin1_code":"40",
    "gn:admin2_code":"539.0",
    "gn:asciiname":"Shettigudani",
    "gn:country_code":"IN",
    "gn:dem":168,
    "gn:feature_class":"P",
    "gn:feature_code":"PPL",
    "gn:name":"Shettigudani",
    "gn:population":0,
    "gn:timezone":"Asia/Kolkata",
    "iso:country":"IN",
    "name:eng_x_preferred":[
        "Shettigudani"
    ],
    "wof:name":"Shettigudani",
    "wof:placetype":"locality"
},
  "geometry": {"coordinates":[79.78964000000001,17.26173],"type":"Point"}
}