{
  "type": "Feature",
  "properties": {
    "iso:country":"IN",
    "ks:ks_name":"Suralu",
    "ks:ks_pop":312,
    "ks:ks_type":"HABITATION",
    "name:eng_x_preferred":[
        "Suralu"
    ],
    "wof:name":"Suralu",
    "wof:placetype":"locality",
    "wof:population":312
},
  "geometry": {"coordinates":[74.854097,13.449665],"type":"Point"}
}