{
  "type": "Feature",
  "properties": {
    "gn:admin1_code":"36",
    "gn:admin2_code":"173.0",
    "gn:asciiname":"Pura Bodhram",
    "gn:country_code":"IN",
    "gn:dem":94,
    "gn:feature_class":"P",
    "gn:feature_code":"PPL",
    "gn:name":"Pura Bodhr\u0101m",
    "gn:population":0,
    "gn:timezone":"Asia/Kolkata",
    "iso:country":"IN",
    "ks:ks_alt_nam":"Pura Bodhr\u0101m",
    "ks:ks_name":"Pura Bodhram",
    "ks:ks_type":"VILLAGE",
    "ks:ks_uagg_main":0,
    "name:eng_x_preferred":[
        "Pura Bodhram"
    ],
    "name:eng_x_variant":[
        "Pura Bodhr\u0101m"
    ],
    "wof:name":"Pura Bodhram",
    "wof:placetype":"neighbourhood"
},
  "geometry": {"coordinates":[82.17822700000001,25.905239],"type":"Point"}
}