{
  "type": "Feature",
  "properties": {
    "gn:admin1_code":"35",
    "gn:admin2_code":"423.0",
    "gn:asciiname":"Kathmari",
    "gn:country_code":"IN",
    "gn:dem":470,
    "gn:feature_class":"P",
    "gn:feature_code":"PPL",
    "gn:name":"Kathm\u0101ri",
    "gn:population":0,
    "gn:timezone":"Asia/Kolkata",
    "iso:country":"IN",
    "ks:ks_alt_nam":"Kathm\u0101ri",
    "ks:ks_name":"Kathmari",
    "ks:ks_type":"VILLAGE",
    "name:eng_x_preferred":[
        "Kathmari"
    ],
    "name:eng_x_variant":[
        "Kathm\u0101ri"
    ],
    "wof:name":"Kathmari",
    "wof:placetype":"locality"
},
  "geometry": {"coordinates":[77.682661,25.473406],"type":"Point"}
}