{
  "type": "Feature",
  "properties": {
    "iso:country":"IN",
    "ks:ks_name":"Dhanumandal",
    "ks:ks_pop":1373,
    "ks:ks_type":"VILLAGE",
    "ks:ks_uagg_main":0,
    "name:eng_x_preferred":[
        "Dhanumandal"
    ],
    "wof:name":"Dhanumandal",
    "wof:placetype":"neighbourhood",
    "wof:population":1373
},
  "geometry": {"coordinates":[88.23605000000001,22.104867],"type":"Point"}
}