{
  "type": "Feature",
  "properties": {
    "iso:country":"IN",
    "ks:ks_name":"Chalkewadi",
    "ks:ks_pop":97,
    "ks:ks_type":"HABITATION",
    "name:eng_x_preferred":[
        "Chalkewadi"
    ],
    "wof:name":"Chalkewadi",
    "wof:placetype":"locality",
    "wof:population":97
},
  "geometry": {"coordinates":[73.638136,16.881649],"type":"Point"}
}