{
  "type": "Feature",
  "properties": {
    "iso:country":"IN",
    "ks:ks_name":"27 PTP",
    "ks:ks_pop":14,
    "ks:ks_type":"VILLAGE",
    "name:eng_x_preferred":[
        "27 PTP"
    ],
    "wof:name":"27 PTP",
    "wof:placetype":"locality",
    "wof:population":14
},
  "geometry": {"coordinates":[74.214997,29.818789],"type":"Point"}
}