{
  "type": "Feature",
  "properties": {
    "iso:country":"IN",
    "ks:ks_alt_nam":"Kotha likkidi",
    "ks:ks_name":"Kotha Likkidi",
    "ks:ks_pop":811,
    "ks:ks_type":"HABITATION",
    "name:eng_x_preferred":[
        "Kotha Likkidi"
    ],
    "wof:name":"Kotha Likkidi",
    "wof:placetype":"locality",
    "wof:population":811
},
  "geometry": {"coordinates":[83.67010500000001,19.01548],"type":"Point"}
}