{
  "type": "Feature",
  "properties": {
    "gn:admin1_code":"35.0",
    "gn:admin2_code":"432",
    "gn:asciiname":"Bharbharia",
    "gn:country_code":"IN",
    "gn:dem":513,
    "gn:feature_class":"P",
    "gn:feature_code":"PPL",
    "gn:name":"Bharbharia",
    "gn:population":0,
    "gn:timezone":"Asia/Kolkata",
    "iso:country":"IN",
    "wof:name":"Bharbharia",
    "wof:placetype":"locality"
},
  "geometry": {"coordinates":[74.86615,24.5267],"type":"Point"}
}