{
  "type": "Feature",
  "properties": {
    "iso:country":"IN",
    "ks:ks_name":"Pura Gher",
    "ks:ks_pop":245,
    "ks:ks_type":"HABITATION",
    "ks:ks_uagg_main":0,
    "name:eng_x_preferred":[
        "Pura Gher"
    ],
    "wof:name":"Pura Gher",
    "wof:placetype":"neighbourhood",
    "wof:population":245
},
  "geometry": {"coordinates":[78.23384900000001,26.964661],"type":"Point"}
}