{
  "type": "Feature",
  "properties": {
    "iso:country":"IN",
    "ks:ks_name":"Gobindaganj",
    "ks:ks_pop":983,
    "ks:ks_type":"HABITATION",
    "name:eng_x_preferred":[
        "Gobindaganj"
    ],
    "wof:name":"Gobindaganj",
    "wof:placetype":"locality",
    "wof:population":983
},
  "geometry": {"coordinates":[92.425308,24.616948],"type":"Point"}
}