{
  "type": "Feature",
  "properties": {
    "iso:country":"IN",
    "ks:ks_name":"Sidamguda",
    "ks:ks_pop":101,
    "ks:ks_type":"HABITATION",
    "name:eng_x_preferred":[
        "Sidamguda"
    ],
    "wof:name":"Sidamguda",
    "wof:placetype":"locality",
    "wof:population":101
},
  "geometry": {"coordinates":[79.014169,19.685206],"type":"Point"}
}