{
  "type": "Feature",
  "properties": {
    "iso:country":"IN",
    "ks:ks_name":"Pimpalwadi",
    "ks:ks_pop":229,
    "ks:ks_type":"HABITATION",
    "name:eng_x_preferred":[
        "Pimpalwadi"
    ],
    "wof:name":"Pimpalwadi",
    "wof:placetype":"locality",
    "wof:population":229
},
  "geometry": {"coordinates":[73.727777,16.527824],"type":"Point"}
}