{
  "type": "Feature",
  "properties": {
    "iso:country":"IN",
    "ks:ks_alt_nam":"Medha khurd",
    "ks:ks_name":"Medha Khurd",
    "ks:ks_pop":184,
    "ks:ks_type":"HABITATION",
    "name:eng_x_preferred":[
        "Medha Khurd"
    ],
    "wof:name":"Medha Khurd",
    "wof:placetype":"locality",
    "wof:population":184
},
  "geometry": {"coordinates":[80.45356099999999,20.209522],"type":"Point"}
}