{
  "type": "Feature",
  "properties": {
    "iso:country":"IN",
    "ks:ks_name":"P Singa Rai",
    "ks:ks_pop":122,
    "ks:ks_type":"HABITATION",
    "name:eng_x_preferred":[
        "P Singa Rai"
    ],
    "wof:name":"P Singa Rai",
    "wof:placetype":"locality",
    "wof:population":122
},
  "geometry": {"coordinates":[81.316412,26.345492],"type":"Point"}
}