{
  "type": "Feature",
  "properties": {
    "iso:country":"IN",
    "ks:ks_name":"Das Ka Guda",
    "ks:ks_pop":1443,
    "ks:ks_type":"VILLAGE",
    "name:eng_x_preferred":[
        "Das Ka Guda"
    ],
    "wof:name":"Das Ka Guda",
    "wof:placetype":"locality",
    "wof:population":1443
},
  "geometry": {"coordinates":[74.414117,24.131878],"type":"Point"}
}