{
  "type": "Feature",
  "properties": {
    "iso:country":"IN",
    "ks:ks_name":"Ramaianapalya",
    "ks:ks_pop":184,
    "ks:ks_type":"HABITATION",
    "name:eng_x_preferred":[
        "Ramaianapalya"
    ],
    "wof:name":"Ramaianapalya",
    "wof:placetype":"locality",
    "wof:population":184
},
  "geometry": {"coordinates":[77.22233,13.340479],"type":"Point"}
}