{
  "type": "Feature",
  "properties": {
    "gn:admin1_code":"34.0",
    "gn:admin2_code":"234.0",
    "gn:asciiname":"Kukurha",
    "gn:country_code":"IN",
    "gn:dem":81,
    "gn:feature_class":"P",
    "gn:feature_code":"PPL",
    "gn:name":"Kukurha",
    "gn:population":0,
    "gn:timezone":"Asia/Kolkata",
    "iso:country":"IN",
    "name:tam_x_preferred":[
        "\u0b95\u0bc1\u0b95\u0bcd\u0b95\u0bc1\u0bb0\u0bcd\u0b95\u0bbe"
    ],
    "wof:name":"Kukurha",
    "wof:placetype":"locality"
},
  "geometry": {"coordinates":[84.15153000000002,25.3491],"type":"Point"}
}