{
  "type": "Feature",
  "properties": {
    "gn:admin1_code":"19.0",
    "gn:admin2_code":"566.0",
    "gn:asciiname":"Nellikatte",
    "gn:country_code":"IN",
    "gn:dem":782,
    "gn:feature_class":"P",
    "gn:feature_code":"PPL",
    "gn:name":"Nellikatte",
    "gn:population":0,
    "gn:timezone":"Asia/Kolkata",
    "iso:country":"IN",
    "wof:name":"Nellikatte",
    "wof:placetype":"locality"
},
  "geometry": {"coordinates":[76.3017,14.06059],"type":"Point"}
}