{
  "type": "Feature",
  "properties": {
    "iso:country":"IN",
    "ks:ks_name":"Simada Falia",
    "ks:ks_pop":697,
    "ks:ks_type":"HABITATION",
    "name:eng_x_preferred":[
        "Simada Falia"
    ],
    "wof:name":"Simada Falia",
    "wof:placetype":"locality",
    "wof:population":697
},
  "geometry": {"coordinates":[74.002917,22.759944],"type":"Point"}
}