{
  "type": "Feature",
  "properties": {
    "gn:admin1_code":"19.0",
    "gn:admin2_code":"582.0",
    "gn:asciiname":"Marinainipalli",
    "gn:country_code":"IN",
    "gn:dem":854,
    "gn:feature_class":"P",
    "gn:feature_code":"PPL",
    "gn:name":"Marin\u0101inipalli",
    "gn:population":0,
    "gn:timezone":"Asia/Kolkata",
    "iso:country":"IN",
    "wof:name":"Marinainipalli",
    "wof:placetype":"locality"
},
  "geometry": {"coordinates":[78.14551999999998,13.41503],"type":"Point"}
}