{
  "type": "Feature",
  "properties": {
    "iso:country":"IN",
    "ks:ks_name":"Rai Dhunwa",
    "ks:ks_pop":430,
    "ks:ks_type":"HABITATION",
    "ks:ks_uagg_main":0,
    "name:eng_x_preferred":[
        "Rai Dhunwa"
    ],
    "wof:name":"Rai Dhunwa",
    "wof:placetype":"neighbourhood",
    "wof:population":430
},
  "geometry": {"coordinates":[84.516814,26.845093],"type":"Point"}
}