{
  "type": "Feature",
  "properties": {
    "iso:country":"IN",
    "ks:ks_name":"Matar",
    "ks:ks_pop":316,
    "ks:ks_type":"VILLAGE",
    "name:eng_x_preferred":[
        "Matar"
    ],
    "wof:name":"Matar",
    "wof:placetype":"locality",
    "wof:population":316
},
  "geometry": {"coordinates":[74.70251500000001,23.451685],"type":"Point"}
}