{
  "type": "Feature",
  "properties": {
    "iso:country":"IN",
    "ks:ks_name":"Langkhal Punji",
    "ks:ks_pop":289,
    "ks:ks_type":"HABITATION",
    "name:eng_x_preferred":[
        "Langkhal Punji"
    ],
    "wof:name":"Langkhal Punji",
    "wof:placetype":"locality",
    "wof:population":289
},
  "geometry": {"coordinates":[93.100173,24.944228],"type":"Point"}
}