{
  "type": "Feature",
  "properties": {
    "iso:country":"IN",
    "ks:ks_name":"Delwapurwa",
    "ks:ks_pop":414,
    "ks:ks_type":"HABITATION",
    "name:eng_x_preferred":[
        "Delwapurwa"
    ],
    "wof:name":"Delwapurwa",
    "wof:placetype":"locality",
    "wof:population":414
},
  "geometry": {"coordinates":[81.03685,28.081107],"type":"Point"}
}