{
  "type": "Feature",
  "properties": {
    "gn:admin1_code":"35.0",
    "gn:admin2_code":"427",
    "gn:asciiname":"Maraiya",
    "gn:country_code":"IN",
    "gn:dem":430,
    "gn:feature_class":"P",
    "gn:feature_code":"PPL",
    "gn:name":"Maraiya",
    "gn:population":0,
    "gn:timezone":"Asia/Kolkata",
    "iso:country":"IN",
    "wof:name":"Maraiya",
    "wof:placetype":"locality"
},
  "geometry": {"coordinates":[78.48401,24.20636],"type":"Point"}
}