{
  "type": "Feature",
  "properties": {
    "gn:admin1_code":"37",
    "gn:admin2_code":"406.0",
    "gn:asciiname":"Lata",
    "gn:country_code":"IN",
    "gn:dem":613,
    "gn:feature_class":"P",
    "gn:feature_code":"PPL",
    "gn:name":"L\u0101ta",
    "gn:population":0,
    "gn:timezone":"Asia/Kolkata",
    "iso:country":"IN",
    "ks:ks_alt_nam":"L\u0101ta",
    "ks:ks_name":"Lata",
    "ks:ks_pop":1337,
    "ks:ks_type":"VILLAGE",
    "name:eng_x_preferred":[
        "Lata"
    ],
    "name:eng_x_variant":[
        "L\u0101ta"
    ],
    "name:heb_x_preferred":[
        "\u05dc\u05d0\u05d8\u05d4"
    ],
    "name:hun_x_preferred":[
        "Lata"
    ],
    "wof:name":"Lata",
    "wof:placetype":"locality",
    "wof:population":1337
},
  "geometry": {"coordinates":[82.018441,22.696917],"type":"Point"}
}