{
  "type": "Feature",
  "properties": {
    "iso:country":"IN",
    "ks:ks_name":"Manihar Goth",
    "ks:ks_pop":3067,
    "ks:ks_type":"VILLAGE",
    "ks:ks_uagg_main":0,
    "name:eng_x_preferred":[
        "Manihar Goth"
    ],
    "wof:name":"Manihar Goth",
    "wof:placetype":"neighbourhood",
    "wof:population":3067
},
  "geometry": {"coordinates":[80.109478,29.056818],"type":"Point"}
}