{
  "type": "Feature",
  "properties": {
    "gn:admin1_code":"36.0",
    "gn:admin2_code":"170.0",
    "gn:asciiname":"Palhri",
    "gn:country_code":"IN",
    "gn:dem":155,
    "gn:feature_class":"P",
    "gn:feature_code":"PPL",
    "gn:name":"Palhri",
    "gn:population":0,
    "gn:timezone":"Asia/Kolkata",
    "iso:country":"IN",
    "wof:name":"Palhri",
    "wof:placetype":"locality"
},
  "geometry": {"coordinates":[80.60051999999997,25.0829],"type":"Point"}
}