{
  "type": "Feature",
  "properties": {
    "gn:admin1_code":"36.0",
    "gn:admin2_code":"165",
    "gn:asciiname":"Bohra",
    "gn:country_code":"IN",
    "gn:dem":152,
    "gn:feature_class":"P",
    "gn:feature_code":"PPL",
    "gn:name":"Bohr\u0101",
    "gn:population":0,
    "gn:timezone":"Asia/Kolkata",
    "iso:country":"IN",
    "name:ara_x_preferred":[
        "\u0628\u0647\u0631\u0629"
    ],
    "name:snd_x_preferred":[
        "\u0628\u0648\u06be\u0631\u0627"
    ],
    "name:spa_x_preferred":[
        "Bohra"
    ],
    "name:urd_x_preferred":[
        "\u0628\u0648\u06c1\u0631\u06c1"
    ],
    "wof:name":"Bohra",
    "wof:placetype":"locality"
},
  "geometry": {"coordinates":[79.23674,26.25027],"type":"Point"}
}