{
  "type": "Feature",
  "properties": {
    "iso:country":"IN",
    "ks:ks_name":"Choutra",
    "ks:ks_pop":224,
    "ks:ks_type":"VILLAGE",
    "name:eng_x_preferred":[
        "Choutra"
    ],
    "wof:name":"Choutra",
    "wof:placetype":"locality",
    "wof:population":224
},
  "geometry": {"coordinates":[77.00416800000001,23.993878],"type":"Point"}
}