{
  "type": "Feature",
  "properties": {
    "iso:country":"IN",
    "ks:ks_name":"Pipariya Kheda",
    "ks:ks_pop":0,
    "ks:ks_type":"VILLAGE",
    "name:eng_x_preferred":[
        "Pipariya Kheda"
    ],
    "wof:name":"Pipariya Kheda",
    "wof:placetype":"locality",
    "wof:population":0
},
  "geometry": {"coordinates":[77.55867600000001,24.477578],"type":"Point"}
}