{
  "type": "Feature",
  "properties": {
    "iso:country":"IN",
    "ks:ks_name":"Maharaj Pur",
    "ks:ks_pop":336,
    "ks:ks_type":"HABITATION",
    "name:eng_x_preferred":[
        "Maharaj Pur"
    ],
    "wof:name":"Maharaj Pur",
    "wof:placetype":"locality",
    "wof:population":336
},
  "geometry": {"coordinates":[85.96868000000001,26.379345],"type":"Point"}
}