{
  "type": "Feature",
  "properties": {
    "iso:country":"IN",
    "ks:ks_name":"Kukuralima",
    "ks:ks_pop":53,
    "ks:ks_type":"VILLAGE",
    "name:eng_x_preferred":[
        "Kukuralima"
    ],
    "wof:name":"Kukuralima",
    "wof:placetype":"locality",
    "wof:population":53
},
  "geometry": {"coordinates":[83.49675999999999,19.701668],"type":"Point"}
}