{
  "type": "Feature",
  "properties": {
    "gn:admin1_code":"19.0",
    "gn:admin2_code":"572",
    "gn:asciiname":"Kengri",
    "gn:country_code":"IN",
    "gn:dem":799,
    "gn:feature_class":"P",
    "gn:feature_code":"PPL",
    "gn:name":"Kengri",
    "gn:population":0,
    "gn:timezone":"Asia/Kolkata",
    "iso:country":"IN",
    "name:ben_x_preferred":[
        "\u0995\u09c7\u09a8\u0997\u09c7\u09b0\u09bf"
    ],
    "name:bpy_x_preferred":[
        "\u0995\u09c7\u09a8\u0997\u09c7\u09b0\u09bf"
    ],
    "name:ceb_x_preferred":[
        "Kengeri"
    ],
    "name:ita_x_preferred":[
        "Kengeri"
    ],
    "name:kan_x_preferred":[
        "\u0c95\u0cc6\u0c82\u0c97\u0cc7\u0cb0\u0cbf"
    ],
    "name:mlg_x_preferred":[
        "Kengeri"
    ],
    "name:msa_x_preferred":[
        "Kengeri"
    ],
    "name:new_x_preferred":[
        "\u0915\u0947\u0928\u094d\u0917\u0947\u0930\u0940"
    ],
    "name:nld_x_preferred":[
        "Kengeri"
    ],
    "name:por_x_preferred":[
        "Kengeri"
    ],
    "name:spa_x_preferred":[
        "Kengeri"
    ],
    "name:swe_x_preferred":[
        "Kengeri"
    ],
    "name:und_x_variant":[
        "Kengri"
    ],
    "name:vie_x_preferred":[
        "Kengeri"
    ],
    "name:zho_x_preferred":[
        "\u80af\u683c\u57c3\u91cc"
    ],
    "wof:name":"Kengri",
    "wof:placetype":"locality"
},
  "geometry": {"coordinates":[77.48269999999999,12.91218],"type":"Point"}
}