{
  "type": "Feature",
  "properties": {
    "gn:admin1_code":"19.0",
    "gn:admin2_code":"572",
    "gn:asciiname":"Kengri",
    "gn:country_code":"IN",
    "gn:dem":799,
    "gn:feature_class":"P",
    "gn:feature_code":"PPL",
    "gn:name":"Kengri",
    "gn:population":0,
    "gn:timezone":"Asia/Kolkata",
    "iso:country":"IN",
    "name:und_x_variant":[
        "Kengeri",
        "Kengri"
    ],
    "wof:name":"Kengri",
    "wof:placetype":"locality"
},
  "geometry": {"coordinates":[77.48269999999999,12.91218],"type":"Point"}
}