{
  "type": "Feature",
  "properties": {
    "iso:country":"IN",
    "ks:ks_name":"Boudhawadi",
    "ks:ks_pop":8,
    "ks:ks_type":"HABITATION",
    "name:eng_x_preferred":[
        "Boudhawadi"
    ],
    "wof:name":"Boudhawadi",
    "wof:placetype":"locality",
    "wof:population":8
},
  "geometry": {"coordinates":[73.47643100000001,17.837986],"type":"Point"}
}