{
  "type": "Feature",
  "properties": {
    "gn:admin1_code":"12.0",
    "gn:admin2_code":"005",
    "gn:asciiname":"Sakhi Pir",
    "gn:country_code":"IN",
    "gn:dem":926,
    "gn:feature_class":"P",
    "gn:feature_code":"PPL",
    "gn:name":"Sakhi P\u012br",
    "gn:population":0,
    "gn:timezone":"Asia/Kolkata",
    "iso:country":"IN",
    "wof:name":"Sakhi Pir",
    "wof:placetype":"locality"
},
  "geometry": {"coordinates":[74.11754999999999,33.62154],"type":"Point"}
}