{
  "type": "Feature",
  "properties": {
    "iso:country":"IN",
    "ks:ks_name":"Birangatoli",
    "ks:ks_pop":131,
    "ks:ks_type":"HABITATION",
    "name:eng_x_preferred":[
        "Birangatoli"
    ],
    "wof:name":"Birangatoli",
    "wof:placetype":"locality",
    "wof:population":131
},
  "geometry": {"coordinates":[84.49301699999999,22.498527],"type":"Point"}
}