{
  "type": "Feature",
  "properties": {
    "iso:country":"IN",
    "ks:ks_name":"Mahsewa",
    "ks:ks_pop":763,
    "ks:ks_type":"HABITATION",
    "name:eng_x_preferred":[
        "Mahsewa"
    ],
    "wof:name":"Mahsewa",
    "wof:placetype":"locality",
    "wof:population":763
},
  "geometry": {"coordinates":[84.03276,27.326902],"type":"Point"}
}