{
  "type": "Feature",
  "properties": {
    "iso:country":"IN",
    "ks:ks_name":"Patadewasti",
    "ks:ks_pop":145,
    "ks:ks_type":"HABITATION",
    "name:eng_x_preferred":[
        "Patadewasti"
    ],
    "wof:name":"Patadewasti",
    "wof:placetype":"locality",
    "wof:population":145
},
  "geometry": {"coordinates":[75.465592,18.126742],"type":"Point"}
}