{
  "type": "Feature",
  "properties": {
    "iso:country":"IN",
    "ks:ks_name":"Tabalasahi",
    "ks:ks_pop":31,
    "ks:ks_type":"VILLAGE",
    "name:eng_x_preferred":[
        "Tabalasahi"
    ],
    "wof:name":"Tabalasahi",
    "wof:placetype":"locality",
    "wof:population":31
},
  "geometry": {"coordinates":[84.434882,19.064867],"type":"Point"}
}