{
  "type": "Feature",
  "properties": {
    "iso:country":"IN",
    "ks:ks_name":"Sampigehalla",
    "ks:ks_pop":67,
    "ks:ks_type":"HABITATION",
    "name:eng_x_preferred":[
        "Sampigehalla"
    ],
    "wof:name":"Sampigehalla",
    "wof:placetype":"locality",
    "wof:population":67
},
  "geometry": {"coordinates":[75.39438699999999,13.920552],"type":"Point"}
}