{
  "type": "Feature",
  "properties": {
    "gn:admin1_code":"36.0",
    "gn:admin2_code":"177.0",
    "gn:asciiname":"Purwa Suphal",
    "gn:country_code":"IN",
    "gn:dem":107,
    "gn:feature_class":"P",
    "gn:feature_code":"PPL",
    "gn:name":"Purwa Suphal",
    "gn:population":0,
    "gn:timezone":"Asia/Kolkata",
    "iso:country":"IN",
    "wof:name":"Purwa Suphal",
    "wof:placetype":"locality"
},
  "geometry": {"coordinates":[82.06371,26.70518],"type":"Point"}
}