{
  "type": "Feature",
  "properties": {
    "iso:country":"IN",
    "ks:ks_name":"Kanavana Halli",
    "ks:ks_pop":2,
    "ks:ks_type":"HABITATION",
    "name:eng_x_preferred":[
        "Kanavana Halli"
    ],
    "wof:name":"Kanavana Halli",
    "wof:placetype":"locality",
    "wof:population":2
},
  "geometry": {"coordinates":[76.15787400000001,13.179454],"type":"Point"}
}