{
  "type": "Feature",
  "properties": {
    "iso:country":"IN",
    "ks:ks_alt_nam":"Inchippara road",
    "ks:ks_name":"Inchippara Road",
    "ks:ks_pop":320,
    "ks:ks_type":"HABITATION",
    "name:eng_x_preferred":[
        "Inchippara Road"
    ],
    "wof:name":"Inchippara Road",
    "wof:placetype":"locality",
    "wof:population":320
},
  "geometry": {"coordinates":[76.75608,10.032604],"type":"Point"}
}