{
  "type": "Feature",
  "properties": {
    "gn:admin1_code":"12.0",
    "gn:admin2_code":"021",
    "gn:asciiname":"Jamotian",
    "gn:country_code":"IN",
    "gn:dem":447,
    "gn:feature_class":"P",
    "gn:feature_code":"PPL",
    "gn:name":"Jamoti\u0101n",
    "gn:population":0,
    "gn:timezone":"Asia/Kolkata",
    "iso:country":"IN",
    "name:und_x_variant":[
        "Jamoti\u0101n",
        "Jamati\u0101n"
    ],
    "wof:name":"Jamotian",
    "wof:placetype":"locality"
},
  "geometry": {"coordinates":[74.6309,32.91731],"type":"Point"}
}