{
  "type": "Feature",
  "properties": {
    "iso:country":"IN",
    "ks:ks_name":"Gonjhi Raiyat",
    "ks:ks_pop":118,
    "ks:ks_type":"HABITATION",
    "name:eng_x_preferred":[
        "Gonjhi Raiyat"
    ],
    "wof:name":"Gonjhi Raiyat",
    "wof:placetype":"locality",
    "wof:population":118
},
  "geometry": {"coordinates":[80.351133,22.632505],"type":"Point"}
}