{
  "type": "Feature",
  "properties": {
    "iso:country":"IN",
    "ks:ks_name":"Keshawpur Mahuapara",
    "ks:ks_pop":350,
    "ks:ks_type":"HABITATION",
    "name:eng_x_preferred":[
        "Keshawpur Mahuapara"
    ],
    "wof:name":"Keshawpur Mahuapara",
    "wof:placetype":"locality",
    "wof:population":350
},
  "geometry": {"coordinates":[82.70211399999999,23.1108],"type":"Point"}
}