{
  "type": "Feature",
  "properties": {
    "gn:admin1_code":"24.0",
    "gn:admin2_code":"109.0",
    "gn:asciiname":"Khaoda",
    "gn:country_code":"IN",
    "gn:dem":235,
    "gn:feature_class":"P",
    "gn:feature_code":"PPL",
    "gn:name":"Khaoda",
    "gn:population":0,
    "gn:timezone":"Asia/Kolkata",
    "iso:country":"IN",
    "wof:name":"Khaoda",
    "wof:placetype":"locality"
},
  "geometry": {"coordinates":[76.95003,26.96974],"type":"Point"}
}