{
  "type": "Feature",
  "properties": {
    "iso:country":"IN",
    "ks:ks_name":"Bodgaon",
    "ks:ks_pop":1330,
    "ks:ks_type":"VILLAGE",
    "name:eng_x_preferred":[
        "Bodgaon"
    ],
    "wof:name":"Bodgaon",
    "wof:placetype":"locality",
    "wof:population":1330
},
  "geometry": {"coordinates":[74.397363,22.115472],"type":"Point"}
}