{
  "type": "Feature",
  "properties": {
    "iso:country":"IN",
    "ks:ks_alt_nam":"Bamnoo khurd",
    "ks:ks_name":"Bamnoo Khurd",
    "ks:ks_pop":299,
    "ks:ks_type":"HABITATION",
    "name:eng_x_preferred":[
        "Bamnoo Khurd"
    ],
    "wof:name":"Bamnoo Khurd",
    "wof:placetype":"locality",
    "wof:population":299
},
  "geometry": {"coordinates":[72.198553,26.904389],"type":"Point"}
}