{
  "type": "Feature",
  "properties": {
    "iso:country":"IN",
    "ks:ks_name":"Devkar",
    "ks:ks_pop":35,
    "ks:ks_type":"HABITATION",
    "name:eng_x_preferred":[
        "Devkar"
    ],
    "wof:name":"Devkar",
    "wof:placetype":"locality",
    "wof:population":35
},
  "geometry": {"coordinates":[74.701965,14.467461],"type":"Point"}
}