{
  "type": "Feature",
  "properties": {
    "iso:country":"IN",
    "ks:ks_name":"Penamarti",
    "ks:ks_pop":75,
    "ks:ks_type":"VILLAGE",
    "name:eng_x_preferred":[
        "Penamarti"
    ],
    "wof:name":"Penamarti",
    "wof:placetype":"locality",
    "wof:population":75
},
  "geometry": {"coordinates":[82.92137700000001,18.166806],"type":"Point"}
}