{
  "type": "Feature",
  "properties": {
    "iso:country":"IN",
    "ks:ks_name":"Kanda Malla",
    "ks:ks_pop":392,
    "ks:ks_type":"VILLAGE",
    "name:eng_x_preferred":[
        "Kanda Malla"
    ],
    "wof:name":"Kanda Malla",
    "wof:placetype":"locality",
    "wof:population":392
},
  "geometry": {"coordinates":[78.955252,29.825553],"type":"Point"}
}