{
  "type": "Feature",
  "properties": {
    "iso:country":"IN",
    "ks:ks_name":"Hargen Basti",
    "ks:ks_pop":50,
    "ks:ks_type":"HABITATION",
    "name:eng_x_preferred":[
        "Hargen Basti"
    ],
    "wof:name":"Hargen Basti",
    "wof:placetype":"locality",
    "wof:population":50
},
  "geometry": {"coordinates":[81.16140900000001,25.226365],"type":"Point"}
}