{
  "type": "Feature",
  "properties": {
    "iso:country":"IN",
    "ks:ks_name":"Barat",
    "ks:ks_pop":32,
    "ks:ks_type":"HABITATION",
    "name:eng_x_preferred":[
        "Barat"
    ],
    "wof:name":"Barat",
    "wof:placetype":"locality",
    "wof:population":32
},
  "geometry": {"coordinates":[76.008889,11.964722],"type":"Point"}
}