{
  "type": "Feature",
  "properties": {
    "iso:country":"IN",
    "ks:ks_name":"Kaferpur",
    "ks:ks_pop":643,
    "ks:ks_type":"VILLAGE",
    "ks:ks_uagg_main":0,
    "name:eng_x_preferred":[
        "Kaferpur"
    ],
    "wof:name":"Kaferpur",
    "wof:placetype":"neighbourhood",
    "wof:population":643
},
  "geometry": {"coordinates":[87.884857,23.780997],"type":"Point"}
}