{
  "type": "Feature",
  "properties": {
    "iso:country":"IN",
    "ks:ks_name":"Chotiya",
    "ks:ks_pop":284,
    "ks:ks_type":"VILLAGE",
    "name:eng_x_preferred":[
        "Chotiya"
    ],
    "wof:name":"Chotiya",
    "wof:placetype":"locality",
    "wof:population":284
},
  "geometry": {"coordinates":[74.300389,23.1485],"type":"Point"}
}