{
  "type": "Feature",
  "properties": {
    "gn:admin1_code":"35",
    "gn:admin2_code":"447.0",
    "gn:asciiname":"Ghorkidhana",
    "gn:country_code":"IN",
    "gn:dem":449,
    "gn:feature_class":"P",
    "gn:feature_code":"PPL",
    "gn:name":"Ghork\u012bdh\u0101na",
    "gn:population":0,
    "gn:timezone":"Asia/Kolkata",
    "iso:country":"IN",
    "wof:name":"Ghorkidhana",
    "wof:placetype":"locality"
},
  "geometry": {"coordinates":[77.56963,21.79482],"type":"Point"}
}