{
  "type": "Feature",
  "properties": {
    "iso:country":"IN",
    "ks:ks_name":"Umarkot",
    "ks:ks_pop":666,
    "ks:ks_type":"HABITATION",
    "name:eng_x_preferred":[
        "Umarkot"
    ],
    "wof:name":"Umarkot",
    "wof:placetype":"locality",
    "wof:population":666
},
  "geometry": {"coordinates":[71.438914,24.754025],"type":"Point"}
}