{
  "type": "Feature",
  "properties": {
    "iso:country":"IN",
    "ks:ks_name":"Sela Salpar",
    "ks:ks_pop":756,
    "ks:ks_type":"VILLAGE",
    "name:eng_x_preferred":[
        "Sela Salpar"
    ],
    "wof:name":"Sela Salpar",
    "wof:placetype":"locality",
    "wof:population":756
},
  "geometry": {"coordinates":[80.233439,29.376811],"type":"Point"}
}