{
  "type": "Feature",
  "properties": {
    "iso:country":"IN",
    "ks:ks_name":"Kuthiathode",
    "ks:ks_pop":22880,
    "ks:ks_type":"VILLAGE",
    "name:eng_x_preferred":[
        "Kuthiathode"
    ],
    "wof:name":"Kuthiathode",
    "wof:placetype":"locality",
    "wof:population":22880
},
  "geometry": {"coordinates":[76.305628,9.779014],"type":"Point"}
}