{
  "type": "Feature",
  "properties": {
    "iso:country":"IN",
    "ks:ks_name":"Saurabadi",
    "ks:ks_pop":60,
    "ks:ks_type":"VILLAGE",
    "name:eng_x_preferred":[
        "Saurabadi"
    ],
    "wof:name":"Saurabadi",
    "wof:placetype":"locality",
    "wof:population":60
},
  "geometry": {"coordinates":[84.694524,19.227346],"type":"Point"}
}