{
  "type": "Feature",
  "properties": {
    "iso:country":"IN",
    "ks:ks_name":"Ranikere",
    "ks:ks_pop":710,
    "ks:ks_type":"HABITATION",
    "ks:ks_uagg_main":0,
    "name:eng_x_preferred":[
        "Ranikere"
    ],
    "wof:name":"Ranikere",
    "wof:placetype":"neighbourhood",
    "wof:population":710
},
  "geometry": {"coordinates":[74.76523299999999,13.219188],"type":"Point"}
}