{
  "type": "Feature",
  "properties": {
    "iso:country":"IN",
    "ks:ks_name":"Kapase Wasti",
    "ks:ks_pop":109,
    "ks:ks_type":"HABITATION",
    "name:eng_x_preferred":[
        "Kapase Wasti"
    ],
    "wof:name":"Kapase Wasti",
    "wof:placetype":"locality",
    "wof:population":109
},
  "geometry": {"coordinates":[75.90064,18.053071],"type":"Point"}
}