{
  "type": "Feature",
  "properties": {
    "gn:admin1_code":"10.0",
    "gn:admin2_code":"83.0",
    "gn:asciiname":"Khorra",
    "gn:country_code":"IN",
    "gn:dem":229,
    "gn:feature_class":"P",
    "gn:feature_code":"PPL",
    "gn:name":"Khorra",
    "gn:population":0,
    "gn:timezone":"Asia/Kolkata",
    "iso:country":"IN",
    "name:tat_x_preferred":[
        "\u041a\u04bb\u043e\u0440\u0440\u0430"
    ],
    "wof:name":"Khorra",
    "wof:placetype":"locality"
},
  "geometry": {"coordinates":[76.30356,28.48209],"type":"Point"}
}