{
  "type": "Feature",
  "properties": {
    "iso:country":"IN",
    "ks:ks_name":"Mali Wasti",
    "ks:ks_pop":250,
    "ks:ks_type":"HABITATION",
    "name:eng_x_preferred":[
        "Mali Wasti"
    ],
    "wof:name":"Mali Wasti",
    "wof:placetype":"locality",
    "wof:population":250
},
  "geometry": {"coordinates":[75.92463100000001,18.152619],"type":"Point"}
}