{
  "type": "Feature",
  "properties": {
    "iso:country":"IN",
    "ks:ks_name":"Gaggalagutta Thanda",
    "ks:ks_pop":16,
    "ks:ks_type":"HABITATION",
    "name:eng_x_preferred":[
        "Gaggalagutta Thanda"
    ],
    "wof:name":"Gaggalagutta Thanda",
    "wof:placetype":"locality",
    "wof:population":16
},
  "geometry": {"coordinates":[79.01307300000001,13.884042],"type":"Point"}
}