{
  "type": "Feature",
  "properties": {
    "iso:country":"IN",
    "ks:ks_name":"Kherwa",
    "ks:ks_pop":61,
    "ks:ks_type":"HABITATION",
    "name:eng_x_preferred":[
        "Kherwa"
    ],
    "wof:name":"Kherwa",
    "wof:placetype":"locality",
    "wof:population":61
},
  "geometry": {"coordinates":[86.83882,24.286422],"type":"Point"}
}