{
  "type": "Feature",
  "properties": {
    "iso:country":"IN",
    "ks:ks_name":"Pandera",
    "ks:ks_pop":278,
    "ks:ks_type":"VILLAGE",
    "name:eng_x_preferred":[
        "Pandera"
    ],
    "wof:name":"Pandera",
    "wof:placetype":"locality",
    "wof:population":278
},
  "geometry": {"coordinates":[74.332672,23.340966],"type":"Point"}
}