{
  "type": "Feature",
  "properties": {
    "iso:country":"IN",
    "ks:ks_name":"Adirangam",
    "ks:ks_pop":2788,
    "ks:ks_type":"VILLAGE",
    "ks:ks_uagg_main":0,
    "name:eng_x_preferred":[
        "Adirangam"
    ],
    "wof:name":"Adirangam",
    "wof:placetype":"neighbourhood",
    "wof:population":2788
},
  "geometry": {"coordinates":[79.66086300000001,10.502649],"type":"Point"}
}