{
  "type": "Feature",
  "properties": {
    "gn:admin1_code":"13.0",
    "gn:admin2_code":"589.0",
    "gn:asciiname":"Kannapuram",
    "gn:country_code":"IN",
    "gn:dem":10,
    "gn:feature_class":"P",
    "gn:feature_code":"PPL",
    "gn:name":"Kannapuram",
    "gn:population":0,
    "gn:timezone":"Asia/Kolkata",
    "iso:country":"IN",
    "ks:ks_name":"Kannapuram",
    "ks:ks_pop":18527,
    "ks:ks_type":"VILLAGE",
    "ks:ks_uagg_main":0,
    "name:ben_x_preferred":[
        "\u0995\u09be\u09a8\u09cd\u09a8\u09aa\u09c1\u09b0\u09ae"
    ],
    "name:bpy_x_preferred":[
        "\u0995\u09be\u09a8\u09cd\u09a8\u09aa\u09c1\u09b0\u09ae"
    ],
    "name:eng_x_preferred":[
        "Kannapuram"
    ],
    "name:ita_x_preferred":[
        "Kannapuram"
    ],
    "name:mal_x_preferred":[
        "\u0d15\u0d23\u0d4d\u0d23\u0d2a\u0d41\u0d30\u0d02"
    ],
    "name:msa_x_preferred":[
        "Kannapuram"
    ],
    "name:new_x_preferred":[
        "\u0915\u0928\u094d\u0928\u092a\u0941\u0930\u092e"
    ],
    "name:nld_x_preferred":[
        "Kannapuram"
    ],
    "name:por_x_preferred":[
        "Kannapuram"
    ],
    "name:tam_x_preferred":[
        "\u0b95\u0ba3\u0bcd\u0ba3\u0baa\u0bc1\u0bb0\u0bae\u0bcd"
    ],
    "name:vie_x_preferred":[
        "Kannapuram"
    ],
    "name:zho_x_preferred":[
        "\u574e\u7eb3\u666e\u62c9\u59c6"
    ],
    "wof:name":"Kannapuram",
    "wof:placetype":"neighbourhood",
    "wof:population":18527
},
  "geometry": {"coordinates":[75.30414,11.984342],"type":"Point"}
}