{
  "type": "Feature",
  "properties": {
    "iso:country":"IN",
    "ks:ks_name":"Akherighata",
    "ks:ks_pop":0,
    "ks:ks_type":"VILLAGE",
    "name:eng_x_preferred":[
        "Akherighata"
    ],
    "wof:name":"Akherighata",
    "wof:placetype":"locality",
    "wof:population":0
},
  "geometry": {"coordinates":[88.28783799999999,24.210744],"type":"Point"}
}