{
  "type": "Feature",
  "properties": {
    "gn:admin1_code":"36",
    "gn:admin2_code":"199.0",
    "gn:asciiname":"Saoli",
    "gn:country_code":"IN",
    "gn:dem":86,
    "gn:feature_class":"P",
    "gn:feature_code":"PPL",
    "gn:name":"Saoli",
    "gn:population":0,
    "gn:timezone":"Asia/Kolkata",
    "iso:country":"IN",
    "name:ceb_x_preferred":[
        "S\u0101oli"
    ],
    "name:guj_x_preferred":[
        "\u0ab8\u0abe\u0ab5\u0ab2\u0ac0"
    ],
    "name:swe_x_preferred":[
        "S\u0101oli"
    ],
    "name:urd_x_preferred":[
        "\u0633\u0627\u0624\u0644\u06cc"
    ],
    "wof:name":"Saoli",
    "wof:placetype":"locality"
},
  "geometry": {"coordinates":[82.77601,25.2289],"type":"Point"}
}