{
  "type": "Feature",
  "properties": {
    "iso:country":"IN",
    "ks:ks_name":"Baita Gobindapur",
    "ks:ks_pop":962,
    "ks:ks_type":"VILLAGE",
    "name:eng_x_preferred":[
        "Baita Gobindapur"
    ],
    "wof:name":"Baita Gobindapur",
    "wof:placetype":"locality",
    "wof:population":962
},
  "geometry": {"coordinates":[87.00008699999999,22.279403],"type":"Point"}
}