{
  "type": "Feature",
  "properties": {
    "iso:country":"IN",
    "ks:ks_name":"Balkaje",
    "ks:ks_pop":674,
    "ks:ks_type":"HABITATION",
    "name:eng_x_preferred":[
        "Balkaje"
    ],
    "wof:name":"Balkaje",
    "wof:placetype":"locality",
    "wof:population":674
},
  "geometry": {"coordinates":[75.55923799999999,12.604399],"type":"Point"}
}