{
  "type": "Feature",
  "properties": {
    "iso:country":"IN",
    "ks:ks_name":"Karrevanipalle",
    "ks:ks_pop":9,
    "ks:ks_type":"VILLAGE",
    "name:eng_x_preferred":[
        "Karrevanipalle"
    ],
    "wof:name":"Karrevanipalle",
    "wof:placetype":"locality",
    "wof:population":9
},
  "geometry": {"coordinates":[78.497981,16.753662],"type":"Point"}
}