{
  "type": "Feature",
  "properties": {
    "iso:country":"IN",
    "ks:ks_name":"Nonia Tola",
    "ks:ks_pop":372,
    "ks:ks_type":"HABITATION",
    "name:eng_x_preferred":[
        "Nonia Tola"
    ],
    "wof:name":"Nonia Tola",
    "wof:placetype":"locality",
    "wof:population":372
},
  "geometry": {"coordinates":[85.72969000000001,25.794317],"type":"Point"}
}