{
  "type": "Feature",
  "properties": {
    "iso:country":"IN",
    "ks:ks_alt_nam":"rakshemala",
    "ks:ks_name":"Rakshemala",
    "ks:ks_pop":206,
    "ks:ks_type":"HABITATION",
    "name:eng_x_preferred":[
        "Rakshemala"
    ],
    "wof:name":"Rakshemala",
    "wof:placetype":"locality",
    "wof:population":206
},
  "geometry": {"coordinates":[73.99780199999999,18.977274],"type":"Point"}
}