{
  "type": "Feature",
  "properties": {
    "iso:country":"IN",
    "ks:ks_name":"Krishnamati",
    "ks:ks_pop":3168,
    "ks:ks_type":"VILLAGE",
    "ks:ks_uagg_main":0,
    "name:eng_x_preferred":[
        "Krishnamati"
    ],
    "wof:name":"Krishnamati",
    "wof:placetype":"locality",
    "wof:population":3168
},
  "geometry": {"coordinates":[88.53241,22.654691],"type":"Point"}
}