{
  "type": "Feature",
  "properties": {
    "gn:admin1_code":"35.0",
    "gn:admin2_code":"443.0",
    "gn:asciiname":"Lateri",
    "gn:country_code":"IN",
    "gn:dem":534,
    "gn:feature_class":"P",
    "gn:feature_code":"PPL",
    "gn:name":"Lateri",
    "gn:population":0,
    "gn:timezone":"Asia/Kolkata",
    "iso:country":"IN",
    "wof:name":"Lateri",
    "wof:placetype":"locality"
},
  "geometry": {"coordinates":[77.41044000000002,24.06091],"type":"Point"}
}