{
  "type": "Feature",
  "properties": {
    "iso:country":"IN",
    "ks:ks_name":"Ghagwadi",
    "ks:ks_pop":232,
    "ks:ks_type":"HABITATION",
    "name:eng_x_preferred":[
        "Ghagwadi"
    ],
    "wof:name":"Ghagwadi",
    "wof:placetype":"locality",
    "wof:population":232
},
  "geometry": {"coordinates":[73.65434399999999,16.929907],"type":"Point"}
}