{
  "type": "Feature",
  "properties": {
    "gn:admin1_code":"10",
    "gn:admin2_code":"75.0",
    "gn:asciiname":"Goela Khurd",
    "gn:country_code":"IN",
    "gn:dem":230,
    "gn:feature_class":"P",
    "gn:feature_code":"PPL",
    "gn:name":"Goela Khurd",
    "gn:population":0,
    "gn:timezone":"Asia/Kolkata",
    "iso:country":"IN",
    "name:ara_x_preferred":[
        "\u063a\u0648\u064a\u0644\u0627 \u062e\u0648\u0631\u062f"
    ],
    "name:ben_bn_x_preferred":[
        "\u0997\u09cb\u09df\u09c7\u09b2\u09be \u0996\u09c1\u09b0\u09cd\u09a6"
    ],
    "name:ben_in_x_preferred":[
        "\u0997\u09cb\u09df\u09c7\u09b2\u09be \u0996\u09c1\u09b0\u09cd\u09a6"
    ],
    "name:guj_x_preferred":[
        "\u0a97\u0acb\u0ab2\u0abe \u0a96\u0ac1\u0ab0\u0acd\u0aa6"
    ],
    "name:hin_x_preferred":[
        "\u0917\u094b\u090f\u0932\u093e \u0916\u0941\u0930\u094d\u0926"
    ],
    "name:kan_x_preferred":[
        "\u0c97\u0cca\u0cb5\u0cc6\u0cb2\u0cbe \u0c96\u0cc1\u0cb0\u0ccd\u0ca6\u0ccd"
    ],
    "name:mal_x_preferred":[
        "\u0d17\u0d4b\u0d2f \u0d16\u0d41\u0d7c\u0d26\u0d4d"
    ],
    "name:mar_x_preferred":[
        "\u0917\u094b\u090f\u0932\u093e \u0916\u0941\u0930\u094d\u0926"
    ],
    "name:pan_x_preferred":[
        "\u0a17\u0a4b\u0a0f\u0a32\u0a3e \u0a16\u0a41\u0a30\u0a26"
    ],
    "name:tam_x_preferred":[
        "\u0b95\u0bca\u0baf\u0bc6\u0bb2\u0bcd\u0bb2\u0bbe \u0b95\u0bc1\u0bb0\u0bcd\u0ba4\u0bcd"
    ],
    "name:tel_x_preferred":[
        "\u0c17\u0c4b\u0c2f\u0c46\u0c32\u0c3e \u0c16\u0c41\u0c30\u0c4d\u0c26\u0c4d"
    ],
    "name:urd_x_preferred":[
        "\u06af\u0648\u0626\u0644\u0627 \u062e\u0631\u062f"
    ],
    "wof:name":"Goela Khurd",
    "wof:placetype":"locality"
},
  "geometry": {"coordinates":[77.12933000000002,29.30252],"type":"Point"}
}