{
  "type": "Feature",
  "properties": {
    "iso:country":"IN",
    "ks:ks_name":"Shahzadpur 254",
    "ks:ks_pop":381,
    "ks:ks_type":"HABITATION",
    "name:eng_x_preferred":[
        "Shahzadpur 254"
    ],
    "wof:name":"Shahzadpur 254",
    "wof:placetype":"locality",
    "wof:population":381
},
  "geometry": {"coordinates":[76.866482,30.179553],"type":"Point"}
}