{
  "type": "Feature",
  "properties": {
    "gn:admin1_code":"35",
    "gn:admin2_code":"452.0",
    "gn:asciiname":"Kodsa",
    "gn:country_code":"IN",
    "gn:dem":366,
    "gn:feature_class":"P",
    "gn:feature_code":"PPL",
    "gn:name":"Kodsa",
    "gn:population":0,
    "gn:timezone":"Asia/Kolkata",
    "iso:country":"IN",
    "wof:name":"Kodsa",
    "wof:placetype":"locality"
},
  "geometry": {"coordinates":[79.2037,22.89504],"type":"Point"}
}