{
  "type": "Feature",
  "properties": {
    "iso:country":"IN",
    "ks:ks_name":"1 DWSM",
    "ks:ks_pop":442,
    "ks:ks_type":"VILLAGE",
    "name:eng_x_preferred":[
        "1 DWSM"
    ],
    "wof:name":"1 DWSM",
    "wof:placetype":"locality",
    "wof:population":442
},
  "geometry": {"coordinates":[73.629757,29.161832],"type":"Point"}
}