{
  "type": "Feature",
  "properties": {
    "iso:country":"IN",
    "ks:ks_name":"Balebailu",
    "ks:ks_pop":170,
    "ks:ks_type":"HABITATION",
    "name:eng_x_preferred":[
        "Balebailu"
    ],
    "wof:name":"Balebailu",
    "wof:placetype":"locality",
    "wof:population":170
},
  "geometry": {"coordinates":[75.382822,13.502218],"type":"Point"}
}