{
  "type": "Feature",
  "properties": {
    "gn:admin1_code":"39",
    "gn:admin2_code":"61.0",
    "gn:asciiname":"Chupra",
    "gn:country_code":"IN",
    "gn:dem":1644,
    "gn:feature_class":"P",
    "gn:feature_code":"PPL",
    "gn:name":"Chupra",
    "gn:population":0,
    "gn:timezone":"Asia/Kolkata",
    "iso:country":"IN",
    "ks:ks_name":"Chopra",
    "ks:ks_pop":443,
    "ks:ks_type":"VILLAGE",
    "name:eng_x_preferred":[
        "Chopra"
    ],
    "name:eng_x_variant":[
        "Chupra"
    ],
    "wof:name":"Chopra",
    "wof:placetype":"locality",
    "wof:population":443
},
  "geometry": {"coordinates":[78.93058000000001,30.159498],"type":"Point"}
}