{
  "type": "Feature",
  "properties": {
    "iso:country":"IN",
    "ks:ks_name":"Baghana Sahi",
    "ks:ks_pop":115,
    "ks:ks_type":"HABITATION",
    "name:eng_x_preferred":[
        "Baghana Sahi"
    ],
    "wof:name":"Baghana Sahi",
    "wof:placetype":"locality",
    "wof:population":115
},
  "geometry": {"coordinates":[85.96217300000001,21.009016],"type":"Point"}
}