{
  "type": "Feature",
  "properties": {
    "iso:country":"IN",
    "ks:ks_name":"Narendraposi",
    "ks:ks_pop":585,
    "ks:ks_type":"VILLAGE",
    "name:eng_x_preferred":[
        "Narendraposi"
    ],
    "wof:name":"Narendraposi",
    "wof:placetype":"locality",
    "wof:population":585
},
  "geometry": {"coordinates":[86.127819,22.157453],"type":"Point"}
}