{
  "type": "Feature",
  "properties": {
    "iso:country":"IN",
    "ks:ks_name":"Bolepalli Tola",
    "ks:ks_pop":127,
    "ks:ks_type":"HABITATION",
    "name:eng_x_preferred":[
        "Bolepalli Tola"
    ],
    "wof:name":"Bolepalli Tola",
    "wof:placetype":"locality",
    "wof:population":127
},
  "geometry": {"coordinates":[80.130781,19.710829],"type":"Point"}
}