{
  "type": "Feature",
  "properties": {
    "iso:country":"IN",
    "ks:ks_name":"Tekari Falia",
    "ks:ks_pop":255,
    "ks:ks_type":"HABITATION",
    "name:eng_x_preferred":[
        "Tekari Falia"
    ],
    "wof:name":"Tekari Falia",
    "wof:placetype":"locality",
    "wof:population":255
},
  "geometry": {"coordinates":[73.73205,22.531517],"type":"Point"}
}