{
  "type": "Feature",
  "properties": {
    "iso:country":"IN",
    "ks:ks_name":"Umnem",
    "ks:ks_pop":461,
    "ks:ks_type":"HABITATION",
    "name:eng_x_preferred":[
        "Umnem"
    ],
    "wof:name":"Umnem",
    "wof:placetype":"locality",
    "wof:population":461
},
  "geometry": {"coordinates":[92.28652200000001,25.753307],"type":"Point"}
}