{
  "type": "Feature",
  "properties": {
    "gn:admin1_code":"19.0",
    "gn:admin2_code":"563.0",
    "gn:asciiname":"Gudhalli",
    "gn:country_code":"IN",
    "gn:dem":549,
    "gn:feature_class":"P",
    "gn:feature_code":"PPL",
    "gn:name":"Gudhalli",
    "gn:population":0,
    "gn:timezone":"Asia/Kolkata",
    "iso:country":"IN",
    "ks:ks_name":"Gudalli",
    "ks:ks_pop":32,
    "ks:ks_type":"HABITATION",
    "name:eng_x_preferred":[
        "Gudalli"
    ],
    "name:eng_x_variant":[
        "Gudhalli"
    ],
    "wof:name":"Gudalli",
    "wof:placetype":"locality",
    "wof:population":32
},
  "geometry": {"coordinates":[74.697177,14.740274],"type":"Point"}
}