{
  "type": "Feature",
  "properties": {
    "iso:country":"IN",
    "ks:ks_name":"Kalelkarwadi",
    "ks:ks_pop":390,
    "ks:ks_type":"HABITATION",
    "name:eng_x_preferred":[
        "Kalelkarwadi"
    ],
    "wof:name":"Kalelkarwadi",
    "wof:placetype":"locality",
    "wof:population":390
},
  "geometry": {"coordinates":[73.73947699999999,16.000954],"type":"Point"}
}