{
  "type": "Feature",
  "properties": {
    "iso:country":"IN",
    "ks:ks_name":"Rooppura",
    "ks:ks_pop":102,
    "ks:ks_type":"VILLAGE",
    "name:eng_x_preferred":[
        "Rooppura"
    ],
    "wof:name":"Rooppura",
    "wof:placetype":"locality",
    "wof:population":102
},
  "geometry": {"coordinates":[76.33707099999999,24.245276],"type":"Point"}
}