{
  "type": "Feature",
  "properties": {
    "gn:admin1_code":"24.0",
    "gn:admin2_code":"122.0",
    "gn:asciiname":"Bhawansinhji ka Khera",
    "gn:country_code":"IN",
    "gn:dem":365,
    "gn:feature_class":"P",
    "gn:feature_code":"PPL",
    "gn:name":"Bhaw\u0101nsinhji ka Khera",
    "gn:population":0,
    "gn:timezone":"Asia/Kolkata",
    "iso:country":"IN",
    "wof:name":"Bhawansinhji ka Khera",
    "wof:placetype":"neighbourhood"
},
  "geometry": {"coordinates":[74.97790000000001,25.19779],"type":"Point"}
}