{
  "type": "Feature",
  "properties": {
    "gn:admin1_code":"25.0",
    "gn:admin2_code":"617.0",
    "gn:asciiname":"Vaddakku Palaiyam",
    "gn:country_code":"IN",
    "gn:dem":30,
    "gn:feature_class":"P",
    "gn:feature_code":"PPL",
    "gn:name":"Vaddakku P\u0101laiyam",
    "gn:population":0,
    "gn:timezone":"Asia/Kolkata",
    "iso:country":"IN",
    "ks:ks_name":"Vadakkupalayam",
    "ks:ks_pop":3700,
    "ks:ks_type":"VILLAGE",
    "name:eng_x_preferred":[
        "Vadakkupalayam"
    ],
    "name:eng_x_variant":[
        "Vaddakku Palaiyam"
    ],
    "wof:name":"Vadakkupalayam",
    "wof:placetype":"locality",
    "wof:population":3700
},
  "geometry": {"coordinates":[79.469193,11.37258],"type":"Point"}
}