{
  "type": "Feature",
  "properties": {
    "gn:admin1_code":"09",
    "gn:admin2_code":"479.0",
    "gn:asciiname":"Sodaori",
    "gn:country_code":"IN",
    "gn:dem":190,
    "gn:feature_class":"P",
    "gn:feature_code":"PPL",
    "gn:name":"Sodaori",
    "gn:population":0,
    "gn:timezone":"Asia/Kolkata",
    "iso:country":"IN",
    "wof:name":"Sodaori",
    "wof:placetype":"locality"
},
  "geometry": {"coordinates":[70.84759,21.09355],"type":"Point"}
}