{
  "type": "Feature",
  "properties": {
    "iso:country":"IN",
    "ks:ks_name":"Bhandeswar",
    "ks:ks_pop":308,
    "ks:ks_type":"VILLAGE",
    "name:eng_x_preferred":[
        "Bhandeswar"
    ],
    "wof:name":"Bhandeswar",
    "wof:placetype":"locality",
    "wof:population":308
},
  "geometry": {"coordinates":[86.97663900000001,21.566896],"type":"Point"}
}