{
  "type": "Feature",
  "properties": {
    "gn:admin1_code":"16",
    "gn:admin2_code":"521.0",
    "gn:asciiname":"Nimsakhar",
    "gn:country_code":"IN",
    "gn:dem":509,
    "gn:feature_class":"P",
    "gn:feature_code":"PPL",
    "gn:name":"N\u012bms\u0101khar",
    "gn:population":0,
    "gn:timezone":"Asia/Kolkata",
    "iso:country":"IN",
    "name:und_x_variant":[
        "Nimskhar",
        "N\u012bms\u0101khar"
    ],
    "wof:name":"Nimsakhar",
    "wof:placetype":"locality"
},
  "geometry": {"coordinates":[74.77188000000002,18.02566],"type":"Point"}
}