{
  "type": "Feature",
  "properties": {
    "iso:country":"IN",
    "ks:ks_alt_nam":"Paras pada",
    "ks:ks_name":"Paras Pada",
    "ks:ks_pop":563,
    "ks:ks_type":"HABITATION",
    "name:eng_x_preferred":[
        "Paras Pada"
    ],
    "wof:name":"Paras Pada",
    "wof:placetype":"locality",
    "wof:population":563
},
  "geometry": {"coordinates":[73.317472,20.257417],"type":"Point"}
}