{
  "type": "Feature",
  "properties": {
    "iso:country":"IN",
    "ks:ks_name":"Kudamsada",
    "ks:ks_pop":804,
    "ks:ks_type":"VILLAGE",
    "name:eng_x_preferred":[
        "Kudamsada"
    ],
    "wof:name":"Kudamsada",
    "wof:placetype":"locality",
    "wof:population":804
},
  "geometry": {"coordinates":[85.63311899999999,22.373386],"type":"Point"}
}