{
  "type": "Feature",
  "properties": {
    "iso:country":"IN",
    "ks:ks_name":"Burut Kheda",
    "ks:ks_pop":456,
    "ks:ks_type":"HABITATION",
    "name:eng_x_preferred":[
        "Burut Kheda"
    ],
    "wof:name":"Burut Kheda",
    "wof:placetype":"locality",
    "wof:population":456
},
  "geometry": {"coordinates":[76.634956,22.679235],"type":"Point"}
}