{
  "type": "Feature",
  "properties": {
    "iso:country":"IN",
    "ks:ks_name":"Umer",
    "ks:ks_pop":44,
    "ks:ks_type":"VILLAGE",
    "name:eng_x_preferred":[
        "Umer"
    ],
    "wof:name":"Umer",
    "wof:placetype":"locality",
    "wof:population":44
},
  "geometry": {"coordinates":[83.388363,19.880607],"type":"Point"}
}