{
  "type": "Feature",
  "properties": {
    "iso:country":"IN",
    "ks:ks_name":"Bhatakhol",
    "ks:ks_pop":76,
    "ks:ks_type":"HABITATION",
    "name:eng_x_preferred":[
        "Bhatakhol"
    ],
    "wof:name":"Bhatakhol",
    "wof:placetype":"locality",
    "wof:population":76
},
  "geometry": {"coordinates":[84.489493,19.616215],"type":"Point"}
}