{
  "type": "Feature",
  "properties": {
    "gn:admin1_code":"36.0",
    "gn:admin2_code":"152.0",
    "gn:asciiname":"Nizampur",
    "gn:country_code":"IN",
    "gn:dem":161,
    "gn:feature_class":"P",
    "gn:feature_code":"PPL",
    "gn:name":"Niz\u0101mpur",
    "gn:population":0,
    "gn:timezone":"Asia/Kolkata",
    "iso:country":"IN",
    "ks:ks_alt_nam":"Niz\u0101mpur",
    "ks:ks_name":"Nizampur",
    "ks:ks_pop":955,
    "ks:ks_type":"VILLAGE",
    "name:eng_x_preferred":[
        "Nizampur"
    ],
    "name:eng_x_variant":[
        "Niz\u0101mpur"
    ],
    "wof:name":"Nizampur",
    "wof:placetype":"locality",
    "wof:population":955
},
  "geometry": {"coordinates":[79.64990299999999,28.142186],"type":"Point"}
}