{
  "type": "Feature",
  "properties": {
    "iso:country":"IN",
    "ks:ks_name":"Naudiha",
    "ks:ks_pop":811,
    "ks:ks_type":"VILLAGE",
    "name:eng_x_preferred":[
        "Naudiha"
    ],
    "wof:name":"Naudiha",
    "wof:placetype":"locality",
    "wof:population":811
},
  "geometry": {"coordinates":[83.202411,24.070317],"type":"Point"}
}