{
  "type": "Feature",
  "properties": {
    "gn:admin1_code":"24",
    "gn:admin2_code":"115.0",
    "gn:asciiname":"Rasliani",
    "gn:country_code":"IN",
    "gn:dem":113,
    "gn:feature_class":"P",
    "gn:feature_code":"PPL",
    "gn:name":"Rasli\u0101ni",
    "gn:population":0,
    "gn:timezone":"Asia/Kolkata",
    "iso:country":"IN",
    "wof:name":"Rasliani",
    "wof:placetype":"locality"
},
  "geometry": {"coordinates":[70.43468,25.93175],"type":"Point"}
}