{
  "type": "Feature",
  "properties": {
    "iso:country":"IN",
    "ks:ks_alt_nam":"Su nallur",
    "ks:ks_name":"Su Nallur",
    "ks:ks_pop":1057,
    "ks:ks_type":"HABITATION",
    "name:eng_x_preferred":[
        "Su Nallur"
    ],
    "wof:name":"Su Nallur",
    "wof:placetype":"locality",
    "wof:population":1057
},
  "geometry": {"coordinates":[79.14575499999999,12.086653],"type":"Point"}
}