{
  "type": "Feature",
  "properties": {
    "iso:country":"IN",
    "ks:ks_name":"Argaza Pandeypur",
    "ks:ks_pop":787,
    "ks:ks_type":"HABITATION",
    "ks:ks_uagg_main":0,
    "name:eng_x_preferred":[
        "Argaza Pandeypur"
    ],
    "wof:name":"Argaza Pandeypur",
    "wof:placetype":"neighbourhood",
    "wof:population":787
},
  "geometry": {"coordinates":[82.525897,25.092908],"type":"Point"}
}