{
  "type": "Feature",
  "properties": {
    "iso:country":"IN",
    "ks:ks_name":"Konora",
    "ks:ks_pop":1571,
    "ks:ks_type":"VILLAGE",
    "name:eng_x_preferred":[
        "Konora"
    ],
    "wof:name":"Konora",
    "wof:placetype":"locality",
    "wof:population":1571
},
  "geometry": {"coordinates":[87.738136,22.770724],"type":"Point"}
}