{
  "type": "Feature",
  "properties": {
    "iso:country":"IN",
    "ks:ks_name":"Narinnpur",
    "ks:ks_pop":900,
    "ks:ks_type":"HABITATION",
    "name:eng_x_preferred":[
        "Narinnpur"
    ],
    "wof:name":"Narinnpur",
    "wof:placetype":"locality",
    "wof:population":900
},
  "geometry": {"coordinates":[84.92945899999999,25.818189],"type":"Point"}
}