{
  "type": "Feature",
  "properties": {
    "iso:country":"IN",
    "ks:ks_name":"Bhrouli Talli",
    "ks:ks_pop":64,
    "ks:ks_type":"VILLAGE",
    "name:eng_x_preferred":[
        "Bhrouli Talli"
    ],
    "wof:name":"Bhrouli Talli",
    "wof:placetype":"locality",
    "wof:population":64
},
  "geometry": {"coordinates":[79.030361,29.849917],"type":"Point"}
}