{
  "type": "Feature",
  "properties": {
    "gn:admin1_code":"10.0",
    "gn:admin2_code":"070",
    "gn:asciiname":"Mahlan",
    "gn:country_code":"IN",
    "gn:dem":255,
    "gn:feature_class":"P",
    "gn:feature_code":"PPL",
    "gn:name":"Mahl\u0101n",
    "gn:population":0,
    "gn:timezone":"Asia/Kolkata",
    "iso:country":"IN",
    "wof:name":"Mahlan",
    "wof:placetype":"locality"
},
  "geometry": {"coordinates":[76.64771999999998,30.16238],"type":"Point"}
}