{
  "type": "Feature",
  "properties": {
    "iso:country":"IN",
    "ks:ks_name":"Venkatanagaram",
    "ks:ks_pop":99,
    "ks:ks_type":"HABITATION",
    "name:eng_x_preferred":[
        "Venkatanagaram"
    ],
    "wof:name":"Venkatanagaram",
    "wof:placetype":"locality",
    "wof:population":99
},
  "geometry": {"coordinates":[82.409936,17.455091],"type":"Point"}
}