{
  "type": "Feature",
  "properties": {
    "iso:country":"IN",
    "ks:ks_name":"Simli Malli",
    "ks:ks_pop":65,
    "ks:ks_type":"VILLAGE",
    "name:eng_x_preferred":[
        "Simli Malli"
    ],
    "wof:name":"Simli Malli",
    "wof:placetype":"locality",
    "wof:population":65
},
  "geometry": {"coordinates":[78.998508,29.660003],"type":"Point"}
}