{
  "type": "Feature",
  "properties": {
    "iso:country":"IN",
    "ks:ks_name":"Vaderahalli",
    "ks:ks_pop":75,
    "ks:ks_type":"VILLAGE",
    "name:eng_x_preferred":[
        "Vaderahalli"
    ],
    "wof:name":"Vaderahalli",
    "wof:placetype":"locality",
    "wof:population":75
},
  "geometry": {"coordinates":[77.599712,12.829971],"type":"Point"}
}