{
  "type": "Feature",
  "properties": {
    "iso:country":"IN",
    "ks:ks_name":"17 NWD",
    "ks:ks_pop":99,
    "ks:ks_type":"VILLAGE",
    "name:eng_x_preferred":[
        "17 NWD"
    ],
    "wof:name":"17 NWD",
    "wof:placetype":"locality",
    "wof:population":99
},
  "geometry": {"coordinates":[74.36560299999999,29.186434],"type":"Point"}
}