{
  "type": "Feature",
  "properties": {
    "iso:country":"IN",
    "ks:ks_alt_nam":"Salempur Begam Jamohra",
    "ks:ks_name":"Salempur Begam",
    "ks:ks_type":"VILLAGE",
    "name:eng_x_preferred":[
        "Salempur Begam"
    ],
    "name:eng_x_variant":[
        "Salempur Begam Jamohra"
    ],
    "wof:name":"Salempur Begam",
    "wof:placetype":"locality"
},
  "geometry": {"coordinates":[83.573795,25.360135],"type":"Point"}
}