{
  "type": "Feature",
  "properties": {
    "iso:country":"IN",
    "ks:ks_name":"Ramalakatte",
    "ks:ks_pop":1138,
    "ks:ks_type":"HABITATION",
    "name:eng_x_preferred":[
        "Ramalakatte"
    ],
    "wof:name":"Ramalakatte",
    "wof:placetype":"locality",
    "wof:population":1138
},
  "geometry": {"coordinates":[74.99221,12.876958],"type":"Point"}
}