{
  "type": "Feature",
  "properties": {
    "iso:country":"IN",
    "ks:ks_name":"Kaldari",
    "ks:ks_pop":1293,
    "ks:ks_type":"HABITATION",
    "name:eng_x_preferred":[
        "Kaldari"
    ],
    "wof:name":"Kaldari",
    "wof:placetype":"locality",
    "wof:population":1293
},
  "geometry": {"coordinates":[72.931292,24.947269],"type":"Point"}
}