{
  "type": "Feature",
  "properties": {
    "iso:country":"IN",
    "ks:ks_alt_nam":"bhusanpurwa",
    "ks:ks_name":"Bhusanpurwa",
    "ks:ks_pop":113,
    "ks:ks_type":"HABITATION",
    "ks:ks_uagg_main":0,
    "name:eng_x_preferred":[
        "Bhusanpurwa"
    ],
    "wof:name":"Bhusanpurwa",
    "wof:placetype":"neighbourhood",
    "wof:population":113
},
  "geometry": {"coordinates":[81.242908,28.103652],"type":"Point"}
}