{
  "type": "Feature",
  "properties": {
    "gn:admin1_code":"12.0",
    "gn:admin2_code":"5.0",
    "gn:asciiname":"Hari",
    "gn:country_code":"IN",
    "gn:dem":1614,
    "gn:feature_class":"P",
    "gn:feature_code":"PPL",
    "gn:name":"H\u0101ri",
    "gn:population":0,
    "gn:timezone":"Asia/Kolkata",
    "iso:country":"IN",
    "name:deu_x_preferred":[
        "Hari"
    ],
    "name:ita_x_preferred":[
        "Hari"
    ],
    "name:kan_x_preferred":[
        "\u0cb9\u0cb0\u0cbf"
    ],
    "name:kaz_x_preferred":[
        "\u0425\u0430\u0440\u0438"
    ],
    "name:pol_x_preferred":[
        "Hari"
    ],
    "name:por_x_preferred":[
        "Hari"
    ],
    "name:rus_x_preferred":[
        "\u0425\u0430\u0440\u0438"
    ],
    "name:tam_x_preferred":[
        "\u0bb9\u0bb0\u0bbf"
    ],
    "name:tel_x_preferred":[
        "\u0c39\u0c30\u0c3f"
    ],
    "name:ukr_x_preferred":[
        "\u0425\u0430\u0440\u0456"
    ],
    "wof:name":"Hari",
    "wof:placetype":"locality"
},
  "geometry": {"coordinates":[74.28708,33.70797],"type":"Point"}
}