{
  "type": "Feature",
  "properties": {
    "iso:country":"IN",
    "ks:ks_name":"Kumbemula",
    "ks:ks_pop":53,
    "ks:ks_type":"VILLAGE",
    "name:eng_x_preferred":[
        "Kumbemula"
    ],
    "wof:name":"Kumbemula",
    "wof:placetype":"locality",
    "wof:population":53
},
  "geometry": {"coordinates":[83.797478,20.37848],"type":"Point"}
}