{
  "type": "Feature",
  "properties": {
    "iso:country":"IN",
    "ks:ks_name":"Sodhai",
    "ks:ks_pop":239,
    "ks:ks_type":"VILLAGE",
    "name:eng_x_preferred":[
        "Sodhai"
    ],
    "wof:name":"Sodhai",
    "wof:placetype":"locality",
    "wof:population":239
},
  "geometry": {"coordinates":[70.767972,25.690553],"type":"Point"}
}