{
  "type": "Feature",
  "properties": {
    "gn:admin1_code":"12.0",
    "gn:admin2_code":"001",
    "gn:asciiname":"Shoghapur",
    "gn:country_code":"IN",
    "gn:dem":1637,
    "gn:feature_class":"P",
    "gn:feature_code":"PPL",
    "gn:name":"Shoghapur",
    "gn:population":0,
    "gn:timezone":"Asia/Kolkata",
    "iso:country":"IN",
    "wof:name":"Shoghapur",
    "wof:placetype":"locality"
},
  "geometry": {"coordinates":[74.22051999999999,34.45079],"type":"Point"}
}