{
  "type": "Feature",
  "properties": {
    "gn:admin1_code":"9.0",
    "gn:admin2_code":"468.0",
    "gn:asciiname":"Dafa",
    "gn:country_code":"IN",
    "gn:dem":1,
    "gn:feature_class":"P",
    "gn:feature_code":"PPL",
    "gn:name":"Dafa",
    "gn:population":0,
    "gn:timezone":"Asia/Kolkata",
    "iso:country":"IN",
    "wof:name":"Dafa",
    "wof:placetype":"locality"
},
  "geometry": {"coordinates":[68.23063,23.77984],"type":"Point"}
}