{
  "type": "Feature",
  "properties": {
    "iso:country":"IN",
    "ks:ks_name":"Chhirabasta",
    "ks:ks_pop":451,
    "ks:ks_type":"VILLAGE",
    "name:eng_x_preferred":[
        "Chhirabasta"
    ],
    "wof:name":"Chhirabasta",
    "wof:placetype":"locality",
    "wof:population":451
},
  "geometry": {"coordinates":[87.167174,23.253308],"type":"Point"}
}