{
  "type": "Feature",
  "properties": {
    "gn:admin1_code":"12.0",
    "gn:admin2_code":"020",
    "gn:asciiname":"Kaindor",
    "gn:country_code":"IN",
    "gn:dem":2195,
    "gn:feature_class":"P",
    "gn:feature_code":"PPL",
    "gn:name":"Kaindor",
    "gn:population":0,
    "gn:timezone":"Asia/Kolkata",
    "iso:country":"IN",
    "wof:name":"Kaindor",
    "wof:placetype":"locality"
},
  "geometry": {"coordinates":[74.91001,33.43222],"type":"Point"}
}