{
  "type": "Feature",
  "properties": {
    "iso:country":"IN",
    "ks:ks_name":"Kapasiya",
    "ks:ks_pop":765,
    "ks:ks_type":"VILLAGE",
    "name:eng_x_preferred":[
        "Kapasiya"
    ],
    "wof:name":"Kapasiya",
    "wof:placetype":"locality",
    "wof:population":765
},
  "geometry": {"coordinates":[74.812521,23.432843],"type":"Point"}
}