{
  "type": "Feature",
  "properties": {
    "iso:country":"IN",
    "ks:ks_name":"Digambarpur",
    "ks:ks_pop":133,
    "ks:ks_type":"VILLAGE",
    "name:eng_x_preferred":[
        "Digambarpur"
    ],
    "wof:name":"Digambarpur",
    "wof:placetype":"locality",
    "wof:population":133
},
  "geometry": {"coordinates":[86.132831,20.639756],"type":"Point"}
}