{
  "type": "Feature",
  "properties": {
    "gn:admin1_code":"36",
    "gn:admin2_code":"191.0",
    "gn:asciiname":"Hilalpur",
    "gn:country_code":"IN",
    "gn:dem":81,
    "gn:feature_class":"P",
    "gn:feature_code":"PPL",
    "gn:name":"Hil\u0101lpur",
    "gn:population":0,
    "gn:timezone":"Asia/Kolkata",
    "iso:country":"IN",
    "wof:name":"Hilalpur",
    "wof:placetype":"locality"
},
  "geometry": {"coordinates":[83.06829999999999,25.70643],"type":"Point"}
}