{
  "type": "Feature",
  "properties": {
    "iso:country":"IN",
    "ks:ks_name":"Karappane",
    "ks:ks_pop":25,
    "ks:ks_type":"HABITATION",
    "name:eng_x_preferred":[
        "Karappane"
    ],
    "wof:name":"Karappane",
    "wof:placetype":"locality",
    "wof:population":25
},
  "geometry": {"coordinates":[75.523202,12.684556],"type":"Point"}
}