{
  "type": "Feature",
  "properties": {
    "iso:country":"IN",
    "ks:ks_name":"Gochhaguda",
    "ks:ks_pop":204,
    "ks:ks_type":"VILLAGE",
    "name:eng_x_preferred":[
        "Gochhaguda"
    ],
    "wof:name":"Gochhaguda",
    "wof:placetype":"locality",
    "wof:population":204
},
  "geometry": {"coordinates":[83.57544,20.055799],"type":"Point"}
}