{
  "type": "Feature",
  "properties": {
    "iso:country":"IN",
    "ks:ks_name":"Modaband",
    "ks:ks_pop":136,
    "ks:ks_type":"VILLAGE",
    "ks:ks_uagg_main":0,
    "name:eng_x_preferred":[
        "Modaband"
    ],
    "wof:name":"Modaband",
    "wof:placetype":"neighbourhood",
    "wof:population":136
},
  "geometry": {"coordinates":[87.12455300000001,22.416366],"type":"Point"}
}