{
  "type": "Feature",
  "properties": {
    "iso:country":"IN",
    "ks:ks_name":"Kurumblaje",
    "ks:ks_pop":262,
    "ks:ks_type":"HABITATION",
    "name:eng_x_preferred":[
        "Kurumblaje"
    ],
    "wof:name":"Kurumblaje",
    "wof:placetype":"locality",
    "wof:population":262
},
  "geometry": {"coordinates":[75.168269,12.826047],"type":"Point"}
}