{
  "type": "Feature",
  "properties": {
    "iso:country":"IN",
    "ks:ks_alt_nam":"CHAMAR TOLA",
    "ks:ks_name":"Chamar Tola",
    "ks:ks_pop":156,
    "ks:ks_type":"HABITATION",
    "name:eng_x_preferred":[
        "Chamar Tola"
    ],
    "wof:name":"Chamar Tola",
    "wof:placetype":"locality",
    "wof:population":156
},
  "geometry": {"coordinates":[84.987033,24.53758],"type":"Point"}
}