{
  "type": "Feature",
  "properties": {
    "iso:country":"IN",
    "ks:ks_name":"Nand Ram Purwa",
    "ks:ks_pop":32,
    "ks:ks_type":"HABITATION",
    "ks:ks_uagg_main":0,
    "name:eng_x_preferred":[
        "Nand Ram Purwa"
    ],
    "wof:name":"Nand Ram Purwa",
    "wof:placetype":"neighbourhood",
    "wof:population":32
},
  "geometry": {"coordinates":[81.47417,27.552995],"type":"Point"}
}