{
  "type": "Feature",
  "properties": {
    "iso:country":"IN",
    "ks:ks_name":"Zer Falia",
    "ks:ks_pop":496,
    "ks:ks_type":"HABITATION",
    "ks:ks_uagg_main":0,
    "name:eng_x_preferred":[
        "Zer Falia"
    ],
    "wof:name":"Zer Falia",
    "wof:placetype":"neighbourhood",
    "wof:population":496
},
  "geometry": {"coordinates":[73.7052,22.584017],"type":"Point"}
}