{
  "type": "Feature",
  "properties": {
    "iso:country":"IN",
    "ks:ks_name":"Velapadi",
    "ks:ks_pop":225,
    "ks:ks_type":"HABITATION",
    "name:eng_x_preferred":[
        "Velapadi"
    ],
    "wof:name":"Velapadi",
    "wof:placetype":"locality",
    "wof:population":225
},
  "geometry": {"coordinates":[79.647524,11.408926],"type":"Point"}
}