{
  "type": "Feature",
  "properties": {
    "gn:admin1_code":"24",
    "gn:admin2_code":"128.0",
    "gn:asciiname":"Dhaturiya",
    "gn:country_code":"IN",
    "gn:dem":435,
    "gn:feature_class":"P",
    "gn:feature_code":"PPL",
    "gn:name":"Dhat\u016briya",
    "gn:population":0,
    "gn:timezone":"Asia/Kolkata",
    "iso:country":"IN",
    "wof:name":"Dhaturiya",
    "wof:placetype":"locality"
},
  "geometry": {"coordinates":[77.01791,25.26016],"type":"Point"}
}