{
  "type": "Feature",
  "properties": {
    "gn:admin1_code":"36",
    "gn:admin2_code":"185.0",
    "gn:asciiname":"Sikri",
    "gn:country_code":"IN",
    "gn:dem":97,
    "gn:feature_class":"P",
    "gn:feature_code":"PPL",
    "gn:name":"Sikri",
    "gn:population":0,
    "gn:timezone":"Asia/Kolkata",
    "iso:country":"IN",
    "name:ceb_x_preferred":[
        "Sikri"
    ],
    "name:swe_x_preferred":[
        "Sikri"
    ],
    "wof:name":"Sikri",
    "wof:placetype":"neighbourhood"
},
  "geometry": {"coordinates":[82.56135,26.92772],"type":"Point"}
}