{
  "type": "Feature",
  "properties": {
    "gn:admin1_code":"2.0",
    "gn:admin2_code":"544.0",
    "gn:asciiname":"Vagapalle",
    "gn:country_code":"IN",
    "gn:dem":934,
    "gn:feature_class":"P",
    "gn:feature_code":"PPL",
    "gn:name":"V\u0101gapalle",
    "gn:population":0,
    "gn:timezone":"Asia/Kolkata",
    "iso:country":"IN",
    "ks:ks_name":"Vakapalli",
    "ks:ks_pop":414,
    "ks:ks_type":"VILLAGE",
    "name:eng_x_preferred":[
        "Vakapalli"
    ],
    "name:eng_x_variant":[
        "Vagapalle"
    ],
    "wof:name":"Vakapalli",
    "wof:placetype":"locality",
    "wof:population":414
},
  "geometry": {"coordinates":[82.454087,18.105324],"type":"Point"}
}