{
  "type": "Feature",
  "properties": {
    "iso:country":"IN",
    "ks:ks_name":"Ramegoundensalai",
    "ks:ks_pop":328,
    "ks:ks_type":"HABITATION",
    "name:eng_x_preferred":[
        "Ramegoundensalai"
    ],
    "wof:name":"Ramegoundensalai",
    "wof:placetype":"locality",
    "wof:population":328
},
  "geometry": {"coordinates":[77.199973,11.405654],"type":"Point"}
}