{
  "type": "Feature",
  "properties": {
    "iso:country":"IN",
    "ks:ks_alt_nam":"kantadand",
    "ks:ks_name":"Kantadand",
    "ks:ks_pop":236,
    "ks:ks_type":"HABITATION",
    "name:eng_x_preferred":[
        "Kantadand"
    ],
    "wof:name":"Kantadand",
    "wof:placetype":"locality",
    "wof:population":236
},
  "geometry": {"coordinates":[83.19047999999999,22.537296],"type":"Point"}
}