{
  "type": "Feature",
  "properties": {
    "iso:country":"IN",
    "ks:ks_name":"Kharidpipal",
    "ks:ks_pop":1878,
    "ks:ks_type":"VILLAGE",
    "ks:ks_uagg_main":0,
    "name:eng_x_preferred":[
        "Kharidpipal"
    ],
    "wof:name":"Kharidpipal",
    "wof:placetype":"neighbourhood",
    "wof:population":1878
},
  "geometry": {"coordinates":[87.311886,21.706372],"type":"Point"}
}