{
  "type": "Feature",
  "properties": {
    "iso:country":"IN",
    "ks:ks_name":"Bhola Purva",
    "ks:ks_pop":185,
    "ks:ks_type":"HABITATION",
    "name:eng_x_preferred":[
        "Bhola Purva"
    ],
    "wof:name":"Bhola Purva",
    "wof:placetype":"locality",
    "wof:population":185
},
  "geometry": {"coordinates":[80.13448699999999,27.186618],"type":"Point"}
}