{
  "type": "Feature",
  "properties": {
    "gn:admin1_code":"2.0",
    "gn:admin2_code":"548",
    "gn:asciiname":"Ipuru",
    "gn:country_code":"IN",
    "gn:dem":127,
    "gn:feature_class":"P",
    "gn:feature_code":"PPL",
    "gn:name":"\u012ap\u016bru",
    "gn:population":0,
    "gn:timezone":"Asia/Kolkata",
    "iso:country":"IN",
    "name:und_x_variant":[
        "\u012ap\u016bru",
        "\u00cfp\u016bru"
    ],
    "wof:name":"Ipuru",
    "wof:placetype":"locality"
},
  "geometry": {"coordinates":[79.77509999999999,16.23038],"type":"Point"}
}