{
  "type": "Feature",
  "properties": {
    "gn:admin1_code":"25.0",
    "gn:admin2_code":"631.0",
    "gn:asciiname":"Doddakodipalti",
    "gn:country_code":"IN",
    "gn:dem":943,
    "gn:feature_class":"P",
    "gn:feature_code":"PPL",
    "gn:name":"Doddakodipalti",
    "gn:population":0,
    "gn:timezone":"Asia/Kolkata",
    "iso:country":"IN",
    "wof:name":"Doddakodipalti",
    "wof:placetype":"neighbourhood"
},
  "geometry": {"coordinates":[77.73332000000001,12.65366],"type":"Point"}
}