{
  "type": "Feature",
  "properties": {
    "iso:country":"IN",
    "ks:ks_name":"No.1 Dhola Bagan No.1 Dhola Te.120 133 Fs",
    "ks:ks_pop":2558,
    "ks:ks_type":"HABITATION",
    "name:eng_x_preferred":[
        "No.1 Dhola Bagan No.1 Dhola Te.120 133 Fs"
    ],
    "wof:name":"No.1 Dhola Bagan No.1 Dhola Te.120 133 Fs",
    "wof:placetype":"locality",
    "wof:population":2558
},
  "geometry": {"coordinates":[95.606301,27.755031],"type":"Point"}
}