{
  "type": "Feature",
  "properties": {
    "iso:country":"IN",
    "ks:ks_name":"Bilsari",
    "ks:ks_pop":0,
    "ks:ks_type":"VILLAGE",
    "name:eng_x_preferred":[
        "Bilsari"
    ],
    "wof:name":"Bilsari",
    "wof:placetype":"locality",
    "wof:population":0
},
  "geometry": {"coordinates":[82.430965,25.169328],"type":"Point"}
}