{
  "type": "Feature",
  "properties": {
    "iso:country":"IN",
    "ks:ks_name":"Brahman Toli",
    "ks:ks_pop":162,
    "ks:ks_type":"HABITATION",
    "name:eng_x_preferred":[
        "Brahman Toli"
    ],
    "wof:name":"Brahman Toli",
    "wof:placetype":"locality",
    "wof:population":162
},
  "geometry": {"coordinates":[84.387451,27.068539],"type":"Point"}
}