{
  "type": "Feature",
  "properties": {
    "iso:country":"IN",
    "ks:ks_name":"Hatholi",
    "ks:ks_pop":250,
    "ks:ks_type":"VILLAGE",
    "name:eng_x_preferred":[
        "Hatholi"
    ],
    "wof:name":"Hatholi",
    "wof:placetype":"locality",
    "wof:population":250
},
  "geometry": {"coordinates":[75.49856699999999,24.908419],"type":"Point"}
}