{
  "type": "Feature",
  "properties": {
    "iso:country":"IN",
    "ks:ks_alt_nam":"tutwali boudhwadi",
    "ks:ks_name":"Tutwali Boudhwadi",
    "ks:ks_pop":100,
    "ks:ks_type":"HABITATION",
    "name:eng_x_preferred":[
        "Tutwali Boudhwadi"
    ],
    "wof:name":"Tutwali Boudhwadi",
    "wof:placetype":"locality",
    "wof:population":100
},
  "geometry": {"coordinates":[73.513729,17.910617],"type":"Point"}
}