{
  "type": "Feature",
  "properties": {
    "gn:admin1_code":"11.0",
    "gn:admin2_code":"27.0",
    "gn:asciiname":"Pajaut",
    "gn:country_code":"IN",
    "gn:dem":2176,
    "gn:feature_class":"P",
    "gn:feature_code":"PPL",
    "gn:name":"Pajaut",
    "gn:population":0,
    "gn:timezone":"Asia/Kolkata",
    "iso:country":"IN",
    "wof:name":"Pajaut",
    "wof:placetype":"locality"
},
  "geometry": {"coordinates":[77.14733000000003,31.6701],"type":"Point"}
}