{
  "type": "Feature",
  "properties": {
    "iso:country":"IN",
    "ks:ks_name":"Aurahi",
    "ks:ks_pop":260,
    "ks:ks_type":"VILLAGE",
    "name:eng_x_preferred":[
        "Aurahi"
    ],
    "wof:name":"Aurahi",
    "wof:placetype":"locality",
    "wof:population":260
},
  "geometry": {"coordinates":[87.19480900000001,25.678794],"type":"Point"}
}