{
  "type": "Feature",
  "properties": {
    "iso:country":"IN",
    "ks:ks_name":"Hathor Teron Arong",
    "ks:ks_pop":256,
    "ks:ks_type":"HABITATION",
    "ks:ks_uagg_main":0,
    "name:eng_x_preferred":[
        "Hathor Teron Arong"
    ],
    "wof:name":"Hathor Teron Arong",
    "wof:placetype":"neighbourhood",
    "wof:population":256
},
  "geometry": {"coordinates":[92.738283,25.921077],"type":"Point"}
}