{
  "type": "Feature",
  "properties": {
    "iso:country":"IN",
    "ks:ks_name":"Patheri Gram",
    "ks:ks_pop":1234,
    "ks:ks_type":"VILLAGE",
    "ks:ks_uagg_main":0,
    "name:eng_x_preferred":[
        "Patheri Gram"
    ],
    "wof:name":"Patheri Gram",
    "wof:placetype":"neighbourhood",
    "wof:population":1234
},
  "geometry": {"coordinates":[92.694858,24.851337],"type":"Point"}
}