{
  "type": "Feature",
  "properties": {
    "iso:country":"IN",
    "ks:ks_name":"Pemmireddipalem",
    "ks:ks_pop":797,
    "ks:ks_type":"HABITATION",
    "name:eng_x_preferred":[
        "Pemmireddipalem"
    ],
    "wof:name":"Pemmireddipalem",
    "wof:placetype":"locality",
    "wof:population":797
},
  "geometry": {"coordinates":[82.168553,16.638816],"type":"Point"}
}