{
  "type": "Feature",
  "properties": {
    "iso:country":"IN",
    "ks:ks_alt_nam":"Nagpur chek",
    "ks:ks_name":"Nagpur Chek",
    "ks:ks_pop":233,
    "ks:ks_type":"HABITATION",
    "name:eng_x_preferred":[
        "Nagpur Chek"
    ],
    "wof:name":"Nagpur Chek",
    "wof:placetype":"locality",
    "wof:population":233
},
  "geometry": {"coordinates":[79.867082,19.902881],"type":"Point"}
}