{
  "type": "Feature",
  "properties": {
    "iso:country":"IN",
    "ks:ks_alt_nam":"Ad. tola",
    "ks:ks_name":"Ad. Tola",
    "ks:ks_pop":176,
    "ks:ks_type":"HABITATION",
    "name:eng_x_preferred":[
        "Ad. Tola"
    ],
    "wof:name":"Ad. Tola",
    "wof:placetype":"locality",
    "wof:population":176
},
  "geometry": {"coordinates":[86.68093,24.655149],"type":"Point"}
}