{
  "type": "Feature",
  "properties": {
    "iso:country":"IN",
    "ks:ks_name":"Subramanyadahalli",
    "ks:ks_pop":10,
    "ks:ks_type":"VILLAGE",
    "name:eng_x_preferred":[
        "Subramanyadahalli"
    ],
    "wof:name":"Subramanyadahalli",
    "wof:placetype":"locality",
    "wof:population":10
},
  "geometry": {"coordinates":[76.03554200000001,13.294574],"type":"Point"}
}