{
  "type": "Feature",
  "properties": {
    "iso:country":"IN",
    "ks:ks_name":"Majar Suba",
    "ks:ks_pop":79,
    "ks:ks_type":"HABITATION",
    "ks:ks_uagg_main":0,
    "name:eng_x_preferred":[
        "Majar Suba"
    ],
    "wof:name":"Majar Suba",
    "wof:placetype":"neighbourhood",
    "wof:population":79
},
  "geometry": {"coordinates":[91.477216,26.177407],"type":"Point"}
}