{
  "type": "Feature",
  "properties": {
    "iso:country":"IN",
    "ks:ks_name":"Nelagadde",
    "ks:ks_type":"VILLAGE",
    "name:eng_x_preferred":[
        "Nelagadde"
    ],
    "wof:name":"Nelagadde",
    "wof:placetype":"locality"
},
  "geometry": {"coordinates":[75.55917700000001,13.687797],"type":"Point"}
}