{
  "type": "Feature",
  "properties": {
    "gn:admin1_code":"19",
    "gn:admin2_code":"579.0",
    "gn:asciiname":"Sonath",
    "gn:country_code":"IN",
    "gn:dem":554,
    "gn:feature_class":"P",
    "gn:feature_code":"PPL",
    "gn:name":"Sonath",
    "gn:population":0,
    "gn:timezone":"Asia/Kolkata",
    "iso:country":"IN",
    "wof:name":"Sonath",
    "wof:placetype":"locality"
},
  "geometry": {"coordinates":[77.11069999999999,17.61185],"type":"Point"}
}