{
  "type": "Feature",
  "properties": {
    "iso:country":"IN",
    "ks:ks_name":"Chikana",
    "ks:ks_pop":2185,
    "ks:ks_type":"VILLAGE",
    "ks:ks_uagg_main":0,
    "name:eng_x_preferred":[
        "Chikana"
    ],
    "wof:name":"Chikana",
    "wof:placetype":"neighbourhood",
    "wof:population":2185
},
  "geometry": {"coordinates":[86.40560499999999,20.760152],"type":"Point"}
}