{
  "type": "Feature",
  "properties": {
    "gn:admin1_code":"19.0",
    "gn:admin2_code":"560",
    "gn:asciiname":"Hulihaidar",
    "gn:country_code":"IN",
    "gn:dem":517,
    "gn:feature_class":"P",
    "gn:feature_code":"PPL",
    "gn:name":"Hulihaidar",
    "gn:population":0,
    "gn:timezone":"Asia/Kolkata",
    "iso:country":"IN",
    "wof:name":"Hulihaidar",
    "wof:placetype":"locality"
},
  "geometry": {"coordinates":[76.39071,15.65911],"type":"Point"}
}