{
  "type": "Feature",
  "properties": {
    "gn:admin1_code":"36",
    "gn:admin2_code":"188.0",
    "gn:asciiname":"Daulatnagar",
    "gn:country_code":"IN",
    "gn:dem":85,
    "gn:feature_class":"P",
    "gn:feature_code":"PPL",
    "gn:name":"Daulatnagar",
    "gn:population":0,
    "gn:timezone":"Asia/Kolkata",
    "iso:country":"IN",
    "ks:ks_name":"Daulatnagar",
    "ks:ks_pop":342,
    "ks:ks_type":"HABITATION",
    "ks:ks_uagg_main":0,
    "name:eng_x_preferred":[
        "Daulatnagar"
    ],
    "wof:name":"Daulatnagar",
    "wof:placetype":"neighbourhood",
    "wof:population":342
},
  "geometry": {"coordinates":[83.251531,26.985538],"type":"Point"}
}