{
  "type": "Feature",
  "properties": {
    "iso:country":"IN",
    "ks:ks_name":"Shahila Balli",
    "ks:ks_pop":2961,
    "ks:ks_type":"VILLAGE",
    "name:eng_x_preferred":[
        "Shahila Balli"
    ],
    "wof:name":"Shahila Balli",
    "wof:placetype":"locality",
    "wof:population":2961
},
  "geometry": {"coordinates":[85.502753,26.261544],"type":"Point"}
}