{
  "type": "Feature",
  "properties": {
    "gn:admin1_code":"38.0",
    "gn:admin2_code":"347.0",
    "gn:asciiname":"Mandhania",
    "gn:country_code":"IN",
    "gn:dem":424,
    "gn:feature_class":"P",
    "gn:feature_code":"PPL",
    "gn:name":"Mandhani\u0101",
    "gn:population":0,
    "gn:timezone":"Asia/Kolkata",
    "iso:country":"IN",
    "ks:ks_name":"Mandhania",
    "ks:ks_pop":740,
    "ks:ks_type":"VILLAGE",
    "ks:ks_uagg_main":0,
    "name:eng_x_preferred":[
        "Mandhania"
    ],
    "wof:name":"Mandhania",
    "wof:placetype":"neighbourhood",
    "wof:population":740
},
  "geometry": {"coordinates":[85.276821,24.243699],"type":"Point"}
}