{
  "type": "Feature",
  "properties": {
    "iso:country":"IN",
    "ks:ks_name":"Thirumaligai",
    "ks:ks_pop":520,
    "ks:ks_type":"HABITATION",
    "name:eng_x_preferred":[
        "Thirumaligai"
    ],
    "wof:name":"Thirumaligai",
    "wof:placetype":"locality",
    "wof:population":520
},
  "geometry": {"coordinates":[77.720844,12.569574],"type":"Point"}
}