{
  "type": "Feature",
  "properties": {
    "iso:country":"IN",
    "ks:ks_name":"Peepli Pathar",
    "ks:ks_pop":106,
    "ks:ks_type":"VILLAGE",
    "name:eng_x_preferred":[
        "Peepli Pathar"
    ],
    "wof:name":"Peepli Pathar",
    "wof:placetype":"locality",
    "wof:population":106
},
  "geometry": {"coordinates":[74.660647,23.946897],"type":"Point"}
}