{
  "type": "Feature",
  "properties": {
    "gn:admin1_code":"10.0",
    "gn:admin2_code":"77.0",
    "gn:asciiname":"Gharonda",
    "gn:country_code":"IN",
    "gn:dem":229,
    "gn:feature_class":"P",
    "gn:feature_code":"PPL",
    "gn:name":"Gharonda",
    "gn:population":0,
    "gn:timezone":"Asia/Kolkata",
    "iso:country":"IN",
    "name:und_x_variant":[
        "Bishanpura"
    ],
    "wof:name":"Gharonda",
    "wof:placetype":"locality"
},
  "geometry": {"coordinates":[76.3282,29.27097],"type":"Point"}
}