{
  "type": "Feature",
  "properties": {
    "iso:country":"IN",
    "ks:ks_alt_nam":"GIRDHARSHAH",
    "ks:ks_name":"Girdharshah",
    "ks:ks_pop":337,
    "ks:ks_type":"HABITATION",
    "name:eng_x_preferred":[
        "Girdharshah"
    ],
    "wof:name":"Girdharshah",
    "wof:placetype":"locality",
    "wof:population":337
},
  "geometry": {"coordinates":[81.89482599999999,26.151556],"type":"Point"}
}