{
  "type": "Feature",
  "properties": {
    "iso:country":"IN",
    "ks:ks_name":"Nacharewadi",
    "ks:ks_pop":295,
    "ks:ks_type":"HABITATION",
    "name:eng_x_preferred":[
        "Nacharewadi"
    ],
    "wof:name":"Nacharewadi",
    "wof:placetype":"locality",
    "wof:population":295
},
  "geometry": {"coordinates":[73.541944,17.308333],"type":"Point"}
}