{
  "type": "Feature",
  "properties": {
    "iso:country":"IN",
    "ks:ks_name":"Pure Talwa",
    "ks:ks_pop":309,
    "ks:ks_type":"HABITATION",
    "name:eng_x_preferred":[
        "Pure Talwa"
    ],
    "wof:name":"Pure Talwa",
    "wof:placetype":"locality",
    "wof:population":309
},
  "geometry": {"coordinates":[81.71482899999999,27.230334],"type":"Point"}
}