{
  "type": "Feature",
  "properties": {
    "gn:admin1_code":"36.0",
    "gn:admin2_code":"179.0",
    "gn:asciiname":"Makhdumpur",
    "gn:country_code":"IN",
    "gn:dem":109,
    "gn:feature_class":"P",
    "gn:feature_code":"PPL",
    "gn:name":"Makhdumpur",
    "gn:population":0,
    "gn:timezone":"Asia/Kolkata",
    "iso:country":"IN",
    "ks:ks_name":"Makhdum Pur",
    "ks:ks_pop":298,
    "ks:ks_type":"VILLAGE",
    "ks:ks_uagg_main":0,
    "name:ben_x_preferred":[
        "\u09ae\u09be\u0996\u09a6\u09c1\u09ae\u09aa\u09c1\u09b0"
    ],
    "name:bpy_x_preferred":[
        "\u09ae\u09be\u0996\u09a6\u09c1\u09ae\u09aa\u09c1\u09b0"
    ],
    "name:eng_x_preferred":[
        "Makhdum Pur"
    ],
    "name:ita_x_preferred":[
        "Makhdumpur"
    ],
    "name:msa_x_preferred":[
        "Makhdumpur"
    ],
    "name:new_x_preferred":[
        "\u092e\u0916\u094d\u0926\u0941\u092e\u094d\u092a\u0941\u0930"
    ],
    "name:nld_x_preferred":[
        "Makhdumpur"
    ],
    "name:ori_x_preferred":[
        "\u0b2e\u0b16\u0b21\u0b2e\u0b2a\u0b41\u0b30"
    ],
    "name:por_x_preferred":[
        "Makhdumpur"
    ],
    "name:spa_x_preferred":[
        "Makhdumpur"
    ],
    "name:urd_x_preferred":[
        "\u0645\u062e\u062f\u0648\u0645 \u067e\u0648\u0631"
    ],
    "name:vie_x_preferred":[
        "Makhdumpur"
    ],
    "name:zho_x_preferred":[
        "\u9a6c\u514b\u675c\u59c6\u666e\u5c14"
    ],
    "wof:name":"Makhdum Pur",
    "wof:placetype":"neighbourhood",
    "wof:population":298
},
  "geometry": {"coordinates":[81.894403,26.499449],"type":"Point"}
}