{
  "type": "Feature",
  "properties": {
    "iso:country":"IN",
    "ks:ks_name":"Kasba Kachhi",
    "ks:ks_pop":296,
    "ks:ks_type":"VILLAGE",
    "name:eng_x_preferred":[
        "Kasba Kachhi"
    ],
    "wof:name":"Kasba Kachhi",
    "wof:placetype":"locality",
    "wof:population":296
},
  "geometry": {"coordinates":[78.096147,24.389669],"type":"Point"}
}