{
  "type": "Feature",
  "properties": {
    "iso:country":"IN",
    "ks:ks_name":"Gadit",
    "ks:ks_pop":304,
    "ks:ks_type":"HABITATION",
    "name:eng_x_preferred":[
        "Gadit"
    ],
    "wof:name":"Gadit",
    "wof:placetype":"locality",
    "wof:population":304
},
  "geometry": {"coordinates":[73.601951,22.354345],"type":"Point"}
}