{
  "type": "Feature",
  "properties": {
    "gn:admin1_code":"36.0",
    "gn:admin2_code":"143.0",
    "gn:asciiname":"Munrilal Ka Nagal",
    "gn:country_code":"IN",
    "gn:dem":193,
    "gn:feature_class":"P",
    "gn:feature_code":"PPL",
    "gn:name":"Munril\u0101l Ka Nagal",
    "gn:population":0,
    "gn:timezone":"Asia/Kolkata",
    "iso:country":"IN",
    "wof:name":"Munrilal Ka Nagal",
    "wof:placetype":"neighbourhood"
},
  "geometry": {"coordinates":[77.86853000000001,27.96057],"type":"Point"}
}