{
  "type": "Feature",
  "properties": {
    "iso:country":"IN",
    "ks:ks_name":"Dhantola Pt-ii",
    "ks:ks_pop":121,
    "ks:ks_type":"VILLAGE",
    "ks:ks_uagg_main":0,
    "name:eng_x_preferred":[
        "Dhantola Pt-ii"
    ],
    "wof:name":"Dhantola Pt-ii",
    "wof:placetype":"neighbourhood",
    "wof:population":121
},
  "geometry": {"coordinates":[90.999905,26.013719],"type":"Point"}
}