{
  "type": "Feature",
  "properties": {
    "iso:country":"IN",
    "ks:ks_name":"Leliri",
    "ks:ks_pop":108,
    "ks:ks_type":"VILLAGE",
    "name:eng_x_preferred":[
        "Leliri"
    ],
    "wof:name":"Leliri",
    "wof:placetype":"locality",
    "wof:population":108
},
  "geometry": {"coordinates":[83.25446100000001,19.130739],"type":"Point"}
}