{
  "type": "Feature",
  "properties": {
    "iso:country":"IN",
    "ks:ks_name":"Manjgawn",
    "ks:ks_pop":638,
    "ks:ks_type":"HABITATION",
    "name:eng_x_preferred":[
        "Manjgawn"
    ],
    "wof:name":"Manjgawn",
    "wof:placetype":"locality",
    "wof:population":638
},
  "geometry": {"coordinates":[80.35947,24.145943],"type":"Point"}
}