{
  "type": "Feature",
  "properties": {
    "gn:admin1_code":"35",
    "gn:admin2_code":"442.0",
    "gn:asciiname":"Khanjarpura",
    "gn:country_code":"IN",
    "gn:dem":457,
    "gn:feature_class":"P",
    "gn:feature_code":"PPL",
    "gn:name":"Khanjarpura",
    "gn:population":0,
    "gn:timezone":"Asia/Kolkata",
    "iso:country":"IN",
    "ks:ks_name":"Khanjarpur",
    "ks:ks_pop":446,
    "ks:ks_type":"HABITATION",
    "name:eng_x_preferred":[
        "Khanjarpur"
    ],
    "name:eng_x_variant":[
        "Khanjarpura"
    ],
    "wof:name":"Khanjarpur",
    "wof:placetype":"locality",
    "wof:population":446
},
  "geometry": {"coordinates":[76.544301,23.819341],"type":"Point"}
}