{
  "type": "Feature",
  "properties": {
    "gn:admin1_code":"35",
    "gn:admin2_code":"442.0",
    "gn:asciiname":"Khanjarpura",
    "gn:country_code":"IN",
    "gn:dem":457,
    "gn:feature_class":"P",
    "gn:feature_code":"PPL",
    "gn:name":"Khanjarpura",
    "gn:population":0,
    "gn:timezone":"Asia/Kolkata",
    "iso:country":"IN",
    "wof:name":"Khanjarpura",
    "wof:placetype":"locality"
},
  "geometry": {"coordinates":[76.54181,23.81878],"type":"Point"}
}