{
  "type": "Feature",
  "properties": {
    "iso:country":"IN",
    "ks:ks_name":"Tinitina Palli",
    "ks:ks_pop":109,
    "ks:ks_type":"VILLAGE",
    "name:eng_x_preferred":[
        "Tinitina Palli"
    ],
    "wof:name":"Tinitina Palli",
    "wof:placetype":"locality",
    "wof:population":109
},
  "geometry": {"coordinates":[84.56426,19.621499],"type":"Point"}
}