{
  "type": "Feature",
  "properties": {
    "iso:country":"IN",
    "ks:ks_name":"Kunda",
    "ks:ks_pop":459,
    "ks:ks_type":"VILLAGE",
    "name:eng_x_preferred":[
        "Kunda"
    ],
    "wof:name":"Kunda",
    "wof:placetype":"locality",
    "wof:population":459
},
  "geometry": {"coordinates":[73.96947400000001,21.925263],"type":"Point"}
}