{
  "type": "Feature",
  "properties": {
    "gn:admin1_code":"19.0",
    "gn:admin2_code":"584.0",
    "gn:asciiname":"Alalsandra",
    "gn:country_code":"IN",
    "gn:dem":671,
    "gn:feature_class":"P",
    "gn:feature_code":"PPL",
    "gn:name":"Al\u0101lsandra",
    "gn:population":0,
    "gn:timezone":"Asia/Kolkata",
    "iso:country":"IN",
    "wof:name":"Alalsandra",
    "wof:placetype":"locality"
},
  "geometry": {"coordinates":[77.27559000000002,12.5795],"type":"Point"}
}