{
  "type": "Feature",
  "properties": {
    "gn:admin1_code":"35",
    "gn:admin2_code":"456.0",
    "gn:asciiname":"Piparwani",
    "gn:country_code":"IN",
    "gn:dem":356,
    "gn:feature_class":"P",
    "gn:feature_code":"PPL",
    "gn:name":"P\u012bparw\u0101ni",
    "gn:population":0,
    "gn:timezone":"Asia/Kolkata",
    "iso:country":"IN",
    "name:und_x_variant":[
        "P\u012bparw\u0101ni",
        "Piparw\u0101ni"
    ],
    "wof:name":"Piparwani",
    "wof:placetype":"locality"
},
  "geometry": {"coordinates":[79.57014000000002,21.66041],"type":"Point"}
}