{
  "type": "Feature",
  "properties": {
    "iso:country":"IN",
    "ks:ks_name":"Teja Dumri 4 Annas",
    "ks:ks_pop":0,
    "ks:ks_type":"VILLAGE",
    "name:eng_x_preferred":[
        "Teja Dumri 4 Annas"
    ],
    "wof:name":"Teja Dumri 4 Annas",
    "wof:placetype":"locality",
    "wof:population":0
},
  "geometry": {"coordinates":[84.969483,26.002136],"type":"Point"}
}