{
  "type": "Feature",
  "properties": {
    "iso:country":"IN",
    "ks:ks_alt_nam":"Menmeji Tisso gaon",
    "ks:ks_name":"Menmeji Tisso Gaon",
    "ks:ks_pop":96,
    "ks:ks_type":"HABITATION",
    "ks:ks_uagg_main":0,
    "name:eng_x_preferred":[
        "Menmeji Tisso Gaon"
    ],
    "wof:name":"Menmeji Tisso Gaon",
    "wof:placetype":"neighbourhood",
    "wof:population":96
},
  "geometry": {"coordinates":[92.799314,25.901358],"type":"Point"}
}