{
  "type": "Feature",
  "properties": {
    "iso:country":"IN",
    "ks:ks_name":"Pratap Nagar",
    "ks:ks_pop":478,
    "ks:ks_type":"HABITATION",
    "name:eng_x_preferred":[
        "Pratap Nagar"
    ],
    "wof:name":"Pratap Nagar",
    "wof:placetype":"locality",
    "wof:population":478
},
  "geometry": {"coordinates":[74.825557,16.512944],"type":"Point"}
}