{
  "type": "Feature",
  "properties": {
    "iso:country":"IN",
    "ks:ks_name":"Neralakatte",
    "ks:ks_pop":387,
    "ks:ks_type":"HABITATION",
    "name:eng_x_preferred":[
        "Neralakatte"
    ],
    "wof:name":"Neralakatte",
    "wof:placetype":"locality",
    "wof:population":387
},
  "geometry": {"coordinates":[75.505854,12.691893],"type":"Point"}
}