{
  "type": "Feature",
  "properties": {
    "iso:country":"IN",
    "ks:ks_name":"Patalipura",
    "ks:ks_pop":626,
    "ks:ks_type":"VILLAGE",
    "name:eng_x_preferred":[
        "Patalipura"
    ],
    "wof:name":"Patalipura",
    "wof:placetype":"locality",
    "wof:population":626
},
  "geometry": {"coordinates":[86.857249,21.636944],"type":"Point"}
}