{
  "type": "Feature",
  "properties": {
    "iso:country":"IN",
    "ks:ks_name":"Nizampur",
    "ks:ks_pop":315,
    "ks:ks_type":"VILLAGE",
    "name:eng_x_preferred":[
        "Nizampur"
    ],
    "wof:name":"Nizampur",
    "wof:placetype":"locality",
    "wof:population":315
},
  "geometry": {"coordinates":[77.787926,29.690074],"type":"Point"}
}