{
  "type": "Feature",
  "properties": {
    "gn:admin1_code":"36",
    "gn:admin2_code":"162.0",
    "gn:asciiname":"Nagla Makka",
    "gn:country_code":"IN",
    "gn:dem":145,
    "gn:feature_class":"P",
    "gn:feature_code":"PPL",
    "gn:name":"Nagla Makka",
    "gn:population":0,
    "gn:timezone":"Asia/Kolkata",
    "iso:country":"IN",
    "wof:name":"Nagla Makka",
    "wof:placetype":"locality"
},
  "geometry": {"coordinates":[79.59378000000002,26.60502],"type":"Point"}
}