{
  "type": "Feature",
  "properties": {
    "iso:country":"IN",
    "ks:ks_alt_nam":"Badanav\u0101di Reserved Forest",
    "ks:ks_name":"Badanavadi Reserved Forest",
    "ks:ks_pop":129,
    "ks:ks_type":"VILLAGE",
    "name:eng_x_preferred":[
        "Badanavadi Reserved Forest"
    ],
    "name:eng_x_variant":[
        "Badanav\u0101di Reserved Forest"
    ],
    "wof:name":"Badanavadi Reserved Forest",
    "wof:placetype":"locality",
    "wof:population":129
},
  "geometry": {"coordinates":[77.72221,11.99747],"type":"Point"}
}