{
  "type": "Feature",
  "properties": {
    "iso:country":"IN",
    "ks:ks_alt_nam":"CHAKARBHATHA",
    "ks:ks_name":"Chakarbhatha",
    "ks:ks_pop":280,
    "ks:ks_type":"HABITATION",
    "name:eng_x_preferred":[
        "Chakarbhatha"
    ],
    "wof:name":"Chakarbhatha",
    "wof:placetype":"locality",
    "wof:population":280
},
  "geometry": {"coordinates":[82.15048,22.423041],"type":"Point"}
}