{
  "type": "Feature",
  "properties": {
    "iso:country":"IN",
    "ks:ks_name":"Lwesar",
    "ks:ks_pop":85,
    "ks:ks_type":"HABITATION",
    "name:eng_x_preferred":[
        "Lwesar"
    ],
    "wof:name":"Lwesar",
    "wof:placetype":"locality",
    "wof:population":85
},
  "geometry": {"coordinates":[80.022854,29.697738],"type":"Point"}
}