{
  "type": "Feature",
  "properties": {
    "iso:country":"IN",
    "ks:ks_name":"Kalmidadar",
    "ks:ks_pop":48,
    "ks:ks_type":"VILLAGE",
    "name:eng_x_preferred":[
        "Kalmidadar"
    ],
    "wof:name":"Kalmidadar",
    "wof:placetype":"locality",
    "wof:population":48
},
  "geometry": {"coordinates":[82.273546,20.718962],"type":"Point"}
}