{
  "type": "Feature",
  "properties": {
    "iso:country":"IN",
    "ks:ks_name":"Saladaranga",
    "ks:ks_pop":25,
    "ks:ks_type":"HABITATION",
    "name:eng_x_preferred":[
        "Saladaranga"
    ],
    "wof:name":"Saladaranga",
    "wof:placetype":"locality",
    "wof:population":25
},
  "geometry": {"coordinates":[84.192609,20.611077],"type":"Point"}
}