{
  "type": "Feature",
  "properties": {
    "iso:country":"IN",
    "ks:ks_name":"Mukansar",
    "ks:ks_pop":330,
    "ks:ks_type":"VILLAGE",
    "name:eng_x_preferred":[
        "Mukansar"
    ],
    "wof:name":"Mukansar",
    "wof:placetype":"locality",
    "wof:population":330
},
  "geometry": {"coordinates":[72.63091799999999,26.366037],"type":"Point"}
}