{
  "type": "Feature",
  "properties": {
    "iso:country":"IN",
    "ks:ks_name":"Nagochiwadi",
    "ks:ks_pop":185,
    "ks:ks_type":"HABITATION",
    "name:eng_x_preferred":[
        "Nagochiwadi"
    ],
    "wof:name":"Nagochiwadi",
    "wof:placetype":"locality",
    "wof:population":185
},
  "geometry": {"coordinates":[73.483947,16.229044],"type":"Point"}
}