{
  "type": "Feature",
  "properties": {
    "gn:admin1_code":"16.0",
    "gn:admin2_code":"505.0",
    "gn:asciiname":"Maskhapra",
    "gn:country_code":"IN",
    "gn:dem":504,
    "gn:feature_class":"P",
    "gn:feature_code":"PPL",
    "gn:name":"Maskh\u0101pra",
    "gn:population":0,
    "gn:timezone":"Asia/Kolkata",
    "iso:country":"IN",
    "wof:name":"Maskhapra",
    "wof:placetype":"locality"
},
  "geometry": {"coordinates":[78.68930999999998,21.31618],"type":"Point"}
}