{
  "type": "Feature",
  "properties": {
    "gn:admin1_code":"40.0",
    "gn:admin2_code":"534.0",
    "gn:asciiname":"Yatanaram",
    "gn:country_code":"IN",
    "gn:dem":121,
    "gn:feature_class":"P",
    "gn:feature_code":"PPL",
    "gn:name":"Y\u0101tan\u0101ram",
    "gn:population":0,
    "gn:timezone":"Asia/Kolkata",
    "iso:country":"IN",
    "ks:ks_name":"Yetnaram",
    "ks:ks_pop":414,
    "ks:ks_type":"VILLAGE",
    "name:eng_x_preferred":[
        "Yetnaram"
    ],
    "name:eng_x_variant":[
        "Yatanaram"
    ],
    "wof:name":"Yetnaram",
    "wof:placetype":"locality",
    "wof:population":414
},
  "geometry": {"coordinates":[80.149058,18.574759],"type":"Point"}
}