{
  "type": "Feature",
  "properties": {
    "gn:admin1_code":"12.0",
    "gn:admin2_code":"002",
    "gn:asciiname":"Barzul",
    "gn:country_code":"IN",
    "gn:dem":1590,
    "gn:feature_class":"P",
    "gn:feature_code":"PPL",
    "gn:name":"Barzul",
    "gn:population":0,
    "gn:timezone":"Asia/Kolkata",
    "iso:country":"IN",
    "name:ara_x_preferred":[
        "\u0628\u0631\u0632\u0648\u0644"
    ],
    "name:aze_x_preferred":[
        "B\u0259rzul"
    ],
    "name:ceb_x_preferred":[
        "Barz\u016bl"
    ],
    "name:fas_x_preferred":[
        "\u0628\u0631\u0632\u0648\u0644"
    ],
    "name:mlg_x_preferred":[
        "Barzul"
    ],
    "name:msa_x_preferred":[
        "Barzul"
    ],
    "name:swe_x_preferred":[
        "Barz\u016bl"
    ],
    "name:tur_x_preferred":[
        "Berzul"
    ],
    "wof:name":"Barzul",
    "wof:placetype":"neighbourhood"
},
  "geometry": {"coordinates":[74.79819000000001,34.05146],"type":"Point"}
}