{
  "type": "Feature",
  "properties": {
    "iso:country":"IN",
    "ks:ks_name":"Hongalavadi",
    "ks:ks_pop":383,
    "ks:ks_type":"VILLAGE",
    "name:eng_x_preferred":[
        "Hongalavadi"
    ],
    "wof:name":"Hongalavadi",
    "wof:placetype":"locality",
    "wof:population":383
},
  "geometry": {"coordinates":[77.022097,11.857974],"type":"Point"}
}