{
  "type": "Feature",
  "properties": {
    "iso:country":"IN",
    "ks:ks_alt_nam":"DHUNDHAN KATALA",
    "ks:ks_name":"Dhundhan Katala",
    "ks:ks_pop":110,
    "ks:ks_type":"HABITATION",
    "name:eng_x_preferred":[
        "Dhundhan Katala"
    ],
    "wof:name":"Dhundhan Katala",
    "wof:placetype":"locality",
    "wof:population":110
},
  "geometry": {"coordinates":[70.99982799999999,25.393586],"type":"Point"}
}