{
  "type": "Feature",
  "properties": {
    "gn:admin1_code":"40.0",
    "gn:admin2_code":"532.0",
    "gn:asciiname":"Baregudem",
    "gn:country_code":"IN",
    "gn:dem":173,
    "gn:feature_class":"P",
    "gn:feature_code":"PPL",
    "gn:name":"B\u0101regudem",
    "gn:population":0,
    "gn:timezone":"Asia/Kolkata",
    "iso:country":"IN",
    "wof:name":"Baregudem",
    "wof:placetype":"locality"
},
  "geometry": {"coordinates":[79.72695999999998,19.44649],"type":"Point"}
}