{
  "type": "Feature",
  "properties": {
    "iso:country":"IN",
    "ks:ks_name":"Gattu Purwa",
    "ks:ks_pop":256,
    "ks:ks_type":"HABITATION",
    "name:eng_x_preferred":[
        "Gattu Purwa"
    ],
    "wof:name":"Gattu Purwa",
    "wof:placetype":"locality",
    "wof:population":256
},
  "geometry": {"coordinates":[81.061352,25.257903],"type":"Point"}
}