{
  "type": "Feature",
  "properties": {
    "iso:country":"IN",
    "ks:ks_alt_nam":"AHIR TOLI",
    "ks:ks_name":"Ahir Toli",
    "ks:ks_pop":609,
    "ks:ks_type":"HABITATION",
    "name:eng_x_preferred":[
        "Ahir Toli"
    ],
    "wof:name":"Ahir Toli",
    "wof:placetype":"locality",
    "wof:population":609
},
  "geometry": {"coordinates":[84.056648,25.451072],"type":"Point"}
}