{
  "type": "Feature",
  "properties": {
    "iso:country":"IN",
    "ks:ks_name":"Bheemaganipalle",
    "ks:ks_pop":4809,
    "ks:ks_type":"VILLAGE",
    "ks:ks_uagg_main":0,
    "name:eng_x_preferred":[
        "Bheemaganipalle"
    ],
    "wof:name":"Bheemaganipalle",
    "wof:placetype":"locality",
    "wof:population":4809
},
  "geometry": {"coordinates":[78.55917599999999,13.383057],"type":"Point"}
}