{
  "type": "Feature",
  "properties": {
    "gn:admin1_code":"21",
    "gn:admin2_code":"375.0",
    "gn:asciiname":"Kundrupani",
    "gn:country_code":"IN",
    "gn:dem":553,
    "gn:feature_class":"P",
    "gn:feature_code":"PPL",
    "gn:name":"Kundrup\u0101ni",
    "gn:population":0,
    "gn:timezone":"Asia/Kolkata",
    "iso:country":"IN",
    "ks:ks_name":"Kundurupani",
    "ks:ks_pop":349,
    "ks:ks_type":"VILLAGE",
    "name:eng_x_preferred":[
        "Kundurupani"
    ],
    "name:eng_x_variant":[
        "Kundrupani"
    ],
    "wof:name":"Kundurupani",
    "wof:placetype":"locality",
    "wof:population":349
},
  "geometry": {"coordinates":[85.365353,21.977391],"type":"Point"}
}