{
  "type": "Feature",
  "properties": {
    "gn:admin1_code":"21",
    "gn:admin2_code":"375.0",
    "gn:asciiname":"Kundrupani",
    "gn:country_code":"IN",
    "gn:dem":553,
    "gn:feature_class":"P",
    "gn:feature_code":"PPL",
    "gn:name":"Kundrup\u0101ni",
    "gn:population":0,
    "gn:timezone":"Asia/Kolkata",
    "iso:country":"IN",
    "wof:name":"Kundrupani",
    "wof:placetype":"locality"
},
  "geometry": {"coordinates":[85.36632,21.9818],"type":"Point"}
}