{
  "type": "Feature",
  "properties": {
    "iso:country":"IN",
    "ks:ks_name":"Pandor Faliya",
    "ks:ks_pop":421,
    "ks:ks_type":"HABITATION",
    "name:eng_x_preferred":[
        "Pandor Faliya"
    ],
    "wof:name":"Pandor Faliya",
    "wof:placetype":"locality",
    "wof:population":421
},
  "geometry": {"coordinates":[73.857861,23.304722],"type":"Point"}
}