{
  "type": "Feature",
  "properties": {
    "gn:admin1_code":"16",
    "gn:admin2_code":"510.0",
    "gn:asciiname":"Mandva",
    "gn:country_code":"IN",
    "gn:dem":305,
    "gn:feature_class":"P",
    "gn:feature_code":"PPL",
    "gn:name":"M\u0101ndva",
    "gn:population":0,
    "gn:timezone":"Asia/Kolkata",
    "iso:country":"IN",
    "name:guj_x_preferred":[
        "\u0aae\u0abe\u0a82\u0aa1\u0ab5\u0abe \u0aac\u0ac1\u0a9d\u0ab0\u0acd\u0a97"
    ],
    "name:ita_x_preferred":[
        "Mandwa"
    ],
    "wof:name":"Mandva",
    "wof:placetype":"locality"
},
  "geometry": {"coordinates":[78.39407,20.08024],"type":"Point"}
}