{
  "type": "Feature",
  "properties": {
    "gn:admin1_code":"37",
    "gn:admin2_code":"404.0",
    "gn:asciiname":"Lamna",
    "gn:country_code":"IN",
    "gn:dem":439,
    "gn:feature_class":"P",
    "gn:feature_code":"PPL",
    "gn:name":"Lamna",
    "gn:population":0,
    "gn:timezone":"Asia/Kolkata",
    "iso:country":"IN",
    "name:und_x_variant":[
        "Nemna"
    ],
    "wof:name":"Lamna",
    "wof:placetype":"locality"
},
  "geometry": {"coordinates":[82.48283000000001,22.75158],"type":"Point"}
}