{
  "type": "Feature",
  "properties": {
    "iso:country":"IN",
    "ks:ks_alt_nam":"KEBAT TOLA",
    "ks:ks_name":"Kebat Tola",
    "ks:ks_pop":648,
    "ks:ks_type":"HABITATION",
    "name:eng_x_preferred":[
        "Kebat Tola"
    ],
    "wof:name":"Kebat Tola",
    "wof:placetype":"locality",
    "wof:population":648
},
  "geometry": {"coordinates":[86.76504799999999,26.441766],"type":"Point"}
}