{
  "type": "Feature",
  "properties": {
    "iso:country":"IN",
    "ks:ks_name":"Maranayakanahalli",
    "ks:ks_pop":225,
    "ks:ks_type":"HABITATION",
    "name:eng_x_preferred":[
        "Maranayakanahalli"
    ],
    "wof:name":"Maranayakanahalli",
    "wof:placetype":"locality",
    "wof:population":225
},
  "geometry": {"coordinates":[76.264365,13.006942],"type":"Point"}
}