{
  "type": "Feature",
  "properties": {
    "gn:admin1_code":"21",
    "gn:admin2_code":"392.0",
    "gn:asciiname":"Sarasdadar",
    "gn:country_code":"IN",
    "gn:dem":156,
    "gn:feature_class":"P",
    "gn:feature_code":"PPL",
    "gn:name":"S\u0101rasd\u0101dar",
    "gn:population":0,
    "gn:timezone":"Asia/Kolkata",
    "iso:country":"IN",
    "ks:ks_alt_nam":"S\u0101rasd\u0101dar",
    "ks:ks_name":"Sarasdadar",
    "ks:ks_type":"VILLAGE",
    "name:eng_x_preferred":[
        "Sarasdadar"
    ],
    "name:eng_x_variant":[
        "S\u0101rasd\u0101dar"
    ],
    "wof:name":"Sarasdadar",
    "wof:placetype":"locality"
},
  "geometry": {"coordinates":[83.98464,21.036066],"type":"Point"}
}