{
  "type": "Feature",
  "properties": {
    "iso:country":"IN",
    "ks:ks_alt_nam":"Khiratwadi- dhangarwadi",
    "ks:ks_name":"Khiratwadi- Dhangarwadi",
    "ks:ks_pop":196,
    "ks:ks_type":"HABITATION",
    "name:eng_x_preferred":[
        "Khiratwadi- Dhangarwadi"
    ],
    "wof:name":"Khiratwadi- Dhangarwadi",
    "wof:placetype":"locality",
    "wof:population":196
},
  "geometry": {"coordinates":[73.297837,18.925453],"type":"Point"}
}