{
  "type": "Feature",
  "properties": {
    "iso:country":"IN",
    "ks:ks_alt_nam":"Niz-Salmara part 1",
    "ks:ks_name":"Niz-salmara Part 1",
    "ks:ks_pop":397,
    "ks:ks_type":"HABITATION",
    "name:eng_x_preferred":[
        "Niz-salmara Part 1"
    ],
    "wof:name":"Niz-salmara Part 1",
    "wof:placetype":"locality",
    "wof:population":397
},
  "geometry": {"coordinates":[91.852315,26.316189],"type":"Point"}
}