{
  "type": "Feature",
  "properties": {
    "iso:country":"IN",
    "ks:ks_name":"Bhanwatipura",
    "ks:ks_pop":351,
    "ks:ks_type":"VILLAGE",
    "name:eng_x_preferred":[
        "Bhanwatipura"
    ],
    "wof:name":"Bhanwatipura",
    "wof:placetype":"locality",
    "wof:population":351
},
  "geometry": {"coordinates":[76.989228,25.231372],"type":"Point"}
}