{
  "type": "Feature",
  "properties": {
    "gn:admin1_code":"25.0",
    "gn:admin2_code":"631.0",
    "gn:asciiname":"Nellumaru Agraharam",
    "gn:country_code":"IN",
    "gn:dem":971,
    "gn:feature_class":"P",
    "gn:feature_code":"PPL",
    "gn:name":"Nellum\u0101ru Agrah\u0101ram",
    "gn:population":0,
    "gn:timezone":"Asia/Kolkata",
    "iso:country":"IN",
    "wof:name":"Nellumaru Agraharam",
    "wof:placetype":"locality"
},
  "geometry": {"coordinates":[77.6223,12.55851],"type":"Point"}
}