{
  "type": "Feature",
  "properties": {
    "iso:country":"IN",
    "ks:ks_name":"Upadhyay Purwa",
    "ks:ks_pop":200,
    "ks:ks_type":"HABITATION",
    "name:eng_x_preferred":[
        "Upadhyay Purwa"
    ],
    "wof:name":"Upadhyay Purwa",
    "wof:placetype":"locality",
    "wof:population":200
},
  "geometry": {"coordinates":[81.103521,25.143315],"type":"Point"}
}