{
  "type": "Feature",
  "properties": {
    "iso:country":"IN",
    "ks:ks_alt_nam":"Chubba Chhangay I ii",
    "ks:ks_name":"Chubba Chhangay I Ii",
    "ks:ks_pop":1505,
    "ks:ks_type":"HABITATION",
    "name:eng_x_preferred":[
        "Chubba Chhangay I Ii"
    ],
    "wof:name":"Chubba Chhangay I Ii",
    "wof:placetype":"locality",
    "wof:population":1505
},
  "geometry": {"coordinates":[88.678318,27.140578],"type":"Point"}
}