{
  "type": "Feature",
  "properties": {
    "iso:country":"IN",
    "ks:ks_name":"Relawa",
    "ks:ks_pop":476,
    "ks:ks_type":"HABITATION",
    "name:eng_x_preferred":[
        "Relawa"
    ],
    "wof:name":"Relawa",
    "wof:placetype":"locality",
    "wof:population":476
},
  "geometry": {"coordinates":[73.79575,23.333694],"type":"Point"}
}