{
  "type": "Feature",
  "properties": {
    "iso:country":"IN",
    "ks:ks_name":"Jamri",
    "ks:ks_pop":45,
    "ks:ks_type":"VILLAGE",
    "name:eng_x_preferred":[
        "Jamri"
    ],
    "wof:name":"Jamri",
    "wof:placetype":"locality",
    "wof:population":45
},
  "geometry": {"coordinates":[87.467642,24.604638],"type":"Point"}
}