{
  "type": "Feature",
  "properties": {
    "iso:country":"IN",
    "name:ara_x_preferred":[
        "\u0645\u0627\u064a\u062b\u0646"
    ],
    "name:ben_bn_x_preferred":[
        "\u09ae\u09be\u0987\u09a5\u09be\u09a8"
    ],
    "name:ben_in_x_preferred":[
        "\u09ae\u09be\u0987\u09a5\u09be\u09a8"
    ],
    "name:eng_x_preferred":[
        "Maithan"
    ],
    "name:guj_x_preferred":[
        "\u0aae\u0ac8\u0aa5\u0abe\u0aa8"
    ],
    "name:hin_x_preferred":[
        "\u092e\u0948\u0925\u0928"
    ],
    "name:kan_x_preferred":[
        "\u0cae\u0cc8\u0ca5\u0cbe\u0ca8\u0ccd"
    ],
    "name:mal_x_preferred":[
        "\u0d2e\u0d48\u0d24\u0d3e\u0d7b"
    ],
    "name:mar_x_preferred":[
        "\u092e\u0948\u0925\u0928"
    ],
    "name:pan_x_preferred":[
        "\u0a2e\u0a48\u0a25\u0a3e\u0a28"
    ],
    "name:tam_x_preferred":[
        "\u0bae\u0bc8\u0ba4\u0bbe\u0ba9\u0bcd"
    ],
    "name:tel_x_preferred":[
        "\u0c2e\u0c48\u0c25\u0c3e\u0c28\u0c4d"
    ],
    "name:und_x_variant":[
        "M\u0101\u012bthan"
    ],
    "name:urd_x_preferred":[
        "\u0645\u06cc\u062a\u06be\u0646"
    ],
    "qs:gn_adm0_cc":"IN",
    "qs:gn_fcode":"PPLX",
    "qs:gn_local":1279259,
    "qs:gn_nam_loc":"Agra, Agra, Uttar Pradesh, IN",
    "qs:gn_namadm1":"36",
    "qs:gn_name":"M\u0101\u012bthan",
    "qs:local_max":10925,
    "qs:local_sum":42779,
    "qs:localhoods":21,
    "qs:name":"Maithan",
    "qs:name_adm0":"India",
    "qs:name_adm1":"Uttar Pradesh",
    "qs:name_adm2":"Agra",
    "qs:name_local":"Agra",
    "qs:photo_max":647,
    "qs:photo_sum":8508,
    "qs:placetype":"Suburb",
    "qs:quad_count":156,
    "qs:woe_adm0":23424848,
    "qs:woe_adm1":2345760,
    "qs:woe_adm2":12586712,
    "qs:woe_lau":0,
    "qs:woe_local":2295399,
    "qs:woe_ver":"7.10.0",
    "wof:lang":[
        "eng"
    ],
    "wof:name":"Maithan",
    "wof:placetype":"neighbourhood"
},
  "geometry": {"coordinates":[78.014847,27.180428],"type":"Point"}
}