{
  "type": "Feature",
  "properties": {
    "iso:country":"IN",
    "name:eng_x_preferred":[
        "Maithan"
    ],
    "name:und_x_preferred":[
        "M\u0101\u012bthan"
    ],
    "name:unk_x_variant":[
        "Maithan"
    ],
    "qs:gn_adm0_cc":"IN",
    "qs:gn_fcode":"PPLX",
    "qs:gn_local":1279259,
    "qs:gn_nam_loc":"Agra, Agra, Uttar Pradesh, IN",
    "qs:gn_namadm1":"36",
    "qs:gn_name":"M\u0101\u012bthan",
    "qs:local_max":10925,
    "qs:local_sum":42779,
    "qs:localhoods":21,
    "qs:name":"Maithan",
    "qs:name_adm0":"India",
    "qs:name_adm1":"Uttar Pradesh",
    "qs:name_adm2":"Agra",
    "qs:name_local":"Agra",
    "qs:photo_max":647,
    "qs:photo_sum":8508,
    "qs:placetype":"Suburb",
    "qs:quad_count":156,
    "qs:woe_adm0":23424848,
    "qs:woe_adm1":2345760,
    "qs:woe_adm2":12586712,
    "qs:woe_lau":0,
    "qs:woe_local":2295399,
    "qs:woe_ver":"7.10.0",
    "wof:lang":[
        "eng"
    ],
    "wof:name":"Maithan",
    "wof:placetype":"neighbourhood"
},
  "geometry": {"coordinates":[78.014847,27.180428],"type":"Point"}
}