{
  "type": "Feature",
  "properties": {
    "iso:country":"IN",
    "ks:ks_alt_nam":"Sa\u012bd\u0101b\u0101d",
    "ks:ks_name":"Saidabad",
    "ks:ks_type":"VILLAGE",
    "name:eng_x_preferred":[
        "Saidabad"
    ],
    "name:eng_x_variant":[
        "Sa\u012bd\u0101b\u0101d"
    ],
    "wof:name":"Saidabad",
    "wof:placetype":"locality"
},
  "geometry": {"coordinates":[78.416658,28.790289],"type":"Point"}
}