{
  "type": "Feature",
  "properties": {
    "gn:admin1_code":"24",
    "gn:admin2_code":"119.0",
    "gn:asciiname":"Singaria",
    "gn:country_code":"IN",
    "gn:dem":476,
    "gn:feature_class":"P",
    "gn:feature_code":"PPL",
    "gn:name":"Sing\u0101ria",
    "gn:population":0,
    "gn:timezone":"Asia/Kolkata",
    "iso:country":"IN",
    "wof:name":"Singaria",
    "wof:placetype":"locality"
},
  "geometry": {"coordinates":[74.30906,26.05292],"type":"Point"}
}