{
  "type": "Feature",
  "properties": {
    "iso:country":"IN",
    "ks:ks_name":"Elakania",
    "ks:ks_pop":465,
    "ks:ks_type":"VILLAGE",
    "name:eng_x_preferred":[
        "Elakania"
    ],
    "wof:name":"Elakania",
    "wof:placetype":"locality",
    "wof:population":465
},
  "geometry": {"coordinates":[86.275727,21.075427],"type":"Point"}
}