{
  "type": "Feature",
  "properties": {
    "iso:country":"IN",
    "ks:ks_name":"Bangaru Bandala",
    "ks:ks_pop":164,
    "ks:ks_type":"HABITATION",
    "name:eng_x_preferred":[
        "Bangaru Bandala"
    ],
    "wof:name":"Bangaru Bandala",
    "wof:placetype":"locality",
    "wof:population":164
},
  "geometry": {"coordinates":[81.853853,17.666437],"type":"Point"}
}