{
  "type": "Feature",
  "properties": {
    "gn:admin1_code":"11",
    "gn:admin2_code":"27.0",
    "gn:asciiname":"Kunaila",
    "gn:country_code":"IN",
    "gn:dem":1341,
    "gn:feature_class":"P",
    "gn:feature_code":"PPL",
    "gn:name":"Kun\u0101\u012bla",
    "gn:population":0,
    "gn:timezone":"Asia/Kolkata",
    "iso:country":"IN",
    "wof:name":"Kunaila",
    "wof:placetype":"locality"
},
  "geometry": {"coordinates":[76.81721999999998,31.48931],"type":"Point"}
}