{
  "type": "Feature",
  "properties": {
    "iso:country":"IN",
    "ks:ks_name":"Talav Faliya",
    "ks:ks_pop":266,
    "ks:ks_type":"HABITATION",
    "name:eng_x_preferred":[
        "Talav Faliya"
    ],
    "wof:name":"Talav Faliya",
    "wof:placetype":"locality",
    "wof:population":266
},
  "geometry": {"coordinates":[73.6871,22.810783],"type":"Point"}
}