{
  "type": "Feature",
  "properties": {
    "iso:country":"IN",
    "ks:ks_name":"Ajharguri No.1",
    "ks:ks_pop":136,
    "ks:ks_type":"HABITATION",
    "ks:ks_uagg_main":0,
    "name:eng_x_preferred":[
        "Ajharguri No.1"
    ],
    "wof:name":"Ajharguri No.1",
    "wof:placetype":"neighbourhood",
    "wof:population":136
},
  "geometry": {"coordinates":[93.969048,26.102015],"type":"Point"}
}