{
  "type": "Feature",
  "properties": {
    "iso:country":"IN",
    "qs:name":"Rurka",
    "qs:name_adm0":"India",
    "qs:name_adm1":"Punjab",
    "qs:photos":1,
    "qs:photos_1k":1,
    "qs:photos_9k":1,
    "qs:photos_9r":1,
    "qs:photos_all":1,
    "qs:photos_sr":1,
    "qs:placetype":"Suburb",
    "qs:pop_sr":"0",
    "wd:wordcount":131,
    "wof:name":"Rurka",
    "wof:placetype":"neighbourhood"
},
  "geometry": {"coordinates":[76.782889,30.737704],"type":"Point"}
}