{
  "type": "Feature",
  "properties": {
    "iso:country":"IN",
    "ks:ks_name":"Ballalasamudra Kaval",
    "ks:ks_pop":126,
    "ks:ks_type":"VILLAGE",
    "name:eng_x_preferred":[
        "Ballalasamudra Kaval"
    ],
    "wof:name":"Ballalasamudra Kaval",
    "wof:placetype":"locality",
    "wof:population":126
},
  "geometry": {"coordinates":[76.26418200000001,13.716297],"type":"Point"}
}