{
  "type": "Feature",
  "properties": {
    "iso:country":"IN",
    "ks:ks_alt_nam":"rayaroth thazha",
    "ks:ks_name":"Rayaroth Thazha",
    "ks:ks_pop":315,
    "ks:ks_type":"HABITATION",
    "name:eng_x_preferred":[
        "Rayaroth Thazha"
    ],
    "wof:name":"Rayaroth Thazha",
    "wof:placetype":"locality",
    "wof:population":315
},
  "geometry": {"coordinates":[75.79334299999999,11.532238],"type":"Point"}
}