{
  "type": "Feature",
  "properties": {
    "iso:country":"IN",
    "ks:ks_name":"Somanpalli",
    "ks:ks_pop":68,
    "ks:ks_type":"HABITATION",
    "name:eng_x_preferred":[
        "Somanpalli"
    ],
    "wof:name":"Somanpalli",
    "wof:placetype":"locality",
    "wof:population":68
},
  "geometry": {"coordinates":[80.067598,19.900478],"type":"Point"}
}