{
  "type": "Feature",
  "properties": {
    "gn:admin1_code":"19.0",
    "gn:admin2_code":"574.0",
    "gn:asciiname":"Hodenur",
    "gn:country_code":"IN",
    "gn:dem":882,
    "gn:feature_class":"P",
    "gn:feature_code":"PPL",
    "gn:name":"Hodenur",
    "gn:population":0,
    "gn:timezone":"Asia/Kolkata",
    "iso:country":"IN",
    "ks:ks_name":"Hodenur",
    "ks:ks_pop":981,
    "ks:ks_type":"VILLAGE",
    "name:eng_x_preferred":[
        "Hodenur"
    ],
    "wof:name":"Hodenur",
    "wof:placetype":"locality",
    "wof:population":981
},
  "geometry": {"coordinates":[75.966515,12.615999],"type":"Point"}
}