{
  "type": "Feature",
  "properties": {
    "gn:admin1_code":"19.0",
    "gn:admin2_code":"574.0",
    "gn:asciiname":"Hodenur",
    "gn:country_code":"IN",
    "gn:dem":882,
    "gn:feature_class":"P",
    "gn:feature_code":"PPL",
    "gn:name":"Hodenur",
    "gn:population":0,
    "gn:timezone":"Asia/Kolkata",
    "iso:country":"IN",
    "wof:name":"Hodenur",
    "wof:placetype":"locality"
},
  "geometry": {"coordinates":[75.9646,12.61766],"type":"Point"}
}