{
  "type": "Feature",
  "properties": {
    "iso:country":"IN",
    "ks:ks_name":"Masakatta",
    "ks:ks_pop":21,
    "ks:ks_type":"HABITATION",
    "name:eng_x_preferred":[
        "Masakatta"
    ],
    "wof:name":"Masakatta",
    "wof:placetype":"locality",
    "wof:population":21
},
  "geometry": {"coordinates":[74.586928,14.680346],"type":"Point"}
}