{
  "type": "Feature",
  "properties": {
    "iso:country":"IN",
    "ks:ks_alt_nam":"HARIJAN WASTI",
    "ks:ks_name":"Harijan Wasti",
    "ks:ks_pop":75,
    "ks:ks_type":"HABITATION",
    "ks:ks_uagg_main":0,
    "name:eng_x_preferred":[
        "Harijan Wasti"
    ],
    "wof:name":"Harijan Wasti",
    "wof:placetype":"neighbourhood",
    "wof:population":75
},
  "geometry": {"coordinates":[74.759533,17.065133],"type":"Point"}
}