{
  "type": "Feature",
  "properties": {
    "iso:country":"IN",
    "ks:ks_name":"S Basavanna Temple",
    "ks:ks_pop":10,
    "ks:ks_type":"HABITATION",
    "name:eng_x_preferred":[
        "S Basavanna Temple"
    ],
    "wof:name":"S Basavanna Temple",
    "wof:placetype":"locality",
    "wof:population":10
},
  "geometry": {"coordinates":[76.719093,13.471043],"type":"Point"}
}