{
  "type": "Feature",
  "properties": {
    "iso:country":"IN",
    "ks:ks_alt_nam":"GUDITOLI",
    "ks:ks_name":"Guditoli",
    "ks:ks_pop":125,
    "ks:ks_type":"HABITATION",
    "name:eng_x_preferred":[
        "Guditoli"
    ],
    "wof:name":"Guditoli",
    "wof:placetype":"locality",
    "wof:population":125
},
  "geometry": {"coordinates":[83.755116,22.726882],"type":"Point"}
}