{
  "type": "Feature",
  "properties": {
    "iso:country":"IN",
    "ks:ks_name":"Manipur",
    "ks:ks_pop":357,
    "ks:ks_type":"HABITATION",
    "name:eng_x_preferred":[
        "Manipur"
    ],
    "wof:name":"Manipur",
    "wof:placetype":"locality",
    "wof:population":357
},
  "geometry": {"coordinates":[84.050674,21.985046],"type":"Point"}
}