{
  "type": "Feature",
  "properties": {
    "gn:admin1_code":"11",
    "gn:admin2_code":"24.0",
    "gn:asciiname":"Purani Palum",
    "gn:country_code":"IN",
    "gn:dem":1182,
    "gn:feature_class":"P",
    "gn:feature_code":"PPL",
    "gn:name":"Purani Palum",
    "gn:population":0,
    "gn:timezone":"Asia/Kolkata",
    "iso:country":"IN",
    "wof:name":"Purani Palum",
    "wof:placetype":"locality"
},
  "geometry": {"coordinates":[76.59005999999999,32.08996],"type":"Point"}
}