{
  "type": "Feature",
  "properties": {
    "gn:admin1_code":"24.0",
    "gn:admin2_code":"122",
    "gn:asciiname":"Bholi",
    "gn:country_code":"IN",
    "gn:dem":415,
    "gn:feature_class":"P",
    "gn:feature_code":"PPL",
    "gn:name":"Bholi",
    "gn:population":0,
    "gn:timezone":"Asia/Kolkata",
    "iso:country":"IN",
    "wof:name":"Bholi",
    "wof:placetype":"locality"
},
  "geometry": {"coordinates":[74.68066999999998,25.28269],"type":"Point"}
}