{
  "type": "Feature",
  "properties": {
    "gn:admin1_code":"35.0",
    "gn:admin2_code":"449.0",
    "gn:asciiname":"Taron Khurd",
    "gn:country_code":"IN",
    "gn:dem":345,
    "gn:feature_class":"P",
    "gn:feature_code":"PPL",
    "gn:name":"Taron Khurd",
    "gn:population":0,
    "gn:timezone":"Asia/Kolkata",
    "iso:country":"IN",
    "wof:name":"Taron Khurd",
    "wof:placetype":"locality"
},
  "geometry": {"coordinates":[78.33764000000002,22.71264],"type":"Point"}
}