{
  "type": "Feature",
  "properties": {
    "gn:admin1_code":"16.0",
    "gn:admin2_code":"511.0",
    "gn:asciiname":"Wat Mangri",
    "gn:country_code":"IN",
    "gn:dem":387,
    "gn:feature_class":"P",
    "gn:feature_code":"PPL",
    "gn:name":"Wat M\u0101ngri",
    "gn:population":0,
    "gn:timezone":"Asia/Kolkata",
    "iso:country":"IN",
    "wof:name":"Wat Mangri",
    "wof:placetype":"locality"
},
  "geometry": {"coordinates":[77.94289999999999,19.80048],"type":"Point"}
}