{
  "type": "Feature",
  "properties": {
    "iso:country":"IN",
    "ks:ks_name":"Monipuratup",
    "ks:ks_pop":1017,
    "ks:ks_type":"HABITATION",
    "name:eng_x_preferred":[
        "Monipuratup"
    ],
    "wof:name":"Monipuratup",
    "wof:placetype":"locality",
    "wof:population":1017
},
  "geometry": {"coordinates":[92.451756,26.22365],"type":"Point"}
}