{
  "type": "Feature",
  "properties": {
    "iso:country":"IN",
    "ks:ks_name":"Rayganja",
    "ks:ks_pop":181,
    "ks:ks_type":"VILLAGE",
    "name:eng_x_preferred":[
        "Rayganja"
    ],
    "wof:name":"Rayganja",
    "wof:placetype":"locality",
    "wof:population":181
},
  "geometry": {"coordinates":[87.776993,22.139473],"type":"Point"}
}