{
  "type": "Feature",
  "properties": {
    "iso:country":"IN",
    "ks:ks_name":"Dakshin Khujasur",
    "ks:ks_pop":898,
    "ks:ks_type":"HABITATION",
    "ks:ks_uagg_main":0,
    "name:eng_x_preferred":[
        "Dakshin Khujasur"
    ],
    "wof:name":"Dakshin Khujasur",
    "wof:placetype":"neighbourhood",
    "wof:population":898
},
  "geometry": {"coordinates":[88.030627,26.1178],"type":"Point"}
}