{
  "type": "Feature",
  "properties": {
    "iso:country":"IN",
    "ks:ks_name":"Anakanur",
    "ks:ks_pop":1000,
    "ks:ks_type":"VILLAGE",
    "ks:ks_uagg_main":0,
    "name:eng_x_preferred":[
        "Anakanur"
    ],
    "wof:name":"Anakanur",
    "wof:placetype":"neighbourhood",
    "wof:population":1000
},
  "geometry": {"coordinates":[77.747463,13.436677],"type":"Point"}
}