{
  "type": "Feature",
  "properties": {
    "iso:country":"IN",
    "ks:ks_name":"Jemlani Sarnon Ka Tala",
    "ks:ks_pop":641,
    "ks:ks_type":"VILLAGE",
    "name:eng_x_preferred":[
        "Jemlani Sarnon Ka Tala"
    ],
    "wof:name":"Jemlani Sarnon Ka Tala",
    "wof:placetype":"locality",
    "wof:population":641
},
  "geometry": {"coordinates":[71.79020300000001,25.514939],"type":"Point"}
}