{
  "type": "Feature",
  "properties": {
    "iso:country":"IN",
    "ks:ks_name":"Pale Bk.",
    "ks:ks_pop":751,
    "ks:ks_type":"VILLAGE",
    "ks:ks_uagg_main":0,
    "name:eng_x_preferred":[
        "Pale Bk."
    ],
    "wof:name":"Pale Bk.",
    "wof:placetype":"neighbourhood",
    "wof:population":751
},
  "geometry": {"coordinates":[73.20279600000001,18.403121],"type":"Point"}
}