{
  "type": "Feature",
  "properties": {
    "gn:admin1_code":"19.0",
    "gn:admin2_code":"582.0",
    "gn:asciiname":"Nagarbhavi",
    "gn:country_code":"IN",
    "gn:dem":813,
    "gn:feature_class":"P",
    "gn:feature_code":"PPL",
    "gn:name":"N\u0101garbh\u0101vi",
    "gn:population":0,
    "gn:timezone":"Asia/Kolkata",
    "iso:country":"IN",
    "wof:name":"Nagarbhavi",
    "wof:placetype":"locality"
},
  "geometry": {"coordinates":[77.55738000000002,13.44509],"type":"Point"}
}