{
  "type": "Feature",
  "properties": {
    "gn:admin1_code":"11.0",
    "gn:admin2_code":"33.0",
    "gn:asciiname":"Chaberi",
    "gn:country_code":"IN",
    "gn:dem":1997,
    "gn:feature_class":"P",
    "gn:feature_code":"PPL",
    "gn:name":"Chaberi",
    "gn:population":0,
    "gn:timezone":"Asia/Kolkata",
    "iso:country":"IN",
    "wof:name":"Chaberi",
    "wof:placetype":"locality"
},
  "geometry": {"coordinates":[77.55261,31.30086],"type":"Point"}
}