{
  "type": "Feature",
  "properties": {
    "gn:admin1_code":"35",
    "gn:admin2_code":"429.0",
    "gn:asciiname":"Khamaria",
    "gn:country_code":"IN",
    "gn:dem":396,
    "gn:feature_class":"P",
    "gn:feature_code":"PPL",
    "gn:name":"Khamaria",
    "gn:population":0,
    "gn:timezone":"Asia/Kolkata",
    "iso:country":"IN",
    "wof:name":"Khamaria",
    "wof:placetype":"locality"
},
  "geometry": {"coordinates":[80.44228000000003,24.0073],"type":"Point"}
}