{
  "type": "Feature",
  "properties": {
    "gn:admin1_code":"37",
    "gn:admin2_code":"409.0",
    "gn:asciiname":"Kunjkanhar",
    "gn:country_code":"IN",
    "gn:dem":373,
    "gn:feature_class":"P",
    "gn:feature_code":"PPL",
    "gn:name":"Kunjkanh\u0101r",
    "gn:population":0,
    "gn:timezone":"Asia/Kolkata",
    "iso:country":"IN",
    "wof:name":"Kunjkanhar",
    "wof:placetype":"locality"
},
  "geometry": {"coordinates":[81.15845,20.48179],"type":"Point"}
}