{
  "type": "Feature",
  "properties": {
    "iso:country":"IN",
    "ks:ks_name":"Poodhamangalacherry",
    "ks:ks_pop":563,
    "ks:ks_type":"HABITATION",
    "name:eng_x_preferred":[
        "Poodhamangalacherry"
    ],
    "wof:name":"Poodhamangalacherry",
    "wof:placetype":"locality",
    "wof:population":563
},
  "geometry": {"coordinates":[79.63024799999999,10.709417],"type":"Point"}
}