{
  "type": "Feature",
  "properties": {
    "iso:country":"IN",
    "ks:ks_name":"Satariya",
    "ks:ks_pop":375,
    "ks:ks_type":"VILLAGE",
    "name:eng_x_preferred":[
        "Satariya"
    ],
    "wof:name":"Satariya",
    "wof:placetype":"locality",
    "wof:population":375
},
  "geometry": {"coordinates":[86.680564,24.420009],"type":"Point"}
}