{
  "type": "Feature",
  "properties": {
    "iso:country":"IN",
    "ks:ks_name":"Bodagunta",
    "ks:ks_pop":155,
    "ks:ks_type":"HABITATION",
    "name:eng_x_preferred":[
        "Bodagunta"
    ],
    "wof:name":"Bodagunta",
    "wof:placetype":"locality",
    "wof:population":155
},
  "geometry": {"coordinates":[81.189663,16.345158],"type":"Point"}
}