{
  "type": "Feature",
  "properties": {
    "iso:country":"IN",
    "ks:ks_name":"Bagiya",
    "ks:ks_pop":57,
    "ks:ks_type":"HABITATION",
    "ks:ks_uagg_main":0,
    "name:eng_x_preferred":[
        "Bagiya"
    ],
    "wof:name":"Bagiya",
    "wof:placetype":"neighbourhood",
    "wof:population":57
},
  "geometry": {"coordinates":[82.195744,26.413514],"type":"Point"}
}