{
  "type": "Feature",
  "properties": {
    "iso:country":"IN",
    "ks:ks_name":"Sarodewadi",
    "ks:ks_pop":94,
    "ks:ks_type":"HABITATION",
    "name:eng_x_preferred":[
        "Sarodewadi"
    ],
    "wof:name":"Sarodewadi",
    "wof:placetype":"locality",
    "wof:population":94
},
  "geometry": {"coordinates":[73.36027799999999,17.136111],"type":"Point"}
}