{
  "type": "Feature",
  "properties": {
    "gn:admin1_code":"19.0",
    "gn:admin2_code":"577.0",
    "gn:asciiname":"Maidanahalli",
    "gn:country_code":"IN",
    "gn:dem":795,
    "gn:feature_class":"P",
    "gn:feature_code":"PPL",
    "gn:name":"Maidanahalli",
    "gn:population":0,
    "gn:timezone":"Asia/Kolkata",
    "iso:country":"IN",
    "wof:name":"Maidanahalli",
    "wof:placetype":"locality"
},
  "geometry": {"coordinates":[76.55235,12.37132],"type":"Point"}
}