{
  "type": "Feature",
  "properties": {
    "iso:country":"IN",
    "ks:ks_name":"Dewapara",
    "ks:ks_pop":183,
    "ks:ks_type":"HABITATION",
    "name:eng_x_preferred":[
        "Dewapara"
    ],
    "wof:name":"Dewapara",
    "wof:placetype":"locality",
    "wof:population":183
},
  "geometry": {"coordinates":[81.785071,19.046253],"type":"Point"}
}