{
  "type": "Feature",
  "properties": {
    "iso:country":"IN",
    "ks:ks_name":"Debottar Bakshiganj",
    "ks:ks_pop":704,
    "ks:ks_type":"VILLAGE",
    "ks:ks_uagg_main":0,
    "name:eng_x_preferred":[
        "Debottar Bakshiganj"
    ],
    "wof:name":"Debottar Bakshiganj",
    "wof:placetype":"neighbourhood",
    "wof:population":704
},
  "geometry": {"coordinates":[88.7878,26.322021],"type":"Point"}
}