{
  "type": "Feature",
  "properties": {
    "iso:country":"IN",
    "ks:ks_name":"Jagdishpur",
    "ks:ks_pop":442,
    "ks:ks_type":"VILLAGE",
    "name:eng_x_preferred":[
        "Jagdishpur"
    ],
    "wof:name":"Jagdishpur",
    "wof:placetype":"locality",
    "wof:population":442
},
  "geometry": {"coordinates":[85.64918900000001,26.464087],"type":"Point"}
}