{
  "type": "Feature",
  "properties": {
    "iso:country":"IN",
    "ks:ks_name":"T Thanda",
    "ks:ks_pop":264,
    "ks:ks_type":"HABITATION",
    "name:eng_x_preferred":[
        "T Thanda"
    ],
    "wof:name":"T Thanda",
    "wof:placetype":"locality",
    "wof:population":264
},
  "geometry": {"coordinates":[78.463993,13.825026],"type":"Point"}
}