{
  "type": "Feature",
  "properties": {
    "iso:country":"IN",
    "ks:ks_name":"West Tola",
    "ks:ks_pop":287,
    "ks:ks_type":"HABITATION",
    "name:eng_x_preferred":[
        "West Tola"
    ],
    "wof:name":"West Tola",
    "wof:placetype":"locality",
    "wof:population":287
},
  "geometry": {"coordinates":[86.464986,25.983874],"type":"Point"}
}