{
  "type": "Feature",
  "properties": {
    "iso:country":"IN",
    "ks:ks_name":"Dumarjor",
    "ks:ks_pop":11,
    "ks:ks_type":"VILLAGE",
    "name:eng_x_preferred":[
        "Dumarjor"
    ],
    "wof:name":"Dumarjor",
    "wof:placetype":"locality",
    "wof:population":11
},
  "geometry": {"coordinates":[86.03894099999999,24.506998],"type":"Point"}
}