{
  "type": "Feature",
  "properties": {
    "gn:admin1_code":"36",
    "gn:admin2_code":"176.0",
    "gn:asciiname":"Dhawa",
    "gn:country_code":"IN",
    "gn:dem":118,
    "gn:feature_class":"P",
    "gn:feature_code":"PPL",
    "gn:name":"Dhawa",
    "gn:population":0,
    "gn:timezone":"Asia/Kolkata",
    "iso:country":"IN",
    "name:ceb_x_preferred":[
        "Dhawa"
    ],
    "name:mai_x_preferred":[
        "\u0927\u093e\u0935\u093e"
    ],
    "name:swe_x_preferred":[
        "Dhawa"
    ],
    "wof:name":"Dhawa",
    "wof:placetype":"locality"
},
  "geometry": {"coordinates":[81.58603000000002,26.88378],"type":"Point"}
}