{
  "type": "Feature",
  "properties": {
    "iso:country":"IN",
    "ks:ks_name":"Kapiyakudi",
    "ks:ks_pop":415,
    "ks:ks_type":"HABITATION",
    "name:eng_x_preferred":[
        "Kapiyakudi"
    ],
    "wof:name":"Kapiyakudi",
    "wof:placetype":"locality",
    "wof:population":415
},
  "geometry": {"coordinates":[79.729157,11.271064],"type":"Point"}
}