{
  "type": "Feature",
  "properties": {
    "iso:country":"IN",
    "ks:ks_name":"Thelapada",
    "ks:ks_pop":85,
    "ks:ks_type":"HABITATION",
    "name:eng_x_preferred":[
        "Thelapada"
    ],
    "wof:name":"Thelapada",
    "wof:placetype":"locality",
    "wof:population":85
},
  "geometry": {"coordinates":[82.692092,20.084141],"type":"Point"}
}