{
  "type": "Feature",
  "properties": {
    "iso:country":"IN",
    "ks:ks_alt_nam":"PANDAV WASTI",
    "ks:ks_name":"Pandav Wasti",
    "ks:ks_pop":102,
    "ks:ks_type":"HABITATION",
    "name:eng_x_preferred":[
        "Pandav Wasti"
    ],
    "wof:name":"Pandav Wasti",
    "wof:placetype":"locality",
    "wof:population":102
},
  "geometry": {"coordinates":[74.91732,19.20008],"type":"Point"}
}