{
  "type": "Feature",
  "properties": {
    "gn:admin1_code":"28.0",
    "gn:admin2_code":"330.0",
    "gn:asciiname":"Palsa",
    "gn:country_code":"IN",
    "gn:dem":42,
    "gn:feature_class":"P",
    "gn:feature_code":"PPL",
    "gn:name":"Palsa",
    "gn:population":0,
    "gn:timezone":"Asia/Kolkata",
    "iso:country":"IN",
    "name:deu_x_preferred":[
        "Palsa"
    ],
    "name:epo_x_preferred":[
        "Palso"
    ],
    "name:fin_x_preferred":[
        "Palsasuo"
    ],
    "name:fra_x_preferred":[
        "Palse"
    ],
    "name:fry_x_preferred":[
        "Palsa"
    ],
    "name:isl_x_preferred":[
        "R\u00fastir"
    ],
    "name:ita_x_preferred":[
        "Palsa"
    ],
    "name:lim_x_preferred":[
        "Palsa"
    ],
    "name:nld_x_preferred":[
        "Palsa"
    ],
    "name:nno_x_preferred":[
        "Pals"
    ],
    "name:nor_x_preferred":[
        "Pals"
    ],
    "name:pol_x_preferred":[
        "Bugier mrozowy"
    ],
    "name:spa_x_preferred":[
        "Palsa"
    ],
    "name:swe_x_preferred":[
        "Pals"
    ],
    "name:tur_x_preferred":[
        "Palsa"
    ],
    "name:ukr_x_preferred":[
        "\u041f\u0430\u043b\u044c\u0437\u0430"
    ],
    "wof:name":"Palsa",
    "wof:placetype":"locality"
},
  "geometry": {"coordinates":[87.92681999999998,25.87395],"type":"Point"}
}