{
  "type": "Feature",
  "properties": {
    "iso:country":"IN",
    "ks:ks_name":"Barakola",
    "ks:ks_pop":60,
    "ks:ks_type":"HABITATION",
    "name:eng_x_preferred":[
        "Barakola"
    ],
    "wof:name":"Barakola",
    "wof:placetype":"locality",
    "wof:population":60
},
  "geometry": {"coordinates":[86.753139,24.548867],"type":"Point"}
}