{
  "type": "Feature",
  "properties": {
    "gn:admin1_code":"39.0",
    "gn:admin2_code":"63.0",
    "gn:asciiname":"Rithabagar",
    "gn:country_code":"IN",
    "gn:dem":1193,
    "gn:feature_class":"P",
    "gn:feature_code":"PPL",
    "gn:name":"Rithabagar",
    "gn:population":0,
    "gn:timezone":"Asia/Kolkata",
    "iso:country":"IN",
    "wof:name":"Rithabagar",
    "wof:placetype":"locality"
},
  "geometry": {"coordinates":[79.91282,29.99329],"type":"Point"}
}