{
  "type": "Feature",
  "properties": {
    "gn:admin1_code":"25",
    "gn:admin2_code":"620.0",
    "gn:asciiname":"Tirupananthal",
    "gn:cc2":"IN",
    "gn:country_code":"IN",
    "gn:dem":26,
    "gn:feature_class":"P",
    "gn:feature_code":"PPL",
    "gn:name":"Tirupananthal",
    "gn:population":0,
    "gn:timezone":"Asia/Kolkata",
    "iso:country":"IN",
    "name:und_x_variant":[
        "Tirupanandal",
        "Tiruppanand\u0101l"
    ],
    "wof:name":"Tirupananthal",
    "wof:placetype":"neighbourhood"
},
  "geometry": {"coordinates":[79.45252000000001,11.09233],"type":"Point"}
}