{
  "type": "Feature",
  "properties": {
    "gn:admin1_code":"35.0",
    "gn:admin2_code":"438.0",
    "gn:asciiname":"Julwania",
    "gn:country_code":"IN",
    "gn:dem":228,
    "gn:feature_class":"P",
    "gn:feature_code":"PPL",
    "gn:name":"Julw\u0101nia",
    "gn:population":0,
    "gn:timezone":"Asia/Kolkata",
    "iso:country":"IN",
    "ks:ks_name":"Julwaniya",
    "ks:ks_pop":102,
    "ks:ks_type":"VILLAGE",
    "name:eng_x_preferred":[
        "Julwaniya"
    ],
    "name:eng_x_variant":[
        "Julwania"
    ],
    "wof:name":"Julwaniya",
    "wof:placetype":"locality",
    "wof:population":102
},
  "geometry": {"coordinates":[74.968048,22.266113],"type":"Point"}
}