{
  "type": "Feature",
  "properties": {
    "gn:admin1_code":"36",
    "gn:admin2_code":"196.0",
    "gn:asciiname":"Jogwa",
    "gn:country_code":"IN",
    "gn:dem":77,
    "gn:feature_class":"P",
    "gn:feature_code":"PPL",
    "gn:name":"Jogwa",
    "gn:population":0,
    "gn:timezone":"Asia/Kolkata",
    "iso:country":"IN",
    "name:ind_x_preferred":[
        "Jogwa"
    ],
    "name:mar_x_preferred":[
        "\u091c\u094b\u0917\u0935\u093e"
    ],
    "wof:name":"Jogwa",
    "wof:placetype":"locality"
},
  "geometry": {"coordinates":[83.375,25.34725],"type":"Point"}
}