{
  "type": "Feature",
  "properties": {
    "gn:admin1_code":"36.0",
    "gn:admin2_code":"141.0",
    "gn:asciiname":"Deri",
    "gn:country_code":"IN",
    "gn:dem":196,
    "gn:feature_class":"P",
    "gn:feature_code":"PPL",
    "gn:name":"Deri",
    "gn:population":0,
    "gn:timezone":"Asia/Kolkata",
    "iso:country":"IN",
    "name:ara_x_preferred":[
        "\u062f\u064a\u0631\u064a"
    ],
    "name:ben_bn_x_preferred":[
        "\u09a6\u09c7\u09b0\u09bf"
    ],
    "name:ben_in_x_preferred":[
        "\u09a6\u09c7\u09b0\u09bf"
    ],
    "name:ceb_x_preferred":[
        "Deri"
    ],
    "name:deu_x_preferred":[
        "Deri"
    ],
    "name:fra_x_preferred":[
        "D\u00e9ri"
    ],
    "name:guj_x_preferred":[
        "\u0aa6\u0ac7\u0ab0\u0ac0"
    ],
    "name:heb_x_preferred":[
        "\u05d3\u05e8\u05e2\u05d9"
    ],
    "name:hin_x_preferred":[
        "\u0921\u0947\u0930\u0940"
    ],
    "name:kan_x_preferred":[
        "\u0ca6\u0cc7\u0cb0\u0cbf"
    ],
    "name:mal_x_preferred":[
        "\u0d21\u0d46\u0d31\u0d3f"
    ],
    "name:mar_x_preferred":[
        "\u0921\u0947\u0930\u0940"
    ],
    "name:pan_x_preferred":[
        "\u0a21\u0a47\u0a30\u0a40"
    ],
    "name:swe_x_preferred":[
        "Deri"
    ],
    "name:tam_x_preferred":[
        "\u0b9f\u0bc6\u0bb0\u0bbf"
    ],
    "name:tel_x_preferred":[
        "\u0c21\u0c46\u0c30\u0c3f"
    ],
    "name:urd_x_preferred":[
        "\u0688\u06cc\u0631\u06cc"
    ],
    "wof:name":"Deri",
    "wof:placetype":"neighbourhood"
},
  "geometry": {"coordinates":[77.52460000000001,28.32719],"type":"Point"}
}