{
  "type": "Feature",
  "properties": {
    "gn:admin1_code":"11",
    "gn:admin2_code":"23.0",
    "gn:asciiname":"Majonban Adwar",
    "gn:country_code":"IN",
    "gn:dem":2631,
    "gn:feature_class":"P",
    "gn:feature_code":"PPL",
    "gn:name":"Majonban Adw\u0101r",
    "gn:population":0,
    "gn:timezone":"Asia/Kolkata",
    "iso:country":"IN",
    "wof:name":"Majonban Adwar",
    "wof:placetype":"locality"
},
  "geometry": {"coordinates":[76.01815999999999,32.78077],"type":"Point"}
}