{
  "type": "Feature",
  "properties": {
    "iso:country":"IN",
    "ks:ks_alt_nam":"MUSHHAR TOLA",
    "ks:ks_name":"Mushhar Tola",
    "ks:ks_pop":305,
    "ks:ks_type":"HABITATION",
    "ks:ks_uagg_main":0,
    "name:eng_x_preferred":[
        "Mushhar Tola"
    ],
    "wof:name":"Mushhar Tola",
    "wof:placetype":"neighbourhood",
    "wof:population":305
},
  "geometry": {"coordinates":[84.54814,26.605424],"type":"Point"}
}