{
  "type": "Feature",
  "properties": {
    "iso:country":"IN",
    "ks:ks_name":"Rameshwar Nagari",
    "ks:ks_pop":349,
    "ks:ks_type":"HABITATION",
    "name:eng_x_preferred":[
        "Rameshwar Nagari"
    ],
    "wof:name":"Rameshwar Nagari",
    "wof:placetype":"locality",
    "wof:population":349
},
  "geometry": {"coordinates":[71.569642,25.30895],"type":"Point"}
}