{
  "type": "Feature",
  "properties": {
    "iso:country":"IN",
    "ks:ks_alt_nam":"kanchimane",
    "ks:ks_name":"Kanchimane",
    "ks:ks_pop":45,
    "ks:ks_type":"HABITATION",
    "name:eng_x_preferred":[
        "Kanchimane"
    ],
    "wof:name":"Kanchimane",
    "wof:placetype":"locality",
    "wof:population":45
},
  "geometry": {"coordinates":[74.788236,14.48363],"type":"Point"}
}