{
  "type": "Feature",
  "properties": {
    "iso:country":"IN",
    "name:bel_x_preferred":[
        "\u041a\u0440\u044d\u043f\u0430\u0441\u0446\u044c \u0420\u0430\u0442\u0445\u0430\u043c\u0431\u043e\u0440"
    ],
    "name:deu_x_preferred":[
        "Festung Ranthambhor"
    ],
    "name:eng_x_preferred":[
        "Ranthambore Fort"
    ],
    "name:fin_x_preferred":[
        "Ranthamboren linnake"
    ],
    "name:guj_x_preferred":[
        "\u0ab0\u0aa3\u0aa5\u0a82\u0aad\u0acb\u0ab0\u0aa8\u0acb \u0a95\u0abf\u0ab2\u0acd\u0ab2\u0acb"
    ],
    "name:hin_x_preferred":[
        "\u0930\u0923\u0925\u0902\u092d\u094b\u0930 \u0926\u0941\u0930\u094d\u0917"
    ],
    "name:hun_x_preferred":[
        "Ranthambhaur-er\u0151d"
    ],
    "name:ita_x_preferred":[
        "Forte Ranthambore"
    ],
    "name:jpn_x_preferred":[
        "\u30e9\u30f3\u30bf\u30f3\u30dc\u30fc\u30eb\u57ce"
    ],
    "name:mai_x_preferred":[
        "\u0930\u0923\u0925\u092e\u094d\u092d\u094b\u0930 \u0915\u093f\u0932\u093e"
    ],
    "name:mal_x_preferred":[
        "\u0d30\u0d7a\u0d25\u0d02\u0d2d\u0d4b\u0d7c \u0d15\u0d4b\u0d1f\u0d4d\u0d1f"
    ],
    "name:ori_x_preferred":[
        "\u0b30\u0b23\u0b25\u0b2e\u0b4d\u0b2d\u0b4c\u0b30 \u0b26\u0b41\u0b30\u0b4d\u0b17"
    ],
    "name:pan_x_preferred":[
        "\u0a30\u0a23\u0a25\u0a70\u0a2d\u0a4b\u0a30 \u0a15\u0a3f\u0a32\u0a3e"
    ],
    "name:tam_x_preferred":[
        "\u0bb0\u0ba8\u0bcd\u0ba4\u0bae\u0bcd\u0baa\u0bc2\u0bb0\u0bcd \u0b95\u0bcb\u0b9f\u0bcd\u0b9f\u0bc8"
    ],
    "name:zho_x_preferred":[
        "Ranthambhore\u5821"
    ],
    "qs:name":"Ranthambore",
    "qs:name_adm0":"India",
    "qs:name_adm1":"Rajasthan",
    "qs:photos":3644,
    "qs:photos_1k":738,
    "qs:photos_9k":16,
    "qs:photos_9r":12,
    "qs:photos_all":3644,
    "qs:photos_sr":21,
    "qs:placetype":"Town",
    "qs:pop_sr":"0",
    "wd:wordcount":885,
    "wof:name":"Ranthambore",
    "wof:placetype":"locality"
},
  "geometry": {"coordinates":[76.459007,26.028333],"type":"Point"}
}