{
  "type": "Feature",
  "properties": {
    "iso:country":"IN",
    "qs:name":"Ranthambore",
    "qs:name_adm0":"India",
    "qs:name_adm1":"Rajasthan",
    "qs:photos":3644,
    "qs:photos_1k":738,
    "qs:photos_9k":16,
    "qs:photos_9r":12,
    "qs:photos_all":3644,
    "qs:photos_sr":21,
    "qs:placetype":"Town",
    "qs:pop_sr":"0",
    "wd:wordcount":885,
    "wof:name":"Ranthambore",
    "wof:placetype":"locality"
},
  "geometry": {"coordinates":[76.459007,26.028333],"type":"Point"}
}