{
  "type": "Feature",
  "properties": {
    "iso:country":"IN",
    "ks:ks_alt_nam":"UPPERPARA",
    "ks:ks_name":"Upperpara",
    "ks:ks_pop":202,
    "ks:ks_type":"HABITATION",
    "name:eng_x_preferred":[
        "Upperpara"
    ],
    "wof:name":"Upperpara",
    "wof:placetype":"locality",
    "wof:population":202
},
  "geometry": {"coordinates":[83.608141,22.964148],"type":"Point"}
}