{
  "type": "Feature",
  "properties": {
    "iso:country":"IN",
    "ks:ks_alt_nam":"Chola FR",
    "ks:ks_name":"Chola Fr",
    "ks:ks_pop":87,
    "ks:ks_type":"HABITATION",
    "name:eng_x_preferred":[
        "Chola Fr"
    ],
    "wof:name":"Chola Fr",
    "wof:placetype":"locality",
    "wof:population":87
},
  "geometry": {"coordinates":[94.91309699999999,27.020176],"type":"Point"}
}