{
  "type": "Feature",
  "properties": {
    "gn:admin1_code":"2.0",
    "gn:admin2_code":"554.0",
    "gn:asciiname":"Kamatampalle",
    "gn:country_code":"IN",
    "gn:dem":678,
    "gn:feature_class":"P",
    "gn:feature_code":"PPL",
    "gn:name":"Kamatampalle",
    "gn:population":0,
    "gn:timezone":"Asia/Kolkata",
    "iso:country":"IN",
    "ks:ks_name":"Kamatampalle",
    "ks:ks_pop":339,
    "ks:ks_type":"HABITATION",
    "ks:ks_uagg_main":0,
    "name:eng_x_preferred":[
        "Kamatampalle"
    ],
    "wof:name":"Kamatampalle",
    "wof:placetype":"neighbourhood",
    "wof:population":339
},
  "geometry": {"coordinates":[78.486341,13.626099],"type":"Point"}
}