{
  "type": "Feature",
  "properties": {
    "gn:admin1_code":"35",
    "gn:admin2_code":"462.0",
    "gn:asciiname":"Baghaun",
    "gn:country_code":"IN",
    "gn:dem":276,
    "gn:feature_class":"P",
    "gn:feature_code":"PPL",
    "gn:name":"Bagha\u016bn",
    "gn:population":0,
    "gn:timezone":"Asia/Kolkata",
    "iso:country":"IN",
    "wof:name":"Baghaun",
    "wof:placetype":"locality"
},
  "geometry": {"coordinates":[81.78952,24.48404],"type":"Point"}
}