{
  "type": "Feature",
  "properties": {
    "gn:admin1_code":"10",
    "gn:admin2_code":"89.0",
    "gn:asciiname":"Milkgani",
    "gn:country_code":"IN",
    "gn:dem":198,
    "gn:feature_class":"P",
    "gn:feature_code":"PPL",
    "gn:name":"Milkgani",
    "gn:population":0,
    "gn:timezone":"Asia/Kolkata",
    "iso:country":"IN",
    "name:und_x_variant":[
        "Ganiki"
    ],
    "wof:name":"Milkgani",
    "wof:placetype":"locality"
},
  "geometry": {"coordinates":[77.39034000000002,28.14936],"type":"Point"}
}