{
  "type": "Feature",
  "properties": {
    "gn:admin1_code":"10.0",
    "gn:admin2_code":"069",
    "gn:asciiname":"Jansu",
    "gn:country_code":"IN",
    "gn:dem":688,
    "gn:feature_class":"P",
    "gn:feature_code":"PPL",
    "gn:name":"J\u0101nsu",
    "gn:population":0,
    "gn:timezone":"Asia/Kolkata",
    "iso:country":"IN",
    "wof:name":"Jansu",
    "wof:placetype":"locality"
},
  "geometry": {"coordinates":[76.99460000000001,30.72229],"type":"Point"}
}