{
  "type": "Feature",
  "properties": {
    "iso:country":"IN",
    "ks:ks_name":"Kirkil",
    "ks:ks_pop":11,
    "ks:ks_type":"VILLAGE",
    "name:eng_x_preferred":[
        "Kirkil"
    ],
    "wof:name":"Kirkil",
    "wof:placetype":"locality",
    "wof:population":11
},
  "geometry": {"coordinates":[81.46758800000001,24.986093],"type":"Point"}
}