{
  "type": "Feature",
  "properties": {
    "iso:country":"IN",
    "ks:ks_name":"Kiye",
    "ks:ks_pop":173,
    "ks:ks_type":"VILLAGE",
    "name:eng_x_preferred":[
        "Kiye"
    ],
    "wof:name":"Kiye",
    "wof:placetype":"locality",
    "wof:population":173
},
  "geometry": {"coordinates":[73.583338,18.084775],"type":"Point"}
}