{
  "type": "Feature",
  "properties": {
    "gn:admin1_code":"39.0",
    "gn:admin2_code":"64.0",
    "gn:asciiname":"Malota",
    "gn:country_code":"IN",
    "gn:dem":1187,
    "gn:feature_class":"P",
    "gn:feature_code":"PPL",
    "gn:name":"Malota",
    "gn:population":0,
    "gn:timezone":"Asia/Kolkata",
    "iso:country":"IN",
    "ks:ks_name":"Malota",
    "ks:ks_type":"VILLAGE",
    "name:eng_x_preferred":[
        "Malota"
    ],
    "wof:name":"Malota",
    "wof:placetype":"locality"
},
  "geometry": {"coordinates":[79.37074200000001,29.644128],"type":"Point"}
}