{
  "type": "Feature",
  "properties": {
    "gn:country":"IN",
    "gn:fcode":"PPL",
    "gn:population":0,
    "iso:country":"IN",
    "name:ara_x_preferred":[
        "\u0643\u0627\u0646\u0643\u0631\u0648\u0644\u064a"
    ],
    "name:ben_bn_x_preferred":[
        "\u0995\u09be\u0981\u0995\u09b0\u09cb\u09b2\u09bf"
    ],
    "name:ben_in_x_preferred":[
        "\u0995\u09be\u0981\u0995\u09b0\u09cb\u09b2\u09bf"
    ],
    "name:cat_x_preferred":[
        "Kankroli"
    ],
    "name:guj_x_preferred":[
        "\u0a95\u0abe\u0a82\u0a95\u0acd\u0ab0\u0acb\u0ab2\u0ac0"
    ],
    "name:hin_x_preferred":[
        "\u0915\u0902\u0915\u0930\u094b\u0932\u0940"
    ],
    "name:hin_x_variant":[
        "\u0915\u093e\u0902\u0915\u0930\u094b\u0932\u0940"
    ],
    "name:kan_x_preferred":[
        "\u0c95\u0c82\u0c95\u0ccd\u0cb0\u0ccb\u0cb2\u0cbf"
    ],
    "name:mal_x_preferred":[
        "\u0d15\u0d3e\u0d7b\u0d15\u0d4d\u0d30\u0d4b\u0d32\u0d3f"
    ],
    "name:mar_x_preferred":[
        "\u0915\u093e\u0902\u0915\u0930\u094b\u0932\u0940"
    ],
    "name:pan_x_preferred":[
        "\u0a15\u0a70\u0a15\u0a30\u0a4c\u0a32\u0a40"
    ],
    "name:tam_x_preferred":[
        "\u0b95\u0ba9\u0bcd\u0b95\u0bcd\u0bb0\u0bcb\u0bb2\u0bbf"
    ],
    "name:tel_x_preferred":[
        "\u0c15\u0c02\u0c15\u0c4d\u0c30\u0c4a\u0c32\u0c3f"
    ],
    "name:und_x_variant":[
        "K\u0101nkroli"
    ],
    "name:urd_x_preferred":[
        "\u06a9\u0646\u06a9\u0631\u0648\u0644\u06cc"
    ],
    "qs_pg:aaroncc":"IN",
    "qs_pg:gn_country":"IN",
    "qs_pg:gn_fcode":"PPL",
    "qs_pg:gn_pop":0,
    "qs_pg:name":"Kankroli",
    "qs_pg:name_adm0":"India",
    "qs_pg:name_adm1":"Rajasthan",
    "qs_pg:photos":24,
    "qs_pg:photos_1k":5,
    "qs_pg:photos_9k":1,
    "qs_pg:photos_9r":1,
    "qs_pg:photos_all":24,
    "qs_pg:photos_sr":1,
    "qs_pg:pop_sr":5,
    "qs_pg:qs_pg_placetype":"neighbourhood",
    "qs_pg:qs_pg_placetype_gp":"Suburb",
    "qs_pg:woe_adm0":23424848,
    "woe:adm0_id":23424848,
    "woe:name_adm0":"India",
    "woe:name_adm1":"Rajasthan",
    "woe:placetype":"Suburb",
    "wof:name":"Kankroli",
    "wof:placetype":"neighbourhood"
},
  "geometry": {"coordinates":[73.88816,25.05881],"type":"Point"}
}