{
  "type": "Feature",
  "properties": {
    "iso:country":"IN",
    "ks:ks_name":"Tiklijharan",
    "ks:ks_pop":214,
    "ks:ks_type":"HABITATION",
    "name:eng_x_preferred":[
        "Tiklijharan"
    ],
    "wof:name":"Tiklijharan",
    "wof:placetype":"locality",
    "wof:population":214
},
  "geometry": {"coordinates":[84.630734,21.499689],"type":"Point"}
}