{
  "type": "Feature",
  "properties": {
    "iso:country":"IN",
    "ks:ks_name":"Kadangode",
    "ks:ks_pop":2736,
    "ks:ks_type":"VILLAGE",
    "name:eng_x_preferred":[
        "Kadangode"
    ],
    "wof:name":"Kadangode",
    "wof:placetype":"locality",
    "wof:population":2736
},
  "geometry": {"coordinates":[76.14044699999999,10.696301],"type":"Point"}
}