{
  "type": "Feature",
  "properties": {
    "iso:country":"IN",
    "ks:ks_name":"Karuppakovilpatti",
    "ks:ks_pop":565,
    "ks:ks_type":"HABITATION",
    "name:eng_x_preferred":[
        "Karuppakovilpatti"
    ],
    "wof:name":"Karuppakovilpatti",
    "wof:placetype":"locality",
    "wof:population":565
},
  "geometry": {"coordinates":[78.150757,10.36368],"type":"Point"}
}