{
  "type": "Feature",
  "properties": {
    "iso:country":"IN",
    "ks:ks_name":"Panthappadam",
    "ks:ks_pop":900,
    "ks:ks_type":"HABITATION",
    "name:eng_x_preferred":[
        "Panthappadam"
    ],
    "wof:name":"Panthappadam",
    "wof:placetype":"locality",
    "wof:population":900
},
  "geometry": {"coordinates":[76.80018,10.570419],"type":"Point"}
}