{
  "type": "Feature",
  "properties": {
    "gn:admin1_code":"24.0",
    "gn:admin2_code":"123.0",
    "gn:asciiname":"Motala",
    "gn:country_code":"IN",
    "gn:dem":614,
    "gn:feature_class":"P",
    "gn:feature_code":"PPL",
    "gn:name":"Mot\u0101la",
    "gn:population":0,
    "gn:timezone":"Asia/Kolkata",
    "iso:country":"IN",
    "name:bul_x_preferred":[
        "\u041c\u0443\u0442\u0430\u043b\u0430"
    ],
    "name:ceb_x_preferred":[
        "Motala"
    ],
    "name:dan_x_preferred":[
        "Motala"
    ],
    "name:deu_x_preferred":[
        "Motala"
    ],
    "name:est_x_preferred":[
        "Motala"
    ],
    "name:fao_x_preferred":[
        "Motala"
    ],
    "name:fas_x_preferred":[
        "\u0645\u0648\u062a\u0644\u0627"
    ],
    "name:fin_x_preferred":[
        "Motala"
    ],
    "name:fra_x_preferred":[
        "Motala"
    ],
    "name:gla_x_preferred":[
        "Motala"
    ],
    "name:heb_x_preferred":[
        "\u05de\u05d5\u05d8\u05dc\u05d4"
    ],
    "name:hrv_x_preferred":[
        "Motala"
    ],
    "name:ind_x_preferred":[
        "Motala"
    ],
    "name:isl_x_preferred":[
        "Motala"
    ],
    "name:ita_x_preferred":[
        "Motala"
    ],
    "name:kat_x_preferred":[
        "\u10db\u10e3\u10e2\u10d0\u10da\u10d0"
    ],
    "name:kor_x_preferred":[
        "\ubaa8\ud0c8\ub77c"
    ],
    "name:lav_x_preferred":[
        "M\u016btala"
    ],
    "name:lit_x_preferred":[
        "Mutala"
    ],
    "name:min_x_preferred":[
        "Motala"
    ],
    "name:nld_x_preferred":[
        "Motala"
    ],
    "name:nno_x_preferred":[
        "Motala"
    ],
    "name:nor_x_preferred":[
        "Motala"
    ],
    "name:pol_x_preferred":[
        "Motala"
    ],
    "name:por_x_preferred":[
        "Motala"
    ],
    "name:ron_x_preferred":[
        "Motala"
    ],
    "name:rus_x_preferred":[
        "\u041c\u0443\u0442\u0430\u043b\u0430"
    ],
    "name:spa_x_preferred":[
        "Motala"
    ],
    "name:sqi_x_preferred":[
        "Motala"
    ],
    "name:srp_x_preferred":[
        "\u041c\u043e\u0442\u0430\u043b\u0430"
    ],
    "name:swa_x_preferred":[
        "Motala"
    ],
    "name:swe_x_preferred":[
        "Motala"
    ],
    "name:tur_x_preferred":[
        "Motala"
    ],
    "name:ukr_x_preferred":[
        "\u041c\u0443\u0442\u0430\u043b\u0430"
    ],
    "name:vol_x_preferred":[
        "Motala"
    ],
    "wof:name":"Motala",
    "wof:placetype":"locality"
},
  "geometry": {"coordinates":[74.20161999999998,25.86891],"type":"Point"}
}