{
  "type": "Feature",
  "properties": {
    "iso:country":"IN",
    "ks:ks_name":"Sundarpura",
    "ks:ks_pop":404,
    "ks:ks_type":"HABITATION",
    "name:eng_x_preferred":[
        "Sundarpura"
    ],
    "wof:name":"Sundarpura",
    "wof:placetype":"locality",
    "wof:population":404
},
  "geometry": {"coordinates":[77.063934,24.182956],"type":"Point"}
}