{
  "type": "Feature",
  "properties": {
    "iso:country":"IN",
    "ks:ks_name":"Balethi",
    "ks:ks_pop":310,
    "ks:ks_type":"VILLAGE",
    "name:eng_x_preferred":[
        "Balethi"
    ],
    "wof:name":"Balethi",
    "wof:placetype":"locality",
    "wof:population":310
},
  "geometry": {"coordinates":[73.32938300000001,21.432139],"type":"Point"}
}