{
  "type": "Feature",
  "properties": {
    "iso:country":"IN",
    "ks:ks_name":"Sanarpalayam",
    "ks:ks_pop":110,
    "ks:ks_type":"HABITATION",
    "name:eng_x_preferred":[
        "Sanarpalayam"
    ],
    "wof:name":"Sanarpalayam",
    "wof:placetype":"locality",
    "wof:population":110
},
  "geometry": {"coordinates":[77.723021,11.898732],"type":"Point"}
}