{
  "type": "Feature",
  "properties": {
    "iso:country":"IN",
    "ks:ks_name":"Kotenpadar",
    "ks:ks_pop":0,
    "ks:ks_type":"VILLAGE",
    "name:eng_x_preferred":[
        "Kotenpadar"
    ],
    "wof:name":"Kotenpadar",
    "wof:placetype":"locality",
    "wof:population":0
},
  "geometry": {"coordinates":[83.17263,19.846024],"type":"Point"}
}