{
  "type": "Feature",
  "properties": {
    "gn:admin1_code":"3.0",
    "gn:admin2_code":"303.0",
    "gn:asciiname":"Ahompathar",
    "gn:country_code":"IN",
    "gn:dem":50,
    "gn:feature_class":"P",
    "gn:feature_code":"PPL",
    "gn:name":"Ahompath\u0101r",
    "gn:population":0,
    "gn:timezone":"Asia/Kolkata",
    "iso:country":"IN",
    "wof:name":"Ahompathar",
    "wof:placetype":"locality"
},
  "geometry": {"coordinates":[90.88369,26.50862],"type":"Point"}
}