{
  "type": "Feature",
  "properties": {
    "iso:country":"IN",
    "ks:ks_alt_nam":"prayagpur ram garhwa",
    "ks:ks_name":"Prayagpur Ram Garhwa",
    "ks:ks_pop":1100,
    "ks:ks_type":"HABITATION",
    "name:eng_x_preferred":[
        "Prayagpur Ram Garhwa"
    ],
    "wof:name":"Prayagpur Ram Garhwa",
    "wof:placetype":"locality",
    "wof:population":1100
},
  "geometry": {"coordinates":[82.19991,25.16619],"type":"Point"}
}