{
  "type": "Feature",
  "properties": {
    "gn:admin1_code":"12.0",
    "gn:admin2_code":"16.0",
    "gn:asciiname":"Seuta",
    "gn:country_code":"IN",
    "gn:dem":1415,
    "gn:feature_class":"P",
    "gn:feature_code":"PPL",
    "gn:name":"Seuta",
    "gn:population":0,
    "gn:timezone":"Asia/Kolkata",
    "iso:country":"IN",
    "wof:name":"Seuta",
    "wof:placetype":"locality"
},
  "geometry": {"coordinates":[75.61936999999998,33.0478],"type":"Point"}
}