{
  "type": "Feature",
  "properties": {
    "iso:country":"IN",
    "ks:ks_name":"Haropara",
    "ks:ks_pop":207,
    "ks:ks_type":"VILLAGE",
    "ks:ks_uagg_main":0,
    "name:eng_x_preferred":[
        "Haropara"
    ],
    "wof:name":"Haropara",
    "wof:placetype":"locality",
    "wof:population":207
},
  "geometry": {"coordinates":[91.48376500000001,26.057856],"type":"Point"}
}