{
  "type": "Feature",
  "properties": {
    "iso:country":"IN",
    "ks:ks_name":"Pure Diggaj",
    "ks:ks_pop":98,
    "ks:ks_type":"HABITATION",
    "ks:ks_uagg_main":0,
    "name:eng_x_preferred":[
        "Pure Diggaj"
    ],
    "wof:name":"Pure Diggaj",
    "wof:placetype":"neighbourhood",
    "wof:population":98
},
  "geometry": {"coordinates":[81.731495,26.170321],"type":"Point"}
}