{
  "type": "Feature",
  "properties": {
    "iso:country":"IN",
    "ks:ks_alt_nam":"Mangron sirau",
    "ks:ks_name":"Mangron Sirau",
    "ks:ks_pop":358,
    "ks:ks_type":"HABITATION",
    "name:eng_x_preferred":[
        "Mangron Sirau"
    ],
    "wof:name":"Mangron Sirau",
    "wof:placetype":"locality",
    "wof:population":358
},
  "geometry": {"coordinates":[79.21794300000001,29.693698],"type":"Point"}
}