{
  "type": "Feature",
  "properties": {
    "iso:country":"IN",
    "ks:ks_name":"Kew Taliya",
    "ks:ks_pop":275,
    "ks:ks_type":"HABITATION",
    "ks:ks_uagg_main":0,
    "name:eng_x_preferred":[
        "Kew Taliya"
    ],
    "wof:name":"Kew Taliya",
    "wof:placetype":"neighbourhood",
    "wof:population":275
},
  "geometry": {"coordinates":[83.743537,26.440583],"type":"Point"}
}