{
  "type": "Feature",
  "properties": {
    "gn:admin1_code":"21.0",
    "gn:admin2_code":"396.0",
    "gn:asciiname":"Maskapadu",
    "gn:country_code":"IN",
    "gn:dem":418,
    "gn:feature_class":"P",
    "gn:feature_code":"PPL",
    "gn:name":"Maskap\u0101du",
    "gn:population":0,
    "gn:timezone":"Asia/Kolkata",
    "iso:country":"IN",
    "ks:ks_alt_nam":"Maskap\u0101du",
    "ks:ks_alt_nam_2":"Maskapadu",
    "ks:ks_name":"Maskapadai",
    "ks:ks_pop":0,
    "ks:ks_type":"VILLAGE",
    "name:eng_x_preferred":[
        "Maskapadai"
    ],
    "name:eng_x_variant":[
        "Maskapadu",
        "Maskap\u0101du"
    ],
    "wof:name":"Maskapadai",
    "wof:placetype":"locality",
    "wof:population":0
},
  "geometry": {"coordinates":[83.276433,19.217386],"type":"Point"}
}