{
  "type": "Feature",
  "properties": {
    "iso:country":"IN",
    "ks:ks_name":"Kukkdelu",
    "ks:ks_pop":289,
    "ks:ks_type":"HABITATION",
    "name:eng_x_preferred":[
        "Kukkdelu"
    ],
    "wof:name":"Kukkdelu",
    "wof:placetype":"locality",
    "wof:population":289
},
  "geometry": {"coordinates":[75.371258,12.622486],"type":"Point"}
}