{
  "type": "Feature",
  "properties": {
    "gn:admin1_code":"36.0",
    "gn:admin2_code":"135.0",
    "gn:asciiname":"Daulatpur Bharkau",
    "gn:country_code":"IN",
    "gn:dem":192,
    "gn:feature_class":"P",
    "gn:feature_code":"PPL",
    "gn:name":"Daulatpur Bharkau",
    "gn:population":0,
    "gn:timezone":"Asia/Kolkata",
    "iso:country":"IN",
    "wof:name":"Daulatpur Bharkau",
    "wof:placetype":"locality"
},
  "geometry": {"coordinates":[78.70815999999998,28.52659],"type":"Point"}
}