{
  "type": "Feature",
  "properties": {
    "gn:admin1_code":"36.0",
    "gn:admin2_code":"135.0",
    "gn:asciiname":"Daulatpur Bharkau",
    "gn:country_code":"IN",
    "gn:dem":192,
    "gn:feature_class":"P",
    "gn:feature_code":"PPL",
    "gn:name":"Daulatpur Bharkau",
    "gn:population":0,
    "gn:timezone":"Asia/Kolkata",
    "iso:country":"IN",
    "ks:ks_name":"Daulatpur Bharkau",
    "ks:ks_pop":336,
    "ks:ks_type":"VILLAGE",
    "name:eng_x_preferred":[
        "Daulatpur Bharkau"
    ],
    "wof:name":"Daulatpur Bharkau",
    "wof:placetype":"locality",
    "wof:population":336
},
  "geometry": {"coordinates":[78.708158,28.526589],"type":"Point"}
}