{
  "type": "Feature",
  "properties": {
    "iso:country":"IN",
    "ks:ks_name":"Darha Bari",
    "ks:ks_pop":4713,
    "ks:ks_type":"VILLAGE",
    "name:eng_x_preferred":[
        "Darha Bari"
    ],
    "wof:name":"Darha Bari",
    "wof:placetype":"locality",
    "wof:population":4713
},
  "geometry": {"coordinates":[85.73720400000001,26.600788],"type":"Point"}
}