{
  "type": "Feature",
  "properties": {
    "gn:admin1_code":"12.0",
    "gn:admin2_code":"1.0",
    "gn:asciiname":"Kain Maih",
    "gn:country_code":"IN",
    "gn:dem":2180,
    "gn:feature_class":"P",
    "gn:feature_code":"PPL",
    "gn:name":"Kain Maih",
    "gn:population":0,
    "gn:timezone":"Asia/Kolkata",
    "iso:country":"IN",
    "wof:name":"Kain Maih",
    "wof:placetype":"locality"
},
  "geometry": {"coordinates":[74.22103,34.61379],"type":"Point"}
}