{
  "type": "Feature",
  "properties": {
    "gn:admin1_code":"36",
    "gn:admin2_code":"197.0",
    "gn:asciiname":"Sagarpur",
    "gn:country_code":"IN",
    "gn:dem":83,
    "gn:feature_class":"P",
    "gn:feature_code":"PPL",
    "gn:name":"S\u0101garpur",
    "gn:population":0,
    "gn:timezone":"Asia/Kolkata",
    "iso:country":"IN",
    "name:ara_x_preferred":[
        "\u0633\u0627\u062c\u0627\u0631\u0628\u0648\u0631"
    ],
    "name:ben_bn_x_preferred":[
        "\u09b8\u09be\u0997\u09b0\u09aa\u09c1\u09b0"
    ],
    "name:ben_in_x_preferred":[
        "\u09b8\u09be\u0997\u09b0\u09aa\u09c1\u09b0"
    ],
    "name:guj_x_preferred":[
        "\u0ab8\u0abe\u0a97\u0ab0\u0aaa\u0ac1\u0ab0"
    ],
    "name:hin_x_preferred":[
        "\u0938\u093e\u0917\u0930\u092a\u0941\u0930"
    ],
    "name:kan_x_preferred":[
        "\u0cb8\u0c97\u0cb0\u0ccd"
    ],
    "name:mal_x_preferred":[
        "\u0d38\u0d3e\u0d17\u0d7c\u0d2a\u0d42\u0d7c"
    ],
    "name:mar_x_preferred":[
        "\u0938\u093e\u0917\u0930\u092a\u0942\u0930"
    ],
    "name:pan_x_preferred":[
        "\u0a38\u0a3e\u0a17\u0a30\u0a2a\u0a41\u0a30"
    ],
    "name:tam_x_preferred":[
        "\u0b9a\u0bbe\u0b95\u0bb0\u0bcd\u0baa\u0bc2\u0bb0\u0bcd"
    ],
    "name:tel_x_preferred":[
        "\u0c38\u0c3e\u0c17\u0c30\u0c4d"
    ],
    "name:urd_x_preferred":[
        "\u0633\u0627\u06af\u0631 \u067e\u0648\u0631"
    ],
    "wof:name":"Sagarpur",
    "wof:placetype":"locality"
},
  "geometry": {"coordinates":[82.89603000000002,25.28252],"type":"Point"}
}