{
  "type": "Feature",
  "properties": {
    "gn:admin1_code":"19.0",
    "gn:admin2_code":"583.0",
    "gn:asciiname":"Kugonhalli",
    "gn:country_code":"IN",
    "gn:dem":908,
    "gn:feature_class":"P",
    "gn:feature_code":"PPL",
    "gn:name":"Kugonhalli",
    "gn:population":0,
    "gn:timezone":"Asia/Kolkata",
    "iso:country":"IN",
    "wof:name":"Kugonhalli",
    "wof:placetype":"locality"
},
  "geometry": {"coordinates":[77.46176,13.30963],"type":"Point"}
}