{
  "type": "Feature",
  "properties": {
    "iso:country":"IN",
    "ks:ks_alt_nam":"BARHI BIGHA",
    "ks:ks_name":"Barhi Bigha",
    "ks:ks_pop":305,
    "ks:ks_type":"HABITATION",
    "ks:ks_uagg_main":0,
    "name:eng_x_preferred":[
        "Barhi Bigha"
    ],
    "wof:name":"Barhi Bigha",
    "wof:placetype":"neighbourhood",
    "wof:population":305
},
  "geometry": {"coordinates":[85.02699800000001,24.881419],"type":"Point"}
}