{
  "type": "Feature",
  "properties": {
    "iso:country":"IN",
    "ks:ks_name":"Kanpur",
    "ks:ks_pop":0,
    "ks:ks_type":"VILLAGE",
    "name:eng_x_preferred":[
        "Kanpur"
    ],
    "name:hin_x_preferred":[
        "\u0915\u093e\u0928\u092a\u0941\u0930"
    ],
    "wof:name":"Kanpur",
    "wof:placetype":"locality",
    "wof:population":0
},
  "geometry": {"coordinates":[87.789749,23.490865],"type":"Point"}
}