{
  "type": "Feature",
  "properties": {
    "gn:admin1_code":"36",
    "gn:admin2_code":"193.0",
    "gn:asciiname":"Gurgujpur",
    "gn:country_code":"IN",
    "gn:dem":70,
    "gn:feature_class":"P",
    "gn:feature_code":"PPL",
    "gn:name":"Gurgujpur",
    "gn:population":0,
    "gn:timezone":"Asia/Kolkata",
    "iso:country":"IN",
    "wof:name":"Gurgujpur",
    "wof:placetype":"locality"
},
  "geometry": {"coordinates":[83.91298,25.84093],"type":"Point"}
}