{
  "type": "Feature",
  "properties": {
    "iso:country":"IN",
    "ks:ks_name":"Janglil Purwa",
    "ks:ks_pop":202,
    "ks:ks_type":"HABITATION",
    "ks:ks_uagg_main":0,
    "name:eng_x_preferred":[
        "Janglil Purwa"
    ],
    "wof:name":"Janglil Purwa",
    "wof:placetype":"neighbourhood",
    "wof:population":202
},
  "geometry": {"coordinates":[81.41495399999999,27.877484],"type":"Point"}
}