{
  "type": "Feature",
  "properties": {
    "iso:country":"IN",
    "ks:ks_name":"Kilambakkam",
    "ks:ks_pop":492,
    "ks:ks_type":"VILLAGE",
    "ks:ks_uagg_main":0,
    "name:eng_x_preferred":[
        "Kilambakkam"
    ],
    "wof:name":"Kilambakkam",
    "wof:placetype":"locality",
    "wof:population":492
},
  "geometry": {"coordinates":[80.07572999999999,12.870333],"type":"Point"}
}