{
  "type": "Feature",
  "properties": {
    "iso:country":"IN",
    "ks:ks_name":"Fatamunda",
    "ks:ks_pop":166,
    "ks:ks_type":"VILLAGE",
    "name:eng_x_preferred":[
        "Fatamunda"
    ],
    "wof:name":"Fatamunda",
    "wof:placetype":"locality",
    "wof:population":166
},
  "geometry": {"coordinates":[83.68826,20.459955],"type":"Point"}
}