{
  "type": "Feature",
  "properties": {
    "iso:country":"IN",
    "ks:ks_name":"Kulathur",
    "ks:ks_pop":507,
    "ks:ks_type":"HABITATION",
    "name:eng_x_preferred":[
        "Kulathur"
    ],
    "wof:name":"Kulathur",
    "wof:placetype":"locality",
    "wof:population":507
},
  "geometry": {"coordinates":[79.77227499999999,11.25022],"type":"Point"}
}