{
  "type": "Feature",
  "properties": {
    "gn:admin1_code":"23.0",
    "gn:admin2_code":"35.0",
    "gn:asciiname":"Bahlolpur",
    "gn:country_code":"IN",
    "gn:dem":255,
    "gn:feature_class":"P",
    "gn:feature_code":"PPL",
    "gn:name":"Bahlolpur",
    "gn:population":0,
    "gn:timezone":"Asia/Kolkata",
    "iso:country":"IN",
    "ks:ks_name":"Bahlolpur",
    "ks:ks_pop":467,
    "ks:ks_type":"VILLAGE",
    "ks:ks_uagg_main":0,
    "name:eng_x_preferred":[
        "Bahlolpur"
    ],
    "wof:name":"Bahlolpur",
    "wof:placetype":"neighbourhood",
    "wof:population":467
},
  "geometry": {"coordinates":[75.357739,32.116884],"type":"Point"}
}