{
  "type": "Feature",
  "properties": {
    "iso:country":"IN",
    "ks:ks_name":"Parwat t. wagawale",
    "ks:ks_pop":346,
    "ks:ks_type":"VILLAGE",
    "name:eng_x_preferred":[
        "Parwat t. wagawale"
    ],
    "wof:name":"Parwat t. wagawale",
    "wof:placetype":"locality",
    "wof:population":346
},
  "geometry": {"coordinates":[73.62076500000001,17.746646],"type":"Point"}
}