{
  "type": "Feature",
  "properties": {
    "iso:country":"IN",
    "ks:ks_name":"Paraipatti",
    "ks:ks_pop":2504,
    "ks:ks_type":"HABITATION",
    "ks:ks_uagg_main":0,
    "name:eng_x_preferred":[
        "Paraipatti"
    ],
    "wof:name":"Paraipatti",
    "wof:placetype":"locality",
    "wof:population":2504
},
  "geometry": {"coordinates":[77.819081,9.438774],"type":"Point"}
}