{
  "type": "Feature",
  "properties": {
    "iso:country":"IN",
    "ks:ks_name":"Birawlidand",
    "ks:ks_pop":214,
    "ks:ks_type":"VILLAGE",
    "name:eng_x_preferred":[
        "Birawlidand"
    ],
    "wof:name":"Birawlidand",
    "wof:placetype":"locality",
    "wof:population":214
},
  "geometry": {"coordinates":[82.48219899999999,23.418699],"type":"Point"}
}