{
  "type": "Feature",
  "properties": {
    "iso:country":"IN",
    "ks:ks_name":"Tola Rajasare",
    "ks:ks_pop":268,
    "ks:ks_type":"VILLAGE",
    "ks:ks_uagg_main":0,
    "name:eng_x_preferred":[
        "Tola Rajasare"
    ],
    "wof:name":"Tola Rajasare",
    "wof:placetype":"neighbourhood",
    "wof:population":268
},
  "geometry": {"coordinates":[86.757954,24.73565],"type":"Point"}
}