{
  "type": "Feature",
  "properties": {
    "iso:country":"IN",
    "ks:ks_name":"Neduvayal",
    "ks:ks_pop":3174,
    "ks:ks_type":"VILLAGE",
    "ks:ks_uagg_main":0,
    "name:eng_x_preferred":[
        "Neduvayal"
    ],
    "wof:name":"Neduvayal",
    "wof:placetype":"neighbourhood",
    "wof:population":3174
},
  "geometry": {"coordinates":[77.29845400000001,9.036007],"type":"Point"}
}