{
  "type": "Feature",
  "properties": {
    "iso:country":"IN",
    "ks:ks_name":"Maragpada",
    "ks:ks_pop":170,
    "ks:ks_type":"HABITATION",
    "name:eng_x_preferred":[
        "Maragpada"
    ],
    "wof:name":"Maragpada",
    "wof:placetype":"locality",
    "wof:population":170
},
  "geometry": {"coordinates":[73.114563,20.059467],"type":"Point"}
}