{
  "type": "Feature",
  "properties": {
    "gn:admin1_code":"34.0",
    "gn:admin2_code":"222.0",
    "gn:asciiname":"Nadel",
    "gn:country_code":"IN",
    "gn:dem":43,
    "gn:feature_class":"P",
    "gn:feature_code":"PPL",
    "gn:name":"Nadel",
    "gn:population":0,
    "gn:timezone":"Asia/Kolkata",
    "iso:country":"IN",
    "name:ceb_x_preferred":[
        "Nadel"
    ],
    "name:deu_x_preferred":[
        "Nadel"
    ],
    "name:pol_x_preferred":[
        "Nadel"
    ],
    "name:swe_x_preferred":[
        "Nadel"
    ],
    "wof:name":"Nadel",
    "wof:placetype":"locality"
},
  "geometry": {"coordinates":[86.25419000000002,25.62273],"type":"Point"}
}