{
  "type": "Feature",
  "properties": {
    "gn:admin1_code":"36.0",
    "gn:admin2_code":"182.0",
    "gn:asciiname":"Jagannathpur Grant",
    "gn:country_code":"IN",
    "gn:dem":98,
    "gn:feature_class":"P",
    "gn:feature_code":"PPL",
    "gn:name":"Jagann\u0101thpur Grant",
    "gn:population":0,
    "gn:timezone":"Asia/Kolkata",
    "iso:country":"IN",
    "wof:name":"Jagannathpur Grant",
    "wof:placetype":"locality"
},
  "geometry": {"coordinates":[82.48208000000002,27.14924],"type":"Point"}
}