{
  "type": "Feature",
  "properties": {
    "gn:admin1_code":"10",
    "gn:admin2_code":"73.0",
    "gn:asciiname":"Mandi",
    "gn:country_code":"IN",
    "gn:dem":243,
    "gn:feature_class":"P",
    "gn:feature_code":"PPL",
    "gn:name":"M\u0101ndi",
    "gn:population":0,
    "gn:timezone":"Asia/Kolkata",
    "iso:country":"IN",
    "name:ara_x_preferred":[
        "\u0645\u0627\u0646\u062f\u064a"
    ],
    "name:ben_bn_x_preferred":[
        "\u09ae\u09be\u09a8\u09cd\u09a1\u09bf"
    ],
    "name:ben_in_x_preferred":[
        "\u09ae\u09be\u09a8\u09cd\u09a1\u09bf"
    ],
    "name:ceb_x_preferred":[
        "Mandi"
    ],
    "name:deu_x_preferred":[
        "Mandi"
    ],
    "name:fin_x_preferred":[
        "Mandi"
    ],
    "name:guj_x_preferred":[
        "\u0aae\u0a82\u0aa1\u0ac0"
    ],
    "name:hin_x_preferred":[
        "\u092e\u0902\u0921\u0940"
    ],
    "name:ita_x_preferred":[
        "Mandi"
    ],
    "name:kan_x_preferred":[
        "\u0cae\u0c82\u0ca1\u0cbf"
    ],
    "name:mal_x_preferred":[
        "\u0d2e\u0d23\u0d4d\u0d21\u0d3f"
    ],
    "name:mar_x_preferred":[
        "\u092e\u0902\u0921\u0940"
    ],
    "name:nld_x_preferred":[
        "Mandi"
    ],
    "name:pan_x_preferred":[
        "\u0a2e\u0a70\u0a21\u0a40"
    ],
    "name:pol_x_preferred":[
        "Mandi"
    ],
    "name:rus_x_preferred":[
        "\u041c\u0430\u043d\u0434\u0438"
    ],
    "name:spa_x_preferred":[
        "Mandi"
    ],
    "name:swe_x_preferred":[
        "Mandi"
    ],
    "name:tam_x_preferred":[
        "\u0bae\u0ba9\u0bcd\u0b9f\u0bbf"
    ],
    "name:tel_x_preferred":[
        "\u0c2e\u0c02\u0c21\u0c3f"
    ],
    "name:ukr_x_preferred":[
        "\u041c\u0430\u043d\u0434\u0456"
    ],
    "name:urd_x_preferred":[
        "\u0645\u0627\u0646\u0688\u06cc"
    ],
    "wof:name":"Mandi",
    "wof:placetype":"locality"
},
  "geometry": {"coordinates":[76.38458,29.92612],"type":"Point"}
}