{
  "type": "Feature",
  "properties": {
    "iso:country":"IN",
    "ks:ks_name":"Datpura",
    "ks:ks_pop":1,
    "ks:ks_type":"HABITATION",
    "name:eng_x_preferred":[
        "Datpura"
    ],
    "wof:name":"Datpura",
    "wof:placetype":"locality",
    "wof:population":1
},
  "geometry": {"coordinates":[77.590035,22.638801],"type":"Point"}
}