{
  "type": "Feature",
  "properties": {
    "gn:admin1_code":"36",
    "gn:admin2_code":"159.0",
    "gn:asciiname":"Gadanpur Bakht",
    "gn:country_code":"IN",
    "gn:dem":150,
    "gn:feature_class":"P",
    "gn:feature_code":"PPL",
    "gn:name":"Gadanpur Bakht",
    "gn:population":0,
    "gn:timezone":"Asia/Kolkata",
    "iso:country":"IN",
    "ks:ks_name":"Gadanpurbagh",
    "ks:ks_pop":408,
    "ks:ks_type":"VILLAGE",
    "ks:ks_uagg_main":0,
    "name:eng_x_preferred":[
        "Gadanpurbagh"
    ],
    "wof:name":"Gadanpurbagh",
    "wof:placetype":"neighbourhood",
    "wof:population":408
},
  "geometry": {"coordinates":[79.50842799999999,27.461602],"type":"Point"}
}