{
  "type": "Feature",
  "properties": {
    "gn:admin1_code":"2.0",
    "gn:admin2_code":"547",
    "gn:asciiname":"Bantumilli",
    "gn:country_code":"IN",
    "gn:dem":8,
    "gn:feature_class":"P",
    "gn:feature_code":"PPL",
    "gn:name":"Bantumilli",
    "gn:population":0,
    "gn:timezone":"Asia/Kolkata",
    "iso:country":"IN",
    "name:new_x_preferred":[
        "\u092c\u0902\u091f\u0941\u092e\u093f\u0932\u094d\u0932\u093f \u092e\u0923\u094d\u0921\u0932"
    ],
    "name:tat_x_preferred":[
        "\u0411\u0430\u043d\u0442\u0443\u043c\u0438\u043b\u043b\u0438"
    ],
    "name:tel_x_preferred":[
        "\u0c2c\u0c02\u0c1f\u0c41\u0c2e\u0c3f\u0c32\u0c4d\u0c32\u0c3f"
    ],
    "name:urd_x_preferred":[
        "\u0628\u0646\u0679\u0648\u0645\u0644\u06cc"
    ],
    "wof:name":"Bantumilli",
    "wof:placetype":"locality"
},
  "geometry": {"coordinates":[81.27199999999998,16.37199],"type":"Point"}
}