{
  "type": "Feature",
  "properties": {
    "gn:admin1_code":"2.0",
    "gn:admin2_code":"547",
    "gn:asciiname":"Bantumilli",
    "gn:country_code":"IN",
    "gn:dem":8,
    "gn:feature_class":"P",
    "gn:feature_code":"PPL",
    "gn:name":"Bantumilli",
    "gn:population":0,
    "gn:timezone":"Asia/Kolkata",
    "iso:country":"IN",
    "wof:name":"Bantumilli",
    "wof:placetype":"locality"
},
  "geometry": {"coordinates":[81.27199999999998,16.37199],"type":"Point"}
}