{
  "type": "Feature",
  "properties": {
    "iso:country":"IN",
    "ks:ks_name":"Vanzarapara",
    "ks:ks_pop":425,
    "ks:ks_type":"HABITATION",
    "name:eng_x_preferred":[
        "Vanzarapara"
    ],
    "wof:name":"Vanzarapara",
    "wof:placetype":"locality",
    "wof:population":425
},
  "geometry": {"coordinates":[72.175994,23.810932],"type":"Point"}
}