{
  "type": "Feature",
  "properties": {
    "iso:country":"IN",
    "ks:ks_name":"Jadabpur",
    "ks:ks_pop":695,
    "ks:ks_type":"VILLAGE",
    "ks:ks_uagg_main":0,
    "name:eng_x_preferred":[
        "Jadabpur"
    ],
    "wof:name":"Jadabpur",
    "wof:placetype":"neighbourhood",
    "wof:population":695
},
  "geometry": {"coordinates":[88.31687599999999,22.89431],"type":"Point"}
}