{
  "type": "Feature",
  "properties": {
    "iso:country":"IN",
    "ks:ks_name":"Dharmpuri",
    "ks:ks_pop":413,
    "ks:ks_type":"VILLAGE",
    "name:eng_x_preferred":[
        "Dharmpuri"
    ],
    "wof:name":"Dharmpuri",
    "wof:placetype":"locality",
    "wof:population":413
},
  "geometry": {"coordinates":[75.58225,21.996498],"type":"Point"}
}