{
  "type": "Feature",
  "properties": {
    "gn:admin1_code":"24",
    "gn:admin2_code":"99.0",
    "gn:asciiname":"Rilmilsar",
    "gn:country_code":"IN",
    "gn:dem":173,
    "gn:feature_class":"P",
    "gn:feature_code":"PPL",
    "gn:name":"Rilmilsar",
    "gn:population":0,
    "gn:timezone":"Asia/Kolkata",
    "iso:country":"IN",
    "wof:name":"Rilmilsar",
    "wof:placetype":"locality"
},
  "geometry": {"coordinates":[73.73083000000003,29.56406],"type":"Point"}
}