{
  "type": "Feature",
  "properties": {
    "iso:country":"IN",
    "ks:ks_name":"Pittagedda",
    "ks:ks_pop":213,
    "ks:ks_type":"HABITATION",
    "name:eng_x_preferred":[
        "Pittagedda"
    ],
    "wof:name":"Pittagedda",
    "wof:placetype":"locality",
    "wof:population":213
},
  "geometry": {"coordinates":[82.37679300000001,18.249832],"type":"Point"}
}