{
  "type": "Feature",
  "properties": {
    "gn:admin1_code":"2",
    "gn:admin2_code":"545.0",
    "gn:asciiname":"Pudupalle",
    "gn:country_code":"IN",
    "gn:dem":45,
    "gn:feature_class":"P",
    "gn:feature_code":"PPL",
    "gn:name":"P\u016bdupalle",
    "gn:population":0,
    "gn:timezone":"Asia/Kolkata",
    "iso:country":"IN",
    "ks:ks_name":"Pudipalle",
    "ks:ks_pop":1048,
    "ks:ks_type":"VILLAGE",
    "name:eng_x_preferred":[
        "Pudipalle"
    ],
    "name:eng_x_variant":[
        "Pudupalle"
    ],
    "wof:name":"Pudipalle",
    "wof:placetype":"locality",
    "wof:population":1048
},
  "geometry": {"coordinates":[81.696023,17.292084],"type":"Point"}
}