{
  "type": "Feature",
  "properties": {
    "iso:country":"IN",
    "ks:ks_alt_nam":"Gomari no 2",
    "ks:ks_name":"Gomari No 2",
    "ks:ks_pop":1070,
    "ks:ks_type":"HABITATION",
    "ks:ks_uagg_main":0,
    "name:eng_x_preferred":[
        "Gomari No 2"
    ],
    "wof:name":"Gomari No 2",
    "wof:placetype":"neighbourhood",
    "wof:population":1070
},
  "geometry": {"coordinates":[94.087309,26.33865],"type":"Point"}
}