{
  "type": "Feature",
  "properties": {
    "iso:country":"IN",
    "ks:ks_name":"Simulia",
    "ks:ks_pop":2662,
    "ks:ks_type":"VILLAGE",
    "ks:ks_uagg_main":0,
    "name:eng_x_preferred":[
        "Simulia"
    ],
    "wof:name":"Simulia",
    "wof:placetype":"locality",
    "wof:population":2662
},
  "geometry": {"coordinates":[86.356652,23.30017],"type":"Point"}
}