{
  "type": "Feature",
  "properties": {
    "iso:country":"IN",
    "ks:ks_name":"Teleighutu",
    "ks:ks_pop":278,
    "ks:ks_type":"HABITATION",
    "name:eng_x_preferred":[
        "Teleighutu"
    ],
    "wof:name":"Teleighutu",
    "wof:placetype":"locality",
    "wof:population":278
},
  "geometry": {"coordinates":[86.496492,22.042264],"type":"Point"}
}