{
  "type": "Feature",
  "properties": {
    "iso:country":"IN",
    "ks:ks_name":"Chidaratanger",
    "ks:ks_pop":272,
    "ks:ks_type":"HABITATION",
    "name:eng_x_preferred":[
        "Chidaratanger"
    ],
    "wof:name":"Chidaratanger",
    "wof:placetype":"locality",
    "wof:population":272
},
  "geometry": {"coordinates":[84.041647,22.618532],"type":"Point"}
}