{
  "type": "Feature",
  "properties": {
    "iso:country":"IN",
    "ks:ks_alt_nam":"Motr\u0101",
    "ks:ks_name":"Motra",
    "ks:ks_pop":467,
    "ks:ks_type":"VILLAGE",
    "name:eng_x_preferred":[
        "Motra"
    ],
    "name:eng_x_variant":[
        "Motr\u0101"
    ],
    "wof:name":"Motra",
    "wof:placetype":"locality",
    "wof:population":467
},
  "geometry": {"coordinates":[85.29790199999999,23.862327],"type":"Point"}
}