{
  "type": "Feature",
  "properties": {
    "iso:country":"IN",
    "ks:ks_name":"Bhalia",
    "ks:ks_pop":174,
    "ks:ks_type":"VILLAGE",
    "name:eng_x_preferred":[
        "Bhalia"
    ],
    "wof:name":"Bhalia",
    "wof:placetype":"locality",
    "wof:population":174
},
  "geometry": {"coordinates":[83.193843,19.798172],"type":"Point"}
}