{
  "type": "Feature",
  "properties": {
    "iso:country":"IN",
    "ks:ks_name":"Loonara",
    "ks:ks_pop":2315,
    "ks:ks_type":"HABITATION",
    "name:eng_x_preferred":[
        "Loonara"
    ],
    "wof:name":"Loonara",
    "wof:placetype":"locality",
    "wof:population":2315
},
  "geometry": {"coordinates":[71.668781,26.114647],"type":"Point"}
}