{
  "type": "Feature",
  "properties": {
    "gn:admin1_code":"19.0",
    "gn:admin2_code":"558",
    "gn:asciiname":"Katak Chincholi",
    "gn:country_code":"IN",
    "gn:dem":603,
    "gn:feature_class":"P",
    "gn:feature_code":"PPL",
    "gn:name":"Katak Chincholi",
    "gn:population":0,
    "gn:timezone":"Asia/Kolkata",
    "iso:country":"IN",
    "wof:name":"Katak Chincholi",
    "wof:placetype":"locality"
},
  "geometry": {"coordinates":[77.20586999999998,17.90097],"type":"Point"}
}