{
  "type": "Feature",
  "properties": {
    "gn:admin1_code":"35.0",
    "gn:admin2_code":"464.0",
    "gn:asciiname":"Dudhi",
    "gn:country_code":"IN",
    "gn:dem":512,
    "gn:feature_class":"P",
    "gn:feature_code":"PPL",
    "gn:name":"Dudhi",
    "gn:population":0,
    "gn:timezone":"Asia/Kolkata",
    "iso:country":"IN",
    "name:bpy_x_preferred":[
        "\u09a6\u09c1\u09a7\u09bf"
    ],
    "name:ceb_x_preferred":[
        "D\u016bdhi"
    ],
    "name:hin_x_preferred":[
        "\u0926\u0941\u0926\u094d\u0927\u0940"
    ],
    "name:ita_x_preferred":[
        "Dudhi"
    ],
    "name:mlg_x_preferred":[
        "Dudhi"
    ],
    "name:msa_x_preferred":[
        "Dudhi"
    ],
    "name:new_x_preferred":[
        "\u0926\u0941\u0927\u0940"
    ],
    "name:nld_x_preferred":[
        "Dudhi"
    ],
    "name:pol_x_preferred":[
        "Dudhi"
    ],
    "name:por_x_preferred":[
        "Dudhi"
    ],
    "name:swe_x_preferred":[
        "D\u016bdhi"
    ],
    "name:urd_x_preferred":[
        "\u062f\u0648\u062f\u06be\u06cc"
    ],
    "name:vie_x_preferred":[
        "Dudhi"
    ],
    "wof:name":"Dudhi",
    "wof:placetype":"locality"
},
  "geometry": {"coordinates":[74.84121999999998,22.75963],"type":"Point"}
}