{
  "type": "Feature",
  "properties": {
    "gn:admin1_code":"12.0",
    "gn:admin2_code":"9.0",
    "gn:asciiname":"Athabut",
    "gn:country_code":"IN",
    "gn:dem":1869,
    "gn:feature_class":"P",
    "gn:feature_code":"PPL",
    "gn:name":"Athabut",
    "gn:population":0,
    "gn:timezone":"Asia/Kolkata",
    "iso:country":"IN",
    "name:eng_x_preferred":[
        "Athabut"
    ],
    "wof:name":"Athabut",
    "wof:placetype":"locality"
},
  "geometry": {"coordinates":[74.69936,34.49204],"type":"Point"}
}