{
  "type": "Feature",
  "properties": {
    "iso:country":"IN",
    "ks:ks_name":"Teliachook",
    "ks:ks_pop":627,
    "ks:ks_type":"VILLAGE",
    "name:eng_x_preferred":[
        "Teliachook"
    ],
    "wof:name":"Teliachook",
    "wof:placetype":"locality",
    "wof:population":627
},
  "geometry": {"coordinates":[92.935514,26.557862],"type":"Point"}
}