{
  "type": "Feature",
  "properties": {
    "iso:country":"IN",
    "ks:ks_name":"Gailadera",
    "ks:ks_pop":86,
    "ks:ks_type":"HABITATION",
    "name:eng_x_preferred":[
        "Gailadera"
    ],
    "wof:name":"Gailadera",
    "wof:placetype":"locality",
    "wof:population":86
},
  "geometry": {"coordinates":[75.867276,27.265352],"type":"Point"}
}