{
  "type": "Feature",
  "properties": {
    "iso:country":"IN",
    "ks:ks_alt_nam":"PATELTOLA",
    "ks:ks_name":"Pateltola",
    "ks:ks_pop":295,
    "ks:ks_type":"HABITATION",
    "name:eng_x_preferred":[
        "Pateltola"
    ],
    "wof:name":"Pateltola",
    "wof:placetype":"locality",
    "wof:population":295
},
  "geometry": {"coordinates":[81.9268,22.874915],"type":"Point"}
}