{
  "type": "Feature",
  "properties": {
    "iso:country":"IN",
    "ks:ks_name":"Girwarpur Ryt",
    "ks:ks_pop":35,
    "ks:ks_type":"HABITATION",
    "name:eng_x_preferred":[
        "Girwarpur Ryt"
    ],
    "wof:name":"Girwarpur Ryt",
    "wof:placetype":"locality",
    "wof:population":35
},
  "geometry": {"coordinates":[81.270753,22.797695],"type":"Point"}
}