{
  "type": "Feature",
  "properties": {
    "iso:country":"IN",
    "ks:ks_name":"Mahuwa",
    "ks:ks_pop":439,
    "ks:ks_type":"VILLAGE",
    "name:eng_x_preferred":[
        "Mahuwa"
    ],
    "wof:name":"Mahuwa",
    "wof:placetype":"locality",
    "wof:population":439
},
  "geometry": {"coordinates":[83.777829,23.055207],"type":"Point"}
}