{
  "type": "Feature",
  "properties": {
    "iso:country":"IN",
    "ks:ks_name":"Shiragalale Harijankeri",
    "ks:ks_pop":25,
    "ks:ks_type":"HABITATION",
    "name:eng_x_preferred":[
        "Shiragalale Harijankeri"
    ],
    "wof:name":"Shiragalale Harijankeri",
    "wof:placetype":"locality",
    "wof:population":25
},
  "geometry": {"coordinates":[74.774868,14.387333],"type":"Point"}
}