{
  "type": "Feature",
  "properties": {
    "gn:admin1_code":"11.0",
    "gn:admin2_code":"033",
    "gn:asciiname":"Kahal ka Jubar",
    "gn:country_code":"IN",
    "gn:dem":1206,
    "gn:feature_class":"P",
    "gn:feature_code":"PPL",
    "gn:name":"K\u0101hal ka Jubar",
    "gn:population":0,
    "gn:timezone":"Asia/Kolkata",
    "iso:country":"IN",
    "name:und_x_variant":[
        "K\u0101hal ka Jubar",
        "K\u0101hal ka Jubbar"
    ],
    "wof:name":"Kahal ka Jubar",
    "wof:placetype":"locality"
},
  "geometry": {"coordinates":[77.05574,31.20099],"type":"Point"}
}