{
  "type": "Feature",
  "properties": {
    "iso:country":"IN",
    "ks:ks_name":"Maghhoua",
    "ks:ks_pop":42,
    "ks:ks_type":"VILLAGE",
    "name:eng_x_preferred":[
        "Maghhoua"
    ],
    "wof:name":"Maghhoua",
    "wof:placetype":"locality",
    "wof:population":42
},
  "geometry": {"coordinates":[83.75700999999999,26.329694],"type":"Point"}
}