{
  "type": "Feature",
  "properties": {
    "gn:admin1_code":"25.0",
    "gn:admin2_code":"606.0",
    "gn:asciiname":"Madurampattu",
    "gn:country_code":"IN",
    "gn:dem":116,
    "gn:feature_class":"P",
    "gn:feature_code":"PPL",
    "gn:name":"M\u0101dur\u0101mpattu",
    "gn:population":0,
    "gn:timezone":"Asia/Kolkata",
    "iso:country":"IN",
    "ks:ks_alt_nam":"M\u0101dur\u0101mpattu",
    "ks:ks_name":"Madurampattu",
    "ks:ks_pop":1801,
    "ks:ks_type":"VILLAGE",
    "name:eng_x_preferred":[
        "Madurampattu"
    ],
    "name:eng_x_variant":[
        "M\u0101dur\u0101mpattu"
    ],
    "wof:name":"Madurampattu",
    "wof:placetype":"locality",
    "wof:population":1801
},
  "geometry": {"coordinates":[79.185264,12.06517],"type":"Point"}
}