{
  "type": "Feature",
  "properties": {
    "iso:country":"IN",
    "ks:ks_name":"Lakshanpur",
    "ks:ks_pop":226,
    "ks:ks_type":"VILLAGE",
    "name:eng_x_preferred":[
        "Lakshanpur"
    ],
    "wof:name":"Lakshanpur",
    "wof:placetype":"locality",
    "wof:population":226
},
  "geometry": {"coordinates":[86.735662,23.637206],"type":"Point"}
}