{
  "type": "Feature",
  "properties": {
    "gn:admin1_code":"38.0",
    "gn:admin2_code":"353.0",
    "gn:asciiname":"Dhangora",
    "gn:country_code":"IN",
    "gn:dem":112,
    "gn:feature_class":"P",
    "gn:feature_code":"PPL",
    "gn:name":"Dh\u0101ngora",
    "gn:population":0,
    "gn:timezone":"Asia/Kolkata",
    "iso:country":"IN",
    "ks:ks_name":"Dhanghara",
    "ks:ks_pop":153,
    "ks:ks_type":"VILLAGE",
    "name:eng_x_preferred":[
        "Dhanghara"
    ],
    "name:eng_x_variant":[
        "Dhangora"
    ],
    "wof:name":"Dhanghara",
    "wof:placetype":"locality",
    "wof:population":153
},
  "geometry": {"coordinates":[87.761098,24.620807],"type":"Point"}
}