{
  "type": "Feature",
  "properties": {
    "gn:admin1_code":"38.0",
    "gn:admin2_code":"352.0",
    "gn:asciiname":"Mande",
    "gn:country_code":"IN",
    "gn:dem":221,
    "gn:feature_class":"P",
    "gn:feature_code":"PPL",
    "gn:name":"M\u0101nde",
    "gn:population":0,
    "gn:timezone":"Asia/Kolkata",
    "iso:country":"IN",
    "name:ceb_x_preferred":[
        "Mande"
    ],
    "name:deu_x_preferred":[
        "Mande"
    ],
    "name:hrv_x_preferred":[
        "Mande"
    ],
    "name:nld_x_preferred":[
        "Mande"
    ],
    "name:por_x_preferred":[
        "Mande"
    ],
    "name:swe_x_preferred":[
        "Mande"
    ],
    "wof:name":"Mande",
    "wof:placetype":"locality"
},
  "geometry": {"coordinates":[87.72889000000001,25.2027],"type":"Point"}
}