{
  "type": "Feature",
  "properties": {
    "gn:admin1_code":"38.0",
    "gn:admin2_code":"352.0",
    "gn:asciiname":"Mande",
    "gn:country_code":"IN",
    "gn:dem":221,
    "gn:feature_class":"P",
    "gn:feature_code":"PPL",
    "gn:name":"M\u0101nde",
    "gn:population":0,
    "gn:timezone":"Asia/Kolkata",
    "iso:country":"IN",
    "ks:ks_alt_nam":"M\u0101nde",
    "ks:ks_name":"Mande",
    "ks:ks_pop":119,
    "ks:ks_type":"VILLAGE",
    "name:ceb_x_preferred":[
        "Mande"
    ],
    "name:deu_x_preferred":[
        "Mande"
    ],
    "name:eng_x_preferred":[
        "Mande"
    ],
    "name:eng_x_variant":[
        "M\u0101nde"
    ],
    "name:hrv_x_preferred":[
        "Mande"
    ],
    "name:nld_x_preferred":[
        "Mande"
    ],
    "name:por_x_preferred":[
        "Mande"
    ],
    "name:swe_x_preferred":[
        "Mande"
    ],
    "wof:name":"Mande",
    "wof:placetype":"locality",
    "wof:population":119
},
  "geometry": {"coordinates":[87.729079,25.202951],"type":"Point"}
}