{
  "type": "Feature",
  "properties": {
    "gn:admin1_code":"19.0",
    "gn:admin2_code":"573.0",
    "gn:asciiname":"Pihalli",
    "gn:country_code":"IN",
    "gn:dem":718,
    "gn:feature_class":"P",
    "gn:feature_code":"PPL",
    "gn:name":"Pihalli",
    "gn:population":0,
    "gn:timezone":"Asia/Kolkata",
    "iso:country":"IN",
    "wof:name":"Pihalli",
    "wof:placetype":"neighbourhood"
},
  "geometry": {"coordinates":[76.85507,12.45729],"type":"Point"}
}