{
  "type": "Feature",
  "properties": {
    "gn:admin1_code":"35.0",
    "gn:admin2_code":"419.0",
    "gn:asciiname":"Basahe ka Pura",
    "gn:country_code":"IN",
    "gn:dem":194,
    "gn:feature_class":"P",
    "gn:feature_code":"PPL",
    "gn:name":"Bas\u0101he ka Pura",
    "gn:population":0,
    "gn:timezone":"Asia/Kolkata",
    "iso:country":"IN",
    "wof:name":"Basahe ka Pura",
    "wof:placetype":"locality"
},
  "geometry": {"coordinates":[77.86951999999999,26.30183],"type":"Point"}
}