{
  "type": "Feature",
  "properties": {
    "iso:country":"IN",
    "ks:ks_alt_nam":"RAM TUIYA PARA",
    "ks:ks_name":"Ram Tuiya Para",
    "ks:ks_pop":184,
    "ks:ks_type":"HABITATION",
    "name:eng_x_preferred":[
        "Ram Tuiya Para"
    ],
    "wof:name":"Ram Tuiya Para",
    "wof:placetype":"locality",
    "wof:population":184
},
  "geometry": {"coordinates":[91.616079,23.786467],"type":"Point"}
}