{
  "type": "Feature",
  "properties": {
    "gn:admin1_code":"12.0",
    "gn:asciiname":"Mothu",
    "gn:country_code":"IN",
    "gn:dem":2268,
    "gn:feature_class":"P",
    "gn:feature_code":"PPL",
    "gn:name":"Mothu",
    "gn:population":0,
    "gn:timezone":"Asia/Kolkata",
    "iso:country":"IN",
    "wof:name":"Mothu",
    "wof:placetype":"locality"
},
  "geometry": {"coordinates":[73.92896999999998,34.04851],"type":"Point"}
}