{
  "type": "Feature",
  "properties": {
    "iso:country":"IN",
    "ks:ks_name":"Amali",
    "ks:ks_pop":89,
    "ks:ks_type":"VILLAGE",
    "name:eng_x_preferred":[
        "Amali"
    ],
    "wof:name":"Amali",
    "wof:placetype":"locality",
    "wof:population":89
},
  "geometry": {"coordinates":[80.313928,29.700566],"type":"Point"}
}