{
  "type": "Feature",
  "properties": {
    "gn:admin1_code":"12",
    "gn:admin2_code":"15.0",
    "gn:asciiname":"Hum Shalrbug",
    "gn:country_code":"IN",
    "gn:dem":1653,
    "gn:feature_class":"P",
    "gn:feature_code":"PPL",
    "gn:name":"Hum Sh\u0101lrbug",
    "gn:population":0,
    "gn:timezone":"Asia/Kolkata",
    "iso:country":"IN",
    "wof:name":"Hum Shalrbug",
    "wof:placetype":"locality"
},
  "geometry": {"coordinates":[75.02269,33.72663],"type":"Point"}
}