{
  "type": "Feature",
  "properties": {
    "gn:admin1_code":"37",
    "gn:admin2_code":"401.0",
    "gn:asciiname":"Dhouli",
    "gn:country_code":"IN",
    "gn:dem":343,
    "gn:feature_class":"P",
    "gn:feature_code":"PPL",
    "gn:name":"Dhouli",
    "gn:population":0,
    "gn:timezone":"Asia/Kolkata",
    "iso:country":"IN",
    "ks:ks_name":"Dhouli",
    "ks:ks_pop":970,
    "ks:ks_type":"VILLAGE",
    "name:eng_x_preferred":[
        "Dhouli"
    ],
    "wof:name":"Dhouli",
    "wof:placetype":"locality",
    "wof:population":970
},
  "geometry": {"coordinates":[83.411165,24.061619],"type":"Point"}
}