{
  "type": "Feature",
  "properties": {
    "gn:admin1_code":"37",
    "gn:admin2_code":"401.0",
    "gn:asciiname":"Dhouli",
    "gn:country_code":"IN",
    "gn:dem":343,
    "gn:feature_class":"P",
    "gn:feature_code":"PPL",
    "gn:name":"Dhouli",
    "gn:population":0,
    "gn:timezone":"Asia/Kolkata",
    "iso:country":"IN",
    "wof:name":"Dhouli",
    "wof:placetype":"locality"
},
  "geometry": {"coordinates":[83.41116,24.06162],"type":"Point"}
}