{
  "type": "Feature",
  "properties": {
    "gn:admin1_code":"11",
    "gn:admin2_code":"23.0",
    "gn:asciiname":"Samra",
    "gn:country_code":"IN",
    "gn:dem":2257,
    "gn:feature_class":"P",
    "gn:feature_code":"PPL",
    "gn:name":"S\u0101mra",
    "gn:population":0,
    "gn:timezone":"Asia/Kolkata",
    "iso:country":"IN",
    "name:ceb_x_preferred":[
        "Samra"
    ],
    "name:deu_x_preferred":[
        "Samra"
    ],
    "name:rus_x_preferred":[
        "\u0421\u0430\u043c\u0440\u0430"
    ],
    "wof:name":"Samra",
    "wof:placetype":"locality"
},
  "geometry": {"coordinates":[76.40446,32.40631],"type":"Point"}
}