{
  "type": "Feature",
  "properties": {
    "iso:country":"IN",
    "ks:ks_name":"Barba",
    "ks:ks_pop":0,
    "ks:ks_type":"VILLAGE",
    "name:eng_x_preferred":[
        "Barba"
    ],
    "wof:name":"Barba",
    "wof:placetype":"locality",
    "wof:population":0
},
  "geometry": {"coordinates":[84.113091,27.226969],"type":"Point"}
}