{
  "type": "Feature",
  "properties": {
    "iso:country":"IN",
    "ks:ks_name":"Jawahar Purwa",
    "ks:ks_pop":225,
    "ks:ks_type":"HABITATION",
    "ks:ks_uagg_main":0,
    "name:eng_x_preferred":[
        "Jawahar Purwa"
    ],
    "wof:name":"Jawahar Purwa",
    "wof:placetype":"neighbourhood",
    "wof:population":225
},
  "geometry": {"coordinates":[79.908798,26.838841],"type":"Point"}
}