{
  "type": "Feature",
  "properties": {
    "iso:country":"IN",
    "ks:ks_name":"8 NRD",
    "ks:ks_pop":38,
    "ks:ks_type":"VILLAGE",
    "name:eng_x_preferred":[
        "8 NRD"
    ],
    "wof:name":"8 NRD",
    "wof:placetype":"locality",
    "wof:population":38
},
  "geometry": {"coordinates":[73.711107,29.449854],"type":"Point"}
}