{
  "type": "Feature",
  "properties": {
    "gn:admin1_code":"36",
    "gn:admin2_code":"199.0",
    "gn:asciiname":"Rajgarhwa",
    "gn:country_code":"IN",
    "gn:dem":222,
    "gn:feature_class":"P",
    "gn:feature_code":"PPL",
    "gn:name":"Rajgarhwa",
    "gn:population":0,
    "gn:timezone":"Asia/Kolkata",
    "iso:country":"IN",
    "ks:ks_name":"Rajgarhwa",
    "ks:ks_pop":496,
    "ks:ks_type":"HABITATION",
    "name:eng_x_preferred":[
        "Rajgarhwa"
    ],
    "wof:name":"Rajgarhwa",
    "wof:placetype":"locality",
    "wof:population":496
},
  "geometry": {"coordinates":[82.495452,24.93411],"type":"Point"}
}