{
  "type": "Feature",
  "properties": {
    "iso:country":"IN",
    "ks:ks_name":"Aldamala",
    "ks:ks_pop":69,
    "ks:ks_type":"HABITATION",
    "name:eng_x_preferred":[
        "Aldamala"
    ],
    "wof:name":"Aldamala",
    "wof:placetype":"locality",
    "wof:population":69
},
  "geometry": {"coordinates":[82.52345800000001,18.492561],"type":"Point"}
}