{
  "type": "Feature",
  "properties": {
    "gn:admin1_code":"35.0",
    "gn:admin2_code":"457.0",
    "gn:asciiname":"Ataria",
    "gn:country_code":"IN",
    "gn:dem":578,
    "gn:feature_class":"P",
    "gn:feature_code":"PPL",
    "gn:name":"Atari\u0101",
    "gn:population":0,
    "gn:timezone":"Asia/Kolkata",
    "iso:country":"IN",
    "ks:ks_name":"Atariya",
    "ks:ks_pop":241,
    "ks:ks_type":"VILLAGE",
    "name:eng_x_preferred":[
        "Atariya"
    ],
    "name:eng_x_variant":[
        "Ataria"
    ],
    "name:eus_x_preferred":[
        "Ataria"
    ],
    "name:spa_x_preferred":[
        "Ataria"
    ],
    "wof:name":"Atariya",
    "wof:placetype":"locality",
    "wof:population":241
},
  "geometry": {"coordinates":[80.62112399999999,22.082404],"type":"Point"}
}