{
  "type": "Feature",
  "properties": {
    "gn:admin1_code":"35.0",
    "gn:admin2_code":"457.0",
    "gn:asciiname":"Ataria",
    "gn:country_code":"IN",
    "gn:dem":578,
    "gn:feature_class":"P",
    "gn:feature_code":"PPL",
    "gn:name":"Atari\u0101",
    "gn:population":0,
    "gn:timezone":"Asia/Kolkata",
    "iso:country":"IN",
    "name:eus_x_preferred":[
        "Ataria"
    ],
    "name:spa_x_preferred":[
        "Ataria"
    ],
    "wof:name":"Ataria",
    "wof:placetype":"locality"
},
  "geometry": {"coordinates":[80.62156,22.08186],"type":"Point"}
}