{
  "type": "Feature",
  "properties": {
    "iso:country":"IN",
    "ks:ks_name":"Ram Nagar",
    "ks:ks_pop":151,
    "ks:ks_type":"HABITATION",
    "name:eng_x_preferred":[
        "Ram Nagar"
    ],
    "wof:name":"Ram Nagar",
    "wof:placetype":"locality",
    "wof:population":151
},
  "geometry": {"coordinates":[79.77865799999999,26.637698],"type":"Point"}
}