{
  "type": "Feature",
  "properties": {
    "iso:country":"IN",
    "ks:ks_alt_nam":"PACHIM TOLA",
    "ks:ks_name":"Pachim Tola",
    "ks:ks_pop":200,
    "ks:ks_type":"HABITATION",
    "name:eng_x_preferred":[
        "Pachim Tola"
    ],
    "wof:name":"Pachim Tola",
    "wof:placetype":"locality",
    "wof:population":200
},
  "geometry": {"coordinates":[84.838308,26.191712],"type":"Point"}
}