{
  "type": "Feature",
  "properties": {
    "iso:country":"IN",
    "ks:ks_name":"Asayach",
    "ks:ks_pop":152,
    "ks:ks_type":"VILLAGE",
    "name:eng_x_preferred":[
        "Asayach"
    ],
    "wof:name":"Asayach",
    "wof:placetype":"locality",
    "wof:population":152
},
  "geometry": {"coordinates":[71.128703,26.84051],"type":"Point"}
}