{
  "type": "Feature",
  "properties": {
    "iso:country":"IN",
    "ks:ks_name":"Puduvalavu K",
    "ks:ks_pop":366,
    "ks:ks_type":"HABITATION",
    "ks:ks_uagg_main":0,
    "name:eng_x_preferred":[
        "Puduvalavu K"
    ],
    "wof:name":"Puduvalavu K",
    "wof:placetype":"neighbourhood",
    "wof:population":366
},
  "geometry": {"coordinates":[78.47552399999999,10.27871],"type":"Point"}
}