{
  "type": "Feature",
  "properties": {
    "iso:country":"IN",
    "ks:ks_name":"Hulugunda",
    "ks:ks_pop":2990,
    "ks:ks_type":"HABITATION",
    "name:eng_x_preferred":[
        "Hulugunda"
    ],
    "wof:name":"Hulugunda",
    "wof:placetype":"locality",
    "wof:population":2990
},
  "geometry": {"coordinates":[75.905815,12.49543],"type":"Point"}
}