{
  "type": "Feature",
  "properties": {
    "iso:country":"IN",
    "ks:ks_name":"Pal Basti",
    "ks:ks_pop":312,
    "ks:ks_type":"HABITATION",
    "name:eng_x_preferred":[
        "Pal Basti"
    ],
    "wof:name":"Pal Basti",
    "wof:placetype":"locality",
    "wof:population":312
},
  "geometry": {"coordinates":[82.06929,25.926648],"type":"Point"}
}