{
  "type": "Feature",
  "properties": {
    "iso:country":"IN",
    "ks:ks_alt_nam":"Tikuri kothar",
    "ks:ks_name":"Tikuri Kothar",
    "ks:ks_pop":124,
    "ks:ks_type":"HABITATION",
    "name:eng_x_preferred":[
        "Tikuri Kothar"
    ],
    "wof:name":"Tikuri Kothar",
    "wof:placetype":"locality",
    "wof:population":124
},
  "geometry": {"coordinates":[80.832742,24.642843],"type":"Point"}
}