{
  "type": "Feature",
  "properties": {
    "iso:country":"IN",
    "ks:ks_name":"Chaupada",
    "ks:ks_pop":93,
    "ks:ks_type":"VILLAGE",
    "name:eng_x_preferred":[
        "Chaupada"
    ],
    "wof:name":"Chaupada",
    "wof:placetype":"locality",
    "wof:population":93
},
  "geometry": {"coordinates":[80.549801,24.72369],"type":"Point"}
}