{
  "type": "Feature",
  "properties": {
    "iso:country":"IN",
    "ks:ks_name":"Byadhpara",
    "ks:ks_pop":1324,
    "ks:ks_type":"HABITATION",
    "name:eng_x_preferred":[
        "Byadhpara"
    ],
    "wof:name":"Byadhpara",
    "wof:placetype":"locality",
    "wof:population":1324
},
  "geometry": {"coordinates":[88.840919,26.279324],"type":"Point"}
}