{
  "type": "Feature",
  "properties": {
    "gn:admin1_code":"12",
    "gn:admin2_code":"18.0",
    "gn:asciiname":"Halur",
    "gn:country_code":"IN",
    "gn:dem":2383,
    "gn:feature_class":"P",
    "gn:feature_code":"PPL",
    "gn:name":"Hal\u016br",
    "gn:population":0,
    "gn:timezone":"Asia/Kolkata",
    "iso:country":"IN",
    "wof:name":"Halur",
    "wof:placetype":"locality"
},
  "geometry": {"coordinates":[76.19965999999999,33.3001],"type":"Point"}
}