{
  "type": "Feature",
  "properties": {
    "gn:admin1_code":"40.0",
    "gn:admin2_code":"540.0",
    "gn:asciiname":"Gonepalli",
    "gn:country_code":"IN",
    "gn:dem":131,
    "gn:feature_class":"P",
    "gn:feature_code":"PPL",
    "gn:name":"Gonepalli",
    "gn:population":0,
    "gn:timezone":"Asia/Kolkata",
    "iso:country":"IN",
    "ks:ks_name":"Gonepalle",
    "ks:ks_pop":261,
    "ks:ks_type":"VILLAGE",
    "name:eng_x_preferred":[
        "Gonepalle"
    ],
    "name:eng_x_variant":[
        "Gonepalli"
    ],
    "wof:name":"Gonepalle",
    "wof:placetype":"locality",
    "wof:population":261
},
  "geometry": {"coordinates":[80.22031699999999,18.269729],"type":"Point"}
}