{
  "type": "Feature",
  "properties": {
    "iso:country":"IN",
    "ks:ks_name":"Khuti Para",
    "ks:ks_pop":2000,
    "ks:ks_type":"HABITATION",
    "name:eng_x_preferred":[
        "Khuti Para"
    ],
    "wof:name":"Khuti Para",
    "wof:placetype":"locality",
    "wof:population":2000
},
  "geometry": {"coordinates":[88.561449,22.240925],"type":"Point"}
}