{
  "type": "Feature",
  "properties": {
    "iso:country":"IN",
    "ks:ks_name":"Kotmunda Dehlia Falia",
    "ks:ks_pop":1187,
    "ks:ks_type":"HABITATION",
    "name:eng_x_preferred":[
        "Kotmunda Dehlia Falia"
    ],
    "wof:name":"Kotmunda Dehlia Falia",
    "wof:placetype":"locality",
    "wof:population":1187
},
  "geometry": {"coordinates":[73.26047199999999,21.136639],"type":"Point"}
}