{
  "type": "Feature",
  "properties": {
    "iso:country":"IN",
    "ks:ks_alt_nam":"PURE JEET",
    "ks:ks_name":"Pure Jeet",
    "ks:ks_pop":154,
    "ks:ks_type":"HABITATION",
    "ks:ks_uagg_main":0,
    "name:eng_x_preferred":[
        "Pure Jeet"
    ],
    "wof:name":"Pure Jeet",
    "wof:placetype":"neighbourhood",
    "wof:population":154
},
  "geometry": {"coordinates":[81.359764,26.192721],"type":"Point"}
}