{
  "type": "Feature",
  "properties": {
    "gn:admin1_code":"7.0",
    "gn:admin2_code":"90.0",
    "gn:asciiname":"Bhorgarh",
    "gn:country_code":"IN",
    "gn:dem":218,
    "gn:feature_class":"P",
    "gn:feature_code":"PPL",
    "gn:name":"Bhorgarh",
    "gn:population":0,
    "gn:timezone":"Asia/Kolkata",
    "iso:country":"IN",
    "wof:name":"Bhorgarh",
    "wof:placetype":"locality"
},
  "geometry": {"coordinates":[77.09520999999999,28.82926],"type":"Point"}
}