{
  "type": "Feature",
  "properties": {
    "iso:country":"IN",
    "ks:ks_name":"Wandhalsu",
    "ks:ks_pop":72,
    "ks:ks_type":"HABITATION",
    "name:eng_x_preferred":[
        "Wandhalsu"
    ],
    "wof:name":"Wandhalsu",
    "wof:placetype":"locality",
    "wof:population":72
},
  "geometry": {"coordinates":[74.603398,14.121619],"type":"Point"}
}