{
  "type": "Feature",
  "properties": {
    "iso:country":"IN",
    "ks:ks_name":"Ludhgawanbarachh",
    "ks:ks_pop":427,
    "ks:ks_type":"HABITATION",
    "name:eng_x_preferred":[
        "Ludhgawanbarachh"
    ],
    "wof:name":"Ludhgawanbarachh",
    "wof:placetype":"locality",
    "wof:population":427
},
  "geometry": {"coordinates":[80.17218,24.520766],"type":"Point"}
}