{
  "type": "Feature",
  "properties": {
    "gn:admin1_code":"34.0",
    "gn:admin2_code":"219.0",
    "gn:asciiname":"Khawaspur",
    "gn:country_code":"IN",
    "gn:dem":60,
    "gn:feature_class":"P",
    "gn:feature_code":"PPL",
    "gn:name":"Khaw\u0101spur",
    "gn:population":0,
    "gn:timezone":"Asia/Kolkata",
    "iso:country":"IN",
    "ks:ks_alt_nam":"Khaw\u0101spur",
    "ks:ks_name":"Khawaspur",
    "ks:ks_type":"VILLAGE",
    "ks:ks_uagg_main":0,
    "name:eng_x_preferred":[
        "Khawaspur"
    ],
    "name:eng_x_variant":[
        "Khaw\u0101spur"
    ],
    "name:urd_x_preferred":[
        "\u062e\u0648\u0627\u0635 \u067e\u0648\u0631"
    ],
    "wof:name":"Khawaspur",
    "wof:placetype":"locality"
},
  "geometry": {"coordinates":[84.834716,25.730589],"type":"Point"}
}