{
  "type": "Feature",
  "properties": {
    "gn:admin1_code":"16",
    "gn:admin2_code":"507.0",
    "gn:asciiname":"Palandur",
    "gn:country_code":"IN",
    "gn:dem":270,
    "gn:feature_class":"P",
    "gn:feature_code":"PPL",
    "gn:name":"Pal\u0101ndur",
    "gn:population":0,
    "gn:timezone":"Asia/Kolkata",
    "iso:country":"IN",
    "name:mar_x_preferred":[
        "\u092a\u093e\u0932\u093e\u0902\u0926\u0942\u0930"
    ],
    "name:urd_x_preferred":[
        "\u067e\u0644\u0646\u062f\u0648\u0631"
    ],
    "wof:name":"Palandur",
    "wof:placetype":"locality"
},
  "geometry": {"coordinates":[80.25993000000003,20.8511],"type":"Point"}
}