{
  "type": "Feature",
  "properties": {
    "iso:country":"IN",
    "ks:ks_name":"Nai Tola",
    "ks:ks_pop":125,
    "ks:ks_type":"HABITATION",
    "name:eng_x_preferred":[
        "Nai Tola"
    ],
    "wof:name":"Nai Tola",
    "wof:placetype":"locality",
    "wof:population":125
},
  "geometry": {"coordinates":[87.37427700000001,25.227585],"type":"Point"}
}