{
  "type": "Feature",
  "properties": {
    "iso:country":"IN",
    "ks:ks_name":"Rajupur Kalan",
    "ks:ks_pop":1369,
    "ks:ks_type":"VILLAGE",
    "ks:ks_uagg_main":0,
    "name:eng_x_preferred":[
        "Rajupur Kalan"
    ],
    "wof:name":"Rajupur Kalan",
    "wof:placetype":"neighbourhood",
    "wof:population":1369
},
  "geometry": {"coordinates":[78.749161,29.182023],"type":"Point"}
}