{
  "type": "Feature",
  "properties": {
    "gn:admin1_code":"34",
    "gn:admin2_code":"233.0",
    "gn:asciiname":"Dumdum",
    "gn:country_code":"IN",
    "gn:dem":92,
    "gn:feature_class":"P",
    "gn:feature_code":"PPL",
    "gn:name":"Dumdum",
    "gn:population":0,
    "gn:timezone":"Asia/Kolkata",
    "iso:country":"IN",
    "name:ara_x_preferred":[
        "\u062f\u0645\u062f\u0645"
    ],
    "name:ben_bn_x_preferred":[
        "\u09a6\u09ae\u09a6\u09ae"
    ],
    "name:ben_in_x_preferred":[
        "\u09a6\u09ae\u09a6\u09ae"
    ],
    "name:guj_x_preferred":[
        "\u0aa1\u0aae\u0aa1\u0aae"
    ],
    "name:hin_x_preferred":[
        "\u0926\u092e\u0926\u092e"
    ],
    "name:kan_x_preferred":[
        "\u0ca1\u0cae\u0ccd"
    ],
    "name:mal_x_preferred":[
        "\u0d26\u0d41\u0d02\u0d26\u0d41\u0d02"
    ],
    "name:mar_x_preferred":[
        "\u0926\u092e\u0926\u092e"
    ],
    "name:pan_x_preferred":[
        "\u0a26\u0a2e\u0a26\u0a2e"
    ],
    "name:tam_x_preferred":[
        "\u0b9f\u0bae\u0bcd\u0b9f\u0bae\u0bcd"
    ],
    "name:tel_x_preferred":[
        "\u0c21\u0c02\u0c21\u0c02"
    ],
    "name:urd_x_preferred":[
        "\u062f\u0645\u062f\u0645"
    ],
    "wof:name":"Dumdum",
    "wof:placetype":"locality"
},
  "geometry": {"coordinates":[83.58819,25.02452000000001],"type":"Point"}
}