{
  "type": "Feature",
  "properties": {
    "iso:country":"IN",
    "ks:ks_alt_nam":"lower tola",
    "ks:ks_name":"Lower Tola",
    "ks:ks_pop":107,
    "ks:ks_type":"HABITATION",
    "name:eng_x_preferred":[
        "Lower Tola"
    ],
    "wof:name":"Lower Tola",
    "wof:placetype":"locality",
    "wof:population":107
},
  "geometry": {"coordinates":[86.50593000000001,24.598225],"type":"Point"}
}