{
  "type": "Feature",
  "properties": {
    "gn:admin1_code":"19.0",
    "gn:admin2_code":"582.0",
    "gn:asciiname":"Gousanhalli",
    "gn:country_code":"IN",
    "gn:dem":945,
    "gn:feature_class":"P",
    "gn:feature_code":"PPL",
    "gn:name":"Gousanhalli",
    "gn:population":0,
    "gn:timezone":"Asia/Kolkata",
    "iso:country":"IN",
    "wof:name":"Gousanhalli",
    "wof:placetype":"neighbourhood"
},
  "geometry": {"coordinates":[77.63522,13.3981],"type":"Point"}
}