{
  "type": "Feature",
  "properties": {
    "gn:admin1_code":"2",
    "gn:admin2_code":"547.0",
    "gn:asciiname":"Naikangudem",
    "gn:country_code":"IN",
    "gn:dem":145,
    "gn:feature_class":"P",
    "gn:feature_code":"PPL",
    "gn:name":"N\u0101ikang\u016bdem",
    "gn:population":0,
    "gn:timezone":"Asia/Kolkata",
    "iso:country":"IN",
    "wof:name":"Naikangudem",
    "wof:placetype":"locality"
},
  "geometry": {"coordinates":[80.78123000000002,17.05414],"type":"Point"}
}