{
  "type": "Feature",
  "properties": {
    "iso:country":"IN",
    "ks:ks_name":"Bisaua Bhual",
    "ks:ks_pop":978,
    "ks:ks_type":"VILLAGE",
    "name:eng_x_preferred":[
        "Bisaua Bhual"
    ],
    "wof:name":"Bisaua Bhual",
    "wof:placetype":"locality",
    "wof:population":978
},
  "geometry": {"coordinates":[85.91015899999999,25.516545],"type":"Point"}
}