{
  "type": "Feature",
  "properties": {
    "iso:country":"IN",
    "ks:ks_name":"Kumabatoli",
    "ks:ks_pop":102,
    "ks:ks_type":"HABITATION",
    "name:eng_x_preferred":[
        "Kumabatoli"
    ],
    "wof:name":"Kumabatoli",
    "wof:placetype":"locality",
    "wof:population":102
},
  "geometry": {"coordinates":[84.280477,22.534649],"type":"Point"}
}