{
  "type": "Feature",
  "properties": {
    "gn:admin1_code":"16",
    "gn:admin2_code":"502.0",
    "gn:asciiname":"Bhur",
    "gn:country_code":"IN",
    "gn:dem":449,
    "gn:feature_class":"P",
    "gn:feature_code":"PPL",
    "gn:name":"Bhur",
    "gn:population":0,
    "gn:timezone":"Asia/Kolkata",
    "iso:country":"IN",
    "name:ceb_x_preferred":[
        "Bhoor"
    ],
    "name:msa_x_preferred":[
        "Bhoor"
    ],
    "name:nep_x_preferred":[
        "\u092d\u0941\u0930"
    ],
    "name:new_x_preferred":[
        "\u092d\u0941\u0930"
    ],
    "name:pol_x_preferred":[
        "Bhoor"
    ],
    "wof:name":"Bhur",
    "wof:placetype":"locality"
},
  "geometry": {"coordinates":[77.21576,20.3914],"type":"Point"}
}