{
  "type": "Feature",
  "properties": {
    "iso:country":"IN",
    "ks:ks_name":"Bayadih",
    "ks:ks_pop":419,
    "ks:ks_type":"HABITATION",
    "name:eng_x_preferred":[
        "Bayadih"
    ],
    "wof:name":"Bayadih",
    "wof:placetype":"locality",
    "wof:population":419
},
  "geometry": {"coordinates":[83.443499,24.187964],"type":"Point"}
}