{
  "type": "Feature",
  "properties": {
    "iso:country":"IN",
    "ks:ks_name":"Pichagunta",
    "ks:ks_pop":109,
    "ks:ks_type":"HABITATION",
    "name:eng_x_preferred":[
        "Pichagunta"
    ],
    "wof:name":"Pichagunta",
    "wof:placetype":"locality",
    "wof:population":109
},
  "geometry": {"coordinates":[79.845946,13.723684],"type":"Point"}
}