{
  "type": "Feature",
  "properties": {
    "iso:country":"IN",
    "ks:ks_name":"Changel Urf Madhurapur",
    "ks:ks_pop":3328,
    "ks:ks_type":"VILLAGE",
    "name:eng_x_preferred":[
        "Changel Urf Madhurapur"
    ],
    "wof:name":"Changel Urf Madhurapur",
    "wof:placetype":"locality",
    "wof:population":3328
},
  "geometry": {"coordinates":[85.64204700000001,26.279551],"type":"Point"}
}