{
  "type": "Feature",
  "properties": {
    "iso:country":"IN",
    "ks:ks_name":"Haji Deeh",
    "ks:ks_pop":357,
    "ks:ks_type":"HABITATION",
    "name:eng_x_preferred":[
        "Haji Deeh"
    ],
    "wof:name":"Haji Deeh",
    "wof:placetype":"locality",
    "wof:population":357
},
  "geometry": {"coordinates":[82.71643299999999,27.224819],"type":"Point"}
}