{
  "type": "Feature",
  "properties": {
    "gn:admin1_code":"19.0",
    "gn:admin2_code":"566.0",
    "gn:asciiname":"Chikka Iranna Malige",
    "gn:country_code":"IN",
    "gn:dem":664,
    "gn:feature_class":"P",
    "gn:feature_code":"PPL",
    "gn:name":"Chikka \u012aranna M\u0101lige",
    "gn:population":0,
    "gn:timezone":"Asia/Kolkata",
    "iso:country":"IN",
    "wof:name":"Chikka Iranna Malige",
    "wof:placetype":"neighbourhood"
},
  "geometry": {"coordinates":[76.52737,14.03994],"type":"Point"}
}