{
  "type": "Feature",
  "properties": {
    "iso:country":"IN",
    "ks:ks_name":"Koiri Tola",
    "ks:ks_pop":200,
    "ks:ks_type":"HABITATION",
    "name:eng_x_preferred":[
        "Koiri Tola"
    ],
    "wof:name":"Koiri Tola",
    "wof:placetype":"locality",
    "wof:population":200
},
  "geometry": {"coordinates":[83.75551400000001,26.93659],"type":"Point"}
}