{
  "type": "Feature",
  "properties": {
    "iso:country":"IN",
    "ks:ks_name":"Maladhia",
    "ks:ks_pop":0,
    "ks:ks_type":"VILLAGE",
    "name:eng_x_preferred":[
        "Maladhia"
    ],
    "wof:name":"Maladhia",
    "wof:placetype":"locality",
    "wof:population":0
},
  "geometry": {"coordinates":[86.729662,20.486407],"type":"Point"}
}