{
  "type": "Feature",
  "properties": {
    "iso:country":"IN",
    "ks:ks_name":"Andhiya",
    "ks:ks_pop":275,
    "ks:ks_type":"HABITATION",
    "name:eng_x_preferred":[
        "Andhiya"
    ],
    "wof:name":"Andhiya",
    "wof:placetype":"locality",
    "wof:population":275
},
  "geometry": {"coordinates":[79.82970400000001,27.197667],"type":"Point"}
}