{
  "type": "Feature",
  "properties": {
    "iso:country":"IN",
    "ks:ks_name":"Gadabapalem",
    "ks:ks_pop":24,
    "ks:ks_type":"HABITATION",
    "name:eng_x_preferred":[
        "Gadabapalem"
    ],
    "wof:name":"Gadabapalem",
    "wof:placetype":"locality",
    "wof:population":24
},
  "geometry": {"coordinates":[82.797588,17.785915],"type":"Point"}
}