{
  "type": "Feature",
  "properties": {
    "iso:country":"IN",
    "ks:ks_name":"Ugritola",
    "ks:ks_pop":5155,
    "ks:ks_type":"VILLAGE",
    "ks:ks_uagg_main":0,
    "name:eng_x_preferred":[
        "Ugritola"
    ],
    "wof:name":"Ugritola",
    "wof:placetype":"neighbourhood",
    "wof:population":5155
},
  "geometry": {"coordinates":[87.897818,25.077675],"type":"Point"}
}