{
  "type": "Feature",
  "properties": {
    "iso:country":"IN",
    "ks:ks_name":"Minya Tola",
    "ks:ks_pop":630,
    "ks:ks_type":"HABITATION",
    "ks:ks_uagg_main":0,
    "name:eng_x_preferred":[
        "Minya Tola"
    ],
    "wof:name":"Minya Tola",
    "wof:placetype":"neighbourhood",
    "wof:population":630
},
  "geometry": {"coordinates":[84.51334,27.00393],"type":"Point"}
}