{
  "type": "Feature",
  "properties": {
    "iso:country":"IN",
    "ks:ks_name":"Khiriya",
    "ks:ks_pop":10,
    "ks:ks_type":"HABITATION",
    "name:eng_x_preferred":[
        "Khiriya"
    ],
    "wof:name":"Khiriya",
    "wof:placetype":"locality",
    "wof:population":10
},
  "geometry": {"coordinates":[77.71001800000001,23.660464],"type":"Point"}
}