{
  "type": "Feature",
  "properties": {
    "gn:admin1_code":"25.0",
    "gn:admin2_code":"633.0",
    "gn:asciiname":"Virankuttaivalasu",
    "gn:country_code":"IN",
    "gn:dem":282,
    "gn:feature_class":"P",
    "gn:feature_code":"PPL",
    "gn:name":"V\u012brankuttaivalasu",
    "gn:population":0,
    "gn:timezone":"Asia/Kolkata",
    "iso:country":"IN",
    "wof:name":"Virankuttaivalasu",
    "wof:placetype":"locality"
},
  "geometry": {"coordinates":[77.56409000000002,11.06258],"type":"Point"}
}