{
  "type": "Feature",
  "properties": {
    "gn:admin1_code":"35",
    "gn:admin2_code":"426.0",
    "gn:asciiname":"Bolia",
    "gn:country_code":"IN",
    "gn:dem":476,
    "gn:feature_class":"P",
    "gn:feature_code":"PPL",
    "gn:name":"Bolia",
    "gn:population":0,
    "gn:timezone":"Asia/Kolkata",
    "iso:country":"IN",
    "name:ceb_x_preferred":[
        "Bolia"
    ],
    "name:fra_x_preferred":[
        "Bolia"
    ],
    "name:swe_x_preferred":[
        "Bolia"
    ],
    "wof:name":"Bolia",
    "wof:placetype":"locality"
},
  "geometry": {"coordinates":[80.4764,24.32547000000001],"type":"Point"}
}