{
  "type": "Feature",
  "properties": {
    "gn:admin1_code":"34.0",
    "gn:admin2_code":"219.0",
    "gn:asciiname":"Ratanpura",
    "gn:country_code":"IN",
    "gn:dem":57,
    "gn:feature_class":"P",
    "gn:feature_code":"PPL",
    "gn:name":"Ratanpura",
    "gn:population":0,
    "gn:timezone":"Asia/Kolkata",
    "iso:country":"IN",
    "name:hin_x_preferred":[
        "\u0930\u0924\u0928\u092a\u0941\u0930\u093e"
    ],
    "wof:name":"Ratanpura",
    "wof:placetype":"locality"
},
  "geometry": {"coordinates":[84.73183,25.79978],"type":"Point"}
}