{
  "type": "Feature",
  "properties": {
    "iso:country":"IN",
    "ks:ks_name":"Karli",
    "ks:ks_pop":27,
    "ks:ks_type":"VILLAGE",
    "name:eng_x_preferred":[
        "Karli"
    ],
    "wof:name":"Karli",
    "wof:placetype":"locality",
    "wof:population":27
},
  "geometry": {"coordinates":[78.930609,21.160361],"type":"Point"}
}