{
  "type": "Feature",
  "properties": {
    "gn:admin1_code":"39.0",
    "gn:admin2_code":"68.0",
    "gn:asciiname":"Thekawala Khatta",
    "gn:country_code":"IN",
    "gn:dem":269,
    "gn:feature_class":"P",
    "gn:feature_code":"PPL",
    "gn:name":"Thek\u0101w\u0101la Khatta",
    "gn:population":0,
    "gn:timezone":"Asia/Kolkata",
    "iso:country":"IN",
    "wof:name":"Thekawala Khatta",
    "wof:placetype":"locality"
},
  "geometry": {"coordinates":[78.23723000000003,29.78102],"type":"Point"}
}