{
  "type": "Feature",
  "properties": {
    "iso:country":"IN",
    "ks:ks_name":"Boolchand Pur",
    "ks:ks_pop":790,
    "ks:ks_type":"VILLAGE",
    "ks:ks_uagg_main":0,
    "name:eng_x_preferred":[
        "Boolchand Pur"
    ],
    "wof:name":"Boolchand Pur",
    "wof:placetype":"neighbourhood",
    "wof:population":790
},
  "geometry": {"coordinates":[78.285787,29.556416],"type":"Point"}
}