{
  "type": "Feature",
  "properties": {
    "gn:admin1_code":"28.0",
    "gn:admin2_code":"330.0",
    "gn:asciiname":"Dala",
    "gn:country_code":"IN",
    "gn:dem":48,
    "gn:feature_class":"P",
    "gn:feature_code":"PPL",
    "gn:name":"D\u0101la",
    "gn:population":0,
    "gn:timezone":"Asia/Kolkata",
    "iso:country":"IN",
    "name:ceb_x_preferred":[
        "Dala"
    ],
    "name:deu_x_preferred":[
        "Dala"
    ],
    "name:fin_x_preferred":[
        "Dala"
    ],
    "name:fra_x_preferred":[
        "Dala"
    ],
    "name:ita_x_preferred":[
        "Dala"
    ],
    "name:nld_x_preferred":[
        "Dala"
    ],
    "name:swe_x_preferred":[
        "Dala"
    ],
    "wof:name":"Dala",
    "wof:placetype":"locality"
},
  "geometry": {"coordinates":[87.97985,25.98074],"type":"Point"}
}