{
  "type": "Feature",
  "properties": {
    "iso:country":"IN",
    "ks:ks_name":"Bataliguri",
    "ks:ks_pop":265,
    "ks:ks_type":"VILLAGE",
    "ks:ks_uagg_main":0,
    "name:eng_x_preferred":[
        "Bataliguri"
    ],
    "wof:name":"Bataliguri",
    "wof:placetype":"locality",
    "wof:population":265
},
  "geometry": {"coordinates":[88.332714,26.735787],"type":"Point"}
}