{
  "type": "Feature",
  "properties": {
    "gn:admin1_code":"24.0",
    "gn:admin2_code":"129.0",
    "gn:asciiname":"Bilonya",
    "gn:country_code":"IN",
    "gn:dem":341,
    "gn:feature_class":"P",
    "gn:feature_code":"PPL",
    "gn:name":"Bilonya",
    "gn:population":0,
    "gn:timezone":"Asia/Kolkata",
    "iso:country":"IN",
    "wof:name":"Bilonya",
    "wof:placetype":"locality"
},
  "geometry": {"coordinates":[76.10695,24.64248],"type":"Point"}
}