{
  "type": "Feature",
  "properties": {
    "gn:admin1_code":"24.0",
    "gn:admin2_code":"129.0",
    "gn:asciiname":"Bilonya",
    "gn:country_code":"IN",
    "gn:dem":341,
    "gn:feature_class":"P",
    "gn:feature_code":"PPL",
    "gn:name":"Bilonya",
    "gn:population":0,
    "gn:timezone":"Asia/Kolkata",
    "iso:country":"IN",
    "ks:ks_name":"Biloniya",
    "ks:ks_pop":448,
    "ks:ks_type":"VILLAGE",
    "name:eng_x_preferred":[
        "Biloniya"
    ],
    "name:eng_x_variant":[
        "Bilonya"
    ],
    "wof:name":"Biloniya",
    "wof:placetype":"locality",
    "wof:population":448
},
  "geometry": {"coordinates":[76.10719,24.642246],"type":"Point"}
}