{
  "type": "Feature",
  "properties": {
    "gn:admin1_code":"39.0",
    "gn:admin2_code":"63.0",
    "gn:asciiname":"Nadela",
    "gn:country_code":"IN",
    "gn:dem":1430,
    "gn:feature_class":"P",
    "gn:feature_code":"PPL",
    "gn:name":"Nadela",
    "gn:population":0,
    "gn:timezone":"Asia/Kolkata",
    "iso:country":"IN",
    "name:fas_x_preferred":[
        "\u0646\u0627\u062f\u0644\u0627"
    ],
    "name:fra_x_preferred":[
        "Nadela"
    ],
    "name:nno_x_preferred":[
        "Nadela"
    ],
    "name:srp_x_preferred":[
        "\u041d\u0430\u0434\u0435\u043b\u0430"
    ],
    "name:tgk_x_preferred":[
        "\u041d\u0430\u0434\u0435\u043b\u0430"
    ],
    "wof:name":"Nadela",
    "wof:placetype":"locality"
},
  "geometry": {"coordinates":[79.77330000000001,29.78702],"type":"Point"}
}