{
  "type": "Feature",
  "properties": {
    "gn:admin1_code":"36.0",
    "gn:admin2_code":"182.0",
    "gn:asciiname":"Pakri",
    "gn:country_code":"IN",
    "gn:dem":104,
    "gn:feature_class":"P",
    "gn:feature_code":"PPL",
    "gn:name":"Pakri",
    "gn:population":0,
    "gn:timezone":"Asia/Kolkata",
    "iso:country":"IN",
    "name:est_x_preferred":[
        "Pakri"
    ],
    "name:lav_x_preferred":[
        "Pakri"
    ],
    "wof:name":"Pakri",
    "wof:placetype":"neighbourhood"
},
  "geometry": {"coordinates":[82.42464,27.43122],"type":"Point"}
}