{
  "type": "Feature",
  "properties": {
    "gn:admin1_code":"38.0",
    "gn:admin2_code":"362.0",
    "gn:asciiname":"Dhobaghati",
    "gn:country_code":"IN",
    "gn:dem":81,
    "gn:feature_class":"P",
    "gn:feature_code":"PPL",
    "gn:name":"Dhob\u0101gh\u0101ti",
    "gn:population":0,
    "gn:timezone":"Asia/Kolkata",
    "iso:country":"IN",
    "wof:name":"Dhobaghati",
    "wof:placetype":"locality"
},
  "geometry": {"coordinates":[87.56053,24.09069],"type":"Point"}
}