{
  "type": "Feature",
  "properties": {
    "iso:country":"IN",
    "ks:ks_name":"Bakiyapara",
    "ks:ks_pop":141,
    "ks:ks_type":"HABITATION",
    "name:eng_x_preferred":[
        "Bakiyapara"
    ],
    "wof:name":"Bakiyapara",
    "wof:placetype":"locality",
    "wof:population":141
},
  "geometry": {"coordinates":[82.90723300000001,23.01858],"type":"Point"}
}