{
  "type": "Feature",
  "properties": {
    "gn:admin1_code":"35.0",
    "gn:admin2_code":"457",
    "gn:asciiname":"Damoh",
    "gn:country_code":"IN",
    "gn:dem":611,
    "gn:feature_class":"P",
    "gn:feature_code":"PPL",
    "gn:name":"Damoh",
    "gn:population":0,
    "gn:timezone":"Asia/Kolkata",
    "iso:country":"IN",
    "wof:name":"Damoh",
    "wof:placetype":"locality"
},
  "geometry": {"coordinates":[80.79246999999999,21.89826],"type":"Point"}
}