{
  "type": "Feature",
  "properties": {
    "gn:admin1_code":"35.0",
    "gn:admin2_code":"457",
    "gn:asciiname":"Damoh",
    "gn:country_code":"IN",
    "gn:dem":611,
    "gn:feature_class":"P",
    "gn:feature_code":"PPL",
    "gn:name":"Damoh",
    "gn:population":0,
    "gn:timezone":"Asia/Kolkata",
    "iso:country":"IN",
    "name:ben_x_preferred":[
        "\u09a6\u09be\u09ae\u09cb\u09b9"
    ],
    "name:bih_x_preferred":[
        "\u0926\u092e\u094b\u0939"
    ],
    "name:bpy_x_preferred":[
        "\u09a6\u09be\u09ae\u09cb\u09b9"
    ],
    "name:cat_x_preferred":[
        "Damoh"
    ],
    "name:ceb_x_preferred":[
        "Damoh"
    ],
    "name:fra_x_preferred":[
        "Damoh"
    ],
    "name:guj_x_preferred":[
        "\u0aa6\u0abe\u0aae\u0acb\u0ab9"
    ],
    "name:hin_x_preferred":[
        "\u0926\u092e\u094b\u0939"
    ],
    "name:ita_x_preferred":[
        "Damoh"
    ],
    "name:mal_x_preferred":[
        "\u0d26\u0d2e\u0d4b\u0d39\u0d4d"
    ],
    "name:mar_x_preferred":[
        "\u0926\u093e\u092e\u094b\u0939"
    ],
    "name:mlg_x_preferred":[
        "Damoh"
    ],
    "name:msa_x_preferred":[
        "Damoh"
    ],
    "name:nep_x_preferred":[
        "\u0926\u092e\u094b\u0939"
    ],
    "name:new_x_preferred":[
        "\u0926\u092e\u094b\u0939"
    ],
    "name:pam_x_preferred":[
        "Damoh"
    ],
    "name:por_x_preferred":[
        "Damoh"
    ],
    "name:san_x_preferred":[
        "\u0926\u092e\u094b\u0939"
    ],
    "name:spa_x_preferred":[
        "Damoh"
    ],
    "name:swe_x_preferred":[
        "Damoh"
    ],
    "name:urd_x_preferred":[
        "\u062f\u0627\u0645\u0648\u06c1"
    ],
    "name:vie_x_preferred":[
        "Damoh"
    ],
    "name:war_x_preferred":[
        "Damoh"
    ],
    "wof:name":"Damoh",
    "wof:placetype":"locality"
},
  "geometry": {"coordinates":[80.79246999999999,21.89826],"type":"Point"}
}