{
  "type": "Feature",
  "properties": {
    "iso:country":"IN",
    "ks:ks_name":"Gopalganj",
    "ks:ks_pop":367,
    "ks:ks_type":"VILLAGE",
    "name:eng_x_preferred":[
        "Gopalganj"
    ],
    "wof:name":"Gopalganj",
    "wof:placetype":"locality",
    "wof:population":367
},
  "geometry": {"coordinates":[89.555015,26.103809],"type":"Point"}
}