{
  "type": "Feature",
  "properties": {
    "iso:country":"IN",
    "ks:ks_name":"Maukhali",
    "ks:ks_pop":3599,
    "ks:ks_type":"VILLAGE",
    "name:eng_x_preferred":[
        "Maukhali"
    ],
    "wof:name":"Maukhali",
    "wof:placetype":"locality",
    "wof:population":3599
},
  "geometry": {"coordinates":[88.618323,22.282337],"type":"Point"}
}