{
  "type": "Feature",
  "properties": {
    "gn:admin1_code":"34.0",
    "gn:admin2_code":"222.0",
    "gn:asciiname":"Makha Chak",
    "gn:country_code":"IN",
    "gn:dem":44,
    "gn:feature_class":"P",
    "gn:feature_code":"PPL",
    "gn:name":"Makha Chak",
    "gn:population":0,
    "gn:timezone":"Asia/Kolkata",
    "iso:country":"IN",
    "ks:ks_name":"Makha Chak",
    "ks:ks_pop":6428,
    "ks:ks_type":"VILLAGE",
    "ks:ks_uagg_main":0,
    "name:eng_x_preferred":[
        "Makha Chak"
    ],
    "wof:name":"Makha Chak",
    "wof:placetype":"neighbourhood",
    "wof:population":6428
},
  "geometry": {"coordinates":[86.253073,25.597146],"type":"Point"}
}