{
  "type": "Feature",
  "properties": {
    "iso:country":"IN",
    "ks:ks_alt_nam":"2 no bagrikhuti boro supa",
    "ks:ks_name":"2 No Bagrikhuti Boro Supa",
    "ks:ks_pop":605,
    "ks:ks_type":"HABITATION",
    "name:eng_x_preferred":[
        "2 No Bagrikhuti Boro Supa"
    ],
    "wof:name":"2 No Bagrikhuti Boro Supa",
    "wof:placetype":"locality",
    "wof:population":605
},
  "geometry": {"coordinates":[91.65516599999999,26.771852],"type":"Point"}
}