{
  "type": "Feature",
  "properties": {
    "iso:country":"IN",
    "ks:ks_name":"Hatewadi",
    "ks:ks_pop":54,
    "ks:ks_type":"HABITATION",
    "name:eng_x_preferred":[
        "Hatewadi"
    ],
    "wof:name":"Hatewadi",
    "wof:placetype":"locality",
    "wof:population":54
},
  "geometry": {"coordinates":[73.52578200000001,18.045383],"type":"Point"}
}