{
  "type": "Feature",
  "properties": {
    "iso:country":"IN",
    "ks:ks_name":"Maskand Kachua",
    "ks:ks_pop":54,
    "ks:ks_type":"VILLAGE",
    "ks:ks_uagg_main":0,
    "name:eng_x_preferred":[
        "Maskand Kachua"
    ],
    "wof:name":"Maskand Kachua",
    "wof:placetype":"neighbourhood",
    "wof:population":54
},
  "geometry": {"coordinates":[87.31057199999999,25.041735],"type":"Point"}
}