{
  "type": "Feature",
  "properties": {
    "iso:country":"IN",
    "ks:ks_alt_nam":"Harijan tola",
    "ks:ks_name":"Harijan Tola",
    "ks:ks_pop":597,
    "ks:ks_type":"HABITATION",
    "ks:ks_uagg_main":0,
    "name:eng_x_preferred":[
        "Harijan Tola"
    ],
    "wof:name":"Harijan Tola",
    "wof:placetype":"neighbourhood",
    "wof:population":597
},
  "geometry": {"coordinates":[84.54959100000001,26.56697],"type":"Point"}
}