{
  "type": "Feature",
  "properties": {
    "iso:country":"IN",
    "ks:ks_alt_nam":"KARANJUA",
    "ks:ks_name":"Karanjua",
    "ks:ks_pop":59,
    "ks:ks_type":"HABITATION",
    "name:eng_x_preferred":[
        "Karanjua"
    ],
    "wof:name":"Karanjua",
    "wof:placetype":"locality",
    "wof:population":59
},
  "geometry": {"coordinates":[85.300432,24.359394],"type":"Point"}
}