{
  "type": "Feature",
  "properties": {
    "gn:admin1_code":"35.0",
    "gn:admin2_code":"441.0",
    "gn:asciiname":"Tapar",
    "gn:country_code":"IN",
    "gn:dem":458,
    "gn:feature_class":"P",
    "gn:feature_code":"PPL",
    "gn:name":"T\u0101par",
    "gn:population":0,
    "gn:timezone":"Asia/Kolkata",
    "iso:country":"IN",
    "ks:ks_alt_nam":"T\u0101par",
    "ks:ks_name":"Tapar",
    "ks:ks_type":"VILLAGE",
    "name:eng_x_preferred":[
        "Tapar"
    ],
    "name:eng_x_variant":[
        "T\u0101par"
    ],
    "wof:name":"Tapar",
    "wof:placetype":"locality"
},
  "geometry": {"coordinates":[74.653251,21.877364],"type":"Point"}
}