{
  "type": "Feature",
  "properties": {
    "iso:country":"IN",
    "ks:ks_name":"Angrej Singh Dhani",
    "ks:ks_pop":1752,
    "ks:ks_type":"HABITATION",
    "name:eng_x_preferred":[
        "Angrej Singh Dhani"
    ],
    "wof:name":"Angrej Singh Dhani",
    "wof:placetype":"locality",
    "wof:population":1752
},
  "geometry": {"coordinates":[74.130696,30.357136],"type":"Point"}
}