{
  "type": "Feature",
  "properties": {
    "gn:admin1_code":"40",
    "gn:admin2_code":"532.0",
    "gn:asciiname":"Gajali",
    "gn:country_code":"IN",
    "gn:dem":388,
    "gn:feature_class":"P",
    "gn:feature_code":"PPL",
    "gn:name":"G\u0101jali",
    "gn:population":0,
    "gn:timezone":"Asia/Kolkata",
    "iso:country":"IN",
    "ks:ks_name":"Gajli",
    "ks:ks_pop":148,
    "ks:ks_type":"VILLAGE",
    "name:eng_x_preferred":[
        "Gajli"
    ],
    "name:eng_x_variant":[
        "Gajali"
    ],
    "wof:name":"Gajli",
    "wof:placetype":"locality",
    "wof:population":148
},
  "geometry": {"coordinates":[78.40006099999999,19.382088],"type":"Point"}
}