{
  "type": "Feature",
  "properties": {
    "iso:country":"IN",
    "ks:ks_name":"Kuerpata",
    "ks:ks_pop":10,
    "ks:ks_type":"VILLAGE",
    "name:eng_x_preferred":[
        "Kuerpata"
    ],
    "wof:name":"Kuerpata",
    "wof:placetype":"locality",
    "wof:population":10
},
  "geometry": {"coordinates":[83.850902,20.329546],"type":"Point"}
}