{
  "type": "Feature",
  "properties": {
    "gn:admin1_code":"11.0",
    "gn:admin2_code":"23.0",
    "gn:asciiname":"Malot",
    "gn:country_code":"IN",
    "gn:dem":934,
    "gn:feature_class":"P",
    "gn:feature_code":"PPL",
    "gn:name":"Malot",
    "gn:population":0,
    "gn:timezone":"Asia/Kolkata",
    "iso:country":"IN",
    "name:pnb_x_preferred":[
        "\u0645\u0644\u0648\u0679"
    ],
    "name:urd_x_preferred":[
        "\u0645\u0644\u0648\u0679"
    ],
    "wof:name":"Malot",
    "wof:placetype":"locality"
},
  "geometry": {"coordinates":[75.9216,32.49951],"type":"Point"}
}