{
  "type": "Feature",
  "properties": {
    "iso:country":"IN",
    "ks:ks_alt_nam":"Vadivel nagar",
    "ks:ks_name":"Vadivel Nagar",
    "ks:ks_pop":3884,
    "ks:ks_type":"HABITATION",
    "ks:ks_uagg_main":0,
    "name:eng_x_preferred":[
        "Vadivel Nagar"
    ],
    "wof:name":"Vadivel Nagar",
    "wof:placetype":"locality",
    "wof:population":3884
},
  "geometry": {"coordinates":[78.037221,9.936469],"type":"Point"}
}