{
  "type": "Feature",
  "properties": {
    "gn:admin1_code":"36",
    "gn:admin2_code":"200.0",
    "gn:asciiname":"Narahati",
    "gn:country_code":"IN",
    "gn:dem":166,
    "gn:feature_class":"P",
    "gn:feature_code":"PPL",
    "gn:name":"Narahati",
    "gn:population":0,
    "gn:timezone":"Asia/Kolkata",
    "iso:country":"IN",
    "ks:ks_name":"Narhati",
    "ks:ks_pop":619,
    "ks:ks_type":"VILLAGE",
    "name:eng_x_preferred":[
        "Narhati"
    ],
    "name:eng_x_variant":[
        "Narahati"
    ],
    "wof:name":"Narhati",
    "wof:placetype":"locality",
    "wof:population":619
},
  "geometry": {"coordinates":[83.316613,24.46992],"type":"Point"}
}