{
  "type": "Feature",
  "properties": {
    "gn:admin1_code":"19.0",
    "gn:admin2_code":"570.0",
    "gn:asciiname":"Bagasgodu",
    "gn:country_code":"IN",
    "gn:dem":964,
    "gn:feature_class":"P",
    "gn:feature_code":"PPL",
    "gn:name":"Bagasgodu",
    "gn:population":0,
    "gn:timezone":"Asia/Kolkata",
    "iso:country":"IN",
    "wof:name":"Bagasgodu",
    "wof:placetype":"locality"
},
  "geometry": {"coordinates":[75.5757,13.14897],"type":"Point"}
}