{
  "type": "Feature",
  "properties": {
    "gn:admin1_code":"12",
    "gn:admin2_code":"15.0",
    "gn:asciiname":"Tsandargi",
    "gn:country_code":"IN",
    "gn:dem":1844,
    "gn:feature_class":"P",
    "gn:feature_code":"PPL",
    "gn:name":"Tsandargi",
    "gn:population":0,
    "gn:timezone":"Asia/Kolkata",
    "iso:country":"IN",
    "wof:name":"Tsandargi",
    "wof:placetype":"locality"
},
  "geometry": {"coordinates":[75.01023000000001,33.59820999999999],"type":"Point"}
}