{
  "type": "Feature",
  "properties": {
    "iso:country":"IN",
    "ks:ks_name":"Thikkodi Town",
    "ks:ks_pop":1428,
    "ks:ks_type":"HABITATION",
    "ks:ks_uagg_main":0,
    "name:eng_x_preferred":[
        "Thikkodi Town"
    ],
    "wof:name":"Thikkodi Town",
    "wof:placetype":"locality",
    "wof:population":1428
},
  "geometry": {"coordinates":[75.62728199999999,11.495587],"type":"Point"}
}