{
  "type": "Feature",
  "properties": {
    "gn:admin1_code":"11",
    "gn:admin2_code":"24.0",
    "gn:asciiname":"Sirmani",
    "gn:country_code":"IN",
    "gn:dem":517,
    "gn:feature_class":"P",
    "gn:feature_code":"PPL",
    "gn:name":"Sirmani",
    "gn:population":0,
    "gn:timezone":"Asia/Kolkata",
    "iso:country":"IN",
    "wof:name":"Sirmani",
    "wof:placetype":"locality"
},
  "geometry": {"coordinates":[76.00841,32.1774],"type":"Point"}
}