{
  "type": "Feature",
  "properties": {
    "gn:country":"IN",
    "gn:fcode":"PPL",
    "gn:population":35087,
    "iso:country":"IN",
    "name:ben_x_preferred":[
        "\u09a6\u09c1\u09ac\u09b0\u09be\u099c\u09aa\u09c1\u09b0"
    ],
    "name:bpy_x_preferred":[
        "\u09a6\u09c1\u09ac\u09b0\u09be\u099c\u09aa\u09c1\u09b0"
    ],
    "name:ceb_x_preferred":[
        "Dubr\u0101jpur"
    ],
    "name:eng_x_preferred":[
        "Dubrajpur"
    ],
    "name:fra_x_preferred":[
        "Dubrajpur"
    ],
    "name:ita_x_preferred":[
        "Dubrajpur"
    ],
    "name:mlg_x_preferred":[
        "Dubrajpur"
    ],
    "name:msa_x_preferred":[
        "Dubrajpur"
    ],
    "name:new_x_preferred":[
        "\u0926\u0941\u092c\u094d\u0930\u093e\u091c\u092a\u0941\u0930"
    ],
    "name:nld_x_preferred":[
        "Dubrajpur"
    ],
    "name:por_x_preferred":[
        "Dubrajpur"
    ],
    "name:spa_x_preferred":[
        "Dubrajpur"
    ],
    "name:swe_x_preferred":[
        "Dubr\u0101jpur"
    ],
    "name:vie_x_preferred":[
        "Dubrajpur"
    ],
    "name:zho_x_preferred":[
        "\u675c\u5e03\u62c9\u6770\u666e\u5c14"
    ],
    "qs:name":"Dubrajpur",
    "qs:name_adm0":"India",
    "qs:name_adm1":"West Bengal",
    "qs:photos_9r":0,
    "qs:photos_sr":0,
    "qs:placetype":"Town",
    "qs:pop_sr":"7",
    "wd:wordcount":321,
    "wof:name":"Dubrajpur",
    "wof:placetype":"locality",
    "wof:population":35087
},
  "geometry": {"coordinates":[87.37648,23.7902],"type":"Point"}
}