{
  "type": "Feature",
  "properties": {
    "iso:country":"IN",
    "ks:ks_name":"Ekarani Grant",
    "ks:ks_pop":583,
    "ks:ks_type":"HABITATION",
    "name:eng_x_preferred":[
        "Ekarani Grant"
    ],
    "wof:name":"Ekarani Grant",
    "wof:placetype":"locality",
    "wof:population":583
},
  "geometry": {"coordinates":[94.710836,27.116773],"type":"Point"}
}