{
  "type": "Feature",
  "properties": {
    "iso:country":"IN",
    "ks:ks_name":"Alibandha",
    "ks:ks_pop":475,
    "ks:ks_type":"HABITATION",
    "name:eng_x_preferred":[
        "Alibandha"
    ],
    "wof:name":"Alibandha",
    "wof:placetype":"locality",
    "wof:population":475
},
  "geometry": {"coordinates":[82.560712,19.312081],"type":"Point"}
}