{
  "type": "Feature",
  "properties": {
    "iso:country":"IN",
    "ks:ks_name":"Bahuari Chamr Tola",
    "ks:ks_pop":238,
    "ks:ks_type":"HABITATION",
    "ks:ks_uagg_main":0,
    "name:eng_x_preferred":[
        "Bahuari Chamr Tola"
    ],
    "wof:name":"Bahuari Chamr Tola",
    "wof:placetype":"neighbourhood",
    "wof:population":238
},
  "geometry": {"coordinates":[84.910946,26.763946],"type":"Point"}
}