{
  "type": "Feature",
  "properties": {
    "iso:country":"IN",
    "ks:ks_name":"Bazidpur",
    "ks:ks_pop":6309,
    "ks:ks_type":"VILLAGE",
    "ks:ks_uagg_main":0,
    "name:eng_x_preferred":[
        "Bazidpur"
    ],
    "wof:name":"Bazidpur",
    "wof:placetype":"neighbourhood",
    "wof:population":6309
},
  "geometry": {"coordinates":[85.105361,26.144859],"type":"Point"}
}