{
  "type": "Feature",
  "properties": {
    "iso:country":"IN",
    "ks:ks_name":"Ramsaytola",
    "ks:ks_pop":102,
    "ks:ks_type":"VILLAGE",
    "name:eng_x_preferred":[
        "Ramsaytola"
    ],
    "wof:name":"Ramsaytola",
    "wof:placetype":"locality",
    "wof:population":102
},
  "geometry": {"coordinates":[80.541207,20.789808],"type":"Point"}
}