{
  "type": "Feature",
  "properties": {
    "iso:country":"IN",
    "ks:ks_name":"Hirna",
    "ks:ks_pop":220,
    "ks:ks_type":"VILLAGE",
    "name:eng_x_preferred":[
        "Hirna"
    ],
    "wof:name":"Hirna",
    "wof:placetype":"locality",
    "wof:population":220
},
  "geometry": {"coordinates":[86.73697,24.558719],"type":"Point"}
}