{
  "type": "Feature",
  "properties": {
    "iso:country":"IN",
    "ks:ks_name":"Haripur",
    "ks:ks_pop":22,
    "ks:ks_type":"HABITATION",
    "name:eng_x_preferred":[
        "Haripur"
    ],
    "wof:name":"Haripur",
    "wof:placetype":"locality",
    "wof:population":22
},
  "geometry": {"coordinates":[77.16178499999999,24.358207],"type":"Point"}
}