{
  "type": "Feature",
  "properties": {
    "iso:country":"IN",
    "ks:ks_name":"Pakadoloni",
    "ks:ks_pop":30,
    "ks:ks_type":"VILLAGE",
    "name:eng_x_preferred":[
        "Pakadoloni"
    ],
    "wof:name":"Pakadoloni",
    "wof:placetype":"locality",
    "wof:population":30
},
  "geometry": {"coordinates":[91.20633100000001,26.390896],"type":"Point"}
}