{
  "type": "Feature",
  "properties": {
    "gn:admin1_code":"16",
    "gn:admin2_code":"509.0",
    "gn:asciiname":"Kag",
    "gn:country_code":"IN",
    "gn:dem":229,
    "gn:feature_class":"P",
    "gn:feature_code":"PPL",
    "gn:name":"K\u0101g",
    "gn:population":0,
    "gn:timezone":"Asia/Kolkata",
    "iso:country":"IN",
    "wof:name":"Kag",
    "wof:placetype":"locality"
},
  "geometry": {"coordinates":[79.40369,20.46977],"type":"Point"}
}