{
  "type": "Feature",
  "properties": {
    "iso:country":"IN",
    "ks:ks_name":"Kharde Kh.",
    "ks:ks_pop":1444,
    "ks:ks_type":"VILLAGE",
    "ks:ks_uagg_main":0,
    "name:eng_x_preferred":[
        "Kharde Kh."
    ],
    "wof:name":"Kharde Kh.",
    "wof:placetype":"neighbourhood",
    "wof:population":1444
},
  "geometry": {"coordinates":[74.43793599999999,21.270403],"type":"Point"}
}