{
  "type": "Feature",
  "properties": {
    "iso:country":"IN",
    "ks:ks_name":"Ghotpal",
    "ks:ks_pop":926,
    "ks:ks_type":"VILLAGE",
    "name:eng_x_preferred":[
        "Ghotpal"
    ],
    "wof:name":"Ghotpal",
    "wof:placetype":"locality",
    "wof:population":926
},
  "geometry": {"coordinates":[81.39672899999999,19.013324],"type":"Point"}
}