{
  "type": "Feature",
  "properties": {
    "iso:country":"IN",
    "ks:ks_name":"Jalkipani",
    "ks:ks_pop":350,
    "ks:ks_type":"VILLAGE",
    "name:eng_x_preferred":[
        "Jalkipani"
    ],
    "wof:name":"Jalkipani",
    "wof:placetype":"locality",
    "wof:population":350
},
  "geometry": {"coordinates":[82.30782000000001,20.816394],"type":"Point"}
}