{
  "type": "Feature",
  "properties": {
    "gn:admin1_code":"36.0",
    "gn:admin2_code":"184",
    "gn:asciiname":"Domariaganj",
    "gn:country_code":"IN",
    "gn:dem":94,
    "gn:feature_class":"P",
    "gn:feature_code":"PPL",
    "gn:name":"Domari\u0101ganj",
    "gn:population":0,
    "gn:timezone":"Asia/Kolkata",
    "iso:country":"IN",
    "ks:ks_alt_nam":"Domari\u0101ganj",
    "ks:ks_name":"Domariaganj",
    "ks:ks_type":"VILLAGE",
    "ks:ks_uagg_main":0,
    "name:eng_x_preferred":[
        "Domariaganj"
    ],
    "name:eng_x_variant":[
        "Domari\u0101ganj"
    ],
    "name:und_x_variant":[
        "Domari\u0101ganj"
    ],
    "wof:name":"Domariaganj",
    "wof:placetype":"neighbourhood"
},
  "geometry": {"coordinates":[82.652235,27.205031],"type":"Point"}
}