{
  "type": "Feature",
  "properties": {
    "iso:country":"IN",
    "ks:ks_alt_nam":"Pathiyaram Rd END",
    "ks:ks_name":"Pathiyaram Rd End",
    "ks:ks_pop":249,
    "ks:ks_type":"HABITATION",
    "name:eng_x_preferred":[
        "Pathiyaram Rd End"
    ],
    "wof:name":"Pathiyaram Rd End",
    "wof:placetype":"locality",
    "wof:population":249
},
  "geometry": {"coordinates":[76.16973,10.699976],"type":"Point"}
}