{
  "type": "Feature",
  "properties": {
    "iso:country":"IN",
    "ks:ks_name":"Thkellapadu",
    "ks:ks_pop":120,
    "ks:ks_type":"HABITATION",
    "name:eng_x_preferred":[
        "Thkellapadu"
    ],
    "wof:name":"Thkellapadu",
    "wof:placetype":"locality",
    "wof:population":120
},
  "geometry": {"coordinates":[79.421195,15.414933],"type":"Point"}
}