{
  "type": "Feature",
  "properties": {
    "iso:country":"IN",
    "ks:ks_alt_nam":"Musahar tola",
    "ks:ks_name":"Musahar Tola",
    "ks:ks_pop":485,
    "ks:ks_type":"HABITATION",
    "name:eng_x_preferred":[
        "Musahar Tola"
    ],
    "wof:name":"Musahar Tola",
    "wof:placetype":"locality",
    "wof:population":485
},
  "geometry": {"coordinates":[87.371312,26.350345],"type":"Point"}
}