{
  "type": "Feature",
  "properties": {
    "gn:admin1_code":"37",
    "gn:admin2_code":"400.0",
    "gn:asciiname":"Mugum",
    "gn:country_code":"IN",
    "gn:dem":464,
    "gn:feature_class":"P",
    "gn:feature_code":"PPL",
    "gn:name":"Mugum",
    "gn:population":0,
    "gn:timezone":"Asia/Kolkata",
    "iso:country":"IN",
    "wof:name":"Mugum",
    "wof:placetype":"locality"
},
  "geometry": {"coordinates":[82.48269000000001,22.98212],"type":"Point"}
}