{
  "type": "Feature",
  "properties": {
    "gn:admin1_code":"37",
    "gn:admin2_code":"400.0",
    "gn:asciiname":"Mugum",
    "gn:country_code":"IN",
    "gn:dem":464,
    "gn:feature_class":"P",
    "gn:feature_code":"PPL",
    "gn:name":"Mugum",
    "gn:population":0,
    "gn:timezone":"Asia/Kolkata",
    "iso:country":"IN",
    "ks:ks_name":"Mugum",
    "ks:ks_pop":733,
    "ks:ks_type":"VILLAGE",
    "name:eng_x_preferred":[
        "Mugum"
    ],
    "wof:name":"Mugum",
    "wof:placetype":"locality",
    "wof:population":733
},
  "geometry": {"coordinates":[82.482694,22.982119],"type":"Point"}
}