{
  "type": "Feature",
  "properties": {
    "gn:admin1_code":"36",
    "gn:admin2_code":"143.0",
    "gn:asciiname":"Kanthi Ka Nagaliya",
    "gn:country_code":"IN",
    "gn:dem":183,
    "gn:feature_class":"P",
    "gn:feature_code":"PPL",
    "gn:name":"Kanthi Ka Nagaliya",
    "gn:population":0,
    "gn:timezone":"Asia/Kolkata",
    "iso:country":"IN",
    "wof:name":"Kanthi Ka Nagaliya",
    "wof:placetype":"locality"
},
  "geometry": {"coordinates":[77.80662,27.74193],"type":"Point"}
}