{
  "type": "Feature",
  "properties": {
    "iso:country":"IN",
    "ks:ks_name":"Surigram Pt I",
    "ks:ks_pop":238,
    "ks:ks_type":"VILLAGE",
    "name:eng_x_preferred":[
        "Surigram Pt I"
    ],
    "wof:name":"Surigram Pt I",
    "wof:placetype":"locality",
    "wof:population":238
},
  "geometry": {"coordinates":[92.31671799999999,24.822855],"type":"Point"}
}