{
  "type": "Feature",
  "properties": {
    "gn:admin1_code":"35.0",
    "gn:admin2_code":"453",
    "gn:asciiname":"Ghusia",
    "gn:country_code":"IN",
    "gn:dem":694,
    "gn:feature_class":"P",
    "gn:feature_code":"PPL",
    "gn:name":"Ghusia",
    "gn:population":0,
    "gn:timezone":"Asia/Kolkata",
    "iso:country":"IN",
    "wof:name":"Ghusia",
    "wof:placetype":"neighbourhood"
},
  "geometry": {"coordinates":[80.90004999999999,23.04051],"type":"Point"}
}