{
  "type": "Feature",
  "properties": {
    "iso:country":"IN",
    "ks:ks_name":"South Khola",
    "ks:ks_pop":138,
    "ks:ks_type":"HABITATION",
    "name:eng_x_preferred":[
        "South Khola"
    ],
    "wof:name":"South Khola",
    "wof:placetype":"locality",
    "wof:population":138
},
  "geometry": {"coordinates":[86.72925499999999,20.342959],"type":"Point"}
}