{
  "type": "Feature",
  "properties": {
    "iso:country":"IN",
    "ks:ks_alt_nam":"Mekabanda thanda",
    "ks:ks_name":"Mekabanda Thanda",
    "ks:ks_pop":110,
    "ks:ks_type":"HABITATION",
    "name:eng_x_preferred":[
        "Mekabanda Thanda"
    ],
    "wof:name":"Mekabanda Thanda",
    "wof:placetype":"locality",
    "wof:population":110
},
  "geometry": {"coordinates":[77.75382399999999,16.72187],"type":"Point"}
}