{
  "type": "Feature",
  "properties": {
    "iso:country":"IN",
    "ks:ks_name":"Jalwand",
    "ks:ks_pop":834,
    "ks:ks_type":"HABITATION",
    "name:eng_x_preferred":[
        "Jalwand"
    ],
    "wof:name":"Jalwand",
    "wof:placetype":"locality",
    "wof:population":834
},
  "geometry": {"coordinates":[84.531041,24.537256],"type":"Point"}
}