{
  "type": "Feature",
  "properties": {
    "iso:country":"IN",
    "ks:ks_name":"Gair Laga Bijarakot",
    "ks:ks_pop":103,
    "ks:ks_type":"HABITATION",
    "name:eng_x_preferred":[
        "Gair Laga Bijarakot"
    ],
    "wof:name":"Gair Laga Bijarakot",
    "wof:placetype":"locality",
    "wof:population":103
},
  "geometry": {"coordinates":[79.143153,30.319078],"type":"Point"}
}