{
  "type": "Feature",
  "properties": {
    "iso:country":"IN",
    "ks:ks_name":"Harirajpur",
    "ks:ks_pop":4163,
    "ks:ks_type":"VILLAGE",
    "ks:ks_uagg_main":0,
    "name:eng_x_preferred":[
        "Harirajpur"
    ],
    "wof:name":"Harirajpur",
    "wof:placetype":"locality",
    "wof:population":4163
},
  "geometry": {"coordinates":[85.567702,20.391932],"type":"Point"}
}