{
  "type": "Feature",
  "properties": {
    "iso:country":"IN",
    "ks:ks_name":"Saliadhipa",
    "ks:ks_pop":125,
    "ks:ks_type":"HABITATION",
    "name:eng_x_preferred":[
        "Saliadhipa"
    ],
    "wof:name":"Saliadhipa",
    "wof:placetype":"locality",
    "wof:population":125
},
  "geometry": {"coordinates":[84.62464799999999,22.136549],"type":"Point"}
}