{
  "type": "Feature",
  "properties": {
    "iso:country":"IN",
    "ks:ks_alt_nam":"chafewadi",
    "ks:ks_name":"Chafewadi",
    "ks:ks_pop":197,
    "ks:ks_type":"HABITATION",
    "name:eng_x_preferred":[
        "Chafewadi"
    ],
    "wof:name":"Chafewadi",
    "wof:placetype":"locality",
    "wof:population":197
},
  "geometry": {"coordinates":[73.463611,17.2275],"type":"Point"}
}