{
  "type": "Feature",
  "properties": {
    "iso:country":"IN",
    "ks:ks_name":"Brahmnwadi",
    "ks:ks_pop":31,
    "ks:ks_type":"HABITATION",
    "name:eng_x_preferred":[
        "Brahmnwadi"
    ],
    "wof:name":"Brahmnwadi",
    "wof:placetype":"locality",
    "wof:population":31
},
  "geometry": {"coordinates":[73.167761,17.562658],"type":"Point"}
}