{
  "type": "Feature",
  "properties": {
    "iso:country":"IN",
    "ks:ks_name":"Ghatooli",
    "ks:ks_pop":221,
    "ks:ks_type":"HABITATION",
    "name:eng_x_preferred":[
        "Ghatooli"
    ],
    "wof:name":"Ghatooli",
    "wof:placetype":"locality",
    "wof:population":221
},
  "geometry": {"coordinates":[76.71773399999999,26.300468],"type":"Point"}
}