{
  "type": "Feature",
  "properties": {
    "iso:country":"IN",
    "name:eng_x_preferred":[
        "Kainakary North"
    ],
    "name:nld_x_preferred":[
        "Kainakary North"
    ],
    "qs:name":"Kainakary North",
    "qs:name_adm0":"India",
    "qs:name_adm1":"Kerala",
    "qs:photos":819,
    "qs:photos_1k":166,
    "qs:photos_9k":4,
    "qs:photos_9r":6,
    "qs:photos_all":819,
    "qs:photos_sr":9,
    "qs:placetype":"Town",
    "qs:pop_sr":"0",
    "wd:wordcount":66,
    "wof:name":"Kainakary North",
    "wof:placetype":"locality"
},
  "geometry": {"coordinates":[76.38090099999999,9.528215],"type":"Point"}
}