{
  "type": "Feature",
  "properties": {
    "iso:country":"IN",
    "ks:ks_name":"Khednapara",
    "ks:ks_pop":116,
    "ks:ks_type":"VILLAGE",
    "name:eng_x_preferred":[
        "Khednapara"
    ],
    "wof:name":"Khednapara",
    "wof:placetype":"locality",
    "wof:population":116
},
  "geometry": {"coordinates":[87.070966,24.281306],"type":"Point"}
}