{
  "type": "Feature",
  "properties": {
    "iso:country":"IN",
    "ks:ks_name":"Panjan No 2",
    "ks:ks_pop":180,
    "ks:ks_type":"VILLAGE",
    "ks:ks_uagg_main":0,
    "name:eng_x_preferred":[
        "Panjan No 2"
    ],
    "wof:name":"Panjan No 2",
    "wof:placetype":"neighbourhood",
    "wof:population":180
},
  "geometry": {"coordinates":[93.84573899999999,26.17171],"type":"Point"}
}