{
  "type": "Feature",
  "properties": {
    "iso:country":"IN",
    "ks:ks_name":"Komdih",
    "ks:ks_pop":1,
    "ks:ks_type":"VILLAGE",
    "name:eng_x_preferred":[
        "Komdih"
    ],
    "wof:name":"Komdih",
    "wof:placetype":"locality",
    "wof:population":1
},
  "geometry": {"coordinates":[85.91437999999999,22.556928],"type":"Point"}
}