{
  "type": "Feature",
  "properties": {
    "iso:country":"IN",
    "ks:ks_name":"Dhola Gaon",
    "ks:ks_pop":248,
    "ks:ks_type":"HABITATION",
    "name:eng_x_preferred":[
        "Dhola Gaon"
    ],
    "wof:name":"Dhola Gaon",
    "wof:placetype":"locality",
    "wof:population":248
},
  "geometry": {"coordinates":[79.97109399999999,29.803663],"type":"Point"}
}