{
  "type": "Feature",
  "properties": {
    "gn:admin1_code":"37.0",
    "gn:admin2_code":"413.0",
    "gn:asciiname":"Chhote Teora",
    "gn:country_code":"IN",
    "gn:dem":645,
    "gn:feature_class":"P",
    "gn:feature_code":"PPL",
    "gn:name":"Chhote Teora",
    "gn:population":0,
    "gn:timezone":"Asia/Kolkata",
    "iso:country":"IN",
    "wof:name":"Chhote Teora",
    "wof:placetype":"locality"
},
  "geometry": {"coordinates":[81.29375999999998,20.05778],"type":"Point"}
}