{
  "type": "Feature",
  "properties": {
    "iso:country":"IN",
    "ks:ks_name":"Keadchalam",
    "ks:ks_pop":969,
    "ks:ks_type":"VILLAGE",
    "name:eng_x_preferred":[
        "Keadchalam"
    ],
    "wof:name":"Keadchalam",
    "wof:placetype":"locality",
    "wof:population":969
},
  "geometry": {"coordinates":[85.845733,22.702146],"type":"Point"}
}