{
  "type": "Feature",
  "properties": {
    "gn:admin1_code":"39.0",
    "gn:admin2_code":"66.0",
    "gn:asciiname":"Dhungani",
    "gn:country_code":"IN",
    "gn:dem":1801,
    "gn:feature_class":"P",
    "gn:feature_code":"PPL",
    "gn:name":"Dhung\u0101ni",
    "gn:population":0,
    "gn:timezone":"Asia/Kolkata",
    "iso:country":"IN",
    "wof:name":"Dhungani",
    "wof:placetype":"locality"
},
  "geometry": {"coordinates":[79.5398,29.39759],"type":"Point"}
}