{
  "type": "Feature",
  "properties": {
    "iso:country":"IN",
    "ks:ks_name":"Brajendra Roaja Para",
    "ks:ks_pop":239,
    "ks:ks_type":"HABITATION",
    "name:eng_x_preferred":[
        "Brajendra Roaja Para"
    ],
    "wof:name":"Brajendra Roaja Para",
    "wof:placetype":"locality",
    "wof:population":239
},
  "geometry": {"coordinates":[91.993647,23.895217],"type":"Point"}
}