{
  "type": "Feature",
  "properties": {
    "gn:admin1_code":"09",
    "gn:admin2_code":"488.0",
    "gn:asciiname":"Sajod",
    "gn:country_code":"IN",
    "gn:dem":19,
    "gn:feature_class":"P",
    "gn:feature_code":"PPL",
    "gn:name":"Sajod",
    "gn:population":0,
    "gn:timezone":"Asia/Kolkata",
    "iso:country":"IN",
    "wof:name":"Sajod",
    "wof:placetype":"locality"
},
  "geometry": {"coordinates":[72.90398,21.6193],"type":"Point"}
}