{
  "type": "Feature",
  "properties": {
    "gn:admin1_code":"2",
    "gn:admin2_code":"549.0",
    "gn:asciiname":"Devarapalle",
    "gn:country_code":"IN",
    "gn:dem":14,
    "gn:feature_class":"P",
    "gn:feature_code":"PPL",
    "gn:name":"Devarapalle",
    "gn:population":0,
    "gn:timezone":"Asia/Kolkata",
    "iso:country":"IN",
    "name:vie_x_preferred":[
        "Devarapalle"
    ],
    "wof:name":"Devarapalle",
    "wof:placetype":"locality"
},
  "geometry": {"coordinates":[80.27975000000001,16.01162],"type":"Point"}
}