{
  "type": "Feature",
  "properties": {
    "gn:admin1_code":"36.0",
    "gn:admin2_code":"175.0",
    "gn:asciiname":"Koksand",
    "gn:country_code":"IN",
    "gn:dem":96,
    "gn:feature_class":"P",
    "gn:feature_code":"PPL",
    "gn:name":"Koksand",
    "gn:population":0,
    "gn:timezone":"Asia/Kolkata",
    "iso:country":"IN",
    "ks:ks_name":"Kokasand",
    "ks:ks_pop":542,
    "ks:ks_type":"VILLAGE",
    "name:eng_x_preferred":[
        "Kokasand"
    ],
    "name:eng_x_variant":[
        "Koksand"
    ],
    "wof:name":"Kokasand",
    "wof:placetype":"locality",
    "wof:population":542
},
  "geometry": {"coordinates":[81.959594,25.22679],"type":"Point"}
}