{
  "type": "Feature",
  "properties": {
    "iso:country":"IN",
    "ks:ks_name":"Gopimane",
    "ks:ks_pop":39,
    "ks:ks_type":"HABITATION",
    "name:eng_x_preferred":[
        "Gopimane"
    ],
    "wof:name":"Gopimane",
    "wof:placetype":"locality",
    "wof:population":39
},
  "geometry": {"coordinates":[74.597956,14.652754],"type":"Point"}
}