{
  "type": "Feature",
  "properties": {
    "gn:admin1_code":"09",
    "gn:admin2_code":"475.0",
    "gn:asciiname":"Patri",
    "gn:country_code":"IN",
    "gn:dem":17,
    "gn:feature_class":"P",
    "gn:feature_code":"PPL",
    "gn:name":"P\u0101tri",
    "gn:population":0,
    "gn:timezone":"Asia/Kolkata",
    "iso:country":"IN",
    "name:nld_x_preferred":[
        "Patri"
    ],
    "name:vie_x_preferred":[
        "Patri"
    ],
    "wof:name":"Patri",
    "wof:placetype":"neighbourhood"
},
  "geometry": {"coordinates":[71.79701,23.19138],"type":"Point"}
}