{
  "type": "Feature",
  "properties": {
    "gn:admin1_code":"36.0",
    "gn:admin2_code":"193.0",
    "gn:asciiname":"Bishunpura",
    "gn:country_code":"IN",
    "gn:dem":68,
    "gn:feature_class":"P",
    "gn:feature_code":"PPL",
    "gn:name":"Bishunpura",
    "gn:population":0,
    "gn:timezone":"Asia/Kolkata",
    "iso:country":"IN",
    "ks:ks_name":"Bisun Pura",
    "ks:ks_pop":112,
    "ks:ks_type":"HABITATION",
    "name:eng_x_preferred":[
        "Bisun Pura"
    ],
    "name:eng_x_variant":[
        "Bishunpura"
    ],
    "wof:name":"Bisun Pura",
    "wof:placetype":"locality",
    "wof:population":112
},
  "geometry": {"coordinates":[84.084491,25.938553],"type":"Point"}
}