{
  "type": "Feature",
  "properties": {
    "gn:admin1_code":"21.0",
    "gn:admin2_code":"393",
    "gn:asciiname":"Banjipali",
    "gn:country_code":"IN",
    "gn:dem":283,
    "gn:feature_class":"P",
    "gn:feature_code":"PPL",
    "gn:name":"Banj\u012bp\u0101li",
    "gn:population":0,
    "gn:timezone":"Asia/Kolkata",
    "iso:country":"IN",
    "wof:name":"Banjipali",
    "wof:placetype":"neighbourhood"
},
  "geometry": {"coordinates":[82.94335,20.80998],"type":"Point"}
}