{
  "type": "Feature",
  "properties": {
    "iso:country":"IN",
    "ks:ks_name":"Bandagar Wasti",
    "ks:ks_pop":128,
    "ks:ks_type":"HABITATION",
    "name:eng_x_preferred":[
        "Bandagar Wasti"
    ],
    "wof:name":"Bandagar Wasti",
    "wof:placetype":"locality",
    "wof:population":128
},
  "geometry": {"coordinates":[74.916,17.956],"type":"Point"}
}