{
  "type": "Feature",
  "properties": {
    "gn:admin1_code":"24.0",
    "gn:admin2_code":"130.0",
    "gn:asciiname":"Dakhankhera",
    "gn:country_code":"IN",
    "gn:dem":280,
    "gn:feature_class":"P",
    "gn:feature_code":"PPL",
    "gn:name":"D\u0101khankhera",
    "gn:population":0,
    "gn:timezone":"Asia/Kolkata",
    "iso:country":"IN",
    "wof:name":"Dakhankhera",
    "wof:placetype":"neighbourhood"
},
  "geometry": {"coordinates":[73.8539,24.15703],"type":"Point"}
}