{
  "type": "Feature",
  "properties": {
    "iso:country":"IN",
    "ks:ks_name":"Boudhwadi",
    "ks:ks_pop":126,
    "ks:ks_type":"HABITATION",
    "name:eng_x_preferred":[
        "Boudhwadi"
    ],
    "wof:name":"Boudhwadi",
    "wof:placetype":"locality",
    "wof:population":126
},
  "geometry": {"coordinates":[73.33785,17.931506],"type":"Point"}
}