{
  "type": "Feature",
  "properties": {
    "iso:country":"IN",
    "ks:ks_name":"Marrivalasa",
    "ks:ks_pop":135,
    "ks:ks_type":"HABITATION",
    "name:eng_x_preferred":[
        "Marrivalasa"
    ],
    "wof:name":"Marrivalasa",
    "wof:placetype":"locality",
    "wof:population":135
},
  "geometry": {"coordinates":[83.185907,18.225137],"type":"Point"}
}