{
  "type": "Feature",
  "properties": {
    "gn:admin1_code":"40.0",
    "gn:admin2_code":"539.0",
    "gn:asciiname":"Raghwapuram",
    "gn:country_code":"IN",
    "gn:dem":407,
    "gn:feature_class":"P",
    "gn:feature_code":"PPL",
    "gn:name":"R\u0101ghw\u0101puram",
    "gn:population":0,
    "gn:timezone":"Asia/Kolkata",
    "iso:country":"IN",
    "wof:name":"Raghwapuram",
    "wof:placetype":"locality"
},
  "geometry": {"coordinates":[78.79071999999999,17.42312],"type":"Point"}
}