{
  "type": "Feature",
  "properties": {
    "iso:country":"IN",
    "ks:ks_name":"Munnowar Purwa",
    "ks:ks_pop":227,
    "ks:ks_type":"HABITATION",
    "ks:ks_uagg_main":0,
    "name:eng_x_preferred":[
        "Munnowar Purwa"
    ],
    "wof:name":"Munnowar Purwa",
    "wof:placetype":"neighbourhood",
    "wof:population":227
},
  "geometry": {"coordinates":[80.194273,27.647174],"type":"Point"}
}