{
  "type": "Feature",
  "properties": {
    "iso:country":"IN",
    "ks:ks_name":"Bhumiyar Tola",
    "ks:ks_pop":184,
    "ks:ks_type":"HABITATION",
    "name:eng_x_preferred":[
        "Bhumiyar Tola"
    ],
    "wof:name":"Bhumiyar Tola",
    "wof:placetype":"locality",
    "wof:population":184
},
  "geometry": {"coordinates":[86.74131199999999,25.175227],"type":"Point"}
}