{
  "type": "Feature",
  "properties": {
    "iso:country":"IN",
    "ks:ks_name":"Radhakantapur",
    "ks:ks_pop":1619,
    "ks:ks_type":"VILLAGE",
    "name:eng_x_preferred":[
        "Radhakantapur"
    ],
    "wof:name":"Radhakantapur",
    "wof:placetype":"locality",
    "wof:population":1619
},
  "geometry": {"coordinates":[87.390128,23.417186],"type":"Point"}
}