{
  "type": "Feature",
  "properties": {
    "iso:country":"IN",
    "ks:ks_name":"Ratan Bigha",
    "ks:ks_pop":263,
    "ks:ks_type":"HABITATION",
    "name:eng_x_preferred":[
        "Ratan Bigha"
    ],
    "wof:name":"Ratan Bigha",
    "wof:placetype":"locality",
    "wof:population":263
},
  "geometry": {"coordinates":[84.566687,24.72764],"type":"Point"}
}