{
  "type": "Feature",
  "properties": {
    "iso:country":"IN",
    "ks:ks_name":"Padyarwadi",
    "ks:ks_pop":313,
    "ks:ks_type":"HABITATION",
    "name:eng_x_preferred":[
        "Padyarwadi"
    ],
    "wof:name":"Padyarwadi",
    "wof:placetype":"locality",
    "wof:population":313
},
  "geometry": {"coordinates":[73.32722200000001,17.046111],"type":"Point"}
}