{
  "type": "Feature",
  "properties": {
    "iso:country":"IN",
    "ks:ks_name":"Muslimpalya",
    "ks:ks_pop":80,
    "ks:ks_type":"HABITATION",
    "name:eng_x_preferred":[
        "Muslimpalya"
    ],
    "wof:name":"Muslimpalya",
    "wof:placetype":"locality",
    "wof:population":80
},
  "geometry": {"coordinates":[76.89599800000001,12.991915],"type":"Point"}
}