{
  "type": "Feature",
  "properties": {
    "gn:admin1_code":"25.0",
    "gn:admin2_code":"619.0",
    "gn:asciiname":"Kumaramangalam",
    "gn:country_code":"IN",
    "gn:dem":32,
    "gn:feature_class":"P",
    "gn:feature_code":"PPL",
    "gn:name":"Kum\u0101ramangalam",
    "gn:population":0,
    "gn:timezone":"Asia/Kolkata",
    "iso:country":"IN",
    "ks:ks_alt_nam":"kumaramangalam",
    "ks:ks_name":"Kumaramangalam",
    "ks:ks_pop":1028,
    "ks:ks_type":"HABITATION",
    "name:eng_x_preferred":[
        "Kumaramangalam"
    ],
    "wof:name":"Kumaramangalam",
    "wof:placetype":"locality",
    "wof:population":1028
},
  "geometry": {"coordinates":[79.33130800000001,10.834935],"type":"Point"}
}