{
  "type": "Feature",
  "properties": {
    "gn:country":"IN",
    "gn:fcode":"PPL",
    "gn:pop":14770,
    "iso:country":"IN",
    "name:ben_x_preferred":[
        "\u0995\u09c1\u09a8\u09cd\u09a6\u09b2\u0993\u09af\u09bc\u09be\u09a6\u09bf"
    ],
    "name:bpy_x_preferred":[
        "\u0995\u09c1\u09a8\u09cd\u09a6\u09b2\u09f1\u09be\u09a6\u09bf"
    ],
    "name:eng_x_preferred":[
        "Kundalwadi"
    ],
    "name:fra_x_preferred":[
        "Kundalwadi"
    ],
    "name:ita_x_preferred":[
        "Kundalwadi"
    ],
    "name:msa_x_preferred":[
        "Kundalwadi"
    ],
    "name:nan_x_preferred":[
        "Kundalwadi"
    ],
    "name:new_x_preferred":[
        "\u0915\u0941\u0928\u094d\u0926\u0932\u0935\u093e\u0921\u0940"
    ],
    "name:nld_x_preferred":[
        "Kundalwadi"
    ],
    "name:por_x_preferred":[
        "Kundalwadi"
    ],
    "name:urd_x_preferred":[
        "\u06a9\u0646\u062f\u0644 \u0648\u0627\u0691\u06cc"
    ],
    "name:vie_x_preferred":[
        "Kundalwadi"
    ],
    "name:zho_x_preferred":[
        "\u6606\u8fbe\u5c14\u74e6\u8fea"
    ],
    "qs:name":"Kundalwadi",
    "qs:name_adm0":"India",
    "qs:name_adm1":"Maharashtra",
    "qs:photos_9r":0,
    "qs:photos_sr":0,
    "qs:placetype":"Town",
    "qs:pop_sr":"6",
    "wd:wordcount":192,
    "wof:name":"Kundalwadi",
    "wof:placetype":"locality",
    "wof:population":14770
},
  "geometry": {"coordinates":[77.76913,18.80758],"type":"Point"}
}