{
  "type": "Feature",
  "properties": {
    "gn:admin1_code":"03",
    "gn:admin2_code":"313.0",
    "gn:asciiname":"Parghat",
    "gn:country_code":"IN",
    "gn:dem":87,
    "gn:feature_class":"P",
    "gn:feature_code":"PPL",
    "gn:name":"P\u0101rgh\u0101t",
    "gn:population":0,
    "gn:timezone":"Asia/Kolkata",
    "iso:country":"IN",
    "name:und_x_variant":[
        "Parchat",
        "P\u0101rgh\u0101t"
    ],
    "wof:name":"Parghat",
    "wof:placetype":"locality"
},
  "geometry": {"coordinates":[93.73860999999999,26.62609],"type":"Point"}
}