{
  "type": "Feature",
  "properties": {
    "gn:admin1_code":"35",
    "gn:admin2_code":"453.0",
    "gn:asciiname":"Titarhai",
    "gn:country_code":"IN",
    "gn:dem":781,
    "gn:feature_class":"P",
    "gn:feature_code":"PPL",
    "gn:name":"Titarhai",
    "gn:population":0,
    "gn:timezone":"Asia/Kolkata",
    "iso:country":"IN",
    "wof:name":"Titarhai",
    "wof:placetype":"neighbourhood"
},
  "geometry": {"coordinates":[81.18628,22.67083],"type":"Point"}
}