{
  "type": "Feature",
  "properties": {
    "iso:country":"IN",
    "ks:ks_name":"Warpetwadi",
    "ks:ks_pop":179,
    "ks:ks_type":"HABITATION",
    "name:eng_x_preferred":[
        "Warpetwadi"
    ],
    "wof:name":"Warpetwadi",
    "wof:placetype":"locality",
    "wof:population":179
},
  "geometry": {"coordinates":[73.37822300000001,16.818173],"type":"Point"}
}