{
  "type": "Feature",
  "properties": {
    "iso:country":"IN",
    "ks:ks_name":"Tyula",
    "ks:ks_pop":125,
    "ks:ks_type":"VILLAGE",
    "name:eng_x_preferred":[
        "Tyula"
    ],
    "wof:name":"Tyula",
    "wof:placetype":"locality",
    "wof:population":125
},
  "geometry": {"coordinates":[79.42719,30.091019],"type":"Point"}
}