{
  "type": "Feature",
  "properties": {
    "gn:admin1_code":"37.0",
    "gn:admin2_code":"416.0",
    "gn:asciiname":"Dosalpara",
    "gn:country_code":"IN",
    "gn:dem":544,
    "gn:feature_class":"P",
    "gn:feature_code":"PPL",
    "gn:name":"Dosalp\u0101ra",
    "gn:population":0,
    "gn:timezone":"Asia/Kolkata",
    "iso:country":"IN",
    "wof:name":"Dosalpara",
    "wof:placetype":"locality"
},
  "geometry": {"coordinates":[81.32429999999999,18.68576],"type":"Point"}
}