{
  "type": "Feature",
  "properties": {
    "iso:country":"IN",
    "ks:ks_alt_nam":"muslimwadi",
    "ks:ks_name":"Muslimwadi",
    "ks:ks_pop":390,
    "ks:ks_type":"HABITATION",
    "name:eng_x_preferred":[
        "Muslimwadi"
    ],
    "wof:name":"Muslimwadi",
    "wof:placetype":"locality",
    "wof:population":390
},
  "geometry": {"coordinates":[73.416464,16.595192],"type":"Point"}
}