{
  "type": "Feature",
  "properties": {
    "gn:admin1_code":"36",
    "gn:admin2_code":"194.0",
    "gn:asciiname":"Mahmudpur",
    "gn:country_code":"IN",
    "gn:dem":92,
    "gn:feature_class":"P",
    "gn:feature_code":"PPL",
    "gn:name":"Mahm\u016bdpur",
    "gn:population":0,
    "gn:timezone":"Asia/Kolkata",
    "iso:country":"IN",
    "ks:ks_name":"Mahmoodpur",
    "ks:ks_pop":415,
    "ks:ks_type":"VILLAGE",
    "ks:ks_uagg_main":0,
    "name:eng_x_preferred":[
        "Mahmoodpur"
    ],
    "wof:name":"Mahmoodpur",
    "wof:placetype":"neighbourhood",
    "wof:population":415
},
  "geometry": {"coordinates":[82.602031,26.12513],"type":"Point"}
}