{
  "type": "Feature",
  "properties": {
    "iso:country":"IN",
    "ks:ks_name":"Bandavalasa",
    "ks:ks_pop":152,
    "ks:ks_type":"HABITATION",
    "name:eng_x_preferred":[
        "Bandavalasa"
    ],
    "wof:name":"Bandavalasa",
    "wof:placetype":"locality",
    "wof:population":152
},
  "geometry": {"coordinates":[83.17419,18.170045],"type":"Point"}
}