{
  "type": "Feature",
  "properties": {
    "gn:admin1_code":"36.0",
    "gn:admin2_code":"175.0",
    "gn:asciiname":"Bhaunka",
    "gn:country_code":"IN",
    "gn:dem":103,
    "gn:feature_class":"P",
    "gn:feature_code":"PPL",
    "gn:name":"Bhaunka",
    "gn:population":0,
    "gn:timezone":"Asia/Kolkata",
    "iso:country":"IN",
    "name:und_x_variant":[
        "Chak Faizull\u0101h"
    ],
    "wof:name":"Bhaunka",
    "wof:placetype":"locality"
},
  "geometry": {"coordinates":[81.96368000000002,25.67355],"type":"Point"}
}