{
  "type": "Feature",
  "properties": {
    "iso:country":"IN",
    "ks:ks_name":"Ng Lami",
    "ks:ks_pop":351,
    "ks:ks_type":"HABITATION",
    "name:eng_x_preferred":[
        "Ng Lami"
    ],
    "wof:name":"Ng Lami",
    "wof:placetype":"locality",
    "wof:population":351
},
  "geometry": {"coordinates":[78.63567999999999,27.84161],"type":"Point"}
}