{
  "type": "Feature",
  "properties": {
    "gn:admin1_code":"36.0",
    "gn:admin2_code":"155",
    "gn:asciiname":"Nihal Purwa",
    "gn:country_code":"IN",
    "gn:dem":122,
    "gn:feature_class":"P",
    "gn:feature_code":"PPL",
    "gn:name":"Nih\u0101l Purwa",
    "gn:population":0,
    "gn:timezone":"Asia/Kolkata",
    "iso:country":"IN",
    "wof:name":"Nihal Purwa",
    "wof:placetype":"locality"
},
  "geometry": {"coordinates":[79.99038,27.06889],"type":"Point"}
}