{
  "type": "Feature",
  "properties": {
    "iso:country":"IN",
    "ks:ks_name":"Tulakshi Pur Simen",
    "ks:ks_pop":222,
    "ks:ks_type":"VILLAGE",
    "name:eng_x_preferred":[
        "Tulakshi Pur Simen"
    ],
    "wof:name":"Tulakshi Pur Simen",
    "wof:placetype":"locality",
    "wof:population":222
},
  "geometry": {"coordinates":[94.822473,27.593454],"type":"Point"}
}