{
  "type": "Feature",
  "properties": {
    "iso:country":"IN",
    "ks:ks_alt_nam":"GIDDEJADHAV",
    "ks:ks_name":"Giddejadhav",
    "ks:ks_pop":77,
    "ks:ks_type":"HABITATION",
    "name:eng_x_preferred":[
        "Giddejadhav"
    ],
    "wof:name":"Giddejadhav",
    "wof:placetype":"locality",
    "wof:population":77
},
  "geometry": {"coordinates":[74.923839,17.037218],"type":"Point"}
}