{
  "type": "Feature",
  "properties": {
    "iso:country":"IN",
    "ks:ks_name":"Kalakhet",
    "ks:ks_pop":238,
    "ks:ks_type":"VILLAGE",
    "name:eng_x_preferred":[
        "Kalakhet"
    ],
    "wof:name":"Kalakhet",
    "wof:placetype":"locality",
    "wof:population":238
},
  "geometry": {"coordinates":[74.48479399999999,23.212875],"type":"Point"}
}