{
  "type": "Feature",
  "properties": {
    "iso:country":"IN",
    "ks:ks_name":"Abdul Karimpur",
    "ks:ks_pop":1100,
    "ks:ks_type":"VILLAGE",
    "ks:ks_uagg_main":0,
    "name:eng_x_preferred":[
        "Abdul Karimpur"
    ],
    "wof:name":"Abdul Karimpur",
    "wof:placetype":"neighbourhood",
    "wof:population":1100
},
  "geometry": {"coordinates":[88.449845,22.245021],"type":"Point"}
}