{
  "type": "Feature",
  "properties": {
    "gn:admin1_code":"2.0",
    "gn:admin2_code":"549.0",
    "gn:asciiname":"Mattagunta",
    "gn:country_code":"IN",
    "gn:dem":11,
    "gn:feature_class":"P",
    "gn:feature_code":"PPL",
    "gn:name":"Mattagunta",
    "gn:population":0,
    "gn:timezone":"Asia/Kolkata",
    "iso:country":"IN",
    "name:hin_x_preferred":[
        "\u092e\u091f\u094d\u091f\u0917\u0941\u0902\u091f"
    ],
    "name:new_x_preferred":[
        "\u092e\u091f\u094d\u091f\u0917\u0941\u0902\u091f"
    ],
    "name:tel_x_preferred":[
        "\u0c2e\u0c1f\u0c4d\u0c1f\u0c17\u0c41\u0c02\u0c1f"
    ],
    "wof:name":"Mattagunta",
    "wof:placetype":"locality"
},
  "geometry": {"coordinates":[80.17395999999999,15.70228],"type":"Point"}
}