{
  "type": "Feature",
  "properties": {
    "gn:admin1_code":"31.0",
    "gn:admin2_code":"287",
    "gn:asciiname":"Bungtlang",
    "gn:country_code":"IN",
    "gn:dem":612,
    "gn:feature_class":"P",
    "gn:feature_code":"PPL",
    "gn:name":"Bungtl\u0101ng",
    "gn:population":0,
    "gn:timezone":"Asia/Kolkata",
    "iso:country":"IN",
    "wof:name":"Bungtlang",
    "wof:placetype":"locality"
},
  "geometry": {"coordinates":[92.75903,22.33988],"type":"Point"}
}