{
  "type": "Feature",
  "properties": {
    "gn:admin1_code":"2.0",
    "gn:admin2_code":"542.0",
    "gn:asciiname":"Amaram",
    "gn:country_code":"IN",
    "gn:dem":72,
    "gn:feature_class":"P",
    "gn:feature_code":"PPL",
    "gn:name":"Amar\u0101m",
    "gn:population":0,
    "gn:timezone":"Asia/Kolkata",
    "iso:country":"IN",
    "name:mal_x_preferred":[
        "\u0d05\u0d2e\u0d30\u0d02"
    ],
    "name:tam_x_preferred":[
        "\u0b85\u0bae\u0bb0\u0bae\u0bcd"
    ],
    "wof:name":"Amaram",
    "wof:placetype":"locality"
},
  "geometry": {"coordinates":[83.61353000000003,18.49347],"type":"Point"}
}