{
  "type": "Feature",
  "properties": {
    "gn:admin1_code":"16",
    "gn:admin2_code":"502.0",
    "gn:asciiname":"Pimparkhed",
    "gn:country_code":"IN",
    "gn:dem":530,
    "gn:feature_class":"P",
    "gn:feature_code":"PPL",
    "gn:name":"Pimparkhed",
    "gn:population":0,
    "gn:timezone":"Asia/Kolkata",
    "iso:country":"IN",
    "wof:name":"Pimparkhed",
    "wof:placetype":"locality"
},
  "geometry": {"coordinates":[76.68666999999998,19.99698],"type":"Point"}
}