{
  "type": "Feature",
  "properties": {
    "iso:country":"IN",
    "ks:ks_name":"Kadepur",
    "ks:ks_pop":695,
    "ks:ks_type":"HABITATION",
    "name:eng_x_preferred":[
        "Kadepur"
    ],
    "wof:name":"Kadepur",
    "wof:placetype":"locality",
    "wof:population":695
},
  "geometry": {"coordinates":[82.97195600000001,26.361383],"type":"Point"}
}