{
  "type": "Feature",
  "properties": {
    "iso:country":"IN",
    "ks:ks_alt_nam":"LACHHMAN BIGHA",
    "ks:ks_name":"Lachhman Bigha",
    "ks:ks_pop":303,
    "ks:ks_type":"HABITATION",
    "name:eng_x_preferred":[
        "Lachhman Bigha"
    ],
    "wof:name":"Lachhman Bigha",
    "wof:placetype":"locality",
    "wof:population":303
},
  "geometry": {"coordinates":[84.720204,24.661373],"type":"Point"}
}