{
  "type": "Feature",
  "properties": {
    "iso:country":"IN",
    "ks:ks_name":"Ng Shisham",
    "ks:ks_pop":137,
    "ks:ks_type":"HABITATION",
    "name:eng_x_preferred":[
        "Ng Shisham"
    ],
    "wof:name":"Ng Shisham",
    "wof:placetype":"locality",
    "wof:population":137
},
  "geometry": {"coordinates":[79.139358,27.737545],"type":"Point"}
}