{
  "type": "Feature",
  "properties": {
    "iso:country":"IN",
    "ks:ks_name":"Warchiwadi",
    "ks:ks_pop":300,
    "ks:ks_type":"HABITATION",
    "name:eng_x_preferred":[
        "Warchiwadi"
    ],
    "wof:name":"Warchiwadi",
    "wof:placetype":"locality",
    "wof:population":300
},
  "geometry": {"coordinates":[73.130222,18.039427],"type":"Point"}
}