{
  "type": "Feature",
  "properties": {
    "gn:admin1_code":"39.0",
    "gn:admin2_code":"061",
    "gn:asciiname":"Sakmunda",
    "gn:country_code":"IN",
    "gn:dem":1422,
    "gn:feature_class":"P",
    "gn:feature_code":"PPL",
    "gn:name":"Sakmunda",
    "gn:population":0,
    "gn:timezone":"Asia/Kolkata",
    "iso:country":"IN",
    "wof:name":"Sakmunda",
    "wof:placetype":"locality"
},
  "geometry": {"coordinates":[78.6741,29.86714000000001],"type":"Point"}
}