{
  "type": "Feature",
  "properties": {
    "iso:country":"IN",
    "ks:ks_name":"Arusulepadavu",
    "ks:ks_pop":255,
    "ks:ks_type":"HABITATION",
    "name:eng_x_preferred":[
        "Arusulepadavu"
    ],
    "wof:name":"Arusulepadavu",
    "wof:placetype":"locality",
    "wof:population":255
},
  "geometry": {"coordinates":[74.878596,13.036792],"type":"Point"}
}