{
  "type": "Feature",
  "properties": {
    "gn:admin1_code":"39.0",
    "gn:admin2_code":"62.0",
    "gn:asciiname":"Seragara",
    "gn:country_code":"IN",
    "gn:dem":724,
    "gn:feature_class":"P",
    "gn:feature_code":"PPL",
    "gn:name":"Seragara",
    "gn:population":0,
    "gn:timezone":"Asia/Kolkata",
    "iso:country":"IN",
    "ks:ks_name":"Sera Ghara",
    "ks:ks_pop":106,
    "ks:ks_type":"VILLAGE",
    "name:eng_x_preferred":[
        "Sera Ghara"
    ],
    "name:eng_x_variant":[
        "Seragara"
    ],
    "wof:name":"Sera Ghara",
    "wof:placetype":"locality",
    "wof:population":106
},
  "geometry": {"coordinates":[79.96737899999999,29.651808],"type":"Point"}
}