{
  "type": "Feature",
  "properties": {
    "gn:admin1_code":"11.0",
    "gn:admin2_code":"32.0",
    "gn:asciiname":"Kurech",
    "gn:country_code":"IN",
    "gn:dem":1347,
    "gn:feature_class":"P",
    "gn:feature_code":"PPL",
    "gn:name":"Kurech",
    "gn:population":0,
    "gn:timezone":"Asia/Kolkata",
    "iso:country":"IN",
    "name:bak_x_preferred":[
        "\u041a\u04e9\u0440\u04d9\u0448"
    ],
    "name:che_x_preferred":[
        "\u041a\u0443\u0440\u0435\u0447"
    ],
    "name:hye_x_preferred":[
        "\u053f\u0578\u0582\u0580\u0565\u0579"
    ],
    "name:kaz_x_preferred":[
        "\u041a\u0443\u0440\u0435\u0447"
    ],
    "name:kir_x_preferred":[
        "\u041a\u0443\u0440\u0435\u0447"
    ],
    "name:rus_x_preferred":[
        "\u041a\u0443\u0440\u0435\u0447"
    ],
    "name:tat_x_preferred":[
        "\u041a\u04e9\u0440\u04d9\u0447"
    ],
    "wof:name":"Kurech",
    "wof:placetype":"locality"
},
  "geometry": {"coordinates":[77.58046,30.73859],"type":"Point"}
}