{
  "type": "Feature",
  "properties": {
    "gn:admin1_code":"34.0",
    "gn:admin2_code":"219.0",
    "gn:asciiname":"Rajganwan",
    "gn:country_code":"IN",
    "gn:dem":59,
    "gn:feature_class":"P",
    "gn:feature_code":"PPL",
    "gn:name":"R\u0101jg\u0101nw\u0101n",
    "gn:population":0,
    "gn:timezone":"Asia/Kolkata",
    "iso:country":"IN",
    "ks:ks_name":"Raj Ganwan",
    "ks:ks_pop":545,
    "ks:ks_type":"VILLAGE",
    "ks:ks_uagg_main":0,
    "name:eng_x_preferred":[
        "Raj Ganwan"
    ],
    "wof:name":"Raj Ganwan",
    "wof:placetype":"neighbourhood",
    "wof:population":545
},
  "geometry": {"coordinates":[84.78922300000001,25.905978],"type":"Point"}
}