{
  "type": "Feature",
  "properties": {
    "iso:country":"IN",
    "ks:ks_name":"Hirekai",
    "ks:ks_pop":57,
    "ks:ks_type":"HABITATION",
    "name:eng_x_preferred":[
        "Hirekai"
    ],
    "wof:name":"Hirekai",
    "wof:placetype":"locality",
    "wof:population":57
},
  "geometry": {"coordinates":[74.72029499999999,14.538757],"type":"Point"}
}