{
  "type": "Feature",
  "properties": {
    "iso:country":"IN",
    "ks:ks_name":"Munar",
    "ks:ks_pop":118,
    "ks:ks_type":"VILLAGE",
    "name:eng_x_preferred":[
        "Munar"
    ],
    "wof:name":"Munar",
    "wof:placetype":"locality",
    "wof:population":118
},
  "geometry": {"coordinates":[79.963841,30.047918],"type":"Point"}
}