{
  "type": "Feature",
  "properties": {
    "iso:country":"IN",
    "ks:ks_alt_nam":"Lakhi pathar supa",
    "ks:ks_name":"Lakhi Pathar Supa",
    "ks:ks_pop":201,
    "ks:ks_type":"HABITATION",
    "name:eng_x_preferred":[
        "Lakhi Pathar Supa"
    ],
    "wof:name":"Lakhi Pathar Supa",
    "wof:placetype":"locality",
    "wof:population":201
},
  "geometry": {"coordinates":[91.462456,26.674467],"type":"Point"}
}