{
  "type": "Feature",
  "properties": {
    "iso:country":"IN",
    "ks:ks_name":"Kachrotia",
    "ks:ks_pop":493,
    "ks:ks_type":"VILLAGE",
    "name:eng_x_preferred":[
        "Kachrotia"
    ],
    "wof:name":"Kachrotia",
    "wof:placetype":"locality",
    "wof:population":493
},
  "geometry": {"coordinates":[74.97384599999999,22.993716],"type":"Point"}
}