{
  "type": "Feature",
  "properties": {
    "iso:country":"IN",
    "ks:ks_alt_nam":"Pip\u0101li",
    "ks:ks_name":"Pipali",
    "ks:ks_pop":136,
    "ks:ks_type":"VILLAGE",
    "name:eng_x_preferred":[
        "Pipali"
    ],
    "name:eng_x_variant":[
        "Pip\u0101li"
    ],
    "wof:name":"Pipali",
    "wof:placetype":"locality",
    "wof:population":136
},
  "geometry": {"coordinates":[84.14675800000001,20.439701],"type":"Point"}
}