{
  "type": "Feature",
  "properties": {
    "gn:admin1_code":"38.0",
    "gn:admin2_code":"358.0",
    "gn:asciiname":"Gulabjhari",
    "gn:country_code":"IN",
    "gn:dem":232,
    "gn:feature_class":"P",
    "gn:feature_code":"PPL",
    "gn:name":"Gul\u0101bjhar\u012b",
    "gn:population":0,
    "gn:timezone":"Asia/Kolkata",
    "iso:country":"IN",
    "ks:ks_alt_nam":"Gul\u0101bjhar\u012b",
    "ks:ks_name":"Gulabjhari",
    "ks:ks_pop":827,
    "ks:ks_type":"VILLAGE",
    "name:eng_x_preferred":[
        "Gulabjhari"
    ],
    "name:eng_x_variant":[
        "Gul\u0101bjhar\u012b"
    ],
    "wof:name":"Gulabjhari",
    "wof:placetype":"locality",
    "wof:population":827
},
  "geometry": {"coordinates":[84.266853,24.411367],"type":"Point"}
}