{
  "type": "Feature",
  "properties": {
    "iso:country":"IN",
    "ks:ks_name":"Natun Chandra Para",
    "ks:ks_pop":387,
    "ks:ks_type":"HABITATION",
    "name:eng_x_preferred":[
        "Natun Chandra Para"
    ],
    "wof:name":"Natun Chandra Para",
    "wof:placetype":"locality",
    "wof:population":387
},
  "geometry": {"coordinates":[91.63828100000001,23.19653],"type":"Point"}
}