{
  "type": "Feature",
  "properties": {
    "iso:country":"IN",
    "ks:ks_name":"Ushuldunri",
    "ks:ks_pop":377,
    "ks:ks_type":"VILLAGE",
    "name:eng_x_preferred":[
        "Ushuldunri"
    ],
    "wof:name":"Ushuldunri",
    "wof:placetype":"locality",
    "wof:population":377
},
  "geometry": {"coordinates":[86.162869,23.203198],"type":"Point"}
}