{
  "type": "Feature",
  "properties": {
    "iso:country":"IN",
    "ks:ks_name":"Kund",
    "ks:ks_pop":189,
    "ks:ks_type":"VILLAGE",
    "name:eng_x_preferred":[
        "Kund"
    ],
    "wof:name":"Kund",
    "wof:placetype":"locality",
    "wof:population":189
},
  "geometry": {"coordinates":[73.450333,21.684205],"type":"Point"}
}