{
  "type": "Feature",
  "properties": {
    "gn:admin1_code":"16",
    "gn:admin2_code":"502.0",
    "gn:asciiname":"Pimpri Barhat",
    "gn:country_code":"IN",
    "gn:dem":385,
    "gn:feature_class":"P",
    "gn:feature_code":"PPL",
    "gn:name":"Pimpri B\u0101rh\u0101t",
    "gn:population":0,
    "gn:timezone":"Asia/Kolkata",
    "iso:country":"IN",
    "ks:ks_alt_nam":"Pimpri B\u0101rh\u0101t",
    "ks:ks_name":"Pimpri Barhat",
    "ks:ks_type":"VILLAGE",
    "name:eng_x_preferred":[
        "Pimpri Barhat"
    ],
    "name:eng_x_variant":[
        "Pimpri B\u0101rh\u0101t"
    ],
    "wof:name":"Pimpri Barhat",
    "wof:placetype":"locality"
},
  "geometry": {"coordinates":[77.549431,20.413104],"type":"Point"}
}