{
  "type": "Feature",
  "properties": {
    "gn:admin1_code":"02",
    "gn:admin2_code":"551.0",
    "gn:asciiname":"Nandalur",
    "gn:country_code":"IN",
    "gn:dem":144,
    "gn:feature_class":"P",
    "gn:feature_code":"PPL",
    "gn:name":"Nandal\u016br",
    "gn:population":0,
    "gn:timezone":"Asia/Kolkata",
    "iso:country":"IN",
    "name:und_x_variant":[
        "Nandal\u016br"
    ],
    "wof:name":"Nandalur",
    "wof:placetype":"locality"
},
  "geometry": {"coordinates":[79.11884000000001,14.26747],"type":"Point"}
}