{
  "type": "Feature",
  "properties": {
    "iso:country":"IN",
    "ks:ks_name":"Ulidih",
    "ks:ks_pop":248,
    "ks:ks_type":"HABITATION",
    "name:eng_x_preferred":[
        "Ulidih"
    ],
    "wof:name":"Ulidih",
    "wof:placetype":"locality",
    "wof:population":248
},
  "geometry": {"coordinates":[85.317447,23.125899],"type":"Point"}
}