{
  "type": "Feature",
  "properties": {
    "iso:country":"IN",
    "ks:ks_name":"Khajri",
    "ks:ks_pop":0,
    "ks:ks_type":"VILLAGE",
    "name:eng_x_preferred":[
        "Khajri"
    ],
    "wof:name":"Khajri",
    "wof:placetype":"locality",
    "wof:population":0
},
  "geometry": {"coordinates":[79.054992,24.043746],"type":"Point"}
}