{
  "type": "Feature",
  "properties": {
    "gn:admin1_code":"39.0",
    "gn:admin2_code":"068",
    "gn:asciiname":"Hasnawala",
    "gn:country_code":"IN",
    "gn:dem":304,
    "gn:feature_class":"P",
    "gn:feature_code":"PPL",
    "gn:name":"Hasn\u0101w\u0101la",
    "gn:population":0,
    "gn:timezone":"Asia/Kolkata",
    "iso:country":"IN",
    "wof:name":"Hasnawala",
    "wof:placetype":"locality"
},
  "geometry": {"coordinates":[77.82064,30.08079],"type":"Point"}
}