{
  "type": "Feature",
  "properties": {
    "iso:country":"IN",
    "ks:ks_name":"Kaugachhi",
    "ks:ks_pop":13908,
    "ks:ks_type":"VILLAGE",
    "ks:ks_uagg_main":0,
    "name:eng_x_preferred":[
        "Kaugachhi"
    ],
    "wof:name":"Kaugachhi",
    "wof:placetype":"locality",
    "wof:population":13908
},
  "geometry": {"coordinates":[88.389205,22.812619],"type":"Point"}
}