{
  "type": "Feature",
  "properties": {
    "iso:country":"IN",
    "ks:ks_name":"Thetham",
    "ks:ks_pop":1240,
    "ks:ks_type":"VILLAGE",
    "name:eng_x_preferred":[
        "Thetham"
    ],
    "wof:name":"Thetham",
    "wof:placetype":"locality",
    "wof:population":1240
},
  "geometry": {"coordinates":[74.403696,23.103066],"type":"Point"}
}