{
  "type": "Feature",
  "properties": {
    "gn:admin1_code":"36.0",
    "gn:admin2_code":"153.0",
    "gn:asciiname":"Palia",
    "gn:country_code":"IN",
    "gn:dem":151,
    "gn:feature_class":"P",
    "gn:feature_code":"PPL",
    "gn:name":"Pali\u0101",
    "gn:population":0,
    "gn:timezone":"Asia/Kolkata",
    "iso:country":"IN",
    "name:fas_x_preferred":[
        "\u067e\u0627\u0644\u06cc\u0627"
    ],
    "name:urd_x_preferred":[
        "\u067e\u0627\u0644\u06cc\u0627"
    ],
    "wof:name":"Palia",
    "wof:placetype":"neighbourhood"
},
  "geometry": {"coordinates":[80.47247,27.85212],"type":"Point"}
}