{
  "type": "Feature",
  "properties": {
    "gn:admin1_code":"34.0",
    "gn:admin2_code":"207.0",
    "gn:asciiname":"Paita",
    "gn:country_code":"IN",
    "gn:dem":61,
    "gn:feature_class":"P",
    "gn:feature_code":"PPL",
    "gn:name":"Paita",
    "gn:population":0,
    "gn:timezone":"Asia/Kolkata",
    "iso:country":"IN",
    "name:ara_x_preferred":[
        "\u0628\u0627\u064a\u062a\u0627"
    ],
    "name:aym_x_preferred":[
        "Paita"
    ],
    "name:cat_x_preferred":[
        "Paita"
    ],
    "name:ceb_x_preferred":[
        "Paita"
    ],
    "name:deu_x_preferred":[
        "Paita"
    ],
    "name:fas_x_preferred":[
        "\u067e\u0627\u06cc\u062a\u0627"
    ],
    "name:fra_x_preferred":[
        "Paita"
    ],
    "name:ita_x_preferred":[
        "Paita"
    ],
    "name:lit_x_preferred":[
        "Paita"
    ],
    "name:pol_x_preferred":[
        "Paita"
    ],
    "name:por_x_preferred":[
        "Paita"
    ],
    "name:que_x_preferred":[
        "Payta"
    ],
    "name:rus_x_preferred":[
        "\u041f\u0430\u0439\u0442\u0430"
    ],
    "name:spa_x_preferred":[
        "Paita"
    ],
    "name:ukr_x_preferred":[
        "\u041f\u0430\u0439\u0442\u0430"
    ],
    "name:war_x_preferred":[
        "Paita"
    ],
    "wof:name":"Paita",
    "wof:placetype":"locality"
},
  "geometry": {"coordinates":[86.45905,26.33371],"type":"Point"}
}