{
  "type": "Feature",
  "properties": {
    "gn:admin1_code":"34.0",
    "gn:admin2_code":"207.0",
    "gn:asciiname":"Paita",
    "gn:country_code":"IN",
    "gn:dem":61,
    "gn:feature_class":"P",
    "gn:feature_code":"PPL",
    "gn:name":"Paita",
    "gn:population":0,
    "gn:timezone":"Asia/Kolkata",
    "iso:country":"IN",
    "name:ara_x_preferred":[
        "\u0628\u0627\u064a\u062a\u0627"
    ],
    "name:aym_x_preferred":[
        "Paita"
    ],
    "name:ben_x_preferred":[
        "\u09aa\u09be\u09a4\u09bf\u09df\u09be"
    ],
    "name:cat_x_preferred":[
        "Paita"
    ],
    "name:ceb_x_preferred":[
        "Paita"
    ],
    "name:deu_x_preferred":[
        "Paita"
    ],
    "name:ell_x_preferred":[
        "\u03a0\u03ac\u03b9\u03c4\u03b1"
    ],
    "name:fas_x_preferred":[
        "\u067e\u0627\u06cc\u062a\u0627"
    ],
    "name:fra_x_preferred":[
        "Paita"
    ],
    "name:hin_x_preferred":[
        "\u092a\u093e\u0907\u091f\u093e"
    ],
    "name:ind_x_preferred":[
        "Paita"
    ],
    "name:ita_x_preferred":[
        "Paita"
    ],
    "name:jpn_x_preferred":[
        "\u30d1\u30a4\u30bf"
    ],
    "name:kor_x_preferred":[
        "\ud30c\uc774\ud0c0"
    ],
    "name:lit_x_preferred":[
        "Paita"
    ],
    "name:pol_x_preferred":[
        "Paita"
    ],
    "name:por_x_preferred":[
        "Paita"
    ],
    "name:que_x_preferred":[
        "Payta"
    ],
    "name:rus_x_preferred":[
        "\u041f\u0430\u0439\u0442\u0430"
    ],
    "name:spa_x_preferred":[
        "Paita"
    ],
    "name:swe_x_preferred":[
        "Paita"
    ],
    "name:tur_x_preferred":[
        "Paita"
    ],
    "name:ukr_x_preferred":[
        "\u041f\u0430\u0439\u0442\u0430"
    ],
    "name:urd_x_preferred":[
        "\u067e\u0627\u0626\u0679\u0627"
    ],
    "name:vie_x_preferred":[
        "Paita"
    ],
    "name:war_x_preferred":[
        "Paita"
    ],
    "wof:name":"Paita",
    "wof:placetype":"locality"
},
  "geometry": {"coordinates":[86.45905,26.33371],"type":"Point"}
}