{
  "type": "Feature",
  "properties": {
    "gn:admin1_code":"35.0",
    "gn:admin2_code":"449.0",
    "gn:asciiname":"Gujar Borna",
    "gn:country_code":"IN",
    "gn:dem":320,
    "gn:feature_class":"P",
    "gn:feature_code":"PPL",
    "gn:name":"G\u016bjar Borna",
    "gn:population":0,
    "gn:timezone":"Asia/Kolkata",
    "iso:country":"IN",
    "wof:name":"Gujar Borna",
    "wof:placetype":"locality"
},
  "geometry": {"coordinates":[78.12023000000001,22.72678],"type":"Point"}
}