{
  "type": "Feature",
  "properties": {
    "gn:admin1_code":"2.0",
    "gn:admin2_code":"544.0",
    "gn:asciiname":"Gunduru",
    "gn:country_code":"IN",
    "gn:dem":943,
    "gn:feature_class":"P",
    "gn:feature_code":"PPL",
    "gn:name":"Gund\u016bru",
    "gn:population":0,
    "gn:timezone":"Asia/Kolkata",
    "iso:country":"IN",
    "ks:ks_name":"Gonduru",
    "ks:ks_pop":1699,
    "ks:ks_type":"VILLAGE",
    "ks:ks_uagg_main":0,
    "name:eng_x_preferred":[
        "Gonduru"
    ],
    "wof:name":"Gonduru",
    "wof:placetype":"neighbourhood",
    "wof:population":1699
},
  "geometry": {"coordinates":[82.65666400000001,18.071541],"type":"Point"}
}