{
  "type": "Feature",
  "properties": {
    "iso:country":"IN",
    "ks:ks_name":"Derjangjungle",
    "ks:ks_pop":37,
    "ks:ks_type":"VILLAGE",
    "name:eng_x_preferred":[
        "Derjangjungle"
    ],
    "wof:name":"Derjangjungle",
    "wof:placetype":"locality",
    "wof:population":37
},
  "geometry": {"coordinates":[85.016125,20.851294],"type":"Point"}
}