{
  "type": "Feature",
  "properties": {
    "gn:admin1_code":"35",
    "gn:admin2_code":"466.0",
    "gn:asciiname":"Rajhori",
    "gn:country_code":"IN",
    "gn:dem":315,
    "gn:feature_class":"P",
    "gn:feature_code":"PPL",
    "gn:name":"Rajhori",
    "gn:population":0,
    "gn:timezone":"Asia/Kolkata",
    "iso:country":"IN",
    "name:und_x_variant":[
        "Roshn\u0101i"
    ],
    "wof:name":"Rajhori",
    "wof:placetype":"locality"
},
  "geometry": {"coordinates":[76.32334,21.81158],"type":"Point"}
}