{
  "type": "Feature",
  "properties": {
    "iso:country":"IN",
    "ks:ks_name":"Singheswar",
    "ks:ks_pop":2929,
    "ks:ks_type":"VILLAGE",
    "name:eng_x_preferred":[
        "Singheswar"
    ],
    "wof:name":"Singheswar",
    "wof:placetype":"locality",
    "wof:population":2929
},
  "geometry": {"coordinates":[88.60326000000001,22.400978],"type":"Point"}
}