{
  "type": "Feature",
  "properties": {
    "iso:country":"IN",
    "ks:ks_name":"Sonari Nikatiar Kuthi",
    "ks:ks_pop":906,
    "ks:ks_type":"VILLAGE",
    "name:eng_x_preferred":[
        "Sonari Nikatiar Kuthi"
    ],
    "wof:name":"Sonari Nikatiar Kuthi",
    "wof:placetype":"locality",
    "wof:population":906
},
  "geometry": {"coordinates":[89.472528,26.379147],"type":"Point"}
}