{
  "type": "Feature",
  "properties": {
    "iso:country":"IN",
    "ks:ks_name":"Vaniwadi",
    "ks:ks_pop":140,
    "ks:ks_type":"VILLAGE",
    "name:eng_x_preferred":[
        "Vaniwadi"
    ],
    "wof:name":"Vaniwadi",
    "wof:placetype":"locality",
    "wof:population":140
},
  "geometry": {"coordinates":[73.6421,16.535367],"type":"Point"}
}