{
  "type": "Feature",
  "properties": {
    "iso:country":"IN",
    "ks:ks_alt_nam":"Malk\u0101pur",
    "ks:ks_name":"Malkapur",
    "ks:ks_pop":173,
    "ks:ks_type":"VILLAGE",
    "name:eng_x_preferred":[
        "Malkapur"
    ],
    "name:eng_x_variant":[
        "Malk\u0101pur"
    ],
    "wof:name":"Malkapur",
    "wof:placetype":"locality",
    "wof:population":173
},
  "geometry": {"coordinates":[78.073279,19.037489],"type":"Point"}
}