{
  "type": "Feature",
  "properties": {
    "gn:admin1_code":"36.0",
    "gn:admin2_code":"184.0",
    "gn:asciiname":"Bale Jinwan Nankar",
    "gn:country_code":"IN",
    "gn:dem":94,
    "gn:feature_class":"P",
    "gn:feature_code":"PPL",
    "gn:name":"B\u0101le Jinw\u0101n N\u0101nk\u0101r",
    "gn:population":0,
    "gn:timezone":"Asia/Kolkata",
    "iso:country":"IN",
    "wof:name":"Bale Jinwan Nankar",
    "wof:placetype":"locality"
},
  "geometry": {"coordinates":[82.81628000000001,27.19088],"type":"Point"}
}