{
  "type": "Feature",
  "properties": {
    "gn:admin1_code":"36.0",
    "gn:admin2_code":"192.0",
    "gn:asciiname":"Panti",
    "gn:country_code":"IN",
    "gn:dem":78,
    "gn:feature_class":"P",
    "gn:feature_code":"PPL",
    "gn:name":"Panti",
    "gn:population":0,
    "gn:timezone":"Asia/Kolkata",
    "iso:country":"IN",
    "name:deu_x_preferred":[
        "Panti Bliss"
    ],
    "name:fra_x_preferred":[
        "Panti"
    ],
    "name:gle_x_preferred":[
        "Panti"
    ],
    "name:spa_x_preferred":[
        "Panti"
    ],
    "wof:name":"Panti",
    "wof:placetype":"locality"
},
  "geometry": {"coordinates":[83.66972,26.15434],"type":"Point"}
}