{
  "type": "Feature",
  "properties": {
    "iso:country":"IN",
    "ks:ks_name":"Petko",
    "ks:ks_type":"VILLAGE",
    "name:eng_x_preferred":[
        "Petko"
    ],
    "wof:name":"Petko",
    "wof:placetype":"locality"
},
  "geometry": {"coordinates":[85.76385000000001,23.941561],"type":"Point"}
}