{
  "type": "Feature",
  "properties": {
    "iso:country":"IN",
    "ks:ks_alt_nam":"AMRATI UTTARI",
    "ks:ks_name":"Amrati Uttari",
    "ks:ks_pop":140,
    "ks:ks_type":"HABITATION",
    "ks:ks_uagg_main":0,
    "name:eng_x_preferred":[
        "Amrati Uttari"
    ],
    "wof:name":"Amrati Uttari",
    "wof:placetype":"neighbourhood",
    "wof:population":140
},
  "geometry": {"coordinates":[81.789343,26.180544],"type":"Point"}
}