{
  "type": "Feature",
  "properties": {
    "iso:country":"IN",
    "ks:ks_name":"Maachpalli",
    "ks:ks_pop":799,
    "ks:ks_type":"VILLAGE",
    "name:eng_x_preferred":[
        "Maachpalli"
    ],
    "wof:name":"Maachpalli",
    "wof:placetype":"locality",
    "wof:population":799
},
  "geometry": {"coordinates":[80.683713,19.920051],"type":"Point"}
}