{
  "type": "Feature",
  "properties": {
    "iso:country":"IN",
    "ks:ks_name":"Bhandawa Fali",
    "ks:ks_pop":100,
    "ks:ks_type":"HABITATION",
    "name:eng_x_preferred":[
        "Bhandawa Fali"
    ],
    "wof:name":"Bhandawa Fali",
    "wof:placetype":"locality",
    "wof:population":100
},
  "geometry": {"coordinates":[72.900147,24.348444],"type":"Point"}
}