{
  "type": "Feature",
  "properties": {
    "gn:admin1_code":"34.0",
    "gn:admin2_code":"235.0",
    "gn:asciiname":"Duamba",
    "gn:country_code":"IN",
    "gn:dem":167,
    "gn:feature_class":"P",
    "gn:feature_code":"PPL",
    "gn:name":"Duamb\u0101",
    "gn:population":0,
    "gn:timezone":"Asia/Kolkata",
    "iso:country":"IN",
    "ks:ks_name":"Duamba",
    "ks:ks_pop":0,
    "ks:ks_type":"VILLAGE",
    "name:eng_x_preferred":[
        "Duamba"
    ],
    "wof:name":"Duamba",
    "wof:placetype":"locality",
    "wof:population":0
},
  "geometry": {"coordinates":[84.110423,24.530906],"type":"Point"}
}