{
  "type": "Feature",
  "properties": {
    "iso:country":"IN",
    "ks:ks_name":"Rudarpur",
    "ks:ks_pop":540,
    "ks:ks_type":"VILLAGE",
    "ks:ks_uagg_main":0,
    "name:eng_x_preferred":[
        "Rudarpur"
    ],
    "wof:name":"Rudarpur",
    "wof:placetype":"neighbourhood",
    "wof:population":540
},
  "geometry": {"coordinates":[86.723724,24.538757],"type":"Point"}
}