{
  "type": "Feature",
  "properties": {
    "iso:country":"IN",
    "ks:ks_name":"Bhat Khedi",
    "ks:ks_pop":0,
    "ks:ks_type":"VILLAGE",
    "name:eng_x_preferred":[
        "Bhat Khedi"
    ],
    "wof:name":"Bhat Khedi",
    "wof:placetype":"locality",
    "wof:population":0
},
  "geometry": {"coordinates":[75.08362099999999,23.342021],"type":"Point"}
}