{
  "type": "Feature",
  "properties": {
    "iso:country":"IN",
    "ks:ks_name":"Hasan Alipur",
    "ks:ks_pop":3,
    "ks:ks_type":"VILLAGE",
    "ks:ks_uagg_main":0,
    "name:eng_x_preferred":[
        "Hasan Alipur"
    ],
    "wof:name":"Hasan Alipur",
    "wof:placetype":"neighbourhood",
    "wof:population":3
},
  "geometry": {"coordinates":[77.89264,29.835238],"type":"Point"}
}