{
  "type": "Feature",
  "properties": {
    "iso:country":"IN",
    "ks:ks_name":"Bocharewadi",
    "ks:ks_pop":110,
    "ks:ks_type":"HABITATION",
    "name:eng_x_preferred":[
        "Bocharewadi"
    ],
    "wof:name":"Bocharewadi",
    "wof:placetype":"locality",
    "wof:population":110
},
  "geometry": {"coordinates":[75.674826,20.024753],"type":"Point"}
}