{
  "type": "Feature",
  "properties": {
    "iso:country":"IN",
    "ks:ks_name":"Purbba Islampur",
    "ks:ks_pop":1003,
    "ks:ks_type":"VILLAGE",
    "name:eng_x_preferred":[
        "Purbba Islampur"
    ],
    "wof:name":"Purbba Islampur",
    "wof:placetype":"locality",
    "wof:population":1003
},
  "geometry": {"coordinates":[87.739115,23.68365],"type":"Point"}
}