{
  "type": "Feature",
  "properties": {
    "gn:admin1_code":"36.0",
    "gn:admin2_code":"183.0",
    "gn:asciiname":"Bhagat",
    "gn:country_code":"IN",
    "gn:dem":105,
    "gn:feature_class":"P",
    "gn:feature_code":"PPL",
    "gn:name":"Bhagat",
    "gn:population":0,
    "gn:timezone":"Asia/Kolkata",
    "iso:country":"IN",
    "name:fra_x_preferred":[
        "Bhagat"
    ],
    "name:ita_x_preferred":[
        "Bhagat"
    ],
    "name:pan_x_preferred":[
        "\u0a38\u0a3f\u0a71\u0a16 \u0a2d\u0a17\u0a24"
    ],
    "name:pol_x_preferred":[
        "Bhagat"
    ],
    "name:snd_x_preferred":[
        "\u0680\u06b3\u062a"
    ],
    "wof:name":"Bhagat",
    "wof:placetype":"neighbourhood"
},
  "geometry": {"coordinates":[81.66212,27.02782],"type":"Point"}
}