{
  "type": "Feature",
  "properties": {
    "gn:admin1_code":"36",
    "gn:admin2_code":"194.0",
    "gn:asciiname":"Chak Maigar",
    "gn:country_code":"IN",
    "gn:dem":91,
    "gn:feature_class":"P",
    "gn:feature_code":"PPL",
    "gn:name":"Chak Maigar",
    "gn:population":0,
    "gn:timezone":"Asia/Kolkata",
    "iso:country":"IN",
    "ks:ks_name":"Chak Maigar",
    "ks:ks_pop":129,
    "ks:ks_type":"VILLAGE",
    "ks:ks_uagg_main":0,
    "name:eng_x_preferred":[
        "Chak Maigar"
    ],
    "wof:name":"Chak Maigar",
    "wof:placetype":"neighbourhood",
    "wof:population":129
},
  "geometry": {"coordinates":[82.61490000000001,25.463834],"type":"Point"}
}