{
  "type": "Feature",
  "properties": {
    "iso:country":"IN",
    "ks:ks_name":"Kansara",
    "ks:ks_pop":1031,
    "ks:ks_type":"VILLAGE",
    "name:eng_x_preferred":[
        "Kansara"
    ],
    "wof:name":"Kansara",
    "wof:placetype":"locality",
    "wof:population":1031
},
  "geometry": {"coordinates":[86.464646,20.497933],"type":"Point"}
}