{
  "type": "Feature",
  "properties": {
    "iso:country":"IN",
    "ks:ks_name":"Chiada",
    "ks:ks_pop":0,
    "ks:ks_type":"VILLAGE",
    "name:eng_x_preferred":[
        "Chiada"
    ],
    "wof:name":"Chiada",
    "wof:placetype":"locality",
    "wof:population":0
},
  "geometry": {"coordinates":[86.73649500000001,22.948484],"type":"Point"}
}