{
  "type": "Feature",
  "properties": {
    "iso:country":"IN",
    "ks:ks_name":"Balijan Bengali",
    "ks:ks_pop":876,
    "ks:ks_type":"VILLAGE",
    "ks:ks_uagg_main":0,
    "name:eng_x_preferred":[
        "Balijan Bengali"
    ],
    "wof:name":"Balijan Bengali",
    "wof:placetype":"neighbourhood",
    "wof:population":876
},
  "geometry": {"coordinates":[92.43571,26.628958],"type":"Point"}
}