{
  "type": "Feature",
  "properties": {
    "iso:country":"IN",
    "ks:ks_name":"Jhatikaram",
    "ks:ks_pop":69,
    "ks:ks_type":"HABITATION",
    "name:eng_x_preferred":[
        "Jhatikaram"
    ],
    "wof:name":"Jhatikaram",
    "wof:placetype":"locality",
    "wof:population":69
},
  "geometry": {"coordinates":[86.654056,22.013899],"type":"Point"}
}