{
  "type": "Feature",
  "properties": {
    "iso:country":"IN",
    "ks:ks_name":"Lahangia Falia",
    "ks:ks_pop":136,
    "ks:ks_type":"HABITATION",
    "name:eng_x_preferred":[
        "Lahangia Falia"
    ],
    "wof:name":"Lahangia Falia",
    "wof:placetype":"locality",
    "wof:population":136
},
  "geometry": {"coordinates":[73.106972,20.227722],"type":"Point"}
}