{
  "type": "Feature",
  "properties": {
    "iso:country":"IN",
    "ks:ks_name":"Karkata",
    "ks:ks_pop":170,
    "ks:ks_type":"VILLAGE",
    "name:eng_x_preferred":[
        "Karkata"
    ],
    "wof:name":"Karkata",
    "wof:placetype":"locality",
    "wof:population":170
},
  "geometry": {"coordinates":[85.364632,22.840939],"type":"Point"}
}