{
  "type": "Feature",
  "properties": {
    "iso:country":"IN",
    "ks:ks_name":"Gopalganja",
    "ks:ks_pop":2931,
    "ks:ks_type":"VILLAGE",
    "name:eng_x_preferred":[
        "Gopalganja"
    ],
    "wof:name":"Gopalganja",
    "wof:placetype":"locality",
    "wof:population":2931
},
  "geometry": {"coordinates":[87.11530500000001,23.572535],"type":"Point"}
}