{
  "type": "Feature",
  "properties": {
    "iso:country":"IN",
    "ks:ks_name":"Kakotigaon",
    "ks:ks_pop":510,
    "ks:ks_type":"HABITATION",
    "name:eng_x_preferred":[
        "Kakotigaon"
    ],
    "wof:name":"Kakotigaon",
    "wof:placetype":"locality",
    "wof:population":510
},
  "geometry": {"coordinates":[93.922353,26.573659],"type":"Point"}
}