{
  "type": "Feature",
  "properties": {
    "iso:country":"IN",
    "ks:ks_name":"Rasalpur",
    "ks:ks_pop":111,
    "ks:ks_type":"VILLAGE",
    "name:eng_x_preferred":[
        "Rasalpur"
    ],
    "wof:name":"Rasalpur",
    "wof:placetype":"locality",
    "wof:population":111
},
  "geometry": {"coordinates":[85.21164,20.97369],"type":"Point"}
}