{
  "type": "Feature",
  "properties": {
    "gn:admin1_code":"24.0",
    "gn:admin2_code":"124.0",
    "gn:asciiname":"Bildi",
    "gn:country_code":"IN",
    "gn:dem":305,
    "gn:feature_class":"P",
    "gn:feature_code":"PPL",
    "gn:name":"Bildi",
    "gn:population":0,
    "gn:timezone":"Asia/Kolkata",
    "iso:country":"IN",
    "wof:name":"Bildi",
    "wof:placetype":"neighbourhood"
},
  "geometry": {"coordinates":[73.73061,23.83701],"type":"Point"}
}