{
  "type": "Feature",
  "properties": {
    "iso:country":"IN",
    "ks:ks_name":"Hatankarwadi",
    "ks:ks_pop":29,
    "ks:ks_type":"HABITATION",
    "name:eng_x_preferred":[
        "Hatankarwadi"
    ],
    "wof:name":"Hatankarwadi",
    "wof:placetype":"locality",
    "wof:population":29
},
  "geometry": {"coordinates":[73.56419200000001,16.663455],"type":"Point"}
}