{
  "type": "Feature",
  "properties": {
    "iso:country":"IN",
    "ks:ks_alt_nam":"Pure Sh\u0101m",
    "ks:ks_alt_nam_2":"Pure Sham",
    "ks:ks_name":"Pureshyam",
    "ks:ks_pop":63,
    "ks:ks_type":"VILLAGE",
    "ks:ks_uagg_main":0,
    "name:eng_x_preferred":[
        "Pureshyam"
    ],
    "name:eng_x_variant":[
        "Pure Sh\u0101m",
        "Pure Sham"
    ],
    "wof:name":"Pureshyam",
    "wof:placetype":"neighbourhood",
    "wof:population":63
},
  "geometry": {"coordinates":[82.57596700000001,25.390689],"type":"Point"}
}