{
  "type": "Feature",
  "properties": {
    "gn:admin1_code":"23.0",
    "gn:admin2_code":"47.0",
    "gn:asciiname":"Odat Saidewala",
    "gn:country_code":"IN",
    "gn:dem":220,
    "gn:feature_class":"P",
    "gn:feature_code":"PPL",
    "gn:name":"Odat Saidew\u0101la",
    "gn:population":0,
    "gn:timezone":"Asia/Kolkata",
    "iso:country":"IN",
    "wof:name":"Odat Saidewala",
    "wof:placetype":"locality"
},
  "geometry": {"coordinates":[75.48335,29.82161],"type":"Point"}
}