{
  "type": "Feature",
  "properties": {
    "iso:country":"IN",
    "ks:ks_name":"Neralekudige",
    "ks:ks_pop":21,
    "ks:ks_type":"HABITATION",
    "name:eng_x_preferred":[
        "Neralekudige"
    ],
    "wof:name":"Neralekudige",
    "wof:placetype":"locality",
    "wof:population":21
},
  "geometry": {"coordinates":[75.263953,13.55887],"type":"Point"}
}