{
  "type": "Feature",
  "properties": {
    "iso:country":"IN",
    "ks:ks_name":"Mareikana",
    "ks:ks_type":"VILLAGE",
    "name:eng_x_preferred":[
        "Mareikana"
    ],
    "wof:name":"Mareikana",
    "wof:placetype":"locality"
},
  "geometry": {"coordinates":[85.186239,20.352666],"type":"Point"}
}