{
  "type": "Feature",
  "properties": {
    "iso:country":"IN",
    "ks:ks_name":"Bhanwa",
    "ks:ks_pop":372,
    "ks:ks_type":"HABITATION",
    "name:eng_x_preferred":[
        "Bhanwa"
    ],
    "wof:name":"Bhanwa",
    "wof:placetype":"locality",
    "wof:population":372
},
  "geometry": {"coordinates":[81.173052,27.719016],"type":"Point"}
}