{
  "type": "Feature",
  "properties": {
    "gn:admin1_code":"34.0",
    "gn:admin2_code":"219.0",
    "gn:asciiname":"Rampur Atauli",
    "gn:country_code":"IN",
    "gn:dem":60,
    "gn:feature_class":"P",
    "gn:feature_code":"PPL",
    "gn:name":"R\u0101mpur Atauli",
    "gn:population":0,
    "gn:timezone":"Asia/Kolkata",
    "iso:country":"IN",
    "ks:ks_alt_nam":"R\u0101mpur Atauli",
    "ks:ks_name":"Rampur Atauli",
    "ks:ks_pop":2339,
    "ks:ks_type":"VILLAGE",
    "ks:ks_uagg_main":0,
    "name:eng_x_preferred":[
        "Rampur Atauli"
    ],
    "name:eng_x_variant":[
        "R\u0101mpur Atauli"
    ],
    "wof:name":"Rampur Atauli",
    "wof:placetype":"neighbourhood",
    "wof:population":2339
},
  "geometry": {"coordinates":[84.775212,26.054839],"type":"Point"}
}