{
  "type": "Feature",
  "properties": {
    "iso:country":"IN",
    "ks:ks_name":"Borichaghoda",
    "ks:ks_pop":134,
    "ks:ks_type":"HABITATION",
    "name:eng_x_preferred":[
        "Borichaghoda"
    ],
    "wof:name":"Borichaghoda",
    "wof:placetype":"locality",
    "wof:population":134
},
  "geometry": {"coordinates":[73.273753,19.964452],"type":"Point"}
}