{
  "type": "Feature",
  "properties": {
    "iso:country":"IN",
    "ks:ks_name":"Harijanawada",
    "ks:ks_pop":259,
    "ks:ks_type":"HABITATION",
    "name:eng_x_preferred":[
        "Harijanawada"
    ],
    "wof:name":"Harijanawada",
    "wof:placetype":"locality",
    "wof:population":259
},
  "geometry": {"coordinates":[79.641133,13.713951],"type":"Point"}
}