{
  "type": "Feature",
  "properties": {
    "iso:country":"IN",
    "ks:ks_name":"Booth Sara",
    "ks:ks_pop":433,
    "ks:ks_type":"HABITATION",
    "name:eng_x_preferred":[
        "Booth Sara"
    ],
    "wof:name":"Booth Sara",
    "wof:placetype":"locality",
    "wof:population":433
},
  "geometry": {"coordinates":[71.81383599999999,25.819817],"type":"Point"}
}