{
  "type": "Feature",
  "properties": {
    "iso:country":"IN",
    "ks:ks_name":"Sriramapuram",
    "ks:ks_pop":247,
    "ks:ks_type":"HABITATION",
    "name:eng_x_preferred":[
        "Sriramapuram"
    ],
    "wof:name":"Sriramapuram",
    "wof:placetype":"locality",
    "wof:population":247
},
  "geometry": {"coordinates":[78.244906,9.02697],"type":"Point"}
}