{
  "type": "Feature",
  "properties": {
    "gn:admin1_code":"11",
    "gn:admin2_code":"24.0",
    "gn:asciiname":"Peral",
    "gn:country_code":"IN",
    "gn:dem":695,
    "gn:feature_class":"P",
    "gn:feature_code":"PPL",
    "gn:name":"Peral",
    "gn:population":0,
    "gn:timezone":"Asia/Kolkata",
    "iso:country":"IN",
    "name:ceb_x_preferred":[
        "Peral"
    ],
    "name:deu_x_preferred":[
        "Peral"
    ],
    "name:nld_x_preferred":[
        "Peral"
    ],
    "name:por_x_preferred":[
        "Peral"
    ],
    "name:rus_x_preferred":[
        "\u041f\u0435\u0440\u0430\u043b"
    ],
    "name:spa_x_preferred":[
        "Peral"
    ],
    "name:swe_x_preferred":[
        "Peral"
    ],
    "wof:name":"Peral",
    "wof:placetype":"locality"
},
  "geometry": {"coordinates":[76.39076,31.85533],"type":"Point"}
}