{
  "type": "Feature",
  "properties": {
    "gn:admin1_code":"36",
    "gn:admin2_code":"195.0",
    "gn:asciiname":"Bareji",
    "gn:country_code":"IN",
    "gn:dem":72,
    "gn:feature_class":"P",
    "gn:feature_code":"PPL",
    "gn:name":"Bareji",
    "gn:population":0,
    "gn:timezone":"Asia/Kolkata",
    "iso:country":"IN",
    "wof:name":"Bareji",
    "wof:placetype":"neighbourhood"
},
  "geometry": {"coordinates":[83.78107,25.71062],"type":"Point"}
}