{
  "type": "Feature",
  "properties": {
    "iso:country":"IN",
    "ks:ks_alt_nam":"Arunthathiyar colony",
    "ks:ks_name":"Arunthathiyar Colony",
    "ks:ks_pop":105,
    "ks:ks_type":"HABITATION",
    "name:eng_x_preferred":[
        "Arunthathiyar Colony"
    ],
    "wof:name":"Arunthathiyar Colony",
    "wof:placetype":"locality",
    "wof:population":105
},
  "geometry": {"coordinates":[78.92258,13.056503],"type":"Point"}
}