{
  "type": "Feature",
  "properties": {
    "iso:country":"IN",
    "ks:ks_name":"Vankachintalavalasa",
    "ks:ks_pop":4,
    "ks:ks_type":"HABITATION",
    "name:eng_x_preferred":[
        "Vankachintalavalasa"
    ],
    "wof:name":"Vankachintalavalasa",
    "wof:placetype":"locality",
    "wof:population":4
},
  "geometry": {"coordinates":[83.091812,18.609351],"type":"Point"}
}