{
  "type": "Feature",
  "properties": {
    "gn:admin1_code":"36.0",
    "gn:admin2_code":"177.0",
    "gn:asciiname":"Mehdauna",
    "gn:country_code":"IN",
    "gn:dem":105,
    "gn:feature_class":"P",
    "gn:feature_code":"PPL",
    "gn:name":"Mehdauna",
    "gn:population":0,
    "gn:timezone":"Asia/Kolkata",
    "iso:country":"IN",
    "ks:ks_name":"Mehdauna",
    "ks:ks_pop":5588,
    "ks:ks_type":"VILLAGE",
    "ks:ks_uagg_main":0,
    "name:eng_x_preferred":[
        "Mehdauna"
    ],
    "wof:name":"Mehdauna",
    "wof:placetype":"neighbourhood",
    "wof:population":5588
},
  "geometry": {"coordinates":[82.036007,26.66747],"type":"Point"}
}