{
  "type": "Feature",
  "properties": {
    "iso:country":"IN",
    "ks:ks_name":"Bisaona",
    "ks:ks_pop":129,
    "ks:ks_type":"HABITATION",
    "name:eng_x_preferred":[
        "Bisaona"
    ],
    "wof:name":"Bisaona",
    "wof:placetype":"locality",
    "wof:population":129
},
  "geometry": {"coordinates":[79.342726,29.630677],"type":"Point"}
}