{
  "type": "Feature",
  "properties": {
    "gn:admin1_code":"25.0",
    "gn:admin2_code":"633.0",
    "gn:asciiname":"Moyyandampalaiyampudur",
    "gn:country_code":"IN",
    "gn:dem":333,
    "gn:feature_class":"P",
    "gn:feature_code":"PPL",
    "gn:name":"Moyy\u0101ndamp\u0101laiyampud\u016br",
    "gn:population":0,
    "gn:timezone":"Asia/Kolkata",
    "iso:country":"IN",
    "wof:name":"Moyyandampalaiyampudur",
    "wof:placetype":"locality"
},
  "geometry": {"coordinates":[77.35359,11.21344],"type":"Point"}
}