{
  "type": "Feature",
  "properties": {
    "iso:country":"IN",
    "ks:ks_name":"Madiguda",
    "ks:ks_pop":164,
    "ks:ks_type":"HABITATION",
    "name:eng_x_preferred":[
        "Madiguda"
    ],
    "wof:name":"Madiguda",
    "wof:placetype":"locality",
    "wof:population":164
},
  "geometry": {"coordinates":[82.10285500000001,18.556883],"type":"Point"}
}