{
  "type": "Feature",
  "properties": {
    "iso:country":"IN",
    "ks:ks_name":"Ajitpur",
    "ks:ks_pop":17,
    "ks:ks_type":"VILLAGE",
    "name:eng_x_preferred":[
        "Ajitpur"
    ],
    "wof:name":"Ajitpur",
    "wof:placetype":"locality",
    "wof:population":17
},
  "geometry": {"coordinates":[77.482148,21.279653],"type":"Point"}
}