{
  "type": "Feature",
  "properties": {
    "iso:country":"IN",
    "ks:ks_name":"Kandhasarli",
    "ks:ks_pop":322,
    "ks:ks_type":"VILLAGE",
    "name:eng_x_preferred":[
        "Kandhasarli"
    ],
    "wof:name":"Kandhasarli",
    "wof:placetype":"locality",
    "wof:population":322
},
  "geometry": {"coordinates":[83.267234,19.693887],"type":"Point"}
}