{
  "type": "Feature",
  "properties": {
    "gn:admin1_code":"19",
    "gn:admin2_code":"559.0",
    "gn:asciiname":"Gudijavur",
    "gn:country_code":"IN",
    "gn:dem":492,
    "gn:feature_class":"P",
    "gn:feature_code":"PPL",
    "gn:name":"Gudij\u0101v\u016br",
    "gn:population":0,
    "gn:timezone":"Asia/Kolkata",
    "iso:country":"IN",
    "ks:ks_alt_nam":"Gudij\u0101v\u016br",
    "ks:ks_name":"Gudijavur",
    "ks:ks_type":"VILLAGE",
    "name:eng_x_preferred":[
        "Gudijavur"
    ],
    "name:eng_x_variant":[
        "Gudij\u0101v\u016br"
    ],
    "wof:name":"Gudijavur",
    "wof:placetype":"locality"
},
  "geometry": {"coordinates":[76.343923,16.193573],"type":"Point"}
}