{
  "type": "Feature",
  "properties": {
    "iso:country":"IN",
    "ks:ks_name":"Pipalya Singaji Theka",
    "ks:ks_pop":459,
    "ks:ks_type":"HABITATION",
    "name:eng_x_preferred":[
        "Pipalya Singaji Theka"
    ],
    "wof:name":"Pipalya Singaji Theka",
    "wof:placetype":"locality",
    "wof:population":459
},
  "geometry": {"coordinates":[76.679891,22.095082],"type":"Point"}
}