{
  "type": "Feature",
  "properties": {
    "iso:country":"IN",
    "ks:ks_name":"Ghatiniya",
    "ks:ks_pop":16,
    "ks:ks_type":"HABITATION",
    "name:eng_x_preferred":[
        "Ghatiniya"
    ],
    "wof:name":"Ghatiniya",
    "wof:placetype":"locality",
    "wof:population":16
},
  "geometry": {"coordinates":[81.002291,24.89524],"type":"Point"}
}