{
  "type": "Feature",
  "properties": {
    "iso:country":"IN",
    "ks:ks_name":"Gokul Purwa",
    "ks:ks_pop":305,
    "ks:ks_type":"HABITATION",
    "name:eng_x_preferred":[
        "Gokul Purwa"
    ],
    "wof:name":"Gokul Purwa",
    "wof:placetype":"locality",
    "wof:population":305
},
  "geometry": {"coordinates":[80.147918,27.133948],"type":"Point"}
}