{
  "type": "Feature",
  "properties": {
    "iso:country":"IN",
    "ks:ks_alt_nam":"vilathuveli",
    "ks:ks_name":"Vilathuveli",
    "ks:ks_pop":120,
    "ks:ks_type":"HABITATION",
    "name:eng_x_preferred":[
        "Vilathuveli"
    ],
    "wof:name":"Vilathuveli",
    "wof:placetype":"locality",
    "wof:population":120
},
  "geometry": {"coordinates":[79.506936,10.438778],"type":"Point"}
}