{
  "type": "Feature",
  "properties": {
    "iso:country":"IN",
    "ks:ks_name":"Atghara",
    "ks:ks_pop":978,
    "ks:ks_type":"VILLAGE",
    "ks:ks_uagg_main":0,
    "name:eng_x_preferred":[
        "Atghara"
    ],
    "wof:name":"Atghara",
    "wof:placetype":"locality",
    "wof:population":978
},
  "geometry": {"coordinates":[88.46463199999999,22.365367],"type":"Point"}
}