{
  "type": "Feature",
  "properties": {
    "gn:admin1_code":"16.0",
    "gn:admin2_code":"522",
    "gn:asciiname":"Kharwandi",
    "gn:country_code":"IN",
    "gn:dem":572,
    "gn:feature_class":"P",
    "gn:feature_code":"PPL",
    "gn:name":"Kharw\u0101ndi",
    "gn:population":0,
    "gn:timezone":"Asia/Kolkata",
    "iso:country":"IN",
    "wof:name":"Kharwandi",
    "wof:placetype":"locality"
},
  "geometry": {"coordinates":[75.3763,19.16204],"type":"Point"}
}