{
  "type": "Feature",
  "properties": {
    "gn:admin1_code":"2.0",
    "gn:admin2_code":"544.0",
    "gn:asciiname":"Adalputtu",
    "gn:country_code":"IN",
    "gn:dem":816,
    "gn:feature_class":"P",
    "gn:feature_code":"PPL",
    "gn:name":"Adalputtu",
    "gn:population":0,
    "gn:timezone":"Asia/Kolkata",
    "iso:country":"IN",
    "ks:ks_name":"Adalaputtu",
    "ks:ks_pop":78,
    "ks:ks_type":"HABITATION",
    "name:eng_x_preferred":[
        "Adalaputtu"
    ],
    "name:eng_x_variant":[
        "Adalputtu"
    ],
    "wof:name":"Adalaputtu",
    "wof:placetype":"locality",
    "wof:population":78
},
  "geometry": {"coordinates":[82.49248299999999,18.478145],"type":"Point"}
}