{
  "type": "Feature",
  "properties": {
    "gn:admin1_code":"2.0",
    "gn:admin2_code":"544.0",
    "gn:asciiname":"Adalputtu",
    "gn:country_code":"IN",
    "gn:dem":816,
    "gn:feature_class":"P",
    "gn:feature_code":"PPL",
    "gn:name":"Adalputtu",
    "gn:population":0,
    "gn:timezone":"Asia/Kolkata",
    "iso:country":"IN",
    "wof:name":"Adalputtu",
    "wof:placetype":"locality"
},
  "geometry": {"coordinates":[82.49283,18.47852],"type":"Point"}
}