{
  "type": "Feature",
  "properties": {
    "gn:admin1_code":"2",
    "gn:admin2_code":"544.0",
    "gn:asciiname":"Dumrivalasa",
    "gn:country_code":"IN",
    "gn:dem":1052,
    "gn:feature_class":"P",
    "gn:feature_code":"PPL",
    "gn:name":"Dumrivalasa",
    "gn:population":0,
    "gn:timezone":"Asia/Kolkata",
    "iso:country":"IN",
    "wof:name":"Dumrivalasa",
    "wof:placetype":"locality"
},
  "geometry": {"coordinates":[82.89917,18.16485],"type":"Point"}
}