{
  "type": "Feature",
  "properties": {
    "gn:admin1_code":"2",
    "gn:admin2_code":"544.0",
    "gn:asciiname":"Dumrivalasa",
    "gn:country_code":"IN",
    "gn:dem":1052,
    "gn:feature_class":"P",
    "gn:feature_code":"PPL",
    "gn:name":"Dumrivalasa",
    "gn:population":0,
    "gn:timezone":"Asia/Kolkata",
    "iso:country":"IN",
    "ks:ks_name":"Dumbrivalasa",
    "ks:ks_pop":8,
    "ks:ks_type":"HABITATION",
    "name:eng_x_preferred":[
        "Dumbrivalasa"
    ],
    "name:eng_x_variant":[
        "Dumrivalasa"
    ],
    "wof:name":"Dumbrivalasa",
    "wof:placetype":"locality",
    "wof:population":8
},
  "geometry": {"coordinates":[82.900932,18.164047],"type":"Point"}
}