{
  "type": "Feature",
  "properties": {
    "iso:country":"IN",
    "ks:ks_name":"Purba Panchurasia",
    "ks:ks_pop":514,
    "ks:ks_type":"VILLAGE",
    "name:eng_x_preferred":[
        "Purba Panchurasia"
    ],
    "wof:name":"Purba Panchurasia",
    "wof:placetype":"locality",
    "wof:population":514
},
  "geometry": {"coordinates":[88.157988,26.198075],"type":"Point"}
}