{
  "type": "Feature",
  "properties": {
    "gn:admin1_code":"19.0",
    "gn:admin2_code":"581.0",
    "gn:asciiname":"Siddanhalli",
    "gn:country_code":"IN",
    "gn:dem":891,
    "gn:feature_class":"P",
    "gn:feature_code":"PPL",
    "gn:name":"Siddanhalli",
    "gn:population":0,
    "gn:timezone":"Asia/Kolkata",
    "iso:country":"IN",
    "wof:name":"Siddanhalli",
    "wof:placetype":"locality"
},
  "geometry": {"coordinates":[77.91369,12.89413],"type":"Point"}
}