{
  "type": "Feature",
  "properties": {
    "iso:country":"IN",
    "ks:ks_name":"Kalakhowa",
    "ks:ks_pop":1017,
    "ks:ks_type":"VILLAGE",
    "ks:ks_uagg_main":0,
    "name:eng_x_preferred":[
        "Kalakhowa"
    ],
    "wof:name":"Kalakhowa",
    "wof:placetype":"locality",
    "wof:population":1017
},
  "geometry": {"coordinates":[93.576466,26.629265],"type":"Point"}
}