{
  "type": "Feature",
  "properties": {
    "iso:country":"IN",
    "ks:ks_name":"Mandharewadi",
    "ks:ks_pop":160,
    "ks:ks_type":"HABITATION",
    "name:eng_x_preferred":[
        "Mandharewadi"
    ],
    "wof:name":"Mandharewadi",
    "wof:placetype":"locality",
    "wof:population":160
},
  "geometry": {"coordinates":[74.54221699999999,18.724829],"type":"Point"}
}