{
  "type": "Feature",
  "properties": {
    "gn:admin1_code":"11",
    "gn:admin2_code":"33.0",
    "gn:asciiname":"Kuhl",
    "gn:country_code":"IN",
    "gn:dem":2008,
    "gn:feature_class":"P",
    "gn:feature_code":"PPL",
    "gn:name":"Kuhl",
    "gn:population":0,
    "gn:timezone":"Asia/Kolkata",
    "iso:country":"IN",
    "wof:name":"Kuhl",
    "wof:placetype":"locality"
},
  "geometry": {"coordinates":[77.54765,30.92346],"type":"Point"}
}