{
  "type": "Feature",
  "properties": {
    "iso:country":"IN",
    "ks:ks_name":"Deora",
    "ks:ks_pop":1215,
    "ks:ks_type":"VILLAGE",
    "name:eng_x_preferred":[
        "Deora"
    ],
    "wof:name":"Deora",
    "wof:placetype":"locality",
    "wof:population":1215
},
  "geometry": {"coordinates":[82.32615800000001,24.189596],"type":"Point"}
}