{
  "type": "Feature",
  "properties": {
    "gn:admin1_code":"24.0",
    "gn:admin2_code":"104.0",
    "gn:asciiname":"Pinan",
    "gn:country_code":"IN",
    "gn:dem":264,
    "gn:feature_class":"P",
    "gn:feature_code":"PPL",
    "gn:name":"Pin\u0101n",
    "gn:population":0,
    "gn:timezone":"Asia/Kolkata",
    "iso:country":"IN",
    "name:bul_x_preferred":[
        "\u0425\u0435\u044f\u043d \u0448\u043e\u0434\u0430\u043d"
    ],
    "name:cat_x_preferred":[
        "Pinan"
    ],
    "name:ces_x_preferred":[
        "Heian sandan"
    ],
    "name:est_x_preferred":[
        "Pinan"
    ],
    "name:fra_x_preferred":[
        "Pinan"
    ],
    "name:ita_x_preferred":[
        "Pinan"
    ],
    "name:jpn_x_preferred":[
        "\u30d4\u30f3\u30a2\u30f3"
    ],
    "name:por_x_preferred":[
        "Pinan"
    ],
    "name:rus_x_preferred":[
        "\u041f\u0438\u043d\u0430\u043d"
    ],
    "name:spa_x_preferred":[
        "Heian"
    ],
    "name:swe_x_preferred":[
        "Pinan"
    ],
    "name:vie_x_preferred":[
        "Pin'an"
    ],
    "wof:name":"Pinan",
    "wof:placetype":"locality"
},
  "geometry": {"coordinates":[76.75147,27.26774],"type":"Point"}
}