{
  "type": "Feature",
  "properties": {
    "iso:country":"IN",
    "ks:ks_name":"Loharakani",
    "ks:ks_pop":51,
    "ks:ks_type":"VILLAGE",
    "name:eng_x_preferred":[
        "Loharakani"
    ],
    "wof:name":"Loharakani",
    "wof:placetype":"locality",
    "wof:population":51
},
  "geometry": {"coordinates":[83.25100500000001,19.882786],"type":"Point"}
}