{
  "type": "Feature",
  "properties": {
    "iso:country":"IN",
    "ks:ks_name":"Chipatpada",
    "ks:ks_pop":195,
    "ks:ks_type":"HABITATION",
    "name:eng_x_preferred":[
        "Chipatpada"
    ],
    "wof:name":"Chipatpada",
    "wof:placetype":"locality",
    "wof:population":195
},
  "geometry": {"coordinates":[72.890901,19.902706],"type":"Point"}
}