{
  "type": "Feature",
  "properties": {
    "iso:country":"IN",
    "ks:ks_name":"Budamaha",
    "ks:ks_pop":34,
    "ks:ks_type":"VILLAGE",
    "name:eng_x_preferred":[
        "Budamaha"
    ],
    "wof:name":"Budamaha",
    "wof:placetype":"locality",
    "wof:population":34
},
  "geometry": {"coordinates":[84.148742,20.119746],"type":"Point"}
}