{
  "type": "Feature",
  "properties": {
    "iso:country":"IN",
    "ks:ks_name":"Nagwahi",
    "ks:ks_pop":619,
    "ks:ks_type":"HABITATION",
    "name:eng_x_preferred":[
        "Nagwahi"
    ],
    "wof:name":"Nagwahi",
    "wof:placetype":"locality",
    "wof:population":619
},
  "geometry": {"coordinates":[80.92840099999999,21.96228],"type":"Point"}
}