{
  "type": "Feature",
  "properties": {
    "iso:country":"IN",
    "ks:ks_name":"Ahamadnagar",
    "ks:ks_pop":1712,
    "ks:ks_type":"VILLAGE",
    "name:eng_x_preferred":[
        "Ahamadnagar"
    ],
    "wof:name":"Ahamadnagar",
    "wof:placetype":"locality",
    "wof:population":1712
},
  "geometry": {"coordinates":[77.31272300000001,28.819964],"type":"Point"}
}