{
  "type": "Feature",
  "properties": {
    "gn:admin1_code":"36",
    "gn:admin2_code":"160.0",
    "gn:asciiname":"Bhagwantpur",
    "gn:country_code":"IN",
    "gn:dem":141,
    "gn:feature_class":"P",
    "gn:feature_code":"PPL",
    "gn:name":"Bhagwantpur",
    "gn:population":0,
    "gn:timezone":"Asia/Kolkata",
    "iso:country":"IN",
    "ks:ks_alt_nam":"Bhagwanta pur",
    "ks:ks_name":"Bhagwanta Pur",
    "ks:ks_pop":259,
    "ks:ks_type":"HABITATION",
    "name:eng_x_preferred":[
        "Bhagwanta Pur"
    ],
    "name:eng_x_variant":[
        "Bhagwantpur"
    ],
    "wof:name":"Bhagwanta Pur",
    "wof:placetype":"locality",
    "wof:population":259
},
  "geometry": {"coordinates":[79.85910699999999,26.848346],"type":"Point"}
}