{
  "type": "Feature",
  "properties": {
    "iso:country":"IN",
    "ks:ks_name":"Kunda",
    "ks:ks_pop":0,
    "ks:ks_type":"VILLAGE",
    "name:eng_x_preferred":[
        "Kunda"
    ],
    "wof:name":"Kunda",
    "wof:placetype":"locality",
    "wof:population":0
},
  "geometry": {"coordinates":[85.972471,24.944555],"type":"Point"}
}