{
  "type": "Feature",
  "properties": {
    "gn:admin1_code":"19.0",
    "gn:admin2_code":"576.0",
    "gn:asciiname":"Yedehalli",
    "gn:country_code":"IN",
    "gn:dem":948,
    "gn:feature_class":"P",
    "gn:feature_code":"PPL",
    "gn:name":"Yedehalli",
    "gn:population":0,
    "gn:timezone":"Asia/Kolkata",
    "iso:country":"IN",
    "wof:name":"Yedehalli",
    "wof:placetype":"locality"
},
  "geometry": {"coordinates":[75.85828000000002,12.72955],"type":"Point"}
}