{
  "type": "Feature",
  "properties": {
    "iso:country":"IN",
    "ks:ks_name":"Alkhetu",
    "ks:ks_pop":20,
    "ks:ks_type":"VILLAGE",
    "name:eng_x_preferred":[
        "Alkhetu"
    ],
    "wof:name":"Alkhetu",
    "wof:placetype":"locality",
    "wof:population":20
},
  "geometry": {"coordinates":[78.93714,29.89515],"type":"Point"}
}