{
  "type": "Feature",
  "properties": {
    "iso:country":"IN",
    "ks:ks_name":"Lasmikanthahalli",
    "ks:ks_pop":249,
    "ks:ks_type":"HABITATION",
    "name:eng_x_preferred":[
        "Lasmikanthahalli"
    ],
    "wof:name":"Lasmikanthahalli",
    "wof:placetype":"locality",
    "wof:population":249
},
  "geometry": {"coordinates":[75.709017,13.275997],"type":"Point"}
}