{
  "type": "Feature",
  "properties": {
    "iso:country":"IN",
    "ks:ks_name":"Kosavanpudur",
    "ks:ks_pop":548,
    "ks:ks_type":"HABITATION",
    "name:eng_x_preferred":[
        "Kosavanpudur"
    ],
    "wof:name":"Kosavanpudur",
    "wof:placetype":"locality",
    "wof:population":548
},
  "geometry": {"coordinates":[78.934849,12.956468],"type":"Point"}
}