{
  "type": "Feature",
  "properties": {
    "iso:country":"IN",
    "ks:ks_name":"Harijan Basti Ii",
    "ks:ks_pop":175,
    "ks:ks_type":"HABITATION",
    "name:eng_x_preferred":[
        "Harijan Basti Ii"
    ],
    "wof:name":"Harijan Basti Ii",
    "wof:placetype":"locality",
    "wof:population":175
},
  "geometry": {"coordinates":[82.84711,26.542912],"type":"Point"}
}