{
  "type": "Feature",
  "properties": {
    "iso:country":"IN",
    "ks:ks_name":"Ghawdepara",
    "ks:ks_pop":76,
    "ks:ks_type":"HABITATION",
    "name:eng_x_preferred":[
        "Ghawdepara"
    ],
    "wof:name":"Ghawdepara",
    "wof:placetype":"locality",
    "wof:population":76
},
  "geometry": {"coordinates":[80.948122,20.554923],"type":"Point"}
}