{
  "type": "Feature",
  "properties": {
    "iso:country":"IN",
    "ks:ks_name":"Thekaha",
    "ks:ks_pop":196,
    "ks:ks_type":"VILLAGE",
    "name:eng_x_preferred":[
        "Thekaha"
    ],
    "wof:name":"Thekaha",
    "wof:placetype":"locality",
    "wof:population":196
},
  "geometry": {"coordinates":[87.162019,24.185938],"type":"Point"}
}