{
  "type": "Feature",
  "properties": {
    "iso:country":"IN",
    "ks:ks_name":"Kampuda",
    "ks:ks_pop":145,
    "ks:ks_type":"HABITATION",
    "name:eng_x_preferred":[
        "Kampuda"
    ],
    "wof:name":"Kampuda",
    "wof:placetype":"locality",
    "wof:population":145
},
  "geometry": {"coordinates":[84.990543,22.693799],"type":"Point"}
}