{
  "type": "Feature",
  "properties": {
    "gn:admin1_code":"36",
    "gn:admin2_code":"171.0",
    "gn:asciiname":"Kanti",
    "gn:country_code":"IN",
    "gn:dem":115,
    "gn:feature_class":"P",
    "gn:feature_code":"PPL",
    "gn:name":"K\u0101nt\u012b",
    "gn:population":0,
    "gn:timezone":"Asia/Kolkata",
    "iso:country":"IN",
    "name:ben_x_preferred":[
        "\u0995\u09be\u09a8\u09cd\u09a4\u09bf"
    ],
    "name:bpy_x_preferred":[
        "\u0995\u09be\u09a8\u09cd\u09a4\u09bf"
    ],
    "name:ita_x_preferred":[
        "Kanti"
    ],
    "name:msa_x_preferred":[
        "Kanti"
    ],
    "name:new_x_preferred":[
        "\u0915\u093e\u0928\u094d\u0924\u0940"
    ],
    "name:nld_x_preferred":[
        "Kanti"
    ],
    "name:por_x_preferred":[
        "Kanti"
    ],
    "name:spa_x_preferred":[
        "Kanti"
    ],
    "name:vie_x_preferred":[
        "Kanti"
    ],
    "wof:name":"Kanti",
    "wof:placetype":"locality"
},
  "geometry": {"coordinates":[80.96188000000002,25.36664],"type":"Point"}
}