{
  "type": "Feature",
  "properties": {
    "gn:admin1_code":"19",
    "gn:admin2_code":"569.0",
    "gn:asciiname":"Kundabarandadi",
    "gn:country_code":"IN",
    "gn:dem":16,
    "gn:feature_class":"P",
    "gn:feature_code":"PPLL",
    "gn:name":"Kundab\u0101rand\u0101di",
    "gn:population":0,
    "gn:timezone":"Asia/Kolkata",
    "iso:country":"IN",
    "ks:ks_alt_nam":"Kundab\u0101rand\u0101di",
    "ks:ks_name":"Kundabarandadi",
    "ks:ks_pop":1538,
    "ks:ks_type":"VILLAGE",
    "name:eng_x_preferred":[
        "Kundabarandadi"
    ],
    "name:eng_x_variant":[
        "Kundab\u0101rand\u0101di"
    ],
    "wof:name":"Kundabarandadi",
    "wof:placetype":"locality",
    "wof:population":1538
},
  "geometry": {"coordinates":[74.720597,13.713407],"type":"Point"}
}