{
  "type": "Feature",
  "properties": {
    "iso:country":"IN",
    "ks:ks_name":"Pushpali M.V.103",
    "ks:ks_pop":435,
    "ks:ks_type":"VILLAGE",
    "name:eng_x_preferred":[
        "Pushpali M.V.103"
    ],
    "wof:name":"Pushpali M.V.103",
    "wof:placetype":"locality",
    "wof:population":435
},
  "geometry": {"coordinates":[82.027998,18.303878],"type":"Point"}
}