{
  "type": "Feature",
  "properties": {
    "gn:admin1_code":"38.0",
    "gn:admin2_code":"352.0",
    "gn:asciiname":"Junatola",
    "gn:country_code":"IN",
    "gn:dem":181,
    "gn:feature_class":"P",
    "gn:feature_code":"PPL",
    "gn:name":"Jun\u0101tola",
    "gn:population":0,
    "gn:timezone":"Asia/Kolkata",
    "iso:country":"IN",
    "ks:ks_alt_nam":"Jun\u0101tola",
    "ks:ks_name":"Junatola",
    "ks:ks_pop":93,
    "ks:ks_type":"VILLAGE",
    "name:eng_x_preferred":[
        "Junatola"
    ],
    "name:eng_x_variant":[
        "Jun\u0101tola"
    ],
    "wof:name":"Junatola",
    "wof:placetype":"locality",
    "wof:population":93
},
  "geometry": {"coordinates":[87.698553,25.116452],"type":"Point"}
}