{
  "type": "Feature",
  "properties": {
    "iso:country":"IN",
    "ks:ks_name":"Pacchim Jira",
    "ks:ks_pop":77,
    "ks:ks_type":"HABITATION",
    "name:eng_x_preferred":[
        "Pacchim Jira"
    ],
    "wof:name":"Pacchim Jira",
    "wof:placetype":"locality",
    "wof:population":77
},
  "geometry": {"coordinates":[90.627092,25.986176],"type":"Point"}
}