{
  "type": "Feature",
  "properties": {
    "gn:admin1_code":"35.0",
    "gn:admin2_code":"429.0",
    "gn:asciiname":"Bigdari",
    "gn:country_code":"IN",
    "gn:dem":385,
    "gn:feature_class":"P",
    "gn:feature_code":"PPL",
    "gn:name":"Bigdar\u012b",
    "gn:population":0,
    "gn:timezone":"Asia/Kolkata",
    "iso:country":"IN",
    "ks:ks_alt_nam":"Bigdar\u012b",
    "ks:ks_name":"Bigdari",
    "ks:ks_pop":0,
    "ks:ks_type":"VILLAGE",
    "name:eng_x_preferred":[
        "Bigdari"
    ],
    "name:eng_x_variant":[
        "Bigdar\u012b"
    ],
    "wof:name":"Bigdari",
    "wof:placetype":"locality",
    "wof:population":0
},
  "geometry": {"coordinates":[80.568223,25.009431],"type":"Point"}
}