{
  "type": "Feature",
  "properties": {
    "iso:country":"IN",
    "ks:ks_alt_nam":"anachal",
    "ks:ks_name":"Anachal",
    "ks:ks_pop":438,
    "ks:ks_type":"HABITATION",
    "name:eng_x_preferred":[
        "Anachal"
    ],
    "wof:name":"Anachal",
    "wof:placetype":"locality",
    "wof:population":438
},
  "geometry": {"coordinates":[77.081113,9.973858],"type":"Point"}
}