{
  "type": "Feature",
  "properties": {
    "gn:admin1_code":"19.0",
    "gn:admin2_code":"582.0",
    "gn:asciiname":"Ragimakulapalli",
    "gn:country_code":"IN",
    "gn:dem":789,
    "gn:feature_class":"P",
    "gn:feature_code":"PPL",
    "gn:name":"R\u0101gim\u0101kulapalli",
    "gn:population":0,
    "gn:timezone":"Asia/Kolkata",
    "iso:country":"IN",
    "wof:name":"Ragimakulapalli",
    "wof:placetype":"locality"
},
  "geometry": {"coordinates":[77.88630999999999,13.7746],"type":"Point"}
}