{
  "type": "Feature",
  "properties": {
    "iso:country":"IN",
    "ks:ks_name":"Sadanandapur",
    "ks:ks_pop":160,
    "ks:ks_type":"VILLAGE",
    "ks:ks_uagg_main":0,
    "name:eng_x_preferred":[
        "Sadanandapur"
    ],
    "wof:name":"Sadanandapur",
    "wof:placetype":"neighbourhood",
    "wof:population":160
},
  "geometry": {"coordinates":[85.74704199999999,21.361957],"type":"Point"}
}