{
  "type": "Feature",
  "properties": {
    "gn:admin1_code":"12.0",
    "gn:admin2_code":"6.0",
    "gn:asciiname":"Gaja Draman",
    "gn:country_code":"IN",
    "gn:dem":2220,
    "gn:feature_class":"P",
    "gn:feature_code":"PPL",
    "gn:name":"Gaj\u0101 Draman",
    "gn:population":0,
    "gn:timezone":"Asia/Kolkata",
    "iso:country":"IN",
    "wof:name":"Gaja Draman",
    "wof:placetype":"locality"
},
  "geometry": {"coordinates":[74.63819000000002,33.31844],"type":"Point"}
}