{
  "type": "Feature",
  "properties": {
    "iso:country":"IN",
    "ks:ks_name":"Thakur Ram Purwa",
    "ks:ks_pop":104,
    "ks:ks_type":"HABITATION",
    "name:eng_x_preferred":[
        "Thakur Ram Purwa"
    ],
    "wof:name":"Thakur Ram Purwa",
    "wof:placetype":"locality",
    "wof:population":104
},
  "geometry": {"coordinates":[81.869917,27.199267],"type":"Point"}
}