{
  "type": "Feature",
  "properties": {
    "iso:country":"IN",
    "ks:ks_name":"Chndivdewadi",
    "ks:ks_pop":103,
    "ks:ks_type":"HABITATION",
    "name:eng_x_preferred":[
        "Chndivdewadi"
    ],
    "wof:name":"Chndivdewadi",
    "wof:placetype":"locality",
    "wof:population":103
},
  "geometry": {"coordinates":[73.443611,17.559167],"type":"Point"}
}