{
  "type": "Feature",
  "properties": {
    "iso:country":"IN",
    "ks:ks_name":"Sundarpur Babhnauli",
    "ks:ks_pop":3137,
    "ks:ks_type":"VILLAGE",
    "name:eng_x_preferred":[
        "Sundarpur Babhnauli"
    ],
    "wof:name":"Sundarpur Babhnauli",
    "wof:placetype":"locality",
    "wof:population":3137
},
  "geometry": {"coordinates":[84.99719899999999,26.731491],"type":"Point"}
}