{
  "type": "Feature",
  "properties": {
    "iso:country":"IN",
    "ks:ks_name":"Raisar",
    "ks:ks_pop":3752,
    "ks:ks_type":"VILLAGE",
    "name:eng_x_preferred":[
        "Raisar"
    ],
    "wof:name":"Raisar",
    "wof:placetype":"locality",
    "wof:population":3752
},
  "geometry": {"coordinates":[72.31545,26.482061],"type":"Point"}
}