{
  "type": "Feature",
  "properties": {
    "iso:country":"IN",
    "ks:ks_name":"Sawantwadi",
    "ks:ks_pop":75,
    "ks:ks_type":"HABITATION",
    "name:eng_x_preferred":[
        "Sawantwadi"
    ],
    "wof:name":"Sawantwadi",
    "wof:placetype":"locality",
    "wof:population":75
},
  "geometry": {"coordinates":[73.511692,17.012167],"type":"Point"}
}