{
  "type": "Feature",
  "properties": {
    "iso:country":"IN",
    "ks:ks_name":"Pegdapalli",
    "ks:ks_pop":555,
    "ks:ks_type":"VILLAGE",
    "name:eng_x_preferred":[
        "Pegdapalli"
    ],
    "wof:name":"Pegdapalli",
    "wof:placetype":"locality",
    "wof:population":555
},
  "geometry": {"coordinates":[80.93158099999999,18.519686],"type":"Point"}
}