{
  "type": "Feature",
  "properties": {
    "iso:country":"IN",
    "ks:ks_name":"Bautiberena",
    "ks:ks_pop":220,
    "ks:ks_type":"HABITATION",
    "name:eng_x_preferred":[
        "Bautiberena"
    ],
    "wof:name":"Bautiberena",
    "wof:placetype":"locality",
    "wof:population":220
},
  "geometry": {"coordinates":[85.68421499999999,20.668329],"type":"Point"}
}