{
  "type": "Feature",
  "properties": {
    "iso:country":"IN",
    "ks:ks_name":"Teraval",
    "ks:ks_pop":106,
    "ks:ks_type":"HABITATION",
    "name:eng_x_preferred":[
        "Teraval"
    ],
    "wof:name":"Teraval",
    "wof:placetype":"locality",
    "wof:population":106
},
  "geometry": {"coordinates":[73.50726299999999,15.975636],"type":"Point"}
}