{
  "type": "Feature",
  "properties": {
    "gn:admin1_code":"35",
    "gn:admin2_code":"425.0",
    "gn:asciiname":"Udaipur",
    "gn:country_code":"IN",
    "gn:dem":161,
    "gn:feature_class":"P",
    "gn:feature_code":"PPL",
    "gn:name":"Udaipur",
    "gn:population":0,
    "gn:timezone":"Asia/Kolkata",
    "iso:country":"IN",
    "wof:name":"Udaipur",
    "wof:placetype":"locality"
},
  "geometry": {"coordinates":[80.20498000000001,25.13434],"type":"Point"}
}