{
  "type": "Feature",
  "properties": {
    "iso:country":"IN",
    "ks:ks_name":"Dakshin Ambarishnagar",
    "ks:ks_pop":405,
    "ks:ks_type":"HABITATION",
    "name:eng_x_preferred":[
        "Dakshin Ambarishnagar"
    ],
    "wof:name":"Dakshin Ambarishnagar",
    "wof:placetype":"locality",
    "wof:population":405
},
  "geometry": {"coordinates":[91.700694,26.736548],"type":"Point"}
}