{
  "type": "Feature",
  "properties": {
    "iso:country":"IN",
    "ks:ks_alt_nam":"PARACHANI GAON",
    "ks:ks_name":"Parachani Gaon",
    "ks:ks_pop":99,
    "ks:ks_type":"HABITATION",
    "name:eng_x_preferred":[
        "Parachani Gaon"
    ],
    "wof:name":"Parachani Gaon",
    "wof:placetype":"locality",
    "wof:population":99
},
  "geometry": {"coordinates":[94.87323600000001,27.091783],"type":"Point"}
}