{
  "type": "Feature",
  "properties": {
    "iso:country":"IN",
    "ks:ks_name":"Debipatanpur",
    "ks:ks_pop":0,
    "ks:ks_type":"VILLAGE",
    "name:eng_x_preferred":[
        "Debipatanpur"
    ],
    "wof:name":"Debipatanpur",
    "wof:placetype":"locality",
    "wof:population":0
},
  "geometry": {"coordinates":[84.975695,21.088738],"type":"Point"}
}