{
  "type": "Feature",
  "properties": {
    "iso:country":"IN",
    "ks:ks_name":"Dimwadi",
    "ks:ks_pop":108,
    "ks:ks_type":"HABITATION",
    "name:eng_x_preferred":[
        "Dimwadi"
    ],
    "wof:name":"Dimwadi",
    "wof:placetype":"locality",
    "wof:population":108
},
  "geometry": {"coordinates":[73.59097,15.916081],"type":"Point"}
}