{
  "type": "Feature",
  "properties": {
    "iso:country":"IN",
    "ks:ks_alt_nam":"Dara gaon 2",
    "ks:ks_name":"Dara Gaon 2",
    "ks:ks_pop":886,
    "ks:ks_type":"HABITATION",
    "name:eng_x_preferred":[
        "Dara Gaon 2"
    ],
    "wof:name":"Dara Gaon 2",
    "wof:placetype":"locality",
    "wof:population":886
},
  "geometry": {"coordinates":[88.216398,26.994829],"type":"Point"}
}