{
  "type": "Feature",
  "properties": {
    "iso:country":"IN",
    "ks:ks_name":"Thevarinakoppa",
    "ks:ks_pop":36,
    "ks:ks_type":"HABITATION",
    "name:eng_x_preferred":[
        "Thevarinakoppa"
    ],
    "wof:name":"Thevarinakoppa",
    "wof:placetype":"locality",
    "wof:population":36
},
  "geometry": {"coordinates":[74.992963,14.083458],"type":"Point"}
}