{
  "type": "Feature",
  "properties": {
    "iso:country":"IN",
    "ks:ks_name":"Tetariya Tanr",
    "ks:ks_pop":150,
    "ks:ks_type":"HABITATION",
    "name:eng_x_preferred":[
        "Tetariya Tanr"
    ],
    "wof:name":"Tetariya Tanr",
    "wof:placetype":"locality",
    "wof:population":150
},
  "geometry": {"coordinates":[85.86487099999999,23.836685],"type":"Point"}
}