{
  "type": "Feature",
  "properties": {
    "iso:country":"IN",
    "ks:ks_name":"Bamuri Unmukt",
    "ks:ks_pop":129,
    "ks:ks_type":"VILLAGE",
    "name:eng_x_preferred":[
        "Bamuri Unmukt"
    ],
    "wof:name":"Bamuri Unmukt",
    "wof:placetype":"locality",
    "wof:population":129
},
  "geometry": {"coordinates":[82.22390300000001,24.567203],"type":"Point"}
}