{
  "type": "Feature",
  "properties": {
    "gn:admin1_code":"24.0",
    "gn:admin2_code":"107.0",
    "gn:asciiname":"Salimpur",
    "gn:country_code":"IN",
    "gn:dem":222,
    "gn:feature_class":"P",
    "gn:feature_code":"PPL",
    "gn:name":"Sal\u012bmpur",
    "gn:population":0,
    "gn:timezone":"Asia/Kolkata",
    "iso:country":"IN",
    "name:ara_x_preferred":[
        "\u0633\u0627\u0644\u0645 \u0628\u0648\u0631"
    ],
    "name:ben_bn_x_preferred":[
        "\u09b8\u09b2\u09bf\u09ae\u09aa\u09c1\u09b0"
    ],
    "name:ben_in_x_preferred":[
        "\u09b8\u09b2\u09bf\u09ae\u09aa\u09c1\u09b0"
    ],
    "name:guj_x_preferred":[
        "\u0ab8\u0abe\u0ab2\u0abf\u0aae\u0abe\u0ab0"
    ],
    "name:hin_x_preferred":[
        "\u0938\u0932\u0940\u092e\u092a\u0941\u0930"
    ],
    "name:kan_x_preferred":[
        "\u0cb8\u0cb2\u0cc0\u0cae\u0ccd"
    ],
    "name:mal_x_preferred":[
        "\u0d38\u0d32\u0d3f\u0d02\u0d2a\u0d42\u0d7c"
    ],
    "name:mar_x_preferred":[
        "\u0938\u0932\u0940\u092e\u092a\u0942\u0930"
    ],
    "name:pan_x_preferred":[
        "\u0a38\u0a32\u0a40\u0a2e\u0a2a\u0a41\u0a30"
    ],
    "name:tam_x_preferred":[
        "\u0b9a\u0bb2\u0bc0\u0bae\u0bcd\u0baa\u0bc2\u0bb0\u0bcd"
    ],
    "name:tel_x_preferred":[
        "\u0c38\u0c32\u0c3f\u0c02\u0c2a\u0c42\u0c30\u0c4d"
    ],
    "name:urd_x_preferred":[
        "\u0633\u0644\u06cc\u0645 \u067e\u0648\u0631"
    ],
    "wof:name":"Salimpur",
    "wof:placetype":"locality"
},
  "geometry": {"coordinates":[76.92052,26.81512],"type":"Point"}
}