{
  "type": "Feature",
  "properties": {
    "iso:country":"IN",
    "ks:ks_name":"Ganakghuli",
    "ks:ks_pop":102,
    "ks:ks_type":"VILLAGE",
    "name:eng_x_preferred":[
        "Ganakghuli"
    ],
    "wof:name":"Ganakghuli",
    "wof:placetype":"locality",
    "wof:population":102
},
  "geometry": {"coordinates":[90.516727,26.284197],"type":"Point"}
}