{
  "type": "Feature",
  "properties": {
    "gn:admin1_code":"35",
    "gn:admin2_code":"447.0",
    "gn:asciiname":"Bhojidhana",
    "gn:country_code":"IN",
    "gn:dem":760,
    "gn:feature_class":"P",
    "gn:feature_code":"PPL",
    "gn:name":"Bhoj\u012bdh\u0101na",
    "gn:population":0,
    "gn:timezone":"Asia/Kolkata",
    "iso:country":"IN",
    "wof:name":"Bhojidhana",
    "wof:placetype":"locality"
},
  "geometry": {"coordinates":[77.78008,21.53042],"type":"Point"}
}