{
  "type": "Feature",
  "properties": {
    "gn:admin1_code":"36.0",
    "gn:admin2_code":"179.0",
    "gn:asciiname":"Jalali",
    "gn:country_code":"IN",
    "gn:dem":112,
    "gn:feature_class":"P",
    "gn:feature_code":"PPL",
    "gn:name":"Jal\u0101li",
    "gn:population":0,
    "gn:timezone":"Asia/Kolkata",
    "iso:country":"IN",
    "name:deu_x_preferred":[
        "Jalali"
    ],
    "name:fas_x_preferred":[
        "\u062c\u0644\u0627\u0644\u06cc"
    ],
    "name:rus_x_preferred":[
        "\u0414\u0436\u0430\u043b\u0430\u043b\u0438"
    ],
    "wof:name":"Jalali",
    "wof:placetype":"locality"
},
  "geometry": {"coordinates":[81.63013000000002,26.53477],"type":"Point"}
}