{
  "type": "Feature",
  "properties": {
    "iso:country":"IN",
    "ks:ks_name":"Baniyane",
    "ks:ks_pop":1496,
    "ks:ks_type":"VILLAGE",
    "ks:ks_uagg_main":0,
    "name:eng_x_preferred":[
        "Baniyane"
    ],
    "wof:name":"Baniyane",
    "wof:placetype":"neighbourhood",
    "wof:population":1496
},
  "geometry": {"coordinates":[82.756266,26.491347],"type":"Point"}
}