{
  "type": "Feature",
  "properties": {
    "iso:country":"IN",
    "ks:ks_name":"Rawatpara",
    "ks:ks_pop":271,
    "ks:ks_type":"HABITATION",
    "name:eng_x_preferred":[
        "Rawatpara"
    ],
    "wof:name":"Rawatpara",
    "wof:placetype":"locality",
    "wof:population":271
},
  "geometry": {"coordinates":[81.770093,19.751074],"type":"Point"}
}