{
  "type": "Feature",
  "properties": {
    "gn:admin1_code":"9.0",
    "gn:admin2_code":"483.0",
    "gn:asciiname":"Kasuri",
    "gn:country_code":"IN",
    "gn:dem":111,
    "gn:feature_class":"P",
    "gn:feature_code":"PPL",
    "gn:name":"K\u0101suri",
    "gn:population":0,
    "gn:timezone":"Asia/Kolkata",
    "iso:country":"IN",
    "name:ara_x_preferred":[
        "\u0643\u0627\u0633\u0648\u0631\u064a"
    ],
    "name:fra_x_preferred":[
        "Kasuri"
    ],
    "wof:name":"Kasuri",
    "wof:placetype":"locality"
},
  "geometry": {"coordinates":[73.47523000000002,23.21633],"type":"Point"}
}