{
  "type": "Feature",
  "properties": {
    "iso:country":"IN",
    "ks:ks_name":"Senapatibar",
    "ks:ks_pop":208,
    "ks:ks_type":"VILLAGE",
    "ks:ks_uagg_main":0,
    "name:eng_x_preferred":[
        "Senapatibar"
    ],
    "wof:name":"Senapatibar",
    "wof:placetype":"neighbourhood",
    "wof:population":208
},
  "geometry": {"coordinates":[87.632397,21.753418],"type":"Point"}
}