{
  "type": "Feature",
  "properties": {
    "iso:country":"IN",
    "ks:ks_name":"Siyagon Ki Dhani",
    "ks:ks_pop":1048,
    "ks:ks_type":"VILLAGE",
    "name:eng_x_preferred":[
        "Siyagon Ki Dhani"
    ],
    "wof:name":"Siyagon Ki Dhani",
    "wof:placetype":"locality",
    "wof:population":1048
},
  "geometry": {"coordinates":[73.48283600000001,27.069214],"type":"Point"}
}