{
  "type": "Feature",
  "properties": {
    "gn:admin1_code":"36.0",
    "gn:admin2_code":"175.0",
    "gn:asciiname":"Bastar",
    "gn:country_code":"IN",
    "gn:dem":96,
    "gn:feature_class":"P",
    "gn:feature_code":"PPL",
    "gn:name":"Bastar",
    "gn:population":0,
    "gn:timezone":"Asia/Kolkata",
    "iso:country":"IN",
    "ks:ks_name":"Bastar",
    "ks:ks_pop":619,
    "ks:ks_type":"VILLAGE",
    "ks:ks_uagg_main":0,
    "name:ara_x_preferred":[
        "\u0628\u0627\u0633\u062a\u0627\u0631"
    ],
    "name:ben_bn_x_preferred":[
        "\u09ac\u09be\u09b8\u09cd\u09a4\u09be\u09b0"
    ],
    "name:ben_in_x_preferred":[
        "\u09ac\u09be\u09b8\u09cd\u09a4\u09be\u09b0"
    ],
    "name:deu_x_preferred":[
        "Bastar"
    ],
    "name:eng_x_preferred":[
        "Bastar"
    ],
    "name:guj_x_preferred":[
        "\u0aac\u0ab8\u0acd\u0aa4\u0ab0"
    ],
    "name:hin_x_preferred":[
        "\u092c\u0938\u094d\u0924\u0930"
    ],
    "name:kan_x_preferred":[
        "\u0cac\u0cb8\u0ccd\u0ca4\u0cbe\u0cb0\u0ccd"
    ],
    "name:mal_x_preferred":[
        "\u0d2c\u0d38\u0d4d\u0d24\u0d7c"
    ],
    "name:mar_x_preferred":[
        "\u092c\u0938\u094d\u0924\u0930"
    ],
    "name:nep_x_preferred":[
        "\u092c\u0938\u094d\u0924\u0930"
    ],
    "name:nld_x_preferred":[
        "Bastar"
    ],
    "name:pan_x_preferred":[
        "\u0a2c\u0a38\u0a24\u0a30"
    ],
    "name:pli_x_preferred":[
        "\u092c\u0938\u094d\u0924\u0930"
    ],
    "name:tam_x_preferred":[
        "\u0baa\u0bb8\u0bcd\u0ba4\u0bb0\u0bcd"
    ],
    "name:tel_x_preferred":[
        "\u0c2c\u0c38\u0c4d\u0c24\u0c30\u0c4d"
    ],
    "name:urd_x_preferred":[
        "\u0628\u0633\u062a\u0631"
    ],
    "wof:name":"Bastar",
    "wof:placetype":"neighbourhood",
    "wof:population":619
},
  "geometry": {"coordinates":[81.98826099999999,25.255379],"type":"Point"}
}