{
  "type": "Feature",
  "properties": {
    "iso:country":"IN",
    "ks:ks_name":"Injani",
    "ks:ks_pop":907,
    "ks:ks_type":"VILLAGE",
    "name:eng_x_preferred":[
        "Injani"
    ],
    "wof:name":"Injani",
    "wof:placetype":"locality",
    "wof:population":907
},
  "geometry": {"coordinates":[82.83344,23.678385],"type":"Point"}
}