{
  "type": "Feature",
  "properties": {
    "iso:country":"IN",
    "name:ara_x_preferred":[
        "\u0628\u0627\u0643\u064a\u0627\u0628\u0648\u0631\u0627\u0645"
    ],
    "name:ben_bn_x_preferred":[
        "\u09aa\u09be\u0995\u09bf\u09df\u09be\u09aa\u09c1\u09b0\u09ae"
    ],
    "name:ben_in_x_preferred":[
        "\u09aa\u09be\u0995\u09bf\u09df\u09be\u09aa\u09c1\u09b0\u09ae"
    ],
    "name:eng_x_preferred":[
        "Packiyapuram"
    ],
    "name:guj_x_preferred":[
        "\u0aaa\u0ac7\u0a95\u0abf\u0aaf\u0abe\u0aaa\u0ac1\u0ab0\u0aae"
    ],
    "name:hin_x_preferred":[
        "\u092a\u0915\u093f\u092f\u093e\u092a\u0941\u0930\u092e"
    ],
    "name:kan_x_preferred":[
        "\u0caa\u0c95\u0cbf\u0caf\u0cbe\u0caa\u0cc1\u0cb0\u0cae\u0ccd"
    ],
    "name:mal_x_preferred":[
        "\u0d2a\u0d3e\u0d15\u0d4d\u0d15\u0d3f\u0d2f\u0d2a\u0d41\u0d30\u0d02"
    ],
    "name:mar_x_preferred":[
        "\u092a\u0945\u0915\u093f\u092f\u093e\u092a\u0941\u0930\u092e"
    ],
    "name:pan_x_preferred":[
        "\u0a2a\u0a48\u0a15\u0a40\u0a06\u0a2a\u0a41\u0a30\u0a2e"
    ],
    "name:tam_x_preferred":[
        "\u0baa\u0bbe\u0b95\u0bcd\u0b95\u0bbf\u0baf\u0baa\u0bc1\u0bb0\u0bae\u0bcd"
    ],
    "name:tel_x_preferred":[
        "\u0c2a\u0c3e\u0c15\u0c3f\u0c2f\u0c3e\u0c2a\u0c41\u0c30\u0c02"
    ],
    "name:urd_x_preferred":[
        "\u067e\u06a9\u06cc\u0627 \u067e\u0648\u0631\u0645"
    ],
    "qs:gn_adm0_cc":"IN",
    "qs:gn_local":1266425,
    "qs:gn_nam_loc":"kodaikanal",
    "qs:gn_namadm1":"25",
    "qs:local_max":394,
    "qs:local_sum":535,
    "qs:localhoods":3,
    "qs:name":"Packiyapuram",
    "qs:name_adm0":"India",
    "qs:name_adm1":"Tamil Nadu",
    "qs:name_adm2":"Dindigul",
    "qs:name_local":"Kodaikanal",
    "qs:photo_max":33,
    "qs:photo_sum":60,
    "qs:placetype":"Suburb",
    "qs:quad_count":3,
    "qs:woe_adm0":23424848,
    "qs:woe_adm1":2345758,
    "qs:woe_adm2":12586681,
    "qs:woe_lau":0,
    "qs:woe_local":2294589,
    "qs:woe_ver":"7.10.0",
    "wof:lang":[
        "eng"
    ],
    "wof:name":"Packiyapuram",
    "wof:placetype":"neighbourhood"
},
  "geometry": {"coordinates":[77.491653,10.246907],"type":"Point"}
}