{
  "type": "Feature",
  "properties": {
    "iso:country":"IN",
    "name:eng_x_preferred":[
        "Packiyapuram"
    ],
    "name:unk_x_variant":[
        "Packiyapuram"
    ],
    "qs:gn_adm0_cc":"IN",
    "qs:gn_local":1266425,
    "qs:gn_nam_loc":"kodaikanal",
    "qs:gn_namadm1":"25",
    "qs:local_max":394,
    "qs:local_sum":535,
    "qs:localhoods":3,
    "qs:name":"Packiyapuram",
    "qs:name_adm0":"India",
    "qs:name_adm1":"Tamil Nadu",
    "qs:name_adm2":"Dindigul",
    "qs:name_local":"Kodaikanal",
    "qs:photo_max":33,
    "qs:photo_sum":60,
    "qs:placetype":"Suburb",
    "qs:quad_count":3,
    "qs:woe_adm0":23424848,
    "qs:woe_adm1":2345758,
    "qs:woe_adm2":12586681,
    "qs:woe_lau":0,
    "qs:woe_local":2294589,
    "qs:woe_ver":"7.10.0",
    "wof:lang":[
        "eng"
    ],
    "wof:name":"Packiyapuram",
    "wof:placetype":"neighbourhood"
},
  "geometry": {"coordinates":[77.491653,10.246907],"type":"Point"}
}