{
  "type": "Feature",
  "properties": {
    "gn:admin1_code":"36",
    "gn:admin2_code":"145.0",
    "gn:asciiname":"Goga",
    "gn:country_code":"IN",
    "gn:dem":179,
    "gn:feature_class":"P",
    "gn:feature_code":"PPL",
    "gn:name":"Goga",
    "gn:population":0,
    "gn:timezone":"Asia/Kolkata",
    "iso:country":"IN",
    "name:ceb_x_preferred":[
        "Goga"
    ],
    "name:deu_x_preferred":[
        "Goga"
    ],
    "name:fra_x_preferred":[
        "Goga"
    ],
    "name:pol_x_preferred":[
        "Goga"
    ],
    "name:ron_x_preferred":[
        "Goga"
    ],
    "name:slv_x_preferred":[
        "Goga"
    ],
    "name:swe_x_preferred":[
        "Goga"
    ],
    "wof:name":"Goga",
    "wof:placetype":"locality"
},
  "geometry": {"coordinates":[77.77741999999998,27.5549],"type":"Point"}
}