{
  "type": "Feature",
  "properties": {
    "iso:country":"IN",
    "ks:ks_name":"Kharauna Urf Misraulia",
    "ks:ks_pop":1181,
    "ks:ks_type":"VILLAGE",
    "name:eng_x_preferred":[
        "Kharauna Urf Misraulia"
    ],
    "wof:name":"Kharauna Urf Misraulia",
    "wof:placetype":"locality",
    "wof:population":1181
},
  "geometry": {"coordinates":[85.176284,25.888853],"type":"Point"}
}