{
  "type": "Feature",
  "properties": {
    "iso:country":"IN",
    "ks:ks_name":"Mahajanpara",
    "ks:ks_pop":920,
    "ks:ks_type":"VILLAGE",
    "name:eng_x_preferred":[
        "Mahajanpara"
    ],
    "wof:name":"Mahajanpara",
    "wof:placetype":"locality",
    "wof:population":920
},
  "geometry": {"coordinates":[90.244207,26.329238],"type":"Point"}
}