{
  "type": "Feature",
  "properties": {
    "gn:admin1_code":"21.0",
    "gn:admin2_code":"395",
    "gn:asciiname":"Kasurupara",
    "gn:country_code":"IN",
    "gn:dem":188,
    "gn:feature_class":"P",
    "gn:feature_code":"PPL",
    "gn:name":"Kasurup\u0101ra",
    "gn:population":0,
    "gn:timezone":"Asia/Kolkata",
    "iso:country":"IN",
    "wof:name":"Kasurupara",
    "wof:placetype":"locality"
},
  "geometry": {"coordinates":[83.26666999999998,20.25],"type":"Point"}
}