{
  "type": "Feature",
  "properties": {
    "gn:admin1_code":"23.0",
    "gn:admin2_code":"53.0",
    "gn:asciiname":"Kanai",
    "gn:country_code":"IN",
    "gn:dem":238,
    "gn:feature_class":"P",
    "gn:feature_code":"PPL",
    "gn:name":"Kanai",
    "gn:population":0,
    "gn:timezone":"Asia/Kolkata",
    "iso:country":"IN",
    "name:deu_x_preferred":[
        "Kanai"
    ],
    "name:rus_x_preferred":[
        "\u041a\u0430\u043d\u0430\u0438"
    ],
    "wof:name":"Kanai",
    "wof:placetype":"locality"
},
  "geometry": {"coordinates":[75.8557,30.19304],"type":"Point"}
}