{
  "type": "Feature",
  "properties": {
    "gn:admin1_code":"12.0",
    "gn:asciiname":"Balal",
    "gn:country_code":"IN",
    "gn:dem":928,
    "gn:feature_class":"P",
    "gn:feature_code":"PPL",
    "gn:name":"Bal\u0101l",
    "gn:population":0,
    "gn:timezone":"Asia/Kolkata",
    "iso:country":"IN",
    "wof:name":"Balal",
    "wof:placetype":"locality"
},
  "geometry": {"coordinates":[74.07772,33.19495999999999],"type":"Point"}
}