{
  "type": "Feature",
  "properties": {
    "gn:admin1_code":"36.0",
    "gn:admin2_code":"176.0",
    "gn:asciiname":"Rasulpur",
    "gn:country_code":"IN",
    "gn:dem":114,
    "gn:feature_class":"P",
    "gn:feature_code":"PPL",
    "gn:name":"Ras\u016blpur",
    "gn:population":0,
    "gn:timezone":"Asia/Kolkata",
    "iso:country":"IN",
    "ks:ks_alt_nam":"Ras\u016blpur",
    "ks:ks_name":"Rasulpur",
    "ks:ks_pop":1912,
    "ks:ks_type":"VILLAGE",
    "name:ara_x_preferred":[
        "\u0631\u0627\u0633\u064a\u0644\u0628\u0648\u0631"
    ],
    "name:ben_bn_x_preferred":[
        "\u09b0\u09b8\u09c1\u09b2\u09aa\u09c1\u09b0"
    ],
    "name:ben_in_x_preferred":[
        "\u09b0\u09b8\u09c1\u09b2\u09aa\u09c1\u09b0"
    ],
    "name:eng_x_preferred":[
        "Rasulpur"
    ],
    "name:eng_x_variant":[
        "Ras\u016blpur"
    ],
    "name:fas_x_preferred":[
        "\u0631\u0633\u0648\u0644\u200c\u067e\u0648\u0631"
    ],
    "name:guj_x_preferred":[
        "\u0ab0\u0ab8\u0ac1\u0ab2\u0aaa\u0ac1\u0ab0"
    ],
    "name:hin_x_preferred":[
        "\u0930\u0938\u0942\u0932\u092a\u0941\u0930"
    ],
    "name:kan_x_preferred":[
        "\u0cb0\u0cb8\u0cc2\u0cb2\u0ccd\u0caa\u0cc1\u0cb0"
    ],
    "name:mal_x_preferred":[
        "\u0d31\u0d38\u0d42\u0d7d\u0d2a\u0d42\u0d7c"
    ],
    "name:mar_x_preferred":[
        "\u0930\u0938\u0942\u0932\u092a\u0942\u0930"
    ],
    "name:pan_x_preferred":[
        "\u0a30\u0a38\u0a42\u0a32\u0a2a\u0a41\u0a30"
    ],
    "name:tam_x_preferred":[
        "\u0bb0\u0b9a\u0bc2\u0bb2\u0bcd\u0baa\u0bc2\u0bb0\u0bcd"
    ],
    "name:tel_x_preferred":[
        "\u0c30\u0c38\u0c42\u0c32\u0c4d"
    ],
    "name:urd_x_preferred":[
        "\u0631\u0633\u0648\u0644 \u067e\u0648\u0631"
    ],
    "name:urd_x_variant":[
        "\u0631\u0633\u0648\u0644\u067e\u0648\u0631"
    ],
    "wof:name":"Rasulpur",
    "wof:placetype":"locality",
    "wof:population":1912
},
  "geometry": {"coordinates":[81.57972599999999,26.731111],"type":"Point"}
}