{
  "type": "Feature",
  "properties": {
    "gn:admin1_code":"40",
    "gn:admin2_code":"538.0",
    "gn:asciiname":"Sompur",
    "gn:country_code":"IN",
    "gn:dem":344,
    "gn:feature_class":"P",
    "gn:feature_code":"PPL",
    "gn:name":"Sompur",
    "gn:population":0,
    "gn:timezone":"Asia/Kolkata",
    "iso:country":"IN",
    "wof:name":"Sompur",
    "wof:placetype":"locality"
},
  "geometry": {"coordinates":[77.70761999999998,16.25921],"type":"Point"}
}