{
  "type": "Feature",
  "properties": {
    "iso:country":"IN",
    "ks:ks_name":"Makhopur",
    "ks:ks_pop":314,
    "ks:ks_type":"HABITATION",
    "name:eng_x_preferred":[
        "Makhopur"
    ],
    "wof:name":"Makhopur",
    "wof:placetype":"locality",
    "wof:population":314
},
  "geometry": {"coordinates":[82.530295,25.022893],"type":"Point"}
}