{
  "type": "Feature",
  "properties": {
    "iso:country":"IN",
    "ks:ks_name":"Chak Khatundra",
    "ks:ks_pop":695,
    "ks:ks_type":"HABITATION",
    "name:eng_x_preferred":[
        "Chak Khatundra"
    ],
    "wof:name":"Chak Khatundra",
    "wof:placetype":"locality",
    "wof:population":695
},
  "geometry": {"coordinates":[75.494749,27.53738],"type":"Point"}
}