{
  "type": "Feature",
  "properties": {
    "iso:country":"IN",
    "ks:ks_name":"Sri Ballabhpur",
    "ks:ks_pop":678,
    "ks:ks_type":"VILLAGE",
    "ks:ks_uagg_main":0,
    "name:eng_x_preferred":[
        "Sri Ballabhpur"
    ],
    "wof:name":"Sri Ballabhpur",
    "wof:placetype":"neighbourhood",
    "wof:population":678
},
  "geometry": {"coordinates":[88.12408499999999,22.352582],"type":"Point"}
}