{
  "type": "Feature",
  "properties": {
    "gn:admin1_code":"24.0",
    "gn:admin2_code":"111.0",
    "gn:asciiname":"Sanjasar",
    "gn:country_code":"IN",
    "gn:dem":330,
    "gn:feature_class":"P",
    "gn:feature_code":"PPL",
    "gn:name":"S\u0101nj\u0101sar",
    "gn:population":0,
    "gn:timezone":"Asia/Kolkata",
    "iso:country":"IN",
    "wof:name":"Sanjasar",
    "wof:placetype":"locality"
},
  "geometry": {"coordinates":[75.00124,28.06206],"type":"Point"}
}