{
  "type": "Feature",
  "properties": {
    "iso:country":"IN",
    "ks:ks_name":"Rajakhana Amagaro",
    "ks:ks_pop":340,
    "ks:ks_type":"HABITATION",
    "ks:ks_uagg_main":0,
    "name:eng_x_preferred":[
        "Rajakhana Amagaro"
    ],
    "wof:name":"Rajakhana Amagaro",
    "wof:placetype":"neighbourhood",
    "wof:population":340
},
  "geometry": {"coordinates":[95.16985,27.801975],"type":"Point"}
}