{
  "type": "Feature",
  "properties": {
    "gn:admin1_code":"10.0",
    "gn:admin2_code":"85.0",
    "gn:asciiname":"Bhimnagar",
    "gn:country_code":"IN",
    "gn:dem":246,
    "gn:feature_class":"P",
    "gn:feature_code":"PPL",
    "gn:name":"Bh\u012bmnagar",
    "gn:population":0,
    "gn:timezone":"Asia/Kolkata",
    "iso:country":"IN",
    "wof:name":"Bhimnagar",
    "wof:placetype":"locality"
},
  "geometry": {"coordinates":[76.75279,28.15786],"type":"Point"}
}