{
  "type": "Feature",
  "properties": {
    "iso:country":"IN",
    "ks:ks_name":"Mohanacolony",
    "ks:ks_pop":125,
    "ks:ks_type":"HABITATION",
    "name:eng_x_preferred":[
        "Mohanacolony"
    ],
    "wof:name":"Mohanacolony",
    "wof:placetype":"locality",
    "wof:population":125
},
  "geometry": {"coordinates":[83.83440299999999,18.772084],"type":"Point"}
}