{
  "type": "Feature",
  "properties": {
    "iso:country":"IN",
    "ks:ks_name":"Barafpada",
    "ks:ks_pop":128,
    "ks:ks_type":"HABITATION",
    "name:eng_x_preferred":[
        "Barafpada"
    ],
    "wof:name":"Barafpada",
    "wof:placetype":"locality",
    "wof:population":128
},
  "geometry": {"coordinates":[73.01544199999999,19.820522],"type":"Point"}
}