{
  "type": "Feature",
  "properties": {
    "iso:country":"IN",
    "ks:ks_name":"11 JRK",
    "ks:ks_pop":237,
    "ks:ks_type":"VILLAGE",
    "ks:ks_uagg_main":0,
    "name:eng_x_preferred":[
        "11 JRK"
    ],
    "wof:name":"11 JRK",
    "wof:placetype":"neighbourhood",
    "wof:population":237
},
  "geometry": {"coordinates":[74.187472,29.612672],"type":"Point"}
}