{
  "type": "Feature",
  "properties": {
    "iso:country":"IN",
    "ks:ks_name":"Kumarpara 3",
    "ks:ks_pop":582,
    "ks:ks_type":"HABITATION",
    "name:eng_x_preferred":[
        "Kumarpara 3"
    ],
    "wof:name":"Kumarpara 3",
    "wof:placetype":"locality",
    "wof:population":582
},
  "geometry": {"coordinates":[91.747018,26.330823],"type":"Point"}
}