{
  "type": "Feature",
  "properties": {
    "iso:country":"IN",
    "ks:ks_name":"Nimkata",
    "ks:ks_pop":66,
    "ks:ks_type":"VILLAGE",
    "name:eng_x_preferred":[
        "Nimkata"
    ],
    "wof:name":"Nimkata",
    "wof:placetype":"locality",
    "wof:population":66
},
  "geometry": {"coordinates":[87.178487,22.702114],"type":"Point"}
}