{
  "type": "Feature",
  "properties": {
    "gn:admin1_code":"11.0",
    "gn:admin2_code":"32.0",
    "gn:asciiname":"Shiya",
    "gn:country_code":"IN",
    "gn:dem":1588,
    "gn:feature_class":"P",
    "gn:feature_code":"PPL",
    "gn:name":"Shiya",
    "gn:population":0,
    "gn:timezone":"Asia/Kolkata",
    "iso:country":"IN",
    "wof:name":"Shiya",
    "wof:placetype":"locality"
},
  "geometry": {"coordinates":[77.46498000000003,30.74921],"type":"Point"}
}