{
  "type": "Feature",
  "properties": {
    "gn:admin1_code":"36",
    "gn:admin2_code":"195.0",
    "gn:asciiname":"Ahirauli",
    "gn:country_code":"IN",
    "gn:dem":80,
    "gn:feature_class":"P",
    "gn:feature_code":"PPL",
    "gn:name":"Ah\u012brauli",
    "gn:population":0,
    "gn:timezone":"Asia/Kolkata",
    "iso:country":"IN",
    "ks:ks_name":"Ahiroli",
    "ks:ks_pop":98,
    "ks:ks_type":"VILLAGE",
    "name:eng_x_preferred":[
        "Ahiroli"
    ],
    "name:eng_x_variant":[
        "Ahirauli"
    ],
    "wof:name":"Ahiroli",
    "wof:placetype":"locality",
    "wof:population":98
},
  "geometry": {"coordinates":[83.10933300000001,25.651486],"type":"Point"}
}