{
  "type": "Feature",
  "properties": {
    "iso:country":"IN",
    "name:bpy_x_preferred":[
        "\u09b6\u09cb\u09b2\u09cb\u09b0"
    ],
    "name:eng_x_preferred":[
        "Sholur"
    ],
    "name:fra_x_preferred":[
        "Sholur"
    ],
    "name:ita_x_preferred":[
        "Sholur"
    ],
    "name:mal_x_preferred":[
        "\u0d37\u0d4b\u0d33\u0d42\u0d7c"
    ],
    "name:msa_x_preferred":[
        "Sholur"
    ],
    "name:nan_x_preferred":[
        "Sholur"
    ],
    "name:nld_x_preferred":[
        "Sholur"
    ],
    "name:por_x_preferred":[
        "Sholur"
    ],
    "name:tam_x_preferred":[
        "\u0b9a\u0bcb\u0bb3\u0bc2\u0bb0\u0bcd"
    ],
    "name:vie_x_preferred":[
        "Sholur"
    ],
    "name:zho_x_preferred":[
        "\u65af\u970d\u5362\u5c14"
    ],
    "qs:name":"Sholur",
    "qs:name_adm0":"India",
    "qs:name_adm1":"Tamil Nadu",
    "qs:photos":134,
    "qs:photos_1k":27,
    "qs:photos_9k":1,
    "qs:photos_9r":3,
    "qs:photos_all":134,
    "qs:photos_sr":3,
    "qs:placetype":"Town",
    "qs:pop_sr":"0",
    "wd:wordcount":140,
    "wof:name":"Sholur",
    "wof:placetype":"locality"
},
  "geometry": {"coordinates":[76.650378,11.531245],"type":"Point"}
}