{
  "type": "Feature",
  "properties": {
    "gn:admin1_code":"24",
    "gn:admin2_code":"104.0",
    "gn:asciiname":"Pipli",
    "gn:country_code":"IN",
    "gn:dem":311,
    "gn:feature_class":"P",
    "gn:feature_code":"PPL",
    "gn:name":"Pipli",
    "gn:population":0,
    "gn:timezone":"Asia/Kolkata",
    "iso:country":"IN",
    "wof:name":"Pipli",
    "wof:placetype":"locality"
},
  "geometry": {"coordinates":[76.34076,27.96624000000001],"type":"Point"}
}