{
  "type": "Feature",
  "properties": {
    "iso:country":"IN",
    "ks:ks_name":"Thavasipatti",
    "ks:ks_pop":97,
    "ks:ks_type":"HABITATION",
    "name:eng_x_preferred":[
        "Thavasipatti"
    ],
    "wof:name":"Thavasipatti",
    "wof:placetype":"locality",
    "wof:population":97
},
  "geometry": {"coordinates":[78.08034600000001,10.668112],"type":"Point"}
}