{
  "type": "Feature",
  "properties": {
    "gn:admin1_code":"34.0",
    "gn:admin2_code":"204.0",
    "gn:asciiname":"Man Tola",
    "gn:country_code":"IN",
    "gn:dem":68,
    "gn:feature_class":"P",
    "gn:feature_code":"PPL",
    "gn:name":"M\u0101n Tola",
    "gn:population":0,
    "gn:timezone":"Asia/Kolkata",
    "iso:country":"IN",
    "ks:ks_alt_nam":"M\u0101n Tola",
    "ks:ks_name":"Man Tola",
    "ks:ks_pop":682,
    "ks:ks_type":"VILLAGE",
    "ks:ks_uagg_main":0,
    "name:eng_x_preferred":[
        "Man Tola"
    ],
    "name:eng_x_variant":[
        "M\u0101n Tola"
    ],
    "wof:name":"Man Tola",
    "wof:placetype":"neighbourhood",
    "wof:population":682
},
  "geometry": {"coordinates":[84.715619,26.469569],"type":"Point"}
}