{
  "type": "Feature",
  "properties": {
    "gn:admin1_code":"36.0",
    "gn:admin2_code":"183.0",
    "gn:asciiname":"Parsan Purwa",
    "gn:country_code":"IN",
    "gn:dem":111,
    "gn:feature_class":"P",
    "gn:feature_code":"PPL",
    "gn:name":"Parsan Purwa",
    "gn:population":0,
    "gn:timezone":"Asia/Kolkata",
    "iso:country":"IN",
    "ks:ks_name":"Parsauni Purwa",
    "ks:ks_pop":235,
    "ks:ks_type":"HABITATION",
    "name:eng_x_preferred":[
        "Parsauni Purwa"
    ],
    "name:eng_x_variant":[
        "Parsan Purwa"
    ],
    "wof:name":"Parsauni Purwa",
    "wof:placetype":"locality",
    "wof:population":235
},
  "geometry": {"coordinates":[81.71610200000001,27.253118],"type":"Point"}
}