{
  "type": "Feature",
  "properties": {
    "iso:country":"IN",
    "ks:ks_name":"Purkait Para",
    "ks:ks_pop":569,
    "ks:ks_type":"HABITATION",
    "name:eng_x_preferred":[
        "Purkait Para"
    ],
    "wof:name":"Purkait Para",
    "wof:placetype":"locality",
    "wof:population":569
},
  "geometry": {"coordinates":[88.348178,22.235061],"type":"Point"}
}