{
  "type": "Feature",
  "properties": {
    "iso:country":"IN",
    "ks:ks_name":"Karkamane",
    "ks:ks_pop":71,
    "ks:ks_type":"HABITATION",
    "name:eng_x_preferred":[
        "Karkamane"
    ],
    "wof:name":"Karkamane",
    "wof:placetype":"locality",
    "wof:population":71
},
  "geometry": {"coordinates":[74.47958199999999,15.053783],"type":"Point"}
}