{
  "type": "Feature",
  "properties": {
    "iso:country":"IN",
    "ks:ks_alt_nam":"Santhal tola",
    "ks:ks_name":"Santhal Tola",
    "ks:ks_pop":85,
    "ks:ks_type":"HABITATION",
    "name:eng_x_preferred":[
        "Santhal Tola"
    ],
    "wof:name":"Santhal Tola",
    "wof:placetype":"locality",
    "wof:population":85
},
  "geometry": {"coordinates":[86.85047,24.56322],"type":"Point"}
}