{
  "type": "Feature",
  "properties": {
    "iso:country":"IN",
    "ks:ks_name":"Rup Pur",
    "ks:ks_pop":335,
    "ks:ks_type":"HABITATION",
    "name:eng_x_preferred":[
        "Rup Pur"
    ],
    "wof:name":"Rup Pur",
    "wof:placetype":"locality",
    "wof:population":335
},
  "geometry": {"coordinates":[87.854078,24.853989],"type":"Point"}
}