{
  "type": "Feature",
  "properties": {
    "iso:country":"IN",
    "ks:ks_name":"Chawargaon",
    "ks:ks_pop":332,
    "ks:ks_type":"VILLAGE",
    "name:eng_x_preferred":[
        "Chawargaon"
    ],
    "wof:name":"Chawargaon",
    "wof:placetype":"locality",
    "wof:population":332
},
  "geometry": {"coordinates":[80.693051,20.294004],"type":"Point"}
}