{
  "type": "Feature",
  "properties": {
    "gn:admin1_code":"34.0",
    "gn:admin2_code":"217.0",
    "gn:asciiname":"Dumar Shukul",
    "gn:country_code":"IN",
    "gn:dem":78,
    "gn:feature_class":"P",
    "gn:feature_code":"PPL",
    "gn:name":"Dumar Shukul",
    "gn:population":0,
    "gn:timezone":"Asia/Kolkata",
    "iso:country":"IN",
    "ks:ks_name":"Dumar Shukul",
    "ks:ks_pop":1034,
    "ks:ks_type":"VILLAGE",
    "name:eng_x_preferred":[
        "Dumar Shukul"
    ],
    "wof:name":"Dumar Shukul",
    "wof:placetype":"locality",
    "wof:population":1034
},
  "geometry": {"coordinates":[84.127009,26.481573],"type":"Point"}
}