{
  "type": "Feature",
  "properties": {
    "gn:admin1_code":"36.0",
    "gn:admin2_code":"172.0",
    "gn:asciiname":"Ekaunagarh",
    "gn:country_code":"IN",
    "gn:dem":104,
    "gn:feature_class":"P",
    "gn:feature_code":"PPL",
    "gn:name":"Ekaun\u0101garh",
    "gn:population":0,
    "gn:timezone":"Asia/Kolkata",
    "iso:country":"IN",
    "wof:name":"Ekaunagarh",
    "wof:placetype":"locality"
},
  "geometry": {"coordinates":[81.32443000000001,25.81107],"type":"Point"}
}