{
  "type": "Feature",
  "properties": {
    "iso:country":"IN",
    "ks:ks_name":"Koley Pramanikpara",
    "ks:ks_pop":566,
    "ks:ks_type":"HABITATION",
    "name:eng_x_preferred":[
        "Koley Pramanikpara"
    ],
    "wof:name":"Koley Pramanikpara",
    "wof:placetype":"locality",
    "wof:population":566
},
  "geometry": {"coordinates":[87.948436,22.588334],"type":"Point"}
}