{
  "type": "Feature",
  "properties": {
    "gn:admin1_code":"11.0",
    "gn:admin2_code":"27.0",
    "gn:asciiname":"Kalthwal",
    "gn:country_code":"IN",
    "gn:dem":1366,
    "gn:feature_class":"P",
    "gn:feature_code":"PPL",
    "gn:name":"Kalthw\u0101l",
    "gn:population":0,
    "gn:timezone":"Asia/Kolkata",
    "iso:country":"IN",
    "wof:name":"Kalthwal",
    "wof:placetype":"locality"
},
  "geometry": {"coordinates":[77.03485000000001,31.60239],"type":"Point"}
}