{
  "type": "Feature",
  "properties": {
    "gn:admin1_code":"21.0",
    "gn:admin2_code":"396.0",
    "gn:asciiname":"Bondaguda",
    "gn:country_code":"IN",
    "gn:dem":387,
    "gn:feature_class":"P",
    "gn:feature_code":"PPL",
    "gn:name":"Bondaguda",
    "gn:population":0,
    "gn:timezone":"Asia/Kolkata",
    "iso:country":"IN",
    "wof:name":"Bondaguda",
    "wof:placetype":"locality"
},
  "geometry": {"coordinates":[83.49689000000002,19.4675],"type":"Point"}
}