{
  "type": "Feature",
  "properties": {
    "iso:country":"IN",
    "ks:ks_name":"Chhota Telopara",
    "ks:ks_pop":29,
    "ks:ks_type":"VILLAGE",
    "name:eng_x_preferred":[
        "Chhota Telopara"
    ],
    "wof:name":"Chhota Telopara",
    "wof:placetype":"locality",
    "wof:population":29
},
  "geometry": {"coordinates":[87.509198,24.660016],"type":"Point"}
}