{
  "type": "Feature",
  "properties": {
    "gn:admin1_code":"24.0",
    "gn:admin2_code":"100.0",
    "gn:asciiname":"Abdul Khan ki Dhani",
    "gn:country_code":"IN",
    "gn:dem":203,
    "gn:feature_class":"P",
    "gn:feature_code":"PPL",
    "gn:name":"Abdul Kh\u0101n ki Dh\u0101ni",
    "gn:population":0,
    "gn:timezone":"Asia/Kolkata",
    "iso:country":"IN",
    "wof:name":"Abdul Khan ki Dhani",
    "wof:placetype":"locality"
},
  "geometry": {"coordinates":[75.23054,29.12769],"type":"Point"}
}