{
  "type": "Feature",
  "properties": {
    "iso:country":"IN",
    "ks:ks_name":"Duvvupalem",
    "ks:ks_pop":519,
    "ks:ks_type":"HABITATION",
    "ks:ks_uagg_main":0,
    "name:eng_x_preferred":[
        "Duvvupalem"
    ],
    "wof:name":"Duvvupalem",
    "wof:placetype":"neighbourhood",
    "wof:population":519
},
  "geometry": {"coordinates":[83.245993,17.819175],"type":"Point"}
}