{
  "type": "Feature",
  "properties": {
    "iso:country":"IN",
    "ks:ks_name":"Pathar Kani Mal",
    "ks:ks_pop":579,
    "ks:ks_type":"VILLAGE",
    "ks:ks_uagg_main":0,
    "name:eng_x_preferred":[
        "Pathar Kani Mal"
    ],
    "wof:name":"Pathar Kani Mal",
    "wof:placetype":"neighbourhood",
    "wof:population":579
},
  "geometry": {"coordinates":[87.225054,24.899414],"type":"Point"}
}