{
  "type": "Feature",
  "properties": {
    "iso:country":"IN",
    "ks:ks_name":"Korpe Wadi",
    "ks:ks_pop":133,
    "ks:ks_type":"HABITATION",
    "name:eng_x_preferred":[
        "Korpe Wadi"
    ],
    "wof:name":"Korpe Wadi",
    "wof:placetype":"locality",
    "wof:population":133
},
  "geometry": {"coordinates":[75.770876,20.394206],"type":"Point"}
}