{
  "type": "Feature",
  "properties": {
    "iso:country":"IN",
    "ks:ks_name":"Gadabavalasa",
    "ks:ks_pop":92,
    "ks:ks_type":"HABITATION",
    "name:eng_x_preferred":[
        "Gadabavalasa"
    ],
    "wof:name":"Gadabavalasa",
    "wof:placetype":"locality",
    "wof:population":92
},
  "geometry": {"coordinates":[83.841015,18.564825],"type":"Point"}
}