{
  "type": "Feature",
  "properties": {
    "gn:admin1_code":"36.0",
    "gn:admin2_code":"135.0",
    "gn:asciiname":"Matipur",
    "gn:country_code":"IN",
    "gn:dem":208,
    "gn:feature_class":"P",
    "gn:feature_code":"PPL",
    "gn:name":"M\u0101t\u012bpur",
    "gn:population":0,
    "gn:timezone":"Asia/Kolkata",
    "iso:country":"IN",
    "wof:name":"Matipur",
    "wof:placetype":"locality"
},
  "geometry": {"coordinates":[78.51193000000001,28.76766],"type":"Point"}
}