{
  "type": "Feature",
  "properties": {
    "iso:country":"IN",
    "ks:ks_name":"Bibni Rongpi",
    "ks:ks_pop":90,
    "ks:ks_type":"HABITATION",
    "name:eng_x_preferred":[
        "Bibni Rongpi"
    ],
    "wof:name":"Bibni Rongpi",
    "wof:placetype":"locality",
    "wof:population":90
},
  "geometry": {"coordinates":[93.774508,26.444151],"type":"Point"}
}