{
  "type": "Feature",
  "properties": {
    "gn:admin1_code":"16",
    "gn:admin2_code":"512.0",
    "gn:asciiname":"Sonegaon",
    "gn:country_code":"IN",
    "gn:dem":380,
    "gn:feature_class":"P",
    "gn:feature_code":"PPL",
    "gn:name":"Sonegaon",
    "gn:population":0,
    "gn:timezone":"Asia/Kolkata",
    "iso:country":"IN",
    "wof:name":"Sonegaon",
    "wof:placetype":"locality"
},
  "geometry": {"coordinates":[77.18565,19.24407],"type":"Point"}
}