{
  "type": "Feature",
  "properties": {
    "iso:country":"IN",
    "ks:ks_name":"Koliya",
    "ks:ks_pop":1263,
    "ks:ks_type":"VILLAGE",
    "name:eng_x_preferred":[
        "Koliya"
    ],
    "wof:name":"Koliya",
    "wof:placetype":"locality",
    "wof:population":1263
},
  "geometry": {"coordinates":[73.122596,24.441432],"type":"Point"}
}