{
  "type": "Feature",
  "properties": {
    "gn:admin1_code":"39",
    "gn:admin2_code":"61.0",
    "gn:asciiname":"Kimsera",
    "gn:country_code":"IN",
    "gn:dem":870,
    "gn:feature_class":"P",
    "gn:feature_code":"PPL",
    "gn:name":"Kimsera",
    "gn:population":0,
    "gn:timezone":"Asia/Kolkata",
    "iso:country":"IN",
    "ks:ks_name":"Kimsera",
    "ks:ks_pop":170,
    "ks:ks_type":"VILLAGE",
    "name:eng_x_preferred":[
        "Kimsera"
    ],
    "wof:name":"Kimsera",
    "wof:placetype":"locality",
    "wof:population":170
},
  "geometry": {"coordinates":[78.486936,29.862688],"type":"Point"}
}