{
  "type": "Feature",
  "properties": {
    "gn:admin1_code":"35.0",
    "gn:admin2_code":"431.0",
    "gn:asciiname":"Karimati",
    "gn:country_code":"IN",
    "gn:dem":476,
    "gn:feature_class":"P",
    "gn:feature_code":"PPL",
    "gn:name":"K\u0101rim\u0101ti",
    "gn:population":0,
    "gn:timezone":"Asia/Kolkata",
    "iso:country":"IN",
    "ks:ks_alt_nam":"K\u0101rim\u0101ti",
    "ks:ks_name":"Karimati",
    "ks:ks_type":"VILLAGE",
    "name:eng_x_preferred":[
        "Karimati"
    ],
    "name:eng_x_variant":[
        "K\u0101rim\u0101ti"
    ],
    "wof:name":"Karimati",
    "wof:placetype":"locality"
},
  "geometry": {"coordinates":[80.819602,23.489889],"type":"Point"}
}