{
  "type": "Feature",
  "properties": {
    "iso:country":"IN",
    "ks:ks_name":"Karhi",
    "ks:ks_pop":203,
    "ks:ks_type":"HABITATION",
    "name:eng_x_preferred":[
        "Karhi"
    ],
    "wof:name":"Karhi",
    "wof:placetype":"locality",
    "wof:population":203
},
  "geometry": {"coordinates":[82.968738,27.217942],"type":"Point"}
}