{
  "type": "Feature",
  "properties": {
    "gn:admin1_code":"35.0",
    "gn:admin2_code":"420.0",
    "gn:asciiname":"Kanipura",
    "gn:country_code":"IN",
    "gn:dem":166,
    "gn:feature_class":"P",
    "gn:feature_code":"PPL",
    "gn:name":"Kan\u012bpura",
    "gn:population":0,
    "gn:timezone":"Asia/Kolkata",
    "iso:country":"IN",
    "name:ara_x_preferred":[
        "\u0643\u0627\u0646\u0628\u0648\u0631\u0627"
    ],
    "name:ben_bn_x_preferred":[
        "\u0995\u09be\u09a8\u09bf\u09aa\u09c1\u09b0\u09be"
    ],
    "name:ben_in_x_preferred":[
        "\u0995\u09be\u09a8\u09bf\u09aa\u09c1\u09b0\u09be"
    ],
    "name:guj_x_preferred":[
        "\u0a95\u0abe\u0aa8\u0ac0\u0aaa\u0ac1\u0ab0\u0abe"
    ],
    "name:hin_x_preferred":[
        "\u0915\u0928\u093f\u092a\u0941\u0930\u093e"
    ],
    "name:kan_x_preferred":[
        "\u0c95\u0ca8\u0cbf\u0caa\u0cc1\u0cb0"
    ],
    "name:mal_x_preferred":[
        "\u0d15\u0d28\u0d3f\u0d2a\u0d41\u0d30"
    ],
    "name:mar_x_preferred":[
        "\u0915\u093e\u0928\u093f\u092a\u0941\u0930\u093e"
    ],
    "name:pan_x_preferred":[
        "\u0a15\u0a3e\u0a28\u0a40\u0a2a\u0a41\u0a30\u0a3e"
    ],
    "name:tam_x_preferred":[
        "\u0b95\u0ba9\u0bbf\u0baa\u0bcd\u0baa\u0bc1\u0bb0\u0bbe"
    ],
    "name:tel_x_preferred":[
        "\u0c15\u0c28\u0c3f\u0c2a\u0c42\u0c30\u0c3e"
    ],
    "name:urd_x_preferred":[
        "\u06a9\u0627\u0646\u06cc \u067e\u0648\u0631\u06c1"
    ],
    "wof:name":"Kanipura",
    "wof:placetype":"locality"
},
  "geometry": {"coordinates":[78.40475000000001,26.47977],"type":"Point"}
}