{
  "type": "Feature",
  "properties": {
    "iso:country":"IN",
    "ks:ks_name":"Milaghat",
    "ks:ks_pop":447,
    "ks:ks_type":"VILLAGE",
    "name:eng_x_preferred":[
        "Milaghat"
    ],
    "wof:name":"Milaghat",
    "wof:placetype":"locality",
    "wof:population":447
},
  "geometry": {"coordinates":[91.314696,25.991866],"type":"Point"}
}