{
  "type": "Feature",
  "properties": {
    "iso:country":"IN",
    "ks:ks_name":"Gidhmudi",
    "ks:ks_pop":1284,
    "ks:ks_type":"VILLAGE",
    "name:eng_x_preferred":[
        "Gidhmudi"
    ],
    "wof:name":"Gidhmudi",
    "wof:placetype":"locality",
    "wof:population":1284
},
  "geometry": {"coordinates":[82.329138,23.028734],"type":"Point"}
}