{
  "type": "Feature",
  "properties": {
    "gn:admin1_code":"11",
    "gn:admin2_code":"23.0",
    "gn:asciiname":"Khabbar",
    "gn:country_code":"IN",
    "gn:dem":1017,
    "gn:feature_class":"P",
    "gn:feature_code":"PPL",
    "gn:name":"Khabbar",
    "gn:population":0,
    "gn:timezone":"Asia/Kolkata",
    "iso:country":"IN",
    "wof:name":"Khabbar",
    "wof:placetype":"locality"
},
  "geometry": {"coordinates":[76.05020999999998,32.66854],"type":"Point"}
}