{
  "type": "Feature",
  "properties": {
    "iso:country":"IN",
    "ks:ks_name":"Kothiyal Danda Walla",
    "ks:ks_pop":36,
    "ks:ks_type":"VILLAGE",
    "name:eng_x_preferred":[
        "Kothiyal Danda Walla"
    ],
    "wof:name":"Kothiyal Danda Walla",
    "wof:placetype":"locality",
    "wof:population":36
},
  "geometry": {"coordinates":[78.639809,29.824522],"type":"Point"}
}