{
  "type": "Feature",
  "properties": {
    "iso:country":"IN",
    "ks:ks_name":"Mahishgara",
    "ks:ks_pop":860,
    "ks:ks_type":"VILLAGE",
    "name:eng_x_preferred":[
        "Mahishgara"
    ],
    "wof:name":"Mahishgara",
    "wof:placetype":"locality",
    "wof:population":860
},
  "geometry": {"coordinates":[88.07281500000001,23.028521],"type":"Point"}
}