{
  "type": "Feature",
  "properties": {
    "iso:country":"IN",
    "ks:ks_name":"Padukotekaval",
    "ks:ks_pop":344,
    "ks:ks_type":"HABITATION",
    "name:eng_x_preferred":[
        "Padukotekaval"
    ],
    "wof:name":"Padukotekaval",
    "wof:placetype":"locality",
    "wof:population":344
},
  "geometry": {"coordinates":[76.311059,12.18099],"type":"Point"}
}