{
  "type": "Feature",
  "properties": {
    "gn:admin1_code":"36",
    "gn:admin2_code":"179.0",
    "gn:asciiname":"Chatar Bhojpur",
    "gn:country_code":"IN",
    "gn:dem":95,
    "gn:feature_class":"P",
    "gn:feature_code":"PPL",
    "gn:name":"Chatar Bhojpur",
    "gn:population":0,
    "gn:timezone":"Asia/Kolkata",
    "iso:country":"IN",
    "ks:ks_name":"Chaturbhujpur",
    "ks:ks_pop":1595,
    "ks:ks_type":"VILLAGE",
    "name:eng_x_preferred":[
        "Chaturbhujpur"
    ],
    "name:eng_x_variant":[
        "Chatar Bhojpur"
    ],
    "wof:name":"Chaturbhujpur",
    "wof:placetype":"locality",
    "wof:population":1595
},
  "geometry": {"coordinates":[82.44158899999999,26.029144],"type":"Point"}
}