{
  "type": "Feature",
  "properties": {
    "gn:admin1_code":"39.0",
    "gn:admin2_code":"59.0",
    "gn:asciiname":"Kaphalta",
    "gn:country_code":"IN",
    "gn:dem":1424,
    "gn:feature_class":"P",
    "gn:feature_code":"PPL",
    "gn:name":"Kaphalta",
    "gn:population":0,
    "gn:timezone":"Asia/Kolkata",
    "iso:country":"IN",
    "wof:name":"Kaphalta",
    "wof:placetype":"locality"
},
  "geometry": {"coordinates":[78.08913000000003,30.48236],"type":"Point"}
}