{
  "type": "Feature",
  "properties": {
    "gn:admin1_code":"35.0",
    "gn:admin2_code":"429.0",
    "gn:asciiname":"Ailahal",
    "gn:country_code":"IN",
    "gn:dem":360,
    "gn:feature_class":"P",
    "gn:feature_code":"PPL",
    "gn:name":"Ailahal",
    "gn:population":0,
    "gn:timezone":"Asia/Kolkata",
    "iso:country":"IN",
    "wof:name":"Ailahal",
    "wof:placetype":"locality"
},
  "geometry": {"coordinates":[81.02767,24.86396],"type":"Point"}
}