{
  "type": "Feature",
  "properties": {
    "gn:admin1_code":"2.0",
    "gn:admin2_code":"551.0",
    "gn:asciiname":"Siddayyagarimatam",
    "gn:country_code":"IN",
    "gn:dem":161,
    "gn:feature_class":"P",
    "gn:feature_code":"PPL",
    "gn:name":"Siddayyag\u0101rimatam",
    "gn:population":0,
    "gn:timezone":"Asia/Kolkata",
    "iso:country":"IN",
    "wof:name":"Siddayyagarimatam",
    "wof:placetype":"neighbourhood"
},
  "geometry": {"coordinates":[78.92355999999999,14.90657],"type":"Point"}
}