{
  "type": "Feature",
  "properties": {
    "iso:country":"IN",
    "ks:ks_name":"Mamidikuduru",
    "ks:ks_pop":4030,
    "ks:ks_type":"VILLAGE",
    "ks:ks_uagg_main":0,
    "name:eng_x_preferred":[
        "Mamidikuduru"
    ],
    "wof:name":"Mamidikuduru",
    "wof:placetype":"neighbourhood",
    "wof:population":4030
},
  "geometry": {"coordinates":[81.918744,16.503321],"type":"Point"}
}