{
  "type": "Feature",
  "properties": {
    "gn:admin1_code":"11",
    "gn:admin2_code":"31.0",
    "gn:asciiname":"Chak",
    "gn:country_code":"IN",
    "gn:dem":429,
    "gn:feature_class":"P",
    "gn:feature_code":"PPL",
    "gn:name":"Chak",
    "gn:population":0,
    "gn:timezone":"Asia/Kolkata",
    "iso:country":"IN",
    "name:ceb_x_preferred":[
        "Chak"
    ],
    "name:swe_x_preferred":[
        "Chak"
    ],
    "wof:name":"Chak",
    "wof:placetype":"locality"
},
  "geometry": {"coordinates":[76.79705,30.94947],"type":"Point"}
}