{
  "type": "Feature",
  "properties": {
    "iso:country":"IN",
    "ks:ks_name":"Korajguda",
    "ks:ks_pop":250,
    "ks:ks_type":"HABITATION",
    "name:eng_x_preferred":[
        "Korajguda"
    ],
    "wof:name":"Korajguda",
    "wof:placetype":"locality",
    "wof:population":250
},
  "geometry": {"coordinates":[81.206884,17.979949],"type":"Point"}
}