{
  "type": "Feature",
  "properties": {
    "gn:admin1_code":"16.0",
    "gn:admin2_code":"516.0",
    "gn:asciiname":"Soyagaon",
    "gn:country_code":"IN",
    "gn:dem":429,
    "gn:feature_class":"P",
    "gn:feature_code":"PPL",
    "gn:name":"Soy\u0101gaon",
    "gn:population":0,
    "gn:timezone":"Asia/Kolkata",
    "iso:country":"IN",
    "wof:name":"Soyagaon",
    "wof:placetype":"locality"
},
  "geometry": {"coordinates":[74.50686999999998,20.5525],"type":"Point"}
}