{
  "type": "Feature",
  "properties": {
    "iso:country":"IN",
    "ks:ks_name":"Radhakrishnapur",
    "ks:ks_pop":2887,
    "ks:ks_type":"VILLAGE",
    "name:eng_x_preferred":[
        "Radhakrishnapur"
    ],
    "wof:name":"Radhakrishnapur",
    "wof:placetype":"locality",
    "wof:population":2887
},
  "geometry": {"coordinates":[87.825608,22.663752],"type":"Point"}
}