{
  "type": "Feature",
  "properties": {
    "gn:admin1_code":"13.0",
    "gn:admin2_code":"593.0",
    "gn:asciiname":"Murigalai",
    "gn:country_code":"IN",
    "gn:dem":710,
    "gn:feature_class":"P",
    "gn:feature_code":"PPL",
    "gn:name":"Murigalai",
    "gn:population":0,
    "gn:timezone":"Asia/Kolkata",
    "iso:country":"IN",
    "wof:name":"Murigalai",
    "wof:placetype":"locality"
},
  "geometry": {"coordinates":[76.53293000000002,11.10343],"type":"Point"}
}