{
  "type": "Feature",
  "properties": {
    "iso:country":"IN",
    "ks:ks_name":"Bargachia Para",
    "ks:ks_pop":336,
    "ks:ks_type":"HABITATION",
    "name:eng_x_preferred":[
        "Bargachia Para"
    ],
    "wof:name":"Bargachia Para",
    "wof:placetype":"locality",
    "wof:population":336
},
  "geometry": {"coordinates":[91.476606,23.948268],"type":"Point"}
}