{
  "type": "Feature",
  "properties": {
    "gn:admin1_code":"39.0",
    "gn:admin2_code":"64.0",
    "gn:asciiname":"Churi Jakhni",
    "gn:country_code":"IN",
    "gn:dem":853,
    "gn:feature_class":"P",
    "gn:feature_code":"PPL",
    "gn:name":"Ch\u016bri J\u0101khni",
    "gn:population":0,
    "gn:timezone":"Asia/Kolkata",
    "iso:country":"IN",
    "ks:ks_name":"Churi Jakhani",
    "ks:ks_pop":127,
    "ks:ks_type":"HABITATION",
    "name:eng_x_preferred":[
        "Churi Jakhani"
    ],
    "name:eng_x_variant":[
        "Churi Jakhni"
    ],
    "wof:name":"Churi Jakhani",
    "wof:placetype":"locality",
    "wof:population":127
},
  "geometry": {"coordinates":[79.18284,29.642825],"type":"Point"}
}