{
  "type": "Feature",
  "properties": {
    "gn:admin1_code":"39.0",
    "gn:admin2_code":"64.0",
    "gn:asciiname":"Churi Jakhni",
    "gn:country_code":"IN",
    "gn:dem":853,
    "gn:feature_class":"P",
    "gn:feature_code":"PPL",
    "gn:name":"Ch\u016bri J\u0101khni",
    "gn:population":0,
    "gn:timezone":"Asia/Kolkata",
    "iso:country":"IN",
    "wof:name":"Churi Jakhni",
    "wof:placetype":"locality"
},
  "geometry": {"coordinates":[79.19046,29.63687],"type":"Point"}
}