{
  "type": "Feature",
  "properties": {
    "iso:country":"IN",
    "ks:ks_name":"Thagarapully",
    "ks:ks_pop":105,
    "ks:ks_type":"HABITATION",
    "name:eng_x_preferred":[
        "Thagarapully"
    ],
    "wof:name":"Thagarapully",
    "wof:placetype":"locality",
    "wof:population":105
},
  "geometry": {"coordinates":[75.459565,13.017622],"type":"Point"}
}