{
  "type": "Feature",
  "properties": {
    "iso:country":"IN",
    "ks:ks_alt_nam":"ORAWTOLI",
    "ks:ks_name":"Orawtoli",
    "ks:ks_pop":258,
    "ks:ks_type":"HABITATION",
    "name:eng_x_preferred":[
        "Orawtoli"
    ],
    "wof:name":"Orawtoli",
    "wof:placetype":"locality",
    "wof:population":258
},
  "geometry": {"coordinates":[83.810329,22.77464],"type":"Point"}
}