{
  "type": "Feature",
  "properties": {
    "iso:country":"IN",
    "ks:ks_name":"Hamakki",
    "ks:ks_pop":181,
    "ks:ks_type":"HABITATION",
    "name:eng_x_preferred":[
        "Hamakki"
    ],
    "wof:name":"Hamakki",
    "wof:placetype":"locality",
    "wof:population":181
},
  "geometry": {"coordinates":[74.49485799999999,14.214033],"type":"Point"}
}