{
  "type": "Feature",
  "properties": {
    "iso:country":"IN",
    "ks:ks_name":"Kudari",
    "ks:ks_pop":562,
    "ks:ks_type":"VILLAGE",
    "name:eng_x_preferred":[
        "Kudari"
    ],
    "wof:name":"Kudari",
    "wof:placetype":"neighbourhood",
    "wof:population":562
},
  "geometry": {"coordinates":[82.74078299999999,22.305215],"type":"Point"}
}