{
  "type": "Feature",
  "properties": {
    "iso:country":"IN",
    "ks:ks_alt_nam":"vajragad fort",
    "ks:ks_name":"Vajragad Fort",
    "ks:ks_pop":290,
    "ks:ks_type":"HABITATION",
    "name:eng_x_preferred":[
        "Vajragad Fort"
    ],
    "wof:name":"Vajragad Fort",
    "wof:placetype":"locality",
    "wof:population":290
},
  "geometry": {"coordinates":[73.95221600000001,18.290274],"type":"Point"}
}