{
  "type": "Feature",
  "properties": {
    "gn:admin1_code":"21",
    "gn:admin2_code":"370.0",
    "gn:asciiname":"Gulhiapadar",
    "gn:country_code":"IN",
    "gn:dem":181,
    "gn:feature_class":"P",
    "gn:feature_code":"PPL",
    "gn:name":"Gulhiapadar",
    "gn:population":0,
    "gn:timezone":"Asia/Kolkata",
    "iso:country":"IN",
    "ks:ks_name":"Gulihapadar",
    "ks:ks_pop":601,
    "ks:ks_type":"VILLAGE",
    "name:eng_x_preferred":[
        "Gulihapadar"
    ],
    "name:eng_x_variant":[
        "Gulhiapadar"
    ],
    "wof:name":"Gulihapadar",
    "wof:placetype":"locality",
    "wof:population":601
},
  "geometry": {"coordinates":[83.592579,21.098717],"type":"Point"}
}