{
  "type": "Feature",
  "properties": {
    "iso:country":"IN",
    "ks:ks_name":"Madavoor",
    "ks:ks_pop":918,
    "ks:ks_type":"VILLAGE",
    "name:eng_x_preferred":[
        "Madavoor"
    ],
    "wof:name":"Madavoor",
    "wof:placetype":"locality",
    "wof:population":918
},
  "geometry": {"coordinates":[75.884106,11.358953],"type":"Point"}
}