{
  "type": "Feature",
  "properties": {
    "iso:country":"IN",
    "ks:ks_name":"Sedikini",
    "ks:ks_pop":14,
    "ks:ks_type":"HABITATION",
    "name:eng_x_preferred":[
        "Sedikini"
    ],
    "wof:name":"Sedikini",
    "wof:placetype":"locality",
    "wof:population":14
},
  "geometry": {"coordinates":[74.829887,14.563483],"type":"Point"}
}