{
  "type": "Feature",
  "properties": {
    "gn:admin1_code":"16.0",
    "gn:admin2_code":"522",
    "gn:asciiname":"Dhawalpuri",
    "gn:country_code":"IN",
    "gn:dem":686,
    "gn:feature_class":"P",
    "gn:feature_code":"PPL",
    "gn:name":"Dhawalpuri",
    "gn:population":0,
    "gn:timezone":"Asia/Kolkata",
    "iso:country":"IN",
    "wof:name":"Dhawalpuri",
    "wof:placetype":"locality"
},
  "geometry": {"coordinates":[74.53055000000001,19.17682000000001],"type":"Point"}
}