{
  "type": "Feature",
  "properties": {
    "iso:country":"IN",
    "ks:ks_name":"Begampur",
    "ks:ks_pop":1737,
    "ks:ks_type":"VILLAGE",
    "ks:ks_uagg_main":0,
    "name:eng_x_preferred":[
        "Begampur"
    ],
    "wof:name":"Begampur",
    "wof:placetype":"locality",
    "wof:population":1737
},
  "geometry": {"coordinates":[88.770439,22.832299],"type":"Point"}
}