{
  "type": "Feature",
  "properties": {
    "iso:country":"IN",
    "ks:ks_name":"Chourtoli",
    "ks:ks_pop":142,
    "ks:ks_type":"HABITATION",
    "name:eng_x_preferred":[
        "Chourtoli"
    ],
    "wof:name":"Chourtoli",
    "wof:placetype":"locality",
    "wof:population":142
},
  "geometry": {"coordinates":[84.679722,23.180425],"type":"Point"}
}