{
  "type": "Feature",
  "properties": {
    "iso:country":"IN",
    "ks:ks_name":"Dubagadia",
    "ks:ks_pop":487,
    "ks:ks_type":"VILLAGE",
    "ks:ks_uagg_main":0,
    "name:eng_x_preferred":[
        "Dubagadia"
    ],
    "wof:name":"Dubagadia",
    "wof:placetype":"neighbourhood",
    "wof:population":487
},
  "geometry": {"coordinates":[86.15486300000001,20.762066],"type":"Point"}
}