{
  "type": "Feature",
  "properties": {
    "iso:country":"IN",
    "ks:ks_name":"Pokharhiya",
    "ks:ks_pop":97,
    "ks:ks_type":"HABITATION",
    "name:eng_x_preferred":[
        "Pokharhiya"
    ],
    "wof:name":"Pokharhiya",
    "wof:placetype":"locality",
    "wof:population":97
},
  "geometry": {"coordinates":[83.11642500000001,24.579673],"type":"Point"}
}