{
  "type": "Feature",
  "properties": {
    "gn:admin1_code":"11",
    "gn:admin2_code":"27.0",
    "gn:asciiname":"Seog",
    "gn:country_code":"IN",
    "gn:dem":633,
    "gn:feature_class":"P",
    "gn:feature_code":"PPL",
    "gn:name":"Seog",
    "gn:population":0,
    "gn:timezone":"Asia/Kolkata",
    "iso:country":"IN",
    "wof:name":"Seog",
    "wof:placetype":"locality"
},
  "geometry": {"coordinates":[76.88323000000003,31.42437],"type":"Point"}
}