{
  "type": "Feature",
  "properties": {
    "gn:admin1_code":"36",
    "gn:admin2_code":"187.0",
    "gn:asciiname":"Janakpur",
    "gn:country_code":"IN",
    "gn:dem":89,
    "gn:feature_class":"P",
    "gn:feature_code":"PPL",
    "gn:name":"Janakpur",
    "gn:population":0,
    "gn:timezone":"Asia/Kolkata",
    "iso:country":"IN",
    "name:fra_x_preferred":[
        "Janakpur"
    ],
    "name:heb_x_preferred":[
        "\u05d2'\u05e0\u05d0\u05e7\u05e4\u05d5\u05e8"
    ],
    "name:hin_x_preferred":[
        "\u091c\u0928\u0915\u092a\u0941\u0930"
    ],
    "name:hun_x_preferred":[
        "Janakpur"
    ],
    "name:nep_x_preferred":[
        "\u091c\u0928\u0915\u092a\u0941\u0930\u0927\u093e\u092e"
    ],
    "name:new_x_preferred":[
        "\u091c\u0928\u0915\u092a\u0941\u0930 \u0928\u0917\u0930\u092a\u093e\u0932\u093f\u0915\u093e"
    ],
    "name:nor_x_preferred":[
        "Janakpur"
    ],
    "name:pol_x_preferred":[
        "Janakpur"
    ],
    "name:swe_x_preferred":[
        "Janakpur"
    ],
    "wof:name":"Janakpur",
    "wof:placetype":"neighbourhood"
},
  "geometry": {"coordinates":[83.31128,27.15899],"type":"Point"}
}