{
  "type": "Feature",
  "properties": {
    "iso:country":"IN",
    "ks:ks_name":"Chuakhol",
    "ks:ks_pop":346,
    "ks:ks_type":"VILLAGE",
    "name:eng_x_preferred":[
        "Chuakhol"
    ],
    "wof:name":"Chuakhol",
    "wof:placetype":"locality",
    "wof:population":346
},
  "geometry": {"coordinates":[84.90522300000001,21.373746],"type":"Point"}
}