{
  "type": "Feature",
  "properties": {
    "iso:country":"IN",
    "ks:ks_name":"Karondiya",
    "ks:ks_pop":10,
    "ks:ks_type":"VILLAGE",
    "name:eng_x_preferred":[
        "Karondiya"
    ],
    "wof:name":"Karondiya",
    "wof:placetype":"locality",
    "wof:population":10
},
  "geometry": {"coordinates":[77.707735,23.474096],"type":"Point"}
}