{
  "type": "Feature",
  "properties": {
    "iso:country":"IN",
    "ks:ks_name":"Garihali Chuk",
    "ks:ks_pop":123,
    "ks:ks_type":"VILLAGE",
    "name:eng_x_preferred":[
        "Garihali Chuk"
    ],
    "wof:name":"Garihali Chuk",
    "wof:placetype":"locality",
    "wof:population":123
},
  "geometry": {"coordinates":[94.819627,27.189376],"type":"Point"}
}