{
  "type": "Feature",
  "properties": {
    "iso:country":"IN",
    "ks:ks_alt_nam":"BHAGALPUR",
    "ks:ks_name":"Bhagalpur",
    "ks:ks_pop":270,
    "ks:ks_type":"HABITATION",
    "name:eng_x_preferred":[
        "Bhagalpur"
    ],
    "name:hin_x_preferred":[
        "\u092d\u093e\u0917\u0932\u092a\u0941\u0930"
    ],
    "wof:name":"Bhagalpur",
    "wof:placetype":"locality",
    "wof:population":270
},
  "geometry": {"coordinates":[84.961474,24.804908],"type":"Point"}
}