{
  "type": "Feature",
  "properties": {
    "iso:country":"IN",
    "ks:ks_alt_nam":"NAGLA BANJARA",
    "ks:ks_name":"Nagla Banjara",
    "ks:ks_pop":317,
    "ks:ks_type":"HABITATION",
    "name:eng_x_preferred":[
        "Nagla Banjara"
    ],
    "wof:name":"Nagla Banjara",
    "wof:placetype":"locality",
    "wof:population":317
},
  "geometry": {"coordinates":[78.55334000000001,27.07785],"type":"Point"}
}