{
  "type": "Feature",
  "properties": {
    "iso:country":"IN",
    "ks:ks_name":"Rangannagudem",
    "ks:ks_pop":576,
    "ks:ks_type":"HABITATION",
    "name:eng_x_preferred":[
        "Rangannagudem"
    ],
    "wof:name":"Rangannagudem",
    "wof:placetype":"locality",
    "wof:population":576
},
  "geometry": {"coordinates":[78.80800499999999,17.51565],"type":"Point"}
}