{
  "type": "Feature",
  "properties": {
    "iso:country":"IN",
    "ks:ks_name":"Eguvapalli",
    "ks:ks_pop":202,
    "ks:ks_type":"HABITATION",
    "ks:ks_uagg_main":0,
    "name:eng_x_preferred":[
        "Eguvapalli"
    ],
    "wof:name":"Eguvapalli",
    "wof:placetype":"neighbourhood",
    "wof:population":202
},
  "geometry": {"coordinates":[78.331205,14.158964],"type":"Point"}
}