{
  "type": "Feature",
  "properties": {
    "gn:admin1_code":"2.0",
    "gn:admin2_code":"552.0",
    "gn:asciiname":"Tippatalamari",
    "gn:country_code":"IN",
    "gn:dem":458,
    "gn:feature_class":"P",
    "gn:feature_code":"PPL",
    "gn:name":"Tippatalamari",
    "gn:population":0,
    "gn:timezone":"Asia/Kolkata",
    "iso:country":"IN",
    "wof:name":"Tippatalamari",
    "wof:placetype":"locality"
},
  "geometry": {"coordinates":[77.58305,15.49135],"type":"Point"}
}