{
  "type": "Feature",
  "properties": {
    "gn:admin1_code":"21",
    "gn:admin2_code":"393.0",
    "gn:asciiname":"Purapadar",
    "gn:country_code":"IN",
    "gn:dem":175,
    "gn:feature_class":"P",
    "gn:feature_code":"PPL",
    "gn:name":"Purapadar",
    "gn:population":0,
    "gn:timezone":"Asia/Kolkata",
    "iso:country":"IN",
    "wof:name":"Purapadar",
    "wof:placetype":"locality"
},
  "geometry": {"coordinates":[83.35405,21.06076],"type":"Point"}
}