{
  "type": "Feature",
  "properties": {
    "gn:admin1_code":"24.0",
    "gn:admin2_code":"128",
    "gn:asciiname":"Amrod",
    "gn:country_code":"IN",
    "gn:dem":351,
    "gn:feature_class":"P",
    "gn:feature_code":"PPL",
    "gn:name":"Amrod",
    "gn:population":0,
    "gn:timezone":"Asia/Kolkata",
    "iso:country":"IN",
    "name:bos_x_preferred":[
        "Amrod"
    ],
    "name:cat_x_preferred":[
        "\u00c0mrod"
    ],
    "name:eus_x_preferred":[
        "Amrod"
    ],
    "name:ita_x_preferred":[
        "Amrod"
    ],
    "name:jpn_x_preferred":[
        "\u30a2\u30e0\u30ed\u30c9"
    ],
    "name:nld_x_preferred":[
        "Amrod"
    ],
    "name:pol_x_preferred":[
        "Lista Calaquendich#Amrod"
    ],
    "name:por_x_preferred":[
        "Amrod"
    ],
    "name:slv_x_preferred":[
        "Amrod"
    ],
    "name:spa_x_preferred":[
        "Amrod"
    ],
    "name:swe_x_preferred":[
        "Amrod"
    ],
    "name:zho_x_preferred":[
        "\u5b89\u7f85\u5fb7"
    ],
    "wof:name":"Amrod",
    "wof:placetype":"locality"
},
  "geometry": {"coordinates":[77.39050999999998,25.12341],"type":"Point"}
}