{
  "type": "Feature",
  "properties": {
    "gn:admin1_code":"24.0",
    "gn:admin2_code":"128",
    "gn:asciiname":"Amrod",
    "gn:country_code":"IN",
    "gn:dem":351,
    "gn:feature_class":"P",
    "gn:feature_code":"PPL",
    "gn:name":"Amrod",
    "gn:population":0,
    "gn:timezone":"Asia/Kolkata",
    "iso:country":"IN",
    "wof:name":"Amrod",
    "wof:placetype":"locality"
},
  "geometry": {"coordinates":[77.39050999999998,25.12341],"type":"Point"}
}