{
  "type": "Feature",
  "properties": {
    "iso:country":"IN",
    "ks:ks_name":"Labhanguda",
    "ks:ks_pop":285,
    "ks:ks_type":"HABITATION",
    "name:eng_x_preferred":[
        "Labhanguda"
    ],
    "wof:name":"Labhanguda",
    "wof:placetype":"locality",
    "wof:population":285
},
  "geometry": {"coordinates":[79.06798499999999,19.566284],"type":"Point"}
}