{
  "type": "Feature",
  "properties": {
    "iso:country":"IN",
    "ks:ks_name":"Hundru",
    "ks:ks_pop":92,
    "ks:ks_type":"HABITATION",
    "name:eng_x_preferred":[
        "Hundru"
    ],
    "wof:name":"Hundru",
    "wof:placetype":"locality",
    "wof:population":92
},
  "geometry": {"coordinates":[85.608813,23.356513],"type":"Point"}
}