{
  "type": "Feature",
  "properties": {
    "iso:country":"IN",
    "ks:ks_name":"Varna Mahatman",
    "ks:ks_pop":823,
    "ks:ks_type":"HABITATION",
    "name:eng_x_preferred":[
        "Varna Mahatman"
    ],
    "wof:name":"Varna Mahatman",
    "wof:placetype":"locality",
    "wof:population":823
},
  "geometry": {"coordinates":[82.1421,24.674569],"type":"Point"}
}