{
  "type": "Feature",
  "properties": {
    "iso:country":"IN",
    "ks:ks_alt_nam":"Da Borahi III",
    "ks:ks_name":"Da Borahi Iii",
    "ks:ks_pop":936,
    "ks:ks_type":"HABITATION",
    "name:eng_x_preferred":[
        "Da Borahi Iii"
    ],
    "wof:name":"Da Borahi Iii",
    "wof:placetype":"locality",
    "wof:population":936
},
  "geometry": {"coordinates":[94.057619,26.483118],"type":"Point"}
}