{
  "type": "Feature",
  "properties": {
    "iso:country":"IN",
    "ks:ks_name":"Thirumalapuram",
    "ks:ks_pop":350,
    "ks:ks_type":"HABITATION",
    "name:eng_x_preferred":[
        "Thirumalapuram"
    ],
    "wof:name":"Thirumalapuram",
    "wof:placetype":"locality",
    "wof:population":350
},
  "geometry": {"coordinates":[78.043604,8.574443],"type":"Point"}
}