{
  "type": "Feature",
  "properties": {
    "gn:admin1_code":"11",
    "gn:admin2_code":"24.0",
    "gn:asciiname":"Uchhahr",
    "gn:country_code":"IN",
    "gn:dem":515,
    "gn:feature_class":"P",
    "gn:feature_code":"PPL",
    "gn:name":"Uchhahr",
    "gn:population":0,
    "gn:timezone":"Asia/Kolkata",
    "iso:country":"IN",
    "wof:name":"Uchhahr",
    "wof:placetype":"locality"
},
  "geometry": {"coordinates":[76.31669000000002,31.86163],"type":"Point"}
}