{
  "type": "Feature",
  "properties": {
    "gn:admin1_code":"40",
    "gn:admin2_code":"537.0",
    "gn:asciiname":"Malagudam",
    "gn:country_code":"IN",
    "gn:dem":595,
    "gn:feature_class":"P",
    "gn:feature_code":"PPL",
    "gn:name":"M\u0101lagudam",
    "gn:population":0,
    "gn:timezone":"Asia/Kolkata",
    "iso:country":"IN",
    "wof:name":"Malagudam",
    "wof:placetype":"locality"
},
  "geometry": {"coordinates":[78.58598000000001,17.06802],"type":"Point"}
}