{
  "type": "Feature",
  "properties": {
    "iso:country":"IN",
    "ks:ks_name":"Derva",
    "ks:ks_pop":350,
    "ks:ks_type":"HABITATION",
    "name:eng_x_preferred":[
        "Derva"
    ],
    "wof:name":"Derva",
    "wof:placetype":"locality",
    "wof:population":350
},
  "geometry": {"coordinates":[82.48457399999999,26.361542],"type":"Point"}
}