{
  "type": "Feature",
  "properties": {
    "iso:country":"IN",
    "ks:ks_name":"Kumharon Ka Pathar",
    "ks:ks_pop":105,
    "ks:ks_type":"HABITATION",
    "name:eng_x_preferred":[
        "Kumharon Ka Pathar"
    ],
    "wof:name":"Kumharon Ka Pathar",
    "wof:placetype":"locality",
    "wof:population":105
},
  "geometry": {"coordinates":[74.749475,23.646232],"type":"Point"}
}