{
  "type": "Feature",
  "properties": {
    "iso:country":"IN",
    "ks:ks_name":"Tentulipada 2",
    "ks:ks_pop":200,
    "ks:ks_type":"HABITATION",
    "name:eng_x_preferred":[
        "Tentulipada 2"
    ],
    "wof:name":"Tentulipada 2",
    "wof:placetype":"locality",
    "wof:population":200
},
  "geometry": {"coordinates":[82.666207,19.693112],"type":"Point"}
}