{
  "type": "Feature",
  "properties": {
    "iso:country":"IN",
    "ks:ks_name":"Hathla",
    "ks:ks_pop":1482,
    "ks:ks_type":"VILLAGE",
    "name:eng_x_preferred":[
        "Hathla"
    ],
    "wof:name":"Hathla",
    "wof:placetype":"locality",
    "wof:population":1482
},
  "geometry": {"coordinates":[71.067868,24.80524],"type":"Point"}
}