{
  "type": "Feature",
  "properties": {
    "gn:admin1_code":"2.0",
    "gn:admin2_code":"552.0",
    "gn:asciiname":"Rekalakunta",
    "gn:country_code":"IN",
    "gn:dem":536,
    "gn:feature_class":"P",
    "gn:feature_code":"PPL",
    "gn:name":"Rekalakunta",
    "gn:population":0,
    "gn:timezone":"Asia/Kolkata",
    "iso:country":"IN",
    "wof:name":"Rekalakunta",
    "wof:placetype":"locality"
},
  "geometry": {"coordinates":[77.81310999999999,15.32724],"type":"Point"}
}