{
  "type": "Feature",
  "properties": {
    "iso:country":"IN",
    "ks:ks_name":"Ghuteghari",
    "ks:ks_pop":254,
    "ks:ks_type":"VILLAGE",
    "name:eng_x_preferred":[
        "Ghuteghari"
    ],
    "wof:name":"Ghuteghari",
    "wof:placetype":"locality",
    "wof:population":254
},
  "geometry": {"coordinates":[88.064184,22.704798],"type":"Point"}
}