{
  "type": "Feature",
  "properties": {
    "iso:country":"IN",
    "ks:ks_name":"Antarved",
    "ks:ks_pop":130,
    "ks:ks_type":"HABITATION",
    "name:eng_x_preferred":[
        "Antarved"
    ],
    "wof:name":"Antarved",
    "wof:placetype":"locality",
    "wof:population":130
},
  "geometry": {"coordinates":[80.519493,24.573009],"type":"Point"}
}