{
  "type": "Feature",
  "properties": {
    "gn:country":"IN",
    "gn:fcode":"PPL",
    "gn:pop":12023,
    "iso:country":"IN",
    "name:ben_x_preferred":[
        "\u09af\u09bc\u09c7\u09b2\u09ac\u09be\u09b0\u09cd\u0997"
    ],
    "name:bpy_x_preferred":[
        "\u09af\u09bc\u09c7\u09b2\u09ac\u09be\u09b0\u09cd\u0997"
    ],
    "name:ceb_x_preferred":[
        "Yelbarga"
    ],
    "name:deu_x_preferred":[
        "Yelbarga"
    ],
    "name:eng_x_preferred":[
        "Yelburga"
    ],
    "name:fra_x_preferred":[
        "Yelbarga"
    ],
    "name:guj_x_preferred":[
        "\u0aaf\u0ac7\u0ab2\u0aac\u0ac1\u0ab0\u0acd\u0a97\u0abe"
    ],
    "name:ita_x_preferred":[
        "Yelbarga"
    ],
    "name:jpn_x_preferred":[
        "\u30a4\u30a7\u30eb\u30d0\u30fc\u30ac"
    ],
    "name:kan_x_preferred":[
        "\u0caf\u0cb2\u0cac\u0cc1\u0cb0\u0ccd\u0c97\u0cbe"
    ],
    "name:kor_x_preferred":[
        "\uc610\ubd80\uac00"
    ],
    "name:msa_x_preferred":[
        "Yelburga"
    ],
    "name:nan_x_preferred":[
        "Yelbarga"
    ],
    "name:new_x_preferred":[
        "\u092f\u0947\u0932\u094d\u092c\u093e\u0930\u094d\u0917\u093e"
    ],
    "name:nld_x_preferred":[
        "Yelbarga"
    ],
    "name:por_x_preferred":[
        "Yelbarga"
    ],
    "name:rus_x_preferred":[
        "\u0415\u043b\u0431\u0443\u0440\u0433\u0430"
    ],
    "name:spa_x_preferred":[
        "Yelburga"
    ],
    "name:swe_x_preferred":[
        "Yelbarga"
    ],
    "name:tam_x_preferred":[
        "\u0b8f\u0bb2\u0bcd\u0baa\u0bc1\u0bb0\u0bcd\u0b95\u0bbe"
    ],
    "name:tel_x_preferred":[
        "\u0c0e\u0c32\u0c2c\u0c41\u0c30\u0c4d\u0c17"
    ],
    "name:urd_x_preferred":[
        "\u06cc\u0644\u0628\u0631\u06af\u06c1"
    ],
    "name:vie_x_preferred":[
        "Yelbarga"
    ],
    "name:zho_x_preferred":[
        "\u8036\u5c14\u5df4\u5c14\u52a0"
    ],
    "qs:name":"Yelbarga",
    "qs:photos_9r":0,
    "qs:photos_sr":0,
    "qs:pop_sr":"6",
    "wd:wordcount":268,
    "wof:name":"Yelbarga",
    "wof:placetype":"locality",
    "wof:population":12023
},
  "geometry": {"coordinates":[76.01184000000001,15.61545],"type":"Point"}
}