{
  "type": "Feature",
  "properties": {
    "iso:country":"IN",
    "ks:ks_name":"Badura",
    "ks:ks_pop":867,
    "ks:ks_type":"HABITATION",
    "name:eng_x_preferred":[
        "Badura"
    ],
    "wof:name":"Badura",
    "wof:placetype":"locality",
    "wof:population":867
},
  "geometry": {"coordinates":[82.972469,24.149436],"type":"Point"}
}