{
  "type": "Feature",
  "properties": {
    "iso:country":"IN",
    "ks:ks_name":"Ellajanga",
    "ks:ks_pop":260,
    "ks:ks_type":"HABITATION",
    "name:eng_x_preferred":[
        "Ellajanga"
    ],
    "wof:name":"Ellajanga",
    "wof:placetype":"locality",
    "wof:population":260
},
  "geometry": {"coordinates":[85.961339,19.881046],"type":"Point"}
}