{
  "type": "Feature",
  "properties": {
    "iso:country":"IN",
    "ks:ks_name":"Paraspura",
    "ks:ks_pop":57,
    "ks:ks_type":"HABITATION",
    "name:eng_x_preferred":[
        "Paraspura"
    ],
    "wof:name":"Paraspura",
    "wof:placetype":"locality",
    "wof:population":57
},
  "geometry": {"coordinates":[76.704122,23.931071],"type":"Point"}
}