{
  "type": "Feature",
  "properties": {
    "iso:country":"IN",
    "ks:ks_name":"Bokhra",
    "ks:ks_pop":148,
    "ks:ks_type":"VILLAGE",
    "name:eng_x_preferred":[
        "Bokhra"
    ],
    "wof:name":"Bokhra",
    "wof:placetype":"locality",
    "wof:population":148
},
  "geometry": {"coordinates":[84.97995899999999,24.279152],"type":"Point"}
}