{
  "type": "Feature",
  "properties": {
    "iso:country":"IN",
    "ks:ks_name":"Paschim Para",
    "ks:ks_pop":1510,
    "ks:ks_type":"HABITATION",
    "name:eng_x_preferred":[
        "Paschim Para"
    ],
    "wof:name":"Paschim Para",
    "wof:placetype":"locality",
    "wof:population":1510
},
  "geometry": {"coordinates":[89.436851,26.396835],"type":"Point"}
}