{
  "type": "Feature",
  "properties": {
    "iso:country":"IN",
    "ks:ks_name":"Ghaghar",
    "ks:ks_pop":176,
    "ks:ks_type":"HABITATION",
    "name:eng_x_preferred":[
        "Ghaghar"
    ],
    "wof:name":"Ghaghar",
    "wof:placetype":"locality",
    "wof:population":176
},
  "geometry": {"coordinates":[85.293159,24.926899],"type":"Point"}
}