{
  "type": "Feature",
  "properties": {
    "gn:admin1_code":"34.0",
    "gn:admin2_code":"207.0",
    "gn:asciiname":"Tingri",
    "gn:country_code":"IN",
    "gn:dem":54,
    "gn:feature_class":"P",
    "gn:feature_code":"PPL",
    "gn:name":"Tingri",
    "gn:population":0,
    "gn:timezone":"Asia/Kolkata",
    "iso:country":"IN",
    "name:ita_x_preferred":[
        "Tingri"
    ],
    "name:nld_x_preferred":[
        "Tingri"
    ],
    "wof:name":"Tingri",
    "wof:placetype":"locality"
},
  "geometry": {"coordinates":[86.41028,26.16804],"type":"Point"}
}