{
  "type": "Feature",
  "properties": {
    "iso:country":"IN",
    "ks:ks_name":"Jhiriya Koparihan Tola",
    "ks:ks_pop":899,
    "ks:ks_type":"VILLAGE",
    "name:eng_x_preferred":[
        "Jhiriya Koparihan Tola"
    ],
    "wof:name":"Jhiriya Koparihan Tola",
    "wof:placetype":"locality",
    "wof:population":899
},
  "geometry": {"coordinates":[81.192322,24.456826],"type":"Point"}
}