{
  "type": "Feature",
  "properties": {
    "iso:country":"IN",
    "ks:ks_name":"Kolvera",
    "ks:ks_pop":795,
    "ks:ks_type":"VILLAGE",
    "name:eng_x_preferred":[
        "Kolvera"
    ],
    "wof:name":"Kolvera",
    "wof:placetype":"locality",
    "wof:population":795
},
  "geometry": {"coordinates":[73.29791400000001,20.25835],"type":"Point"}
}