{
  "type": "Feature",
  "properties": {
    "iso:country":"IN",
    "ks:ks_name":"Bhutna",
    "ks:ks_pop":4342,
    "ks:ks_type":"HABITATION",
    "name:eng_x_preferred":[
        "Bhutna"
    ],
    "wof:name":"Bhutna",
    "wof:placetype":"locality",
    "wof:population":4342
},
  "geometry": {"coordinates":[75.486778,30.437789],"type":"Point"}
}