{
  "type": "Feature",
  "properties": {
    "iso:country":"IN",
    "ks:ks_name":"Mohaddinagar",
    "ks:ks_pop":379,
    "ks:ks_type":"HABITATION",
    "name:eng_x_preferred":[
        "Mohaddinagar"
    ],
    "wof:name":"Mohaddinagar",
    "wof:placetype":"locality",
    "wof:population":379
},
  "geometry": {"coordinates":[82.57135100000001,26.560525],"type":"Point"}
}