{
  "type": "Feature",
  "properties": {
    "iso:country":"IN",
    "ks:ks_name":"Pathori No 1",
    "ks:ks_pop":305,
    "ks:ks_type":"HABITATION",
    "ks:ks_uagg_main":0,
    "name:eng_x_preferred":[
        "Pathori No 1"
    ],
    "wof:name":"Pathori No 1",
    "wof:placetype":"neighbourhood",
    "wof:population":305
},
  "geometry": {"coordinates":[93.82587100000001,26.714971],"type":"Point"}
}