{
  "type": "Feature",
  "properties": {
    "iso:country":"IN",
    "ks:ks_name":"Kuranbaglow",
    "ks:ks_pop":550,
    "ks:ks_type":"HABITATION",
    "name:eng_x_preferred":[
        "Kuranbaglow"
    ],
    "wof:name":"Kuranbaglow",
    "wof:placetype":"locality",
    "wof:population":550
},
  "geometry": {"coordinates":[74.923794,17.939806],"type":"Point"}
}