{
  "type": "Feature",
  "properties": {
    "iso:country":"IN",
    "ks:ks_alt_nam":"JULEWADI ROAD",
    "ks:ks_name":"Julewadi Road",
    "ks:ks_pop":150,
    "ks:ks_type":"HABITATION",
    "name:eng_x_preferred":[
        "Julewadi Road"
    ],
    "wof:name":"Julewadi Road",
    "wof:placetype":"locality",
    "wof:population":150
},
  "geometry": {"coordinates":[74.50778099999999,17.029904],"type":"Point"}
}