{
  "type": "Feature",
  "properties": {
    "iso:country":"IN",
    "ks:ks_name":"Kurikempanadoddi",
    "ks:ks_pop":817,
    "ks:ks_type":"HABITATION",
    "name:eng_x_preferred":[
        "Kurikempanadoddi"
    ],
    "wof:name":"Kurikempanadoddi",
    "wof:placetype":"locality",
    "wof:population":817
},
  "geometry": {"coordinates":[77.013777,12.489449],"type":"Point"}
}