{
  "type": "Feature",
  "properties": {
    "iso:country":"IN",
    "ks:ks_name":"N Kothuru",
    "ks:ks_pop":170,
    "ks:ks_type":"HABITATION",
    "name:eng_x_preferred":[
        "N Kothuru"
    ],
    "wof:name":"N Kothuru",
    "wof:placetype":"locality",
    "wof:population":170
},
  "geometry": {"coordinates":[80.86703799999999,18.073691],"type":"Point"}
}