{
  "type": "Feature",
  "properties": {
    "iso:country":"IN",
    "ks:ks_name":"Janathepada",
    "ks:ks_pop":365,
    "ks:ks_type":"HABITATION",
    "ks:ks_uagg_main":0,
    "name:eng_x_preferred":[
        "Janathepada"
    ],
    "wof:name":"Janathepada",
    "wof:placetype":"neighbourhood",
    "wof:population":365
},
  "geometry": {"coordinates":[72.789608,19.865086],"type":"Point"}
}