{
  "type": "Feature",
  "properties": {
    "iso:country":"IN",
    "ks:ks_name":"Gargoti Tanda",
    "ks:ks_pop":440,
    "ks:ks_type":"HABITATION",
    "name:eng_x_preferred":[
        "Gargoti Tanda"
    ],
    "wof:name":"Gargoti Tanda",
    "wof:placetype":"locality",
    "wof:population":440
},
  "geometry": {"coordinates":[76.620632,19.056766],"type":"Point"}
}