{
  "type": "Feature",
  "properties": {
    "iso:country":"IN",
    "ks:ks_name":"Beri",
    "ks:ks_pop":123,
    "ks:ks_type":"VILLAGE",
    "name:eng_x_preferred":[
        "Beri"
    ],
    "name:hin_x_preferred":[
        "\u092c\u0947\u0930\u0940"
    ],
    "wof:name":"Beri",
    "wof:placetype":"locality",
    "wof:population":123
},
  "geometry": {"coordinates":[86.170008,23.997473],"type":"Point"}
}