{
  "type": "Feature",
  "properties": {
    "iso:country":"IN",
    "ks:ks_alt_nam":"Kandhai purwa",
    "ks:ks_name":"Kandhai Purwa",
    "ks:ks_pop":85,
    "ks:ks_type":"HABITATION",
    "ks:ks_uagg_main":0,
    "name:eng_x_preferred":[
        "Kandhai Purwa"
    ],
    "wof:name":"Kandhai Purwa",
    "wof:placetype":"neighbourhood",
    "wof:population":85
},
  "geometry": {"coordinates":[81.337902,27.358067],"type":"Point"}
}