{
  "type": "Feature",
  "properties": {
    "iso:country":"IN",
    "ks:ks_name":"Ghorkhand Malla",
    "ks:ks_pop":28,
    "ks:ks_type":"VILLAGE",
    "name:eng_x_preferred":[
        "Ghorkhand Malla"
    ],
    "wof:name":"Ghorkhand Malla",
    "wof:placetype":"locality",
    "wof:population":28
},
  "geometry": {"coordinates":[79.003276,29.658561],"type":"Point"}
}