{
  "type": "Feature",
  "properties": {
    "iso:country":"IN",
    "ks:ks_name":"Bharathi Nagar",
    "ks:ks_pop":570,
    "ks:ks_type":"HABITATION",
    "ks:ks_uagg_main":0,
    "name:eng_x_preferred":[
        "Bharathi Nagar"
    ],
    "wof:name":"Bharathi Nagar",
    "wof:placetype":"locality",
    "wof:population":570
},
  "geometry": {"coordinates":[80.05715499999999,12.974391],"type":"Point"}
}