{
  "type": "Feature",
  "properties": {
    "gn:admin1_code":"2.0",
    "gn:admin2_code":"543.0",
    "gn:asciiname":"Gilledivalasa",
    "gn:country_code":"IN",
    "gn:dem":213,
    "gn:feature_class":"P",
    "gn:feature_code":"PPL",
    "gn:name":"Gilledivalasa",
    "gn:population":0,
    "gn:timezone":"Asia/Kolkata",
    "iso:country":"IN",
    "ks:ks_name":"Jilleduvalasa",
    "ks:ks_pop":112,
    "ks:ks_type":"VILLAGE",
    "name:eng_x_preferred":[
        "Jilleduvalasa"
    ],
    "name:eng_x_variant":[
        "Gilledivalasa"
    ],
    "wof:name":"Jilleduvalasa",
    "wof:placetype":"locality",
    "wof:population":112
},
  "geometry": {"coordinates":[83.126915,18.599246],"type":"Point"}
}