{
  "type": "Feature",
  "properties": {
    "gn:admin1_code":"16",
    "gn:admin2_code":"525.0",
    "gn:asciiname":"Khandalkarwadi",
    "gn:country_code":"IN",
    "gn:dem":548,
    "gn:feature_class":"P",
    "gn:feature_code":"PPL",
    "gn:name":"Khandalkarw\u0101di",
    "gn:population":0,
    "gn:timezone":"Asia/Kolkata",
    "iso:country":"IN",
    "wof:name":"Khandalkarwadi",
    "wof:placetype":"locality"
},
  "geometry": {"coordinates":[76.07928000000003,17.92067],"type":"Point"}
}