{
  "type": "Feature",
  "properties": {
    "iso:country":"IN",
    "ks:ks_name":"Taldihipara",
    "ks:ks_pop":138,
    "ks:ks_type":"HABITATION",
    "name:eng_x_preferred":[
        "Taldihipara"
    ],
    "wof:name":"Taldihipara",
    "wof:placetype":"locality",
    "wof:population":138
},
  "geometry": {"coordinates":[84.11717,22.247469],"type":"Point"}
}