{
  "type": "Feature",
  "properties": {
    "iso:country":"IN",
    "ks:ks_name":"Barhuncha",
    "ks:ks_type":"VILLAGE",
    "name:eng_x_preferred":[
        "Barhuncha"
    ],
    "wof:name":"Barhuncha",
    "wof:placetype":"locality"
},
  "geometry": {"coordinates":[84.039952,26.088742],"type":"Point"}
}