{
  "type": "Feature",
  "properties": {
    "iso:country":"IN",
    "ks:ks_name":"Merkul",
    "ks:ks_type":"VILLAGE",
    "name:eng_x_preferred":[
        "Merkul"
    ],
    "wof:name":"Merkul",
    "wof:placetype":"locality"
},
  "geometry": {"coordinates":[83.168757,19.76452],"type":"Point"}
}