{
  "type": "Feature",
  "properties": {
    "iso:country":"IN",
    "ks:ks_name":"Thanakkankulam",
    "ks:ks_pop":2025,
    "ks:ks_type":"URBAN",
    "ks:ks_uagg_main":0,
    "name:eng_x_preferred":[
        "Thanakkankulam"
    ],
    "wof:name":"Thanakkankulam",
    "wof:placetype":"locality",
    "wof:population":2025
},
  "geometry": {"coordinates":[78.040209,9.888954],"type":"Point"}
}