{
  "type": "Feature",
  "properties": {
    "iso:country":"IN",
    "ks:ks_name":"Balabhut",
    "ks:ks_pop":9033,
    "ks:ks_type":"VILLAGE",
    "name:eng_x_preferred":[
        "Balabhut"
    ],
    "wof:name":"Balabhut",
    "wof:placetype":"locality",
    "wof:population":9033
},
  "geometry": {"coordinates":[89.696861,26.205592],"type":"Point"}
}