{
  "type": "Feature",
  "properties": {
    "iso:country":"IN",
    "ks:ks_name":"Loharna",
    "ks:ks_pop":86,
    "ks:ks_type":"HABITATION",
    "name:eng_x_preferred":[
        "Loharna"
    ],
    "wof:name":"Loharna",
    "wof:placetype":"locality",
    "wof:population":86
},
  "geometry": {"coordinates":[77.95481599999999,30.55447],"type":"Point"}
}