{
  "type": "Feature",
  "properties": {
    "gn:admin1_code":"25.0",
    "gn:admin2_code":"605.0",
    "gn:asciiname":"Agaram",
    "gn:country_code":"IN",
    "gn:dem":132,
    "gn:feature_class":"P",
    "gn:feature_code":"PPL",
    "gn:name":"Agaram",
    "gn:population":0,
    "gn:timezone":"Asia/Kolkata",
    "iso:country":"IN",
    "name:ara_x_preferred":[
        "\u0623\u063a\u0627\u0631\u0627\u0645"
    ],
    "name:ben_bn_x_preferred":[
        "\u0986\u0997\u09be\u09b0\u09be\u09ae"
    ],
    "name:ben_in_x_preferred":[
        "\u0986\u0997\u09be\u09b0\u09be\u09ae"
    ],
    "name:guj_x_preferred":[
        "\u0a85\u0a97\u0ab0\u0aae"
    ],
    "name:hin_x_preferred":[
        "\u0905\u0917\u0930\u092e"
    ],
    "name:kan_x_preferred":[
        "\u0c85\u0c97\u0cb0\u0c82"
    ],
    "name:mal_x_preferred":[
        "\u0d05\u0d17\u0d30\u0d02"
    ],
    "name:mar_x_preferred":[
        "\u0906\u0917\u0930\u092e"
    ],
    "name:pan_x_preferred":[
        "\u0a05\u0a17\u0a3e\u0a30\u0a3e\u0a2e"
    ],
    "name:tam_x_preferred":[
        "\u0b85\u0b95\u0bb0\u0bae\u0bcd"
    ],
    "name:tel_x_preferred":[
        "\u0c05\u0c17\u0c3e\u0c30\u0c02"
    ],
    "name:urd_x_preferred":[
        "\u0622\u06af\u0627\u0631\u0627\u0645"
    ],
    "wof:name":"Agaram",
    "wof:placetype":"locality"
},
  "geometry": {"coordinates":[79.40908,12.77408],"type":"Point"}
}