{
  "type": "Feature",
  "properties": {
    "iso:country":"IN",
    "ks:ks_alt_nam":"koramarahatti",
    "ks:ks_name":"Koramarahatti",
    "ks:ks_pop":74,
    "ks:ks_type":"HABITATION",
    "ks:ks_uagg_main":0,
    "name:eng_x_preferred":[
        "Koramarahatti"
    ],
    "wof:name":"Koramarahatti",
    "wof:placetype":"neighbourhood",
    "wof:population":74
},
  "geometry": {"coordinates":[76.63685599999999,13.160991],"type":"Point"}
}