{
  "type": "Feature",
  "properties": {
    "gn:admin1_code":"35.0",
    "gn:admin2_code":"450.0",
    "gn:asciiname":"Paraikap",
    "gn:country_code":"IN",
    "gn:dem":443,
    "gn:feature_class":"P",
    "gn:feature_code":"PPL",
    "gn:name":"Paraik\u0101p",
    "gn:population":0,
    "gn:timezone":"Asia/Kolkata",
    "iso:country":"IN",
    "wof:name":"Paraikap",
    "wof:placetype":"locality"
},
  "geometry": {"coordinates":[80.5663,23.69982000000001],"type":"Point"}
}