{
  "type": "Feature",
  "properties": {
    "gn:admin1_code":"10.0",
    "gn:admin2_code":"73.0",
    "gn:asciiname":"Buchi",
    "gn:country_code":"IN",
    "gn:dem":245,
    "gn:feature_class":"P",
    "gn:feature_code":"PPL",
    "gn:name":"B\u016bchi",
    "gn:population":0,
    "gn:timezone":"Asia/Kolkata",
    "iso:country":"IN",
    "name:ceb_x_preferred":[
        "Buchi"
    ],
    "name:swe_x_preferred":[
        "Buchi"
    ],
    "wof:name":"Buchi",
    "wof:placetype":"locality"
},
  "geometry": {"coordinates":[76.65368000000002,29.7509],"type":"Point"}
}