{
  "type": "Feature",
  "properties": {
    "gn:admin1_code":"34.0",
    "gn:admin2_code":"227.0",
    "gn:asciiname":"Rata",
    "gn:country_code":"IN",
    "gn:dem":62,
    "gn:feature_class":"P",
    "gn:feature_code":"PPL",
    "gn:name":"R\u0101ta",
    "gn:population":0,
    "gn:timezone":"Asia/Kolkata",
    "iso:country":"IN",
    "name:cat_x_preferred":[
        "Rata"
    ],
    "name:ceb_x_preferred":[
        "Rata"
    ],
    "name:deu_x_preferred":[
        "Rata"
    ],
    "name:fin_x_preferred":[
        "Rata"
    ],
    "name:heb_x_preferred":[
        "\u05e8\u05d0\u05d8\u05d4"
    ],
    "name:rus_x_preferred":[
        "\u0420\u0430\u0442\u0430"
    ],
    "name:spa_x_preferred":[
        "Rata"
    ],
    "name:ukr_x_preferred":[
        "\u0420\u0430\u0442\u0430"
    ],
    "wof:name":"Rata",
    "wof:placetype":"locality"
},
  "geometry": {"coordinates":[86.09366999999997,25.03531],"type":"Point"}
}