{
  "type": "Feature",
  "properties": {
    "iso:country":"IN",
    "ks:ks_name":"Baninayakanadoddi",
    "ks:ks_pop":291,
    "ks:ks_type":"HABITATION",
    "name:eng_x_preferred":[
        "Baninayakanadoddi"
    ],
    "wof:name":"Baninayakanadoddi",
    "wof:placetype":"locality",
    "wof:population":291
},
  "geometry": {"coordinates":[77.54850999999999,12.380825],"type":"Point"}
}