{
  "type": "Feature",
  "properties": {
    "iso:country":"IN",
    "ks:ks_name":"Bhalkudar",
    "ks:ks_pop":980,
    "ks:ks_type":"VILLAGE",
    "name:eng_x_preferred":[
        "Bhalkudar"
    ],
    "wof:name":"Bhalkudar",
    "wof:placetype":"locality",
    "wof:population":980
},
  "geometry": {"coordinates":[86.393467,24.366849],"type":"Point"}
}