{
  "type": "Feature",
  "properties": {
    "iso:country":"IN",
    "ks:ks_name":"Bhoirpada",
    "ks:ks_pop":396,
    "ks:ks_type":"HABITATION",
    "ks:ks_uagg_main":0,
    "name:eng_x_preferred":[
        "Bhoirpada"
    ],
    "wof:name":"Bhoirpada",
    "wof:placetype":"neighbourhood",
    "wof:population":396
},
  "geometry": {"coordinates":[73.138715,19.340427],"type":"Point"}
}