{
  "type": "Feature",
  "properties": {
    "iso:country":"IN",
    "ks:ks_name":"Sainanur",
    "ks:ks_pop":785,
    "ks:ks_type":"VILLAGE",
    "name:eng_x_preferred":[
        "Sainanur"
    ],
    "wof:name":"Sainanur",
    "wof:placetype":"locality",
    "wof:population":785
},
  "geometry": {"coordinates":[79.22175799999999,29.688348],"type":"Point"}
}