{
  "type": "Feature",
  "properties": {
    "gn:admin1_code":"34.0",
    "gn:admin2_code":"234.0",
    "gn:asciiname":"Sakhara",
    "gn:country_code":"IN",
    "gn:dem":112,
    "gn:feature_class":"P",
    "gn:feature_code":"PPL",
    "gn:name":"Sakhara",
    "gn:population":0,
    "gn:timezone":"Asia/Kolkata",
    "iso:country":"IN",
    "ks:ks_name":"Sakhara",
    "ks:ks_pop":4740,
    "ks:ks_type":"VILLAGE",
    "ks:ks_uagg_main":0,
    "name:eng_x_preferred":[
        "Sakhara"
    ],
    "wof:name":"Sakhara",
    "wof:placetype":"neighbourhood",
    "wof:population":4740
},
  "geometry": {"coordinates":[84.15839699999999,24.909061],"type":"Point"}
}