{
  "type": "Feature",
  "properties": {
    "iso:country":"IN",
    "ks:ks_name":"Khajoori",
    "ks:ks_pop":92,
    "ks:ks_type":"VILLAGE",
    "name:eng_x_preferred":[
        "Khajoori"
    ],
    "wof:name":"Khajoori",
    "wof:placetype":"locality",
    "wof:population":92
},
  "geometry": {"coordinates":[74.78176000000001,23.672908],"type":"Point"}
}