{
  "type": "Feature",
  "properties": {
    "iso:country":"IN",
    "ks:ks_name":"Nidigurthi",
    "ks:ks_pop":229,
    "ks:ks_type":"HABITATION",
    "name:eng_x_preferred":[
        "Nidigurthi"
    ],
    "wof:name":"Nidigurthi",
    "wof:placetype":"locality",
    "wof:population":229
},
  "geometry": {"coordinates":[80.158247,13.885665],"type":"Point"}
}