{
  "type": "Feature",
  "properties": {
    "gn:admin1_code":"19.0",
    "gn:admin2_code":"569.0",
    "gn:asciiname":"Koderi",
    "gn:country_code":"IN",
    "gn:dem":12,
    "gn:feature_class":"P",
    "gn:feature_code":"PPL",
    "gn:name":"Koderi",
    "gn:population":0,
    "gn:timezone":"Asia/Kolkata",
    "iso:country":"IN",
    "ks:ks_name":"Koderi",
    "ks:ks_pop":480,
    "ks:ks_type":"HABITATION",
    "name:eng_x_preferred":[
        "Koderi"
    ],
    "name:tam_x_preferred":[
        "\u0b95\u0bcb\u0b9f\u0bc7\u0bb0\u0bbf"
    ],
    "wof:name":"Koderi",
    "wof:placetype":"locality",
    "wof:population":480
},
  "geometry": {"coordinates":[74.624205,13.814293],"type":"Point"}
}