{
  "type": "Feature",
  "properties": {
    "gn:admin1_code":"19.0",
    "gn:admin2_code":"569.0",
    "gn:asciiname":"Koderi",
    "gn:country_code":"IN",
    "gn:dem":12,
    "gn:feature_class":"P",
    "gn:feature_code":"PPL",
    "gn:name":"Koderi",
    "gn:population":0,
    "gn:timezone":"Asia/Kolkata",
    "iso:country":"IN",
    "name:tam_x_preferred":[
        "\u0b95\u0bcb\u0b9f\u0bc7\u0bb0\u0bbf"
    ],
    "wof:name":"Koderi",
    "wof:placetype":"locality"
},
  "geometry": {"coordinates":[74.63035000000001,13.8015],"type":"Point"}
}