{
  "type": "Feature",
  "properties": {
    "iso:country":"IN",
    "ks:ks_name":"Mahulia",
    "ks:ks_pop":858,
    "ks:ks_type":"VILLAGE",
    "name:eng_x_preferred":[
        "Mahulia"
    ],
    "wof:name":"Mahulia",
    "wof:placetype":"locality",
    "wof:population":858
},
  "geometry": {"coordinates":[86.751502,20.599034],"type":"Point"}
}