{
  "type": "Feature",
  "properties": {
    "iso:country":"IN",
    "ks:ks_name":"Kadamdiha",
    "ks:ks_pop":66,
    "ks:ks_type":"VILLAGE",
    "name:eng_x_preferred":[
        "Kadamdiha"
    ],
    "wof:name":"Kadamdiha",
    "wof:placetype":"locality",
    "wof:population":66
},
  "geometry": {"coordinates":[86.610716,22.125515],"type":"Point"}
}