{
  "type": "Feature",
  "properties": {
    "iso:country":"IN",
    "ks:ks_name":"Moti Daberi",
    "ks:ks_pop":40,
    "ks:ks_type":"VILLAGE",
    "name:eng_x_preferred":[
        "Moti Daberi"
    ],
    "wof:name":"Moti Daberi",
    "wof:placetype":"locality",
    "wof:population":40
},
  "geometry": {"coordinates":[73.521143,21.767541],"type":"Point"}
}