{
  "type": "Feature",
  "properties": {
    "gn:admin1_code":"30.0",
    "gn:admin2_code":"256.0",
    "gn:asciiname":"Koloriang",
    "gn:country_code":"IN",
    "gn:dem":1141,
    "gn:feature_class":"P",
    "gn:feature_code":"PPL",
    "gn:name":"Kolori\u0101ng",
    "gn:population":0,
    "gn:timezone":"Asia/Kolkata",
    "iso:country":"IN",
    "name:ceb_x_preferred":[
        "Kolori\u0101ng"
    ],
    "name:fra_x_preferred":[
        "Koloriang"
    ],
    "name:guj_x_preferred":[
        "\u0a95\u0acb\u0ab2\u0acb\u0ab0\u0ac0\u0aaf\u0abe\u0a82\u0a97"
    ],
    "name:hin_x_preferred":[
        "\u0915\u094b\u0932\u094b\u0930\u093f\u0906\u0902\u0917"
    ],
    "name:ita_x_preferred":[
        "Koloriang"
    ],
    "name:spa_x_preferred":[
        "Koloriang"
    ],
    "name:swe_x_preferred":[
        "Kolori\u0101ng"
    ],
    "name:tgl_x_preferred":[
        "Koloriang"
    ],
    "name:und_x_variant":[
        "Kolori\u0101ng"
    ],
    "name:urd_x_preferred":[
        "\u06a9\u0648\u0644\u0648\u0631\u06cc\u0627\u0646\u06af"
    ],
    "wof:name":"Koloriang",
    "wof:placetype":"locality"
},
  "geometry": {"coordinates":[93.35500999999999,27.91001],"type":"Point"}
}