{
  "type": "Feature",
  "properties": {
    "iso:country":"IN",
    "ks:ks_alt_nam":"pooraparambu",
    "ks:ks_name":"Pooraparambu",
    "ks:ks_pop":1012,
    "ks:ks_type":"HABITATION",
    "name:eng_x_preferred":[
        "Pooraparambu"
    ],
    "wof:name":"Pooraparambu",
    "wof:placetype":"locality",
    "wof:population":1012
},
  "geometry": {"coordinates":[76.39064,9.935681],"type":"Point"}
}