{
  "type": "Feature",
  "properties": {
    "iso:country":"IN",
    "ks:ks_name":"Beltekari",
    "ks:ks_pop":544,
    "ks:ks_type":"HABITATION",
    "name:eng_x_preferred":[
        "Beltekari"
    ],
    "wof:name":"Beltekari",
    "wof:placetype":"locality",
    "wof:population":544
},
  "geometry": {"coordinates":[86.738896,24.337954],"type":"Point"}
}