{
  "type": "Feature",
  "properties": {
    "iso:country":"IN",
    "ks:ks_name":"Tikarpada",
    "ks:ks_pop":278,
    "ks:ks_type":"HABITATION",
    "name:eng_x_preferred":[
        "Tikarpada"
    ],
    "wof:name":"Tikarpada",
    "wof:placetype":"locality",
    "wof:population":278
},
  "geometry": {"coordinates":[82.406718,18.61287],"type":"Point"}
}