{
  "type": "Feature",
  "properties": {
    "iso:country":"IN",
    "ks:ks_alt_nam":"lala purwa",
    "ks:ks_name":"Lala Purwa",
    "ks:ks_pop":422,
    "ks:ks_type":"HABITATION",
    "name:eng_x_preferred":[
        "Lala Purwa"
    ],
    "wof:name":"Lala Purwa",
    "wof:placetype":"locality",
    "wof:population":422
},
  "geometry": {"coordinates":[81.60682,27.364403],"type":"Point"}
}