{
  "type": "Feature",
  "properties": {
    "gn:admin1_code":"9.0",
    "gn:admin2_code":"485.0",
    "gn:asciiname":"Undar",
    "gn:country_code":"IN",
    "gn:dem":324,
    "gn:feature_class":"P",
    "gn:feature_code":"PPL",
    "gn:name":"Und\u0101r",
    "gn:population":0,
    "gn:timezone":"Asia/Kolkata",
    "iso:country":"IN",
    "ks:ks_alt_nam":"Und\u0101r",
    "ks:ks_name":"Undar",
    "ks:ks_pop":1653,
    "ks:ks_type":"VILLAGE",
    "name:eng_x_preferred":[
        "Undar"
    ],
    "name:eng_x_variant":[
        "Und\u0101r"
    ],
    "wof:name":"Undar",
    "wof:placetype":"locality",
    "wof:population":1653
},
  "geometry": {"coordinates":[74.118611,22.722556],"type":"Point"}
}