{
  "type": "Feature",
  "properties": {
    "iso:country":"IN",
    "ks:ks_alt_nam":"SUBANANDA PARA",
    "ks:ks_name":"Subananda Para",
    "ks:ks_pop":135,
    "ks:ks_type":"HABITATION",
    "name:eng_x_preferred":[
        "Subananda Para"
    ],
    "wof:name":"Subananda Para",
    "wof:placetype":"locality",
    "wof:population":135
},
  "geometry": {"coordinates":[91.72011000000001,23.894309],"type":"Point"}
}