{
  "type": "Feature",
  "properties": {
    "gn:admin1_code":"16",
    "gn:admin2_code":"500.0",
    "gn:asciiname":"Dhongardi",
    "gn:country_code":"IN",
    "gn:dem":235,
    "gn:feature_class":"P",
    "gn:feature_code":"PPL",
    "gn:name":"Dhongardi",
    "gn:population":0,
    "gn:timezone":"Asia/Kolkata",
    "iso:country":"IN",
    "wof:name":"Dhongardi",
    "wof:placetype":"locality"
},
  "geometry": {"coordinates":[76.24763,20.9355],"type":"Point"}
}