{
  "type": "Feature",
  "properties": {
    "iso:country":"IN",
    "ks:ks_name":"28 NP",
    "ks:ks_pop":300,
    "ks:ks_type":"VILLAGE",
    "ks:ks_uagg_main":0,
    "name:eng_x_preferred":[
        "28 NP"
    ],
    "wof:name":"28 NP",
    "wof:placetype":"neighbourhood",
    "wof:population":300
},
  "geometry": {"coordinates":[73.472469,29.479085],"type":"Point"}
}