{
  "type": "Feature",
  "properties": {
    "gn:admin1_code":"29",
    "gn:admin2_code":"243.0",
    "gn:asciiname":"Ravangla",
    "gn:country_code":"IN",
    "gn:dem":2022,
    "gn:feature_class":"P",
    "gn:feature_code":"PPL",
    "gn:name":"Ravangla",
    "gn:population":0,
    "gn:timezone":"Asia/Kolkata",
    "iso:country":"IN",
    "name:ara_x_preferred":[
        "\u0631\u0627\u0641\u0627\u0646\u062c\u0644\u0627"
    ],
    "name:epo_x_preferred":[
        "Ravangla"
    ],
    "name:fra_x_preferred":[
        "Ravangla"
    ],
    "name:ori_x_preferred":[
        "\u0b30\u0b3e\u0b2d\u0b19\u0b4d\u0b17\u0b33\u0b3e"
    ],
    "name:ukr_x_preferred":[
        "\u0420\u0430\u0432\u0430\u043d\u0491\u043b\u0430"
    ],
    "wof:name":"Ravangla",
    "wof:placetype":"locality"
},
  "geometry": {"coordinates":[88.36355,27.30589],"type":"Point"}
}