{
  "type": "Feature",
  "properties": {
    "gn:admin1_code":"29",
    "gn:admin2_code":"243.0",
    "gn:asciiname":"Ravangla",
    "gn:country_code":"IN",
    "gn:dem":2022,
    "gn:feature_class":"P",
    "gn:feature_code":"PPL",
    "gn:name":"Ravangla",
    "gn:population":0,
    "gn:timezone":"Asia/Kolkata",
    "iso:country":"IN",
    "wof:name":"Ravangla",
    "wof:placetype":"locality"
},
  "geometry": {"coordinates":[88.36355,27.30589],"type":"Point"}
}