{
  "type": "Feature",
  "properties": {
    "iso:country":"IN",
    "ks:ks_name":"Fulaira",
    "ks:ks_pop":0,
    "ks:ks_type":"VILLAGE",
    "name:eng_x_preferred":[
        "Fulaira"
    ],
    "wof:name":"Fulaira",
    "wof:placetype":"locality",
    "wof:population":0
},
  "geometry": {"coordinates":[78.054451,28.550633],"type":"Point"}
}