{
  "type": "Feature",
  "properties": {
    "gn:admin1_code":"35",
    "gn:admin2_code":"451.0",
    "gn:asciiname":"Biharia",
    "gn:country_code":"IN",
    "gn:dem":386,
    "gn:feature_class":"P",
    "gn:feature_code":"PPL",
    "gn:name":"Biharia",
    "gn:population":0,
    "gn:timezone":"Asia/Kolkata",
    "iso:country":"IN",
    "name:ceb_x_preferred":[
        "Comuna Biharia"
    ],
    "name:epo_x_preferred":[
        "Biharia"
    ],
    "name:fra_x_preferred":[
        "Biharia"
    ],
    "name:ita_x_preferred":[
        "Biharia"
    ],
    "name:msa_x_preferred":[
        "Biharia"
    ],
    "name:nld_x_preferred":[
        "Biharia"
    ],
    "name:por_x_preferred":[
        "Biharia"
    ],
    "name:ron_x_preferred":[
        "Comuna Biharia"
    ],
    "name:slk_x_preferred":[
        "Biharia"
    ],
    "name:sqi_x_preferred":[
        "Biharia"
    ],
    "name:srp_x_preferred":[
        "\u041e\u043f\u0448\u0442\u0438\u043d\u0430 \u0411\u0438\u0445\u0430\u0440\u0438\u0458\u0430"
    ],
    "name:ukr_x_preferred":[
        "\u0411\u0456\u0445\u0430\u0440\u0456\u044f"
    ],
    "name:vie_x_preferred":[
        "Biharia"
    ],
    "name:vol_x_preferred":[
        "Biharia"
    ],
    "name:zho_x_preferred":[
        "\u6bd4\u54c8\u91cc\u4e9e\u9109"
    ],
    "wof:name":"Biharia",
    "wof:placetype":"locality"
},
  "geometry": {"coordinates":[79.88724000000001,23.25166],"type":"Point"}
}