{
  "type": "Feature",
  "properties": {
    "iso:country":"IN",
    "ks:ks_name":"Nalkeri",
    "ks:ks_pop":1535,
    "ks:ks_type":"VILLAGE",
    "name:eng_x_preferred":[
        "Nalkeri"
    ],
    "wof:name":"Nalkeri",
    "wof:placetype":"locality",
    "wof:population":1535
},
  "geometry": {"coordinates":[75.757625,12.256469],"type":"Point"}
}