{
  "type": "Feature",
  "properties": {
    "iso:country":"IN",
    "ks:ks_name":"Jhakhron Ki Bhagal",
    "ks:ks_pop":478,
    "ks:ks_type":"HABITATION",
    "name:eng_x_preferred":[
        "Jhakhron Ki Bhagal"
    ],
    "wof:name":"Jhakhron Ki Bhagal",
    "wof:placetype":"locality",
    "wof:population":478
},
  "geometry": {"coordinates":[73.573988,24.884725],"type":"Point"}
}