{
  "type": "Feature",
  "properties": {
    "iso:country":"IN",
    "ks:ks_name":"Lokasahi",
    "ks:ks_pop":422,
    "ks:ks_type":"VILLAGE",
    "name:eng_x_preferred":[
        "Lokasahi"
    ],
    "wof:name":"Lokasahi",
    "wof:placetype":"locality",
    "wof:population":422
},
  "geometry": {"coordinates":[84.437996,19.019334],"type":"Point"}
}