{
  "type": "Feature",
  "properties": {
    "iso:country":"IN",
    "ks:ks_name":"Dujasar",
    "ks:ks_pop":301,
    "ks:ks_type":"HABITATION",
    "name:eng_x_preferred":[
        "Dujasar"
    ],
    "wof:name":"Dujasar",
    "wof:placetype":"locality",
    "wof:population":301
},
  "geometry": {"coordinates":[73.409181,27.166011],"type":"Point"}
}