{
  "type": "Feature",
  "properties": {
    "iso:country":"IN",
    "ks:ks_alt_nam":"Sult\u0101npur",
    "ks:ks_name":"Sultanpur",
    "ks:ks_type":"VILLAGE",
    "name:eng_x_preferred":[
        "Sultanpur"
    ],
    "name:eng_x_variant":[
        "Sult\u0101npur"
    ],
    "wof:name":"Sultanpur",
    "wof:placetype":"locality"
},
  "geometry": {"coordinates":[77.914919,28.320572],"type":"Point"}
}