{
  "type": "Feature",
  "properties": {
    "iso:country":"IN",
    "ks:ks_alt_nam":"Kalmati pathar Uttar supa",
    "ks:ks_name":"Kalmati Pathar Uttar Supa",
    "ks:ks_pop":234,
    "ks:ks_type":"HABITATION",
    "name:eng_x_preferred":[
        "Kalmati Pathar Uttar Supa"
    ],
    "wof:name":"Kalmati Pathar Uttar Supa",
    "wof:placetype":"locality",
    "wof:population":234
},
  "geometry": {"coordinates":[91.093299,26.614438],"type":"Point"}
}