{
  "type": "Feature",
  "properties": {
    "gn:admin1_code":"19.0",
    "gn:admin2_code":"566.0",
    "gn:asciiname":"Bharmanaikanadurga",
    "gn:country_code":"IN",
    "gn:dem":701,
    "gn:feature_class":"P",
    "gn:feature_code":"PPL",
    "gn:name":"Bharman\u0101ikanadurga",
    "gn:population":0,
    "gn:timezone":"Asia/Kolkata",
    "iso:country":"IN",
    "wof:name":"Bharmanaikanadurga",
    "wof:placetype":"neighbourhood"
},
  "geometry": {"coordinates":[76.13275,14.18261],"type":"Point"}
}