{
  "type": "Feature",
  "properties": {
    "gn:admin1_code":"34.0",
    "gn:admin2_code":"209.0",
    "gn:asciiname":"Dumaria",
    "gn:country_code":"IN",
    "gn:dem":61,
    "gn:feature_class":"P",
    "gn:feature_code":"PPL",
    "gn:name":"Dumaria",
    "gn:population":0,
    "gn:timezone":"Asia/Kolkata",
    "iso:country":"IN",
    "ks:ks_name":"Dumaria",
    "ks:ks_pop":573,
    "ks:ks_type":"VILLAGE",
    "ks:ks_uagg_main":0,
    "name:cat_x_preferred":[
        "Dumaria"
    ],
    "name:eng_x_preferred":[
        "Dumaria"
    ],
    "name:tam_x_preferred":[
        "\u0ba4\u0bc1\u0bae\u0bbe\u0bb0\u0bbf\u0baf\u0bbe"
    ],
    "wof:name":"Dumaria",
    "wof:placetype":"neighbourhood",
    "wof:population":573
},
  "geometry": {"coordinates":[87.323345,26.314711],"type":"Point"}
}