{
  "type": "Feature",
  "properties": {
    "gn:admin1_code":"25.0",
    "gn:admin2_code":"621.0",
    "gn:asciiname":"Maramadakki",
    "gn:country_code":"IN",
    "gn:dem":60,
    "gn:feature_class":"P",
    "gn:feature_code":"PPL",
    "gn:name":"Maramadakki",
    "gn:population":0,
    "gn:timezone":"Asia/Kolkata",
    "iso:country":"IN",
    "ks:ks_name":"Maramadakki",
    "ks:ks_pop":3563,
    "ks:ks_type":"VILLAGE",
    "ks:ks_uagg_main":0,
    "name:eng_x_preferred":[
        "Maramadakki"
    ],
    "name:tam_x_preferred":[
        "\u0bae\u0bb1\u0bae\u0b9f\u0b95\u0bcd\u0b95\u0bbf"
    ],
    "wof:name":"Maramadakki",
    "wof:placetype":"neighbourhood",
    "wof:population":3563
},
  "geometry": {"coordinates":[79.009625,10.288174],"type":"Point"}
}