{
  "type": "Feature",
  "properties": {
    "iso:country":"IN",
    "ks:ks_name":"Govindpur",
    "ks:ks_pop":464,
    "ks:ks_type":"HABITATION",
    "name:eng_x_preferred":[
        "Govindpur"
    ],
    "wof:name":"Govindpur",
    "wof:placetype":"locality",
    "wof:population":464
},
  "geometry": {"coordinates":[84.197002,25.790751],"type":"Point"}
}