{
  "type": "Feature",
  "properties": {
    "iso:country":"IN",
    "ks:ks_alt_nam":"L\u0101dhudera",
    "ks:ks_name":"Ladhudera",
    "ks:ks_pop":124,
    "ks:ks_type":"VILLAGE",
    "name:eng_x_preferred":[
        "Ladhudera"
    ],
    "name:eng_x_variant":[
        "L\u0101dhudera"
    ],
    "wof:name":"Ladhudera",
    "wof:placetype":"locality",
    "wof:population":124
},
  "geometry": {"coordinates":[84.516074,22.89222],"type":"Point"}
}