{
  "type": "Feature",
  "properties": {
    "iso:country":"IN",
    "ks:ks_name":"Sothamangalam",
    "ks:ks_pop":473,
    "ks:ks_type":"HABITATION",
    "name:eng_x_preferred":[
        "Sothamangalam"
    ],
    "wof:name":"Sothamangalam",
    "wof:placetype":"locality",
    "wof:population":473
},
  "geometry": {"coordinates":[79.600606,11.148789],"type":"Point"}
}