{
  "type": "Feature",
  "properties": {
    "gn:admin1_code":"38.0",
    "gn:admin2_code":"358.0",
    "gn:asciiname":"Bairia",
    "gn:country_code":"IN",
    "gn:dem":220,
    "gn:feature_class":"P",
    "gn:feature_code":"PPL",
    "gn:name":"Bairi\u0101",
    "gn:population":0,
    "gn:timezone":"Asia/Kolkata",
    "iso:country":"IN",
    "ks:ks_alt_nam":"Bairi\u0101",
    "ks:ks_name":"Bairia",
    "ks:ks_pop":1573,
    "ks:ks_type":"VILLAGE",
    "ks:ks_uagg_main":0,
    "name:bih_x_preferred":[
        "\u092c\u0948\u0930\u093f\u092f\u093e"
    ],
    "name:eng_x_preferred":[
        "Bairia"
    ],
    "name:eng_x_variant":[
        "Bairi\u0101"
    ],
    "name:hin_x_preferred":[
        "\u092c\u0948\u0930\u093f\u092f\u093e"
    ],
    "wof:name":"Bairia",
    "wof:placetype":"locality",
    "wof:population":1573
},
  "geometry": {"coordinates":[84.083056,24.06898],"type":"Point"}
}