{
  "type": "Feature",
  "properties": {
    "iso:country":"IN",
    "ks:ks_alt_nam":"mailped",
    "ks:ks_name":"Mailped",
    "ks:ks_pop":173,
    "ks:ks_type":"HABITATION",
    "name:eng_x_preferred":[
        "Mailped"
    ],
    "wof:name":"Mailped",
    "wof:placetype":"locality",
    "wof:population":173
},
  "geometry": {"coordinates":[85.43940499999999,22.634068],"type":"Point"}
}