{
  "type": "Feature",
  "properties": {
    "gn:admin1_code":"34",
    "gn:admin2_code":"218.0",
    "gn:asciiname":"Sadhpur",
    "gn:country_code":"IN",
    "gn:dem":66,
    "gn:feature_class":"P",
    "gn:feature_code":"PPL",
    "gn:name":"S\u0101dhpur",
    "gn:population":0,
    "gn:timezone":"Asia/Kolkata",
    "iso:country":"IN",
    "wof:name":"Sadhpur",
    "wof:placetype":"locality"
},
  "geometry": {"coordinates":[84.46828000000002,26.09512],"type":"Point"}
}