{
  "type": "Feature",
  "properties": {
    "iso:country":"IN",
    "ks:ks_name":"Ahir Toli",
    "ks:ks_pop":110,
    "ks:ks_type":"HABITATION",
    "name:eng_x_preferred":[
        "Ahir Toli"
    ],
    "wof:name":"Ahir Toli",
    "wof:placetype":"locality",
    "wof:population":110
},
  "geometry": {"coordinates":[83.95389400000001,25.539798],"type":"Point"}
}