{
  "type": "Feature",
  "properties": {
    "iso:country":"IN",
    "ks:ks_name":"Sauli",
    "ks:ks_pop":61,
    "ks:ks_type":"HABITATION",
    "name:eng_x_preferred":[
        "Sauli"
    ],
    "wof:name":"Sauli",
    "wof:placetype":"locality",
    "wof:population":61
},
  "geometry": {"coordinates":[80.123756,29.658514],"type":"Point"}
}