{
  "type": "Feature",
  "properties": {
    "gn:admin1_code":"34.0",
    "gn:admin2_code":"229.0",
    "gn:asciiname":"Dewaspura",
    "gn:country_code":"IN",
    "gn:dem":68,
    "gn:feature_class":"P",
    "gn:feature_code":"PPL",
    "gn:name":"Dew\u0101spura",
    "gn:population":0,
    "gn:timezone":"Asia/Kolkata",
    "iso:country":"IN",
    "wof:name":"Dewaspura",
    "wof:placetype":"locality"
},
  "geometry": {"coordinates":[85.59385,25.07669],"type":"Point"}
}