{
  "type": "Feature",
  "properties": {
    "iso:country":"IN",
    "ks:ks_alt_nam":"KARTARA",
    "ks:ks_name":"Kartara",
    "ks:ks_pop":166,
    "ks:ks_type":"HABITATION",
    "ks:ks_uagg_main":0,
    "name:eng_x_preferred":[
        "Kartara"
    ],
    "wof:name":"Kartara",
    "wof:placetype":"neighbourhood",
    "wof:population":166
},
  "geometry": {"coordinates":[85.750339,24.957447],"type":"Point"}
}