{
  "type": "Feature",
  "properties": {
    "iso:country":"IN",
    "ks:ks_name":"Nalliyampatti South",
    "ks:ks_pop":489,
    "ks:ks_type":"HABITATION",
    "name:eng_x_preferred":[
        "Nalliyampatti South"
    ],
    "wof:name":"Nalliyampatti South",
    "wof:placetype":"locality",
    "wof:population":489
},
  "geometry": {"coordinates":[78.562714,11.019428],"type":"Point"}
}