{
  "type": "Feature",
  "properties": {
    "iso:country":"IN",
    "ks:ks_alt_nam":"KUMBHAGATHA",
    "ks:ks_name":"Kumbhagatha",
    "ks:ks_pop":87,
    "ks:ks_type":"HABITATION",
    "name:eng_x_preferred":[
        "Kumbhagatha"
    ],
    "wof:name":"Kumbhagatha",
    "wof:placetype":"locality",
    "wof:population":87
},
  "geometry": {"coordinates":[91.302046,23.76873],"type":"Point"}
}