{
  "type": "Feature",
  "properties": {
    "gn:admin1_code":"36.0",
    "gn:admin2_code":"132.0",
    "gn:asciiname":"Aplana",
    "gn:country_code":"IN",
    "gn:dem":265,
    "gn:feature_class":"P",
    "gn:feature_code":"PPL",
    "gn:name":"Apl\u0101na",
    "gn:population":0,
    "gn:timezone":"Asia/Kolkata",
    "iso:country":"IN",
    "wof:name":"Aplana",
    "wof:placetype":"neighbourhood"
},
  "geometry": {"coordinates":[77.32444,30.01559],"type":"Point"}
}