{
  "type": "Feature",
  "properties": {
    "iso:country":"IN",
    "ks:ks_name":"Navali",
    "ks:ks_pop":290,
    "ks:ks_type":"VILLAGE",
    "name:eng_x_preferred":[
        "Navali"
    ],
    "wof:name":"Navali",
    "wof:placetype":"locality",
    "wof:population":290
},
  "geometry": {"coordinates":[73.81779899999999,17.661547],"type":"Point"}
}