{
  "type": "Feature",
  "properties": {
    "iso:country":"IN",
    "ks:ks_alt_nam":"KADAMBHOSALE WASTI",
    "ks:ks_name":"Kadambhosale Wasti",
    "ks:ks_pop":146,
    "ks:ks_type":"HABITATION",
    "name:eng_x_preferred":[
        "Kadambhosale Wasti"
    ],
    "wof:name":"Kadambhosale Wasti",
    "wof:placetype":"locality",
    "wof:population":146
},
  "geometry": {"coordinates":[75.085032,16.986191],"type":"Point"}
}