{
  "type": "Feature",
  "properties": {
    "gn:admin1_code":"12.0",
    "gn:admin2_code":"008",
    "gn:asciiname":"Ghat Gopal",
    "gn:country_code":"IN",
    "gn:dem":1583,
    "gn:feature_class":"P",
    "gn:feature_code":"PPL",
    "gn:name":"Gh\u0101t Gop\u0101l",
    "gn:population":0,
    "gn:timezone":"Asia/Kolkata",
    "iso:country":"IN",
    "wof:name":"Ghat Gopal",
    "wof:placetype":"locality"
},
  "geometry": {"coordinates":[74.57889,34.20315],"type":"Point"}
}