{
  "type": "Feature",
  "properties": {
    "gn:admin1_code":"35",
    "gn:admin2_code":"425.0",
    "gn:asciiname":"Kharrohi",
    "gn:country_code":"IN",
    "gn:dem":227,
    "gn:feature_class":"P",
    "gn:feature_code":"PPL",
    "gn:name":"Kharrohi",
    "gn:population":0,
    "gn:timezone":"Asia/Kolkata",
    "iso:country":"IN",
    "wof:name":"Kharrohi",
    "wof:placetype":"locality"
},
  "geometry": {"coordinates":[79.87564999999999,24.82787],"type":"Point"}
}