{
  "type": "Feature",
  "properties": {
    "gn:admin1_code":"25.0",
    "gn:admin2_code":"631.0",
    "gn:asciiname":"Gollapalli",
    "gn:country_code":"IN",
    "gn:dem":660,
    "gn:feature_class":"P",
    "gn:feature_code":"PPL",
    "gn:name":"Gollapalli",
    "gn:population":0,
    "gn:timezone":"Asia/Kolkata",
    "iso:country":"IN",
    "wof:name":"Gollapalli",
    "wof:placetype":"locality"
},
  "geometry": {"coordinates":[78.03430999999998,12.65296],"type":"Point"}
}