{
  "type": "Feature",
  "properties": {
    "iso:country":"IN",
    "ks:ks_name":"Midalam",
    "ks:ks_pop":14234,
    "ks:ks_type":"URBAN",
    "name:eng_x_preferred":[
        "Midalam"
    ],
    "wof:name":"Midalam",
    "wof:placetype":"locality",
    "wof:population":14234
},
  "geometry": {"coordinates":[77.261679,8.221625],"type":"Point"}
}