{
  "type": "Feature",
  "properties": {
    "iso:country":"IN",
    "ks:ks_alt_nam":"Beldari bigha",
    "ks:ks_name":"Beldari Bigha",
    "ks:ks_pop":350,
    "ks:ks_type":"HABITATION",
    "name:eng_x_preferred":[
        "Beldari Bigha"
    ],
    "wof:name":"Beldari Bigha",
    "wof:placetype":"locality",
    "wof:population":350
},
  "geometry": {"coordinates":[84.962068,25.173188],"type":"Point"}
}