{
  "type": "Feature",
  "properties": {
    "gn:admin1_code":"28.0",
    "gn:admin2_code":"335.0",
    "gn:asciiname":"Uttar Lakshmipur",
    "gn:country_code":"IN",
    "gn:dem":19,
    "gn:feature_class":"P",
    "gn:feature_code":"PPL",
    "gn:name":"Uttar Lakshmipur",
    "gn:population":0,
    "gn:timezone":"Asia/Kolkata",
    "iso:country":"IN",
    "wof:name":"Uttar Lakshmipur",
    "wof:placetype":"locality"
},
  "geometry": {"coordinates":[88.33608000000002,23.51341],"type":"Point"}
}