{
  "type": "Feature",
  "properties": {
    "iso:country":"IN",
    "ks:ks_alt_nam":"MOLVI KALA",
    "ks:ks_name":"Molvi Kala",
    "ks:ks_pop":250,
    "ks:ks_type":"HABITATION",
    "name:eng_x_preferred":[
        "Molvi Kala"
    ],
    "wof:name":"Molvi Kala",
    "wof:placetype":"locality",
    "wof:population":250
},
  "geometry": {"coordinates":[81.41030000000001,26.2868],"type":"Point"}
}