{
  "type": "Feature",
  "properties": {
    "gn:admin1_code":"35",
    "gn:admin2_code":"462.0",
    "gn:asciiname":"Chandwahi",
    "gn:country_code":"IN",
    "gn:dem":269,
    "gn:feature_class":"P",
    "gn:feature_code":"PPL",
    "gn:name":"Chandw\u0101hi",
    "gn:population":0,
    "gn:timezone":"Asia/Kolkata",
    "iso:country":"IN",
    "wof:name":"Chandwahi",
    "wof:placetype":"locality"
},
  "geometry": {"coordinates":[82.15418000000003,24.43653],"type":"Point"}
}