{
  "type": "Feature",
  "properties": {
    "gn:admin1_code":"35",
    "gn:admin2_code":"462.0",
    "gn:asciiname":"Chandwahi",
    "gn:country_code":"IN",
    "gn:dem":269,
    "gn:feature_class":"P",
    "gn:feature_code":"PPL",
    "gn:name":"Chandw\u0101hi",
    "gn:population":0,
    "gn:timezone":"Asia/Kolkata",
    "iso:country":"IN",
    "ks:ks_alt_nam":"Chandw\u0101hi",
    "ks:ks_name":"Chandwahi",
    "ks:ks_pop":3766,
    "ks:ks_type":"VILLAGE",
    "name:eng_x_preferred":[
        "Chandwahi"
    ],
    "name:eng_x_variant":[
        "Chandw\u0101hi"
    ],
    "wof:name":"Chandwahi",
    "wof:placetype":"locality",
    "wof:population":3766
},
  "geometry": {"coordinates":[82.160827,24.446501],"type":"Point"}
}