{
  "type": "Feature",
  "properties": {
    "iso:country":"IN",
    "ks:ks_name":"Acharadi",
    "ks:ks_pop":403,
    "ks:ks_type":"VILLAGE",
    "name:eng_x_preferred":[
        "Acharadi"
    ],
    "wof:name":"Acharadi",
    "wof:placetype":"locality",
    "wof:population":403
},
  "geometry": {"coordinates":[75.71699,13.019418],"type":"Point"}
}