{
  "type": "Feature",
  "properties": {
    "iso:country":"IN",
    "ks:ks_name":"Dudha Tola",
    "ks:ks_pop":234,
    "ks:ks_type":"HABITATION",
    "name:eng_x_preferred":[
        "Dudha Tola"
    ],
    "wof:name":"Dudha Tola",
    "wof:placetype":"locality",
    "wof:population":234
},
  "geometry": {"coordinates":[87.573015,26.312964],"type":"Point"}
}