{
  "type": "Feature",
  "properties": {
    "iso:country":"IN",
    "ks:ks_name":"Ambatoli",
    "ks:ks_pop":429,
    "ks:ks_type":"HABITATION",
    "name:eng_x_preferred":[
        "Ambatoli"
    ],
    "wof:name":"Ambatoli",
    "wof:placetype":"locality",
    "wof:population":429
},
  "geometry": {"coordinates":[84.431791,22.857563],"type":"Point"}
}