{
  "type": "Feature",
  "properties": {
    "iso:country":"IN",
    "ks:ks_name":"Kalyakhedikhurd",
    "ks:ks_pop":128,
    "ks:ks_type":"HABITATION",
    "name:eng_x_preferred":[
        "Kalyakhedikhurd"
    ],
    "wof:name":"Kalyakhedikhurd",
    "wof:placetype":"locality",
    "wof:population":128
},
  "geometry": {"coordinates":[75.301087,24.25179],"type":"Point"}
}