{
  "type": "Feature",
  "properties": {
    "gn:admin1_code":"36",
    "gn:admin2_code":"166.0",
    "gn:asciiname":"Machhli Kachh",
    "gn:country_code":"IN",
    "gn:dem":137,
    "gn:feature_class":"P",
    "gn:feature_code":"PPL",
    "gn:name":"Machhli K\u0101chh",
    "gn:population":0,
    "gn:timezone":"Asia/Kolkata",
    "iso:country":"IN",
    "ks:ks_name":"Machhali Kanch",
    "ks:ks_pop":246,
    "ks:ks_type":"HABITATION",
    "name:eng_x_preferred":[
        "Machhali Kanch"
    ],
    "name:eng_x_variant":[
        "Machhli Kachh"
    ],
    "wof:name":"Machhali Kanch",
    "wof:placetype":"locality",
    "wof:population":246
},
  "geometry": {"coordinates":[79.37494,25.689325],"type":"Point"}
}