{
  "type": "Feature",
  "properties": {
    "iso:country":"IN",
    "ks:ks_name":"Mauhari",
    "ks:ks_pop":902,
    "ks:ks_type":"HABITATION",
    "name:eng_x_preferred":[
        "Mauhari"
    ],
    "wof:name":"Mauhari",
    "wof:placetype":"locality",
    "wof:population":902
},
  "geometry": {"coordinates":[81.148183,24.166677],"type":"Point"}
}