{
  "type": "Feature",
  "properties": {
    "gn:admin1_code":"20",
    "gn:admin2_code":"264.0",
    "gn:asciiname":"Lakhuti",
    "gn:country_code":"IN",
    "gn:dem":872,
    "gn:feature_class":"P",
    "gn:feature_code":"PPL",
    "gn:name":"L\u0101khuti",
    "gn:population":0,
    "gn:timezone":"Asia/Kolkata",
    "iso:country":"IN",
    "wof:name":"Lakhuti",
    "wof:placetype":"locality"
},
  "geometry": {"coordinates":[94.24527999999999,26.29119],"type":"Point"}
}