{
  "type": "Feature",
  "properties": {
    "iso:country":"IN",
    "ks:ks_name":"Nigha",
    "ks:ks_pop":428,
    "ks:ks_type":"HABITATION",
    "name:eng_x_preferred":[
        "Nigha"
    ],
    "wof:name":"Nigha",
    "wof:placetype":"locality",
    "wof:population":428
},
  "geometry": {"coordinates":[81.316002,25.355673],"type":"Point"}
}