{
  "type": "Feature",
  "properties": {
    "iso:country":"IN",
    "ks:ks_name":"Someswarpur",
    "ks:ks_pop":521,
    "ks:ks_type":"VILLAGE",
    "ks:ks_uagg_main":0,
    "name:eng_x_preferred":[
        "Someswarpur"
    ],
    "wof:name":"Someswarpur",
    "wof:placetype":"neighbourhood",
    "wof:population":521
},
  "geometry": {"coordinates":[87.27530400000001,22.310753],"type":"Point"}
}