{
  "type": "Feature",
  "properties": {
    "gn:admin1_code":"28.0",
    "gn:admin2_code":"334.0",
    "gn:asciiname":"Rarhtara",
    "gn:country_code":"IN",
    "gn:dem":37,
    "gn:feature_class":"P",
    "gn:feature_code":"PPL",
    "gn:name":"R\u0101rhtara",
    "gn:population":0,
    "gn:timezone":"Asia/Kolkata",
    "iso:country":"IN",
    "wof:name":"Rarhtara",
    "wof:placetype":"locality"
},
  "geometry": {"coordinates":[87.86445000000001,24.05045],"type":"Point"}
}