{
  "type": "Feature",
  "properties": {
    "iso:country":"IN",
    "ks:ks_name":"A H Road",
    "ks:ks_pop":150,
    "ks:ks_type":"HABITATION",
    "name:eng_x_preferred":[
        "A H Road"
    ],
    "wof:name":"A H Road",
    "wof:placetype":"locality",
    "wof:population":150
},
  "geometry": {"coordinates":[76.10589299999999,13.333767],"type":"Point"}
}