{
  "type": "Feature",
  "properties": {
    "gn:admin1_code":"36.0",
    "gn:admin2_code":"162.0",
    "gn:asciiname":"Bamhnauti",
    "gn:country_code":"IN",
    "gn:dem":144,
    "gn:feature_class":"P",
    "gn:feature_code":"PPL",
    "gn:name":"Bamhnauti",
    "gn:population":0,
    "gn:timezone":"Asia/Kolkata",
    "iso:country":"IN",
    "name:und_x_variant":[
        "Bamhnouti"
    ],
    "wof:name":"Bamhnauti",
    "wof:placetype":"locality"
},
  "geometry": {"coordinates":[79.70883000000001,26.79841],"type":"Point"}
}