{
  "type": "Feature",
  "properties": {
    "gn:admin1_code":"19.0",
    "gn:admin2_code":"568.0",
    "gn:asciiname":"Sabara",
    "gn:country_code":"IN",
    "gn:dem":553,
    "gn:feature_class":"P",
    "gn:feature_code":"PPL",
    "gn:name":"S\u0101b\u0101ra",
    "gn:population":0,
    "gn:timezone":"Asia/Kolkata",
    "iso:country":"IN",
    "name:ceb_x_preferred":[
        "Sabara"
    ],
    "name:deu_x_preferred":[
        "Sabara"
    ],
    "name:hye_x_preferred":[
        "\u0536\u0561\u0562\u0561\u0580\u0561"
    ],
    "name:rus_x_preferred":[
        "\u0417\u0430\u0431\u0430\u0440\u0430"
    ],
    "name:swe_x_preferred":[
        "Sabara"
    ],
    "name:ukr_x_preferred":[
        "\u0417\u0430\u0431\u0430\u0440\u0430"
    ],
    "wof:name":"Sabara",
    "wof:placetype":"locality"
},
  "geometry": {"coordinates":[75.13229,14.62506],"type":"Point"}
}