{
  "type": "Feature",
  "properties": {
    "iso:country":"IN",
    "ks:ks_name":"Bhoora",
    "ks:ks_pop":862,
    "ks:ks_type":"VILLAGE",
    "name:eng_x_preferred":[
        "Bhoora"
    ],
    "wof:name":"Bhoora",
    "wof:placetype":"locality",
    "wof:population":862
},
  "geometry": {"coordinates":[73.397358,24.541783],"type":"Point"}
}