{
  "type": "Feature",
  "properties": {
    "gn:admin1_code":"37",
    "gn:admin2_code":"409.0",
    "gn:asciiname":"Tamora",
    "gn:country_code":"IN",
    "gn:dem":313,
    "gn:feature_class":"P",
    "gn:feature_code":"PPL",
    "gn:name":"Tamora",
    "gn:population":0,
    "gn:timezone":"Asia/Kolkata",
    "iso:country":"IN",
    "name:deu_x_preferred":[
        "Tamora"
    ],
    "name:jpn_x_preferred":[
        "\u30bf\u30e2\u30fc\u30e9"
    ],
    "wof:name":"Tamora",
    "wof:placetype":"locality"
},
  "geometry": {"coordinates":[81.37665,21.02073],"type":"Point"}
}