{
  "type": "Feature",
  "properties": {
    "gn:admin1_code":"2.0",
    "gn:admin2_code":"551.0",
    "gn:asciiname":"Gopavaram",
    "gn:country_code":"IN",
    "gn:dem":153,
    "gn:feature_class":"P",
    "gn:feature_code":"PPL",
    "gn:name":"Gopavaram",
    "gn:population":0,
    "gn:timezone":"Asia/Kolkata",
    "iso:country":"IN",
    "name:pam_x_preferred":[
        "Gopavaram"
    ],
    "name:tgl_x_preferred":[
        "Gopavaram"
    ],
    "wof:name":"Gopavaram",
    "wof:placetype":"locality"
},
  "geometry": {"coordinates":[78.5729,14.78412],"type":"Point"}
}