{
  "type": "Feature",
  "properties": {
    "iso:country":"IN",
    "ks:ks_alt_nam":"Jahori Maver tola",
    "ks:ks_name":"Jahori Maver Tola",
    "ks:ks_pop":315,
    "ks:ks_type":"HABITATION",
    "name:eng_x_preferred":[
        "Jahori Maver Tola"
    ],
    "wof:name":"Jahori Maver Tola",
    "wof:placetype":"locality",
    "wof:population":315
},
  "geometry": {"coordinates":[86.53867200000001,25.420746],"type":"Point"}
}