{
  "type": "Feature",
  "properties": {
    "gn:admin1_code":"34.0",
    "gn:admin2_code":"227.0",
    "gn:asciiname":"Ghoghi",
    "gn:country_code":"IN",
    "gn:dem":51,
    "gn:feature_class":"P",
    "gn:feature_code":"PPL",
    "gn:name":"Ghoghi",
    "gn:population":0,
    "gn:timezone":"Asia/Kolkata",
    "iso:country":"IN",
    "wof:name":"Ghoghi",
    "wof:placetype":"locality"
},
  "geometry": {"coordinates":[86.31104000000001,25.20183],"type":"Point"}
}