{
  "type": "Feature",
  "properties": {
    "iso:country":"IN",
    "ks:ks_name":"Kathabaunsuli",
    "ks:ks_pop":2012,
    "ks:ks_type":"HABITATION",
    "name:eng_x_preferred":[
        "Kathabaunsuli"
    ],
    "wof:name":"Kathabaunsuli",
    "wof:placetype":"locality",
    "wof:population":2012
},
  "geometry": {"coordinates":[85.63730200000001,21.800049],"type":"Point"}
}