{
  "type": "Feature",
  "properties": {
    "gn:admin1_code":"12.0",
    "gn:admin2_code":"22.0",
    "gn:asciiname":"Karar",
    "gn:country_code":"IN",
    "gn:dem":531,
    "gn:feature_class":"P",
    "gn:feature_code":"PPL",
    "gn:name":"K\u0101rar",
    "gn:population":0,
    "gn:timezone":"Asia/Kolkata",
    "iso:country":"IN",
    "wof:name":"Karar",
    "wof:placetype":"locality"
},
  "geometry": {"coordinates":[75.22839999999999,32.62929],"type":"Point"}
}