{
  "type": "Feature",
  "properties": {
    "iso:country":"IN",
    "ks:ks_name":"Bhodakachar Abad",
    "ks:ks_pop":342,
    "ks:ks_type":"VILLAGE",
    "name:eng_x_preferred":[
        "Bhodakachar Abad"
    ],
    "wof:name":"Bhodakachar Abad",
    "wof:placetype":"locality",
    "wof:population":342
},
  "geometry": {"coordinates":[81.897476,23.31686],"type":"Point"}
}