{
  "type": "Feature",
  "properties": {
    "gn:admin1_code":"19.0",
    "gn:admin2_code":"571.0",
    "gn:asciiname":"Ajaboranhalli",
    "gn:country_code":"IN",
    "gn:dem":894,
    "gn:feature_class":"P",
    "gn:feature_code":"PPL",
    "gn:name":"Ajaboranhalli",
    "gn:population":0,
    "gn:timezone":"Asia/Kolkata",
    "iso:country":"IN",
    "wof:name":"Ajaboranhalli",
    "wof:placetype":"locality"
},
  "geometry": {"coordinates":[77.24578000000002,13.32076],"type":"Point"}
}