{
  "type": "Feature",
  "properties": {
    "iso:country":"IN",
    "ks:ks_name":"Kalenatty",
    "ks:ks_pop":506,
    "ks:ks_type":"HABITATION",
    "name:eng_x_preferred":[
        "Kalenatty"
    ],
    "wof:name":"Kalenatty",
    "wof:placetype":"locality",
    "wof:population":506
},
  "geometry": {"coordinates":[77.698987,12.558768],"type":"Point"}
}