{
  "type": "Feature",
  "properties": {
    "iso:country":"IN",
    "ks:ks_name":"Thakarwali Sar",
    "ks:ks_pop":61,
    "ks:ks_type":"HABITATION",
    "name:eng_x_preferred":[
        "Thakarwali Sar"
    ],
    "wof:name":"Thakarwali Sar",
    "wof:placetype":"locality",
    "wof:population":61
},
  "geometry": {"coordinates":[78.739195,29.776143],"type":"Point"}
}