{
  "type": "Feature",
  "properties": {
    "iso:country":"IN",
    "ks:ks_alt_nam":"P\u0101nis\u0101ni",
    "ks:ks_name":"Panisani",
    "ks:ks_pop":148,
    "ks:ks_type":"VILLAGE",
    "name:eng_x_preferred":[
        "Panisani"
    ],
    "name:eng_x_variant":[
        "P\u0101nis\u0101ni"
    ],
    "wof:name":"Panisani",
    "wof:placetype":"locality",
    "wof:population":148
},
  "geometry": {"coordinates":[84.633132,22.831634],"type":"Point"}
}