{
  "type": "Feature",
  "properties": {
    "gn:admin1_code":"36",
    "gn:admin2_code":"138.0",
    "gn:asciiname":"Nabipur Amanatnagar",
    "gn:country_code":"IN",
    "gn:dem":229,
    "gn:feature_class":"P",
    "gn:feature_code":"PPL",
    "gn:name":"Nabipur Am\u0101natnagar",
    "gn:population":0,
    "gn:timezone":"Asia/Kolkata",
    "iso:country":"IN",
    "wof:name":"Nabipur Amanatnagar",
    "wof:placetype":"locality"
},
  "geometry": {"coordinates":[77.84206,29.01181],"type":"Point"}
}