{
  "type": "Feature",
  "properties": {
    "gn:admin1_code":"11.0",
    "gn:admin2_code":"33.0",
    "gn:asciiname":"Mohan",
    "gn:country_code":"IN",
    "gn:dem":1840,
    "gn:feature_class":"P",
    "gn:feature_code":"PPL",
    "gn:name":"Mohan",
    "gn:population":0,
    "gn:timezone":"Asia/Kolkata",
    "iso:country":"IN",
    "name:bpy_x_preferred":[
        "\u09ae\u09cb\u09b9\u09a8"
    ],
    "name:cat_x_preferred":[
        "Mohan"
    ],
    "name:ceb_x_preferred":[
        "Mohan"
    ],
    "name:deu_x_preferred":[
        "Mohan"
    ],
    "name:new_x_preferred":[
        "\u092e\u094b\u0939\u0928"
    ],
    "name:nld_x_preferred":[
        "Mohan"
    ],
    "name:rus_x_preferred":[
        "\u041c\u043e\u0445\u0430\u043d"
    ],
    "name:swe_x_preferred":[
        "Mohan"
    ],
    "name:tel_x_preferred":[
        "\u0c2e\u0c4b\u0c39\u0c28\u0c4d"
    ],
    "wof:name":"Mohan",
    "wof:placetype":"locality"
},
  "geometry": {"coordinates":[77.43263,31.30613],"type":"Point"}
}