{
  "type": "Feature",
  "properties": {
    "iso:country":"IN",
    "ks:ks_name":"Pachilamkunnu",
    "ks:ks_pop":625,
    "ks:ks_type":"HABITATION",
    "name:eng_x_preferred":[
        "Pachilamkunnu"
    ],
    "wof:name":"Pachilamkunnu",
    "wof:placetype":"locality",
    "wof:population":625
},
  "geometry": {"coordinates":[76.76079799999999,9.823204],"type":"Point"}
}