{
  "type": "Feature",
  "properties": {
    "gn:admin1_code":"36",
    "gn:admin2_code":"145.0",
    "gn:asciiname":"Chandanpur",
    "gn:country_code":"IN",
    "gn:dem":181,
    "gn:feature_class":"P",
    "gn:feature_code":"PPL",
    "gn:name":"Chandanpur",
    "gn:population":0,
    "gn:timezone":"Asia/Kolkata",
    "iso:country":"IN",
    "name:bih_x_preferred":[
        "\u091a\u0928\u094d\u0926\u0928\u092a\u0941\u0930"
    ],
    "name:ceb_x_preferred":[
        "Chandanpur"
    ],
    "name:msa_x_preferred":[
        "Chandanpur"
    ],
    "name:nep_x_preferred":[
        "\u091a\u0928\u094d\u0926\u0928\u092a\u0941\u0930"
    ],
    "name:new_x_preferred":[
        "\u091a\u0928\u094d\u0926\u0928\u092a\u0941\u0930"
    ],
    "name:pol_x_preferred":[
        "Chandanpur"
    ],
    "wof:name":"Chandanpur",
    "wof:placetype":"locality"
},
  "geometry": {"coordinates":[77.64747,27.5347],"type":"Point"}
}