{
  "type": "Feature",
  "properties": {
    "gn:admin1_code":"19.0",
    "gn:admin2_code":"571.0",
    "gn:asciiname":"Puttenahalli",
    "gn:country_code":"IN",
    "gn:dem":734,
    "gn:feature_class":"P",
    "gn:feature_code":"PPL",
    "gn:name":"Puttenahalli",
    "gn:population":0,
    "gn:timezone":"Asia/Kolkata",
    "iso:country":"IN",
    "wof:name":"Puttenahalli",
    "wof:placetype":"locality"
},
  "geometry": {"coordinates":[77.25199000000001,13.65291],"type":"Point"}
}