{
  "type": "Feature",
  "properties": {
    "iso:country":"IN",
    "ks:ks_name":"Salik Purwa",
    "ks:ks_pop":66,
    "ks:ks_type":"HABITATION",
    "name:eng_x_preferred":[
        "Salik Purwa"
    ],
    "wof:name":"Salik Purwa",
    "wof:placetype":"locality",
    "wof:population":66
},
  "geometry": {"coordinates":[82.48036500000001,26.764243],"type":"Point"}
}