{
  "type": "Feature",
  "properties": {
    "iso:country":"IN",
    "ks:ks_name":"Dhonda Nahar No 2",
    "ks:ks_pop":343,
    "ks:ks_type":"HABITATION",
    "name:eng_x_preferred":[
        "Dhonda Nahar No 2"
    ],
    "wof:name":"Dhonda Nahar No 2",
    "wof:placetype":"locality",
    "wof:population":343
},
  "geometry": {"coordinates":[95.232764,27.308956],"type":"Point"}
}