{
  "type": "Feature",
  "properties": {
    "gn:admin1_code":"34.0",
    "gn:admin2_code":"219.0",
    "gn:asciiname":"Rajmal Pirari",
    "gn:country_code":"IN",
    "gn:dem":60,
    "gn:feature_class":"P",
    "gn:feature_code":"PPL",
    "gn:name":"Rajmal Pir\u0101ri",
    "gn:population":0,
    "gn:timezone":"Asia/Kolkata",
    "iso:country":"IN",
    "ks:ks_name":"Rajmalpirari",
    "ks:ks_pop":524,
    "ks:ks_type":"VILLAGE",
    "name:eng_x_preferred":[
        "Rajmalpirari"
    ],
    "name:eng_x_variant":[
        "Rajmal Pirari"
    ],
    "wof:name":"Rajmalpirari",
    "wof:placetype":"locality",
    "wof:population":524
},
  "geometry": {"coordinates":[84.695413,25.821801],"type":"Point"}
}