{
  "type": "Feature",
  "properties": {
    "iso:country":"IN",
    "ks:ks_name":"Shille",
    "ks:ks_pop":79,
    "ks:ks_type":"HABITATION",
    "name:eng_x_preferred":[
        "Shille"
    ],
    "wof:name":"Shille",
    "wof:placetype":"locality",
    "wof:population":79
},
  "geometry": {"coordinates":[74.473964,14.451709],"type":"Point"}
}