{
  "type": "Feature",
  "properties": {
    "iso:country":"IN",
    "ks:ks_name":"1 C",
    "ks:ks_pop":1392,
    "ks:ks_type":"VILLAGE",
    "name:eng_x_preferred":[
        "1 C"
    ],
    "wof:name":"1 C",
    "wof:placetype":"locality",
    "wof:population":1392
},
  "geometry": {"coordinates":[73.802206,29.918364],"type":"Point"}
}