{
  "type": "Feature",
  "properties": {
    "gn:admin1_code":"34.0",
    "gn:admin2_code":"236.0",
    "gn:asciiname":"Bedauli",
    "gn:country_code":"IN",
    "gn:dem":93,
    "gn:feature_class":"P",
    "gn:feature_code":"PPL",
    "gn:name":"Bedauli",
    "gn:population":0,
    "gn:timezone":"Asia/Kolkata",
    "iso:country":"IN",
    "ks:ks_name":"Bedauli",
    "ks:ks_pop":278,
    "ks:ks_type":"VILLAGE",
    "ks:ks_uagg_main":0,
    "name:ceb_x_preferred":[
        "Bedauli"
    ],
    "name:eng_x_preferred":[
        "Bedauli"
    ],
    "name:msa_x_preferred":[
        "Bedauli"
    ],
    "name:pol_x_preferred":[
        "Bedauli"
    ],
    "wof:name":"Bedauli",
    "wof:placetype":"neighbourhood",
    "wof:population":278
},
  "geometry": {"coordinates":[84.884004,24.959105],"type":"Point"}
}