{
  "type": "Feature",
  "properties": {
    "iso:country":"IN",
    "ks:ks_name":"Honagodu",
    "ks:ks_pop":101,
    "ks:ks_type":"HABITATION",
    "name:eng_x_preferred":[
        "Honagodu"
    ],
    "wof:name":"Honagodu",
    "wof:placetype":"locality",
    "wof:population":101
},
  "geometry": {"coordinates":[74.84073100000001,14.215929],"type":"Point"}
}