{
  "type": "Feature",
  "properties": {
    "gn:admin1_code":"36.0",
    "gn:admin2_code":"174.0",
    "gn:asciiname":"Taiyabpur Magaura",
    "gn:country_code":"IN",
    "gn:dem":109,
    "gn:feature_class":"P",
    "gn:feature_code":"PPL",
    "gn:name":"Taiyabpur Magaura",
    "gn:population":0,
    "gn:timezone":"Asia/Kolkata",
    "iso:country":"IN",
    "wof:name":"Taiyabpur Magaura",
    "wof:placetype":"locality"
},
  "geometry": {"coordinates":[81.42673000000001,25.42788],"type":"Point"}
}