{
  "type": "Feature",
  "properties": {
    "iso:country":"IN",
    "ks:ks_name":"Sotia Jalam",
    "ks:ks_pop":1137,
    "ks:ks_type":"HABITATION",
    "name:eng_x_preferred":[
        "Sotia Jalam"
    ],
    "wof:name":"Sotia Jalam",
    "wof:placetype":"locality",
    "wof:population":1137
},
  "geometry": {"coordinates":[74.396404,22.67166],"type":"Point"}
}