{
  "type": "Feature",
  "properties": {
    "iso:country":"IN",
    "ks:ks_name":"6 NZP-C",
    "ks:ks_pop":42,
    "ks:ks_type":"VILLAGE",
    "name:eng_x_preferred":[
        "6 NZP-C"
    ],
    "wof:name":"6 NZP-C",
    "wof:placetype":"locality",
    "wof:population":42
},
  "geometry": {"coordinates":[73.413669,29.371445],"type":"Point"}
}