{
  "type": "Feature",
  "properties": {
    "iso:country":"IN",
    "ks:ks_name":"Kododihi",
    "ks:ks_pop":181,
    "ks:ks_type":"VILLAGE",
    "name:eng_x_preferred":[
        "Kododihi"
    ],
    "wof:name":"Kododihi",
    "wof:placetype":"locality",
    "wof:population":181
},
  "geometry": {"coordinates":[84.988428,21.824048],"type":"Point"}
}