{
  "type": "Feature",
  "properties": {
    "iso:country":"IN",
    "ks:ks_name":"Purab Tola Mabbi",
    "ks:ks_pop":1437,
    "ks:ks_type":"HABITATION",
    "ks:ks_uagg_main":0,
    "name:eng_x_preferred":[
        "Purab Tola Mabbi"
    ],
    "wof:name":"Purab Tola Mabbi",
    "wof:placetype":"neighbourhood",
    "wof:population":1437
},
  "geometry": {"coordinates":[86.068381,25.74997],"type":"Point"}
}