{
  "type": "Feature",
  "properties": {
    "iso:country":"IN",
    "name:ara_x_preferred":[
        "\u0627\u0644\u0642\u0637\u0627\u0639 53"
    ],
    "name:ben_bn_x_preferred":[
        "\u09b8\u09c7\u0995\u09cd\u099f\u09b0 53"
    ],
    "name:ben_in_x_preferred":[
        "\u09b8\u09c7\u0995\u09cd\u099f\u09b0 53"
    ],
    "name:guj_x_preferred":[
        "\u0ab8\u0ac7\u0a95\u0acd\u0a9f\u0ab0 53"
    ],
    "name:hin_x_preferred":[
        "\u0938\u0947\u0915\u094d\u091f\u0930 53"
    ],
    "name:kan_x_preferred":[
        "\u0cb8\u0cc6\u0c95\u0ccd\u0c9f\u0cb0\u0ccd 53"
    ],
    "name:mal_x_preferred":[
        "\u0d38\u0d46\u0d15\u0d4d\u0d1f\u0d30\u0d4d\u200d\u200c 53"
    ],
    "name:mar_x_preferred":[
        "\u0938\u0947\u0915\u094d\u091f\u0930 \u096b\u0969"
    ],
    "name:pan_x_preferred":[
        "\u0a38\u0a48\u0a15\u0a1f\u0a30 53"
    ],
    "name:tam_x_preferred":[
        "\u0baa\u0bbf\u0bb0\u0bbf\u0bb5\u0bc1 53"
    ],
    "name:tel_x_preferred":[
        "\u0c38\u0c46\u0c15\u0c4d\u0c1f\u0c30\u0c4d\u200c 53"
    ],
    "name:urd_x_preferred":[
        "\u0633\u06cc\u06a9\u0679\u0631 53"
    ],
    "qs:name":"Sector 53",
    "qs:name_adm0":"India",
    "qs:name_adm1":"Haryana",
    "qs:photos":30,
    "qs:photos_1k":6,
    "qs:photos_9k":1,
    "qs:photos_9r":2,
    "qs:photos_all":30,
    "qs:photos_sr":2,
    "qs:placetype":"Suburb",
    "qs:pop_sr":"0",
    "wof:name":"Sector 53",
    "wof:placetype":"neighbourhood"
},
  "geometry": {"coordinates":[77.0973285,28.4315105],"type":"Point"}
}