{
  "type": "Feature",
  "properties": {
    "iso:country":"IN",
    "qs:name":"Sector 53",
    "qs:name_adm0":"India",
    "qs:name_adm1":"Haryana",
    "qs:photos":30,
    "qs:photos_1k":6,
    "qs:photos_9k":1,
    "qs:photos_9r":2,
    "qs:photos_all":30,
    "qs:photos_sr":2,
    "qs:placetype":"Suburb",
    "qs:pop_sr":"0",
    "wof:name":"Sector 53",
    "wof:placetype":"neighbourhood"
},
  "geometry": {"coordinates":[77.0973285,28.4315105],"type":"Point"}
}