{
  "type": "Feature",
  "properties": {
    "gn:admin1_code":"36",
    "gn:admin2_code":"142.0",
    "gn:asciiname":"Amrala",
    "gn:country_code":"IN",
    "gn:dem":202,
    "gn:feature_class":"P",
    "gn:feature_code":"PPL",
    "gn:name":"Amr\u0101la",
    "gn:population":0,
    "gn:timezone":"Asia/Kolkata",
    "iso:country":"IN",
    "name:fas_x_preferred":[
        "\u0627\u0645\u0631\u0627\u0644\u0627"
    ],
    "wof:name":"Amrala",
    "wof:placetype":"locality"
},
  "geometry": {"coordinates":[77.82791999999998,28.32563],"type":"Point"}
}