{
  "type": "Feature",
  "properties": {
    "gn:admin1_code":"16.0",
    "gn:admin2_code":"508.0",
    "gn:asciiname":"Hodri",
    "gn:country_code":"IN",
    "gn:dem":242,
    "gn:feature_class":"P",
    "gn:feature_code":"PPL",
    "gn:name":"Hodri",
    "gn:population":0,
    "gn:timezone":"Asia/Kolkata",
    "iso:country":"IN",
    "ks:ks_name":"Hodri",
    "ks:ks_pop":277,
    "ks:ks_type":"VILLAGE",
    "name:eng_x_preferred":[
        "Hodri"
    ],
    "wof:name":"Hodri",
    "wof:placetype":"locality",
    "wof:population":277
},
  "geometry": {"coordinates":[80.714598,19.458186],"type":"Point"}
}