{
  "type": "Feature",
  "properties": {
    "iso:country":"IN",
    "ks:ks_name":"Samraipur",
    "ks:ks_pop":1025,
    "ks:ks_type":"VILLAGE",
    "name:eng_x_preferred":[
        "Samraipur"
    ],
    "wof:name":"Samraipur",
    "wof:placetype":"locality",
    "wof:population":1025
},
  "geometry": {"coordinates":[87.299603,22.369813],"type":"Point"}
}