{
  "type": "Feature",
  "properties": {
    "iso:country":"IN",
    "ks:ks_name":"Gavthanpada",
    "ks:ks_pop":168,
    "ks:ks_type":"HABITATION",
    "name:eng_x_preferred":[
        "Gavthanpada"
    ],
    "wof:name":"Gavthanpada",
    "wof:placetype":"locality",
    "wof:population":168
},
  "geometry": {"coordinates":[72.993427,19.861604],"type":"Point"}
}