{
  "type": "Feature",
  "properties": {
    "gn:admin1_code":"2",
    "gn:admin2_code":"544.0",
    "gn:asciiname":"Bandagaruvu",
    "gn:country_code":"IN",
    "gn:dem":673,
    "gn:feature_class":"P",
    "gn:feature_code":"PPL",
    "gn:name":"Bandagaruvu",
    "gn:population":0,
    "gn:timezone":"Asia/Kolkata",
    "iso:country":"IN",
    "ks:ks_name":"Bandagaravu",
    "ks:ks_pop":24,
    "ks:ks_type":"HABITATION",
    "name:eng_x_preferred":[
        "Bandagaravu"
    ],
    "name:eng_x_variant":[
        "Bandagaruvu"
    ],
    "wof:name":"Bandagaravu",
    "wof:placetype":"locality",
    "wof:population":24
},
  "geometry": {"coordinates":[82.90674300000001,18.117861],"type":"Point"}
}