{
  "type": "Feature",
  "properties": {
    "iso:country":"IN",
    "ks:ks_alt_nam":"Arunthathiar colony",
    "ks:ks_name":"Arunthathiar Colony",
    "ks:ks_pop":76,
    "ks:ks_type":"HABITATION",
    "name:eng_x_preferred":[
        "Arunthathiar Colony"
    ],
    "wof:name":"Arunthathiar Colony",
    "wof:placetype":"locality",
    "wof:population":76
},
  "geometry": {"coordinates":[78.05430699999999,8.605378],"type":"Point"}
}