{
  "type": "Feature",
  "properties": {
    "iso:country":"IN",
    "ks:ks_name":"Rebarion Ki Dhani",
    "ks:ks_pop":150,
    "ks:ks_type":"HABITATION",
    "name:eng_x_preferred":[
        "Rebarion Ki Dhani"
    ],
    "wof:name":"Rebarion Ki Dhani",
    "wof:placetype":"locality",
    "wof:population":150
},
  "geometry": {"coordinates":[72.762276,24.871464],"type":"Point"}
}