{
  "type": "Feature",
  "properties": {
    "gn:admin1_code":"35.0",
    "gn:admin2_code":"441.0",
    "gn:asciiname":"Charpatia",
    "gn:country_code":"IN",
    "gn:dem":380,
    "gn:feature_class":"P",
    "gn:feature_code":"PPL",
    "gn:name":"Ch\u0101rp\u0101tia",
    "gn:population":0,
    "gn:timezone":"Asia/Kolkata",
    "iso:country":"IN",
    "ks:ks_name":"Charpatiya",
    "ks:ks_pop":388,
    "ks:ks_type":"VILLAGE",
    "name:eng_x_preferred":[
        "Charpatiya"
    ],
    "name:eng_x_variant":[
        "Charpatia"
    ],
    "wof:name":"Charpatiya",
    "wof:placetype":"locality",
    "wof:population":388
},
  "geometry": {"coordinates":[74.72458399999999,21.886474],"type":"Point"}
}