{
  "type": "Feature",
  "properties": {
    "iso:country":"IN",
    "ks:ks_name":"Mathmalana",
    "ks:ks_pop":65,
    "ks:ks_type":"VILLAGE",
    "name:eng_x_preferred":[
        "Mathmalana"
    ],
    "wof:name":"Mathmalana",
    "wof:placetype":"locality",
    "wof:population":65
},
  "geometry": {"coordinates":[79.351619,30.408329],"type":"Point"}
}