{
  "type": "Feature",
  "properties": {
    "iso:country":"IN",
    "ks:ks_name":"Kalyanpur",
    "ks:ks_pop":4,
    "ks:ks_type":"HABITATION",
    "name:eng_x_preferred":[
        "Kalyanpur"
    ],
    "wof:name":"Kalyanpur",
    "wof:placetype":"locality",
    "wof:population":4
},
  "geometry": {"coordinates":[74.71252200000001,15.409125],"type":"Point"}
}