{
  "type": "Feature",
  "properties": {
    "iso:country":"IN",
    "ks:ks_name":"Kochlo",
    "ks:ks_pop":155,
    "ks:ks_type":"VILLAGE",
    "name:eng_x_preferred":[
        "Kochlo"
    ],
    "wof:name":"Kochlo",
    "wof:placetype":"locality",
    "wof:population":155
},
  "geometry": {"coordinates":[87.685365,24.963184],"type":"Point"}
}