{
  "type": "Feature",
  "properties": {
    "gn:admin1_code":"21.0",
    "gn:admin2_code":"398.0",
    "gn:asciiname":"Maijaruguda",
    "gn:country_code":"IN",
    "gn:dem":401,
    "gn:feature_class":"P",
    "gn:feature_code":"PPL",
    "gn:name":"Maij\u0101rug\u016bda",
    "gn:population":0,
    "gn:timezone":"Asia/Kolkata",
    "iso:country":"IN",
    "ks:ks_name":"Manjariguda",
    "ks:ks_pop":60,
    "ks:ks_type":"VILLAGE",
    "name:eng_x_preferred":[
        "Manjariguda"
    ],
    "name:eng_x_variant":[
        "Maijaruguda"
    ],
    "wof:name":"Manjariguda",
    "wof:placetype":"locality",
    "wof:population":60
},
  "geometry": {"coordinates":[83.196777,18.811451],"type":"Point"}
}