{
  "type": "Feature",
  "properties": {
    "iso:country":"IN",
    "ks:ks_name":"Chakrasila Hill",
    "ks:ks_pop":25,
    "ks:ks_type":"HABITATION",
    "name:eng_x_preferred":[
        "Chakrasila Hill"
    ],
    "wof:name":"Chakrasila Hill",
    "wof:placetype":"locality",
    "wof:population":25
},
  "geometry": {"coordinates":[90.331444,26.321503],"type":"Point"}
}