{
  "type": "Feature",
  "properties": {
    "iso:country":"IN",
    "ks:ks_name":"Keggal D",
    "ks:ks_pop":29,
    "ks:ks_type":"HABITATION",
    "name:eng_x_preferred":[
        "Keggal D"
    ],
    "wof:name":"Keggal D",
    "wof:placetype":"locality",
    "wof:population":29
},
  "geometry": {"coordinates":[76.800764,15.73632],"type":"Point"}
}