{
  "type": "Feature",
  "properties": {
    "iso:country":"IN",
    "ks:ks_name":"Semarbari",
    "ks:ks_pop":375,
    "ks:ks_type":"VILLAGE",
    "name:eng_x_preferred":[
        "Semarbari"
    ],
    "wof:name":"Semarbari",
    "wof:placetype":"locality",
    "wof:population":375
},
  "geometry": {"coordinates":[84.191616,26.945664],"type":"Point"}
}