{
  "type": "Feature",
  "properties": {
    "gn:admin1_code":"19.0",
    "gn:admin2_code":"574.0",
    "gn:asciiname":"Jakkenahalli",
    "gn:country_code":"IN",
    "gn:dem":969,
    "gn:feature_class":"P",
    "gn:feature_code":"PPL",
    "gn:name":"Jakkenahalli",
    "gn:population":0,
    "gn:timezone":"Asia/Kolkata",
    "iso:country":"IN",
    "wof:name":"Jakkenahalli",
    "wof:placetype":"locality"
},
  "geometry": {"coordinates":[76.18838000000002,13.05903],"type":"Point"}
}