{
  "type": "Feature",
  "properties": {
    "iso:country":"IN",
    "ks:ks_name":"Gopinathpur",
    "ks:ks_pop":1069,
    "ks:ks_type":"VILLAGE",
    "ks:ks_uagg_main":0,
    "name:eng_x_preferred":[
        "Gopinathpur"
    ],
    "wof:name":"Gopinathpur",
    "wof:placetype":"neighbourhood",
    "wof:population":1069
},
  "geometry": {"coordinates":[85.66042299999999,19.801718],"type":"Point"}
}