{
  "type": "Feature",
  "properties": {
    "iso:country":"IN",
    "ks:ks_name":"Karimane",
    "ks:ks_pop":10,
    "ks:ks_type":"HABITATION",
    "name:eng_x_preferred":[
        "Karimane"
    ],
    "wof:name":"Karimane",
    "wof:placetype":"locality",
    "wof:population":10
},
  "geometry": {"coordinates":[75.2403,13.357519],"type":"Point"}
}