{
  "type": "Feature",
  "properties": {
    "gn:admin1_code":"37.0",
    "gn:admin2_code":"408.0",
    "gn:asciiname":"Sitadabri",
    "gn:country_code":"IN",
    "gn:dem":331,
    "gn:feature_class":"P",
    "gn:feature_code":"PPL",
    "gn:name":"S\u012bt\u0101dabri",
    "gn:population":0,
    "gn:timezone":"Asia/Kolkata",
    "iso:country":"IN",
    "name:eng_x_preferred":[
        "S\u012bt\u0101dabri"
    ],
    "wof:name":"Sitadabri",
    "wof:placetype":"locality"
},
  "geometry": {"coordinates":[81.08728000000001,21.55265],"type":"Point"}
}