{
  "type": "Feature",
  "properties": {
    "gn:admin1_code":"19.0",
    "gn:admin2_code":"574.0",
    "gn:asciiname":"Sankaranahalli",
    "gn:country_code":"IN",
    "gn:dem":774,
    "gn:feature_class":"P",
    "gn:feature_code":"PPL",
    "gn:name":"Sankaranahalli",
    "gn:population":0,
    "gn:timezone":"Asia/Kolkata",
    "iso:country":"IN",
    "wof:name":"Sankaranahalli",
    "wof:placetype":"locality"
},
  "geometry": {"coordinates":[76.39948000000003,13.51339],"type":"Point"}
}