{
  "type": "Feature",
  "properties": {
    "iso:country":"IN",
    "ks:ks_name":"Mahajanguda",
    "ks:ks_pop":96,
    "ks:ks_type":"HABITATION",
    "name:eng_x_preferred":[
        "Mahajanguda"
    ],
    "wof:name":"Mahajanguda",
    "wof:placetype":"locality",
    "wof:population":96
},
  "geometry": {"coordinates":[79.428004,19.357913],"type":"Point"}
}