{
  "type": "Feature",
  "properties": {
    "iso:country":"IN",
    "ks:ks_name":"Moujbrindabanpur",
    "ks:ks_pop":589,
    "ks:ks_type":"VILLAGE",
    "ks:ks_uagg_main":0,
    "name:eng_x_preferred":[
        "Moujbrindabanpur"
    ],
    "wof:name":"Moujbrindabanpur",
    "wof:placetype":"neighbourhood",
    "wof:population":589
},
  "geometry": {"coordinates":[88.005808,22.043032],"type":"Point"}
}