{
  "type": "Feature",
  "properties": {
    "iso:country":"IN",
    "ks:ks_name":"Chund",
    "ks:ks_pop":1079,
    "ks:ks_type":"VILLAGE",
    "ks:ks_uagg_main":0,
    "name:eng_x_preferred":[
        "Chund"
    ],
    "wof:name":"Chund",
    "wof:placetype":"neighbourhood",
    "wof:population":1079
},
  "geometry": {"coordinates":[84.704086,23.573165],"type":"Point"}
}