{
  "type": "Feature",
  "properties": {
    "gn:admin1_code":"38.0",
    "gn:admin2_code":"353.0",
    "gn:asciiname":"Rajapur",
    "gn:country_code":"IN",
    "gn:dem":66,
    "gn:feature_class":"P",
    "gn:feature_code":"PPL",
    "gn:name":"Raj\u0101pur",
    "gn:population":0,
    "gn:timezone":"Asia/Kolkata",
    "iso:country":"IN",
    "name:ceb_x_preferred":[
        "Rajapur"
    ],
    "name:fra_x_preferred":[
        "Rajapur"
    ],
    "name:ita_x_preferred":[
        "Rajapur"
    ],
    "name:pol_x_preferred":[
        "Rajapur"
    ],
    "name:swe_x_preferred":[
        "Rajapur"
    ],
    "wof:name":"Rajapur",
    "wof:placetype":"locality"
},
  "geometry": {"coordinates":[87.74460000000001,24.32372],"type":"Point"}
}