{
  "type": "Feature",
  "properties": {
    "iso:country":"IN",
    "ks:ks_name":"Maesa Tola",
    "ks:ks_pop":29,
    "ks:ks_type":"VILLAGE",
    "name:eng_x_preferred":[
        "Maesa Tola"
    ],
    "wof:name":"Maesa Tola",
    "wof:placetype":"locality",
    "wof:population":29
},
  "geometry": {"coordinates":[87.581885,25.117536],"type":"Point"}
}