{
  "type": "Feature",
  "properties": {
    "iso:country":"IN",
    "ks:ks_name":"Banibhusanpur",
    "ks:ks_pop":103,
    "ks:ks_type":"VILLAGE",
    "ks:ks_uagg_main":0,
    "name:eng_x_preferred":[
        "Banibhusanpur"
    ],
    "wof:name":"Banibhusanpur",
    "wof:placetype":"neighbourhood",
    "wof:population":103
},
  "geometry": {"coordinates":[84.419274,20.57898],"type":"Point"}
}