{
  "type": "Feature",
  "properties": {
    "iso:country":"IN",
    "ks:ks_name":"Arkaguda",
    "ks:ks_pop":195,
    "ks:ks_type":"HABITATION",
    "name:eng_x_preferred":[
        "Arkaguda"
    ],
    "wof:name":"Arkaguda",
    "wof:placetype":"locality",
    "wof:population":195
},
  "geometry": {"coordinates":[79.818985,19.397113],"type":"Point"}
}