{
  "type": "Feature",
  "properties": {
    "gn:admin1_code":"35",
    "gn:admin2_code":"425.0",
    "gn:asciiname":"Dardonia",
    "gn:country_code":"IN",
    "gn:dem":410,
    "gn:feature_class":"P",
    "gn:feature_code":"PPL",
    "gn:name":"Dardonia",
    "gn:population":0,
    "gn:timezone":"Asia/Kolkata",
    "iso:country":"IN",
    "ks:ks_name":"Dardoniya",
    "ks:ks_pop":90,
    "ks:ks_type":"HABITATION",
    "name:eng_x_preferred":[
        "Dardoniya"
    ],
    "name:eng_x_variant":[
        "Dardonia"
    ],
    "wof:name":"Dardoniya",
    "wof:placetype":"locality",
    "wof:population":90
},
  "geometry": {"coordinates":[79.297954,24.362721],"type":"Point"}
}