{
  "type": "Feature",
  "properties": {
    "iso:country":"IN",
    "ks:ks_name":"Jampada",
    "ks:ks_pop":179,
    "ks:ks_type":"HABITATION",
    "name:eng_x_preferred":[
        "Jampada"
    ],
    "wof:name":"Jampada",
    "wof:placetype":"locality",
    "wof:population":179
},
  "geometry": {"coordinates":[82.50158399999999,19.77143],"type":"Point"}
}