{
  "type": "Feature",
  "properties": {
    "gn:admin1_code":"34.0",
    "gn:admin2_code":"220.0",
    "gn:asciiname":"Hasanpur Osti",
    "gn:country_code":"IN",
    "gn:dem":55,
    "gn:feature_class":"P",
    "gn:feature_code":"PPL",
    "gn:name":"Hasanpur Osti",
    "gn:population":0,
    "gn:timezone":"Asia/Kolkata",
    "iso:country":"IN",
    "ks:ks_name":"Hasanpur Osti",
    "ks:ks_pop":1927,
    "ks:ks_type":"VILLAGE",
    "name:eng_x_preferred":[
        "Hasanpur Osti"
    ],
    "wof:name":"Hasanpur Osti",
    "wof:placetype":"locality",
    "wof:population":1927
},
  "geometry": {"coordinates":[85.391971,25.785479],"type":"Point"}
}