{
  "type": "Feature",
  "properties": {
    "gn:admin1_code":"10.0",
    "gn:asciiname":"Kartarpur",
    "gn:country_code":"IN",
    "gn:dem":242,
    "gn:feature_class":"P",
    "gn:feature_code":"PPL",
    "gn:name":"Kart\u0101rpur",
    "gn:population":0,
    "gn:timezone":"Asia/Kolkata",
    "iso:country":"IN",
    "name:fra_x_preferred":[
        "Kartarpur"
    ],
    "wof:name":"Kartarpur",
    "wof:placetype":"locality"
},
  "geometry": {"coordinates":[76.38991999999998,30.14061],"type":"Point"}
}