{
  "type": "Feature",
  "properties": {
    "iso:country":"IN",
    "ks:ks_name":"Chambharwadi",
    "ks:ks_pop":33,
    "ks:ks_type":"HABITATION",
    "name:eng_x_preferred":[
        "Chambharwadi"
    ],
    "wof:name":"Chambharwadi",
    "wof:placetype":"locality",
    "wof:population":33
},
  "geometry": {"coordinates":[73.598316,16.177274],"type":"Point"}
}