{
  "type": "Feature",
  "properties": {
    "iso:country":"IN",
    "ks:ks_name":"Amritpur",
    "ks:ks_pop":0,
    "ks:ks_type":"VILLAGE",
    "name:eng_x_preferred":[
        "Amritpur"
    ],
    "wof:name":"Amritpur",
    "wof:placetype":"locality",
    "wof:population":0
},
  "geometry": {"coordinates":[81.272783,27.675477],"type":"Point"}
}