{
  "type": "Feature",
  "properties": {
    "iso:country":"IN",
    "ks:ks_name":"Padima Chak",
    "ks:ks_pop":1048,
    "ks:ks_type":"VILLAGE",
    "name:eng_x_preferred":[
        "Padima Chak"
    ],
    "wof:name":"Padima Chak",
    "wof:placetype":"locality",
    "wof:population":1048
},
  "geometry": {"coordinates":[87.834079,22.48996],"type":"Point"}
}