{
  "type": "Feature",
  "properties": {
    "iso:country":"IN",
    "ks:ks_name":"Vijaya Chandra Puram",
    "ks:ks_pop":121,
    "ks:ks_type":"HABITATION",
    "ks:ks_uagg_main":0,
    "name:eng_x_preferred":[
        "Vijaya Chandra Puram"
    ],
    "wof:name":"Vijaya Chandra Puram",
    "wof:placetype":"neighbourhood",
    "wof:population":121
},
  "geometry": {"coordinates":[79.152348,14.709748],"type":"Point"}
}