{
  "type": "Feature",
  "properties": {
    "iso:country":"IN",
    "ks:ks_name":"Kelashanuvalli",
    "ks:ks_pop":84,
    "ks:ks_type":"HABITATION",
    "name:eng_x_preferred":[
        "Kelashanuvalli"
    ],
    "wof:name":"Kelashanuvalli",
    "wof:placetype":"locality",
    "wof:population":84
},
  "geometry": {"coordinates":[75.246865,13.516881],"type":"Point"}
}