{
  "type": "Feature",
  "properties": {
    "gn:admin1_code":"36",
    "gn:admin2_code":"191.0",
    "gn:asciiname":"Arazi Machhrihwa Roshan Bibi",
    "gn:country_code":"IN",
    "gn:dem":79,
    "gn:feature_class":"P",
    "gn:feature_code":"PPL",
    "gn:name":"Ar\u0101zi Machhrihwa Roshan B\u012bbi",
    "gn:population":0,
    "gn:timezone":"Asia/Kolkata",
    "iso:country":"IN",
    "wof:name":"Arazi Machhrihwa Roshan Bibi",
    "wof:placetype":"locality"
},
  "geometry": {"coordinates":[83.1974,26.35586],"type":"Point"}
}