{
  "type": "Feature",
  "properties": {
    "gn:admin1_code":"36",
    "gn:admin2_code":"173.0",
    "gn:asciiname":"Thakuraini ka Purwa",
    "gn:country_code":"IN",
    "gn:dem":109,
    "gn:feature_class":"P",
    "gn:feature_code":"PPL",
    "gn:name":"Thakuraini ka Purwa",
    "gn:population":0,
    "gn:timezone":"Asia/Kolkata",
    "iso:country":"IN",
    "wof:name":"Thakuraini ka Purwa",
    "wof:placetype":"neighbourhood"
},
  "geometry": {"coordinates":[81.56735,25.69507],"type":"Point"}
}