{
  "type": "Feature",
  "properties": {
    "gn:admin1_code":"25.0",
    "gn:admin2_code":"610.0",
    "gn:asciiname":"Serengakkavundanpalaiyam",
    "gn:country_code":"IN",
    "gn:dem":261,
    "gn:feature_class":"P",
    "gn:feature_code":"PPL",
    "gn:name":"Serengakkavundanp\u0101laiyam",
    "gn:population":0,
    "gn:timezone":"Asia/Kolkata",
    "iso:country":"IN",
    "wof:name":"Serengakkavundanpalaiyam",
    "wof:placetype":"locality"
},
  "geometry": {"coordinates":[77.54705,11.3141],"type":"Point"}
}