{
  "type": "Feature",
  "properties": {
    "iso:country":"IN",
    "ks:ks_name":"Bandua",
    "ks:ks_pop":155,
    "ks:ks_type":"VILLAGE",
    "name:eng_x_preferred":[
        "Bandua"
    ],
    "wof:name":"Bandua",
    "wof:placetype":"locality",
    "wof:population":155
},
  "geometry": {"coordinates":[87.344503,22.8666],"type":"Point"}
}