{
  "type": "Feature",
  "properties": {
    "gn:admin1_code":"16.0",
    "gn:admin2_code":"513.0",
    "gn:asciiname":"Bhogaon",
    "gn:country_code":"IN",
    "gn:dem":429,
    "gn:feature_class":"P",
    "gn:feature_code":"PPL",
    "gn:name":"Bhogaon",
    "gn:population":0,
    "gn:timezone":"Asia/Kolkata",
    "iso:country":"IN",
    "name:bpy_x_preferred":[
        "\u09ad\u09cb\u0997\u09be\u0981\u0993"
    ],
    "name:ita_x_preferred":[
        "Bhogaon"
    ],
    "name:msa_x_preferred":[
        "Bhogaon"
    ],
    "name:new_x_preferred":[
        "\u092d\u094b\u0917\u093e\u0935\u0902"
    ],
    "name:nld_x_preferred":[
        "Bhogaon"
    ],
    "name:pol_x_preferred":[
        "Bhogaon"
    ],
    "name:por_x_preferred":[
        "Bhogaon"
    ],
    "name:tam_x_preferred":[
        "\u0baa\u0bcb\u0b95\u0bcc\u0ba9\u0bcd"
    ],
    "name:urd_x_preferred":[
        "\u0628\u06be\u0648\u06af\u0627\u0624\u06ba"
    ],
    "name:vie_x_preferred":[
        "Bhogaon"
    ],
    "name:zho_x_preferred":[
        "\u535a\u52a0\u5965\u6069"
    ],
    "wof:name":"Bhogaon",
    "wof:placetype":"locality"
},
  "geometry": {"coordinates":[76.62114,19.30081],"type":"Point"}
}