{
  "type": "Feature",
  "properties": {
    "gn:admin1_code":"12.0",
    "gn:admin2_code":"2.0",
    "gn:asciiname":"Zabagul",
    "gn:country_code":"IN",
    "gn:dem":1985,
    "gn:feature_class":"P",
    "gn:feature_code":"PPL",
    "gn:name":"Zabagul",
    "gn:population":0,
    "gn:timezone":"Asia/Kolkata",
    "iso:country":"IN",
    "wof:name":"Zabagul",
    "wof:placetype":"locality"
},
  "geometry": {"coordinates":[74.60583000000003,33.96384],"type":"Point"}
}