{
  "type": "Feature",
  "properties": {
    "iso:country":"IN",
    "ks:ks_name":"Harijan Basti Aabadi Ke Pass",
    "ks:ks_pop":8,
    "ks:ks_type":"HABITATION",
    "name:eng_x_preferred":[
        "Harijan Basti Aabadi Ke Pass"
    ],
    "wof:name":"Harijan Basti Aabadi Ke Pass",
    "wof:placetype":"locality",
    "wof:population":8
},
  "geometry": {"coordinates":[82.796227,25.224813],"type":"Point"}
}