{
  "type": "Feature",
  "properties": {
    "gn:admin1_code":"11.0",
    "gn:admin2_code":"32.0",
    "gn:asciiname":"Maithu",
    "gn:country_code":"IN",
    "gn:dem":890,
    "gn:feature_class":"P",
    "gn:feature_code":"PPL",
    "gn:name":"Maithu",
    "gn:population":0,
    "gn:timezone":"Asia/Kolkata",
    "iso:country":"IN",
    "wof:name":"Maithu",
    "wof:placetype":"locality"
},
  "geometry": {"coordinates":[77.42811999999998,30.64108],"type":"Point"}
}