{
  "type": "Feature",
  "properties": {
    "gn:admin1_code":"39.0",
    "gn:admin2_code":"66.0",
    "gn:asciiname":"Bithuria Number Two",
    "gn:country_code":"IN",
    "gn:dem":448,
    "gn:feature_class":"P",
    "gn:feature_code":"PPL",
    "gn:name":"Bithuria Number Two",
    "gn:population":0,
    "gn:timezone":"Asia/Kolkata",
    "iso:country":"IN",
    "name:und_x_variant":[
        "Bithuria No. 2"
    ],
    "wof:name":"Bithuria Number Two",
    "wof:placetype":"locality"
},
  "geometry": {"coordinates":[79.5042,29.23249],"type":"Point"}
}