{
  "type": "Feature",
  "properties": {
    "gn:admin1_code":"2",
    "gn:admin2_code":"544.0",
    "gn:asciiname":"Gammelavalasa",
    "gn:country_code":"IN",
    "gn:dem":982,
    "gn:feature_class":"P",
    "gn:feature_code":"PPL",
    "gn:name":"Gammelavalasa",
    "gn:population":0,
    "gn:timezone":"Asia/Kolkata",
    "iso:country":"IN",
    "ks:ks_name":"Gammelivalasa",
    "ks:ks_pop":91,
    "ks:ks_type":"HABITATION",
    "name:eng_x_preferred":[
        "Gammelivalasa"
    ],
    "name:eng_x_variant":[
        "Gammelavalasa"
    ],
    "wof:name":"Gammelivalasa",
    "wof:placetype":"locality",
    "wof:population":91
},
  "geometry": {"coordinates":[82.862542,18.314777],"type":"Point"}
}