{
  "type": "Feature",
  "properties": {
    "gn:admin1_code":"2",
    "gn:admin2_code":"544.0",
    "gn:asciiname":"Gammelavalasa",
    "gn:country_code":"IN",
    "gn:dem":982,
    "gn:feature_class":"P",
    "gn:feature_code":"PPL",
    "gn:name":"Gammelavalasa",
    "gn:population":0,
    "gn:timezone":"Asia/Kolkata",
    "iso:country":"IN",
    "wof:name":"Gammelavalasa",
    "wof:placetype":"locality"
},
  "geometry": {"coordinates":[82.86286,18.31429],"type":"Point"}
}