{
  "type": "Feature",
  "properties": {
    "gn:admin1_code":"19.0",
    "gn:admin2_code":"567.0",
    "gn:asciiname":"Erehalli",
    "gn:country_code":"IN",
    "gn:dem":601,
    "gn:feature_class":"P",
    "gn:feature_code":"PPL",
    "gn:name":"Erehalli",
    "gn:population":0,
    "gn:timezone":"Asia/Kolkata",
    "iso:country":"IN",
    "wof:name":"Erehalli",
    "wof:placetype":"locality"
},
  "geometry": {"coordinates":[75.77242,14.31779],"type":"Point"}
}