{
  "type": "Feature",
  "properties": {
    "iso:country":"IN",
    "ks:ks_name":"Harijanwasti",
    "ks:ks_pop":110,
    "ks:ks_type":"HABITATION",
    "name:eng_x_preferred":[
        "Harijanwasti"
    ],
    "wof:name":"Harijanwasti",
    "wof:placetype":"locality",
    "wof:population":110
},
  "geometry": {"coordinates":[74.09375,17.270232],"type":"Point"}
}