{
  "type": "Feature",
  "properties": {
    "gn:admin1_code":"36.0",
    "gn:admin2_code":"173.0",
    "gn:asciiname":"Khargapur",
    "gn:country_code":"IN",
    "gn:dem":103,
    "gn:feature_class":"P",
    "gn:feature_code":"PPL",
    "gn:name":"Kharg\u0101pur",
    "gn:population":0,
    "gn:timezone":"Asia/Kolkata",
    "iso:country":"IN",
    "name:ben_x_preferred":[
        "\u0996\u09a1\u09bc\u0997\u09aa\u09c1\u09b0"
    ],
    "name:bpy_x_preferred":[
        "\u0996\u09a1\u09bc\u0997\u09aa\u09c1\u09b0"
    ],
    "name:ceb_x_preferred":[
        "Kharg\u0101pur"
    ],
    "name:ita_x_preferred":[
        "Khargapur"
    ],
    "name:msa_x_preferred":[
        "Khargapur"
    ],
    "name:new_x_preferred":[
        "\u0916\u0930\u0917\u093e\u092a\u0941\u0930"
    ],
    "name:nld_x_preferred":[
        "Khargapur"
    ],
    "name:por_x_preferred":[
        "Khargapur"
    ],
    "name:swe_x_preferred":[
        "Kharg\u0101pur"
    ],
    "name:vie_x_preferred":[
        "Khargapur"
    ],
    "name:zho_x_preferred":[
        "\u5361\u5c14\u52a0\u666e\u5c14"
    ],
    "wof:name":"Khargapur",
    "wof:placetype":"locality"
},
  "geometry": {"coordinates":[81.74869,25.71395],"type":"Point"}
}