{
  "type": "Feature",
  "properties": {
    "gn:admin1_code":"36.0",
    "gn:admin2_code":"150.0",
    "gn:asciiname":"Debi Nawada",
    "gn:country_code":"IN",
    "gn:dem":195,
    "gn:feature_class":"P",
    "gn:feature_code":"PPL",
    "gn:name":"Debi Naw\u0101da",
    "gn:population":0,
    "gn:timezone":"Asia/Kolkata",
    "iso:country":"IN",
    "wof:name":"Debi Nawada",
    "wof:placetype":"locality"
},
  "geometry": {"coordinates":[79.56156,28.79129],"type":"Point"}
}