{
  "type": "Feature",
  "properties": {
    "iso:country":"IN",
    "ks:ks_name":"Rajsingh Purwa",
    "ks:ks_pop":602,
    "ks:ks_type":"HABITATION",
    "name:eng_x_preferred":[
        "Rajsingh Purwa"
    ],
    "wof:name":"Rajsingh Purwa",
    "wof:placetype":"locality",
    "wof:population":602
},
  "geometry": {"coordinates":[80.041563,26.978063],"type":"Point"}
}