{
  "type": "Feature",
  "properties": {
    "iso:country":"IN",
    "ks:ks_name":"17 PTP",
    "ks:ks_pop":72,
    "ks:ks_type":"VILLAGE",
    "name:eng_x_preferred":[
        "17 PTP"
    ],
    "wof:name":"17 PTP",
    "wof:placetype":"locality",
    "wof:population":72
},
  "geometry": {"coordinates":[74.253114,29.882787],"type":"Point"}
}