{
  "type": "Feature",
  "properties": {
    "iso:country":"IN",
    "ks:ks_name":"Thenpathi",
    "ks:ks_pop":350,
    "ks:ks_type":"HABITATION",
    "name:eng_x_preferred":[
        "Thenpathi"
    ],
    "wof:name":"Thenpathi",
    "wof:placetype":"locality",
    "wof:population":350
},
  "geometry": {"coordinates":[79.646265,10.958531],"type":"Point"}
}