{
  "type": "Feature",
  "properties": {
    "iso:country":"IN",
    "ks:ks_name":"Bayal",
    "ks:ks_pop":4611,
    "ks:ks_type":"VILLAGE",
    "name:eng_x_preferred":[
        "Bayal"
    ],
    "wof:name":"Bayal",
    "wof:placetype":"locality",
    "wof:population":4611
},
  "geometry": {"coordinates":[87.95469,22.078775],"type":"Point"}
}