{
  "type": "Feature",
  "properties": {
    "iso:country":"IN",
    "ks:ks_name":"Madar Pur",
    "ks:ks_pop":112,
    "ks:ks_type":"HABITATION",
    "name:eng_x_preferred":[
        "Madar Pur"
    ],
    "wof:name":"Madar Pur",
    "wof:placetype":"locality",
    "wof:population":112
},
  "geometry": {"coordinates":[84.59672,24.66853],"type":"Point"}
}