{
  "type": "Feature",
  "properties": {
    "iso:country":"IN",
    "ks:ks_alt_nam":"Jagatap wasti",
    "ks:ks_name":"Jagatap Wasti",
    "ks:ks_pop":213,
    "ks:ks_type":"HABITATION",
    "name:eng_x_preferred":[
        "Jagatap Wasti"
    ],
    "wof:name":"Jagatap Wasti",
    "wof:placetype":"locality",
    "wof:population":213
},
  "geometry": {"coordinates":[74.44074000000001,18.51867],"type":"Point"}
}