{
  "type": "Feature",
  "properties": {
    "gn:admin1_code":"12.0",
    "gn:asciiname":"Mandwal",
    "gn:country_code":"IN",
    "gn:dem":554,
    "gn:feature_class":"P",
    "gn:feature_code":"PPL",
    "gn:name":"Mandw\u0101l",
    "gn:population":0,
    "gn:timezone":"Asia/Kolkata",
    "iso:country":"IN",
    "name:und_x_variant":[
        "Mandw\u0101l"
    ],
    "wof:name":"Mandwal",
    "wof:placetype":"locality"
},
  "geometry": {"coordinates":[74.4586,33.0585],"type":"Point"}
}