{
  "type": "Feature",
  "properties": {
    "iso:country":"IN",
    "ks:ks_name":"Lani Kantha",
    "ks:ks_pop":870,
    "ks:ks_type":"HABITATION",
    "name:eng_x_preferred":[
        "Lani Kantha"
    ],
    "wof:name":"Lani Kantha",
    "wof:placetype":"locality",
    "wof:population":870
},
  "geometry": {"coordinates":[71.477442,25.783742],"type":"Point"}
}