{
  "type": "Feature",
  "properties": {
    "iso:country":"IN",
    "ks:ks_name":"Sagunmari Pt.II",
    "ks:ks_pop":1381,
    "ks:ks_type":"VILLAGE",
    "name:eng_x_preferred":[
        "Sagunmari Pt.II"
    ],
    "wof:name":"Sagunmari Pt.II",
    "wof:placetype":"locality",
    "wof:population":1381
},
  "geometry": {"coordinates":[90.18963100000001,26.221599],"type":"Point"}
}