{
  "type": "Feature",
  "properties": {
    "gn:admin1_code":"25",
    "gn:admin2_code":"606.0",
    "gn:asciiname":"Tandarampattu",
    "gn:country_code":"IN",
    "gn:dem":177,
    "gn:feature_class":"P",
    "gn:feature_code":"PPL",
    "gn:name":"Tandar\u0101mpattu",
    "gn:population":0,
    "gn:timezone":"Asia/Kolkata",
    "iso:country":"IN",
    "name:und_x_variant":[
        "Tandarampatti",
        "Tandar\u0101mbattu",
        "Tandar\u0101mpattu"
    ],
    "wof:name":"Tandarampattu",
    "wof:placetype":"locality"
},
  "geometry": {"coordinates":[78.94728000000001,12.15327],"type":"Point"}
}