{
  "type": "Feature",
  "properties": {
    "gn:admin1_code":"35",
    "gn:admin2_code":"448.0",
    "gn:asciiname":"Bhavarwani",
    "gn:country_code":"IN",
    "gn:dem":357,
    "gn:feature_class":"P",
    "gn:feature_code":"PPL",
    "gn:name":"Bhavarw\u0101ni",
    "gn:population":0,
    "gn:timezone":"Asia/Kolkata",
    "iso:country":"IN",
    "ks:ks_name":"Bhawar Pani",
    "ks:ks_pop":175,
    "ks:ks_type":"VILLAGE",
    "name:eng_x_preferred":[
        "Bhawar Pani"
    ],
    "name:eng_x_variant":[
        "Bhavarwani"
    ],
    "wof:name":"Bhawar Pani",
    "wof:placetype":"locality",
    "wof:population":175
},
  "geometry": {"coordinates":[77.066416,22.039416],"type":"Point"}
}