{
  "type": "Feature",
  "properties": {
    "iso:country":"IN",
    "ks:ks_name":"Chandberia",
    "ks:ks_pop":529,
    "ks:ks_type":"VILLAGE",
    "ks:ks_uagg_main":0,
    "name:eng_x_preferred":[
        "Chandberia"
    ],
    "wof:name":"Chandberia",
    "wof:placetype":"neighbourhood",
    "wof:population":529
},
  "geometry": {"coordinates":[87.744482,21.78936],"type":"Point"}
}