{
  "type": "Feature",
  "properties": {
    "iso:country":"IN",
    "ks:ks_name":"Kyathedevaragudi",
    "ks:ks_pop":185,
    "ks:ks_type":"HABITATION",
    "name:eng_x_preferred":[
        "Kyathedevaragudi"
    ],
    "wof:name":"Kyathedevaragudi",
    "wof:placetype":"locality",
    "wof:population":185
},
  "geometry": {"coordinates":[77.123105,11.901752],"type":"Point"}
}