{
  "type": "Feature",
  "properties": {
    "gn:admin1_code":"39.0",
    "gn:admin2_code":"63.0",
    "gn:asciiname":"Walriya Kharak",
    "gn:country_code":"IN",
    "gn:dem":2144,
    "gn:feature_class":"P",
    "gn:feature_code":"PPL",
    "gn:name":"Walriya Kharak",
    "gn:population":0,
    "gn:timezone":"Asia/Kolkata",
    "iso:country":"IN",
    "wof:name":"Walriya Kharak",
    "wof:placetype":"locality"
},
  "geometry": {"coordinates":[79.77382,29.98682],"type":"Point"}
}