{
  "type": "Feature",
  "properties": {
    "gn:admin1_code":"35",
    "gn:admin2_code":"457.0",
    "gn:asciiname":"Agarwara",
    "gn:country_code":"IN",
    "gn:dem":621,
    "gn:feature_class":"P",
    "gn:feature_code":"PPL",
    "gn:name":"Agarwara",
    "gn:population":0,
    "gn:timezone":"Asia/Kolkata",
    "iso:country":"IN",
    "wof:name":"Agarwara",
    "wof:placetype":"locality"
},
  "geometry": {"coordinates":[80.80385,21.74828],"type":"Point"}
}