{
  "type": "Feature",
  "properties": {
    "gn:admin1_code":"34.0",
    "gn:admin2_code":"204.0",
    "gn:asciiname":"Bedia",
    "gn:country_code":"IN",
    "gn:dem":69,
    "gn:feature_class":"P",
    "gn:feature_code":"PPL",
    "gn:name":"Bedia",
    "gn:population":0,
    "gn:timezone":"Asia/Kolkata",
    "iso:country":"IN",
    "ks:ks_name":"Bedia",
    "ks:ks_pop":1,
    "ks:ks_type":"VILLAGE",
    "name:ceb_x_preferred":[
        "Bedia"
    ],
    "name:deu_x_preferred":[
        "Bedia"
    ],
    "name:eng_x_preferred":[
        "Bedia"
    ],
    "name:fra_x_preferred":[
        "Bedia"
    ],
    "name:rus_x_preferred":[
        "\u0411\u0435\u0434\u0438\u0430"
    ],
    "name:sco_x_preferred":[
        "Bedia"
    ],
    "name:swe_x_preferred":[
        "Bedia"
    ],
    "name:tur_x_preferred":[
        "Bedia"
    ],
    "wof:name":"Bedia",
    "wof:placetype":"locality",
    "wof:population":1
},
  "geometry": {"coordinates":[84.97171,26.585601],"type":"Point"}
}