{
  "type": "Feature",
  "properties": {
    "iso:country":"IN",
    "ks:ks_alt_nam":"TETARDIH GANJHU TOLA",
    "ks:ks_name":"Tetardih Ganjhu Tola",
    "ks:ks_pop":126,
    "ks:ks_type":"HABITATION",
    "name:eng_x_preferred":[
        "Tetardih Ganjhu Tola"
    ],
    "wof:name":"Tetardih Ganjhu Tola",
    "wof:placetype":"locality",
    "wof:population":126
},
  "geometry": {"coordinates":[84.75254200000001,24.070935],"type":"Point"}
}