{
  "type": "Feature",
  "properties": {
    "iso:country":"IN",
    "ks:ks_alt_nam":"MOCHI TOLA",
    "ks:ks_name":"Mochi Tola",
    "ks:ks_pop":234,
    "ks:ks_type":"HABITATION",
    "name:eng_x_preferred":[
        "Mochi Tola"
    ],
    "wof:name":"Mochi Tola",
    "wof:placetype":"locality",
    "wof:population":234
},
  "geometry": {"coordinates":[86.03785999999999,25.24767],"type":"Point"}
}