{
  "type": "Feature",
  "properties": {
    "gn:admin1_code":"12",
    "gn:admin2_code":"14.0",
    "gn:asciiname":"Bod Gopalpur",
    "gn:country_code":"IN",
    "gn:dem":1698,
    "gn:feature_class":"P",
    "gn:feature_code":"PPL",
    "gn:name":"Bod Gop\u0101lpur",
    "gn:population":0,
    "gn:timezone":"Asia/Kolkata",
    "iso:country":"IN",
    "wof:name":"Bod Gopalpur",
    "wof:placetype":"locality"
},
  "geometry": {"coordinates":[75.21075,33.72689],"type":"Point"}
}