{
  "type": "Feature",
  "properties": {
    "gn:admin1_code":"19.0",
    "gn:admin2_code":"564.0",
    "gn:asciiname":"Nukapur",
    "gn:country_code":"IN",
    "gn:dem":539,
    "gn:feature_class":"P",
    "gn:feature_code":"PPL",
    "gn:name":"N\u016bk\u0101pur",
    "gn:population":0,
    "gn:timezone":"Asia/Kolkata",
    "iso:country":"IN",
    "wof:name":"Nukapur",
    "wof:placetype":"locality"
},
  "geometry": {"coordinates":[75.62935,14.77387],"type":"Point"}
}