{
  "type": "Feature",
  "properties": {
    "iso:country":"IN",
    "ks:ks_name":"Domalagondi",
    "ks:ks_pop":174,
    "ks:ks_type":"HABITATION",
    "name:eng_x_preferred":[
        "Domalagondi"
    ],
    "wof:name":"Domalagondi",
    "wof:placetype":"locality",
    "wof:population":174
},
  "geometry": {"coordinates":[82.401946,17.95547],"type":"Point"}
}