{
  "type": "Feature",
  "properties": {
    "gn:admin1_code":"24.0",
    "gn:admin2_code":"125",
    "gn:asciiname":"Baronia",
    "gn:country_code":"IN",
    "gn:dem":150,
    "gn:feature_class":"P",
    "gn:feature_code":"PPL",
    "gn:name":"Baronia",
    "gn:population":0,
    "gn:timezone":"Asia/Kolkata",
    "iso:country":"IN",
    "wof:name":"Baronia",
    "wof:placetype":"locality"
},
  "geometry": {"coordinates":[74.10734000000002,23.41424],"type":"Point"}
}