{
  "type": "Feature",
  "properties": {
    "gn:admin1_code":"24.0",
    "gn:admin2_code":"125",
    "gn:asciiname":"Baronia",
    "gn:country_code":"IN",
    "gn:dem":150,
    "gn:feature_class":"P",
    "gn:feature_code":"PPL",
    "gn:name":"Baronia",
    "gn:population":0,
    "gn:timezone":"Asia/Kolkata",
    "iso:country":"IN",
    "name:afr_x_preferred":[
        "Baronvlinder"
    ],
    "name:ast_x_preferred":[
        "Baronia brevicornis"
    ],
    "name:bul_x_preferred":[
        "\u041a\u044a\u0441\u043e\u043f\u0438\u043f\u0430\u043b\u043d\u0430 \u0431\u0430\u0440\u043e\u043d\u0438\u044f"
    ],
    "name:cat_x_preferred":[
        "Baronia brevicornis"
    ],
    "name:ceb_x_preferred":[
        "Baronia brevicornis"
    ],
    "name:fin_x_preferred":[
        "Alkuritari"
    ],
    "name:fra_x_preferred":[
        "Baronia brevicornis"
    ],
    "name:ita_x_preferred":[
        "Baronia brevicornis"
    ],
    "name:jpn_x_preferred":[
        "\u30a6\u30e9\u30ae\u30f3\u30a2\u30b2\u30cf\u4e9c\u79d1"
    ],
    "name:nld_x_preferred":[
        "Baronia brevicornis"
    ],
    "name:nor_x_preferred":[
        "Baronia brevicornis"
    ],
    "name:pnb_x_preferred":[
        "\u0628\u06cc\u0631\u0648\u0646\u06cc\u0627 \u0628\u0631\u06cc\u0648\u06cc\u06a9\u0627\u0631\u0646\u0633"
    ],
    "name:pol_x_preferred":[
        "Baronia brevicornis"
    ],
    "name:ron_x_preferred":[
        "Baronia brevicornis"
    ],
    "name:rus_x_preferred":[
        "Baronia brevicornis"
    ],
    "name:spa_x_preferred":[
        "Baronia brevicornis"
    ],
    "name:srp_x_preferred":[
        "Baronia brevicornis"
    ],
    "name:swe_x_preferred":[
        "Baronia brevicornis"
    ],
    "name:vie_x_preferred":[
        "Baronia brevicornis"
    ],
    "name:war_x_preferred":[
        "Baronia brevicornis"
    ],
    "name:zho_x_preferred":[
        "\u5b9d\u51e4\u8776\u5c5e"
    ],
    "wof:name":"Baronia",
    "wof:placetype":"locality"
},
  "geometry": {"coordinates":[74.10734000000002,23.41424],"type":"Point"}
}