{
  "type": "Feature",
  "properties": {
    "iso:country":"IN",
    "ks:ks_name":"Khairan Purwa",
    "ks:ks_pop":131,
    "ks:ks_type":"HABITATION",
    "ks:ks_uagg_main":0,
    "name:eng_x_preferred":[
        "Khairan Purwa"
    ],
    "wof:name":"Khairan Purwa",
    "wof:placetype":"neighbourhood",
    "wof:population":131
},
  "geometry": {"coordinates":[81.74088500000001,27.379493],"type":"Point"}
}