{
  "type": "Feature",
  "properties": {
    "iso:country":"IN",
    "ks:ks_name":"Mazgaon No.1",
    "ks:ks_pop":3620,
    "ks:ks_type":"VILLAGE",
    "ks:ks_uagg_main":0,
    "name:eng_x_preferred":[
        "Mazgaon No.1"
    ],
    "wof:name":"Mazgaon No.1",
    "wof:placetype":"neighbourhood",
    "wof:population":3620
},
  "geometry": {"coordinates":[92.110739,26.629522],"type":"Point"}
}