{
  "type": "Feature",
  "properties": {
    "iso:country":"IN",
    "ks:ks_name":"Bhandarwadi",
    "ks:ks_pop":349,
    "ks:ks_type":"HABITATION",
    "name:eng_x_preferred":[
        "Bhandarwadi"
    ],
    "wof:name":"Bhandarwadi",
    "wof:placetype":"locality",
    "wof:population":349
},
  "geometry": {"coordinates":[73.78525500000001,15.854975],"type":"Point"}
}