{
  "type": "Feature",
  "properties": {
    "iso:country":"IN",
    "ks:ks_name":"Mohite Bhiosale Wasti",
    "ks:ks_pop":250,
    "ks:ks_type":"HABITATION",
    "name:eng_x_preferred":[
        "Mohite Bhiosale Wasti"
    ],
    "wof:name":"Mohite Bhiosale Wasti",
    "wof:placetype":"locality",
    "wof:population":250
},
  "geometry": {"coordinates":[74.896,17.995],"type":"Point"}
}