{
  "type": "Feature",
  "properties": {
    "iso:country":"IN",
    "ks:ks_name":"Kadagedda",
    "ks:ks_pop":81,
    "ks:ks_type":"HABITATION",
    "name:eng_x_preferred":[
        "Kadagedda"
    ],
    "wof:name":"Kadagedda",
    "wof:placetype":"locality",
    "wof:population":81
},
  "geometry": {"coordinates":[82.661494,17.830216],"type":"Point"}
}