{
  "type": "Feature",
  "properties": {
    "iso:country":"IN",
    "ks:ks_name":"Parayil Jn",
    "ks:ks_pop":428,
    "ks:ks_type":"HABITATION",
    "name:eng_x_preferred":[
        "Parayil Jn"
    ],
    "wof:name":"Parayil Jn",
    "wof:placetype":"locality",
    "wof:population":428
},
  "geometry": {"coordinates":[76.638595,9.074849],"type":"Point"}
}