{
  "type": "Feature",
  "properties": {
    "iso:country":"IN",
    "ks:ks_name":"Mulakukodithottam",
    "ks:ks_pop":963,
    "ks:ks_type":"HABITATION",
    "name:eng_x_preferred":[
        "Mulakukodithottam"
    ],
    "wof:name":"Mulakukodithottam",
    "wof:placetype":"locality",
    "wof:population":963
},
  "geometry": {"coordinates":[76.87738400000001,9.224181],"type":"Point"}
}