{
  "type": "Feature",
  "properties": {
    "iso:country":"IN",
    "ks:ks_name":"Jayanagarpatna",
    "ks:ks_pop":318,
    "ks:ks_type":"VILLAGE",
    "ks:ks_uagg_main":0,
    "name:eng_x_preferred":[
        "Jayanagarpatna"
    ],
    "wof:name":"Jayanagarpatna",
    "wof:placetype":"neighbourhood",
    "wof:population":318
},
  "geometry": {"coordinates":[87.131011,21.63325],"type":"Point"}
}