{
  "type": "Feature",
  "properties": {
    "iso:country":"IN",
    "ks:ks_name":"Budhijharanjungle",
    "ks:ks_pop":73,
    "ks:ks_type":"VILLAGE",
    "name:eng_x_preferred":[
        "Budhijharanjungle"
    ],
    "wof:name":"Budhijharanjungle",
    "wof:placetype":"locality",
    "wof:population":73
},
  "geometry": {"coordinates":[83.874353,21.126967],"type":"Point"}
}