{
  "type": "Feature",
  "properties": {
    "iso:country":"IN",
    "ks:ks_name":"Sikharada",
    "ks:ks_pop":0,
    "ks:ks_type":"VILLAGE",
    "name:eng_x_preferred":[
        "Sikharada"
    ],
    "wof:name":"Sikharada",
    "wof:placetype":"locality",
    "wof:population":0
},
  "geometry": {"coordinates":[85.516915,20.20245],"type":"Point"}
}