{
  "type": "Feature",
  "properties": {
    "iso:country":"IN",
    "ks:ks_name":"Kelagina Kere",
    "ks:ks_pop":19,
    "ks:ks_type":"HABITATION",
    "name:eng_x_preferred":[
        "Kelagina Kere"
    ],
    "wof:name":"Kelagina Kere",
    "wof:placetype":"locality",
    "wof:population":19
},
  "geometry": {"coordinates":[74.806692,14.792294],"type":"Point"}
}