{
  "type": "Feature",
  "properties": {
    "gn:admin1_code":"39.0",
    "gn:admin2_code":"57.0",
    "gn:asciiname":"Padairgaon",
    "gn:country_code":"IN",
    "gn:dem":2577,
    "gn:feature_class":"P",
    "gn:feature_code":"PPL",
    "gn:name":"Padairgaon",
    "gn:population":0,
    "gn:timezone":"Asia/Kolkata",
    "iso:country":"IN",
    "ks:ks_name":"Padairgaon",
    "ks:ks_pop":336,
    "ks:ks_type":"VILLAGE",
    "name:eng_x_preferred":[
        "Padairgaon"
    ],
    "wof:name":"Padairgaon",
    "wof:placetype":"locality",
    "wof:population":336
},
  "geometry": {"coordinates":[79.527878,30.306422],"type":"Point"}
}