{
  "type": "Feature",
  "properties": {
    "gn:admin1_code":"39.0",
    "gn:admin2_code":"57.0",
    "gn:asciiname":"Padairgaon",
    "gn:country_code":"IN",
    "gn:dem":2577,
    "gn:feature_class":"P",
    "gn:feature_code":"PPL",
    "gn:name":"Padairgaon",
    "gn:population":0,
    "gn:timezone":"Asia/Kolkata",
    "iso:country":"IN",
    "wof:name":"Padairgaon",
    "wof:placetype":"locality"
},
  "geometry": {"coordinates":[79.53069000000001,30.30625],"type":"Point"}
}