{
  "type": "Feature",
  "properties": {
    "iso:country":"IN",
    "ks:ks_name":"Aranchala",
    "ks:ks_pop":277,
    "ks:ks_type":"VILLAGE",
    "name:eng_x_preferred":[
        "Aranchala"
    ],
    "wof:name":"Aranchala",
    "wof:placetype":"locality",
    "wof:population":277
},
  "geometry": {"coordinates":[85.55673299999999,19.961006],"type":"Point"}
}