{
  "type": "Feature",
  "properties": {
    "iso:country":"IN",
    "ks:ks_name":"Badabhela",
    "ks:ks_pop":220,
    "ks:ks_type":"HABITATION",
    "name:eng_x_preferred":[
        "Badabhela"
    ],
    "wof:name":"Badabhela",
    "wof:placetype":"locality",
    "wof:population":220
},
  "geometry": {"coordinates":[82.946693,19.522201],"type":"Point"}
}