{
  "type": "Feature",
  "properties": {
    "iso:country":"IN",
    "ks:ks_name":"Chaitanyapuram",
    "ks:ks_pop":722,
    "ks:ks_type":"HABITATION",
    "name:eng_x_preferred":[
        "Chaitanyapuram"
    ],
    "wof:name":"Chaitanyapuram",
    "wof:placetype":"locality",
    "wof:population":722
},
  "geometry": {"coordinates":[79.49093000000001,13.697669],"type":"Point"}
}