{
  "type": "Feature",
  "properties": {
    "gn:admin1_code":"34.0",
    "gn:asciiname":"Itahari",
    "gn:country_code":"IN",
    "gn:dem":65,
    "gn:feature_class":"P",
    "gn:feature_code":"PPL",
    "gn:name":"It\u0101hari",
    "gn:population":0,
    "gn:timezone":"Asia/Kolkata",
    "iso:country":"IN",
    "name:bih_x_preferred":[
        "\u0907\u091f\u0939\u0930\u0940"
    ],
    "name:ceb_x_preferred":[
        "Ithari"
    ],
    "name:deu_x_preferred":[
        "Itahari"
    ],
    "name:dty_x_preferred":[
        "\u0907\u091f\u0939\u0930\u0940 \u0909\u092a\u092e\u0939\u093e\u0928\u0917\u0930\u092a\u093e\u0932\u093f\u0915\u093e"
    ],
    "name:fin_x_preferred":[
        "Itahari"
    ],
    "name:fra_x_preferred":[
        "Itahari"
    ],
    "name:hin_x_preferred":[
        "\u0907\u091f\u0939\u0930\u0940"
    ],
    "name:ita_x_preferred":[
        "Itahari"
    ],
    "name:mai_x_preferred":[
        "\u0907\u091f\u0939\u0930\u0940 \u0909\u092a\u092e\u0939\u093e\u0928\u0917\u0930\u092a\u093e\u0932\u093f\u0915\u093e"
    ],
    "name:msa_x_preferred":[
        "Itahari"
    ],
    "name:nep_x_preferred":[
        "\u0907\u091f\u0939\u0930\u0940 \u0909\u092a\u092e\u0939\u093e\u0928\u0917\u0930\u092a\u093e\u0932\u093f\u0915\u093e"
    ],
    "name:new_x_preferred":[
        "\u0907\u091f\u0939\u0930\u0940 \u0928\u0917\u0930\u092a\u093e\u0932\u093f\u0915\u093e"
    ],
    "name:pol_x_preferred":[
        "Itahari"
    ],
    "name:rus_x_preferred":[
        "\u0418\u0442\u0430\u0445\u0430\u0440\u0438"
    ],
    "name:tam_x_preferred":[
        "\u0b87\u0ba4\u0bbe\u0bb0\u0bbf"
    ],
    "name:urd_x_preferred":[
        "\u0627\u062a\u06c1\u0627\u0631\u06cc"
    ],
    "name:zho_x_preferred":[
        "\u4f0a\u5854\u54c8\u91cc"
    ],
    "wof:name":"Itahari",
    "wof:placetype":"locality"
},
  "geometry": {"coordinates":[87.396,25.22597],"type":"Point"}
}