{
  "type": "Feature",
  "properties": {
    "iso:country":"IN",
    "ks:ks_name":"Meyyappa Kottam",
    "ks:ks_pop":514,
    "ks:ks_type":"HABITATION",
    "name:eng_x_preferred":[
        "Meyyappa Kottam"
    ],
    "wof:name":"Meyyappa Kottam",
    "wof:placetype":"locality",
    "wof:population":514
},
  "geometry": {"coordinates":[79.771232,11.280294],"type":"Point"}
}