{
  "type": "Feature",
  "properties": {
    "gn:admin1_code":"09",
    "gn:admin2_code":"468.0",
    "gn:asciiname":"Suthri",
    "gn:country_code":"IN",
    "gn:dem":14,
    "gn:feature_class":"P",
    "gn:feature_code":"PPL",
    "gn:name":"Suthri",
    "gn:population":0,
    "gn:timezone":"Asia/Kolkata",
    "iso:country":"IN",
    "name:und_x_variant":[
        "Sothri",
        "Suthri"
    ],
    "wof:name":"Suthri",
    "wof:placetype":"locality"
},
  "geometry": {"coordinates":[68.91355,23.03328],"type":"Point"}
}