{
  "type": "Feature",
  "properties": {
    "iso:country":"IN",
    "ks:ks_name":"Omaisingi",
    "ks:ks_pop":149,
    "ks:ks_type":"VILLAGE",
    "name:eng_x_preferred":[
        "Omaisingi"
    ],
    "wof:name":"Omaisingi",
    "wof:placetype":"locality",
    "wof:population":149
},
  "geometry": {"coordinates":[84.057198,19.005289],"type":"Point"}
}