{
  "type": "Feature",
  "properties": {
    "gn:admin1_code":"11",
    "gn:admin2_code":"23.0",
    "gn:asciiname":"Dug",
    "gn:country_code":"IN",
    "gn:dem":762,
    "gn:feature_class":"P",
    "gn:feature_code":"PPL",
    "gn:name":"Dug",
    "gn:population":0,
    "gn:timezone":"Asia/Kolkata",
    "iso:country":"IN",
    "name:dan_x_preferred":[
        "Dug"
    ],
    "wof:name":"Dug",
    "wof:placetype":"locality"
},
  "geometry": {"coordinates":[76.02171,32.60461],"type":"Point"}
}