{
  "type": "Feature",
  "properties": {
    "iso:country":"IN",
    "ks:ks_name":"Bhaliaguda",
    "ks:ks_pop":77,
    "ks:ks_type":"VILLAGE",
    "name:eng_x_preferred":[
        "Bhaliaguda"
    ],
    "wof:name":"Bhaliaguda",
    "wof:placetype":"locality",
    "wof:population":77
},
  "geometry": {"coordinates":[84.46897199999999,19.513148],"type":"Point"}
}