{
  "type": "Feature",
  "properties": {
    "gn:admin1_code":"25",
    "gn:admin2_code":"628.0",
    "gn:asciiname":"Papanasam",
    "gn:country_code":"IN",
    "gn:dem":91,
    "gn:feature_class":"P",
    "gn:feature_code":"PPL",
    "gn:name":"P\u0101pan\u0101sam",
    "gn:population":0,
    "gn:timezone":"Asia/Kolkata",
    "iso:country":"IN",
    "wof:name":"Papanasam",
    "wof:placetype":"locality"
},
  "geometry": {"coordinates":[77.37553,8.71676],"type":"Point"}
}