{
  "type": "Feature",
  "properties": {
    "gn:admin1_code":"19",
    "gn:admin2_code":"563.0",
    "gn:asciiname":"Potolai",
    "gn:country_code":"IN",
    "gn:dem":528,
    "gn:feature_class":"P",
    "gn:feature_code":"PPL",
    "gn:name":"Potolai",
    "gn:population":0,
    "gn:timezone":"Asia/Kolkata",
    "iso:country":"IN",
    "ks:ks_name":"Potoli",
    "ks:ks_pop":126,
    "ks:ks_type":"HABITATION",
    "name:eng_x_preferred":[
        "Potoli"
    ],
    "name:eng_x_variant":[
        "Potolai"
    ],
    "wof:name":"Potoli",
    "wof:placetype":"locality",
    "wof:population":126
},
  "geometry": {"coordinates":[74.537358,15.193222],"type":"Point"}
}