{
  "type": "Feature",
  "properties": {
    "gn:admin1_code":"19",
    "gn:admin2_code":"563.0",
    "gn:asciiname":"Potolai",
    "gn:country_code":"IN",
    "gn:dem":528,
    "gn:feature_class":"P",
    "gn:feature_code":"PPL",
    "gn:name":"Potolai",
    "gn:population":0,
    "gn:timezone":"Asia/Kolkata",
    "iso:country":"IN",
    "wof:name":"Potolai",
    "wof:placetype":"locality"
},
  "geometry": {"coordinates":[74.54734999999999,15.18576],"type":"Point"}
}