{
  "type": "Feature",
  "properties": {
    "gn:admin1_code":"12.0",
    "gn:admin2_code":"7.0",
    "gn:asciiname":"Senan",
    "gn:country_code":"IN",
    "gn:dem":504,
    "gn:feature_class":"P",
    "gn:feature_code":"PPL",
    "gn:name":"Senan",
    "gn:population":0,
    "gn:timezone":"Asia/Kolkata",
    "iso:country":"IN",
    "name:deu_x_preferred":[
        "Senan"
    ],
    "name:epo_x_preferred":[
        "Senan"
    ],
    "name:fra_x_preferred":[
        "Senan"
    ],
    "name:ita_x_preferred":[
        "Senan"
    ],
    "name:nld_x_preferred":[
        "Senan"
    ],
    "name:oci_x_preferred":[
        "Senan"
    ],
    "name:rus_x_preferred":[
        "\u0421\u0435\u043d\u0430\u043d"
    ],
    "name:spa_x_preferred":[
        "Senan"
    ],
    "name:swe_x_preferred":[
        "Senan"
    ],
    "name:ukr_x_preferred":[
        "\u0421\u0435\u043d\u0430\u043d"
    ],
    "wof:name":"Senan",
    "wof:placetype":"locality"
},
  "geometry": {"coordinates":[75.66500000000001,32.50693],"type":"Point"}
}