{
  "type": "Feature",
  "properties": {
    "iso:country":"IN",
    "name:ara_x_preferred":[
        "\u0633\u064a\u0631\u0641\u0648\u0643 \u0645\u0648\u0631"
    ],
    "name:ben_bn_x_preferred":[
        "\u09b8\u09c7\u09b0\u09ad\u0995 \u09ae\u09cb\u09dc"
    ],
    "name:ben_in_x_preferred":[
        "\u09b8\u09c7\u09b0\u09ad\u0995 \u09ae\u09cb\u09dc"
    ],
    "name:eng_x_preferred":[
        "Servoke More"
    ],
    "name:guj_x_preferred":[
        "\u0ab8\u0ac7\u0ab0\u0acd\u0ab5\u0acb\u0a95 \u0aae\u0acb\u0ab0\u0ac7"
    ],
    "name:hin_x_preferred":[
        "\u0938\u0930\u094d\u0935\u094b\u0915\u0947 \u092e\u094b\u0930\u0947"
    ],
    "name:kan_x_preferred":[
        "\u0cb8\u0cb0\u0ccd\u0cb5\u0ccb\u0c95\u0cc6 \u0cae\u0cca\u0cb0\u0cc6"
    ],
    "name:mal_x_preferred":[
        "\u0d15\u0d42\u0d1f\u0d41\u0d24\u0d7d \u0d38\u0d47\u0d35\u0d3f\u0d15\u0d4d\u0d15\u0d41\u0d15"
    ],
    "name:mar_x_preferred":[
        "\u0938\u0930\u094d\u0935\u094d\u0939\u094b\u0915 \u092e\u094b\u0930\u0947"
    ],
    "name:pan_x_preferred":[
        "\u0a38\u0a30\u0a35\u0a4b\u0a15 \u0a2e\u0a4b\u0a30"
    ],
    "name:tam_x_preferred":[
        "\u0b9a\u0bc6\u0bb0\u0bcd\u0bb5\u0bcb\u0b95\u0bc6 \u0bae\u0bcb\u0bb0\u0bcd"
    ],
    "name:tel_x_preferred":[
        "\u0c38\u0c46\u0c30\u0c4d"
    ],
    "name:urd_x_preferred":[
        "\u0633\u0631\u0648\u0648\u06a9 \u0645\u0648\u0631\u06cc"
    ],
    "qs:gn_adm0_cc":"IN",
    "qs:gn_local":1256525,
    "qs:gn_nam_loc":"sonakhuli",
    "qs:gn_namadm1":"28",
    "qs:local_max":223,
    "qs:local_sum":230,
    "qs:localhoods":2,
    "qs:name":"Servoke More",
    "qs:name_adm0":"India",
    "qs:name_adm1":"West Bengal",
    "qs:name_adm2":"Jalpaiguri",
    "qs:name_local":"Siliguri",
    "qs:photo_max":152,
    "qs:photo_sum":223,
    "qs:placetype":"Suburb",
    "qs:quad_count":18,
    "qs:woe_adm0":23424848,
    "qs:woe_adm1":2345761,
    "qs:woe_adm2":12586803,
    "qs:woe_lau":0,
    "qs:woe_local":2294819,
    "qs:woe_ver":"7.10.0",
    "wof:lang":[
        "eng"
    ],
    "wof:name":"Servoke More",
    "wof:placetype":"neighbourhood"
},
  "geometry": {"coordinates":[88.426417,26.715595],"type":"Point"}
}