{
  "type": "Feature",
  "properties": {
    "iso:country":"IN",
    "name:eng_x_preferred":[
        "Servoke More"
    ],
    "name:unk_x_variant":[
        "Servoke More"
    ],
    "qs:gn_adm0_cc":"IN",
    "qs:gn_local":1256525,
    "qs:gn_nam_loc":"sonakhuli",
    "qs:gn_namadm1":"28",
    "qs:local_max":223,
    "qs:local_sum":230,
    "qs:localhoods":2,
    "qs:name":"Servoke More",
    "qs:name_adm0":"India",
    "qs:name_adm1":"West Bengal",
    "qs:name_adm2":"Jalpaiguri",
    "qs:name_local":"Siliguri",
    "qs:photo_max":152,
    "qs:photo_sum":223,
    "qs:placetype":"Suburb",
    "qs:quad_count":18,
    "qs:woe_adm0":23424848,
    "qs:woe_adm1":2345761,
    "qs:woe_adm2":12586803,
    "qs:woe_lau":0,
    "qs:woe_local":2294819,
    "qs:woe_ver":"7.10.0",
    "wof:lang":[
        "eng"
    ],
    "wof:name":"Servoke More",
    "wof:placetype":"neighbourhood"
},
  "geometry": {"coordinates":[88.426417,26.715595],"type":"Point"}
}