{
  "type": "Feature",
  "properties": {
    "iso:country":"IN",
    "ks:ks_name":"Sanagochha",
    "ks:ks_pop":187,
    "ks:ks_type":"VILLAGE",
    "name:eng_x_preferred":[
        "Sanagochha"
    ],
    "wof:name":"Sanagochha",
    "wof:placetype":"locality",
    "wof:population":187
},
  "geometry": {"coordinates":[84.212166,19.715315],"type":"Point"}
}