{
  "type": "Feature",
  "properties": {
    "gn:admin1_code":"2.0",
    "gn:admin2_code":"543.0",
    "gn:asciiname":"Dukkanivalasa",
    "gn:country_code":"IN",
    "gn:dem":185,
    "gn:feature_class":"P",
    "gn:feature_code":"PPL",
    "gn:name":"Dukkanivalasa",
    "gn:population":0,
    "gn:timezone":"Asia/Kolkata",
    "iso:country":"IN",
    "ks:ks_name":"Dukkadivalasa",
    "ks:ks_pop":30,
    "ks:ks_type":"HABITATION",
    "name:eng_x_preferred":[
        "Dukkadivalasa"
    ],
    "name:eng_x_variant":[
        "Dukkanivalasa"
    ],
    "wof:name":"Dukkadivalasa",
    "wof:placetype":"locality",
    "wof:population":30
},
  "geometry": {"coordinates":[83.23652300000001,18.596243],"type":"Point"}
}