{
  "type": "Feature",
  "properties": {
    "iso:country":"IN",
    "ks:ks_name":"Jaitanpar",
    "ks:ks_pop":36,
    "ks:ks_type":"HABITATION",
    "name:eng_x_preferred":[
        "Jaitanpar"
    ],
    "wof:name":"Jaitanpar",
    "wof:placetype":"locality",
    "wof:population":36
},
  "geometry": {"coordinates":[80.49526899999999,20.791789],"type":"Point"}
}