{
  "type": "Feature",
  "properties": {
    "iso:country":"IN",
    "ks:ks_name":"Mahaliapalli",
    "ks:ks_pop":49,
    "ks:ks_type":"VILLAGE",
    "ks:ks_uagg_main":0,
    "name:eng_x_preferred":[
        "Mahaliapalli"
    ],
    "wof:name":"Mahaliapalli",
    "wof:placetype":"neighbourhood",
    "wof:population":49
},
  "geometry": {"coordinates":[84.743582,22.240775],"type":"Point"}
}