{
  "type": "Feature",
  "properties": {
    "iso:country":"IN",
    "ks:ks_name":"Kaltali",
    "ks:ks_pop":340,
    "ks:ks_type":"VILLAGE",
    "name:eng_x_preferred":[
        "Kaltali"
    ],
    "wof:name":"Kaltali",
    "wof:placetype":"locality",
    "wof:population":340
},
  "geometry": {"coordinates":[91.236536,26.247349],"type":"Point"}
}