{
  "type": "Feature",
  "properties": {
    "iso:country":"IN",
    "ks:ks_name":"Ambatoli",
    "ks:ks_pop":305,
    "ks:ks_type":"HABITATION",
    "name:eng_x_preferred":[
        "Ambatoli"
    ],
    "wof:name":"Ambatoli",
    "wof:placetype":"locality",
    "wof:population":305
},
  "geometry": {"coordinates":[85.489417,23.394222],"type":"Point"}
}