{
  "type": "Feature",
  "properties": {
    "iso:country":"IN",
    "ks:ks_name":"Deswade",
    "ks:ks_pop":1525,
    "ks:ks_type":"VILLAGE",
    "name:eng_x_preferred":[
        "Deswade"
    ],
    "wof:name":"Deswade",
    "wof:placetype":"locality",
    "wof:population":1525
},
  "geometry": {"coordinates":[74.303363,19.317996],"type":"Point"}
}