{
  "type": "Feature",
  "properties": {
    "iso:country":"IN",
    "ks:ks_name":"Harijanpada",
    "ks:ks_pop":260,
    "ks:ks_type":"HABITATION",
    "name:eng_x_preferred":[
        "Harijanpada"
    ],
    "wof:name":"Harijanpada",
    "wof:placetype":"locality",
    "wof:population":260
},
  "geometry": {"coordinates":[82.906204,19.49088],"type":"Point"}
}