{
  "type": "Feature",
  "properties": {
    "gn:admin1_code":"36",
    "gn:admin2_code":"188.0",
    "gn:asciiname":"Lachhmi Chak",
    "gn:country_code":"IN",
    "gn:dem":77,
    "gn:feature_class":"P",
    "gn:feature_code":"PPL",
    "gn:name":"Lachhmi Chak",
    "gn:population":0,
    "gn:timezone":"Asia/Kolkata",
    "iso:country":"IN",
    "ks:ks_name":"Lachhmi Chak",
    "ks:ks_type":"VILLAGE",
    "name:eng_x_preferred":[
        "Lachhmi Chak"
    ],
    "wof:name":"Lachhmi Chak",
    "wof:placetype":"locality"
},
  "geometry": {"coordinates":[83.131502,26.401301],"type":"Point"}
}