{
  "type": "Feature",
  "properties": {
    "iso:country":"IN",
    "ks:ks_name":"Kathalbari",
    "ks:ks_pop":3195,
    "ks:ks_type":"VILLAGE",
    "ks:ks_uagg_main":0,
    "name:eng_x_preferred":[
        "Kathalbari"
    ],
    "wof:name":"Kathalbari",
    "wof:placetype":"neighbourhood",
    "wof:population":3195
},
  "geometry": {"coordinates":[87.874832,24.915079],"type":"Point"}
}