{
  "type": "Feature",
  "properties": {
    "gn:admin1_code":"16",
    "gn:admin2_code":"520.0",
    "gn:asciiname":"Revas Bandar",
    "gn:cc2":"IN",
    "gn:country_code":"IN",
    "gn:dem":2,
    "gn:feature_class":"P",
    "gn:feature_code":"PPL",
    "gn:name":"Revas Bandar",
    "gn:population":0,
    "gn:timezone":"Asia/Kolkata",
    "iso:country":"IN",
    "name:und_x_variant":[
        "Revas-Bunder",
        "Revas Bundar",
        "Revas Bandar"
    ],
    "wof:name":"Revas Bandar",
    "wof:placetype":"locality"
},
  "geometry": {"coordinates":[72.95,18.81667],"type":"Point"}
}