{
  "type": "Feature",
  "properties": {
    "iso:country":"IN",
    "ks:ks_name":"Dhanowal",
    "ks:ks_pop":81,
    "ks:ks_type":"VILLAGE",
    "name:eng_x_preferred":[
        "Dhanowal"
    ],
    "wof:name":"Dhanowal",
    "wof:placetype":"locality",
    "wof:population":81
},
  "geometry": {"coordinates":[75.88113199999999,31.654067],"type":"Point"}
}