{
  "type": "Feature",
  "properties": {
    "iso:country":"IN",
    "ks:ks_name":"Gamharia",
    "ks:ks_type":"VILLAGE",
    "ks:ks_uagg_main":0,
    "name:eng_x_preferred":[
        "Gamharia"
    ],
    "wof:name":"Gamharia",
    "wof:placetype":"neighbourhood"
},
  "geometry": {"coordinates":[86.323489,24.720269],"type":"Point"}
}