{
  "type": "Feature",
  "properties": {
    "gn:admin1_code":"35",
    "gn:admin2_code":"445.0",
    "gn:asciiname":"Itarsi",
    "gn:country_code":"IN",
    "gn:dem":304,
    "gn:feature_class":"P",
    "gn:feature_code":"PPL",
    "gn:name":"It\u0101rsi",
    "gn:population":0,
    "gn:timezone":"Asia/Kolkata",
    "iso:country":"IN",
    "wof:name":"Itarsi",
    "wof:placetype":"locality"
},
  "geometry": {"coordinates":[77.49186999999998,22.71978],"type":"Point"}
}