{
  "type": "Feature",
  "properties": {
    "gn:admin1_code":"35",
    "gn:admin2_code":"445.0",
    "gn:asciiname":"Itarsi",
    "gn:country_code":"IN",
    "gn:dem":304,
    "gn:feature_class":"P",
    "gn:feature_code":"PPL",
    "gn:name":"It\u0101rsi",
    "gn:population":0,
    "gn:timezone":"Asia/Kolkata",
    "iso:country":"IN",
    "name:ben_x_preferred":[
        "\u0987\u09a4\u09be\u09b0\u09b8\u09bf"
    ],
    "name:bpy_x_preferred":[
        "\u0987\u09a4\u09be\u09b0\u09b8\u09bf"
    ],
    "name:ceb_x_preferred":[
        "It\u0101rsi"
    ],
    "name:deu_x_preferred":[
        "Itarsi"
    ],
    "name:fra_x_preferred":[
        "Itarsi"
    ],
    "name:hif_x_preferred":[
        "Itarsi"
    ],
    "name:hin_x_preferred":[
        "\u0907\u091f\u093e\u0930\u0938\u0940"
    ],
    "name:ita_x_preferred":[
        "Itarsi"
    ],
    "name:mar_x_preferred":[
        "\u0907\u091f\u093e\u0930\u0938\u0940"
    ],
    "name:mlg_x_preferred":[
        "Itarsi"
    ],
    "name:msa_x_preferred":[
        "Itarsi"
    ],
    "name:new_x_preferred":[
        "\u0907\u0924\u093e\u0930\u094d\u0938\u0940"
    ],
    "name:ori_x_preferred":[
        "\u0b07\u0b24\u0b3e\u0b30\u0b4d\u0b38\u0b3f"
    ],
    "name:pan_x_preferred":[
        "\u0a07\u0a1f\u0a3e\u0a30\u0a38\u0a40"
    ],
    "name:por_x_preferred":[
        "Itarsi"
    ],
    "name:swe_x_preferred":[
        "Itarsi"
    ],
    "name:tam_x_preferred":[
        "\u0b87\u0b9f\u0bcd\u0b9f\u0bbe\u0bb0\u0bcd\u0b9a\u0bbf"
    ],
    "name:urd_x_preferred":[
        "\u0627\u0679\u0627\u0631\u0633\u06cc"
    ],
    "name:vie_x_preferred":[
        "Itarsi"
    ],
    "name:zho_x_preferred":[
        "\u4f0a\u5854\u5c14\u897f"
    ],
    "wof:name":"Itarsi",
    "wof:placetype":"locality"
},
  "geometry": {"coordinates":[77.49186999999998,22.71978],"type":"Point"}
}