{
  "type": "Feature",
  "properties": {
    "iso:country":"IN",
    "ks:ks_name":"Sulthanpete",
    "ks:ks_pop":130,
    "ks:ks_type":"HABITATION",
    "name:eng_x_preferred":[
        "Sulthanpete"
    ],
    "wof:name":"Sulthanpete",
    "wof:placetype":"locality",
    "wof:population":130
},
  "geometry": {"coordinates":[75.431088,13.149494],"type":"Point"}
}