{
  "type": "Feature",
  "properties": {
    "gn:admin1_code":"21.0",
    "gn:admin2_code":"398.0",
    "gn:asciiname":"Poibeda",
    "gn:country_code":"IN",
    "gn:dem":856,
    "gn:feature_class":"P",
    "gn:feature_code":"PPL",
    "gn:name":"Poibeda",
    "gn:population":0,
    "gn:timezone":"Asia/Kolkata",
    "iso:country":"IN",
    "wof:name":"Poibeda",
    "wof:placetype":"locality"
},
  "geometry": {"coordinates":[82.5468,18.58144],"type":"Point"}
}