{
  "type": "Feature",
  "properties": {
    "gn:admin1_code":"19.0",
    "gn:admin2_code":"574.0",
    "gn:asciiname":"Lingadhalli",
    "gn:country_code":"IN",
    "gn:dem":943,
    "gn:feature_class":"P",
    "gn:feature_code":"PPL",
    "gn:name":"Lingadhalli",
    "gn:population":0,
    "gn:timezone":"Asia/Kolkata",
    "iso:country":"IN",
    "ks:ks_name":"Lingadahalli",
    "ks:ks_pop":186,
    "ks:ks_type":"VILLAGE",
    "name:eng_x_preferred":[
        "Lingadahalli"
    ],
    "name:eng_x_variant":[
        "Lingadhalli"
    ],
    "wof:name":"Lingadahalli",
    "wof:placetype":"locality",
    "wof:population":186
},
  "geometry": {"coordinates":[75.992048,12.692898],"type":"Point"}
}