{
  "type": "Feature",
  "properties": {
    "iso:country":"IN",
    "ks:ks_name":"Kewerketa",
    "ks:ks_pop":121,
    "ks:ks_type":"HABITATION",
    "name:eng_x_preferred":[
        "Kewerketa"
    ],
    "wof:name":"Kewerketa",
    "wof:placetype":"locality",
    "wof:population":121
},
  "geometry": {"coordinates":[84.844562,22.629537],"type":"Point"}
}