{
  "type": "Feature",
  "properties": {
    "iso:country":"IN",
    "qs:name":"Amaravathi",
    "qs:name_adm0":"India",
    "qs:name_adm1":"Tamil Nadu",
    "qs:photos":35,
    "qs:photos_1k":7,
    "qs:photos_9k":1,
    "qs:photos_9r":2,
    "qs:photos_all":35,
    "qs:photos_sr":2,
    "qs:placetype":"Town",
    "qs:pop_sr":"0",
    "wd:wordcount":217,
    "wof:name":"Amaravathi",
    "wof:placetype":"locality"
},
  "geometry": {"coordinates":[77.218608,10.345317],"type":"Point"}
}