{
  "type": "Feature",
  "properties": {
    "iso:country":"IN",
    "name:ben_x_preferred":[
        "\u0985\u09ae\u09b0\u09be\u09ac\u09a4\u09c0"
    ],
    "name:deu_x_preferred":[
        "Amaravati"
    ],
    "name:fra_x_preferred":[
        "Amaravati"
    ],
    "name:guj_x_preferred":[
        "\u0a85\u0aae\u0ab0\u0abe\u0ab5\u0aa4\u0ac0"
    ],
    "name:hin_x_preferred":[
        "\u0905\u092e\u0930\u093e\u0935\u0924\u0940"
    ],
    "name:ind_x_preferred":[
        "Amaravati"
    ],
    "name:ita_x_preferred":[
        "Amaravati"
    ],
    "name:jpn_x_preferred":[
        "\u30a2\u30de\u30e9\u30fc\u30f4\u30a1\u30c6\u30a3\u30fc"
    ],
    "name:kan_x_preferred":[
        "\u0c85\u0cae\u0cb0\u0cbe\u0cb5\u0ca4\u0cbf"
    ],
    "name:mal_x_preferred":[
        "\u0d05\u0d2e\u0d30\u0d3e\u0d35\u0d24\u0d3f"
    ],
    "name:mar_x_preferred":[
        "\u0905\u092e\u0930\u093e\u0935\u0924\u0940"
    ],
    "name:pan_x_preferred":[
        "\u0a05\u0a2e\u0a30\u0a3e\u0a35\u0a24\u0a40"
    ],
    "name:swe_x_preferred":[
        "Amaravati"
    ],
    "name:tam_x_preferred":[
        "\u0b85\u0bae\u0bb0\u0bbe\u0bb5\u0ba4\u0bbf"
    ],
    "name:tel_x_preferred":[
        "\u0c05\u0c2e\u0c30\u0c3e\u0c35\u0c24\u0c3f"
    ],
    "name:urd_x_preferred":[
        "\u0627\u0645\u0631\u0627\u0648\u062a\u06cc"
    ],
    "name:vie_x_preferred":[
        "Amaravati"
    ],
    "name:zho_x_preferred":[
        "\u963f\u9a6c\u62c9\u74e6\u8482"
    ],
    "qs:name":"Amaravathi",
    "qs:name_adm0":"India",
    "qs:name_adm1":"Tamil Nadu",
    "qs:photos":35,
    "qs:photos_1k":7,
    "qs:photos_9k":1,
    "qs:photos_9r":2,
    "qs:photos_all":35,
    "qs:photos_sr":2,
    "qs:placetype":"Town",
    "qs:pop_sr":"0",
    "wd:wordcount":217,
    "wof:name":"Amaravathi",
    "wof:placetype":"locality"
},
  "geometry": {"coordinates":[77.218608,10.345317],"type":"Point"}
}