{
  "type": "Feature",
  "properties": {
    "gn:admin1_code":"36.0",
    "gn:admin2_code":"161",
    "gn:asciiname":"Gopiyapur",
    "gn:country_code":"IN",
    "gn:dem":150,
    "gn:feature_class":"P",
    "gn:feature_code":"PPL",
    "gn:name":"Gopiy\u0101pur",
    "gn:population":0,
    "gn:timezone":"Asia/Kolkata",
    "iso:country":"IN",
    "name:und_x_variant":[
        "Gopiy\u0101pur",
        "Gopiy\u0101pura"
    ],
    "wof:name":"Gopiyapur",
    "wof:placetype":"locality"
},
  "geometry": {"coordinates":[79.24605,26.83002],"type":"Point"}
}