{
  "type": "Feature",
  "properties": {
    "iso:country":"IN",
    "ks:ks_name":"Soojipara",
    "ks:ks_pop":1000,
    "ks:ks_type":"HABITATION",
    "name:eng_x_preferred":[
        "Soojipara"
    ],
    "wof:name":"Soojipara",
    "wof:placetype":"locality",
    "wof:population":1000
},
  "geometry": {"coordinates":[76.157619,11.508075],"type":"Point"}
}