{
  "type": "Feature",
  "properties": {
    "iso:country":"IN",
    "ks:ks_name":"Moodukudru",
    "ks:ks_pop":450,
    "ks:ks_type":"HABITATION",
    "name:eng_x_preferred":[
        "Moodukudru"
    ],
    "wof:name":"Moodukudru",
    "wof:placetype":"locality",
    "wof:population":450
},
  "geometry": {"coordinates":[74.733003,13.404336],"type":"Point"}
}