{
  "type": "Feature",
  "properties": {
    "iso:country":"IN",
    "ks:ks_name":"Kaijuri",
    "ks:ks_pop":4843,
    "ks:ks_type":"VILLAGE",
    "ks:ks_uagg_main":0,
    "name:eng_x_preferred":[
        "Kaijuri"
    ],
    "wof:name":"Kaijuri",
    "wof:placetype":"locality",
    "wof:population":4843
},
  "geometry": {"coordinates":[88.0727,22.473907],"type":"Point"}
}