{
  "type": "Feature",
  "properties": {
    "iso:country":"IN",
    "ks:ks_alt_nam":"hegdegadde",
    "ks:ks_name":"Hegdegadde",
    "ks:ks_pop":39,
    "ks:ks_type":"HABITATION",
    "name:eng_x_preferred":[
        "Hegdegadde"
    ],
    "wof:name":"Hegdegadde",
    "wof:placetype":"locality",
    "wof:population":39
},
  "geometry": {"coordinates":[74.55396,14.098494],"type":"Point"}
}