{
  "type": "Feature",
  "properties": {
    "iso:country":"IN",
    "ks:ks_name":"Patel Basti",
    "ks:ks_pop":769,
    "ks:ks_type":"HABITATION",
    "name:eng_x_preferred":[
        "Patel Basti"
    ],
    "wof:name":"Patel Basti",
    "wof:placetype":"locality",
    "wof:population":769
},
  "geometry": {"coordinates":[82.64190499999999,25.671779],"type":"Point"}
}