{
  "type": "Feature",
  "properties": {
    "iso:country":"IN",
    "ks:ks_name":"Khablisera",
    "ks:ks_pop":1397,
    "ks:ks_type":"VILLAGE",
    "ks:ks_uagg_main":0,
    "name:eng_x_preferred":[
        "Khablisera"
    ],
    "wof:name":"Khablisera",
    "wof:placetype":"neighbourhood",
    "wof:population":1397
},
  "geometry": {"coordinates":[78.093403,30.881047],"type":"Point"}
}