{
  "type": "Feature",
  "properties": {
    "iso:country":"IN",
    "ks:ks_name":"Chanri Durg",
    "ks:ks_pop":654,
    "ks:ks_type":"VILLAGE",
    "name:eng_x_preferred":[
        "Chanri Durg"
    ],
    "wof:name":"Chanri Durg",
    "wof:placetype":"locality",
    "wof:population":654
},
  "geometry": {"coordinates":[84.248788,26.546328],"type":"Point"}
}