{
  "type": "Feature",
  "properties": {
    "iso:country":"IN",
    "ks:ks_alt_nam":"Luh\u016brt\u0101nr",
    "ks:ks_name":"Luhurtanr",
    "ks:ks_pop":388,
    "ks:ks_type":"VILLAGE",
    "ks:ks_uagg_main":0,
    "name:eng_x_preferred":[
        "Luhurtanr"
    ],
    "name:eng_x_variant":[
        "Luh\u016brt\u0101nr"
    ],
    "wof:name":"Luhurtanr",
    "wof:placetype":"neighbourhood",
    "wof:population":388
},
  "geometry": {"coordinates":[84.241365,23.675939],"type":"Point"}
}