{
  "type": "Feature",
  "properties": {
    "iso:country":"IN",
    "ks:ks_name":"Bedma Para",
    "ks:ks_pop":250,
    "ks:ks_type":"HABITATION",
    "name:eng_x_preferred":[
        "Bedma Para"
    ],
    "wof:name":"Bedma Para",
    "wof:placetype":"locality",
    "wof:population":250
},
  "geometry": {"coordinates":[81.560502,19.379925],"type":"Point"}
}