{
  "type": "Feature",
  "properties": {
    "iso:country":"IN",
    "ks:ks_alt_nam":"Gulkaia Pur pasiyan",
    "ks:ks_name":"Gulkaia Pur Pasiyan",
    "ks:ks_pop":816,
    "ks:ks_type":"HABITATION",
    "name:eng_x_preferred":[
        "Gulkaia Pur Pasiyan"
    ],
    "wof:name":"Gulkaia Pur Pasiyan",
    "wof:placetype":"locality",
    "wof:population":816
},
  "geometry": {"coordinates":[81.837463,25.65481],"type":"Point"}
}