{
  "type": "Feature",
  "properties": {
    "gn:admin1_code":"36.0",
    "gn:admin2_code":"184.0",
    "gn:asciiname":"Ausanpur",
    "gn:country_code":"IN",
    "gn:dem":97,
    "gn:feature_class":"P",
    "gn:feature_code":"PPL",
    "gn:name":"Aus\u0101npur",
    "gn:population":0,
    "gn:timezone":"Asia/Kolkata",
    "iso:country":"IN",
    "ks:ks_alt_nam":"Aus\u0101npur",
    "ks:ks_name":"Ausanpur",
    "ks:ks_type":"VILLAGE",
    "ks:ks_uagg_main":0,
    "name:eng_x_preferred":[
        "Ausanpur"
    ],
    "name:eng_x_variant":[
        "Aus\u0101npur"
    ],
    "name:urd_x_preferred":[
        "\u0627\u0648\u0633\u0627\u0646 \u067e\u0648\u0631"
    ],
    "wof:name":"Ausanpur",
    "wof:placetype":"neighbourhood"
},
  "geometry": {"coordinates":[82.64156,27.191049],"type":"Point"}
}