{
  "type": "Feature",
  "properties": {
    "gn:admin1_code":"35.0",
    "gn:admin2_code":"430.0",
    "gn:asciiname":"Mahathiya",
    "gn:country_code":"IN",
    "gn:dem":138,
    "gn:feature_class":"P",
    "gn:feature_code":"PPL",
    "gn:name":"Mahathiya",
    "gn:population":0,
    "gn:timezone":"Asia/Kolkata",
    "iso:country":"IN",
    "wof:name":"Mahathiya",
    "wof:placetype":"locality"
},
  "geometry": {"coordinates":[81.51033000000002,25.13162],"type":"Point"}
}