{
  "type": "Feature",
  "properties": {
    "iso:country":"IN",
    "ks:ks_name":"Urpanjoor",
    "ks:ks_pop":112,
    "ks:ks_type":"HABITATION",
    "name:eng_x_preferred":[
        "Urpanjoor"
    ],
    "wof:name":"Urpanjoor",
    "wof:placetype":"locality",
    "wof:population":112
},
  "geometry": {"coordinates":[80.807205,20.017325],"type":"Point"}
}