{
  "type": "Feature",
  "properties": {
    "iso:country":"IN",
    "ks:ks_name":"Shavijipura",
    "ks:ks_pop":487,
    "ks:ks_type":"HABITATION",
    "name:eng_x_preferred":[
        "Shavijipura"
    ],
    "wof:name":"Shavijipura",
    "wof:placetype":"locality",
    "wof:population":487
},
  "geometry": {"coordinates":[72.958806,22.677111],"type":"Point"}
}