{
  "type": "Feature",
  "properties": {
    "gn:admin1_code":"34.0",
    "gn:admin2_code":"215.0",
    "gn:asciiname":"Asma",
    "gn:country_code":"IN",
    "gn:dem":50,
    "gn:feature_class":"P",
    "gn:feature_code":"PPL",
    "gn:name":"Asma",
    "gn:population":0,
    "gn:timezone":"Asia/Kolkata",
    "iso:country":"IN",
    "name:che_x_preferred":[
        "\u0410\u0441\u043c\u0430\u044a"
    ],
    "name:deu_x_preferred":[
        "Asma"
    ],
    "name:glg_x_preferred":[
        "Asma"
    ],
    "name:ind_x_preferred":[
        "Asma"
    ],
    "name:ita_x_preferred":[
        "Asma"
    ],
    "name:jav_x_preferred":[
        "Asma"
    ],
    "name:rus_x_preferred":[
        "\u0410\u0441\u043c\u0430"
    ],
    "wof:name":"Asma",
    "wof:placetype":"locality"
},
  "geometry": {"coordinates":[86.35675999999999,26.05846],"type":"Point"}
}