{
  "type": "Feature",
  "properties": {
    "iso:country":"IN",
    "ks:ks_name":"Satharcombai",
    "ks:ks_pop":121,
    "ks:ks_type":"HABITATION",
    "name:eng_x_preferred":[
        "Satharcombai"
    ],
    "wof:name":"Satharcombai",
    "wof:placetype":"locality",
    "wof:population":121
},
  "geometry": {"coordinates":[77.212492,11.565917],"type":"Point"}
}