{
  "type": "Feature",
  "properties": {
    "gn:country":"IN",
    "gn:fcode":"PPL",
    "gn:population":0,
    "iso:country":"IN",
    "name:ben_x_preferred":[
        "\u09ad\u09be\u09ac\u09be\u09a4"
    ],
    "name:bpy_x_preferred":[
        "\u09ad\u09be\u09ac\u09be\u09a4"
    ],
    "name:ceb_x_preferred":[
        "Bhab\u0101t"
    ],
    "name:eng_x_preferred":[
        "Bhabat"
    ],
    "name:fra_x_preferred":[
        "Bhabat"
    ],
    "name:ita_x_preferred":[
        "Bhabat"
    ],
    "name:msa_x_preferred":[
        "Bhabat"
    ],
    "name:nan_x_preferred":[
        "Bhabat"
    ],
    "name:new_x_preferred":[
        "\u092d\u0935\u091f"
    ],
    "name:nld_x_preferred":[
        "Bhabat"
    ],
    "name:por_x_preferred":[
        "Bhabat"
    ],
    "name:swe_x_preferred":[
        "Bhab\u0101t"
    ],
    "name:vie_x_preferred":[
        "Bhabat"
    ],
    "name:zho_x_preferred":[
        "\u5df4\u5df4\u7279"
    ],
    "qs:name":"Bhabat",
    "qs:name_adm0":"India",
    "qs:name_adm1":"Punjab",
    "qs:photos":40,
    "qs:photos_1k":8,
    "qs:photos_9k":1,
    "qs:photos_9r":2,
    "qs:photos_all":40,
    "qs:photos_sr":2,
    "qs:placetype":"Town",
    "qs:pop_sr":"0",
    "wd:wordcount":102,
    "wof:name":"Bhabat",
    "wof:placetype":"locality",
    "wof:population":0
},
  "geometry": {"coordinates":[76.80533,30.65691],"type":"Point"}
}