{
  "type": "Feature",
  "properties": {
    "gn:admin1_code":"25.0",
    "gn:admin2_code":"605.0",
    "gn:asciiname":"Nagal",
    "gn:country_code":"IN",
    "gn:dem":289,
    "gn:feature_class":"P",
    "gn:feature_code":"PPL",
    "gn:name":"N\u0101gal",
    "gn:population":0,
    "gn:timezone":"Asia/Kolkata",
    "iso:country":"IN",
    "ks:ks_alt_nam":"N\u0101gal",
    "ks:ks_name":"Nagal",
    "ks:ks_pop":1116,
    "ks:ks_type":"VILLAGE",
    "ks:ks_uagg_main":0,
    "name:eng_x_preferred":[
        "Nagal"
    ],
    "name:eng_x_variant":[
        "N\u0101gal"
    ],
    "wof:name":"Nagal",
    "wof:placetype":"neighbourhood",
    "wof:population":1116
},
  "geometry": {"coordinates":[78.925082,12.966451],"type":"Point"}
}