{
  "type": "Feature",
  "properties": {
    "gn:admin1_code":"36",
    "gn:admin2_code":"142.0",
    "gn:asciiname":"Karera",
    "gn:country_code":"IN",
    "gn:dem":198,
    "gn:feature_class":"P",
    "gn:feature_code":"PPL",
    "gn:name":"Karera",
    "gn:population":0,
    "gn:timezone":"Asia/Kolkata",
    "iso:country":"IN",
    "name:ben_x_preferred":[
        "\u0995\u09be\u09b0\u09c7\u09b0\u09be"
    ],
    "name:bpy_x_preferred":[
        "\u0995\u09be\u09b0\u09c7\u09b0\u09be"
    ],
    "name:ceb_x_preferred":[
        "Karera"
    ],
    "name:ita_x_preferred":[
        "Karera"
    ],
    "name:msa_x_preferred":[
        "Karera"
    ],
    "name:new_x_preferred":[
        "\u0915\u0930\u0947\u0930\u093e"
    ],
    "name:nld_x_preferred":[
        "Karera"
    ],
    "name:por_x_preferred":[
        "Karera"
    ],
    "name:spa_x_preferred":[
        "Karera"
    ],
    "name:swe_x_preferred":[
        "Karera"
    ],
    "name:vie_x_preferred":[
        "Karera"
    ],
    "name:zho_x_preferred":[
        "\u5361\u96f7\u62c9"
    ],
    "wof:name":"Karera",
    "wof:placetype":"locality"
},
  "geometry": {"coordinates":[78.01178,28.30695],"type":"Point"}
}