{
  "type": "Feature",
  "properties": {
    "gn:admin1_code":"36",
    "gn:admin2_code":"142.0",
    "gn:asciiname":"Karera",
    "gn:country_code":"IN",
    "gn:dem":198,
    "gn:feature_class":"P",
    "gn:feature_code":"PPL",
    "gn:name":"Karera",
    "gn:population":0,
    "gn:timezone":"Asia/Kolkata",
    "iso:country":"IN",
    "name:ara_x_preferred":[
        "\u0643\u0627\u0631\u064a\u0631\u0627"
    ],
    "name:ben_bn_x_preferred":[
        "\u0995\u09b0\u09c7\u09b0\u09be"
    ],
    "name:ben_in_x_preferred":[
        "\u0995\u09b0\u09c7\u09b0\u09be"
    ],
    "name:ben_x_preferred":[
        "\u0995\u09be\u09b0\u09c7\u09b0\u09be"
    ],
    "name:bpy_x_preferred":[
        "\u0995\u09be\u09b0\u09c7\u09b0\u09be"
    ],
    "name:ceb_x_preferred":[
        "Karera"
    ],
    "name:guj_x_preferred":[
        "\u0a95\u0abe\u0ab0\u0ac7\u0ab0\u0abe"
    ],
    "name:hin_x_preferred":[
        "\u0915\u0930\u0947\u0930\u093e"
    ],
    "name:ita_x_preferred":[
        "Karera"
    ],
    "name:kan_x_preferred":[
        "\u0c95\u0cb0\u0cc6\u0cb0\u0cbe"
    ],
    "name:mal_x_preferred":[
        "\u0d15\u0d30\u0d47\u0d30"
    ],
    "name:mar_x_preferred":[
        "\u0915\u0930\u0947\u0930\u093e"
    ],
    "name:msa_x_preferred":[
        "Karera"
    ],
    "name:new_x_preferred":[
        "\u0915\u0930\u0947\u0930\u093e"
    ],
    "name:nld_x_preferred":[
        "Karera"
    ],
    "name:pan_x_preferred":[
        "\u0a15\u0a30\u0a48\u0a30\u0a3e"
    ],
    "name:por_x_preferred":[
        "Karera"
    ],
    "name:spa_x_preferred":[
        "Karera"
    ],
    "name:swe_x_preferred":[
        "Karera"
    ],
    "name:tam_x_preferred":[
        "\u0b95\u0bb0\u0bc7\u0bb0\u0bbe"
    ],
    "name:tel_x_preferred":[
        "\u0c15\u0c30\u0c46\u0c30\u0c3e"
    ],
    "name:urd_x_preferred":[
        "\u06a9\u0631\u06cc\u0631\u0627"
    ],
    "name:vie_x_preferred":[
        "Karera"
    ],
    "name:zho_x_preferred":[
        "\u5361\u96f7\u62c9"
    ],
    "wof:name":"Karera",
    "wof:placetype":"locality"
},
  "geometry": {"coordinates":[78.01178,28.30695],"type":"Point"}
}