{
  "type": "Feature",
  "properties": {
    "iso:country":"IN",
    "ks:ks_name":"Sapertara",
    "ks:ks_pop":80,
    "ks:ks_type":"HABITATION",
    "name:eng_x_preferred":[
        "Sapertara"
    ],
    "wof:name":"Sapertara",
    "wof:placetype":"locality",
    "wof:population":80
},
  "geometry": {"coordinates":[82.726117,22.819285],"type":"Point"}
}