{
  "type": "Feature",
  "properties": {
    "iso:country":"IN",
    "ks:ks_name":"Bhurungiasole",
    "ks:ks_pop":1024,
    "ks:ks_type":"VILLAGE",
    "name:eng_x_preferred":[
        "Bhurungiasole"
    ],
    "wof:name":"Bhurungiasole",
    "wof:placetype":"locality",
    "wof:population":1024
},
  "geometry": {"coordinates":[86.96583200000001,21.933908],"type":"Point"}
}