{
  "type": "Feature",
  "properties": {
    "gn:admin1_code":"39.0",
    "gn:admin2_code":"67.0",
    "gn:asciiname":"Bharauni",
    "gn:country_code":"IN",
    "gn:dem":222,
    "gn:feature_class":"P",
    "gn:feature_code":"PPL",
    "gn:name":"Bharauni",
    "gn:population":0,
    "gn:timezone":"Asia/Kolkata",
    "iso:country":"IN",
    "wof:name":"Bharauni",
    "wof:placetype":"locality"
},
  "geometry": {"coordinates":[79.73633000000002,28.99576],"type":"Point"}
}