{
  "type": "Feature",
  "properties": {
    "gn:admin1_code":"12.0",
    "gn:admin2_code":"18.0",
    "gn:asciiname":"Dachhila",
    "gn:country_code":"IN",
    "gn:dem":2170,
    "gn:feature_class":"P",
    "gn:feature_code":"PPL",
    "gn:name":"Dachh\u012bla",
    "gn:population":0,
    "gn:timezone":"Asia/Kolkata",
    "iso:country":"IN",
    "wof:name":"Dachhila",
    "wof:placetype":"locality"
},
  "geometry": {"coordinates":[75.89102,33.31583],"type":"Point"}
}