{
  "type": "Feature",
  "properties": {
    "iso:country":"IN",
    "ks:ks_name":"Jagannathdi",
    "ks:ks_pop":168,
    "ks:ks_type":"VILLAGE",
    "name:eng_x_preferred":[
        "Jagannathdi"
    ],
    "wof:name":"Jagannathdi",
    "wof:placetype":"locality",
    "wof:population":168
},
  "geometry": {"coordinates":[86.795441,23.446471],"type":"Point"}
}