{
  "type": "Feature",
  "properties": {
    "iso:country":"IN",
    "ks:ks_name":"Sudukhanda",
    "ks:ks_pop":89,
    "ks:ks_type":"VILLAGE",
    "ks:ks_uagg_main":0,
    "name:eng_x_preferred":[
        "Sudukhanda"
    ],
    "wof:name":"Sudukhanda",
    "wof:placetype":"neighbourhood",
    "wof:population":89
},
  "geometry": {"coordinates":[85.95453500000001,19.92126],"type":"Point"}
}