{
  "type": "Feature",
  "properties": {
    "gn:admin1_code":"19.0",
    "gn:admin2_code":"567.0",
    "gn:asciiname":"Dyamavvanahalli",
    "gn:country_code":"IN",
    "gn:dem":641,
    "gn:feature_class":"P",
    "gn:feature_code":"PPL",
    "gn:name":"Dy\u0101mavvanahalli",
    "gn:population":0,
    "gn:timezone":"Asia/Kolkata",
    "iso:country":"IN",
    "name:vie_x_preferred":[
        "Dyamavvanahalli"
    ],
    "wof:name":"Dyamavvanahalli",
    "wof:placetype":"locality"
},
  "geometry": {"coordinates":[76.11088000000002,14.48437],"type":"Point"}
}