{
  "type": "Feature",
  "properties": {
    "iso:country":"IN",
    "ks:ks_name":"Tafrapurwa",
    "ks:ks_pop":100,
    "ks:ks_type":"HABITATION",
    "name:eng_x_preferred":[
        "Tafrapurwa"
    ],
    "wof:name":"Tafrapurwa",
    "wof:placetype":"locality",
    "wof:population":100
},
  "geometry": {"coordinates":[80.941559,27.667204],"type":"Point"}
}