{
  "type": "Feature",
  "properties": {
    "gn:admin1_code":"12.0",
    "gn:admin2_code":"002",
    "gn:asciiname":"Haiyatpur",
    "gn:country_code":"IN",
    "gn:dem":1784,
    "gn:feature_class":"P",
    "gn:feature_code":"PPL",
    "gn:name":"Haiyatpur",
    "gn:population":0,
    "gn:timezone":"Asia/Kolkata",
    "iso:country":"IN",
    "wof:name":"Haiyatpur",
    "wof:placetype":"locality"
},
  "geometry": {"coordinates":[74.61423000000001,34.01927],"type":"Point"}
}