{
  "type": "Feature",
  "properties": {
    "iso:country":"IN",
    "ks:ks_name":"Sirki",
    "ks:ks_pop":229,
    "ks:ks_type":"VILLAGE",
    "name:eng_x_preferred":[
        "Sirki"
    ],
    "wof:name":"Sirki",
    "wof:placetype":"locality",
    "wof:population":229
},
  "geometry": {"coordinates":[83.140455,22.585362],"type":"Point"}
}