{
  "type": "Feature",
  "properties": {
    "iso:country":"IN",
    "ks:ks_name":"Arazi Tegaraha",
    "ks:ks_pop":0,
    "ks:ks_type":"VILLAGE",
    "name:eng_x_preferred":[
        "Arazi Tegaraha"
    ],
    "wof:name":"Arazi Tegaraha",
    "wof:placetype":"locality",
    "wof:population":0
},
  "geometry": {"coordinates":[83.234081,26.34254],"type":"Point"}
}