{
  "type": "Feature",
  "properties": {
    "iso:country":"IN",
    "ks:ks_name":"Kambapada",
    "ks:ks_pop":22,
    "ks:ks_type":"VILLAGE",
    "name:eng_x_preferred":[
        "Kambapada"
    ],
    "wof:name":"Kambapada",
    "wof:placetype":"locality",
    "wof:population":22
},
  "geometry": {"coordinates":[84.01439999999999,20.289539],"type":"Point"}
}