{
  "type": "Feature",
  "properties": {
    "iso:country":"IN",
    "ks:ks_name":"Kodalhara",
    "ks:ks_pop":0,
    "ks:ks_type":"VILLAGE",
    "name:eng_x_preferred":[
        "Kodalhara"
    ],
    "wof:name":"Kodalhara",
    "wof:placetype":"locality",
    "wof:population":0
},
  "geometry": {"coordinates":[87.32575799999999,22.469219],"type":"Point"}
}