{
  "type": "Feature",
  "properties": {
    "iso:country":"IN",
    "ks:ks_name":"Chenglimari",
    "ks:ks_pop":334,
    "ks:ks_type":"VILLAGE",
    "ks:ks_uagg_main":0,
    "name:eng_x_preferred":[
        "Chenglimari"
    ],
    "wof:name":"Chenglimari",
    "wof:placetype":"neighbourhood",
    "wof:population":334
},
  "geometry": {"coordinates":[91.13090200000001,26.638818],"type":"Point"}
}