{
  "type": "Feature",
  "properties": {
    "gn:admin1_code":"11.0",
    "gn:admin2_code":"025",
    "gn:asciiname":"Chamrat",
    "gn:country_code":"IN",
    "gn:dem":2993,
    "gn:feature_class":"P",
    "gn:feature_code":"PPL",
    "gn:name":"Chamrat",
    "gn:population":0,
    "gn:timezone":"Asia/Kolkata",
    "iso:country":"IN",
    "wof:name":"Chamrat",
    "wof:placetype":"locality"
},
  "geometry": {"coordinates":[76.72269,32.78918],"type":"Point"}
}