{
  "type": "Feature",
  "properties": {
    "iso:country":"IN",
    "ks:ks_name":"Mahret",
    "ks:ks_type":"VILLAGE",
    "name:eng_x_preferred":[
        "Mahret"
    ],
    "wof:name":"Mahret",
    "wof:placetype":"locality"
},
  "geometry": {"coordinates":[79.92284600000001,29.953312],"type":"Point"}
}