{
  "type": "Feature",
  "properties": {
    "gn:admin1_code":"34.0",
    "gn:admin2_code":"235.0",
    "gn:asciiname":"Saharsa",
    "gn:country_code":"IN",
    "gn:dem":122,
    "gn:feature_class":"P",
    "gn:feature_code":"PPL",
    "gn:name":"Sahars\u0101",
    "gn:population":0,
    "gn:timezone":"Asia/Kolkata",
    "iso:country":"IN",
    "name:ara_x_preferred":[
        "\u0633\u0627\u0647\u0627\u0631\u0633\u0627"
    ],
    "name:ben_x_preferred":[
        "\u09b8\u09b9\u09b0\u09cd\u09b8\u09be"
    ],
    "name:bih_x_preferred":[
        "\u0938\u0939\u0930\u0938\u093e"
    ],
    "name:bpy_x_preferred":[
        "\u09b8\u09b9\u09b0\u09cd\u09b7"
    ],
    "name:ceb_x_preferred":[
        "Saharsa"
    ],
    "name:deu_x_preferred":[
        "Saharsa"
    ],
    "name:fra_x_preferred":[
        "Saharsa"
    ],
    "name:guj_x_preferred":[
        "\u0ab8\u0ab9\u0ab0\u0ab8\u0abe"
    ],
    "name:hin_x_preferred":[
        "\u0938\u0939\u0930\u0938\u093e"
    ],
    "name:ita_x_preferred":[
        "Saharsa"
    ],
    "name:mar_x_preferred":[
        "\u0938\u0939\u0930\u094d\u0938\u093e"
    ],
    "name:mlg_x_preferred":[
        "Saharsa"
    ],
    "name:msa_x_preferred":[
        "Saharsa"
    ],
    "name:nep_x_preferred":[
        "\u0938\u0939\u0930\u0938\u093e"
    ],
    "name:ori_x_preferred":[
        "\u0b38\u0b3e\u0b39\u0b3e\u0b30\u0b4d\u0b38\u0b3e"
    ],
    "name:pol_x_preferred":[
        "Saharsa"
    ],
    "name:por_x_preferred":[
        "Saharsa"
    ],
    "name:rus_x_preferred":[
        "\u0421\u0430\u0445\u0430\u0440\u0441\u0430"
    ],
    "name:san_x_preferred":[
        "\u0938\u0939\u0930\u0938\u093e"
    ],
    "name:spa_x_preferred":[
        "Saharsa"
    ],
    "name:swe_x_preferred":[
        "Saharsa"
    ],
    "name:tel_x_preferred":[
        "\u0c38\u0c39\u0c30\u0c4d\u0c38\u0c3e"
    ],
    "name:tgl_x_preferred":[
        "Saharsa"
    ],
    "name:tur_x_preferred":[
        "Saharsa"
    ],
    "name:urd_x_preferred":[
        "\u0633\u06c1\u0631\u0633\u06c1"
    ],
    "name:vie_x_preferred":[
        "Saharsa"
    ],
    "name:war_x_preferred":[
        "Saharsa"
    ],
    "name:zho_x_preferred":[
        "\u8428\u54c8\u5c14\u8428"
    ],
    "wof:name":"Saharsa",
    "wof:placetype":"locality"
},
  "geometry": {"coordinates":[84.26094999999999,24.74804],"type":"Point"}
}