{
  "type": "Feature",
  "properties": {
    "iso:country":"IN",
    "ks:ks_name":"Mavinakere",
    "ks:ks_pop":365,
    "ks:ks_type":"HABITATION",
    "name:eng_x_preferred":[
        "Mavinakere"
    ],
    "wof:name":"Mavinakere",
    "wof:placetype":"locality",
    "wof:population":365
},
  "geometry": {"coordinates":[75.387528,13.232883],"type":"Point"}
}