{
  "type": "Feature",
  "properties": {
    "iso:country":"IN",
    "ks:ks_name":"Bikrampur",
    "ks:ks_pop":89,
    "ks:ks_type":"HABITATION",
    "name:eng_x_preferred":[
        "Bikrampur"
    ],
    "wof:name":"Bikrampur",
    "wof:placetype":"locality",
    "wof:population":89
},
  "geometry": {"coordinates":[84.171924,19.295082],"type":"Point"}
}