{
  "type": "Feature",
  "properties": {
    "iso:country":"IN",
    "ks:ks_alt_nam":"boyalagudem",
    "ks:ks_name":"Boyalagudem",
    "ks:ks_pop":23,
    "ks:ks_type":"HABITATION",
    "name:eng_x_preferred":[
        "Boyalagudem"
    ],
    "wof:name":"Boyalagudem",
    "wof:placetype":"locality",
    "wof:population":23
},
  "geometry": {"coordinates":[82.415228,17.797057],"type":"Point"}
}