{
  "type": "Feature",
  "properties": {
    "gn:admin1_code":"35.0",
    "gn:admin2_code":"432",
    "gn:asciiname":"Chitakhera",
    "gn:country_code":"IN",
    "gn:dem":506,
    "gn:feature_class":"P",
    "gn:feature_code":"PPL",
    "gn:name":"Chit\u0101khera",
    "gn:population":0,
    "gn:timezone":"Asia/Kolkata",
    "iso:country":"IN",
    "wof:name":"Chitakhera",
    "wof:placetype":"locality"
},
  "geometry": {"coordinates":[74.81799000000002,24.31963],"type":"Point"}
}