{
  "type": "Feature",
  "properties": {
    "iso:country":"IN",
    "ks:ks_name":"Islampur",
    "ks:ks_pop":490,
    "ks:ks_type":"HABITATION",
    "ks:ks_uagg_main":0,
    "name:ben_x_preferred":[
        "\u0987\u09b8\u09b2\u09be\u09ae\u09aa\u09c1\u09b0"
    ],
    "name:eng_x_preferred":[
        "Islampur"
    ],
    "name:hin_x_preferred":[
        "\u0907\u0938\u094d\u0932\u093e\u092e\u092a\u0941\u0930"
    ],
    "name:mar_x_preferred":[
        "\u0907\u0938\u094d\u0932\u093e\u092e\u092a\u0942\u0930"
    ],
    "wof:name":"Islampur",
    "wof:placetype":"neighbourhood",
    "wof:population":490
},
  "geometry": {"coordinates":[82.547957,27.055795],"type":"Point"}
}