{
  "type": "Feature",
  "properties": {
    "gn:admin1_code":"11.0",
    "gn:admin2_code":"24.0",
    "gn:asciiname":"Basa",
    "gn:country_code":"IN",
    "gn:dem":604,
    "gn:feature_class":"P",
    "gn:feature_code":"PPL",
    "gn:name":"B\u0101sa",
    "gn:population":0,
    "gn:timezone":"Asia/Kolkata",
    "iso:country":"IN",
    "name:ceb_x_preferred":[
        "Basa"
    ],
    "name:ces_x_preferred":[
        "Basa"
    ],
    "name:deu_x_preferred":[
        "Basa"
    ],
    "name:fra_x_preferred":[
        "Basa"
    ],
    "name:heb_x_preferred":[
        "\u05d1\u05d0\u05e1\u05d4"
    ],
    "name:lmo_x_preferred":[
        "Basa"
    ],
    "name:slk_x_preferred":[
        "Basa"
    ],
    "name:swe_x_preferred":[
        "Basa"
    ],
    "name:tgl_x_preferred":[
        "Basa"
    ],
    "wof:name":"Basa",
    "wof:placetype":"locality"
},
  "geometry": {"coordinates":[75.94788,32.24492],"type":"Point"}
}