{
  "type": "Feature",
  "properties": {
    "gn:admin1_code":"35.0",
    "gn:admin2_code":"438.0",
    "gn:asciiname":"Kharwali",
    "gn:country_code":"IN",
    "gn:dem":356,
    "gn:feature_class":"P",
    "gn:feature_code":"PPL",
    "gn:name":"Kharw\u0101li",
    "gn:population":0,
    "gn:timezone":"Asia/Kolkata",
    "iso:country":"IN",
    "ks:ks_name":"Kharwali",
    "ks:ks_pop":367,
    "ks:ks_type":"VILLAGE",
    "name:eng_x_preferred":[
        "Kharwali"
    ],
    "wof:name":"Kharwali",
    "wof:placetype":"locality",
    "wof:population":367
},
  "geometry": {"coordinates":[74.858344,22.494],"type":"Point"}
}