{
  "type": "Feature",
  "properties": {
    "gn:admin1_code":"16.0",
    "gn:admin2_code":"529",
    "gn:asciiname":"Bheshi",
    "gn:country_code":"IN",
    "gn:dem":48,
    "gn:feature_class":"P",
    "gn:feature_code":"PPL",
    "gn:name":"Bheshi",
    "gn:population":0,
    "gn:timezone":"Asia/Kolkata",
    "iso:country":"IN",
    "ks:ks_name":"Bhedshi",
    "ks:ks_type":"VILLAGE",
    "ks:ks_uagg_main":0,
    "name:eng_x_preferred":[
        "Bhedshi"
    ],
    "name:und_x_variant":[
        "Bhedshi"
    ],
    "wof:name":"Bhedshi",
    "wof:placetype":"neighbourhood"
},
  "geometry": {"coordinates":[74.031392,15.725728],"type":"Point"}
}