{
  "type": "Feature",
  "properties": {
    "gn:country":"IN",
    "gn:fcode":"PPL",
    "gn:pop":8330,
    "iso:country":"IN",
    "name:ara_x_preferred":[
        "\u0641\u0627\u0644\u0628\u0648\u064a"
    ],
    "name:ben_x_preferred":[
        "\u09ad\u09be\u09b2\u09cd\u09aa\u09cb\u0987"
    ],
    "name:bpy_x_preferred":[
        "\u09ad\u09be\u09b2\u09cd\u09aa\u09cb\u0987"
    ],
    "name:bul_x_preferred":[
        "\u0412\u0430\u043b\u043f\u043e\u0439"
    ],
    "name:chi_x_preferred":[
        "\u74e6\u5c14\u6ce2\u4f0a"
    ],
    "name:dut_x_preferred":[
        "Valpoi"
    ],
    "name:eng_x_preferred":[
        "Valpoi"
    ],
    "name:fre_x_preferred":[
        "Valpoi"
    ],
    "name:hin_x_preferred":[
        "\u0935\u093e\u0932\u092a\u092f"
    ],
    "name:ind_x_preferred":[
        "Valpoi"
    ],
    "name:ita_x_preferred":[
        "Valpoi"
    ],
    "name:may_x_preferred":[
        "Valpoi"
    ],
    "name:nan_x_preferred":[
        "Valpoi"
    ],
    "name:por_x_preferred":[
        "Valpoi"
    ],
    "name:swe_x_preferred":[
        "Valpoy"
    ],
    "name:unk_x_variant":[
        "Valpoi Town"
    ],
    "name:vie_x_preferred":[
        "Valpoi"
    ],
    "qs:name":"Valpoi",
    "qs:name_adm0":"India",
    "qs:name_adm1":"Goa",
    "qs:photos_9k":1,
    "qs:photos_9r":1,
    "qs:photos_all":1,
    "qs:photos_sr":0,
    "qs:placetype":"Town",
    "qs:pop_sr":"5",
    "wd:wordcount":262,
    "wof:name":"Valpoi",
    "wof:placetype":"locality",
    "wof:population":8330
},
  "geometry": {"coordinates":[74.13697000000001,15.53223],"type":"Point"}
}