{
  "type": "Feature",
  "properties": {
    "gn:admin1_code":"34.0",
    "gn:admin2_code":"229.0",
    "gn:asciiname":"Nohsa",
    "gn:country_code":"IN",
    "gn:dem":67,
    "gn:feature_class":"P",
    "gn:feature_code":"PPL",
    "gn:name":"Nohsa",
    "gn:population":0,
    "gn:timezone":"Asia/Kolkata",
    "iso:country":"IN",
    "name:urd_x_preferred":[
        "\u0646\u06c1\u0633\u06c1"
    ],
    "wof:name":"Nohsa",
    "wof:placetype":"locality"
},
  "geometry": {"coordinates":[85.33904,25.13582],"type":"Point"}
}