{
  "type": "Feature",
  "properties": {
    "iso:country":"IN",
    "ks:ks_name":"Loharwadi",
    "ks:ks_pop":10,
    "ks:ks_type":"HABITATION",
    "name:eng_x_preferred":[
        "Loharwadi"
    ],
    "wof:name":"Loharwadi",
    "wof:placetype":"locality",
    "wof:population":10
},
  "geometry": {"coordinates":[73.37105200000001,16.864606],"type":"Point"}
}