{
  "type": "Feature",
  "properties": {
    "gn:admin1_code":"34.0",
    "gn:admin2_code":"208.0",
    "gn:asciiname":"Mahi Sardar Chakla",
    "gn:country_code":"IN",
    "gn:dem":60,
    "gn:feature_class":"P",
    "gn:feature_code":"PPL",
    "gn:name":"Mahi Sard\u0101r Chakla",
    "gn:population":0,
    "gn:timezone":"Asia/Kolkata",
    "iso:country":"IN",
    "wof:name":"Mahi Sardar Chakla",
    "wof:placetype":"locality"
},
  "geometry": {"coordinates":[86.76243000000002,26.21157],"type":"Point"}
}