{
  "type": "Feature",
  "properties": {
    "gn:admin1_code":"36",
    "gn:admin2_code":"172.0",
    "gn:asciiname":"Didar ka Purwa",
    "gn:country_code":"IN",
    "gn:dem":108,
    "gn:feature_class":"P",
    "gn:feature_code":"PPL",
    "gn:name":"Did\u0101r ka Purwa",
    "gn:population":0,
    "gn:timezone":"Asia/Kolkata",
    "iso:country":"IN",
    "wof:name":"Didar ka Purwa",
    "wof:placetype":"locality"
},
  "geometry": {"coordinates":[81.23172,25.56843],"type":"Point"}
}