{
  "type": "Feature",
  "properties": {
    "iso:country":"IN",
    "ks:ks_name":"Pimpalshend",
    "ks:ks_pop":0,
    "ks:ks_type":"VILLAGE",
    "name:eng_x_preferred":[
        "Pimpalshend"
    ],
    "wof:name":"Pimpalshend",
    "wof:placetype":"locality",
    "wof:population":0
},
  "geometry": {"coordinates":[77.083206,20.55945],"type":"Point"}
}