{
  "type": "Feature",
  "properties": {
    "iso:country":"IN",
    "ks:ks_name":"Singarpur",
    "ks:ks_type":"VILLAGE",
    "name:eng_x_preferred":[
        "Singarpur"
    ],
    "wof:name":"Singarpur",
    "wof:placetype":"locality"
},
  "geometry": {"coordinates":[80.497962,22.757821],"type":"Point"}
}