{
  "type": "Feature",
  "properties": {
    "iso:country":"IN",
    "ks:ks_name":"Dhartemia",
    "ks:ks_pop":784,
    "ks:ks_type":"HABITATION",
    "name:eng_x_preferred":[
        "Dhartemia"
    ],
    "wof:name":"Dhartemia",
    "wof:placetype":"locality",
    "wof:population":784
},
  "geometry": {"coordinates":[88.39286,23.049219],"type":"Point"}
}