{
  "type": "Feature",
  "properties": {
    "gn:country":"IN",
    "gn:fcode":"PPL",
    "gn:population":4302,
    "iso:country":"IN",
    "name:ben_x_preferred":[
        "\u09b6\u09be\u09b9\u09aa\u09c1\u09b0"
    ],
    "name:cat_x_preferred":[
        "Shapur"
    ],
    "name:nld_x_preferred":[
        "Shahpur"
    ],
    "name:pol_x_preferred":[
        "Shahpur"
    ],
    "name:por_x_preferred":[
        "Shahpur"
    ],
    "qs:name":"Shahpur",
    "qs:name_adm0":"India",
    "qs:name_adm1":"Madhya Pradesh",
    "qs:photos_9r":0,
    "qs:photos_sr":0,
    "qs:placetype":"Town",
    "qs:pop_sr":"4",
    "wd:wordcount":145,
    "wof:name":"Shahpur",
    "wof:placetype":"locality",
    "wof:population":4302
},
  "geometry": {"coordinates":[77.90777,22.1951],"type":"Point"}
}