{
  "type": "Feature",
  "properties": {
    "gn:country":"IN",
    "gn:fcode":"PPL",
    "gn:population":4302,
    "iso:country":"IN",
    "name:ara_x_preferred":[
        "\u0634\u0627\u0647\u0628\u0648\u0631"
    ],
    "name:ben_bn_x_preferred":[
        "\u09b6\u09be\u09b9\u09aa\u09c1\u09b0"
    ],
    "name:ben_in_x_preferred":[
        "\u09b6\u09be\u09b9\u09aa\u09c1\u09b0"
    ],
    "name:ben_x_preferred":[
        "\u09b6\u09be\u09b9\u09aa\u09c1\u09b0"
    ],
    "name:cat_x_preferred":[
        "Shapur"
    ],
    "name:guj_x_preferred":[
        "\u0ab6\u0abe\u0ab9\u0aaa\u0ac1\u0ab0"
    ],
    "name:hin_x_preferred":[
        "\u0936\u093e\u0939\u092a\u0941\u0930"
    ],
    "name:kan_x_preferred":[
        "\u0cb6\u0cbe\u0cb9\u0ccd"
    ],
    "name:mal_x_preferred":[
        "\u0d37\u0d3e\u0d2a\u0d4d\u0d2a\u0d42\u0d7c"
    ],
    "name:mar_x_preferred":[
        "\u0936\u093e\u0939\u092a\u0942\u0930"
    ],
    "name:nld_x_preferred":[
        "Shahpur"
    ],
    "name:pan_x_preferred":[
        "\u0a36\u0a3e\u0a39\u0a2a\u0a41\u0a30"
    ],
    "name:pol_x_preferred":[
        "Shahpur"
    ],
    "name:por_x_preferred":[
        "Shahpur"
    ],
    "name:tam_x_preferred":[
        "\u0bb7\u0bbe\u0baa\u0bc2\u0bb0\u0bcd"
    ],
    "name:tel_x_preferred":[
        "\u0c37\u0c3e\u0c2a\u0c42\u0c30\u0c4d"
    ],
    "name:urd_x_preferred":[
        "\u0634\u0627\u06c1 \u067e\u0648\u0631"
    ],
    "qs:name":"Shahpur",
    "qs:name_adm0":"India",
    "qs:name_adm1":"Madhya Pradesh",
    "qs:photos_9r":0,
    "qs:photos_sr":0,
    "qs:placetype":"Town",
    "qs:pop_sr":"4",
    "wd:wordcount":145,
    "wof:name":"Shahpur",
    "wof:placetype":"locality",
    "wof:population":4302
},
  "geometry": {"coordinates":[77.90777,22.1951],"type":"Point"}
}