{
  "type": "Feature",
  "properties": {
    "iso:country":"IN",
    "ks:ks_name":"Kamarabandha",
    "ks:ks_pop":383,
    "ks:ks_type":"VILLAGE",
    "ks:ks_uagg_main":0,
    "name:eng_x_preferred":[
        "Kamarabandha"
    ],
    "wof:name":"Kamarabandha",
    "wof:placetype":"neighbourhood",
    "wof:population":383
},
  "geometry": {"coordinates":[85.80380700000001,21.960051],"type":"Point"}
}