{
  "type": "Feature",
  "properties": {
    "iso:country":"IN",
    "ks:ks_name":"Salura Dakhili",
    "ks:ks_pop":188,
    "ks:ks_type":"HABITATION",
    "name:eng_x_preferred":[
        "Salura Dakhili"
    ],
    "wof:name":"Salura Dakhili",
    "wof:placetype":"locality",
    "wof:population":188
},
  "geometry": {"coordinates":[77.94721800000001,25.147722],"type":"Point"}
}