{
  "type": "Feature",
  "properties": {
    "iso:country":"IN",
    "ks:ks_name":"Bhuiya Tola",
    "ks:ks_pop":164,
    "ks:ks_type":"HABITATION",
    "name:eng_x_preferred":[
        "Bhuiya Tola"
    ],
    "wof:name":"Bhuiya Tola",
    "wof:placetype":"locality",
    "wof:population":164
},
  "geometry": {"coordinates":[83.56882400000001,24.174225],"type":"Point"}
}