{
  "type": "Feature",
  "properties": {
    "iso:country":"IN",
    "ks:ks_name":"Jalwalli",
    "ks:ks_pop":2529,
    "ks:ks_type":"VILLAGE",
    "name:eng_x_preferred":[
        "Jalwalli"
    ],
    "wof:name":"Jalwalli",
    "wof:placetype":"locality",
    "wof:population":2529
},
  "geometry": {"coordinates":[74.52858999999999,14.256689],"type":"Point"}
}