{
  "type": "Feature",
  "properties": {
    "iso:country":"IN",
    "name:ast_x_preferred":[
        "Halebidu"
    ],
    "name:bar_x_preferred":[
        "Halebid"
    ],
    "name:ben_x_preferred":[
        "\u09b9\u09c8\u09b2\u09c7\u09ac\u09bf\u09a1\u09c1"
    ],
    "name:ben_x_variant":[
        "\u09b9\u09be\u09b2\u09c7\u09ac\u09bf\u09a1\u09bc\u09c1"
    ],
    "name:cat_x_preferred":[
        "Halebidu"
    ],
    "name:ceb_x_preferred":[
        "Haleb\u012bd"
    ],
    "name:deu_x_preferred":[
        "Halebid"
    ],
    "name:eng_x_preferred":[
        "Halebidu"
    ],
    "name:fra_x_preferred":[
        "Halebid"
    ],
    "name:heb_x_preferred":[
        "\u05d4\u05dc\u05d1\u05d9\u05d3\u05d5"
    ],
    "name:hin_x_preferred":[
        "\u0939\u0948\u0932\u0947\u092c\u093f\u0921\u0941"
    ],
    "name:hun_x_preferred":[
        "Halebid"
    ],
    "name:ita_x_preferred":[
        "Halebidu"
    ],
    "name:jpn_x_preferred":[
        "\u30cf\u30ec\u30fc\u30d3\u30fc\u30c9\u30a5"
    ],
    "name:kan_x_preferred":[
        "\u0cb9\u0cb3\u0cc7\u0cac\u0cc0\u0ca1\u0cc1"
    ],
    "name:mal_x_preferred":[
        "\u0d39\u0d32\u0d47\u0d2c\u0d40\u0d21\u0d41"
    ],
    "name:mar_x_preferred":[
        "\u0939\u0933\u0947\u092c\u0940\u0921\u0941"
    ],
    "name:mlg_x_preferred":[
        "Halebidu"
    ],
    "name:nld_x_preferred":[
        "Halebidu"
    ],
    "name:pol_x_preferred":[
        "Halebidu"
    ],
    "name:rus_x_preferred":[
        "\u0425\u0430\u043b\u0435\u0431\u0438\u0434"
    ],
    "name:san_x_preferred":[
        "\u0939\u0933\u0947\u092c\u0940\u0921\u0941"
    ],
    "name:spa_x_preferred":[
        "Halebidu"
    ],
    "name:swe_x_preferred":[
        "Haleb\u012bd"
    ],
    "name:tam_x_preferred":[
        "\u0bb9\u0bb3\u0baa\u0bc0\u0b9f\u0bc1"
    ],
    "name:tel_x_preferred":[
        "\u0c39\u0c33\u0c47\u0c2c\u0c40\u0c21\u0c41"
    ],
    "name:tha_x_preferred":[
        "\u0e2b\u0e40\u0e25\u0e1e\u0e35\u0e11\u0e39"
    ],
    "name:tur_x_preferred":[
        "Halebidu"
    ],
    "name:vie_x_preferred":[
        "Halebeedu"
    ],
    "name:zho_x_preferred":[
        "\u54c8\u52d2\u6bd4\u5fb7"
    ],
    "qs:name":"Halebeedu",
    "qs:name_adm0":"India",
    "qs:name_adm1":"Karnataka",
    "qs:photos":531,
    "qs:photos_1k":108,
    "qs:photos_9k":2,
    "qs:photos_9r":5,
    "qs:photos_all":531,
    "qs:photos_sr":7,
    "qs:placetype":"Town",
    "qs:pop_sr":"0",
    "wd:wordcount":656,
    "wof:name":"Halebeedu",
    "wof:placetype":"neighbourhood"
},
  "geometry": {"coordinates":[75.99071499999999,13.218054],"type":"Point"}
}