{
  "type": "Feature",
  "properties": {
    "iso:country":"IN",
    "ks:ks_name":"Kapiya Khalaswa",
    "ks:ks_pop":862,
    "ks:ks_type":"HABITATION",
    "name:eng_x_preferred":[
        "Kapiya Khalaswa"
    ],
    "wof:name":"Kapiya Khalaswa",
    "wof:placetype":"locality",
    "wof:population":862
},
  "geometry": {"coordinates":[83.03524,27.380962],"type":"Point"}
}