{
  "type": "Feature",
  "properties": {
    "iso:country":"IN",
    "ks:ks_name":"Amasinaickanur",
    "ks:ks_pop":101,
    "ks:ks_type":"HABITATION",
    "name:eng_x_preferred":[
        "Amasinaickanur"
    ],
    "wof:name":"Amasinaickanur",
    "wof:placetype":"locality",
    "wof:population":101
},
  "geometry": {"coordinates":[78.393029,12.444077],"type":"Point"}
}