{
  "type": "Feature",
  "properties": {
    "iso:country":"IN",
    "ks:ks_name":"Santipur",
    "ks:ks_pop":155,
    "ks:ks_type":"HABITATION",
    "name:eng_x_preferred":[
        "Santipur"
    ],
    "wof:name":"Santipur",
    "wof:placetype":"locality",
    "wof:population":155
},
  "geometry": {"coordinates":[92.02514600000001,26.16445],"type":"Point"}
}