{
  "type": "Feature",
  "properties": {
    "iso:country":"IN",
    "ks:ks_name":"Santipur",
    "ks:ks_pop":155,
    "ks:ks_type":"HABITATION",
    "name:ben_x_preferred":[
        "\u09b6\u09be\u09a8\u09cd\u09a4\u09bf\u09aa\u09c1\u09b0"
    ],
    "name:eng_x_preferred":[
        "Santipur"
    ],
    "name:hin_x_preferred":[
        "\u0936\u093e\u0902\u0924\u093f\u092a\u0941\u0930"
    ],
    "wof:name":"Santipur",
    "wof:placetype":"locality",
    "wof:population":155
},
  "geometry": {"coordinates":[92.02514600000001,26.16445],"type":"Point"}
}