{
  "type": "Feature",
  "properties": {
    "iso:country":"IN",
    "ks:ks_name":"Bhanarkola",
    "ks:ks_pop":122,
    "ks:ks_type":"HABITATION",
    "name:eng_x_preferred":[
        "Bhanarkola"
    ],
    "wof:name":"Bhanarkola",
    "wof:placetype":"locality",
    "wof:population":122
},
  "geometry": {"coordinates":[86.931895,24.643621],"type":"Point"}
}