{
  "type": "Feature",
  "properties": {
    "iso:country":"IN",
    "ks:ks_name":"Chalchalia",
    "ks:ks_pop":714,
    "ks:ks_type":"VILLAGE",
    "ks:ks_uagg_main":0,
    "name:eng_x_preferred":[
        "Chalchalia"
    ],
    "wof:name":"Chalchalia",
    "wof:placetype":"neighbourhood",
    "wof:population":714
},
  "geometry": {"coordinates":[90.897228,26.452667],"type":"Point"}
}