{
  "type": "Feature",
  "properties": {
    "iso:country":"IN",
    "ks:ks_name":"Kattumedu",
    "ks:ks_pop":110,
    "ks:ks_type":"HABITATION",
    "name:eng_x_preferred":[
        "Kattumedu"
    ],
    "wof:name":"Kattumedu",
    "wof:placetype":"locality",
    "wof:population":110
},
  "geometry": {"coordinates":[80.10735200000001,13.454617],"type":"Point"}
}