{
  "type": "Feature",
  "properties": {
    "gn:admin1_code":"36",
    "gn:admin2_code":"176.0",
    "gn:asciiname":"Palhri",
    "gn:country_code":"IN",
    "gn:dem":120,
    "gn:feature_class":"P",
    "gn:feature_code":"PPL",
    "gn:name":"Palhri",
    "gn:population":0,
    "gn:timezone":"Asia/Kolkata",
    "iso:country":"IN",
    "ks:ks_name":"Palhari",
    "ks:ks_pop":3008,
    "ks:ks_type":"VILLAGE",
    "name:eng_x_preferred":[
        "Palhari"
    ],
    "name:eng_x_variant":[
        "Palhri"
    ],
    "wof:name":"Palhari",
    "wof:placetype":"locality",
    "wof:population":3008
},
  "geometry": {"coordinates":[81.359421,26.898824],"type":"Point"}
}