{
  "type": "Feature",
  "properties": {
    "gn:admin1_code":"31.0",
    "gn:admin2_code":"283",
    "gn:asciiname":"Khawlek",
    "gn:country_code":"IN",
    "gn:dem":1250,
    "gn:feature_class":"P",
    "gn:feature_code":"PPL",
    "gn:name":"Khawlek",
    "gn:population":0,
    "gn:timezone":"Asia/Kolkata",
    "iso:country":"IN",
    "wof:name":"Khawlek",
    "wof:placetype":"locality"
},
  "geometry": {"coordinates":[93.02549999999999,24.07059],"type":"Point"}
}