{
  "type": "Feature",
  "properties": {
    "iso:country":"IN",
    "ks:ks_alt_nam":"Bhatnapaity Char N.C.-6",
    "ks:ks_name":"Bhatnapaity Char N.c.-6",
    "ks:ks_pop":1323,
    "ks:ks_type":"HABITATION",
    "name:eng_x_preferred":[
        "Bhatnapaity Char N.c.-6"
    ],
    "wof:name":"Bhatnapaity Char N.c.-6",
    "wof:placetype":"locality",
    "wof:population":1323
},
  "geometry": {"coordinates":[90.85171800000001,26.104601],"type":"Point"}
}