{
  "type": "Feature",
  "properties": {
    "iso:country":"IN",
    "ks:ks_name":"Salebettu",
    "ks:ks_pop":90,
    "ks:ks_type":"HABITATION",
    "name:eng_x_preferred":[
        "Salebettu"
    ],
    "wof:name":"Salebettu",
    "wof:placetype":"locality",
    "wof:population":90
},
  "geometry": {"coordinates":[74.833899,13.805661],"type":"Point"}
}