{
  "type": "Feature",
  "properties": {
    "iso:country":"IN",
    "ks:ks_name":"Chikkaianapalya",
    "ks:ks_pop":248,
    "ks:ks_type":"HABITATION",
    "name:eng_x_preferred":[
        "Chikkaianapalya"
    ],
    "wof:name":"Chikkaianapalya",
    "wof:placetype":"locality",
    "wof:population":248
},
  "geometry": {"coordinates":[77.083652,13.217729],"type":"Point"}
}