{
  "type": "Feature",
  "properties": {
    "iso:country":"IN",
    "ks:ks_name":"Lafasail Pt IIi",
    "ks:ks_pop":3485,
    "ks:ks_type":"VILLAGE",
    "name:eng_x_preferred":[
        "Lafasail Pt IIi"
    ],
    "wof:name":"Lafasail Pt IIi",
    "wof:placetype":"locality",
    "wof:population":3485
},
  "geometry": {"coordinates":[92.250683,24.902521],"type":"Point"}
}