{
  "type": "Feature",
  "properties": {
    "iso:country":"IN",
    "ks:ks_name":"Sabarpada",
    "ks:ks_pop":439,
    "ks:ks_type":"HABITATION",
    "name:eng_x_preferred":[
        "Sabarpada"
    ],
    "wof:name":"Sabarpada",
    "wof:placetype":"locality",
    "wof:population":439
},
  "geometry": {"coordinates":[73.1019,20.044795],"type":"Point"}
}