{
  "type": "Feature",
  "properties": {
    "iso:country":"IN",
    "ks:ks_name":"Kalarpara",
    "ks:ks_pop":442,
    "ks:ks_type":"HABITATION",
    "name:eng_x_preferred":[
        "Kalarpara"
    ],
    "wof:name":"Kalarpara",
    "wof:placetype":"locality",
    "wof:population":442
},
  "geometry": {"coordinates":[81.86528300000001,19.476822],"type":"Point"}
}