{
  "type": "Feature",
  "properties": {
    "iso:country":"IN",
    "ks:ks_name":"Balakat",
    "ks:ks_pop":187,
    "ks:ks_type":"VILLAGE",
    "name:eng_x_preferred":[
        "Balakat"
    ],
    "wof:name":"Balakat",
    "wof:placetype":"locality",
    "wof:population":187
},
  "geometry": {"coordinates":[88.089213,25.362631],"type":"Point"}
}