{
  "type": "Feature",
  "properties": {
    "iso:country":"IN",
    "ks:ks_name":"Dihi Kalas",
    "ks:ks_pop":9594,
    "ks:ks_type":"URBAN",
    "ks:ks_uagg_main":0,
    "name:eng_x_preferred":[
        "Dihi Kalas"
    ],
    "wof:name":"Dihi Kalas",
    "wof:placetype":"neighbourhood",
    "wof:population":9594
},
  "geometry": {"coordinates":[88.352509,22.245384],"type":"Point"}
}