{
  "type": "Feature",
  "properties": {
    "gn:admin1_code":"19",
    "gn:admin2_code":"556.0",
    "gn:asciiname":"Savalgi",
    "gn:country_code":"IN",
    "gn:dem":567,
    "gn:feature_class":"P",
    "gn:feature_code":"PPL",
    "gn:name":"S\u0101valgi",
    "gn:population":0,
    "gn:timezone":"Asia/Kolkata",
    "iso:country":"IN",
    "name:und_x_variant":[
        "Savaigi",
        "S\u0101valgi"
    ],
    "wof:name":"Savalgi",
    "wof:placetype":"locality"
},
  "geometry": {"coordinates":[75.34726999999999,16.6713],"type":"Point"}
}