{
  "type": "Feature",
  "properties": {
    "iso:country":"IN",
    "ks:ks_name":"Bamblewadi",
    "ks:ks_pop":190,
    "ks:ks_type":"HABITATION",
    "name:eng_x_preferred":[
        "Bamblewadi"
    ],
    "wof:name":"Bamblewadi",
    "wof:placetype":"locality",
    "wof:population":190
},
  "geometry": {"coordinates":[73.76704599999999,19.163307],"type":"Point"}
}