{
  "type": "Feature",
  "properties": {
    "iso:country":"IN",
    "ks:ks_name":"Visheswar Pur",
    "ks:ks_pop":307,
    "ks:ks_type":"HABITATION",
    "name:eng_x_preferred":[
        "Visheswar Pur"
    ],
    "wof:name":"Visheswar Pur",
    "wof:placetype":"locality",
    "wof:population":307
},
  "geometry": {"coordinates":[80.395748,27.031943],"type":"Point"}
}