{
  "type": "Feature",
  "properties": {
    "gn:admin1_code":"21",
    "gn:asciiname":"Banbahali",
    "gn:country_code":"IN",
    "gn:dem":273,
    "gn:feature_class":"P",
    "gn:feature_code":"PPL",
    "gn:name":"Banbah\u0101li",
    "gn:population":0,
    "gn:timezone":"Asia/Kolkata",
    "iso:country":"IN",
    "ks:ks_alt_nam":"Banbah\u0101li",
    "ks:ks_name":"Banbahali",
    "ks:ks_type":"VILLAGE",
    "name:eng_x_preferred":[
        "Banbahali"
    ],
    "name:eng_x_variant":[
        "Banbah\u0101li"
    ],
    "wof:name":"Banbahali",
    "wof:placetype":"locality"
},
  "geometry": {"coordinates":[83.599227,21.915729],"type":"Point"}
}