{
  "type": "Feature",
  "properties": {
    "iso:country":"IN",
    "ks:ks_name":"Sarvar",
    "ks:ks_pop":128,
    "ks:ks_type":"VILLAGE",
    "name:eng_x_preferred":[
        "Sarvar"
    ],
    "wof:name":"Sarvar",
    "wof:placetype":"locality",
    "wof:population":128
},
  "geometry": {"coordinates":[73.14261500000001,18.142792],"type":"Point"}
}