{
  "type": "Feature",
  "properties": {
    "gn:admin1_code":"37",
    "gn:admin2_code":"408.0",
    "gn:asciiname":"Saloni",
    "gn:country_code":"IN",
    "gn:dem":347,
    "gn:feature_class":"P",
    "gn:feature_code":"PPL",
    "gn:name":"Salon\u012b",
    "gn:population":0,
    "gn:timezone":"Asia/Kolkata",
    "iso:country":"IN",
    "name:ara_x_preferred":[
        "\u0635\u0627\u0644\u0648\u0646\u064a"
    ],
    "name:ben_bn_x_preferred":[
        "\u09b8\u09be\u09b2\u09cb\u09a8\u09bf"
    ],
    "name:ben_in_x_preferred":[
        "\u09b8\u09be\u09b2\u09cb\u09a8\u09bf"
    ],
    "name:cat_x_preferred":[
        "Saloni"
    ],
    "name:guj_x_preferred":[
        "\u0ab8\u0ab2\u0acb\u0aa8\u0ac0"
    ],
    "name:hin_x_preferred":[
        "\u0938\u0932\u094b\u0928\u0940"
    ],
    "name:kan_x_preferred":[
        "\u0cb8\u0cb2\u0ccb\u0ca8\u0cbf"
    ],
    "name:mal_x_preferred":[
        "\u0d38\u0d32\u0d4b\u0d28\u0d3f"
    ],
    "name:mar_x_preferred":[
        "\u0938\u0932\u094b\u0928\u0940"
    ],
    "name:pan_x_preferred":[
        "\u0a38\u0a3e\u0a32\u0a4c\u0a28\u0a40"
    ],
    "name:tam_x_preferred":[
        "\u0b9a\u0bb2\u0bcb\u0ba9\u0bbf"
    ],
    "name:tel_x_preferred":[
        "\u0c38\u0c32\u0c4b\u0c28\u0c3f"
    ],
    "name:urd_x_preferred":[
        "\u0633\u0644\u0648\u0646\u06cc"
    ],
    "wof:name":"Saloni",
    "wof:placetype":"locality"
},
  "geometry": {"coordinates":[80.85032,21.24299],"type":"Point"}
}