{
  "type": "Feature",
  "properties": {
    "gn:admin1_code":"37",
    "gn:admin2_code":"408.0",
    "gn:asciiname":"Saloni",
    "gn:country_code":"IN",
    "gn:dem":347,
    "gn:feature_class":"P",
    "gn:feature_code":"PPL",
    "gn:name":"Salon\u012b",
    "gn:population":0,
    "gn:timezone":"Asia/Kolkata",
    "iso:country":"IN",
    "name:cat_x_preferred":[
        "Saloni"
    ],
    "wof:name":"Saloni",
    "wof:placetype":"locality"
},
  "geometry": {"coordinates":[80.85032,21.24299],"type":"Point"}
}