{
  "type": "Feature",
  "properties": {
    "iso:country":"IN",
    "ks:ks_name":"Murambi",
    "ks:ks_pop":770,
    "ks:ks_type":"VILLAGE",
    "name:eng_x_preferred":[
        "Murambi"
    ],
    "wof:name":"Murambi",
    "wof:placetype":"locality",
    "wof:population":770
},
  "geometry": {"coordinates":[73.67025,20.618056],"type":"Point"}
}