{
  "type": "Feature",
  "properties": {
    "iso:country":"IN",
    "ks:ks_name":"Saria",
    "ks:ks_pop":0,
    "ks:ks_type":"VILLAGE",
    "name:eng_x_preferred":[
        "Saria"
    ],
    "wof:name":"Saria",
    "wof:placetype":"locality",
    "wof:population":0
},
  "geometry": {"coordinates":[85.589696,21.43894],"type":"Point"}
}