{
  "type": "Feature",
  "properties": {
    "iso:country":"IN",
    "ks:ks_name":"Patode Wadgaon",
    "ks:ks_pop":763,
    "ks:ks_type":"VILLAGE",
    "ks:ks_uagg_main":0,
    "name:eng_x_preferred":[
        "Patode Wadgaon"
    ],
    "wof:name":"Patode Wadgaon",
    "wof:placetype":"neighbourhood",
    "wof:population":763
},
  "geometry": {"coordinates":[75.3291,19.759452],"type":"Point"}
}