{
  "type": "Feature",
  "properties": {
    "gn:admin1_code":"2",
    "gn:admin2_code":"546.0",
    "gn:asciiname":"Kamalapuram",
    "gn:country_code":"IN",
    "gn:dem":155,
    "gn:feature_class":"P",
    "gn:feature_code":"PPL",
    "gn:name":"Kam\u0101l\u0101puram",
    "gn:population":0,
    "gn:timezone":"Asia/Kolkata",
    "iso:country":"IN",
    "ks:ks_name":"Kamalapuram",
    "ks:ks_pop":243,
    "ks:ks_type":"HABITATION",
    "name:ceb_x_preferred":[
        "Kamalapuram"
    ],
    "name:eng_x_preferred":[
        "Kamalapuram"
    ],
    "name:swe_x_preferred":[
        "Kamalapuram"
    ],
    "name:vie_x_preferred":[
        "Kamalapuram"
    ],
    "wof:name":"Kamalapuram",
    "wof:placetype":"locality",
    "wof:population":243
},
  "geometry": {"coordinates":[80.920255,17.134321],"type":"Point"}
}