{
  "type": "Feature",
  "properties": {
    "iso:country":"IN",
    "ks:ks_name":"Katapali",
    "ks:ks_pop":89,
    "ks:ks_type":"VILLAGE",
    "name:eng_x_preferred":[
        "Katapali"
    ],
    "wof:name":"Katapali",
    "wof:placetype":"locality",
    "wof:population":89
},
  "geometry": {"coordinates":[83.654003,20.657752],"type":"Point"}
}