{
  "type": "Feature",
  "properties": {
    "iso:country":"IN",
    "ks:ks_name":"Ambatanr",
    "ks:ks_pop":94,
    "ks:ks_type":"VILLAGE",
    "name:eng_x_preferred":[
        "Ambatanr"
    ],
    "wof:name":"Ambatanr",
    "wof:placetype":"locality",
    "wof:population":94
},
  "geometry": {"coordinates":[85.629997,23.867753],"type":"Point"}
}