{
  "type": "Feature",
  "properties": {
    "iso:country":"IN",
    "ks:ks_name":"Daffala Garh Te 281 492 Grant",
    "ks:ks_pop":381,
    "ks:ks_type":"HABITATION",
    "name:eng_x_preferred":[
        "Daffala Garh Te 281 492 Grant"
    ],
    "wof:name":"Daffala Garh Te 281 492 Grant",
    "wof:placetype":"locality",
    "wof:population":381
},
  "geometry": {"coordinates":[93.516599,26.938952],"type":"Point"}
}