{
  "type": "Feature",
  "properties": {
    "iso:country":"IN",
    "ks:ks_name":"Khambiya",
    "ks:ks_pop":394,
    "ks:ks_type":"VILLAGE",
    "name:eng_x_preferred":[
        "Khambiya"
    ],
    "wof:name":"Khambiya",
    "wof:placetype":"locality",
    "wof:population":394
},
  "geometry": {"coordinates":[73.370683,24.561397],"type":"Point"}
}