{
  "type": "Feature",
  "properties": {
    "iso:country":"IN",
    "ks:ks_name":"Pedawada",
    "ks:ks_pop":180,
    "ks:ks_type":"VILLAGE",
    "name:eng_x_preferred":[
        "Pedawada"
    ],
    "wof:name":"Pedawada",
    "wof:placetype":"locality",
    "wof:population":180
},
  "geometry": {"coordinates":[81.894588,18.88744],"type":"Point"}
}