{
  "type": "Feature",
  "properties": {
    "gn:admin1_code":"36",
    "gn:admin2_code":"161.0",
    "gn:asciiname":"Gianpur Janib Rast",
    "gn:country_code":"IN",
    "gn:dem":147,
    "gn:feature_class":"P",
    "gn:feature_code":"PPL",
    "gn:name":"Gi\u0101npur J\u0101nib R\u0101st",
    "gn:population":0,
    "gn:timezone":"Asia/Kolkata",
    "iso:country":"IN",
    "wof:name":"Gianpur Janib Rast",
    "wof:placetype":"locality"
},
  "geometry": {"coordinates":[78.9175,26.72602],"type":"Point"}
}