{
  "type": "Feature",
  "properties": {
    "iso:country":"IN",
    "ks:ks_alt_nam":"langdisa",
    "ks:ks_name":"Langdisa",
    "ks:ks_pop":40,
    "ks:ks_type":"HABITATION",
    "name:eng_x_preferred":[
        "Langdisa"
    ],
    "wof:name":"Langdisa",
    "wof:placetype":"locality",
    "wof:population":40
},
  "geometry": {"coordinates":[92.947963,25.572107],"type":"Point"}
}