{
  "type": "Feature",
  "properties": {
    "iso:country":"IN",
    "ks:ks_name":"Suryapet",
    "ks:ks_pop":106,
    "ks:ks_type":"HABITATION",
    "name:eng_x_preferred":[
        "Suryapet"
    ],
    "name:hin_x_preferred":[
        "\u0938\u0942\u0930\u094d\u092f\u093e\u092a\u0947\u091f"
    ],
    "name:tel_x_preferred":[
        "\u0c38\u0c42\u0c30\u0c4d\u0c2f\u0c3e\u0c2a\u0c47\u0c1f"
    ],
    "wof:name":"Suryapet",
    "wof:placetype":"locality",
    "wof:population":106
},
  "geometry": {"coordinates":[78.596512,19.354285],"type":"Point"}
}