{
  "type": "Feature",
  "properties": {
    "iso:country":"IN",
    "ks:ks_name":"Uveri Madhurachathiram",
    "ks:ks_pop":280,
    "ks:ks_type":"HABITATION",
    "name:eng_x_preferred":[
        "Uveri Madhurachathiram"
    ],
    "wof:name":"Uveri Madhurachathiram",
    "wof:placetype":"locality",
    "wof:population":280
},
  "geometry": {"coordinates":[79.691339,12.936774],"type":"Point"}
}