{
  "type": "Feature",
  "properties": {
    "iso:country":"IN",
    "ks:ks_name":"Purbi Tola",
    "ks:ks_pop":996,
    "ks:ks_type":"HABITATION",
    "name:eng_x_preferred":[
        "Purbi Tola"
    ],
    "wof:name":"Purbi Tola",
    "wof:placetype":"locality",
    "wof:population":996
},
  "geometry": {"coordinates":[85.69130199999999,25.943734],"type":"Point"}
}