{
  "type": "Feature",
  "properties": {
    "iso:country":"IN",
    "ks:ks_name":"Srirampuram",
    "ks:ks_pop":539,
    "ks:ks_type":"VILLAGE",
    "name:eng_x_preferred":[
        "Srirampuram"
    ],
    "wof:name":"Srirampuram",
    "wof:placetype":"locality",
    "wof:population":539
},
  "geometry": {"coordinates":[84.483936,18.888537],"type":"Point"}
}