{
  "type": "Feature",
  "properties": {
    "gn:admin1_code":"12",
    "gn:admin2_code":"14.0",
    "gn:asciiname":"Kanganhal",
    "gn:country_code":"IN",
    "gn:dem":1643,
    "gn:feature_class":"P",
    "gn:feature_code":"PPL",
    "gn:name":"Kanganh\u0101l",
    "gn:population":0,
    "gn:timezone":"Asia/Kolkata",
    "iso:country":"IN",
    "wof:name":"Kanganhal",
    "wof:placetype":"locality"
},
  "geometry": {"coordinates":[75.22065000000001,33.70703],"type":"Point"}
}