{
  "type": "Feature",
  "properties": {
    "gn:admin1_code":"36.0",
    "gn:admin2_code":"184.0",
    "gn:asciiname":"Hardan",
    "gn:country_code":"IN",
    "gn:dem":91,
    "gn:feature_class":"P",
    "gn:feature_code":"PPL",
    "gn:name":"Hardan",
    "gn:population":0,
    "gn:timezone":"Asia/Kolkata",
    "iso:country":"IN",
    "name:fas_x_preferred":[
        "\u0647\u0631\u062f\u0627\u0646"
    ],
    "name:msa_x_preferred":[
        "Hardan"
    ],
    "wof:name":"Hardan",
    "wof:placetype":"locality"
},
  "geometry": {"coordinates":[82.98696,27.09856],"type":"Point"}
}