{
  "type": "Feature",
  "properties": {
    "iso:country":"IN",
    "ks:ks_name":"Karadipara",
    "ks:ks_pop":150,
    "ks:ks_type":"HABITATION",
    "name:eng_x_preferred":[
        "Karadipara"
    ],
    "wof:name":"Karadipara",
    "wof:placetype":"locality",
    "wof:population":150
},
  "geometry": {"coordinates":[76.611187,11.040291],"type":"Point"}
}