{
  "type": "Feature",
  "properties": {
    "gn:admin1_code":"12.0",
    "gn:admin2_code":"001",
    "gn:asciiname":"Giripur",
    "gn:country_code":"IN",
    "gn:dem":1627,
    "gn:feature_class":"P",
    "gn:feature_code":"PPL",
    "gn:name":"G\u012bripur",
    "gn:population":0,
    "gn:timezone":"Asia/Kolkata",
    "iso:country":"IN",
    "name:und_x_variant":[
        "G\u012bripur",
        "Giripur"
    ],
    "wof:name":"Giripur",
    "wof:placetype":"locality"
},
  "geometry": {"coordinates":[74.2239,34.45199],"type":"Point"}
}