{
  "type": "Feature",
  "properties": {
    "iso:country":"IN",
    "ks:ks_name":"Karaimeendarkottai",
    "ks:ks_pop":1212,
    "ks:ks_type":"VILLAGE",
    "name:eng_x_preferred":[
        "Karaimeendarkottai"
    ],
    "wof:name":"Karaimeendarkottai",
    "wof:placetype":"locality",
    "wof:population":1212
},
  "geometry": {"coordinates":[79.22332299999999,10.728117],"type":"Point"}
}