{
  "type": "Feature",
  "properties": {
    "iso:country":"IN",
    "ks:ks_name":"Kalachan Para",
    "ks:ks_pop":217,
    "ks:ks_type":"HABITATION",
    "name:eng_x_preferred":[
        "Kalachan Para"
    ],
    "wof:name":"Kalachan Para",
    "wof:placetype":"locality",
    "wof:population":217
},
  "geometry": {"coordinates":[91.67602100000001,23.647726],"type":"Point"}
}