{
  "type": "Feature",
  "properties": {
    "gn:admin1_code":"36",
    "gn:admin2_code":"135.0",
    "gn:asciiname":"Dhakia Jat",
    "gn:country_code":"IN",
    "gn:dem":209,
    "gn:feature_class":"P",
    "gn:feature_code":"PPL",
    "gn:name":"Dhakia Jat",
    "gn:population":0,
    "gn:timezone":"Asia/Kolkata",
    "iso:country":"IN",
    "ks:ks_name":"Dhakia Jat",
    "ks:ks_pop":8728,
    "ks:ks_type":"VILLAGE",
    "ks:ks_uagg_main":0,
    "name:eng_x_preferred":[
        "Dhakia Jat"
    ],
    "wof:name":"Dhakia Jat",
    "wof:placetype":"neighbourhood",
    "wof:population":8728
},
  "geometry": {"coordinates":[78.769462,29.05891],"type":"Point"}
}