{
  "type": "Feature",
  "properties": {
    "iso:country":"IN",
    "ks:ks_name":"Aadnar",
    "ks:ks_pop":33,
    "ks:ks_type":"HABITATION",
    "name:eng_x_preferred":[
        "Aadnar"
    ],
    "wof:name":"Aadnar",
    "wof:placetype":"locality",
    "wof:population":33
},
  "geometry": {"coordinates":[80.944202,19.788244],"type":"Point"}
}