{
  "type": "Feature",
  "properties": {
    "iso:country":"IN",
    "qs:name":"Wazirpur Industrial Area",
    "qs:name_adm0":"India",
    "qs:name_adm1":"Delhi",
    "qs:photos":28,
    "qs:photos_1k":6,
    "qs:photos_9k":1,
    "qs:photos_9r":2,
    "qs:photos_all":28,
    "qs:photos_sr":2,
    "qs:placetype":"Suburb",
    "qs:pop_sr":"0",
    "wof:name":"Wazirpur Industrial Area",
    "wof:placetype":"neighbourhood"
},
  "geometry": {"coordinates":[77.165769,28.704083],"type":"Point"}
}