{
  "type": "Feature",
  "properties": {
    "iso:country":"IN",
    "ks:ks_name":"Uttar Upanchauki Kuchlibari",
    "ks:ks_pop":442,
    "ks:ks_type":"VILLAGE",
    "name:eng_x_preferred":[
        "Uttar Upanchauki Kuchlibari"
    ],
    "wof:name":"Uttar Upanchauki Kuchlibari",
    "wof:placetype":"locality",
    "wof:population":442
},
  "geometry": {"coordinates":[88.98784499999999,26.298222],"type":"Point"}
}