{
  "type": "Feature",
  "properties": {
    "gn:admin1_code":"25.0",
    "gn:admin2_code":"602.0",
    "gn:asciiname":"Vullamnayunipeta",
    "gn:country_code":"IN",
    "gn:dem":48,
    "gn:feature_class":"P",
    "gn:feature_code":"PPL",
    "gn:name":"Vullamn\u0101yunipeta",
    "gn:population":0,
    "gn:timezone":"Asia/Kolkata",
    "iso:country":"IN",
    "wof:name":"Vullamnayunipeta",
    "wof:placetype":"neighbourhood"
},
  "geometry": {"coordinates":[79.80301,13.18114],"type":"Point"}
}