{
  "type": "Feature",
  "properties": {
    "iso:country":"IN",
    "ks:ks_name":"Bhaga Banpur",
    "ks:ks_pop":2838,
    "ks:ks_type":"VILLAGE",
    "name:eng_x_preferred":[
        "Bhaga Banpur"
    ],
    "wof:name":"Bhaga Banpur",
    "wof:placetype":"locality",
    "wof:population":2838
},
  "geometry": {"coordinates":[88.531222,22.558241],"type":"Point"}
}