{
  "type": "Feature",
  "properties": {
    "iso:country":"IN",
    "ks:ks_name":"25 APD",
    "ks:ks_type":"VILLAGE",
    "name:eng_x_preferred":[
        "25 APD"
    ],
    "wof:name":"25 APD",
    "wof:placetype":"locality"
},
  "geometry": {"coordinates":[73.19756099999999,29.27206],"type":"Point"}
}