{
  "type": "Feature",
  "properties": {
    "iso:country":"IN",
    "ks:ks_alt_nam":"railway ke pass",
    "ks:ks_name":"Railway Ke Pass",
    "ks:ks_pop":280,
    "ks:ks_type":"HABITATION",
    "name:eng_x_preferred":[
        "Railway Ke Pass"
    ],
    "wof:name":"Railway Ke Pass",
    "wof:placetype":"locality",
    "wof:population":280
},
  "geometry": {"coordinates":[82.19039600000001,25.193053],"type":"Point"}
}