{
  "type": "Feature",
  "properties": {
    "iso:country":"IN",
    "ks:ks_name":"Tatupur",
    "ks:ks_pop":659,
    "ks:ks_type":"HABITATION",
    "name:eng_x_preferred":[
        "Tatupur"
    ],
    "wof:name":"Tatupur",
    "wof:placetype":"locality",
    "wof:population":659
},
  "geometry": {"coordinates":[82.54349499999999,26.003245],"type":"Point"}
}