{
  "type": "Feature",
  "properties": {
    "iso:country":"IN",
    "ks:ks_name":"Byataganahatti",
    "ks:ks_pop":163,
    "ks:ks_type":"HABITATION",
    "name:eng_x_preferred":[
        "Byataganahatti"
    ],
    "wof:name":"Byataganahatti",
    "wof:placetype":"locality",
    "wof:population":163
},
  "geometry": {"coordinates":[76.981382,13.598265],"type":"Point"}
}