{
  "type": "Feature",
  "properties": {
    "gn:admin1_code":"34.0",
    "gn:admin2_code":"224.0",
    "gn:asciiname":"Gosaingaon",
    "gn:country_code":"IN",
    "gn:dem":41,
    "gn:feature_class":"P",
    "gn:feature_code":"PPL",
    "gn:name":"Gosaingaon",
    "gn:population":0,
    "gn:timezone":"Asia/Kolkata",
    "iso:country":"IN",
    "ks:ks_name":"Goshaingaon",
    "ks:ks_pop":9464,
    "ks:ks_type":"VILLAGE",
    "name:eng_x_preferred":[
        "Goshaingaon"
    ],
    "name:eng_x_variant":[
        "Gosaingaon"
    ],
    "wof:name":"Goshaingaon",
    "wof:placetype":"locality",
    "wof:population":9464
},
  "geometry": {"coordinates":[87.090846,25.360765],"type":"Point"}
}