{
  "type": "Feature",
  "properties": {
    "iso:country":"IN",
    "ks:ks_name":"Chandragadde",
    "ks:ks_pop":18,
    "ks:ks_type":"HABITATION",
    "name:eng_x_preferred":[
        "Chandragadde"
    ],
    "wof:name":"Chandragadde",
    "wof:placetype":"locality",
    "wof:population":18
},
  "geometry": {"coordinates":[75.023898,13.744658],"type":"Point"}
}