{
  "type": "Feature",
  "properties": {
    "iso:country":"IN",
    "ks:ks_alt_nam":"Kulathumettu kuppam",
    "ks:ks_name":"Kulathumettu Kuppam",
    "ks:ks_pop":416,
    "ks:ks_type":"HABITATION",
    "name:eng_x_preferred":[
        "Kulathumettu Kuppam"
    ],
    "wof:name":"Kulathumettu Kuppam",
    "wof:placetype":"locality",
    "wof:population":416
},
  "geometry": {"coordinates":[79.20430500000001,12.612243],"type":"Point"}
}