{
  "type": "Feature",
  "properties": {
    "gn:admin1_code":"21",
    "gn:admin2_code":"389.0",
    "gn:asciiname":"Raipanga",
    "gn:country_code":"IN",
    "gn:dem":457,
    "gn:feature_class":"P",
    "gn:feature_code":"PPL",
    "gn:name":"Raipanga",
    "gn:population":0,
    "gn:timezone":"Asia/Kolkata",
    "iso:country":"IN",
    "wof:name":"Raipanga",
    "wof:placetype":"locality"
},
  "geometry": {"coordinates":[83.98289,19.39915],"type":"Point"}
}