{
  "type": "Feature",
  "properties": {
    "gn:admin1_code":"39",
    "gn:admin2_code":"68.0",
    "gn:asciiname":"Katebarh",
    "gn:country_code":"IN",
    "gn:dem":330,
    "gn:feature_class":"P",
    "gn:feature_code":"PPL",
    "gn:name":"Katebarh",
    "gn:population":0,
    "gn:timezone":"Asia/Kolkata",
    "iso:country":"IN",
    "wof:name":"Katebarh",
    "wof:placetype":"locality"
},
  "geometry": {"coordinates":[78.29415999999998,29.82617],"type":"Point"}
}