{
  "type": "Feature",
  "properties": {
    "iso:country":"IN",
    "ks:ks_name":"Chargoda",
    "ks:ks_pop":2554,
    "ks:ks_type":"VILLAGE",
    "name:eng_x_preferred":[
        "Chargoda"
    ],
    "wof:name":"Chargoda",
    "wof:placetype":"locality",
    "wof:population":2554
},
  "geometry": {"coordinates":[82.71167,23.995199],"type":"Point"}
}