{
  "type": "Feature",
  "properties": {
    "iso:country":"IN",
    "ks:ks_alt_nam":"khalchiwadi",
    "ks:ks_name":"Khalchiwadi",
    "ks:ks_pop":39,
    "ks:ks_type":"HABITATION",
    "name:eng_x_preferred":[
        "Khalchiwadi"
    ],
    "wof:name":"Khalchiwadi",
    "wof:placetype":"locality",
    "wof:population":39
},
  "geometry": {"coordinates":[73.9195,15.784917],"type":"Point"}
}