{
  "type": "Feature",
  "properties": {
    "iso:country":"IN",
    "ks:ks_name":"Baidikotha",
    "ks:ks_pop":205,
    "ks:ks_type":"VILLAGE",
    "name:eng_x_preferred":[
        "Baidikotha"
    ],
    "wof:name":"Baidikotha",
    "wof:placetype":"locality",
    "wof:population":205
},
  "geometry": {"coordinates":[86.57634299999999,22.067572],"type":"Point"}
}