{
  "type": "Feature",
  "properties": {
    "iso:country":"IN",
    "ks:ks_alt_nam":"Ch\u0101tams\u0101l",
    "ks:ks_name":"Chatamsal",
    "ks:ks_pop":354,
    "ks:ks_type":"VILLAGE",
    "name:eng_x_preferred":[
        "Chatamsal"
    ],
    "name:eng_x_variant":[
        "Ch\u0101tams\u0101l"
    ],
    "wof:name":"Chatamsal",
    "wof:placetype":"locality",
    "wof:population":354
},
  "geometry": {"coordinates":[85.56547999999999,22.929064],"type":"Point"}
}