{
  "type": "Feature",
  "properties": {
    "iso:country":"IN",
    "ks:ks_name":"Suhel Ahatmali",
    "ks:ks_pop":0,
    "ks:ks_type":"VILLAGE",
    "name:eng_x_preferred":[
        "Suhel Ahatmali"
    ],
    "wof:name":"Suhel Ahatmali",
    "wof:placetype":"locality",
    "wof:population":0
},
  "geometry": {"coordinates":[81.307188,25.339951],"type":"Point"}
}