{
  "type": "Feature",
  "properties": {
    "iso:country":"IN",
    "ks:ks_alt_nam":"middle harijan tola",
    "ks:ks_name":"Middle Harijan Tola",
    "ks:ks_pop":178,
    "ks:ks_type":"HABITATION",
    "name:eng_x_preferred":[
        "Middle Harijan Tola"
    ],
    "wof:name":"Middle Harijan Tola",
    "wof:placetype":"locality",
    "wof:population":178
},
  "geometry": {"coordinates":[86.463832,24.650975],"type":"Point"}
}