{
  "type": "Feature",
  "properties": {
    "iso:country":"IN",
    "ks:ks_name":"Shiunagar",
    "ks:ks_pop":129,
    "ks:ks_type":"VILLAGE",
    "name:eng_x_preferred":[
        "Shiunagar"
    ],
    "wof:name":"Shiunagar",
    "wof:placetype":"locality",
    "wof:population":129
},
  "geometry": {"coordinates":[86.974244,24.451868],"type":"Point"}
}