{
  "type": "Feature",
  "properties": {
    "gn:admin1_code":"36.0",
    "gn:admin2_code":"149.0",
    "gn:asciiname":"Gandha",
    "gn:country_code":"IN",
    "gn:dem":163,
    "gn:feature_class":"P",
    "gn:feature_code":"PPL",
    "gn:name":"Gandha",
    "gn:population":0,
    "gn:timezone":"Asia/Kolkata",
    "iso:country":"IN",
    "name:tel_x_preferred":[
        "\u0c17\u0c02\u0c27\u0c2e\u0c41"
    ],
    "wof:name":"Gandha",
    "wof:placetype":"neighbourhood"
},
  "geometry": {"coordinates":[79.4126,28.14671],"type":"Point"}
}