{
  "type": "Feature",
  "properties": {
    "iso:country":"IN",
    "ks:ks_name":"Natungram",
    "ks:ks_pop":610,
    "ks:ks_type":"HABITATION",
    "name:eng_x_preferred":[
        "Natungram"
    ],
    "wof:name":"Natungram",
    "wof:placetype":"locality",
    "wof:population":610
},
  "geometry": {"coordinates":[87.895338,24.495053],"type":"Point"}
}