{
  "type": "Feature",
  "properties": {
    "gn:country":"IN",
    "gn:fcode":"PPL",
    "gn:population":51577,
    "iso:country":"IN",
    "name:ben_x_preferred":[
        "\u0996\u09be\u0997\u09be\u0989\u09b2"
    ],
    "name:bho_x_preferred":[
        "\u0916\u0917\u094c\u0932"
    ],
    "name:bpy_x_preferred":[
        "\u0996\u09be\u0997\u09be\u0989\u09b2"
    ],
    "name:bul_x_preferred":[
        "\u041a\u0445\u0430\u0433\u0430\u0443\u043b"
    ],
    "name:ceb_x_preferred":[
        "Khagaul"
    ],
    "name:eng_x_preferred":[
        "Khagaul"
    ],
    "name:fra_x_preferred":[
        "Khagaul"
    ],
    "name:hin_x_preferred":[
        "\u0916\u0917\u094c\u0932"
    ],
    "name:ita_x_preferred":[
        "Khagaul"
    ],
    "name:msa_x_preferred":[
        "Khagaul"
    ],
    "name:nep_x_preferred":[
        "\u0916\u0917\u094c\u0932"
    ],
    "name:new_x_preferred":[
        "\u0916\u0917\u094c\u0932"
    ],
    "name:nld_x_preferred":[
        "Khagaul"
    ],
    "name:por_x_preferred":[
        "Khagaul"
    ],
    "name:spa_x_preferred":[
        "Khagaul"
    ],
    "name:swe_x_preferred":[
        "Khagaul"
    ],
    "name:urd_x_preferred":[
        "\u06a9\u06be\u06af\u0648\u0644"
    ],
    "name:vie_x_preferred":[
        "Khagaul"
    ],
    "name:zho_x_preferred":[
        "\u5361\u9ad8\u5c14"
    ],
    "qs:name":"Khargauli",
    "qs:name_adm0":"India",
    "qs:name_adm1":"Bihar",
    "qs:photos_9r":0,
    "qs:photos_sr":0,
    "qs:placetype":"Town",
    "qs:pop_sr":"8",
    "wof:name":"Khargauli",
    "wof:placetype":"locality",
    "wof:population":51577
},
  "geometry": {"coordinates":[85.04548,25.58282],"type":"Point"}
}