{
  "type": "Feature",
  "properties": {
    "gn:admin1_code":"36",
    "gn:admin2_code":"197.0",
    "gn:asciiname":"Bhadrasi",
    "gn:country_code":"IN",
    "gn:dem":81,
    "gn:feature_class":"P",
    "gn:feature_code":"PPL",
    "gn:name":"Bhadr\u0101si",
    "gn:population":0,
    "gn:timezone":"Asia/Kolkata",
    "iso:country":"IN",
    "ks:ks_name":"Bhadarasi",
    "ks:ks_pop":1310,
    "ks:ks_type":"VILLAGE",
    "name:eng_x_preferred":[
        "Bhadarasi"
    ],
    "name:eng_x_variant":[
        "Bhadrasi"
    ],
    "wof:name":"Bhadarasi",
    "wof:placetype":"locality",
    "wof:population":1310
},
  "geometry": {"coordinates":[82.88370999999999,25.235295],"type":"Point"}
}