{
  "type": "Feature",
  "properties": {
    "gn:admin1_code":"38.0",
    "gn:admin2_code":"352.0",
    "gn:asciiname":"Shampur",
    "gn:country_code":"IN",
    "gn:dem":94,
    "gn:feature_class":"P",
    "gn:feature_code":"PPL",
    "gn:name":"Sh\u0101mpur",
    "gn:population":0,
    "gn:timezone":"Asia/Kolkata",
    "iso:country":"IN",
    "ks:ks_alt_nam":"Sh\u0101mpur",
    "ks:ks_name":"Shampur",
    "ks:ks_pop":350,
    "ks:ks_type":"VILLAGE",
    "name:eng_x_preferred":[
        "Shampur"
    ],
    "name:eng_x_variant":[
        "Sh\u0101mpur"
    ],
    "wof:name":"Shampur",
    "wof:placetype":"locality",
    "wof:population":350
},
  "geometry": {"coordinates":[87.543245,25.043243],"type":"Point"}
}