{
  "type": "Feature",
  "properties": {
    "iso:country":"IN",
    "ks:ks_name":"Pura Bade",
    "ks:ks_pop":288,
    "ks:ks_type":"HABITATION",
    "name:eng_x_preferred":[
        "Pura Bade"
    ],
    "wof:name":"Pura Bade",
    "wof:placetype":"locality",
    "wof:population":288
},
  "geometry": {"coordinates":[81.60192000000001,26.611238],"type":"Point"}
}