{
  "type": "Feature",
  "properties": {
    "iso:country":"IN",
    "ks:ks_name":"Dilma Adap",
    "ks:ks_pop":399,
    "ks:ks_type":"HABITATION",
    "name:eng_x_preferred":[
        "Dilma Adap"
    ],
    "wof:name":"Dilma Adap",
    "wof:placetype":"locality",
    "wof:population":399
},
  "geometry": {"coordinates":[91.031334,25.871935],"type":"Point"}
}