{
  "type": "Feature",
  "properties": {
    "iso:country":"IN",
    "ks:ks_name":"Shisne",
    "ks:ks_pop":1798,
    "ks:ks_type":"VILLAGE",
    "name:eng_x_preferred":[
        "Shisne"
    ],
    "wof:name":"Shisne",
    "wof:placetype":"locality",
    "wof:population":1798
},
  "geometry": {"coordinates":[72.95056099999999,20.02741],"type":"Point"}
}