{
  "type": "Feature",
  "properties": {
    "gn:admin1_code":"36.0",
    "gn:admin2_code":"158.0",
    "gn:asciiname":"Thakurganj",
    "gn:country_code":"IN",
    "gn:dem":114,
    "gn:feature_class":"P",
    "gn:feature_code":"PPL",
    "gn:name":"Th\u0101kurganj",
    "gn:population":0,
    "gn:timezone":"Asia/Kolkata",
    "iso:country":"IN",
    "name:ben_x_preferred":[
        "\u09a0\u09be\u0995\u09c1\u09b0\u0997\u099e\u09cd\u099c"
    ],
    "name:bih_x_preferred":[
        "\u0920\u093e\u0915\u0941\u0930\u0917\u0902\u091c"
    ],
    "name:bpy_x_preferred":[
        "\u09a0\u09be\u0995\u09c1\u09b0\u0997\u099e\u09cd\u099c"
    ],
    "name:ceb_x_preferred":[
        "Th\u0101kurganj"
    ],
    "name:hin_x_preferred":[
        "\u0920\u093e\u0915\u0941\u0930\u0917\u0902\u091c"
    ],
    "name:ita_x_preferred":[
        "Thakurganj"
    ],
    "name:msa_x_preferred":[
        "Thakurganj"
    ],
    "name:nld_x_preferred":[
        "Thakurganj"
    ],
    "name:swe_x_preferred":[
        "Th\u0101kurganj"
    ],
    "name:tam_x_preferred":[
        "\u0b9f\u0bbe\u0b95\u0bcd\u0b95\u0bc1\u0bb0\u0bcd\u0b95\u0b9e\u0bcd\u0b9a\u0bc1"
    ],
    "name:vie_x_preferred":[
        "Thakurganj"
    ],
    "name:zho_x_preferred":[
        "\u5854\u5e93\u5c14\u7518\u6770"
    ],
    "wof:name":"Thakurganj",
    "wof:placetype":"locality"
},
  "geometry": {"coordinates":[81.15651,26.02666],"type":"Point"}
}