{
  "type": "Feature",
  "properties": {
    "gn:admin1_code":"19.0",
    "gn:admin2_code":"569.0",
    "gn:asciiname":"Punja",
    "gn:country_code":"IN",
    "gn:dem":51,
    "gn:feature_class":"P",
    "gn:feature_code":"PPL",
    "gn:name":"Punja",
    "gn:population":0,
    "gn:timezone":"Asia/Kolkata",
    "iso:country":"IN",
    "name:swe_x_preferred":[
        "Punja"
    ],
    "wof:name":"Punja",
    "wof:placetype":"locality"
},
  "geometry": {"coordinates":[74.78522,13.38802],"type":"Point"}
}