{
  "type": "Feature",
  "properties": {
    "gn:admin1_code":"16",
    "gn:admin2_code":"504.0",
    "gn:asciiname":"Salapur",
    "gn:country_code":"IN",
    "gn:dem":235,
    "gn:feature_class":"P",
    "gn:feature_code":"PPL",
    "gn:name":"S\u0101l\u0101pur",
    "gn:population":0,
    "gn:timezone":"Asia/Kolkata",
    "iso:country":"IN",
    "wof:name":"Salapur",
    "wof:placetype":"locality"
},
  "geometry": {"coordinates":[78.90608,20.77925],"type":"Point"}
}