{
  "type": "Feature",
  "properties": {
    "gn:admin1_code":"16",
    "gn:admin2_code":"504.0",
    "gn:asciiname":"Salapur",
    "gn:country_code":"IN",
    "gn:dem":235,
    "gn:feature_class":"P",
    "gn:feature_code":"PPL",
    "gn:name":"S\u0101l\u0101pur",
    "gn:population":0,
    "gn:timezone":"Asia/Kolkata",
    "iso:country":"IN",
    "ks:ks_alt_nam":"S\u0101l\u0101pur",
    "ks:ks_name":"Salapur",
    "ks:ks_pop":79,
    "ks:ks_type":"VILLAGE",
    "name:eng_x_preferred":[
        "Salapur"
    ],
    "name:eng_x_variant":[
        "S\u0101l\u0101pur"
    ],
    "wof:name":"Salapur",
    "wof:placetype":"locality",
    "wof:population":79
},
  "geometry": {"coordinates":[78.906158,20.779264],"type":"Point"}
}