{
  "type": "Feature",
  "properties": {
    "iso:country":"IN",
    "ks:ks_name":"Sikari Gaon",
    "ks:ks_pop":290,
    "ks:ks_type":"HABITATION",
    "name:eng_x_preferred":[
        "Sikari Gaon"
    ],
    "wof:name":"Sikari Gaon",
    "wof:placetype":"locality",
    "wof:population":290
},
  "geometry": {"coordinates":[93.53819799999999,25.833722],"type":"Point"}
}