{
  "type": "Feature",
  "properties": {
    "iso:country":"IN",
    "ks:ks_name":"Galpatpur",
    "ks:ks_pop":291,
    "ks:ks_type":"HABITATION",
    "ks:ks_uagg_main":0,
    "name:eng_x_preferred":[
        "Galpatpur"
    ],
    "wof:name":"Galpatpur",
    "wof:placetype":"neighbourhood",
    "wof:population":291
},
  "geometry": {"coordinates":[81.956853,27.693285],"type":"Point"}
}