{
  "type": "Feature",
  "properties": {
    "gn:admin1_code":"35.0",
    "gn:admin2_code":"463.0",
    "gn:asciiname":"Chitrangi",
    "gn:country_code":"IN",
    "gn:dem":284,
    "gn:feature_class":"P",
    "gn:feature_code":"PPL",
    "gn:name":"Chitrangi",
    "gn:population":0,
    "gn:timezone":"Asia/Kolkata",
    "iso:country":"IN",
    "name:tam_x_preferred":[
        "\u0b9a\u0bbf\u0ba4\u0bcd\u0bb0\u0bbe\u0b99\u0bcd\u0b95\u0bbf"
    ],
    "wof:name":"Chitrangi",
    "wof:placetype":"locality"
},
  "geometry": {"coordinates":[82.53923,24.4718],"type":"Point"}
}