{
  "type": "Feature",
  "properties": {
    "gn:admin1_code":"02",
    "gn:admin2_code":"550.0",
    "gn:asciiname":"Mijuru",
    "gn:country_code":"IN",
    "gn:dem":4,
    "gn:feature_class":"P",
    "gn:feature_code":"PPL",
    "gn:name":"M\u012bjuru",
    "gn:population":0,
    "gn:timezone":"Asia/Kolkata",
    "iso:country":"IN",
    "wof:name":"Mijuru",
    "wof:placetype":"locality"
},
  "geometry": {"coordinates":[80.08154,13.76604],"type":"Point"}
}