{
  "type": "Feature",
  "properties": {
    "gn:admin1_code":"13",
    "gn:admin2_code":"601.0",
    "gn:asciiname":"Vettutura",
    "gn:country_code":"IN",
    "gn:dem":12,
    "gn:feature_class":"P",
    "gn:feature_code":"PPL",
    "gn:name":"Vettutura",
    "gn:population":0,
    "gn:timezone":"Asia/Kolkata",
    "iso:country":"IN",
    "wof:name":"Vettutura",
    "wof:placetype":"locality"
},
  "geometry": {"coordinates":[76.83088000000002,8.58004],"type":"Point"}
}