{
  "type": "Feature",
  "properties": {
    "iso:country":"IN",
    "ks:ks_name":"Borson Gaon 2",
    "ks:ks_pop":310,
    "ks:ks_type":"HABITATION",
    "name:eng_x_preferred":[
        "Borson Gaon 2"
    ],
    "wof:name":"Borson Gaon 2",
    "wof:placetype":"locality",
    "wof:population":310
},
  "geometry": {"coordinates":[92.690646,26.731555],"type":"Point"}
}