{
  "type": "Feature",
  "properties": {
    "iso:country":"IN",
    "ks:ks_name":"Bangarwasti",
    "ks:ks_pop":54,
    "ks:ks_type":"HABITATION",
    "name:eng_x_preferred":[
        "Bangarwasti"
    ],
    "wof:name":"Bangarwasti",
    "wof:placetype":"locality",
    "wof:population":54
},
  "geometry": {"coordinates":[75.36581200000001,19.464388],"type":"Point"}
}