{
  "type": "Feature",
  "properties": {
    "iso:country":"IN",
    "ks:ks_name":"Achawa Tola",
    "ks:ks_pop":267,
    "ks:ks_type":"HABITATION",
    "ks:ks_uagg_main":0,
    "name:eng_x_preferred":[
        "Achawa Tola"
    ],
    "wof:name":"Achawa Tola",
    "wof:placetype":"neighbourhood",
    "wof:population":267
},
  "geometry": {"coordinates":[83.329741,27.242648],"type":"Point"}
}