{
  "type": "Feature",
  "properties": {
    "iso:country":"IN",
    "ks:ks_name":"Orekkar Colony",
    "ks:ks_pop":543,
    "ks:ks_type":"HABITATION",
    "name:eng_x_preferred":[
        "Orekkar Colony"
    ],
    "wof:name":"Orekkar Colony",
    "wof:placetype":"locality",
    "wof:population":543
},
  "geometry": {"coordinates":[77.022451,9.115692],"type":"Point"}
}