{
  "type": "Feature",
  "properties": {
    "iso:country":"IN",
    "ks:ks_alt_nam":"PURAB TOLA",
    "ks:ks_name":"Purab Tola",
    "ks:ks_pop":477,
    "ks:ks_type":"HABITATION",
    "name:eng_x_preferred":[
        "Purab Tola"
    ],
    "wof:name":"Purab Tola",
    "wof:placetype":"locality",
    "wof:population":477
},
  "geometry": {"coordinates":[84.841598,25.902486],"type":"Point"}
}