{
  "type": "Feature",
  "properties": {
    "iso:country":"IN",
    "ks:ks_name":"Ilampur",
    "ks:ks_pop":490,
    "ks:ks_type":"VILLAGE",
    "name:eng_x_preferred":[
        "Ilampur"
    ],
    "wof:name":"Ilampur",
    "wof:placetype":"locality",
    "wof:population":490
},
  "geometry": {"coordinates":[88.023882,22.722065],"type":"Point"}
}