{
  "type": "Feature",
  "properties": {
    "iso:country":"IN",
    "ks:ks_name":"Bhelwadih",
    "ks:ks_pop":1236,
    "ks:ks_type":"VILLAGE",
    "name:eng_x_preferred":[
        "Bhelwadih"
    ],
    "wof:name":"Bhelwadih",
    "wof:placetype":"locality",
    "wof:population":1236
},
  "geometry": {"coordinates":[84.517838,22.725888],"type":"Point"}
}