{
  "type": "Feature",
  "properties": {
    "iso:country":"IN",
    "ks:ks_name":"Korhalli Tanda",
    "ks:ks_pop":988,
    "ks:ks_type":"HABITATION",
    "name:eng_x_preferred":[
        "Korhalli Tanda"
    ],
    "wof:name":"Korhalli Tanda",
    "wof:placetype":"locality",
    "wof:population":988
},
  "geometry": {"coordinates":[76.586523,17.500187],"type":"Point"}
}