{
  "type": "Feature",
  "properties": {
    "gn:admin1_code":"36.0",
    "gn:admin2_code":"192.0",
    "gn:asciiname":"Mubarakpur Asna",
    "gn:country_code":"IN",
    "gn:dem":77,
    "gn:feature_class":"P",
    "gn:feature_code":"PPL",
    "gn:name":"Mub\u0101rakpur Asna",
    "gn:population":0,
    "gn:timezone":"Asia/Kolkata",
    "iso:country":"IN",
    "ks:ks_alt_nam":"Mub\u0101rakpur Asna",
    "ks:ks_name":"Mubarakpur Asna",
    "ks:ks_type":"VILLAGE",
    "ks:ks_uagg_main":0,
    "name:eng_x_preferred":[
        "Mubarakpur Asna"
    ],
    "name:eng_x_variant":[
        "Mub\u0101rakpur Asna"
    ],
    "wof:name":"Mubarakpur Asna",
    "wof:placetype":"neighbourhood"
},
  "geometry": {"coordinates":[83.561395,26.120905],"type":"Point"}
}