{
  "type": "Feature",
  "properties": {
    "iso:country":"IN",
    "ks:ks_name":"Savant Deeh",
    "ks:ks_pop":50,
    "ks:ks_type":"HABITATION",
    "name:eng_x_preferred":[
        "Savant Deeh"
    ],
    "wof:name":"Savant Deeh",
    "wof:placetype":"locality",
    "wof:population":50
},
  "geometry": {"coordinates":[82.97774800000001,27.456621],"type":"Point"}
}