{
  "type": "Feature",
  "properties": {
    "iso:country":"IN",
    "ks:ks_name":"Mamrezpur",
    "ks:ks_pop":105,
    "ks:ks_type":"VILLAGE",
    "ks:ks_uagg_main":0,
    "name:eng_x_preferred":[
        "Mamrezpur"
    ],
    "wof:name":"Mamrezpur",
    "wof:placetype":"neighbourhood",
    "wof:population":105
},
  "geometry": {"coordinates":[87.481453,23.890888],"type":"Point"}
}