{
  "type": "Feature",
  "properties": {
    "gn:admin1_code":"11",
    "gn:admin2_code":"23.0",
    "gn:asciiname":"Drankund",
    "gn:country_code":"IN",
    "gn:dem":1818,
    "gn:feature_class":"P",
    "gn:feature_code":"PPL",
    "gn:name":"Drankund",
    "gn:population":0,
    "gn:timezone":"Asia/Kolkata",
    "iso:country":"IN",
    "wof:name":"Drankund",
    "wof:placetype":"locality"
},
  "geometry": {"coordinates":[76.29349000000001,32.43034],"type":"Point"}
}