{
  "type": "Feature",
  "properties": {
    "iso:country":"IN",
    "ks:ks_alt_nam":"Gardhan khurd",
    "ks:ks_name":"Gardhan Khurd",
    "ks:ks_pop":140,
    "ks:ks_type":"HABITATION",
    "name:eng_x_preferred":[
        "Gardhan Khurd"
    ],
    "wof:name":"Gardhan Khurd",
    "wof:placetype":"locality",
    "wof:population":140
},
  "geometry": {"coordinates":[88.107681,26.264661],"type":"Point"}
}