{
  "type": "Feature",
  "properties": {
    "gn:admin1_code":"11.0",
    "gn:admin2_code":"32.0",
    "gn:asciiname":"Dabar ka Bagh",
    "gn:country_code":"IN",
    "gn:dem":639,
    "gn:feature_class":"P",
    "gn:feature_code":"PPL",
    "gn:name":"D\u0101bar ka B\u0101gh",
    "gn:population":0,
    "gn:timezone":"Asia/Kolkata",
    "iso:country":"IN",
    "wof:name":"Dabar ka Bagh",
    "wof:placetype":"locality"
},
  "geometry": {"coordinates":[77.29633000000003,30.54932],"type":"Point"}
}