{
  "type": "Feature",
  "properties": {
    "gn:admin1_code":"16.0",
    "gn:admin2_code":"520",
    "gn:asciiname":"Surekhar",
    "gn:country_code":"IN",
    "gn:dem":6,
    "gn:feature_class":"P",
    "gn:feature_code":"PPL",
    "gn:name":"Surekh\u0101r",
    "gn:population":0,
    "gn:timezone":"Asia/Kolkata",
    "iso:country":"IN",
    "ks:ks_alt_nam":"Surekh\u0101r",
    "ks:ks_name":"Surekhar",
    "ks:ks_pop":157,
    "ks:ks_type":"VILLAGE",
    "name:eng_x_preferred":[
        "Surekhar"
    ],
    "name:eng_x_variant":[
        "Surekh\u0101r"
    ],
    "wof:name":"Surekhar",
    "wof:placetype":"locality",
    "wof:population":157
},
  "geometry": {"coordinates":[72.86767,18.752469],"type":"Point"}
}