{
  "type": "Feature",
  "properties": {
    "iso:country":"IN",
    "ks:ks_name":"Patalammanahalli",
    "ks:ks_pop":325,
    "ks:ks_type":"HABITATION",
    "name:eng_x_preferred":[
        "Patalammanahalli"
    ],
    "wof:name":"Patalammanahalli",
    "wof:placetype":"locality",
    "wof:population":325
},
  "geometry": {"coordinates":[77.808705,13.342349],"type":"Point"}
}