{
  "type": "Feature",
  "properties": {
    "iso:country":"IN",
    "ks:ks_name":"Puchirala",
    "ks:ks_pop":1507,
    "ks:ks_type":"HABITATION",
    "name:eng_x_preferred":[
        "Puchirala"
    ],
    "wof:name":"Puchirala",
    "wof:placetype":"locality",
    "wof:population":1507
},
  "geometry": {"coordinates":[81.233458,17.514558],"type":"Point"}
}