{
  "type": "Feature",
  "properties": {
    "iso:country":"IN",
    "ks:ks_name":"Gathaura",
    "ks:ks_pop":403,
    "ks:ks_type":"VILLAGE",
    "name:eng_x_preferred":[
        "Gathaura"
    ],
    "wof:name":"Gathaura",
    "wof:placetype":"locality",
    "wof:population":403
},
  "geometry": {"coordinates":[79.03245800000001,27.821522],"type":"Point"}
}