{
  "type": "Feature",
  "properties": {
    "gn:admin1_code":"16",
    "gn:admin2_code":"507.0",
    "gn:asciiname":"Karargaon",
    "gn:country_code":"IN",
    "gn:dem":254,
    "gn:feature_class":"P",
    "gn:feature_code":"PPL",
    "gn:name":"Karargaon",
    "gn:population":0,
    "gn:timezone":"Asia/Kolkata",
    "iso:country":"IN",
    "ks:ks_name":"Karadgaon",
    "ks:ks_pop":167,
    "ks:ks_type":"VILLAGE",
    "name:eng_x_preferred":[
        "Karadgaon"
    ],
    "name:eng_x_variant":[
        "Karargaon"
    ],
    "wof:name":"Karadgaon",
    "wof:placetype":"locality",
    "wof:population":167
},
  "geometry": {"coordinates":[79.971098,20.8065],"type":"Point"}
}