{
  "type": "Feature",
  "properties": {
    "iso:country":"IN",
    "ks:ks_alt_nam":"Plot pada",
    "ks:ks_name":"Plot Pada",
    "ks:ks_pop":252,
    "ks:ks_type":"HABITATION",
    "name:eng_x_preferred":[
        "Plot Pada"
    ],
    "wof:name":"Plot Pada",
    "wof:placetype":"locality",
    "wof:population":252
},
  "geometry": {"coordinates":[72.967642,19.511222],"type":"Point"}
}