{
  "type": "Feature",
  "properties": {
    "iso:country":"IN",
    "ks:ks_name":"Phanaswadi",
    "ks:ks_pop":360,
    "ks:ks_type":"HABITATION",
    "name:eng_x_preferred":[
        "Phanaswadi"
    ],
    "wof:name":"Phanaswadi",
    "wof:placetype":"locality",
    "wof:population":360
},
  "geometry": {"coordinates":[73.213229,18.71538],"type":"Point"}
}