{
  "type": "Feature",
  "properties": {
    "gn:admin1_code":"25.0",
    "gn:admin2_code":"605.0",
    "gn:asciiname":"Yelagiri",
    "gn:country_code":"IN",
    "gn:dem":975,
    "gn:elevation":"0.0",
    "gn:feature_class":"P",
    "gn:feature_code":"PPL",
    "gn:name":"Yelagiri",
    "gn:population":0,
    "gn:timezone":"Asia/Kolkata",
    "iso:country":"IN",
    "name:san_x_preferred":[
        "\u090f\u0932\u0917\u093f\u0930\u093f\u092a\u0930\u094d\u0935\u0924\u0903"
    ],
    "name:tam_x_preferred":[
        "\u0b8f\u0bb2\u0b95\u0bbf\u0bb0\u0bbf \u0bae\u0bb2\u0bc8"
    ],
    "name:urd_x_preferred":[
        "\u06cc\u0644\u0627\u06af\u06cc\u0631\u06cc"
    ],
    "wof:name":"Yelagiri",
    "wof:placetype":"locality"
},
  "geometry": {"coordinates":[78.64013,12.57969],"type":"Point"}
}