{
  "type": "Feature",
  "properties": {
    "iso:country":"IN",
    "ks:ks_name":"Padampur",
    "ks:ks_pop":36,
    "ks:ks_type":"VILLAGE",
    "name:eng_x_preferred":[
        "Padampur"
    ],
    "wof:name":"Padampur",
    "wof:placetype":"locality",
    "wof:population":36
},
  "geometry": {"coordinates":[86.575603,24.082699],"type":"Point"}
}