{
  "type": "Feature",
  "properties": {
    "iso:country":"IN",
    "ks:ks_name":"Karathiallwar",
    "ks:ks_pop":243,
    "ks:ks_type":"VILLAGE",
    "name:eng_x_preferred":[
        "Karathiallwar"
    ],
    "wof:name":"Karathiallwar",
    "wof:placetype":"locality",
    "wof:population":243
},
  "geometry": {"coordinates":[81.574378,19.631206],"type":"Point"}
}