{
  "type": "Feature",
  "properties": {
    "gn:admin1_code":"36",
    "gn:admin2_code":"135.0",
    "gn:asciiname":"Umri Kalan",
    "gn:country_code":"IN",
    "gn:dem":216,
    "gn:feature_class":"P",
    "gn:feature_code":"PPL",
    "gn:name":"Umri Kal\u0101n",
    "gn:population":0,
    "gn:timezone":"Asia/Kolkata",
    "iso:country":"IN",
    "name:bpy_x_preferred":[
        "\u0989\u09ae\u09b0\u09bf \u0995\u09b2\u09a8"
    ],
    "name:ita_x_preferred":[
        "Umri Kalan"
    ],
    "name:msa_x_preferred":[
        "Umri Kalan"
    ],
    "name:nld_x_preferred":[
        "Umri Kalan"
    ],
    "name:pol_x_preferred":[
        "Umri Kalan"
    ],
    "name:por_x_preferred":[
        "Umri Kalan"
    ],
    "name:vie_x_preferred":[
        "Umri Kalan"
    ],
    "name:zho_x_preferred":[
        "\u4e4c\u59c6\u91cc\u5361\u5170"
    ],
    "wof:name":"Umri Kalan",
    "wof:placetype":"locality"
},
  "geometry": {"coordinates":[78.5685,29.03862],"type":"Point"}
}