{
  "type": "Feature",
  "properties": {
    "iso:country":"IN",
    "ks:ks_name":"Lasudlya Bazyaft",
    "ks:ks_pop":59,
    "ks:ks_type":"VILLAGE",
    "name:eng_x_preferred":[
        "Lasudlya Bazyaft"
    ],
    "wof:name":"Lasudlya Bazyaft",
    "wof:placetype":"locality",
    "wof:population":59
},
  "geometry": {"coordinates":[77.302862,23.073526],"type":"Point"}
}