{
  "type": "Feature",
  "properties": {
    "iso:country":"IN",
    "ks:ks_name":"Kumarpali",
    "ks:ks_pop":0,
    "ks:ks_type":"VILLAGE",
    "name:eng_x_preferred":[
        "Kumarpali"
    ],
    "wof:name":"Kumarpali",
    "wof:placetype":"locality",
    "wof:population":0
},
  "geometry": {"coordinates":[83.72119600000001,20.694037],"type":"Point"}
}