{
  "type": "Feature",
  "properties": {
    "iso:country":"IN",
    "ks:ks_name":"Arimbramala Rd Jnc",
    "ks:ks_pop":1314,
    "ks:ks_type":"HABITATION",
    "name:eng_x_preferred":[
        "Arimbramala Rd Jnc"
    ],
    "wof:name":"Arimbramala Rd Jnc",
    "wof:placetype":"locality",
    "wof:population":1314
},
  "geometry": {"coordinates":[76.031719,11.077053],"type":"Point"}
}