{
  "type": "Feature",
  "properties": {
    "iso:country":"IN",
    "ks:ks_name":"Baregowdanapalya",
    "ks:ks_pop":83,
    "ks:ks_type":"HABITATION",
    "name:eng_x_preferred":[
        "Baregowdanapalya"
    ],
    "wof:name":"Baregowdanapalya",
    "wof:placetype":"locality",
    "wof:population":83
},
  "geometry": {"coordinates":[77.32423900000001,12.916844],"type":"Point"}
}