{
  "type": "Feature",
  "properties": {
    "iso:country":"IN",
    "ks:ks_name":"Betabari",
    "ks:ks_pop":208,
    "ks:ks_type":"HABITATION",
    "name:eng_x_preferred":[
        "Betabari"
    ],
    "wof:name":"Betabari",
    "wof:placetype":"locality",
    "wof:population":208
},
  "geometry": {"coordinates":[82.726111,18.396413],"type":"Point"}
}