{
  "type": "Feature",
  "properties": {
    "iso:country":"IN",
    "ks:ks_alt_nam":"\u0100g\u0101sk\u0101nd",
    "ks:ks_name":"Agaskand",
    "ks:ks_pop":0,
    "ks:ks_type":"VILLAGE",
    "name:eng_x_preferred":[
        "Agaskand"
    ],
    "name:eng_x_variant":[
        "\u0100g\u0101sk\u0101nd"
    ],
    "wof:name":"Agaskand",
    "wof:placetype":"locality",
    "wof:population":0
},
  "geometry": {"coordinates":[78.60327100000001,20.488561],"type":"Point"}
}