{
  "type": "Feature",
  "properties": {
    "iso:country":"IN",
    "ks:ks_name":"Valasaikinar",
    "ks:ks_pop":154,
    "ks:ks_type":"HABITATION",
    "name:eng_x_preferred":[
        "Valasaikinar"
    ],
    "wof:name":"Valasaikinar",
    "wof:placetype":"locality",
    "wof:population":154
},
  "geometry": {"coordinates":[77.967736,8.480702],"type":"Point"}
}