{
  "type": "Feature",
  "properties": {
    "iso:country":"IN",
    "ks:ks_name":"Mahupadar",
    "ks:ks_pop":3706,
    "ks:ks_type":"VILLAGE",
    "name:eng_x_preferred":[
        "Mahupadar"
    ],
    "wof:name":"Mahupadar",
    "wof:placetype":"locality",
    "wof:population":3706
},
  "geometry": {"coordinates":[81.973602,18.607655],"type":"Point"}
}