{
  "type": "Feature",
  "properties": {
    "iso:country":"IN",
    "ks:ks_name":"Chhana",
    "ks:ks_pop":5,
    "ks:ks_type":"HABITATION",
    "name:eng_x_preferred":[
        "Chhana"
    ],
    "wof:name":"Chhana",
    "wof:placetype":"locality",
    "wof:population":5
},
  "geometry": {"coordinates":[79.925111,29.832961],"type":"Point"}
}