{
  "type": "Feature",
  "properties": {
    "gn:admin1_code":"25",
    "gn:admin2_code":"615.0",
    "gn:asciiname":"Ranjangudi",
    "gn:country_code":"IN",
    "gn:dem":106,
    "gn:feature_class":"P",
    "gn:feature_code":"PPL",
    "gn:name":"Ranjangudi",
    "gn:population":0,
    "gn:timezone":"Asia/Kolkata",
    "iso:country":"IN",
    "wof:name":"Ranjangudi",
    "wof:placetype":"locality"
},
  "geometry": {"coordinates":[78.94266,11.34626],"type":"Point"}
}