{
  "type": "Feature",
  "properties": {
    "gn:admin1_code":"25",
    "gn:admin2_code":"615.0",
    "gn:asciiname":"Ranjangudi",
    "gn:country_code":"IN",
    "gn:dem":106,
    "gn:feature_class":"P",
    "gn:feature_code":"PPL",
    "gn:name":"Ranjangudi",
    "gn:population":0,
    "gn:timezone":"Asia/Kolkata",
    "iso:country":"IN",
    "ks:ks_name":"Ranjankudi",
    "ks:ks_pop":2603,
    "ks:ks_type":"HABITATION",
    "name:eng_x_preferred":[
        "Ranjankudi"
    ],
    "name:eng_x_variant":[
        "Ranjangudi"
    ],
    "wof:name":"Ranjankudi",
    "wof:placetype":"locality",
    "wof:population":2603
},
  "geometry": {"coordinates":[78.941614,11.340396],"type":"Point"}
}