{
  "type": "Feature",
  "properties": {
    "gn:admin1_code":"37",
    "gn:admin2_code":"406.0",
    "gn:asciiname":"Neosa",
    "gn:country_code":"IN",
    "gn:dem":309,
    "gn:feature_class":"P",
    "gn:feature_code":"PPL",
    "gn:name":"Neosa",
    "gn:population":0,
    "gn:timezone":"Asia/Kolkata",
    "iso:country":"IN",
    "wof:name":"Neosa",
    "wof:placetype":"locality"
},
  "geometry": {"coordinates":[81.75922,22.26581],"type":"Point"}
}