{
  "type": "Feature",
  "properties": {
    "gn:admin1_code":"39.0",
    "gn:admin2_code":"63.0",
    "gn:asciiname":"Dhura Izar Chak",
    "gn:country_code":"IN",
    "gn:dem":1167,
    "gn:feature_class":"P",
    "gn:feature_code":"PPL",
    "gn:name":"Dhura Izar Chak",
    "gn:population":0,
    "gn:timezone":"Asia/Kolkata",
    "iso:country":"IN",
    "wof:name":"Dhura Izar Chak",
    "wof:placetype":"locality"
},
  "geometry": {"coordinates":[79.7624,29.8876],"type":"Point"}
}