{
  "type": "Feature",
  "properties": {
    "iso:country":"IN",
    "ks:ks_name":"Balibheta Missing Gaon",
    "ks:ks_pop":349,
    "ks:ks_type":"HABITATION",
    "name:eng_x_preferred":[
        "Balibheta Missing Gaon"
    ],
    "wof:name":"Balibheta Missing Gaon",
    "wof:placetype":"locality",
    "wof:population":349
},
  "geometry": {"coordinates":[94.204604,27.18384],"type":"Point"}
}