{
  "type": "Feature",
  "properties": {
    "gn:admin1_code":"37",
    "gn:admin2_code":"413.0",
    "gn:asciiname":"Binayakpur",
    "gn:country_code":"IN",
    "gn:dem":378,
    "gn:feature_class":"P",
    "gn:feature_code":"PPL",
    "gn:name":"Bin\u0101yakpur",
    "gn:population":0,
    "gn:timezone":"Asia/Kolkata",
    "iso:country":"IN",
    "ks:ks_alt_nam":"Bin\u0101yakpur",
    "ks:ks_name":"Binayakpur",
    "ks:ks_type":"VILLAGE",
    "name:eng_x_preferred":[
        "Binayakpur"
    ],
    "name:eng_x_variant":[
        "Bin\u0101yakpur"
    ],
    "wof:name":"Binayakpur",
    "wof:placetype":"locality"
},
  "geometry": {"coordinates":[81.01065699999999,20.345517],"type":"Point"}
}