{
  "type": "Feature",
  "properties": {
    "iso:country":"IN",
    "ks:ks_name":"Venkateswara Nagar",
    "ks:ks_pop":104,
    "ks:ks_type":"HABITATION",
    "name:eng_x_preferred":[
        "Venkateswara Nagar"
    ],
    "wof:name":"Venkateswara Nagar",
    "wof:placetype":"locality",
    "wof:population":104
},
  "geometry": {"coordinates":[79.05021499999999,12.923023],"type":"Point"}
}