{
  "type": "Feature",
  "properties": {
    "gn:admin1_code":"19.0",
    "gn:admin2_code":"571.0",
    "gn:asciiname":"Timmanahalli",
    "gn:country_code":"IN",
    "gn:dem":704,
    "gn:feature_class":"P",
    "gn:feature_code":"PPL",
    "gn:name":"Timmanahalli",
    "gn:population":0,
    "gn:timezone":"Asia/Kolkata",
    "iso:country":"IN",
    "wof:name":"Timmanahalli",
    "wof:placetype":"locality"
},
  "geometry": {"coordinates":[77.32153000000002,13.61575],"type":"Point"}
}