{
  "type": "Feature",
  "properties": {
    "iso:country":"IN",
    "ks:ks_name":"Saroli 1 Faliya",
    "ks:ks_pop":332,
    "ks:ks_type":"HABITATION",
    "name:eng_x_preferred":[
        "Saroli 1 Faliya"
    ],
    "wof:name":"Saroli 1 Faliya",
    "wof:placetype":"locality",
    "wof:population":332
},
  "geometry": {"coordinates":[73.390111,23.124167],"type":"Point"}
}