{
  "type": "Feature",
  "properties": {
    "iso:country":"IN",
    "ks:ks_name":"Amarpur",
    "ks:ks_pop":2875,
    "ks:ks_type":"HABITATION",
    "ks:ks_uagg_main":0,
    "name:eng_x_preferred":[
        "Amarpur"
    ],
    "wof:name":"Amarpur",
    "wof:placetype":"neighbourhood",
    "wof:population":2875
},
  "geometry": {"coordinates":[85.988432,25.428502],"type":"Point"}
}