{
  "type": "Feature",
  "properties": {
    "iso:country":"IN",
    "ks:ks_name":"Chak Hardi",
    "ks:ks_pop":249,
    "ks:ks_type":"VILLAGE",
    "name:eng_x_preferred":[
        "Chak Hardi"
    ],
    "wof:name":"Chak Hardi",
    "wof:placetype":"locality",
    "wof:population":249
},
  "geometry": {"coordinates":[85.539177,25.694908],"type":"Point"}
}