{
  "type": "Feature",
  "properties": {
    "iso:country":"IN",
    "ks:ks_name":"Sawarwadi",
    "ks:ks_pop":23,
    "ks:ks_type":"HABITATION",
    "name:eng_x_preferred":[
        "Sawarwadi"
    ],
    "wof:name":"Sawarwadi",
    "wof:placetype":"locality",
    "wof:population":23
},
  "geometry": {"coordinates":[74.217389,16.114261],"type":"Point"}
}