{
  "type": "Feature",
  "properties": {
    "iso:country":"IN",
    "ks:ks_name":"Harpur",
    "ks:ks_pop":555,
    "ks:ks_type":"VILLAGE",
    "ks:ks_uagg_main":0,
    "name:eng_x_preferred":[
        "Harpur"
    ],
    "wof:name":"Harpur",
    "wof:placetype":"neighbourhood",
    "wof:population":555
},
  "geometry": {"coordinates":[92.08301,26.757432],"type":"Point"}
}