{
  "type": "Feature",
  "properties": {
    "gn:admin1_code":"36.0",
    "gn:admin2_code":"177.0",
    "gn:asciiname":"Bakarpur",
    "gn:country_code":"IN",
    "gn:dem":112,
    "gn:feature_class":"P",
    "gn:feature_code":"PPL",
    "gn:name":"B\u0101karpur",
    "gn:population":0,
    "gn:timezone":"Asia/Kolkata",
    "iso:country":"IN",
    "name:pan_x_preferred":[
        "\u0a2c\u0a3e\u0a15\u0a30\u0a2a\u0a41\u0a30"
    ],
    "wof:name":"Bakarpur",
    "wof:placetype":"locality"
},
  "geometry": {"coordinates":[81.72261999999998,26.68474],"type":"Point"}
}