{
  "type": "Feature",
  "properties": {
    "gn:admin1_code":"23.0",
    "gn:admin2_code":"52.0",
    "gn:asciiname":"Manana",
    "gn:country_code":"IN",
    "gn:dem":327,
    "gn:feature_class":"P",
    "gn:feature_code":"PPL",
    "gn:name":"Man\u0101na",
    "gn:population":0,
    "gn:timezone":"Asia/Kolkata",
    "iso:country":"IN",
    "wof:name":"Manana",
    "wof:placetype":"locality"
},
  "geometry": {"coordinates":[76.69131,30.77188],"type":"Point"}
}