{
  "type": "Feature",
  "properties": {
    "gn:admin1_code":"38",
    "gn:admin2_code":"346.0",
    "gn:asciiname":"Naudihwa",
    "gn:country_code":"IN",
    "gn:dem":175,
    "gn:feature_class":"P",
    "gn:feature_code":"PPL",
    "gn:name":"Naud\u012bhwa",
    "gn:population":0,
    "gn:timezone":"Asia/Kolkata",
    "iso:country":"IN",
    "ks:ks_alt_nam":"NAWDIHWA",
    "ks:ks_name":"Nawdihwa",
    "ks:ks_pop":410,
    "ks:ks_type":"HABITATION",
    "ks:ks_uagg_main":0,
    "name:eng_x_preferred":[
        "Nawdihwa"
    ],
    "wof:name":"Nawdihwa",
    "wof:placetype":"neighbourhood",
    "wof:population":410
},
  "geometry": {"coordinates":[83.726563,24.452403],"type":"Point"}
}