{
  "type": "Feature",
  "properties": {
    "gn:admin1_code":"38.0",
    "gn:admin2_code":"347.0",
    "gn:asciiname":"Jobhi",
    "gn:country_code":"IN",
    "gn:dem":429,
    "gn:feature_class":"P",
    "gn:feature_code":"PPL",
    "gn:name":"Jobh\u012b",
    "gn:population":0,
    "gn:timezone":"Asia/Kolkata",
    "iso:country":"IN",
    "ks:ks_alt_nam":"Jobh\u012b",
    "ks:ks_name":"Jobhi",
    "ks:ks_pop":144,
    "ks:ks_type":"VILLAGE",
    "name:eng_x_preferred":[
        "Jobhi"
    ],
    "name:eng_x_variant":[
        "Jobh\u012b"
    ],
    "wof:name":"Jobhi",
    "wof:placetype":"locality",
    "wof:population":144
},
  "geometry": {"coordinates":[84.654579,24.054613],"type":"Point"}
}