{
  "type": "Feature",
  "properties": {
    "iso:country":"IN",
    "ks:ks_name":"Chalak Pur Kurmian",
    "ks:ks_pop":281,
    "ks:ks_type":"HABITATION",
    "ks:ks_uagg_main":0,
    "name:eng_x_preferred":[
        "Chalak Pur Kurmian"
    ],
    "wof:name":"Chalak Pur Kurmian",
    "wof:placetype":"neighbourhood",
    "wof:population":281
},
  "geometry": {"coordinates":[82.070273,25.915299],"type":"Point"}
}