{
  "type": "Feature",
  "properties": {
    "iso:country":"IN",
    "ks:ks_name":"Kolhewadi",
    "ks:ks_pop":21,
    "ks:ks_type":"HABITATION",
    "name:eng_x_preferred":[
        "Kolhewadi"
    ],
    "wof:name":"Kolhewadi",
    "wof:placetype":"locality",
    "wof:population":21
},
  "geometry": {"coordinates":[73.569508,16.586322],"type":"Point"}
}