{
  "type": "Feature",
  "properties": {
    "iso:country":"IN",
    "ks:ks_name":"Shri Ramnagar",
    "ks:ks_pop":570,
    "ks:ks_type":"HABITATION",
    "name:eng_x_preferred":[
        "Shri Ramnagar"
    ],
    "wof:name":"Shri Ramnagar",
    "wof:placetype":"locality",
    "wof:population":570
},
  "geometry": {"coordinates":[72.549359,27.345223],"type":"Point"}
}