{
  "type": "Feature",
  "properties": {
    "gn:admin1_code":"39.0",
    "gn:admin2_code":"66.0",
    "gn:asciiname":"Basgaon",
    "gn:country_code":"IN",
    "gn:dem":1655,
    "gn:feature_class":"P",
    "gn:feature_code":"PPL",
    "gn:name":"B\u0101sgaon",
    "gn:population":0,
    "gn:timezone":"Asia/Kolkata",
    "iso:country":"IN",
    "ks:ks_name":"Basgaon",
    "ks:ks_pop":201,
    "ks:ks_type":"HABITATION",
    "name:eng_x_preferred":[
        "Basgaon"
    ],
    "wof:name":"Basgaon",
    "wof:placetype":"locality",
    "wof:population":201
},
  "geometry": {"coordinates":[79.55154,29.503395],"type":"Point"}
}