{
  "type": "Feature",
  "properties": {
    "gn:admin1_code":"39.0",
    "gn:admin2_code":"66.0",
    "gn:asciiname":"Basgaon",
    "gn:country_code":"IN",
    "gn:dem":1655,
    "gn:feature_class":"P",
    "gn:feature_code":"PPL",
    "gn:name":"B\u0101sgaon",
    "gn:population":0,
    "gn:timezone":"Asia/Kolkata",
    "iso:country":"IN",
    "wof:name":"Basgaon",
    "wof:placetype":"locality"
},
  "geometry": {"coordinates":[79.54300000000001,29.50175],"type":"Point"}
}