{
  "type": "Feature",
  "properties": {
    "iso:country":"IN",
    "ks:ks_name":"Sagarpali",
    "ks:ks_pop":274,
    "ks:ks_type":"VILLAGE",
    "name:eng_x_preferred":[
        "Sagarpali"
    ],
    "wof:name":"Sagarpali",
    "wof:placetype":"locality",
    "wof:population":274
},
  "geometry": {"coordinates":[83.499008,22.332142],"type":"Point"}
}