{
  "type": "Feature",
  "properties": {
    "iso:country":"IN",
    "ks:ks_name":"Suri",
    "ks:ks_pop":89,
    "ks:ks_type":"VILLAGE",
    "name:eng_x_preferred":[
        "Suri"
    ],
    "name:hin_x_preferred":[
        "\u0938\u0942\u0930\u0940"
    ],
    "wof:name":"Suri",
    "wof:placetype":"locality",
    "wof:population":89
},
  "geometry": {"coordinates":[80.027553,29.454944],"type":"Point"}
}