{
  "type": "Feature",
  "properties": {
    "iso:country":"IN",
    "ks:ks_name":"Jangalabadi",
    "ks:ks_pop":267,
    "ks:ks_type":"VILLAGE",
    "name:eng_x_preferred":[
        "Jangalabadi"
    ],
    "wof:name":"Jangalabadi",
    "wof:placetype":"locality",
    "wof:population":267
},
  "geometry": {"coordinates":[87.224383,22.868243],"type":"Point"}
}