{
  "type": "Feature",
  "properties": {
    "iso:country":"IN",
    "ks:ks_name":"Honnekoppa",
    "ks:ks_pop":44,
    "ks:ks_type":"HABITATION",
    "name:eng_x_preferred":[
        "Honnekoppa"
    ],
    "wof:name":"Honnekoppa",
    "wof:placetype":"locality",
    "wof:population":44
},
  "geometry": {"coordinates":[74.735409,14.496798],"type":"Point"}
}