{
  "type": "Feature",
  "properties": {
    "gn:admin1_code":"12.0",
    "gn:admin2_code":"2.0",
    "gn:asciiname":"Muran",
    "gn:country_code":"IN",
    "gn:dem":1699,
    "gn:feature_class":"P",
    "gn:feature_code":"PPL",
    "gn:name":"Muran",
    "gn:population":0,
    "gn:timezone":"Asia/Kolkata",
    "iso:country":"IN",
    "name:ceb_x_preferred":[
        "Muran"
    ],
    "name:swe_x_preferred":[
        "Muran"
    ],
    "wof:name":"Muran",
    "wof:placetype":"locality"
},
  "geometry": {"coordinates":[74.86648000000002,33.86499],"type":"Point"}
}