{
  "type": "Feature",
  "properties": {
    "iso:country":"IN",
    "ks:ks_name":"Barunsing",
    "ks:ks_pop":2094,
    "ks:ks_type":"VILLAGE",
    "name:eng_x_preferred":[
        "Barunsing"
    ],
    "wof:name":"Barunsing",
    "wof:placetype":"locality",
    "wof:population":2094
},
  "geometry": {"coordinates":[86.854958,21.417753],"type":"Point"}
}