{
  "type": "Feature",
  "properties": {
    "gn:admin1_code":"11.0",
    "gn:admin2_code":"26.0",
    "gn:asciiname":"Luthubil",
    "gn:country_code":"IN",
    "gn:dem":2160,
    "gn:feature_class":"P",
    "gn:feature_code":"PPL",
    "gn:name":"Luthubil",
    "gn:population":0,
    "gn:timezone":"Asia/Kolkata",
    "iso:country":"IN",
    "wof:name":"Luthubil",
    "wof:placetype":"locality"
},
  "geometry": {"coordinates":[77.45395000000001,31.41493],"type":"Point"}
}