{
  "type": "Feature",
  "properties": {
    "iso:country":"IN",
    "ks:ks_name":"Palli",
    "ks:ks_pop":671,
    "ks:ks_type":"VILLAGE",
    "name:eng_x_preferred":[
        "Palli"
    ],
    "wof:name":"Palli",
    "wof:placetype":"locality",
    "wof:population":671
},
  "geometry": {"coordinates":[75.874362,31.878825],"type":"Point"}
}