{
  "type": "Feature",
  "properties": {
    "iso:country":"IN",
    "ks:ks_name":"Ransinghpura",
    "ks:ks_type":"VILLAGE",
    "name:eng_x_preferred":[
        "Ransinghpura"
    ],
    "wof:name":"Ransinghpura",
    "wof:placetype":"locality"
},
  "geometry": {"coordinates":[77.266221,25.960214],"type":"Point"}
}