{
  "type": "Feature",
  "properties": {
    "iso:country":"IN",
    "ks:ks_name":"Brahmapuri",
    "ks:ks_pop":370,
    "ks:ks_type":"HABITATION",
    "name:eng_x_preferred":[
        "Brahmapuri"
    ],
    "wof:name":"Brahmapuri",
    "wof:placetype":"locality",
    "wof:population":370
},
  "geometry": {"coordinates":[74.153565,17.595597],"type":"Point"}
}