{
  "type": "Feature",
  "properties": {
    "gn:admin1_code":"24.0",
    "gn:admin2_code":"104.0",
    "gn:asciiname":"Shadipur",
    "gn:country_code":"IN",
    "gn:dem":353,
    "gn:feature_class":"P",
    "gn:feature_code":"PPL",
    "gn:name":"Sh\u0101dipur",
    "gn:population":0,
    "gn:timezone":"Asia/Kolkata",
    "iso:country":"IN",
    "ks:ks_alt_nam":"Sh\u0101dipur",
    "ks:ks_name":"Shadipur",
    "ks:ks_pop":209,
    "ks:ks_type":"VILLAGE",
    "name:ara_x_preferred":[
        "\u0634\u0627\u062f\u064a\u0628\u0648\u0631"
    ],
    "name:ben_bn_x_preferred":[
        "\u09b8\u09be\u09a6\u09bf\u09aa\u09c1\u09b0"
    ],
    "name:ben_in_x_preferred":[
        "\u09b8\u09be\u09a6\u09bf\u09aa\u09c1\u09b0"
    ],
    "name:eng_x_preferred":[
        "Shadipur"
    ],
    "name:eng_x_variant":[
        "Sh\u0101dipur"
    ],
    "name:guj_x_preferred":[
        "\u0ab6\u0abe\u0aa6\u0ac0\u0aaa\u0ac1\u0ab0"
    ],
    "name:hin_x_preferred":[
        "\u0936\u093e\u0926\u0940\u092a\u0941\u0930"
    ],
    "name:kan_x_preferred":[
        "\u0cb6\u0cbe\u0ca6\u0cbf\u0caa\u0cc1\u0cb0"
    ],
    "name:mal_x_preferred":[
        "\u0d37\u0d3e\u0d21\u0d3f\u0d2a\u0d42\u0d7c"
    ],
    "name:mal_x_variant":[
        "\u0d36\u0d3e\u0d26\u0d3f\u0d2a\u0d42\u0d7c"
    ],
    "name:mar_x_preferred":[
        "\u0936\u093e\u0926\u093f\u092a\u0942\u0930"
    ],
    "name:pan_x_preferred":[
        "\u0a36\u0a3e\u0a26\u0a40\u0a2a\u0a41\u0a30"
    ],
    "name:pan_x_variant":[
        "\u0a38\u0a3c\u0a3e\u0a26\u0a40\u0a2a\u0a41\u0a30"
    ],
    "name:tam_x_preferred":[
        "\u0bb7\u0bbe\u0ba4\u0bbf\u0baa\u0bcd\u0baa\u0bc2\u0bb0\u0bcd"
    ],
    "name:tel_x_preferred":[
        "\u0c37\u0c3e\u0c26\u0c3f\u0c2a\u0c42\u0c30\u0c4d"
    ],
    "name:urd_x_preferred":[
        "\u0634\u0627\u062f\u06cc \u067e\u0648\u0631"
    ],
    "wof:name":"Shadipur",
    "wof:placetype":"locality",
    "wof:population":209
},
  "geometry": {"coordinates":[76.929692,28.008253],"type":"Point"}
}