{
  "type": "Feature",
  "properties": {
    "iso:country":"IN",
    "ks:ks_name":"Ajanisar",
    "ks:ks_pop":279,
    "ks:ks_type":"HABITATION",
    "name:eng_x_preferred":[
        "Ajanisar"
    ],
    "wof:name":"Ajanisar",
    "wof:placetype":"locality",
    "wof:population":279
},
  "geometry": {"coordinates":[72.511022,27.503203],"type":"Point"}
}