{
  "type": "Feature",
  "properties": {
    "iso:country":"IN",
    "ks:ks_name":"Kasa",
    "ks:ks_pop":188,
    "ks:ks_type":"HABITATION",
    "name:eng_x_preferred":[
        "Kasa"
    ],
    "wof:name":"Kasa",
    "wof:placetype":"locality",
    "wof:population":188
},
  "geometry": {"coordinates":[78.49796600000001,25.029733],"type":"Point"}
}