{
  "type": "Feature",
  "properties": {
    "gn:admin1_code":"36",
    "gn:admin2_code":"145.0",
    "gn:asciiname":"Garhi Balkishan",
    "gn:country_code":"IN",
    "gn:dem":183,
    "gn:feature_class":"P",
    "gn:feature_code":"PPL",
    "gn:name":"Garhi B\u0101lkishan",
    "gn:population":0,
    "gn:timezone":"Asia/Kolkata",
    "iso:country":"IN",
    "wof:name":"Garhi Balkishan",
    "wof:placetype":"neighbourhood"
},
  "geometry": {"coordinates":[77.72754999999999,27.6657],"type":"Point"}
}