{
  "type": "Feature",
  "properties": {
    "gn:admin1_code":"16.0",
    "gn:admin2_code":"508.0",
    "gn:asciiname":"Sedaram",
    "gn:country_code":"IN",
    "gn:dem":127,
    "gn:feature_class":"P",
    "gn:feature_code":"PPL",
    "gn:name":"Sed\u0101ram",
    "gn:population":0,
    "gn:timezone":"Asia/Kolkata",
    "iso:country":"IN",
    "wof:name":"Sedaram",
    "wof:placetype":"locality"
},
  "geometry": {"coordinates":[79.87893000000003,19.06625],"type":"Point"}
}