{
  "type": "Feature",
  "properties": {
    "iso:country":"IN",
    "ks:ks_name":"Sewariya",
    "ks:ks_pop":979,
    "ks:ks_type":"VILLAGE",
    "name:eng_x_preferred":[
        "Sewariya"
    ],
    "wof:name":"Sewariya",
    "wof:placetype":"locality",
    "wof:population":979
},
  "geometry": {"coordinates":[74.641856,22.402641],"type":"Point"}
}