{
  "type": "Feature",
  "properties": {
    "iso:country":"IN",
    "ks:ks_name":"Delana Chhota",
    "ks:ks_pop":965,
    "ks:ks_type":"VILLAGE",
    "name:eng_x_preferred":[
        "Delana Chhota"
    ],
    "wof:name":"Delana Chhota",
    "wof:placetype":"locality",
    "wof:population":965
},
  "geometry": {"coordinates":[73.661233,28.571725],"type":"Point"}
}