{
  "type": "Feature",
  "properties": {
    "iso:country":"IN",
    "ks:ks_alt_nam":"W\u0101ghj\u0101li",
    "ks:ks_name":"Waghjali",
    "ks:ks_type":"VILLAGE",
    "name:eng_x_preferred":[
        "Waghjali"
    ],
    "name:eng_x_variant":[
        "W\u0101ghj\u0101li"
    ],
    "wof:name":"Waghjali",
    "wof:placetype":"locality"
},
  "geometry": {"coordinates":[77.307284,19.952841],"type":"Point"}
}