{
  "type": "Feature",
  "properties": {
    "iso:country":"IN",
    "ks:ks_name":"Balekai",
    "ks:ks_pop":110,
    "ks:ks_type":"HABITATION",
    "name:eng_x_preferred":[
        "Balekai"
    ],
    "wof:name":"Balekai",
    "wof:placetype":"locality",
    "wof:population":110
},
  "geometry": {"coordinates":[74.855981,14.493518],"type":"Point"}
}