{
  "type": "Feature",
  "properties": {
    "iso:country":"IN",
    "ks:ks_alt_nam":"MPR Nagar",
    "ks:ks_name":"Mpr Nagar",
    "ks:ks_pop":301,
    "ks:ks_type":"HABITATION",
    "ks:ks_uagg_main":0,
    "name:eng_x_preferred":[
        "Mpr Nagar"
    ],
    "wof:name":"Mpr Nagar",
    "wof:placetype":"neighbourhood",
    "wof:population":301
},
  "geometry": {"coordinates":[78.157055,10.032126],"type":"Point"}
}