{
  "type": "Feature",
  "properties": {
    "iso:country":"IN",
    "ks:ks_name":"Roorh Khadar",
    "ks:ks_pop":891,
    "ks:ks_type":"VILLAGE",
    "name:eng_x_preferred":[
        "Roorh Khadar"
    ],
    "wof:name":"Roorh Khadar",
    "wof:placetype":"locality",
    "wof:population":891
},
  "geometry": {"coordinates":[78.27319,28.381845],"type":"Point"}
}