{
  "type": "Feature",
  "properties": {
    "gn:admin1_code":"11.0",
    "gn:admin2_code":"33.0",
    "gn:asciiname":"Danalata",
    "gn:country_code":"IN",
    "gn:dem":1748,
    "gn:feature_class":"P",
    "gn:feature_code":"PPL",
    "gn:name":"Dan\u0101lata",
    "gn:population":0,
    "gn:timezone":"Asia/Kolkata",
    "iso:country":"IN",
    "wof:name":"Danalata",
    "wof:placetype":"locality"
},
  "geometry": {"coordinates":[77.24450999999998,30.99987],"type":"Point"}
}