{
  "type": "Feature",
  "properties": {
    "iso:country":"IN",
    "ks:ks_name":"Kayyani",
    "ks:ks_pop":69,
    "ks:ks_type":"HABITATION",
    "name:eng_x_preferred":[
        "Kayyani"
    ],
    "wof:name":"Kayyani",
    "wof:placetype":"locality",
    "wof:population":69
},
  "geometry": {"coordinates":[74.853182,13.62334],"type":"Point"}
}