{
  "type": "Feature",
  "properties": {
    "iso:country":"IN",
    "ks:ks_name":"Urantola",
    "ks:ks_pop":522,
    "ks:ks_type":"HABITATION",
    "name:eng_x_preferred":[
        "Urantola"
    ],
    "wof:name":"Urantola",
    "wof:placetype":"locality",
    "wof:population":522
},
  "geometry": {"coordinates":[85.164328,25.45767],"type":"Point"}
}