{
  "type": "Feature",
  "properties": {
    "gn:admin1_code":"2.0",
    "gn:admin2_code":"549.0",
    "gn:asciiname":"Kodigumpala",
    "gn:country_code":"IN",
    "gn:dem":105,
    "gn:feature_class":"P",
    "gn:feature_code":"PPL",
    "gn:name":"Kodigumpala",
    "gn:population":0,
    "gn:timezone":"Asia/Kolkata",
    "iso:country":"IN",
    "wof:name":"Kodigumpala",
    "wof:placetype":"locality"
},
  "geometry": {"coordinates":[79.51787,15.14196],"type":"Point"}
}