{
  "type": "Feature",
  "properties": {
    "iso:country":"IN",
    "ks:ks_name":"Kuluwa",
    "ks:ks_pop":1720,
    "ks:ks_type":"VILLAGE",
    "name:eng_x_preferred":[
        "Kuluwa"
    ],
    "wof:name":"Kuluwa",
    "wof:placetype":"locality",
    "wof:population":1720
},
  "geometry": {"coordinates":[79.45407,23.792045],"type":"Point"}
}