{
  "type": "Feature",
  "properties": {
    "iso:country":"IN",
    "ks:ks_name":"Seonighat",
    "ks:ks_pop":75,
    "ks:ks_type":"HABITATION",
    "name:eng_x_preferred":[
        "Seonighat"
    ],
    "wof:name":"Seonighat",
    "wof:placetype":"locality",
    "wof:population":75
},
  "geometry": {"coordinates":[78.402315,22.310805],"type":"Point"}
}