{
  "type": "Feature",
  "properties": {
    "iso:country":"IN",
    "ks:ks_name":"Kota",
    "ks:ks_type":"VILLAGE",
    "name:eng_x_preferred":[
        "Kota"
    ],
    "wof:name":"Kota",
    "wof:placetype":"locality"
},
  "geometry": {"coordinates":[79.252144,29.937841],"type":"Point"}
}