{
  "type": "Feature",
  "properties": {
    "iso:country":"IN",
    "ks:ks_name":"Kairat",
    "ks:ks_pop":163,
    "ks:ks_type":"HABITATION",
    "name:eng_x_preferred":[
        "Kairat"
    ],
    "wof:name":"Kairat",
    "wof:placetype":"locality",
    "wof:population":163
},
  "geometry": {"coordinates":[80.56677000000001,24.961841],"type":"Point"}
}