{
  "type": "Feature",
  "properties": {
    "iso:country":"IN",
    "ks:ks_name":"Tivarewadi",
    "ks:ks_pop":210,
    "ks:ks_type":"HABITATION",
    "name:eng_x_preferred":[
        "Tivarewadi"
    ],
    "wof:name":"Tivarewadi",
    "wof:placetype":"locality",
    "wof:population":210
},
  "geometry": {"coordinates":[73.668503,15.737419],"type":"Point"}
}