{
  "type": "Feature",
  "properties": {
    "iso:country":"IN",
    "ks:ks_alt_nam":"Putt\u016brani",
    "ks:ks_name":"Putturani",
    "ks:ks_type":"VILLAGE",
    "name:eng_x_preferred":[
        "Putturani"
    ],
    "name:eng_x_variant":[
        "Putt\u016brani"
    ],
    "wof:name":"Putturani",
    "wof:placetype":"locality"
},
  "geometry": {"coordinates":[78.90034900000001,9.954804],"type":"Point"}
}