{
  "type": "Feature",
  "properties": {
    "iso:country":"IN",
    "ks:ks_name":"Dharmohan",
    "ks:ks_pop":2040,
    "ks:ks_type":"VILLAGE",
    "name:eng_x_preferred":[
        "Dharmohan"
    ],
    "wof:name":"Dharmohan",
    "wof:placetype":"locality",
    "wof:population":2040
},
  "geometry": {"coordinates":[85.346626,26.017022],"type":"Point"}
}