{
  "type": "Feature",
  "properties": {
    "iso:country":"IN",
    "ks:ks_name":"Chaturipur Kalan",
    "ks:ks_pop":361,
    "ks:ks_type":"VILLAGE",
    "name:eng_x_preferred":[
        "Chaturipur Kalan"
    ],
    "wof:name":"Chaturipur Kalan",
    "wof:placetype":"locality",
    "wof:population":361
},
  "geometry": {"coordinates":[83.06692200000001,25.060314],"type":"Point"}
}