{
  "type": "Feature",
  "properties": {
    "iso:country":"IN",
    "ks:ks_name":"Chak Nandu",
    "ks:ks_pop":242,
    "ks:ks_type":"HABITATION",
    "name:eng_x_preferred":[
        "Chak Nandu"
    ],
    "wof:name":"Chak Nandu",
    "wof:placetype":"locality",
    "wof:population":242
},
  "geometry": {"coordinates":[82.602825,25.355242],"type":"Point"}
}