{
  "type": "Feature",
  "properties": {
    "iso:country":"IN",
    "ks:ks_name":"Pusheli",
    "ks:ks_pop":31,
    "ks:ks_type":"VILLAGE",
    "name:eng_x_preferred":[
        "Pusheli"
    ],
    "wof:name":"Pusheli",
    "wof:placetype":"locality",
    "wof:population":31
},
  "geometry": {"coordinates":[74.531221,15.331425],"type":"Point"}
}