{
  "type": "Feature",
  "properties": {
    "gn:admin1_code":"36.0",
    "gn:admin2_code":"153.0",
    "gn:asciiname":"Mahua Dhab",
    "gn:country_code":"IN",
    "gn:dem":146,
    "gn:feature_class":"P",
    "gn:feature_code":"PPL",
    "gn:name":"Mahua Dh\u0101b",
    "gn:population":0,
    "gn:timezone":"Asia/Kolkata",
    "iso:country":"IN",
    "name:und_x_variant":[
        "Mahua Dh\u0101b",
        "Ekghara"
    ],
    "wof:name":"Mahua Dhab",
    "wof:placetype":"locality"
},
  "geometry": {"coordinates":[80.27537,27.77689],"type":"Point"}
}