{
  "type": "Feature",
  "properties": {
    "iso:country":"IN",
    "ks:ks_name":"Dulahinia",
    "ks:ks_pop":8,
    "ks:ks_type":"HABITATION",
    "name:eng_x_preferred":[
        "Dulahinia"
    ],
    "wof:name":"Dulahinia",
    "wof:placetype":"locality",
    "wof:population":8
},
  "geometry": {"coordinates":[81.221816,24.84464],"type":"Point"}
}