{
  "type": "Feature",
  "properties": {
    "iso:country":"IN",
    "ks:ks_name":"Madhopur",
    "ks:ks_pop":3077,
    "ks:ks_type":"VILLAGE",
    "ks:ks_uagg_main":0,
    "name:eng_x_preferred":[
        "Madhopur"
    ],
    "wof:name":"Madhopur",
    "wof:placetype":"neighbourhood",
    "wof:population":3077
},
  "geometry": {"coordinates":[82.71321,25.359605],"type":"Point"}
}