{
  "type": "Feature",
  "properties": {
    "iso:country":"IN",
    "ks:ks_alt_nam":"T\u0101jpur Kal\u0101n",
    "ks:ks_name":"Tajpur Kalan",
    "ks:ks_type":"VILLAGE",
    "name:eng_x_preferred":[
        "Tajpur Kalan"
    ],
    "name:eng_x_variant":[
        "T\u0101jpur Kal\u0101n"
    ],
    "wof:name":"Tajpur Kalan",
    "wof:placetype":"neighbourhood"
},
  "geometry": {"coordinates":[77.169935,28.838403],"type":"Point"}
}