{
  "type": "Feature",
  "properties": {
    "iso:country":"IN",
    "ks:ks_name":"Bari",
    "ks:ks_pop":165,
    "ks:ks_type":"VILLAGE",
    "name:eng_x_preferred":[
        "Bari"
    ],
    "wof:name":"Bari",
    "wof:placetype":"locality",
    "wof:population":165
},
  "geometry": {"coordinates":[87.190978,22.117574],"type":"Point"}
}