{
  "type": "Feature",
  "properties": {
    "gn:admin1_code":"34.0",
    "gn:admin2_code":"238.0",
    "gn:asciiname":"Khiria",
    "gn:country_code":"IN",
    "gn:dem":116,
    "gn:feature_class":"P",
    "gn:feature_code":"PPL",
    "gn:name":"Khiria",
    "gn:population":0,
    "gn:timezone":"Asia/Kolkata",
    "iso:country":"IN",
    "ks:ks_alt_nam":"kheria",
    "ks:ks_name":"Kheria",
    "ks:ks_pop":408,
    "ks:ks_type":"HABITATION",
    "name:eng_x_preferred":[
        "Kheria"
    ],
    "name:eng_x_variant":[
        "Khiria"
    ],
    "name:tam_x_preferred":[
        "\u0b95\u0bc0\u0bb0\u0bbf\u0baf\u0bbe"
    ],
    "wof:name":"Kheria",
    "wof:placetype":"locality",
    "wof:population":408
},
  "geometry": {"coordinates":[86.324084,25.013875],"type":"Point"}
}