{
  "type": "Feature",
  "properties": {
    "iso:country":"IN",
    "ks:ks_name":"2 BLD-A",
    "ks:ks_type":"VILLAGE",
    "name:eng_x_preferred":[
        "2 BLD-A"
    ],
    "wof:name":"2 BLD-A",
    "wof:placetype":"locality"
},
  "geometry": {"coordinates":[73.48436700000001,29.325602],"type":"Point"}
}