{
  "type": "Feature",
  "properties": {
    "iso:country":"IN",
    "ks:ks_name":"Benipadar",
    "ks:ks_pop":132,
    "ks:ks_type":"VILLAGE",
    "name:eng_x_preferred":[
        "Benipadar"
    ],
    "wof:name":"Benipadar",
    "wof:placetype":"locality",
    "wof:population":132
},
  "geometry": {"coordinates":[84.32058499999999,19.475723],"type":"Point"}
}