{
  "type": "Feature",
  "properties": {
    "gn:admin1_code":"11",
    "gn:admin2_code":"23.0",
    "gn:asciiname":"Lowari",
    "gn:country_code":"IN",
    "gn:dem":2581,
    "gn:feature_class":"P",
    "gn:feature_code":"PPL",
    "gn:name":"Low\u0101ri",
    "gn:population":0,
    "gn:timezone":"Asia/Kolkata",
    "iso:country":"IN",
    "wof:name":"Lowari",
    "wof:placetype":"locality"
},
  "geometry": {"coordinates":[76.49781999999998,32.98318],"type":"Point"}
}