{
  "type": "Feature",
  "properties": {
    "iso:country":"IN",
    "ks:ks_alt_nam":"MORE MANDRE WASTI",
    "ks:ks_name":"More Mandre Wasti",
    "ks:ks_pop":118,
    "ks:ks_type":"HABITATION",
    "name:eng_x_preferred":[
        "More Mandre Wasti"
    ],
    "wof:name":"More Mandre Wasti",
    "wof:placetype":"locality",
    "wof:population":118
},
  "geometry": {"coordinates":[75.106329,18.532575],"type":"Point"}
}