{
  "type": "Feature",
  "properties": {
    "gn:admin1_code":"3.0",
    "gn:admin2_code":"317.0",
    "gn:asciiname":"Maizgram",
    "gn:country_code":"IN",
    "gn:dem":31,
    "gn:feature_class":"P",
    "gn:feature_code":"PPL",
    "gn:name":"Maizgram",
    "gn:population":0,
    "gn:timezone":"Asia/Kolkata",
    "iso:country":"IN",
    "wof:name":"Maizgram",
    "wof:placetype":"locality"
},
  "geometry": {"coordinates":[92.31478,24.85126],"type":"Point"}
}