{
  "type": "Feature",
  "properties": {
    "gn:admin1_code":"37",
    "gn:admin2_code":"408.0",
    "gn:asciiname":"Mohara",
    "gn:country_code":"IN",
    "gn:dem":301,
    "gn:feature_class":"P",
    "gn:feature_code":"PPL",
    "gn:name":"Moh\u0101ra",
    "gn:population":0,
    "gn:timezone":"Asia/Kolkata",
    "iso:country":"IN",
    "name:ceb_x_preferred":[
        "Mo\u1e29ar\u0101"
    ],
    "name:fas_x_preferred":[
        "\u0645\u062d\u0631\u0627"
    ],
    "name:msa_x_preferred":[
        "Mohara"
    ],
    "name:swe_x_preferred":[
        "Mo\u1e29ar\u0101"
    ],
    "wof:name":"Mohara",
    "wof:placetype":"locality"
},
  "geometry": {"coordinates":[81.02998000000002,21.07444],"type":"Point"}
}