{
  "type": "Feature",
  "properties": {
    "iso:country":"IN",
    "ks:ks_name":"Mukundapur",
    "ks:ks_pop":619,
    "ks:ks_type":"VILLAGE",
    "name:eng_x_preferred":[
        "Mukundapur"
    ],
    "wof:name":"Mukundapur",
    "wof:placetype":"locality",
    "wof:population":619
},
  "geometry": {"coordinates":[86.612314,20.991235],"type":"Point"}
}