{
  "type": "Feature",
  "properties": {
    "iso:country":"IN",
    "ks:ks_name":"Thathaiahgaripalle",
    "ks:ks_pop":33,
    "ks:ks_type":"HABITATION",
    "name:eng_x_preferred":[
        "Thathaiahgaripalle"
    ],
    "wof:name":"Thathaiahgaripalle",
    "wof:placetype":"locality",
    "wof:population":33
},
  "geometry": {"coordinates":[78.98234600000001,13.996893],"type":"Point"}
}