{
  "type": "Feature",
  "properties": {
    "iso:country":"IN",
    "ks:ks_name":"Kalligadde",
    "ks:ks_pop":288,
    "ks:ks_type":"HABITATION",
    "name:eng_x_preferred":[
        "Kalligadde"
    ],
    "wof:name":"Kalligadde",
    "wof:placetype":"locality",
    "wof:population":288
},
  "geometry": {"coordinates":[75.38584299999999,13.820893],"type":"Point"}
}