{
  "type": "Feature",
  "properties": {
    "iso:country":"IN",
    "ks:ks_name":"Kothuru",
    "ks:ks_pop":38,
    "ks:ks_type":"HABITATION",
    "name:eng_x_preferred":[
        "Kothuru"
    ],
    "wof:name":"Kothuru",
    "wof:placetype":"locality",
    "wof:population":38
},
  "geometry": {"coordinates":[83.707864,18.912013],"type":"Point"}
}