{
  "type": "Feature",
  "properties": {
    "iso:country":"IN",
    "ks:ks_name":"Labangola",
    "ks:ks_pop":1410,
    "ks:ks_type":"VILLAGE",
    "ks:ks_uagg_main":0,
    "name:eng_x_preferred":[
        "Labangola"
    ],
    "wof:name":"Labangola",
    "wof:placetype":"neighbourhood",
    "wof:population":1410
},
  "geometry": {"coordinates":[88.8104,22.859742],"type":"Point"}
}