{
  "type": "Feature",
  "properties": {
    "iso:country":"IN",
    "ks:ks_name":"Pokhari Bilwal",
    "ks:ks_pop":16,
    "ks:ks_type":"HABITATION",
    "name:eng_x_preferred":[
        "Pokhari Bilwal"
    ],
    "wof:name":"Pokhari Bilwal",
    "wof:placetype":"locality",
    "wof:population":16
},
  "geometry": {"coordinates":[79.74570900000001,29.510472],"type":"Point"}
}