{
  "type": "Feature",
  "properties": {
    "iso:country":"IN",
    "ks:ks_name":"Mulemane",
    "ks:ks_pop":8,
    "ks:ks_type":"HABITATION",
    "name:eng_x_preferred":[
        "Mulemane"
    ],
    "wof:name":"Mulemane",
    "wof:placetype":"locality",
    "wof:population":8
},
  "geometry": {"coordinates":[74.620071,14.699064],"type":"Point"}
}