{
  "type": "Feature",
  "properties": {
    "gn:admin1_code":"34",
    "gn:admin2_code":"232.0",
    "gn:asciiname":"Bhar Parasi",
    "gn:country_code":"IN",
    "gn:dem":70,
    "gn:feature_class":"P",
    "gn:feature_code":"PPL",
    "gn:name":"Bhar Par\u0101si",
    "gn:population":0,
    "gn:timezone":"Asia/Kolkata",
    "iso:country":"IN",
    "ks:ks_name":"Bharparasi",
    "ks:ks_pop":0,
    "ks:ks_type":"VILLAGE",
    "name:eng_x_preferred":[
        "Bharparasi"
    ],
    "name:eng_x_variant":[
        "Bhar Parasi"
    ],
    "wof:name":"Bharparasi",
    "wof:placetype":"locality",
    "wof:population":0
},
  "geometry": {"coordinates":[83.998239,25.436804],"type":"Point"}
}