{
  "type": "Feature",
  "properties": {
    "iso:country":"IN",
    "ks:ks_name":"Khamaria J. Padri",
    "ks:ks_pop":4,
    "ks:ks_type":"VILLAGE",
    "name:eng_x_preferred":[
        "Khamaria J. Padri"
    ],
    "wof:name":"Khamaria J. Padri",
    "wof:placetype":"locality",
    "wof:population":4
},
  "geometry": {"coordinates":[80.090056,28.230881],"type":"Point"}
}