{
  "type": "Feature",
  "properties": {
    "iso:country":"IN",
    "ks:ks_name":"Sarpanch Falia",
    "ks:ks_pop":198,
    "ks:ks_type":"HABITATION",
    "name:eng_x_preferred":[
        "Sarpanch Falia"
    ],
    "wof:name":"Sarpanch Falia",
    "wof:placetype":"locality",
    "wof:population":198
},
  "geometry": {"coordinates":[73.857333,23.274083],"type":"Point"}
}