{
  "type": "Feature",
  "properties": {
    "gn:admin1_code":"11.0",
    "gn:admin2_code":"32.0",
    "gn:asciiname":"Baghur",
    "gn:country_code":"IN",
    "gn:dem":956,
    "gn:feature_class":"P",
    "gn:feature_code":"PPL",
    "gn:name":"Baghur",
    "gn:population":0,
    "gn:timezone":"Asia/Kolkata",
    "iso:country":"IN",
    "wof:name":"Baghur",
    "wof:placetype":"locality"
},
  "geometry": {"coordinates":[77.32396999999997,30.5797],"type":"Point"}
}