{
  "type": "Feature",
  "properties": {
    "iso:country":"IN",
    "ks:ks_name":"Miyanwalijhiriya Aliasn",
    "ks:ks_pop":184,
    "ks:ks_type":"HABITATION",
    "name:eng_x_preferred":[
        "Miyanwalijhiriya Aliasn"
    ],
    "wof:name":"Miyanwalijhiriya Aliasn",
    "wof:placetype":"locality",
    "wof:population":184
},
  "geometry": {"coordinates":[77.33095400000001,24.805502],"type":"Point"}
}