{
  "type": "Feature",
  "properties": {
    "gn:admin1_code":"34.0",
    "gn:admin2_code":"216.0",
    "gn:asciiname":"Lakhnauri",
    "gn:country_code":"IN",
    "gn:dem":64,
    "gn:feature_class":"P",
    "gn:feature_code":"PPL",
    "gn:name":"Lakhnauri",
    "gn:population":0,
    "gn:timezone":"Asia/Kolkata",
    "iso:country":"IN",
    "ks:ks_name":"Lakhnauri",
    "ks:ks_pop":2072,
    "ks:ks_type":"VILLAGE",
    "name:eng_x_preferred":[
        "Lakhnauri"
    ],
    "wof:name":"Lakhnauri",
    "wof:placetype":"locality",
    "wof:population":2072
},
  "geometry": {"coordinates":[84.993756,26.166188],"type":"Point"}
}