{
  "type": "Feature",
  "properties": {
    "gn:admin1_code":"12.0",
    "gn:admin2_code":"018",
    "gn:asciiname":"Chishot",
    "gn:country_code":"IN",
    "gn:dem":2405,
    "gn:feature_class":"P",
    "gn:feature_code":"PPL",
    "gn:name":"Chish\u014dt",
    "gn:population":0,
    "gn:timezone":"Asia/Kolkata",
    "iso:country":"IN",
    "name:und_x_variant":[
        "Chish\u014dt",
        "Chishot"
    ],
    "wof:name":"Chishot",
    "wof:placetype":"locality"
},
  "geometry": {"coordinates":[76.279,33.37945],"type":"Point"}
}