{
  "type": "Feature",
  "properties": {
    "iso:country":"IN",
    "ks:ks_name":"Atholi",
    "ks:ks_pop":52,
    "ks:ks_type":"VILLAGE",
    "name:eng_x_preferred":[
        "Atholi"
    ],
    "wof:name":"Atholi",
    "wof:placetype":"locality",
    "wof:population":52
},
  "geometry": {"coordinates":[78.935126,30.391101],"type":"Point"}
}