{
  "type": "Feature",
  "properties": {
    "iso:country":"IN",
    "ks:ks_name":"Ganjiakhari",
    "ks:ks_pop":286,
    "ks:ks_type":"HABITATION",
    "name:eng_x_preferred":[
        "Ganjiakhari"
    ],
    "wof:name":"Ganjiakhari",
    "wof:placetype":"locality",
    "wof:population":286
},
  "geometry": {"coordinates":[82.548301,19.523843],"type":"Point"}
}