{
  "type": "Feature",
  "properties": {
    "iso:country":"IN",
    "ks:ks_alt_nam":"BadhiyaTola",
    "ks:ks_name":"Badhiyatola",
    "ks:ks_pop":42,
    "ks:ks_type":"HABITATION",
    "name:eng_x_preferred":[
        "Badhiyatola"
    ],
    "wof:name":"Badhiyatola",
    "wof:placetype":"locality",
    "wof:population":42
},
  "geometry": {"coordinates":[81.28739299999999,22.420187],"type":"Point"}
}