{
  "type": "Feature",
  "properties": {
    "gn:admin1_code":"23.0",
    "gn:admin2_code":"51.0",
    "gn:asciiname":"Baman",
    "gn:country_code":"IN",
    "gn:dem":260,
    "gn:feature_class":"P",
    "gn:feature_code":"PPL",
    "gn:name":"Bam\u0101n",
    "gn:population":0,
    "gn:timezone":"Asia/Kolkata",
    "iso:country":"IN",
    "wof:name":"Baman",
    "wof:placetype":"locality"
},
  "geometry": {"coordinates":[76.43574,30.94074],"type":"Point"}
}