{
  "type": "Feature",
  "properties": {
    "iso:country":"IN",
    "ks:ks_alt_nam":"N\u0101haldari",
    "ks:ks_name":"Nahaldari",
    "ks:ks_pop":1793,
    "ks:ks_type":"VILLAGE",
    "name:eng_x_preferred":[
        "Nahaldari"
    ],
    "name:eng_x_variant":[
        "N\u0101haldari"
    ],
    "wof:name":"Nahaldari",
    "wof:placetype":"locality",
    "wof:population":1793
},
  "geometry": {"coordinates":[75.946994,21.600696],"type":"Point"}
}