{
  "type": "Feature",
  "properties": {
    "gn:admin1_code":"3.0",
    "gn:admin2_code":"303.0",
    "gn:asciiname":"Dambra Bawa",
    "gn:country_code":"IN",
    "gn:dem":40,
    "gn:feature_class":"P",
    "gn:feature_code":"PPL",
    "gn:name":"Dambra Bawa",
    "gn:population":0,
    "gn:timezone":"Asia/Kolkata",
    "iso:country":"IN",
    "name:und_x_variant":[
        "Damrabua"
    ],
    "wof:name":"Dambra Bawa",
    "wof:placetype":"locality"
},
  "geometry": {"coordinates":[91.12691,26.31611],"type":"Point"}
}