{
  "type": "Feature",
  "properties": {
    "iso:country":"IN",
    "ks:ks_name":"Gothasahi",
    "ks:ks_pop":47,
    "ks:ks_type":"HABITATION",
    "name:eng_x_preferred":[
        "Gothasahi"
    ],
    "wof:name":"Gothasahi",
    "wof:placetype":"locality",
    "wof:population":47
},
  "geometry": {"coordinates":[84.793857,20.360642],"type":"Point"}
}