{
  "type": "Feature",
  "properties": {
    "iso:country":"IN",
    "ks:ks_name":"Sondhni",
    "ks:ks_pop":270,
    "ks:ks_type":"VILLAGE",
    "name:eng_x_preferred":[
        "Sondhni"
    ],
    "wof:name":"Sondhni",
    "wof:placetype":"locality",
    "wof:population":270
},
  "geometry": {"coordinates":[76.98531199999999,25.317765],"type":"Point"}
}