{
  "type": "Feature",
  "properties": {
    "gn:admin1_code":"34.0",
    "gn:admin2_code":"230.0",
    "gn:asciiname":"Gopalganj",
    "gn:country_code":"IN",
    "gn:dem":56,
    "gn:feature_class":"P",
    "gn:feature_code":"PPL",
    "gn:name":"Gop\u0101lganj",
    "gn:population":0,
    "gn:timezone":"Asia/Kolkata",
    "iso:country":"IN",
    "name:ara_x_preferred":[
        "\u062c\u0648\u0628\u0627\u0644\u063a\u0627\u0646\u062c"
    ],
    "name:ben_bn_x_preferred":[
        "\u0997\u09cb\u09aa\u09be\u09b2\u0997\u099e\u09cd\u099c"
    ],
    "name:ben_in_x_preferred":[
        "\u0997\u09cb\u09aa\u09be\u09b2\u0997\u099e\u09cd\u099c"
    ],
    "name:ben_x_preferred":[
        "\u0997\u09cb\u09aa\u09be\u09b2\u0997\u099e\u09cd\u099c"
    ],
    "name:ceb_x_preferred":[
        "Gopalganj"
    ],
    "name:deu_x_preferred":[
        "Gopalganj"
    ],
    "name:guj_x_preferred":[
        "\u0a97\u0acb\u0aaa\u0abe\u0ab2\u0a97\u0a82\u0a9c"
    ],
    "name:hin_x_preferred":[
        "\u0917\u094b\u092a\u093e\u0932\u0917\u0902\u091c"
    ],
    "name:kan_x_preferred":[
        "\u0c97\u0ccb\u0caa\u0cbe\u0cb2\u0ccd"
    ],
    "name:mal_x_preferred":[
        "\u0d17\u0d4b\u0d2a\u0d3e\u0d7d\u0d17\u0d1e\u0d4d\u0d1a\u0d4d"
    ],
    "name:mar_x_preferred":[
        "\u0917\u094b\u092a\u093e\u0933\u0917\u0902\u091c"
    ],
    "name:nld_x_preferred":[
        "Gopalganj"
    ],
    "name:pan_x_preferred":[
        "\u0a17\u0a4b\u0a2a\u0a3e\u0a32\u0a17\u0a70\u0a1c"
    ],
    "name:sco_x_preferred":[
        "Gopalganj"
    ],
    "name:swe_x_preferred":[
        "Gopalganj"
    ],
    "name:tam_x_preferred":[
        "\u0b95\u0bcb\u0baa\u0bbe\u0bb2\u0bcd\u0b95\u0b9e\u0bcd\u0b9a\u0bcd"
    ],
    "name:tel_x_preferred":[
        "\u0c17\u0c4b\u0c2a\u0c3e\u0c32\u0c4d"
    ],
    "name:urd_x_preferred":[
        "\u06af\u0648\u067e\u0627\u0644 \u06af\u0646\u062c"
    ],
    "wof:name":"Gopalganj",
    "wof:placetype":"locality"
},
  "geometry": {"coordinates":[85.18494,25.43647],"type":"Point"}
}