{
  "type": "Feature",
  "properties": {
    "gn:admin1_code":"25.0",
    "gn:admin2_code":"631.0",
    "gn:asciiname":"Ellayaur",
    "gn:country_code":"IN",
    "gn:dem":838,
    "gn:feature_class":"P",
    "gn:feature_code":"PPL",
    "gn:name":"Ellaya\u016br",
    "gn:population":0,
    "gn:timezone":"Asia/Kolkata",
    "iso:country":"IN",
    "wof:name":"Ellayaur",
    "wof:placetype":"locality"
},
  "geometry": {"coordinates":[77.80161,12.56352],"type":"Point"}
}