{
  "type": "Feature",
  "properties": {
    "gn:admin1_code":"24.0",
    "gn:admin2_code":"125.0",
    "gn:asciiname":"Heja",
    "gn:country_code":"IN",
    "gn:dem":219,
    "gn:feature_class":"P",
    "gn:feature_code":"PPL",
    "gn:name":"Heja",
    "gn:population":0,
    "gn:timezone":"Asia/Kolkata",
    "iso:country":"IN",
    "ks:ks_name":"Heja",
    "ks:ks_type":"VILLAGE",
    "name:eng_x_preferred":[
        "Heja"
    ],
    "wof:name":"Heja",
    "wof:placetype":"locality"
},
  "geometry": {"coordinates":[74.26012799999999,23.30598],"type":"Point"}
}