{
  "type": "Feature",
  "properties": {
    "iso:country":"IN",
    "ks:ks_alt_nam":"Khatara-Pathar",
    "ks:ks_name":"Khatara-pathar",
    "ks:ks_pop":95,
    "ks:ks_type":"HABITATION",
    "name:eng_x_preferred":[
        "Khatara-pathar"
    ],
    "wof:name":"Khatara-pathar",
    "wof:placetype":"locality",
    "wof:population":95
},
  "geometry": {"coordinates":[91.830437,26.27997],"type":"Point"}
}