{
  "type": "Feature",
  "properties": {
    "iso:country":"IN",
    "ks:ks_name":"Madanpur",
    "ks:ks_pop":188,
    "ks:ks_type":"HABITATION",
    "name:eng_x_preferred":[
        "Madanpur"
    ],
    "wof:name":"Madanpur",
    "wof:placetype":"locality",
    "wof:population":188
},
  "geometry": {"coordinates":[81.86897399999999,26.197931],"type":"Point"}
}