{
  "type": "Feature",
  "properties": {
    "iso:country":"IN",
    "ks:ks_name":"Shindewasti-1",
    "ks:ks_pop":182,
    "ks:ks_type":"HABITATION",
    "name:eng_x_preferred":[
        "Shindewasti-1"
    ],
    "wof:name":"Shindewasti-1",
    "wof:placetype":"locality",
    "wof:population":182
},
  "geometry": {"coordinates":[74.400381,19.226369],"type":"Point"}
}