{
  "type": "Feature",
  "properties": {
    "iso:country":"IN",
    "ks:ks_name":"Jaggandoravalasa",
    "ks:ks_pop":23,
    "ks:ks_type":"HABITATION",
    "name:eng_x_preferred":[
        "Jaggandoravalasa"
    ],
    "wof:name":"Jaggandoravalasa",
    "wof:placetype":"locality",
    "wof:population":23
},
  "geometry": {"coordinates":[83.695796,18.86346],"type":"Point"}
}