{
  "type": "Feature",
  "properties": {
    "iso:country":"IN",
    "ks:ks_name":"Lohniya",
    "ks:ks_pop":109,
    "ks:ks_type":"HABITATION",
    "ks:ks_uagg_main":0,
    "name:eng_x_preferred":[
        "Lohniya"
    ],
    "wof:name":"Lohniya",
    "wof:placetype":"neighbourhood",
    "wof:population":109
},
  "geometry": {"coordinates":[81.174663,27.086179],"type":"Point"}
}