{
  "type": "Feature",
  "properties": {
    "gn:admin1_code":"35.0",
    "gn:admin2_code":"429.0",
    "gn:asciiname":"Chhatari",
    "gn:country_code":"IN",
    "gn:dem":396,
    "gn:feature_class":"P",
    "gn:feature_code":"PPL",
    "gn:name":"Chhatari",
    "gn:population":0,
    "gn:timezone":"Asia/Kolkata",
    "iso:country":"IN",
    "ks:ks_name":"Chhatari",
    "ks:ks_type":"VILLAGE",
    "name:bpy_x_preferred":[
        "\u099b\u09be\u09a4\u09be\u09b0\u09bf"
    ],
    "name:eng_x_preferred":[
        "Chhatari"
    ],
    "name:ita_x_preferred":[
        "Chhatari"
    ],
    "name:msa_x_preferred":[
        "Chhatari"
    ],
    "name:new_x_preferred":[
        "\u091b\u0924\u0930\u0940"
    ],
    "name:nld_x_preferred":[
        "Chhatari"
    ],
    "name:pol_x_preferred":[
        "Chhatari"
    ],
    "name:por_x_preferred":[
        "Chatari"
    ],
    "name:urd_x_preferred":[
        "\u0686\u06be\u062a\u0627\u0631\u06cc"
    ],
    "name:vie_x_preferred":[
        "Chhatari"
    ],
    "name:zho_x_preferred":[
        "\u6070\u5854\u91cc"
    ],
    "wof:name":"Chhatari",
    "wof:placetype":"locality"
},
  "geometry": {"coordinates":[81.000181,24.919564],"type":"Point"}
}