{
  "type": "Feature",
  "properties": {
    "iso:country":"IN",
    "ks:ks_name":"Athiyappagoundanvalasu",
    "ks:ks_pop":113,
    "ks:ks_type":"HABITATION",
    "ks:ks_uagg_main":0,
    "name:eng_x_preferred":[
        "Athiyappagoundanvalasu"
    ],
    "wof:name":"Athiyappagoundanvalasu",
    "wof:placetype":"neighbourhood",
    "wof:population":113
},
  "geometry": {"coordinates":[77.88653600000001,11.004408],"type":"Point"}
}