{
  "type": "Feature",
  "properties": {
    "iso:country":"IN",
    "ks:ks_name":"Chak Ballarpur",
    "ks:ks_pop":0,
    "ks:ks_type":"VILLAGE",
    "name:eng_x_preferred":[
        "Chak Ballarpur"
    ],
    "wof:name":"Chak Ballarpur",
    "wof:placetype":"locality",
    "wof:population":0
},
  "geometry": {"coordinates":[79.920445,20.342709],"type":"Point"}
}