{
  "type": "Feature",
  "properties": {
    "gn:admin1_code":"34.0",
    "gn:admin2_code":"222.0",
    "gn:asciiname":"Chak Sadat",
    "gn:country_code":"IN",
    "gn:dem":49,
    "gn:feature_class":"P",
    "gn:feature_code":"PPL",
    "gn:name":"Chak S\u0101d\u0101t",
    "gn:population":0,
    "gn:timezone":"Asia/Kolkata",
    "iso:country":"IN",
    "ks:ks_alt_nam":"Chak S\u0101d\u0101t",
    "ks:ks_name":"Chak Sadat",
    "ks:ks_type":"VILLAGE",
    "name:eng_x_preferred":[
        "Chak Sadat"
    ],
    "name:eng_x_variant":[
        "Chak S\u0101d\u0101t"
    ],
    "wof:name":"Chak Sadat",
    "wof:placetype":"locality"
},
  "geometry": {"coordinates":[85.95457500000001,25.552731],"type":"Point"}
}