{
  "type": "Feature",
  "properties": {
    "iso:country":"IN",
    "ks:ks_alt_nam":"DOKHAR PAR",
    "ks:ks_name":"Dokhar Par",
    "ks:ks_pop":1850,
    "ks:ks_type":"HABITATION",
    "name:eng_x_preferred":[
        "Dokhar Par"
    ],
    "wof:name":"Dokhar Par",
    "wof:placetype":"locality",
    "wof:population":1850
},
  "geometry": {"coordinates":[83.913134,25.797299],"type":"Point"}
}