{
  "type": "Feature",
  "properties": {
    "gn:admin1_code":"2.0",
    "gn:admin2_code":"554.0",
    "gn:asciiname":"Lokkunta",
    "gn:country_code":"IN",
    "gn:dem":750,
    "gn:feature_class":"P",
    "gn:feature_code":"PPL",
    "gn:name":"Lokkunta",
    "gn:population":0,
    "gn:timezone":"Asia/Kolkata",
    "iso:country":"IN",
    "wof:name":"Lokkunta",
    "wof:placetype":"locality"
},
  "geometry": {"coordinates":[78.5727,13.40009],"type":"Point"}
}