{
  "type": "Feature",
  "properties": {
    "iso:country":"IN",
    "ks:ks_name":"Takoli",
    "ks:ks_pop":39,
    "ks:ks_type":"VILLAGE",
    "name:eng_x_preferred":[
        "Takoli"
    ],
    "wof:name":"Takoli",
    "wof:placetype":"locality",
    "wof:population":39
},
  "geometry": {"coordinates":[80.05600699999999,29.682335],"type":"Point"}
}