{
  "type": "Feature",
  "properties": {
    "iso:country":"IN",
    "ks:ks_name":"Bararangrash South West",
    "ks:ks_pop":748,
    "ks:ks_type":"HABITATION",
    "name:eng_x_preferred":[
        "Bararangrash South West"
    ],
    "wof:name":"Bararangrash South West",
    "wof:placetype":"locality",
    "wof:population":748
},
  "geometry": {"coordinates":[89.495833,26.427787],"type":"Point"}
}