{
  "type": "Feature",
  "properties": {
    "gn:admin1_code":"33.0",
    "gn:admin2_code":"586",
    "gn:asciiname":"Calate",
    "gn:country_code":"IN",
    "gn:dem":18,
    "gn:feature_class":"P",
    "gn:feature_code":"PPL",
    "gn:name":"Calate",
    "gn:population":0,
    "gn:timezone":"Asia/Kolkata",
    "iso:country":"IN",
    "name:und_x_variant":[
        "Calata",
        "Calate"
    ],
    "wof:name":"Calate",
    "wof:placetype":"neighbourhood"
},
  "geometry": {"coordinates":[73.91822999999999,15.31106],"type":"Point"}
}