{
  "type": "Feature",
  "properties": {
    "iso:country":"IN",
    "ks:ks_name":"Koewa Pur",
    "ks:ks_pop":254,
    "ks:ks_type":"HABITATION",
    "name:eng_x_preferred":[
        "Koewa Pur"
    ],
    "wof:name":"Koewa Pur",
    "wof:placetype":"locality",
    "wof:population":254
},
  "geometry": {"coordinates":[81.9533,27.530067],"type":"Point"}
}