{
  "type": "Feature",
  "properties": {
    "iso:country":"IN",
    "ks:ks_name":"2 SRW",
    "ks:ks_pop":79,
    "ks:ks_type":"VILLAGE",
    "name:eng_x_preferred":[
        "2 SRW"
    ],
    "wof:name":"2 SRW",
    "wof:placetype":"locality",
    "wof:population":79
},
  "geometry": {"coordinates":[74.546898,29.582711],"type":"Point"}
}