{
  "type": "Feature",
  "properties": {
    "iso:country":"IN",
    "ks:ks_alt_nam":"padyewadi",
    "ks:ks_name":"Padyewadi",
    "ks:ks_pop":62,
    "ks:ks_type":"HABITATION",
    "name:eng_x_preferred":[
        "Padyewadi"
    ],
    "wof:name":"Padyewadi",
    "wof:placetype":"locality",
    "wof:population":62
},
  "geometry": {"coordinates":[73.48419199999999,17.261236],"type":"Point"}
}