{
  "type": "Feature",
  "properties": {
    "gn:admin1_code":"2",
    "gn:admin2_code":"544.0",
    "gn:asciiname":"Ranganiguda",
    "gn:country_code":"IN",
    "gn:dem":923,
    "gn:feature_class":"P",
    "gn:feature_code":"PPL",
    "gn:name":"Ranganig\u016bda",
    "gn:population":0,
    "gn:timezone":"Asia/Kolkata",
    "iso:country":"IN",
    "ks:ks_name":"Ranginiguda",
    "ks:ks_pop":143,
    "ks:ks_type":"VILLAGE",
    "name:eng_x_preferred":[
        "Ranginiguda"
    ],
    "name:eng_x_variant":[
        "Ranganiguda"
    ],
    "wof:name":"Ranginiguda",
    "wof:placetype":"locality",
    "wof:population":143
},
  "geometry": {"coordinates":[82.98794599999999,18.298057],"type":"Point"}
}