{
  "type": "Feature",
  "properties": {
    "gn:admin1_code":"36",
    "gn:admin2_code":"155.0",
    "gn:asciiname":"Karta",
    "gn:country_code":"IN",
    "gn:dem":137,
    "gn:feature_class":"P",
    "gn:feature_code":"PPL",
    "gn:name":"Karta",
    "gn:population":0,
    "gn:timezone":"Asia/Kolkata",
    "iso:country":"IN",
    "name:bos_x_preferred":[
        "Karta"
    ],
    "name:ceb_x_preferred":[
        "Karta"
    ],
    "name:ces_x_preferred":[
        "Karta"
    ],
    "name:epo_x_preferred":[
        "Karto"
    ],
    "name:heb_x_preferred":[
        "\u05e7\u05e8\u05ea\u05d0"
    ],
    "name:hrv_x_preferred":[
        "Karta"
    ],
    "name:ido_x_preferred":[
        "Karto"
    ],
    "name:nld_x_preferred":[
        "Karta"
    ],
    "name:pol_x_preferred":[
        "Karta"
    ],
    "name:que_x_preferred":[
        "Karta"
    ],
    "name:slk_x_preferred":[
        "Karta"
    ],
    "name:slv_x_preferred":[
        "Karta"
    ],
    "name:swe_x_preferred":[
        "Karta"
    ],
    "name:tgl_x_preferred":[
        "Karta"
    ],
    "wof:name":"Karta",
    "wof:placetype":"locality"
},
  "geometry": {"coordinates":[79.87164,27.28165],"type":"Point"}
}