{
  "type": "Feature",
  "properties": {
    "iso:country":"IN",
    "ks:ks_name":"Uchdeeh",
    "ks:ks_pop":515,
    "ks:ks_type":"HABITATION",
    "name:eng_x_preferred":[
        "Uchdeeh"
    ],
    "wof:name":"Uchdeeh",
    "wof:placetype":"locality",
    "wof:population":515
},
  "geometry": {"coordinates":[83.031342,27.410457],"type":"Point"}
}