{
  "type": "Feature",
  "properties": {
    "iso:country":"IN",
    "ks:ks_name":"Ali",
    "ks:ks_pop":684,
    "ks:ks_type":"VILLAGE",
    "name:eng_x_preferred":[
        "Ali"
    ],
    "wof:name":"Ali",
    "wof:placetype":"locality",
    "wof:population":684
},
  "geometry": {"coordinates":[74.5894,23.360389],"type":"Point"}
}