{
  "type": "Feature",
  "properties": {
    "iso:country":"IN",
    "ks:ks_name":"Taskeri",
    "ks:ks_pop":27,
    "ks:ks_type":"VILLAGE",
    "name:eng_x_preferred":[
        "Taskeri"
    ],
    "wof:name":"Taskeri",
    "wof:placetype":"locality",
    "wof:population":27
},
  "geometry": {"coordinates":[83.703042,19.512806],"type":"Point"}
}