{
  "type": "Feature",
  "properties": {
    "iso:country":"IN",
    "ks:ks_name":"Paikthuaguda",
    "ks:ks_pop":132,
    "ks:ks_type":"VILLAGE",
    "name:eng_x_preferred":[
        "Paikthuaguda"
    ],
    "wof:name":"Paikthuaguda",
    "wof:placetype":"locality",
    "wof:population":132
},
  "geometry": {"coordinates":[83.237978,19.594891],"type":"Point"}
}