{
  "type": "Feature",
  "properties": {
    "gn:admin1_code":"09",
    "gn:admin2_code":"478.0",
    "gn:asciiname":"Navibandar",
    "gn:country_code":"IN",
    "gn:dem":11,
    "gn:feature_class":"P",
    "gn:feature_code":"PPL",
    "gn:name":"Nav\u012bbandar",
    "gn:population":0,
    "gn:timezone":"Asia/Kolkata",
    "iso:country":"IN",
    "name:und_x_variant":[
        "Navabandar",
        "Nav\u012bbandar"
    ],
    "wof:name":"Navibandar",
    "wof:placetype":"locality"
},
  "geometry": {"coordinates":[69.78657,21.45078],"type":"Point"}
}