{
  "type": "Feature",
  "properties": {
    "gn:admin1_code":"19.0",
    "gn:admin2_code":"573.0",
    "gn:asciiname":"Nagendoddi",
    "gn:country_code":"IN",
    "gn:dem":656,
    "gn:feature_class":"P",
    "gn:feature_code":"PPL",
    "gn:name":"Nagendoddi",
    "gn:population":0,
    "gn:timezone":"Asia/Kolkata",
    "iso:country":"IN",
    "wof:name":"Nagendoddi",
    "wof:placetype":"locality"
},
  "geometry": {"coordinates":[77.01061,12.67686],"type":"Point"}
}