{
  "type": "Feature",
  "properties": {
    "iso:country":"IN",
    "ks:ks_name":"Jhiliya",
    "ks:ks_pop":56,
    "ks:ks_type":"HABITATION",
    "ks:ks_uagg_main":0,
    "name:eng_x_preferred":[
        "Jhiliya"
    ],
    "wof:name":"Jhiliya",
    "wof:placetype":"neighbourhood",
    "wof:population":56
},
  "geometry": {"coordinates":[81.60288199999999,27.328527],"type":"Point"}
}