{
  "type": "Feature",
  "properties": {
    "iso:country":"IN",
    "ks:ks_name":"Bhuvanapuram",
    "ks:ks_pop":66,
    "ks:ks_type":"HABITATION",
    "name:eng_x_preferred":[
        "Bhuvanapuram"
    ],
    "wof:name":"Bhuvanapuram",
    "wof:placetype":"locality",
    "wof:population":66
},
  "geometry": {"coordinates":[84.546791,19.01515],"type":"Point"}
}