{
  "type": "Feature",
  "properties": {
    "iso:country":"IN",
    "ks:ks_name":"Krupapadar",
    "ks:ks_pop":117,
    "ks:ks_type":"VILLAGE",
    "name:eng_x_preferred":[
        "Krupapadar"
    ],
    "wof:name":"Krupapadar",
    "wof:placetype":"locality",
    "wof:population":117
},
  "geometry": {"coordinates":[83.413956,20.073716],"type":"Point"}
}