{
  "type": "Feature",
  "properties": {
    "iso:country":"IN",
    "ks:ks_name":"Husainpur",
    "ks:ks_pop":3,
    "ks:ks_type":"VILLAGE",
    "name:eng_x_preferred":[
        "Husainpur"
    ],
    "wof:name":"Husainpur",
    "wof:placetype":"locality",
    "wof:population":3
},
  "geometry": {"coordinates":[79.541842,28.017008],"type":"Point"}
}