{
  "type": "Feature",
  "properties": {
    "iso:country":"IN",
    "ks:ks_name":"Bhithhuk Purwa",
    "ks:ks_pop":252,
    "ks:ks_type":"HABITATION",
    "name:eng_x_preferred":[
        "Bhithhuk Purwa"
    ],
    "wof:name":"Bhithhuk Purwa",
    "wof:placetype":"locality",
    "wof:population":252
},
  "geometry": {"coordinates":[82.140129,26.966383],"type":"Point"}
}