{
  "type": "Feature",
  "properties": {
    "iso:country":"IN",
    "ks:ks_name":"Mushahar Tole East",
    "ks:ks_pop":766,
    "ks:ks_type":"HABITATION",
    "name:eng_x_preferred":[
        "Mushahar Tole East"
    ],
    "wof:name":"Mushahar Tole East",
    "wof:placetype":"locality",
    "wof:population":766
},
  "geometry": {"coordinates":[84.59296399999999,26.121427],"type":"Point"}
}