{
  "type": "Feature",
  "properties": {
    "gn:admin1_code":"39.0",
    "gn:admin2_code":"64.0",
    "gn:asciiname":"Bankot",
    "gn:country_code":"IN",
    "gn:dem":1060,
    "gn:feature_class":"P",
    "gn:feature_code":"PPL",
    "gn:name":"Bankot",
    "gn:population":0,
    "gn:timezone":"Asia/Kolkata",
    "iso:country":"IN",
    "ks:ks_name":"Ban Kota",
    "ks:ks_pop":378,
    "ks:ks_type":"VILLAGE",
    "name:cat_x_preferred":[
        "Bankot"
    ],
    "name:eng_x_preferred":[
        "Ban Kota"
    ],
    "name:eng_x_variant":[
        "Bankot"
    ],
    "name:mar_x_preferred":[
        "\u092c\u093e\u0923\u0915\u094b\u091f"
    ],
    "name:urd_x_preferred":[
        "\u0628\u0646\u06a9\u0648\u0679"
    ],
    "wof:name":"Ban Kota",
    "wof:placetype":"locality",
    "wof:population":378
},
  "geometry": {"coordinates":[79.246174,29.57676],"type":"Point"}
}