{
  "type": "Feature",
  "properties": {
    "iso:country":"IN",
    "ks:ks_name":"Rojibeg",
    "ks:ks_pop":155,
    "ks:ks_type":"HABITATION",
    "name:eng_x_preferred":[
        "Rojibeg"
    ],
    "wof:name":"Rojibeg",
    "wof:placetype":"locality",
    "wof:population":155
},
  "geometry": {"coordinates":[77.342545,23.382898],"type":"Point"}
}