{
  "type": "Feature",
  "properties": {
    "iso:country":"IN",
    "ks:ks_alt_nam":"Ku\u0101jharan",
    "ks:ks_name":"Kuajharan",
    "ks:ks_pop":241,
    "ks:ks_type":"VILLAGE",
    "name:eng_x_preferred":[
        "Kuajharan"
    ],
    "name:eng_x_variant":[
        "Ku\u0101jharan"
    ],
    "wof:name":"Kuajharan",
    "wof:placetype":"locality",
    "wof:population":241
},
  "geometry": {"coordinates":[85.730334,21.404074],"type":"Point"}
}