{
  "type": "Feature",
  "properties": {
    "iso:country":"IN",
    "ks:ks_alt_nam":"MATAKARIMALA",
    "ks:ks_name":"Matakarimala",
    "ks:ks_pop":150,
    "ks:ks_type":"HABITATION",
    "ks:ks_uagg_main":0,
    "name:eng_x_preferred":[
        "Matakarimala"
    ],
    "wof:name":"Matakarimala",
    "wof:placetype":"neighbourhood",
    "wof:population":150
},
  "geometry": {"coordinates":[74.255315,17.177043],"type":"Point"}
}