{
  "type": "Feature",
  "properties": {
    "iso:country":"IN",
    "ks:ks_name":"Chhota Nimgacchi",
    "ks:ks_pop":0,
    "ks:ks_type":"VILLAGE",
    "name:eng_x_preferred":[
        "Chhota Nimgacchi"
    ],
    "wof:name":"Chhota Nimgacchi",
    "wof:placetype":"locality",
    "wof:population":0
},
  "geometry": {"coordinates":[87.751182,24.976863],"type":"Point"}
}