{
  "type": "Feature",
  "properties": {
    "iso:country":"IN",
    "ks:ks_name":"Ibrahimabad",
    "ks:ks_pop":0,
    "ks:ks_type":"VILLAGE",
    "name:eng_x_preferred":[
        "Ibrahimabad"
    ],
    "wof:name":"Ibrahimabad",
    "wof:placetype":"locality",
    "wof:population":0
},
  "geometry": {"coordinates":[81.432215,25.469518],"type":"Point"}
}