{
  "type": "Feature",
  "properties": {
    "gn:admin1_code":"19.0",
    "gn:admin2_code":"566.0",
    "gn:asciiname":"Heruru",
    "gn:country_code":"IN",
    "gn:dem":506,
    "gn:feature_class":"P",
    "gn:feature_code":"PPL",
    "gn:name":"Heruru",
    "gn:population":0,
    "gn:timezone":"Asia/Kolkata",
    "iso:country":"IN",
    "wof:name":"Heruru",
    "wof:placetype":"locality"
},
  "geometry": {"coordinates":[76.77108,14.81098],"type":"Point"}
}