{
  "type": "Feature",
  "properties": {
    "iso:country":"IN",
    "ks:ks_name":"Podiadamodarpalli",
    "ks:ks_pop":36,
    "ks:ks_type":"VILLAGE",
    "ks:ks_uagg_main":0,
    "name:eng_x_preferred":[
        "Podiadamodarpalli"
    ],
    "wof:name":"Podiadamodarpalli",
    "wof:placetype":"neighbourhood",
    "wof:population":36
},
  "geometry": {"coordinates":[84.652896,19.596617],"type":"Point"}
}