{
  "type": "Feature",
  "properties": {
    "gn:admin1_code":"10",
    "gn:admin2_code":"69.0",
    "gn:asciiname":"Surajpur",
    "gn:country_code":"IN",
    "gn:dem":498,
    "gn:feature_class":"P",
    "gn:feature_code":"PPL",
    "gn:name":"Surajpur",
    "gn:population":0,
    "gn:timezone":"Asia/Kolkata",
    "iso:country":"IN",
    "name:ara_x_preferred":[
        "\u0633\u0648\u0631\u0627\u062c \u0628\u0648\u0631"
    ],
    "name:ara_x_variant":[
        "\u0633\u0627\u0631\u062c \u0628\u0648\u0631"
    ],
    "name:ben_bn_x_preferred":[
        "\u09b8\u09c1\u09b0\u099c\u09aa\u09c1\u09b0"
    ],
    "name:ben_in_x_preferred":[
        "\u09b8\u09c1\u09b0\u099c\u09aa\u09c1\u09b0"
    ],
    "name:ben_x_preferred":[
        "\u09b8\u09c1\u09b0\u099c\u09aa\u09c1\u09b0"
    ],
    "name:bpy_x_preferred":[
        "\u09b8\u09c1\u09b0\u099c\u09aa\u09c1\u09b0"
    ],
    "name:ceb_x_preferred":[
        "Surajpur"
    ],
    "name:fra_x_preferred":[
        "Surajpur"
    ],
    "name:guj_x_preferred":[
        "\u0ab8\u0ac1\u0ab0\u0a9c\u0aaa\u0ac1\u0ab0"
    ],
    "name:hin_x_preferred":[
        "\u0938\u0942\u0930\u091c\u092a\u0941\u0930"
    ],
    "name:ita_x_preferred":[
        "Surajpur"
    ],
    "name:kan_x_preferred":[
        "\u0cb8\u0cc2\u0cb0\u0c9c\u0ccd"
    ],
    "name:mal_x_preferred":[
        "\u0d38\u0d42\u0d30\u0d1c\u0d4d\u0d2a\u0d42\u0d7c"
    ],
    "name:mar_x_preferred":[
        "\u0938\u0942\u0930\u091c\u092a\u0941\u0930"
    ],
    "name:mlg_x_preferred":[
        "Surajpur"
    ],
    "name:msa_x_preferred":[
        "Surajpur"
    ],
    "name:nld_x_preferred":[
        "Surajpur"
    ],
    "name:pan_x_preferred":[
        "\u0a38\u0a42\u0a30\u0a1c\u0a2a\u0a41\u0a30"
    ],
    "name:swe_x_preferred":[
        "Surajpur"
    ],
    "name:tam_x_preferred":[
        "\u0b9a\u0bc1\u0bb0\u0bbe\u0b9c\u0bcd\u0baa\u0bc2\u0bb0\u0bcd"
    ],
    "name:tel_x_preferred":[
        "\u0c38\u0c42\u0c30\u0c1c\u0c4d"
    ],
    "name:tgl_x_preferred":[
        "Surajpur"
    ],
    "name:tur_x_preferred":[
        "Surajpur"
    ],
    "name:urd_x_preferred":[
        "\u0633\u0648\u0631\u062c \u067e\u0648\u0631"
    ],
    "name:vie_x_preferred":[
        "Surajpur"
    ],
    "name:zho_x_preferred":[
        "\u82cf\u62c9\u6770\u666e\u5c14"
    ],
    "wof:name":"Surajpur",
    "wof:placetype":"locality"
},
  "geometry": {"coordinates":[76.89986999999998,30.7876],"type":"Point"}
}