{
  "type": "Feature",
  "properties": {
    "iso:country":"IN",
    "ks:ks_alt_nam":"Tikariya ryt padariya",
    "ks:ks_name":"Tikariya Ryt Padariya",
    "ks:ks_pop":516,
    "ks:ks_type":"HABITATION",
    "name:eng_x_preferred":[
        "Tikariya Ryt Padariya"
    ],
    "wof:name":"Tikariya Ryt Padariya",
    "wof:placetype":"locality",
    "wof:population":516
},
  "geometry": {"coordinates":[81.09334200000001,22.824449],"type":"Point"}
}