{
  "type": "Feature",
  "properties": {
    "iso:country":"IN",
    "ks:ks_name":"Kadokotha",
    "ks:ks_pop":474,
    "ks:ks_type":"VILLAGE",
    "name:eng_x_preferred":[
        "Kadokotha"
    ],
    "wof:name":"Kadokotha",
    "wof:placetype":"locality",
    "wof:population":474
},
  "geometry": {"coordinates":[86.992378,22.043254],"type":"Point"}
}