{
  "type": "Feature",
  "properties": {
    "iso:country":"IN",
    "ks:ks_alt_nam":"Bardhan supa",
    "ks:ks_name":"Bardhan Supa",
    "ks:ks_pop":253,
    "ks:ks_type":"HABITATION",
    "name:eng_x_preferred":[
        "Bardhan Supa"
    ],
    "wof:name":"Bardhan Supa",
    "wof:placetype":"locality",
    "wof:population":253
},
  "geometry": {"coordinates":[91.626411,26.737547],"type":"Point"}
}