{
  "type": "Feature",
  "properties": {
    "gn:admin1_code":"36.0",
    "gn:admin2_code":"157.0",
    "gn:asciiname":"Nawa Khera",
    "gn:country_code":"IN",
    "gn:dem":124,
    "gn:feature_class":"P",
    "gn:feature_code":"PPL",
    "gn:name":"Nawa Khera",
    "gn:population":0,
    "gn:timezone":"Asia/Kolkata",
    "iso:country":"IN",
    "wof:name":"Nawa Khera",
    "wof:placetype":"locality"
},
  "geometry": {"coordinates":[80.89454000000001,27.03094],"type":"Point"}
}