{
  "type": "Feature",
  "properties": {
    "iso:country":"IN",
    "ks:ks_name":"Rahimpura",
    "ks:ks_pop":1133,
    "ks:ks_type":"HABITATION",
    "name:eng_x_preferred":[
        "Rahimpura"
    ],
    "wof:name":"Rahimpura",
    "wof:placetype":"locality",
    "wof:population":1133
},
  "geometry": {"coordinates":[72.623458,27.198578],"type":"Point"}
}