{
  "type": "Feature",
  "properties": {
    "iso:country":"IN",
    "ks:ks_name":"Maliphala",
    "ks:ks_pop":1895,
    "ks:ks_type":"HABITATION",
    "name:eng_x_preferred":[
        "Maliphala"
    ],
    "wof:name":"Maliphala",
    "wof:placetype":"locality",
    "wof:population":1895
},
  "geometry": {"coordinates":[73.457342,23.899469],"type":"Point"}
}