{
  "type": "Feature",
  "properties": {
    "iso:country":"IN",
    "ks:ks_name":"Hanumanpura",
    "ks:ks_pop":425,
    "ks:ks_type":"HABITATION",
    "name:eng_x_preferred":[
        "Hanumanpura"
    ],
    "wof:name":"Hanumanpura",
    "wof:placetype":"locality",
    "wof:population":425
},
  "geometry": {"coordinates":[79.150109,26.330455],"type":"Point"}
}