{
  "type": "Feature",
  "properties": {
    "iso:country":"IN",
    "ks:ks_name":"Sandalpur",
    "ks:ks_pop":439,
    "ks:ks_type":"VILLAGE",
    "name:eng_x_preferred":[
        "Sandalpur"
    ],
    "wof:name":"Sandalpur",
    "wof:placetype":"locality",
    "wof:population":439
},
  "geometry": {"coordinates":[87.619901,25.711525],"type":"Point"}
}