{
  "type": "Feature",
  "properties": {
    "gn:admin1_code":"13.0",
    "gn:admin2_code":"595.0",
    "gn:asciiname":"Cherai",
    "gn:country_code":"IN",
    "gn:dem":1,
    "gn:feature_class":"P",
    "gn:feature_code":"PPL",
    "gn:name":"Cherai",
    "gn:population":0,
    "gn:timezone":"Asia/Kolkata",
    "iso:country":"IN",
    "name:fra_x_preferred":[
        "Cherai"
    ],
    "name:mal_x_preferred":[
        "\u0d1a\u0d46\u0d31\u0d3e\u0d2f\u0d3f"
    ],
    "wof:name":"Cherai",
    "wof:placetype":"locality"
},
  "geometry": {"coordinates":[76.27,9.977],"type":"Point"}
}