{
  "type": "Feature",
  "properties": {
    "iso:country":"IN",
    "ks:ks_name":"Kambaguda",
    "ks:ks_pop":665,
    "ks:ks_type":"VILLAGE",
    "name:eng_x_preferred":[
        "Kambaguda"
    ],
    "wof:name":"Kambaguda",
    "wof:placetype":"locality",
    "wof:population":665
},
  "geometry": {"coordinates":[84.439807,20.225049],"type":"Point"}
}