{
  "type": "Feature",
  "properties": {
    "iso:country":"IN",
    "name:ast_x_preferred":[
        "Aiahole"
    ],
    "name:eng_x_preferred":[
        "Aiahole"
    ],
    "name:fas_x_preferred":[
        "\u0627\u06cc\u0627\u0647\u0648\u0644"
    ],
    "name:nld_x_preferred":[
        "Aiahole"
    ],
    "name:vie_x_preferred":[
        "Aiahole"
    ],
    "qs:name":"Aiahole",
    "qs:name_adm0":"India",
    "qs:name_adm1":"Karnataka",
    "qs:photos":286,
    "qs:photos_1k":58,
    "qs:photos_9k":1,
    "qs:photos_9r":4,
    "qs:photos_all":286,
    "qs:photos_sr":5,
    "qs:placetype":"Town",
    "qs:pop_sr":"0",
    "wd:wordcount":63,
    "wof:name":"Aiahole",
    "wof:placetype":"locality"
},
  "geometry": {"coordinates":[75.87965,16.022633],"type":"Point"}
}