{
  "type": "Feature",
  "properties": {
    "gn:country":"IN",
    "gn:fcode":"PPL",
    "gn:population":0,
    "iso:country":"IN",
    "name:ara_x_preferred":[
        "\u0645\u0627\u062b\u0648\u062f\u0647"
    ],
    "name:ben_bn_x_preferred":[
        "\u09ae\u09a0\u0993\u09df\u09be\u09a1\u09be"
    ],
    "name:ben_in_x_preferred":[
        "\u09ae\u09a0\u0993\u09df\u09be\u09a1\u09be"
    ],
    "name:guj_x_preferred":[
        "\u0aae\u0aa5\u0ab5\u0abe\u0aa1\u0abe"
    ],
    "name:hin_x_preferred":[
        "\u092e\u0925\u0935\u093e\u095c\u093e"
    ],
    "name:kan_x_preferred":[
        "\u0cae\u0ca0\u0cb5\u0cbe\u0ca1"
    ],
    "name:mal_x_preferred":[
        "\u0d2e\u0d3e\u0d24\u0d4d\u0d35\u0d3e\u0d21"
    ],
    "name:mar_x_preferred":[
        "\u092e\u0920\u0935\u093e\u0921\u093e"
    ],
    "name:pan_x_preferred":[
        "\u0a2e\u0a25\u0a35\u0a3e\u0a5c\u0a3e"
    ],
    "name:tam_x_preferred":[
        "\u0bae\u0ba4\u0bcd\u0bb5\u0bbe\u0b9f\u0bbe"
    ],
    "name:tel_x_preferred":[
        "\u0c2e\u0c20\u0c4d"
    ],
    "name:und_x_variant":[
        "Matwada"
    ],
    "name:urd_x_preferred":[
        "\u0645\u062a\u06be\u0648\u0627\u0688\u0627"
    ],
    "qs:name":"Mathwada",
    "qs:name_adm0":"India",
    "qs:name_adm1":"Andhra Pradesh",
    "qs:photos":5,
    "qs:photos_1k":1,
    "qs:photos_9k":1,
    "qs:photos_9r":1,
    "qs:photos_all":5,
    "qs:photos_sr":1,
    "qs:placetype":"Suburb",
    "qs:pop_sr":"7",
    "wof:name":"Mathwada",
    "wof:placetype":"neighbourhood",
    "wof:population":0
},
  "geometry": {"coordinates":[79.60087,17.98362],"type":"Point"}
}