{
  "type": "Feature",
  "properties": {
    "gn:country":"IN",
    "gn:fcode":"PPL",
    "gn:population":0,
    "iso:country":"IN",
    "name:und_x_variant":[
        "Matwada"
    ],
    "qs:name":"Mathwada",
    "qs:name_adm0":"India",
    "qs:name_adm1":"Andhra Pradesh",
    "qs:photos":5,
    "qs:photos_1k":1,
    "qs:photos_9k":1,
    "qs:photos_9r":1,
    "qs:photos_all":5,
    "qs:photos_sr":1,
    "qs:placetype":"Suburb",
    "qs:pop_sr":"7",
    "wof:name":"Mathwada",
    "wof:placetype":"neighbourhood",
    "wof:population":0
},
  "geometry": {"coordinates":[79.60087,17.98362],"type":"Point"}
}