{
  "type": "Feature",
  "properties": {
    "iso:country":"IN",
    "ks:ks_name":"Salapatty",
    "ks:ks_pop":117,
    "ks:ks_type":"HABITATION",
    "name:eng_x_preferred":[
        "Salapatty"
    ],
    "wof:name":"Salapatty",
    "wof:placetype":"locality",
    "wof:population":117
},
  "geometry": {"coordinates":[78.21317500000001,11.025285],"type":"Point"}
}