{
  "type": "Feature",
  "properties": {
    "iso:country":"IN",
    "ks:ks_name":"Kucholi",
    "ks:ks_pop":686,
    "ks:ks_type":"VILLAGE",
    "name:eng_x_preferred":[
        "Kucholi"
    ],
    "wof:name":"Kucholi",
    "wof:placetype":"locality",
    "wof:population":686
},
  "geometry": {"coordinates":[79.09981500000001,30.104184],"type":"Point"}
}