{
  "type": "Feature",
  "properties": {
    "gn:admin1_code":"21",
    "gn:admin2_code":"394.0",
    "gn:asciiname":"Nawagaon",
    "gn:country_code":"IN",
    "gn:dem":302,
    "gn:feature_class":"P",
    "gn:feature_code":"PPL",
    "gn:name":"Naw\u0101gaon",
    "gn:population":0,
    "gn:timezone":"Asia/Kolkata",
    "iso:country":"IN",
    "wof:name":"Nawagaon",
    "wof:placetype":"locality"
},
  "geometry": {"coordinates":[82.6947,20.6054],"type":"Point"}
}