{
  "type": "Feature",
  "properties": {
    "iso:country":"IN",
    "ks:ks_name":"Khaspara Budhakasa",
    "ks:ks_pop":609,
    "ks:ks_type":"HABITATION",
    "name:eng_x_preferred":[
        "Khaspara Budhakasa"
    ],
    "wof:name":"Khaspara Budhakasa",
    "wof:placetype":"locality",
    "wof:population":609
},
  "geometry": {"coordinates":[81.57722800000001,19.378961],"type":"Point"}
}