{
  "type": "Feature",
  "properties": {
    "gn:admin1_code":"11.0",
    "gn:admin2_code":"33.0",
    "gn:asciiname":"Ghat",
    "gn:country_code":"IN",
    "gn:dem":1604,
    "gn:feature_class":"P",
    "gn:feature_code":"PPL",
    "gn:name":"Gh\u0101t",
    "gn:population":0,
    "gn:timezone":"Asia/Kolkata",
    "iso:country":"IN",
    "name:afr_x_preferred":[
        "Ghat"
    ],
    "name:ara_x_preferred":[
        "\u063a\u0627\u062a"
    ],
    "name:bih_x_preferred":[
        "\u0918\u093e\u091f"
    ],
    "name:deu_x_preferred":[
        "Ghat"
    ],
    "name:fra_x_preferred":[
        "Ghat"
    ],
    "name:heb_x_preferred":[
        "\u05d2\u05d4\u05d0\u05d8"
    ],
    "name:hin_x_preferred":[
        "\u0918\u093e\u091f"
    ],
    "name:hun_x_preferred":[
        "Gh\u00e1tok"
    ],
    "name:ita_x_preferred":[
        "Ghat"
    ],
    "name:jpn_x_preferred":[
        "\u30ac\u30fc\u30c8"
    ],
    "name:kan_x_preferred":[
        "\u0cb8\u0ccd\u0ca8\u0cbe\u0ca8\u0c98\u0c9f\u0ccd\u0c9f"
    ],
    "name:kor_x_preferred":[
        "\uac00\ud2b8"
    ],
    "name:lit_x_preferred":[
        "Ghatas"
    ],
    "name:pol_x_preferred":[
        "Ghaty"
    ],
    "name:rus_x_preferred":[
        "\u0413\u0445\u0430\u0442"
    ],
    "name:spa_x_preferred":[
        "Ghat"
    ],
    "name:sqi_x_preferred":[
        "Ghatet"
    ],
    "name:swe_x_preferred":[
        "Ghats"
    ],
    "name:tam_x_preferred":[
        "\u0baa\u0b9f\u0bbf\u0ba4\u0bcd\u0ba4\u0bc1\u0bb1\u0bc8"
    ],
    "name:tel_x_preferred":[
        "\u0c18\u0c3e\u0c1f\u0c4d"
    ],
    "name:ukr_x_preferred":[
        "\u0490\u0433\u0430\u0442"
    ],
    "wof:name":"Ghat",
    "wof:placetype":"locality"
},
  "geometry": {"coordinates":[77.62231,31.34800000000001],"type":"Point"}
}