{
  "type": "Feature",
  "properties": {
    "iso:country":"IN",
    "ks:ks_name":"Purba Amtalia",
    "ks:ks_pop":1670,
    "ks:ks_type":"VILLAGE",
    "name:eng_x_preferred":[
        "Purba Amtalia"
    ],
    "wof:name":"Purba Amtalia",
    "wof:placetype":"locality",
    "wof:population":1670
},
  "geometry": {"coordinates":[87.861875,21.842061],"type":"Point"}
}