{
  "type": "Feature",
  "properties": {
    "gn:admin1_code":"19.0",
    "gn:admin2_code":"575.0",
    "gn:asciiname":"Pattaje",
    "gn:country_code":"IN",
    "gn:dem":137,
    "gn:feature_class":"P",
    "gn:feature_code":"PPL",
    "gn:name":"Pattaje",
    "gn:population":0,
    "gn:timezone":"Asia/Kolkata",
    "iso:country":"IN",
    "ks:ks_name":"Pathaje",
    "ks:ks_pop":260,
    "ks:ks_type":"HABITATION",
    "name:eng_x_preferred":[
        "Pathaje"
    ],
    "name:eng_x_variant":[
        "Pattaje"
    ],
    "wof:name":"Pathaje",
    "wof:placetype":"locality",
    "wof:population":260
},
  "geometry": {"coordinates":[75.55632799999999,12.73432],"type":"Point"}
}