{
  "type": "Feature",
  "properties": {
    "iso:country":"IN",
    "ks:ks_name":"Ameli Reserved Forest",
    "ks:ks_type":"VILLAGE",
    "name:eng_x_preferred":[
        "Ameli Reserved Forest"
    ],
    "wof:name":"Ameli Reserved Forest",
    "wof:placetype":"locality"
},
  "geometry": {"coordinates":[79.009496,29.938741],"type":"Point"}
}