{
  "type": "Feature",
  "properties": {
    "iso:country":"IN",
    "ks:ks_name":"Chindadevi",
    "ks:ks_pop":150,
    "ks:ks_type":"HABITATION",
    "name:eng_x_preferred":[
        "Chindadevi"
    ],
    "wof:name":"Chindadevi",
    "wof:placetype":"locality",
    "wof:population":150
},
  "geometry": {"coordinates":[74.718718,17.875051],"type":"Point"}
}