{
  "type": "Feature",
  "properties": {
    "iso:country":"IN",
    "ks:ks_name":"Koroda",
    "ks:ks_pop":187,
    "ks:ks_type":"VILLAGE",
    "name:eng_x_preferred":[
        "Koroda"
    ],
    "wof:name":"Koroda",
    "wof:placetype":"locality",
    "wof:population":187
},
  "geometry": {"coordinates":[83.64509099999999,19.266478],"type":"Point"}
}