{
  "type": "Feature",
  "properties": {
    "gn:admin1_code":"19.0",
    "gn:admin2_code":"566.0",
    "gn:asciiname":"Hindedevarahatti",
    "gn:country_code":"IN",
    "gn:dem":664,
    "gn:feature_class":"P",
    "gn:feature_code":"PPL",
    "gn:name":"Hindedevarahatti",
    "gn:population":0,
    "gn:timezone":"Asia/Kolkata",
    "iso:country":"IN",
    "wof:name":"Hindedevarahatti",
    "wof:placetype":"locality"
},
  "geometry": {"coordinates":[76.44303000000002,13.80984],"type":"Point"}
}