{
  "type": "Feature",
  "properties": {
    "gn:admin1_code":"19.0",
    "gn:admin2_code":"566.0",
    "gn:asciiname":"Hindedevarahatti",
    "gn:country_code":"IN",
    "gn:dem":664,
    "gn:feature_class":"P",
    "gn:feature_code":"PPL",
    "gn:name":"Hindedevarahatti",
    "gn:population":0,
    "gn:timezone":"Asia/Kolkata",
    "iso:country":"IN",
    "ks:ks_name":"Indedevarahatty",
    "ks:ks_pop":236,
    "ks:ks_type":"HABITATION",
    "name:eng_x_preferred":[
        "Indedevarahatty"
    ],
    "name:eng_x_variant":[
        "Hindedevarahatti"
    ],
    "wof:name":"Indedevarahatty",
    "wof:placetype":"locality",
    "wof:population":236
},
  "geometry": {"coordinates":[76.44216,13.80989],"type":"Point"}
}