{
  "type": "Feature",
  "properties": {
    "gn:admin1_code":"23",
    "gn:admin2_code":"51.0",
    "gn:asciiname":"Lakher",
    "gn:country_code":"IN",
    "gn:dem":357,
    "gn:feature_class":"P",
    "gn:feature_code":"PPL",
    "gn:name":"Lakher",
    "gn:population":0,
    "gn:timezone":"Asia/Kolkata",
    "iso:country":"IN",
    "wof:name":"Lakher",
    "wof:placetype":"locality"
},
  "geometry": {"coordinates":[76.55974000000001,31.24173],"type":"Point"}
}