{
  "type": "Feature",
  "properties": {
    "gn:admin1_code":"35",
    "gn:admin2_code":"443.0",
    "gn:asciiname":"Koluwa",
    "gn:country_code":"IN",
    "gn:dem":479,
    "gn:feature_class":"P",
    "gn:feature_code":"PPL",
    "gn:name":"Koluwa",
    "gn:population":0,
    "gn:timezone":"Asia/Kolkata",
    "iso:country":"IN",
    "wof:name":"Koluwa",
    "wof:placetype":"locality"
},
  "geometry": {"coordinates":[78.19535999999999,23.56707],"type":"Point"}
}