{
  "type": "Feature",
  "properties": {
    "gn:admin1_code":"16.0",
    "gn:admin2_code":"517",
    "gn:asciiname":"Chikaldongri",
    "gn:country_code":"IN",
    "gn:dem":5,
    "gn:feature_class":"P",
    "gn:feature_code":"PPL",
    "gn:name":"Chikaldongri",
    "gn:population":0,
    "gn:timezone":"Asia/Kolkata",
    "iso:country":"IN",
    "wof:name":"Chikaldongri",
    "wof:placetype":"locality"
},
  "geometry": {"coordinates":[72.78585,19.48045],"type":"Point"}
}