{
  "type": "Feature",
  "properties": {
    "iso:country":"IN",
    "ks:ks_name":"Beela Kheda",
    "ks:ks_pop":491,
    "ks:ks_type":"VILLAGE",
    "name:eng_x_preferred":[
        "Beela Kheda"
    ],
    "wof:name":"Beela Kheda",
    "wof:placetype":"locality",
    "wof:population":491
},
  "geometry": {"coordinates":[77.24769000000001,22.876008],"type":"Point"}
}