{
  "type": "Feature",
  "properties": {
    "iso:country":"IN",
    "ks:ks_name":"Oddekandriga",
    "ks:ks_pop":82,
    "ks:ks_type":"HABITATION",
    "name:eng_x_preferred":[
        "Oddekandriga"
    ],
    "wof:name":"Oddekandriga",
    "wof:placetype":"locality",
    "wof:population":82
},
  "geometry": {"coordinates":[79.33508999999999,13.235313],"type":"Point"}
}