{
  "type": "Feature",
  "properties": {
    "gn:admin1_code":"19.0",
    "gn:admin2_code":"567.0",
    "gn:asciiname":"Gopanhal",
    "gn:country_code":"IN",
    "gn:dem":717,
    "gn:feature_class":"P",
    "gn:feature_code":"PPL",
    "gn:name":"Gopanh\u0101l",
    "gn:population":0,
    "gn:timezone":"Asia/Kolkata",
    "iso:country":"IN",
    "ks:ks_alt_nam":"Gopanh\u0101l",
    "ks:ks_name":"Gopanhal",
    "ks:ks_pop":338,
    "ks:ks_type":"VILLAGE",
    "name:eng_x_preferred":[
        "Gopanhal"
    ],
    "name:eng_x_variant":[
        "Gopanh\u0101l"
    ],
    "wof:name":"Gopanhal",
    "wof:placetype":"locality",
    "wof:population":338
},
  "geometry": {"coordinates":[75.86670599999999,13.983646],"type":"Point"}
}