{
  "type": "Feature",
  "properties": {
    "iso:country":"IN",
    "ks:ks_name":"Raut Chak",
    "ks:ks_pop":462,
    "ks:ks_type":"VILLAGE",
    "name:eng_x_preferred":[
        "Raut Chak"
    ],
    "wof:name":"Raut Chak",
    "wof:placetype":"locality",
    "wof:population":462
},
  "geometry": {"coordinates":[87.49861900000001,22.298786],"type":"Point"}
}