{
  "type": "Feature",
  "properties": {
    "gn:admin1_code":"34.0",
    "gn:admin2_code":"203.0",
    "gn:asciiname":"Phulwariya",
    "gn:country_code":"IN",
    "gn:dem":108,
    "gn:feature_class":"P",
    "gn:feature_code":"PPL",
    "gn:name":"Phulwariy\u0101",
    "gn:population":0,
    "gn:timezone":"Asia/Kolkata",
    "iso:country":"IN",
    "ks:ks_name":"Phulwariya",
    "ks:ks_pop":872,
    "ks:ks_type":"HABITATION",
    "name:eng_x_preferred":[
        "Phulwariya"
    ],
    "wof:name":"Phulwariya",
    "wof:placetype":"locality",
    "wof:population":872
},
  "geometry": {"coordinates":[84.374703,27.223785],"type":"Point"}
}