{
  "type": "Feature",
  "properties": {
    "gn:admin1_code":"25.0",
    "gn:admin2_code":"606.0",
    "gn:asciiname":"Kumarakudi",
    "gn:country_code":"IN",
    "gn:dem":151,
    "gn:feature_class":"P",
    "gn:feature_code":"PPL",
    "gn:name":"Kum\u0101rakudi",
    "gn:population":0,
    "gn:timezone":"Asia/Kolkata",
    "iso:country":"IN",
    "ks:ks_alt_nam":"Kum\u0101rakudi",
    "ks:ks_name":"Kumarakudi",
    "ks:ks_type":"VILLAGE",
    "ks:ks_uagg_main":0,
    "name:eng_x_preferred":[
        "Kumarakudi"
    ],
    "name:eng_x_variant":[
        "Kum\u0101rakudi"
    ],
    "wof:name":"Kumarakudi",
    "wof:placetype":"neighbourhood"
},
  "geometry": {"coordinates":[79.13401,12.220799],"type":"Point"}
}