{
  "type": "Feature",
  "properties": {
    "iso:country":"IN",
    "ks:ks_name":"Checharia Kalan",
    "ks:ks_pop":24,
    "ks:ks_type":"VILLAGE",
    "name:eng_x_preferred":[
        "Checharia Kalan"
    ],
    "wof:name":"Checharia Kalan",
    "wof:placetype":"locality",
    "wof:population":24
},
  "geometry": {"coordinates":[83.841734,24.422104],"type":"Point"}
}