{
  "type": "Feature",
  "properties": {
    "iso:country":"IN",
    "ks:ks_name":"Western Mushari",
    "ks:ks_pop":415,
    "ks:ks_type":"HABITATION",
    "name:eng_x_preferred":[
        "Western Mushari"
    ],
    "wof:name":"Western Mushari",
    "wof:placetype":"locality",
    "wof:population":415
},
  "geometry": {"coordinates":[86.271889,26.056932],"type":"Point"}
}