{
  "type": "Feature",
  "properties": {
    "gn:admin1_code":"11",
    "gn:admin2_code":"23.0",
    "gn:asciiname":"Andwas",
    "gn:country_code":"IN",
    "gn:dem":2263,
    "gn:feature_class":"P",
    "gn:feature_code":"PPL",
    "gn:name":"Andw\u0101s",
    "gn:population":0,
    "gn:timezone":"Asia/Kolkata",
    "iso:country":"IN",
    "wof:name":"Andwas",
    "wof:placetype":"locality"
},
  "geometry": {"coordinates":[76.10353000000001,32.79416],"type":"Point"}
}