{
  "type": "Feature",
  "properties": {
    "iso:country":"IN",
    "ks:ks_name":"Venpura",
    "ks:ks_pop":489,
    "ks:ks_type":"HABITATION",
    "name:eng_x_preferred":[
        "Venpura"
    ],
    "wof:name":"Venpura",
    "wof:placetype":"locality",
    "wof:population":489
},
  "geometry": {"coordinates":[72.55071,23.83423],"type":"Point"}
}