{
  "type": "Feature",
  "properties": {
    "gn:admin1_code":"16.0",
    "gn:admin2_code":"525.0",
    "gn:asciiname":"Pimpalgaon Dola",
    "gn:country_code":"IN",
    "gn:dem":667,
    "gn:feature_class":"P",
    "gn:feature_code":"PPL",
    "gn:name":"Pimpalgaon Dola",
    "gn:population":0,
    "gn:timezone":"Asia/Kolkata",
    "iso:country":"IN",
    "wof:name":"Pimpalgaon Dola",
    "wof:placetype":"locality"
},
  "geometry": {"coordinates":[76.05339000000002,18.53134],"type":"Point"}
}