{
  "type": "Feature",
  "properties": {
    "gn:admin1_code":"36",
    "gn:admin2_code":"186.0",
    "gn:asciiname":"Siswa Fatehullah",
    "gn:country_code":"IN",
    "gn:dem":90,
    "gn:feature_class":"P",
    "gn:feature_code":"PPL",
    "gn:name":"Siswa Fatehullah",
    "gn:population":0,
    "gn:timezone":"Asia/Kolkata",
    "iso:country":"IN",
    "ks:ks_name":"Siswa Fatehullah",
    "ks:ks_type":"VILLAGE",
    "ks:ks_uagg_main":0,
    "name:eng_x_preferred":[
        "Siswa Fatehullah"
    ],
    "wof:name":"Siswa Fatehullah",
    "wof:placetype":"neighbourhood"
},
  "geometry": {"coordinates":[82.93388899999999,26.859283],"type":"Point"}
}