{
  "type": "Feature",
  "properties": {
    "iso:country":"IN",
    "ks:ks_alt_nam":"NINIDRA",
    "ks:ks_name":"Ninidra",
    "ks:ks_pop":469,
    "ks:ks_type":"HABITATION",
    "name:eng_x_preferred":[
        "Ninidra"
    ],
    "wof:name":"Ninidra",
    "wof:placetype":"locality",
    "wof:population":469
},
  "geometry": {"coordinates":[84.72216899999999,23.73633],"type":"Point"}
}