{
  "type": "Feature",
  "properties": {
    "iso:country":"IN",
    "ks:ks_name":"Rajipur",
    "ks:ks_pop":2188,
    "ks:ks_type":"VILLAGE",
    "name:eng_x_preferred":[
        "Rajipur"
    ],
    "wof:name":"Rajipur",
    "wof:placetype":"locality",
    "wof:population":2188
},
  "geometry": {"coordinates":[76.895852,30.769385],"type":"Point"}
}