{
  "type": "Feature",
  "properties": {
    "gn:admin1_code":"11",
    "gn:admin2_code":"34.0",
    "gn:asciiname":"Grammal Dogri",
    "gn:country_code":"IN",
    "gn:dem":3646,
    "gn:feature_class":"P",
    "gn:feature_code":"PPL",
    "gn:name":"Grammal Dogri",
    "gn:population":0,
    "gn:timezone":"Asia/Kolkata",
    "iso:country":"IN",
    "wof:name":"Grammal Dogri",
    "wof:placetype":"locality"
},
  "geometry": {"coordinates":[78.47599,31.61727],"type":"Point"}
}