{
  "type": "Feature",
  "properties": {
    "iso:country":"IN",
    "ks:ks_name":"Edathua North",
    "ks:ks_pop":1469,
    "ks:ks_type":"HABITATION",
    "name:eng_x_preferred":[
        "Edathua North"
    ],
    "wof:name":"Edathua North",
    "wof:placetype":"locality",
    "wof:population":1469
},
  "geometry": {"coordinates":[76.47272700000001,9.376075],"type":"Point"}
}