{
  "type": "Feature",
  "properties": {
    "iso:country":"IN",
    "ks:ks_alt_nam":"Roti Badda thanda",
    "ks:ks_name":"Roti Badda Thanda",
    "ks:ks_pop":300,
    "ks:ks_type":"HABITATION",
    "name:eng_x_preferred":[
        "Roti Badda Thanda"
    ],
    "wof:name":"Roti Badda Thanda",
    "wof:placetype":"locality",
    "wof:population":300
},
  "geometry": {"coordinates":[78.536776,18.39938],"type":"Point"}
}