{
  "type": "Feature",
  "properties": {
    "iso:country":"IN",
    "ks:ks_name":"Matsajibi Para",
    "ks:ks_pop":1175,
    "ks:ks_type":"HABITATION",
    "name:eng_x_preferred":[
        "Matsajibi Para"
    ],
    "wof:name":"Matsajibi Para",
    "wof:placetype":"locality",
    "wof:population":1175
},
  "geometry": {"coordinates":[89.533248,26.382909],"type":"Point"}
}