{
  "type": "Feature",
  "properties": {
    "iso:country":"IN",
    "ks:ks_name":"Jadhav Thaware",
    "ks:ks_pop":152,
    "ks:ks_type":"HABITATION",
    "name:eng_x_preferred":[
        "Jadhav Thaware"
    ],
    "wof:name":"Jadhav Thaware",
    "wof:placetype":"locality",
    "wof:population":152
},
  "geometry": {"coordinates":[74.715,18.254],"type":"Point"}
}