{
  "type": "Feature",
  "properties": {
    "iso:country":"IN",
    "ks:ks_name":"Andgulapet",
    "ks:ks_pop":1686,
    "ks:ks_type":"VILLAGE",
    "ks:ks_uagg_main":0,
    "name:eng_x_preferred":[
        "Andgulapet"
    ],
    "wof:name":"Andgulapet",
    "wof:placetype":"locality",
    "wof:population":1686
},
  "geometry": {"coordinates":[79.453667,18.972924],"type":"Point"}
}