{
  "type": "Feature",
  "properties": {
    "iso:country":"IN",
    "ks:ks_alt_nam":"BARKITARN JAMIRA",
    "ks:ks_name":"Barkitarn Jamira",
    "ks:ks_pop":101,
    "ks:ks_type":"HABITATION",
    "name:eng_x_preferred":[
        "Barkitarn Jamira"
    ],
    "wof:name":"Barkitarn Jamira",
    "wof:placetype":"locality",
    "wof:population":101
},
  "geometry": {"coordinates":[85.131058,23.881804],"type":"Point"}
}