{
  "type": "Feature",
  "properties": {
    "gn:admin1_code":"16",
    "gn:admin2_code":"528.0",
    "gn:asciiname":"Vanked",
    "gn:country_code":"IN",
    "gn:dem":71,
    "gn:feature_class":"P",
    "gn:feature_code":"PPL",
    "gn:name":"Vanked",
    "gn:population":0,
    "gn:timezone":"Asia/Kolkata",
    "iso:country":"IN",
    "wof:name":"Vanked",
    "wof:placetype":"locality"
},
  "geometry": {"coordinates":[73.57857,16.78533],"type":"Point"}
}