{
  "type": "Feature",
  "properties": {
    "iso:country":"IN",
    "ks:ks_name":"Dalabeherapatna",
    "ks:ks_pop":215,
    "ks:ks_type":"VILLAGE",
    "ks:ks_uagg_main":0,
    "name:eng_x_preferred":[
        "Dalabeherapatna"
    ],
    "wof:name":"Dalabeherapatna",
    "wof:placetype":"neighbourhood",
    "wof:population":215
},
  "geometry": {"coordinates":[85.414975,20.237298],"type":"Point"}
}