{
  "type": "Feature",
  "properties": {
    "iso:country":"IN",
    "ks:ks_name":"South Maipith",
    "ks:ks_pop":2026,
    "ks:ks_type":"HABITATION",
    "name:eng_x_preferred":[
        "South Maipith"
    ],
    "wof:name":"South Maipith",
    "wof:placetype":"locality",
    "wof:population":2026
},
  "geometry": {"coordinates":[88.54371,21.920056],"type":"Point"}
}