{
  "type": "Feature",
  "properties": {
    "iso:country":"IN",
    "ks:ks_name":"Vajegaon",
    "ks:ks_pop":0,
    "ks:ks_type":"VILLAGE",
    "name:eng_x_preferred":[
        "Vajegaon"
    ],
    "wof:name":"Vajegaon",
    "wof:placetype":"locality",
    "wof:population":0
},
  "geometry": {"coordinates":[73.81231,17.391442],"type":"Point"}
}