{
  "type": "Feature",
  "properties": {
    "gn:admin1_code":"37",
    "gn:admin2_code":"407.0",
    "gn:asciiname":"Amlidih",
    "gn:country_code":"IN",
    "gn:dem":309,
    "gn:feature_class":"P",
    "gn:feature_code":"PPL",
    "gn:name":"Aml\u012bdih",
    "gn:population":0,
    "gn:timezone":"Asia/Kolkata",
    "iso:country":"IN",
    "ks:ks_name":"Amalidih",
    "ks:ks_pop":176,
    "ks:ks_type":"VILLAGE",
    "name:eng_x_preferred":[
        "Amalidih"
    ],
    "name:eng_x_variant":[
        "Amlidih"
    ],
    "wof:name":"Amalidih",
    "wof:placetype":"locality",
    "wof:population":176
},
  "geometry": {"coordinates":[81.332115,21.881547],"type":"Point"}
}