{
  "type": "Feature",
  "properties": {
    "iso:country":"IN",
    "ks:ks_name":"Pusiwada",
    "ks:ks_pop":134,
    "ks:ks_type":"HABITATION",
    "name:eng_x_preferred":[
        "Pusiwada"
    ],
    "wof:name":"Pusiwada",
    "wof:placetype":"locality",
    "wof:population":134
},
  "geometry": {"coordinates":[81.780224,17.760508],"type":"Point"}
}