{
  "type": "Feature",
  "properties": {
    "iso:country":"IN",
    "ks:ks_name":"Appannapalem",
    "ks:ks_pop":230,
    "ks:ks_type":"HABITATION",
    "name:eng_x_preferred":[
        "Appannapalem"
    ],
    "wof:name":"Appannapalem",
    "wof:placetype":"locality",
    "wof:population":230
},
  "geometry": {"coordinates":[83.253339,18.062197],"type":"Point"}
}