{
  "type": "Feature",
  "properties": {
    "iso:country":"IN",
    "ks:ks_name":"Small Lapathy",
    "ks:ks_type":"VILLAGE",
    "ks:ks_uagg_main":0,
    "name:eng_x_preferred":[
        "Small Lapathy"
    ],
    "wof:name":"Small Lapathy",
    "wof:placetype":"neighbourhood"
},
  "geometry": {"coordinates":[92.796384,9.216791],"type":"Point"}
}