{
  "type": "Feature",
  "properties": {
    "iso:country":"IN",
    "name:ara_x_preferred":[
        "\u062a\u064a\u0631\u0643\u0648 \u0641\u0627\u0632\u0644"
    ],
    "name:ben_bn_x_preferred":[
        "\u09a4\u09c7\u09b0\u0995\u09cd\u0995\u09c1 \u09ad\u09be\u09b8\u09be\u09b2"
    ],
    "name:ben_in_x_preferred":[
        "\u09a4\u09c7\u09b0\u0995\u09cd\u0995\u09c1 \u09ad\u09be\u09b8\u09be\u09b2"
    ],
    "name:eng_x_preferred":[
        "Terkku Vasal"
    ],
    "name:guj_x_preferred":[
        "\u0a9f\u0ac7\u0ab0\u0acd\u0a95\u0acd\u0a95\u0ac1 \u0ab5\u0ab8\u0abe\u0ab2"
    ],
    "name:hin_x_preferred":[
        "\u0924\u0947\u0930\u094d\u0915\u094d\u0915\u0942 \u0935\u0938\u093e\u0932"
    ],
    "name:kan_x_preferred":[
        "\u0ca4\u0cc6\u0cb0\u0ccd\u0c95\u0cc1 \u0cb5\u0cb8\u0cb2\u0ccd"
    ],
    "name:mal_x_preferred":[
        "\u0d24\u0d46\u0d7c\u0d15\u0d41 \u0d35\u0d3e\u0d38\u0d7d"
    ],
    "name:mar_x_preferred":[
        "\u0924\u0947\u0930\u0915\u0942 \u0935\u093e\u0938\u0932"
    ],
    "name:pan_x_preferred":[
        "\u0a1f\u0a48\u0a30\u0a15\u0a42 \u0a35\u0a3e\u0a38\u0a32"
    ],
    "name:tam_x_preferred":[
        "\u0ba4\u0bc6\u0bb1\u0bcd\u0b95\u0bc1 \u0bb5\u0bbe\u0b9a\u0bb2\u0bcd"
    ],
    "name:tel_x_preferred":[
        "\u0c1f\u0c46\u0c30\u0c4d\u0c15\u0c41 \u0c35\u0c38\u0c32\u0c4d"
    ],
    "name:urd_x_preferred":[
        "\u062a\u06cc\u0631\u06a9\u0651\u0648 \u0648\u0627\u0633\u0644"
    ],
    "qs:gn_adm0_cc":"IN",
    "qs:gn_local":1264521,
    "qs:gn_nam_loc":"Madurai, Madurai, Tamil Nadu, IN",
    "qs:gn_namadm1":"25",
    "qs:local_max":1568,
    "qs:local_sum":2851,
    "qs:localhoods":8,
    "qs:name":"Terkku Vasal",
    "qs:name_adm0":"India",
    "qs:name_adm1":"Tamil Nadu",
    "qs:name_adm2":"Madurai",
    "qs:name_local":"Madurai",
    "qs:photo_max":111,
    "qs:photo_sum":269,
    "qs:placetype":"Suburb",
    "qs:quad_count":4,
    "qs:woe_adm0":23424848,
    "qs:woe_adm1":2345758,
    "qs:woe_adm2":12586687,
    "qs:woe_lau":0,
    "qs:woe_local":2295425,
    "qs:woe_ver":"7.10.0",
    "wof:lang":[
        "eng"
    ],
    "wof:name":"Terkku Vasal",
    "wof:placetype":"neighbourhood"
},
  "geometry": {"coordinates":[78.11963,9.91704],"type":"Point"}
}