{
  "type": "Feature",
  "properties": {
    "iso:country":"IN",
    "ks:ks_name":"Pokharia",
    "ks:ks_pop":282,
    "ks:ks_type":"VILLAGE",
    "name:eng_x_preferred":[
        "Pokharia"
    ],
    "wof:name":"Pokharia",
    "wof:placetype":"locality",
    "wof:population":282
},
  "geometry": {"coordinates":[85.497958,22.31343],"type":"Point"}
}