{
  "type": "Feature",
  "properties": {
    "iso:country":"IN",
    "ks:ks_name":"Ambinong",
    "ks:ks_pop":200,
    "ks:ks_type":"HABITATION",
    "ks:ks_uagg_main":0,
    "name:eng_x_preferred":[
        "Ambinong"
    ],
    "wof:name":"Ambinong",
    "wof:placetype":"neighbourhood",
    "wof:population":200
},
  "geometry": {"coordinates":[92.56635900000001,25.845289],"type":"Point"}
}