{
  "type": "Feature",
  "properties": {
    "gn:admin1_code":"36",
    "gn:admin2_code":"158.0",
    "gn:asciiname":"Jankipur",
    "gn:country_code":"IN",
    "gn:dem":116,
    "gn:feature_class":"P",
    "gn:feature_code":"PPL",
    "gn:name":"J\u0101nkipur",
    "gn:population":0,
    "gn:timezone":"Asia/Kolkata",
    "iso:country":"IN",
    "wof:name":"Jankipur",
    "wof:placetype":"neighbourhood"
},
  "geometry": {"coordinates":[81.57447999999999,26.2365],"type":"Point"}
}