{
  "type": "Feature",
  "properties": {
    "gn:admin1_code":"12.0",
    "gn:admin2_code":"002",
    "gn:asciiname":"Methan",
    "gn:country_code":"IN",
    "gn:dem":1588,
    "gn:feature_class":"P",
    "gn:feature_code":"PPL",
    "gn:name":"Methan",
    "gn:population":0,
    "gn:timezone":"Asia/Kolkata",
    "iso:country":"IN",
    "wof:name":"Methan",
    "wof:placetype":"neighbourhood"
},
  "geometry": {"coordinates":[74.81422000000001,34.02827],"type":"Point"}
}