{
  "type": "Feature",
  "properties": {
    "iso:country":"IN",
    "ks:ks_name":"Burakhar",
    "ks:ks_pop":500,
    "ks:ks_type":"HABITATION",
    "name:eng_x_preferred":[
        "Burakhar"
    ],
    "wof:name":"Burakhar",
    "wof:placetype":"locality",
    "wof:population":500
},
  "geometry": {"coordinates":[80.828784,27.062729],"type":"Point"}
}