{
  "type": "Feature",
  "properties": {
    "iso:country":"IN",
    "ks:ks_name":"Bheema Nagar",
    "ks:ks_pop":183,
    "ks:ks_type":"HABITATION",
    "name:eng_x_preferred":[
        "Bheema Nagar"
    ],
    "wof:name":"Bheema Nagar",
    "wof:placetype":"locality",
    "wof:population":183
},
  "geometry": {"coordinates":[76.057579,17.295759],"type":"Point"}
}