{
  "type": "Feature",
  "properties": {
    "gn:admin1_code":"24.0",
    "gn:admin2_code":"123.0",
    "gn:asciiname":"Amner",
    "gn:country_code":"IN",
    "gn:dem":561,
    "gn:feature_class":"P",
    "gn:feature_code":"PPL",
    "gn:name":"Amner",
    "gn:population":0,
    "gn:timezone":"Asia/Kolkata",
    "iso:country":"IN",
    "wof:name":"Amner",
    "wof:placetype":"locality"
},
  "geometry": {"coordinates":[74.12656,25.75509],"type":"Point"}
}