{
  "type": "Feature",
  "properties": {
    "iso:country":"IN",
    "ks:ks_name":"Bhar Kol",
    "ks:ks_pop":300,
    "ks:ks_type":"HABITATION",
    "name:eng_x_preferred":[
        "Bhar Kol"
    ],
    "wof:name":"Bhar Kol",
    "wof:placetype":"locality",
    "wof:population":300
},
  "geometry": {"coordinates":[84.552898,24.904531],"type":"Point"}
}