{
  "type": "Feature",
  "properties": {
    "gn:admin1_code":"11.0",
    "gn:admin2_code":"27.0",
    "gn:asciiname":"Bahaul",
    "gn:country_code":"IN",
    "gn:dem":1858,
    "gn:feature_class":"P",
    "gn:feature_code":"PPL",
    "gn:name":"Bahaul",
    "gn:population":0,
    "gn:timezone":"Asia/Kolkata",
    "iso:country":"IN",
    "wof:name":"Bahaul",
    "wof:placetype":"locality"
},
  "geometry": {"coordinates":[77.15281999999998,31.31529],"type":"Point"}
}