{
  "type": "Feature",
  "properties": {
    "iso:country":"IN",
    "ks:ks_name":"Uttar Tentulia",
    "ks:ks_pop":928,
    "ks:ks_type":"HABITATION",
    "name:eng_x_preferred":[
        "Uttar Tentulia"
    ],
    "wof:name":"Uttar Tentulia",
    "wof:placetype":"locality",
    "wof:population":928
},
  "geometry": {"coordinates":[88.53308699999999,22.726348],"type":"Point"}
}