{
  "type": "Feature",
  "properties": {
    "iso:country":"IN",
    "ks:ks_alt_nam":"Mehilalpurwa or Khera",
    "ks:ks_name":"Mehilalpurwa Or Khera",
    "ks:ks_pop":119,
    "ks:ks_type":"HABITATION",
    "ks:ks_uagg_main":0,
    "name:eng_x_preferred":[
        "Mehilalpurwa Or Khera"
    ],
    "wof:name":"Mehilalpurwa Or Khera",
    "wof:placetype":"neighbourhood",
    "wof:population":119
},
  "geometry": {"coordinates":[81.15861200000001,26.687293],"type":"Point"}
}