{
  "type": "Feature",
  "properties": {
    "iso:country":"IN",
    "ks:ks_name":"Codvol",
    "ks:ks_pop":6,
    "ks:ks_type":"VILLAGE",
    "name:eng_x_preferred":[
        "Codvol"
    ],
    "wof:name":"Codvol",
    "wof:placetype":"locality",
    "wof:population":6
},
  "geometry": {"coordinates":[74.24866400000001,15.553365],"type":"Point"}
}