{
  "type": "Feature",
  "properties": {
    "gn:admin1_code":"24.0",
    "gn:admin2_code":"124.0",
    "gn:asciiname":"Dhodha",
    "gn:country_code":"IN",
    "gn:dem":225,
    "gn:feature_class":"P",
    "gn:feature_code":"PPL",
    "gn:name":"Dhodha",
    "gn:population":0,
    "gn:timezone":"Asia/Kolkata",
    "iso:country":"IN",
    "name:tat_x_preferred":[
        "\u0414\u04bb\u043e\u0434\u04bb\u0430"
    ],
    "wof:name":"Dhodha",
    "wof:placetype":"neighbourhood"
},
  "geometry": {"coordinates":[73.97564,23.85147],"type":"Point"}
}