{
  "type": "Feature",
  "properties": {
    "iso:country":"IN",
    "ks:ks_name":"Paraw Purwa",
    "ks:ks_pop":102,
    "ks:ks_type":"HABITATION",
    "name:eng_x_preferred":[
        "Paraw Purwa"
    ],
    "wof:name":"Paraw Purwa",
    "wof:placetype":"locality",
    "wof:population":102
},
  "geometry": {"coordinates":[82.041268,27.445627],"type":"Point"}
}