{
  "type": "Feature",
  "properties": {
    "iso:country":"IN",
    "ks:ks_name":"Karakoppa",
    "ks:ks_pop":60,
    "ks:ks_type":"HABITATION",
    "name:eng_x_preferred":[
        "Karakoppa"
    ],
    "wof:name":"Karakoppa",
    "wof:placetype":"locality",
    "wof:population":60
},
  "geometry": {"coordinates":[75.506212,13.583652],"type":"Point"}
}