{
  "type": "Feature",
  "properties": {
    "gn:admin1_code":"16.0",
    "gn:admin2_code":"507.0",
    "gn:asciiname":"Kojbi",
    "gn:country_code":"IN",
    "gn:dem":276,
    "gn:feature_class":"P",
    "gn:feature_code":"PPL",
    "gn:name":"Kojb\u012b",
    "gn:population":0,
    "gn:timezone":"Asia/Kolkata",
    "iso:country":"IN",
    "wof:name":"Kojbi",
    "wof:placetype":"locality"
},
  "geometry": {"coordinates":[80.15047,21.06252000000001],"type":"Point"}
}