{
  "type": "Feature",
  "properties": {
    "iso:country":"IN",
    "ks:ks_name":"Malipara",
    "ks:ks_pop":547,
    "ks:ks_type":"HABITATION",
    "name:eng_x_preferred":[
        "Malipara"
    ],
    "wof:name":"Malipara",
    "wof:placetype":"locality",
    "wof:population":547
},
  "geometry": {"coordinates":[91.481914,26.069011],"type":"Point"}
}