{
  "type": "Feature",
  "properties": {
    "gn:admin1_code":"19.0",
    "gn:admin2_code":"571.0",
    "gn:asciiname":"Machanhalli",
    "gn:country_code":"IN",
    "gn:dem":854,
    "gn:feature_class":"P",
    "gn:feature_code":"PPL",
    "gn:name":"M\u0101chanhalli",
    "gn:population":0,
    "gn:timezone":"Asia/Kolkata",
    "iso:country":"IN",
    "ks:ks_name":"Machanahalli",
    "ks:ks_pop":499,
    "ks:ks_type":"VILLAGE",
    "name:eng_x_preferred":[
        "Machanahalli"
    ],
    "name:eng_x_variant":[
        "Machanhalli"
    ],
    "wof:name":"Machanahalli",
    "wof:placetype":"locality",
    "wof:population":499
},
  "geometry": {"coordinates":[77.159605,13.28499],"type":"Point"}
}