{
  "type": "Feature",
  "properties": {
    "iso:country":"IN",
    "ks:ks_alt_nam":"Ghunghutp\u0101li",
    "ks:ks_name":"Ghunghutpali",
    "ks:ks_type":"VILLAGE",
    "name:eng_x_preferred":[
        "Ghunghutpali"
    ],
    "name:eng_x_variant":[
        "Ghunghutp\u0101li"
    ],
    "wof:name":"Ghunghutpali",
    "wof:placetype":"locality"
},
  "geometry": {"coordinates":[83.544477,21.770348],"type":"Point"}
}