{
  "type": "Feature",
  "properties": {
    "iso:country":"IN",
    "ks:ks_name":"Gutripara",
    "ks:ks_pop":103,
    "ks:ks_type":"HABITATION",
    "name:eng_x_preferred":[
        "Gutripara"
    ],
    "wof:name":"Gutripara",
    "wof:placetype":"locality",
    "wof:population":103
},
  "geometry": {"coordinates":[83.20847000000001,22.742361],"type":"Point"}
}