{
  "type": "Feature",
  "properties": {
    "iso:country":"IN",
    "ks:ks_alt_nam":"Tatama tola",
    "ks:ks_name":"Tatama Tola",
    "ks:ks_pop":212,
    "ks:ks_type":"HABITATION",
    "name:eng_x_preferred":[
        "Tatama Tola"
    ],
    "wof:name":"Tatama Tola",
    "wof:placetype":"locality",
    "wof:population":212
},
  "geometry": {"coordinates":[87.411145,26.323373],"type":"Point"}
}