{
  "type": "Feature",
  "properties": {
    "iso:country":"IN",
    "ks:ks_name":"Basawaria",
    "ks:ks_pop":1201,
    "ks:ks_type":"HABITATION",
    "name:eng_x_preferred":[
        "Basawaria"
    ],
    "wof:name":"Basawaria",
    "wof:placetype":"locality",
    "wof:population":1201
},
  "geometry": {"coordinates":[84.121394,25.90969],"type":"Point"}
}