{
  "type": "Feature",
  "properties": {
    "iso:country":"IN",
    "ks:ks_name":"Basipitha",
    "ks:ks_pop":687,
    "ks:ks_type":"VILLAGE",
    "name:eng_x_preferred":[
        "Basipitha"
    ],
    "wof:name":"Basipitha",
    "wof:placetype":"locality",
    "wof:population":687
},
  "geometry": {"coordinates":[86.655924,21.758577],"type":"Point"}
}