{
  "type": "Feature",
  "properties": {
    "iso:country":"IN",
    "ks:ks_name":"Kaka Sonari",
    "ks:ks_pop":79,
    "ks:ks_type":"VILLAGE",
    "name:eng_x_preferred":[
        "Kaka Sonari"
    ],
    "wof:name":"Kaka Sonari",
    "wof:placetype":"locality",
    "wof:population":79
},
  "geometry": {"coordinates":[95.62354999999999,27.718027],"type":"Point"}
}