{
  "type": "Feature",
  "properties": {
    "iso:country":"IN",
    "ks:ks_name":"Baluachak",
    "ks:ks_pop":291,
    "ks:ks_type":"VILLAGE",
    "ks:ks_uagg_main":0,
    "name:eng_x_preferred":[
        "Baluachak"
    ],
    "wof:name":"Baluachak",
    "wof:placetype":"neighbourhood",
    "wof:population":291
},
  "geometry": {"coordinates":[87.031474,25.428284],"type":"Point"}
}