{
  "type": "Feature",
  "properties": {
    "iso:country":"IN",
    "ks:ks_name":"Chaphla",
    "ks:ks_pop":684,
    "ks:ks_type":"VILLAGE",
    "ks:ks_uagg_main":0,
    "name:eng_x_preferred":[
        "Chaphla"
    ],
    "wof:name":"Chaphla",
    "wof:placetype":"neighbourhood",
    "wof:population":684
},
  "geometry": {"coordinates":[87.192036,21.854187],"type":"Point"}
}