{
  "type": "Feature",
  "properties": {
    "gn:admin1_code":"36",
    "gn:admin2_code":"155.0",
    "gn:asciiname":"Ilahi Khera",
    "gn:country_code":"IN",
    "gn:dem":133,
    "gn:feature_class":"P",
    "gn:feature_code":"PPL",
    "gn:name":"Il\u0101hi Khera",
    "gn:population":0,
    "gn:timezone":"Asia/Kolkata",
    "iso:country":"IN",
    "wof:name":"Ilahi Khera",
    "wof:placetype":"locality"
},
  "geometry": {"coordinates":[80.61100999999999,27.12642],"type":"Point"}
}