{
  "type": "Feature",
  "properties": {
    "gn:admin1_code":"35",
    "gn:admin2_code":"454.0",
    "gn:asciiname":"Papri Khurd",
    "gn:country_code":"IN",
    "gn:dem":414,
    "gn:feature_class":"P",
    "gn:feature_code":"PPL",
    "gn:name":"P\u0101pri Khurd",
    "gn:population":0,
    "gn:timezone":"Asia/Kolkata",
    "iso:country":"IN",
    "wof:name":"Papri Khurd",
    "wof:placetype":"locality"
},
  "geometry": {"coordinates":[79.96559000000001,22.95167],"type":"Point"}
}