{
  "type": "Feature",
  "properties": {
    "gn:admin1_code":"35",
    "gn:admin2_code":"454.0",
    "gn:asciiname":"Papri Khurd",
    "gn:country_code":"IN",
    "gn:dem":414,
    "gn:feature_class":"P",
    "gn:feature_code":"PPL",
    "gn:name":"P\u0101pri Khurd",
    "gn:population":0,
    "gn:timezone":"Asia/Kolkata",
    "iso:country":"IN",
    "ks:ks_alt_nam":"Papri khurd",
    "ks:ks_name":"Papri Khurd",
    "ks:ks_pop":89,
    "ks:ks_type":"HABITATION",
    "name:eng_x_preferred":[
        "Papri Khurd"
    ],
    "wof:name":"Papri Khurd",
    "wof:placetype":"locality",
    "wof:population":89
},
  "geometry": {"coordinates":[79.965018,22.951833],"type":"Point"}
}