{
  "type": "Feature",
  "properties": {
    "iso:country":"IN",
    "ks:ks_name":"Uppira",
    "ks:ks_pop":378,
    "ks:ks_type":"HABITATION",
    "name:eng_x_preferred":[
        "Uppira"
    ],
    "wof:name":"Uppira",
    "wof:placetype":"locality",
    "wof:population":378
},
  "geometry": {"coordinates":[75.07232,12.991646],"type":"Point"}
}