{
  "type": "Feature",
  "properties": {
    "iso:country":"IN",
    "ks:ks_name":"Natham",
    "ks:ks_pop":106,
    "ks:ks_type":"HABITATION",
    "name:eng_x_preferred":[
        "Natham"
    ],
    "wof:name":"Natham",
    "wof:placetype":"locality",
    "wof:population":106
},
  "geometry": {"coordinates":[80.095354,12.478631],"type":"Point"}
}