{
  "type": "Feature",
  "properties": {
    "iso:country":"IN",
    "ks:ks_name":"Sar Terang-1",
    "ks:ks_pop":38,
    "ks:ks_type":"HABITATION",
    "name:eng_x_preferred":[
        "Sar Terang-1"
    ],
    "wof:name":"Sar Terang-1",
    "wof:placetype":"locality",
    "wof:population":38
},
  "geometry": {"coordinates":[93.165567,25.987344],"type":"Point"}
}