{
  "type": "Feature",
  "properties": {
    "gn:admin1_code":"12.0",
    "gn:admin2_code":"16.0",
    "gn:asciiname":"Subrgar",
    "gn:country_code":"IN",
    "gn:dem":973,
    "gn:feature_class":"P",
    "gn:feature_code":"PPL",
    "gn:name":"Subrg\u0101r",
    "gn:population":0,
    "gn:timezone":"Asia/Kolkata",
    "iso:country":"IN",
    "wof:name":"Subrgar",
    "wof:placetype":"locality"
},
  "geometry": {"coordinates":[75.62739000000001,33.12672],"type":"Point"}
}