{
  "type": "Feature",
  "properties": {
    "iso:country":"IN",
    "ks:ks_name":"Pure Chka",
    "ks:ks_pop":275,
    "ks:ks_type":"HABITATION",
    "name:eng_x_preferred":[
        "Pure Chka"
    ],
    "wof:name":"Pure Chka",
    "wof:placetype":"locality",
    "wof:population":275
},
  "geometry": {"coordinates":[82.22183200000001,26.634198],"type":"Point"}
}