{
  "type": "Feature",
  "properties": {
    "gn:admin1_code":"39",
    "gn:admin2_code":"61.0",
    "gn:asciiname":"Deul",
    "gn:country_code":"IN",
    "gn:dem":1202,
    "gn:feature_class":"P",
    "gn:feature_code":"PPL",
    "gn:name":"Deul",
    "gn:population":0,
    "gn:timezone":"Asia/Kolkata",
    "iso:country":"IN",
    "ks:ks_name":"Deul",
    "ks:ks_type":"VILLAGE",
    "name:ben_x_preferred":[
        "\u09a6\u09c7\u0989\u09b2"
    ],
    "name:deu_x_preferred":[
        "Deul"
    ],
    "name:eng_x_preferred":[
        "Deul"
    ],
    "wof:name":"Deul",
    "wof:placetype":"locality"
},
  "geometry": {"coordinates":[78.813339,29.970486],"type":"Point"}
}