{
  "type": "Feature",
  "properties": {
    "gn:admin1_code":"11.0",
    "gn:admin2_code":"26.0",
    "gn:asciiname":"Satangidhar",
    "gn:country_code":"IN",
    "gn:dem":1193,
    "gn:feature_class":"P",
    "gn:feature_code":"PPL",
    "gn:name":"Satangidh\u0101r",
    "gn:population":0,
    "gn:timezone":"Asia/Kolkata",
    "iso:country":"IN",
    "wof:name":"Satangidhar",
    "wof:placetype":"locality"
},
  "geometry": {"coordinates":[77.56771999999999,31.41937],"type":"Point"}
}