{
  "type": "Feature",
  "properties": {
    "iso:country":"IN",
    "ks:ks_name":"Nandara Kalan",
    "ks:ks_pop":1963,
    "ks:ks_type":"VILLAGE",
    "name:eng_x_preferred":[
        "Nandara Kalan"
    ],
    "wof:name":"Nandara Kalan",
    "wof:placetype":"neighbourhood",
    "wof:population":1963
},
  "geometry": {"coordinates":[73.123651,26.282152],"type":"Point"}
}