{
  "type": "Feature",
  "properties": {
    "iso:country":"IN",
    "ks:ks_name":"Bhapura Bhim Pur",
    "ks:ks_pop":1918,
    "ks:ks_type":"VILLAGE",
    "ks:ks_uagg_main":0,
    "name:eng_x_preferred":[
        "Bhapura Bhim Pur"
    ],
    "wof:name":"Bhapura Bhim Pur",
    "wof:placetype":"neighbourhood",
    "wof:population":1918
},
  "geometry": {"coordinates":[85.471901,26.4281],"type":"Point"}
}