{
  "type": "Feature",
  "properties": {
    "iso:country":"IN",
    "ks:ks_name":"Jaikhanda",
    "ks:ks_pop":103,
    "ks:ks_type":"HABITATION",
    "name:eng_x_preferred":[
        "Jaikhanda"
    ],
    "wof:name":"Jaikhanda",
    "wof:placetype":"locality",
    "wof:population":103
},
  "geometry": {"coordinates":[79.13403700000001,30.438134],"type":"Point"}
}