{
  "type": "Feature",
  "properties": {
    "iso:country":"IN",
    "ks:ks_name":"Madhawipada",
    "ks:ks_pop":257,
    "ks:ks_type":"HABITATION",
    "name:eng_x_preferred":[
        "Madhawipada"
    ],
    "wof:name":"Madhawipada",
    "wof:placetype":"locality",
    "wof:population":257
},
  "geometry": {"coordinates":[73.365667,19.525044],"type":"Point"}
}