{
  "type": "Feature",
  "properties": {
    "iso:country":"IN",
    "ks:ks_name":"Lambatewasti",
    "ks:ks_pop":90,
    "ks:ks_type":"HABITATION",
    "name:eng_x_preferred":[
        "Lambatewasti"
    ],
    "wof:name":"Lambatewasti",
    "wof:placetype":"locality",
    "wof:population":90
},
  "geometry": {"coordinates":[74.77791999999999,18.38018],"type":"Point"}
}