{
  "type": "Feature",
  "properties": {
    "iso:country":"IN",
    "ks:ks_name":"Sarang Dewpur",
    "ks:ks_pop":2447,
    "ks:ks_type":"VILLAGE",
    "name:eng_x_preferred":[
        "Sarang Dewpur"
    ],
    "wof:name":"Sarang Dewpur",
    "wof:placetype":"locality",
    "wof:population":2447
},
  "geometry": {"coordinates":[92.30429700000001,24.865039],"type":"Point"}
}