{
  "type": "Feature",
  "properties": {
    "iso:country":"IN",
    "ks:ks_name":"Purab Tola",
    "ks:ks_pop":159,
    "ks:ks_type":"HABITATION",
    "name:eng_x_preferred":[
        "Purab Tola"
    ],
    "wof:name":"Purab Tola",
    "wof:placetype":"locality",
    "wof:population":159
},
  "geometry": {"coordinates":[84.105501,25.389161],"type":"Point"}
}