{
  "type": "Feature",
  "properties": {
    "iso:country":"IN",
    "ks:ks_name":"Bazar Tola",
    "ks:ks_pop":606,
    "ks:ks_type":"HABITATION",
    "ks:ks_uagg_main":0,
    "name:eng_x_preferred":[
        "Bazar Tola"
    ],
    "wof:name":"Bazar Tola",
    "wof:placetype":"neighbourhood",
    "wof:population":606
},
  "geometry": {"coordinates":[85.521783,26.807925],"type":"Point"}
}