{
  "type": "Feature",
  "properties": {
    "iso:country":"IN",
    "ks:ks_name":"Bangalisahi",
    "ks:ks_pop":104,
    "ks:ks_type":"HABITATION",
    "name:eng_x_preferred":[
        "Bangalisahi"
    ],
    "wof:name":"Bangalisahi",
    "wof:placetype":"locality",
    "wof:population":104
},
  "geometry": {"coordinates":[82.76057400000001,19.391864],"type":"Point"}
}