{
  "type": "Feature",
  "properties": {
    "iso:country":"IN",
    "ks:ks_name":"Dadadahalli",
    "ks:ks_pop":795,
    "ks:ks_type":"HABITATION",
    "name:eng_x_preferred":[
        "Dadadahalli"
    ],
    "wof:name":"Dadadahalli",
    "wof:placetype":"locality",
    "wof:population":795
},
  "geometry": {"coordinates":[76.38754900000001,12.849224],"type":"Point"}
}