{
  "type": "Feature",
  "properties": {
    "iso:country":"IN",
    "ks:ks_name":"Khonar Pubpar",
    "ks:ks_pop":1828,
    "ks:ks_type":"VILLAGE",
    "ks:ks_uagg_main":0,
    "name:eng_x_preferred":[
        "Khonar Pubpar"
    ],
    "wof:name":"Khonar Pubpar",
    "wof:placetype":"neighbourhood",
    "wof:population":1828
},
  "geometry": {"coordinates":[90.354834,26.074491],"type":"Point"}
}