{
  "type": "Feature",
  "properties": {
    "iso:country":"IN",
    "ks:ks_name":"Dhundwa",
    "ks:ks_pop":59,
    "ks:ks_type":"HABITATION",
    "name:eng_x_preferred":[
        "Dhundwa"
    ],
    "wof:name":"Dhundwa",
    "wof:placetype":"locality",
    "wof:population":59
},
  "geometry": {"coordinates":[76.348097,29.985977],"type":"Point"}
}