{
  "type": "Feature",
  "properties": {
    "iso:country":"IN",
    "ks:ks_name":"Kukkujadka",
    "ks:ks_pop":1324,
    "ks:ks_type":"HABITATION",
    "name:eng_x_preferred":[
        "Kukkujadka"
    ],
    "wof:name":"Kukkujadka",
    "wof:placetype":"locality",
    "wof:population":1324
},
  "geometry": {"coordinates":[75.431219,12.621768],"type":"Point"}
}