{
  "type": "Feature",
  "properties": {
    "iso:country":"IN",
    "ks:ks_name":"Angarkata Pt.iii",
    "ks:ks_pop":560,
    "ks:ks_type":"VILLAGE",
    "name:eng_x_preferred":[
        "Angarkata Pt.iii"
    ],
    "wof:name":"Angarkata Pt.iii",
    "wof:placetype":"locality",
    "wof:population":560
},
  "geometry": {"coordinates":[90.13971100000001,26.201325],"type":"Point"}
}