{
  "type": "Feature",
  "properties": {
    "iso:country":"IN",
    "ks:ks_name":"Gududa",
    "ks:ks_pop":710,
    "ks:ks_type":"VILLAGE",
    "name:eng_x_preferred":[
        "Gududa"
    ],
    "wof:name":"Gududa",
    "wof:placetype":"locality",
    "wof:population":710
},
  "geometry": {"coordinates":[87.020769,21.524175],"type":"Point"}
}