{
  "type": "Feature",
  "properties": {
    "iso:country":"IN",
    "ks:ks_name":"Bhanarawat",
    "ks:ks_pop":1186,
    "ks:ks_type":"HABITATION",
    "name:eng_x_preferred":[
        "Bhanarawat"
    ],
    "wof:name":"Bhanarawat",
    "wof:placetype":"locality",
    "wof:population":1186
},
  "geometry": {"coordinates":[76.552477,25.793935],"type":"Point"}
}