{
  "type": "Feature",
  "properties": {
    "iso:country":"IN",
    "ks:ks_name":"Koliyanpara",
    "ks:ks_pop":1034,
    "ks:ks_type":"HABITATION",
    "name:eng_x_preferred":[
        "Koliyanpara"
    ],
    "wof:name":"Koliyanpara",
    "wof:placetype":"locality",
    "wof:population":1034
},
  "geometry": {"coordinates":[81.426073,18.596892],"type":"Point"}
}