{
  "type": "Feature",
  "properties": {
    "iso:country":"IN",
    "ks:ks_name":"Bhaisari",
    "ks:ks_pop":431,
    "ks:ks_type":"HABITATION",
    "name:eng_x_preferred":[
        "Bhaisari"
    ],
    "wof:name":"Bhaisari",
    "wof:placetype":"locality",
    "wof:population":431
},
  "geometry": {"coordinates":[79.804373,25.411875],"type":"Point"}
}