{
  "type": "Feature",
  "properties": {
    "iso:country":"IN",
    "ks:ks_name":"Shirur",
    "ks:ks_pop":523,
    "ks:ks_type":"VILLAGE",
    "name:eng_x_preferred":[
        "Shirur"
    ],
    "wof:name":"Shirur",
    "wof:placetype":"locality",
    "wof:population":523
},
  "geometry": {"coordinates":[74.356982,14.604367],"type":"Point"}
}