{
  "type": "Feature",
  "properties": {
    "gn:admin1_code":"36",
    "gn:admin2_code":"176.0",
    "gn:asciiname":"Ansari",
    "gn:country_code":"IN",
    "gn:dem":114,
    "gn:feature_class":"P",
    "gn:feature_code":"PPL",
    "gn:name":"Ans\u0101ri",
    "gn:population":0,
    "gn:timezone":"Asia/Kolkata",
    "iso:country":"IN",
    "name:deu_x_preferred":[
        "Ansari"
    ],
    "name:fra_x_preferred":[
        "Ansari"
    ],
    "wof:name":"Ansari",
    "wof:placetype":"locality"
},
  "geometry": {"coordinates":[81.36581,26.59418],"type":"Point"}
}