{
  "type": "Feature",
  "properties": {
    "iso:country":"IN",
    "ks:ks_name":"Pastewadi",
    "ks:ks_pop":157,
    "ks:ks_type":"HABITATION",
    "name:eng_x_preferred":[
        "Pastewadi"
    ],
    "wof:name":"Pastewadi",
    "wof:placetype":"locality",
    "wof:population":157
},
  "geometry": {"coordinates":[73.658889,16.896667],"type":"Point"}
}