{
  "type": "Feature",
  "properties": {
    "iso:country":"IN",
    "ks:ks_name":"Moda Ganeshpura",
    "ks:ks_pop":252,
    "ks:ks_type":"HABITATION",
    "name:eng_x_preferred":[
        "Moda Ganeshpura"
    ],
    "wof:name":"Moda Ganeshpura",
    "wof:placetype":"locality",
    "wof:population":252
},
  "geometry": {"coordinates":[71.123842,26.676103],"type":"Point"}
}