{
  "type": "Feature",
  "properties": {
    "gn:admin1_code":"16",
    "gn:admin2_code":"508.0",
    "gn:asciiname":"Pandrapani",
    "gn:country_code":"IN",
    "gn:dem":385,
    "gn:feature_class":"P",
    "gn:feature_code":"PPL",
    "gn:name":"Pandr\u0101p\u0101ni",
    "gn:population":0,
    "gn:timezone":"Asia/Kolkata",
    "iso:country":"IN",
    "ks:ks_name":"Pandharapani",
    "ks:ks_pop":77,
    "ks:ks_type":"VILLAGE",
    "name:eng_x_preferred":[
        "Pandharapani"
    ],
    "name:eng_x_variant":[
        "Pandrapani"
    ],
    "wof:name":"Pandharapani",
    "wof:placetype":"locality",
    "wof:population":77
},
  "geometry": {"coordinates":[80.49487999999999,20.700735],"type":"Point"}
}