{
  "type": "Feature",
  "properties": {
    "gn:admin1_code":"36.0",
    "gn:admin2_code":"152.0",
    "gn:asciiname":"Dulha Dhakia",
    "gn:country_code":"IN",
    "gn:dem":155,
    "gn:feature_class":"P",
    "gn:feature_code":"PPL",
    "gn:name":"D\u016blha Dhakia",
    "gn:population":0,
    "gn:timezone":"Asia/Kolkata",
    "iso:country":"IN",
    "ks:ks_alt_nam":"D\u016blha Dhakia",
    "ks:ks_name":"Dulha Dhakia",
    "ks:ks_type":"VILLAGE",
    "name:eng_x_preferred":[
        "Dulha Dhakia"
    ],
    "name:eng_x_variant":[
        "D\u016blha Dhakia"
    ],
    "wof:name":"Dulha Dhakia",
    "wof:placetype":"locality"
},
  "geometry": {"coordinates":[79.79428799999999,28.015644],"type":"Point"}
}